{
  "type": "Feature",
  "properties": {
    "iso:country":"US",
    "sg:address":"11805 N Pennsylvania St",
    "sg:city":"Carmel",
    "sg:classifiers":[
        {
            "category":"Professional",
            "subcategory":"Engineering",
            "type":"Services"
        }
    ],
    "sg:phone":"+1 317 660 6661",
    "sg:postcode":"46032",
    "sg:province":"IN",
    "sg:tags":[
        "consulting",
        "engineer"
    ],
    "wof:name":"Environmental Engineernig",
    "wof:placetype":"venue"
},
  "geometry": {"coordinates":[-86.155152,39.961389],"type":"Point"}
}