{
  "type": "Feature",
  "properties": {
    "addr:full":"23677 US Hwy 33 Elkhart IN 46517",
    "addr:postcode":"23677;46517",
    "addr:street":"Us Hwy 33",
    "iso:country":"US",
    "sg:address":"23677 US Hwy 33",
    "sg:city":"Elkhart",
    "sg:classifiers":[
        {
            "category":"Restaurant",
            "type":"Food & Drink"
        }
    ],
    "sg:phone":"+1 574 875 7154",
    "sg:postcode":"46517",
    "sg:province":"IN",
    "wof:name":"Minuteman Drive In",
    "wof:placetype":"venue"
},
  "geometry": {"coordinates":[-85.918147,41.63403],"type":"Point"}
}