{
  "type": "Feature",
  "properties": {
    "addr:full":"129 Orpha Dr Middlebury IN 46540",
    "addr:housenumber":"129",
    "addr:postcode":"46540",
    "addr:street":"Orpha Dr",
    "iso:country":"US",
    "sg:address":"129 Orpha Dr",
    "sg:city":"Middlebury",
    "sg:classifiers":[
        {
            "category":"Sports & Exercise",
            "subcategory":"Gym",
            "type":"Entertainment"
        }
    ],
    "sg:phone":"+1 574 825 8145",
    "sg:postcode":"46540",
    "sg:province":"IN",
    "sg:tags":[
        "club",
        "health",
        "studio",
        "gymnasium"
    ],
    "wof:name":"Northridge Health & Fitness",
    "wof:placetype":"venue"
},
  "geometry": {"coordinates":[-85.708736,41.658401],"type":"Point"}
}