{
  "type": "Feature",
  "properties": {
    "addr:full":"6602 E 75th St Indianapolis IN 46250",
    "addr:housenumber":"6602",
    "addr:postcode":"46250",
    "addr:street":"E 75Th St",
    "iso:country":"US",
    "sg:address":"6602 E 75th St",
    "sg:city":"Indianapolis",
    "sg:classifiers":[
        {
            "category":"Place Of Worship",
            "type":"Public Place"
        }
    ],
    "sg:phone":"+1 317 842 6890",
    "sg:postcode":"46250",
    "sg:province":"IN",
    "sg:tags":[
        "consultant",
        "traffic",
        "parking"
    ],
    "sg:website":"http://www.walkerparking.com",
    "wof:name":"Walker Parking Consultants",
    "wof:placetype":"venue"
},
  "geometry": {"coordinates":[-86.05497800000001,39.890678],"type":"Point"}
}