{
  "type": "Feature",
  "properties": {
    "iso:country":"US",
    "sg:address":"4452 N Washington Blvd",
    "sg:city":"Indianapolis",
    "sg:classifiers":[
        {
            "category":"Real Estate",
            "subcategory":"Architect",
            "type":"Services"
        }
    ],
    "sg:phone":"+1 317 927 0073",
    "sg:postcode":"46205",
    "sg:province":"IN",
    "sg:tags":[
        "architectural"
    ],
    "wof:name":"Logan- Architect Inc",
    "wof:placetype":"venue"
},
  "geometry": {"coordinates":[-86.152262,39.83828],"type":"Point"}
}