{
  "type": "Feature",
  "properties": {
    "iso:country":"US",
    "sg:address":"4301 Franklin St",
    "sg:city":"Michigan City",
    "sg:classifiers":[
        {
            "category":"Banks & Credit Unions",
            "subcategory":"Bank",
            "type":"Services"
        }
    ],
    "sg:phone":"+1 219 878 9343",
    "sg:postcode":"46360",
    "sg:province":"IN",
    "wof:name":"Union Federal Bank",
    "wof:placetype":"venue"
},
  "geometry": {"coordinates":[-86.893973,41.680343],"type":"Point"}
}