{
  "type": "Feature",
  "properties": {
    "addr:full":"4757 N Franklin Rd Indianapolis IN 46226",
    "addr:housenumber":"4757",
    "addr:postcode":"46226",
    "addr:street":"N Franklin Rd",
    "iso:country":"US",
    "sg:address":"4757 N Franklin Rd",
    "sg:city":"Indianapolis",
    "sg:classifiers":[
        {
            "category":"Building & Trades",
            "subcategory":"Plumbing",
            "type":"Services"
        }
    ],
    "sg:phone":"+1 317 831 7726",
    "sg:postcode":"46226",
    "sg:province":"IN",
    "sg:tags":[
        "heating",
        "contractor"
    ],
    "wof:name":"Swift Air Mechanical Heating",
    "wof:placetype":"venue"
},
  "geometry": {"coordinates":[-86.02709400000001,39.841879],"type":"Point"}
}