{
  "type": "Feature",
  "properties": {
    "iso:country":"US",
    "sg:address":"701 Broad Ripple Ave",
    "sg:city":"Indianapolis",
    "sg:classifiers":[
        {
            "category":"Bars & Pubs",
            "type":"Food & Drink"
        },
        {
            "category":"Restaurant",
            "type":"Food & Drink"
        },
        {
            "category":"Bars & Pubs",
            "subcategory":"Nightclub",
            "type":"Food & Drink"
        }
    ],
    "sg:phone":"+1 317 257 5600",
    "sg:postcode":"46220",
    "sg:province":"IN",
    "sg:tags":[
        "club",
        "brew",
        "american",
        "night"
    ],
    "sg:website":"http://barleyisland.com",
    "wof:name":"Barley Island Restaurant and Brewhouse",
    "wof:placetype":"venue"
},
  "geometry": {"coordinates":[-86.146156,39.869671],"type":"Point"}
}