{
  "type": "Feature",
  "properties": {
    "addr:full":"17823 Gasparilla Ct Noblesville IN 46062",
    "addr:housenumber":"17823",
    "addr:postcode":"46062",
    "addr:street":"Gasparilla Ct",
    "iso:country":"US",
    "sg:address":"17823 Gasparilla Ct",
    "sg:city":"Noblesville",
    "sg:classifiers":[
        {
            "category":"Professional",
            "subcategory":"Advertising",
            "type":"Services"
        }
    ],
    "sg:phone":"+1 317 536 2343",
    "sg:postcode":"46062",
    "sg:province":"IN",
    "sg:tags":[
        "counselor"
    ],
    "wof:name":"Yellowwood Marketing Co",
    "wof:placetype":"venue"
},
  "geometry": {"coordinates":[-86.095637,40.045556],"type":"Point"}
}