{
  "type": "Feature",
  "properties": {
    "iso:country":"US",
    "sg:address":"950 Cloverleaf Ct",
    "sg:city":"Martinsville",
    "sg:classifiers":[
        {
            "category":"Real Estate",
            "subcategory":"Real Estate Operator",
            "type":"Services"
        }
    ],
    "sg:phone":"+1 765 342 9622",
    "sg:postcode":"46151",
    "sg:province":"IN",
    "sg:tags":[
        "apartment"
    ],
    "wof:name":"Heather Heights Apartments",
    "wof:placetype":"venue"
},
  "geometry": {"coordinates":[-86.440527,39.407006],"type":"Point"}
}