{
  "type": "Feature",
  "properties": {
    "iso:country":"US",
    "sg:address":"1808 Dogwood Dr",
    "sg:city":"Kokomo",
    "sg:classifiers":[
        {
            "category":"Real Estate",
            "subcategory":"Real Estate Agent",
            "type":"Services"
        }
    ],
    "sg:phone":"+1 765 457 7214",
    "sg:postcode":"46902",
    "sg:province":"IN",
    "sg:website":"www.thehardiegroup.com",
    "wof:name":"Hardie Group",
    "wof:placetype":"venue"
},
  "geometry": {"coordinates":[-86.117803,40.465364],"type":"Point"}
}