{
  "type": "Feature",
  "properties": {
    "iso:country":"US",
    "sg:address":"29765 Co Rd 12",
    "sg:city":"Elkhart",
    "sg:classifiers":[
        {
            "category":"Organizations",
            "subcategory":"Religious Organization",
            "type":"Services"
        }
    ],
    "sg:phone":"+1 574 264 4246",
    "sg:postcode":"46514",
    "sg:province":"IN",
    "sg:tags":[
        "church"
    ],
    "wof:name":"California Road Missionary",
    "wof:placetype":"venue"
},
  "geometry": {"coordinates":[-86.038546,41.695436],"type":"Point"}
}