{
  "type": "Feature",
  "properties": {
    "iso:country":"US",
    "sg:address":"2515 W 800 S",
    "sg:city":"North Judson",
    "sg:classifiers":[
        {
            "category":"Building & Trades",
            "subcategory":"Construction",
            "type":"Services"
        }
    ],
    "sg:phone":"+1 574 896 3495",
    "sg:postcode":"46366",
    "sg:province":"IN",
    "sg:tags":[
        "plastering",
        "contractor"
    ],
    "wof:name":"Eichelberg Plastering",
    "wof:placetype":"venue"
},
  "geometry": {"coordinates":[-86.746734,41.186423],"type":"Point"}
}