{
  "type": "Feature",
  "properties": {
    "addr:full":"8220 Calumet Ave Munster IN 46321",
    "addr:housenumber":"8220",
    "addr:postcode":"46321",
    "addr:street":"Calumet Ave",
    "iso:country":"US",
    "sg:address":"8220 Calumet Ave",
    "sg:city":"Munster",
    "sg:classifiers":[
        {
            "category":"Health Services",
            "subcategory":"Doctor",
            "type":"Services"
        }
    ],
    "sg:phone":"+1 219 836 7710",
    "sg:postcode":"46321",
    "sg:province":"IN",
    "wof:name":"Shah Manzoor H MD",
    "wof:placetype":"venue"
},
  "geometry": {"coordinates":[-87.50913300000001,41.564311],"type":"Point"}
}