{
  "type": "Feature",
  "properties": {
    "iso:country":"US",
    "sg:address":"922 Harrison St",
    "sg:city":"Elkhart",
    "sg:classifiers":[
        {
            "category":"Manufacturing",
            "subcategory":"Printing",
            "type":"Manufacturing & Wholesale Goods"
        }
    ],
    "sg:phone":"+1 574 293 6019",
    "sg:postcode":"46516",
    "sg:province":"IN",
    "sg:tags":[
        "mfg"
    ],
    "wof:name":"Selective Memories",
    "wof:placetype":"venue"
},
  "geometry": {"coordinates":[-85.982767,41.67878],"type":"Point"}
}