{
  "type": "Feature",
  "properties": {
    "iso:country":"US",
    "sg:address":"1540 E Valley Pl",
    "sg:city":"Dyer",
    "sg:classifiers":[
        {
            "category":"Professional",
            "type":"Services"
        }
    ],
    "sg:phone":"+1 219 322 0826",
    "sg:postcode":"46311",
    "sg:province":"IN",
    "sg:tags":[
        "establishment"
    ],
    "wof:name":"Krysztof Szurgot",
    "wof:placetype":"venue"
},
  "geometry": {"coordinates":[-87.494277,41.489598],"type":"Point"}
}