{
  "type": "Feature",
  "properties": {
    "iso:country":"US",
    "sg:address":"99 Chestnut Ave",
    "sg:city":"Winona Lake",
    "sg:classifiers":[
        {
            "category":"Banks & Credit Unions",
            "subcategory":"Bank",
            "type":"Services"
        }
    ],
    "sg:phone":"+1 574 267 9150",
    "sg:postcode":"46590",
    "sg:province":"IN",
    "wof:name":"Lake City Bank",
    "wof:placetype":"venue"
},
  "geometry": {"coordinates":[-85.821247,41.230249],"type":"Point"}
}