{
  "type": "Feature",
  "properties": {
    "addr:full":"409 S Park Ave Alexandria IN 46001",
    "addr:housenumber":"409",
    "addr:postcode":"46001",
    "addr:street":"S Park Ave",
    "iso:country":"US",
    "sg:address":"409 S Park Ave",
    "sg:city":"Alexandria",
    "sg:classifiers":[
        {
            "category":"Personal",
            "subcategory":"Beauty Salon",
            "type":"Services"
        }
    ],
    "sg:phone":"+1 765 724 2405",
    "sg:postcode":"46001",
    "sg:province":"IN",
    "wof:name":"Marla's Permanent Solution",
    "wof:placetype":"venue"
},
  "geometry": {"coordinates":[-85.670937,40.261113],"type":"Point"}
}