{
  "type": "Feature",
  "properties": {
    "iso:country":"US",
    "sg:address":"5525 Pearl Dr",
    "sg:city":"Evansville",
    "sg:classifiers":[
        {
            "category":"Banks & Credit Unions",
            "subcategory":"Bank",
            "type":"Services"
        }
    ],
    "sg:phone":"+1 812 425 6137",
    "sg:postcode":"47712",
    "sg:province":"IN",
    "sg:tags":[
        "financing"
    ],
    "wof:name":"American General Finance Inc",
    "wof:placetype":"venue"
},
  "geometry": {"coordinates":[-87.640686,37.974456],"type":"Point"}
}