{
  "type": "Feature",
  "properties": {
    "iso:country":"US",
    "sg:address":"5249 S Co Rd 350 W",
    "sg:city":"Clay City",
    "sg:phone":"+1 812 939 2050",
    "sg:postcode":"47841",
    "sg:province":"IN",
    "sg:tags":[
        "farm",
        "corn",
        "soybean"
    ],
    "wof:name":"Joe Tiefel",
    "wof:placetype":"venue"
},
  "geometry": {"coordinates":[-87.174977,39.31172],"type":"Point"}
}