{
  "type": "Feature",
  "properties": {
    "iso:country":"US",
    "sg:address":"2947 S Washington St",
    "sg:city":"Kokomo",
    "sg:classifiers":[
        {
            "category":"Wholesale",
            "subcategory":"Machinery & Supplies",
            "type":"Manufacturing & Wholesale Goods"
        }
    ],
    "sg:phone":"+1 765 864 0043",
    "sg:postcode":"46902",
    "sg:province":"IN",
    "sg:tags":[
        "farm",
        "equipment"
    ],
    "wof:name":"Kokomo Rural King Inc",
    "wof:placetype":"venue"
},
  "geometry": {"coordinates":[-86.128456,40.453126],"type":"Point"}
}