{
  "type": "Feature",
  "properties": {
    "iso:country":"US",
    "sg:address":"55 S Gladstone Ave",
    "sg:city":"Indianapolis",
    "sg:classifiers":[
        {
            "category":"Building & Trades",
            "subcategory":"Construction",
            "type":"Services"
        }
    ],
    "sg:phone":"+1 317 356 4055",
    "sg:postcode":"46201",
    "sg:province":"IN",
    "sg:tags":[
        "house"
    ],
    "wof:name":"Hart General Contractor Co",
    "wof:placetype":"venue"
},
  "geometry": {"coordinates":[-86.09607200000001,39.76744],"type":"Point"}
}