{
  "type": "Feature",
  "properties": {
    "iso:country":"US",
    "sg:address":"2605 E Chicago Ave",
    "sg:city":"East Chicago",
    "sg:classifiers":[
        {
            "category":"Professional",
            "subcategory":"Business Services",
            "type":"Services"
        }
    ],
    "sg:phone":"+1 219 746 4410",
    "sg:postcode":"46312",
    "sg:province":"IN",
    "sg:tags":[
        "graphic",
        "layout",
        "promotional",
        "production",
        "design",
        "print"
    ],
    "wof:name":"Optimum Illusions",
    "wof:placetype":"venue"
},
  "geometry": {"coordinates":[-87.44009800000001,41.628879],"type":"Point"}
}