{
  "type": "Feature",
  "properties": {
    "iso:country":"US",
    "sg:address":"1252 S Bend Ave",
    "sg:city":"South Bend",
    "sg:classifiers":[
        {
            "category":"Professional",
            "subcategory":"Management & Consulting",
            "type":"Services"
        }
    ],
    "sg:phone":"+1 574 233 3000",
    "sg:postcode":"46617",
    "sg:province":"IN",
    "sg:tags":[
        "consultant",
        "business"
    ],
    "wof:name":"Gary A Murray-Business Conslnt",
    "wof:placetype":"venue"
},
  "geometry": {"coordinates":[-86.230848,41.690067],"type":"Point"}
}