{
  "type": "Feature",
  "properties": {
    "iso:country":"US",
    "sg:address":"4066 Rommel Dr",
    "sg:city":"Indianapolis",
    "sg:classifiers":[
        {
            "category":"Education",
            "subcategory":"Special Training",
            "type":"Public Place"
        }
    ],
    "sg:phone":"+1 317 216 9791",
    "sg:postcode":"46228",
    "sg:province":"IN",
    "sg:tags":[
        "instruction",
        "music"
    ],
    "wof:name":"Piano Instruction By Talley",
    "wof:placetype":"venue"
},
  "geometry": {"coordinates":[-86.199011,39.827069],"type":"Point"}
}