{
  "type": "Feature",
  "properties": {
    "iso:country":"US",
    "sg:address":"7740 Records St",
    "sg:city":"Indianapolis",
    "sg:classifiers":[
        {
            "category":"Wholesale",
            "subcategory":"Medical Equipment & Supplies",
            "type":"Manufacturing & Wholesale Goods"
        }
    ],
    "sg:phone":"+1 317 545 6196",
    "sg:postcode":"46226",
    "sg:province":"IN",
    "sg:tags":[
        "physician",
        "surgeon"
    ],
    "sg:website":"www.anthonyproducts.com",
    "wof:name":"Anthony Products Inc",
    "wof:placetype":"venue"
},
  "geometry": {"coordinates":[-86.030314,39.837102],"type":"Point"}
}