{
  "type": "Feature",
  "properties": {
    "iso:country":"US",
    "sg:address":"700 S Walnut St",
    "sg:city":"Bloomington",
    "sg:classifiers":[
        {
            "category":"Shopping",
            "subcategory":"Catalog Store",
            "type":"Retail Goods"
        }
    ],
    "sg:phone":"+1 812 336 0385",
    "sg:postcode":"47401",
    "sg:province":"IN",
    "sg:tags":[
        "e"
    ],
    "wof:name":"Sold",
    "wof:placetype":"venue"
},
  "geometry": {"coordinates":[-86.533655,39.157416],"type":"Point"}
}