{
  "type": "Feature",
  "properties": {
    "addr:full":"11 N Morton Ave Evansville IN 47711",
    "addr:housenumber":"11",
    "addr:postcode":"47711",
    "addr:street":"N Morton Ave",
    "iso:country":"US",
    "sg:address":"11 N Morton Ave",
    "sg:city":"Evansville",
    "sg:classifiers":[
        {
            "category":"Retail",
            "subcategory":"Auto Repair",
            "type":"Services"
        }
    ],
    "sg:phone":"+1 812 425 9003",
    "sg:postcode":"47711",
    "sg:province":"IN",
    "sg:tags":[
        "spring"
    ],
    "wof:name":"North Side Auto Spring Inc",
    "wof:placetype":"venue"
},
  "geometry": {"coordinates":[-87.554292,37.978029],"type":"Point"}
}