{
  "type": "Feature",
  "properties": {
    "iso:country":"US",
    "sg:address":"1506 Chester Blvd",
    "sg:city":"Richmond",
    "sg:classifiers":[
        {
            "category":"Health Services",
            "subcategory":"Doctor",
            "type":"Services"
        }
    ],
    "sg:phone":"+1 765 966 6787",
    "sg:postcode":"47374",
    "sg:province":"IN",
    "sg:tags":[
        "dentist"
    ],
    "wof:name":"Ernest W Hendricks DDS",
    "wof:placetype":"venue"
},
  "geometry": {"coordinates":[-84.88887099999999,39.850291],"type":"Point"}
}