{
  "type": "Feature",
  "properties": {
    "iso:country":"US",
    "sg:address":"1706 S 150 W",
    "sg:city":"Greenfield",
    "sg:classifiers":[
        {
            "category":"Organizations",
            "subcategory":"Membership Organization",
            "type":"Services"
        }
    ],
    "sg:phone":"+1 317 462 0778",
    "sg:postcode":"46140",
    "sg:province":"IN",
    "wof:name":"Laleche League of Indiana",
    "wof:placetype":"venue"
},
  "geometry": {"coordinates":[-85.827492,39.759992],"type":"Point"}
}