{
  "type": "Feature",
  "properties": {
    "addr:full":"501 E Co Rd 300 S Logansport IN 46947",
    "addr:housenumber":"501",
    "addr:postcode":"46947",
    "addr:street":"E Co Rd 300 S",
    "iso:country":"US",
    "sg:address":"501 E Co Rd 300 S",
    "sg:city":"Logansport",
    "sg:classifiers":[
        {
            "category":"Farming",
            "subcategory":"Farm",
            "type":"Manufacturing & Wholesale Goods"
        }
    ],
    "sg:phone":"+1 574 859 3344",
    "sg:postcode":"46947",
    "sg:province":"IN",
    "sg:tags":[
        "crop",
        "general"
    ],
    "wof:name":"Dillon Farms",
    "wof:placetype":"venue"
},
  "geometry": {"coordinates":[-86.362419,40.721637],"type":"Point"}
}