{
  "type": "Feature",
  "properties": {
    "addr:full":"2465 E Wabash St Frankfort IN 46041",
    "addr:housenumber":"2465",
    "addr:postcode":"46041",
    "addr:street":"E Wabash St",
    "iso:country":"US",
    "sg:address":"2465 E Wabash St",
    "sg:city":"Frankfort",
    "sg:classifiers":[
        {
            "category":"Food & Beverages",
            "subcategory":"Groceries & Convenience Stores",
            "type":"Retail Goods"
        }
    ],
    "sg:phone":"+1 765 000 1111",
    "sg:postcode":"46041",
    "sg:province":"IN",
    "sg:tags":[
        "grocer"
    ],
    "wof:name":"Aldi",
    "wof:placetype":"venue"
},
  "geometry": {"coordinates":[-86.48062,40.27877],"type":"Point"}
}