{
  "type": "Feature",
  "properties": {
    "iso:country":"US",
    "sg:address":"930 S 10th St",
    "sg:city":"West Terre Haute",
    "sg:classifiers":[
        {
            "category":"Organizations",
            "subcategory":"Religious Organization",
            "type":"Services"
        }
    ],
    "sg:phone":"+1 812 847 2576",
    "sg:postcode":"47885",
    "sg:province":"IN",
    "sg:tags":[
        "church"
    ],
    "wof:name":"Linton Wesleyan Church",
    "wof:placetype":"venue"
},
  "geometry": {"coordinates":[-87.454317,39.455797],"type":"Point"}
}