{
  "type": "Feature",
  "properties": {
    "iso:country":"US",
    "sg:address":"4027 Hathaway Rd",
    "sg:city":"Fort Wayne",
    "sg:classifiers":[
        {
            "category":"Education",
            "subcategory":"School",
            "type":"Public Place"
        }
    ],
    "sg:phone":"+1 260 637 5159",
    "sg:postcode":"46818",
    "sg:province":"IN",
    "wof:name":"Carroll Middle School",
    "wof:placetype":"venue"
},
  "geometry": {"coordinates":[-85.190623,41.20607],"type":"Point"}
}