{
  "type": "Feature",
  "properties": {
    "iso:country":"US",
    "sg:address":"600 E Main St",
    "sg:city":"Greenwood",
    "sg:classifiers":[
        {
            "category":"Home & Garden",
            "subcategory":"Building Materials",
            "type":"Retail Goods"
        }
    ],
    "sg:phone":"+1 317 859 8665",
    "sg:postcode":"46143",
    "sg:province":"IN",
    "sg:tags":[
        "windows"
    ],
    "wof:name":"Simplicity Siding & Windows",
    "wof:placetype":"venue"
},
  "geometry": {"coordinates":[-86.09805,39.6139],"type":"Point"}
}