{
  "type": "Feature",
  "properties": {
    "iso:country":"US",
    "sg:address":"18197 Walnut Fork Rd",
    "sg:city":"Batesville",
    "sg:classifiers":[
        {
            "category":"Building & Trades",
            "subcategory":"Construction",
            "type":"Services"
        }
    ],
    "sg:phone":"+1 812 934 3906",
    "sg:postcode":"47006",
    "sg:province":"IN",
    "sg:tags":[
        "masonry",
        "contractor"
    ],
    "wof:name":"Bane Masonry & Construction",
    "wof:placetype":"venue"
},
  "geometry": {"coordinates":[-85.130803,39.393558],"type":"Point"}
}