{
  "type": "Feature",
  "properties": {
    "iso:country":"US",
    "sg:address":"24 N Broadway",
    "sg:city":"Peru",
    "sg:classifiers":[
        {
            "category":"Restaurant",
            "type":"Food & Drink"
        }
    ],
    "sg:phone":"+1 765 473 8833",
    "sg:postcode":"46970",
    "sg:province":"IN",
    "wof:name":"Chen Garden",
    "wof:placetype":"venue"
},
  "geometry": {"coordinates":[-86.069564,40.754144],"type":"Point"}
}