{
  "type": "Feature",
  "properties": {
    "iso:country":"US",
    "sg:address":"23355 Shorelane",
    "sg:city":"Elkhart",
    "sg:classifiers":[
        {
            "category":"Health Services",
            "subcategory":"Optometrist",
            "type":"Services"
        }
    ],
    "sg:phone":"+1 574 264 5300",
    "sg:postcode":"46514",
    "sg:province":"IN",
    "wof:name":"James Leaverton Od",
    "wof:placetype":"venue"
},
  "geometry": {"coordinates":[-85.91273099999999,41.697056],"type":"Point"}
}