{
  "type": "Feature",
  "properties": {
    "addr:full":"3477 S 200 E Franklin IN 46131",
    "addr:housenumber":"3477;200 e",
    "addr:postcode":"46131",
    "addr:street":"S",
    "iso:country":"US",
    "sg:address":"3477 S 200 E",
    "sg:city":"Franklin",
    "sg:classifiers":[
        {
            "category":"Airport",
            "type":"Transportation"
        }
    ],
    "sg:phone":"+1 317 736 6633",
    "sg:postcode":"46131",
    "sg:province":"IN",
    "wof:name":"Franklin Flying Field",
    "wof:placetype":"venue"
},
  "geometry": {"coordinates":[-86.06668000000001,39.426253],"type":"Point"}
}