{
  "type": "Feature",
  "properties": {
    "addr:full":"27488 Legion Rd Sunman IN 47041",
    "addr:postcode":"27488;47041",
    "addr:street":"Legion Rd",
    "iso:country":"US",
    "sg:address":"27488 Legion Rd",
    "sg:city":"Sunman",
    "sg:classifiers":[
        {
            "category":"Shopping",
            "subcategory":"Gifts & Souvenirs",
            "type":"Retail Goods"
        }
    ],
    "sg:phone":"+1 812 623 2796",
    "sg:postcode":"47041",
    "sg:province":"IN",
    "wof:name":"Keepsakes",
    "wof:placetype":"venue"
},
  "geometry": {"coordinates":[-85.011994,39.267982],"type":"Point"}
}