{
  "type": "Feature",
  "properties": {
    "iso:country":"US",
    "sg:address":"564 Eastern Blvd",
    "sg:city":"Clarksville",
    "sg:classifiers":[
        {
            "category":"Building & Trades",
            "subcategory":"Plumbing",
            "type":"Services"
        }
    ],
    "sg:phone":"+1 812 282 7740",
    "sg:postcode":"47129",
    "sg:province":"IN",
    "sg:tags":[
        "heating",
        "contractor"
    ],
    "wof:name":"GBMC Inc",
    "wof:placetype":"venue"
},
  "geometry": {"coordinates":[-85.760784,38.298058],"type":"Point"}
}