{
  "type": "Feature",
  "properties": {
    "iso:country":"US",
    "sg:address":"202 Mc Claflin St",
    "sg:city":"Williamsport",
    "sg:classifiers":[
        {
            "category":"Professional",
            "subcategory":"Art Services",
            "type":"Services"
        }
    ],
    "sg:phone":"+1 765 762 6870",
    "sg:postcode":"47993",
    "sg:province":"IN",
    "sg:tags":[
        "photography",
        "commercial"
    ],
    "wof:name":"Studio M",
    "wof:placetype":"venue"
},
  "geometry": {"coordinates":[-87.298379,40.28888],"type":"Point"}
}