{
  "type": "Feature",
  "properties": {
    "addr:full":"200 E Chicago St Columbia City IN 46725",
    "addr:housenumber":"200",
    "addr:postcode":"46725",
    "addr:street":"E Chicago St",
    "iso:country":"US",
    "sg:address":"200 E Chicago St",
    "sg:city":"Columbia City",
    "sg:classifiers":[
        {
            "category":"Personal",
            "subcategory":"Beauty Salon",
            "type":"Services"
        }
    ],
    "sg:phone":"+1 260 244 7998",
    "sg:postcode":"46725",
    "sg:province":"IN",
    "wof:name":"House Of Style",
    "wof:placetype":"venue"
},
  "geometry": {"coordinates":[-85.48622,41.150021],"type":"Point"}
}