{
  "type": "Feature",
  "properties": {
    "addr:full":"802 E 7th St Auburn IN 46706",
    "addr:housenumber":"802",
    "addr:postcode":"46706",
    "addr:street":"E 7Th St",
    "iso:country":"US",
    "sg:address":"802 E 7th St",
    "sg:city":"Auburn",
    "sg:classifiers":[
        {
            "category":"Restaurant",
            "type":"Food & Drink"
        }
    ],
    "sg:phone":"+1 260 925 1105",
    "sg:postcode":"46706",
    "sg:province":"IN",
    "wof:name":"RDM",
    "wof:placetype":"venue"
},
  "geometry": {"coordinates":[-85.04471100000001,41.36751],"type":"Point"}
}