{
  "type": "Feature",
  "properties": {
    "iso:country":"US",
    "sg:address":"30895 US Hwy 20",
    "sg:city":"Elkhart",
    "sg:classifiers":[
        {
            "category":"Restaurant",
            "type":"Food & Drink"
        }
    ],
    "sg:phone":"+1 574 674 7427",
    "sg:postcode":"46514",
    "sg:province":"IN",
    "wof:name":"Rib Aroma",
    "wof:placetype":"venue"
},
  "geometry": {"coordinates":[-86.056859,41.688528],"type":"Point"}
}