{
  "type": "Feature",
  "properties": {
    "iso:country":"US",
    "sg:address":"823 E Main St",
    "sg:city":"Richmond",
    "sg:classifiers":[
        {
            "category":"Shopping",
            "type":"Retail Goods"
        }
    ],
    "sg:phone":"+1 765 962 0214",
    "sg:postcode":"47374",
    "sg:province":"IN",
    "sg:tags":[
        "picture",
        "frame"
    ],
    "wof:name":"John's Custom Framing",
    "wof:placetype":"venue"
},
  "geometry": {"coordinates":[-84.890551,39.828967],"type":"Point"}
}