{
  "type": "Feature",
  "properties": {
    "iso:country":"US",
    "sg:address":"8100 W Nixon Rd",
    "sg:city":"Yorktown",
    "sg:classifiers":[
        {
            "category":"Building & Trades",
            "subcategory":"Construction",
            "type":"Services"
        }
    ],
    "sg:phone":"+1 765 759 5830",
    "sg:postcode":"47396",
    "sg:province":"IN",
    "sg:tags":[
        "house"
    ],
    "wof:name":"York Construction & Excavati",
    "wof:placetype":"venue"
},
  "geometry": {"coordinates":[-85.480584,40.15441],"type":"Point"}
}