{
  "type": "Feature",
  "properties": {
    "iso:country":"US",
    "sg:address":"13975 Jameson Ln",
    "sg:city":"Carmel",
    "sg:classifiers":[
        {
            "category":"Professional",
            "subcategory":"Art Services",
            "type":"Services"
        }
    ],
    "sg:phone":"+1 317 846 3461",
    "sg:postcode":"46032",
    "sg:province":"IN",
    "sg:tags":[
        "artist"
    ],
    "wof:name":"Brian W Mc Farland Illustrator",
    "wof:placetype":"venue"
},
  "geometry": {"coordinates":[-86.173359,39.990438],"type":"Point"}
}