{
  "type": "Feature",
  "properties": {
    "iso:country":"US",
    "sg:address":"811 E Markland Ave",
    "sg:city":"Kokomo",
    "sg:classifiers":[
        {
            "category":"Personal",
            "subcategory":"Beauty Salon",
            "type":"Services"
        }
    ],
    "sg:phone":"+1 765 452 6277",
    "sg:postcode":"46901",
    "sg:province":"IN",
    "wof:name":"Designing Lines",
    "wof:placetype":"venue"
},
  "geometry": {"coordinates":[-86.12301,40.476463],"type":"Point"}
}