{
  "type": "Feature",
  "properties": {
    "iso:country":"US",
    "sg:address":"321 SW C St",
    "sg:city":"Richmond",
    "sg:classifiers":[
        {
            "category":"Organizations",
            "subcategory":"Religious Organization",
            "type":"Services"
        }
    ],
    "sg:phone":"+1 765 935 7783",
    "sg:postcode":"47374",
    "sg:province":"IN",
    "sg:tags":[
        "church"
    ],
    "wof:name":"Alliance Bible Church",
    "wof:placetype":"venue"
},
  "geometry": {"coordinates":[-84.905731,39.825187],"type":"Point"}
}