{
  "type": "Feature",
  "properties": {
    "addr:full":"845 W Main St Madison IN 47250",
    "addr:housenumber":"845",
    "addr:postcode":"47250",
    "addr:street":"W Main St",
    "iso:country":"US",
    "sg:address":"845 W Main St",
    "sg:city":"Madison",
    "sg:classifiers":[
        {
            "category":"Retail",
            "subcategory":"Portrait Studio",
            "type":"Services"
        }
    ],
    "sg:phone":"+1 812 265 4044",
    "sg:postcode":"47250",
    "sg:province":"IN",
    "sg:tags":[
        "photographer"
    ],
    "wof:name":"Madison Photo & Bridal Svc",
    "wof:placetype":"venue"
},
  "geometry": {"coordinates":[-85.392574,38.738569],"type":"Point"}
}