{
  "type": "Feature",
  "properties": {
    "iso:country":"US",
    "sg:address":"7717 Opportunity Dr",
    "sg:city":"Fort Wayne",
    "sg:classifiers":[
        {
            "category":"Building & Trades",
            "subcategory":"Construction",
            "type":"Services"
        }
    ],
    "sg:phone":"+1 260 489 1234",
    "sg:postcode":"46825",
    "sg:province":"IN",
    "sg:tags":[
        "general",
        "contractor"
    ],
    "wof:name":"Shawnee Construction & Engrng",
    "wof:placetype":"venue"
},
  "geometry": {"coordinates":[-85.149062,41.149269],"type":"Point"}
}