{
  "type": "Feature",
  "properties": {
    "iso:country":"US",
    "sg:address":"215 W Main St",
    "sg:city":"Pennville",
    "sg:classifiers":[
        {
            "category":"Building & Trades",
            "subcategory":"Construction",
            "type":"Services"
        }
    ],
    "sg:phone":"+1 260 731 5593",
    "sg:postcode":"47369",
    "sg:province":"IN",
    "sg:tags":[
        "excavating",
        "contractor"
    ],
    "wof:name":"Corwin Trenching Svc",
    "wof:placetype":"venue"
},
  "geometry": {"coordinates":[-85.150648,40.492462],"type":"Point"}
}