{
  "type": "Feature",
  "properties": {
    "addr:full":"108 E 14th St Marion IN 46953",
    "addr:housenumber":"108",
    "addr:postcode":"46953",
    "addr:street":"E 14Th St",
    "iso:country":"US",
    "sg:address":"108 E 14th St",
    "sg:city":"Marion",
    "sg:classifiers":[
        {
            "category":"Social Services",
            "type":"Services"
        }
    ],
    "sg:phone":"+1 765 662 1393",
    "sg:postcode":"46953",
    "sg:province":"IN",
    "sg:tags":[
        "organization",
        "welfare"
    ],
    "wof:name":"Genesis Place",
    "wof:placetype":"venue"
},
  "geometry": {"coordinates":[-85.65864999999999,40.548269],"type":"Point"}
}