{
  "type": "Feature",
  "properties": {
    "iso:country":"US",
    "sg:address":"654 Indiana St",
    "sg:city":"Berne",
    "sg:classifiers":[
        {
            "category":"Personal",
            "subcategory":"Beauty Salon",
            "type":"Services"
        }
    ],
    "sg:phone":"+1 260 589 2896",
    "sg:postcode":"46711",
    "sg:province":"IN",
    "sg:tags":[
        "shop"
    ],
    "wof:name":"Sharons Beauty Shop",
    "wof:placetype":"venue"
},
  "geometry": {"coordinates":[-84.953936,40.653136],"type":"Point"}
}