{
  "type": "Feature",
  "properties": {
    "iso:country":"US",
    "sg:address":"1744 Broadway",
    "sg:city":"Gary",
    "sg:classifiers":[
        {
            "category":"Restaurant",
            "type":"Food & Drink"
        }
    ],
    "sg:phone":"+1 219 882 2287",
    "sg:postcode":"46407",
    "sg:province":"IN",
    "wof:name":"L L's Coney Island",
    "wof:placetype":"venue"
},
  "geometry": {"coordinates":[-87.337076,41.585352],"type":"Point"}
}