{
  "type": "Feature",
  "properties": {
    "iso:country":"US",
    "sg:address":"7301 Mardyke Ln",
    "sg:city":"Lawrence",
    "sg:classifiers":[
        {
            "category":"Building & Trades",
            "subcategory":"Construction",
            "type":"Services"
        }
    ],
    "sg:phone":"+1 317 546 0164",
    "sg:postcode":"46226",
    "sg:province":"IN",
    "sg:tags":[
        "builder",
        "patio",
        "deck"
    ],
    "wof:name":"Midwest Wood Renovation Inc",
    "wof:placetype":"venue"
},
  "geometry": {"coordinates":[-86.044451,39.852381],"type":"Point"}
}