{
  "type": "Feature",
  "properties": {
    "addr:full":"8425 Woodfield Crossing Blvd Indianapolis IN 46240",
    "addr:housenumber":"8425",
    "addr:postcode":"46240",
    "addr:street":"Woodfield Crossing Blvd",
    "iso:country":"US",
    "sg:address":"8425 Woodfield Crossing Blvd",
    "sg:city":"Indianapolis",
    "sg:classifiers":[
        {
            "category":"Professional",
            "subcategory":"Management & Consulting",
            "type":"Services"
        }
    ],
    "sg:phone":"+1 317 469 4255",
    "sg:postcode":"46240",
    "sg:province":"IN",
    "sg:tags":[
        "consultant",
        "business"
    ],
    "sg:website":"www.right.com",
    "wof:name":"Right Management Consultants",
    "wof:placetype":"venue"
},
  "geometry": {"coordinates":[-86.120125,39.909799],"type":"Point"}
}