{
  "type": "Feature",
  "properties": {
    "addr:full":"10336 Leo Rd Fort Wayne IN 46825",
    "addr:housenumber":"10336",
    "addr:postcode":"46825",
    "addr:street":"Leo Rd",
    "iso:country":"US",
    "sg:address":"10336 Leo Rd",
    "sg:city":"Fort Wayne",
    "sg:classifiers":[
        {
            "category":"Restaurant",
            "type":"Food & Drink"
        }
    ],
    "sg:menulink":"http://www.allmenus.com/in/cedar-creek/47839-bad-dog-saloon/menu/",
    "sg:phone":"+1 260 483 1311",
    "sg:postcode":"46825",
    "sg:province":"IN",
    "sg:tags":[
        "wrap",
        "american",
        "sandwich"
    ],
    "wof:name":"Bad Dog Saloon",
    "wof:placetype":"venue"
},
  "geometry": {"coordinates":[-85.074958,41.179947],"type":"Point"}
}