{
  "type": "Feature",
  "properties": {
    "addr:full":"1950 Saint Charles St Jasper IN 47546",
    "addr:housenumber":"1950",
    "addr:postcode":"47546",
    "addr:street":"Saint Charles St",
    "iso:country":"US",
    "sg:address":"1950 Saint Charles St",
    "sg:city":"Jasper",
    "sg:classifiers":[
        {
            "category":"Health Services",
            "subcategory":"Doctor",
            "type":"Services"
        }
    ],
    "sg:phone":"+1 812 482 4321",
    "sg:postcode":"47546",
    "sg:province":"IN",
    "sg:tags":[
        "dentist"
    ],
    "wof:name":"Lesley Kizior DDS",
    "wof:placetype":"venue"
},
  "geometry": {"coordinates":[-86.951829,38.405031],"type":"Point"}
}