{
  "type": "Feature",
  "properties": {
    "addr:full":"1400 W State Rte 68 Lynnville IN 47619",
    "addr:housenumber":"1400",
    "addr:postcode":"47619",
    "addr:street":"W State Rte 68 Lynnville",
    "iso:country":"US",
    "sg:address":"1400 W State Rte 68",
    "sg:city":"Lynnville",
    "sg:phone":"+1 812 922 5308",
    "sg:postcode":"47619",
    "sg:province":"IN",
    "sg:tags":[
        "farm",
        "corn"
    ],
    "wof:name":"Alan Graper",
    "wof:placetype":"venue"
},
  "geometry": {"coordinates":[-87.270655,38.200291],"type":"Point"}
}