{
  "type": "Feature",
  "properties": {
    "addr:full":"620 State Rd 39 Byp Martinsville IN 46151",
    "addr:housenumber":"620",
    "addr:postcode":"46151",
    "addr:street":"State Rd 39 Byp",
    "iso:country":"US",
    "sg:address":"620 State Rd 39 Byp",
    "sg:city":"Martinsville",
    "sg:classifiers":[
        {
            "category":"Restaurant",
            "type":"Food & Drink"
        }
    ],
    "sg:phone":"+1 765 342 7621",
    "sg:postcode":"46151",
    "sg:province":"IN",
    "wof:name":"Mr Gatti's Pizza",
    "wof:placetype":"venue"
},
  "geometry": {"coordinates":[-86.43560600000001,39.421377],"type":"Point"}
}