{
  "type": "Feature",
  "properties": {
    "iso:country":"US",
    "sg:address":"602 N Front St",
    "sg:city":"Whiteland",
    "sg:classifiers":[
        {
            "category":"Retail",
            "subcategory":"Auto Repair",
            "type":"Services"
        }
    ],
    "sg:phone":"+1 317 535 2300",
    "sg:postcode":"46184",
    "sg:province":"IN",
    "sg:tags":[
        "repairing",
        "automobile"
    ],
    "wof:name":"Duff's Automotive",
    "wof:placetype":"venue"
},
  "geometry": {"coordinates":[-86.078238,39.554067],"type":"Point"}
}