{
  "type": "Feature",
  "properties": {
    "iso:country":"US",
    "sg:address":"6270 E Union City Pike",
    "sg:city":"Union City",
    "sg:classifiers":[
        {
            "category":"Building & Trades",
            "subcategory":"Electrical",
            "type":"Services"
        }
    ],
    "sg:phone":"+1 765 964 4271",
    "sg:postcode":"47390",
    "sg:province":"IN",
    "sg:tags":[
        "electrical",
        "contractor"
    ],
    "wof:name":"Mills Electric",
    "wof:placetype":"venue"
},
  "geometry": {"coordinates":[-84.857198,40.200412],"type":"Point"}
}