{
  "type": "Feature",
  "properties": {
    "addr:full":"901 State Rd 47 N Crawfordsville IN 47933",
    "addr:housenumber":"901;47",
    "addr:postcode":"47933",
    "addr:street":"State Rd;N",
    "iso:country":"US",
    "sg:address":"901 State Rd 47 N",
    "sg:city":"Crawfordsville",
    "sg:classifiers":[
        {
            "category":"Professional",
            "subcategory":"Business Services",
            "type":"Services"
        }
    ],
    "sg:phone":"+1 765 362 0831",
    "sg:postcode":"47933",
    "sg:province":"IN",
    "wof:name":"Central Indiana Home Insp",
    "wof:placetype":"venue"
},
  "geometry": {"coordinates":[-86.889664,40.042916],"type":"Point"}
}