{
  "type": "Feature",
  "properties": {
    "iso:country":"US",
    "sg:address":"650 S Lake Rd S",
    "sg:city":"Scottsburg",
    "sg:classifiers":[
        {
            "category":"Recreation",
            "type":"Entertainment"
        }
    ],
    "sg:phone":"+1 812 752 7087",
    "sg:postcode":"47170",
    "sg:province":"IN",
    "sg:tags":[
        "instruction",
        "gymnastic"
    ],
    "wof:name":"All Star Tumbling",
    "wof:placetype":"venue"
},
  "geometry": {"coordinates":[-85.794252,38.679536],"type":"Point"}
}