{
  "type": "Feature",
  "properties": {
    "iso:country":"US",
    "sg:address":"111 N Main St",
    "sg:city":"Monticello",
    "sg:classifiers":[
        {
            "category":"Professional",
            "type":"Services"
        }
    ],
    "sg:phone":"+1 574 583 4616",
    "sg:postcode":"47960",
    "sg:province":"IN",
    "wof:name":"Juan J Ramirez",
    "wof:placetype":"venue"
},
  "geometry": {"coordinates":[-86.761854,40.747266],"type":"Point"}
}