{
  "type": "Feature",
  "properties": {
    "iso:country":"US",
    "sg:address":"3687 S Co Rd 600 E",
    "sg:city":"Seymour",
    "sg:classifiers":[
        {
            "category":"Farming",
            "subcategory":"Dairy Farm",
            "type":"Manufacturing & Wholesale Goods"
        }
    ],
    "sg:phone":"+1 812 523 8921",
    "sg:postcode":"47274",
    "sg:province":"IN",
    "wof:name":"Rothert Marlin",
    "wof:placetype":"venue"
},
  "geometry": {"coordinates":[-85.924147,38.82716],"type":"Point"}
}