{
  "type": "Feature",
  "properties": {
    "addr:full":"232 N Brooks St Francesville IN 47946",
    "addr:housenumber":"232",
    "addr:postcode":"47946",
    "addr:street":"N Brooks St",
    "iso:country":"US",
    "sg:address":"232 N Brooks St",
    "sg:city":"Francesville",
    "sg:classifiers":[
        {
            "category":"Retail",
            "subcategory":"Funeral Services",
            "type":"Services"
        }
    ],
    "sg:phone":"+1 219 567 9551",
    "sg:postcode":"47946",
    "sg:province":"IN",
    "sg:tags":[
        "director"
    ],
    "wof:name":"Querry & Ulbricht Funeral Home",
    "wof:placetype":"venue"
},
  "geometry": {"coordinates":[-86.88072,40.987126],"type":"Point"}
}