{
  "type": "Feature",
  "properties": {
    "addr:full":"1725 E Tipton St Seymour IN 47274",
    "addr:housenumber":"1725",
    "addr:postcode":"47274",
    "addr:street":"E Tipton St",
    "iso:country":"US",
    "sg:address":"1725 E Tipton St",
    "sg:city":"Seymour",
    "sg:classifiers":[
        {
            "category":"Food & Beverages",
            "subcategory":"Groceries & Convenience Stores",
            "type":"Retail Goods"
        }
    ],
    "sg:phone":"+1 812 522 2224",
    "sg:postcode":"47274",
    "sg:province":"IN",
    "sg:website":"www.kocolenemarketing.com",
    "wof:name":"Kocolene Marketing LLC",
    "wof:placetype":"venue"
},
  "geometry": {"coordinates":[-85.859897,38.958173],"type":"Point"}
}