{
  "type": "Feature",
  "properties": {
    "iso:country":"US",
    "sg:address":"103 S Main St",
    "sg:city":"Dunkirk",
    "sg:classifiers":[
        {
            "category":"Shopping",
            "subcategory":"Department Store",
            "type":"Retail Goods"
        }
    ],
    "sg:phone":"+1 765 768 6553",
    "sg:postcode":"47336",
    "sg:province":"IN",
    "sg:tags":[
        "shop"
    ],
    "wof:name":"Penny Pinchers",
    "wof:placetype":"venue"
},
  "geometry": {"coordinates":[-85.209729,40.374921],"type":"Point"}
}