{
  "type": "Feature",
  "properties": {
    "iso:country":"US",
    "sg:address":"1128 W 37th St",
    "sg:city":"Indianapolis",
    "sg:classifiers":[
        {
            "category":"Professional",
            "type":"Services"
        }
    ],
    "sg:phone":"+1 317 925 7669",
    "sg:postcode":"46208",
    "sg:province":"IN",
    "sg:tags":[
        "establishment"
    ],
    "wof:name":"Tracy's",
    "wof:placetype":"venue"
},
  "geometry": {"coordinates":[-86.18051699999999,39.81845],"type":"Point"}
}