{
  "type": "Feature",
  "properties": {
    "iso:country":"US",
    "sg:address":"57275 Pine Rd",
    "sg:city":"South Bend",
    "sg:classifiers":[
        {
            "category":"Real Estate",
            "subcategory":"Real Estate Agent",
            "type":"Services"
        }
    ],
    "sg:phone":"+1 574 233 5045",
    "sg:postcode":"46619",
    "sg:province":"IN",
    "wof:name":"Home Plus Realty",
    "wof:placetype":"venue"
},
  "geometry": {"coordinates":[-86.35092899999999,41.659334],"type":"Point"}
}