{
  "type": "Feature",
  "properties": {
    "addr:full":"6322 W Thompson Rd Indianapolis IN 46221",
    "addr:housenumber":"6322",
    "addr:postcode":"46221",
    "addr:street":"W Thompson Rd",
    "iso:country":"US",
    "sg:address":"6322 W Thompson Rd",
    "sg:city":"Indianapolis",
    "sg:classifiers":[
        {
            "category":"Health Services",
            "subcategory":"Chiropractor",
            "type":"Services"
        }
    ],
    "sg:phone":"+1 317 856 4802",
    "sg:postcode":"46221",
    "sg:province":"IN",
    "wof:name":"Heavin Chiropractic Clinic",
    "wof:placetype":"venue"
},
  "geometry": {"coordinates":[-86.27141899999999,39.69224],"type":"Point"}
}