{
  "type": "Feature",
  "properties": {
    "addr:full":"28810 Co Rd 38 Wakarusa IN 46573",
    "addr:housenumber":"28810;38",
    "addr:postcode":"46573",
    "addr:street":"Co Rd",
    "iso:country":"US",
    "sg:address":"28810 Co Rd 38",
    "sg:city":"Wakarusa",
    "sg:classifiers":[
        {
            "category":"Insurance",
            "subcategory":"Insurance Agent",
            "type":"Services"
        }
    ],
    "sg:phone":"+1 574 862 1962",
    "sg:postcode":"46573",
    "sg:province":"IN",
    "sg:tags":[
        "consulting",
        "management"
    ],
    "wof:name":"Timothy J Loutzenhiser",
    "wof:placetype":"venue"
},
  "geometry": {"coordinates":[-86.017364,41.550521],"type":"Point"}
}