{
  "type": "Feature",
  "properties": {
    "iso:country":"US",
    "sg:address":"5250 Keystone Ct",
    "sg:city":"Indianapolis",
    "sg:classifiers":[
        {
            "category":"Personal",
            "subcategory":"Barber",
            "type":"Services"
        }
    ],
    "sg:phone":"+1 317 726 1111",
    "sg:postcode":"46220",
    "sg:province":"IN",
    "wof:name":"All-N-1",
    "wof:placetype":"venue"
},
  "geometry": {"coordinates":[-86.12375400000001,39.848619],"type":"Point"}
}