{
  "type": "Feature",
  "properties": {
    "iso:country":"US",
    "sg:address":"901 Conner St",
    "sg:city":"Noblesville",
    "sg:classifiers":[
        {
            "category":"Professional",
            "type":"Services"
        }
    ],
    "sg:phone":"+1 317 770 6200",
    "sg:postcode":"46060",
    "sg:province":"IN",
    "sg:tags":[
        "establishment"
    ],
    "wof:name":"Express Line",
    "wof:placetype":"venue"
},
  "geometry": {"coordinates":[-86.013482,40.045601],"type":"Point"}
}