{
  "type": "Feature",
  "properties": {
    "addr:full":"1100 S Main St Goshen IN 46526",
    "addr:housenumber":"1100",
    "addr:postcode":"46526",
    "addr:street":"S Main St",
    "iso:country":"US",
    "sg:address":"1100 S Main St",
    "sg:city":"Goshen",
    "sg:classifiers":[
        {
            "category":"Shopping",
            "subcategory":"Books",
            "type":"Retail Goods"
        }
    ],
    "sg:phone":"+1 574 606 1112",
    "sg:postcode":"46526",
    "sg:province":"IN",
    "wof:name":"B&M Personalized",
    "wof:placetype":"venue"
},
  "geometry": {"coordinates":[-85.83014,41.571993],"type":"Point"}
}