{
  "type": "Feature",
  "properties": {
    "iso:country":"US",
    "sg:address":"4825 Stratford Ave",
    "sg:city":"Indianapolis",
    "sg:classifiers":[
        {
            "category":"Building & Trades",
            "subcategory":"Construction",
            "type":"Services"
        }
    ],
    "sg:phone":"+1 317 356 3760",
    "sg:postcode":"46201",
    "sg:province":"IN",
    "sg:tags":[
        "painter"
    ],
    "wof:name":"D & R Painting & Decorating",
    "wof:placetype":"venue"
},
  "geometry": {"coordinates":[-86.086974,39.762001],"type":"Point"}
}