{
  "type": "Feature",
  "properties": {
    "iso:country":"US",
    "sg:address":"56629 S Mayflower Rd",
    "sg:city":"South Bend",
    "sg:classifiers":[
        {
            "category":"Bars & Pubs",
            "type":"Food & Drink"
        }
    ],
    "sg:phone":"+1 574 233 5168",
    "sg:postcode":"46619",
    "sg:province":"IN",
    "wof:name":"West Winds",
    "wof:placetype":"venue"
},
  "geometry": {"coordinates":[-86.322125,41.671794],"type":"Point"}
}