{
  "type": "Feature",
  "properties": {
    "iso:country":"US",
    "sg:address":"3154 N Ritter Ave",
    "sg:city":"Indianapolis",
    "sg:classifiers":[
        {
            "category":"Wholesale",
            "subcategory":"Auto Parts",
            "type":"Manufacturing & Wholesale Goods"
        }
    ],
    "sg:phone":"+1 317 547 3730",
    "sg:postcode":"46218",
    "sg:province":"IN",
    "sg:tags":[
        "automobile",
        "rebuilt",
        "supplies-used"
    ],
    "wof:name":"Barlow Used Parts Inc",
    "wof:placetype":"venue"
},
  "geometry": {"coordinates":[-86.074096,39.814031],"type":"Point"}
}