{
  "type": "Feature",
  "properties": {
    "iso:country":"US",
    "sg:address":"3632 E 700 S",
    "sg:city":"Warren",
    "sg:classifiers":[
        {
            "category":"Farming",
            "subcategory":"Livestock Farm",
            "type":"Manufacturing & Wholesale Goods"
        }
    ],
    "sg:phone":"+1 260 375 2288",
    "sg:postcode":"46792",
    "sg:province":"IN",
    "sg:tags":[
        "hog",
        "or",
        "feedlot"
    ],
    "wof:name":"Renbarger Farm",
    "wof:placetype":"venue"
},
  "geometry": {"coordinates":[-85.385177,40.726807],"type":"Point"}
}