{
  "type": "Feature",
  "properties": {
    "iso:country":"US",
    "sg:address":"187 Summertree Dr",
    "sg:city":"Chesterton",
    "sg:classifiers":[
        {
            "category":"Wholesale",
            "subcategory":"Machinery & Supplies",
            "type":"Manufacturing & Wholesale Goods"
        }
    ],
    "sg:phone":"+1 219 983 9977",
    "sg:postcode":"46304",
    "sg:province":"IN",
    "sg:tags":[
        "equipment",
        "material",
        "handling"
    ],
    "wof:name":"Ssi Technology Inc",
    "wof:placetype":"venue"
},
  "geometry": {"coordinates":[-87.070768,41.632504],"type":"Point"}
}