{
  "type": "Feature",
  "properties": {
    "iso:country":"US",
    "sg:address":"54655 28th St",
    "sg:city":"South Bend",
    "sg:classifiers":[
        {
            "category":"Social Services",
            "type":"Services"
        }
    ],
    "sg:phone":"+1 574 243 0927",
    "sg:postcode":"46635",
    "sg:province":"IN",
    "sg:tags":[
        "organization",
        "welfare"
    ],
    "wof:name":"Liberia Association-Michiana",
    "wof:placetype":"venue"
},
  "geometry": {"coordinates":[-86.20935299999999,41.698898],"type":"Point"}
}