{
  "type": "Feature",
  "properties": {
    "iso:country":"US",
    "sg:address":"575 N 21st St",
    "sg:city":"Terre Haute",
    "sg:classifiers":[
        {
            "category":"Shopping",
            "subcategory":"Florist",
            "type":"Retail Goods"
        }
    ],
    "sg:phone":"+1 812 232 9606",
    "sg:postcode":"47807",
    "sg:province":"IN",
    "wof:name":"Cowan & Cook Florist",
    "wof:placetype":"venue"
},
  "geometry": {"coordinates":[-87.386385,39.47463],"type":"Point"}
}