{
  "type": "Feature",
  "properties": {
    "iso:country":"US",
    "sg:address":"1929 Lakeview Dr",
    "sg:city":"Fort Wayne",
    "sg:classifiers":[
        {
            "category":"Manufacturing",
            "subcategory":"Tools & Machinery",
            "type":"Manufacturing & Wholesale Goods"
        }
    ],
    "sg:phone":"+1 260 436 5741",
    "sg:postcode":"46808",
    "sg:province":"IN",
    "sg:tags":[
        "machine",
        "shop"
    ],
    "wof:name":"Randal's Machine & Welding",
    "wof:placetype":"venue"
},
  "geometry": {"coordinates":[-85.174374,41.093927],"type":"Point"}
}