{
  "type": "Feature",
  "properties": {
    "addr:full":"110 Elm St Clinton IN 47842",
    "addr:housenumber":"110",
    "addr:postcode":"47842",
    "addr:street":"Elm St",
    "iso:country":"US",
    "sg:address":"110 Elm St",
    "sg:city":"Clinton",
    "sg:classifiers":[
        {
            "category":"Ice Cream",
            "type":"Food & Drink"
        }
    ],
    "sg:menulink":"http://www.allmenus.com/in/clinton/161558-dairy-queen/menu/",
    "sg:phone":"+1 765 832 2537",
    "sg:postcode":"47842",
    "sg:province":"IN",
    "sg:tags":[
        "burger",
        "american"
    ],
    "wof:name":"Dairy Queen",
    "wof:placetype":"venue"
},
  "geometry": {"coordinates":[-87.39699899999999,39.657155],"type":"Point"}
}