{
  "type": "Feature",
  "properties": {
    "iso:country":"US",
    "sg:address":"68845 Co Rd 11",
    "sg:city":"Nappanee",
    "sg:classifiers":[
        {
            "category":"Wholesale",
            "subcategory":"Farm Supplies",
            "type":"Manufacturing & Wholesale Goods"
        }
    ],
    "sg:phone":"+1 574 831 2611",
    "sg:postcode":"46550",
    "sg:province":"IN",
    "wof:name":"Irvin Martin & Son's Woodshvng",
    "wof:placetype":"venue"
},
  "geometry": {"coordinates":[-85.94399,41.496833],"type":"Point"}
}