{
  "type": "Feature",
  "properties": {
    "iso:country":"US",
    "sg:address":"1210 S Hackley St",
    "sg:city":"Muncie",
    "sg:classifiers":[
        {
            "category":"Organizations",
            "subcategory":"Religious Organization",
            "type":"Services"
        }
    ],
    "sg:phone":"+1 765 284 4515",
    "sg:postcode":"47302",
    "sg:province":"IN",
    "wof:name":"Trinity United Methodist",
    "wof:placetype":"venue"
},
  "geometry": {"coordinates":[-85.377052,40.183655],"type":"Point"}
}