{
  "type": "Feature",
  "properties": {
    "addr:full":"7045 Brenlee Dr Georgetown IN 47122",
    "addr:housenumber":"7045",
    "addr:postcode":"47122",
    "addr:street":"Brenlee Dr",
    "iso:country":"US",
    "sg:address":"7045 Brenlee Dr",
    "sg:city":"Georgetown",
    "sg:classifiers":[
        {
            "category":"Manufacturing",
            "subcategory":"Wood Products",
            "type":"Manufacturing & Wholesale Goods"
        },
        {
            "category":"Manufacturing",
            "subcategory":"Building Materials",
            "type":"Manufacturing & Wholesale Goods"
        }
    ],
    "sg:phone":"+1 812 923 3551",
    "sg:postcode":"47122",
    "sg:province":"IN",
    "sg:tags":[
        "veneers-wholesale",
        "materials-wholesale",
        "plywood",
        "manufacturer"
    ],
    "wof:name":"Quality Veneer",
    "wof:placetype":"venue"
},
  "geometry": {"coordinates":[-85.955084,38.336136],"type":"Point"}
}