{
  "type": "Feature",
  "properties": {
    "iso:country":"US",
    "sg:address":"5397 S Elm St",
    "sg:city":"Knox",
    "sg:classifiers":[
        {
            "category":"Restaurant",
            "type":"Food & Drink"
        }
    ],
    "sg:phone":"+1 574 772 5344",
    "sg:postcode":"46534",
    "sg:province":"IN",
    "sg:tags":[
        "caterer"
    ],
    "wof:name":"Wyma Catering",
    "wof:placetype":"venue"
},
  "geometry": {"coordinates":[-86.591998,41.227853],"type":"Point"}
}