{
  "type": "Feature",
  "properties": {
    "iso:country":"US",
    "sg:address":"2054 Hanley St",
    "sg:city":"Gary",
    "sg:classifiers":[
        {
            "category":"Professional",
            "type":"Services"
        }
    ],
    "sg:phone":"+1 219 949 6601",
    "sg:postcode":"46406",
    "sg:province":"IN",
    "wof:name":"International Bus Comm Inc",
    "wof:placetype":"venue"
},
  "geometry": {"coordinates":[-87.401132,41.581103],"type":"Point"}
}