{
  "type": "Feature",
  "properties": {
    "iso:country":"US",
    "sg:address":"533 E Main St",
    "sg:city":"Brownsburg",
    "sg:classifiers":[
        {
            "category":"Insurance",
            "subcategory":"Insurance Agent",
            "type":"Services"
        }
    ],
    "sg:phone":"+1 317 852 1970",
    "sg:postcode":"46112",
    "sg:province":"IN",
    "wof:name":"Federated Insurance Co",
    "wof:placetype":"venue"
},
  "geometry": {"coordinates":[-86.389785,39.840893],"type":"Point"}
}