{
  "type": "Feature",
  "properties": {
    "iso:country":"US",
    "sg:address":"725 7th St",
    "sg:city":"Columbus",
    "sg:classifiers":[
        {
            "category":"Education",
            "subcategory":"School",
            "type":"Public Place"
        }
    ],
    "sg:phone":"+1 812 376 4286",
    "sg:postcode":"47201",
    "sg:province":"IN",
    "wof:name":"Central Middle School",
    "wof:placetype":"venue"
},
  "geometry": {"coordinates":[-85.916845,39.205606],"type":"Point"}
}