{
  "type": "Feature",
  "properties": {
    "iso:country":"US",
    "sg:address":"10605 Deme Dr",
    "sg:city":"Indianapolis",
    "sg:classifiers":[
        {
            "category":"Professional",
            "subcategory":"Business Services",
            "type":"Services"
        }
    ],
    "sg:phone":"+1 317 826 4467",
    "sg:postcode":"46236",
    "sg:province":"IN",
    "sg:tags":[
        "paging",
        "signaling"
    ],
    "wof:name":"SBC Paging",
    "wof:placetype":"venue"
},
  "geometry": {"coordinates":[-85.978713,39.861403],"type":"Point"}
}