{
  "type": "Feature",
  "properties": {
    "iso:country":"US",
    "sg:address":"1118 S Pocket Rd",
    "sg:city":"Batesville",
    "sg:phone":"+1 812 934 4489",
    "sg:postcode":"47006",
    "sg:province":"IN",
    "sg:tags":[
        "farm",
        "corn",
        "soybean"
    ],
    "wof:name":"Schone John",
    "wof:placetype":"venue"
},
  "geometry": {"coordinates":[-85.2775,39.295363],"type":"Point"}
}