{
  "type": "Feature",
  "properties": {
    "iso:country":"US",
    "sg:address":"6653 E Co Rd 950 S",
    "sg:city":"Cloverdale",
    "sg:phone":"+1 765 795 4133",
    "sg:postcode":"46120",
    "sg:province":"IN",
    "sg:tags":[
        "farm",
        "corn"
    ],
    "wof:name":"Terry Farms",
    "wof:placetype":"venue"
},
  "geometry": {"coordinates":[-86.73759699999999,39.521782],"type":"Point"}
}