{
  "type": "Feature",
  "properties": {
    "iso:country":"US",
    "sg:address":"2802 Merchants Dr",
    "sg:city":"Indianapolis",
    "sg:classifiers":[
        {
            "category":"Organizations",
            "subcategory":"Community Association",
            "type":"Services"
        }
    ],
    "sg:phone":"+1 317 920 5919",
    "sg:postcode":"46222",
    "sg:province":"IN",
    "sg:tags":[
        "club"
    ],
    "wof:name":"Ticket Booth Club Mecca",
    "wof:placetype":"venue"
},
  "geometry": {"coordinates":[-86.222707,39.809057],"type":"Point"}
}