{
  "type": "Feature",
  "properties": {
    "iso:country":"US",
    "sg:address":"2006 Raintree Dr",
    "sg:city":"Elkhart",
    "sg:classifiers":[
        {
            "category":"Shopping",
            "type":"Retail Goods"
        }
    ],
    "sg:phone":"+1 574 264 0063",
    "sg:postcode":"46514",
    "sg:province":"IN",
    "sg:tags":[
        "merchandise"
    ],
    "wof:name":"Art World of Indiana",
    "wof:placetype":"venue"
},
  "geometry": {"coordinates":[-85.946482,41.705992],"type":"Point"}
}