{
  "type": "Feature",
  "properties": {
    "addr:full":"6691 W State Rd 46 Columbus IN 47201",
    "addr:housenumber":"6691;46",
    "addr:postcode":"47201",
    "addr:street":"W State Rd",
    "iso:country":"US",
    "sg:address":"6691 W State Rd 46",
    "sg:city":"Columbus",
    "sg:classifiers":[
        {
            "category":"Education",
            "subcategory":"School",
            "type":"Public Place"
        }
    ],
    "sg:phone":"+1 812 342 3029",
    "sg:postcode":"47201",
    "sg:province":"IN",
    "sg:website":"www.abc-stewart.org",
    "wof:name":"ABC Stewart Montessori School",
    "wof:placetype":"venue"
},
  "geometry": {"coordinates":[-85.996123,39.196685],"type":"Point"}
}