{
  "type": "Feature",
  "properties": {
    "iso:country":"US",
    "sg:address":"705 C Ave E",
    "sg:city":"Seymour",
    "sg:classifiers":[
        {
            "category":"Government",
            "subcategory":"Office",
            "type":"Public Place"
        }
    ],
    "sg:phone":"+1 812 522 7229",
    "sg:postcode":"47274",
    "sg:province":"IN",
    "sg:tags":[
        "village"
    ],
    "wof:name":"Seymour Maintenance Garage",
    "wof:placetype":"venue"
},
  "geometry": {"coordinates":[-85.897559,38.934976],"type":"Point"}
}