{
  "type": "Feature",
  "properties": {
    "iso:country":"US",
    "sg:address":"432 S 5th St",
    "sg:city":"Clinton",
    "sg:classifiers":[
        {
            "category":"Professional",
            "subcategory":"Business Services",
            "type":"Services"
        }
    ],
    "sg:phone":"+1 765 832 3253",
    "sg:postcode":"47842",
    "sg:province":"IN",
    "wof:name":"Royal Arch Masons of Indi",
    "wof:placetype":"venue"
},
  "geometry": {"coordinates":[-87.402424,39.656767],"type":"Point"}
}