{
  "type": "Feature",
  "properties": {
    "iso:country":"US",
    "sg:address":"1103 Riverside Dr",
    "sg:city":"Huntington",
    "sg:classifiers":[
        {
            "category":"Wholesale",
            "subcategory":"Beer",
            "type":"Manufacturing & Wholesale Goods"
        }
    ],
    "sg:phone":"+1 260 356 6910",
    "sg:postcode":"46750",
    "sg:province":"IN",
    "sg:tags":[
        "ale"
    ],
    "wof:name":"City Beverage Inc",
    "wof:placetype":"venue"
},
  "geometry": {"coordinates":[-85.479113,40.880244],"type":"Point"}
}