{
  "type": "Feature",
  "properties": {
    "iso:country":"US",
    "sg:address":"5896 N Stahl Rd",
    "sg:city":"Monon",
    "sg:classifiers":[
        {
            "category":"Building & Trades",
            "subcategory":"Construction",
            "type":"Services"
        }
    ],
    "sg:phone":"+1 219 253 8280",
    "sg:postcode":"47959",
    "sg:province":"IN",
    "sg:tags":[
        "house",
        "general",
        "contractor"
    ],
    "wof:name":"Studio 46 Construction",
    "wof:placetype":"venue"
},
  "geometry": {"coordinates":[-86.806528,40.83977],"type":"Point"}
}