{
  "type": "Feature",
  "properties": {
    "iso:country":"US",
    "sg:address":"825 Sycamore St",
    "sg:city":"Rockport",
    "sg:classifiers":[
        {
            "category":"Insurance",
            "subcategory":"Insurance Agent",
            "type":"Services"
        }
    ],
    "sg:phone":"+1 812 649 5848",
    "sg:postcode":"47635",
    "sg:province":"IN",
    "wof:name":"Angela Hart Agency Inc",
    "wof:placetype":"venue"
},
  "geometry": {"coordinates":[-87.055419,37.891672],"type":"Point"}
}