{
  "type": "Feature",
  "properties": {
    "iso:country":"US",
    "sg:address":"3639 169th St",
    "sg:city":"Hammond",
    "sg:classifiers":[
        {
            "category":"Fast Food",
            "type":"Food & Drink"
        },
        {
            "category":"Food & Beverages",
            "subcategory":"Meat & Fish",
            "type":"Retail Goods"
        }
    ],
    "sg:phone":"+1 219 845 8625",
    "sg:postcode":"46323",
    "sg:province":"IN",
    "sg:tags":[
        "burger",
        "hot",
        "dog"
    ],
    "sg:website":"www.mcdonalds.com",
    "wof:name":"McDonalds Hamburgers",
    "wof:placetype":"venue"
},
  "geometry": {"coordinates":[-87.44068300000001,41.588304],"type":"Point"}
}