{
  "type": "Feature",
  "properties": {
    "addr:full":"822 Herrenbruck Ln Evansville IN 47712",
    "addr:housenumber":"822",
    "addr:postcode":"47712",
    "addr:street":"Herrenbruck Ln",
    "iso:country":"US",
    "sg:address":"822 Herrenbruck Ln",
    "sg:city":"Evansville",
    "sg:classifiers":[
        {
            "category":"Real Estate",
            "subcategory":"Real Estate Operator",
            "type":"Services"
        }
    ],
    "sg:phone":"+1 812 985 2688",
    "sg:postcode":"47712",
    "sg:province":"IN",
    "sg:tags":[
        "property",
        "lessor"
    ],
    "wof:name":"Herrenbruck Farms",
    "wof:placetype":"venue"
},
  "geometry": {"coordinates":[-87.73503599999999,38.029871],"type":"Point"}
}