{
  "type": "Feature",
  "properties": {
    "iso:country":"US",
    "sg:address":"2432 Clifty Dr",
    "sg:city":"Madison",
    "sg:classifiers":[
        {
            "category":"Health Services",
            "subcategory":"Chiropractor",
            "type":"Services"
        }
    ],
    "sg:phone":"+1 812 265 1000",
    "sg:postcode":"47250",
    "sg:province":"IN",
    "wof:name":"Clifty Falls Chiropractic Ctr",
    "wof:placetype":"venue"
},
  "geometry": {"coordinates":[-85.447659,38.768797],"type":"Point"}
}