{
  "type": "Feature",
  "properties": {
    "iso:country":"US",
    "sg:address":"15276 Michigan Rd",
    "sg:city":"Argos",
    "sg:classifiers":[
        {
            "category":"Retail",
            "subcategory":"Auto Rental",
            "type":"Services"
        }
    ],
    "sg:phone":"+1 574 892 6440",
    "sg:postcode":"46501",
    "sg:province":"IN",
    "sg:tags":[
        "trailer",
        "utility"
    ],
    "wof:name":"Gordon Taiclet Rentals",
    "wof:placetype":"venue"
},
  "geometry": {"coordinates":[-86.249581,41.246488],"type":"Point"}
}