{
  "type": "Feature",
  "properties": {
    "iso:country":"US",
    "sg:address":"9213 S Sullivan Pl",
    "sg:city":"Terre Haute",
    "sg:classifiers":[
        {
            "category":"Organizations",
            "subcategory":"Religious Organization",
            "type":"Services"
        }
    ],
    "sg:phone":"+1 812 298 8641",
    "sg:postcode":"47802",
    "sg:province":"IN",
    "sg:tags":[
        "church"
    ],
    "wof:name":"Farmers Chapel Community Chr",
    "wof:placetype":"venue"
},
  "geometry": {"coordinates":[-87.436672,39.350904],"type":"Point"}
}