{
  "type": "Feature",
  "properties": {
    "iso:country":"US",
    "sg:address":"2021 Hulman St",
    "sg:city":"Terre Haute",
    "sg:classifiers":[
        {
            "category":"Shopping",
            "type":"Retail Goods"
        }
    ],
    "sg:phone":"+1 812 235 0884",
    "sg:postcode":"47803",
    "sg:province":"IN",
    "sg:tags":[
        "coin",
        "dealer",
        "supply"
    ],
    "sg:website":"www.thecoinmerchant.com",
    "wof:name":"Coin Merchant",
    "wof:placetype":"venue"
},
  "geometry": {"coordinates":[-87.386644,39.448301],"type":"Point"}
}