{
  "type": "Feature",
  "properties": {
    "iso:country":"US",
    "sg:address":"5383 W 400 N",
    "sg:city":"Warsaw",
    "sg:classifiers":[
        {
            "category":"Manufacturing",
            "subcategory":"Apparel",
            "type":"Manufacturing & Wholesale Goods"
        }
    ],
    "sg:phone":"+1 574 858 2260",
    "sg:postcode":"46582",
    "sg:province":"IN",
    "wof:name":"Raymond Truex",
    "wof:placetype":"venue"
},
  "geometry": {"coordinates":[-85.94657599999999,41.290301],"type":"Point"}
}