{
  "type": "Feature",
  "properties": {
    "iso:country":"US",
    "sg:address":"516 W Washington St",
    "sg:city":"Lebanon",
    "sg:classifiers":[
        {
            "category":"Building & Trades",
            "subcategory":"Construction",
            "type":"Services"
        }
    ],
    "sg:phone":"+1 765 482 4674",
    "sg:postcode":"46052",
    "sg:province":"IN",
    "sg:tags":[
        "contractor"
    ],
    "wof:name":"Netherton Tile Co",
    "wof:placetype":"venue"
},
  "geometry": {"coordinates":[-86.47265299999999,40.048544],"type":"Point"}
}