{
  "type": "Feature",
  "properties": {
    "addr:full":"2090 N Jefferson St Huntington IN 46750",
    "addr:housenumber":"2090",
    "addr:postcode":"46750",
    "addr:street":"N Jefferson",
    "iso:country":"US",
    "sg:address":"2090 N Jefferson St",
    "sg:city":"Huntington",
    "sg:classifiers":[
        {
            "category":"Food & Beverages",
            "subcategory":"Groceries & Convenience Stores",
            "type":"Retail Goods"
        }
    ],
    "sg:phone":"+1 260 356 1118",
    "sg:postcode":"46750",
    "sg:province":"IN",
    "wof:name":"Pak-A-Sak",
    "wof:placetype":"venue"
},
  "geometry": {"coordinates":[-85.504845,40.892047],"type":"Point"}
}