{
  "type": "Feature",
  "properties": {
    "iso:country":"US",
    "sg:address":"416 E Walnut St",
    "sg:city":"Brownstown",
    "sg:classifiers":[
        {
            "category":"Government",
            "subcategory":"Office",
            "type":"Public Place"
        }
    ],
    "sg:phone":"+1 812 358 5180",
    "sg:postcode":"47220",
    "sg:province":"IN",
    "sg:tags":[
        "county"
    ],
    "wof:name":"Jackson County Juvenile",
    "wof:placetype":"venue"
},
  "geometry": {"coordinates":[-86.036947,38.877948],"type":"Point"}
}