{
  "type": "Feature",
  "properties": {
    "iso:country":"US",
    "sg:address":"7034 Kennedy Ave",
    "sg:city":"Hammond",
    "sg:classifiers":[
        {
            "category":"Shopping",
            "subcategory":"Florist",
            "type":"Retail Goods"
        }
    ],
    "sg:phone":"+1 219 844 3013",
    "sg:postcode":"46323",
    "sg:province":"IN",
    "wof:name":"Nemcek Florists",
    "wof:placetype":"venue"
},
  "geometry": {"coordinates":[-87.4618,41.585201],"type":"Point"}
}