{
  "type": "Feature",
  "properties": {
    "addr:full":"717 E 49th Ave Gary IN 46409",
    "addr:housenumber":"717",
    "addr:postcode":"46409",
    "addr:street":"E 49Th Ave",
    "iso:country":"US",
    "sg:address":"717 E 49th Ave",
    "sg:city":"Gary",
    "sg:classifiers":[
        {
            "category":"Food & Beverages",
            "subcategory":"Groceries & Convenience Stores",
            "type":"Retail Goods"
        }
    ],
    "sg:phone":"+1 219 887 4060",
    "sg:postcode":"46409",
    "sg:province":"IN",
    "wof:name":"Family Food Discount",
    "wof:placetype":"venue"
},
  "geometry": {"coordinates":[-87.32660799999999,41.529326],"type":"Point"}
}