{
  "type": "Feature",
  "properties": {
    "iso:country":"US",
    "sg:address":"2759 N State Rd 39",
    "sg:city":"Monticello",
    "sg:classifiers":[
        {
            "category":"Farming",
            "subcategory":"Livestock Farm",
            "type":"Manufacturing & Wholesale Goods"
        }
    ],
    "sg:phone":"+1 574 583 3725",
    "sg:postcode":"47960",
    "sg:province":"IN",
    "sg:tags":[
        "hog",
        "or",
        "feedlot"
    ],
    "wof:name":"Bb Hog Farm",
    "wof:placetype":"venue"
},
  "geometry": {"coordinates":[-86.744928,40.792043],"type":"Point"}
}