{
  "type": "Feature",
  "properties": {
    "iso:country":"US",
    "sg:address":"10804 Lake Shasta Ct",
    "sg:city":"Fort Wayne",
    "sg:classifiers":[
        {
            "category":"Manufacturing",
            "subcategory":"Paper Products",
            "type":"Manufacturing & Wholesale Goods"
        }
    ],
    "sg:phone":"+1 260 434 0500",
    "sg:postcode":"46804",
    "sg:province":"IN",
    "sg:tags":[
        "envelope"
    ],
    "wof:name":"Double Envelope Corp",
    "wof:placetype":"venue"
},
  "geometry": {"coordinates":[-85.282531,41.047085],"type":"Point"}
}