{
  "type": "Feature",
  "properties": {
    "iso:country":"US",
    "sg:address":"201 S Perry St",
    "sg:city":"Attica",
    "sg:classifiers":[
        {
            "category":"Home & Garden",
            "subcategory":"Carpets & Floor Coverings",
            "type":"Retail Goods"
        }
    ],
    "sg:phone":"+1 765 764 4554",
    "sg:postcode":"47918",
    "sg:province":"IN",
    "sg:tags":[
        "dealer",
        "rug"
    ],
    "wof:name":"L C Roemer & Son",
    "wof:placetype":"venue"
},
  "geometry": {"coordinates":[-87.249102,40.293746],"type":"Point"}
}