{
  "type": "Feature",
  "properties": {
    "iso:country":"US",
    "sg:address":"2896 W 1000 S",
    "sg:city":"Huntingburg",
    "sg:classifiers":[
        {
            "category":"Retail",
            "subcategory":"Repair Shop",
            "type":"Services"
        }
    ],
    "sg:phone":"+1 812 683 8914",
    "sg:postcode":"47542",
    "sg:province":"IN",
    "sg:tags":[
        "scooter",
        "motorcycle",
        "motor"
    ],
    "wof:name":"Twin Lakes V Twins",
    "wof:placetype":"venue"
},
  "geometry": {"coordinates":[-86.960123,38.232565],"type":"Point"}
}