{
  "type": "Feature",
  "properties": {
    "addr:full":"3601 E Main St Richmond IN 47374",
    "addr:housenumber":"3601",
    "addr:postcode":"47374",
    "addr:street":"E Main St",
    "iso:country":"US",
    "sg:address":"3601 E Main St",
    "sg:city":"Richmond",
    "sg:classifiers":[
        {
            "category":"Shopping",
            "subcategory":"Department Store",
            "type":"Retail Goods"
        }
    ],
    "sg:phone":"+1 765 935 9158",
    "sg:postcode":"47374",
    "sg:province":"IN",
    "wof:name":"Wal-Mart Supercenter",
    "wof:placetype":"venue"
},
  "geometry": {"coordinates":[-84.852828,39.830984],"type":"Point"}
}