{
  "type": "Feature",
  "properties": {
    "iso:country":"US",
    "sg:address":"2302 E 38th St",
    "sg:city":"Indianapolis",
    "sg:classifiers":[
        {
            "category":"Retail",
            "subcategory":"Auto Repair",
            "type":"Services"
        }
    ],
    "sg:phone":"+1 317 546 7038",
    "sg:postcode":"46218",
    "sg:province":"IN",
    "sg:tags":[
        "repairing",
        "automobile"
    ],
    "wof:name":"Vandever Auto Svc",
    "wof:placetype":"venue"
},
  "geometry": {"coordinates":[-86.121739,39.825403],"type":"Point"}
}