{
  "type": "Feature",
  "properties": {
    "iso:country":"US",
    "sg:address":"3781 Central Ave",
    "sg:city":"Lake Station",
    "sg:classifiers":[
        {
            "category":"Retail",
            "subcategory":"Funeral Services",
            "type":"Services"
        }
    ],
    "sg:phone":"+1 219 962 1606",
    "sg:postcode":"46405",
    "sg:province":"IN",
    "sg:tags":[
        "director"
    ],
    "wof:name":"Rees Funeral Home Brady Chapel",
    "wof:placetype":"venue"
},
  "geometry": {"coordinates":[-87.239696,41.574583],"type":"Point"}
}