{
  "type": "Feature",
  "properties": {
    "iso:country":"US",
    "sg:address":"5904 S Western Ave",
    "sg:city":"Marion",
    "sg:classifiers":[
        {
            "category":"Government",
            "subcategory":"Office",
            "type":"Public Place"
        }
    ],
    "sg:phone":"+1 765 674 5041",
    "sg:postcode":"46953",
    "sg:province":"IN",
    "sg:tags":[
        "federal"
    ],
    "wof:name":"US Transportation Dept",
    "wof:placetype":"venue"
},
  "geometry": {"coordinates":[-85.669993,40.497514],"type":"Point"}
}