{
  "type": "Feature",
  "properties": {
    "iso:country":"US",
    "sg:address":"4527 N Meridian Rd",
    "sg:city":"Huntington",
    "sg:classifiers":[
        {
            "category":"Wholesale",
            "subcategory":"Petroleum",
            "type":"Manufacturing & Wholesale Goods"
        }
    ],
    "sg:phone":"+1 260 356 5802",
    "sg:postcode":"46750",
    "sg:province":"IN",
    "sg:tags":[
        "pipe",
        "line",
        "company"
    ],
    "wof:name":"Buckeye Pipe Line Co",
    "wof:placetype":"venue"
},
  "geometry": {"coordinates":[-85.45182,40.894899],"type":"Point"}
}