{
  "type": "Feature",
  "properties": {
    "addr:full":"601 N 9th Ave Evansville IN 47712",
    "addr:housenumber":"601",
    "addr:postcode":"47712",
    "addr:street":"N 9Th Ave",
    "iso:country":"US",
    "sg:address":"601 N 9th Ave",
    "sg:city":"Evansville",
    "sg:classifiers":[
        {
            "category":"Building & Trades",
            "subcategory":"Equipment Rental",
            "type":"Services"
        }
    ],
    "sg:phone":"+1 812 768 6116",
    "sg:postcode":"47712",
    "sg:province":"IN",
    "sg:tags":[
        "contractor"
    ],
    "wof:name":"Skyline Equipment Svc",
    "wof:placetype":"venue"
},
  "geometry": {"coordinates":[-87.592056,37.983713],"type":"Point"}
}