{
  "type": "Feature",
  "properties": {
    "iso:country":"US",
    "sg:address":"714 W Main St",
    "sg:city":"Greensburg",
    "sg:classifiers":[
        {
            "category":"Organizations",
            "subcategory":"Religious Organization",
            "type":"Services"
        }
    ],
    "sg:phone":"+1 812 663 6230",
    "sg:postcode":"47240",
    "sg:province":"IN",
    "sg:tags":[
        "church"
    ],
    "wof:name":"Wesleyan Church",
    "wof:placetype":"venue"
},
  "geometry": {"coordinates":[-85.498398,39.336522],"type":"Point"}
}