{
  "type": "Feature",
  "properties": {
    "addr:full":"213 E 33rd St Marion IN 46953",
    "addr:housenumber":"213",
    "addr:postcode":"46953",
    "addr:street":"E 33Rd St",
    "iso:country":"US",
    "sg:address":"213 E 33rd St",
    "sg:city":"Marion",
    "sg:classifiers":[
        {
            "category":"Freight",
            "type":"Transportation"
        }
    ],
    "sg:phone":"+1 765 671 9622",
    "sg:postcode":"46953",
    "sg:province":"IN",
    "sg:tags":[
        "trucking"
    ],
    "wof:name":"Teamwork Transport Inc",
    "wof:placetype":"venue"
},
  "geometry": {"coordinates":[-85.65984400000001,40.530264],"type":"Point"}
}