{
  "type": "Feature",
  "properties": {
    "iso:country":"US",
    "sg:address":"15 NE 3rd St",
    "sg:city":"Washington",
    "sg:classifiers":[
        {
            "category":"Real Estate",
            "subcategory":"Surveying",
            "type":"Services"
        }
    ],
    "sg:phone":"+1 812 257 0950",
    "sg:postcode":"47501",
    "sg:province":"IN",
    "sg:tags":[
        "surveyor"
    ],
    "wof:name":"Landmark Surveying Co",
    "wof:placetype":"venue"
},
  "geometry": {"coordinates":[-87.172397,38.657641],"type":"Point"}
}