{
  "type": "Feature",
  "properties": {
    "iso:country":"US",
    "sg:address":"1013 Miller Ave",
    "sg:city":"Shelbyville",
    "sg:classifiers":[
        {
            "category":"Home & Garden",
            "subcategory":"Furniture",
            "type":"Retail Goods"
        }
    ],
    "sg:phone":"+1 317 398 3923",
    "sg:postcode":"46176",
    "sg:province":"IN",
    "sg:tags":[
        "top",
        "counter"
    ],
    "wof:name":"KBS Quality Laminates Inc",
    "wof:placetype":"venue"
},
  "geometry": {"coordinates":[-85.790055,39.515744],"type":"Point"}
}