{
  "type": "Feature",
  "properties": {
    "iso:country":"US",
    "sg:address":"7852 Marten Ct S",
    "sg:city":"Indianapolis",
    "sg:classifiers":[
        {
            "category":"Real Estate",
            "subcategory":"Real Estate Operator",
            "type":"Services"
        }
    ],
    "sg:phone":"+1 317 545 9131",
    "sg:postcode":"46226",
    "sg:province":"IN",
    "sg:tags":[
        "apartment"
    ],
    "wof:name":"Marten Manor East Apartments",
    "wof:placetype":"venue"
},
  "geometry": {"coordinates":[-86.029851,39.833468],"type":"Point"}
}