{
  "type": "Feature",
  "properties": {
    "addr:full":"1704 Cortland Ave Fort Wayne IN 46808",
    "addr:housenumber":"1704",
    "addr:postcode":"46808",
    "addr:street":"Cortland Ave",
    "iso:country":"US",
    "sg:address":"1704 Cortland Ave",
    "sg:city":"Fort Wayne",
    "sg:classifiers":[
        {
            "category":"Building & Trades",
            "subcategory":"Construction",
            "type":"Services"
        }
    ],
    "sg:phone":"+1 260 426 8103",
    "sg:postcode":"46808",
    "sg:province":"IN",
    "sg:tags":[
        "dry wall",
        "contractor"
    ],
    "wof:name":"Exquisite Drywall Inc",
    "wof:placetype":"venue"
},
  "geometry": {"coordinates":[-85.146996,41.091592],"type":"Point"}
}