{
  "type": "Feature",
  "properties": {
    "iso:country":"US",
    "sg:address":"5724 N 600 E",
    "sg:city":"Falmouth",
    "sg:phone":"+1 765 679 5710",
    "sg:postcode":"46127",
    "sg:province":"IN",
    "sg:tags":[
        "farm",
        "corn",
        "wheat",
        "soybean"
    ],
    "wof:name":"Newkirk Farms",
    "wof:placetype":"venue"
},
  "geometry": {"coordinates":[-85.339116,39.698648],"type":"Point"}
}