{
  "type": "Feature",
  "properties": {
    "iso:country":"US",
    "sg:address":"545 Raines St",
    "sg:city":"Plainfield",
    "sg:classifiers":[
        {
            "category":"Manufacturing",
            "subcategory":"Glass & Minerals",
            "type":"Manufacturing & Wholesale Goods"
        }
    ],
    "sg:phone":"+1 317 839 5550",
    "sg:postcode":"46168",
    "sg:province":"IN",
    "sg:tags":[
        "glass-stained",
        "stained",
        "leaded-commercial",
        "leaded",
        "glass-wholesale",
        "manufacturer"
    ],
    "wof:name":"Production Unlimited Inc",
    "wof:placetype":"venue"
},
  "geometry": {"coordinates":[-86.392124,39.71071],"type":"Point"}
}