{
  "type": "Feature",
  "properties": {
    "iso:country":"US",
    "sg:address":"3642 N Emerson Ave",
    "sg:city":"Indianapolis",
    "sg:classifiers":[
        {
            "category":"Social Services",
            "subcategory":"Child Care",
            "type":"Services"
        }
    ],
    "sg:phone":"+1 317 549 8978",
    "sg:postcode":"46218",
    "sg:province":"IN",
    "wof:name":"Precious Moments Day Care",
    "wof:placetype":"venue"
},
  "geometry": {"coordinates":[-86.083747,39.822994],"type":"Point"}
}