{
  "type": "Feature",
  "properties": {
    "addr:full":"206 N Sycamore St Flora IN 46929",
    "addr:housenumber":"206",
    "addr:postcode":"46929",
    "addr:street":"N Sycamore St",
    "iso:country":"US",
    "sg:address":"206 N Sycamore St",
    "sg:city":"Flora",
    "sg:classifiers":[
        {
            "category":"Restaurant",
            "type":"Food & Drink"
        }
    ],
    "sg:phone":"+1 574 967 0188",
    "sg:postcode":"46929",
    "sg:province":"IN",
    "wof:name":"Connie's Restaurant",
    "wof:placetype":"venue"
},
  "geometry": {"coordinates":[-86.529674,40.549942],"type":"Point"}
}