{
  "type": "Feature",
  "properties": {
    "addr:full":"2930 Performance Dr Kendallville IN 46755",
    "addr:postcode":"2930;46755",
    "addr:street":"Performance Dr",
    "iso:country":"US",
    "sg:address":"2930 Performance Dr",
    "sg:city":"Kendallville",
    "sg:classifiers":[
        {
            "category":"Professional",
            "subcategory":"Advertising",
            "type":"Services"
        }
    ],
    "sg:phone":"+1 260 349 0347",
    "sg:postcode":"46755",
    "sg:province":"IN",
    "sg:tags":[
        "distribution"
    ],
    "wof:name":"PFG Customized Distribution",
    "wof:placetype":"venue"
},
  "geometry": {"coordinates":[-85.21224599999999,41.443504],"type":"Point"}
}