{
  "type": "Feature",
  "properties": {
    "iso:country":"US",
    "sg:address":"2342 Deerfield Ct",
    "sg:city":"Greenwood",
    "sg:classifiers":[
        {
            "category":"Real Estate",
            "subcategory":"Real Estate Agent",
            "type":"Services"
        }
    ],
    "sg:phone":"+1 317 888 4242",
    "sg:postcode":"46143",
    "sg:province":"IN",
    "wof:name":"Heber Homes",
    "wof:placetype":"venue"
},
  "geometry": {"coordinates":[-86.222535,39.581009],"type":"Point"}
}