{
  "type": "Feature",
  "properties": {
    "iso:country":"US",
    "sg:address":"127 W Main St",
    "sg:city":"Lebanon",
    "sg:classifiers":[
        {
            "category":"Manufacturing",
            "subcategory":"Metals",
            "type":"Manufacturing & Wholesale Goods"
        }
    ],
    "sg:phone":"+1 765 483 9690",
    "sg:postcode":"46052",
    "sg:province":"IN",
    "sg:tags":[
        "equipment",
        "cryogenic",
        "supply"
    ],
    "wof:name":"Chart Industries Inc",
    "wof:placetype":"venue"
},
  "geometry": {"coordinates":[-86.46905099999999,40.047495],"type":"Point"}
}