{
  "type": "Feature",
  "properties": {
    "addr:full":"18915 Allen Rd Harlan IN 46743",
    "addr:housenumber":"18915",
    "addr:postcode":"46743",
    "addr:street":"Allen Rd",
    "iso:country":"US",
    "sg:address":"18915 Allen Rd",
    "sg:city":"Harlan",
    "sg:classifiers":[
        {
            "category":"Building & Trades",
            "subcategory":"Construction",
            "type":"Services"
        }
    ],
    "sg:phone":"+1 260 657 5960",
    "sg:postcode":"46743",
    "sg:province":"IN",
    "sg:tags":[
        "house"
    ],
    "wof:name":"Northeast Allen County Cnstr",
    "wof:placetype":"venue"
},
  "geometry": {"coordinates":[-84.82803699999999,41.262687],"type":"Point"}
}