{
  "type": "Feature",
  "properties": {
    "iso:country":"US",
    "sg:address":"2800 Enterprise St",
    "sg:city":"Indianapolis",
    "sg:classifiers":[
        {
            "category":"Freight",
            "type":"Transportation"
        }
    ],
    "sg:phone":"+1 317 357 3690",
    "sg:postcode":"46219",
    "sg:province":"IN",
    "sg:tags":[
        "trucking"
    ],
    "sg:website":"www.mmtransport.com",
    "wof:name":"M & M Transport",
    "wof:placetype":"venue"
},
  "geometry": {"coordinates":[-86.03174,39.807217],"type":"Point"}
}