{
  "type": "Feature",
  "properties": {
    "iso:country":"US",
    "sg:address":"688 E Co Rd 450 N",
    "sg:city":"Danville",
    "sg:classifiers":[
        {
            "category":"Building & Trades",
            "subcategory":"Equipment Rental",
            "type":"Services"
        }
    ],
    "sg:phone":"+1 317 745 0754",
    "sg:postcode":"46122",
    "sg:province":"IN",
    "sg:tags":[
        "party",
        "supply"
    ],
    "wof:name":"Clown Around Party Rentals",
    "wof:placetype":"venue"
},
  "geometry": {"coordinates":[-86.52606,39.827007],"type":"Point"}
}