{
  "type": "Feature",
  "properties": {
    "addr:full":"8165 W 300 N Etna Green IN 46524",
    "addr:housenumber":"8165",
    "addr:postcode":"46524",
    "addr:street":"W 300 N Etna Green",
    "iso:country":"US",
    "sg:address":"8165 W 300 N",
    "sg:city":"Etna Green",
    "sg:classifiers":[
        {
            "category":"Professional",
            "type":"Services"
        }
    ],
    "sg:phone":"+1 574 858 9451",
    "sg:postcode":"46524",
    "sg:province":"IN",
    "sg:tags":[
        "establishment"
    ],
    "wof:name":"Pickin' Patch Inc",
    "wof:placetype":"venue"
},
  "geometry": {"coordinates":[-86.00112900000001,41.274855],"type":"Point"}
}