{
  "type": "Feature",
  "properties": {
    "iso:country":"US",
    "sg:address":"5351 N Washington Blvd",
    "sg:city":"Indianapolis",
    "sg:classifiers":[
        {
            "category":"Professional",
            "subcategory":"Management & Consulting",
            "type":"Services"
        }
    ],
    "sg:phone":"+1 317 465 9334",
    "sg:postcode":"46220",
    "sg:province":"IN",
    "sg:tags":[
        "business"
    ],
    "wof:name":"Cognitive Solutions Inc",
    "wof:placetype":"venue"
},
  "geometry": {"coordinates":[-86.152345,39.849925],"type":"Point"}
}