{
  "type": "Feature",
  "properties": {
    "iso:country":"US",
    "sg:address":"420 W Cleveland Rd",
    "sg:city":"Granger",
    "sg:classifiers":[
        {
            "category":"Personal",
            "subcategory":"Beauty Salon",
            "type":"Services"
        }
    ],
    "sg:phone":"+1 574 277 6721",
    "sg:postcode":"46530",
    "sg:province":"IN",
    "wof:name":"Masters Styling Salon",
    "wof:placetype":"venue"
},
  "geometry": {"coordinates":[-86.18662500000001,41.723887],"type":"Point"}
}