{
  "type": "Feature",
  "properties": {
    "iso:country":"US",
    "sg:address":"1316 Jonathan Ct",
    "sg:city":"Laporte",
    "sg:classifiers":[
        {
            "category":"Building & Trades",
            "subcategory":"Construction",
            "type":"Services"
        }
    ],
    "sg:phone":"+1 219 874 2015",
    "sg:postcode":"46350",
    "sg:province":"IN",
    "sg:tags":[
        "general",
        "contractor"
    ],
    "wof:name":"Wentland Construction Corp",
    "wof:placetype":"venue"
},
  "geometry": {"coordinates":[-86.850387,41.627458],"type":"Point"}
}