{
  "type": "Feature",
  "properties": {
    "addr:full":"5524 Broadway Merrillville IN 46410",
    "addr:housenumber":"5524",
    "addr:postcode":"46410",
    "addr:street":"Broadway",
    "iso:country":"US",
    "sg:address":"5524 Broadway",
    "sg:city":"Merrillville",
    "sg:classifiers":[
        {
            "category":"Shopping",
            "subcategory":"Books",
            "type":"Retail Goods"
        }
    ],
    "sg:phone":"+1 219 980 8343",
    "sg:postcode":"46410",
    "sg:province":"IN",
    "sg:tags":[
        "dealer"
    ],
    "wof:name":"Christian Lifestyle Coffee",
    "wof:placetype":"venue"
},
  "geometry": {"coordinates":[-87.336174,41.516715],"type":"Point"}
}