{
  "type": "Feature",
  "properties": {
    "addr:full":"8575 State Rd 350 Milan IN 47031",
    "addr:housenumber":"8575;350",
    "addr:postcode":"47031",
    "addr:street":"State Rd",
    "iso:country":"US",
    "sg:address":"8575 State Rd 350",
    "sg:city":"Milan",
    "sg:classifiers":[
        {
            "category":"Professional",
            "subcategory":"Lawyer & Legal Services",
            "type":"Services"
        }
    ],
    "sg:phone":"+1 812 654 3453",
    "sg:postcode":"47031",
    "sg:province":"IN",
    "sg:tags":[
        "attorney"
    ],
    "wof:name":"Tamara A Drummond",
    "wof:placetype":"venue"
},
  "geometry": {"coordinates":[-85.100663,39.124296],"type":"Point"}
}