{
  "type": "Feature",
  "properties": {
    "iso:country":"US",
    "sg:address":"200 N Cowen St",
    "sg:city":"Garrett",
    "sg:classifiers":[
        {
            "category":"Government",
            "subcategory":"Police Station",
            "type":"Public Place"
        }
    ],
    "sg:phone":"+1 260 357 5151",
    "sg:postcode":"46738",
    "sg:province":"IN",
    "sg:tags":[
        "department"
    ],
    "wof:name":"Garrett City Police Dept",
    "wof:placetype":"venue"
},
  "geometry": {"coordinates":[-85.13688999999999,41.35039],"type":"Point"}
}