{
  "type": "Feature",
  "properties": {
    "iso:country":"US",
    "sg:address":"9302 N Meridian St",
    "sg:city":"Indianapolis",
    "sg:classifiers":[
        {
            "category":"Professional",
            "subcategory":"Business Services",
            "type":"Services"
        }
    ],
    "sg:phone":"+1 317 202 3300",
    "sg:postcode":"46260",
    "sg:province":"IN",
    "sg:tags":[
        "paging",
        "answering"
    ],
    "wof:name":"Onramp Medical Communications",
    "wof:placetype":"venue"
},
  "geometry": {"coordinates":[-86.158129,39.926977],"type":"Point"}
}