{
  "type": "Feature",
  "properties": {
    "addr:full":"3835 Douglas Dr Gary IN 46408",
    "addr:housenumber":"3835",
    "addr:postcode":"46408",
    "addr:street":"Douglas Dr",
    "iso:country":"US",
    "sg:address":"3835 Douglas Dr",
    "sg:city":"Gary",
    "sg:classifiers":[
        {
            "category":"Insurance",
            "subcategory":"Hazard Insurance",
            "type":"Services"
        }
    ],
    "sg:phone":"+1 219 939 2245",
    "sg:postcode":"46408",
    "sg:province":"IN",
    "sg:tags":[
        "bond"
    ],
    "wof:name":"Blazing Bail Bonds",
    "wof:placetype":"venue"
},
  "geometry": {"coordinates":[-87.384685,41.533383],"type":"Point"}
}