{
  "type": "Feature",
  "properties": {
    "iso:country":"US",
    "sg:address":"10 N Fairground St",
    "sg:city":"Liberty",
    "sg:classifiers":[
        {
            "category":"Professional",
            "subcategory":"Accounting & Tax Preparation",
            "type":"Services"
        }
    ],
    "sg:phone":"+1 765 458 5598",
    "sg:postcode":"47353",
    "sg:province":"IN",
    "sg:tags":[
        "return"
    ],
    "wof:name":"Hensley Tax Service",
    "wof:placetype":"venue"
},
  "geometry": {"coordinates":[-84.92858,39.636316],"type":"Point"}
}