{
  "type": "Feature",
  "properties": {
    "iso:country":"US",
    "sg:address":"6780 W 450 S",
    "sg:city":"Columbus",
    "sg:classifiers":[
        {
            "category":"Building & Trades",
            "subcategory":"Cleaning & Sanitation",
            "type":"Services"
        }
    ],
    "sg:phone":"+1 812 342 4863",
    "sg:postcode":"47201",
    "sg:province":"IN",
    "sg:tags":[
        "maintenance"
    ],
    "wof:name":"Indiana Soot Bstrs Chmny Swp",
    "wof:placetype":"venue"
},
  "geometry": {"coordinates":[-85.996073,39.133123],"type":"Point"}
}