{
  "type": "Feature",
  "properties": {
    "iso:country":"US",
    "sg:address":"104 Country Place Cir",
    "sg:city":"Edinburgh",
    "sg:classifiers":[
        {
            "category":"Real Estate",
            "subcategory":"Real Estate Operator",
            "type":"Services"
        }
    ],
    "sg:phone":"+1 812 526 0322",
    "sg:postcode":"46124",
    "sg:province":"IN",
    "sg:tags":[
        "building",
        "apartment"
    ],
    "wof:name":"Country Place Apartments",
    "wof:placetype":"venue"
},
  "geometry": {"coordinates":[-85.974812,39.355741],"type":"Point"}
}