{
  "type": "Feature",
  "properties": {
    "iso:country":"US",
    "sg:address":"357 E Troy Ave",
    "sg:city":"Indianapolis",
    "sg:classifiers":[
        {
            "category":"Autos & Motor Vehicles",
            "subcategory":"Automobile Sales",
            "type":"Retail Goods"
        }
    ],
    "sg:phone":"+1 317 791 9116",
    "sg:postcode":"46225",
    "sg:province":"IN",
    "sg:tags":[
        "car",
        "dealer"
    ],
    "wof:name":"Accent Auto Inc",
    "wof:placetype":"venue"
},
  "geometry": {"coordinates":[-86.151714,39.722484],"type":"Point"}
}