{
  "type": "Feature",
  "properties": {
    "iso:country":"US",
    "sg:address":"1905 Washington Ave",
    "sg:city":"Vincennes",
    "sg:classifiers":[
        {
            "category":"Wholesale",
            "subcategory":"Auto Parts",
            "type":"Manufacturing & Wholesale Goods"
        }
    ],
    "sg:phone":"+1 812 882 1700",
    "sg:postcode":"47591",
    "sg:province":"IN",
    "sg:tags":[
        "equipment",
        "truck"
    ],
    "wof:name":"Gatemate Inc",
    "wof:placetype":"venue"
},
  "geometry": {"coordinates":[-87.50673,38.682618],"type":"Point"}
}