{
  "type": "Feature",
  "properties": {
    "iso:country":"US",
    "sg:address":"515 NW 2nd St",
    "sg:city":"Evansville",
    "sg:classifiers":[
        {
            "category":"Building & Trades",
            "subcategory":"Electrical",
            "type":"Services"
        }
    ],
    "sg:phone":"+1 812 422 5358",
    "sg:postcode":"47708",
    "sg:province":"IN",
    "sg:tags":[
        "electric",
        "contractor"
    ],
    "wof:name":"Mounts Electric Inc",
    "wof:placetype":"venue"
},
  "geometry": {"coordinates":[-87.576909,37.974553],"type":"Point"}
}