{
  "type": "Feature",
  "properties": {
    "iso:country":"US",
    "sg:address":"1025 Johnson Ave",
    "sg:city":"Franklin",
    "sg:classifiers":[
        {
            "category":"Freight",
            "type":"Transportation"
        }
    ],
    "sg:phone":"+1 317 736 0068",
    "sg:postcode":"46131",
    "sg:province":"IN",
    "sg:tags":[
        "warehouse",
        "public"
    ],
    "wof:name":"Johnson Avenue Warehouse",
    "wof:placetype":"venue"
},
  "geometry": {"coordinates":[-86.055039,39.491847],"type":"Point"}
}