{
  "type": "Feature",
  "properties": {
    "addr:full":"2005 Roosevelt Rd Valparaiso IN 46383",
    "addr:housenumber":"2005",
    "addr:postcode":"46383",
    "addr:street":"Roosevelt Rd",
    "iso:country":"US",
    "sg:address":"2005 Roosevelt Rd",
    "sg:city":"Valparaiso",
    "sg:classifiers":[
        {
            "category":"Health Services",
            "subcategory":"Doctor",
            "type":"Services"
        }
    ],
    "sg:phone":"+1 219 531 9293",
    "sg:postcode":"46383",
    "sg:province":"IN",
    "sg:tags":[
        "dentist"
    ],
    "wof:name":"Valparaiso Family Dentistry",
    "wof:placetype":"venue"
},
  "geometry": {"coordinates":[-87.046618,41.486062],"type":"Point"}
}