{
  "type": "Feature",
  "properties": {
    "addr:full":"53402 Co Rd 13 Elkhart IN 46514",
    "addr:housenumber":"53402;13",
    "addr:postcode":"46514",
    "addr:street":"Co Rd",
    "iso:country":"US",
    "sg:address":"53402 Co Rd 13",
    "sg:city":"Elkhart",
    "sg:classifiers":[
        {
            "category":"Manufacturing",
            "subcategory":"Electronics",
            "type":"Manufacturing & Wholesale Goods"
        }
    ],
    "sg:phone":"+1 574 262 0518",
    "sg:postcode":"46514",
    "sg:province":"IN",
    "sg:tags":[
        "equipment",
        "electronic",
        "supply"
    ],
    "sg:website":"www.kibenterprises.com",
    "wof:name":"KIB Enterprises",
    "wof:placetype":"venue"
},
  "geometry": {"coordinates":[-85.927363,41.718275],"type":"Point"}
}