{
  "type": "Feature",
  "properties": {
    "iso:country":"US",
    "sg:address":"800 E Oregon St",
    "sg:city":"Evansville",
    "sg:classifiers":[
        {
            "category":"Building & Trades",
            "subcategory":"Construction",
            "type":"Services"
        }
    ],
    "sg:phone":"+1 812 428 3343",
    "sg:postcode":"47711",
    "sg:province":"IN",
    "sg:tags":[
        "roofing",
        "contractor"
    ],
    "wof:name":"Thermoseal",
    "wof:placetype":"venue"
},
  "geometry": {"coordinates":[-87.552931,37.9866],"type":"Point"}
}