{
  "type": "Feature",
  "properties": {
    "iso:country":"US",
    "sg:address":"1857 Fieldcrest Dr",
    "sg:city":"Lawrenceburg",
    "sg:classifiers":[
        {
            "category":"Professional",
            "type":"Services"
        }
    ],
    "sg:phone":"+1 812 537 9755",
    "sg:postcode":"47025",
    "sg:province":"IN",
    "wof:name":"Larry W Michalek and Company",
    "wof:placetype":"venue"
},
  "geometry": {"coordinates":[-84.853809,39.180065],"type":"Point"}
}