{
  "type": "Feature",
  "properties": {
    "addr:full":"759 Plaza Dr Martinsville IN 46151",
    "addr:housenumber":"759",
    "addr:postcode":"46151",
    "addr:street":"Plaza Dr",
    "iso:country":"US",
    "sg:address":"759 Plaza Dr",
    "sg:city":"Martinsville",
    "sg:classifiers":[
        {
            "category":"Insurance",
            "subcategory":"Insurance Agent",
            "type":"Services"
        }
    ],
    "sg:phone":"+1 765 342 3381",
    "sg:postcode":"46151",
    "sg:province":"IN",
    "wof:name":"Farm Bureau Insurance",
    "wof:placetype":"venue"
},
  "geometry": {"coordinates":[-86.44350900000001,39.405444],"type":"Point"}
}