{
  "type": "Feature",
  "properties": {
    "iso:country":"US",
    "sg:address":"3315 Forsythia Dr",
    "sg:city":"Columbus",
    "sg:classifiers":[
        {
            "category":"Professional",
            "subcategory":"Engineering",
            "type":"Services"
        }
    ],
    "sg:phone":"+1 812 377 7184",
    "sg:postcode":"47203",
    "sg:province":"IN",
    "wof:name":"Kirch Engineering",
    "wof:placetype":"venue"
},
  "geometry": {"coordinates":[-85.88227500000001,39.225483],"type":"Point"}
}