{
  "type": "Feature",
  "properties": {
    "iso:country":"US",
    "sg:address":"1510 S Heaton St",
    "sg:city":"Knox",
    "sg:classifiers":[
        {
            "category":"Insurance",
            "subcategory":"Insurance Agent",
            "type":"Services"
        }
    ],
    "sg:phone":"+1 574 772 6251",
    "sg:postcode":"46534",
    "sg:province":"IN",
    "wof:name":"Farm Bureau Insurance",
    "wof:placetype":"venue"
},
  "geometry": {"coordinates":[-86.620735,41.28335],"type":"Point"}
}