{
  "type": "Feature",
  "properties": {
    "addr:full":"8587 Zionsville Rd Indianapolis IN 46268",
    "addr:housenumber":"8587",
    "addr:postcode":"46268",
    "addr:street":"Zionsville Rd",
    "iso:country":"US",
    "sg:address":"8587 Zionsville Rd",
    "sg:city":"Indianapolis",
    "sg:classifiers":[
        {
            "category":"Banks & Credit Unions",
            "subcategory":"Bank",
            "type":"Services"
        }
    ],
    "sg:phone":"+1 317 297 7723",
    "sg:postcode":"46268",
    "sg:province":"IN",
    "sg:tags":[
        "loan",
        "real estate"
    ],
    "wof:name":"Alpha One Mortgage Lending",
    "wof:placetype":"venue"
},
  "geometry": {"coordinates":[-86.25979,39.910143],"type":"Point"}
}