{
  "type": "Feature",
  "properties": {
    "iso:country":"US",
    "sg:address":"315 W State Rd 218",
    "sg:city":"Poneto",
    "sg:classifiers":[
        {
            "category":"Personal",
            "type":"Services"
        }
    ],
    "sg:phone":"+1 260 694 6353",
    "sg:postcode":"46781",
    "sg:province":"IN",
    "wof:name":"Bulger",
    "wof:placetype":"venue"
},
  "geometry": {"coordinates":[-85.226816,40.654661],"type":"Point"}
}