{
  "type": "Feature",
  "properties": {
    "addr:full":"113 N 3rd St Kentland IN 47951",
    "addr:housenumber":"113",
    "addr:postcode":"47951",
    "addr:street":"N 3Rd St",
    "iso:country":"US",
    "sg:address":"113 N 3rd St",
    "sg:city":"Kentland",
    "sg:classifiers":[
        {
            "category":"Professional",
            "subcategory":"Lawyer & Legal Services",
            "type":"Services"
        }
    ],
    "sg:phone":"+1 219 474 5885",
    "sg:postcode":"47951",
    "sg:province":"IN",
    "sg:tags":[
        "attorney"
    ],
    "wof:name":"Molter & Molter",
    "wof:placetype":"venue"
},
  "geometry": {"coordinates":[-87.4451,40.76898],"type":"Point"}
}