{
  "type": "Feature",
  "properties": {
    "addr:full":"3205 US Hwy 50 Seymour IN 47274",
    "addr:housenumber":"3205",
    "addr:postcode":"47274",
    "addr:street":"Us Hwy 50",
    "iso:country":"US",
    "sg:address":"3205 US Hwy 50",
    "sg:city":"Seymour",
    "sg:classifiers":[
        {
            "category":"Retail",
            "subcategory":"Auto Rental",
            "type":"Services"
        }
    ],
    "sg:phone":"+1 812 358 5505",
    "sg:postcode":"47274",
    "sg:province":"IN",
    "sg:tags":[
        "renting",
        "automobile"
    ],
    "wof:name":"Rent-A-Wreck",
    "wof:placetype":"venue"
},
  "geometry": {"coordinates":[-85.97748,38.916883],"type":"Point"}
}