{
  "type": "Feature",
  "properties": {
    "iso:country":"US",
    "sg:address":"1911 Hazelwood Ave",
    "sg:city":"Fort Wayne",
    "sg:classifiers":[
        {
            "category":"Real Estate",
            "subcategory":"Real Estate Operator",
            "type":"Services"
        }
    ],
    "sg:phone":"+1 260 484 1052",
    "sg:postcode":"46805",
    "sg:province":"IN",
    "sg:tags":[
        "apartment"
    ],
    "wof:name":"Stratford Place Apartments",
    "wof:placetype":"venue"
},
  "geometry": {"coordinates":[-85.113168,41.105201],"type":"Point"}
}