{
  "type": "Feature",
  "properties": {
    "iso:country":"US",
    "sg:address":"1010 Repp Dr",
    "sg:city":"Columbus",
    "sg:classifiers":[
        {
            "category":"Freight",
            "type":"Transportation"
        }
    ],
    "sg:phone":"+1 812 376 7635",
    "sg:postcode":"47201",
    "sg:province":"IN",
    "sg:tags":[
        "commercial",
        "storage"
    ],
    "wof:name":"Ogle's Storage",
    "wof:placetype":"venue"
},
  "geometry": {"coordinates":[-85.88429600000001,39.186413],"type":"Point"}
}