{
  "type": "Feature",
  "properties": {
    "iso:country":"US",
    "sg:address":"3222 Raintree Dr",
    "sg:city":"Newburgh",
    "sg:classifiers":[
        {
            "category":"Professional",
            "subcategory":"Lawyer & Legal Services",
            "type":"Services"
        }
    ],
    "sg:phone":"+1 812 858 1716",
    "sg:postcode":"47630",
    "sg:province":"IN",
    "wof:name":"Bryant Michele S Atty",
    "wof:placetype":"venue"
},
  "geometry": {"coordinates":[-87.387299,37.987099],"type":"Point"}
}