{
  "type": "Feature",
  "properties": {
    "addr:full":"12106 E State Rd 114 Akron IN 46910",
    "addr:housenumber":"12106;114",
    "addr:postcode":"46910",
    "addr:street":"E State Rd",
    "iso:country":"US",
    "sg:address":"12106 E State Rd 114",
    "sg:city":"Akron",
    "sg:classifiers":[
        {
            "category":"Health Services",
            "subcategory":"Chiropractor",
            "type":"Services"
        }
    ],
    "sg:phone":"+1 574 893 4131",
    "sg:postcode":"46910",
    "sg:province":"IN",
    "wof:name":"Morgan Chiropractic Clinic",
    "wof:placetype":"venue"
},
  "geometry": {"coordinates":[-86.013515,41.036932],"type":"Point"}
}