{
  "type": "Feature",
  "properties": {
    "iso:country":"US",
    "sg:address":"1133 W Mill Rd",
    "sg:city":"Evansville",
    "sg:classifiers":[
        {
            "category":"Professional",
            "subcategory":"Management & Consulting",
            "type":"Services"
        }
    ],
    "sg:phone":"+1 812 464 5195",
    "sg:postcode":"47710",
    "sg:province":"IN",
    "sg:tags":[
        "report",
        "construction"
    ],
    "wof:name":"National Construction News",
    "wof:placetype":"venue"
},
  "geometry": {"coordinates":[-87.579466,38.021652],"type":"Point"}
}