{
  "type": "Feature",
  "properties": {
    "addr:full":"322 S Yankeetown Rd Boonville IN 47601",
    "addr:housenumber":"322",
    "addr:postcode":"47601",
    "addr:street":"S Yankeetown Rd",
    "iso:country":"US",
    "sg:address":"322 S Yankeetown Rd",
    "sg:city":"Boonville",
    "sg:classifiers":[
        {
            "category":"Home & Garden",
            "subcategory":"Hardware",
            "type":"Retail Goods"
        }
    ],
    "sg:phone":"+1 812 897 0993",
    "sg:postcode":"47601",
    "sg:province":"IN",
    "wof:name":"Snap-On Tools",
    "wof:placetype":"venue"
},
  "geometry": {"coordinates":[-87.283811,38.02929],"type":"Point"}
}