{
  "type": "Feature",
  "properties": {
    "addr:full":"930 Bayside Way Porter IN 46304",
    "addr:housenumber":"930",
    "addr:postcode":"46304",
    "addr:street":"Bayside Way",
    "iso:country":"US",
    "sg:address":"930 Bayside Way",
    "sg:city":"Porter",
    "sg:classifiers":[
        {
            "category":"Professional",
            "type":"Services"
        }
    ],
    "sg:phone":"+1 219 395 1047",
    "sg:postcode":"46304",
    "sg:province":"IN",
    "sg:tags":[
        "establishment"
    ],
    "wof:name":"Berry Metal",
    "wof:placetype":"venue"
},
  "geometry": {"coordinates":[-87.085516,41.606622],"type":"Point"}
}