{
  "type": "Feature",
  "properties": {
    "iso:country":"US",
    "sg:address":"4730 N Maple Grove Rd",
    "sg:city":"Bloomington",
    "sg:classifiers":[
        {
            "category":"Professional",
            "subcategory":"Management & Consulting",
            "type":"Services"
        }
    ],
    "sg:phone":"+1 812 336 1122",
    "sg:postcode":"47404",
    "sg:province":"IN",
    "sg:tags":[
        "fuel"
    ],
    "wof:name":"Holden Wealth Management",
    "wof:placetype":"venue"
},
  "geometry": {"coordinates":[-86.561474,39.215326],"type":"Point"}
}