{
  "type": "Feature",
  "properties": {
    "iso:country":"US",
    "sg:address":"1401 Main St",
    "sg:city":"Rochester",
    "sg:classifiers":[
        {
            "category":"Real Estate",
            "subcategory":"Real Estate Agent",
            "type":"Services"
        }
    ],
    "sg:phone":"+1 574 223 2209",
    "sg:postcode":"46975",
    "sg:province":"IN",
    "sg:website":"www.heltrealty.com",
    "wof:name":"Dave Helt Realty",
    "wof:placetype":"venue"
},
  "geometry": {"coordinates":[-86.216646,41.059472],"type":"Point"}
}