{
  "type": "Feature",
  "properties": {
    "addr:full":"1508 Lakehurst Dr Fort Wayne IN 46815",
    "addr:housenumber":"1508",
    "addr:postcode":"46815",
    "addr:street":"Lakehurst Dr",
    "iso:country":"US",
    "sg:address":"1508 Lakehurst Dr",
    "sg:city":"Fort Wayne",
    "sg:classifiers":[
        {
            "category":"Arts & Performance",
            "subcategory":"Theater",
            "type":"Entertainment"
        }
    ],
    "sg:phone":"+1 260 493 8534",
    "sg:postcode":"46815",
    "sg:province":"IN",
    "sg:tags":[
        "group"
    ],
    "wof:name":"Craig Voelker",
    "wof:placetype":"venue"
},
  "geometry": {"coordinates":[-85.07442500000001,41.089943],"type":"Point"}
}