{
  "type": "Feature",
  "properties": {
    "iso:country":"US",
    "sg:address":"1622 N Wheeling Ave",
    "sg:city":"Muncie",
    "sg:classifiers":[
        {
            "category":"Professional",
            "subcategory":"Business Services",
            "type":"Services"
        }
    ],
    "sg:phone":"+1 765 284 2588",
    "sg:postcode":"47303",
    "sg:province":"IN",
    "sg:tags":[
        "interior",
        "consultant",
        "design",
        "decorator"
    ],
    "wof:name":"Pineapple House Interiors",
    "wof:placetype":"venue"
},
  "geometry": {"coordinates":[-85.396642,40.208653],"type":"Point"}
}