{
  "type": "Feature",
  "properties": {
    "iso:country":"US",
    "sg:address":"1367 Sherman Cir",
    "sg:city":"Cicero",
    "sg:classifiers":[
        {
            "category":"Home & Garden",
            "subcategory":"Building Materials",
            "type":"Retail Goods"
        }
    ],
    "sg:phone":"+1 317 984 8878",
    "sg:postcode":"46034",
    "sg:province":"IN",
    "sg:tags":[
        "wood",
        "preserving"
    ],
    "wof:name":"Cedar Savers Inc",
    "wof:placetype":"venue"
},
  "geometry": {"coordinates":[-86.031915,40.10882],"type":"Point"}
}