{
  "type": "Feature",
  "properties": {
    "iso:country":"US",
    "sg:address":"29 N 1st St",
    "sg:city":"Vincennes",
    "sg:classifiers":[
        {
            "category":"Building & Trades",
            "subcategory":"Construction",
            "type":"Services"
        }
    ],
    "sg:phone":"+1 812 882 2608",
    "sg:postcode":"47591",
    "sg:province":"IN",
    "sg:tags":[
        "contractor"
    ],
    "wof:name":"St Louis Street Building",
    "wof:placetype":"venue"
},
  "geometry": {"coordinates":[-87.53122999999999,38.68145],"type":"Point"}
}