{
  "type": "Feature",
  "properties": {
    "iso:country":"US",
    "sg:address":"911 Jefferson St",
    "sg:city":"Tell City",
    "sg:classifiers":[
        {
            "category":"Personal",
            "subcategory":"Beauty Salon",
            "type":"Services"
        }
    ],
    "sg:phone":"+1 812 547 5905",
    "sg:postcode":"47586",
    "sg:province":"IN",
    "sg:tags":[
        "shop"
    ],
    "wof:name":"Karen's Beauty Shop",
    "wof:placetype":"venue"
},
  "geometry": {"coordinates":[-86.768369,37.952223],"type":"Point"}
}