{
  "type": "Feature",
  "properties": {
    "iso:country":"US",
    "sg:address":"1444 Holland St",
    "sg:city":"Logansport",
    "sg:classifiers":[
        {
            "category":"Manufacturing",
            "subcategory":"Rubber & Plastics",
            "type":"Manufacturing & Wholesale Goods"
        }
    ],
    "sg:phone":"+1 574 753 4466",
    "sg:postcode":"46947",
    "sg:province":"IN",
    "wof:name":"New Idea Plastics Inc",
    "wof:placetype":"venue"
},
  "geometry": {"coordinates":[-86.382855,40.761535],"type":"Point"}
}