{
  "type": "Feature",
  "properties": {
    "iso:country":"US",
    "sg:address":"3431 Beasley Dr",
    "sg:city":"Indianapolis",
    "sg:classifiers":[
        {
            "category":"Home & Garden",
            "subcategory":"Building Materials",
            "type":"Retail Goods"
        }
    ],
    "sg:phone":"+1 317 297 3552",
    "sg:postcode":"46222",
    "sg:province":"IN",
    "sg:tags":[
        "paint"
    ],
    "wof:name":"Platinum Permanent Paint",
    "wof:placetype":"venue"
},
  "geometry": {"coordinates":[-86.23774,39.819535],"type":"Point"}
}