{
  "type": "Feature",
  "properties": {
    "addr:full":"1725 N Ironwood Dr South Bend IN 46635",
    "addr:housenumber":"1725",
    "addr:postcode":"46635",
    "addr:street":"N Ironwood Dr",
    "iso:country":"US",
    "sg:address":"1725 N Ironwood Dr",
    "sg:city":"South Bend",
    "sg:classifiers":[
        {
            "category":"Building & Trades",
            "subcategory":"Construction",
            "type":"Services"
        }
    ],
    "sg:phone":"+1 574 271 1988",
    "sg:postcode":"46635",
    "sg:province":"IN",
    "sg:tags":[
        "general",
        "contractor"
    ],
    "wof:name":"Elite Construction Corp",
    "wof:placetype":"venue"
},
  "geometry": {"coordinates":[-86.216587,41.698836],"type":"Point"}
}