{
  "type": "Feature",
  "properties": {
    "addr:full":"8618 W Co Rd 850 S Greensburg IN 47240",
    "addr:housenumber":"8618;850",
    "addr:postcode":"47240",
    "addr:street":"W Co Rd;S Greensburg",
    "iso:country":"US",
    "sg:address":"8618 W Co Rd 850 S",
    "sg:city":"Greensburg",
    "sg:phone":"+1 812 591 3128",
    "sg:postcode":"47240",
    "sg:province":"IN",
    "sg:tags":[
        "hog",
        "farm",
        "corn",
        "soybean",
        "or",
        "feedlot"
    ],
    "wof:name":"Tony Marsh",
    "wof:placetype":"venue"
},
  "geometry": {"coordinates":[-85.64349900000001,39.211642],"type":"Point"}
}