{
  "type": "Feature",
  "properties": {
    "iso:country":"US",
    "sg:address":"314 E Main St",
    "sg:city":"Washington",
    "sg:classifiers":[
        {
            "category":"Shopping",
            "subcategory":"Computers & Home Electronics",
            "type":"Retail Goods"
        }
    ],
    "sg:phone":"+1 812 257 2900",
    "sg:postcode":"47501",
    "sg:province":"IN",
    "sg:tags":[
        "equipment",
        "dealer"
    ],
    "wof:name":"Custom Computers",
    "wof:placetype":"venue"
},
  "geometry": {"coordinates":[-87.172194,38.657017],"type":"Point"}
}