{
  "type": "Feature",
  "properties": {
    "iso:country":"US",
    "sg:address":"3155 N Mitthoeffer Rd",
    "sg:city":"Indianapolis",
    "sg:classifiers":[
        {
            "category":"Retail",
            "subcategory":"Auto Repair",
            "type":"Services"
        }
    ],
    "sg:phone":"+1 317 894 4855",
    "sg:postcode":"46235",
    "sg:province":"IN",
    "sg:tags":[
        "general"
    ],
    "wof:name":"Pratts Auto & Transmition",
    "wof:placetype":"venue"
},
  "geometry": {"coordinates":[-85.990829,39.813367],"type":"Point"}
}