{
  "type": "Feature",
  "properties": {
    "iso:country":"US",
    "sg:address":"1416 S Huntington St",
    "sg:city":"Syracuse",
    "sg:classifiers":[
        {
            "category":"Professional",
            "subcategory":"Lawyer & Legal Services",
            "type":"Services"
        }
    ],
    "sg:phone":"+1 574 457 3222",
    "sg:postcode":"46567",
    "sg:province":"IN",
    "sg:tags":[
        "attorney"
    ],
    "wof:name":"Green & Cates",
    "wof:placetype":"venue"
},
  "geometry": {"coordinates":[-85.745001,41.405299],"type":"Point"}
}