{
  "type": "Feature",
  "properties": {
    "iso:country":"US",
    "sg:address":"830 S Washington St",
    "sg:city":"Delphi",
    "sg:classifiers":[
        {
            "category":"Building & Trades",
            "subcategory":"Construction",
            "type":"Services"
        }
    ],
    "sg:phone":"+1 765 564 2174",
    "sg:postcode":"46923",
    "sg:province":"IN",
    "sg:tags":[
        "general",
        "contractor"
    ],
    "wof:name":"Ron's Remodeling & Cnstctn",
    "wof:placetype":"venue"
},
  "geometry": {"coordinates":[-86.670227,40.581835],"type":"Point"}
}