{
  "type": "Feature",
  "properties": {
    "addr:full":"10472 N State St Harrison IN 45030",
    "addr:housenumber":"10472",
    "addr:postcode":"45030",
    "addr:street":"N State St",
    "iso:country":"US",
    "sg:address":"10472 N State St",
    "sg:city":"Harrison",
    "sg:classifiers":[
        {
            "category":"Organizations",
            "subcategory":"Community Association",
            "type":"Services"
        }
    ],
    "sg:phone":"+1 513 367 9194",
    "sg:postcode":"45030",
    "sg:province":"IN",
    "sg:tags":[
        "club"
    ],
    "wof:name":"Harrison Gun & Conservation",
    "wof:placetype":"venue"
},
  "geometry": {"coordinates":[-84.819717,39.268485],"type":"Point"}
}