{
  "type": "Feature",
  "properties": {
    "iso:country":"US",
    "sg:address":"2695 S Tull Rd",
    "sg:city":"Hanover",
    "sg:classifiers":[
        {
            "category":"Building & Trades",
            "subcategory":"Construction",
            "type":"Services"
        }
    ],
    "sg:phone":"+1 812 866 5108",
    "sg:postcode":"47243",
    "sg:province":"IN",
    "sg:tags":[
        "general",
        "contractor"
    ],
    "wof:name":"Davis Construction",
    "wof:placetype":"venue"
},
  "geometry": {"coordinates":[-85.475231,38.700127],"type":"Point"}
}