{
  "type": "Feature",
  "properties": {
    "iso:country":"US",
    "sg:address":"1990 S Memorial Dr",
    "sg:city":"New Castle",
    "sg:classifiers":[
        {
            "category":"Banks & Credit Unions",
            "subcategory":"Bank",
            "type":"Services"
        }
    ],
    "sg:phone":"+1 765 529 9160",
    "sg:postcode":"47362",
    "sg:province":"IN",
    "sg:tags":[
        "loan",
        "institution",
        "business"
    ],
    "wof:name":"United Cash Advance Inc",
    "wof:placetype":"venue"
},
  "geometry": {"coordinates":[-85.384852,39.912959],"type":"Point"}
}