{
  "type": "Feature",
  "properties": {
    "iso:country":"US",
    "sg:address":"4875 Willow Rd",
    "sg:city":"Zionsville",
    "sg:classifiers":[
        {
            "category":"Recreation",
            "type":"Entertainment"
        }
    ],
    "sg:phone":"+1 317 873 3913",
    "sg:postcode":"46077",
    "sg:province":"IN",
    "sg:tags":[
        "pool",
        "swimming"
    ],
    "wof:name":"Azionaqua Swim Club",
    "wof:placetype":"venue"
},
  "geometry": {"coordinates":[-86.25991999999999,39.97059],"type":"Point"}
}