{
  "type": "Feature",
  "properties": {
    "addr:full":"4018 E Southport Rd Indianapolis IN 46237",
    "addr:housenumber":"4018",
    "addr:postcode":"46237",
    "addr:street":"E Southport Rd",
    "iso:country":"US",
    "sg:address":"4018 E Southport Rd",
    "sg:city":"Indianapolis",
    "sg:classifiers":[
        {
            "category":"Health Services",
            "subcategory":"Doctor",
            "type":"Services"
        }
    ],
    "sg:phone":"+1 317 787 3276",
    "sg:postcode":"46237",
    "sg:province":"IN",
    "sg:tags":[
        "physician",
        "surgeon"
    ],
    "wof:name":"Robinson Medical Corp",
    "wof:placetype":"venue"
},
  "geometry": {"coordinates":[-86.096914,39.665587],"type":"Point"}
}