{
  "type": "Feature",
  "properties": {
    "addr:full":"2680 W 625 S North Judson IN 46366",
    "addr:housenumber":"2680",
    "addr:postcode":"46366",
    "addr:street":"W 625 S North Judson",
    "iso:country":"US",
    "sg:address":"2680 W 625 S",
    "sg:city":"North Judson",
    "sg:classifiers":[
        {
            "category":"Retail",
            "subcategory":"Auto Repair",
            "type":"Services"
        }
    ],
    "sg:phone":"+1 574 896 5766",
    "sg:postcode":"46366",
    "sg:province":"IN",
    "sg:tags":[
        "repairing",
        "automobile"
    ],
    "wof:name":"K T's Auto Repair",
    "wof:placetype":"venue"
},
  "geometry": {"coordinates":[-86.751761,41.211655],"type":"Point"}
}