{
  "type": "Feature",
  "properties": {
    "iso:country":"US",
    "sg:address":"2521 E State Rd 44",
    "sg:city":"Shelbyville",
    "sg:classifiers":[
        {
            "category":"Food & Beverages",
            "subcategory":"Groceries & Convenience Stores",
            "type":"Retail Goods"
        }
    ],
    "sg:phone":"+1 317 000 1111",
    "sg:postcode":"46176",
    "sg:province":"IN",
    "sg:tags":[
        "grocer"
    ],
    "wof:name":"Aldi",
    "wof:placetype":"venue"
},
  "geometry": {"coordinates":[-85.738928,39.52515],"type":"Point"}
}