{
  "type": "Feature",
  "properties": {
    "addr:full":"213 E Main St Madison IN 47250",
    "addr:housenumber":"213",
    "addr:postcode":"47250",
    "addr:street":"E Main St",
    "iso:country":"US",
    "sg:address":"213 E Main St",
    "sg:city":"Madison",
    "sg:classifiers":[
        {
            "category":"Banks & Credit Unions",
            "subcategory":"Bank",
            "type":"Services"
        }
    ],
    "sg:phone":"+1 812 265 5121",
    "sg:postcode":"47250",
    "sg:province":"IN",
    "wof:name":"Madison Bank & Trust Co",
    "wof:placetype":"venue"
},
  "geometry": {"coordinates":[-85.377489,38.73634],"type":"Point"}
}