{
  "type": "Feature",
  "properties": {
    "iso:country":"US",
    "sg:address":"67189 Linden Rd",
    "sg:city":"Lakeville",
    "sg:classifiers":[
        {
            "category":"Autos & Motor Vehicles",
            "subcategory":"Fuel & Gas Station",
            "type":"Retail Goods"
        }
    ],
    "sg:phone":"+1 574 784 3733",
    "sg:postcode":"46536",
    "sg:province":"IN",
    "sg:tags":[
        "oil"
    ],
    "wof:name":"Speedy's Amoco",
    "wof:placetype":"venue"
},
  "geometry": {"coordinates":[-86.271408,41.511547],"type":"Point"}
}