{
  "type": "Feature",
  "properties": {
    "iso:country":"US",
    "sg:address":"2323 W Co Rd 800 N",
    "sg:city":"Orleans",
    "sg:classifiers":[
        {
            "category":"Building & Trades",
            "subcategory":"Construction",
            "type":"Services"
        }
    ],
    "sg:phone":"+1 812 865 2979",
    "sg:postcode":"47452",
    "sg:province":"IN",
    "sg:tags":[
        "contractor"
    ],
    "wof:name":"Hagemier Construction",
    "wof:placetype":"venue"
},
  "geometry": {"coordinates":[-86.515386,38.676517],"type":"Point"}
}