{
  "type": "Feature",
  "properties": {
    "iso:country":"US",
    "sg:address":"4578 S Emerson Ave",
    "sg:city":"Indianapolis",
    "sg:classifiers":[
        {
            "category":"Shopping",
            "subcategory":"Bicycles & Sporting Goods",
            "type":"Retail Goods"
        }
    ],
    "sg:phone":"+1 317 783 9461",
    "sg:postcode":"46203",
    "sg:province":"IN",
    "sg:tags":[
        "gun",
        "gunsmith"
    ],
    "sg:website":"www.albroguns.com",
    "wof:name":"Albro's Guns",
    "wof:placetype":"venue"
},
  "geometry": {"coordinates":[-86.082598,39.701643],"type":"Point"}
}