{
  "type": "Feature",
  "properties": {
    "addr:full":"108 W Main St Mentone IN 46539",
    "addr:housenumber":"108",
    "addr:postcode":"46539",
    "addr:street":"W Main St",
    "iso:country":"US",
    "sg:address":"108 W Main St",
    "sg:city":"Mentone",
    "sg:classifiers":[
        {
            "category":"Restaurant",
            "type":"Food & Drink"
        }
    ],
    "sg:phone":"+1 574 353 7979",
    "sg:postcode":"46539",
    "sg:province":"IN",
    "wof:name":"Teels Family Restaurant",
    "wof:placetype":"venue"
},
  "geometry": {"coordinates":[-86.004501,41.166],"type":"Point"}
}