{
  "type": "Feature",
  "properties": {
    "addr:full":"5 S 11th St Richmond IN 47374",
    "addr:housenumber":"5",
    "addr:postcode":"47374",
    "addr:street":"S 11Th St",
    "iso:country":"US",
    "sg:address":"5 S 11th St",
    "sg:city":"Richmond",
    "sg:classifiers":[
        {
            "category":"Shopping",
            "subcategory":"Used Merchandise",
            "type":"Retail Goods"
        }
    ],
    "sg:phone":"+1 765 939 9073",
    "sg:postcode":"47374",
    "sg:province":"IN",
    "sg:tags":[
        "pawnbroker"
    ],
    "wof:name":"All American Pawn Shop",
    "wof:placetype":"venue"
},
  "geometry": {"coordinates":[-84.887612,39.829085],"type":"Point"}
}