{
  "type": "Feature",
  "properties": {
    "iso:country":"US",
    "sg:address":"301 Madison St",
    "sg:city":"New Richmond",
    "sg:classifiers":[
        {
            "category":"Government",
            "subcategory":"Fire Station",
            "type":"Public Place"
        }
    ],
    "sg:phone":"+1 765 339 7200",
    "sg:postcode":"47967",
    "sg:province":"IN",
    "sg:tags":[
        "department"
    ],
    "wof:name":"Coal Creek Fire Dept",
    "wof:placetype":"venue"
},
  "geometry": {"coordinates":[-86.982335,40.194337],"type":"Point"}
}