{
  "type": "Feature",
  "properties": {
    "addr:full":"2219 S Keystone Ave Indianapolis IN 46203",
    "addr:housenumber":"2219",
    "addr:postcode":"46203",
    "addr:street":"S Keystone Ave",
    "iso:country":"US",
    "sg:address":"2219 S Keystone Ave",
    "sg:city":"Indianapolis",
    "sg:classifiers":[
        {
            "category":"Retail",
            "subcategory":"Auto Repair",
            "type":"Services"
        }
    ],
    "sg:phone":"+1 317 780 9900",
    "sg:postcode":"46203",
    "sg:province":"IN",
    "sg:tags":[
        "repairing",
        "automobile"
    ],
    "wof:name":"Formula 1 Automotriz",
    "wof:placetype":"venue"
},
  "geometry": {"coordinates":[-86.120786,39.736366],"type":"Point"}
}