{
  "type": "Feature",
  "properties": {
    "iso:country":"US",
    "sg:address":"622 E Main St",
    "sg:city":"Centerville",
    "sg:classifiers":[
        {
            "category":"Freight",
            "type":"Transportation"
        }
    ],
    "sg:phone":"+1 765 855 3300",
    "sg:postcode":"47330",
    "sg:province":"IN",
    "sg:tags":[
        "commercial",
        "storage"
    ],
    "wof:name":"Andy's Self Storage",
    "wof:placetype":"venue"
},
  "geometry": {"coordinates":[-84.987414,39.818102],"type":"Point"}
}