{
  "type": "Feature",
  "properties": {
    "iso:country":"US",
    "sg:address":"701 W Sample St",
    "sg:city":"South Bend",
    "sg:classifiers":[
        {
            "category":"Government",
            "subcategory":"Police Station",
            "type":"Public Place"
        }
    ],
    "sg:phone":"+1 574 288 3784",
    "sg:postcode":"46601",
    "sg:province":"IN",
    "sg:tags":[
        "department"
    ],
    "wof:name":"United Community Against Drug",
    "wof:placetype":"venue"
},
  "geometry": {"coordinates":[-86.25483800000001,41.665068],"type":"Point"}
}