{
  "type": "Feature",
  "properties": {
    "iso:country":"US",
    "sg:address":"1724 E 53rd St",
    "sg:city":"Anderson",
    "sg:classifiers":[
        {
            "category":"Banks & Credit Unions",
            "subcategory":"Bank",
            "type":"Services"
        }
    ],
    "sg:phone":"+1 765 642 1726",
    "sg:postcode":"46013",
    "sg:province":"IN",
    "wof:name":"Ameriana Bank & Trust",
    "wof:placetype":"venue"
},
  "geometry": {"coordinates":[-85.652959,40.061851],"type":"Point"}
}