{
  "type": "Feature",
  "properties": {
    "iso:country":"US",
    "sg:address":"911 E 86th St",
    "sg:city":"Indianapolis",
    "sg:classifiers":[
        {
            "category":"Shopping",
            "type":"Retail Goods"
        }
    ],
    "sg:phone":"+1 317 573 8020",
    "sg:postcode":"46240",
    "sg:province":"IN",
    "sg:tags":[
        "equipment",
        "care",
        "health",
        "home"
    ],
    "wof:name":"A Plus Medical",
    "wof:placetype":"venue"
},
  "geometry": {"coordinates":[-86.141184,39.912463],"type":"Point"}
}