{
  "type": "Feature",
  "properties": {
    "addr:full":"604 W 5th Ave Gary IN 46402",
    "addr:housenumber":"604",
    "addr:postcode":"46402",
    "addr:street":"W 5Th Ave",
    "iso:country":"US",
    "sg:address":"604 W 5th Ave",
    "sg:city":"Gary",
    "sg:classifiers":[
        {
            "category":"Personal",
            "subcategory":"Beauty Salon",
            "type":"Services"
        }
    ],
    "sg:phone":"+1 219 882 6230",
    "sg:postcode":"46402",
    "sg:province":"IN",
    "wof:name":"House Of Style",
    "wof:placetype":"venue"
},
  "geometry": {"coordinates":[-87.345246,41.602103],"type":"Point"}
}