{
  "type": "Feature",
  "properties": {
    "iso:country":"US",
    "sg:address":"610 Indiana St",
    "sg:city":"Rockville",
    "sg:classifiers":[
        {
            "category":"Retail",
            "subcategory":"Auto Repair",
            "type":"Services"
        }
    ],
    "sg:phone":"+1 765 569 2133",
    "sg:postcode":"47872",
    "sg:province":"IN",
    "sg:tags":[
        "repairing",
        "automobile",
        "general"
    ],
    "wof:name":"Sid's Garage",
    "wof:placetype":"venue"
},
  "geometry": {"coordinates":[-87.220759,39.766576],"type":"Point"}
}