{
  "type": "Feature",
  "properties": {
    "iso:country":"US",
    "sg:address":"7609 W 200 S",
    "sg:city":"Swayzee",
    "sg:classifiers":[
        {
            "category":"Farming",
            "subcategory":"Farm",
            "type":"Manufacturing & Wholesale Goods"
        }
    ],
    "sg:phone":"+1 765 922 7620",
    "sg:postcode":"46986",
    "sg:province":"IN",
    "sg:tags":[
        "crop",
        "general"
    ],
    "wof:name":"Claude Thrailkill",
    "wof:placetype":"venue"
},
  "geometry": {"coordinates":[-85.817803,40.522748],"type":"Point"}
}