{
  "type": "Feature",
  "properties": {
    "iso:country":"US",
    "sg:address":"3913 N Keystone Ave",
    "sg:city":"Indianapolis",
    "sg:classifiers":[
        {
            "category":"Utilities",
            "subcategory":"Telephone",
            "type":"Services"
        }
    ],
    "sg:phone":"+1 317 568 2899",
    "sg:postcode":"46205",
    "sg:province":"IN",
    "sg:tags":[
        "telecommunication"
    ],
    "wof:name":"C-Cat Communications",
    "wof:placetype":"venue"
},
  "geometry": {"coordinates":[-86.12169400000001,39.828385],"type":"Point"}
}