{
  "type": "Feature",
  "properties": {
    "iso:country":"US",
    "sg:address":"2660 Hawcreek Blvd",
    "sg:city":"Columbus",
    "sg:classifiers":[
        {
            "category":"Autos & Motor Vehicles",
            "subcategory":"Auto Supplies",
            "type":"Retail Goods"
        }
    ],
    "sg:phone":"+1 812 372 2529",
    "sg:postcode":"47201",
    "sg:province":"IN",
    "sg:tags":[
        "automobile",
        "parts"
    ],
    "wof:name":"Big A Auto Parts",
    "wof:placetype":"venue"
},
  "geometry": {"coordinates":[-85.894755,39.223585],"type":"Point"}
}