{
  "type": "Feature",
  "properties": {
    "iso:country":"US",
    "sg:address":"801 Monroe St",
    "sg:city":"Laporte",
    "sg:classifiers":[
        {
            "category":"Banks & Credit Unions",
            "subcategory":"Bank",
            "type":"Services"
        }
    ],
    "sg:phone":"+1 219 362 6195",
    "sg:postcode":"46350",
    "sg:province":"IN",
    "wof:name":"Fifth Third Bank",
    "wof:placetype":"venue"
},
  "geometry": {"coordinates":[-86.719696,41.610924],"type":"Point"}
}