{
  "type": "Feature",
  "properties": {
    "addr:full":"212 S Western Ave Marion IN 46952",
    "addr:housenumber":"212",
    "addr:postcode":"46952",
    "addr:street":"S Western Ave",
    "iso:country":"US",
    "sg:address":"212 S Western Ave",
    "sg:city":"Marion",
    "sg:classifiers":[
        {
            "category":"Shopping",
            "subcategory":"Florist",
            "type":"Retail Goods"
        }
    ],
    "sg:phone":"+1 765 662 0022",
    "sg:postcode":"46952",
    "sg:province":"IN",
    "wof:name":"Sweet Pea's",
    "wof:placetype":"venue"
},
  "geometry": {"coordinates":[-85.674047,40.55896],"type":"Point"}
}