{
  "type": "Feature",
  "properties": {
    "iso:country":"US",
    "sg:address":"4914 S Emerson Ave",
    "sg:city":"Indianapolis",
    "sg:classifiers":[
        {
            "category":"Insurance",
            "subcategory":"Insurance Agent",
            "type":"Services"
        },
        {
            "category":"Insurance",
            "subcategory":"Hazard Insurance",
            "type":"Services"
        }
    ],
    "sg:phone":"+1 317 780 2500",
    "sg:postcode":"46203",
    "sg:province":"IN",
    "sg:tags":[
        "auto",
        "marine",
        "motorcycle",
        "boat"
    ],
    "wof:name":"Titan Auto Insurance - & Boat Insurance",
    "wof:placetype":"venue"
},
  "geometry": {"coordinates":[-86.082542,39.695008],"type":"Point"}
}