{
  "type": "Feature",
  "properties": {
    "iso:country":"US",
    "sg:address":"3723 Franklin St",
    "sg:city":"Michigan City",
    "sg:classifiers":[
        {
            "category":"Health Services",
            "subcategory":"Doctor",
            "type":"Services"
        }
    ],
    "sg:phone":"+1 219 874 3313",
    "sg:postcode":"46360",
    "sg:province":"IN",
    "sg:tags":[
        "physician",
        "surgeon"
    ],
    "wof:name":"Franklin Clinic",
    "wof:placetype":"venue"
},
  "geometry": {"coordinates":[-86.893992,41.685408],"type":"Point"}
}