{
  "type": "Feature",
  "properties": {
    "iso:country":"US",
    "sg:address":"111 S Indiana Ave",
    "sg:city":"English",
    "sg:classifiers":[
        {
            "category":"Government",
            "subcategory":"Post Office",
            "type":"Public Place"
        }
    ],
    "sg:phone":"+1 812 338 2055",
    "sg:postcode":"47172",
    "sg:province":"IN",
    "wof:name":"US Post Office",
    "wof:placetype":"venue"
},
  "geometry": {"coordinates":[-85.756551,38.398018],"type":"Point"}
}