{
  "type": "Feature",
  "properties": {
    "iso:country":"US",
    "sg:address":"13644 McKinley Hwy",
    "sg:city":"Mishawaka",
    "sg:classifiers":[
        {
            "category":"Retail",
            "subcategory":"Auto Repair",
            "type":"Services"
        }
    ],
    "sg:phone":"+1 574 256 1981",
    "sg:postcode":"46545",
    "sg:province":"IN",
    "sg:tags":[
        "body",
        "automobile",
        "painting"
    ],
    "wof:name":"Mann's Corvette Shop Inc",
    "wof:placetype":"venue"
},
  "geometry": {"coordinates":[-86.131354,41.680451],"type":"Point"}
}