{
  "type": "Feature",
  "properties": {
    "iso:country":"US",
    "sg:address":"400 S Green River Rd",
    "sg:city":"Evansville",
    "sg:classifiers":[
        {
            "category":"Insurance",
            "subcategory":"Insurance Agent",
            "type":"Services"
        }
    ],
    "sg:phone":"+1 812 476 4943",
    "sg:postcode":"47715",
    "sg:province":"IN",
    "wof:name":"James R Pyle Insurance",
    "wof:placetype":"venue"
},
  "geometry": {"coordinates":[-87.49263500000001,37.971678],"type":"Point"}
}