{
  "type": "Feature",
  "properties": {
    "addr:full":"211 S 3rd St Goshen IN 46526",
    "addr:housenumber":"211",
    "addr:postcode":"46526",
    "addr:street":"S 3Rd St",
    "iso:country":"US",
    "sg:address":"211 S 3rd St",
    "sg:city":"Goshen",
    "sg:classifiers":[
        {
            "category":"Professional",
            "subcategory":"Lawyer & Legal Services",
            "type":"Services"
        }
    ],
    "sg:phone":"+1 574 533 8041",
    "sg:postcode":"46526",
    "sg:province":"IN",
    "sg:tags":[
        "attorney"
    ],
    "wof:name":"Richard W Crowder Atty At Law",
    "wof:placetype":"venue"
},
  "geometry": {"coordinates":[-85.83614,41.584507],"type":"Point"}
}