{
  "type": "Feature",
  "properties": {
    "iso:country":"US",
    "sg:address":"1933 Hwy 337 NW",
    "sg:city":"Corydon",
    "sg:classifiers":[
        {
            "category":"Shopping",
            "subcategory":"Tobacco",
            "type":"Retail Goods"
        }
    ],
    "sg:phone":"+1 812 738 1907",
    "sg:postcode":"47112",
    "sg:province":"IN",
    "sg:tags":[
        "cigarette",
        "cigar",
        "dealer"
    ],
    "wof:name":"Smokey's Discount Tobacco",
    "wof:placetype":"venue"
},
  "geometry": {"coordinates":[-86.136816,38.229941],"type":"Point"}
}