{
  "type": "Feature",
  "properties": {
    "iso:country":"US",
    "sg:address":"8125 Joest Rd",
    "sg:city":"Wadesville",
    "sg:classifiers":[
        {
            "category":"Building & Trades",
            "subcategory":"Cleaning & Sanitation",
            "type":"Services"
        }
    ],
    "sg:phone":"+1 812 673 4617",
    "sg:postcode":"47638",
    "sg:province":"IN",
    "sg:tags":[
        "window"
    ],
    "wof:name":"Brite-Way Window Cleaning",
    "wof:placetype":"venue"
},
  "geometry": {"coordinates":[-87.769261,38.09982],"type":"Point"}
}