{
  "type": "Feature",
  "properties": {
    "iso:country":"US",
    "sg:address":"403 Conkey St",
    "sg:city":"Hammond",
    "sg:classifiers":[
        {
            "category":"Manufacturing",
            "subcategory":"Metals",
            "type":"Manufacturing & Wholesale Goods"
        }
    ],
    "sg:phone":"+1 219 931 0405",
    "sg:postcode":"46324",
    "sg:province":"IN",
    "sg:tags":[
        "valve"
    ],
    "wof:name":"Henry Pratt Co",
    "wof:placetype":"venue"
},
  "geometry": {"coordinates":[-87.517328,41.601371],"type":"Point"}
}