{
  "type": "Feature",
  "properties": {
    "addr:full":"2114 E Washington St Indianapolis IN 46201",
    "addr:housenumber":"2114",
    "addr:postcode":"46201",
    "addr:street":"E Washington St",
    "iso:country":"US",
    "sg:address":"2114 E Washington St",
    "sg:city":"Indianapolis",
    "sg:classifiers":[
        {
            "category":"Organizations",
            "subcategory":"Religious Organization",
            "type":"Services"
        }
    ],
    "sg:phone":"+1 317 636 0223",
    "sg:postcode":"46201",
    "sg:province":"IN",
    "sg:tags":[
        "church"
    ],
    "wof:name":"Changing Lives Through Jesus",
    "wof:placetype":"venue"
},
  "geometry": {"coordinates":[-86.124368,39.767848],"type":"Point"}
}