{
  "type": "Feature",
  "properties": {
    "iso:country":"US",
    "sg:address":"2410 Broadway St",
    "sg:city":"Fort Wayne",
    "sg:classifiers":[
        {
            "category":"Insurance",
            "subcategory":"Insurance Agent",
            "type":"Services"
        }
    ],
    "sg:phone":"+1 260 456 2083",
    "sg:postcode":"46807",
    "sg:province":"IN",
    "sg:website":"www.donnelly-co.com",
    "wof:name":"Donnelly & Co",
    "wof:placetype":"venue"
},
  "geometry": {"coordinates":[-85.152361,41.06251],"type":"Point"}
}