{
  "type": "Feature",
  "properties": {
    "addr:full":"630 173rd St Hammond IN 46324",
    "addr:housenumber":"630",
    "addr:postcode":"46324",
    "addr:street":"173Rd St",
    "iso:country":"US",
    "sg:address":"630 173rd St",
    "sg:city":"Hammond",
    "sg:classifiers":[
        {
            "category":"Retail",
            "subcategory":"Repair Shop",
            "type":"Services"
        }
    ],
    "sg:phone":"+1 219 931 0731",
    "sg:postcode":"46324",
    "sg:province":"IN",
    "sg:tags":[
        "lock",
        "locksmith"
    ],
    "wof:name":"Scott's Locks & Doors",
    "wof:placetype":"venue"
},
  "geometry": {"coordinates":[-87.511442,41.58097],"type":"Point"}
}