{
  "type": "Feature",
  "properties": {
    "addr:full":"2 N Meridian St Ste 1 Indianapolis IN 46204",
    "addr:housenumber":"2",
    "addr:postcode":"46204",
    "addr:street":"N Meridian St Ste 1",
    "iso:country":"US",
    "sg:address":"2 N Meridian St Ste 1",
    "sg:city":"Indianapolis",
    "sg:classifiers":[
        {
            "category":"Professional",
            "subcategory":"Business Services",
            "type":"Services"
        }
    ],
    "sg:phone":"+1 317 233 7413",
    "sg:postcode":"46204",
    "sg:province":"IN",
    "sg:tags":[
        "medical",
        "administration"
    ],
    "sg:website":"http://www.indianachildsupportadoptionlawyertonyzirkl",
    "wof:name":"Human Resources",
    "wof:placetype":"venue"
},
  "geometry": {"coordinates":[-86.158081,39.767101],"type":"Point"}
}