{
  "type": "Feature",
  "properties": {
    "iso:country":"US",
    "sg:address":"421 SW 1st St",
    "sg:city":"Paoli",
    "sg:classifiers":[
        {
            "category":"Social Services",
            "type":"Services"
        }
    ],
    "sg:phone":"+1 812 723 3910",
    "sg:postcode":"47454",
    "sg:province":"IN",
    "sg:tags":[
        "organization",
        "welfare"
    ],
    "wof:name":"Hoosier Uplands Economic",
    "wof:placetype":"venue"
},
  "geometry": {"coordinates":[-86.470304,38.552772],"type":"Point"}
}