{
  "type": "Feature",
  "properties": {
    "addr:full":"524 S L St Richmond IN 47374",
    "addr:housenumber":"524",
    "addr:postcode":"47374",
    "addr:street":"S L St",
    "iso:country":"US",
    "sg:address":"524 S L St",
    "sg:city":"Richmond",
    "sg:classifiers":[
        {
            "category":"Building & Trades",
            "subcategory":"Electrical",
            "type":"Services"
        }
    ],
    "sg:phone":"+1 765 962 6332",
    "sg:postcode":"47374",
    "sg:province":"IN",
    "sg:tags":[
        "electric",
        "contractor"
    ],
    "sg:website":"www.cumminselectric.com",
    "wof:name":"Cummins Electric Inc",
    "wof:placetype":"venue"
},
  "geometry": {"coordinates":[-84.896209,39.814285],"type":"Point"}
}