{
  "type": "Feature",
  "properties": {
    "iso:country":"US",
    "sg:address":"9601 S Co Rd 775 E",
    "sg:city":"Cloverdale",
    "sg:classifiers":[
        {
            "category":"Building & Trades",
            "subcategory":"Construction",
            "type":"Services"
        }
    ],
    "sg:phone":"+1 765 795 5184",
    "sg:postcode":"46120",
    "sg:province":"IN",
    "sg:tags":[
        "general",
        "contractor"
    ],
    "wof:name":"Bud's Construction",
    "wof:placetype":"venue"
},
  "geometry": {"coordinates":[-86.71093399999999,39.520012],"type":"Point"}
}