{
  "type": "Feature",
  "properties": {
    "addr:full":"238 America Pl Jeffersonville IN 47130",
    "addr:housenumber":"238",
    "addr:postcode":"47130",
    "addr:street":"America Pl",
    "iso:country":"US",
    "sg:address":"238 America Pl",
    "sg:city":"Jeffersonville",
    "sg:classifiers":[
        {
            "category":"Professional",
            "type":"Services"
        },
        {
            "category":"Professional",
            "subcategory":"Advertising",
            "type":"Services"
        },
        {
            "category":"Retail",
            "subcategory":"Event Space",
            "type":"Services"
        }
    ],
    "sg:phone":"+1 812 288 1030",
    "sg:postcode":"47130",
    "sg:province":"IN",
    "sg:tags":[
        "product",
        "fair",
        "trade",
        "planning",
        "exposition",
        "advertising-promotional",
        "meeting",
        "shows"
    ],
    "wof:name":"Millennium Events & Flora",
    "wof:placetype":"venue"
},
  "geometry": {"coordinates":[-85.73723699999999,38.288106],"type":"Point"}
}