{
  "type": "Feature",
  "properties": {
    "iso:country":"US",
    "sg:address":"1401 W Jefferson St",
    "sg:city":"Kokomo",
    "sg:classifiers":[
        {
            "category":"Manufacturing",
            "subcategory":"Printing",
            "type":"Manufacturing & Wholesale Goods"
        }
    ],
    "sg:phone":"+1 765 457 5451",
    "sg:postcode":"46901",
    "sg:province":"IN",
    "sg:tags":[
        "screen",
        "silk",
        "design",
        "offset"
    ],
    "wof:name":"Hemmeger Printing",
    "wof:placetype":"venue"
},
  "geometry": {"coordinates":[-86.147283,40.490702],"type":"Point"}
}