{
  "type": "Feature",
  "properties": {
    "addr:full":"305 W Van Buren St Columbia City IN 46725",
    "addr:housenumber":"305",
    "addr:postcode":"46725",
    "addr:street":"W Van Buren St",
    "iso:country":"US",
    "sg:address":"305 W Van Buren St",
    "sg:city":"Columbia City",
    "sg:classifiers":[
        {
            "category":"Professional",
            "subcategory":"Computer Services",
            "type":"Services"
        }
    ],
    "sg:phone":"+1 260 244 7425",
    "sg:postcode":"46725",
    "sg:province":"IN",
    "sg:tags":[
        "internet"
    ],
    "sg:website":"www.3riversarchery.com",
    "wof:name":"Ft Wayne Internet",
    "wof:placetype":"venue"
},
  "geometry": {"coordinates":[-85.49267999999999,41.15693],"type":"Point"}
}