{
  "type": "Feature",
  "properties": {
    "iso:country":"US",
    "sg:address":"17808 Commerce Dr",
    "sg:city":"Westfield",
    "sg:classifiers":[
        {
            "category":"Manufacturing",
            "subcategory":"Tools & Machinery",
            "type":"Manufacturing & Wholesale Goods"
        }
    ],
    "sg:phone":"+1 317 867 4699",
    "sg:postcode":"46074",
    "sg:province":"IN",
    "sg:tags":[
        "machine",
        "shop"
    ],
    "sg:website":"www.voege.com",
    "wof:name":"Voege Precision Mach Products",
    "wof:placetype":"venue"
},
  "geometry": {"coordinates":[-86.149699,40.04584],"type":"Point"}
}