{
  "type": "Feature",
  "properties": {
    "iso:country":"US",
    "sg:address":"55907 S Mayflower Rd",
    "sg:city":"South Bend",
    "sg:classifiers":[
        {
            "category":"Freight",
            "type":"Transportation"
        }
    ],
    "sg:phone":"+1 574 232 4611",
    "sg:postcode":"46619",
    "sg:province":"IN",
    "wof:name":"Centrestage Transportation Inc",
    "wof:placetype":"venue"
},
  "geometry": {"coordinates":[-86.322125,41.671794],"type":"Point"}
}