{
  "type": "Feature",
  "properties": {
    "addr:full":"515 E 13th St Winamac IN 46996",
    "addr:housenumber":"515",
    "addr:postcode":"46996",
    "addr:street":"E 13Th St",
    "iso:country":"US",
    "sg:address":"515 E 13th St",
    "sg:city":"Winamac",
    "sg:classifiers":[
        {
            "category":"Health Services",
            "subcategory":"Nursing And Care Facility",
            "type":"Services"
        }
    ],
    "sg:phone":"+1 574 946 6143",
    "sg:postcode":"46996",
    "sg:province":"IN",
    "wof:name":"Omega Healthcare Investors",
    "wof:placetype":"venue"
},
  "geometry": {"coordinates":[-86.605271,41.057558],"type":"Point"}
}