{
  "type": "Feature",
  "properties": {
    "iso:country":"US",
    "sg:address":"1397 E 700 S",
    "sg:city":"Star City",
    "sg:classifiers":[
        {
            "category":"Building & Trades",
            "subcategory":"Electrical",
            "type":"Services"
        }
    ],
    "sg:phone":"+1 574 595 7146",
    "sg:postcode":"46985",
    "sg:province":"IN",
    "sg:tags":[
        "electrical",
        "contractor"
    ],
    "wof:name":"Jim Electric Service",
    "wof:placetype":"venue"
},
  "geometry": {"coordinates":[-86.581006,40.954415],"type":"Point"}
}