{
  "type": "Feature",
  "properties": {
    "addr:full":"921 W McKinley Ave Mishawaka IN 46545",
    "addr:housenumber":"921",
    "addr:postcode":"46545",
    "addr:street":"W Mckinley Ave",
    "iso:country":"US",
    "sg:address":"921 W McKinley Ave",
    "sg:city":"Mishawaka",
    "sg:classifiers":[
        {
            "category":"Restaurant",
            "type":"Food & Drink"
        }
    ],
    "sg:phone":"+1 574 258 0830",
    "sg:postcode":"46545",
    "sg:province":"IN",
    "wof:name":"Tradewinds Restaurant",
    "wof:placetype":"venue"
},
  "geometry": {"coordinates":[-86.193843,41.680217],"type":"Point"}
}