{
  "type": "Feature",
  "properties": {
    "iso:country":"US",
    "sg:address":"555 Woodrow Ave",
    "sg:city":"Indianapolis",
    "sg:classifiers":[
        {
            "category":"Building & Trades",
            "subcategory":"Construction",
            "type":"Services"
        }
    ],
    "sg:phone":"+1 317 381 0040",
    "sg:postcode":"46241",
    "sg:province":"IN",
    "sg:tags":[
        "painter"
    ],
    "wof:name":"Alexander's Painting & Dry Wl",
    "wof:placetype":"venue"
},
  "geometry": {"coordinates":[-86.24029400000001,39.758309],"type":"Point"}
}