{
  "type": "Feature",
  "properties": {
    "iso:country":"US",
    "sg:address":"3779 N Smith St",
    "sg:city":"Terre Haute",
    "sg:classifiers":[
        {
            "category":"Shopping",
            "subcategory":"Hobbies, Toys, & Games",
            "type":"Retail Goods"
        }
    ],
    "sg:phone":"+1 812 466 5989",
    "sg:postcode":"47805",
    "sg:province":"IN",
    "wof:name":"Just For You",
    "wof:placetype":"venue"
},
  "geometry": {"coordinates":[-87.34888100000001,39.512026],"type":"Point"}
}