{
  "type": "Feature",
  "properties": {
    "iso:country":"US",
    "sg:address":"1041 S Maple St",
    "sg:city":"Orleans",
    "sg:classifiers":[
        {
            "category":"Insurance",
            "subcategory":"Hazard Insurance",
            "type":"Services"
        }
    ],
    "sg:phone":"+1 812 865 8800",
    "sg:postcode":"47452",
    "sg:province":"IN",
    "sg:tags":[
        "bond"
    ],
    "wof:name":"Monopoly Bail Bond Co",
    "wof:placetype":"venue"
},
  "geometry": {"coordinates":[-86.453042,38.653716],"type":"Point"}
}