{
  "type": "Feature",
  "properties": {
    "iso:country":"US",
    "sg:address":"1441 Aberdeen St",
    "sg:city":"Terre Haute",
    "sg:classifiers":[
        {
            "category":"Freight",
            "type":"Transportation"
        }
    ],
    "sg:phone":"+1 812 466 2225",
    "sg:postcode":"47804",
    "sg:province":"IN",
    "sg:tags":[
        "warehouse"
    ],
    "wof:name":"Distributors Terminal Corp",
    "wof:placetype":"venue"
},
  "geometry": {"coordinates":[-87.358778,39.50585],"type":"Point"}
}