{
  "type": "Feature",
  "properties": {
    "addr:full":"9546 Allisonville Rd Indianapolis IN 46250",
    "addr:housenumber":"9546",
    "addr:postcode":"46250",
    "addr:street":"Allisonville Rd",
    "iso:country":"US",
    "sg:address":"9546 Allisonville Rd",
    "sg:city":"Indianapolis",
    "sg:classifiers":[
        {
            "category":"Restaurant",
            "type":"Food & Drink"
        }
    ],
    "sg:menulink":"http://www.allmenus.com/in/lawrence/81717-subway/menu/",
    "sg:phone":"+1 317 578 2929",
    "sg:postcode":"46250",
    "sg:province":"IN",
    "sg:tags":[
        "american",
        "sandwich"
    ],
    "wof:name":"Subway",
    "wof:placetype":"venue"
},
  "geometry": {"coordinates":[-86.067494,39.925635],"type":"Point"}
}