{
  "type": "Feature",
  "properties": {
    "addr:full":"14 W Ramey St Rossville IN 46065",
    "addr:housenumber":"14",
    "addr:postcode":"46065",
    "addr:street":"W Ramey St",
    "iso:country":"US",
    "sg:address":"14 W Ramey St",
    "sg:city":"Rossville",
    "sg:classifiers":[
        {
            "category":"Building & Trades",
            "subcategory":"Construction",
            "type":"Services"
        }
    ],
    "sg:phone":"+1 765 652 1801",
    "sg:postcode":"46065",
    "sg:province":"IN",
    "sg:tags":[
        "contractor"
    ],
    "wof:name":"Beckett Rentals",
    "wof:placetype":"venue"
},
  "geometry": {"coordinates":[-86.59494100000001,40.418861],"type":"Point"}
}