{
  "type": "Feature",
  "properties": {
    "iso:country":"US",
    "sg:address":"204 S Walnut St",
    "sg:city":"Muncie",
    "sg:classifiers":[
        {
            "category":"Government",
            "subcategory":"Office",
            "type":"Public Place"
        }
    ],
    "sg:phone":"+1 765 747 5566",
    "sg:postcode":"47305",
    "sg:province":"IN",
    "wof:name":"Congressman Mike Pence",
    "wof:placetype":"venue"
},
  "geometry": {"coordinates":[-85.386463,40.192],"type":"Point"}
}