{
  "type": "Feature",
  "properties": {
    "iso:country":"US",
    "sg:address":"3045 45th St",
    "sg:city":"Highland",
    "sg:classifiers":[
        {
            "category":"Building & Trades",
            "subcategory":"Pest Control",
            "type":"Services"
        }
    ],
    "sg:phone":"+1 219 924 6900",
    "sg:postcode":"46322",
    "sg:province":"IN",
    "wof:name":"Guardian Pest Control",
    "wof:placetype":"venue"
},
  "geometry": {"coordinates":[-87.455026,41.537523],"type":"Point"}
}