{
  "type": "Feature",
  "properties": {
    "iso:country":"US",
    "sg:address":"1163 Washington Ave",
    "sg:city":"Evansville",
    "sg:classifiers":[
        {
            "category":"Restaurant",
            "type":"Food & Drink"
        }
    ],
    "sg:phone":"+1 812 425 1712",
    "sg:postcode":"47714",
    "sg:province":"IN",
    "wof:name":"Mc Donald's",
    "wof:placetype":"venue"
},
  "geometry": {"coordinates":[-87.54306099999999,37.962702],"type":"Point"}
}