{
  "type": "Feature",
  "properties": {
    "addr:full":"10919 E Washington St Indianapolis IN 46229",
    "addr:housenumber":"10919",
    "addr:postcode":"46229",
    "addr:street":"E Washington St",
    "iso:country":"US",
    "sg:address":"10919 E Washington St",
    "sg:city":"Indianapolis",
    "sg:classifiers":[
        {
            "category":"Restaurant",
            "type":"Food & Drink"
        }
    ],
    "sg:menulink":"http://www.allmenus.com/in/warren/69640-donatos-pizza/menu/",
    "sg:phone":"+1 317 890 4000",
    "sg:postcode":"46229",
    "sg:province":"IN",
    "sg:tags":[
        "sandwich",
        "salad",
        "soup",
        "american",
        "wrap",
        "pizza"
    ],
    "wof:name":"Donatos Pizza",
    "wof:placetype":"venue"
},
  "geometry": {"coordinates":[-85.972796,39.775584],"type":"Point"}
}