{
  "type": "Feature",
  "properties": {
    "iso:country":"US",
    "sg:address":"59166 Co Rd 3",
    "sg:city":"Elkhart",
    "sg:classifiers":[
        {
            "category":"Retail",
            "subcategory":"Auto Repair",
            "type":"Services"
        }
    ],
    "sg:phone":"+1 574 294 3881",
    "sg:postcode":"46517",
    "sg:province":"IN",
    "sg:tags":[
        "body",
        "automobile",
        "painting"
    ],
    "wof:name":"First Choice Body Shop",
    "wof:placetype":"venue"
},
  "geometry": {"coordinates":[-86.02337,41.635391],"type":"Point"}
}