{
  "type": "Feature",
  "properties": {
    "iso:country":"US",
    "sg:address":"950 W North St",
    "sg:city":"Kendallville",
    "sg:classifiers":[
        {
            "category":"Personal",
            "subcategory":"Tanning Parlor",
            "type":"Services"
        }
    ],
    "sg:phone":"+1 260 349 1344",
    "sg:postcode":"46755",
    "sg:province":"IN",
    "sg:tags":[
        "salon"
    ],
    "wof:name":"Golden Myst",
    "wof:placetype":"venue"
},
  "geometry": {"coordinates":[-85.279679,41.452424],"type":"Point"}
}