{
  "type": "Feature",
  "properties": {
    "iso:country":"US",
    "sg:address":"6116 N College Ave",
    "sg:city":"Indianapolis",
    "sg:classifiers":[
        {
            "category":"Health Services",
            "subcategory":"Dentist",
            "type":"Services"
        }
    ],
    "sg:phone":"+1 317 251 9990",
    "sg:postcode":"46220",
    "sg:province":"IN",
    "sg:tags":[
        "denture",
        "dental",
        "clinic",
        "dentists-prosthodontists"
    ],
    "wof:name":"Elrod, Gina M, Dds - Broad Ripple Village Dental",
    "wof:placetype":"venue"
},
  "geometry": {"coordinates":[-86.146062,39.866106],"type":"Point"}
}