{
  "type": "Feature",
  "properties": {
    "iso:country":"US",
    "sg:address":"2601 W 10th St",
    "sg:city":"Indianapolis",
    "sg:classifiers":[
        {
            "category":"Autos & Motor Vehicles",
            "subcategory":"Auto Supplies",
            "type":"Retail Goods"
        }
    ],
    "sg:phone":"+1 317 634 8366",
    "sg:postcode":"46222",
    "sg:province":"IN",
    "sg:tags":[
        "tire"
    ],
    "wof:name":"Tire King",
    "wof:placetype":"venue"
},
  "geometry": {"coordinates":[-86.203857,39.780701],"type":"Point"}
}