{
  "type": "Feature",
  "properties": {
    "iso:country":"US",
    "sg:address":"2814 Calumet Ave",
    "sg:city":"Valparaiso",
    "sg:classifiers":[
        {
            "category":"Shopping",
            "subcategory":"Tobacco",
            "type":"Retail Goods"
        }
    ],
    "sg:phone":"+1 219 477 2726",
    "sg:postcode":"46383",
    "sg:province":"IN",
    "sg:tags":[
        "cigarette",
        "cigar",
        "dealer"
    ],
    "wof:name":"Cigarette Discount Outlet",
    "wof:placetype":"venue"
},
  "geometry": {"coordinates":[-87.043886,41.496713],"type":"Point"}
}