{
  "type": "Feature",
  "properties": {
    "iso:country":"US",
    "sg:address":"5136 E Stop 11 Rd",
    "sg:city":"Indianapolis",
    "sg:classifiers":[
        {
            "category":"Health Services",
            "subcategory":"Doctor",
            "type":"Services"
        }
    ],
    "sg:phone":"+1 317 887 1060",
    "sg:postcode":"46237",
    "sg:province":"IN",
    "sg:tags":[
        "physician",
        "surgeon"
    ],
    "wof:name":"Southeast Family Physicians",
    "wof:placetype":"venue"
},
  "geometry": {"coordinates":[-86.078058,39.651318],"type":"Point"}
}