{
  "type": "Feature",
  "properties": {
    "iso:country":"US",
    "sg:address":"203 S Eastern Ave",
    "sg:city":"Connersville",
    "sg:classifiers":[
        {
            "category":"Manufacturing",
            "subcategory":"Tools & Machinery",
            "type":"Manufacturing & Wholesale Goods"
        }
    ],
    "sg:phone":"+1 765 827 9757",
    "sg:postcode":"47331",
    "sg:province":"IN",
    "sg:tags":[
        "die",
        "maker"
    ],
    "wof:name":"S & L Machine Tool & Die Inc",
    "wof:placetype":"venue"
},
  "geometry": {"coordinates":[-85.142606,39.634731],"type":"Point"}
}