{
  "type": "Feature",
  "properties": {
    "iso:country":"US",
    "sg:address":"4468 E Shore Dr",
    "sg:city":"Bremen",
    "sg:classifiers":[
        {
            "category":"Organizations",
            "subcategory":"Religious Organization",
            "type":"Services"
        }
    ],
    "sg:phone":"+1 574 546 3747",
    "sg:postcode":"46506",
    "sg:province":"IN",
    "wof:name":"Jose Cavazos",
    "wof:placetype":"venue"
},
  "geometry": {"coordinates":[-86.221316,41.414064],"type":"Point"}
}