{
  "type": "Feature",
  "properties": {
    "addr:full":"201 W Main St Vevay IN 47043",
    "addr:housenumber":"201",
    "addr:postcode":"47043",
    "addr:street":"W Main St",
    "iso:country":"US",
    "sg:address":"201 W Main St",
    "sg:city":"Vevay",
    "sg:classifiers":[
        {
            "category":"Personal",
            "subcategory":"Beauty Salon",
            "type":"Services"
        }
    ],
    "sg:phone":"+1 812 427 9080",
    "sg:postcode":"47043",
    "sg:province":"IN",
    "wof:name":"Twisted Ends",
    "wof:placetype":"venue"
},
  "geometry": {"coordinates":[-85.06806400000001,38.747037],"type":"Point"}
}