{
  "type": "Feature",
  "properties": {
    "iso:country":"US",
    "sg:address":"621 Granada Dr",
    "sg:city":"Kendallville",
    "sg:classifiers":[
        {
            "category":"Wholesale",
            "subcategory":"Durable Goods & Equipment",
            "type":"Manufacturing & Wholesale Goods"
        }
    ],
    "sg:phone":"+1 260 349 1077",
    "sg:postcode":"46755",
    "sg:province":"IN",
    "wof:name":"James T Lemon Ltd",
    "wof:placetype":"venue"
},
  "geometry": {"coordinates":[-85.228306,41.450233],"type":"Point"}
}