{
  "type": "Feature",
  "properties": {
    "iso:country":"US",
    "sg:address":"2135 W Whiskey Run Rd NW",
    "sg:city":"Ramsey",
    "sg:classifiers":[
        {
            "category":"Building & Trades",
            "subcategory":"Construction",
            "type":"Services"
        }
    ],
    "sg:phone":"+1 812 347 1344",
    "sg:postcode":"47166",
    "sg:province":"IN",
    "sg:tags":[
        "downspouts",
        "gutter"
    ],
    "wof:name":"Reliable Gutter Svc",
    "wof:placetype":"venue"
},
  "geometry": {"coordinates":[-86.164411,38.325981],"type":"Point"}
}