{
  "type": "Feature",
  "properties": {
    "addr:full":"2920 N Arlington Ave Indianapolis IN 46218",
    "addr:housenumber":"2920",
    "addr:postcode":"46218",
    "addr:street":"N Arlington Ave",
    "iso:country":"US",
    "sg:address":"2920 N Arlington Ave",
    "sg:city":"Indianapolis",
    "sg:classifiers":[
        {
            "category":"Health Services",
            "subcategory":"Doctor",
            "type":"Services"
        }
    ],
    "sg:phone":"+1 317 355 9431",
    "sg:postcode":"46218",
    "sg:province":"IN",
    "sg:tags":[
        "physician",
        "surgeon"
    ],
    "wof:name":"Eastside Medical Ctr",
    "wof:placetype":"venue"
},
  "geometry": {"coordinates":[-86.06472100000001,39.810094],"type":"Point"}
}