{
  "type": "Feature",
  "properties": {
    "iso:country":"US",
    "sg:address":"209 Prairie St",
    "sg:city":"Rolling Prairie",
    "sg:classifiers":[
        {
            "category":"Home & Garden",
            "subcategory":"Building Materials",
            "type":"Retail Goods"
        }
    ],
    "sg:phone":"+1 219 778 2511",
    "sg:postcode":"46371",
    "sg:province":"IN",
    "wof:name":"Wheatbrook Do It Best Home Ctr",
    "wof:placetype":"venue"
},
  "geometry": {"coordinates":[-86.614095,41.672721],"type":"Point"}
}