{
  "type": "Feature",
  "properties": {
    "addr:full":"104 N Sale St Ellettsville IN 47429",
    "addr:housenumber":"104",
    "addr:postcode":"47429",
    "addr:street":"N Sale St",
    "iso:country":"US",
    "sg:address":"104 N Sale St",
    "sg:city":"Ellettsville",
    "sg:classifiers":[
        {
            "category":"Government",
            "subcategory":"Post Office",
            "type":"Public Place"
        }
    ],
    "sg:phone":"+1 812 876 5435",
    "sg:postcode":"47429",
    "sg:province":"IN",
    "sg:website":"www.usps.com",
    "wof:name":"US Post Office",
    "wof:placetype":"venue"
},
  "geometry": {"coordinates":[-86.62460299999999,39.233675],"type":"Point"}
}