{
  "type": "Feature",
  "properties": {
    "iso:country":"US",
    "sg:address":"606 N Collins St",
    "sg:city":"Winslow",
    "sg:classifiers":[
        {
            "category":"Personal",
            "type":"Services"
        }
    ],
    "sg:phone":"+1 812 789 5229",
    "sg:postcode":"47598",
    "sg:province":"IN",
    "wof:name":"George L Bruce",
    "wof:placetype":"venue"
},
  "geometry": {"coordinates":[-87.206193,38.384842],"type":"Point"}
}