{
  "type": "Feature",
  "properties": {
    "iso:country":"US",
    "sg:address":"1104 N Meridian St",
    "sg:city":"Portland",
    "sg:classifiers":[
        {
            "category":"Autos & Motor Vehicles",
            "subcategory":"Automobile Sales",
            "type":"Retail Goods"
        }
    ],
    "sg:phone":"+1 260 726 9876",
    "sg:postcode":"47371",
    "sg:province":"IN",
    "sg:tags":[
        "car",
        "dealer"
    ],
    "wof:name":"Mr G's Auto",
    "wof:placetype":"venue"
},
  "geometry": {"coordinates":[-84.978205,40.444055],"type":"Point"}
}