{
  "type": "Feature",
  "properties": {
    "iso:country":"US",
    "sg:address":"1023 S Union St",
    "sg:city":"Kokomo",
    "sg:classifiers":[
        {
            "category":"Retail",
            "subcategory":"Animal Services",
            "type":"Services"
        }
    ],
    "sg:phone":"+1 765 452 8151",
    "sg:postcode":"46902",
    "sg:province":"IN",
    "wof:name":"Professional Pet Grooming",
    "wof:placetype":"venue"
},
  "geometry": {"coordinates":[-86.12983699999999,40.475105],"type":"Point"}
}