{
  "type": "Feature",
  "properties": {
    "addr:full":"716 Ridge Rd Ste 1 Munster IN 46321",
    "addr:housenumber":"716",
    "addr:postcode":"46321",
    "addr:street":"Ridge Rd Ste 1",
    "iso:country":"US",
    "sg:address":"716 Ridge Rd Ste 1",
    "sg:city":"Munster",
    "sg:classifiers":[
        {
            "category":"Food & Beverages",
            "subcategory":"Groceries & Convenience Stores",
            "type":"Retail Goods"
        }
    ],
    "sg:phone":"+1 219 836 7978",
    "sg:postcode":"46321",
    "sg:province":"IN",
    "sg:website":"www.savon.com",
    "wof:name":"Jewel Food Stores",
    "wof:placetype":"venue"
},
  "geometry": {"coordinates":[-87.51070900000001,41.561384],"type":"Point"}
}