{
  "type": "Feature",
  "properties": {
    "iso:country":"US",
    "sg:address":"129 W Court Ave",
    "sg:city":"Jeffersonville",
    "sg:classifiers":[
        {
            "category":"Professional",
            "type":"Services"
        }
    ],
    "sg:phone":"+1 812 282 3865",
    "sg:postcode":"47130",
    "sg:province":"IN",
    "sg:tags":[
        "establishment"
    ],
    "wof:name":"Gatherings",
    "wof:placetype":"venue"
},
  "geometry": {"coordinates":[-85.743066,38.273697],"type":"Point"}
}