{
  "type": "Feature",
  "properties": {
    "addr:full":"2511 E Market St Logansport IN 46947",
    "addr:housenumber":"2511",
    "addr:postcode":"46947",
    "addr:street":"E Market St",
    "iso:country":"US",
    "sg:address":"2511 E Market St",
    "sg:city":"Logansport",
    "sg:classifiers":[
        {
            "category":"Sports & Exercise",
            "subcategory":"Gym",
            "type":"Entertainment"
        }
    ],
    "sg:phone":"+1 574 739 2878",
    "sg:postcode":"46947",
    "sg:province":"IN",
    "sg:tags":[
        "club",
        "health",
        "studio",
        "gymnasium"
    ],
    "wof:name":"Curves For Women",
    "wof:placetype":"venue"
},
  "geometry": {"coordinates":[-86.334166,40.758166],"type":"Point"}
}