{
  "type": "Feature",
  "properties": {
    "addr:full":"13504 Parent Rd New Haven IN 46774",
    "addr:housenumber":"13504",
    "addr:postcode":"46774",
    "addr:street":"Parent Rd",
    "iso:country":"US",
    "sg:address":"13504 Parent Rd",
    "sg:city":"New Haven",
    "sg:classifiers":[
        {
            "category":"Building & Trades",
            "subcategory":"Construction",
            "type":"Services"
        }
    ],
    "sg:phone":"+1 260 493 7375",
    "sg:postcode":"46774",
    "sg:province":"IN",
    "sg:tags":[
        "masonry",
        "contractor"
    ],
    "wof:name":"M L Worthman Construction Inc",
    "wof:placetype":"venue"
},
  "geometry": {"coordinates":[-84.97506199999999,41.107448],"type":"Point"}
}