{
  "type": "Feature",
  "properties": {
    "addr:full":"1919 W 81st Ave Merrillville IN 46410",
    "addr:housenumber":"1919",
    "addr:postcode":"46410",
    "addr:street":"W 81St Ave",
    "iso:country":"US",
    "sg:address":"1919 W 81st Ave",
    "sg:city":"Merrillville",
    "sg:classifiers":[
        {
            "category":"Education",
            "subcategory":"Library",
            "type":"Public Place"
        }
    ],
    "sg:phone":"+1 219 769 3541",
    "sg:postcode":"46410",
    "sg:province":"IN",
    "sg:website":"www.lakeco.lib.in.us",
    "wof:name":"Lake County Public Library",
    "wof:placetype":"venue"
},
  "geometry": {"coordinates":[-87.35746,41.471034],"type":"Point"}
}