{
  "type": "Feature",
  "properties": {
    "iso:country":"US",
    "sg:address":"11471 Harlequin Ln # 513",
    "sg:city":"Fishers",
    "sg:classifiers":[
        {
            "category":"Farming",
            "subcategory":"Poultry Farm",
            "type":"Manufacturing & Wholesale Goods"
        }
    ],
    "sg:phone":"+1 317 833 3171",
    "sg:postcode":"46038",
    "sg:province":"IN",
    "sg:tags":[
        "hatcheries-poultry"
    ],
    "wof:name":"Neal Davis Chick Fil A",
    "wof:placetype":"venue"
},
  "geometry": {"coordinates":[-86.045351,39.954818],"type":"Point"}
}