{
  "type": "Feature",
  "properties": {
    "iso:country":"US",
    "sg:address":"127 W Berry St",
    "sg:city":"Fort Wayne",
    "sg:classifiers":[
        {
            "category":"Real Estate",
            "subcategory":"Real Estate Agent",
            "type":"Services"
        }
    ],
    "sg:phone":"+1 260 467 1400",
    "sg:postcode":"46802",
    "sg:province":"IN",
    "wof:name":"Martin Realty Inc",
    "wof:placetype":"venue"
},
  "geometry": {"coordinates":[-85.140049,41.079148],"type":"Point"}
}