{
  "type": "Feature",
  "properties": {
    "addr:full":"415 W US Hwy 20 Michigan City IN 46360",
    "addr:housenumber":"415",
    "addr:postcode":"46360",
    "addr:street":"W Us Hwy 20",
    "iso:country":"US",
    "sg:address":"415 W US Hwy 20",
    "sg:city":"Michigan City",
    "sg:classifiers":[
        {
            "category":"Retail",
            "subcategory":"Auto Repair",
            "type":"Services"
        }
    ],
    "sg:phone":"+1 219 872 0671",
    "sg:postcode":"46360",
    "sg:province":"IN",
    "sg:tags":[
        "wrecker"
    ],
    "wof:name":"Music Towing & Auto Ctr",
    "wof:placetype":"venue"
},
  "geometry": {"coordinates":[-86.90018000000001,41.680459],"type":"Point"}
}