{
  "type": "Feature",
  "properties": {
    "iso:country":"US",
    "sg:address":"1605 S Bend Ave",
    "sg:city":"South Bend",
    "sg:classifiers":[
        {
            "category":"Banks & Credit Unions",
            "subcategory":"Investment Brokerage",
            "type":"Services"
        }
    ],
    "sg:phone":"+1 574 282 1432",
    "sg:postcode":"46617",
    "sg:province":"IN",
    "sg:tags":[
        "advisory",
        "financial"
    ],
    "wof:name":"Hogan Capital Management Group",
    "wof:placetype":"venue"
},
  "geometry": {"coordinates":[-86.224984,41.693645],"type":"Point"}
}