{
  "type": "Feature",
  "properties": {
    "iso:country":"US",
    "sg:address":"603 E Water St",
    "sg:city":"Paoli",
    "sg:classifiers":[
        {
            "category":"Organizations",
            "subcategory":"Community Association",
            "type":"Services"
        }
    ],
    "sg:phone":"+1 812 723 0637",
    "sg:postcode":"47454",
    "sg:province":"IN",
    "sg:tags":[
        "club"
    ],
    "wof:name":"Loyal Order Of Moose",
    "wof:placetype":"venue"
},
  "geometry": {"coordinates":[-86.462247,38.554979],"type":"Point"}
}