{
  "type": "Feature",
  "properties": {
    "iso:country":"US",
    "sg:address":"11845 Loughlin Dr",
    "sg:city":"Mishawaka",
    "sg:classifiers":[
        {
            "category":"Building & Trades",
            "subcategory":"Cleaning & Sanitation",
            "type":"Services"
        }
    ],
    "sg:phone":"+1 574 259 4325",
    "sg:postcode":"46545",
    "sg:province":"IN",
    "sg:tags":[
        "maintenance"
    ],
    "wof:name":"Astro Building Products",
    "wof:placetype":"venue"
},
  "geometry": {"coordinates":[-86.09905,41.684598],"type":"Point"}
}