{
  "type": "Feature",
  "properties": {
    "addr:full":"2302 S Geneva Ave Marion IN 46953",
    "addr:housenumber":"2302",
    "addr:postcode":"46953",
    "addr:street":"S Geneva Ave",
    "iso:country":"US",
    "sg:address":"2302 S Geneva Ave",
    "sg:city":"Marion",
    "sg:classifiers":[
        {
            "category":"Organizations",
            "subcategory":"Religious Organization",
            "type":"Services"
        }
    ],
    "sg:phone":"+1 765 662 1600",
    "sg:postcode":"46953",
    "sg:province":"IN",
    "wof:name":"Church of Brethren",
    "wof:placetype":"venue"
},
  "geometry": {"coordinates":[-85.68339400000001,40.539181],"type":"Point"}
}