{
  "type": "Feature",
  "properties": {
    "iso:country":"US",
    "sg:address":"3880 W Key St",
    "sg:city":"West Baden Spgs",
    "sg:classifiers":[
        {
            "category":"Mining & Drilling",
            "type":"Manufacturing & Wholesale Goods"
        }
    ],
    "sg:phone":"+1 812 723 4137",
    "sg:postcode":"47469",
    "sg:province":"IN",
    "sg:tags":[
        "quarry"
    ],
    "wof:name":"Mulzer Crushed Stone Inc",
    "wof:placetype":"venue"
},
  "geometry": {"coordinates":[-86.607716,38.569938],"type":"Point"}
}