{
  "type": "Feature",
  "properties": {
    "iso:country":"US",
    "sg:address":"17505 Co Rd 2",
    "sg:city":"Bristol",
    "sg:classifiers":[
        {
            "category":"Home & Garden",
            "subcategory":"Home Furnishings",
            "type":"Retail Goods"
        }
    ],
    "sg:phone":"+1 574 848 5927",
    "sg:postcode":"46507",
    "sg:province":"IN",
    "wof:name":"Mega Marketing",
    "wof:placetype":"venue"
},
  "geometry": {"coordinates":[-85.802368,41.754169],"type":"Point"}
}