{
  "type": "Feature",
  "properties": {
    "iso:country":"US",
    "sg:address":"7777 E Ridge Rd",
    "sg:city":"Hobart",
    "sg:classifiers":[
        {
            "category":"Health Services",
            "subcategory":"Doctor",
            "type":"Services"
        }
    ],
    "sg:phone":"+1 219 947 2922",
    "sg:postcode":"46342",
    "sg:province":"IN",
    "sg:tags":[
        "dentist"
    ],
    "wof:name":"Ridgewood Dental Ctr",
    "wof:placetype":"venue"
},
  "geometry": {"coordinates":[-87.244176,41.55064],"type":"Point"}
}