{
  "type": "Feature",
  "properties": {
    "iso:country":"US",
    "sg:address":"10800 Joliet St",
    "sg:city":"St John",
    "sg:classifiers":[
        {
            "category":"Building & Trades",
            "subcategory":"Construction",
            "type":"Services"
        }
    ],
    "sg:phone":"+1 219 365 5883",
    "sg:postcode":"46373",
    "sg:province":"IN",
    "sg:tags":[
        "tile",
        "dealer"
    ],
    "wof:name":"Floors & Kitchens LTD",
    "wof:placetype":"venue"
},
  "geometry": {"coordinates":[-87.467134,41.446017],"type":"Point"}
}