{
  "type": "Feature",
  "properties": {
    "iso:country":"US",
    "sg:address":"705 E Line St",
    "sg:city":"Geneva",
    "sg:classifiers":[
        {
            "category":"Organizations",
            "subcategory":"Religious Organization",
            "type":"Services"
        }
    ],
    "sg:phone":"+1 260 368 7343",
    "sg:postcode":"46740",
    "sg:province":"IN",
    "sg:tags":[
        "clergy"
    ],
    "wof:name":"Charles Akins",
    "wof:placetype":"venue"
},
  "geometry": {"coordinates":[-84.955265,40.592172],"type":"Point"}
}