{
  "type": "Feature",
  "properties": {
    "iso:country":"US",
    "sg:address":"3985 E Church St",
    "sg:city":"Hamilton",
    "sg:classifiers":[
        {
            "category":"Retail",
            "subcategory":"Funeral Services",
            "type":"Services"
        }
    ],
    "sg:phone":"+1 260 488 2164",
    "sg:postcode":"46742",
    "sg:province":"IN",
    "sg:tags":[
        "director"
    ],
    "wof:name":"Oberlin & Ford Funeral Home",
    "wof:placetype":"venue"
},
  "geometry": {"coordinates":[-84.913556,41.532546],"type":"Point"}
}