{
  "type": "Feature",
  "properties": {
    "iso:country":"US",
    "sg:address":"1443 119th St",
    "sg:city":"Whiting",
    "sg:classifiers":[
        {
            "category":"Government",
            "subcategory":"Office",
            "type":"Public Place"
        }
    ],
    "sg:phone":"+1 219 659 4688",
    "sg:postcode":"46394",
    "sg:province":"IN",
    "sg:tags":[
        "city",
        "village"
    ],
    "wof:name":"Whiting City Judge's Office",
    "wof:placetype":"venue"
},
  "geometry": {"coordinates":[-87.493286,41.679474],"type":"Point"}
}