{
  "type": "Feature",
  "properties": {
    "iso:country":"US",
    "sg:address":"1009 Central Ave",
    "sg:city":"Anderson",
    "sg:classifiers":[
        {
            "category":"Manufacturing",
            "subcategory":"Printing",
            "type":"Manufacturing & Wholesale Goods"
        }
    ],
    "sg:phone":"+1 765 642 9988",
    "sg:postcode":"46016",
    "sg:province":"IN",
    "sg:tags":[
        "commercial"
    ],
    "sg:website":"www.hudson-print.com",
    "wof:name":"Hudson Printing Co",
    "wof:placetype":"venue"
},
  "geometry": {"coordinates":[-85.676945,40.105193],"type":"Point"}
}