{
  "type": "Feature",
  "properties": {
    "addr:full":"3155 S State Rd 2 Valparaiso IN 46385",
    "addr:housenumber":"3155",
    "addr:postcode":"46385",
    "addr:street":"S State Rd 2",
    "iso:country":"US",
    "sg:address":"3155 S State Rd 2",
    "sg:city":"Valparaiso",
    "sg:classifiers":[
        {
            "category":"Banks & Credit Unions",
            "subcategory":"Investment Brokerage",
            "type":"Services"
        }
    ],
    "sg:phone":"+1 219 462 4225",
    "sg:postcode":"46385",
    "sg:province":"IN",
    "sg:tags":[
        "advisory"
    ],
    "wof:name":"James Bernard Inc",
    "wof:placetype":"venue"
},
  "geometry": {"coordinates":[-87.11007600000001,41.434605],"type":"Point"}
}