{
  "type": "Feature",
  "properties": {
    "iso:country":"US",
    "sg:address":"5758 N 900 W",
    "sg:city":"Thorntown",
    "sg:classifiers":[
        {
            "category":"Professional",
            "type":"Services"
        }
    ],
    "sg:phone":"+1 765 436 7716",
    "sg:postcode":"46071",
    "sg:province":"IN",
    "sg:tags":[
        "establishment"
    ],
    "wof:name":"Wagner & Wagner",
    "wof:placetype":"venue"
},
  "geometry": {"coordinates":[-86.637423,40.127483],"type":"Point"}
}