{
  "type": "Feature",
  "properties": {
    "iso:country":"US",
    "sg:address":"6912 N 800 W",
    "sg:city":"Delphi",
    "sg:classifiers":[
        {
            "category":"Manufacturing",
            "subcategory":"Tools & Machinery",
            "type":"Manufacturing & Wholesale Goods"
        }
    ],
    "sg:phone":"+1 574 965 4249",
    "sg:postcode":"46923",
    "sg:province":"IN",
    "sg:tags":[
        "farm",
        "mfg"
    ],
    "wof:name":"Jeff Craig Farms",
    "wof:placetype":"venue"
},
  "geometry": {"coordinates":[-86.678204,40.641254],"type":"Point"}
}