{
  "type": "Feature",
  "properties": {
    "iso:country":"US",
    "sg:address":"7240 S 125 E",
    "sg:city":"North Judson",
    "sg:classifiers":[
        {
            "category":"Organizations",
            "subcategory":"Religious Organization",
            "type":"Services"
        }
    ],
    "sg:phone":"+1 574 896 2927",
    "sg:postcode":"46366",
    "sg:province":"IN",
    "sg:tags":[
        "church"
    ],
    "wof:name":"United Baptist Church-Aldine",
    "wof:placetype":"venue"
},
  "geometry": {"coordinates":[-86.6741,41.197524],"type":"Point"}
}