{
  "type": "Feature",
  "properties": {
    "iso:country":"US",
    "sg:address":"719 W Main St",
    "sg:city":"Madison",
    "sg:classifiers":[
        {
            "category":"Shopping",
            "subcategory":"Clothing, Apparel, & Fashions",
            "type":"Retail Goods"
        }
    ],
    "sg:phone":"+1 812 265 5987",
    "sg:postcode":"47250",
    "sg:province":"IN",
    "wof:name":"Button Hole",
    "wof:placetype":"venue"
},
  "geometry": {"coordinates":[-85.388068,38.737685],"type":"Point"}
}