{
  "type": "Feature",
  "properties": {
    "addr:full":"849 Whitaker Rd Plainfield IN 46168",
    "addr:housenumber":"849",
    "addr:postcode":"46168",
    "addr:street":"Whitaker Rd",
    "iso:country":"US",
    "sg:address":"849 Whitaker Rd",
    "sg:city":"Plainfield",
    "sg:classifiers":[
        {
            "category":"Professional",
            "type":"Services"
        }
    ],
    "sg:phone":"+1 317 839 9525",
    "sg:postcode":"46168",
    "sg:province":"IN",
    "sg:tags":[
        "establishment"
    ],
    "wof:name":"Quality Reman Inc",
    "wof:placetype":"venue"
},
  "geometry": {"coordinates":[-86.349071,39.696376],"type":"Point"}
}