{
  "type": "Feature",
  "properties": {
    "iso:country":"US",
    "sg:address":"8103 Clearvista Pkwy",
    "sg:city":"Indianapolis",
    "sg:classifiers":[
        {
            "category":"Health Services",
            "subcategory":"Doctor",
            "type":"Services"
        }
    ],
    "sg:phone":"+1 317 842 6300",
    "sg:postcode":"46256",
    "sg:province":"IN",
    "sg:tags":[
        "physician",
        "surgeon"
    ],
    "wof:name":"Eye Institute Of Indiana",
    "wof:placetype":"venue"
},
  "geometry": {"coordinates":[-86.039226,39.902946],"type":"Point"}
}