{
  "type": "Feature",
  "properties": {
    "iso:country":"US",
    "sg:address":"6593 Manchester Dr",
    "sg:city":"Fishers",
    "sg:classifiers":[
        {
            "category":"Professional",
            "subcategory":"Computer Services",
            "type":"Services"
        }
    ],
    "sg:phone":"+1 317 841 8377",
    "sg:postcode":"46038",
    "sg:province":"IN",
    "sg:tags":[
        "web",
        "multimedia",
        "design"
    ],
    "wof:name":"Terrapin Interactive Inc",
    "wof:placetype":"venue"
},
  "geometry": {"coordinates":[-86.054202,39.945503],"type":"Point"}
}