{
  "type": "Feature",
  "properties": {
    "iso:country":"US",
    "sg:address":"861 N Green River Rd",
    "sg:city":"Evansville",
    "sg:classifiers":[
        {
            "category":"Shopping",
            "subcategory":"Used Merchandise",
            "type":"Retail Goods"
        }
    ],
    "sg:phone":"+1 812 477 5165",
    "sg:postcode":"47715",
    "sg:province":"IN",
    "sg:tags":[
        "infant",
        "wear"
    ],
    "wof:name":"Once Upon A Child",
    "wof:placetype":"venue"
},
  "geometry": {"coordinates":[-87.492604,37.984164],"type":"Point"}
}