{
  "type": "Feature",
  "properties": {
    "iso:country":"US",
    "sg:address":"2301 E 38th St",
    "sg:city":"Indianapolis",
    "sg:classifiers":[
        {
            "category":"Retail",
            "subcategory":"Repair Shop",
            "type":"Services"
        }
    ],
    "sg:phone":"+1 317 924 0738",
    "sg:postcode":"46218",
    "sg:province":"IN",
    "sg:tags":[
        "related"
    ],
    "wof:name":"Techno Auto",
    "wof:placetype":"venue"
},
  "geometry": {"coordinates":[-86.121719,39.825327],"type":"Point"}
}