{
  "type": "Feature",
  "properties": {
    "addr:full":"514 E Dustman Rd Bluffton IN 46714",
    "addr:housenumber":"514",
    "addr:postcode":"46714",
    "addr:street":"E Dustman Rd",
    "iso:country":"US",
    "sg:address":"514 E Dustman Rd",
    "sg:city":"Bluffton",
    "sg:classifiers":[
        {
            "category":"Wholesale",
            "subcategory":"Non-durable Goods",
            "type":"Manufacturing & Wholesale Goods"
        }
    ],
    "sg:phone":"+1 260 824 3297",
    "sg:postcode":"46714",
    "sg:province":"IN",
    "wof:name":"Dbs First Aid Inc",
    "wof:placetype":"venue"
},
  "geometry": {"coordinates":[-85.163625,40.756986],"type":"Point"}
}