{
  "type": "Feature",
  "properties": {
    "iso:country":"US",
    "sg:address":"1555 Hwy 64 NE",
    "sg:city":"New Salisbury",
    "sg:classifiers":[
        {
            "category":"Food & Beverages",
            "subcategory":"Groceries & Convenience Stores",
            "type":"Retail Goods"
        }
    ],
    "sg:phone":"+1 812 347 3031",
    "sg:postcode":"47161",
    "sg:province":"IN",
    "wof:name":"Bullock Oil Co",
    "wof:placetype":"venue"
},
  "geometry": {"coordinates":[-86.096205,38.316539],"type":"Point"}
}