{
  "type": "Feature",
  "properties": {
    "iso:country":"US",
    "sg:address":"300 S Guilford Rd",
    "sg:city":"Carmel",
    "sg:classifiers":[
        {
            "category":"Building & Trades",
            "subcategory":"Construction",
            "type":"Services"
        }
    ],
    "sg:phone":"+1 317 574 1697",
    "sg:postcode":"46032",
    "sg:province":"IN",
    "sg:tags":[
        "general",
        "contractor"
    ],
    "wof:name":"Ziolkowski Construction Inc",
    "wof:placetype":"venue"
},
  "geometry": {"coordinates":[-86.141136,39.975491],"type":"Point"}
}