{
  "type": "Feature",
  "properties": {
    "iso:country":"US",
    "sg:address":"108 E Washington St",
    "sg:city":"Muncie",
    "sg:classifiers":[
        {
            "category":"Building & Trades",
            "subcategory":"Construction",
            "type":"Services"
        }
    ],
    "sg:phone":"+1 765 282 4840",
    "sg:postcode":"47305",
    "sg:province":"IN",
    "sg:tags":[
        "contractor"
    ],
    "wof:name":"Built On A Foundation",
    "wof:placetype":"venue"
},
  "geometry": {"coordinates":[-85.385436,40.194607],"type":"Point"}
}