{
  "type": "Feature",
  "properties": {
    "iso:country":"US",
    "sg:address":"101 Washington St",
    "sg:city":"Elizabethtown",
    "sg:classifiers":[
        {
            "category":"Organizations",
            "subcategory":"Religious Organization",
            "type":"Services"
        }
    ],
    "sg:phone":"+1 812 579 6367",
    "sg:postcode":"47232",
    "sg:province":"IN",
    "sg:tags":[
        "church"
    ],
    "wof:name":"Cornerstone Baptist Church",
    "wof:placetype":"venue"
},
  "geometry": {"coordinates":[-85.81016,39.137588],"type":"Point"}
}