{
  "type": "Feature",
  "properties": {
    "iso:country":"US",
    "sg:address":"112 S Elkhart St",
    "sg:city":"Wakarusa",
    "sg:classifiers":[
        {
            "category":"Food & Beverages",
            "subcategory":"Specialty",
            "type":"Retail Goods"
        }
    ],
    "sg:phone":"+1 574 862 4774",
    "sg:postcode":"46573",
    "sg:province":"IN",
    "sg:tags":[
        "herb"
    ],
    "wof:name":"Herb Market",
    "wof:placetype":"venue"
},
  "geometry": {"coordinates":[-86.021027,41.535228],"type":"Point"}
}