{
  "type": "Feature",
  "properties": {
    "iso:country":"US",
    "sg:address":"420 Oberting Rd",
    "sg:city":"Lawrenceburg",
    "sg:classifiers":[
        {
            "category":"Building & Trades",
            "subcategory":"Construction",
            "type":"Services"
        }
    ],
    "sg:phone":"+1 812 537 2875",
    "sg:postcode":"47025",
    "sg:province":"IN",
    "sg:tags":[
        "hanging",
        "contractor"
    ],
    "wof:name":"Pat Stanton & Associates",
    "wof:placetype":"venue"
},
  "geometry": {"coordinates":[-84.827892,39.144453],"type":"Point"}
}