{
  "type": "Feature",
  "properties": {
    "iso:country":"US",
    "sg:address":"745 W US Hwy 30",
    "sg:city":"Valparaiso",
    "sg:classifiers":[
        {
            "category":"Home & Garden",
            "subcategory":"Garden Supply",
            "type":"Retail Goods"
        }
    ],
    "sg:phone":"+1 219 759 2688",
    "sg:postcode":"46385",
    "sg:province":"IN",
    "sg:tags":[
        "lawn",
        "mower"
    ],
    "wof:name":"Burke's Lawn & Garden Equip",
    "wof:placetype":"venue"
},
  "geometry": {"coordinates":[-87.208977,41.471001],"type":"Point"}
}