{
  "type": "Feature",
  "properties": {
    "addr:full":"3807 Main St East Chicago IN 46312",
    "addr:housenumber":"3807",
    "addr:postcode":"46312",
    "addr:street":"Main St",
    "iso:country":"US",
    "sg:address":"3807 Main St",
    "sg:city":"East Chicago",
    "sg:classifiers":[
        {
            "category":"Education",
            "subcategory":"Vocational School",
            "type":"Public Place"
        }
    ],
    "sg:phone":"+1 219 397 1566",
    "sg:postcode":"46312",
    "sg:province":"IN",
    "sg:tags":[
        "training",
        "computer"
    ],
    "wof:name":"Maxwell Street On Main",
    "wof:placetype":"venue"
},
  "geometry": {"coordinates":[-87.444869,41.642671],"type":"Point"}
}