{
  "type": "Feature",
  "properties": {
    "addr:full":"221 W Washington St Fairmount IN 46928",
    "addr:housenumber":"221",
    "addr:postcode":"46928",
    "addr:street":"W Washington St",
    "iso:country":"US",
    "sg:address":"221 W Washington St",
    "sg:city":"Fairmount",
    "sg:classifiers":[
        {
            "category":"Utilities",
            "subcategory":"Telephone",
            "type":"Services"
        }
    ],
    "sg:phone":"+1 765 948 4115",
    "sg:postcode":"46928",
    "sg:province":"IN",
    "sg:tags":[
        "company"
    ],
    "wof:name":"Frontier Communications",
    "wof:placetype":"venue"
},
  "geometry": {"coordinates":[-85.652006,40.415517],"type":"Point"}
}