{
  "type": "Feature",
  "properties": {
    "iso:country":"US",
    "sg:address":"8 W Van Trees St",
    "sg:city":"Washington",
    "sg:classifiers":[
        {
            "category":"Building & Trades",
            "subcategory":"Construction",
            "type":"Services"
        }
    ],
    "sg:phone":"+1 812 254 2674",
    "sg:postcode":"47501",
    "sg:province":"IN",
    "sg:tags":[
        "carpentry",
        "contractor"
    ],
    "wof:name":"Schlotter Cabinets",
    "wof:placetype":"venue"
},
  "geometry": {"coordinates":[-87.17554800000001,38.657809],"type":"Point"}
}