{
  "type": "Feature",
  "properties": {
    "iso:country":"US",
    "sg:address":"4146 Kerry Dr",
    "sg:city":"Indianapolis",
    "sg:classifiers":[
        {
            "category":"Manufacturing",
            "subcategory":"Metals",
            "type":"Manufacturing & Wholesale Goods"
        }
    ],
    "sg:phone":"+1 317 862 9209",
    "sg:postcode":"46239",
    "sg:province":"IN",
    "sg:tags":[
        "tool",
        "mfg"
    ],
    "wof:name":"Snap-On Tools",
    "wof:placetype":"venue"
},
  "geometry": {"coordinates":[-86.02151000000001,39.708088],"type":"Point"}
}