{
  "type": "Feature",
  "properties": {
    "iso:country":"US",
    "sg:address":"3219 E Evans Ave",
    "sg:city":"Terre Haute",
    "sg:classifiers":[
        {
            "category":"Organizations",
            "subcategory":"Religious Organization",
            "type":"Services"
        }
    ],
    "sg:phone":"+1 812 460 4556",
    "sg:postcode":"47805",
    "sg:province":"IN",
    "sg:tags":[
        "church"
    ],
    "wof:name":"Terre Haute Bible Ctr",
    "wof:placetype":"venue"
},
  "geometry": {"coordinates":[-87.360255,39.571535],"type":"Point"}
}