{
  "type": "Feature",
  "properties": {
    "iso:country":"US",
    "sg:address":"6430 Highland Ln",
    "sg:city":"Mc Cordsville",
    "sg:phone":"+1 317 335 2995",
    "sg:postcode":"46055",
    "sg:province":"IN",
    "sg:tags":[
        "farm",
        "corn",
        "soybean"
    ],
    "wof:name":"Watt John",
    "wof:placetype":"venue"
},
  "geometry": {"coordinates":[-85.926316,39.921099],"type":"Point"}
}