{
  "type": "Feature",
  "properties": {
    "addr:full":"2201 Benham Ave Elkhart IN 46517",
    "addr:housenumber":"2201",
    "addr:postcode":"46517",
    "addr:street":"Benham Ave",
    "iso:country":"US",
    "sg:address":"2201 Benham Ave",
    "sg:city":"Elkhart",
    "sg:classifiers":[
        {
            "category":"Organizations",
            "subcategory":"Religious Organization",
            "type":"Services"
        }
    ],
    "sg:phone":"+1 574 522 6257",
    "sg:postcode":"46517",
    "sg:province":"IN",
    "sg:tags":[
        "church"
    ],
    "wof:name":"Ministerios Casa De Msrcrd",
    "wof:placetype":"venue"
},
  "geometry": {"coordinates":[-85.970201,41.663555],"type":"Point"}
}