{
  "type": "Feature",
  "properties": {
    "iso:country":"US",
    "sg:address":"1549 S Grove Ave",
    "sg:city":"Warsaw",
    "sg:classifiers":[
        {
            "category":"Professional",
            "subcategory":"Computer Services",
            "type":"Services"
        }
    ],
    "sg:phone":"+1 574 267 2297",
    "sg:postcode":"46580",
    "sg:province":"IN",
    "wof:name":"Universal Computer Software",
    "wof:placetype":"venue"
},
  "geometry": {"coordinates":[-85.882235,41.210911],"type":"Point"}
}