{
  "type": "Feature",
  "properties": {
    "iso:country":"US",
    "sg:address":"3434 Mc Carty Ln",
    "sg:city":"Lafayette",
    "sg:classifiers":[
        {
            "category":"Manufacturing",
            "subcategory":"Retail Goods",
            "type":"Manufacturing & Wholesale Goods"
        }
    ],
    "sg:phone":"+1 765 447 4423",
    "sg:postcode":"47905",
    "sg:province":"IN",
    "sg:tags":[
        "manufacturer"
    ],
    "wof:name":"Wadake Inc",
    "wof:placetype":"venue"
},
  "geometry": {"coordinates":[-86.84535700000001,40.403005],"type":"Point"}
}