{
  "type": "Feature",
  "properties": {
    "iso:country":"US",
    "sg:address":"418 Kentucky Dr",
    "sg:city":"Kokomo",
    "sg:classifiers":[
        {
            "category":"Retail",
            "subcategory":"Auto Repair",
            "type":"Services"
        }
    ],
    "sg:phone":"+1 765 453 7181",
    "sg:postcode":"46902",
    "sg:province":"IN",
    "sg:tags":[
        "body",
        "automobile",
        "painting"
    ],
    "wof:name":"Collison Cure Kokomo Inc",
    "wof:placetype":"venue"
},
  "geometry": {"coordinates":[-86.126273,40.43509],"type":"Point"}
}