{
  "type": "Feature",
  "properties": {
    "addr:full":"3232 Michigan St Hobart IN 46342",
    "addr:housenumber":"3232",
    "addr:postcode":"46342",
    "addr:street":"Michigan St",
    "iso:country":"US",
    "sg:address":"3232 Michigan St",
    "sg:city":"Hobart",
    "sg:classifiers":[
        {
            "category":"Food & Beverages",
            "subcategory":"Groceries & Convenience Stores",
            "type":"Retail Goods"
        }
    ],
    "sg:phone":"+1 219 962 2880",
    "sg:postcode":"46342",
    "sg:province":"IN",
    "wof:name":"Dari Maid",
    "wof:placetype":"venue"
},
  "geometry": {"coordinates":[-87.274725,41.558254],"type":"Point"}
}