{
  "type": "Feature",
  "properties": {
    "iso:country":"US",
    "sg:address":"2916 Grant Line Rd",
    "sg:city":"New Albany",
    "sg:classifiers":[
        {
            "category":"Shopping",
            "subcategory":"Shoes",
            "type":"Retail Goods"
        }
    ],
    "sg:phone":"+1 812 949 2621",
    "sg:postcode":"47150",
    "sg:province":"IN",
    "wof:name":"Payless Shoe Source",
    "wof:placetype":"venue"
},
  "geometry": {"coordinates":[-85.82064699999999,38.315909],"type":"Point"}
}