{
  "type": "Feature",
  "properties": {
    "iso:country":"US",
    "sg:address":"202 E Main St",
    "sg:city":"Westport",
    "sg:classifiers":[
        {
            "category":"Organizations",
            "subcategory":"Religious Organization",
            "type":"Services"
        }
    ],
    "sg:phone":"+1 812 591 3721",
    "sg:postcode":"47283",
    "sg:province":"IN",
    "sg:tags":[
        "church"
    ],
    "wof:name":"Westport Baptist Church",
    "wof:placetype":"venue"
},
  "geometry": {"coordinates":[-85.573593,39.175958],"type":"Point"}
}