{
  "type": "Feature",
  "properties": {
    "addr:full":"726 S Calumet Rd Chesterton IN 46304",
    "addr:housenumber":"726",
    "addr:postcode":"46304",
    "addr:street":"S Calumet Rd",
    "iso:country":"US",
    "sg:address":"726 S Calumet Rd",
    "sg:city":"Chesterton",
    "sg:classifiers":[
        {
            "category":"Shopping",
            "subcategory":"Florist",
            "type":"Retail Goods"
        }
    ],
    "sg:phone":"+1 219 926 7641",
    "sg:postcode":"46304",
    "sg:province":"IN",
    "wof:name":"Shady Lawn Florists",
    "wof:placetype":"venue"
},
  "geometry": {"coordinates":[-87.051492,41.604208],"type":"Point"}
}