{
  "type": "Feature",
  "properties": {
    "iso:country":"US",
    "sg:address":"5666 Autumn Ridge Dr",
    "sg:city":"Newburgh",
    "sg:classifiers":[
        {
            "category":"Professional",
            "subcategory":"Business Services",
            "type":"Services"
        }
    ],
    "sg:phone":"+1 812 842 0549",
    "sg:postcode":"47630",
    "sg:province":"IN",
    "wof:name":"V/V Miller Family Partners",
    "wof:placetype":"venue"
},
  "geometry": {"coordinates":[-87.389989,37.951863],"type":"Point"}
}