{
  "type": "Feature",
  "properties": {
    "iso:country":"US",
    "sg:address":"28967 US Hwy 33",
    "sg:city":"Elkhart",
    "sg:classifiers":[
        {
            "category":"Manufacturing",
            "subcategory":"Motor Vehicles & Parts",
            "type":"Manufacturing & Wholesale Goods"
        }
    ],
    "sg:phone":"+1 574 294 7681",
    "sg:postcode":"46516",
    "sg:province":"IN",
    "sg:tags":[
        "automobile",
        "supply"
    ],
    "wof:name":"Global Molding Technologies",
    "wof:placetype":"venue"
},
  "geometry": {"coordinates":[-86.014579,41.668784],"type":"Point"}
}