{
  "type": "Feature",
  "properties": {
    "addr:full":"2810 Beaver Ave Fort Wayne IN 46807",
    "addr:housenumber":"2810",
    "addr:postcode":"46807",
    "addr:street":"Beaver Ave",
    "iso:country":"US",
    "sg:address":"2810 Beaver Ave",
    "sg:city":"Fort Wayne",
    "sg:classifiers":[
        {
            "category":"Professional",
            "subcategory":"Lawyer & Legal Services",
            "type":"Services"
        }
    ],
    "sg:phone":"+1 260 745 1970",
    "sg:postcode":"46807",
    "sg:province":"IN",
    "sg:tags":[
        "attorney"
    ],
    "wof:name":"Shine & Hardin",
    "wof:placetype":"venue"
},
  "geometry": {"coordinates":[-85.152331,41.05966],"type":"Point"}
}