{
  "type": "Feature",
  "properties": {
    "iso:country":"US",
    "sg:address":"3635 S Bainbridge Dr",
    "sg:city":"Bloomington",
    "sg:classifiers":[
        {
            "category":"Professional",
            "subcategory":"Accounting & Tax Preparation",
            "type":"Services"
        }
    ],
    "sg:phone":"+1 812 333 6940",
    "sg:postcode":"47401",
    "sg:province":"IN",
    "sg:tags":[
        "accountant"
    ],
    "wof:name":"G R Dvorak CPA",
    "wof:placetype":"venue"
},
  "geometry": {"coordinates":[-86.519465,39.129692],"type":"Point"}
}