{
  "type": "Feature",
  "properties": {
    "iso:country":"US",
    "sg:address":"940 W 16th St",
    "sg:city":"Indianapolis",
    "sg:classifiers":[
        {
            "category":"Wholesale",
            "subcategory":"Auto Parts",
            "type":"Manufacturing & Wholesale Goods"
        }
    ],
    "sg:phone":"+1 317 926 5381",
    "sg:postcode":"46202",
    "sg:province":"IN",
    "sg:tags":[
        "dealers-used",
        "automobile",
        "rebuilt",
        "cars-wholesale"
    ],
    "wof:name":"Michigan Auto & Parts Co",
    "wof:placetype":"venue"
},
  "geometry": {"coordinates":[-86.177677,39.788714],"type":"Point"}
}