{
  "type": "Feature",
  "properties": {
    "addr:full":"3417 W Sample St South Bend IN 46619",
    "addr:housenumber":"3417",
    "addr:postcode":"46619",
    "addr:street":"W Sample St",
    "iso:country":"US",
    "sg:address":"3417 W Sample St",
    "sg:city":"South Bend",
    "sg:classifiers":[
        {
            "category":"Autos & Motor Vehicles",
            "subcategory":"Automobile Sales",
            "type":"Retail Goods"
        }
    ],
    "sg:phone":"+1 574 288 2842",
    "sg:postcode":"46619",
    "sg:province":"IN",
    "sg:tags":[
        "car",
        "dealer"
    ],
    "wof:name":"M & S Auto Sales",
    "wof:placetype":"venue"
},
  "geometry": {"coordinates":[-86.296954,41.66477],"type":"Point"}
}