{
  "type": "Feature",
  "properties": {
    "iso:country":"US",
    "sg:address":"113 S Main St",
    "sg:city":"Kirklin",
    "sg:classifiers":[
        {
            "category":"Shopping",
            "subcategory":"Used Merchandise",
            "type":"Retail Goods"
        }
    ],
    "sg:phone":"+1 765 279 5777",
    "sg:postcode":"46050",
    "sg:province":"IN",
    "sg:tags":[
        "antique"
    ],
    "wof:name":"White Lion Antiques",
    "wof:placetype":"venue"
},
  "geometry": {"coordinates":[-86.360013,40.19228],"type":"Point"}
}