{
  "type": "Feature",
  "properties": {
    "addr:full":"1008 S Adams St Versailles IN 47042",
    "addr:housenumber":"1008",
    "addr:postcode":"47042",
    "addr:street":"S Adams St",
    "iso:country":"US",
    "sg:address":"1008 S Adams St",
    "sg:city":"Versailles",
    "sg:classifiers":[
        {
            "category":"Shopping",
            "subcategory":"Department Store",
            "type":"Retail Goods"
        }
    ],
    "sg:phone":"+1 812 689 5351",
    "sg:postcode":"47042",
    "sg:province":"IN",
    "sg:tags":[
        "shop"
    ],
    "wof:name":"ALCO",
    "wof:placetype":"venue"
},
  "geometry": {"coordinates":[-85.25820299999999,39.056012],"type":"Point"}
}