{
  "type": "Feature",
  "properties": {
    "iso:country":"US",
    "sg:address":"95 S 1st St",
    "sg:city":"Zionsville",
    "sg:classifiers":[
        {
            "category":"Professional",
            "subcategory":"Advertising",
            "type":"Services"
        }
    ],
    "sg:phone":"+1 317 733 8500",
    "sg:postcode":"46077",
    "sg:province":"IN",
    "sg:tags":[
        "counselor"
    ],
    "wof:name":"Keyword Universe LLC",
    "wof:placetype":"venue"
},
  "geometry": {"coordinates":[-86.262413,39.951352],"type":"Point"}
}