{
  "type": "Feature",
  "properties": {
    "iso:country":"US",
    "sg:address":"529 Birch St",
    "sg:city":"Beech Grove",
    "sg:classifiers":[
        {
            "category":"Real Estate",
            "subcategory":"Real Estate Agent",
            "type":"Services"
        }
    ],
    "sg:phone":"+1 317 634 5447",
    "sg:postcode":"46107",
    "sg:province":"IN",
    "wof:name":"Re-New-It General Contractors",
    "wof:placetype":"venue"
},
  "geometry": {"coordinates":[-86.08857999999999,39.713099],"type":"Point"}
}