{
  "type": "Feature",
  "properties": {
    "iso:country":"US",
    "sg:address":"1310 W Maumee St",
    "sg:city":"Angola",
    "sg:classifiers":[
        {
            "category":"Wholesale",
            "subcategory":"Construction Materials",
            "type":"Manufacturing & Wholesale Goods"
        }
    ],
    "sg:phone":"+1 260 665 2052",
    "sg:postcode":"46703",
    "sg:province":"IN",
    "sg:tags":[
        "concrete",
        "product"
    ],
    "wof:name":"Aggregate Industries",
    "wof:placetype":"venue"
},
  "geometry": {"coordinates":[-85.018277,41.635121],"type":"Point"}
}