{
  "type": "Feature",
  "properties": {
    "addr:full":"433 S Jefferson St Huntington IN 46750",
    "addr:housenumber":"433",
    "addr:postcode":"46750",
    "addr:street":"S Jefferson",
    "iso:country":"US",
    "sg:address":"433 S Jefferson St",
    "sg:city":"Huntington",
    "sg:classifiers":[
        {
            "category":"Restaurant",
            "type":"Food & Drink"
        }
    ],
    "sg:phone":"+1 260 356 0090",
    "sg:postcode":"46750",
    "sg:province":"IN",
    "wof:name":"Hong Kong Chinese Restaurant",
    "wof:placetype":"venue"
},
  "geometry": {"coordinates":[-85.491598,40.877431],"type":"Point"}
}