{
  "type": "Feature",
  "properties": {
    "addr:full":"917 Madison St Gary IN 46402",
    "addr:housenumber":"917",
    "addr:postcode":"46402",
    "addr:street":"Madison St Gary",
    "iso:country":"US",
    "sg:address":"917 Madison St",
    "sg:city":"Gary",
    "sg:classifiers":[
        {
            "category":"Building & Trades",
            "subcategory":"Construction",
            "type":"Services"
        }
    ],
    "sg:phone":"+1 219 886 9239",
    "sg:postcode":"46402",
    "sg:province":"IN",
    "sg:tags":[
        "fire",
        "restoration",
        "damage"
    ],
    "wof:name":"Orbesen Construction Co",
    "wof:placetype":"venue"
},
  "geometry": {"coordinates":[-87.34165299999999,41.594638],"type":"Point"}
}