{
  "type": "Feature",
  "properties": {
    "iso:country":"US",
    "sg:address":"217 N 6th St",
    "sg:city":"Terre Haute",
    "sg:classifiers":[
        {
            "category":"Professional",
            "subcategory":"Business Services",
            "type":"Services"
        }
    ],
    "sg:phone":"+1 812 237 7610",
    "sg:postcode":"47842",
    "sg:province":"IN",
    "wof:name":"Indiana State University",
    "wof:placetype":"venue"
},
  "geometry": {"coordinates":[-87.403897,39.66202],"type":"Point"}
}