{
  "type": "Feature",
  "properties": {
    "iso:country":"US",
    "sg:address":"3125 Dandy Trl",
    "sg:city":"Indianapolis",
    "sg:classifiers":[
        {
            "category":"Organizations",
            "subcategory":"Non-profit Organization",
            "type":"Services"
        }
    ],
    "sg:phone":"+1 317 280 2635",
    "sg:postcode":"46214",
    "sg:province":"IN",
    "sg:tags":[
        "alternative",
        "abortion"
    ],
    "wof:name":"Crisis Pregnancy Ctr",
    "wof:placetype":"venue"
},
  "geometry": {"coordinates":[-86.306933,39.811963],"type":"Point"}
}