{
  "type": "Feature",
  "properties": {
    "iso:country":"US",
    "sg:address":"8227 Northwest Blvd",
    "sg:city":"Indianapolis",
    "sg:classifiers":[
        {
            "category":"Food & Beverages",
            "subcategory":"Bakery",
            "type":"Retail Goods"
        }
    ],
    "sg:phone":"+1 317 872 2660",
    "sg:postcode":"46278",
    "sg:province":"IN",
    "sg:tags":[
        "baker"
    ],
    "sg:website":"www.crawfordsbakery.com",
    "wof:name":"Crawford's Bakery & Deli",
    "wof:placetype":"venue"
},
  "geometry": {"coordinates":[-86.26724900000001,39.905574],"type":"Point"}
}