{
  "type": "Feature",
  "properties": {
    "iso:country":"US",
    "sg:address":"827 W Lincoln Ave",
    "sg:city":"Chandler",
    "sg:classifiers":[
        {
            "category":"Professional",
            "subcategory":"Business Services",
            "type":"Services"
        }
    ],
    "sg:phone":"+1 812 925 7153",
    "sg:postcode":"47610",
    "sg:province":"IN",
    "wof:name":"Wilmac Technology Services",
    "wof:placetype":"venue"
},
  "geometry": {"coordinates":[-87.38081699999999,38.037341],"type":"Point"}
}