{
  "type": "Feature",
  "properties": {
    "iso:country":"US",
    "sg:address":"803 S Bend Ave",
    "sg:city":"South Bend",
    "sg:classifiers":[
        {
            "category":"Professional",
            "type":"Services"
        }
    ],
    "sg:phone":"+1 574 235 9675",
    "sg:postcode":"46617",
    "sg:province":"IN",
    "sg:tags":[
        "establishment"
    ],
    "wof:name":"Northeast Neighborhood Ctr",
    "wof:placetype":"venue"
},
  "geometry": {"coordinates":[-86.239197,41.685065],"type":"Point"}
}