{
  "type": "Feature",
  "properties": {
    "iso:country":"US",
    "sg:address":"429 S Dunn St",
    "sg:city":"Bloomington",
    "sg:classifiers":[
        {
            "category":"Real Estate",
            "subcategory":"Real Estate Agent",
            "type":"Services"
        }
    ],
    "sg:phone":"+1 812 334 8419",
    "sg:postcode":"47401",
    "sg:province":"IN",
    "wof:name":"Coller Real Estate",
    "wof:placetype":"venue"
},
  "geometry": {"coordinates":[-86.528325,39.161771],"type":"Point"}
}