{
  "type": "Feature",
  "properties": {
    "addr:full":"1007 E Chicago Ave East Chicago IN 46312",
    "addr:housenumber":"1007",
    "addr:postcode":"46312",
    "addr:street":"E Chicago Ave",
    "iso:country":"US",
    "sg:address":"1007 E Chicago Ave",
    "sg:city":"East Chicago",
    "sg:classifiers":[
        {
            "category":"Wholesale",
            "subcategory":"Non-durable Goods",
            "type":"Manufacturing & Wholesale Goods"
        }
    ],
    "sg:phone":"+1 219 397 7335",
    "sg:postcode":"46312",
    "sg:province":"IN",
    "sg:tags":[
        "merchandise",
        "general"
    ],
    "wof:name":"T-Mar Sales",
    "wof:placetype":"venue"
},
  "geometry": {"coordinates":[-87.458113,41.629112],"type":"Point"}
}