{
  "type": "Feature",
  "properties": {
    "iso:country":"US",
    "sg:address":"11 Main St",
    "sg:city":"Plainville",
    "sg:classifiers":[
        {
            "category":"Wholesale",
            "subcategory":"Farm Supplies",
            "type":"Manufacturing & Wholesale Goods"
        }
    ],
    "sg:phone":"+1 812 687 7254",
    "sg:postcode":"47532",
    "sg:province":"IN",
    "sg:tags":[
        "grain"
    ],
    "wof:name":"Boyd Grain",
    "wof:placetype":"venue"
},
  "geometry": {"coordinates":[-86.864079,38.217151],"type":"Point"}
}