{
  "type": "Feature",
  "properties": {
    "addr:full":"201 W Cleveland St Alexandria IN 46001",
    "addr:housenumber":"201",
    "addr:postcode":"46001",
    "addr:street":"W Cleveland St",
    "iso:country":"US",
    "sg:address":"201 W Cleveland St",
    "sg:city":"Alexandria",
    "sg:classifiers":[
        {
            "category":"Professional",
            "subcategory":"Business Services",
            "type":"Services"
        }
    ],
    "sg:phone":"+1 765 724 1021",
    "sg:postcode":"46001",
    "sg:province":"IN",
    "wof:name":"Message Carrier Twlv Step Rec",
    "wof:placetype":"venue"
},
  "geometry": {"coordinates":[-85.675538,40.277751],"type":"Point"}
}