{
  "type": "Feature",
  "properties": {
    "iso:country":"US",
    "sg:address":"23 Superior St",
    "sg:city":"Orestes",
    "sg:classifiers":[
        {
            "category":"Manufacturing",
            "subcategory":"Signs",
            "type":"Manufacturing & Wholesale Goods"
        }
    ],
    "sg:phone":"+1 765 754 3129",
    "sg:postcode":"46063",
    "sg:province":"IN",
    "sg:website":"www.magneticsign.com",
    "wof:name":"Dick's Sign Shop",
    "wof:placetype":"venue"
},
  "geometry": {"coordinates":[-85.728206,40.271094],"type":"Point"}
}