{
  "type": "Feature",
  "properties": {
    "iso:country":"US",
    "sg:address":"1009 Broad Ripple Ave",
    "sg:city":"Indianapolis",
    "sg:classifiers":[
        {
            "category":"Professional",
            "subcategory":"Business Services",
            "type":"Services"
        }
    ],
    "sg:phone":"+1 317 251 8180",
    "sg:postcode":"46220",
    "sg:province":"IN",
    "sg:tags":[
        "mail",
        "messenger",
        "shipping"
    ],
    "wof:name":"Voice Mail Valu",
    "wof:placetype":"venue"
},
  "geometry": {"coordinates":[-86.140968,39.869719],"type":"Point"}
}