{
  "type": "Feature",
  "properties": {
    "iso:country":"US",
    "sg:address":"402 W Washington St W161",
    "sg:city":"Indianapolis",
    "sg:classifiers":[
        {
            "category":"Government",
            "subcategory":"Office",
            "type":"Public Place"
        }
    ],
    "sg:phone":"+1 317 232 4030",
    "sg:postcode":"46204",
    "sg:province":"IN",
    "wof:name":"Budget And Support Services",
    "wof:placetype":"venue"
},
  "geometry": {"coordinates":[-86.165288,39.767248],"type":"Point"}
}