{
  "type": "Feature",
  "properties": {
    "iso:country":"US",
    "sg:address":"1521 S Co Rd 75 W",
    "sg:city":"Danville",
    "sg:classifiers":[
        {
            "category":"Organizations",
            "subcategory":"Religious Organization",
            "type":"Services"
        }
    ],
    "sg:phone":"+1 317 745 2266",
    "sg:postcode":"46122",
    "sg:province":"IN",
    "sg:tags":[
        "church"
    ],
    "wof:name":"First Baptist Church-Danville",
    "wof:placetype":"venue"
},
  "geometry": {"coordinates":[-86.537626,39.738257],"type":"Point"}
}