{
  "type": "Feature",
  "properties": {
    "addr:full":"8824 N 750 E New Carlisle IN 46552",
    "addr:housenumber":"8824",
    "addr:postcode":"46552",
    "addr:street":"N 750 E",
    "iso:country":"US",
    "sg:address":"8824 N 750 E",
    "sg:city":"New Carlisle",
    "sg:classifiers":[
        {
            "category":"Building & Trades",
            "subcategory":"Landscaping Services",
            "type":"Services"
        }
    ],
    "sg:phone":"+1 574 298 6376",
    "sg:postcode":"46552",
    "sg:province":"IN",
    "wof:name":"Homestead Lawn & Landscaping",
    "wof:placetype":"venue"
},
  "geometry": {"coordinates":[-86.553543,41.737115],"type":"Point"}
}