{
  "type": "Feature",
  "properties": {
    "iso:country":"US",
    "sg:address":"500 Franklin St",
    "sg:city":"Columbus",
    "sg:classifiers":[
        {
            "category":"Government",
            "subcategory":"Office",
            "type":"Public Place"
        }
    ],
    "sg:phone":"+1 812 379 9766",
    "sg:postcode":"47201",
    "sg:province":"IN",
    "sg:tags":[
        "county"
    ],
    "sg:website":"www.leadershipbc.org",
    "wof:name":"Leadership Bartholomew County",
    "wof:placetype":"venue"
},
  "geometry": {"coordinates":[-85.919828,39.204115],"type":"Point"}
}