{
  "type": "Feature",
  "properties": {
    "iso:country":"US",
    "sg:address":"1025 S Walnut St",
    "sg:city":"Bloomington",
    "sg:classifiers":[
        {
            "category":"Personal",
            "subcategory":"Beauty Salon",
            "type":"Services"
        }
    ],
    "sg:phone":"+1 812 334 7651",
    "sg:postcode":"47401",
    "sg:province":"IN",
    "wof:name":"Shear Perfection",
    "wof:placetype":"venue"
},
  "geometry": {"coordinates":[-86.533631,39.154564],"type":"Point"}
}