{
  "type": "Feature",
  "properties": {
    "iso:country":"US",
    "sg:address":"328 E 200 N",
    "sg:city":"Rushville",
    "sg:classifiers":[
        {
            "category":"Wholesale",
            "subcategory":"Farm Supplies",
            "type":"Manufacturing & Wholesale Goods"
        }
    ],
    "sg:phone":"+1 765 932 4700",
    "sg:postcode":"46173",
    "sg:province":"IN",
    "sg:tags":[
        "equipment",
        "livestock"
    ],
    "wof:name":"Matney Agri-Products Corp",
    "wof:placetype":"venue"
},
  "geometry": {"coordinates":[-85.427295,39.64081],"type":"Point"}
}