{
  "type": "Feature",
  "properties": {
    "addr:full":"1958 Jefferson St Portage IN 46368",
    "addr:housenumber":"1958",
    "addr:postcode":"46368",
    "addr:street":"Jefferson St",
    "iso:country":"US",
    "sg:address":"1958 Jefferson St",
    "sg:city":"Portage",
    "sg:classifiers":[
        {
            "category":"Health Services",
            "subcategory":"Medical Lab",
            "type":"Services"
        }
    ],
    "sg:phone":"+1 219 763 3349",
    "sg:postcode":"46368",
    "sg:province":"IN",
    "sg:tags":[
        "laboratory",
        "dental"
    ],
    "wof:name":"Sosa Dental Labs LLC",
    "wof:placetype":"venue"
},
  "geometry": {"coordinates":[-87.156768,41.59595],"type":"Point"}
}