{
  "type": "Feature",
  "properties": {
    "iso:country":"US",
    "sg:address":"630 N College Ave",
    "sg:city":"Indianapolis",
    "sg:classifiers":[
        {
            "category":"Professional",
            "subcategory":"Art Services",
            "type":"Services"
        }
    ],
    "sg:phone":"+1 317 238 9497",
    "sg:postcode":"46204",
    "sg:province":"IN",
    "sg:tags":[
        "photography",
        "commercial"
    ],
    "wof:name":"Wayne Williams Photography",
    "wof:placetype":"venue"
},
  "geometry": {"coordinates":[-86.145385,39.775846],"type":"Point"}
}