{
  "type": "Feature",
  "properties": {
    "iso:country":"US",
    "sg:address":"5172 E 65th St",
    "sg:city":"Indianapolis",
    "sg:classifiers":[
        {
            "category":"Wholesale",
            "subcategory":"Durable Goods & Equipment",
            "type":"Manufacturing & Wholesale Goods"
        }
    ],
    "sg:phone":"+1 317 558 1595",
    "sg:postcode":"46220",
    "sg:province":"IN",
    "sg:tags":[
        "representative",
        "manufacturer"
    ],
    "wof:name":"Wagner Equipment",
    "wof:placetype":"venue"
},
  "geometry": {"coordinates":[-86.080798,39.876058],"type":"Point"}
}