{
  "type": "Feature",
  "properties": {
    "iso:country":"US",
    "sg:address":"5053 N US Hwy 31",
    "sg:city":"Columbus",
    "sg:classifiers":[
        {
            "category":"Organizations",
            "subcategory":"Religious Organization",
            "type":"Services"
        }
    ],
    "sg:phone":"+1 812 376 3726",
    "sg:postcode":"47201",
    "sg:province":"IN",
    "sg:tags":[
        "church"
    ],
    "wof:name":"Strong Tower Outreach Ministr",
    "wof:placetype":"venue"
},
  "geometry": {"coordinates":[-85.94216900000001,39.252353],"type":"Point"}
}