{
  "type": "Feature",
  "properties": {
    "iso:country":"US",
    "sg:address":"828 W Co Rd 950 N",
    "sg:city":"Springport",
    "sg:classifiers":[
        {
            "category":"Retail",
            "subcategory":"Portrait Studio",
            "type":"Services"
        }
    ],
    "sg:phone":"+1 765 755 9955",
    "sg:postcode":"47386",
    "sg:province":"IN",
    "sg:tags":[
        "photographer"
    ],
    "wof:name":"Jill Shafer Photography",
    "wof:placetype":"venue"
},
  "geometry": {"coordinates":[-85.400415,40.069227],"type":"Point"}
}