{
  "type": "Feature",
  "properties": {
    "iso:country":"US",
    "sg:address":"535 Green Blvd",
    "sg:city":"Aurora",
    "sg:classifiers":[
        {
            "category":"Insurance",
            "subcategory":"Insurance Agent",
            "type":"Services"
        }
    ],
    "sg:phone":"+1 812 926 1659",
    "sg:postcode":"47001",
    "sg:province":"IN",
    "wof:name":"Greg Stuart Insurance",
    "wof:placetype":"venue"
},
  "geometry": {"coordinates":[-84.897223,39.062772],"type":"Point"}
}