{
  "type": "Feature",
  "properties": {
    "iso:country":"US",
    "sg:address":"2855 Northpark Ave",
    "sg:city":"Huntington",
    "sg:classifiers":[
        {
            "category":"Professional",
            "subcategory":"Lawyer & Legal Services",
            "type":"Services"
        }
    ],
    "sg:phone":"+1 260 356 5066",
    "sg:postcode":"46750",
    "sg:province":"IN",
    "sg:tags":[
        "attorney"
    ],
    "wof:name":"Richard T Truitt",
    "wof:placetype":"venue"
},
  "geometry": {"coordinates":[-85.509294,40.901899],"type":"Point"}
}