{
  "type": "Feature",
  "properties": {
    "iso:country":"US",
    "sg:address":"205 W Main St",
    "sg:city":"Lizton",
    "sg:classifiers":[
        {
            "category":"Retail",
            "subcategory":"Auto Repair",
            "type":"Services"
        }
    ],
    "sg:phone":"+1 317 994 5255",
    "sg:postcode":"46149",
    "sg:province":"IN",
    "sg:tags":[
        "repairing",
        "engine"
    ],
    "wof:name":"Dons Small Engine Svc",
    "wof:placetype":"venue"
},
  "geometry": {"coordinates":[-86.518197,39.871147],"type":"Point"}
}