{
  "type": "Feature",
  "properties": {
    "iso:country":"US",
    "sg:address":"20 Bellefontaine St",
    "sg:city":"Beech Grove",
    "sg:classifiers":[
        {
            "category":"Wholesale",
            "subcategory":"Machinery & Supplies",
            "type":"Manufacturing & Wholesale Goods"
        }
    ],
    "sg:phone":"+1 317 787 0734",
    "sg:postcode":"46107",
    "sg:province":"IN",
    "sg:tags":[
        "car"
    ],
    "wof:name":"Washpro Carwash Systems Inc",
    "wof:placetype":"venue"
},
  "geometry": {"coordinates":[-86.0816,39.718202],"type":"Point"}
}