{
  "type": "Feature",
  "properties": {
    "addr:full":"6011 Grape Rd Mishawaka IN 46545",
    "addr:housenumber":"6011",
    "addr:postcode":"46545",
    "addr:street":"Grape Rd",
    "iso:country":"US",
    "sg:address":"6011 Grape Rd",
    "sg:city":"Mishawaka",
    "sg:classifiers":[
        {
            "category":"Shopping",
            "subcategory":"Hobbies, Toys, & Games",
            "type":"Retail Goods"
        }
    ],
    "sg:phone":"+1 574 277 4928",
    "sg:postcode":"46545",
    "sg:province":"IN",
    "wof:name":"Toys r US",
    "wof:placetype":"venue"
},
  "geometry": {"coordinates":[-86.18779000000001,41.71468],"type":"Point"}
}