{
  "type": "Feature",
  "properties": {
    "iso:country":"US",
    "sg:address":"621 S 7th St",
    "sg:city":"Vincennes",
    "sg:classifiers":[
        {
            "category":"Health Services",
            "subcategory":"Doctor",
            "type":"Services"
        }
    ],
    "sg:phone":"+1 812 886 6608",
    "sg:postcode":"47591",
    "sg:province":"IN",
    "sg:tags":[
        "physician",
        "surgeon"
    ],
    "wof:name":"Matick Neurology Clinic",
    "wof:placetype":"venue"
},
  "geometry": {"coordinates":[-87.534308,38.672661],"type":"Point"}
}