{
  "type": "Feature",
  "properties": {
    "iso:country":"US",
    "sg:address":"7633 N US Hwy 231",
    "sg:city":"Jasper",
    "sg:classifiers":[
        {
            "category":"Autos & Motor Vehicles",
            "subcategory":"Automobile Sales",
            "type":"Retail Goods"
        }
    ],
    "sg:phone":"+1 812 695 2100",
    "sg:postcode":"47546",
    "sg:province":"IN",
    "sg:tags":[
        "car",
        "dealer"
    ],
    "wof:name":"Auto Trends",
    "wof:placetype":"venue"
},
  "geometry": {"coordinates":[-86.914278,38.491289],"type":"Point"}
}