{
  "type": "Feature",
  "properties": {
    "addr:full":"7891 Broadway Merrillville IN 46410",
    "addr:housenumber":"7891",
    "addr:postcode":"46410",
    "addr:street":"Broadway",
    "iso:country":"US",
    "sg:address":"7891 Broadway",
    "sg:city":"Merrillville",
    "sg:classifiers":[
        {
            "category":"Health Services",
            "subcategory":"Doctor",
            "type":"Services"
        }
    ],
    "sg:phone":"+1 219 736 2273",
    "sg:postcode":"46410",
    "sg:province":"IN",
    "sg:tags":[
        "dentist"
    ],
    "wof:name":"Premier Dental Group",
    "wof:placetype":"venue"
},
  "geometry": {"coordinates":[-87.335911,41.476933],"type":"Point"}
}