{
  "type": "Feature",
  "properties": {
    "iso:country":"US",
    "sg:address":"609 Michigan Ave",
    "sg:city":"Laporte",
    "sg:classifiers":[
        {
            "category":"Professional",
            "subcategory":"Lawyer & Legal Services",
            "type":"Services"
        }
    ],
    "sg:phone":"+1 219 326 5747",
    "sg:postcode":"46350",
    "sg:province":"IN",
    "sg:tags":[
        "attorney"
    ],
    "wof:name":"Autumn Halaschak",
    "wof:placetype":"venue"
},
  "geometry": {"coordinates":[-86.721906,41.611875],"type":"Point"}
}