{
  "type": "Feature",
  "properties": {
    "iso:country":"US",
    "sg:address":"540 N 700 E",
    "sg:city":"Marion",
    "sg:classifiers":[
        {
            "category":"Shopping",
            "subcategory":"Hobbies, Toys, & Games",
            "type":"Retail Goods"
        }
    ],
    "sg:phone":"+1 765 664 9887",
    "sg:postcode":"46952",
    "sg:province":"IN",
    "wof:name":"Countryside Crafts",
    "wof:placetype":"venue"
},
  "geometry": {"coordinates":[-85.541775,40.560786],"type":"Point"}
}