{
  "type": "Feature",
  "properties": {
    "iso:country":"US",
    "sg:address":"1874 W US Hwy 20",
    "sg:city":"Laporte",
    "sg:classifiers":[
        {
            "category":"Food & Beverages",
            "subcategory":"Groceries & Convenience Stores",
            "type":"Retail Goods"
        }
    ],
    "sg:phone":"+1 219 362 8505",
    "sg:postcode":"46350",
    "sg:province":"IN",
    "wof:name":"Family Express Corp",
    "wof:placetype":"venue"
},
  "geometry": {"coordinates":[-86.739315,41.685401],"type":"Point"}
}