{
  "type": "Feature",
  "properties": {
    "iso:country":"US",
    "sg:address":"340 S Madison Ave",
    "sg:city":"Greenwood",
    "sg:classifiers":[
        {
            "category":"Retail",
            "subcategory":"Auto Repair",
            "type":"Services"
        }
    ],
    "sg:phone":"+1 317 887 1371",
    "sg:postcode":"46142",
    "sg:province":"IN",
    "sg:tags":[
        "transmission"
    ],
    "wof:name":"Kenny's Transmission",
    "wof:placetype":"venue"
},
  "geometry": {"coordinates":[-86.109014,39.611655],"type":"Point"}
}