{
  "type": "Feature",
  "properties": {
    "iso:country":"US",
    "sg:address":"14620 N. Meridian Street",
    "sg:city":"Carmel",
    "sg:classifiers":[
        {
            "category":"Shopping",
            "subcategory":"Bicycles & Sporting Goods",
            "type":"Retail Goods"
        }
    ],
    "sg:phone":"+1 317 818 0860",
    "sg:postcode":"46032",
    "sg:province":"IN",
    "sg:tags":[
        "outdoor",
        "gear"
    ],
    "sg:website":"www.theextremeoutfitters.com",
    "wof:name":"The Extreme Outfitters",
    "wof:placetype":"venue"
},
  "geometry": {"coordinates":[-86.12724300000001,40.000498],"type":"Point"}
}