{
  "type": "Feature",
  "properties": {
    "iso:country":"US",
    "sg:address":"5889 S 800 W",
    "sg:city":"Swayzee",
    "sg:classifiers":[
        {
            "category":"Professional",
            "subcategory":"Accounting & Tax Preparation",
            "type":"Services"
        }
    ],
    "sg:phone":"+1 765 922 7543",
    "sg:postcode":"46986",
    "sg:province":"IN",
    "sg:tags":[
        "return",
        "filing"
    ],
    "wof:name":"Dalrymple Tax Svc",
    "wof:placetype":"venue"
},
  "geometry": {"coordinates":[-85.82503,40.466554],"type":"Point"}
}