{
  "type": "Feature",
  "properties": {
    "iso:country":"US",
    "sg:address":"333 Jackson St",
    "sg:city":"Anderson",
    "sg:classifiers":[
        {
            "category":"Personal",
            "subcategory":"Beauty Salon",
            "type":"Services"
        }
    ],
    "sg:phone":"+1 765 642 7560",
    "sg:postcode":"46016",
    "sg:province":"IN",
    "sg:tags":[
        "school"
    ],
    "wof:name":"Apex Academy Of Hair Design",
    "wof:placetype":"venue"
},
  "geometry": {"coordinates":[-85.680666,40.112139],"type":"Point"}
}