{
  "type": "Feature",
  "properties": {
    "addr:full":"1711 S Yankeetown Rd Boonville IN 47601",
    "addr:housenumber":"1711",
    "addr:postcode":"47601",
    "addr:street":"S Yankeetown Rd",
    "iso:country":"US",
    "sg:address":"1711 S Yankeetown Rd",
    "sg:city":"Boonville",
    "sg:classifiers":[
        {
            "category":"Social Services",
            "type":"Services"
        }
    ],
    "sg:phone":"+1 812 853 0779",
    "sg:postcode":"47601",
    "sg:province":"IN",
    "sg:tags":[
        "referral"
    ],
    "wof:name":"First Advantage Referral Inc",
    "wof:placetype":"venue"
},
  "geometry": {"coordinates":[-87.284316,38.009645],"type":"Point"}
}