{
  "type": "Feature",
  "properties": {
    "addr:full":"2926 E State Hwy 2 Rolling Prairie IN 46371",
    "addr:housenumber":"2926",
    "addr:postcode":"46371",
    "addr:street":"E State Hwy 2",
    "iso:country":"US",
    "sg:address":"2926 E State Hwy 2",
    "sg:city":"Rolling Prairie",
    "sg:classifiers":[
        {
            "category":"Freight",
            "type":"Transportation"
        }
    ],
    "sg:phone":"+1 219 324 5245",
    "sg:postcode":"46371",
    "sg:province":"IN",
    "sg:tags":[
        "commercial",
        "storage",
        "general"
    ],
    "wof:name":"Heaphy's Mini Storage",
    "wof:placetype":"venue"
},
  "geometry": {"coordinates":[-86.642089,41.647586],"type":"Point"}
}