{
  "type": "Feature",
  "properties": {
    "iso:country":"US",
    "sg:address":"2777 Paul Rd",
    "sg:city":"Cambridge City",
    "sg:phone":"+1 765 478 4488",
    "sg:postcode":"47327",
    "sg:province":"IN",
    "sg:tags":[
        "farm",
        "corn",
        "soybean"
    ],
    "wof:name":"Pflum Micheal",
    "wof:placetype":"venue"
},
  "geometry": {"coordinates":[-85.183303,39.793042],"type":"Point"}
}