{
  "type": "Feature",
  "properties": {
    "iso:country":"US",
    "sg:address":"211 Washington St",
    "sg:city":"Columbus",
    "sg:classifiers":[
        {
            "category":"Education",
            "subcategory":"Dance Studio",
            "type":"Public Place"
        }
    ],
    "sg:phone":"+1 812 376 8080",
    "sg:postcode":"47201",
    "sg:province":"IN",
    "sg:tags":[
        "instruction",
        "dancing"
    ],
    "wof:name":"Dancer's Studio Inc",
    "wof:placetype":"venue"
},
  "geometry": {"coordinates":[-85.920935,39.201297],"type":"Point"}
}