{
  "type": "Feature",
  "properties": {
    "addr:full":"375 Wedcor Ave Wabash IN 46992",
    "addr:housenumber":"375",
    "addr:postcode":"46992",
    "addr:street":"Wedcor Ave",
    "iso:country":"US",
    "sg:address":"375 Wedcor Ave",
    "sg:city":"Wabash",
    "sg:classifiers":[
        {
            "category":"Manufacturing",
            "subcategory":"Metals",
            "type":"Manufacturing & Wholesale Goods"
        }
    ],
    "sg:phone":"+1 260 563 5138",
    "sg:postcode":"46992",
    "sg:province":"IN",
    "sg:tags":[
        "steel"
    ],
    "sg:website":"www.bulldog-battery.com",
    "wof:name":"Precision Battery Fabrication",
    "wof:placetype":"venue"
},
  "geometry": {"coordinates":[-85.847909,40.821185],"type":"Point"}
}