{
  "type": "Feature",
  "properties": {
    "iso:country":"US",
    "sg:address":"250 Franklin St",
    "sg:city":"Columbus",
    "sg:classifiers":[
        {
            "category":"Professional",
            "subcategory":"Engineering",
            "type":"Services"
        }
    ],
    "sg:phone":"+1 812 372 9606",
    "sg:postcode":"47201",
    "sg:province":"IN",
    "wof:name":"Vista Engineering",
    "wof:placetype":"venue"
},
  "geometry": {"coordinates":[-85.919737,39.200899],"type":"Point"}
}