{
  "type": "Feature",
  "properties": {
    "iso:country":"US",
    "sg:address":"6231 Co Rd 55",
    "sg:city":"Spencerville",
    "sg:classifiers":[
        {
            "category":"Organizations",
            "subcategory":"Community Association",
            "type":"Services"
        }
    ],
    "sg:phone":"+1 260 337 5241",
    "sg:postcode":"46788",
    "sg:province":"IN",
    "wof:name":"Spencerville Chapter",
    "wof:placetype":"venue"
},
  "geometry": {"coordinates":[-84.925201,41.307406],"type":"Point"}
}