{
  "type": "Feature",
  "properties": {
    "iso:country":"US",
    "sg:address":"406 E Main St",
    "sg:city":"Washington",
    "sg:classifiers":[
        {
            "category":"Personal",
            "subcategory":"Barber",
            "type":"Services"
        }
    ],
    "sg:phone":"+1 812 254 5738",
    "sg:postcode":"47501",
    "sg:province":"IN",
    "sg:tags":[
        "shop"
    ],
    "wof:name":"Arms Barber Shop",
    "wof:placetype":"venue"
},
  "geometry": {"coordinates":[-87.17024,38.657028],"type":"Point"}
}