{
  "type": "Feature",
  "properties": {
    "addr:full":"3850 E Bacon Ridge Rd Marengo IN 47140",
    "addr:housenumber":"3850",
    "addr:postcode":"47140",
    "addr:street":"E Bacon Ridge Rd",
    "iso:country":"US",
    "sg:address":"3850 E Bacon Ridge Rd",
    "sg:city":"Marengo",
    "sg:classifiers":[
        {
            "category":"Real Estate",
            "subcategory":"Real Estate Operator",
            "type":"Services"
        }
    ],
    "sg:phone":"+1 812 365 9306",
    "sg:postcode":"47140",
    "sg:province":"IN",
    "sg:tags":[
        "mobile",
        "home",
        "community"
    ],
    "wof:name":"Cave Springs",
    "wof:placetype":"venue"
},
  "geometry": {"coordinates":[-86.40107,38.372975],"type":"Point"}
}