{
  "type": "Feature",
  "properties": {
    "iso:country":"US",
    "sg:address":"4500 Co Rd 59",
    "sg:city":"Butler",
    "sg:classifiers":[
        {
            "category":"Restaurant",
            "type":"Food & Drink"
        }
    ],
    "sg:phone":"+1 260 925 5214",
    "sg:postcode":"46721",
    "sg:province":"IN",
    "sg:tags":[
        "caterer"
    ],
    "wof:name":"Dove Garden Catering",
    "wof:placetype":"venue"
},
  "geometry": {"coordinates":[-84.907988,41.370446],"type":"Point"}
}