{
  "type": "Feature",
  "properties": {
    "iso:country":"US",
    "sg:address":"720 W Franklin St",
    "sg:city":"Winchester",
    "sg:classifiers":[
        {
            "category":"Banks & Credit Unions",
            "subcategory":"Bank",
            "type":"Services"
        }
    ],
    "sg:phone":"+1 765 584 1055",
    "sg:postcode":"47394",
    "sg:province":"IN",
    "wof:name":"Ahe Plant 3 Federal Cu",
    "wof:placetype":"venue"
},
  "geometry": {"coordinates":[-84.990267,40.171999],"type":"Point"}
}