{
  "type": "Feature",
  "properties": {
    "iso:country":"US",
    "sg:address":"106 E 4th St",
    "sg:city":"Monon",
    "sg:classifiers":[
        {
            "category":"Bars & Pubs",
            "type":"Food & Drink"
        }
    ],
    "sg:phone":"+1 219 253 9355",
    "sg:postcode":"47959",
    "sg:province":"IN",
    "wof:name":"Gibbs Food & Spirits",
    "wof:placetype":"venue"
},
  "geometry": {"coordinates":[-86.878514,40.862855],"type":"Point"}
}