{
  "type": "Feature",
  "properties": {
    "iso:country":"US",
    "sg:address":"211 Ridge Springs Ln",
    "sg:city":"Ellettsville",
    "sg:classifiers":[
        {
            "category":"Social Services",
            "subcategory":"Child Care",
            "type":"Services"
        }
    ],
    "sg:phone":"+1 812 876 6340",
    "sg:postcode":"47429",
    "sg:province":"IN",
    "sg:tags":[
        "day"
    ],
    "wof:name":"Best of Friends Daycare",
    "wof:placetype":"venue"
},
  "geometry": {"coordinates":[-86.63361999999999,39.24023],"type":"Point"}
}