{
  "type": "Feature",
  "properties": {
    "addr:full":"5974 E Co Rd 410 N Seymour IN 47274",
    "addr:housenumber":"5974;410 n",
    "addr:postcode":"47274",
    "addr:street":"E Co Rd",
    "iso:country":"US",
    "sg:address":"5974 E Co Rd 410 N",
    "sg:city":"Seymour",
    "sg:classifiers":[
        {
            "category":"Wholesale",
            "subcategory":"Meat",
            "type":"Manufacturing & Wholesale Goods"
        }
    ],
    "sg:phone":"+1 812 522 1635",
    "sg:postcode":"47274",
    "sg:province":"IN",
    "sg:tags":[
        "butchering"
    ],
    "wof:name":"Hackman Custom Meats Inc",
    "wof:placetype":"venue"
},
  "geometry": {"coordinates":[-85.929643,38.938956],"type":"Point"}
}