{
  "type": "Feature",
  "properties": {
    "iso:country":"US",
    "sg:address":"9998 N Michigan Rd",
    "sg:city":"Carmel",
    "sg:classifiers":[
        {
            "category":"Professional",
            "type":"Services"
        }
    ],
    "sg:phone":"+1 317 805 9724",
    "sg:postcode":"46032",
    "sg:province":"IN",
    "sg:tags":[
        "establishment"
    ],
    "wof:name":"C I Vacation Exchange Co",
    "wof:placetype":"venue"
},
  "geometry": {"coordinates":[-86.232924,39.932663],"type":"Point"}
}