{
  "type": "Feature",
  "properties": {
    "iso:country":"US",
    "sg:address":"6425 N Co Rd 575 W",
    "sg:city":"North Salem",
    "sg:classifiers":[
        {
            "category":"Building & Trades",
            "subcategory":"Construction",
            "type":"Services"
        }
    ],
    "sg:phone":"+1 765 676 5759",
    "sg:postcode":"46165",
    "sg:province":"IN",
    "sg:tags":[
        "house"
    ],
    "wof:name":"Custom Homes By Jwcox",
    "wof:placetype":"venue"
},
  "geometry": {"coordinates":[-86.62938200000001,39.848407],"type":"Point"}
}