{
  "type": "Feature",
  "properties": {
    "addr:full":"1981 S Industrial Park Rd Versailles IN 47042",
    "addr:housenumber":"1981",
    "addr:postcode":"47042",
    "addr:street":"S Industrial Park Rd",
    "iso:country":"US",
    "sg:address":"1981 S Industrial Park Rd",
    "sg:city":"Versailles",
    "sg:classifiers":[
        {
            "category":"Government",
            "subcategory":"Office",
            "type":"Public Place"
        }
    ],
    "sg:phone":"+1 812 689 4224",
    "sg:postcode":"47042",
    "sg:province":"IN",
    "sg:tags":[
        "federal",
        "planning",
        "dev"
    ],
    "wof:name":"USDA Rural Development",
    "wof:placetype":"venue"
},
  "geometry": {"coordinates":[-85.260779,39.046085],"type":"Point"}
}