{
  "type": "Feature",
  "properties": {
    "iso:country":"US",
    "sg:address":"8018 Tyler St",
    "sg:city":"Merrillville",
    "sg:classifiers":[
        {
            "category":"Professional",
            "subcategory":"Employment Agencies",
            "type":"Services"
        }
    ],
    "sg:phone":"+1 219 736 1041",
    "sg:postcode":"46410",
    "sg:province":"IN",
    "sg:tags":[
        "opportunity"
    ],
    "wof:name":"Pro Resources Medical Staffing",
    "wof:placetype":"venue"
},
  "geometry": {"coordinates":[-87.347257,41.471945],"type":"Point"}
}