{
  "type": "Feature",
  "properties": {
    "iso:country":"US",
    "sg:address":"4611 E Morningside Dr",
    "sg:city":"Bloomington",
    "sg:classifiers":[
        {
            "category":"Social Services",
            "type":"Services"
        }
    ],
    "sg:phone":"+1 812 339 3450",
    "sg:postcode":"47408",
    "sg:province":"IN",
    "sg:tags":[
        "organization",
        "welfare"
    ],
    "wof:name":"Quality Case Management",
    "wof:placetype":"venue"
},
  "geometry": {"coordinates":[-86.47479300000001,39.167245],"type":"Point"}
}