{
  "type": "Feature",
  "properties": {
    "iso:country":"US",
    "sg:address":"7657 E 250 N",
    "sg:city":"Rolling Prairie",
    "sg:phone":"+1 219 778 2502",
    "sg:postcode":"46371",
    "sg:province":"IN",
    "sg:tags":[
        "farm",
        "corn",
        "soybean"
    ],
    "wof:name":"Joseph Cuson",
    "wof:placetype":"venue"
},
  "geometry": {"coordinates":[-86.55471799999999,41.643126],"type":"Point"}
}