{
  "type": "Feature",
  "properties": {
    "iso:country":"US",
    "sg:address":"16215 Hand Rd",
    "sg:city":"Huntertown",
    "sg:classifiers":[
        {
            "category":"Building & Trades",
            "subcategory":"Construction",
            "type":"Services"
        }
    ],
    "sg:phone":"+1 260 637 5649",
    "sg:postcode":"46748",
    "sg:province":"IN",
    "sg:tags":[
        "contractor"
    ],
    "wof:name":"Total Masonary",
    "wof:placetype":"venue"
},
  "geometry": {"coordinates":[-85.210641,41.233209],"type":"Point"}
}