{
  "type": "Feature",
  "properties": {
    "iso:country":"US",
    "sg:address":"325 Main St",
    "sg:city":"Ferdinand",
    "sg:classifiers":[
        {
            "category":"Home & Garden",
            "subcategory":"Hardware",
            "type":"Retail Goods"
        }
    ],
    "sg:phone":"+1 812 367 1500",
    "sg:postcode":"47532",
    "sg:province":"IN",
    "wof:name":"Frank Heidet & Son",
    "wof:placetype":"venue"
},
  "geometry": {"coordinates":[-86.863291,38.219982],"type":"Point"}
}