{
  "type": "Feature",
  "properties": {
    "addr:full":"6356 N Park Ave Indianapolis IN 46220",
    "addr:housenumber":"6356",
    "addr:postcode":"46220",
    "addr:street":"N Park",
    "iso:country":"US",
    "sg:address":"6356 N Park Ave",
    "sg:city":"Indianapolis",
    "sg:classifiers":[
        {
            "category":"Building & Trades",
            "subcategory":"Landscaping Services",
            "type":"Services"
        }
    ],
    "sg:phone":"+1 317 254 8976",
    "sg:postcode":"46220",
    "sg:province":"IN",
    "sg:tags":[
        "landscape"
    ],
    "wof:name":"El Green Thumb",
    "wof:placetype":"venue"
},
  "geometry": {"coordinates":[-86.149092,39.871313],"type":"Point"}
}