{
  "type": "Feature",
  "properties": {
    "iso:country":"US",
    "sg:address":"545 Barnhill Dr",
    "sg:city":"Indianapolis",
    "sg:classifiers":[
        {
            "category":"Health Services",
            "subcategory":"Doctor",
            "type":"Services"
        }
    ],
    "sg:phone":"+1 317 274 1121",
    "sg:postcode":"46202",
    "sg:province":"IN",
    "sg:tags":[
        "medical"
    ],
    "wof:name":"Indiana University Medical Ctr",
    "wof:placetype":"venue"
},
  "geometry": {"coordinates":[-86.178528,39.775224],"type":"Point"}
}