{
  "type": "Feature",
  "properties": {
    "iso:country":"US",
    "sg:address":"128 N Delaware St",
    "sg:city":"Indianapolis",
    "sg:classifiers":[
        {
            "category":"Professional",
            "subcategory":"Lawyer & Legal Services",
            "type":"Services"
        }
    ],
    "sg:phone":"+1 317 639 5161",
    "sg:postcode":"46204",
    "sg:province":"IN",
    "sg:tags":[
        "attorney"
    ],
    "wof:name":"Young & Young",
    "wof:placetype":"venue"
},
  "geometry": {"coordinates":[-86.154482,39.768486],"type":"Point"}
}