{
  "type": "Feature",
  "properties": {
    "iso:country":"US",
    "sg:address":"4620 Speedway Dr",
    "sg:city":"Fort Wayne",
    "sg:classifiers":[
        {
            "category":"Building & Trades",
            "subcategory":"Equipment Rental",
            "type":"Services"
        }
    ],
    "sg:phone":"+1 260 484 3964",
    "sg:postcode":"46825",
    "sg:province":"IN",
    "sg:tags":[
        "party",
        "supply"
    ],
    "wof:name":"All Occasion Party Rentals",
    "wof:placetype":"venue"
},
  "geometry": {"coordinates":[-85.142439,41.120789],"type":"Point"}
}