{
  "type": "Feature",
  "properties": {
    "iso:country":"US",
    "sg:address":"250 E 3rd St",
    "sg:city":"Ferdinand",
    "sg:classifiers":[
        {
            "category":"Health Services",
            "subcategory":"Hospital",
            "type":"Services"
        }
    ],
    "sg:phone":"+1 812 367 9987",
    "sg:postcode":"47546",
    "sg:province":"IN",
    "sg:tags":[
        "medical",
        "surgical",
        "emergency"
    ],
    "wof:name":"Ferdinand Ems Station",
    "wof:placetype":"venue"
},
  "geometry": {"coordinates":[-86.862099,38.21933],"type":"Point"}
}