{
  "type": "Feature",
  "properties": {
    "iso:country":"US",
    "sg:address":"5360 Sunset Ave",
    "sg:city":"Indianapolis",
    "sg:classifiers":[
        {
            "category":"Arts & Performance",
            "subcategory":"Theater",
            "type":"Entertainment"
        }
    ],
    "sg:phone":"+1 317 289 0335",
    "sg:postcode":"46208",
    "sg:province":"IN",
    "sg:tags":[
        "theatrical"
    ],
    "wof:name":"Indy Booking",
    "wof:placetype":"venue"
},
  "geometry": {"coordinates":[-86.169035,39.849689],"type":"Point"}
}