{
  "type": "Feature",
  "properties": {
    "iso:country":"US",
    "sg:address":"351 E Chestnut St",
    "sg:city":"Corydon",
    "sg:classifiers":[
        {
            "category":"Insurance",
            "subcategory":"Insurance Agent",
            "type":"Services"
        }
    ],
    "sg:phone":"+1 812 738 2233",
    "sg:postcode":"47112",
    "sg:province":"IN",
    "sg:website":"www.bennettins.com",
    "wof:name":"Bennett & Bennett Insurance",
    "wof:placetype":"venue"
},
  "geometry": {"coordinates":[-86.12307199999999,38.210429],"type":"Point"}
}