{
  "type": "Feature",
  "properties": {
    "iso:country":"US",
    "sg:address":"2904 S 700 W",
    "sg:city":"Kimmell",
    "sg:phone":"+1 260 799 4173",
    "sg:postcode":"46760",
    "sg:province":"IN",
    "sg:tags":[
        "farm",
        "corn",
        "soybean"
    ],
    "wof:name":"Dan Burnworth",
    "wof:placetype":"venue"
},
  "geometry": {"coordinates":[-85.555363,41.311194],"type":"Point"}
}