{
  "type": "Feature",
  "properties": {
    "iso:country":"US",
    "sg:address":"973 W Monoquet Rd",
    "sg:city":"Warsaw",
    "sg:classifiers":[
        {
            "category":"Personal",
            "type":"Services"
        }
    ],
    "sg:phone":"+1 574 269 9865",
    "sg:postcode":"46582",
    "sg:province":"IN",
    "sg:tags":[
        "therapist",
        "massage"
    ],
    "wof:name":"B Smith Inc",
    "wof:placetype":"venue"
},
  "geometry": {"coordinates":[-85.86207,41.289349],"type":"Point"}
}