{
  "type": "Feature",
  "properties": {
    "addr:full":"2127 N Delaware St Indianapolis IN 46202",
    "addr:housenumber":"2127",
    "addr:postcode":"46202",
    "addr:street":"N Delaware St",
    "iso:country":"US",
    "sg:address":"2127 N Delaware St",
    "sg:city":"Indianapolis",
    "sg:classifiers":[
        {
            "category":"Personal",
            "type":"Services"
        },
        {
            "category":"Professional",
            "subcategory":"Art Services",
            "type":"Services"
        }
    ],
    "sg:phone":"+1 317 255 6233",
    "sg:postcode":"46202",
    "sg:province":"IN",
    "sg:tags":[
        "photography",
        "videography",
        "photographers-portrait",
        "wedding"
    ],
    "wof:name":"Romer Scott Photography & Digitial Imagry",
    "wof:placetype":"venue"
},
  "geometry": {"coordinates":[-86.15374199999999,39.796119],"type":"Point"}
}