{
  "type": "Feature",
  "properties": {
    "iso:country":"US",
    "sg:address":"153 Stoney Creek Ovlk",
    "sg:city":"Noblesville",
    "sg:classifiers":[
        {
            "category":"Retail",
            "subcategory":"Repair Shop",
            "type":"Services"
        }
    ],
    "sg:phone":"+1 317 773 7763",
    "sg:postcode":"46060",
    "sg:province":"IN",
    "sg:tags":[
        "related"
    ],
    "wof:name":"Equipment Maintenance Conslntg",
    "wof:placetype":"venue"
},
  "geometry": {"coordinates":[-86.00262499999999,40.024898],"type":"Point"}
}