{
  "type": "Feature",
  "properties": {
    "iso:country":"US",
    "sg:address":"844 S Indiana Ave",
    "sg:city":"Sellersburg",
    "sg:classifiers":[
        {
            "category":"Retail",
            "subcategory":"Auto Repair",
            "type":"Services"
        }
    ],
    "sg:phone":"+1 812 246 5376",
    "sg:postcode":"47172",
    "sg:province":"IN",
    "sg:tags":[
        "body",
        "shop",
        "painting",
        "automobile"
    ],
    "wof:name":"Jewell's Body Shop",
    "wof:placetype":"venue"
},
  "geometry": {"coordinates":[-85.75340300000001,38.389301],"type":"Point"}
}