{
  "type": "Feature",
  "properties": {
    "addr:full":"2828 E 55th Pl Indianapolis IN 46220",
    "addr:housenumber":"2828",
    "addr:postcode":"46220",
    "addr:street":"E 55Th Pl",
    "iso:country":"US",
    "sg:address":"2828 E 55th Pl",
    "sg:city":"Indianapolis",
    "sg:classifiers":[
        {
            "category":"Retail",
            "subcategory":"Animal Services",
            "type":"Services"
        }
    ],
    "sg:phone":"+1 317 698 6971",
    "sg:postcode":"46220",
    "sg:province":"IN",
    "sg:tags":[
        "pet",
        "training"
    ],
    "wof:name":"A Dog's View Inc",
    "wof:placetype":"venue"
},
  "geometry": {"coordinates":[-86.117026,39.853785],"type":"Point"}
}