{
  "type": "Feature",
  "properties": {
    "iso:country":"US",
    "sg:address":"6060 Broadway",
    "sg:city":"Merrillville",
    "sg:classifiers":[
        {
            "category":"Autos & Motor Vehicles",
            "subcategory":"Auto Supplies",
            "type":"Retail Goods"
        }
    ],
    "sg:phone":"+1 219 985 7833",
    "sg:postcode":"46410",
    "sg:province":"IN",
    "sg:tags":[
        "automobile",
        "parts"
    ],
    "wof:name":"Murray's Discount Auto Store",
    "wof:placetype":"venue"
},
  "geometry": {"coordinates":[-87.336139,41.508246],"type":"Point"}
}