{
  "type": "Feature",
  "properties": {
    "addr:full":"11425 Lantern Rd Fishers IN 46038",
    "addr:housenumber":"11425",
    "addr:postcode":"46038",
    "addr:street":"Lantern Rd",
    "iso:country":"US",
    "sg:address":"11425 Lantern Rd",
    "sg:city":"Fishers",
    "sg:classifiers":[
        {
            "category":"Organizations",
            "subcategory":"Religious Organization",
            "type":"Services"
        }
    ],
    "sg:phone":"+1 317 842 2950",
    "sg:postcode":"46038",
    "sg:province":"IN",
    "wof:name":"Christian Life Center",
    "wof:placetype":"venue"
},
  "geometry": {"coordinates":[-86.013848,39.954058],"type":"Point"}
}