{
  "type": "Feature",
  "properties": {
    "iso:country":"US",
    "sg:address":"525 S Reed Rd",
    "sg:city":"Kokomo",
    "sg:classifiers":[
        {
            "category":"Building & Trades",
            "subcategory":"Equipment Rental",
            "type":"Services"
        }
    ],
    "sg:phone":"+1 765 236 0296",
    "sg:postcode":"46901",
    "sg:province":"IN",
    "sg:tags":[
        "leasing",
        "furniture"
    ],
    "wof:name":"Aarons Sales & Lease Ownership",
    "wof:placetype":"venue"
},
  "geometry": {"coordinates":[-86.107843,40.476687],"type":"Point"}
}