{
  "type": "Feature",
  "properties": {
    "iso:country":"US",
    "sg:address":"809 W Carmel Dr. locations in Illinois and Indiana",
    "sg:city":"Carmel",
    "sg:classifiers":[
        {
            "category":"Personal",
            "subcategory":"Hair Removal",
            "type":"Services"
        },
        {
            "category":"Personal",
            "subcategory":"Skin Care",
            "type":"Services"
        }
    ],
    "sg:phone":"+1 888 877 7492",
    "sg:postcode":"46032",
    "sg:province":"IN",
    "sg:tags":[
        "laser"
    ],
    "sg:website":"www.unitedlaserclinics.com/",
    "wof:name":"United Laser Clinics",
    "wof:placetype":"venue"
},
  "geometry": {"coordinates":[-86.146573,39.968386],"type":"Point"}
}