{
  "type": "Feature",
  "properties": {
    "iso:country":"US",
    "sg:address":"40 Main St W",
    "sg:city":"Greenwood",
    "sg:classifiers":[
        {
            "category":"Shopping",
            "subcategory":"Shoes",
            "type":"Retail Goods"
        }
    ],
    "sg:phone":"+1 812 988 7144",
    "sg:postcode":"46142",
    "sg:province":"IN",
    "wof:name":"Four Bare Feet Too",
    "wof:placetype":"venue"
},
  "geometry": {"coordinates":[-86.106506,39.613807],"type":"Point"}
}