{
  "type": "Feature",
  "properties": {
    "iso:country":"US",
    "sg:address":"205 E Main St",
    "sg:city":"Paoli",
    "sg:classifiers":[
        {
            "category":"Government",
            "subcategory":"Court House",
            "type":"Public Place"
        }
    ],
    "sg:phone":"+1 812 723 3322",
    "sg:postcode":"47454",
    "sg:province":"IN",
    "sg:tags":[
        "county"
    ],
    "wof:name":"Judge Of Orange County Court",
    "wof:placetype":"venue"
},
  "geometry": {"coordinates":[-86.467089,38.556051],"type":"Point"}
}