{
  "type": "Feature",
  "properties": {
    "iso:country":"US",
    "sg:address":"300 W Ridge Rd",
    "sg:city":"Gary",
    "sg:classifiers":[
        {
            "category":"Food & Beverages",
            "subcategory":"Groceries & Convenience Stores",
            "type":"Retail Goods"
        }
    ],
    "sg:phone":"+1 219 985 0000",
    "sg:postcode":"46408",
    "sg:province":"IN",
    "sg:tags":[
        "grocer"
    ],
    "wof:name":"Top Value",
    "wof:placetype":"venue"
},
  "geometry": {"coordinates":[-87.341308,41.549409],"type":"Point"}
}