{
  "type": "Feature",
  "properties": {
    "iso:country":"US",
    "sg:address":"3804 Virginia St",
    "sg:city":"Gary",
    "sg:classifiers":[
        {
            "category":"Building & Trades",
            "subcategory":"Cleaning & Sanitation",
            "type":"Services"
        }
    ],
    "sg:phone":"+1 219 981 1213",
    "sg:postcode":"46409",
    "sg:province":"IN",
    "wof:name":"Sims & Snowden Enterprises",
    "wof:placetype":"venue"
},
  "geometry": {"coordinates":[-87.329277,41.547818],"type":"Point"}
}