{
  "type": "Feature",
  "properties": {
    "iso:country":"US",
    "sg:address":"9110 Olmston Dr",
    "sg:city":"Fort Wayne",
    "sg:classifiers":[
        {
            "category":"Building & Trades",
            "subcategory":"Landscaping Services",
            "type":"Services"
        }
    ],
    "sg:phone":"+1 260 704 4109",
    "sg:postcode":"46825",
    "sg:province":"IN",
    "sg:tags":[
        "landscape",
        "contractor"
    ],
    "wof:name":"Kinslow Lawn & Landscape Inc",
    "wof:placetype":"venue"
},
  "geometry": {"coordinates":[-85.147706,41.163134],"type":"Point"}
}