{
  "type": "Feature",
  "properties": {
    "iso:country":"US",
    "sg:address":"7243 Fishers Landing Dr",
    "sg:city":"Fishers",
    "sg:classifiers":[
        {
            "category":"Professional",
            "subcategory":"Employment Agencies",
            "type":"Services"
        }
    ],
    "sg:phone":"+1 317 596 9370",
    "sg:postcode":"46038",
    "sg:province":"IN",
    "sg:tags":[
        "contractor"
    ],
    "wof:name":"Express Personnel Services",
    "wof:placetype":"venue"
},
  "geometry": {"coordinates":[-86.04315200000001,39.955925],"type":"Point"}
}