{
  "type": "Feature",
  "properties": {
    "iso:country":"US",
    "sg:address":"1203 Webster St",
    "sg:city":"Fort Wayne",
    "sg:classifiers":[
        {
            "category":"Professional",
            "subcategory":"Engineering",
            "type":"Services"
        }
    ],
    "sg:phone":"+1 260 426 3119",
    "sg:postcode":"46802",
    "sg:province":"IN",
    "sg:tags":[
        "engineer"
    ],
    "wof:name":"Eastern Engineering Supply",
    "wof:placetype":"venue"
},
  "geometry": {"coordinates":[-85.141626,41.074205],"type":"Point"}
}