{
  "type": "Feature",
  "properties": {
    "addr:full":"114 Main St Aurora IN 47001",
    "addr:housenumber":"114",
    "addr:postcode":"47001",
    "addr:street":"Main St",
    "iso:country":"US",
    "sg:address":"114 Main St",
    "sg:city":"Aurora",
    "sg:classifiers":[
        {
            "category":"Food & Beverages",
            "subcategory":"Liquor & Beverages",
            "type":"Retail Goods"
        }
    ],
    "sg:phone":"+1 812 926 1134",
    "sg:postcode":"47001",
    "sg:province":"IN",
    "wof:name":"C J's Liquor",
    "wof:placetype":"venue"
},
  "geometry": {"coordinates":[-84.89955,39.057256],"type":"Point"}
}