{
  "type": "Feature",
  "properties": {
    "iso:country":"US",
    "sg:address":"3325 Pendleton Ave",
    "sg:city":"Anderson",
    "sg:classifiers":[
        {
            "category":"Organizations",
            "subcategory":"Religious Organization",
            "type":"Services"
        }
    ],
    "sg:phone":"+1 765 683 0504",
    "sg:postcode":"46013",
    "sg:province":"IN",
    "sg:tags":[
        "church"
    ],
    "wof:name":"Grace Holiness Church",
    "wof:placetype":"venue"
},
  "geometry": {"coordinates":[-85.703704,40.082318],"type":"Point"}
}