{
  "type": "Feature",
  "properties": {
    "iso:country":"US",
    "sg:address":"129 Cooper St",
    "sg:city":"Loogootee",
    "sg:classifiers":[
        {
            "category":"Health Services",
            "subcategory":"Chiropractor",
            "type":"Services"
        }
    ],
    "sg:phone":"+1 812 295 3346",
    "sg:postcode":"47553",
    "sg:province":"IN",
    "wof:name":"Omer Chiropractic Clinic",
    "wof:placetype":"venue"
},
  "geometry": {"coordinates":[-86.913453,38.672839],"type":"Point"}
}