{
  "type": "Feature",
  "properties": {
    "iso:country":"US",
    "sg:address":"620 N Range Line Rd",
    "sg:city":"Carmel",
    "sg:classifiers":[
        {
            "category":"Shopping",
            "subcategory":"Florist",
            "type":"Retail Goods"
        }
    ],
    "sg:phone":"+1 317 846 2578",
    "sg:postcode":"46032",
    "sg:province":"IN",
    "sg:website":"www.thecarmelflorist.com",
    "wof:name":"Carmel Florist Llc",
    "wof:placetype":"venue"
},
  "geometry": {"coordinates":[-86.127492,39.983554],"type":"Point"}
}