{
  "type": "Feature",
  "properties": {
    "addr:full":"320 W 8th St Bloomington IN 47404",
    "addr:housenumber":"320",
    "addr:postcode":"47404",
    "addr:street":"W 8Th St",
    "iso:country":"US",
    "sg:address":"320 W 8th St",
    "sg:city":"Bloomington",
    "sg:classifiers":[
        {
            "category":"Professional",
            "subcategory":"Employment Agencies",
            "type":"Services"
        }
    ],
    "sg:phone":"+1 812 333 6210",
    "sg:postcode":"47404",
    "sg:province":"IN",
    "sg:tags":[
        "help",
        "contractor"
    ],
    "sg:website":"www.expresspersonnel.com",
    "wof:name":"Express Personnel Svc",
    "wof:placetype":"venue"
},
  "geometry": {"coordinates":[-86.537464,39.169606],"type":"Point"}
}