{
  "type": "Feature",
  "properties": {
    "iso:country":"US",
    "sg:address":"650 S Pennsylvania St",
    "sg:city":"Marion",
    "sg:classifiers":[
        {
            "category":"Wholesale",
            "subcategory":"Durable Goods & Equipment",
            "type":"Manufacturing & Wholesale Goods"
        }
    ],
    "sg:phone":"+1 765 662 7929",
    "sg:postcode":"46952",
    "sg:province":"IN",
    "sg:tags":[
        "fire",
        "extinguisher"
    ],
    "wof:name":"Thompson Fire & Safety Supply",
    "wof:placetype":"venue"
},
  "geometry": {"coordinates":[-85.644883,40.55701],"type":"Point"}
}