{
  "type": "Feature",
  "properties": {
    "iso:country":"US",
    "sg:address":"5407 S Anthony Blvd",
    "sg:city":"Fort Wayne",
    "sg:classifiers":[
        {
            "category":"Restaurant",
            "type":"Food & Drink"
        }
    ],
    "sg:phone":"+1 260 447 0604",
    "sg:postcode":"46806",
    "sg:province":"IN",
    "wof:name":"Tasty King Gyros",
    "wof:placetype":"venue"
},
  "geometry": {"coordinates":[-85.112751,41.033594],"type":"Point"}
}