{
  "type": "Feature",
  "properties": {
    "addr:full":"2114 E 80th Ave Merrillville IN 46410",
    "addr:housenumber":"2114",
    "addr:postcode":"46410",
    "addr:street":"E 80Th Ave",
    "iso:country":"US",
    "sg:address":"2114 E 80th Ave",
    "sg:city":"Merrillville",
    "sg:classifiers":[
        {
            "category":"Shopping",
            "subcategory":"Clothing, Apparel, & Fashions",
            "type":"Retail Goods"
        },
        {
            "category":"Shopping",
            "subcategory":"Shoes",
            "type":"Retail Goods"
        }
    ],
    "sg:phone":"+1 219 791 0446",
    "sg:postcode":"46410",
    "sg:province":"IN",
    "sg:tags":[
        "handbag",
        "boots-retail",
        "store"
    ],
    "wof:name":"Dsw Inc.",
    "wof:placetype":"venue"
},
  "geometry": {"coordinates":[-87.309827,41.472192],"type":"Point"}
}