{
  "type": "Feature",
  "properties": {
    "addr:full":"11541 N US Hwy 41 Farmersburg IN 47850",
    "addr:housenumber":"11541",
    "addr:postcode":"47850",
    "addr:street":"N Us Hwy 41",
    "iso:country":"US",
    "sg:address":"11541 N US Hwy 41",
    "sg:city":"Farmersburg",
    "sg:classifiers":[
        {
            "category":"Personal",
            "subcategory":"Barber",
            "type":"Services"
        }
    ],
    "sg:phone":"+1 812 696 2312",
    "sg:postcode":"47850",
    "sg:province":"IN",
    "wof:name":"Jerry's Barber Shop",
    "wof:placetype":"venue"
},
  "geometry": {"coordinates":[-87.38911400000001,39.252813],"type":"Point"}
}