{
  "type": "Feature",
  "properties": {
    "iso:country":"US",
    "sg:address":"11541 N US Hwy 41",
    "sg:city":"Farmersburg",
    "sg:classifiers":[
        {
            "category":"Personal",
            "subcategory":"Barber",
            "type":"Services"
        }
    ],
    "sg:phone":"+1 812 696 2312",
    "sg:postcode":"47850",
    "sg:province":"IN",
    "wof:name":"Jerry's Barber Shop",
    "wof:placetype":"venue"
},
  "geometry": {"coordinates":[-87.389114,39.252813],"type":"Point"}
}