{
  "type": "Feature",
  "properties": {
    "iso:country":"US",
    "sg:address":"3000 S 9th St",
    "sg:city":"Lafayette",
    "sg:classifiers":[
        {
            "category":"Food & Beverages",
            "subcategory":"Liquor & Beverages",
            "type":"Retail Goods"
        }
    ],
    "sg:phone":"+1 765 474 5274",
    "sg:postcode":"47909",
    "sg:province":"IN",
    "wof:name":"Bar Barry Liquors V",
    "wof:placetype":"venue"
},
  "geometry": {"coordinates":[-86.885673,40.381887],"type":"Point"}
}