{
  "type": "Feature",
  "properties": {
    "addr:full":"2530 E Minnesota St Indianapolis IN 46203",
    "addr:housenumber":"2530",
    "addr:postcode":"46203",
    "addr:street":"E Minnesota St",
    "iso:country":"US",
    "sg:address":"2530 E Minnesota St",
    "sg:city":"Indianapolis",
    "sg:classifiers":[
        {
            "category":"Personal",
            "subcategory":"Beauty Salon",
            "type":"Services"
        }
    ],
    "sg:phone":"+1 317 780 7450",
    "sg:postcode":"46203",
    "sg:province":"IN",
    "wof:name":"Kanya's Hair Care",
    "wof:placetype":"venue"
},
  "geometry": {"coordinates":[-86.118962,39.745225],"type":"Point"}
}