{
  "type": "Feature",
  "properties": {
    "iso:country":"US",
    "sg:address":"133 Holly Ln",
    "sg:city":"Schererville",
    "sg:classifiers":[
        {
            "category":"Shopping",
            "subcategory":"Hobbies, Toys, & Games",
            "type":"Retail Goods"
        }
    ],
    "sg:phone":"+1 219 865 9833",
    "sg:postcode":"46375",
    "sg:province":"IN",
    "sg:tags":[
        "shop"
    ],
    "wof:name":"Hitech Hobbies & Electronics",
    "wof:placetype":"venue"
},
  "geometry": {"coordinates":[-87.474696,41.519588],"type":"Point"}
}