{
  "type": "Feature",
  "properties": {
    "addr:full":"7349 Scarborough Blvd East Dr Indianapolis IN 46256",
    "addr:housenumber":"7349",
    "addr:postcode":"46256",
    "addr:street":"Scarborough Blvd East Dr",
    "iso:country":"US",
    "sg:address":"7349 Scarborough Blvd East Dr",
    "sg:city":"Indianapolis",
    "sg:classifiers":[
        {
            "category":"Autos & Motor Vehicles",
            "subcategory":"Boat Sales",
            "type":"Retail Goods"
        }
    ],
    "sg:phone":"+1 317 849 7588",
    "sg:postcode":"46256",
    "sg:province":"IN",
    "wof:name":"Northeast Marine",
    "wof:placetype":"venue"
},
  "geometry": {"coordinates":[-86.024353,39.888809],"type":"Point"}
}