{
  "type": "Feature",
  "properties": {
    "addr:full":"14266 Mulberry St Deputy IN 47230",
    "addr:housenumber":"14266",
    "addr:postcode":"47230",
    "addr:street":"Mulberry St",
    "iso:country":"US",
    "sg:address":"14266 Mulberry St",
    "sg:city":"Deputy",
    "sg:classifiers":[
        {
            "category":"Organizations",
            "subcategory":"Religious Organization",
            "type":"Services"
        }
    ],
    "sg:phone":"+1 812 866 2113",
    "sg:postcode":"47230",
    "sg:province":"IN",
    "sg:tags":[
        "church"
    ],
    "wof:name":"Deputy United Methodist Church",
    "wof:placetype":"venue"
},
  "geometry": {"coordinates":[-85.651257,38.795793],"type":"Point"}
}