{
  "type": "Feature",
  "properties": {
    "iso:country":"US",
    "sg:address":"4275 W 96th St",
    "sg:city":"Indianapolis",
    "sg:classifiers":[
        {
            "category":"Home & Garden",
            "subcategory":"Carpets & Floor Coverings",
            "type":"Retail Goods"
        }
    ],
    "sg:phone":"+1 317 334 9550",
    "sg:postcode":"46268",
    "sg:province":"IN",
    "sg:tags":[
        "material"
    ],
    "wof:name":"Lowe Professional Flooring LTD",
    "wof:placetype":"venue"
},
  "geometry": {"coordinates":[-86.231788,39.926063],"type":"Point"}
}