{
  "type": "Feature",
  "properties": {
    "iso:country":"US",
    "sg:address":"3010 Bugaboo Ln",
    "sg:city":"Sellersburg",
    "sg:classifiers":[
        {
            "category":"Building & Trades",
            "subcategory":"Construction",
            "type":"Services"
        }
    ],
    "sg:phone":"+1 812 246 3267",
    "sg:postcode":"47172",
    "sg:province":"IN",
    "sg:tags":[
        "house"
    ],
    "wof:name":"Beyl Construction",
    "wof:placetype":"venue"
},
  "geometry": {"coordinates":[-85.797748,38.381681],"type":"Point"}
}