{
  "type": "Feature",
  "properties": {
    "iso:country":"US",
    "sg:address":"5620 Industrial Rd",
    "sg:city":"Fort Wayne",
    "sg:classifiers":[
        {
            "category":"Manufacturing",
            "subcategory":"Aerospace",
            "type":"Manufacturing & Wholesale Goods"
        }
    ],
    "sg:phone":"+1 260 484 5009",
    "sg:postcode":"46825",
    "sg:province":"IN",
    "sg:tags":[
        "aircraft",
        "support",
        "ground"
    ],
    "wof:name":"Perfection Co",
    "wof:placetype":"venue"
},
  "geometry": {"coordinates":[-85.146498,41.13232],"type":"Point"}
}