{
  "type": "Feature",
  "properties": {
    "iso:country":"US",
    "sg:address":"111 S Walnut St",
    "sg:city":"Edinburgh",
    "sg:classifiers":[
        {
            "category":"Shopping",
            "subcategory":"Computers & Home Electronics",
            "type":"Retail Goods"
        }
    ],
    "sg:phone":"+1 812 526 6003",
    "sg:postcode":"46124",
    "sg:province":"IN",
    "sg:tags":[
        "equipment",
        "satellite",
        "system"
    ],
    "wof:name":"Sonic PC",
    "wof:placetype":"venue"
},
  "geometry": {"coordinates":[-85.966503,39.354186],"type":"Point"}
}