{
  "type": "Feature",
  "properties": {
    "iso:country":"US",
    "sg:address":"4915 E 82nd St",
    "sg:city":"Indianapolis",
    "sg:classifiers":[
        {
            "category":"Coffee & Tea",
            "type":"Food & Drink"
        }
    ],
    "sg:phone":"+1 317 598 1673",
    "sg:postcode":"46250",
    "sg:province":"IN",
    "sg:website":"www.starbucks.com",
    "wof:name":"Starbucks Coffee Company",
    "wof:placetype":"venue"
},
  "geometry": {"coordinates":[-86.087799,39.905499],"type":"Point"}
}