{
  "type": "Feature",
  "properties": {
    "iso:country":"US",
    "sg:address":"10520 S 400 W-90",
    "sg:city":"Montpelier",
    "sg:classifiers":[
        {
            "category":"Wholesale",
            "subcategory":"Construction Materials",
            "type":"Manufacturing & Wholesale Goods"
        }
    ],
    "sg:phone":"+1 765 728 2337",
    "sg:postcode":"47359",
    "sg:province":"IN",
    "sg:tags":[
        "concrete",
        "product"
    ],
    "wof:name":"Ray's Concrete",
    "wof:placetype":"venue"
},
  "geometry": {"coordinates":[-85.297591,40.588639],"type":"Point"}
}