{
  "type": "Feature",
  "properties": {
    "iso:country":"US",
    "sg:address":"124 E Rush St",
    "sg:city":"Kendallville",
    "sg:classifiers":[
        {
            "category":"Professional",
            "subcategory":"Business Services",
            "type":"Services"
        }
    ],
    "sg:phone":"+1 260 347 0930",
    "sg:postcode":"46755",
    "sg:province":"IN",
    "wof:name":"Noble Land Partners An Ind Ltd",
    "wof:placetype":"venue"
},
  "geometry": {"coordinates":[-85.263924,41.441396],"type":"Point"}
}