{
  "type": "Feature",
  "properties": {
    "iso:country":"US",
    "sg:address":"6020 E. 82nd St",
    "sg:city":"Indianapolis",
    "sg:classifiers":[
        {
            "category":"Personal",
            "subcategory":"Nail Salon",
            "type":"Services"
        }
    ],
    "sg:phone":"+1 317 578 3729",
    "sg:postcode":"46250",
    "sg:province":"IN",
    "wof:name":"Best Nails",
    "wof:placetype":"venue"
},
  "geometry": {"coordinates":[-86.063834,39.905345],"type":"Point"}
}