{
  "type": "Feature",
  "properties": {
    "addr:full":"3228 Southview Dr Elkhart IN 46514",
    "addr:housenumber":"3228",
    "addr:postcode":"46514",
    "addr:street":"Southview Dr",
    "iso:country":"US",
    "sg:address":"3228 Southview Dr",
    "sg:city":"Elkhart",
    "sg:classifiers":[
        {
            "category":"Freight",
            "type":"Transportation"
        }
    ],
    "sg:phone":"+1 574 266 0450",
    "sg:postcode":"46514",
    "sg:province":"IN",
    "sg:tags":[
        "commercial",
        "storage"
    ],
    "wof:name":"Spacemaker Self Storage",
    "wof:placetype":"venue"
},
  "geometry": {"coordinates":[-85.979546,41.734525],"type":"Point"}
}