{
  "type": "Feature",
  "properties": {
    "iso:country":"US",
    "sg:address":"508 W 5th St",
    "sg:city":"North Manchester",
    "sg:classifiers":[
        {
            "category":"Retail",
            "subcategory":"Auto Repair",
            "type":"Services"
        }
    ],
    "sg:phone":"+1 260 982 8860",
    "sg:postcode":"46962",
    "sg:province":"IN",
    "sg:tags":[
        "repairing",
        "automobile"
    ],
    "wof:name":"Lambert Auto Repair & Svc",
    "wof:placetype":"venue"
},
  "geometry": {"coordinates":[-85.776361,41.003368],"type":"Point"}
}