{
  "type": "Feature",
  "properties": {
    "iso:country":"US",
    "sg:address":"2220 E 44th St",
    "sg:city":"Indianapolis",
    "sg:classifiers":[
        {
            "category":"Manufacturing",
            "subcategory":"Signs",
            "type":"Manufacturing & Wholesale Goods"
        }
    ],
    "sg:phone":"+1 317 547 2844",
    "sg:postcode":"46205",
    "sg:province":"IN",
    "wof:name":"Signco",
    "wof:placetype":"venue"
},
  "geometry": {"coordinates":[-86.1221,39.836629],"type":"Point"}
}