{
  "type": "Feature",
  "properties": {
    "iso:country":"US",
    "sg:address":"3747 W Landis Rd",
    "sg:city":"Angola",
    "sg:classifiers":[
        {
            "category":"Building & Trades",
            "subcategory":"Construction",
            "type":"Services"
        }
    ],
    "sg:phone":"+1 260 665 9642",
    "sg:postcode":"46703",
    "sg:province":"IN",
    "sg:tags":[
        "general",
        "contractor"
    ],
    "wof:name":"Van Gordon Construction Inc",
    "wof:placetype":"venue"
},
  "geometry": {"coordinates":[-85.054957,41.661527],"type":"Point"}
}