{
  "type": "Feature",
  "properties": {
    "addr:full":"701 W Chippewa Ave South Bend IN 46614",
    "addr:housenumber":"701",
    "addr:postcode":"46614",
    "addr:street":"W Chippewa Ave",
    "iso:country":"US",
    "sg:address":"701 W Chippewa Ave",
    "sg:city":"South Bend",
    "sg:classifiers":[
        {
            "category":"Freight",
            "type":"Transportation"
        }
    ],
    "sg:phone":"+1 574 233 7604",
    "sg:postcode":"46614",
    "sg:province":"IN",
    "sg:tags":[
        "warehouse",
        "self",
        "storage",
        "general"
    ],
    "wof:name":"Chippewa Business Center",
    "wof:placetype":"venue"
},
  "geometry": {"coordinates":[-86.26493600000001,41.636058],"type":"Point"}
}