{
  "type": "Feature",
  "properties": {
    "iso:country":"US",
    "sg:address":"101 S Lafayette Blvd",
    "sg:city":"South Bend",
    "sg:classifiers":[
        {
            "category":"Autos & Motor Vehicles",
            "subcategory":"Fuel & Gas Station",
            "type":"Retail Goods"
        }
    ],
    "sg:phone":"+1 574 233 2885",
    "sg:postcode":"46601",
    "sg:province":"IN",
    "sg:tags":[
        "oil"
    ],
    "wof:name":"Babcock Marathon",
    "wof:placetype":"venue"
},
  "geometry": {"coordinates":[-86.253573,41.675675],"type":"Point"}
}