{
  "type": "Feature",
  "properties": {
    "addr:full":"7870 Broadway Ste 2XX Merrillville IN 46410",
    "addr:housenumber":"7870",
    "addr:postcode":"46410",
    "addr:street":"Broadway Ste 2Xx",
    "iso:country":"US",
    "sg:address":"7870 Broadway Ste 2XX",
    "sg:city":"Merrillville",
    "sg:classifiers":[
        {
            "category":"Professional",
            "subcategory":"Printing & Photocopies",
            "type":"Services"
        }
    ],
    "sg:phone":"+1 219 756 1212",
    "sg:postcode":"46410",
    "sg:province":"IN",
    "sg:tags":[
        "duplicating",
        "copying"
    ],
    "sg:website":"http://www.sirspeedy.com",
    "wof:name":"Sir Speedy Printing and Marketing Services",
    "wof:placetype":"venue"
},
  "geometry": {"coordinates":[-87.33592299999999,41.475866],"type":"Point"}
}