{
  "type": "Feature",
  "properties": {
    "iso:country":"US",
    "sg:address":"11055 Co Rd 2",
    "sg:city":"Middlebury",
    "sg:classifiers":[
        {
            "category":"Autos & Motor Vehicles",
            "subcategory":"Automobile Sales",
            "type":"Retail Goods"
        }
    ],
    "sg:phone":"+1 574 825 7773",
    "sg:postcode":"46540",
    "sg:province":"IN",
    "sg:tags":[
        "sport",
        "trailer",
        "utility"
    ],
    "wof:name":"John's Trailer Sales LLC",
    "wof:placetype":"venue"
},
  "geometry": {"coordinates":[-85.68119,41.755025],"type":"Point"}
}