{
  "type": "Feature",
  "properties": {
    "iso:country":"US",
    "sg:address":"777 W Main St",
    "sg:city":"Greensburg",
    "sg:classifiers":[
        {
            "category":"Retail",
            "subcategory":"Repair Shop",
            "type":"Services"
        }
    ],
    "sg:phone":"+1 812 663 2932",
    "sg:postcode":"47240",
    "sg:province":"IN",
    "sg:tags":[
        "refinishing",
        "furniture"
    ],
    "wof:name":"Superior Furniture Restoration",
    "wof:placetype":"venue"
},
  "geometry": {"coordinates":[-85.49729499999999,39.336393],"type":"Point"}
}