{
  "type": "Feature",
  "properties": {
    "iso:country":"US",
    "sg:address":"3121 W Mishawaka Ave",
    "sg:city":"South Bend",
    "sg:classifiers":[
        {
            "category":"Health Services",
            "subcategory":"Doctor",
            "type":"Services"
        }
    ],
    "sg:phone":"+1 574 288 9411",
    "sg:postcode":"46615",
    "sg:province":"IN",
    "sg:tags":[
        "dentist"
    ],
    "wof:name":"John C Glueckert DDS",
    "wof:placetype":"venue"
},
  "geometry": {"coordinates":[-86.203423,41.665797],"type":"Point"}
}