{
  "type": "Feature",
  "properties": {
    "iso:country":"US",
    "sg:address":"117 S Indiana Ave",
    "sg:city":"Sellersburg",
    "sg:classifiers":[
        {
            "category":"Professional",
            "subcategory":"Engineering",
            "type":"Services"
        }
    ],
    "sg:phone":"+1 812 246 5897",
    "sg:postcode":"47172",
    "sg:province":"IN",
    "sg:tags":[
        "engineer"
    ],
    "wof:name":"Renaissance Design Build Inc",
    "wof:placetype":"venue"
},
  "geometry": {"coordinates":[-85.756518,38.398063],"type":"Point"}
}