{
  "type": "Feature",
  "properties": {
    "iso:country":"US",
    "sg:address":"317 S Cavin St",
    "sg:city":"Ligonier",
    "sg:classifiers":[
        {
            "category":"Retail",
            "subcategory":"Laundry & Dry Cleaning",
            "type":"Services"
        }
    ],
    "sg:phone":"+1 260 894 3614",
    "sg:postcode":"46767",
    "sg:province":"IN",
    "sg:tags":[
        "cleaners"
    ],
    "wof:name":"Toggery Cleaners",
    "wof:placetype":"venue"
},
  "geometry": {"coordinates":[-85.587537,41.463195],"type":"Point"}
}