{
  "type": "Feature",
  "properties": {
    "iso:country":"US",
    "sg:address":"7614 State Rd 64",
    "sg:city":"Georgetown",
    "sg:classifiers":[
        {
            "category":"Health Services",
            "subcategory":"Doctor",
            "type":"Services"
        }
    ],
    "sg:phone":"+1 812 951 1540",
    "sg:postcode":"47122",
    "sg:province":"IN",
    "sg:tags":[
        "dentist"
    ],
    "wof:name":"William T Steinwedel DDS",
    "wof:placetype":"venue"
},
  "geometry": {"coordinates":[-85.949709,38.294809],"type":"Point"}
}