{
  "type": "Feature",
  "properties": {
    "addr:full":"6695 Broadway Merrillville IN 46410",
    "addr:housenumber":"6695",
    "addr:postcode":"46410",
    "addr:street":"Broadway",
    "iso:country":"US",
    "sg:address":"6695 Broadway",
    "sg:city":"Merrillville",
    "sg:classifiers":[
        {
            "category":"Insurance",
            "subcategory":"Insurance Agent",
            "type":"Services"
        }
    ],
    "sg:phone":"+1 219 736 6000",
    "sg:postcode":"46410",
    "sg:province":"IN",
    "wof:name":"Pampalone Insurance",
    "wof:placetype":"venue"
},
  "geometry": {"coordinates":[-87.336118,41.498608],"type":"Point"}
}