{
  "type": "Feature",
  "properties": {
    "iso:country":"US",
    "sg:address":"428 N Market St",
    "sg:city":"Monon",
    "sg:classifiers":[
        {
            "category":"Organizations",
            "subcategory":"Labor Organization",
            "type":"Services"
        }
    ],
    "sg:phone":"+1 219 253 6565",
    "sg:postcode":"47959",
    "sg:province":"IN",
    "wof:name":"Carpenters",
    "wof:placetype":"venue"
},
  "geometry": {"coordinates":[-86.879145,40.863943],"type":"Point"}
}