{
  "type": "Feature",
  "properties": {
    "iso:country":"US",
    "sg:address":"2518 N Arlington Ave",
    "sg:city":"Indianapolis",
    "sg:classifiers":[
        {
            "category":"Organizations",
            "subcategory":"Religious Organization",
            "type":"Services"
        }
    ],
    "sg:phone":"+1 317 541 0524",
    "sg:postcode":"46218",
    "sg:province":"IN",
    "sg:tags":[
        "church"
    ],
    "wof:name":"Mt Lebanon Baptist Church",
    "wof:placetype":"venue"
},
  "geometry": {"coordinates":[-86.064647,39.805292],"type":"Point"}
}