{
  "type": "Feature",
  "properties": {
    "iso:country":"US",
    "sg:address":"411 E 18th St",
    "sg:city":"New Albany",
    "sg:classifiers":[
        {
            "category":"Retail",
            "subcategory":"Repair Shop",
            "type":"Services"
        }
    ],
    "sg:phone":"+1 812 945 2636",
    "sg:postcode":"47150",
    "sg:province":"IN",
    "sg:tags":[
        "scooter",
        "motorcycle",
        "motor"
    ],
    "wof:name":"Finish Line Motorcycles",
    "wof:placetype":"venue"
},
  "geometry": {"coordinates":[-85.806097,38.294533],"type":"Point"}
}