{
  "type": "Feature",
  "properties": {
    "iso:country":"US",
    "sg:address":"1815 S Anthony Blvd",
    "sg:city":"Fort Wayne",
    "sg:classifiers":[
        {
            "category":"Wholesale",
            "subcategory":"Hardware",
            "type":"Manufacturing & Wholesale Goods"
        }
    ],
    "sg:phone":"+1 260 423 9577",
    "sg:postcode":"46803",
    "sg:province":"IN",
    "sg:tags":[
        "plumbing",
        "fixture",
        "supply"
    ],
    "wof:name":"Wayne Pipe & Supply Inc",
    "wof:placetype":"venue"
},
  "geometry": {"coordinates":[-85.114065,41.067278],"type":"Point"}
}