{
  "type": "Feature",
  "properties": {
    "iso:country":"US",
    "sg:address":"9 N Shortridge Rd",
    "sg:city":"Indianapolis",
    "sg:classifiers":[
        {
            "category":"Food & Beverages",
            "subcategory":"Liquor & Beverages",
            "type":"Retail Goods"
        }
    ],
    "sg:phone":"+1 317 359 9463",
    "sg:postcode":"46219",
    "sg:province":"IN",
    "wof:name":"USA Liquors",
    "wof:placetype":"venue"
},
  "geometry": {"coordinates":[-86.04055700000001,39.778009],"type":"Point"}
}