{
  "type": "Feature",
  "properties": {
    "iso:country":"US",
    "sg:address":"825 Elm St",
    "sg:city":"Valparaiso",
    "sg:classifiers":[
        {
            "category":"Building & Trades",
            "subcategory":"Equipment Rental",
            "type":"Services"
        }
    ],
    "sg:phone":"+1 219 476 4350",
    "sg:postcode":"46383",
    "sg:province":"IN",
    "sg:tags":[
        "contractor"
    ],
    "wof:name":"United Rentals Highway Tech",
    "wof:placetype":"venue"
},
  "geometry": {"coordinates":[-87.046795,41.474348],"type":"Point"}
}