{
  "type": "Feature",
  "properties": {
    "iso:country":"US",
    "sg:address":"500 Walnut St",
    "sg:city":"Evansville",
    "sg:classifiers":[
        {
            "category":"Autos & Motor Vehicles",
            "subcategory":"Automobile Sales",
            "type":"Retail Goods"
        }
    ],
    "sg:phone":"+1 812 428 7800",
    "sg:postcode":"47713",
    "sg:province":"IN",
    "sg:tags":[
        "car",
        "dealer"
    ],
    "sg:website":"www.dpatrickford.com",
    "wof:name":"D-Patrick Downtown Ford",
    "wof:placetype":"venue"
},
  "geometry": {"coordinates":[-87.567567,37.970977],"type":"Point"}
}