{
  "type": "Feature",
  "properties": {
    "iso:country":"US",
    "sg:address":"4026 E 82nd St",
    "sg:city":"Indianapolis",
    "sg:classifiers":[
        {
            "category":"Manufacturing",
            "subcategory":"Signs",
            "type":"Manufacturing & Wholesale Goods"
        }
    ],
    "sg:phone":"+1 317 845 5051",
    "sg:postcode":"46250",
    "sg:province":"IN",
    "sg:website":"www.fastsigns.com",
    "wof:name":"Fastsigns",
    "wof:placetype":"venue"
},
  "geometry": {"coordinates":[-86.089097,39.905808],"type":"Point"}
}