{
  "type": "Feature",
  "properties": {
    "iso:country":"US",
    "sg:address":"8695 State Rd 267",
    "sg:city":"Mooresville",
    "sg:classifiers":[
        {
            "category":"Home & Garden",
            "subcategory":"Hardware",
            "type":"Retail Goods"
        }
    ],
    "sg:phone":"+1 317 831 3071",
    "sg:postcode":"46158",
    "sg:province":"IN",
    "sg:tags":[
        "consulting",
        "business"
    ],
    "wof:name":"Construction Cost & Value",
    "wof:placetype":"venue"
},
  "geometry": {"coordinates":[-86.386751,39.637635],"type":"Point"}
}