{
  "type": "Feature",
  "properties": {
    "iso:country":"US",
    "sg:address":"7010 W Washington St",
    "sg:city":"Indianapolis",
    "sg:classifiers":[
        {
            "category":"Building & Trades",
            "subcategory":"Plumbing",
            "type":"Services"
        }
    ],
    "sg:phone":"+1 317 244 3543",
    "sg:postcode":"46241",
    "sg:province":"IN",
    "sg:tags":[
        "heating",
        "contractor"
    ],
    "wof:name":"John Knipe Heating & Cooling",
    "wof:placetype":"venue"
},
  "geometry": {"coordinates":[-86.284029,39.742551],"type":"Point"}
}