{
  "type": "Feature",
  "properties": {
    "iso:country":"US",
    "sg:address":"1316 E 7th St",
    "sg:city":"Auburn",
    "sg:classifiers":[
        {
            "category":"Health Services",
            "subcategory":"Doctor",
            "type":"Services"
        }
    ],
    "sg:phone":"+1 260 927 1410",
    "sg:postcode":"46706",
    "sg:province":"IN",
    "sg:tags":[
        "physician",
        "surgeon"
    ],
    "wof:name":"Fort Wayne Orthopedics",
    "wof:placetype":"venue"
},
  "geometry": {"coordinates":[-85.030802,41.367846],"type":"Point"}
}