{
  "type": "Feature",
  "properties": {
    "iso:country":"US",
    "sg:address":"912 Harlan St",
    "sg:city":"Indianapolis",
    "sg:classifiers":[
        {
            "category":"Wholesale",
            "subcategory":"Toys & Hobbies",
            "type":"Manufacturing & Wholesale Goods"
        }
    ],
    "sg:phone":"+1 317 423 3669",
    "sg:postcode":"46203",
    "sg:province":"IN",
    "sg:tags":[
        "wholesaler"
    ],
    "wof:name":"Michelle Wholesale Svc",
    "wof:placetype":"venue"
},
  "geometry": {"coordinates":[-86.126089,39.754384],"type":"Point"}
}