{
  "type": "Feature",
  "properties": {
    "iso:country":"US",
    "sg:address":"28713 Harrison Rd",
    "sg:city":"South Bend",
    "sg:phone":"+1 574 287 9943",
    "sg:postcode":"46619",
    "sg:province":"IN",
    "sg:tags":[
        "farm",
        "soybean"
    ],
    "wof:name":"Harry Carlton",
    "wof:placetype":"venue"
},
  "geometry": {"coordinates":[-86.421409,41.650187],"type":"Point"}
}