{
  "type": "Feature",
  "properties": {
    "iso:country":"US",
    "sg:address":"9616 Butt Rd",
    "sg:city":"Fort Wayne",
    "sg:classifiers":[
        {
            "category":"Farming",
            "subcategory":"Dairy Farm",
            "type":"Manufacturing & Wholesale Goods"
        }
    ],
    "sg:phone":"+1 260 625 4784",
    "sg:postcode":"46818",
    "sg:province":"IN",
    "wof:name":"Ray Ashbaugh",
    "wof:placetype":"venue"
},
  "geometry": {"coordinates":[-85.323205,41.165642],"type":"Point"}
}