{
  "type": "Feature",
  "properties": {
    "iso:country":"US",
    "sg:address":"2540 Eastbrook Plz",
    "sg:city":"Columbus",
    "sg:classifiers":[
        {
            "category":"Food & Beverages",
            "subcategory":"Groceries & Convenience Stores",
            "type":"Retail Goods"
        }
    ],
    "sg:phone":"+1 812 372 3420",
    "sg:postcode":"47201",
    "sg:province":"IN",
    "sg:tags":[
        "grocer"
    ],
    "wof:name":"Buehler's Save-A-Lot",
    "wof:placetype":"venue"
},
  "geometry": {"coordinates":[-85.89474199999999,39.225357],"type":"Point"}
}