{
  "type": "Feature",
  "properties": {
    "iso:country":"US",
    "sg:address":"438 E 4th St",
    "sg:city":"Williamsport",
    "sg:classifiers":[
        {
            "category":"Professional",
            "subcategory":"Management & Consulting",
            "type":"Services"
        }
    ],
    "sg:phone":"+1 765 427 3742",
    "sg:postcode":"47993",
    "sg:province":"IN",
    "sg:tags":[
        "business"
    ],
    "wof:name":"Snyder Environmental Services",
    "wof:placetype":"venue"
},
  "geometry": {"coordinates":[-87.288674,40.292338],"type":"Point"}
}