{
  "type": "Feature",
  "properties": {
    "iso:country":"US",
    "sg:address":"203 S Park Ave",
    "sg:city":"Rensselaer",
    "sg:classifiers":[
        {
            "category":"Building & Trades",
            "subcategory":"Construction",
            "type":"Services"
        }
    ],
    "sg:phone":"+1 219 866 8437",
    "sg:postcode":"47978",
    "sg:province":"IN",
    "sg:tags":[
        "operator",
        "builder",
        "apartment",
        "operative"
    ],
    "wof:name":"Huhn Real Estate",
    "wof:placetype":"venue"
},
  "geometry": {"coordinates":[-87.154,40.93372],"type":"Point"}
}