{
  "type": "Feature",
  "properties": {
    "iso:country":"US",
    "sg:address":"124 W Market St",
    "sg:city":"Bluffton",
    "sg:classifiers":[
        {
            "category":"Professional",
            "subcategory":"Lawyer & Legal Services",
            "type":"Services"
        }
    ],
    "sg:phone":"+1 260 824 4100",
    "sg:postcode":"46714",
    "sg:province":"IN",
    "sg:tags":[
        "attorney"
    ],
    "wof:name":"Weldy Law Office",
    "wof:placetype":"venue"
},
  "geometry": {"coordinates":[-85.171694,40.739705],"type":"Point"}
}