{
  "type": "Feature",
  "properties": {
    "addr:full":"630 Lincolnway E Goshen IN 46526",
    "addr:housenumber":"630;e",
    "addr:postcode":"46526",
    "addr:street":"Lincolnway",
    "iso:country":"US",
    "sg:address":"630 Lincolnway E",
    "sg:city":"Goshen",
    "sg:classifiers":[
        {
            "category":"Autos & Motor Vehicles",
            "subcategory":"Automobile Sales",
            "type":"Retail Goods"
        }
    ],
    "sg:phone":"+1 574 534 9935",
    "sg:postcode":"46526",
    "sg:province":"IN",
    "sg:tags":[
        "car",
        "dealer"
    ],
    "wof:name":"Rodney Weaver & Sons Auto Sale",
    "wof:placetype":"venue"
},
  "geometry": {"coordinates":[-85.82035500000001,41.57968],"type":"Point"}
}