{
  "type": "Feature",
  "properties": {
    "iso:country":"US",
    "sg:address":"2191 Woodland Trce",
    "sg:city":"Plainfield",
    "sg:classifiers":[
        {
            "category":"Organizations",
            "subcategory":"Community Association",
            "type":"Services"
        }
    ],
    "sg:phone":"+1 317 839 2844",
    "sg:postcode":"46168",
    "sg:province":"IN",
    "wof:name":"Avon Alliance Inc",
    "wof:placetype":"venue"
},
  "geometry": {"coordinates":[-86.391033,39.729878],"type":"Point"}
}