{
  "type": "Feature",
  "properties": {
    "iso:country":"US",
    "sg:address":"120 N Michigan St",
    "sg:city":"Plymouth",
    "sg:classifiers":[
        {
            "category":"Organizations",
            "subcategory":"Professional Association",
            "type":"Services"
        }
    ],
    "sg:phone":"+1 574 936 2323",
    "sg:postcode":"46563",
    "sg:province":"IN",
    "sg:tags":[
        "chambers",
        "commerce"
    ],
    "sg:website":"www.plychamber.org",
    "wof:name":"Chamber Of Commerce",
    "wof:placetype":"venue"
},
  "geometry": {"coordinates":[-86.309089,41.340661],"type":"Point"}
}