{
  "type": "Feature",
  "properties": {
    "iso:country":"US",
    "sg:address":"807 Oak Hill Rd",
    "sg:city":"Evansville",
    "sg:classifiers":[
        {
            "category":"Retail",
            "subcategory":"Repair Shop",
            "type":"Services"
        }
    ],
    "sg:phone":"+1 812 423 6494",
    "sg:postcode":"47711",
    "sg:province":"IN",
    "sg:tags":[
        "appliance"
    ],
    "wof:name":"Hagan Appliance",
    "wof:placetype":"venue"
},
  "geometry": {"coordinates":[-87.533132,37.984835],"type":"Point"}
}