{
  "type": "Feature",
  "properties": {
    "iso:country":"US",
    "sg:address":"905 S Main St",
    "sg:city":"Edinburgh",
    "sg:classifiers":[
        {
            "category":"Organizations",
            "subcategory":"Religious Organization",
            "type":"Services"
        }
    ],
    "sg:phone":"+1 812 526 2225",
    "sg:postcode":"46124",
    "sg:province":"IN",
    "wof:name":"Edinbrgh Sparate Baptst Church",
    "wof:placetype":"venue"
},
  "geometry": {"coordinates":[-85.967482,39.347462],"type":"Point"}
}