{
  "type": "Feature",
  "properties": {
    "iso:country":"US",
    "sg:address":"809 E 10th St",
    "sg:city":"Fowler",
    "sg:classifiers":[
        {
            "category":"Real Estate",
            "subcategory":"Real Estate Operator",
            "type":"Services"
        }
    ],
    "sg:phone":"+1 765 884 1754",
    "sg:postcode":"47944",
    "sg:province":"IN",
    "sg:tags":[
        "apartment"
    ],
    "wof:name":"Country Place Apartments",
    "wof:placetype":"venue"
},
  "geometry": {"coordinates":[-87.314611,40.613033],"type":"Point"}
}