{
  "type": "Feature",
  "properties": {
    "iso:country":"US",
    "sg:address":"4088 E Bethel Ln",
    "sg:city":"Bloomington",
    "sg:classifiers":[
        {
            "category":"Building & Trades",
            "subcategory":"Electrical",
            "type":"Services"
        }
    ],
    "sg:phone":"+1 812 336 8865",
    "sg:postcode":"47408",
    "sg:province":"IN",
    "sg:tags":[
        "electrical",
        "electric",
        "contractor"
    ],
    "wof:name":"Lone Wolf Electric Co",
    "wof:placetype":"venue"
},
  "geometry": {"coordinates":[-86.484899,39.213897],"type":"Point"}
}