{
  "type": "Feature",
  "properties": {
    "iso:country":"US",
    "sg:address":"5900 W Kilgore Ave",
    "sg:city":"Muncie",
    "sg:classifiers":[
        {
            "category":"Professional",
            "subcategory":"Management & Consulting",
            "type":"Services"
        }
    ],
    "sg:phone":"+1 765 284 7133",
    "sg:postcode":"47304",
    "sg:province":"IN",
    "sg:tags":[
        "consultant",
        "lighting"
    ],
    "wof:name":"BIC Products Inc",
    "wof:placetype":"venue"
},
  "geometry": {"coordinates":[-85.455457,40.181104],"type":"Point"}
}