{
  "type": "Feature",
  "properties": {
    "iso:country":"US",
    "sg:address":"8653 E 1400 N",
    "sg:city":"Syracuse",
    "sg:classifiers":[
        {
            "category":"Farming",
            "subcategory":"Farm",
            "type":"Manufacturing & Wholesale Goods"
        }
    ],
    "sg:phone":"+1 574 457 2987",
    "sg:postcode":"46567",
    "sg:province":"IN",
    "sg:tags":[
        "crop",
        "general"
    ],
    "wof:name":"Mikel Farms Inc",
    "wof:placetype":"venue"
},
  "geometry": {"coordinates":[-85.681383,41.436627],"type":"Point"}
}