{
  "type": "Feature",
  "properties": {
    "iso:country":"US",
    "sg:address":"919 S Harrison St",
    "sg:city":"Fort Wayne",
    "sg:classifiers":[
        {
            "category":"Professional",
            "subcategory":"Lawyer & Legal Services",
            "type":"Services"
        }
    ],
    "sg:phone":"+1 260 407 3907",
    "sg:postcode":"46802",
    "sg:province":"IN",
    "sg:tags":[
        "attorney"
    ],
    "wof:name":"O'Malley & Firestone",
    "wof:placetype":"venue"
},
  "geometry": {"coordinates":[-85.140574,41.077207],"type":"Point"}
}