{
  "type": "Feature",
  "properties": {
    "iso:country":"US",
    "sg:address":"510 S Home Ave",
    "sg:city":"Martinsville",
    "sg:classifiers":[
        {
            "category":"Social Services",
            "subcategory":"Child Care",
            "type":"Services"
        }
    ],
    "sg:phone":"+1 765 349 2930",
    "sg:postcode":"46151",
    "sg:province":"IN",
    "wof:name":"Wonderland Day Care",
    "wof:placetype":"venue"
},
  "geometry": {"coordinates":[-86.415391,39.422151],"type":"Point"}
}