{
  "type": "Feature",
  "properties": {
    "iso:country":"US",
    "sg:address":"357 Tanger Blvd",
    "sg:city":"Seymour",
    "sg:classifiers":[
        {
            "category":"Home & Garden",
            "subcategory":"Home Furnishings",
            "type":"Retail Goods"
        }
    ],
    "sg:phone":"+1 812 523 0978",
    "sg:postcode":"47274",
    "sg:province":"IN",
    "sg:tags":[
        "housewares"
    ],
    "wof:name":"Kitchen Collection",
    "wof:placetype":"venue"
},
  "geometry": {"coordinates":[-85.840363,38.960897],"type":"Point"}
}