{
  "type": "Feature",
  "properties": {
    "iso:country":"US",
    "sg:address":"17000 Willow Ridge Trl",
    "sg:city":"Fort Wayne",
    "sg:classifiers":[
        {
            "category":"Sports & Exercise",
            "subcategory":"Golf",
            "type":"Entertainment"
        }
    ],
    "sg:phone":"+1 260 637 3243",
    "sg:postcode":"46845",
    "sg:province":"IN",
    "sg:tags":[
        "course"
    ],
    "wof:name":"Willow Ridge Golf Club",
    "wof:placetype":"venue"
},
  "geometry": {"coordinates":[-85.162733,41.237788],"type":"Point"}
}