{
  "type": "Feature",
  "properties": {
    "iso:country":"US",
    "sg:address":"349 W Main St",
    "sg:city":"Butler",
    "sg:classifiers":[
        {
            "category":"Shopping",
            "subcategory":"Department Store",
            "type":"Retail Goods"
        }
    ],
    "sg:phone":"+1 260 868 5102",
    "sg:postcode":"46721",
    "sg:province":"IN",
    "sg:tags":[
        "shop"
    ],
    "wof:name":"Family Dollar Store",
    "wof:placetype":"venue"
},
  "geometry": {"coordinates":[-84.877962,41.429697],"type":"Point"}
}