{
  "type": "Feature",
  "properties": {
    "iso:country":"US",
    "sg:address":"1100 S Woodlawn Ave",
    "sg:city":"Bloomington",
    "sg:classifiers":[
        {
            "category":"Recreation",
            "type":"Entertainment"
        }
    ],
    "sg:phone":"+1 812 349 3780",
    "sg:postcode":"47401",
    "sg:province":"IN",
    "sg:tags":[
        "pool",
        "swimming"
    ],
    "wof:name":"Bryan Park Pool",
    "wof:placetype":"venue"
},
  "geometry": {"coordinates":[-86.52264,39.154147],"type":"Point"}
}