{
  "type": "Feature",
  "properties": {
    "iso:country":"US",
    "sg:address":"12464 Adams Rd",
    "sg:city":"Granger",
    "sg:classifiers":[
        {
            "category":"Shopping",
            "subcategory":"Department Store",
            "type":"Retail Goods"
        }
    ],
    "sg:phone":"+1 574 243 9913",
    "sg:postcode":"46530",
    "sg:province":"IN",
    "sg:tags":[
        "shop"
    ],
    "wof:name":"Dollar General",
    "wof:placetype":"venue"
},
  "geometry": {"coordinates":[-86.110292,41.753451],"type":"Point"}
}