{
  "type": "Feature",
  "properties": {
    "iso:country":"US",
    "sg:address":"10401 N Meridian St",
    "sg:city":"Indianapolis",
    "sg:classifiers":[
        {
            "category":"Professional",
            "subcategory":"Employment Agencies",
            "type":"Services"
        }
    ],
    "sg:phone":"+1 317 616 3712",
    "sg:postcode":"46290",
    "sg:province":"IN",
    "sg:website":"www.staffingsolutions.com",
    "wof:name":"Preeminent Staffing Solutions",
    "wof:placetype":"venue"
},
  "geometry": {"coordinates":[-86.15645000000001,39.938917],"type":"Point"}
}