{
  "type": "Feature",
  "properties": {
    "iso:country":"US",
    "sg:address":"957 Yorktown Rd",
    "sg:city":"Decatur",
    "sg:classifiers":[
        {
            "category":"Shopping",
            "subcategory":"Computers & Home Electronics",
            "type":"Retail Goods"
        }
    ],
    "sg:phone":"+1 260 728 2632",
    "sg:postcode":"46733",
    "sg:province":"IN",
    "sg:tags":[
        "equipment",
        "dealer"
    ],
    "wof:name":"Midwest Cam & Consulting Inc",
    "wof:placetype":"venue"
},
  "geometry": {"coordinates":[-84.899496,40.830958],"type":"Point"}
}