{
  "type": "Feature",
  "properties": {
    "iso:country":"US",
    "sg:address":"4810 Central Ave",
    "sg:city":"Indianapolis",
    "sg:classifiers":[
        {
            "category":"Professional",
            "subcategory":"Business Services",
            "type":"Services"
        }
    ],
    "sg:phone":"+1 317 283 8315",
    "sg:postcode":"46205",
    "sg:province":"IN",
    "sg:tags":[
        "convention",
        "meeting",
        "facility"
    ],
    "wof:name":"Great Lakes Training Assoc Inc",
    "wof:placetype":"venue"
},
  "geometry": {"coordinates":[-86.150037,39.842628],"type":"Point"}
}