{
  "type": "Feature",
  "properties": {
    "iso:country":"US",
    "sg:address":"5007 New Haven Ave",
    "sg:city":"Fort Wayne",
    "sg:classifiers":[
        {
            "category":"Building & Trades",
            "subcategory":"Construction",
            "type":"Services"
        }
    ],
    "sg:phone":"+1 260 493 2900",
    "sg:postcode":"46803",
    "sg:province":"IN",
    "sg:tags":[
        "roofing",
        "contractor"
    ],
    "wof:name":"C L Schust Co Inc",
    "wof:placetype":"venue"
},
  "geometry": {"coordinates":[-85.076143,41.069064],"type":"Point"}
}