{
  "type": "Feature",
  "properties": {
    "iso:country":"US",
    "sg:address":"1170 S 800 W",
    "sg:city":"Delphi",
    "sg:classifiers":[
        {
            "category":"Professional",
            "type":"Services"
        }
    ],
    "sg:phone":"+1 765 564 2091",
    "sg:postcode":"46923",
    "sg:province":"IN",
    "wof:name":"Howard Bros Inc",
    "wof:placetype":"venue"
},
  "geometry": {"coordinates":[-86.676726,40.530316],"type":"Point"}
}