{
  "type": "Feature",
  "properties": {
    "iso:country":"US",
    "sg:address":"240 E King St",
    "sg:city":"Franklin",
    "sg:classifiers":[
        {
            "category":"Building & Trades",
            "subcategory":"Construction",
            "type":"Services"
        }
    ],
    "sg:phone":"+1 317 346 7663",
    "sg:postcode":"46131",
    "sg:province":"IN",
    "sg:tags":[
        "roofing",
        "contractor"
    ],
    "wof:name":"Enduron Roofing & Sheet Metal",
    "wof:placetype":"venue"
},
  "geometry": {"coordinates":[-86.05221,39.482697],"type":"Point"}
}