{
  "type": "Feature",
  "properties": {
    "iso:country":"US",
    "sg:address":"2801 E Buick Cadillac Blvd",
    "sg:city":"Bloomington",
    "sg:classifiers":[
        {
            "category":"Banks & Credit Unions",
            "subcategory":"Investment Brokerage",
            "type":"Services"
        }
    ],
    "sg:phone":"+1 812 331 3440",
    "sg:postcode":"47401",
    "sg:province":"IN",
    "sg:tags":[
        "security"
    ],
    "wof:name":"Raymond James Securities Inc",
    "wof:placetype":"venue"
},
  "geometry": {"coordinates":[-86.493678,39.159103],"type":"Point"}
}