{
  "type": "Feature",
  "properties": {
    "addr:full":"127 W Berry St Fort Wayne IN 46802",
    "addr:housenumber":"127",
    "addr:postcode":"46802",
    "addr:street":"W Berry St",
    "iso:country":"US",
    "sg:address":"127 W Berry St",
    "sg:city":"Fort Wayne",
    "sg:classifiers":[
        {
            "category":"Banks & Credit Unions",
            "subcategory":"Bank",
            "type":"Services"
        }
    ],
    "sg:phone":"+1 260 467 5564",
    "sg:postcode":"46802",
    "sg:province":"IN",
    "sg:tags":[
        "company",
        "trust"
    ],
    "wof:name":"Star Investment Management",
    "wof:placetype":"venue"
},
  "geometry": {"coordinates":[-85.140049,41.079148],"type":"Point"}
}