{
  "type": "Feature",
  "properties": {
    "iso:country":"US",
    "sg:address":"1930 W 16th St",
    "sg:city":"Indianapolis",
    "sg:classifiers":[
        {
            "category":"Autos & Motor Vehicles",
            "subcategory":"Automobile Sales",
            "type":"Retail Goods"
        }
    ],
    "sg:phone":"+1 317 263 0002",
    "sg:postcode":"46202",
    "sg:province":"IN",
    "sg:tags":[
        "car",
        "dealer"
    ],
    "sg:website":"www.speedwayauto.com",
    "wof:name":"Speedway Volkswagen",
    "wof:placetype":"venue"
},
  "geometry": {"coordinates":[-86.193746,39.789312],"type":"Point"}
}