{
  "type": "Feature",
  "properties": {
    "iso:country":"US",
    "sg:address":"1501 Wabash St",
    "sg:city":"Michigan City",
    "sg:classifiers":[
        {
            "category":"Health Services",
            "subcategory":"Doctor",
            "type":"Services"
        }
    ],
    "sg:phone":"+1 219 878 1300",
    "sg:postcode":"46360",
    "sg:province":"IN",
    "wof:name":"Mirza Raheem MD",
    "wof:placetype":"venue"
},
  "geometry": {"coordinates":[-86.900086,41.706991],"type":"Point"}
}