{
  "type": "Feature",
  "properties": {
    "iso:country":"US",
    "sg:address":"302 Main St",
    "sg:city":"Vincennes",
    "sg:classifiers":[
        {
            "category":"Banks & Credit Unions",
            "subcategory":"Bank",
            "type":"Services"
        }
    ],
    "sg:phone":"+1 812 882 3050",
    "sg:postcode":"47591",
    "sg:province":"IN",
    "wof:name":"Regions",
    "wof:placetype":"venue"
},
  "geometry": {"coordinates":[-87.531532,38.679181],"type":"Point"}
}