{
  "type": "Feature",
  "properties": {
    "iso:country":"US",
    "sg:address":"3136 N National Rd",
    "sg:city":"Columbus",
    "sg:classifiers":[
        {
            "category":"Insurance",
            "subcategory":"Insurance Agent",
            "type":"Services"
        }
    ],
    "sg:phone":"+1 812 378 3279",
    "sg:postcode":"47201",
    "sg:province":"IN",
    "wof:name":"American Family Insurance",
    "wof:placetype":"venue"
},
  "geometry": {"coordinates":[-85.91109,39.230346],"type":"Point"}
}