{
  "type": "Feature",
  "properties": {
    "iso:country":"US",
    "sg:address":"100 Lincolnway E",
    "sg:city":"Osceola",
    "sg:classifiers":[
        {
            "category":"Wholesale",
            "subcategory":"Hardware",
            "type":"Manufacturing & Wholesale Goods"
        }
    ],
    "sg:phone":"+1 574 674 8878",
    "sg:postcode":"46561",
    "sg:province":"IN",
    "sg:tags":[
        "builder"
    ],
    "sg:website":"www.handle.com",
    "wof:name":"Hinges & Handles",
    "wof:placetype":"venue"
},
  "geometry": {"coordinates":[-86.069441,41.663174],"type":"Point"}
}