{
  "type": "Feature",
  "properties": {
    "iso:country":"US",
    "sg:address":"7796 Moller Rd",
    "sg:city":"Indianapolis",
    "sg:classifiers":[
        {
            "category":"Manufacturing",
            "subcategory":"Food",
            "type":"Manufacturing & Wholesale Goods"
        }
    ],
    "sg:phone":"+1 317 334 7744",
    "sg:postcode":"46268",
    "sg:province":"IN",
    "sg:tags":[
        "product",
        "manufacturer"
    ],
    "wof:name":"Millennium Foods LLC",
    "wof:placetype":"venue"
},
  "geometry": {"coordinates":[-86.256269,39.893846],"type":"Point"}
}