{
  "type": "Feature",
  "properties": {
    "iso:country":"US",
    "sg:address":"6620 Pierson Dr",
    "sg:city":"Indianapolis",
    "sg:classifiers":[
        {
            "category":"Restaurant",
            "type":"Food & Drink"
        }
    ],
    "sg:phone":"+1 317 240 6201",
    "sg:postcode":"46241",
    "sg:province":"IN",
    "sg:tags":[
        "caterer"
    ],
    "sg:website":"www.gategourmet.com",
    "wof:name":"Gate Gourmet",
    "wof:placetype":"venue"
},
  "geometry": {"coordinates":[-86.277129,39.738085],"type":"Point"}
}