{
  "type": "Feature",
  "properties": {
    "iso:country":"US",
    "sg:address":"120 W Maple St",
    "sg:city":"Jeffersonville",
    "sg:classifiers":[
        {
            "category":"Retail",
            "subcategory":"Funeral Services",
            "type":"Services"
        },
        {
            "category":"Professional",
            "subcategory":"Detective & Security Services",
            "type":"Services"
        },
        {
            "category":"Cemetery",
            "type":"Public Place"
        }
    ],
    "sg:phone":"+1 812 282 1356",
    "sg:postcode":"47130",
    "sg:province":"IN",
    "sg:tags":[
        "information",
        "advisory",
        "crematory",
        "director",
        "plans-pre-arranged",
        "embalmer"
    ],
    "sg:website":"http://www.cootsfuneralhome.com",
    "wof:name":"Coots Funeral Home",
    "wof:placetype":"venue"
},
  "geometry": {"coordinates":[-85.741579,38.272911],"type":"Point"}
}