{
  "type": "Feature",
  "properties": {
    "iso:country":"US",
    "sg:address":"10537 E Washington St",
    "sg:city":"Indianapolis",
    "sg:classifiers":[
        {
            "category":"Shopping",
            "subcategory":"Gifts & Souvenirs",
            "type":"Retail Goods"
        }
    ],
    "sg:phone":"+1 317 898 2662",
    "sg:postcode":"46229",
    "sg:province":"IN",
    "sg:tags":[
        "party",
        "supply"
    ],
    "sg:website":"www.partycity.com",
    "wof:name":"Party City",
    "wof:placetype":"venue"
},
  "geometry": {"coordinates":[-85.97174099999999,39.77569],"type":"Point"}
}