{
  "type": "Feature",
  "properties": {
    "iso:country":"US",
    "sg:address":"545 Wabash Ave",
    "sg:city":"Chesterton",
    "sg:classifiers":[
        {
            "category":"Building & Trades",
            "subcategory":"Cleaning & Sanitation",
            "type":"Services"
        },
        {
            "category":"Building & Trades",
            "subcategory":"Construction",
            "type":"Services"
        }
    ],
    "sg:phone":"+1 219 926 3241",
    "sg:postcode":"46304",
    "sg:province":"IN",
    "sg:tags":[
        "fireplace",
        "chimney",
        "contractor"
    ],
    "wof:name":"Flue Specialists",
    "wof:placetype":"venue"
},
  "geometry": {"coordinates":[-87.057231,41.613145],"type":"Point"}
}