{
  "type": "Feature",
  "properties": {
    "addr:full":"205 Ash St Henryville IN 47126",
    "addr:housenumber":"205",
    "addr:postcode":"47126",
    "addr:street":"Ash St",
    "iso:country":"US",
    "sg:address":"205 Ash St",
    "sg:city":"Henryville",
    "sg:classifiers":[
        {
            "category":"Autos & Motor Vehicles",
            "subcategory":"Automobile Sales",
            "type":"Retail Goods"
        }
    ],
    "sg:phone":"+1 812 294 1177",
    "sg:postcode":"47126",
    "sg:province":"IN",
    "sg:tags":[
        "car",
        "dealer"
    ],
    "wof:name":"Hill's Auto Sales",
    "wof:placetype":"venue"
},
  "geometry": {"coordinates":[-85.771092,38.540394],"type":"Point"}
}