{
  "type": "Feature",
  "properties": {
    "iso:country":"US",
    "sg:address":"9190 Budd Run Dr",
    "sg:city":"Indianapolis",
    "sg:classifiers":[
        {
            "category":"Banks & Credit Unions",
            "subcategory":"Financial Services",
            "type":"Services"
        }
    ],
    "sg:phone":"+1 317 595 0900",
    "sg:postcode":"46250",
    "sg:province":"IN",
    "sg:tags":[
        "broker",
        "mortgage"
    ],
    "wof:name":"Home Loan Group Inc the",
    "wof:placetype":"venue"
},
  "geometry": {"coordinates":[-86.06627400000001,39.92076],"type":"Point"}
}