{
  "type": "Feature",
  "properties": {
    "addr:full":"121 N Harrison St Shelbyville IN 46176",
    "addr:housenumber":"121",
    "addr:postcode":"46176",
    "addr:street":"N Harrison St",
    "iso:country":"US",
    "sg:address":"121 N Harrison St",
    "sg:city":"Shelbyville",
    "sg:classifiers":[
        {
            "category":"Home & Garden",
            "subcategory":"Garden Supply",
            "type":"Retail Goods"
        }
    ],
    "sg:phone":"+1 317 398 4208",
    "sg:postcode":"46176",
    "sg:province":"IN",
    "sg:tags":[
        "lawn",
        "mower"
    ],
    "wof:name":"Harrison Street Power Equipmen",
    "wof:placetype":"venue"
},
  "geometry": {"coordinates":[-85.777079,39.52558],"type":"Point"}
}