{
  "type": "Feature",
  "properties": {
    "iso:country":"US",
    "sg:address":"801 N Huntington St",
    "sg:city":"Syracuse",
    "sg:classifiers":[
        {
            "category":"Real Estate",
            "subcategory":"Real Estate Services",
            "type":"Services"
        }
    ],
    "sg:phone":"+1 574 457 4474",
    "sg:postcode":"46567",
    "sg:province":"IN",
    "sg:tags":[
        "company",
        "title"
    ],
    "wof:name":"Bodkin Abstract Co",
    "wof:placetype":"venue"
},
  "geometry": {"coordinates":[-85.753344,41.428446],"type":"Point"}
}