{
  "type": "Feature",
  "properties": {
    "iso:country":"US",
    "sg:address":"104 N 5th St",
    "sg:city":"Greencastle",
    "sg:classifiers":[
        {
            "category":"Banks & Credit Unions",
            "subcategory":"Bank",
            "type":"Services"
        }
    ],
    "sg:phone":"+1 765 653 5154",
    "sg:postcode":"46135",
    "sg:province":"IN",
    "sg:tags":[
        "loan",
        "real estate"
    ],
    "wof:name":"Citi Financial",
    "wof:placetype":"venue"
},
  "geometry": {"coordinates":[-86.83653200000001,39.646227],"type":"Point"}
}