{
  "type": "Feature",
  "properties": {
    "iso:country":"US",
    "sg:address":"7973 Calumet Ave",
    "sg:city":"Munster",
    "sg:classifiers":[
        {
            "category":"Real Estate",
            "subcategory":"Real Estate Agent",
            "type":"Services"
        }
    ],
    "sg:phone":"+1 219 513 0039",
    "sg:postcode":"46321",
    "sg:province":"IN",
    "wof:name":"St Andrews Properties Inc",
    "wof:placetype":"venue"
},
  "geometry": {"coordinates":[-87.508955,41.567928],"type":"Point"}
}