{
  "type": "Feature",
  "properties": {
    "iso:country":"US",
    "sg:address":"4530 Bluffton Rd",
    "sg:city":"Fort Wayne",
    "sg:classifiers":[
        {
            "category":"Restaurant",
            "type":"Food & Drink"
        }
    ],
    "sg:phone":"+1 260 478 4906",
    "sg:postcode":"46809",
    "sg:province":"IN",
    "sg:tags":[
        "banquet",
        "rooms"
    ],
    "wof:name":"Winchester Place",
    "wof:placetype":"venue"
},
  "geometry": {"coordinates":[-85.16634500000001,41.0367],"type":"Point"}
}