{
  "type": "Feature",
  "properties": {
    "iso:country":"US",
    "sg:address":"5930 W Jefferson Blvd",
    "sg:city":"Fort Wayne",
    "sg:classifiers":[
        {
            "category":"Professional",
            "subcategory":"Management & Consulting",
            "type":"Services"
        }
    ],
    "sg:phone":"+1 260 459 3350",
    "sg:postcode":"46804",
    "sg:province":"IN",
    "sg:tags":[
        "training",
        "sales"
    ],
    "wof:name":"Troyer School Of Real Estate",
    "wof:placetype":"venue"
},
  "geometry": {"coordinates":[-85.219143,41.059103],"type":"Point"}
}