{
  "type": "Feature",
  "properties": {
    "iso:country":"US",
    "sg:address":"1930 Indiana Ave",
    "sg:city":"Anderson",
    "sg:classifiers":[
        {
            "category":"Home & Garden",
            "subcategory":"Building Materials",
            "type":"Retail Goods"
        }
    ],
    "sg:phone":"+1 765 642 7734",
    "sg:postcode":"46012",
    "sg:province":"IN",
    "sg:tags":[
        "roofing"
    ],
    "wof:name":"Mac Supply",
    "wof:placetype":"venue"
},
  "geometry": {"coordinates":[-85.682007,40.134689],"type":"Point"}
}