{
  "type": "Feature",
  "properties": {
    "iso:country":"US",
    "sg:address":"1009 McCord Rd",
    "sg:city":"Valparaiso",
    "sg:classifiers":[
        {
            "category":"Real Estate",
            "subcategory":"Real Estate Operator",
            "type":"Services"
        }
    ],
    "sg:phone":"+1 219 531 7504",
    "sg:postcode":"46383",
    "sg:province":"IN",
    "sg:tags":[
        "apartment"
    ],
    "wof:name":"Woodside Terrace Apartments",
    "wof:placetype":"venue"
},
  "geometry": {"coordinates":[-87.047835,41.481901],"type":"Point"}
}