{
  "type": "Feature",
  "properties": {
    "iso:country":"US",
    "sg:address":"804 Gerry Ln",
    "sg:city":"Madison",
    "sg:classifiers":[
        {
            "category":"Wholesale",
            "subcategory":"Metals & Minerals",
            "type":"Manufacturing & Wholesale Goods"
        }
    ],
    "sg:phone":"+1 812 265 6450",
    "sg:postcode":"47250",
    "sg:province":"IN",
    "sg:tags":[
        "product",
        "laminated",
        "structural"
    ],
    "wof:name":"Overlay Panel Products Inc",
    "wof:placetype":"venue"
},
  "geometry": {"coordinates":[-85.376411,38.739648],"type":"Point"}
}