{
  "type": "Feature",
  "properties": {
    "iso:country":"US",
    "sg:address":"7984 E 700 S",
    "sg:city":"Upland",
    "sg:classifiers":[
        {
            "category":"Wholesale",
            "subcategory":"Construction Materials",
            "type":"Manufacturing & Wholesale Goods"
        }
    ],
    "sg:phone":"+1 765 998 2050",
    "sg:postcode":"46989",
    "sg:province":"IN",
    "sg:tags":[
        "sand",
        "gravel"
    ],
    "wof:name":"Jack Himelick Gravel Co",
    "wof:placetype":"venue"
},
  "geometry": {"coordinates":[-85.52648,40.452051],"type":"Point"}
}