{
  "type": "Feature",
  "properties": {
    "iso:country":"US",
    "sg:address":"102 S Main St",
    "sg:city":"Morocco",
    "sg:classifiers":[
        {
            "category":"Retail",
            "subcategory":"Auto Repair",
            "type":"Services"
        }
    ],
    "sg:phone":"+1 219 285 6945",
    "sg:postcode":"47963",
    "sg:province":"IN",
    "sg:tags":[
        "muffler",
        "exhaust",
        "system"
    ],
    "wof:name":"G & S Repair Ctr",
    "wof:placetype":"venue"
},
  "geometry": {"coordinates":[-87.45481599999999,40.946117],"type":"Point"}
}