{
  "type": "Feature",
  "properties": {
    "iso:country":"US",
    "sg:address":"29 N Washington St",
    "sg:city":"Worthington",
    "sg:classifiers":[
        {
            "category":"Retail",
            "subcategory":"Laundry & Dry Cleaning",
            "type":"Services"
        }
    ],
    "sg:phone":"+1 812 875 3299",
    "sg:postcode":"47471",
    "sg:province":"IN",
    "wof:name":"Four Season Laundry & Tanning",
    "wof:placetype":"venue"
},
  "geometry": {"coordinates":[-86.976308,39.118781],"type":"Point"}
}