{
  "type": "Feature",
  "properties": {
    "iso:country":"US",
    "sg:address":"1616 N Franklin St",
    "sg:city":"Portland",
    "sg:classifiers":[
        {
            "category":"Government",
            "subcategory":"Fire Station",
            "type":"Public Place"
        }
    ],
    "sg:phone":"+1 260 726 4500",
    "sg:postcode":"47371",
    "sg:province":"IN",
    "sg:tags":[
        "department"
    ],
    "wof:name":"Portland Fire Dept",
    "wof:placetype":"venue"
},
  "geometry": {"coordinates":[-84.981648,40.447856],"type":"Point"}
}