{
  "type": "Feature",
  "properties": {
    "iso:country":"US",
    "sg:address":"10155 College Ave N",
    "sg:city":"Indianapolis",
    "sg:classifiers":[
        {
            "category":"Building & Trades",
            "subcategory":"Construction",
            "type":"Services"
        }
    ],
    "sg:phone":"+1 317 575 9677",
    "sg:postcode":"46280",
    "sg:province":"IN",
    "sg:tags":[
        "carpentry",
        "contractor",
        "electrical",
        "mfg"
    ],
    "wof:name":"E & E Garage Doors",
    "wof:placetype":"venue"
},
  "geometry": {"coordinates":[-86.145839,39.933848],"type":"Point"}
}