{
  "type": "Feature",
  "properties": {
    "iso:country":"US",
    "sg:address":"3308 E 10th St",
    "sg:city":"Indianapolis",
    "sg:classifiers":[
        {
            "category":"Building & Trades",
            "subcategory":"Equipment Rental",
            "type":"Services"
        }
    ],
    "sg:phone":"+1 317 632 1600",
    "sg:postcode":"46201",
    "sg:province":"IN",
    "sg:tags":[
        "audio",
        "leasing"
    ],
    "wof:name":"Sound Citi",
    "wof:placetype":"venue"
},
  "geometry": {"coordinates":[-86.108849,39.781449],"type":"Point"}
}