{
  "type": "Feature",
  "properties": {
    "iso:country":"US",
    "sg:address":"210 N Market St",
    "sg:city":"Winamac",
    "sg:classifiers":[
        {
            "category":"Shopping",
            "subcategory":"Music",
            "type":"Retail Goods"
        }
    ],
    "sg:phone":"+1 574 946 7788",
    "sg:postcode":"46996",
    "sg:province":"IN",
    "sg:tags":[
        "video",
        "disc",
        "tape",
        "cassette"
    ],
    "wof:name":"Best Lil' Video Inc",
    "wof:placetype":"venue"
},
  "geometry": {"coordinates":[-86.604956,41.052624],"type":"Point"}
}