{
  "type": "Feature",
  "properties": {
    "addr:full":"2210 N 735 W Shipshewana IN 46565",
    "addr:housenumber":"2210",
    "addr:postcode":"46565",
    "addr:street":"N 735 W",
    "iso:country":"US",
    "sg:address":"2210 N 735 W",
    "sg:city":"Shipshewana",
    "sg:classifiers":[
        {
            "category":"Farming",
            "subcategory":"Livestock Farm",
            "type":"Manufacturing & Wholesale Goods"
        }
    ],
    "sg:phone":"+1 260 768 7167",
    "sg:postcode":"46565",
    "sg:province":"IN",
    "sg:tags":[
        "beef",
        "corn",
        "crop",
        "field",
        "cattle",
        "feedlot"
    ],
    "wof:name":"Lane Maple Farm",
    "wof:placetype":"venue"
},
  "geometry": {"coordinates":[-85.568539,41.672108],"type":"Point"}
}