{
  "type": "Feature",
  "properties": {
    "addr:full":"6370 Scatterfield Rd Anderson IN 46013",
    "addr:housenumber":"6370",
    "addr:postcode":"46013",
    "addr:street":"Scatterfield Rd",
    "iso:country":"US",
    "sg:address":"6370 Scatterfield Rd",
    "sg:city":"Anderson",
    "sg:classifiers":[
        {
            "category":"Home & Garden",
            "subcategory":"Carpets & Floor Coverings",
            "type":"Retail Goods"
        }
    ],
    "sg:phone":"+1 765 622 0623",
    "sg:postcode":"46013",
    "sg:province":"IN",
    "sg:tags":[
        "material"
    ],
    "wof:name":"Newport's Outlet Store",
    "wof:placetype":"venue"
},
  "geometry": {"coordinates":[-85.65280300000001,40.051797],"type":"Point"}
}