{
  "type": "Feature",
  "properties": {
    "addr:full":"7425 S State Rd 55 Oxford IN 47971",
    "addr:housenumber":"7425;55",
    "addr:postcode":"47971",
    "addr:street":"S State Rd",
    "iso:country":"US",
    "sg:address":"7425 S State Rd 55",
    "sg:city":"Oxford",
    "sg:classifiers":[
        {
            "category":"Real Estate",
            "subcategory":"Real Estate Operator",
            "type":"Services"
        }
    ],
    "sg:phone":"+1 765 385 2650",
    "sg:postcode":"47971",
    "sg:province":"IN",
    "sg:tags":[
        "property",
        "lessor"
    ],
    "wof:name":"Don Atkinson",
    "wof:placetype":"venue"
},
  "geometry": {"coordinates":[-87.254491,40.498394],"type":"Point"}
}