{
  "type": "Feature",
  "properties": {
    "iso:country":"US",
    "sg:address":"1506 Mary Dr",
    "sg:city":"Indianapolis",
    "sg:classifiers":[
        {
            "category":"Retail",
            "subcategory":"Repair Shop",
            "type":"Services"
        }
    ],
    "sg:phone":"+1 317 487 5625",
    "sg:postcode":"46241",
    "sg:province":"IN",
    "sg:tags":[
        "lock",
        "locksmith"
    ],
    "wof:name":"A-1 Key Masters 24 Hour Safe",
    "wof:placetype":"venue"
},
  "geometry": {"coordinates":[-86.287744,39.74141],"type":"Point"}
}