{
  "type": "Feature",
  "properties": {
    "addr:full":"635 Barnhill Dr Ms4067a Indianapolis IN 46202",
    "addr:housenumber":"635",
    "addr:postcode":"46202",
    "addr:street":"Barnhill Dr",
    "iso:country":"US",
    "sg:address":"635 Barnhill Dr Ms4067a",
    "sg:city":"Indianapolis",
    "sg:classifiers":[
        {
            "category":"Professional",
            "subcategory":"Employment Agencies",
            "type":"Services"
        }
    ],
    "sg:phone":"+1 317 274 0549",
    "sg:postcode":"46202",
    "sg:province":"IN",
    "sg:tags":[
        "employer"
    ],
    "wof:name":"Ronald C Wek",
    "wof:placetype":"venue"
},
  "geometry": {"coordinates":[-86.17861499999999,39.776719],"type":"Point"}
}