{
  "type": "Feature",
  "properties": {
    "iso:country":"US",
    "sg:address":"1227 Audubon Rd",
    "sg:city":"New Castle",
    "sg:classifiers":[
        {
            "category":"Professional",
            "subcategory":"Art Services",
            "type":"Services"
        }
    ],
    "sg:phone":"+1 765 521 9190",
    "sg:postcode":"47362",
    "sg:province":"IN",
    "sg:tags":[
        "graphic",
        "designer"
    ],
    "wof:name":"M H Creative",
    "wof:placetype":"venue"
},
  "geometry": {"coordinates":[-85.372131,39.92078],"type":"Point"}
}