{
  "type": "Feature",
  "properties": {
    "iso:country":"US",
    "sg:address":"2760 Gerry St",
    "sg:city":"Gary",
    "sg:classifiers":[
        {
            "category":"Home & Garden",
            "subcategory":"Mobile Homes",
            "type":"Retail Goods"
        }
    ],
    "sg:phone":"+1 219 844 4785",
    "sg:postcode":"46406",
    "sg:province":"IN",
    "wof:name":"Gerry Park For Mobile Homes",
    "wof:placetype":"venue"
},
  "geometry": {"coordinates":[-87.405398,41.568809],"type":"Point"}
}