{
  "type": "Feature",
  "properties": {
    "iso:country":"US",
    "sg:address":"4443 W Western Ave",
    "sg:city":"South Bend",
    "sg:classifiers":[
        {
            "category":"Retail",
            "subcategory":"Auto Repair",
            "type":"Services"
        }
    ],
    "sg:phone":"+1 574 235 8473",
    "sg:postcode":"46619",
    "sg:province":"IN",
    "sg:tags":[
        "repairing",
        "automobile"
    ],
    "wof:name":"D C Tire & Auto",
    "wof:placetype":"venue"
},
  "geometry": {"coordinates":[-86.30896300000001,41.67194],"type":"Point"}
}