{
  "type": "Feature",
  "properties": {
    "iso:country":"US",
    "sg:address":"13630 N Meridian St",
    "sg:city":"Carmel",
    "sg:classifiers":[
        {
            "category":"Personal",
            "subcategory":"Beauty Salon",
            "type":"Services"
        }
    ],
    "sg:phone":"+1 317 208 3223",
    "sg:postcode":"46032",
    "sg:province":"IN",
    "sg:tags":[
        "treatment",
        "skin"
    ],
    "wof:name":"Face One Eighty",
    "wof:placetype":"venue"
},
  "geometry": {"coordinates":[-86.14009,39.985515],"type":"Point"}
}