{
  "type": "Feature",
  "properties": {
    "iso:country":"US",
    "sg:address":"5433 Madison Ave",
    "sg:city":"Indianapolis",
    "sg:classifiers":[
        {
            "category":"Autos & Motor Vehicles",
            "subcategory":"Automobile Sales",
            "type":"Retail Goods"
        }
    ],
    "sg:phone":"+1 317 784 8044",
    "sg:postcode":"46227",
    "sg:province":"IN",
    "sg:tags":[
        "car",
        "dealer"
    ],
    "wof:name":"Eskew Motors",
    "wof:placetype":"venue"
},
  "geometry": {"coordinates":[-86.13495899999999,39.688474],"type":"Point"}
}