{
  "type": "Feature",
  "properties": {
    "addr:full":"3617 W US Hwy 40 Greenfield IN 46140",
    "addr:housenumber":"3617",
    "addr:postcode":"46140",
    "addr:street":"W Us Hwy 40",
    "iso:country":"US",
    "sg:address":"3617 W US Hwy 40",
    "sg:city":"Greenfield",
    "sg:classifiers":[
        {
            "category":"Building & Trades",
            "subcategory":"Construction",
            "type":"Services"
        }
    ],
    "sg:phone":"+1 317 462 7288",
    "sg:postcode":"46140",
    "sg:province":"IN",
    "sg:tags":[
        "house"
    ],
    "wof:name":"Spectrum Homes Inc",
    "wof:placetype":"venue"
},
  "geometry": {"coordinates":[-85.867879,39.780588],"type":"Point"}
}