{
  "type": "Feature",
  "properties": {
    "iso:country":"US",
    "sg:address":"1747 E Margaret Ave",
    "sg:city":"Terre Haute",
    "sg:classifiers":[
        {
            "category":"Professional",
            "subcategory":"Research",
            "type":"Services"
        }
    ],
    "sg:phone":"+1 812 235 6042",
    "sg:postcode":"47802",
    "sg:province":"IN",
    "sg:tags":[
        "environmental",
        "ecological"
    ],
    "wof:name":"Cortez Environmental Svc LLC",
    "wof:placetype":"venue"
},
  "geometry": {"coordinates":[-87.392624,39.433691],"type":"Point"}
}