{
  "type": "Feature",
  "properties": {
    "iso:country":"US",
    "sg:address":"300 E Prairie St",
    "sg:city":"Warsaw",
    "sg:classifiers":[
        {
            "category":"Social Services",
            "subcategory":"Job Training",
            "type":"Services"
        }
    ],
    "sg:phone":"+1 574 267 7679",
    "sg:postcode":"46580",
    "sg:province":"IN",
    "sg:tags":[
        "rehabilitation"
    ],
    "wof:name":"Rehab Care Group",
    "wof:placetype":"venue"
},
  "geometry": {"coordinates":[-85.85439599999999,41.233111],"type":"Point"}
}