{
  "type": "Feature",
  "properties": {
    "iso:country":"US",
    "sg:address":"3600 N Hobart Rd Ste C",
    "sg:city":"Hobart",
    "sg:classifiers":[
        {
            "category":"Arts & Performance",
            "subcategory":"Arts Center",
            "type":"Entertainment"
        },
        {
            "category":"Personal",
            "subcategory":"Skin Care",
            "type":"Services"
        },
        {
            "category":"Personal",
            "subcategory":"Tanning Parlor",
            "type":"Services"
        }
    ],
    "sg:phone":"+1 219 963 7576",
    "sg:postcode":"46342",
    "sg:province":"IN",
    "sg:tags":[
        "salon",
        "brush",
        "air"
    ],
    "wof:name":"Evening Sun Tan",
    "wof:placetype":"venue"
},
  "geometry": {"coordinates":[-87.239357,41.505459],"type":"Point"}
}