{
  "type": "Feature",
  "properties": {
    "iso:country":"US",
    "sg:address":"11401 Lantern Rd",
    "sg:city":"Fishers",
    "sg:classifiers":[
        {
            "category":"Professional",
            "subcategory":"Computer Services",
            "type":"Services"
        }
    ],
    "sg:phone":"+1 317 585 0500",
    "sg:postcode":"46038",
    "sg:province":"IN",
    "sg:tags":[
        "internet"
    ],
    "wof:name":"P C Help Svc Inc",
    "wof:placetype":"venue"
},
  "geometry": {"coordinates":[-86.01385,39.952674],"type":"Point"}
}