{
  "type": "Feature",
  "properties": {
    "iso:country":"US",
    "sg:address":"7205 Overlook Cv",
    "sg:city":"Georgetown",
    "sg:classifiers":[
        {
            "category":"Manufacturing",
            "subcategory":"Wood Products",
            "type":"Manufacturing & Wholesale Goods"
        }
    ],
    "sg:phone":"+1 812 923 2510",
    "sg:postcode":"47122",
    "sg:province":"IN",
    "sg:tags":[
        "veneers-wholesale",
        "plywood",
        "manufacturer"
    ],
    "wof:name":"Bryan Sales Co.",
    "wof:placetype":"venue"
},
  "geometry": {"coordinates":[-85.939334,38.330073],"type":"Point"}
}