{
  "type": "Feature",
  "properties": {
    "iso:country":"US",
    "sg:address":"19020 N State Rd 1",
    "sg:city":"Spencerville",
    "sg:classifiers":[
        {
            "category":"Manufacturing",
            "subcategory":"Musical Instruments",
            "type":"Manufacturing & Wholesale Goods"
        }
    ],
    "sg:phone":"+1 260 238 2000",
    "sg:postcode":"46788",
    "sg:province":"IN",
    "wof:name":"Grem USA",
    "wof:placetype":"venue"
},
  "geometry": {"coordinates":[-84.948538,41.261506],"type":"Point"}
}