{
  "type": "Feature",
  "properties": {
    "iso:country":"US",
    "sg:address":"4403 N Capitol Ave",
    "sg:city":"Indianapolis",
    "sg:classifiers":[
        {
            "category":"Manufacturing",
            "subcategory":"Furniture",
            "type":"Manufacturing & Wholesale Goods"
        }
    ],
    "sg:phone":"+1 317 821 9187",
    "sg:postcode":"46208",
    "sg:province":"IN",
    "sg:tags":[
        "drapery",
        "mfg"
    ],
    "wof:name":"Budget Blinds of Indiana",
    "wof:placetype":"venue"
},
  "geometry": {"coordinates":[-86.161615,39.836608],"type":"Point"}
}