{
  "type": "Feature",
  "properties": {
    "addr:full":"129 W Main St Portland IN 47371",
    "addr:housenumber":"129",
    "addr:postcode":"47371",
    "addr:street":"W Main St",
    "iso:country":"US",
    "sg:address":"129 W Main St",
    "sg:city":"Portland",
    "sg:classifiers":[
        {
            "category":"Real Estate",
            "subcategory":"Real Estate Services",
            "type":"Services"
        }
    ],
    "sg:phone":"+1 260 726 6466",
    "sg:postcode":"47371",
    "sg:province":"IN",
    "sg:tags":[
        "company",
        "title"
    ],
    "wof:name":"Jay Portland Abstract Co",
    "wof:placetype":"venue"
},
  "geometry": {"coordinates":[-84.97833199999999,40.433274],"type":"Point"}
}