{
  "type": "Feature",
  "properties": {
    "iso:country":"US",
    "sg:address":"5318 W US Hwy 40",
    "sg:city":"Greenfield",
    "sg:classifiers":[
        {
            "category":"Personal",
            "subcategory":"Beauty Salon",
            "type":"Services"
        }
    ],
    "sg:phone":"+1 317 894 4323",
    "sg:postcode":"46140",
    "sg:province":"IN",
    "wof:name":"Country Clips & Do's",
    "wof:placetype":"venue"
},
  "geometry": {"coordinates":[-85.895031,39.779522],"type":"Point"}
}