{
  "type": "Feature",
  "properties": {
    "iso:country":"US",
    "sg:address":"2241 State St",
    "sg:city":"New Albany",
    "sg:classifiers":[
        {
            "category":"Communications",
            "subcategory":"Film & Video Production",
            "type":"Services"
        }
    ],
    "sg:phone":"+1 812 948 2771",
    "sg:postcode":"47150",
    "sg:province":"IN",
    "sg:tags":[
        "motion"
    ],
    "wof:name":"Sound Specialist Dj Service",
    "wof:placetype":"venue"
},
  "geometry": {"coordinates":[-85.840127,38.305192],"type":"Point"}
}