{
  "type": "Feature",
  "properties": {
    "iso:country":"US",
    "sg:address":"1001 Main St",
    "sg:city":"Anderson",
    "sg:classifiers":[
        {
            "category":"Government",
            "subcategory":"Post Office",
            "type":"Public Place"
        }
    ],
    "sg:phone":"+1 765 000 1111",
    "sg:postcode":"46016",
    "sg:province":"IN",
    "wof:name":"US Post Office",
    "wof:placetype":"venue"
},
  "geometry": {"coordinates":[-85.678168,40.105103],"type":"Point"}
}