{
  "type": "Feature",
  "properties": {
    "iso:country":"US",
    "sg:address":"2810 N Granville Ave",
    "sg:city":"Muncie",
    "sg:classifiers":[
        {
            "category":"Personal",
            "subcategory":"Beauty Salon",
            "type":"Services"
        }
    ],
    "sg:phone":"+1 765 284 9977",
    "sg:postcode":"47303",
    "sg:province":"IN",
    "sg:tags":[
        "shop"
    ],
    "wof:name":"Glorias Hair Center",
    "wof:placetype":"venue"
},
  "geometry": {"coordinates":[-85.376773,40.215859],"type":"Point"}
}