{
  "type": "Feature",
  "properties": {
    "iso:country":"US",
    "sg:address":"70 N Main St",
    "sg:city":"Bloomingdale",
    "sg:classifiers":[
        {
            "category":"Wholesale",
            "subcategory":"Chemicals & Plastics",
            "type":"Manufacturing & Wholesale Goods"
        }
    ],
    "sg:phone":"+1 765 498 8900",
    "sg:postcode":"47882",
    "sg:province":"IN",
    "wof:name":"Formflex Inc",
    "wof:placetype":"venue"
},
  "geometry": {"coordinates":[-87.407111,39.095698],"type":"Point"}
}