{
  "type": "Feature",
  "properties": {
    "iso:country":"US",
    "sg:address":"915 N 3rd St",
    "sg:city":"Logansport",
    "sg:classifiers":[
        {
            "category":"Personal",
            "subcategory":"Beauty Salon",
            "type":"Services"
        }
    ],
    "sg:phone":"+1 574 753 6038",
    "sg:postcode":"46947",
    "sg:province":"IN",
    "wof:name":"House Of Beauty",
    "wof:placetype":"venue"
},
  "geometry": {"coordinates":[-86.370312,40.758839],"type":"Point"}
}