{
  "type": "Feature",
  "properties": {
    "addr:full":"7440 Rockville Rd Indianapolis IN 46214",
    "addr:housenumber":"7440",
    "addr:postcode":"46214",
    "addr:street":"Rockville Rd",
    "iso:country":"US",
    "sg:address":"7440 Rockville Rd",
    "sg:city":"Indianapolis",
    "sg:classifiers":[
        {
            "category":"Food & Beverages",
            "subcategory":"Liquor & Beverages",
            "type":"Retail Goods"
        }
    ],
    "sg:phone":"+1 317 271 2717",
    "sg:postcode":"46214",
    "sg:province":"IN",
    "wof:name":"Rockville Liquors",
    "wof:placetype":"venue"
},
  "geometry": {"coordinates":[-86.290927,39.764262],"type":"Point"}
}