{
  "type": "Feature",
  "properties": {
    "iso:country":"US",
    "sg:address":"132 S Main St",
    "sg:city":"Batesville",
    "sg:classifiers":[
        {
            "category":"Government",
            "subcategory":"Office",
            "type":"Public Place"
        },
        {
            "category":"Government",
            "subcategory":"Court House",
            "type":"Public Place"
        }
    ],
    "sg:phone":"+1 812 933 6102",
    "sg:postcode":"47006",
    "sg:province":"IN",
    "sg:tags":[
        "city"
    ],
    "wof:name":"Batesville Court Clerk",
    "wof:placetype":"venue"
},
  "geometry": {"coordinates":[-85.223545,39.297193],"type":"Point"}
}