{
  "type": "Feature",
  "properties": {
    "addr:full":"802 W Wayne St Fort Wayne IN 46802",
    "addr:housenumber":"802",
    "addr:postcode":"46802",
    "addr:street":"W Wayne St",
    "iso:country":"US",
    "sg:address":"802 W Wayne St",
    "sg:city":"Fort Wayne",
    "sg:classifiers":[
        {
            "category":"Organizations",
            "subcategory":"Professional Association",
            "type":"Services"
        }
    ],
    "sg:phone":"+1 260 426 1170",
    "sg:postcode":"46802",
    "sg:province":"IN",
    "wof:name":"American Lung Assn",
    "wof:placetype":"venue"
},
  "geometry": {"coordinates":[-85.150929,41.076546],"type":"Point"}
}