{
  "type": "Feature",
  "properties": {
    "addr:full":"2292 W 86th St Indianapolis IN 46260",
    "addr:housenumber":"2292",
    "addr:postcode":"46260",
    "addr:street":"W 86Th St",
    "iso:country":"US",
    "sg:address":"2292 W 86th St",
    "sg:city":"Indianapolis",
    "sg:classifiers":[
        {
            "category":"Shopping",
            "subcategory":"Florist",
            "type":"Retail Goods"
        }
    ],
    "sg:phone":"+1 317 875 3030",
    "sg:postcode":"46260",
    "sg:province":"IN",
    "wof:name":"Andrews Florists",
    "wof:placetype":"venue"
},
  "geometry": {"coordinates":[-86.201043,39.912042],"type":"Point"}
}