{
  "type": "Feature",
  "properties": {
    "iso:country":"US",
    "sg:address":"3112 Venture Blvd",
    "sg:city":"Bloomington",
    "sg:classifiers":[
        {
            "category":"Professional",
            "subcategory":"Accounting & Tax Preparation",
            "type":"Services"
        }
    ],
    "sg:phone":"+1 812 336 2847",
    "sg:postcode":"47404",
    "sg:province":"IN",
    "sg:tags":[
        "accountant"
    ],
    "wof:name":"Langley Ron & Assoc Inc",
    "wof:placetype":"venue"
},
  "geometry": {"coordinates":[-86.567001,39.177399],"type":"Point"}
}