{
  "type": "Feature",
  "properties": {
    "iso:country":"US",
    "sg:address":"211 E Garro St",
    "sg:city":"Plymouth",
    "sg:classifiers":[
        {
            "category":"Autos & Motor Vehicles",
            "subcategory":"Auto Supplies",
            "type":"Retail Goods"
        }
    ],
    "sg:phone":"+1 574 941 4446",
    "sg:postcode":"46563",
    "sg:province":"IN",
    "sg:tags":[
        "automobile",
        "parts"
    ],
    "wof:name":"Hoffman Brothers Auto Parts",
    "wof:placetype":"venue"
},
  "geometry": {"coordinates":[-86.306277,41.341119],"type":"Point"}
}