{
  "type": "Feature",
  "properties": {
    "addr:full":"2436 Old Hobart Rd Lake Station IN 46405",
    "addr:housenumber":"2436",
    "addr:postcode":"46405",
    "addr:street":"Old Hobart Rd",
    "iso:country":"US",
    "sg:address":"2436 Old Hobart Rd",
    "sg:city":"Lake Station",
    "sg:classifiers":[
        {
            "category":"Professional",
            "type":"Services"
        }
    ],
    "sg:phone":"+1 219 962 5407",
    "sg:postcode":"46405",
    "sg:province":"IN",
    "wof:name":"M Mary Statum",
    "wof:placetype":"venue"
},
  "geometry": {"coordinates":[-87.25399,41.565412],"type":"Point"}
}