{
  "type": "Feature",
  "properties": {
    "addr:full":"4540 N Shadeland Ave Indianapolis IN 46226",
    "addr:housenumber":"4540",
    "addr:postcode":"46226",
    "addr:street":"N Shadeland Ave",
    "iso:country":"US",
    "sg:address":"4540 N Shadeland Ave",
    "sg:city":"Indianapolis",
    "sg:classifiers":[
        {
            "category":"Food & Beverages",
            "subcategory":"Supermarket",
            "type":"Retail Goods"
        },
        {
            "category":"Food & Beverages",
            "subcategory":"Groceries & Convenience Stores",
            "type":"Retail Goods"
        }
    ],
    "sg:phone":"+1 317 542 0501",
    "sg:postcode":"46226",
    "sg:province":"IN",
    "sg:tags":[
        "super"
    ],
    "wof:name":"Safeway",
    "wof:placetype":"venue"
},
  "geometry": {"coordinates":[-86.04602800000001,39.83868],"type":"Point"}
}