{
  "type": "Feature",
  "properties": {
    "iso:country":"US",
    "sg:address":"23674 Creek Park Dr",
    "sg:city":"Elkhart",
    "sg:classifiers":[
        {
            "category":"Professional",
            "subcategory":"Management & Consulting",
            "type":"Services"
        }
    ],
    "sg:phone":"+1 574 875 7330",
    "sg:postcode":"46517",
    "sg:province":"IN",
    "sg:tags":[
        "business"
    ],
    "wof:name":"Chx Consulting Inc",
    "wof:placetype":"venue"
},
  "geometry": {"coordinates":[-85.918316,41.624862],"type":"Point"}
}