{
  "type": "Feature",
  "properties": {
    "iso:country":"US",
    "sg:address":"5 Executive Dr",
    "sg:city":"Lafayette",
    "sg:classifiers":[
        {
            "category":"Insurance",
            "subcategory":"Insurance Agent",
            "type":"Services"
        }
    ],
    "sg:phone":"+1 765 474 7310",
    "sg:postcode":"47905",
    "sg:province":"IN",
    "wof:name":"Farm Bureau Insurance",
    "wof:placetype":"venue"
},
  "geometry": {"coordinates":[-86.84371899999999,40.417651],"type":"Point"}
}