{
  "type": "Feature",
  "properties": {
    "iso:country":"US",
    "sg:address":"4106 Merchant Rd",
    "sg:city":"Fort Wayne",
    "sg:classifiers":[
        {
            "category":"Home & Garden",
            "subcategory":"Garden Supply",
            "type":"Retail Goods"
        }
    ],
    "sg:phone":"+1 260 490 9096",
    "sg:postcode":"46818",
    "sg:province":"IN",
    "sg:tags":[
        "sprinkler"
    ],
    "wof:name":"Kenney Corp",
    "wof:placetype":"venue"
},
  "geometry": {"coordinates":[-85.194475,41.136959],"type":"Point"}
}