{
  "type": "Feature",
  "properties": {
    "iso:country":"US",
    "sg:address":"202 N Meridian St",
    "sg:city":"Portland",
    "sg:classifiers":[
        {
            "category":"Cinema",
            "subcategory":"Movie Theater",
            "type":"Entertainment"
        }
    ],
    "sg:phone":"+1 260 726 7489",
    "sg:postcode":"47371",
    "sg:province":"IN",
    "wof:name":"Ritz Theatre",
    "wof:placetype":"venue"
},
  "geometry": {"coordinates":[-84.977987,40.435335],"type":"Point"}
}