{
  "type": "Feature",
  "properties": {
    "addr:full":"811 W McGalliard Rd Muncie IN 47303",
    "addr:housenumber":"811",
    "addr:postcode":"47303",
    "addr:street":"W Mcgalliard Rd",
    "iso:country":"US",
    "sg:address":"811 W McGalliard Rd",
    "sg:city":"Muncie",
    "sg:classifiers":[
        {
            "category":"Shopping",
            "subcategory":"Stationery & Office Supplies",
            "type":"Retail Goods"
        }
    ],
    "sg:phone":"+1 765 213 9900",
    "sg:postcode":"47303",
    "sg:province":"IN",
    "sg:tags":[
        "album",
        "scrapbook"
    ],
    "wof:name":"Scrapaholics",
    "wof:placetype":"venue"
},
  "geometry": {"coordinates":[-85.395905,40.218881],"type":"Point"}
}