{
  "type": "Feature",
  "properties": {
    "iso:country":"US",
    "sg:address":"214 W 13th St",
    "sg:city":"Jasper",
    "sg:classifiers":[
        {
            "category":"Social Services",
            "type":"Services"
        }
    ],
    "sg:phone":"+1 812 481 2442",
    "sg:postcode":"47546",
    "sg:province":"IN",
    "sg:tags":[
        "youth",
        "organization",
        "center"
    ],
    "wof:name":"St John Bosco Youth Ministries",
    "wof:placetype":"venue"
},
  "geometry": {"coordinates":[-86.932373,38.396658],"type":"Point"}
}