{
  "type": "Feature",
  "properties": {
    "iso:country":"US",
    "sg:address":"7402 S Arlington Ave",
    "sg:city":"Indianapolis",
    "sg:classifiers":[
        {
            "category":"Freight",
            "type":"Transportation"
        }
    ],
    "sg:phone":"+1 317 881 0490",
    "sg:postcode":"46237",
    "sg:province":"IN",
    "sg:tags":[
        "arrangement"
    ],
    "wof:name":"Weishaar Global Guidance Svcs",
    "wof:placetype":"venue"
},
  "geometry": {"coordinates":[-86.06368000000001,39.662334],"type":"Point"}
}