{
  "type": "Feature",
  "properties": {
    "iso:country":"US",
    "sg:address":"2500 W Ridge Rd",
    "sg:city":"Gary",
    "sg:classifiers":[
        {
            "category":"Retail",
            "subcategory":"Auto Repair",
            "type":"Services"
        }
    ],
    "sg:phone":"+1 219 884 5918",
    "sg:postcode":"46408",
    "sg:province":"IN",
    "sg:tags":[
        "repairing",
        "automobile"
    ],
    "wof:name":"Mike's Emission Clinic Inc",
    "wof:placetype":"venue"
},
  "geometry": {"coordinates":[-87.369103,41.548073],"type":"Point"}
}