{
  "type": "Feature",
  "properties": {
    "iso:country":"US",
    "sg:address":"1104 Conner St",
    "sg:city":"Noblesville",
    "sg:classifiers":[
        {
            "category":"Health Services",
            "subcategory":"Doctor",
            "type":"Services"
        }
    ],
    "sg:phone":"+1 317 773 0278",
    "sg:postcode":"46060",
    "sg:province":"IN",
    "sg:tags":[
        "dentist"
    ],
    "wof:name":"Robert L Holloway DDS",
    "wof:placetype":"venue"
},
  "geometry": {"coordinates":[-86.010751,40.045675],"type":"Point"}
}