{
  "type": "Feature",
  "properties": {
    "iso:country":"US",
    "sg:address":"1601 N College Ave",
    "sg:city":"Indianapolis",
    "sg:classifiers":[
        {
            "category":"Food & Beverages",
            "subcategory":"Liquor & Beverages",
            "type":"Retail Goods"
        }
    ],
    "sg:phone":"+1 317 925 1332",
    "sg:postcode":"46202",
    "sg:province":"IN",
    "wof:name":"Community Spirits",
    "wof:placetype":"venue"
},
  "geometry": {"coordinates":[-86.144739,39.790301],"type":"Point"}
}