{
  "type": "Feature",
  "properties": {
    "addr:full":"38 N Van Buren St Nashville IN 47448",
    "addr:housenumber":"38",
    "addr:postcode":"47448",
    "addr:street":"N Van Buren St",
    "iso:country":"US",
    "sg:address":"38 N Van Buren St",
    "sg:city":"Nashville",
    "sg:classifiers":[
        {
            "category":"Restaurant",
            "type":"Food & Drink"
        }
    ],
    "sg:phone":"+1 812 988 2355",
    "sg:postcode":"47448",
    "sg:province":"IN",
    "wof:name":"That Sandwich Place",
    "wof:placetype":"venue"
},
  "geometry": {"coordinates":[-86.246871,39.208131],"type":"Point"}
}