{
  "type": "Feature",
  "properties": {
    "addr:full":"2612 Charlestown Rd New Albany IN 47150",
    "addr:postcode":"2612;47150",
    "addr:street":"Charlestown Rd",
    "iso:country":"US",
    "sg:address":"2612 Charlestown Rd",
    "sg:city":"New Albany",
    "sg:classifiers":[
        {
            "category":"Professional",
            "subcategory":"Accounting & Tax Preparation",
            "type":"Services"
        }
    ],
    "sg:phone":"+1 812 945 2275",
    "sg:postcode":"47150",
    "sg:province":"IN",
    "sg:tags":[
        "return",
        "filing"
    ],
    "wof:name":"H & R Block Tax Svc",
    "wof:placetype":"venue"
},
  "geometry": {"coordinates":[-85.804407,38.316098],"type":"Point"}
}