{
  "type": "Feature",
  "properties": {
    "iso:country":"US",
    "sg:address":"1601 S 15th St",
    "sg:city":"Vincennes",
    "sg:classifiers":[
        {
            "category":"Wholesale",
            "subcategory":"Auto Parts",
            "type":"Manufacturing & Wholesale Goods"
        }
    ],
    "sg:phone":"+1 812 882 3414",
    "sg:postcode":"47591",
    "sg:province":"IN",
    "sg:tags":[
        "automobile",
        "rebuilt"
    ],
    "wof:name":"Parker Auto Parts Inc",
    "wof:placetype":"venue"
},
  "geometry": {"coordinates":[-87.53742099999999,38.659744],"type":"Point"}
}