{
  "type": "Feature",
  "properties": {
    "iso:country":"US",
    "sg:address":"1900 W Kem Rd",
    "sg:city":"Marion",
    "sg:classifiers":[
        {
            "category":"Health Services",
            "subcategory":"Podiatrist",
            "type":"Services"
        }
    ],
    "sg:phone":"+1 765 664 0107",
    "sg:postcode":"46952",
    "sg:province":"IN",
    "wof:name":"Riverside Podiatry Clinic Inc",
    "wof:placetype":"venue"
},
  "geometry": {"coordinates":[-85.685568,40.574616],"type":"Point"}
}