{
  "type": "Feature",
  "properties": {
    "iso:country":"US",
    "sg:address":"7041 W 21st Ave",
    "sg:city":"Gary",
    "sg:classifiers":[
        {
            "category":"Manufacturing",
            "subcategory":"Tools & Machinery",
            "type":"Manufacturing & Wholesale Goods"
        }
    ],
    "sg:phone":"+1 219 844 8389",
    "sg:postcode":"46406",
    "sg:province":"IN",
    "sg:tags":[
        "equipment",
        "vehicular",
        "lighting"
    ],
    "wof:name":"Hoosier Electric",
    "wof:placetype":"venue"
},
  "geometry": {"coordinates":[-87.424085,41.580755],"type":"Point"}
}