{
  "type": "Feature",
  "properties": {
    "addr:full":"301 E Waterford St Wakarusa IN 46573",
    "addr:housenumber":"301",
    "addr:postcode":"46573",
    "addr:street":"E Waterford St",
    "iso:country":"US",
    "sg:address":"301 E Waterford St",
    "sg:city":"Wakarusa",
    "sg:classifiers":[
        {
            "category":"Government",
            "subcategory":"Fire Station",
            "type":"Public Place"
        }
    ],
    "sg:phone":"+1 574 862 4850",
    "sg:postcode":"46573",
    "sg:province":"IN",
    "wof:name":"Wakarusa Fire Department",
    "wof:placetype":"venue"
},
  "geometry": {"coordinates":[-86.01551499999999,41.536125],"type":"Point"}
}