{
  "type": "Feature",
  "properties": {
    "iso:country":"US",
    "sg:address":"5801 Rockville Rd",
    "sg:city":"Indianapolis",
    "sg:classifiers":[
        {
            "category":"Restaurant",
            "type":"Food & Drink"
        }
    ],
    "sg:phone":"+1 317 244 7638",
    "sg:postcode":"46224",
    "sg:province":"IN",
    "wof:name":"Kazablanka",
    "wof:placetype":"venue"
},
  "geometry": {"coordinates":[-86.261805,39.764931],"type":"Point"}
}