{
  "type": "Feature",
  "properties": {
    "iso:country":"US",
    "sg:address":"4140 E 96th St",
    "sg:city":"Indianapolis",
    "sg:classifiers":[
        {
            "category":"Autos & Motor Vehicles",
            "subcategory":"Automobile Sales",
            "type":"Retail Goods"
        }
    ],
    "sg:phone":"+1 317 613 0320",
    "sg:postcode":"46240",
    "sg:province":"IN",
    "sg:tags":[
        "car",
        "dealer"
    ],
    "wof:name":"Dellen Automotive Family",
    "wof:placetype":"venue"
},
  "geometry": {"coordinates":[-86.095268,39.926955],"type":"Point"}
}