{
  "type": "Feature",
  "properties": {
    "addr:full":"3925 Rainbow Dr New Albany IN 47150",
    "addr:housenumber":"3925",
    "addr:postcode":"47150",
    "addr:street":"Rainbow Dr",
    "iso:country":"US",
    "sg:address":"3925 Rainbow Dr",
    "sg:city":"New Albany",
    "sg:classifiers":[
        {
            "category":"Recreation",
            "type":"Entertainment"
        }
    ],
    "sg:phone":"+1 812 949 0041",
    "sg:postcode":"47150",
    "sg:province":"IN",
    "sg:tags":[
        "club",
        "membership"
    ],
    "wof:name":"Soccer League of Ind Counties",
    "wof:placetype":"venue"
},
  "geometry": {"coordinates":[-85.800431,38.336046],"type":"Point"}
}