{
  "type": "Feature",
  "properties": {
    "iso:country":"US",
    "sg:address":"7720 E State Rd 4",
    "sg:city":"Walkerton",
    "sg:classifiers":[
        {
            "category":"Cinema",
            "subcategory":"Movie Theater",
            "type":"Entertainment"
        }
    ],
    "sg:phone":"+1 219 369 9440",
    "sg:postcode":"46574",
    "sg:province":"IN",
    "wof:name":"Fish Lake Movie Rental",
    "wof:placetype":"venue"
},
  "geometry": {"coordinates":[-86.549339,41.566306],"type":"Point"}
}