{
  "type": "Feature",
  "properties": {
    "iso:country":"US",
    "sg:address":"1503 W 8th St",
    "sg:city":"Anderson",
    "sg:classifiers":[
        {
            "category":"Home & Garden",
            "subcategory":"Household Appliances",
            "type":"Retail Goods"
        }
    ],
    "sg:phone":"+1 765 642 1883",
    "sg:postcode":"46016",
    "sg:province":"IN",
    "sg:tags":[
        "machine",
        "sewing"
    ],
    "wof:name":"Judy's Sewing Ctr",
    "wof:placetype":"venue"
},
  "geometry": {"coordinates":[-85.699122,40.107927],"type":"Point"}
}