{
  "type": "Feature",
  "properties": {
    "iso:country":"US",
    "sg:address":"808 E Chicago Ave",
    "sg:city":"East Chicago",
    "sg:classifiers":[
        {
            "category":"Cinema",
            "subcategory":"Movie Rental",
            "type":"Entertainment"
        }
    ],
    "sg:phone":"+1 219 397 8335",
    "sg:postcode":"46312",
    "sg:province":"IN",
    "sg:tags":[
        "leasing",
        "video",
        "disc",
        "tape"
    ],
    "wof:name":"East Chicago Video Inc",
    "wof:placetype":"venue"
},
  "geometry": {"coordinates":[-87.46175700000001,41.629307],"type":"Point"}
}