{
  "type": "Feature",
  "properties": {
    "iso:country":"US",
    "sg:address":"9650 S Voyles Rd",
    "sg:city":"Pekin",
    "sg:classifiers":[
        {
            "category":"Building & Trades",
            "subcategory":"Construction",
            "type":"Services"
        }
    ],
    "sg:phone":"+1 812 967 2450",
    "sg:postcode":"47165",
    "sg:province":"IN",
    "sg:tags":[
        "house"
    ],
    "wof:name":"Beckett Remodeling",
    "wof:placetype":"venue"
},
  "geometry": {"coordinates":[-86.005307,38.455672],"type":"Point"}
}