{
  "type": "Feature",
  "properties": {
    "iso:country":"US",
    "sg:address":"3263 N Denny St",
    "sg:city":"Indianapolis",
    "sg:classifiers":[
        {
            "category":"Shopping",
            "subcategory":"Clothing, Apparel, & Fashions",
            "type":"Retail Goods"
        }
    ],
    "sg:phone":"+1 317 545 6520",
    "sg:postcode":"46218",
    "sg:province":"IN",
    "sg:tags":[
        "alteration"
    ],
    "wof:name":"Michelle Alterations",
    "wof:placetype":"venue"
},
  "geometry": {"coordinates":[-86.101285,39.81499],"type":"Point"}
}