{
  "type": "Feature",
  "properties": {
    "iso:country":"US",
    "sg:address":"4470 N College Ave Ste 2",
    "sg:city":"Indianapolis",
    "sg:classifiers":[
        {
            "category":"Professional",
            "subcategory":"Art Services",
            "type":"Services"
        },
        {
            "category":"Professional",
            "subcategory":"Business Services",
            "type":"Services"
        }
    ],
    "sg:phone":"+1 317 924 5003",
    "sg:postcode":"46205",
    "sg:province":"IN",
    "sg:tags":[
        "development",
        "product",
        "graphic",
        "designers-industrial",
        "marketing",
        "commercial",
        "designer",
        "design"
    ],
    "wof:name":"Grove Design",
    "wof:placetype":"venue"
},
  "geometry": {"coordinates":[-86.14518700000001,39.837544],"type":"Point"}
}