{
  "type": "Feature",
  "properties": {
    "iso:country":"US",
    "sg:address":"325 S Summit Dr",
    "sg:city":"South Bend",
    "sg:classifiers":[
        {
            "category":"Professional",
            "subcategory":"Detective & Security Services",
            "type":"Services"
        }
    ],
    "sg:phone":"+1 574 289 7226",
    "sg:postcode":"46619",
    "sg:province":"IN",
    "sg:tags":[
        "guard",
        "patrol"
    ],
    "wof:name":"Mikolajewski & Assoc Inc",
    "wof:placetype":"venue"
},
  "geometry": {"coordinates":[-86.316518,41.670474],"type":"Point"}
}