{
  "type": "Feature",
  "properties": {
    "iso:country":"US",
    "sg:address":"200 Boyd Blvd",
    "sg:city":"Laporte",
    "sg:classifiers":[
        {
            "category":"Restaurant",
            "type":"Food & Drink"
        }
    ],
    "sg:phone":"+1 219 362 6717",
    "sg:postcode":"46350",
    "sg:province":"IN",
    "wof:name":"Mc Donald's",
    "wof:placetype":"venue"
},
  "geometry": {"coordinates":[-86.694224,41.621279],"type":"Point"}
}