{
  "type": "Feature",
  "properties": {
    "addr:full":"14 Public Sq Salem IN 47167",
    "addr:housenumber":"14",
    "addr:postcode":"47167",
    "addr:street":"Public Sq",
    "iso:country":"US",
    "sg:address":"14 Public Sq",
    "sg:city":"Salem",
    "sg:classifiers":[
        {
            "category":"Wholesale",
            "subcategory":"Non-durable Goods",
            "type":"Manufacturing & Wholesale Goods"
        }
    ],
    "sg:phone":"+1 812 883 1727",
    "sg:postcode":"47167",
    "sg:province":"IN",
    "sg:tags":[
        "leather",
        "repair",
        "retail",
        "shoe"
    ],
    "wof:name":"T & T Leather Station",
    "wof:placetype":"venue"
},
  "geometry": {"coordinates":[-86.101041,38.606121],"type":"Point"}
}