{
  "type": "Feature",
  "properties": {
    "iso:country":"US",
    "sg:address":"817 W Franklin St",
    "sg:city":"Elkhart",
    "sg:classifiers":[
        {
            "category":"Professional",
            "subcategory":"Lawyer & Legal Services",
            "type":"Services"
        }
    ],
    "sg:phone":"+1 574 296 6000",
    "sg:postcode":"46516",
    "sg:province":"IN",
    "sg:tags":[
        "attorney"
    ],
    "wof:name":"Baker & Daniels",
    "wof:placetype":"venue"
},
  "geometry": {"coordinates":[-85.982269,41.680961],"type":"Point"}
}