{
  "type": "Feature",
  "properties": {
    "iso:country":"US",
    "sg:address":"5287 W Walnut St",
    "sg:city":"Ireland",
    "sg:classifiers":[
        {
            "category":"Retail",
            "subcategory":"Auto Repair",
            "type":"Services"
        }
    ],
    "sg:phone":"+1 812 482 7544",
    "sg:postcode":"47546",
    "sg:province":"IN",
    "sg:tags":[
        "body",
        "automobile",
        "painting"
    ],
    "wof:name":"Ireland Auto Body",
    "wof:placetype":"venue"
},
  "geometry": {"coordinates":[-87.001692,38.415879],"type":"Point"}
}