{
  "type": "Feature",
  "properties": {
    "addr:full":"7339 Rockville Rd Indianapolis IN 46214",
    "addr:housenumber":"7339",
    "addr:postcode":"46214",
    "addr:street":"Rockville Rd",
    "iso:country":"US",
    "sg:address":"7339 Rockville Rd",
    "sg:city":"Indianapolis",
    "sg:classifiers":[
        {
            "category":"Coffee & Tea",
            "type":"Food & Drink"
        },
        {
            "category":"Restaurant",
            "type":"Food & Drink"
        },
        {
            "category":"Bakery",
            "type":"Food & Drink"
        },
        {
            "category":"Donuts",
            "type":"Food & Drink"
        }
    ],
    "sg:menulink":"http://www.allmenus.com/in/speedway/231163-daylight-donuts/menu/",
    "sg:phone":"+1 317 209 0615",
    "sg:postcode":"46214",
    "sg:province":"IN",
    "sg:tags":[
        "tea",
        "coffee",
        "bakery",
        "american",
        "pastry"
    ],
    "wof:name":"Daylight Donuts",
    "wof:placetype":"venue"
},
  "geometry": {"coordinates":[-86.290458,39.764253],"type":"Point"}
}