{
  "type": "Feature",
  "properties": {
    "iso:country":"US",
    "sg:address":"12 Public Sq",
    "sg:city":"Salem",
    "sg:classifiers":[
        {
            "category":"Professional",
            "subcategory":"Lawyer & Legal Services",
            "type":"Services"
        }
    ],
    "sg:phone":"+1 812 883 4171",
    "sg:postcode":"47167",
    "sg:province":"IN",
    "sg:tags":[
        "attorney"
    ],
    "sg:website":"www.allenlawyers.com",
    "wof:name":"Allen Allen & Allen",
    "wof:placetype":"venue"
},
  "geometry": {"coordinates":[-86.100856,38.606241],"type":"Point"}
}