{
  "type": "Feature",
  "properties": {
    "addr:full":"751 W Kenwood Ave Clarksville IN 47129",
    "addr:housenumber":"751",
    "addr:postcode":"47129",
    "addr:street":"W Kenwood Ave",
    "iso:country":"US",
    "sg:address":"751 W Kenwood Ave",
    "sg:city":"Clarksville",
    "sg:phone":"+1 812 282 5269",
    "sg:postcode":"47129",
    "sg:province":"IN",
    "sg:tags":[
        "scale"
    ],
    "wof:name":"Valley Scale Co LLC",
    "wof:placetype":"venue"
},
  "geometry": {"coordinates":[-85.769291,38.288578],"type":"Point"}
}