{
  "type": "Feature",
  "properties": {
    "iso:country":"US",
    "sg:address":"800 E Carr St",
    "sg:city":"Milan",
    "sg:classifiers":[
        {
            "category":"Freight",
            "type":"Transportation"
        }
    ],
    "sg:phone":"+1 812 654 2261",
    "sg:postcode":"47031",
    "sg:province":"IN",
    "sg:tags":[
        "operator",
        "local",
        "trucking"
    ],
    "wof:name":"Louden Trucking",
    "wof:placetype":"venue"
},
  "geometry": {"coordinates":[-85.112625,39.117592],"type":"Point"}
}