{
  "type": "Feature",
  "properties": {
    "addr:full":"1820 N Labrador Rd Monticello IN 47960",
    "addr:housenumber":"1820",
    "addr:postcode":"47960",
    "addr:street":"N Labrador Rd",
    "iso:country":"US",
    "sg:address":"1820 N Labrador Rd",
    "sg:city":"Monticello",
    "sg:classifiers":[
        {
            "category":"Retail",
            "subcategory":"Car Wash",
            "type":"Services"
        }
    ],
    "sg:phone":"+1 574 583 9399",
    "sg:postcode":"47960",
    "sg:province":"IN",
    "sg:tags":[
        "carwash",
        "automobile",
        "detail",
        "clean"
    ],
    "wof:name":"Paul's Auto Detailing",
    "wof:placetype":"venue"
},
  "geometry": {"coordinates":[-86.750809,40.777977],"type":"Point"}
}