{
  "type": "Feature",
  "properties": {
    "iso:country":"US",
    "sg:address":"201 W Court Ave",
    "sg:city":"Jeffersonville",
    "sg:classifiers":[
        {
            "category":"Banks & Credit Unions",
            "subcategory":"Bank",
            "type":"Services"
        }
    ],
    "sg:phone":"+1 812 285 1111",
    "sg:postcode":"47130",
    "sg:province":"IN",
    "sg:website":"www.heritagebanksi.com",
    "wof:name":"Community Bank",
    "wof:placetype":"venue"
},
  "geometry": {"coordinates":[-85.74441400000001,38.273229],"type":"Point"}
}