{
  "type": "Feature",
  "properties": {
    "addr:full":"13450 Violet Way Carmel IN 46032",
    "addr:housenumber":"13450",
    "addr:postcode":"46032",
    "addr:street":"Violet Way",
    "iso:country":"US",
    "sg:address":"13450 Violet Way",
    "sg:city":"Carmel",
    "sg:classifiers":[
        {
            "category":"Recreation",
            "type":"Entertainment"
        }
    ],
    "sg:phone":"+1 317 573 4200",
    "sg:postcode":"46032",
    "sg:province":"IN",
    "sg:tags":[
        "ticket"
    ],
    "sg:website":"www.ticketmania.com",
    "wof:name":"TICKETMANIA.COM",
    "wof:placetype":"venue"
},
  "geometry": {"coordinates":[-86.167643,39.981752],"type":"Point"}
}