{
  "type": "Feature",
  "properties": {
    "addr:full":"1331 W Boonville New Harmony Rd Evansville IN 47725",
    "addr:housenumber":"1331",
    "addr:postcode":"47725",
    "addr:street":"W;New Harmony Rd",
    "iso:country":"US",
    "sg:address":"1331 W Boonville New Harmony Rd",
    "sg:city":"Evansville",
    "sg:classifiers":[
        {
            "category":"Health Services",
            "subcategory":"Doctor",
            "type":"Services"
        }
    ],
    "sg:phone":"+1 812 867 6428",
    "sg:postcode":"47725",
    "sg:province":"IN",
    "sg:tags":[
        "dentist"
    ],
    "wof:name":"Johns & Bitzer",
    "wof:placetype":"venue"
},
  "geometry": {"coordinates":[-87.57975399999999,38.099581],"type":"Point"}
}