{
  "type": "Feature",
  "properties": {
    "iso:country":"US",
    "sg:address":"19688 Kern Rd",
    "sg:city":"South Bend",
    "sg:classifiers":[
        {
            "category":"Organizations",
            "subcategory":"Religious Organization",
            "type":"Services"
        }
    ],
    "sg:phone":"+1 574 291 7500",
    "sg:postcode":"46614",
    "sg:province":"IN",
    "sg:tags":[
        "church"
    ],
    "wof:name":"New Beginnings Community Fello",
    "wof:placetype":"venue"
},
  "geometry": {"coordinates":[-86.246711,41.608007],"type":"Point"}
}