{
  "type": "Feature",
  "properties": {
    "addr:full":"1517 High St South Bend IN 46613",
    "addr:housenumber":"1517",
    "addr:postcode":"46613",
    "addr:street":"High St",
    "iso:country":"US",
    "sg:address":"1517 High St",
    "sg:city":"South Bend",
    "sg:classifiers":[
        {
            "category":"Freight",
            "type":"Transportation"
        }
    ],
    "sg:phone":"+1 574 289 1495",
    "sg:postcode":"46613",
    "sg:province":"IN",
    "wof:name":"C L Harris Inc",
    "wof:placetype":"venue"
},
  "geometry": {"coordinates":[-86.239408,41.658763],"type":"Point"}
}