{
  "type": "Feature",
  "properties": {
    "iso:country":"US",
    "sg:address":"426 N Harbison Ave",
    "sg:city":"Indianapolis",
    "sg:classifiers":[
        {
            "category":"Personal",
            "subcategory":"Barber",
            "type":"Services"
        }
    ],
    "sg:phone":"+1 317 899 4154",
    "sg:postcode":"46219",
    "sg:province":"IN",
    "wof:name":"Barbershop Quartet Society",
    "wof:placetype":"venue"
},
  "geometry": {"coordinates":[-86.014781,39.778548],"type":"Point"}
}