{
  "type": "Feature",
  "properties": {
    "iso:country":"US",
    "sg:address":"624 E 3rd St",
    "sg:city":"Peru",
    "sg:classifiers":[
        {
            "category":"Retail",
            "subcategory":"Auto Repair",
            "type":"Services"
        }
    ],
    "sg:phone":"+1 765 472 4250",
    "sg:postcode":"46970",
    "sg:province":"IN",
    "sg:tags":[
        "body"
    ],
    "wof:name":"Jason Bowman Towing",
    "wof:placetype":"venue"
},
  "geometry": {"coordinates":[-86.049474,40.760833],"type":"Point"}
}