{
  "type": "Feature",
  "properties": {
    "addr:full":"24133 State Rd 2 South Bend IN 46619",
    "addr:housenumber":"24133",
    "addr:postcode":"46619",
    "addr:street":"State Rd 2",
    "iso:country":"US",
    "sg:address":"24133 State Rd 2",
    "sg:city":"South Bend",
    "sg:classifiers":[
        {
            "category":"Manufacturing",
            "subcategory":"Tools & Machinery",
            "type":"Manufacturing & Wholesale Goods"
        }
    ],
    "sg:phone":"+1 574 288 6899",
    "sg:postcode":"46619",
    "sg:province":"IN",
    "sg:tags":[
        "machine",
        "shop"
    ],
    "wof:name":"Frank's Machine Shop Tool",
    "wof:placetype":"venue"
},
  "geometry": {"coordinates":[-86.331863,41.671906],"type":"Point"}
}