{
  "type": "Feature",
  "properties": {
    "iso:country":"US",
    "sg:address":"654 Red Oak Way",
    "sg:city":"Mooresville",
    "sg:classifiers":[
        {
            "category":"Home & Garden",
            "subcategory":"Home Furnishings",
            "type":"Retail Goods"
        }
    ],
    "sg:phone":"+1 317 834 2065",
    "sg:postcode":"46158",
    "sg:province":"IN",
    "sg:tags":[
        "venetian",
        "blind"
    ],
    "wof:name":"Distinctive Glass",
    "wof:placetype":"venue"
},
  "geometry": {"coordinates":[-86.35710899999999,39.597409],"type":"Point"}
}