{
  "type": "Feature",
  "properties": {
    "iso:country":"US",
    "sg:address":"1640 S Olive St",
    "sg:city":"South Bend",
    "sg:classifiers":[
        {
            "category":"Manufacturing",
            "subcategory":"Metals",
            "type":"Manufacturing & Wholesale Goods"
        }
    ],
    "sg:phone":"+1 574 289 0100",
    "sg:postcode":"46619",
    "sg:province":"IN",
    "sg:tags":[
        "stamping"
    ],
    "sg:website":"www.metalstamps.com",
    "wof:name":"South Bend Metal Products Co",
    "wof:placetype":"venue"
},
  "geometry": {"coordinates":[-86.28293,41.656276],"type":"Point"}
}