{
  "type": "Feature",
  "properties": {
    "iso:country":"US",
    "sg:address":"230 E Broadway",
    "sg:city":"Logansport",
    "sg:classifiers":[
        {
            "category":"Retail",
            "subcategory":"Auto Repair",
            "type":"Services"
        }
    ],
    "sg:phone":"+1 574 753 6170",
    "sg:postcode":"46947",
    "sg:province":"IN",
    "sg:tags":[
        "body",
        "automobile",
        "painting"
    ],
    "wof:name":"Walters Precision Collision",
    "wof:placetype":"venue"
},
  "geometry": {"coordinates":[-86.366264,40.754013],"type":"Point"}
}