{
  "type": "Feature",
  "properties": {
    "iso:country":"US",
    "sg:address":"4011 Shannon Dr",
    "sg:city":"Fort Wayne",
    "sg:phone":"+1 260 492 7372",
    "sg:postcode":"46835",
    "sg:province":"IN",
    "sg:tags":[
        "scale"
    ],
    "wof:name":"Accurate Scale Co",
    "wof:placetype":"venue"
},
  "geometry": {"coordinates":[-85.09019499999999,41.135276],"type":"Point"}
}