{
  "type": "Feature",
  "properties": {
    "iso:country":"US",
    "sg:address":"5993 E Robinson Rd",
    "sg:city":"Bloomington",
    "sg:classifiers":[
        {
            "category":"Building & Trades",
            "subcategory":"Landscaping Services",
            "type":"Services"
        }
    ],
    "sg:phone":"+1 812 332 6495",
    "sg:postcode":"47408",
    "sg:province":"IN",
    "sg:tags":[
        "lawn",
        "maintenance",
        "grounds"
    ],
    "wof:name":"Soaring Eagle Horticultural",
    "wof:placetype":"venue"
},
  "geometry": {"coordinates":[-86.459018,39.246798],"type":"Point"}
}