{
  "type": "Feature",
  "properties": {
    "iso:country":"US",
    "sg:address":"1407 Laporte Ave",
    "sg:city":"Valparaiso",
    "sg:classifiers":[
        {
            "category":"Retail",
            "subcategory":"Auto Repair",
            "type":"Services"
        }
    ],
    "sg:phone":"+1 219 462 9694",
    "sg:postcode":"46383",
    "sg:province":"IN",
    "sg:tags":[
        "repairing",
        "automobile"
    ],
    "wof:name":"Gill's Auto Repair",
    "wof:placetype":"venue"
},
  "geometry": {"coordinates":[-87.042934,41.466732],"type":"Point"}
}