{
  "type": "Feature",
  "properties": {
    "addr:full":"326 E Jefferson St Plymouth IN 46563",
    "addr:housenumber":"326",
    "addr:postcode":"46563",
    "addr:street":"E Jefferson St",
    "iso:country":"US",
    "sg:address":"326 E Jefferson St",
    "sg:city":"Plymouth",
    "sg:classifiers":[
        {
            "category":"Retail",
            "subcategory":"Repair Shop",
            "type":"Services"
        }
    ],
    "sg:phone":"+1 574 936 3556",
    "sg:postcode":"46563",
    "sg:province":"IN",
    "sg:tags":[
        "water",
        "equipment",
        "softening"
    ],
    "wof:name":"Culligan Water Conditioning",
    "wof:placetype":"venue"
},
  "geometry": {"coordinates":[-86.30509499999999,41.343611],"type":"Point"}
}