{
  "type": "Feature",
  "properties": {
    "iso:country":"US",
    "sg:address":"817 E 370 S",
    "sg:city":"Rensselaer",
    "sg:classifiers":[
        {
            "category":"Farming",
            "subcategory":"Farm",
            "type":"Manufacturing & Wholesale Goods"
        }
    ],
    "sg:phone":"+1 219 866 8606",
    "sg:postcode":"47978",
    "sg:province":"IN",
    "wof:name":"Northwind Pork LLC",
    "wof:placetype":"venue"
},
  "geometry": {"coordinates":[-87.031469,40.959351],"type":"Point"}
}