{
  "type": "Feature",
  "properties": {
    "iso:country":"US",
    "sg:address":"1731 W 54th Ave",
    "sg:city":"Merrillville",
    "sg:classifiers":[
        {
            "category":"Professional",
            "subcategory":"Accounting & Tax Preparation",
            "type":"Services"
        }
    ],
    "sg:phone":"+1 219 980 5989",
    "sg:postcode":"46410",
    "sg:province":"IN",
    "sg:tags":[
        "billing"
    ],
    "wof:name":"Electronic Medical Claims Svc",
    "wof:placetype":"venue"
},
  "geometry": {"coordinates":[-87.357775,41.519169],"type":"Point"}
}