{
  "type": "Feature",
  "properties": {
    "addr:full":"5104 Massachusetts Ave Indianapolis IN 46218",
    "addr:housenumber":"5104",
    "addr:postcode":"46218",
    "addr:street":"Massachusetts Ave",
    "iso:country":"US",
    "sg:address":"5104 Massachusetts Ave",
    "sg:city":"Indianapolis",
    "sg:classifiers":[
        {
            "category":"Building & Trades",
            "subcategory":"Construction",
            "type":"Services"
        }
    ],
    "sg:phone":"+1 317 546 8777",
    "sg:postcode":"46218",
    "sg:province":"IN",
    "sg:tags":[
        "roofing",
        "contractor"
    ],
    "wof:name":"Sherriff-Goslin Roofing Co",
    "wof:placetype":"venue"
},
  "geometry": {"coordinates":[-86.082534,39.811252],"type":"Point"}
}