{
  "type": "Feature",
  "properties": {
    "iso:country":"US",
    "sg:address":"6679 W McNeeley St",
    "sg:city":"Ellettsville",
    "sg:classifiers":[
        {
            "category":"Retail",
            "subcategory":"Auto Repair",
            "type":"Services"
        }
    ],
    "sg:phone":"+1 812 876 6366",
    "sg:postcode":"47429",
    "sg:province":"IN",
    "sg:tags":[
        "truck"
    ],
    "wof:name":"Ellettsville Truck & Equipment",
    "wof:placetype":"venue"
},
  "geometry": {"coordinates":[-86.622527,39.238048],"type":"Point"}
}