{
  "type": "Feature",
  "properties": {
    "iso:country":"US",
    "sg:address":"214 S Main St",
    "sg:city":"Winchester",
    "sg:classifiers":[
        {
            "category":"Professional",
            "subcategory":"Lawyer & Legal Services",
            "type":"Services"
        }
    ],
    "sg:phone":"+1 765 584 2831",
    "sg:postcode":"47394",
    "sg:province":"IN",
    "sg:tags":[
        "attorney"
    ],
    "wof:name":"Tanner & Tanner",
    "wof:placetype":"venue"
},
  "geometry": {"coordinates":[-84.981381,40.171467],"type":"Point"}
}