{
  "type": "Feature",
  "properties": {
    "addr:full":"302 Vine St Clinton IN 47842",
    "addr:housenumber":"302",
    "addr:postcode":"47842",
    "addr:street":"Vine St",
    "iso:country":"US",
    "sg:address":"302 Vine St",
    "sg:city":"Clinton",
    "sg:classifiers":[
        {
            "category":"Banks & Credit Unions",
            "subcategory":"Bank",
            "type":"Services"
        }
    ],
    "sg:phone":"+1 765 832 3578",
    "sg:postcode":"47842",
    "sg:province":"IN",
    "wof:name":"Fifth Third Bank",
    "wof:placetype":"venue"
},
  "geometry": {"coordinates":[-87.40109699999999,39.660389],"type":"Point"}
}