{
  "type": "Feature",
  "properties": {
    "iso:country":"US",
    "sg:address":"601 Main St",
    "sg:city":"Brookville",
    "sg:classifiers":[
        {
            "category":"Professional",
            "subcategory":"Lawyer & Legal Services",
            "type":"Services"
        }
    ],
    "sg:phone":"+1 765 647 4156",
    "sg:postcode":"47012",
    "sg:province":"IN",
    "sg:tags":[
        "attorney"
    ],
    "wof:name":"O'Connor Stewart & Wilhelm",
    "wof:placetype":"venue"
},
  "geometry": {"coordinates":[-85.01275,39.421924],"type":"Point"}
}