{
  "type": "Feature",
  "properties": {
    "iso:country":"US",
    "sg:address":"2740 E Chicago Ave",
    "sg:city":"East Chicago",
    "sg:classifiers":[
        {
            "category":"Organizations",
            "subcategory":"Professional Association",
            "type":"Services"
        }
    ],
    "sg:phone":"+1 219 397 7229",
    "sg:postcode":"46312",
    "sg:province":"IN",
    "sg:tags":[
        "business"
    ],
    "wof:name":"Womans Improvement Club Inc",
    "wof:placetype":"venue"
},
  "geometry": {"coordinates":[-87.441958,41.629067],"type":"Point"}
}