{
  "type": "Feature",
  "properties": {
    "iso:country":"US",
    "sg:address":"43 Gleneagles Dr",
    "sg:city":"Schererville",
    "sg:classifiers":[
        {
            "category":"Professional",
            "subcategory":"Management & Consulting",
            "type":"Services"
        }
    ],
    "sg:phone":"+1 219 864 9462",
    "sg:postcode":"46375",
    "sg:province":"IN",
    "sg:tags":[
        "marketing",
        "consultant"
    ],
    "wof:name":"American Marketing",
    "wof:placetype":"venue"
},
  "geometry": {"coordinates":[-87.49016,41.520595],"type":"Point"}
}