{
  "type": "Feature",
  "properties": {
    "iso:country":"US",
    "sg:address":"202 N Main St",
    "sg:city":"Knox",
    "sg:classifiers":[
        {
            "category":"Real Estate",
            "subcategory":"Real Estate Agent",
            "type":"Services"
        }
    ],
    "sg:phone":"+1 574 772 2311",
    "sg:postcode":"46534",
    "sg:province":"IN",
    "wof:name":"F C Tucker Nw Indiana Realtor",
    "wof:placetype":"venue"
},
  "geometry": {"coordinates":[-86.623148,41.300065],"type":"Point"}
}