{
  "type": "Feature",
  "properties": {
    "addr:full":"3951 W Co Rd 350 N Osgood IN 47037",
    "addr:housenumber":"3951;350 n",
    "addr:postcode":"osgood in 47037",
    "addr:street":"W Co Rd",
    "iso:country":"US",
    "sg:address":"3951 W Co Rd 350 N",
    "sg:city":"Osgood",
    "sg:phone":"+1 812 689 5740",
    "sg:postcode":"47037",
    "sg:province":"IN",
    "sg:tags":[
        "farm",
        "corn",
        "soybean"
    ],
    "wof:name":"Roy Thomas",
    "wof:placetype":"venue"
},
  "geometry": {"coordinates":[-85.33204499999999,39.125836],"type":"Point"}
}