{
  "type": "Feature",
  "properties": {
    "iso:country":"US",
    "sg:address":"512 Randle St",
    "sg:city":"Valparaiso",
    "sg:classifiers":[
        {
            "category":"Building & Trades",
            "subcategory":"Construction",
            "type":"Services"
        }
    ],
    "sg:phone":"+1 219 465 3877",
    "sg:postcode":"46383",
    "sg:province":"IN",
    "sg:tags":[
        "general",
        "contractor"
    ],
    "wof:name":"Total Development",
    "wof:placetype":"venue"
},
  "geometry": {"coordinates":[-87.055157,41.482169],"type":"Point"}
}