{
  "type": "Feature",
  "properties": {
    "iso:country":"US",
    "sg:address":"107 N Eastern Ave",
    "sg:city":"Batesville",
    "sg:classifiers":[
        {
            "category":"Building & Trades",
            "subcategory":"Construction",
            "type":"Services"
        }
    ],
    "sg:phone":"+1 812 934 4221",
    "sg:postcode":"47006",
    "sg:province":"IN",
    "sg:tags":[
        "house"
    ],
    "wof:name":"Joels At Your Service Inc",
    "wof:placetype":"venue"
},
  "geometry": {"coordinates":[-85.217973,39.297595],"type":"Point"}
}