{
  "type": "Feature",
  "properties": {
    "iso:country":"US",
    "sg:address":"246 Mulberry St",
    "sg:city":"Clinton",
    "sg:classifiers":[
        {
            "category":"Restaurant",
            "type":"Food & Drink"
        }
    ],
    "sg:phone":"+1 765 832 3385",
    "sg:postcode":"47842",
    "sg:province":"IN",
    "wof:name":"Ol' Mulberry Cafe",
    "wof:placetype":"venue"
},
  "geometry": {"coordinates":[-87.399192,39.659296],"type":"Point"}
}