{
  "type": "Feature",
  "properties": {
    "iso:country":"US",
    "sg:address":"7822 Eyford Ct",
    "sg:city":"Indianapolis",
    "sg:classifiers":[
        {
            "category":"Professional",
            "subcategory":"Advertising",
            "type":"Services"
        }
    ],
    "sg:phone":"+1 317 826 1103",
    "sg:postcode":"46236",
    "sg:province":"IN",
    "sg:tags":[
        "distribution"
    ],
    "wof:name":"Mill Distributors",
    "wof:placetype":"venue"
},
  "geometry": {"coordinates":[-85.971765,39.896379],"type":"Point"}
}