{
  "type": "Feature",
  "properties": {
    "iso:country":"US",
    "sg:address":"2902 Enterprise Dr",
    "sg:city":"Anderson",
    "sg:classifiers":[
        {
            "category":"Manufacturing",
            "subcategory":"Tools & Machinery",
            "type":"Manufacturing & Wholesale Goods"
        }
    ],
    "sg:phone":"+1 765 778 6499",
    "sg:postcode":"46013",
    "sg:province":"IN",
    "sg:tags":[
        "alternator",
        "generator"
    ],
    "sg:website":"www.delcoremy.com",
    "wof:name":"Remy International Inc",
    "wof:placetype":"venue"
},
  "geometry": {"coordinates":[-85.72421900000001,40.039084],"type":"Point"}
}