{
  "type": "Feature",
  "properties": {
    "iso:country":"US",
    "sg:address":"3375 N Russell Rd",
    "sg:city":"Bloomington",
    "sg:classifiers":[
        {
            "category":"Professional",
            "subcategory":"Business Services",
            "type":"Services"
        }
    ],
    "sg:phone":"+1 812 339 8887",
    "sg:postcode":"47408",
    "sg:province":"IN",
    "wof:name":"My Bonnie Designs",
    "wof:placetype":"venue"
},
  "geometry": {"coordinates":[-86.486248,39.197863],"type":"Point"}
}