{
  "type": "Feature",
  "properties": {
    "iso:country":"US",
    "sg:address":"453 N Forest Ave",
    "sg:city":"Indianapolis",
    "sg:classifiers":[
        {
            "category":"Professional",
            "type":"Services"
        }
    ],
    "sg:phone":"+1 317 833 3655",
    "sg:postcode":"46201",
    "sg:province":"IN",
    "sg:tags":[
        "transportation"
    ],
    "wof:name":"Mag Transportion",
    "wof:placetype":"venue"
},
  "geometry": {"coordinates":[-86.120874,39.772117],"type":"Point"}
}