{
  "type": "Feature",
  "properties": {
    "iso:country":"US",
    "sg:address":"15 E Main St",
    "sg:city":"Carmel",
    "sg:classifiers":[
        {
            "category":"Shopping",
            "subcategory":"Clothing, Apparel, & Fashions",
            "type":"Retail Goods"
        }
    ],
    "sg:postcode":"46032",
    "sg:province":"IN",
    "sg:tags":[
        "clothing",
        "women's"
    ],
    "wof:name":"Curiosities",
    "wof:placetype":"venue"
},
  "geometry": {"coordinates":[-86.126752,39.978257],"type":"Point"}
}