{
  "type": "Feature",
  "properties": {
    "iso:country":"US",
    "sg:address":"3242 E 500 S-57",
    "sg:city":"Churubusco",
    "sg:classifiers":[
        {
            "category":"Restaurant",
            "type":"Food & Drink"
        }
    ],
    "sg:phone":"+1 260 693 2202",
    "sg:postcode":"46723",
    "sg:province":"IN",
    "sg:tags":[
        "tea",
        "eating",
        "rooms"
    ],
    "wof:name":"Quiet Corner Tea & Coffee Room",
    "wof:placetype":"venue"
},
  "geometry": {"coordinates":[-85.348845,41.278965],"type":"Point"}
}