{
  "type": "Feature",
  "properties": {
    "iso:country":"US",
    "sg:address":"1819 E Oak St",
    "sg:city":"New Albany",
    "sg:classifiers":[
        {
            "category":"Shopping",
            "type":"Retail Goods"
        },
        {
            "category":"Shopping",
            "subcategory":"Gifts & Souvenirs",
            "type":"Retail Goods"
        }
    ],
    "sg:phone":"+1 812 945 9773",
    "sg:postcode":"47150",
    "sg:province":"IN",
    "sg:tags":[
        "art",
        "gallery",
        "dealer"
    ],
    "wof:name":"Remembrance Art LLC",
    "wof:placetype":"venue"
},
  "geometry": {"coordinates":[-85.805344,38.296483],"type":"Point"}
}