{
  "type": "Feature",
  "properties": {
    "iso:country":"US",
    "sg:address":"20900 W Ireland Rd",
    "sg:city":"South Bend",
    "sg:classifiers":[
        {
            "category":"Manufacturing",
            "subcategory":"Rubber & Plastics",
            "type":"Manufacturing & Wholesale Goods"
        }
    ],
    "sg:phone":"+1 574 299 1888",
    "sg:postcode":"46614",
    "sg:province":"IN",
    "sg:tags":[
        "product"
    ],
    "wof:name":"Clean-Seal Inc",
    "wof:placetype":"venue"
},
  "geometry": {"coordinates":[-86.271227,41.628653],"type":"Point"}
}