{
  "type": "Feature",
  "properties": {
    "iso:country":"US",
    "sg:address":"17254 State Rd 120",
    "sg:city":"Bristol",
    "sg:classifiers":[
        {
            "category":"Autos & Motor Vehicles",
            "subcategory":"Auto Supplies",
            "type":"Retail Goods"
        }
    ],
    "sg:phone":"+1 574 848 7565",
    "sg:postcode":"46507",
    "sg:province":"IN",
    "sg:tags":[
        "tire"
    ],
    "wof:name":"Sam's Tire Svc Inc",
    "wof:placetype":"venue"
},
  "geometry": {"coordinates":[-85.797709,41.723568],"type":"Point"}
}