{
  "type": "Feature",
  "properties": {
    "iso:country":"US",
    "sg:address":"5164 N College Ave",
    "sg:city":"Indianapolis",
    "sg:classifiers":[
        {
            "category":"Restaurant",
            "type":"Food & Drink"
        }
    ],
    "sg:phone":"+1 317 925 2233",
    "sg:postcode":"46205",
    "sg:province":"IN",
    "wof:name":"Taste Cafe & Marketplace",
    "wof:placetype":"venue"
},
  "geometry": {"coordinates":[-86.14582299999999,39.845702],"type":"Point"}
}