{
  "type": "Feature",
  "properties": {
    "iso:country":"US",
    "sg:address":"321 S High St",
    "sg:city":"Warsaw",
    "sg:classifiers":[
        {
            "category":"Health Services",
            "subcategory":"Hospital",
            "type":"Services"
        }
    ],
    "sg:phone":"+1 574 268 9259",
    "sg:postcode":"46580",
    "sg:province":"IN",
    "sg:tags":[
        "mental"
    ],
    "wof:name":"New Hope Clubhouse Warsaw",
    "wof:placetype":"venue"
},
  "geometry": {"coordinates":[-85.85402,41.235908],"type":"Point"}
}