{
  "type": "Feature",
  "properties": {
    "addr:full":"313 W Green St Butler IN 46721",
    "addr:housenumber":"313",
    "addr:postcode":"46721",
    "addr:street":"W Green St",
    "iso:country":"US",
    "sg:address":"313 W Green St",
    "sg:city":"Butler",
    "sg:classifiers":[
        {
            "category":"Shopping",
            "subcategory":"Florist",
            "type":"Retail Goods"
        }
    ],
    "sg:phone":"+1 260 868 2571",
    "sg:postcode":"46721",
    "sg:province":"IN",
    "wof:name":"Armstrong Floral",
    "wof:placetype":"venue"
},
  "geometry": {"coordinates":[-84.87481699999999,41.430669],"type":"Point"}
}