{
  "type": "Feature",
  "properties": {
    "iso:country":"US",
    "sg:address":"1545 Country Club Rd",
    "sg:city":"Indianapolis",
    "sg:classifiers":[
        {
            "category":"Professional",
            "subcategory":"Engineering",
            "type":"Services"
        }
    ],
    "sg:phone":"+1 317 209 4035",
    "sg:postcode":"46234",
    "sg:province":"IN",
    "sg:tags":[
        "engineer"
    ],
    "sg:website":"www.jwsims.com",
    "wof:name":"J W Sims & Assoc Engr Co",
    "wof:placetype":"venue"
},
  "geometry": {"coordinates":[-86.307553,39.785909],"type":"Point"}
}