{
  "type": "Feature",
  "properties": {
    "iso:country":"US",
    "sg:address":"7318 W 15th Ave",
    "sg:city":"Gary",
    "sg:classifiers":[
        {
            "category":"Building & Trades",
            "subcategory":"Construction",
            "type":"Services"
        }
    ],
    "sg:phone":"+1 219 944 0283",
    "sg:postcode":"46406",
    "sg:province":"IN",
    "sg:tags":[
        "demolition",
        "contractor"
    ],
    "wof:name":"Bob Heine Inc",
    "wof:placetype":"venue"
},
  "geometry": {"coordinates":[-87.42851,41.588169],"type":"Point"}
}