{
  "type": "Feature",
  "properties": {
    "iso:country":"US",
    "sg:address":"208 N Miami St",
    "sg:city":"Peru",
    "sg:classifiers":[
        {
            "category":"Manufacturing",
            "subcategory":"Food",
            "type":"Manufacturing & Wholesale Goods"
        }
    ],
    "sg:phone":"+1 765 472 1961",
    "sg:postcode":"46970",
    "sg:province":"IN",
    "sg:tags":[
        "cheese",
        "processor"
    ],
    "wof:name":"Saputo Cheese USA Inc",
    "wof:placetype":"venue"
},
  "geometry": {"coordinates":[-86.073497,40.756665],"type":"Point"}
}