{
  "type": "Feature",
  "properties": {
    "iso:country":"US",
    "sg:address":"3721 S East St",
    "sg:city":"Indianapolis",
    "sg:classifiers":[
        {
            "category":"Banks & Credit Unions",
            "subcategory":"Bank",
            "type":"Services"
        }
    ],
    "sg:phone":"+1 317 266 6640",
    "sg:postcode":"46227",
    "sg:province":"IN",
    "wof:name":"Bank One",
    "wof:placetype":"venue"
},
  "geometry": {"coordinates":[-86.14889599999999,39.71197],"type":"Point"}
}