{
  "type": "Feature",
  "properties": {
    "iso:country":"US",
    "sg:address":"1850 Walter Glaub Dr",
    "sg:city":"Plymouth",
    "sg:classifiers":[
        {
            "category":"Government",
            "subcategory":"Office",
            "type":"Public Place"
        }
    ],
    "sg:phone":"+1 574 935 4059",
    "sg:postcode":"46563",
    "sg:province":"IN",
    "sg:tags":[
        "county",
        "resource"
    ],
    "wof:name":"Child Protection Svc",
    "wof:placetype":"venue"
},
  "geometry": {"coordinates":[-86.336226,41.358671],"type":"Point"}
}