{
  "type": "Feature",
  "properties": {
    "iso:country":"US",
    "sg:address":"210 N Merrill St",
    "sg:city":"Fortville",
    "sg:classifiers":[
        {
            "category":"Recreation",
            "type":"Entertainment"
        }
    ],
    "sg:phone":"+1 317 485 7375",
    "sg:postcode":"46040",
    "sg:province":"IN",
    "wof:name":"Brock Brown Karate Studio",
    "wof:placetype":"venue"
},
  "geometry": {"coordinates":[-85.851956,39.934922],"type":"Point"}
}