{
  "type": "Feature",
  "properties": {
    "iso:country":"US",
    "sg:address":"2053 Gosling Ct",
    "sg:city":"Franklin",
    "sg:classifiers":[
        {
            "category":"Manufacturing",
            "subcategory":"Signs",
            "type":"Manufacturing & Wholesale Goods"
        }
    ],
    "sg:phone":"+1 317 422 1702",
    "sg:postcode":"46131",
    "sg:province":"IN",
    "sg:tags":[
        "advertising",
        "specialty"
    ],
    "wof:name":"Yard Signs Inc",
    "wof:placetype":"venue"
},
  "geometry": {"coordinates":[-86.136777,39.51047],"type":"Point"}
}