{
  "type": "Feature",
  "properties": {
    "iso:country":"US",
    "sg:address":"101 E Jefferson St",
    "sg:city":"Tipton",
    "sg:classifiers":[
        {
            "category":"Government",
            "subcategory":"Office",
            "type":"Public Place"
        }
    ],
    "sg:phone":"+1 765 675 2795",
    "sg:postcode":"46072",
    "sg:province":"IN",
    "sg:tags":[
        "county"
    ],
    "wof:name":"Tipton County Clerk",
    "wof:placetype":"venue"
},
  "geometry": {"coordinates":[-86.04121499999999,40.282246],"type":"Point"}
}