{
  "type": "Feature",
  "properties": {
    "iso:country":"US",
    "sg:address":"27 N Co Rd 300 E",
    "sg:city":"Danville",
    "sg:classifiers":[
        {
            "category":"Professional",
            "subcategory":"Accounting & Tax Preparation",
            "type":"Services"
        }
    ],
    "sg:phone":"+1 317 745 5050",
    "sg:postcode":"46122",
    "sg:province":"IN",
    "sg:tags":[
        "return",
        "filing"
    ],
    "wof:name":"Meyers Tax Svc",
    "wof:placetype":"venue"
},
  "geometry": {"coordinates":[-86.46667600000001,39.763697],"type":"Point"}
}