{
  "type": "Feature",
  "properties": {
    "iso:country":"US",
    "sg:address":"8446 Shattuck Dr",
    "sg:city":"Avon",
    "sg:classifiers":[
        {
            "category":"Professional",
            "type":"Services"
        }
    ],
    "sg:phone":"+1 317 272 2247",
    "sg:postcode":"46123",
    "sg:province":"IN",
    "wof:name":"Moyes Inc",
    "wof:placetype":"venue"
},
  "geometry": {"coordinates":[-86.37518900000001,39.770815],"type":"Point"}
}