{
  "type": "Feature",
  "properties": {
    "addr:full":"107 N John St Frankton IN 46044",
    "addr:housenumber":"107",
    "addr:postcode":"46044",
    "addr:street":"N John St",
    "iso:country":"US",
    "sg:address":"107 N John St",
    "sg:city":"Frankton",
    "sg:classifiers":[
        {
            "category":"Personal",
            "subcategory":"Beauty Salon",
            "type":"Services"
        }
    ],
    "sg:phone":"+1 765 754 7494",
    "sg:postcode":"46044",
    "sg:province":"IN",
    "wof:name":"From The Top Hair & Tanning",
    "wof:placetype":"venue"
},
  "geometry": {"coordinates":[-85.778235,40.223842],"type":"Point"}
}