{
  "type": "Feature",
  "properties": {
    "iso:country":"US",
    "sg:address":"1121 Goshen Ave",
    "sg:city":"Fort Wayne",
    "sg:classifiers":[
        {
            "category":"Autos & Motor Vehicles",
            "subcategory":"Automobile Sales",
            "type":"Retail Goods"
        }
    ],
    "sg:phone":"+1 260 471 0880",
    "sg:postcode":"46808",
    "sg:province":"IN",
    "sg:tags":[
        "car",
        "dealer"
    ],
    "wof:name":"Three Rivers Auto Sales",
    "wof:placetype":"venue"
},
  "geometry": {"coordinates":[-85.155307,41.099585],"type":"Point"}
}