{
  "type": "Feature",
  "properties": {
    "iso:country":"US",
    "sg:address":"7004 Kennedy Ave",
    "sg:city":"Hammond",
    "sg:classifiers":[
        {
            "category":"Real Estate",
            "subcategory":"Real Estate Operator",
            "type":"Services"
        }
    ],
    "sg:phone":"+1 219 844 4090",
    "sg:postcode":"46323",
    "sg:province":"IN",
    "sg:tags":[
        "apartment"
    ],
    "wof:name":"Arzumanian Alex B",
    "wof:placetype":"venue"
},
  "geometry": {"coordinates":[-87.461601,41.586498],"type":"Point"}
}