{
  "type": "Feature",
  "properties": {
    "iso:country":"US",
    "sg:address":"6435 Calumet Ave",
    "sg:city":"Hammond",
    "sg:classifiers":[
        {
            "category":"Freight",
            "type":"Transportation"
        }
    ],
    "sg:phone":"+1 219 662 8922",
    "sg:postcode":"46324",
    "sg:province":"IN",
    "sg:tags":[
        "mover"
    ],
    "wof:name":"Broz Moving & Storage",
    "wof:placetype":"venue"
},
  "geometry": {"coordinates":[-87.508867,41.596089],"type":"Point"}
}