{
  "type": "Feature",
  "properties": {
    "addr:full":"2390 E Stop 11 Rd Indianapolis IN 46227",
    "addr:housenumber":"2390;11",
    "addr:postcode":"46227",
    "addr:street":"E Stop;Rd",
    "iso:country":"US",
    "sg:address":"2390 E Stop 11 Rd",
    "sg:city":"Indianapolis",
    "sg:classifiers":[
        {
            "category":"Fast Food",
            "type":"Food & Drink"
        },
        {
            "category":"Restaurant",
            "type":"Food & Drink"
        }
    ],
    "sg:phone":"+1 317 881 0449",
    "sg:postcode":"46227",
    "sg:province":"IN",
    "sg:tags":[
        "mexican"
    ],
    "sg:website":"http://www.tacobell.com",
    "wof:name":"Taco Bell",
    "wof:placetype":"venue"
},
  "geometry": {"coordinates":[-86.121413,39.650259],"type":"Point"}
}