{
  "type": "Feature",
  "properties": {
    "iso:country":"US",
    "sg:address":"3829 Charlestown Rd",
    "sg:city":"New Albany",
    "sg:classifiers":[
        {
            "category":"Wholesale",
            "subcategory":"Durable Goods & Equipment",
            "type":"Manufacturing & Wholesale Goods"
        }
    ],
    "sg:phone":"+1 812 944 2833",
    "sg:postcode":"47150",
    "sg:province":"IN",
    "wof:name":"Party City Supplies",
    "wof:placetype":"venue"
},
  "geometry": {"coordinates":[-85.796227,38.349519],"type":"Point"}
}