{
  "type": "Feature",
  "properties": {
    "addr:full":"3175 W 3rd St Bloomington IN 47404",
    "addr:housenumber":"3175",
    "addr:postcode":"47404",
    "addr:street":"W 3Rd St",
    "iso:country":"US",
    "sg:address":"3175 W 3rd St",
    "sg:city":"Bloomington",
    "sg:classifiers":[
        {
            "category":"Restaurant",
            "type":"Food & Drink"
        }
    ],
    "sg:menulink":"http://www.allmenus.com/in/van-buren/87425-little-caesars-pizza/menu/",
    "sg:phone":"+1 812 333 1462",
    "sg:postcode":"47404",
    "sg:province":"IN",
    "sg:tags":[
        "american",
        "pizza"
    ],
    "wof:name":"Little Caesar's Pizza",
    "wof:placetype":"venue"
},
  "geometry": {"coordinates":[-86.57502599999999,39.164549],"type":"Point"}
}