{
  "type": "Feature",
  "properties": {
    "iso:country":"US",
    "sg:address":"1003 Hughes St",
    "sg:city":"Rockville",
    "sg:classifiers":[
        {
            "category":"Personal",
            "subcategory":"Beauty Salon",
            "type":"Services"
        }
    ],
    "sg:phone":"+1 765 569 3090",
    "sg:postcode":"47872",
    "sg:province":"IN",
    "wof:name":"Dee's Beauty Salon",
    "wof:placetype":"venue"
},
  "geometry": {"coordinates":[-87.225943,39.774473],"type":"Point"}
}