{
  "type": "Feature",
  "properties": {
    "iso:country":"US",
    "sg:address":"2156 S State Rd 1",
    "sg:city":"Connersville",
    "sg:classifiers":[
        {
            "category":"Wholesale",
            "subcategory":"Non-durable Goods",
            "type":"Manufacturing & Wholesale Goods"
        }
    ],
    "sg:phone":"+1 765 825 3273",
    "sg:postcode":"47331",
    "sg:province":"IN",
    "wof:name":"Advertising Services",
    "wof:placetype":"venue"
},
  "geometry": {"coordinates":[-85.127544,39.610374],"type":"Point"}
}