{
  "type": "Feature",
  "properties": {
    "iso:country":"US",
    "sg:address":"10041 N 1200 W",
    "sg:city":"Demotte",
    "sg:classifiers":[
        {
            "category":"Retail",
            "subcategory":"Repair Shop",
            "type":"Services"
        }
    ],
    "sg:phone":"+1 219 345 4410",
    "sg:postcode":"46310",
    "sg:province":"IN",
    "sg:tags":[
        "repairing",
        "lawn",
        "mower"
    ],
    "wof:name":"R F Small Engine Repair",
    "wof:placetype":"venue"
},
  "geometry": {"coordinates":[-87.275795,41.144832],"type":"Point"}
}