{
  "type": "Feature",
  "properties": {
    "addr:full":"230 Paul St Paoli IN 47454",
    "addr:housenumber":"230",
    "addr:postcode":"47454",
    "addr:street":"Paul St",
    "iso:country":"US",
    "sg:address":"230 Paul St",
    "sg:city":"Paoli",
    "sg:classifiers":[
        {
            "category":"Shopping",
            "subcategory":"Clothing, Apparel, & Fashions",
            "type":"Retail Goods"
        }
    ],
    "sg:phone":"+1 812 723 3132",
    "sg:postcode":"47454",
    "sg:province":"IN",
    "wof:name":"Ruth's Clothing His & Hers",
    "wof:placetype":"venue"
},
  "geometry": {"coordinates":[-86.467015,38.562889],"type":"Point"}
}