{
  "type": "Feature",
  "properties": {
    "iso:country":"US",
    "sg:address":"1245 McClure Rd",
    "sg:city":"Columbus",
    "sg:classifiers":[
        {
            "category":"Social Services",
            "subcategory":"Child Care",
            "type":"Services"
        }
    ],
    "sg:phone":"+1 812 372 2116",
    "sg:postcode":"47201",
    "sg:province":"IN",
    "wof:name":"Kid's Tek",
    "wof:placetype":"venue"
},
  "geometry": {"coordinates":[-85.889607,39.211847],"type":"Point"}
}