{
  "type": "Feature",
  "properties": {
    "iso:country":"US",
    "sg:address":"320 E US Hwy 30",
    "sg:city":"Schererville",
    "sg:classifiers":[
        {
            "category":"Travel",
            "subcategory":"Travel Agent",
            "type":"Entertainment"
        }
    ],
    "sg:phone":"+1 219 736 9105",
    "sg:postcode":"46375",
    "sg:province":"IN",
    "sg:tags":[
        "agency",
        "bureau"
    ],
    "wof:name":"Tasha's Traveling Tappers",
    "wof:placetype":"venue"
},
  "geometry": {"coordinates":[-87.440888,41.48336],"type":"Point"}
}