{
  "type": "Feature",
  "properties": {
    "iso:country":"US",
    "sg:address":"2100 Liberty Dr",
    "sg:city":"Bloomington",
    "sg:classifiers":[
        {
            "category":"Restaurant",
            "type":"Food & Drink"
        }
    ],
    "sg:phone":"+1 812 334 3589",
    "sg:postcode":"47403",
    "sg:province":"IN",
    "sg:tags":[
        "caterer"
    ],
    "wof:name":"Mayfields Ballroom",
    "wof:placetype":"venue"
},
  "geometry": {"coordinates":[-86.578106,39.146046],"type":"Point"}
}