{
  "type": "Feature",
  "properties": {
    "iso:country":"US",
    "sg:address":"9294 S State Rd 15",
    "sg:city":"Silver Lake",
    "sg:classifiers":[
        {
            "category":"Wholesale",
            "subcategory":"Motor Vehicles",
            "type":"Manufacturing & Wholesale Goods"
        }
    ],
    "sg:phone":"+1 260 352 2722",
    "sg:postcode":"46982",
    "sg:province":"IN",
    "sg:tags":[
        "bus"
    ],
    "sg:website":"www.kerlinbus.com",
    "wof:name":"Kerlin Bus Sales & Leasing Inc",
    "wof:placetype":"venue"
},
  "geometry": {"coordinates":[-85.892633,41.097209],"type":"Point"}
}