{
  "type": "Feature",
  "properties": {
    "iso:country":"US",
    "sg:address":"1020 Rochelle Dr",
    "sg:city":"Lafayette",
    "sg:classifiers":[
        {
            "category":"Retail",
            "subcategory":"Repair Shop",
            "type":"Services"
        }
    ],
    "sg:phone":"+1 765 477 2539",
    "sg:postcode":"47909",
    "sg:province":"IN",
    "sg:tags":[
        "clocks",
        "parts"
    ],
    "wof:name":"Sloan's Jewelry Clock & Watch",
    "wof:placetype":"venue"
},
  "geometry": {"coordinates":[-86.88184,40.387394],"type":"Point"}
}