{
  "type": "Feature",
  "properties": {
    "iso:country":"US",
    "sg:address":"5003 Wheatridge Rd",
    "sg:city":"Fort Wayne",
    "sg:classifiers":[
        {
            "category":"Professional",
            "subcategory":"Business Services",
            "type":"Services"
        }
    ],
    "sg:phone":"+1 260 486 1165",
    "sg:postcode":"46835",
    "sg:province":"IN",
    "wof:name":"LDR Enterprises Incorporated",
    "wof:placetype":"venue"
},
  "geometry": {"coordinates":[-85.02185,41.125858],"type":"Point"}
}