{
  "type": "Feature",
  "properties": {
    "iso:country":"US",
    "sg:address":"410 Mulberry St",
    "sg:city":"Madison",
    "sg:classifiers":[
        {
            "category":"Professional",
            "subcategory":"Research",
            "type":"Services"
        }
    ],
    "sg:phone":"+1 812 265 3327",
    "sg:postcode":"47250",
    "sg:province":"IN",
    "sg:tags":[
        "foundation",
        "philanthropic"
    ],
    "wof:name":"Community Foundation",
    "wof:placetype":"venue"
},
  "geometry": {"coordinates":[-85.37871800000001,38.736767],"type":"Point"}
}