{
  "type": "Feature",
  "properties": {
    "iso:country":"US",
    "sg:address":"6109 E 150 S",
    "sg:city":"Rochester",
    "sg:classifiers":[
        {
            "category":"Professional",
            "type":"Services"
        }
    ],
    "sg:phone":"+1 574 224 5959",
    "sg:postcode":"46975",
    "sg:province":"IN",
    "sg:tags":[
        "establishment"
    ],
    "wof:name":"Vandermark & Vandermark",
    "wof:placetype":"venue"
},
  "geometry": {"coordinates":[-86.124206,41.032401],"type":"Point"}
}