{
  "type": "Feature",
  "properties": {
    "addr:full":"1341 W 86th St Indianapolis IN 46260",
    "addr:housenumber":"1341",
    "addr:postcode":"46260",
    "addr:street":"W 86Th St",
    "iso:country":"US",
    "sg:address":"1341 W 86th St",
    "sg:city":"Indianapolis",
    "sg:classifiers":[
        {
            "category":"Restaurant",
            "type":"Food & Drink"
        }
    ],
    "sg:phone":"+1 317 253 7771",
    "sg:postcode":"46260",
    "sg:province":"IN",
    "sg:tags":[
        "chinese"
    ],
    "wof:name":"China Wok",
    "wof:placetype":"venue"
},
  "geometry": {"coordinates":[-86.182503,39.911999],"type":"Point"}
}