{
  "type": "Feature",
  "properties": {
    "iso:country":"US",
    "sg:address":"7119 Sunnyside Rd",
    "sg:city":"Indianapolis",
    "sg:classifiers":[
        {
            "category":"Building & Trades",
            "subcategory":"Construction",
            "type":"Services"
        }
    ],
    "sg:phone":"+1 317 823 0200",
    "sg:postcode":"46236",
    "sg:province":"IN",
    "sg:tags":[
        "home",
        "builder"
    ],
    "wof:name":"Waddy Development Corp",
    "wof:placetype":"venue"
},
  "geometry": {"coordinates":[-85.974348,39.886324],"type":"Point"}
}