{
  "type": "Feature",
  "properties": {
    "iso:country":"US",
    "sg:address":"65169 Co Rd 31",
    "sg:city":"Goshen",
    "sg:classifiers":[
        {
            "category":"Building & Trades",
            "subcategory":"Construction",
            "type":"Services"
        }
    ],
    "sg:phone":"+1 574 642 4424",
    "sg:postcode":"46528",
    "sg:province":"IN",
    "sg:tags":[
        "excavating",
        "contractor"
    ],
    "wof:name":"P & L Backhoe Svc",
    "wof:placetype":"venue"
},
  "geometry": {"coordinates":[-85.770669,41.54954],"type":"Point"}
}