{
  "type": "Feature",
  "properties": {
    "iso:country":"US",
    "sg:address":"302 Waterford Ln",
    "sg:city":"Avon",
    "sg:classifiers":[
        {
            "category":"Building & Trades",
            "subcategory":"Construction",
            "type":"Services"
        }
    ],
    "sg:phone":"+1 317 272 0451",
    "sg:postcode":"46123",
    "sg:province":"IN",
    "sg:tags":[
        "general",
        "contractor"
    ],
    "wof:name":"Landco Inc",
    "wof:placetype":"venue"
},
  "geometry": {"coordinates":[-86.379732,39.76734],"type":"Point"}
}