{
  "type": "Feature",
  "properties": {
    "iso:country":"US",
    "sg:address":"435 W US Hwy 6",
    "sg:city":"Valparaiso",
    "sg:classifiers":[
        {
            "category":"Building & Trades",
            "subcategory":"Construction",
            "type":"Services"
        }
    ],
    "sg:phone":"+1 219 759 3123",
    "sg:postcode":"46385",
    "sg:province":"IN",
    "sg:tags":[
        "hanging",
        "contractor"
    ],
    "wof:name":"Jenkins Painting & Decorating",
    "wof:placetype":"venue"
},
  "geometry": {"coordinates":[-87.152612,41.550512],"type":"Point"}
}