{
  "type": "Feature",
  "properties": {
    "iso:country":"US",
    "sg:address":"1211 Fletcher St",
    "sg:city":"Anderson",
    "sg:classifiers":[
        {
            "category":"Shopping",
            "subcategory":"Used Merchandise",
            "type":"Retail Goods"
        }
    ],
    "sg:phone":"+1 765 642 8132",
    "sg:postcode":"46016",
    "sg:province":"IN",
    "wof:name":"Second Time Around",
    "wof:placetype":"venue"
},
  "geometry": {"coordinates":[-85.67569,40.103267],"type":"Point"}
}