{
  "type": "Feature",
  "properties": {
    "addr:full":"7535 W Jefferson Blvd Fort Wayne IN 46804",
    "addr:housenumber":"7535",
    "addr:postcode":"46804",
    "addr:street":"W Jefferson Blvd",
    "iso:country":"US",
    "sg:address":"7535 W Jefferson Blvd",
    "sg:city":"Fort Wayne",
    "sg:classifiers":[
        {
            "category":"Insurance",
            "subcategory":"Insurance Agent",
            "type":"Services"
        }
    ],
    "sg:phone":"+1 260 432 5527",
    "sg:postcode":"46804",
    "sg:province":"IN",
    "wof:name":"State Farm Insurance",
    "wof:placetype":"venue"
},
  "geometry": {"coordinates":[-85.241422,41.04143],"type":"Point"}
}