{
  "type": "Feature",
  "properties": {
    "iso:country":"US",
    "sg:address":"542 N 12th St",
    "sg:city":"New Castle",
    "sg:classifiers":[
        {
            "category":"Retail",
            "subcategory":"Auto Repair",
            "type":"Services"
        }
    ],
    "sg:phone":"+1 765 529 2364",
    "sg:postcode":"47362",
    "sg:province":"IN",
    "sg:tags":[
        "wrecker"
    ],
    "wof:name":"Hopkins Towing & Recovery",
    "wof:placetype":"venue"
},
  "geometry": {"coordinates":[-85.37155199999999,39.936085],"type":"Point"}
}