{
  "type": "Feature",
  "properties": {
    "iso:country":"US",
    "sg:address":"2632 Pleasant Plain Ave",
    "sg:city":"Elkhart",
    "sg:classifiers":[
        {
            "category":"Retail",
            "subcategory":"Repair Shop",
            "type":"Services"
        }
    ],
    "sg:phone":"+1 574 293 3429",
    "sg:postcode":"46517",
    "sg:province":"IN",
    "sg:tags":[
        "appliance"
    ],
    "wof:name":"Marty's Appliance Repair",
    "wof:placetype":"venue"
},
  "geometry": {"coordinates":[-85.955556,41.659844],"type":"Point"}
}