{
  "type": "Feature",
  "properties": {
    "iso:country":"US",
    "sg:address":"8402 Lincoln Ave",
    "sg:city":"Evansville",
    "sg:classifiers":[
        {
            "category":"Banks & Credit Unions",
            "subcategory":"Financial Services",
            "type":"Services"
        }
    ],
    "sg:phone":"+1 812 471 1748",
    "sg:postcode":"47715",
    "sg:province":"IN",
    "sg:tags":[
        "company",
        "holding"
    ],
    "wof:name":"Racey Enterprises Inc",
    "wof:placetype":"venue"
},
  "geometry": {"coordinates":[-87.452625,37.969465],"type":"Point"}
}