{
  "type": "Feature",
  "properties": {
    "addr:full":"1707 W Gump Rd Huntertown IN 46748",
    "addr:housenumber":"1707",
    "addr:postcode":"46748",
    "addr:street":"W Gump Rd",
    "iso:country":"US",
    "sg:address":"1707 W Gump Rd",
    "sg:city":"Huntertown",
    "sg:classifiers":[
        {
            "category":"Utilities",
            "subcategory":"Water",
            "type":"Services"
        }
    ],
    "sg:phone":"+1 260 637 5058",
    "sg:postcode":"46748",
    "sg:province":"IN",
    "sg:tags":[
        "company",
        "sewage"
    ],
    "wof:name":"Huntertown Water Dept",
    "wof:placetype":"venue"
},
  "geometry": {"coordinates":[-85.164377,41.2245],"type":"Point"}
}