{
  "type": "Feature",
  "properties": {
    "addr:full":"601 Middleton Run Rd Elkhart IN 46516",
    "addr:housenumber":"601",
    "addr:postcode":"46516",
    "addr:street":"Middleton Run Rd",
    "iso:country":"US",
    "sg:address":"601 Middleton Run Rd",
    "sg:city":"Elkhart",
    "sg:classifiers":[
        {
            "category":"Utilities",
            "subcategory":"Telephone",
            "type":"Services"
        }
    ],
    "sg:phone":"+1 574 522 9791",
    "sg:postcode":"46516",
    "sg:province":"IN",
    "sg:tags":[
        "communications"
    ],
    "wof:name":"Strategic Communications",
    "wof:placetype":"venue"
},
  "geometry": {"coordinates":[-85.917255,41.681453],"type":"Point"}
}