{
  "type": "Feature",
  "properties": {
    "iso:country":"US",
    "sg:address":"2740 Mac Arthur Ln",
    "sg:city":"Indianapolis",
    "sg:classifiers":[
        {
            "category":"Professional",
            "subcategory":"Lawyer & Legal Services",
            "type":"Services"
        }
    ],
    "sg:phone":"+1 317 293 1589",
    "sg:postcode":"46224",
    "sg:province":"IN",
    "sg:tags":[
        "attorney"
    ],
    "wof:name":"Joseph W Eke",
    "wof:placetype":"venue"
},
  "geometry": {"coordinates":[-86.259043,39.805292],"type":"Point"}
}