{
  "type": "Feature",
  "properties": {
    "addr:full":"9528 E 126th St Fishers IN 46038",
    "addr:housenumber":"9528",
    "addr:postcode":"46038",
    "addr:street":"E 126Th St",
    "iso:country":"US",
    "sg:address":"9528 E 126th St",
    "sg:city":"Fishers",
    "sg:classifiers":[
        {
            "category":"Food & Beverages",
            "subcategory":"Bakery",
            "type":"Retail Goods"
        }
    ],
    "sg:phone":"+1 317 585 9195",
    "sg:postcode":"46038",
    "sg:province":"IN",
    "sg:tags":[
        "bagel"
    ],
    "wof:name":"Big Apple Bagels",
    "wof:placetype":"venue"
},
  "geometry": {"coordinates":[-85.999465,39.971701],"type":"Point"}
}