{
  "type": "Feature",
  "properties": {
    "addr:full":"601 Gateway Blvd N Chesterton IN 46304",
    "addr:housenumber":"601",
    "addr:postcode":"46304",
    "addr:street":"Gateway Blvd N",
    "iso:country":"US",
    "sg:address":"601 Gateway Blvd N",
    "sg:city":"Chesterton",
    "sg:classifiers":[
        {
            "category":"Health Services",
            "subcategory":"Doctor",
            "type":"Services"
        },
        {
            "category":"Health Services",
            "subcategory":"Podiatrist",
            "type":"Services"
        }
    ],
    "sg:phone":"+1 219 921 1444",
    "sg:postcode":"46304",
    "sg:province":"IN",
    "sg:tags":[
        "physician",
        "rheumatology",
        "arthritis",
        "surgeons",
        "orthopedics",
        "medicine",
        "surgeon",
        "sport"
    ],
    "sg:website":"http://www.lbji.com",
    "wof:name":"Lakeshore Bone & Joint Institute",
    "wof:placetype":"venue"
},
  "geometry": {"coordinates":[-87.042641,41.57584],"type":"Point"}
}