{
  "type": "Feature",
  "properties": {
    "iso:country":"US",
    "sg:address":"217 N Union St",
    "sg:city":"Kokomo",
    "sg:classifiers":[
        {
            "category":"Professional",
            "subcategory":"Management & Consulting",
            "type":"Services"
        }
    ],
    "sg:phone":"+1 765 854 0221",
    "sg:postcode":"46901",
    "sg:province":"IN",
    "sg:tags":[
        "consultant",
        "training"
    ],
    "wof:name":"Advantage Performance Tech Inc",
    "wof:placetype":"venue"
},
  "geometry": {"coordinates":[-86.130085,40.488205],"type":"Point"}
}