{
  "type": "Feature",
  "properties": {
    "iso:country":"US",
    "sg:address":"944 Coliseum Blvd N",
    "sg:city":"Fort Wayne",
    "sg:classifiers":[
        {
            "category":"Shopping",
            "subcategory":"Used Merchandise",
            "type":"Retail Goods"
        }
    ],
    "sg:phone":"+1 260 422 5662",
    "sg:postcode":"46805",
    "sg:province":"IN",
    "sg:tags":[
        "pawnbroker"
    ],
    "wof:name":"Cash America Pawn",
    "wof:placetype":"venue"
},
  "geometry": {"coordinates":[-85.087687,41.084966],"type":"Point"}
}