{
  "type": "Feature",
  "properties": {
    "iso:country":"US",
    "sg:address":"7074 E State Rd 28",
    "sg:city":"Elwood",
    "sg:classifiers":[
        {
            "category":"Home & Garden",
            "subcategory":"Carpets & Floor Coverings",
            "type":"Retail Goods"
        }
    ],
    "sg:phone":"+1 765 552 3830",
    "sg:postcode":"46036",
    "sg:province":"IN",
    "sg:tags":[
        "material"
    ],
    "wof:name":"Floors & More Designs",
    "wof:placetype":"venue"
},
  "geometry": {"coordinates":[-85.870183,40.276926],"type":"Point"}
}