{
  "type": "Feature",
  "properties": {
    "iso:country":"US",
    "sg:address":"15211 Herriman Blvd",
    "sg:city":"Noblesville",
    "sg:classifiers":[
        {
            "category":"Building & Trades",
            "subcategory":"Construction",
            "type":"Services"
        }
    ],
    "sg:phone":"+1 317 773 5020",
    "sg:postcode":"46060",
    "sg:province":"IN",
    "sg:tags":[
        "boring",
        "drilling",
        "contractor"
    ],
    "sg:website":"www.iegs.net",
    "wof:name":"Indiana Engineering Svc Group",
    "wof:placetype":"venue"
},
  "geometry": {"coordinates":[-86.004737,40.013162],"type":"Point"}
}