{
  "type": "Feature",
  "properties": {
    "iso:country":"US",
    "sg:address":"245 S 1150 E",
    "sg:city":"Lagrange",
    "sg:classifiers":[
        {
            "category":"Professional",
            "type":"Services"
        }
    ],
    "sg:phone":"+1 260 351 2006",
    "sg:postcode":"46761",
    "sg:province":"IN",
    "sg:tags":[
        "establishment"
    ],
    "wof:name":"Csn International",
    "wof:placetype":"venue"
},
  "geometry": {"coordinates":[-85.20196900000001,41.638208],"type":"Point"}
}