{
  "type": "Feature",
  "properties": {
    "iso:country":"US",
    "sg:address":"1615 E Michigan Rd",
    "sg:city":"Shelbyville",
    "sg:classifiers":[
        {
            "category":"Shopping",
            "subcategory":"Optical Goods",
            "type":"Retail Goods"
        }
    ],
    "sg:phone":"+1 317 392 8815",
    "sg:postcode":"46176",
    "sg:province":"IN",
    "sg:tags":[
        "optician"
    ],
    "wof:name":"Sears Optical",
    "wof:placetype":"venue"
},
  "geometry": {"coordinates":[-85.75184,39.518605],"type":"Point"}
}