{
  "type": "Feature",
  "properties": {
    "addr:full":"322 W Van Buren St Columbia City IN 46725",
    "addr:housenumber":"322",
    "addr:postcode":"46725",
    "addr:street":"W Van Buren St",
    "iso:country":"US",
    "sg:address":"322 W Van Buren St",
    "sg:city":"Columbia City",
    "sg:classifiers":[
        {
            "category":"Education",
            "subcategory":"Dance Studio",
            "type":"Public Place"
        }
    ],
    "sg:phone":"+1 260 244 3271",
    "sg:postcode":"46725",
    "sg:province":"IN",
    "sg:tags":[
        "instruction",
        "dancing"
    ],
    "wof:name":"Solomon's Song Dance Studio",
    "wof:placetype":"venue"
},
  "geometry": {"coordinates":[-85.49240899999999,41.15708],"type":"Point"}
}