{
  "type": "Feature",
  "properties": {
    "iso:country":"US",
    "sg:address":"2335 W Bunkum Rd",
    "sg:city":"Rensselaer",
    "sg:classifiers":[
        {
            "category":"Organizations",
            "subcategory":"Religious Organization",
            "type":"Services"
        }
    ],
    "sg:phone":"+1 219 866 2230",
    "sg:postcode":"47978",
    "sg:province":"IN",
    "sg:tags":[
        "church"
    ],
    "wof:name":"Iroquois Valley Christian Chr",
    "wof:placetype":"venue"
},
  "geometry": {"coordinates":[-87.17726,40.931478],"type":"Point"}
}