{
  "type": "Feature",
  "properties": {
    "addr:full":"608 Colfax Ave Laporte IN 46350",
    "addr:housenumber":"608",
    "addr:postcode":"46350",
    "addr:street":"Colfax Ave",
    "iso:country":"US",
    "sg:address":"608 Colfax Ave",
    "sg:city":"Laporte",
    "sg:classifiers":[
        {
            "category":"Cinema",
            "subcategory":"Movie Theater",
            "type":"Entertainment"
        }
    ],
    "sg:phone":"+1 219 326 7469",
    "sg:postcode":"46350",
    "sg:province":"IN",
    "wof:name":"LA Porte Cinema Quad",
    "wof:placetype":"venue"
},
  "geometry": {"coordinates":[-86.738328,41.600414],"type":"Point"}
}