{
  "type": "Feature",
  "properties": {
    "iso:country":"US",
    "sg:address":"11643 S Co Rd 850 E",
    "sg:city":"Quincy",
    "sg:classifiers":[
        {
            "category":"Farming",
            "subcategory":"Farm",
            "type":"Manufacturing & Wholesale Goods"
        }
    ],
    "sg:phone":"+1 765 795 4483",
    "sg:postcode":"47456",
    "sg:province":"IN",
    "sg:tags":[
        "crop",
        "general"
    ],
    "wof:name":"Wilbur Cassida",
    "wof:placetype":"venue"
},
  "geometry": {"coordinates":[-86.696879,39.488765],"type":"Point"}
}