{
  "type": "Feature",
  "properties": {
    "iso:country":"US",
    "sg:address":"935 Farwood Ave",
    "sg:city":"Fort Wayne",
    "sg:classifiers":[
        {
            "category":"Organizations",
            "subcategory":"Religious Organization",
            "type":"Services"
        }
    ],
    "sg:phone":"+1 260 447 9414",
    "sg:postcode":"46816",
    "sg:province":"IN",
    "wof:name":"First Pentecostal Church",
    "wof:placetype":"venue"
},
  "geometry": {"coordinates":[-85.12290299999999,41.029123],"type":"Point"}
}