{
  "type": "Feature",
  "properties": {
    "addr:full":"403 E 4th St Huntingburg IN 47542",
    "addr:housenumber":"403",
    "addr:postcode":"47542",
    "addr:street":"E 4Th St",
    "iso:country":"US",
    "sg:address":"403 E 4th St",
    "sg:city":"Huntingburg",
    "sg:classifiers":[
        {
            "category":"Banks & Credit Unions",
            "subcategory":"Investment Brokerage",
            "type":"Services"
        }
    ],
    "sg:phone":"+1 812 683 5958",
    "sg:postcode":"47542",
    "sg:province":"IN",
    "wof:name":"Schulthise Financial Svc",
    "wof:placetype":"venue"
},
  "geometry": {"coordinates":[-86.95544700000001,38.295984],"type":"Point"}
}