{
  "type": "Feature",
  "properties": {
    "iso:country":"US",
    "sg:address":"109 Hunter Station Way",
    "sg:city":"Sellersburg",
    "sg:classifiers":[
        {
            "category":"Health Services",
            "subcategory":"Doctor",
            "type":"Services"
        }
    ],
    "sg:phone":"+1 812 248 4655",
    "sg:postcode":"47172",
    "sg:province":"IN",
    "sg:tags":[
        "practice",
        "family"
    ],
    "wof:name":"Green Jeanne Dr",
    "wof:placetype":"venue"
},
  "geometry": {"coordinates":[-85.771767,38.382607],"type":"Point"}
}