{
  "type": "Feature",
  "properties": {
    "iso:country":"US",
    "sg:address":"205 N Main St",
    "sg:city":"Rushville",
    "sg:classifiers":[
        {
            "category":"Restaurant",
            "type":"Food & Drink"
        }
    ],
    "sg:phone":"+1 765 938 3911",
    "sg:postcode":"46173",
    "sg:province":"IN",
    "wof:name":"Winkerby's",
    "wof:placetype":"venue"
},
  "geometry": {"coordinates":[-85.44487599999999,39.609287],"type":"Point"}
}