{
  "type": "Feature",
  "properties": {
    "iso:country":"US",
    "sg:address":"610 S Jackson St",
    "sg:city":"Frankfort",
    "sg:classifiers":[
        {
            "category":"Building & Trades",
            "subcategory":"Construction",
            "type":"Services"
        }
    ],
    "sg:phone":"+1 765 659 2033",
    "sg:postcode":"46041",
    "sg:province":"IN",
    "sg:tags":[
        "concrete",
        "contractor"
    ],
    "wof:name":"Jim Michael Construction Co",
    "wof:placetype":"venue"
},
  "geometry": {"coordinates":[-86.51069099999999,40.276005],"type":"Point"}
}