{
  "type": "Feature",
  "properties": {
    "iso:country":"US",
    "sg:address":"8819 W Co Rd 225 S",
    "sg:city":"Medora",
    "sg:classifiers":[
        {
            "category":"Real Estate",
            "subcategory":"Surveying",
            "type":"Services"
        }
    ],
    "sg:phone":"+1 812 966 2199",
    "sg:postcode":"47260",
    "sg:province":"IN",
    "sg:tags":[
        "surveyor"
    ],
    "wof:name":"Farrow & Huffman Land Survey",
    "wof:placetype":"venue"
},
  "geometry": {"coordinates":[-86.201156,38.842022],"type":"Point"}
}