{
  "type": "Feature",
  "properties": {
    "iso:country":"US",
    "sg:address":"8335 Allison Pointe Trl",
    "sg:city":"Indianapolis",
    "sg:classifiers":[
        {
            "category":"Professional",
            "type":"Services"
        }
    ],
    "sg:phone":"+1 317 570 6400",
    "sg:postcode":"46250",
    "sg:province":"IN",
    "sg:tags":[
        "establishment"
    ],
    "sg:website":"www.libertyfund.org",
    "wof:name":"Libery Fund",
    "wof:placetype":"venue"
},
  "geometry": {"coordinates":[-86.080905,39.907508],"type":"Point"}
}