{
  "type": "Feature",
  "properties": {
    "addr:full":"123 Helen St Michigan City IN 46360",
    "addr:housenumber":"123",
    "addr:postcode":"46360",
    "addr:street":"Helen St",
    "iso:country":"US",
    "sg:address":"123 Helen St",
    "sg:city":"Michigan City",
    "sg:classifiers":[
        {
            "category":"Organizations",
            "subcategory":"Religious Organization",
            "type":"Services"
        }
    ],
    "sg:phone":"+1 219 872 5275",
    "sg:postcode":"46360",
    "sg:province":"IN",
    "sg:tags":[
        "church"
    ],
    "wof:name":"Mt Zion Baptist Church",
    "wof:placetype":"venue"
},
  "geometry": {"coordinates":[-86.87561100000001,41.711536],"type":"Point"}
}