{
  "type": "Feature",
  "properties": {
    "addr:full":"400 Michigan Ave Logansport IN 46947",
    "addr:housenumber":"400",
    "addr:postcode":"46947",
    "addr:street":"Michigan Ave",
    "iso:country":"US",
    "sg:address":"400 Michigan Ave",
    "sg:city":"Logansport",
    "sg:classifiers":[
        {
            "category":"Building & Trades",
            "subcategory":"Plumbing",
            "type":"Services"
        }
    ],
    "sg:phone":"+1 574 753 4426",
    "sg:postcode":"46947",
    "sg:province":"IN",
    "sg:tags":[
        "heating",
        "contractor"
    ],
    "wof:name":"Moore & Crimmins Inc",
    "wof:placetype":"venue"
},
  "geometry": {"coordinates":[-86.36288399999999,40.759806],"type":"Point"}
}