{
  "type": "Feature",
  "properties": {
    "iso:country":"US",
    "sg:address":"3030 E Paulding Rd",
    "sg:city":"Fort Wayne",
    "sg:classifiers":[
        {
            "category":"Education",
            "subcategory":"Library",
            "type":"Public Place"
        }
    ],
    "sg:phone":"+1 260 421 1330",
    "sg:postcode":"46816",
    "sg:province":"IN",
    "sg:tags":[
        "executive"
    ],
    "wof:name":"Hessen Cassel Branch Library",
    "wof:placetype":"venue"
},
  "geometry": {"coordinates":[-85.096082,41.032426],"type":"Point"}
}