{
  "type": "Feature",
  "properties": {
    "addr:full":"300 N Capitol Ave Corydon IN 47112",
    "addr:housenumber":"300",
    "addr:postcode":"47112",
    "addr:street":"N Capitol Ave",
    "iso:country":"US",
    "sg:address":"300 N Capitol Ave",
    "sg:city":"Corydon",
    "sg:classifiers":[
        {
            "category":"Government",
            "subcategory":"Court House",
            "type":"Public Place"
        }
    ],
    "sg:phone":"+1 812 738 4289",
    "sg:postcode":"47112",
    "sg:province":"IN",
    "sg:tags":[
        "county"
    ],
    "wof:name":"Circuit Court Clerk",
    "wof:placetype":"venue"
},
  "geometry": {"coordinates":[-86.126311,38.212251],"type":"Point"}
}