{
  "type": "Feature",
  "properties": {
    "iso:country":"US",
    "sg:address":"9987 Springwood Ct",
    "sg:city":"Mc Cordsville",
    "sg:classifiers":[
        {
            "category":"Professional",
            "subcategory":"Management & Consulting",
            "type":"Services"
        }
    ],
    "sg:phone":"+1 317 335 7677",
    "sg:postcode":"46055",
    "sg:province":"IN",
    "wof:name":"Apex Marketing Inc",
    "wof:placetype":"venue"
},
  "geometry": {"coordinates":[-85.92607700000001,39.933092],"type":"Point"}
}