{
  "type": "Feature",
  "properties": {
    "iso:country":"US",
    "sg:address":"3944 Marseille Ct",
    "sg:city":"Indianapolis",
    "sg:classifiers":[
        {
            "category":"Professional",
            "subcategory":"Business Services",
            "type":"Services"
        }
    ],
    "sg:phone":"+1 317 898 4897",
    "sg:postcode":"46226",
    "sg:province":"IN",
    "wof:name":"Real Solutions Investments",
    "wof:placetype":"venue"
},
  "geometry": {"coordinates":[-86.01785,39.828813],"type":"Point"}
}