{
  "type": "Feature",
  "properties": {
    "iso:country":"US",
    "sg:address":"3416 Highway Ave",
    "sg:city":"Highland",
    "sg:classifiers":[
        {
            "category":"Retail",
            "subcategory":"Laundry & Dry Cleaning",
            "type":"Services"
        }
    ],
    "sg:phone":"+1 219 838 3667",
    "sg:postcode":"46322",
    "sg:province":"IN",
    "sg:tags":[
        "cleaners",
        "rug",
        "carpet"
    ],
    "wof:name":"Quality Carpet Cleaning",
    "wof:placetype":"venue"
},
  "geometry": {"coordinates":[-87.444931,41.555468],"type":"Point"}
}