{
  "type": "Feature",
  "properties": {
    "iso:country":"US",
    "sg:address":"113 N Main St",
    "sg:city":"Kendallville",
    "sg:classifiers":[
        {
            "category":"Professional",
            "subcategory":"Accounting & Tax Preparation",
            "type":"Services"
        }
    ],
    "sg:phone":"+1 260 347 1940",
    "sg:postcode":"46755",
    "sg:province":"IN",
    "sg:tags":[
        "accountant"
    ],
    "wof:name":"Scott R Frick CPA",
    "wof:placetype":"venue"
},
  "geometry": {"coordinates":[-85.265945,41.444452],"type":"Point"}
}