{
  "type": "Feature",
  "properties": {
    "iso:country":"US",
    "sg:address":"8425 Keystone Xing",
    "sg:city":"Indianapolis",
    "sg:classifiers":[
        {
            "category":"Professional",
            "subcategory":"Management & Consulting",
            "type":"Services"
        }
    ],
    "sg:phone":"+1 317 255 4107",
    "sg:postcode":"46240",
    "sg:province":"IN",
    "wof:name":"Sandlian Management Corp",
    "wof:placetype":"venue"
},
  "geometry": {"coordinates":[-86.114517,39.910141],"type":"Point"}
}