{
  "type": "Feature",
  "properties": {
    "iso:country":"US",
    "sg:address":"1316 Eagle Ridge Dr",
    "sg:city":"Schererville",
    "sg:classifiers":[
        {
            "category":"Education",
            "subcategory":"Special Training",
            "type":"Public Place"
        }
    ],
    "sg:phone":"+1 219 864 5050",
    "sg:postcode":"46375",
    "sg:province":"IN",
    "sg:tags":[
        "educational"
    ],
    "wof:name":"Integrated Educators",
    "wof:placetype":"venue"
},
  "geometry": {"coordinates":[-87.473716,41.506996],"type":"Point"}
}