{
  "type": "Feature",
  "properties": {
    "iso:country":"US",
    "sg:address":"47 S Pennsylvania St",
    "sg:city":"Indianapolis",
    "sg:classifiers":[
        {
            "category":"Banks & Credit Unions",
            "subcategory":"Investment Brokerage",
            "type":"Services"
        },
        {
            "category":"Banks & Credit Unions",
            "subcategory":"Financial Services",
            "type":"Services"
        }
    ],
    "sg:phone":"+1 317 635 1600",
    "sg:postcode":"46204",
    "sg:province":"IN",
    "sg:tags":[
        "management"
    ],
    "wof:name":"Pillar Investments",
    "wof:placetype":"venue"
},
  "geometry": {"coordinates":[-86.156307,39.766119],"type":"Point"}
}