{
  "type": "Feature",
  "properties": {
    "addr:full":"2237 Bellefontaine St Indianapolis IN 46205",
    "addr:housenumber":"2237",
    "addr:postcode":"46205",
    "addr:street":"Bellefontaine St",
    "iso:country":"US",
    "sg:address":"2237 Bellefontaine St",
    "sg:city":"Indianapolis",
    "sg:classifiers":[
        {
            "category":"Personal",
            "subcategory":"Beauty Salon",
            "type":"Services"
        }
    ],
    "sg:phone":"+1 317 931 0528",
    "sg:postcode":"46205",
    "sg:province":"IN",
    "sg:tags":[
        "cosmetologist"
    ],
    "wof:name":"Danielle D Bouquett",
    "wof:placetype":"venue"
},
  "geometry": {"coordinates":[-86.141396,39.798816],"type":"Point"}
}