{
  "type": "Feature",
  "properties": {
    "iso:country":"US",
    "sg:address":"1417 N Belleview Pl",
    "sg:city":"Indianapolis",
    "sg:classifiers":[
        {
            "category":"Social Services",
            "subcategory":"Child Care",
            "type":"Services"
        }
    ],
    "sg:phone":"+1 317 423 8699",
    "sg:postcode":"46222",
    "sg:province":"IN",
    "wof:name":"Tots USA",
    "wof:placetype":"venue"
},
  "geometry": {"coordinates":[-86.202839,39.787792],"type":"Point"}
}