{
  "type": "Feature",
  "properties": {
    "iso:country":"US",
    "sg:address":"520 Broadway",
    "sg:city":"Chesterton",
    "sg:classifiers":[
        {
            "category":"Restaurant",
            "type":"Food & Drink"
        }
    ],
    "sg:phone":"+1 219 929 1804",
    "sg:postcode":"46304",
    "sg:province":"IN",
    "wof:name":"Red Cup Cafe & Deli",
    "wof:placetype":"venue"
},
  "geometry": {"coordinates":[-87.058645,41.61138],"type":"Point"}
}