{
  "type": "Feature",
  "properties": {
    "iso:country":"US",
    "sg:address":"1525 E 79th St",
    "sg:city":"Indianapolis",
    "sg:classifiers":[
        {
            "category":"Professional",
            "subcategory":"Advertising",
            "type":"Services"
        }
    ],
    "sg:phone":"+1 317 255 0289",
    "sg:postcode":"46240",
    "sg:province":"IN",
    "sg:tags":[
        "representative"
    ],
    "wof:name":"Ad Studio",
    "wof:placetype":"venue"
},
  "geometry": {"coordinates":[-86.13036200000001,39.89758],"type":"Point"}
}