{
  "type": "Feature",
  "properties": {
    "iso:country":"US",
    "sg:address":"315 N Miller St",
    "sg:city":"Shelbyville",
    "sg:classifiers":[
        {
            "category":"Personal",
            "subcategory":"Barber",
            "type":"Services"
        }
    ],
    "sg:phone":"+1 317 398 4226",
    "sg:postcode":"46176",
    "sg:province":"IN",
    "sg:tags":[
        "shop"
    ],
    "wof:name":"Hoban Barber Shop",
    "wof:placetype":"venue"
},
  "geometry": {"coordinates":[-85.78479400000001,39.527858],"type":"Point"}
}