{
  "type": "Feature",
  "properties": {
    "iso:country":"US",
    "sg:address":"916 N Central Ave",
    "sg:city":"Connersville",
    "sg:classifiers":[
        {
            "category":"Autos & Motor Vehicles",
            "subcategory":"Auto Supplies",
            "type":"Retail Goods"
        }
    ],
    "sg:phone":"+1 765 825 8585",
    "sg:postcode":"47331",
    "sg:province":"IN",
    "sg:tags":[
        "automobile",
        "parts"
    ],
    "wof:name":"Wells Auto Parts",
    "wof:placetype":"venue"
},
  "geometry": {"coordinates":[-85.135991,39.645568],"type":"Point"}
}