{
  "type": "Feature",
  "properties": {
    "iso:country":"US",
    "sg:address":"4 Swanson Mnr",
    "sg:city":"Elkhart",
    "sg:classifiers":[
        {
            "category":"Organizations",
            "subcategory":"Religious Organization",
            "type":"Services"
        }
    ],
    "sg:phone":"+1 574 522 0525",
    "sg:postcode":"46516",
    "sg:province":"IN",
    "wof:name":"Don & Mary Jane Carpenter",
    "wof:placetype":"venue"
},
  "geometry": {"coordinates":[-85.937513,41.693366],"type":"Point"}
}