{
  "type": "Feature",
  "properties": {
    "iso:country":"US",
    "sg:address":"400 W Vaughn Dr",
    "sg:city":"Madison",
    "sg:classifiers":[
        {
            "category":"Recreation",
            "type":"Entertainment"
        }
    ],
    "sg:phone":"+1 812 273 6268",
    "sg:postcode":"47250",
    "sg:province":"IN",
    "sg:tags":[
        "pool",
        "swimming"
    ],
    "wof:name":"Crystal Beach Swimming Pool",
    "wof:placetype":"venue"
},
  "geometry": {"coordinates":[-85.385694,38.73381],"type":"Point"}
}