{
  "type": "Feature",
  "properties": {
    "iso:country":"US",
    "sg:address":"312 N Vine St",
    "sg:city":"Greencastle",
    "sg:classifiers":[
        {
            "category":"Wholesale",
            "subcategory":"Dairy",
            "type":"Manufacturing & Wholesale Goods"
        }
    ],
    "sg:phone":"+1 765 653 5181",
    "sg:postcode":"46135",
    "sg:province":"IN",
    "sg:tags":[
        "product"
    ],
    "wof:name":"Handy's Dairy Products Inc",
    "wof:placetype":"venue"
},
  "geometry": {"coordinates":[-86.863533,39.64731],"type":"Point"}
}