{
  "type": "Feature",
  "properties": {
    "iso:country":"US",
    "sg:address":"310 Crawford St",
    "sg:city":"Crawfordsville",
    "sg:classifiers":[
        {
            "category":"Education",
            "subcategory":"College",
            "type":"Public Place"
        }
    ],
    "sg:phone":"+1 765 361 0512",
    "sg:postcode":"47933",
    "sg:province":"IN",
    "sg:tags":[
        "academic",
        "school"
    ],
    "wof:name":"Wabash College",
    "wof:placetype":"venue"
},
  "geometry": {"coordinates":[-86.908635,40.039274],"type":"Point"}
}