{
  "type": "Feature",
  "properties": {
    "iso:country":"US",
    "sg:address":"1913 Stringtown Rd",
    "sg:city":"Evansville",
    "sg:classifiers":[
        {
            "category":"Wholesale",
            "subcategory":"Electrical",
            "type":"Manufacturing & Wholesale Goods"
        }
    ],
    "sg:phone":"+1 812 422 2752",
    "sg:postcode":"47711",
    "sg:province":"IN",
    "sg:tags":[
        "intercommunication"
    ],
    "wof:name":"Ruxer Service & Supply",
    "wof:placetype":"venue"
},
  "geometry": {"coordinates":[-87.555411,37.995555],"type":"Point"}
}