{
  "type": "Feature",
  "properties": {
    "addr:full":"10155 Lothbury Cir Fishers IN 46037",
    "addr:housenumber":"10155",
    "addr:postcode":"46037",
    "addr:street":"Lothbury Cir",
    "iso:country":"US",
    "sg:address":"10155 Lothbury Cir",
    "sg:city":"Fishers",
    "sg:classifiers":[
        {
            "category":"Professional",
            "subcategory":"Management & Consulting",
            "type":"Services"
        }
    ],
    "sg:phone":"+1 317 579 1900",
    "sg:postcode":"46037",
    "sg:province":"IN",
    "sg:tags":[
        "consultant",
        "business"
    ],
    "wof:name":"Hamilton Alliance",
    "wof:placetype":"venue"
},
  "geometry": {"coordinates":[-85.950101,39.93852],"type":"Point"}
}