{
  "type": "Feature",
  "properties": {
    "iso:country":"US",
    "sg:address":"5336 Culver Ln",
    "sg:city":"Greenwood",
    "sg:classifiers":[
        {
            "category":"Professional",
            "subcategory":"Business Services",
            "type":"Services"
        }
    ],
    "sg:phone":"+1 317 881 1865",
    "sg:postcode":"46142",
    "sg:province":"IN",
    "wof:name":"Bw Quality Construction Inc",
    "wof:placetype":"venue"
},
  "geometry": {"coordinates":[-86.203371,39.608827],"type":"Point"}
}