{
  "type": "Feature",
  "properties": {
    "iso:country":"US",
    "sg:address":"1202 N 600 W",
    "sg:city":"Anderson",
    "sg:classifiers":[
        {
            "category":"Retail",
            "subcategory":"Auto Repair",
            "type":"Services"
        }
    ],
    "sg:phone":"+1 765 642 3797",
    "sg:postcode":"46011",
    "sg:province":"IN",
    "sg:tags":[
        "repairing",
        "automobile"
    ],
    "wof:name":"Collins Auto Svc",
    "wof:placetype":"venue"
},
  "geometry": {"coordinates":[-85.78636899999999,40.1229],"type":"Point"}
}