{
  "type": "Feature",
  "properties": {
    "iso:country":"US",
    "sg:address":"3329 W County Line Rd S",
    "sg:city":"Fort Wayne",
    "sg:classifiers":[
        {
            "category":"Recreation",
            "type":"Entertainment"
        }
    ],
    "sg:phone":"+1 260 625 3286",
    "sg:postcode":"46814",
    "sg:province":"IN",
    "sg:tags":[
        "stable"
    ],
    "wof:name":"Hunter Hill Stables",
    "wof:placetype":"venue"
},
  "geometry": {"coordinates":[-85.336308,41.049605],"type":"Point"}
}