{
  "type": "Feature",
  "properties": {
    "addr:full":"8081 Zionsville Rd Indianapolis IN 46268",
    "addr:housenumber":"8081",
    "addr:postcode":"46268",
    "addr:street":"Zionsville Rd",
    "iso:country":"US",
    "sg:address":"8081 Zionsville Rd",
    "sg:city":"Indianapolis",
    "sg:classifiers":[
        {
            "category":"Professional",
            "type":"Services"
        },
        {
            "category":"Wholesale",
            "subcategory":"Computers",
            "type":"Manufacturing & Wholesale Goods"
        }
    ],
    "sg:phone":"+1 317 872 7220",
    "sg:postcode":"46268",
    "sg:province":"IN",
    "sg:tags":[
        "equipment",
        "processing",
        "data"
    ],
    "wof:name":"Bisy's Education Services Inc",
    "wof:placetype":"venue"
},
  "geometry": {"coordinates":[-86.25984200000001,39.899583],"type":"Point"}
}