{
  "type": "Feature",
  "properties": {
    "iso:country":"US",
    "sg:address":"675 N Calumet Ave",
    "sg:city":"Valparaiso",
    "sg:classifiers":[
        {
            "category":"Cinema",
            "subcategory":"Movie Theater",
            "type":"Entertainment"
        }
    ],
    "sg:phone":"+1 219 462 6122",
    "sg:postcode":"46383",
    "sg:province":"IN",
    "wof:name":"49er Drive-In Theatre",
    "wof:placetype":"venue"
},
  "geometry": {"coordinates":[-87.035714,41.531452],"type":"Point"}
}