{
  "type": "Feature",
  "properties": {
    "iso:country":"US",
    "sg:address":"53143 Pine Dr",
    "sg:city":"Middlebury",
    "sg:classifiers":[
        {
            "category":"Professional",
            "subcategory":"Management & Consulting",
            "type":"Services"
        }
    ],
    "sg:phone":"+1 574 825 5177",
    "sg:postcode":"46540",
    "sg:province":"IN",
    "sg:tags":[
        "business"
    ],
    "wof:name":"Vantage Unlimited Inc",
    "wof:placetype":"venue"
},
  "geometry": {"coordinates":[-85.707884,41.723614],"type":"Point"}
}