{
  "type": "Feature",
  "properties": {
    "iso:country":"US",
    "sg:address":"10219 River Rapids Run",
    "sg:city":"Fort Wayne",
    "sg:classifiers":[
        {
            "category":"Real Estate",
            "subcategory":"Real Estate Agent",
            "type":"Services"
        }
    ],
    "sg:phone":"+1 260 471 0003",
    "sg:postcode":"46845",
    "sg:province":"IN",
    "sg:tags":[
        "appraiser"
    ],
    "wof:name":"Scott Fields Certified Real",
    "wof:placetype":"venue"
},
  "geometry": {"coordinates":[-85.062595,41.178368],"type":"Point"}
}