{
  "type": "Feature",
  "properties": {
    "iso:country":"US",
    "sg:address":"9229 W Co Rd 650 S",
    "sg:city":"Knightstown",
    "sg:classifiers":[
        {
            "category":"Restaurant",
            "type":"Food & Drink"
        }
    ],
    "sg:phone":"+1 765 785 2700",
    "sg:postcode":"46148",
    "sg:province":"IN",
    "wof:name":"Burger King",
    "wof:placetype":"venue"
},
  "geometry": {"coordinates":[-85.56184,39.836985],"type":"Point"}
}