{
  "type": "Feature",
  "properties": {
    "iso:country":"US",
    "sg:address":"801 Jackson St",
    "sg:city":"Salem",
    "sg:classifiers":[
        {
            "category":"Government",
            "subcategory":"Court House",
            "type":"Public Place"
        }
    ],
    "sg:phone":"+1 812 883 4949",
    "sg:postcode":"47167",
    "sg:province":"IN",
    "sg:tags":[
        "county"
    ],
    "wof:name":"Washington Superior Court",
    "wof:placetype":"venue"
},
  "geometry": {"coordinates":[-86.091832,38.597532],"type":"Point"}
}