{
  "type": "Feature",
  "properties": {
    "iso:country":"US",
    "sg:address":"723 S Range Line Rd",
    "sg:city":"Carmel",
    "sg:classifiers":[
        {
            "category":"Shopping",
            "type":"Retail Goods"
        },
        {
            "category":"Sports & Exercise",
            "subcategory":"Swimming Pool",
            "type":"Entertainment"
        }
    ],
    "sg:phone":"+1 317 848 1320",
    "sg:postcode":"46032",
    "sg:province":"IN",
    "sg:tags":[
        "equipment",
        "divers'",
        "instruction",
        "diving",
        "supply"
    ],
    "wof:name":"Divers Supply Indy North",
    "wof:placetype":"venue"
},
  "geometry": {"coordinates":[-86.126931,39.970277],"type":"Point"}
}