{
  "type": "Feature",
  "properties": {
    "addr:full":"3175 E 500 S Atlanta IN 46031",
    "addr:housenumber":"3175",
    "addr:postcode":"46031",
    "addr:street":"E 500 S",
    "iso:country":"US",
    "sg:address":"3175 E 500 S",
    "sg:city":"Atlanta",
    "sg:phone":"+1 765 292 2232",
    "sg:postcode":"46031",
    "sg:province":"IN",
    "sg:tags":[
        "farm",
        "corn",
        "equine",
        "soybean"
    ],
    "wof:name":"Oakwood",
    "wof:placetype":"venue"
},
  "geometry": {"coordinates":[-85.954393,40.232764],"type":"Point"}
}