{
  "type": "Feature",
  "properties": {
    "iso:country":"US",
    "sg:address":"141 W 22nd St",
    "sg:city":"Anderson",
    "sg:classifiers":[
        {
            "category":"Health Services",
            "subcategory":"Doctor",
            "type":"Services"
        }
    ],
    "sg:phone":"+1 765 643 0766",
    "sg:postcode":"46016",
    "sg:province":"IN",
    "sg:tags":[
        "physician",
        "surgeon"
    ],
    "wof:name":"Anderson Urologic Assoc",
    "wof:placetype":"venue"
},
  "geometry": {"coordinates":[-85.681787,40.094371],"type":"Point"}
}