{
  "type": "Feature",
  "properties": {
    "addr:full":"4701 E Wall St Fort Wayne IN 46816",
    "addr:housenumber":"4701",
    "addr:postcode":"46816",
    "addr:street":"E Wall St",
    "iso:country":"US",
    "sg:address":"4701 E Wall St",
    "sg:city":"Fort Wayne",
    "sg:classifiers":[
        {
            "category":"Professional",
            "subcategory":"Art Services",
            "type":"Services"
        }
    ],
    "sg:phone":"+1 260 639 0006",
    "sg:postcode":"46816",
    "sg:province":"IN",
    "sg:tags":[
        "photography",
        "commercial"
    ],
    "wof:name":"Photography By Don Shutt",
    "wof:placetype":"venue"
},
  "geometry": {"coordinates":[-85.07763199999999,40.979466],"type":"Point"}
}