{
  "type": "Feature",
  "properties": {
    "iso:country":"US",
    "sg:address":"1401 E 84th Pl",
    "sg:city":"Merrillville",
    "sg:classifiers":[
        {
            "category":"Government",
            "subcategory":"Office",
            "type":"Public Place"
        }
    ],
    "sg:phone":"+1 219 769 2671",
    "sg:postcode":"46410",
    "sg:province":"IN",
    "sg:tags":[
        "federal",
        "human"
    ],
    "wof:name":"US Social Security Adm",
    "wof:placetype":"venue"
},
  "geometry": {"coordinates":[-87.31953799999999,41.46485],"type":"Point"}
}