{
  "type": "Feature",
  "properties": {
    "iso:country":"US",
    "sg:address":"1405 E Main St",
    "sg:city":"Griffith",
    "sg:classifiers":[
        {
            "category":"Wholesale",
            "subcategory":"Auto Parts",
            "type":"Manufacturing & Wholesale Goods"
        }
    ],
    "sg:phone":"+1 219 924 2466",
    "sg:postcode":"46319",
    "sg:province":"IN",
    "sg:tags":[
        "automobile",
        "rebuilt"
    ],
    "sg:website":"www.griffithautoparts.com",
    "wof:name":"A Griffith Auto Recycling",
    "wof:placetype":"venue"
},
  "geometry": {"coordinates":[-87.409082,41.522566],"type":"Point"}
}