{
  "type": "Feature",
  "properties": {
    "iso:country":"US",
    "sg:address":"6500 W 800 S",
    "sg:city":"Fairmount",
    "sg:classifiers":[
        {
            "category":"Professional",
            "subcategory":"Employment Agencies",
            "type":"Services"
        }
    ],
    "sg:phone":"+1 765 922 7769",
    "sg:postcode":"46928",
    "sg:province":"IN",
    "wof:name":"Beattie April",
    "wof:placetype":"venue"
},
  "geometry": {"coordinates":[-85.79586999999999,40.436126],"type":"Point"}
}