{
  "type": "Feature",
  "properties": {
    "iso:country":"US",
    "sg:address":"211 W Washington St",
    "sg:city":"South Bend",
    "sg:classifiers":[
        {
            "category":"Professional",
            "subcategory":"Lawyer & Legal Services",
            "type":"Services"
        }
    ],
    "sg:phone":"+1 574 288 1800",
    "sg:postcode":"46601",
    "sg:province":"IN",
    "sg:tags":[
        "attorney"
    ],
    "sg:website":"www.doranblackmond.com",
    "wof:name":"Doran Blackmond",
    "wof:placetype":"venue"
},
  "geometry": {"coordinates":[-86.25346399999999,41.676424],"type":"Point"}
}