{
  "type": "Feature",
  "properties": {
    "iso:country":"US",
    "sg:address":"815 W Main St",
    "sg:city":"Mitchell",
    "sg:classifiers":[
        {
            "category":"Insurance",
            "subcategory":"Insurance Agent",
            "type":"Services"
        }
    ],
    "sg:phone":"+1 812 849 0456",
    "sg:postcode":"47446",
    "sg:province":"IN",
    "wof:name":"Bill Barlow Insurance Svc",
    "wof:placetype":"venue"
},
  "geometry": {"coordinates":[-86.47481399999999,38.732523],"type":"Point"}
}