{
  "type": "Feature",
  "properties": {
    "addr:full":"456 Monroe St Gary IN 46402",
    "addr:housenumber":"456",
    "addr:postcode":"46402",
    "addr:street":"Monroe St Gary",
    "iso:country":"US",
    "sg:address":"456 Monroe St",
    "sg:city":"Gary",
    "sg:classifiers":[
        {
            "category":"Organizations",
            "subcategory":"Religious Organization",
            "type":"Services"
        }
    ],
    "sg:phone":"+1 219 886 0988",
    "sg:postcode":"46402",
    "sg:province":"IN",
    "wof:name":"Anew Life Ministries",
    "wof:placetype":"venue"
},
  "geometry": {"coordinates":[-87.343374,41.603544],"type":"Point"}
}