{
  "type": "Feature",
  "properties": {
    "iso:country":"US",
    "sg:address":"897 Apache Ln",
    "sg:city":"Lowell",
    "sg:classifiers":[
        {
            "category":"Building & Trades",
            "subcategory":"Construction",
            "type":"Services"
        }
    ],
    "sg:phone":"+1 219 696 6424",
    "sg:postcode":"46356",
    "sg:province":"IN",
    "sg:tags":[
        "concrete",
        "contractor"
    ],
    "wof:name":"Husky Concrete",
    "wof:placetype":"venue"
},
  "geometry": {"coordinates":[-87.441975,41.296684],"type":"Point"}
}