{
  "type": "Feature",
  "properties": {
    "iso:country":"US",
    "sg:address":"6421 Oaklandon Rd",
    "sg:city":"Indianapolis",
    "sg:classifiers":[
        {
            "category":"Real Estate",
            "subcategory":"Real Estate Agent",
            "type":"Services"
        }
    ],
    "sg:phone":"+1 317 823 4663",
    "sg:postcode":"46236",
    "sg:province":"IN",
    "sg:website":"www.realestateindy.net",
    "wof:name":"Re/Max Real Estate Group",
    "wof:placetype":"venue"
},
  "geometry": {"coordinates":[-85.95710099999999,39.875765],"type":"Point"}
}