{
  "type": "Feature",
  "properties": {
    "addr:full":"14000 W State Rd 28 Gaston IN 47342",
    "addr:housenumber":"14000;28",
    "addr:postcode":"47342",
    "addr:street":"W State Rd",
    "iso:country":"US",
    "sg:address":"14000 W State Rd 28",
    "sg:city":"Gaston",
    "sg:classifiers":[
        {
            "category":"Restaurant",
            "type":"Food & Drink"
        }
    ],
    "sg:phone":"+1 765 358 3396",
    "sg:postcode":"47342",
    "sg:province":"IN",
    "wof:name":"Iron Skillet Restaurant",
    "wof:placetype":"venue"
},
  "geometry": {"coordinates":[-85.55224,40.276637],"type":"Point"}
}