{
  "type": "Feature",
  "properties": {
    "iso:country":"US",
    "sg:address":"4550 E 100 S",
    "sg:city":"Lagrange",
    "sg:classifiers":[
        {
            "category":"Government",
            "subcategory":"Office",
            "type":"Public Place"
        }
    ],
    "sg:phone":"+1 260 463 4022",
    "sg:postcode":"46761",
    "sg:province":"IN",
    "wof:name":"County Of Lagrange Nature Ctr",
    "wof:placetype":"venue"
},
  "geometry": {"coordinates":[-85.336938,41.627425],"type":"Point"}
}