{
  "type": "Feature",
  "properties": {
    "iso:country":"US",
    "sg:address":"1251 US Hwy 31 N",
    "sg:city":"Greenwood",
    "sg:classifiers":[
        {
            "category":"Manufacturing",
            "subcategory":"Food",
            "type":"Manufacturing & Wholesale Goods"
        }
    ],
    "sg:phone":"+1 317 859 0809",
    "sg:postcode":"46142",
    "sg:province":"IN",
    "sg:tags":[
        "pretzel"
    ],
    "wof:name":"Auntie Anne's Hand Rolled Soft",
    "wof:placetype":"venue"
},
  "geometry": {"coordinates":[-86.126043,39.63459],"type":"Point"}
}