{
  "type": "Feature",
  "properties": {
    "iso:country":"US",
    "sg:address":"519 S Liberty St",
    "sg:city":"Muncie",
    "sg:classifiers":[
        {
            "category":"Freight",
            "type":"Transportation"
        }
    ],
    "sg:phone":"+1 765 741 8776",
    "sg:postcode":"47305",
    "sg:province":"IN",
    "sg:tags":[
        "general"
    ],
    "wof:name":"Kl Costello Group LLC",
    "wof:placetype":"venue"
},
  "geometry": {"coordinates":[-85.390018,40.18955],"type":"Point"}
}