{
  "type": "Feature",
  "properties": {
    "iso:country":"US",
    "sg:address":"12540 E 136th St",
    "sg:city":"Noblesville",
    "sg:classifiers":[
        {
            "category":"Arts & Performance",
            "subcategory":"Theater",
            "type":"Entertainment"
        }
    ],
    "sg:phone":"+1 317 674 9000",
    "sg:postcode":"46060",
    "sg:province":"IN",
    "sg:tags":[
        "bureau"
    ],
    "wof:name":"Indiana Ticket Brokers Inc",
    "wof:placetype":"venue"
},
  "geometry": {"coordinates":[-85.941877,39.986881],"type":"Point"}
}