{
  "type": "Feature",
  "properties": {
    "iso:country":"US",
    "sg:address":"5751 Mahalia Way",
    "sg:city":"Bloomington",
    "sg:classifiers":[
        {
            "category":"Building & Trades",
            "subcategory":"Landscaping Services",
            "type":"Services"
        }
    ],
    "sg:phone":"+1 812 339 7683",
    "sg:postcode":"47408",
    "sg:province":"IN",
    "sg:tags":[
        "lawn",
        "maintenance",
        "grounds"
    ],
    "wof:name":"Nolan's Lawn Care Svc Inc",
    "wof:placetype":"venue"
},
  "geometry": {"coordinates":[-86.447844,39.167303],"type":"Point"}
}