{
  "type": "Feature",
  "properties": {
    "iso:country":"US",
    "sg:address":"3514 Rockville Rd",
    "sg:city":"Indianapolis",
    "sg:classifiers":[
        {
            "category":"Retail",
            "subcategory":"Laundry & Dry Cleaning",
            "type":"Services"
        }
    ],
    "sg:phone":"+1 317 244 8430",
    "sg:postcode":"46222",
    "sg:province":"IN",
    "sg:tags":[
        "cleaners",
        "rug",
        "carpet"
    ],
    "wof:name":"Your Choice Carpet Cleaning",
    "wof:placetype":"venue"
},
  "geometry": {"coordinates":[-86.221059,39.762905],"type":"Point"}
}