{
  "type": "Feature",
  "properties": {
    "iso:country":"US",
    "sg:address":"9120 Otis Ave Ste 201",
    "sg:city":"Indianapolis",
    "sg:classifiers":[
        {
            "category":"Home & Garden",
            "subcategory":"Building Materials",
            "type":"Retail Goods"
        },
        {
            "category":"Building & Trades",
            "subcategory":"Construction",
            "type":"Services"
        }
    ],
    "sg:phone":"+1 317 546 7419",
    "sg:postcode":"46216",
    "sg:province":"IN",
    "sg:tags":[
        "concrete",
        "staining",
        "contractor"
    ],
    "wof:name":"Bridgetek",
    "wof:placetype":"venue"
},
  "geometry": {"coordinates":[-86.009304,39.856665],"type":"Point"}
}