{
  "type": "Feature",
  "properties": {
    "iso:country":"US",
    "sg:address":"28 W Bujey Dr",
    "sg:city":"Evansville",
    "sg:classifiers":[
        {
            "category":"Building & Trades",
            "subcategory":"Construction",
            "type":"Services"
        }
    ],
    "sg:phone":"+1 812 867 0380",
    "sg:postcode":"47710",
    "sg:province":"IN",
    "sg:tags":[
        "roofing",
        "contractor"
    ],
    "wof:name":"Cummings Construction",
    "wof:placetype":"venue"
},
  "geometry": {"coordinates":[-87.567428,38.044881],"type":"Point"}
}