{
  "type": "Feature",
  "properties": {
    "iso:country":"US",
    "sg:address":"4415 McCurdy Rd",
    "sg:city":"Indianapolis",
    "sg:classifiers":[
        {
            "category":"Health Services",
            "subcategory":"Doctor",
            "type":"Services"
        }
    ],
    "sg:phone":"+1 317 291 2097",
    "sg:postcode":"46234",
    "sg:province":"IN",
    "sg:tags":[
        "medical"
    ],
    "wof:name":"Karen L Bumb MD Inc",
    "wof:placetype":"venue"
},
  "geometry": {"coordinates":[-86.313218,39.835977],"type":"Point"}
}