{
  "type": "Feature",
  "properties": {
    "iso:country":"US",
    "sg:address":"7114 E State Rd 28",
    "sg:city":"Elwood",
    "sg:classifiers":[
        {
            "category":"Personal",
            "type":"Services"
        }
    ],
    "sg:phone":"+1 765 552 0655",
    "sg:postcode":"46036",
    "sg:province":"IN",
    "wof:name":"Native Ink Tattoo",
    "wof:placetype":"venue"
},
  "geometry": {"coordinates":[-85.871269,40.27692],"type":"Point"}
}