{
  "type": "Feature",
  "properties": {
    "iso:country":"US",
    "sg:address":"3686 S Co Rd 250 W",
    "sg:city":"Danville",
    "sg:classifiers":[
        {
            "category":"Building & Trades",
            "subcategory":"Construction",
            "type":"Services"
        }
    ],
    "sg:phone":"+1 317 539 0771",
    "sg:postcode":"46122",
    "sg:province":"IN",
    "sg:tags":[
        "contractor"
    ],
    "wof:name":"Ewing & Co",
    "wof:placetype":"venue"
},
  "geometry": {"coordinates":[-86.573869,39.706793],"type":"Point"}
}