{
  "type": "Feature",
  "properties": {
    "iso:country":"US",
    "sg:address":"858 W Lincolnway",
    "sg:city":"Valparaiso",
    "sg:classifiers":[
        {
            "category":"Professional",
            "subcategory":"Detective & Security Services",
            "type":"Services"
        }
    ],
    "sg:phone":"+1 219 548 1331",
    "sg:postcode":"46385",
    "sg:province":"IN",
    "sg:tags":[
        "guard",
        "patrol"
    ],
    "wof:name":"A & B Security Svc Inc",
    "wof:placetype":"venue"
},
  "geometry": {"coordinates":[-87.071301,41.469555],"type":"Point"}
}