{
  "type": "Feature",
  "properties": {
    "iso:country":"US",
    "sg:address":"217 E Pearl St",
    "sg:city":"Portland",
    "sg:classifiers":[
        {
            "category":"Freight",
            "type":"Transportation"
        }
    ],
    "sg:phone":"+1 260 726 2833",
    "sg:postcode":"47371",
    "sg:province":"IN",
    "sg:tags":[
        "commercial",
        "storage"
    ],
    "wof:name":"Inman U Loc Storage",
    "wof:placetype":"venue"
},
  "geometry": {"coordinates":[-84.975136,40.440372],"type":"Point"}
}