{
  "type": "Feature",
  "properties": {
    "iso:country":"US",
    "sg:address":"1050 Kennedy Ave",
    "sg:city":"Schererville",
    "sg:classifiers":[
        {
            "category":"Manufacturing",
            "subcategory":"Metals",
            "type":"Manufacturing & Wholesale Goods"
        }
    ],
    "sg:phone":"+1 219 865 1700",
    "sg:postcode":"46375",
    "sg:province":"IN",
    "sg:tags":[
        "steel"
    ],
    "wof:name":"Schererville Steel",
    "wof:placetype":"venue"
},
  "geometry": {"coordinates":[-87.46144200000001,41.501866],"type":"Point"}
}