{
  "type": "Feature",
  "properties": {
    "iso:country":"US",
    "sg:address":"1906 Pine Rd",
    "sg:city":"Lapaz",
    "sg:classifiers":[
        {
            "category":"Building & Trades",
            "subcategory":"Landscaping Services",
            "type":"Services"
        }
    ],
    "sg:phone":"+1 574 784 8889",
    "sg:postcode":"46563",
    "sg:province":"IN",
    "sg:tags":[
        "tree"
    ],
    "wof:name":"Cut-Rite Tree Svc",
    "wof:placetype":"venue"
},
  "geometry": {"coordinates":[-86.348501,41.450206],"type":"Point"}
}