{
  "type": "Feature",
  "properties": {
    "iso:country":"US",
    "sg:address":"2706 Kessler Boulevard West Dr",
    "sg:city":"Indianapolis",
    "sg:classifiers":[
        {
            "category":"Retail",
            "subcategory":"Funeral Services",
            "type":"Services"
        }
    ],
    "sg:phone":"+1 317 251 5959",
    "sg:postcode":"46228",
    "sg:province":"IN",
    "sg:tags":[
        "director"
    ],
    "wof:name":"Flanner & Buchanan Funeral Ctr",
    "wof:placetype":"venue"
},
  "geometry": {"coordinates":[-86.205504,39.853669],"type":"Point"}
}