{
  "type": "Feature",
  "properties": {
    "addr:full":"1304 N Reed Rd Kokomo IN 46901",
    "addr:housenumber":"1304",
    "addr:postcode":"46901",
    "addr:street":"N Reed Rd",
    "iso:country":"US",
    "sg:address":"1304 N Reed Rd",
    "sg:city":"Kokomo",
    "sg:classifiers":[
        {
            "category":"Restaurant",
            "type":"Food & Drink"
        }
    ],
    "sg:phone":"+1 765 868 2373",
    "sg:postcode":"46901",
    "sg:province":"IN",
    "wof:name":"Mc Donald's",
    "wof:placetype":"venue"
},
  "geometry": {"coordinates":[-86.109998,40.500707],"type":"Point"}
}