{
  "type": "Feature",
  "properties": {
    "addr:full":"4111 N Co Rd 300 E Logansport IN 46947",
    "addr:housenumber":"4111",
    "addr:postcode":"46947",
    "addr:street":"N Co Rd 300 E",
    "iso:country":"US",
    "sg:address":"4111 N Co Rd 300 E",
    "sg:city":"Logansport",
    "sg:phone":"+1 574 735 0431",
    "sg:postcode":"46947",
    "sg:province":"IN",
    "sg:tags":[
        "farm",
        "corn",
        "soybean"
    ],
    "wof:name":"Jane Howard",
    "wof:placetype":"venue"
},
  "geometry": {"coordinates":[-86.318949,40.825222],"type":"Point"}
}