{
  "type": "Feature",
  "properties": {
    "iso:country":"US",
    "sg:address":"2501 Soldiers Home Rd",
    "sg:city":"West Lafayette",
    "sg:classifiers":[
        {
            "category":"Real Estate",
            "subcategory":"Real Estate Operator",
            "type":"Services"
        }
    ],
    "sg:phone":"+1 765 463 1116",
    "sg:postcode":"47906",
    "sg:province":"IN",
    "sg:tags":[
        "building",
        "apartment"
    ],
    "sg:website":"www.rentnet.com",
    "wof:name":"Sagamore Ridge Apartments",
    "wof:placetype":"venue"
},
  "geometry": {"coordinates":[-86.903076,40.454319],"type":"Point"}
}