{
  "type": "Feature",
  "properties": {
    "iso:country":"US",
    "sg:address":"6709 Meadowgreen Dr",
    "sg:city":"Indianapolis",
    "sg:classifiers":[
        {
            "category":"Building & Trades",
            "subcategory":"Construction",
            "type":"Services"
        }
    ],
    "sg:phone":"+1 317 727 6603",
    "sg:postcode":"46236",
    "sg:province":"IN",
    "sg:tags":[
        "restoration",
        "cleaning",
        "patio",
        "deck"
    ],
    "wof:name":"Kustom Klean",
    "wof:placetype":"venue"
},
  "geometry": {"coordinates":[-85.968279,39.87923],"type":"Point"}
}