{
  "type": "Feature",
  "properties": {
    "iso:country":"US",
    "sg:address":"2158 45th St PMB 611",
    "sg:city":"Highland",
    "sg:classifiers":[
        {
            "category":"Wholesale",
            "subcategory":"Groceries",
            "type":"Manufacturing & Wholesale Goods"
        }
    ],
    "sg:phone":"+1 313 377 7729",
    "sg:postcode":"46322",
    "sg:province":"IN",
    "sg:tags":[
        "broker",
        "sugar"
    ],
    "wof:name":"Abi Stella Group",
    "wof:placetype":"venue"
},
  "geometry": {"coordinates":[-87.476951,41.537385],"type":"Point"}
}