{
  "type": "Feature",
  "properties": {
    "iso:country":"US",
    "sg:address":"3005 W Ferguson Rd",
    "sg:city":"Fort Wayne",
    "sg:classifiers":[
        {
            "category":"Government",
            "subcategory":"Office",
            "type":"Public Place"
        }
    ],
    "sg:phone":"+1 260 478 3247",
    "sg:postcode":"46819",
    "sg:province":"IN",
    "sg:tags":[
        "state",
        "security"
    ],
    "wof:name":"Air National Guard",
    "wof:placetype":"venue"
},
  "geometry": {"coordinates":[-85.17573400000001,40.989117],"type":"Point"}
}