{
  "type": "Feature",
  "properties": {
    "iso:country":"US",
    "sg:address":"1331 E Berry St",
    "sg:city":"Fort Wayne",
    "sg:classifiers":[
        {
            "category":"Shopping",
            "subcategory":"Used Merchandise",
            "type":"Retail Goods"
        }
    ],
    "sg:phone":"+1 260 422 7887",
    "sg:postcode":"46803",
    "sg:province":"IN",
    "sg:tags":[
        "shop",
        "consignment"
    ],
    "wof:name":"Equipment Resale Inc",
    "wof:placetype":"venue"
},
  "geometry": {"coordinates":[-85.120091,41.081128],"type":"Point"}
}