{
  "type": "Feature",
  "properties": {
    "iso:country":"US",
    "sg:address":"7171 Twin Oaks Dr",
    "sg:city":"Indianapolis",
    "sg:classifiers":[
        {
            "category":"Real Estate",
            "subcategory":"Real Estate Operator",
            "type":"Services"
        }
    ],
    "sg:phone":"+1 317 542 1557",
    "sg:postcode":"46226",
    "sg:province":"IN",
    "sg:tags":[
        "apartment"
    ],
    "wof:name":"Kingston Square Homes Inc",
    "wof:placetype":"venue"
},
  "geometry": {"coordinates":[-86.0425,39.822364],"type":"Point"}
}