{
  "type": "Feature",
  "properties": {
    "iso:country":"US",
    "sg:address":"809 E Main St",
    "sg:city":"New Albany",
    "sg:classifiers":[
        {
            "category":"Organizations",
            "subcategory":"Community Association",
            "type":"Services"
        }
    ],
    "sg:phone":"+1 812 944 0891",
    "sg:postcode":"47150",
    "sg:province":"IN",
    "sg:tags":[
        "fraternal"
    ],
    "wof:name":"Knights Of Columbus",
    "wof:placetype":"venue"
},
  "geometry": {"coordinates":[-85.81565399999999,38.285838],"type":"Point"}
}