{
  "type": "Feature",
  "properties": {
    "iso:country":"US",
    "sg:address":"3340 S 400 W",
    "sg:city":"Tipton",
    "sg:classifiers":[
        {
            "category":"Manufacturing",
            "subcategory":"Glass & Minerals",
            "type":"Manufacturing & Wholesale Goods"
        }
    ],
    "sg:phone":"+1 765 675 7235",
    "sg:postcode":"46072",
    "sg:province":"IN",
    "sg:tags":[
        "product",
        "mfg",
        "lime"
    ],
    "wof:name":"Ed Henry & Son",
    "wof:placetype":"venue"
},
  "geometry": {"coordinates":[-86.088122,40.255446],"type":"Point"}
}