{
  "type": "Feature",
  "properties": {
    "addr:full":"5416 Falcon Creek Blvd Indianapolis IN 46254",
    "addr:housenumber":"5416",
    "addr:postcode":"46254",
    "addr:street":"Falcon Creek Blvd",
    "iso:country":"US",
    "sg:address":"5416 Falcon Creek Blvd",
    "sg:city":"Indianapolis",
    "sg:classifiers":[
        {
            "category":"Arts & Performance",
            "subcategory":"Theater",
            "type":"Entertainment"
        }
    ],
    "sg:phone":"+1 317 298 2543",
    "sg:postcode":"46254",
    "sg:province":"IN",
    "sg:tags":[
        "bureau"
    ],
    "wof:name":"Get It & Flip It Entertainment",
    "wof:placetype":"venue"
},
  "geometry": {"coordinates":[-86.254678,39.834109],"type":"Point"}
}