{
  "type": "Feature",
  "properties": {
    "iso:country":"US",
    "sg:address":"14154 Nicholas Dr",
    "sg:city":"Westfield",
    "sg:classifiers":[
        {
            "category":"Manufacturing",
            "subcategory":"Chemicals & Compounds",
            "type":"Manufacturing & Wholesale Goods"
        }
    ],
    "sg:phone":"+1 317 815 1088",
    "sg:postcode":"46074",
    "sg:province":"IN",
    "sg:tags":[
        "preparation",
        "pharmaceutical",
        "mfg"
    ],
    "wof:name":"Pfizer Corporation",
    "wof:placetype":"venue"
},
  "geometry": {"coordinates":[-86.185099,39.99245],"type":"Point"}
}