{
  "type": "Feature",
  "properties": {
    "iso:country":"US",
    "sg:address":"721 W Sample St",
    "sg:city":"South Bend",
    "sg:classifiers":[
        {
            "category":"Home & Garden",
            "subcategory":"Building Materials",
            "type":"Retail Goods"
        }
    ],
    "sg:phone":"+1 574 232 9807",
    "sg:postcode":"46601",
    "sg:province":"IN",
    "sg:tags":[
        "plumbing",
        "fixture",
        "supply"
    ],
    "wof:name":"Home Plumbing Supply",
    "wof:placetype":"venue"
},
  "geometry": {"coordinates":[-86.261015,41.665185],"type":"Point"}
}