{
  "type": "Feature",
  "properties": {
    "iso:country":"US",
    "sg:address":"302 Liberty St",
    "sg:city":"Covington",
    "sg:classifiers":[
        {
            "category":"Retail",
            "subcategory":"Self-service Laundry",
            "type":"Services"
        }
    ],
    "sg:phone":"+1 765 793 7703",
    "sg:postcode":"47932",
    "sg:province":"IN",
    "wof:name":"Caribbean Connection",
    "wof:placetype":"venue"
},
  "geometry": {"coordinates":[-87.396388,40.13665],"type":"Point"}
}