{
  "type": "Feature",
  "properties": {
    "iso:country":"US",
    "sg:address":"321 Washington St",
    "sg:city":"Columbus",
    "sg:classifiers":[
        {
            "category":"Professional",
            "subcategory":"Lawyer & Legal Services",
            "type":"Services"
        }
    ],
    "sg:phone":"+1 812 372 1553",
    "sg:postcode":"47201",
    "sg:province":"IN",
    "sg:tags":[
        "attorney"
    ],
    "wof:name":"Sharpnack Bigley",
    "wof:placetype":"venue"
},
  "geometry": {"coordinates":[-85.920969,39.202244],"type":"Point"}
}