{
  "type": "Feature",
  "properties": {
    "iso:country":"US",
    "sg:address":"4103 W Portage Trl",
    "sg:city":"Bloomington",
    "sg:classifiers":[
        {
            "category":"Wholesale",
            "subcategory":"Auto Parts",
            "type":"Manufacturing & Wholesale Goods"
        }
    ],
    "sg:phone":"+1 812 876 2230",
    "sg:postcode":"47404",
    "sg:province":"IN",
    "sg:tags":[
        "truck",
        "accessory"
    ],
    "wof:name":"Van Horn Tint & Accessories",
    "wof:placetype":"venue"
},
  "geometry": {"coordinates":[-86.59519,39.219286],"type":"Point"}
}