{
  "type": "Feature",
  "properties": {
    "iso:country":"US",
    "sg:address":"263 E Main St",
    "sg:city":"Peru",
    "sg:classifiers":[
        {
            "category":"Wholesale",
            "subcategory":"Construction Materials",
            "type":"Manufacturing & Wholesale Goods"
        }
    ],
    "sg:phone":"+1 765 473 4441",
    "sg:postcode":"46970",
    "sg:province":"IN",
    "sg:tags":[
        "lumber"
    ],
    "wof:name":"Wallick Post & Lumber Inc",
    "wof:placetype":"venue"
},
  "geometry": {"coordinates":[-86.06157899999999,40.757044],"type":"Point"}
}