{
  "type": "Feature",
  "properties": {
    "iso:country":"US",
    "sg:address":"3583 Village Ct",
    "sg:city":"Gary",
    "sg:classifiers":[
        {
            "category":"Restaurant",
            "type":"Food & Drink"
        }
    ],
    "sg:phone":"+1 219 985 2000",
    "sg:postcode":"46408",
    "sg:province":"IN",
    "wof:name":"Pagoda Hut II",
    "wof:placetype":"venue"
},
  "geometry": {"coordinates":[-87.355824,41.554649],"type":"Point"}
}