{
  "type": "Feature",
  "properties": {
    "iso:country":"US",
    "sg:address":"8 S Euclid Ave",
    "sg:city":"Indianapolis",
    "sg:classifiers":[
        {
            "category":"Building & Trades",
            "subcategory":"Construction",
            "type":"Services"
        }
    ],
    "sg:phone":"+1 317 375 0718",
    "sg:postcode":"46201",
    "sg:province":"IN",
    "sg:tags":[
        "repairing",
        "remodeling",
        "contractor"
    ],
    "wof:name":"Eversole Remodeling",
    "wof:placetype":"venue"
},
  "geometry": {"coordinates":[-86.093821,39.767825],"type":"Point"}
}