{
  "type": "Feature",
  "properties": {
    "iso:country":"US",
    "sg:address":"3740 S Murphy St",
    "sg:city":"Prairieton",
    "sg:classifiers":[
        {
            "category":"Personal",
            "subcategory":"Beauty Salon",
            "type":"Services"
        }
    ],
    "sg:phone":"+1 812 299 2214",
    "sg:postcode":"47802",
    "sg:province":"IN",
    "wof:name":"Judy's Cut & Curl",
    "wof:placetype":"venue"
},
  "geometry": {"coordinates":[-87.475277,39.370378],"type":"Point"}
}