{
  "type": "Feature",
  "properties": {
    "iso:country":"US",
    "sg:address":"550 N Wayne St",
    "sg:city":"Waterloo",
    "sg:phone":"+1 260 837 5291",
    "sg:postcode":"46793",
    "sg:province":"IN",
    "sg:tags":[
        "farm",
        "corn",
        "wheat",
        "soybean"
    ],
    "wof:name":"Dean Sherck",
    "wof:placetype":"venue"
},
  "geometry": {"coordinates":[-85.019338,41.434533],"type":"Point"}
}