{
  "type": "Feature",
  "properties": {
    "iso:country":"US",
    "sg:address":"661 Tague St",
    "sg:city":"Greenfield",
    "sg:classifiers":[
        {
            "category":"Organizations",
            "subcategory":"Community Association",
            "type":"Services"
        }
    ],
    "sg:phone":"+1 317 462 4334",
    "sg:postcode":"46140",
    "sg:province":"IN",
    "sg:tags":[
        "fraternal"
    ],
    "wof:name":"Masonic Lodge",
    "wof:placetype":"venue"
},
  "geometry": {"coordinates":[-85.783123,39.779407],"type":"Point"}
}