{
  "type": "Feature",
  "properties": {
    "iso:country":"US",
    "sg:address":"304 S Poplar St",
    "sg:city":"Westport",
    "sg:classifiers":[
        {
            "category":"Building & Trades",
            "subcategory":"Electrical",
            "type":"Services"
        }
    ],
    "sg:phone":"+1 812 591 2467",
    "sg:postcode":"47283",
    "sg:province":"IN",
    "sg:tags":[
        "electrical",
        "electric",
        "contractor"
    ],
    "wof:name":"Hempstead Electric & Mech",
    "wof:placetype":"venue"
},
  "geometry": {"coordinates":[-85.572696,39.172786],"type":"Point"}
}