{
  "type": "Feature",
  "properties": {
    "iso:country":"US",
    "sg:address":"6003 Mendenhall Rd",
    "sg:city":"Indianapolis",
    "sg:classifiers":[
        {
            "category":"Wholesale",
            "subcategory":"Hardware",
            "type":"Manufacturing & Wholesale Goods"
        }
    ],
    "sg:phone":"+1 317 856 8095",
    "sg:postcode":"46221",
    "sg:province":"IN",
    "sg:tags":[
        "hardware-wholesale",
        "manufacturer"
    ],
    "wof:name":"Circle C Tack Shack",
    "wof:placetype":"venue"
},
  "geometry": {"coordinates":[-86.288383,39.676591],"type":"Point"}
}