{
  "type": "Feature",
  "properties": {
    "addr:full":"9704 Beaumont Rd Indianapolis IN 46216",
    "addr:housenumber":"9704",
    "addr:postcode":"46216",
    "addr:street":"Beaumont Rd",
    "iso:country":"US",
    "sg:address":"9704 Beaumont Rd",
    "sg:city":"Indianapolis",
    "sg:classifiers":[
        {
            "category":"Government",
            "subcategory":"Office",
            "type":"Public Place"
        }
    ],
    "sg:phone":"+1 317 532 4001",
    "sg:postcode":"46216",
    "sg:province":"IN",
    "sg:tags":[
        "federal",
        "security"
    ],
    "wof:name":"US Army Reserve",
    "wof:placetype":"venue"
},
  "geometry": {"coordinates":[-85.990731,39.860574],"type":"Point"}
}