{
  "type": "Feature",
  "properties": {
    "addr:full":"581 E Main St Hagerstown IN 47346",
    "addr:housenumber":"581",
    "addr:postcode":"47346",
    "addr:street":"E Main St",
    "iso:country":"US",
    "sg:address":"581 E Main St",
    "sg:city":"Hagerstown",
    "sg:classifiers":[
        {
            "category":"Restaurant",
            "type":"Food & Drink"
        }
    ],
    "sg:phone":"+1 765 489 5699",
    "sg:postcode":"47346",
    "sg:province":"IN",
    "wof:name":"Dave's Cafe",
    "wof:placetype":"venue"
},
  "geometry": {"coordinates":[-85.15233499999999,39.910476],"type":"Point"}
}