{
  "type": "Feature",
  "properties": {
    "iso:country":"US",
    "sg:address":"1407 Forest Ave",
    "sg:city":"Fort Wayne",
    "sg:classifiers":[
        {
            "category":"Personal",
            "subcategory":"Beauty Salon",
            "type":"Services"
        }
    ],
    "sg:phone":"+1 260 484 7550",
    "sg:postcode":"46805",
    "sg:province":"IN",
    "sg:tags":[
        "cosmetologist"
    ],
    "wof:name":"Peggy Larrance",
    "wof:placetype":"venue"
},
  "geometry": {"coordinates":[-85.11956600000001,41.094988],"type":"Point"}
}