{
  "type": "Feature",
  "properties": {
    "iso:country":"US",
    "sg:address":"701 N McKinley Ave",
    "sg:city":"Rensselaer",
    "sg:classifiers":[
        {
            "category":"Autos & Motor Vehicles",
            "subcategory":"Fuel & Gas Station",
            "type":"Retail Goods"
        }
    ],
    "sg:phone":"+1 219 866 8470",
    "sg:postcode":"47978",
    "sg:province":"IN",
    "sg:tags":[
        "oil"
    ],
    "wof:name":"KERR-Mc Gee",
    "wof:placetype":"venue"
},
  "geometry": {"coordinates":[-87.150927,40.94454],"type":"Point"}
}