{
  "type": "Feature",
  "properties": {
    "iso:country":"US",
    "sg:address":"152 W 1300 S",
    "sg:city":"Silver Lake",
    "sg:classifiers":[
        {
            "category":"Farming",
            "subcategory":"Farm",
            "type":"Manufacturing & Wholesale Goods"
        }
    ],
    "sg:phone":"+1 260 352 2807",
    "sg:postcode":"46982",
    "sg:province":"IN",
    "wof:name":"Pyle Farms Inc",
    "wof:placetype":"venue"
},
  "geometry": {"coordinates":[-85.836048,41.043546],"type":"Point"}
}