{
  "type": "Feature",
  "properties": {
    "addr:full":"701 E Main St Gas City IN 46933",
    "addr:housenumber":"701",
    "addr:postcode":"46933",
    "addr:street":"E Main",
    "iso:country":"US",
    "sg:address":"701 E Main St",
    "sg:city":"Gas City",
    "sg:classifiers":[
        {
            "category":"Retail",
            "subcategory":"Auto Repair",
            "type":"Services"
        }
    ],
    "sg:phone":"+1 765 674 9419",
    "sg:postcode":"46933",
    "sg:province":"IN",
    "sg:tags":[
        "repairing",
        "automobile"
    ],
    "wof:name":"Clevenger Car Clinic",
    "wof:placetype":"venue"
},
  "geometry": {"coordinates":[-85.60005700000001,40.487894],"type":"Point"}
}