{
  "type": "Feature",
  "properties": {
    "iso:country":"US",
    "sg:address":"9038 E 200 S",
    "sg:city":"Avilla",
    "sg:classifiers":[
        {
            "category":"Recreation",
            "type":"Entertainment"
        }
    ],
    "sg:phone":"+1 260 897 2033",
    "sg:postcode":"46710",
    "sg:province":"IN",
    "sg:tags":[
        "appaloosa",
        "association"
    ],
    "wof:name":"Indiana Appaloosa Association",
    "wof:placetype":"venue"
},
  "geometry": {"coordinates":[-85.235135,41.321555],"type":"Point"}
}