{
  "type": "Feature",
  "properties": {
    "iso:country":"US",
    "sg:address":"132 N Vine St",
    "sg:city":"Batesville",
    "sg:classifiers":[
        {
            "category":"Arts & Performance",
            "subcategory":"Theater",
            "type":"Entertainment"
        }
    ],
    "sg:phone":"+1 812 934 2134",
    "sg:postcode":"47006",
    "sg:province":"IN",
    "sg:tags":[
        "music"
    ],
    "wof:name":"Empire Entertainment",
    "wof:placetype":"venue"
},
  "geometry": {"coordinates":[-85.223775,39.301106],"type":"Point"}
}