{
  "type": "Feature",
  "properties": {
    "addr:full":"4582 S Cross St St Anthony IN 47575",
    "addr:housenumber":"4582",
    "addr:postcode":"47575",
    "addr:street":"S Cross St",
    "iso:country":"US",
    "sg:address":"4582 S Cross St",
    "sg:city":"St Anthony",
    "sg:classifiers":[
        {
            "category":"Manufacturing",
            "subcategory":"Furniture",
            "type":"Manufacturing & Wholesale Goods"
        }
    ],
    "sg:phone":"+1 812 326 2361",
    "sg:postcode":"47575",
    "sg:province":"IN",
    "wof:name":"Othmar KLEM Furniture Co",
    "wof:placetype":"venue"
},
  "geometry": {"coordinates":[-86.827276,38.313094],"type":"Point"}
}