{
  "type": "Feature",
  "properties": {
    "iso:country":"US",
    "sg:address":"320 E 3rd St",
    "sg:city":"Bloomington",
    "sg:classifiers":[
        {
            "category":"Real Estate",
            "subcategory":"Real Estate Services",
            "type":"Services"
        }
    ],
    "sg:phone":"+1 812 330 8655",
    "sg:postcode":"47401",
    "sg:province":"IN",
    "sg:tags":[
        "management",
        "property"
    ],
    "wof:name":"Jamal Property Management",
    "wof:placetype":"venue"
},
  "geometry": {"coordinates":[-86.530817,39.164443],"type":"Point"}
}