{
  "type": "Feature",
  "properties": {
    "addr:full":"201 N Illinois St Ste 700 Indianapolis IN 46204",
    "addr:housenumber":"201",
    "addr:postcode":"46204",
    "addr:street":"N Illinois St Ste 700",
    "iso:country":"US",
    "sg:address":"201 N Illinois St Ste 700",
    "sg:city":"Indianapolis",
    "sg:classifiers":[
        {
            "category":"Professional",
            "subcategory":"Accounting & Tax Preparation",
            "type":"Services"
        }
    ],
    "sg:phone":"+1 317 383 4069",
    "sg:postcode":"46204",
    "sg:province":"IN",
    "sg:tags":[
        "public",
        "accountants-certified"
    ],
    "wof:name":"Kevin E Pahud Cpa",
    "wof:placetype":"venue"
},
  "geometry": {"coordinates":[-86.15979799999999,39.769951],"type":"Point"}
}