{
  "type": "Feature",
  "properties": {
    "iso:country":"US",
    "sg:address":"629 Elm Dr",
    "sg:city":"Plainfield",
    "sg:classifiers":[
        {
            "category":"Professional",
            "subcategory":"Management & Consulting",
            "type":"Services"
        }
    ],
    "sg:phone":"+1 317 839 3628",
    "sg:postcode":"46168",
    "sg:province":"IN",
    "sg:tags":[
        "business"
    ],
    "wof:name":"Jay Farms LLC",
    "wof:placetype":"venue"
},
  "geometry": {"coordinates":[-86.37527799999999,39.699574],"type":"Point"}
}