{
  "type": "Feature",
  "properties": {
    "iso:country":"US",
    "sg:address":"8237 Kentallen Ct",
    "sg:city":"Indianapolis",
    "sg:classifiers":[
        {
            "category":"Professional",
            "subcategory":"Research",
            "type":"Services"
        }
    ],
    "sg:phone":"+1 317 826 2557",
    "sg:postcode":"46236",
    "sg:province":"IN",
    "wof:name":"Radiant Research",
    "wof:placetype":"venue"
},
  "geometry": {"coordinates":[-85.95604299999999,39.906271],"type":"Point"}
}