{
  "type": "Feature",
  "properties": {
    "iso:country":"US",
    "sg:address":"704 S Main St",
    "sg:city":"Edinburgh",
    "sg:classifiers":[
        {
            "category":"Personal",
            "type":"Services"
        }
    ],
    "sg:phone":"+1 812 526 8739",
    "sg:postcode":"46124",
    "sg:province":"IN",
    "wof:name":"Corebuyer",
    "wof:placetype":"venue"
},
  "geometry": {"coordinates":[-85.967645,39.347997],"type":"Point"}
}