{
  "type": "Feature",
  "properties": {
    "iso:country":"US",
    "sg:address":"336 East St",
    "sg:city":"Seymour",
    "sg:classifiers":[
        {
            "category":"Retail",
            "subcategory":"Auto Repair",
            "type":"Services"
        }
    ],
    "sg:phone":"+1 812 522 7752",
    "sg:postcode":"47274",
    "sg:province":"IN",
    "sg:tags":[
        "repairing",
        "automobile"
    ],
    "wof:name":"Auto Repair Inc",
    "wof:placetype":"venue"
},
  "geometry": {"coordinates":[-85.885998,38.955065],"type":"Point"}
}