{
  "type": "Feature",
  "properties": {
    "iso:country":"US",
    "sg:address":"300 S Main St",
    "sg:city":"North Liberty",
    "sg:classifiers":[
        {
            "category":"Personal",
            "type":"Services"
        },
        {
            "category":"Organizations",
            "subcategory":"Professional Association",
            "type":"Services"
        }
    ],
    "sg:phone":"+1 574 656 4134",
    "sg:postcode":"46554",
    "sg:province":"IN",
    "wof:name":"North Liberty Community Center",
    "wof:placetype":"venue"
},
  "geometry": {"coordinates":[-86.426919,41.532039],"type":"Point"}
}