{
  "type": "Feature",
  "properties": {
    "iso:country":"US",
    "sg:address":"1099 N Meridian St",
    "sg:city":"Indianapolis",
    "sg:classifiers":[
        {
            "category":"Professional",
            "subcategory":"Employment Agencies",
            "type":"Services"
        }
    ],
    "sg:phone":"+1 317 237 7990",
    "sg:postcode":"46202",
    "sg:province":"IN",
    "sg:tags":[
        "opportunity"
    ],
    "wof:name":"Adecco",
    "wof:placetype":"venue"
},
  "geometry": {"coordinates":[-86.157501,39.782286],"type":"Point"}
}