{
  "type": "Feature",
  "properties": {
    "iso:country":"US",
    "sg:address":"12195 N Bray Rd",
    "sg:city":"Mooresville",
    "sg:classifiers":[
        {
            "category":"Building & Trades",
            "subcategory":"Electrical",
            "type":"Services"
        }
    ],
    "sg:phone":"+1 317 831 8694",
    "sg:postcode":"46158",
    "sg:province":"IN",
    "sg:tags":[
        "electric",
        "contractor"
    ],
    "wof:name":"Kenworthy Maintenance",
    "wof:placetype":"venue"
},
  "geometry": {"coordinates":[-86.431911,39.601119],"type":"Point"}
}