{
  "type": "Feature",
  "properties": {
    "iso:country":"US",
    "sg:address":"1330 Coliseum Blvd N",
    "sg:city":"Fort Wayne",
    "sg:classifiers":[
        {
            "category":"Shopping",
            "type":"Retail Goods"
        },
        {
            "category":"Professional",
            "subcategory":"Management & Consulting",
            "type":"Services"
        }
    ],
    "sg:phone":"+1 260 424 1400",
    "sg:postcode":"46805",
    "sg:province":"IN",
    "sg:tags":[
        "cellular",
        "business",
        "telephone"
    ],
    "wof:name":"Digital Solutions Store Inc",
    "wof:placetype":"venue"
},
  "geometry": {"coordinates":[-85.08767400000001,41.078943],"type":"Point"}
}