{
  "type": "Feature",
  "properties": {
    "iso:country":"US",
    "sg:address":"4506 S 500 E",
    "sg:city":"Lafayette",
    "sg:classifiers":[
        {
            "category":"Farming",
            "subcategory":"Farm",
            "type":"Manufacturing & Wholesale Goods"
        }
    ],
    "sg:phone":"+1 765 474 2074",
    "sg:postcode":"47909",
    "sg:province":"IN",
    "sg:tags":[
        "beef",
        "corn",
        "crop",
        "general",
        "ho",
        "soybean",
        "cattle"
    ],
    "wof:name":"Peabody Farms Inc",
    "wof:placetype":"venue"
},
  "geometry": {"coordinates":[-86.80934999999999,40.343744],"type":"Point"}
}