{
  "type": "Feature",
  "properties": {
    "addr:full":"57858 Charlotte Ave Elkhart IN 46517",
    "addr:housenumber":"57858",
    "addr:postcode":"46517",
    "addr:street":"Charlotte Ave",
    "iso:country":"US",
    "sg:address":"57858 Charlotte Ave",
    "sg:city":"Elkhart",
    "sg:classifiers":[
        {
            "category":"Wholesale",
            "subcategory":"Scrap",
            "type":"Manufacturing & Wholesale Goods"
        }
    ],
    "sg:phone":"+1 574 296 7909",
    "sg:postcode":"46517",
    "sg:province":"IN",
    "sg:tags":[
        "recycling",
        "center"
    ],
    "wof:name":"Elk Distributing Inc",
    "wof:placetype":"venue"
},
  "geometry": {"coordinates":[-86.01020800000001,41.653622],"type":"Point"}
}