{
  "type": "Feature",
  "properties": {
    "iso:country":"US",
    "sg:address":"1401 N Bosart Ave",
    "sg:city":"Indianapolis",
    "sg:classifiers":[
        {
            "category":"Education",
            "subcategory":"School",
            "type":"Public Place"
        }
    ],
    "sg:phone":"+1 317 353 2282",
    "sg:postcode":"46201",
    "sg:province":"IN",
    "sg:website":"www.littleflowerparish.org",
    "wof:name":"Little Flower Catholic School",
    "wof:placetype":"venue"
},
  "geometry": {"coordinates":[-86.090577,39.786505],"type":"Point"}
}