{
  "type": "Feature",
  "properties": {
    "iso:country":"US",
    "sg:address":"4293 Broadway",
    "sg:city":"Gary",
    "sg:classifiers":[
        {
            "category":"Autos & Motor Vehicles",
            "subcategory":"Automobile Sales",
            "type":"Retail Goods"
        }
    ],
    "sg:phone":"+1 219 980 0098",
    "sg:postcode":"46409",
    "sg:province":"IN",
    "sg:tags":[
        "car",
        "dealer"
    ],
    "wof:name":"4 S Auto Sales Inc",
    "wof:placetype":"venue"
},
  "geometry": {"coordinates":[-87.336293,41.542086],"type":"Point"}
}