{
  "type": "Feature",
  "properties": {
    "iso:country":"US",
    "sg:address":"11480 Jamestown W Dr",
    "sg:city":"Fishers",
    "sg:classifiers":[
        {
            "category":"Professional",
            "subcategory":"Engineering",
            "type":"Services"
        }
    ],
    "sg:phone":"+1 317 915 9243",
    "sg:postcode":"46038",
    "sg:province":"IN",
    "wof:name":"Cetcon Inc",
    "wof:placetype":"venue"
},
  "geometry": {"coordinates":[-86.028391,39.954074],"type":"Point"}
}