{
  "type": "Feature",
  "properties": {
    "iso:country":"US",
    "sg:address":"705 Evergreen St",
    "sg:city":"West Lafayette",
    "sg:classifiers":[
        {
            "category":"Shopping",
            "subcategory":"Florist",
            "type":"Retail Goods"
        }
    ],
    "sg:phone":"+1 765 743 2000",
    "sg:postcode":"47906",
    "sg:province":"IN",
    "sg:website":"www.wrightflowers.com",
    "wof:name":"Wright Flowers",
    "wof:placetype":"venue"
},
  "geometry": {"coordinates":[-86.914939,40.432274],"type":"Point"}
}