{
  "type": "Feature",
  "properties": {
    "iso:country":"US",
    "sg:address":"107 W Waterford St",
    "sg:city":"Wakarusa",
    "sg:classifiers":[
        {
            "category":"Shopping",
            "subcategory":"Jewelry",
            "type":"Retail Goods"
        }
    ],
    "sg:phone":"+1 574 862 1660",
    "sg:postcode":"46573",
    "sg:province":"IN",
    "sg:tags":[
        "jeweler"
    ],
    "wof:name":"Dru's Jewelers",
    "wof:placetype":"venue"
},
  "geometry": {"coordinates":[-86.021033,41.535959],"type":"Point"}
}