{
  "type": "Feature",
  "properties": {
    "iso:country":"US",
    "sg:address":"2238 Broadway",
    "sg:city":"Gary",
    "sg:classifiers":[
        {
            "category":"Personal",
            "subcategory":"Beauty Salon",
            "type":"Services"
        }
    ],
    "sg:phone":"+1 219 886 2770",
    "sg:postcode":"46407",
    "sg:province":"IN",
    "wof:name":"Antis Hair Braiding",
    "wof:placetype":"venue"
},
  "geometry": {"coordinates":[-87.336959,41.577468],"type":"Point"}
}