{
  "type": "Feature",
  "properties": {
    "iso:country":"US",
    "sg:address":"1105 N Main St",
    "sg:city":"Kewanna",
    "sg:classifiers":[
        {
            "category":"Travel",
            "subcategory":"Campground",
            "type":"Entertainment"
        }
    ],
    "sg:phone":"+1 574 653 2017",
    "sg:postcode":"46939",
    "sg:province":"IN",
    "wof:name":"Hoosier Hideaway",
    "wof:placetype":"venue"
},
  "geometry": {"coordinates":[-86.464214,41.07214],"type":"Point"}
}