{
  "type": "Feature",
  "properties": {
    "iso:country":"US",
    "sg:address":"7201 E Washington St",
    "sg:city":"Indianapolis",
    "sg:classifiers":[
        {
            "category":"Retail",
            "subcategory":"Auto Repair",
            "type":"Services"
        }
    ],
    "sg:phone":"+1 317 352 9903",
    "sg:postcode":"46219",
    "sg:province":"IN",
    "sg:tags":[
        "body",
        "automobile",
        "painting"
    ],
    "wof:name":"New Earl Scheib Paint & Body",
    "wof:placetype":"venue"
},
  "geometry": {"coordinates":[-86.03839,39.772445],"type":"Point"}
}