{
  "type": "Feature",
  "properties": {
    "iso:country":"US",
    "sg:address":"5220 N Union Valley Rd",
    "sg:city":"Bloomington",
    "sg:classifiers":[
        {
            "category":"Utilities",
            "subcategory":"Refuse",
            "type":"Services"
        }
    ],
    "sg:phone":"+1 812 935 7169",
    "sg:postcode":"47404",
    "sg:province":"IN",
    "sg:tags":[
        "garbage",
        "collection"
    ],
    "wof:name":"Ron's Trash Hauling",
    "wof:placetype":"venue"
},
  "geometry": {"coordinates":[-86.592635,39.224136],"type":"Point"}
}