{
  "type": "Feature",
  "properties": {
    "iso:country":"US",
    "sg:address":"5701 Industrial Hwy",
    "sg:city":"Gary",
    "sg:classifiers":[
        {
            "category":"Education",
            "subcategory":"Special Training",
            "type":"Public Place"
        }
    ],
    "sg:phone":"+1 219 944 5678",
    "sg:postcode":"46406",
    "sg:province":"IN",
    "sg:tags":[
        "aircraft",
        "school"
    ],
    "wof:name":"Aviation Professionals",
    "wof:placetype":"venue"
},
  "geometry": {"coordinates":[-87.406519,41.617527],"type":"Point"}
}