{
  "type": "Feature",
  "properties": {
    "addr:full":"1350 119th St Whiting IN 46394",
    "addr:housenumber":"1350",
    "addr:postcode":"46394",
    "addr:street":"119Th St",
    "iso:country":"US",
    "sg:address":"1350 119th St",
    "sg:city":"Whiting",
    "sg:classifiers":[
        {
            "category":"Restaurant",
            "type":"Food & Drink"
        }
    ],
    "sg:phone":"+1 219 659 1466",
    "sg:postcode":"46394",
    "sg:province":"IN",
    "sg:tags":[
        "caribbean"
    ],
    "sg:website":"www.wineybeachcafe.com",
    "wof:name":"Winey Beach Cafe",
    "wof:placetype":"venue"
},
  "geometry": {"coordinates":[-87.49600700000001,41.679309],"type":"Point"}
}