{
  "type": "Feature",
  "properties": {
    "iso:country":"US",
    "sg:address":"4609 Grape Rd",
    "sg:city":"Mishawaka",
    "sg:classifiers":[
        {
            "category":"Food & Beverages",
            "subcategory":"Specialty",
            "type":"Retail Goods"
        }
    ],
    "sg:phone":"+1 574 277 6887",
    "sg:postcode":"46545",
    "sg:province":"IN",
    "sg:tags":[
        "tea",
        "coffee"
    ],
    "sg:website":"www.bestcoffeebymail.com",
    "wof:name":"Spice Of Life LTD",
    "wof:placetype":"venue"
},
  "geometry": {"coordinates":[-86.18758200000001,41.70455],"type":"Point"}
}