{
  "type": "Feature",
  "properties": {
    "addr:full":"3910 W Jefferson Blvd Fort Wayne IN 46804",
    "addr:housenumber":"3910",
    "addr:postcode":"46804",
    "addr:street":"W Jefferson Blvd",
    "iso:country":"US",
    "sg:address":"3910 W Jefferson Blvd",
    "sg:city":"Fort Wayne",
    "sg:classifiers":[
        {
            "category":"Home & Garden",
            "subcategory":"Household Appliances",
            "type":"Retail Goods"
        }
    ],
    "sg:phone":"+1 260 435 1822",
    "sg:postcode":"46804",
    "sg:province":"IN",
    "wof:name":"Clark's Appliance",
    "wof:placetype":"venue"
},
  "geometry": {"coordinates":[-85.197344,41.068742],"type":"Point"}
}