{
  "type": "Feature",
  "properties": {
    "iso:country":"US",
    "sg:address":"815 Uhlhorn St",
    "sg:city":"Evansville",
    "sg:classifiers":[
        {
            "category":"Government",
            "subcategory":"Office",
            "type":"Public Place"
        }
    ],
    "sg:phone":"+1 812 435 6015",
    "sg:postcode":"47710",
    "sg:province":"IN",
    "sg:tags":[
        "village"
    ],
    "wof:name":"Animal Control Shelter",
    "wof:placetype":"venue"
},
  "geometry": {"coordinates":[-87.576987,37.995139],"type":"Point"}
}