{
  "type": "Feature",
  "properties": {
    "iso:country":"US",
    "sg:address":"1260 Hamilton Ave",
    "sg:city":"Franklin",
    "sg:classifiers":[
        {
            "category":"Organizations",
            "subcategory":"Religious Organization",
            "type":"Services"
        }
    ],
    "sg:phone":"+1 317 736 4884",
    "sg:postcode":"46131",
    "sg:province":"IN",
    "sg:tags":[
        "church"
    ],
    "wof:name":"Faith Deliverance Church",
    "wof:placetype":"venue"
},
  "geometry": {"coordinates":[-86.04212,39.4896],"type":"Point"}
}