{
  "type": "Feature",
  "properties": {
    "iso:country":"US",
    "sg:address":"202 W Monroe St",
    "sg:city":"Mentone",
    "sg:classifiers":[
        {
            "category":"Wholesale",
            "subcategory":"Farm Supplies",
            "type":"Manufacturing & Wholesale Goods"
        }
    ],
    "sg:phone":"+1 574 353 7791",
    "sg:postcode":"46539",
    "sg:province":"IN",
    "sg:tags":[
        "feed"
    ],
    "wof:name":"Mentone Agri-Center",
    "wof:placetype":"venue"
},
  "geometry": {"coordinates":[-86.041652,41.172404],"type":"Point"}
}