{
  "type": "Feature",
  "properties": {
    "iso:country":"US",
    "sg:address":"3173 Ellen Dr",
    "sg:city":"Indianapolis",
    "sg:classifiers":[
        {
            "category":"Wholesale",
            "subcategory":"Vending Machines",
            "type":"Manufacturing & Wholesale Goods"
        }
    ],
    "sg:phone":"+1 317 347 9897",
    "sg:postcode":"46224",
    "sg:province":"IN",
    "sg:tags":[
        "operator"
    ],
    "wof:name":"Candy Sense",
    "wof:placetype":"venue"
},
  "geometry": {"coordinates":[-86.252677,39.811592],"type":"Point"}
}