{
  "type": "Feature",
  "properties": {
    "iso:country":"US",
    "sg:address":"798 N 16th St",
    "sg:city":"New Castle",
    "sg:classifiers":[
        {
            "category":"Health Services",
            "subcategory":"Nursing And Care Facility",
            "type":"Services"
        }
    ],
    "sg:phone":"+1 765 593 2389",
    "sg:postcode":"47362",
    "sg:province":"IN",
    "sg:tags":[
        "hospice"
    ],
    "sg:website":"www.hcmhcares.org",
    "wof:name":"Hcmh Hospice",
    "wof:placetype":"venue"
},
  "geometry": {"coordinates":[-85.365071,39.9396],"type":"Point"}
}