{
  "type": "Feature",
  "properties": {
    "addr:full":"4120 W Jefferson Blvd Fort Wayne IN 46804",
    "addr:housenumber":"4120",
    "addr:postcode":"46804",
    "addr:street":"W Jefferson Blvd",
    "iso:country":"US",
    "sg:address":"4120 W Jefferson Blvd",
    "sg:city":"Fort Wayne",
    "sg:classifiers":[
        {
            "category":"Shopping",
            "subcategory":"Clothing, Apparel, & Fashions",
            "type":"Retail Goods"
        }
    ],
    "sg:phone":"+1 260 436 3092",
    "sg:postcode":"46804",
    "sg:province":"IN",
    "sg:tags":[
        "sportswear"
    ],
    "sg:website":"www.ae.com",
    "wof:name":"American Eagle Outfitters",
    "wof:placetype":"venue"
},
  "geometry": {"coordinates":[-85.193585,41.071129],"type":"Point"}
}