{
  "type": "Feature",
  "properties": {
    "iso:country":"US",
    "sg:address":"4236 Chatfield Ct",
    "sg:city":"Fort Wayne",
    "sg:classifiers":[
        {
            "category":"Shopping",
            "subcategory":"Stationery & Office Supplies",
            "type":"Retail Goods"
        }
    ],
    "sg:phone":"+1 260 447 7100",
    "sg:postcode":"46816",
    "sg:province":"IN",
    "wof:name":"Indoff Inc",
    "wof:placetype":"venue"
},
  "geometry": {"coordinates":[-85.08417,41.027277],"type":"Point"}
}