{
  "type": "Feature",
  "properties": {
    "iso:country":"US",
    "sg:address":"2942 W 450 N",
    "sg:city":"Rochester",
    "sg:classifiers":[
        {
            "category":"Building & Trades",
            "subcategory":"Construction",
            "type":"Services"
        }
    ],
    "sg:phone":"+1 574 223 9693",
    "sg:postcode":"46975",
    "sg:province":"IN",
    "sg:tags":[
        "contractor"
    ],
    "wof:name":"Robowski Construction",
    "wof:placetype":"venue"
},
  "geometry": {"coordinates":[-86.297777,41.120423],"type":"Point"}
}