{
  "type": "Feature",
  "properties": {
    "iso:country":"US",
    "sg:address":"701 E Taylor St",
    "sg:city":"Kokomo",
    "sg:classifiers":[
        {
            "category":"Organizations",
            "subcategory":"Religious Organization",
            "type":"Services"
        }
    ],
    "sg:phone":"+1 765 452 7448",
    "sg:postcode":"46901",
    "sg:province":"IN",
    "sg:tags":[
        "church"
    ],
    "wof:name":"River Of Life Minstries",
    "wof:placetype":"venue"
},
  "geometry": {"coordinates":[-86.123166,40.489405],"type":"Point"}
}