{
  "type": "Feature",
  "properties": {
    "iso:country":"US",
    "sg:address":"2126 Shelby St",
    "sg:city":"Indianapolis",
    "sg:classifiers":[
        {
            "category":"Restaurant",
            "type":"Food & Drink"
        }
    ],
    "sg:phone":"+1 317 783 4136",
    "sg:postcode":"46203",
    "sg:province":"IN",
    "wof:name":"Greiner's Submarine Shop",
    "wof:placetype":"venue"
},
  "geometry": {"coordinates":[-86.139833,39.739413],"type":"Point"}
}