{
  "type": "Feature",
  "properties": {
    "iso:country":"US",
    "sg:address":"4633 Hillside Ave",
    "sg:city":"Indianapolis",
    "sg:classifiers":[
        {
            "category":"Building & Trades",
            "subcategory":"Construction",
            "type":"Services"
        }
    ],
    "sg:phone":"+1 317 251 1476",
    "sg:postcode":"46205",
    "sg:province":"IN",
    "sg:tags":[
        "general",
        "contractor"
    ],
    "wof:name":"General Contracting",
    "wof:placetype":"venue"
},
  "geometry": {"coordinates":[-86.124174,39.841139],"type":"Point"}
}