{
  "type": "Feature",
  "properties": {
    "iso:country":"US",
    "sg:address":"114 E Walnut St",
    "sg:city":"Kokomo",
    "sg:classifiers":[
        {
            "category":"Banks & Credit Unions",
            "subcategory":"Bank",
            "type":"Services"
        }
    ],
    "sg:phone":"+1 765 868 3800",
    "sg:postcode":"46901",
    "sg:province":"IN",
    "wof:name":"Star Financial Bank",
    "wof:placetype":"venue"
},
  "geometry": {"coordinates":[-86.130131,40.487494],"type":"Point"}
}