{
  "type": "Feature",
  "properties": {
    "addr:full":"7621 Crawfordsville Rd Indianapolis IN 46214",
    "addr:housenumber":"7621",
    "addr:postcode":"46214",
    "addr:street":"Crawfordsville Rd",
    "iso:country":"US",
    "sg:address":"7621 Crawfordsville Rd",
    "sg:city":"Indianapolis",
    "sg:classifiers":[
        {
            "category":"Building & Trades",
            "subcategory":"Plumbing",
            "type":"Services"
        }
    ],
    "sg:phone":"+1 317 299 9200",
    "sg:postcode":"46214",
    "sg:province":"IN",
    "sg:tags":[
        "plumbing",
        "contractor"
    ],
    "wof:name":"Jaynes Plumbing Co Inc",
    "wof:placetype":"venue"
},
  "geometry": {"coordinates":[-86.294983,39.805997],"type":"Point"}
}