{
  "type": "Feature",
  "properties": {
    "iso:country":"US",
    "sg:address":"7659 S Co Rd 325 E",
    "sg:city":"Lewisville",
    "sg:classifiers":[
        {
            "category":"Freight",
            "type":"Transportation"
        }
    ],
    "sg:phone":"+1 765 332 2660",
    "sg:postcode":"47352",
    "sg:province":"IN",
    "sg:tags":[
        "grain",
        "elevator"
    ],
    "wof:name":"Pic-Nic Grain Inc",
    "wof:placetype":"venue"
},
  "geometry": {"coordinates":[-85.324553,39.821614],"type":"Point"}
}