{
  "type": "Feature",
  "properties": {
    "iso:country":"US",
    "sg:address":"27632 Co Rd 20",
    "sg:city":"Elkhart",
    "sg:classifiers":[
        {
            "category":"Government",
            "subcategory":"Office",
            "type":"Public Place"
        }
    ],
    "sg:phone":"+1 574 293 0147",
    "sg:postcode":"46517",
    "sg:province":"IN",
    "sg:tags":[
        "village"
    ],
    "wof:name":"Elkhart Central Garage",
    "wof:placetype":"venue"
},
  "geometry": {"coordinates":[-85.996601,41.655497],"type":"Point"}
}