{
  "type": "Feature",
  "properties": {
    "addr:full":"364 Atherton Dr Carmel IN 46032",
    "addr:housenumber":"364",
    "addr:postcode":"46032",
    "addr:street":"Atherton Dr",
    "iso:country":"US",
    "sg:address":"364 Atherton Dr",
    "sg:city":"Carmel",
    "sg:classifiers":[
        {
            "category":"Health Services",
            "subcategory":"Health Practitioner",
            "type":"Services"
        }
    ],
    "sg:phone":"+1 317 844 7394",
    "sg:postcode":"46032",
    "sg:province":"IN",
    "sg:tags":[
        "therapist",
        "physical"
    ],
    "wof:name":"Toddlers Choice",
    "wof:placetype":"venue"
},
  "geometry": {"coordinates":[-86.132857,39.972289],"type":"Point"}
}