{
  "type": "Feature",
  "properties": {
    "addr:full":"123 Sherman Dr Carmel IN 46032",
    "addr:housenumber":"123",
    "addr:postcode":"46032",
    "addr:street":"Sherman Dr",
    "iso:country":"US",
    "sg:address":"123 Sherman Dr",
    "sg:city":"Carmel",
    "sg:classifiers":[
        {
            "category":"Building & Trades",
            "subcategory":"Landscaping Services",
            "type":"Services"
        }
    ],
    "sg:phone":"+1 317 844 1409",
    "sg:postcode":"46032",
    "sg:province":"IN",
    "sg:tags":[
        "landscape"
    ],
    "wof:name":"Etherington Landscape Services",
    "wof:placetype":"venue"
},
  "geometry": {"coordinates":[-86.13732400000001,39.977878],"type":"Point"}
}