{
  "type": "Feature",
  "properties": {
    "iso:country":"US",
    "sg:address":"11293 N State Rd 15",
    "sg:city":"Milford",
    "sg:classifiers":[
        {
            "category":"Retail",
            "subcategory":"Auto Repair",
            "type":"Services"
        }
    ],
    "sg:phone":"+1 574 658 3003",
    "sg:postcode":"46542",
    "sg:province":"IN",
    "sg:tags":[
        "automobile",
        "restoration",
        "classic"
    ],
    "wof:name":"Appenzeller Brothers",
    "wof:placetype":"venue"
},
  "geometry": {"coordinates":[-85.855189,41.394831],"type":"Point"}
}