{
  "type": "Feature",
  "properties": {
    "iso:country":"US",
    "sg:address":"8354 E Co Rd 1200 N",
    "sg:city":"Sunman",
    "sg:classifiers":[
        {
            "category":"Farming",
            "subcategory":"Farm",
            "type":"Manufacturing & Wholesale Goods"
        }
    ],
    "sg:phone":"+1 812 623 3214",
    "sg:postcode":"47041",
    "sg:province":"IN",
    "sg:tags":[
        "crop",
        "general"
    ],
    "wof:name":"Virgil Moorman",
    "wof:placetype":"venue"
},
  "geometry": {"coordinates":[-85.10649600000001,39.251104],"type":"Point"}
}