{
  "type": "Feature",
  "properties": {
    "iso:country":"US",
    "sg:address":"201 Conrad Harcourt Way",
    "sg:city":"Rushville",
    "sg:classifiers":[
        {
            "category":"Social Services",
            "type":"Services"
        }
    ],
    "sg:phone":"+1 765 932 5316",
    "sg:postcode":"46173",
    "sg:province":"IN",
    "sg:tags":[
        "organization",
        "welfare"
    ],
    "wof:name":"Step Ahead-First Steps Of Rush",
    "wof:placetype":"venue"
},
  "geometry": {"coordinates":[-85.442544,39.623188],"type":"Point"}
}