{
  "type": "Feature",
  "properties": {
    "iso:country":"US",
    "sg:address":"100 Mill St",
    "sg:city":"Elizabethtown",
    "sg:classifiers":[
        {
            "category":"Freight",
            "type":"Transportation"
        }
    ],
    "sg:phone":"+1 812 579 5231",
    "sg:postcode":"47232",
    "sg:province":"IN",
    "sg:tags":[
        "grain",
        "elevator"
    ],
    "wof:name":"Elizabethtown Grain",
    "wof:placetype":"venue"
},
  "geometry": {"coordinates":[-85.813504,39.135925],"type":"Point"}
}