{
  "type": "Feature",
  "properties": {
    "iso:country":"US",
    "sg:address":"4802 Indianapolis Blvd",
    "sg:city":"East Chicago",
    "sg:classifiers":[
        {
            "category":"Professional",
            "subcategory":"Lawyer & Legal Services",
            "type":"Services"
        }
    ],
    "sg:phone":"+1 219 378 8000",
    "sg:postcode":"46312",
    "sg:province":"IN",
    "wof:name":"Law Offices of Milan Petrovic PC",
    "wof:placetype":"venue"
},
  "geometry": {"coordinates":[-87.480797,41.6273],"type":"Point"}
}