{
  "type": "Feature",
  "properties": {
    "iso:country":"US",
    "sg:address":"55950 Country Club Rd",
    "sg:city":"South Bend",
    "sg:classifiers":[
        {
            "category":"Recreation",
            "type":"Entertainment"
        },
        {
            "category":"Organizations",
            "subcategory":"Community Association",
            "type":"Services"
        }
    ],
    "sg:phone":"+1 574 287 8520",
    "sg:postcode":"46619",
    "sg:province":"IN",
    "sg:tags":[
        "club",
        "gun"
    ],
    "wof:name":"Chain Of Lakes Gun Club Inc",
    "wof:placetype":"venue"
},
  "geometry": {"coordinates":[-86.360822,41.68344],"type":"Point"}
}