{
  "type": "Feature",
  "properties": {
    "addr:full":"969 Dorman St Indianapolis IN 46202",
    "addr:housenumber":"969",
    "addr:postcode":"46202",
    "addr:street":"Dorman St",
    "iso:country":"US",
    "sg:address":"969 Dorman St",
    "sg:city":"Indianapolis",
    "sg:classifiers":[
        {
            "category":"Building & Trades",
            "subcategory":"Construction",
            "type":"Services"
        }
    ],
    "sg:phone":"+1 317 822 1790",
    "sg:postcode":"46202",
    "sg:province":"IN",
    "sg:tags":[
        "excavating",
        "contractor"
    ],
    "wof:name":"Kreager Brothers Excavating",
    "wof:placetype":"venue"
},
  "geometry": {"coordinates":[-86.139008,39.780419],"type":"Point"}
}