{
  "type": "Feature",
  "properties": {
    "iso:country":"US",
    "sg:address":"389 E Main St",
    "sg:city":"Greenwood",
    "sg:classifiers":[
        {
            "category":"Manufacturing",
            "subcategory":"Printing",
            "type":"Manufacturing & Wholesale Goods"
        }
    ],
    "sg:phone":"+1 317 882 6691",
    "sg:postcode":"46143",
    "sg:province":"IN",
    "sg:tags":[
        "screen"
    ],
    "wof:name":"Mere Image",
    "wof:placetype":"venue"
},
  "geometry": {"coordinates":[-86.100697,39.613769],"type":"Point"}
}