{
  "type": "Feature",
  "properties": {
    "iso:country":"US",
    "sg:address":"4802 Wegg Ave",
    "sg:city":"East Chicago",
    "sg:classifiers":[
        {
            "category":"Organizations",
            "subcategory":"Religious Organization",
            "type":"Services"
        }
    ],
    "sg:phone":"+1 219 397 4703",
    "sg:postcode":"46312",
    "sg:province":"IN",
    "wof:name":"Assembly of God First",
    "wof:placetype":"venue"
},
  "geometry": {"coordinates":[-87.487786,41.625002],"type":"Point"}
}