{
  "type": "Feature",
  "properties": {
    "iso:country":"US",
    "sg:address":"1126 Miller Ave",
    "sg:city":"Shelbyville",
    "sg:classifiers":[
        {
            "category":"Manufacturing",
            "subcategory":"Glass & Minerals",
            "type":"Manufacturing & Wholesale Goods"
        }
    ],
    "sg:phone":"+1 317 398 8616",
    "sg:postcode":"46176",
    "sg:province":"IN",
    "sg:tags":[
        "concrete",
        "brick",
        "prod",
        "block"
    ],
    "wof:name":"Mark Concrete Products Inc",
    "wof:placetype":"venue"
},
  "geometry": {"coordinates":[-85.790965,39.514622],"type":"Point"}
}