{
  "type": "Feature",
  "properties": {
    "iso:country":"US",
    "sg:address":"1600 S 2nd St",
    "sg:city":"Richmond",
    "sg:classifiers":[
        {
            "category":"Social Services",
            "type":"Services"
        }
    ],
    "sg:phone":"+1 765 983 7309",
    "sg:postcode":"47374",
    "sg:province":"IN",
    "sg:tags":[
        "executive"
    ],
    "wof:name":"Rsvp",
    "wof:placetype":"venue"
},
  "geometry": {"coordinates":[-84.900916,39.807978],"type":"Point"}
}