{
  "type": "Feature",
  "properties": {
    "addr:full":"1942 7th St Columbus IN 47201",
    "addr:housenumber":"1942",
    "addr:postcode":"47201",
    "addr:street":"7Th St",
    "iso:country":"US",
    "sg:address":"1942 7th St",
    "sg:city":"Columbus",
    "sg:classifiers":[
        {
            "category":"Autos & Motor Vehicles",
            "subcategory":"Automobile Sales",
            "type":"Retail Goods"
        }
    ],
    "sg:phone":"+1 812 376 3514",
    "sg:postcode":"47201",
    "sg:province":"IN",
    "sg:tags":[
        "car",
        "dealer"
    ],
    "wof:name":"Bill's Auto Sales",
    "wof:placetype":"venue"
},
  "geometry": {"coordinates":[-85.902447,39.206181],"type":"Point"}
}