{
  "type": "Feature",
  "properties": {
    "iso:country":"US",
    "sg:address":"3526 S Park Dr",
    "sg:city":"Fort Wayne",
    "sg:classifiers":[
        {
            "category":"Social Services",
            "subcategory":"Child Care",
            "type":"Services"
        }
    ],
    "sg:phone":"+1 260 744 6314",
    "sg:postcode":"46806",
    "sg:province":"IN",
    "sg:tags":[
        "day"
    ],
    "wof:name":"It's All About Love Child Care",
    "wof:placetype":"venue"
},
  "geometry": {"coordinates":[-85.125227,41.052276],"type":"Point"}
}