{
  "type": "Feature",
  "properties": {
    "addr:full":"607 Dubois St Vincennes IN 47591",
    "addr:housenumber":"607",
    "addr:postcode":"47591",
    "addr:street":"Dubois St",
    "iso:country":"US",
    "sg:address":"607 Dubois St",
    "sg:city":"Vincennes",
    "sg:classifiers":[
        {
            "category":"Professional",
            "type":"Services"
        }
    ],
    "sg:phone":"+1 812 886 4458",
    "sg:postcode":"47591",
    "sg:province":"IN",
    "sg:tags":[
        "establishment"
    ],
    "wof:name":"Midwest Ent",
    "wof:placetype":"venue"
},
  "geometry": {"coordinates":[-87.532718,38.674805],"type":"Point"}
}