{
  "type": "Feature",
  "properties": {
    "iso:country":"US",
    "sg:address":"200 W Lincoln Hwy",
    "sg:city":"Schererville",
    "sg:classifiers":[
        {
            "category":"Shopping",
            "subcategory":"Books",
            "type":"Retail Goods"
        }
    ],
    "sg:phone":"+1 219 322 2902",
    "sg:postcode":"46375",
    "sg:province":"IN",
    "sg:tags":[
        "comic"
    ],
    "wof:name":"Tenth Planet",
    "wof:placetype":"venue"
},
  "geometry": {"coordinates":[-87.43774500000001,41.482662],"type":"Point"}
}