{
  "type": "Feature",
  "properties": {
    "iso:country":"US",
    "sg:address":"9059 Pendleton Pike",
    "sg:city":"Indianapolis",
    "sg:classifiers":[
        {
            "category":"Autos & Motor Vehicles",
            "subcategory":"Automobile Sales",
            "type":"Retail Goods"
        }
    ],
    "sg:phone":"+1 317 899 0500",
    "sg:postcode":"46236",
    "sg:province":"IN",
    "sg:tags":[
        "used"
    ],
    "wof:name":"500 Auto Sales",
    "wof:placetype":"venue"
},
  "geometry": {"coordinates":[-86.010241,39.844463],"type":"Point"}
}