{
  "type": "Feature",
  "properties": {
    "addr:full":"16599 Maple City Dr Goshen IN 46526",
    "addr:housenumber":"16599",
    "addr:postcode":"46526",
    "addr:street":"Maple City Dr",
    "iso:country":"US",
    "sg:address":"16599 Maple City Dr",
    "sg:city":"Goshen",
    "sg:classifiers":[
        {
            "category":"Manufacturing",
            "subcategory":"Tools & Machinery",
            "type":"Manufacturing & Wholesale Goods"
        }
    ],
    "sg:phone":"+1 574 642 4227",
    "sg:postcode":"46526",
    "sg:province":"IN",
    "sg:tags":[
        "machine",
        "shop"
    ],
    "wof:name":"Buckles Tool & Engineering Co",
    "wof:placetype":"venue"
},
  "geometry": {"coordinates":[-85.782554,41.548373],"type":"Point"}
}