{
  "type": "Feature",
  "properties": {
    "iso:country":"US",
    "sg:address":"986 W Hospital Rd",
    "sg:city":"Paoli",
    "sg:classifiers":[
        {
            "category":"Social Services",
            "type":"Services"
        }
    ],
    "sg:phone":"+1 812 723 4486",
    "sg:postcode":"47454",
    "sg:province":"IN",
    "sg:tags":[
        "organization",
        "welfare"
    ],
    "sg:website":"www.firstchancecenter.com",
    "wof:name":"First Chance Ctr",
    "wof:placetype":"venue"
},
  "geometry": {"coordinates":[-86.479844,38.564301],"type":"Point"}
}