{
  "type": "Feature",
  "properties": {
    "iso:country":"US",
    "sg:address":"5862 Echo Way",
    "sg:city":"Indianapolis",
    "sg:classifiers":[
        {
            "category":"Social Services",
            "type":"Services"
        }
    ],
    "sg:phone":"+1 317 291 4326",
    "sg:postcode":"46278",
    "sg:province":"IN",
    "sg:tags":[
        "parenting",
        "class"
    ],
    "wof:name":"Foster Families Resource Ctr",
    "wof:placetype":"venue"
},
  "geometry": {"coordinates":[-86.263283,39.871545],"type":"Point"}
}