{
  "type": "Feature",
  "properties": {
    "iso:country":"US",
    "sg:address":"115 N Weinbach Ave",
    "sg:city":"Evansville",
    "sg:classifiers":[
        {
            "category":"Insurance",
            "subcategory":"Insurance Agent",
            "type":"Services"
        }
    ],
    "sg:phone":"+1 812 476 7999",
    "sg:postcode":"47711",
    "sg:province":"IN",
    "wof:name":"Gerling Assured Financial",
    "wof:placetype":"venue"
},
  "geometry": {"coordinates":[-87.529253,37.977277],"type":"Point"}
}