{
  "type": "Feature",
  "properties": {
    "addr:full":"3501 Pierce St Gary IN 46408",
    "addr:housenumber":"3501",
    "addr:postcode":"46408",
    "addr:street":"Pierce St Gary",
    "iso:country":"US",
    "sg:address":"3501 Pierce St",
    "sg:city":"Gary",
    "sg:classifiers":[
        {
            "category":"Building & Trades",
            "subcategory":"Construction",
            "type":"Services"
        }
    ],
    "sg:phone":"+1 219 884 3407",
    "sg:postcode":"46408",
    "sg:province":"IN",
    "sg:tags":[
        "roofing",
        "contractor"
    ],
    "wof:name":"J & J Roofing",
    "wof:placetype":"venue"
},
  "geometry": {"coordinates":[-87.35104699999999,41.553191],"type":"Point"}
}