{
  "type": "Feature",
  "properties": {
    "addr:full":"519 NW 5th St Richmond IN 47374",
    "addr:housenumber":"519",
    "addr:postcode":"47374",
    "addr:street":"Nw 5Th St",
    "iso:country":"US",
    "sg:address":"519 NW 5th St",
    "sg:city":"Richmond",
    "sg:classifiers":[
        {
            "category":"Shopping",
            "subcategory":"Discount & Variety Stores",
            "type":"Retail Goods"
        }
    ],
    "sg:phone":"+1 765 966 1257",
    "sg:postcode":"47374",
    "sg:province":"IN",
    "sg:tags":[
        "merchandise",
        "general"
    ],
    "wof:name":"Arandas Mexican Store",
    "wof:placetype":"venue"
},
  "geometry": {"coordinates":[-84.907883,39.835392],"type":"Point"}
}