{
  "type": "Feature",
  "properties": {
    "iso:country":"US",
    "sg:address":"884 W 900 S",
    "sg:city":"Union Mills",
    "sg:phone":"+1 219 393 3757",
    "sg:postcode":"46382",
    "sg:province":"IN",
    "sg:tags":[
        "farm",
        "corn",
        "soybean"
    ],
    "wof:name":"Wilma Marsh",
    "wof:placetype":"venue"
},
  "geometry": {"coordinates":[-86.7663,41.4765],"type":"Point"}
}