{
  "type": "Feature",
  "properties": {
    "addr:full":"247 S Gladstone Ave Columbus IN 47201",
    "addr:housenumber":"247",
    "addr:postcode":"47201",
    "addr:street":"S Gladstone Ave",
    "iso:country":"US",
    "sg:address":"247 S Gladstone Ave",
    "sg:city":"Columbus",
    "sg:classifiers":[
        {
            "category":"Wholesale",
            "subcategory":"Machinery & Supplies",
            "type":"Manufacturing & Wholesale Goods"
        }
    ],
    "sg:phone":"+1 812 379 2329",
    "sg:postcode":"47201",
    "sg:province":"IN",
    "sg:tags":[
        "bearing"
    ],
    "sg:website":"www.motionmro.com",
    "wof:name":"Motion Industries Inc",
    "wof:placetype":"venue"
},
  "geometry": {"coordinates":[-85.894487,39.195364],"type":"Point"}
}