{
  "type": "Feature",
  "properties": {
    "iso:country":"US",
    "sg:address":"5240 Commerce Cir",
    "sg:city":"Indianapolis",
    "sg:classifiers":[
        {
            "category":"Building & Trades",
            "subcategory":"Plumbing",
            "type":"Services"
        }
    ],
    "sg:phone":"+1 317 859 4270",
    "sg:postcode":"46237",
    "sg:province":"IN",
    "sg:tags":[
        "conditioning",
        "air",
        "system",
        "contractor"
    ],
    "wof:name":"Peterman Heating & Cooling",
    "wof:placetype":"venue"
},
  "geometry": {"coordinates":[-86.079886,39.655437],"type":"Point"}
}