{
  "type": "Feature",
  "properties": {
    "addr:full":"345 N Kitley Ave Indianapolis IN 46219",
    "addr:housenumber":"345",
    "addr:postcode":"46219",
    "addr:street":"N Kitley Ave",
    "iso:country":"US",
    "sg:address":"345 N Kitley Ave",
    "sg:city":"Indianapolis",
    "sg:classifiers":[
        {
            "category":"Place Of Worship",
            "subcategory":"Church",
            "type":"Public Place"
        },
        {
            "category":"Place Of Worship",
            "type":"Public Place"
        },
        {
            "category":"Organizations",
            "subcategory":"Religious Organization",
            "type":"Services"
        }
    ],
    "sg:phone":"+1 317 357 8596",
    "sg:postcode":"46219",
    "sg:province":"IN",
    "sg:tags":[
        "lutheran",
        "synod",
        "churches-lutheran-lutheran",
        "churches-lutheran-evangelical",
        "missouri",
        "america",
        "churches-lutheran",
        "lcms"
    ],
    "wof:name":"Christ Lutheran Church Of Irvinton Inc",
    "wof:placetype":"venue"
},
  "geometry": {"coordinates":[-86.05471,39.774539],"type":"Point"}
}