{
  "type": "Feature",
  "properties": {
    "iso:country":"US",
    "sg:address":"239 Walnut St",
    "sg:city":"Lawrenceburg",
    "sg:classifiers":[
        {
            "category":"Banks & Credit Unions",
            "subcategory":"Bank",
            "type":"Services"
        }
    ],
    "sg:phone":"+1 812 537 1212",
    "sg:postcode":"47025",
    "sg:province":"IN",
    "sg:website":"www.usbank.com",
    "wof:name":"US Bank",
    "wof:placetype":"venue"
},
  "geometry": {"coordinates":[-84.84866599999999,39.093466],"type":"Point"}
}