{
  "type": "Feature",
  "properties": {
    "iso:country":"US",
    "sg:address":"211 S Walnut St",
    "sg:city":"Crawfordsville",
    "sg:classifiers":[
        {
            "category":"Organizations",
            "subcategory":"Religious Organization",
            "type":"Services"
        }
    ],
    "sg:phone":"+1 765 362 4812",
    "sg:postcode":"47933",
    "sg:province":"IN",
    "sg:tags":[
        "church"
    ],
    "wof:name":"First Christian Church",
    "wof:placetype":"venue"
},
  "geometry": {"coordinates":[-86.90298300000001,40.040472],"type":"Point"}
}