{
  "type": "Feature",
  "properties": {
    "iso:country":"US",
    "sg:address":"1219 Nelson Rd",
    "sg:city":"Rising Sun",
    "sg:classifiers":[
        {
            "category":"Real Estate",
            "subcategory":"Developer",
            "type":"Services"
        }
    ],
    "sg:phone":"+1 812 438 2864",
    "sg:postcode":"47040",
    "sg:province":"IN",
    "sg:tags":[
        "cemetery"
    ],
    "wof:name":"Rising Sun Cemetery Assn",
    "wof:placetype":"venue"
},
  "geometry": {"coordinates":[-84.865617,38.955611],"type":"Point"}
}