{
  "type": "Feature",
  "properties": {
    "iso:country":"US",
    "sg:address":"9224 S 875 E",
    "sg:city":"Walkerton",
    "sg:classifiers":[
        {
            "category":"Professional",
            "subcategory":"Business Services",
            "type":"Services"
        }
    ],
    "sg:phone":"+1 574 586 9883",
    "sg:postcode":"46574",
    "sg:province":"IN",
    "sg:tags":[
        "auctioneer"
    ],
    "wof:name":"Kankakee Valley Auction Co",
    "wof:placetype":"venue"
},
  "geometry": {"coordinates":[-86.529616,41.473262],"type":"Point"}
}