{
  "type": "Feature",
  "properties": {
    "iso:country":"US",
    "sg:address":"829 W Main St",
    "sg:city":"Peru",
    "sg:classifiers":[
        {
            "category":"Travel",
            "subcategory":"Hotels & Motels",
            "type":"Entertainment"
        }
    ],
    "sg:phone":"+1 765 472 1925",
    "sg:postcode":"46970",
    "sg:province":"IN",
    "wof:name":"Shelton Inn",
    "wof:placetype":"venue"
},
  "geometry": {"coordinates":[-86.091506,40.745012],"type":"Point"}
}