{
  "type": "Feature",
  "properties": {
    "addr:full":"555 Pine Dr Indianapolis IN 46260",
    "addr:housenumber":"555",
    "addr:postcode":"46260",
    "addr:street":"Pine Dr",
    "iso:country":"US",
    "sg:address":"555 Pine Dr",
    "sg:city":"Indianapolis",
    "sg:classifiers":[
        {
            "category":"Wholesale",
            "subcategory":"Hardware",
            "type":"Manufacturing & Wholesale Goods"
        }
    ],
    "sg:phone":"+1 317 848 4720",
    "sg:postcode":"46260",
    "sg:province":"IN",
    "sg:tags":[
        "used",
        "boiler"
    ],
    "wof:name":"M G Sales",
    "wof:placetype":"venue"
},
  "geometry": {"coordinates":[-86.16888400000001,39.924064],"type":"Point"}
}