{
  "type": "Feature",
  "properties": {
    "iso:country":"US",
    "sg:address":"675 Beacon St",
    "sg:city":"Carmel",
    "sg:classifiers":[
        {
            "category":"Real Estate",
            "subcategory":"Real Estate Operator",
            "type":"Services"
        }
    ],
    "sg:phone":"+1 317 569 7368",
    "sg:postcode":"46032",
    "sg:province":"IN",
    "sg:tags":[
        "apartment"
    ],
    "wof:name":"AMLI At Carmel Ctr",
    "wof:placetype":"venue"
},
  "geometry": {"coordinates":[-86.134428,39.968999],"type":"Point"}
}