{
  "type": "Feature",
  "properties": {
    "addr:full":"10808 Weston Dr Carmel IN 46032",
    "addr:housenumber":"10808",
    "addr:postcode":"46032",
    "addr:street":"Weston Dr",
    "iso:country":"US",
    "sg:address":"10808 Weston Dr",
    "sg:city":"Carmel",
    "sg:classifiers":[
        {
            "category":"Professional",
            "subcategory":"Computer Services",
            "type":"Services"
        }
    ],
    "sg:phone":"+1 317 873 1044",
    "sg:postcode":"46032",
    "sg:province":"IN",
    "sg:tags":[
        "management",
        "datum"
    ],
    "wof:name":"Unisys Corporation",
    "wof:placetype":"venue"
},
  "geometry": {"coordinates":[-86.23027999999999,39.943261],"type":"Point"}
}