{
  "type": "Feature",
  "properties": {
    "addr:full":"101 2nd Ave SW Carmel IN 46032",
    "addr:housenumber":"101",
    "addr:postcode":"46032",
    "addr:street":"2Nd Ave Sw",
    "iso:country":"US",
    "sg:address":"101 2nd Ave SW",
    "sg:city":"Carmel",
    "sg:classifiers":[
        {
            "category":"Building & Trades",
            "subcategory":"Locksmith",
            "type":"Services"
        }
    ],
    "sg:phone":"+1 317 682 9093",
    "sg:postcode":"46032",
    "sg:province":"IN",
    "sg:tags":[
        "key"
    ],
    "wof:name":"A Plus Locksmith",
    "wof:placetype":"venue"
},
  "geometry": {"coordinates":[-86.129733,39.976918],"type":"Point"}
}