{
  "type": "Feature",
  "properties": {
    "iso:country":"US",
    "sg:address":"1630 Plantation Dr",
    "sg:city":"Martinsville",
    "sg:classifiers":[
        {
            "category":"Building & Trades",
            "subcategory":"Electrical",
            "type":"Services"
        }
    ],
    "sg:phone":"+1 765 342 4069",
    "sg:postcode":"46151",
    "sg:province":"IN",
    "sg:tags":[
        "electric",
        "contractor"
    ],
    "wof:name":"Artesian Home Improvements",
    "wof:placetype":"venue"
},
  "geometry": {"coordinates":[-86.432025,39.411505],"type":"Point"}
}