{
  "type": "Feature",
  "properties": {
    "iso:country":"US",
    "sg:address":"2012 W 81st Ave",
    "sg:city":"Merrillville",
    "sg:classifiers":[
        {
            "category":"Personal",
            "subcategory":"Beauty Salon",
            "type":"Services"
        }
    ],
    "sg:phone":"+1 219 736 7749",
    "sg:postcode":"46410",
    "sg:province":"IN",
    "wof:name":"Fast Eddie's",
    "wof:placetype":"venue"
},
  "geometry": {"coordinates":[-87.360408,41.471187],"type":"Point"}
}