{
  "type": "Feature",
  "properties": {
    "iso:country":"US",
    "sg:address":"201 S High St",
    "sg:city":"West Lebanon",
    "sg:classifiers":[
        {
            "category":"Government",
            "subcategory":"Office",
            "type":"Public Place"
        }
    ],
    "sg:phone":"+1 765 893 4014",
    "sg:postcode":"47991",
    "sg:province":"IN",
    "sg:tags":[
        "city"
    ],
    "wof:name":"West Lebanon Town Hall",
    "wof:placetype":"venue"
},
  "geometry": {"coordinates":[-87.386696,40.270434],"type":"Point"}
}