{
  "type": "Feature",
  "properties": {
    "addr:full":"125 N Front St Rensselaer IN 47978",
    "addr:housenumber":"125",
    "addr:postcode":"47978",
    "addr:street":"N Front St",
    "iso:country":"US",
    "sg:address":"125 N Front St",
    "sg:city":"Rensselaer",
    "sg:classifiers":[
        {
            "category":"Shopping",
            "subcategory":"Gifts & Souvenirs",
            "type":"Retail Goods"
        }
    ],
    "sg:phone":"+1 219 866 5353",
    "sg:postcode":"47978",
    "sg:province":"IN",
    "sg:tags":[
        "shop"
    ],
    "wof:name":"Long's Gifts",
    "wof:placetype":"venue"
},
  "geometry": {"coordinates":[-87.153775,40.935997],"type":"Point"}
}