{
  "type": "Feature",
  "properties": {
    "iso:country":"US",
    "sg:address":"8186 W Co Rd 575 N",
    "sg:city":"Middletown",
    "sg:classifiers":[
        {
            "category":"Travel",
            "subcategory":"Campground",
            "type":"Entertainment"
        }
    ],
    "sg:phone":"+1 765 354 4521",
    "sg:postcode":"47356",
    "sg:province":"IN",
    "wof:name":"Spring Valley Campgrounds",
    "wof:placetype":"venue"
},
  "geometry": {"coordinates":[-85.535026,40.016872],"type":"Point"}
}