{
  "type": "Feature",
  "properties": {
    "addr:full":"3365 W State Rd 28 West Lebanon IN 47991",
    "addr:housenumber":"3365;28",
    "addr:postcode":"47991",
    "addr:street":"W State Rd",
    "iso:country":"US",
    "sg:address":"3365 W State Rd 28",
    "sg:city":"West Lebanon",
    "sg:classifiers":[
        {
            "category":"Manufacturing",
            "subcategory":"Tools & Machinery",
            "type":"Manufacturing & Wholesale Goods"
        }
    ],
    "sg:phone":"+1 765 893 4426",
    "sg:postcode":"47991",
    "sg:province":"IN",
    "sg:tags":[
        "machine",
        "shop"
    ],
    "wof:name":"Gillum Machine & Tool",
    "wof:placetype":"venue"
},
  "geometry": {"coordinates":[-87.38312000000001,40.280015],"type":"Point"}
}