{
  "type": "Feature",
  "properties": {
    "iso:country":"US",
    "sg:address":"734 22nd St",
    "sg:city":"Tell City",
    "sg:classifiers":[
        {
            "category":"Building & Trades",
            "subcategory":"Construction",
            "type":"Services"
        }
    ],
    "sg:phone":"+1 812 547 5389",
    "sg:postcode":"47586",
    "sg:province":"IN",
    "sg:tags":[
        "concrete",
        "contractor"
    ],
    "wof:name":"Round-A-Bout Co",
    "wof:placetype":"venue"
},
  "geometry": {"coordinates":[-86.751278,37.951633],"type":"Point"}
}