{
  "type": "Feature",
  "properties": {
    "iso:country":"US",
    "sg:address":"711 E 54th St",
    "sg:city":"Indianapolis",
    "sg:classifiers":[
        {
            "category":"Shopping",
            "subcategory":"Used Merchandise",
            "type":"Retail Goods"
        }
    ],
    "sg:phone":"+1 317 251 1936",
    "sg:postcode":"46220",
    "sg:province":"IN",
    "sg:tags":[
        "antique"
    ],
    "wof:name":"Sayger Antiques",
    "wof:placetype":"venue"
},
  "geometry": {"coordinates":[-86.144372,39.851005],"type":"Point"}
}