{
  "type": "Feature",
  "properties": {
    "addr:full":"454 Mill St Churubusco IN 46723",
    "addr:housenumber":"454",
    "addr:postcode":"46723",
    "addr:street":"Mill St",
    "iso:country":"US",
    "sg:address":"454 Mill St",
    "sg:city":"Churubusco",
    "sg:classifiers":[
        {
            "category":"Building & Trades",
            "subcategory":"Construction",
            "type":"Services"
        }
    ],
    "sg:phone":"+1 260 693 0045",
    "sg:postcode":"46723",
    "sg:province":"IN",
    "sg:tags":[
        "house",
        "business",
        "roof"
    ],
    "wof:name":"Greg Zorn",
    "wof:placetype":"venue"
},
  "geometry": {"coordinates":[-85.310908,41.229452],"type":"Point"}
}