{
  "type": "Feature",
  "properties": {
    "iso:country":"US",
    "sg:address":"1810 Williamsburg Pike",
    "sg:city":"Richmond",
    "sg:classifiers":[
        {
            "category":"Personal",
            "subcategory":"Beauty Salon",
            "type":"Services"
        }
    ],
    "sg:phone":"+1 765 965 3360",
    "sg:postcode":"47374",
    "sg:province":"IN",
    "sg:tags":[
        "shop"
    ],
    "wof:name":"Pine Square Hair Design",
    "wof:placetype":"venue"
},
  "geometry": {"coordinates":[-84.91444799999999,39.856912],"type":"Point"}
}