{
  "type": "Feature",
  "properties": {
    "iso:country":"US",
    "sg:address":"306 Old Trl",
    "sg:city":"Bargersville",
    "sg:classifiers":[
        {
            "category":"Freight",
            "type":"Transportation"
        }
    ],
    "sg:phone":"+1 317 422 8281",
    "sg:postcode":"46106",
    "sg:province":"IN",
    "sg:tags":[
        "trucking"
    ],
    "wof:name":"R & S Svc",
    "wof:placetype":"venue"
},
  "geometry": {"coordinates":[-86.163847,39.523168],"type":"Point"}
}