{
  "type": "Feature",
  "properties": {
    "iso:country":"US",
    "sg:address":"140 Washington Pointe Dr",
    "sg:city":"Indianapolis",
    "sg:classifiers":[
        {
            "category":"Real Estate",
            "subcategory":"Real Estate Agent",
            "type":"Services"
        }
    ],
    "sg:phone":"+1 317 899 8030",
    "sg:postcode":"46229",
    "sg:province":"IN",
    "wof:name":"Daniel S Adams",
    "wof:placetype":"venue"
},
  "geometry": {"coordinates":[-85.98041000000001,39.776334],"type":"Point"}
}