{
  "type": "Feature",
  "properties": {
    "iso:country":"US",
    "sg:address":"401 N 10th St",
    "sg:city":"Richmond",
    "sg:classifiers":[
        {
            "category":"Real Estate",
            "subcategory":"Real Estate Operator",
            "type":"Services"
        }
    ],
    "sg:phone":"+1 765 973 6927",
    "sg:postcode":"47374",
    "sg:province":"IN",
    "sg:tags":[
        "apartment"
    ],
    "wof:name":"Atlas Apartments",
    "wof:placetype":"venue"
},
  "geometry": {"coordinates":[-84.888984,39.833025],"type":"Point"}
}