{
  "type": "Feature",
  "properties": {
    "iso:country":"US",
    "sg:address":"6979 Corporate Cir",
    "sg:city":"Indianapolis",
    "sg:classifiers":[
        {
            "category":"Government",
            "subcategory":"Office",
            "type":"Public Place"
        }
    ],
    "sg:phone":"+1 317 293 2437",
    "sg:postcode":"46278",
    "sg:province":"IN",
    "sg:tags":[
        "state",
        "taxation"
    ],
    "sg:website":"www.in.gov/atc",
    "wof:name":"Excise Police",
    "wof:placetype":"venue"
},
  "geometry": {"coordinates":[-86.265624,39.880811],"type":"Point"}
}