{
  "type": "Feature",
  "properties": {
    "iso:country":"US",
    "sg:address":"7612 Pendleton Pike",
    "sg:city":"Indianapolis",
    "sg:classifiers":[
        {
            "category":"Shopping",
            "type":"Retail Goods"
        }
    ],
    "sg:phone":"+1 317 549 2493",
    "sg:postcode":"46226",
    "sg:province":"IN",
    "sg:tags":[
        "product",
        "wood"
    ],
    "wof:name":"Tom Wood Select",
    "wof:placetype":"venue"
},
  "geometry": {"coordinates":[-86.031793,39.834183],"type":"Point"}
}