{
  "type": "Feature",
  "properties": {
    "iso:country":"US",
    "sg:address":"651 S A St",
    "sg:city":"Richmond",
    "sg:classifiers":[
        {
            "category":"Banks & Credit Unions",
            "subcategory":"Investment Brokerage",
            "type":"Services"
        }
    ],
    "sg:phone":"+1 765 962 7393",
    "sg:postcode":"47374",
    "sg:province":"IN",
    "sg:tags":[
        "security"
    ],
    "sg:website":"www.agedwards.com",
    "wof:name":"A G Edwards & Sons Inc",
    "wof:placetype":"venue"
},
  "geometry": {"coordinates":[-84.893687,39.827222],"type":"Point"}
}