{
  "type": "Feature",
  "properties": {
    "iso:country":"US",
    "sg:address":"217 N 15th St",
    "sg:city":"Vincennes",
    "sg:classifiers":[
        {
            "category":"Retail",
            "subcategory":"Repair Shop",
            "type":"Services"
        }
    ],
    "sg:phone":"+1 812 886 0172",
    "sg:postcode":"47591",
    "sg:province":"IN",
    "sg:tags":[
        "repairing",
        "lawn",
        "mower"
    ],
    "wof:name":"D W Handy's",
    "wof:placetype":"venue"
},
  "geometry": {"coordinates":[-87.518771,38.670346],"type":"Point"}
}