{
  "type": "Feature",
  "properties": {
    "iso:country":"US",
    "sg:address":"502 N Rural St",
    "sg:city":"Indianapolis",
    "sg:classifiers":[
        {
            "category":"Shopping",
            "subcategory":"Used Merchandise",
            "type":"Retail Goods"
        }
    ],
    "sg:phone":"+1 317 632 6339",
    "sg:postcode":"46201",
    "sg:province":"IN",
    "sg:tags":[
        "pawnbroker"
    ],
    "wof:name":"Cash-N-Pawn",
    "wof:placetype":"venue"
},
  "geometry": {"coordinates":[-86.116702,39.77613],"type":"Point"}
}