{
  "type": "Feature",
  "properties": {
    "iso:country":"US",
    "sg:address":"600 S Main St",
    "sg:city":"New Castle",
    "sg:classifiers":[
        {
            "category":"Retail",
            "subcategory":"Funeral Services",
            "type":"Services"
        }
    ],
    "sg:phone":"+1 765 529 5900",
    "sg:postcode":"47362",
    "sg:province":"IN",
    "sg:tags":[
        "director"
    ],
    "wof:name":"Macer-Hall Funeral Home Inc",
    "wof:placetype":"venue"
},
  "geometry": {"coordinates":[-85.37029699999999,39.927485],"type":"Point"}
}