{
  "type": "Feature",
  "properties": {
    "iso:country":"US",
    "sg:address":"9064 S 600 W",
    "sg:city":"Edinburgh",
    "sg:classifiers":[
        {
            "category":"Manufacturing",
            "subcategory":"Motor Vehicles & Parts",
            "type":"Manufacturing & Wholesale Goods"
        }
    ],
    "sg:phone":"+1 317 729 5430",
    "sg:postcode":"46124",
    "sg:province":"IN",
    "sg:tags":[
        "automobile",
        "supply"
    ],
    "wof:name":"Niebel Engines Inc",
    "wof:placetype":"venue"
},
  "geometry": {"coordinates":[-85.894046,39.391476],"type":"Point"}
}