{
  "type": "Feature",
  "properties": {
    "iso:country":"US",
    "sg:address":"307 School St",
    "sg:city":"Pierceton",
    "sg:classifiers":[
        {
            "category":"Education",
            "subcategory":"School",
            "type":"Public Place"
        }
    ],
    "sg:phone":"+1 574 594 2210",
    "sg:postcode":"46562",
    "sg:province":"IN",
    "wof:name":"Pierceton Elementary School",
    "wof:placetype":"venue"
},
  "geometry": {"coordinates":[-85.707258,41.194928],"type":"Point"}
}