{
  "type": "Feature",
  "properties": {
    "iso:country":"US",
    "sg:address":"1215 Bluff Rd",
    "sg:city":"Plainfield",
    "sg:classifiers":[
        {
            "category":"Building & Trades",
            "subcategory":"Landscaping Services",
            "type":"Services"
        }
    ],
    "sg:phone":"+1 317 838 0048",
    "sg:postcode":"46168",
    "sg:province":"IN",
    "wof:name":"Flowers Plus",
    "wof:placetype":"venue"
},
  "geometry": {"coordinates":[-86.387705,39.689218],"type":"Point"}
}