{
  "type": "Feature",
  "properties": {
    "iso:country":"US",
    "sg:address":"810 Central Ave",
    "sg:city":"Anderson",
    "sg:classifiers":[
        {
            "category":"Building & Trades",
            "subcategory":"Construction",
            "type":"Services"
        }
    ],
    "sg:phone":"+1 765 644 8502",
    "sg:postcode":"46012",
    "sg:province":"IN",
    "sg:tags":[
        "general",
        "contractor"
    ],
    "wof:name":"Mustin Builders",
    "wof:placetype":"venue"
},
  "geometry": {"coordinates":[-85.67036,40.107202],"type":"Point"}
}