{
  "type": "Feature",
  "properties": {
    "iso:country":"US",
    "sg:address":"4108 Mountbatton Dr",
    "sg:city":"Greenwood",
    "sg:classifiers":[
        {
            "category":"Professional",
            "type":"Services"
        }
    ],
    "sg:phone":"+1 317 882 2046",
    "sg:postcode":"46143",
    "sg:province":"IN",
    "wof:name":"Simplified Logic Inc",
    "wof:placetype":"venue"
},
  "geometry": {"coordinates":[-86.180454,39.593528],"type":"Point"}
}