{
  "type": "Feature",
  "properties": {
    "addr:full":"9013 E 17th St Indianapolis IN 46229",
    "addr:housenumber":"9013",
    "addr:postcode":"46229",
    "addr:street":"E 17Th St",
    "iso:country":"US",
    "sg:address":"9013 E 17th St",
    "sg:city":"Indianapolis",
    "sg:classifiers":[
        {
            "category":"Insurance",
            "subcategory":"Insurance Agent",
            "type":"Services"
        }
    ],
    "sg:phone":"+1 317 897 4154",
    "sg:postcode":"46229",
    "sg:province":"IN",
    "wof:name":"Farmers Insurance Group",
    "wof:placetype":"venue"
},
  "geometry": {"coordinates":[-86.00507,39.790903],"type":"Point"}
}