{
  "type": "Feature",
  "properties": {
    "iso:country":"US",
    "sg:address":"1605 N 12th St",
    "sg:city":"Lafayette",
    "sg:classifiers":[
        {
            "category":"Building & Trades",
            "subcategory":"Plumbing",
            "type":"Services"
        }
    ],
    "sg:phone":"+1 765 742 1836",
    "sg:postcode":"47904",
    "sg:province":"IN",
    "sg:tags":[
        "plumbing",
        "contractor"
    ],
    "wof:name":"A-1 Co",
    "wof:placetype":"venue"
},
  "geometry": {"coordinates":[-86.884614,40.43441],"type":"Point"}
}