{
  "type": "Feature",
  "properties": {
    "iso:country":"US",
    "sg:address":"3828 N Portersville Rd",
    "sg:city":"Jasper",
    "sg:classifiers":[
        {
            "category":"Real Estate",
            "subcategory":"Real Estate Operator",
            "type":"Services"
        }
    ],
    "sg:phone":"+1 812 482 3735",
    "sg:postcode":"47546",
    "sg:province":"IN",
    "sg:tags":[
        "mobile",
        "home",
        "community"
    ],
    "wof:name":"Maple Grove Village",
    "wof:placetype":"venue"
},
  "geometry": {"coordinates":[-86.95263,38.436438],"type":"Point"}
}