{
  "type": "Feature",
  "properties": {
    "iso:country":"US",
    "sg:address":"9137 Pendleton Pike",
    "sg:city":"Indianapolis",
    "sg:classifiers":[
        {
            "category":"Recreation",
            "subcategory":"Dog Park",
            "type":"Entertainment"
        },
        {
            "category":"Shopping",
            "subcategory":"Pets & Pet Supplies",
            "type":"Retail Goods"
        }
    ],
    "sg:phone":"+1 317 898 6974",
    "sg:postcode":"46236",
    "sg:province":"IN",
    "sg:tags":[
        "training"
    ],
    "sg:website":"http://www.specialtypetfoodandtraining.com",
    "wof:name":"Smart K-9",
    "wof:placetype":"venue"
},
  "geometry": {"coordinates":[-86.007051,39.845957],"type":"Point"}
}