{
  "type": "Feature",
  "properties": {
    "iso:country":"US",
    "sg:address":"8128 W Co Rd 750 S",
    "sg:city":"French Lick",
    "sg:classifiers":[
        {
            "category":"Travel",
            "subcategory":"Campground",
            "type":"Entertainment"
        }
    ],
    "sg:phone":"+1 812 936 9140",
    "sg:postcode":"47432",
    "sg:province":"IN",
    "wof:name":"Woodland Hills Campground",
    "wof:placetype":"venue"
},
  "geometry": {"coordinates":[-86.611291,38.4436],"type":"Point"}
}