{
  "type": "Feature",
  "properties": {
    "iso:country":"US",
    "sg:address":"7113 E Co Rd 200 N",
    "sg:city":"Milan",
    "sg:classifiers":[
        {
            "category":"Freight",
            "type":"Transportation"
        }
    ],
    "sg:phone":"+1 812 654 3546",
    "sg:postcode":"47031",
    "sg:province":"IN",
    "sg:tags":[
        "hauling",
        "trucking"
    ],
    "wof:name":"L & D Trucking",
    "wof:placetype":"venue"
},
  "geometry": {"coordinates":[-85.130588,39.104763],"type":"Point"}
}