{
  "type": "Feature",
  "properties": {
    "iso:country":"US",
    "sg:address":"207 S Clark Blvd",
    "sg:city":"Clarksville",
    "sg:classifiers":[
        {
            "category":"Personal",
            "subcategory":"Beauty Salon",
            "type":"Services"
        }
    ],
    "sg:phone":"+1 812 944 6328",
    "sg:postcode":"47129",
    "sg:province":"IN",
    "sg:tags":[
        "manicuring"
    ],
    "wof:name":"Strandz & Nails LLC",
    "wof:placetype":"venue"
},
  "geometry": {"coordinates":[-85.761887,38.284966],"type":"Point"}
}