{
  "type": "Feature",
  "properties": {
    "iso:country":"US",
    "sg:address":"10055 State Rd 101",
    "sg:city":"Brookville",
    "sg:classifiers":[
        {
            "category":"Recreation",
            "subcategory":"Marina",
            "type":"Entertainment"
        }
    ],
    "sg:phone":"+1 765 647 5647",
    "sg:postcode":"47012",
    "sg:province":"IN",
    "sg:tags":[
        "storage",
        "boat"
    ],
    "wof:name":"Barton's Bay",
    "wof:placetype":"venue"
},
  "geometry": {"coordinates":[-84.986511,39.43796],"type":"Point"}
}