{
  "type": "Feature",
  "properties": {
    "iso:country":"US",
    "sg:address":"5944 Massachusetts Ave",
    "sg:city":"Indianapolis",
    "sg:classifiers":[
        {
            "category":"Retail",
            "subcategory":"Auto Repair",
            "type":"Services"
        }
    ],
    "sg:phone":"+1 317 547 7595",
    "sg:postcode":"46218",
    "sg:province":"IN",
    "sg:tags":[
        "repairing",
        "automobile"
    ],
    "wof:name":"Hair Automotive",
    "wof:placetype":"venue"
},
  "geometry": {"coordinates":[-86.065876,39.817901],"type":"Point"}
}