{
  "type": "Feature",
  "properties": {
    "addr:full":"56084 Co Rd 31 Goshen IN 46528",
    "addr:housenumber":"56084;31",
    "addr:postcode":"46528",
    "addr:street":"Co Rd",
    "iso:country":"US",
    "sg:address":"56084 Co Rd 31",
    "sg:city":"Goshen",
    "sg:classifiers":[
        {
            "category":"Retail",
            "subcategory":"Auto Repair",
            "type":"Services"
        }
    ],
    "sg:phone":"+1 574 825 7588",
    "sg:postcode":"46528",
    "sg:province":"IN",
    "sg:tags":[
        "body"
    ],
    "wof:name":"S & D Repair",
    "wof:placetype":"venue"
},
  "geometry": {"coordinates":[-85.772835,41.680287],"type":"Point"}
}