{
  "type": "Feature",
  "properties": {
    "iso:country":"US",
    "sg:address":"435 E Stansifer Ave",
    "sg:city":"Clarksville",
    "sg:classifiers":[
        {
            "category":"Education",
            "subcategory":"School",
            "type":"Public Place"
        }
    ],
    "sg:phone":"+1 812 282 9644",
    "sg:postcode":"47129",
    "sg:province":"IN",
    "wof:name":"George Rogers Clark Elem Schl",
    "wof:placetype":"venue"
},
  "geometry": {"coordinates":[-85.753523,38.284688],"type":"Point"}
}