{
  "type": "Feature",
  "properties": {
    "addr:full":"1626 Scatterfield Rd Anderson IN 46016",
    "addr:housenumber":"1626",
    "addr:postcode":"46016",
    "addr:street":"Scatterfield Rd",
    "iso:country":"US",
    "sg:address":"1626 Scatterfield Rd",
    "sg:city":"Anderson",
    "sg:classifiers":[
        {
            "category":"Banks & Credit Unions",
            "subcategory":"Bank",
            "type":"Services"
        }
    ],
    "sg:phone":"+1 765 644 7741",
    "sg:postcode":"46016",
    "sg:province":"IN",
    "sg:tags":[
        "financing"
    ],
    "wof:name":"Beneficial Finance",
    "wof:placetype":"venue"
},
  "geometry": {"coordinates":[-85.652492,40.100991],"type":"Point"}
}