{
  "type": "Feature",
  "properties": {
    "iso:country":"US",
    "sg:address":"1100 N Burkhardt Rd",
    "sg:city":"Evansville",
    "sg:classifiers":[
        {
            "category":"Restaurant",
            "type":"Food & Drink"
        }
    ],
    "sg:phone":"+1 812 479 9166",
    "sg:postcode":"47715",
    "sg:province":"IN",
    "wof:name":"Raffi's Restaurant",
    "wof:placetype":"venue"
},
  "geometry": {"coordinates":[-87.474054,37.98648],"type":"Point"}
}