{
  "type": "Feature",
  "properties": {
    "iso:country":"US",
    "sg:address":"18391 Co Rd 102",
    "sg:city":"Bristol",
    "sg:classifiers":[
        {
            "category":"Freight",
            "type":"Transportation"
        }
    ],
    "sg:phone":"+1 574 848 4418",
    "sg:postcode":"46507",
    "sg:province":"IN",
    "sg:tags":[
        "arrangement"
    ],
    "wof:name":"B A W Inc",
    "wof:placetype":"venue"
},
  "geometry": {"coordinates":[-85.821256,41.746883],"type":"Point"}
}