{
  "type": "Feature",
  "properties": {
    "iso:country":"US",
    "sg:address":"1711 W Iowa St",
    "sg:city":"Evansville",
    "sg:classifiers":[
        {
            "category":"Retail",
            "subcategory":"Repair Shop",
            "type":"Services"
        }
    ],
    "sg:phone":"+1 812 425 0723",
    "sg:postcode":"47712",
    "sg:province":"IN",
    "sg:tags":[
        "taxidermist"
    ],
    "wof:name":"Wildlife Re-Creations Studio",
    "wof:placetype":"venue"
},
  "geometry": {"coordinates":[-87.592031,37.983328],"type":"Point"}
}