{
  "type": "Feature",
  "properties": {
    "iso:country":"US",
    "sg:address":"328 E Walnut St",
    "sg:city":"Rensselaer",
    "sg:classifiers":[
        {
            "category":"Manufacturing",
            "subcategory":"Metals",
            "type":"Manufacturing & Wholesale Goods"
        }
    ],
    "sg:phone":"+1 219 866 0154",
    "sg:postcode":"47978",
    "sg:province":"IN",
    "sg:tags":[
        "fabrication"
    ],
    "wof:name":"Rwm Construction",
    "wof:placetype":"venue"
},
  "geometry": {"coordinates":[-87.150581,40.943738],"type":"Point"}
}