{
  "type": "Feature",
  "properties": {
    "iso:country":"US",
    "sg:address":"2006 W Judson Rd",
    "sg:city":"Kokomo",
    "sg:classifiers":[
        {
            "category":"Organizations",
            "subcategory":"Religious Organization",
            "type":"Services"
        }
    ],
    "sg:phone":"+1 765 236 0671",
    "sg:postcode":"46901",
    "sg:province":"IN",
    "sg:tags":[
        "church"
    ],
    "wof:name":"Judson Road Christian Church",
    "wof:placetype":"venue"
},
  "geometry": {"coordinates":[-86.15408600000001,40.502417],"type":"Point"}
}