{
  "type": "Feature",
  "properties": {
    "iso:country":"US",
    "sg:address":"4951 US Hwy 231 S",
    "sg:city":"Lafayette",
    "sg:classifiers":[
        {
            "category":"Communications",
            "subcategory":"Radio Station",
            "type":"Services"
        }
    ],
    "sg:phone":"+1 765 471 1965",
    "sg:postcode":"47909",
    "sg:province":"IN",
    "sg:tags":[
        "company",
        "broadcasting"
    ],
    "wof:name":"Wire Radio",
    "wof:placetype":"venue"
},
  "geometry": {"coordinates":[-86.911995,40.352505],"type":"Point"}
}