{
  "type": "Feature",
  "properties": {
    "iso:country":"US",
    "sg:address":"1615 E Wallace St",
    "sg:city":"Fort Wayne",
    "sg:classifiers":[
        {
            "category":"Manufacturing",
            "subcategory":"Tools & Machinery",
            "type":"Manufacturing & Wholesale Goods"
        }
    ],
    "sg:phone":"+1 260 744 2261",
    "sg:postcode":"46803",
    "sg:province":"IN",
    "sg:tags":[
        "wiring",
        "devices"
    ],
    "wof:name":"Stuart Manufacturing Inc",
    "wof:placetype":"venue"
},
  "geometry": {"coordinates":[-85.118549,41.06733],"type":"Point"}
}