{
  "type": "Feature",
  "properties": {
    "addr:full":"323 Ferry St Vevay IN 47043",
    "addr:housenumber":"323",
    "addr:postcode":"47043",
    "addr:street":"Ferry St",
    "iso:country":"US",
    "sg:address":"323 Ferry St",
    "sg:city":"Vevay",
    "sg:classifiers":[
        {
            "category":"Home & Garden",
            "subcategory":"Furniture",
            "type":"Retail Goods"
        }
    ],
    "sg:phone":"+1 812 427 3535",
    "sg:postcode":"47043",
    "sg:province":"IN",
    "wof:name":"Danner's Hardware & Home",
    "wof:placetype":"venue"
},
  "geometry": {"coordinates":[-85.06747799999999,38.747891],"type":"Point"}
}