{
  "type": "Feature",
  "properties": {
    "iso:country":"US",
    "sg:address":"8334 Northcote Ave",
    "sg:city":"Munster",
    "sg:classifiers":[
        {
            "category":"Professional",
            "subcategory":"Business Services",
            "type":"Services"
        }
    ],
    "sg:phone":"+1 219 923 6725",
    "sg:postcode":"46321",
    "sg:province":"IN",
    "wof:name":"Norris Designs",
    "wof:placetype":"venue"
},
  "geometry": {"coordinates":[-87.486611,41.561721],"type":"Point"}
}