{
  "type": "Feature",
  "properties": {
    "iso:country":"US",
    "sg:address":"2747 W Hibbs Rd",
    "sg:city":"Kingman",
    "sg:classifiers":[
        {
            "category":"Wholesale",
            "subcategory":"Meat",
            "type":"Manufacturing & Wholesale Goods"
        }
    ],
    "sg:phone":"+1 765 492 4249",
    "sg:postcode":"47952",
    "sg:province":"IN",
    "wof:name":"Hoosierland Pork Inc",
    "wof:placetype":"venue"
},
  "geometry": {"coordinates":[-87.399037,39.980743],"type":"Point"}
}