{
  "type": "Feature",
  "properties": {
    "iso:country":"US",
    "sg:address":"3801 S Reed Rd",
    "sg:city":"Kokomo",
    "sg:classifiers":[
        {
            "category":"Restaurant",
            "type":"Food & Drink"
        }
    ],
    "sg:menulink":"http://www.allmenus.com/in/kokomo/208075-taco-bell/menu/",
    "sg:phone":"+1 765 453 3559",
    "sg:postcode":"46902",
    "sg:province":"IN",
    "sg:tags":[
        "mexican"
    ],
    "wof:name":"Taco Bell",
    "wof:placetype":"venue"
},
  "geometry": {"coordinates":[-86.125845,40.441763],"type":"Point"}
}