{
  "type": "Feature",
  "properties": {
    "iso:country":"US",
    "sg:address":"103 S State St",
    "sg:city":"Lizton",
    "sg:classifiers":[
        {
            "category":"Government",
            "subcategory":"Fire Station",
            "type":"Public Place"
        }
    ],
    "sg:phone":"+1 317 994 5400",
    "sg:postcode":"46149",
    "sg:province":"IN",
    "sg:tags":[
        "department"
    ],
    "wof:name":"Lizton Fire Dept Adminis Trtv",
    "wof:placetype":"venue"
},
  "geometry": {"coordinates":[-86.542835,39.883242],"type":"Point"}
}