{
  "type": "Feature",
  "properties": {
    "addr:full":"137 E US Hwy 6 Valparaiso IN 46383",
    "addr:housenumber":"137",
    "addr:postcode":"46383",
    "addr:street":"E Us Hwy 6",
    "iso:country":"US",
    "sg:address":"137 E US Hwy 6",
    "sg:city":"Valparaiso",
    "sg:classifiers":[
        {
            "category":"Freight",
            "type":"Transportation"
        }
    ],
    "sg:phone":"+1 219 464 8565",
    "sg:postcode":"46383",
    "sg:province":"IN",
    "sg:tags":[
        "commercial",
        "storage"
    ],
    "wof:name":"6 & 49 Storage",
    "wof:placetype":"venue"
},
  "geometry": {"coordinates":[-87.036079,41.549992],"type":"Point"}
}