{
  "type": "Feature",
  "properties": {
    "iso:country":"US",
    "sg:address":"18565 Co Rd 2",
    "sg:city":"Bristol",
    "sg:classifiers":[
        {
            "category":"Building & Trades",
            "subcategory":"Construction",
            "type":"Services"
        }
    ],
    "sg:phone":"+1 574 536 2040",
    "sg:postcode":"46507",
    "sg:province":"IN",
    "sg:tags":[
        "house"
    ],
    "wof:name":"James D Meadows Jr",
    "wof:placetype":"venue"
},
  "geometry": {"coordinates":[-85.825464,41.754039],"type":"Point"}
}