{
  "type": "Feature",
  "properties": {
    "addr:full":"2454 W 850 S Geneva IN 46740",
    "addr:housenumber":"2454",
    "addr:postcode":"46740",
    "addr:street":"W 850 S",
    "iso:country":"US",
    "sg:address":"2454 W 850 S",
    "sg:city":"Geneva",
    "sg:classifiers":[
        {
            "category":"Farming",
            "subcategory":"Farm",
            "type":"Manufacturing & Wholesale Goods"
        }
    ],
    "sg:phone":"+1 260 589 3698",
    "sg:postcode":"46740",
    "sg:province":"IN",
    "wof:name":"Toland Farms Inc",
    "wof:placetype":"venue"
},
  "geometry": {"coordinates":[-84.981363,40.619661],"type":"Point"}
}