{
  "type": "Feature",
  "properties": {
    "addr:full":"3218 W 100 N Morocco IN 47963",
    "addr:housenumber":"3218",
    "addr:postcode":"47963",
    "addr:street":"W 100 N",
    "iso:country":"US",
    "sg:address":"3218 W 100 N",
    "sg:city":"Morocco",
    "sg:classifiers":[
        {
            "category":"Professional",
            "type":"Services"
        }
    ],
    "sg:phone":"+1 219 285 0926",
    "sg:postcode":"47963",
    "sg:province":"IN",
    "wof:name":"Collins Service Ctr",
    "wof:placetype":"venue"
},
  "geometry": {"coordinates":[-87.451335,41.013953],"type":"Point"}
}