{
  "type": "Feature",
  "properties": {
    "iso:country":"US",
    "sg:address":"7259 N Co Rd 225 E",
    "sg:city":"Pittsboro",
    "sg:classifiers":[
        {
            "category":"Building & Trades",
            "subcategory":"Construction",
            "type":"Services"
        }
    ],
    "sg:phone":"+1 317 892 5432",
    "sg:postcode":"46167",
    "sg:province":"IN",
    "sg:tags":[
        "framing",
        "contractor"
    ],
    "wof:name":"A C Custom Framing",
    "wof:placetype":"venue"
},
  "geometry": {"coordinates":[-86.481938,39.869222],"type":"Point"}
}