{
  "type": "Feature",
  "properties": {
    "iso:country":"US",
    "sg:address":"8016 N 400 W",
    "sg:city":"Bryant",
    "sg:classifiers":[
        {
            "category":"Farming",
            "subcategory":"Farm & Veterinary Services",
            "type":"Manufacturing & Wholesale Goods"
        }
    ],
    "sg:phone":"+1 260 997 8350",
    "sg:postcode":"47326",
    "sg:province":"IN",
    "sg:tags":[
        "management"
    ],
    "wof:name":"Alan Brunswick",
    "wof:placetype":"venue"
},
  "geometry": {"coordinates":[-85.058879,40.561274],"type":"Point"}
}