{
  "type": "Feature",
  "properties": {
    "iso:country":"US",
    "sg:address":"65 W Morgan St",
    "sg:city":"Martinsville",
    "sg:classifiers":[
        {
            "category":"Social Services",
            "type":"Services"
        }
    ],
    "sg:phone":"+1 765 349 8970",
    "sg:postcode":"46151",
    "sg:province":"IN",
    "sg:tags":[
        "mission"
    ],
    "wof:name":"Manna Mission",
    "wof:placetype":"venue"
},
  "geometry": {"coordinates":[-86.429215,39.427779],"type":"Point"}
}