{
  "type": "Feature",
  "properties": {
    "iso:country":"US",
    "sg:address":"2919 Spencer Ditch Rd",
    "sg:city":"Mount Vernon",
    "sg:phone":"+1 812 838 4211",
    "sg:postcode":"47620",
    "sg:province":"IN",
    "sg:tags":[
        "farm",
        "corn",
        "wheat",
        "soybean"
    ],
    "wof:name":"Schmudt Farm",
    "wof:placetype":"venue"
},
  "geometry": {"coordinates":[-87.98152399999999,37.877544],"type":"Point"}
}