{
  "type": "Feature",
  "properties": {
    "iso:country":"US",
    "sg:address":"5141 Madison Ave",
    "sg:city":"Indianapolis",
    "sg:classifiers":[
        {
            "category":"Retail",
            "subcategory":"Funeral Services",
            "type":"Services"
        }
    ],
    "sg:phone":"+1 317 787 7211",
    "sg:postcode":"46227",
    "sg:province":"IN",
    "sg:tags":[
        "director"
    ],
    "sg:website":"www.ghherrmann.com",
    "wof:name":"G H Herrmann Funeral Homes",
    "wof:placetype":"venue"
},
  "geometry": {"coordinates":[-86.135719,39.690778],"type":"Point"}
}