{
  "type": "Feature",
  "properties": {
    "iso:country":"US",
    "sg:address":"1333 Broadway St",
    "sg:city":"Indianapolis",
    "sg:classifiers":[
        {
            "category":"Professional",
            "type":"Services"
        }
    ],
    "sg:phone":"+1 317 638 9340",
    "sg:postcode":"46202",
    "sg:province":"IN",
    "wof:name":"Landlords & Artists",
    "wof:placetype":"venue"
},
  "geometry": {"coordinates":[-86.146134,39.785105],"type":"Point"}
}