{
  "type": "Feature",
  "properties": {
    "iso:country":"US",
    "sg:address":"481 E Dupont Rd",
    "sg:city":"Fort Wayne",
    "sg:classifiers":[
        {
            "category":"Shopping",
            "subcategory":"Crafts & Fabrics",
            "type":"Retail Goods"
        }
    ],
    "sg:phone":"+1 260 338 1050",
    "sg:postcode":"46825",
    "sg:province":"IN",
    "sg:tags":[
        "shop"
    ],
    "wof:name":"Quilt Fabric Shop",
    "wof:placetype":"venue"
},
  "geometry": {"coordinates":[-85.132138,41.178273],"type":"Point"}
}