{
  "type": "Feature",
  "properties": {
    "addr:full":"127 S Michigan St South Bend IN 46601",
    "addr:housenumber":"127",
    "addr:postcode":"46601",
    "addr:street":"S Michigan St",
    "iso:country":"US",
    "sg:address":"127 S Michigan St",
    "sg:city":"South Bend",
    "sg:classifiers":[
        {
            "category":"Restaurant",
            "type":"Food & Drink"
        }
    ],
    "sg:phone":"+1 574 288 7337",
    "sg:postcode":"46601",
    "sg:province":"IN",
    "wof:name":"Le Peep",
    "wof:placetype":"venue"
},
  "geometry": {"coordinates":[-86.250421,41.675387],"type":"Point"}
}