{
  "type": "Feature",
  "properties": {
    "iso:country":"US",
    "sg:address":"1329 W State Blvd",
    "sg:city":"Fort Wayne",
    "sg:classifiers":[
        {
            "category":"Restaurant",
            "type":"Food & Drink"
        }
    ],
    "sg:phone":"+1 260 423 2170",
    "sg:postcode":"46808",
    "sg:province":"IN",
    "wof:name":"West State",
    "wof:placetype":"venue"
},
  "geometry": {"coordinates":[-85.15985499999999,41.095918],"type":"Point"}
}