{
  "type": "Feature",
  "properties": {
    "iso:country":"US",
    "sg:address":"890 E Morgan St",
    "sg:city":"Martinsville",
    "sg:classifiers":[
        {
            "category":"Retail",
            "subcategory":"Portrait Studio",
            "type":"Services"
        }
    ],
    "sg:phone":"+1 765 352 1844",
    "sg:postcode":"46151",
    "sg:province":"IN",
    "sg:tags":[
        "photographer"
    ],
    "wof:name":"Cradle Memories Inc",
    "wof:placetype":"venue"
},
  "geometry": {"coordinates":[-86.417955,39.427905],"type":"Point"}
}