{
  "type": "Feature",
  "properties": {
    "iso:country":"US",
    "sg:address":"525 S Memorial Dr",
    "sg:city":"New Castle",
    "sg:classifiers":[
        {
            "category":"Personal",
            "subcategory":"Beauty Salon",
            "type":"Services"
        }
    ],
    "sg:phone":"+1 765 521 9434",
    "sg:postcode":"47362",
    "sg:province":"IN",
    "wof:name":"Famous Hair Co",
    "wof:placetype":"venue"
},
  "geometry": {"coordinates":[-85.381882,39.92701],"type":"Point"}
}