{
  "type": "Feature",
  "properties": {
    "iso:country":"US",
    "sg:address":"617 N Sycamore St",
    "sg:city":"Ladoga",
    "sg:classifiers":[
        {
            "category":"Personal",
            "subcategory":"Beauty Salon",
            "type":"Services"
        }
    ],
    "sg:phone":"+1 765 942 2237",
    "sg:postcode":"47954",
    "sg:province":"IN",
    "sg:tags":[
        "shop"
    ],
    "wof:name":"Chriss Clip & Curl",
    "wof:placetype":"venue"
},
  "geometry": {"coordinates":[-86.798341,39.917645],"type":"Point"}
}