{
  "type": "Feature",
  "properties": {
    "iso:country":"US",
    "sg:address":"545 N 9th St",
    "sg:city":"Clinton",
    "sg:classifiers":[
        {
            "category":"Restaurant",
            "type":"Food & Drink"
        }
    ],
    "sg:phone":"+1 765 832 2457",
    "sg:postcode":"47842",
    "sg:province":"IN",
    "wof:name":"Pizza City",
    "wof:placetype":"venue"
},
  "geometry": {"coordinates":[-87.408161,39.665465],"type":"Point"}
}