{
  "type": "Feature",
  "properties": {
    "iso:country":"US",
    "sg:address":"3101 Cart Rd",
    "sg:city":"Richmond",
    "sg:classifiers":[
        {
            "category":"Travel",
            "subcategory":"Campground",
            "type":"Entertainment"
        }
    ],
    "sg:phone":"+1 765 962 1219",
    "sg:postcode":"47374",
    "sg:province":"IN",
    "wof:name":"KOA Kampgrounds",
    "wof:placetype":"venue"
},
  "geometry": {"coordinates":[-84.870148,39.871756],"type":"Point"}
}