{
  "type": "Feature",
  "properties": {
    "addr:full":"331 Kimber Ln Evansville IN 47715",
    "addr:housenumber":"331",
    "addr:postcode":"47715",
    "addr:street":"Kimber Ln",
    "iso:country":"US",
    "sg:address":"331 Kimber Ln",
    "sg:city":"Evansville",
    "sg:classifiers":[
        {
            "category":"Health Services",
            "subcategory":"Clinic",
            "type":"Services"
        }
    ],
    "sg:phone":"+1 812 476 5404",
    "sg:postcode":"47715",
    "sg:province":"IN",
    "sg:tags":[
        "home"
    ],
    "sg:website":"www.specialhealthcare.com",
    "wof:name":"Specialty Health Care",
    "wof:placetype":"venue"
},
  "geometry": {"coordinates":[-87.47730199999999,37.976787],"type":"Point"}
}