{
  "type": "Feature",
  "properties": {
    "addr:full":"80 W 6th St Peru IN 46970",
    "addr:housenumber":"80",
    "addr:postcode":"46970",
    "addr:street":"W 6Th St",
    "iso:country":"US",
    "sg:address":"80 W 6th St",
    "sg:city":"Peru",
    "sg:classifiers":[
        {
            "category":"Social Services",
            "type":"Services"
        }
    ],
    "sg:phone":"+1 765 473 9631",
    "sg:postcode":"46970",
    "sg:province":"IN",
    "sg:tags":[
        "organization",
        "welfare"
    ],
    "wof:name":"Miami Indian Bingo",
    "wof:placetype":"venue"
},
  "geometry": {"coordinates":[-86.072866,40.754359],"type":"Point"}
}