{
  "type": "Feature",
  "properties": {
    "iso:country":"US",
    "sg:address":"1240 NW 5th St",
    "sg:city":"Richmond",
    "sg:classifiers":[
        {
            "category":"Food & Beverages",
            "subcategory":"Groceries & Convenience Stores",
            "type":"Retail Goods"
        }
    ],
    "sg:phone":"+1 765 935 7983",
    "sg:postcode":"47374",
    "sg:province":"IN",
    "wof:name":"Village Pantry",
    "wof:placetype":"venue"
},
  "geometry": {"coordinates":[-84.907994,39.843221],"type":"Point"}
}