{
  "type": "Feature",
  "properties": {
    "iso:country":"US",
    "sg:address":"920 W Walnut St",
    "sg:city":"Albany",
    "sg:classifiers":[
        {
            "category":"Professional",
            "subcategory":"Computer Services",
            "type":"Services"
        }
    ],
    "sg:phone":"+1 765 789 6506",
    "sg:postcode":"47320",
    "sg:province":"IN",
    "sg:tags":[
        "consultant",
        "designer"
    ],
    "wof:name":"Weaver Technologies",
    "wof:placetype":"venue"
},
  "geometry": {"coordinates":[-85.247365,40.300791],"type":"Point"}
}