{
  "type": "Feature",
  "properties": {
    "iso:country":"US",
    "sg:address":"2433 Simpson Ln",
    "sg:city":"Shelbyville",
    "sg:classifiers":[
        {
            "category":"Farming",
            "subcategory":"Farm & Veterinary Services",
            "type":"Manufacturing & Wholesale Goods"
        }
    ],
    "sg:phone":"+1 317 392 4508",
    "sg:postcode":"46176",
    "sg:province":"IN",
    "sg:tags":[
        "management"
    ],
    "wof:name":"Steve Runnebohm",
    "wof:placetype":"venue"
},
  "geometry": {"coordinates":[-85.799184,39.501865],"type":"Point"}
}