{
  "type": "Feature",
  "properties": {
    "iso:country":"US",
    "sg:address":"1028 Sycamore St",
    "sg:city":"Lafayette",
    "sg:classifiers":[
        {
            "category":"Building & Trades",
            "subcategory":"Cleaning & Sanitation",
            "type":"Services"
        }
    ],
    "sg:phone":"+1 765 429 6209",
    "sg:postcode":"47905",
    "sg:province":"IN",
    "sg:tags":[
        "janitor"
    ],
    "wof:name":"B & B Cleaning",
    "wof:placetype":"venue"
},
  "geometry": {"coordinates":[-86.90156399999999,40.410653],"type":"Point"}
}