{
  "type": "Feature",
  "properties": {
    "iso:country":"US",
    "sg:address":"836 E 64th St",
    "sg:city":"Indianapolis",
    "sg:classifiers":[
        {
            "category":"Professional",
            "type":"Services"
        }
    ],
    "sg:phone":"+1 317 722 8500",
    "sg:postcode":"46220",
    "sg:province":"IN",
    "sg:tags":[
        "establishment"
    ],
    "sg:website":"www.indyschild.com",
    "wof:name":"Indy's Child",
    "wof:placetype":"venue"
},
  "geometry": {"coordinates":[-86.143552,39.872538],"type":"Point"}
}