{
  "type": "Feature",
  "properties": {
    "iso:country":"US",
    "sg:address":"2824 Elkhart Rd",
    "sg:city":"Goshen",
    "sg:classifiers":[
        {
            "category":"Autos & Motor Vehicles",
            "subcategory":"Automobile Sales",
            "type":"Retail Goods"
        }
    ],
    "sg:phone":"+1 574 534 2521",
    "sg:postcode":"46526",
    "sg:province":"IN",
    "sg:tags":[
        "car",
        "dealer"
    ],
    "sg:website":"www.kirkchevrolet.com",
    "wof:name":"KIRK Chevrolet-Pontiac Inc",
    "wof:placetype":"venue"
},
  "geometry": {"coordinates":[-85.877305,41.607943],"type":"Point"}
}