{
  "type": "Feature",
  "properties": {
    "iso:country":"US",
    "sg:address":"850 Delphi Ave",
    "sg:city":"Frankfort",
    "sg:classifiers":[
        {
            "category":"Organizations",
            "subcategory":"Religious Organization",
            "type":"Services"
        }
    ],
    "sg:phone":"+1 765 659 1963",
    "sg:postcode":"46041",
    "sg:province":"IN",
    "wof:name":"Apostolic Christian Academey",
    "wof:placetype":"venue"
},
  "geometry": {"coordinates":[-86.514184,40.291739],"type":"Point"}
}