{
  "type": "Feature",
  "properties": {
    "iso:country":"US",
    "sg:address":"411 W Kirkwood Ave",
    "sg:city":"Bloomington",
    "sg:classifiers":[
        {
            "category":"Personal",
            "subcategory":"Beauty Salon",
            "type":"Services"
        }
    ],
    "sg:phone":"+1 812 332 1933",
    "sg:postcode":"47404",
    "sg:province":"IN",
    "sg:tags":[
        "hair"
    ],
    "sg:website":"www.dosalon.com",
    "wof:name":"DO A Lee Parker Salon",
    "wof:placetype":"venue"
},
  "geometry": {"coordinates":[-86.537524,39.166465],"type":"Point"}
}