{
  "type": "Feature",
  "properties": {
    "iso:country":"US",
    "sg:address":"1710 W 3rd St",
    "sg:city":"Bloomington",
    "sg:classifiers":[
        {
            "category":"Banks & Credit Unions",
            "subcategory":"Bank",
            "type":"Services"
        }
    ],
    "sg:phone":"+1 812 323 7619",
    "sg:postcode":"47404",
    "sg:province":"IN",
    "sg:tags":[
        "cashing",
        "check"
    ],
    "wof:name":"Cashland",
    "wof:placetype":"venue"
},
  "geometry": {"coordinates":[-86.554676,39.164482],"type":"Point"}
}