{
  "type": "Feature",
  "properties": {
    "addr:full":"1758 W 100 S Portland IN 47371",
    "addr:housenumber":"1758",
    "addr:postcode":"47371",
    "addr:street":"W 100 S",
    "iso:country":"US",
    "sg:address":"1758 W 100 S",
    "sg:city":"Portland",
    "sg:classifiers":[
        {
            "category":"Health Services",
            "subcategory":"Medical Lab",
            "type":"Services"
        }
    ],
    "sg:phone":"+1 260 726 3011",
    "sg:postcode":"47371",
    "sg:province":"IN",
    "sg:tags":[
        "laboratory"
    ],
    "wof:name":"Pathologists Associated",
    "wof:placetype":"venue"
},
  "geometry": {"coordinates":[-85.014843,40.424566],"type":"Point"}
}