{
  "type": "Feature",
  "properties": {
    "iso:country":"US",
    "sg:address":"740 E Morgan St",
    "sg:city":"Martinsville",
    "sg:classifiers":[
        {
            "category":"Building & Trades",
            "subcategory":"Construction",
            "type":"Services"
        }
    ],
    "sg:phone":"+1 765 342 2166",
    "sg:postcode":"46151",
    "sg:province":"IN",
    "sg:tags":[
        "roofing",
        "contractor"
    ],
    "wof:name":"Walls & Son Construction",
    "wof:placetype":"venue"
},
  "geometry": {"coordinates":[-86.419721,39.427897],"type":"Point"}
}