{
  "type": "Feature",
  "properties": {
    "addr:full":"1210 Provident Dr Warsaw IN 46580",
    "addr:housenumber":"1210",
    "addr:postcode":"46580",
    "addr:street":"Provident Dr",
    "iso:country":"US",
    "sg:address":"1210 Provident Dr",
    "sg:city":"Warsaw",
    "sg:classifiers":[
        {
            "category":"Health Services",
            "subcategory":"Doctor",
            "type":"Services"
        }
    ],
    "sg:phone":"+1 574 268 4300",
    "sg:postcode":"46580",
    "sg:province":"IN",
    "sg:tags":[
        "physician",
        "surgeon"
    ],
    "wof:name":"Provident Family Healthcare",
    "wof:placetype":"venue"
},
  "geometry": {"coordinates":[-85.829875,41.251113],"type":"Point"}
}