{
  "type": "Feature",
  "properties": {
    "addr:full":"5361 W Co Rd 600 S Vallonia IN 47281",
    "addr:housenumber":"5361",
    "addr:postcode":"47281",
    "addr:street":"W Co Rd 600 S Vallonia",
    "iso:country":"US",
    "sg:address":"5361 W Co Rd 600 S",
    "sg:city":"Vallonia",
    "sg:classifiers":[
        {
            "category":"Real Estate",
            "subcategory":"Real Estate Operator",
            "type":"Services"
        }
    ],
    "sg:phone":"+1 812 358 2570",
    "sg:postcode":"47281",
    "sg:province":"IN",
    "sg:tags":[
        "property",
        "lessor"
    ],
    "wof:name":"Peters Empson",
    "wof:placetype":"venue"
},
  "geometry": {"coordinates":[-86.135302,38.789317],"type":"Point"}
}