{
  "type": "Feature",
  "properties": {
    "iso:country":"US",
    "sg:address":"12010 S Anthony Exd",
    "sg:city":"Fort Wayne",
    "sg:classifiers":[
        {
            "category":"Real Estate",
            "subcategory":"Surveying",
            "type":"Services"
        }
    ],
    "sg:phone":"+1 260 639 0048",
    "sg:postcode":"46819",
    "sg:province":"IN",
    "sg:tags":[
        "surveyor"
    ],
    "wof:name":"Mc Crea Land Surveying Inc",
    "wof:placetype":"venue"
},
  "geometry": {"coordinates":[-85.102139,40.976853],"type":"Point"}
}