{
  "type": "Feature",
  "properties": {
    "iso:country":"US",
    "sg:address":"7550 E Washington St",
    "sg:city":"Indianapolis",
    "sg:classifiers":[
        {
            "category":"Autos & Motor Vehicles",
            "subcategory":"Automobile Sales",
            "type":"Retail Goods"
        },
        {
            "category":"Autos & Motor Vehicles",
            "subcategory":"Auto Supplies",
            "type":"Retail Goods"
        },
        {
            "category":"Retail",
            "subcategory":"Auto Repair",
            "type":"Services"
        }
    ],
    "sg:phone":"+1 866 287 1216",
    "sg:postcode":"46219",
    "sg:province":"IN",
    "sg:tags":[
        "used",
        "car",
        "part",
        "truck",
        "new"
    ],
    "sg:website":"http://local.ingenio.com/Listings/Details.aspx?NUM=a%3a10120706%3a13%3a4859924%3a14%3a0%3a7",
    "wof:name":"Ray Skillman Northeast Buick GMC",
    "wof:placetype":"venue"
},
  "geometry": {"coordinates":[-86.03415699999999,39.772732],"type":"Point"}
}