{
  "type": "Feature",
  "properties": {
    "iso:country":"US",
    "sg:address":"9067 W State Rd 45",
    "sg:city":"Stanford",
    "sg:classifiers":[
        {
            "category":"Wholesale",
            "subcategory":"Hardware",
            "type":"Manufacturing & Wholesale Goods"
        }
    ],
    "sg:phone":"+1 812 825 5055",
    "sg:postcode":"47403",
    "sg:province":"IN",
    "sg:tags":[
        "fastener"
    ],
    "wof:name":"Bloomington Bolt & Screw Co",
    "wof:placetype":"venue"
},
  "geometry": {"coordinates":[-86.658672,39.095581],"type":"Point"}
}