{
  "type": "Feature",
  "properties": {
    "iso:country":"US",
    "sg:address":"1236 N Main St",
    "sg:city":"Kokomo",
    "sg:classifiers":[
        {
            "category":"Wholesale",
            "subcategory":"Machinery & Supplies",
            "type":"Manufacturing & Wholesale Goods"
        }
    ],
    "sg:phone":"+1 765 459 0311",
    "sg:postcode":"46901",
    "sg:province":"IN",
    "sg:tags":[
        "janitor"
    ],
    "wof:name":"R D Filip Inc",
    "wof:placetype":"venue"
},
  "geometry": {"coordinates":[-86.131191,40.497483],"type":"Point"}
}