{
  "type": "Feature",
  "properties": {
    "iso:country":"US",
    "sg:address":"1510 Amos Rd",
    "sg:city":"Shelbyville",
    "sg:classifiers":[
        {
            "category":"Professional",
            "subcategory":"Research",
            "type":"Services"
        }
    ],
    "sg:phone":"+1 317 421 0325",
    "sg:postcode":"46176",
    "sg:province":"IN",
    "wof:name":"Soybean Research",
    "wof:placetype":"venue"
},
  "geometry": {"coordinates":[-85.761492,39.506705],"type":"Point"}
}