{
  "type": "Feature",
  "properties": {
    "iso:country":"US",
    "sg:address":"206 S Falcon St",
    "sg:city":"South Bend",
    "sg:classifiers":[
        {
            "category":"Organizations",
            "subcategory":"Religious Organization",
            "type":"Services"
        }
    ],
    "sg:phone":"+1 574 288 4532",
    "sg:postcode":"46619",
    "sg:province":"IN",
    "sg:tags":[
        "church"
    ],
    "wof:name":"Missionary Greater Friendship",
    "wof:placetype":"venue"
},
  "geometry": {"coordinates":[-86.297179,41.672439],"type":"Point"}
}