{
  "type": "Feature",
  "properties": {
    "iso:country":"US",
    "sg:address":"1282 W Co Rd 200 S",
    "sg:city":"Frankfort",
    "sg:classifiers":[
        {
            "category":"Farming",
            "subcategory":"Farm",
            "type":"Manufacturing & Wholesale Goods"
        }
    ],
    "sg:phone":"+1 765 654 4021",
    "sg:postcode":"46041",
    "sg:province":"IN",
    "sg:tags":[
        "crop",
        "general"
    ],
    "wof:name":"Fox Family Farm Inc",
    "wof:placetype":"venue"
},
  "geometry": {"coordinates":[-86.52483599999999,40.257341],"type":"Point"}
}