{
  "type": "Feature",
  "properties": {
    "iso:country":"US",
    "sg:address":"800 Mount Tabor Rd",
    "sg:city":"New Albany",
    "sg:classifiers":[
        {
            "category":"Education",
            "subcategory":"School",
            "type":"Public Place"
        }
    ],
    "sg:phone":"+1 812 949 4301",
    "sg:postcode":"47150",
    "sg:province":"IN",
    "wof:name":"Mt Tabor Elementary School",
    "wof:placetype":"venue"
},
  "geometry": {"coordinates":[-85.817037,38.331821],"type":"Point"}
}