{
  "type": "Feature",
  "properties": {
    "iso:country":"US",
    "sg:address":"201 S Capitol Ave",
    "sg:city":"Indianapolis",
    "sg:classifiers":[
        {
            "category":"Organizations",
            "subcategory":"Non-profit Organization",
            "type":"Services"
        }
    ],
    "sg:phone":"+1 317 237 5252",
    "sg:postcode":"46225",
    "sg:province":"IN",
    "wof:name":"United States Diving Inc",
    "wof:placetype":"venue"
},
  "geometry": {"coordinates":[-86.16185900000001,39.763185],"type":"Point"}
}