{
  "type": "Feature",
  "properties": {
    "iso:country":"US",
    "sg:address":"260 Campbell St",
    "sg:city":"Valparaiso",
    "sg:classifiers":[
        {
            "category":"Autos & Motor Vehicles",
            "subcategory":"Boat Sales",
            "type":"Retail Goods"
        }
    ],
    "sg:phone":"+1 219 548 0352",
    "sg:postcode":"46385",
    "sg:province":"IN",
    "sg:tags":[
        "dealer",
        "sales"
    ],
    "wof:name":"Valpo Boat Clinic",
    "wof:placetype":"venue"
},
  "geometry": {"coordinates":[-87.065871,41.470607],"type":"Point"}
}