{
  "type": "Feature",
  "properties": {
    "iso:country":"US",
    "sg:address":"5135 W 10th St",
    "sg:city":"Speedway",
    "sg:classifiers":[
        {
            "category":"Professional",
            "subcategory":"Lawyer & Legal Services",
            "type":"Services"
        }
    ],
    "sg:phone":"+1 317 243 7567",
    "sg:postcode":"46224",
    "sg:province":"IN",
    "sg:tags":[
        "attorney"
    ],
    "wof:name":"Herman E Greenwood",
    "wof:placetype":"venue"
},
  "geometry": {"coordinates":[-86.244861,39.779982],"type":"Point"}
}