{
  "type": "Feature",
  "properties": {
    "iso:country":"US",
    "sg:address":"55 S Main St",
    "sg:city":"Linton",
    "sg:classifiers":[
        {
            "category":"Sports & Exercise",
            "subcategory":"Gym",
            "type":"Entertainment"
        }
    ],
    "sg:phone":"+1 812 847 5932",
    "sg:postcode":"47441",
    "sg:province":"IN",
    "sg:tags":[
        "club",
        "health",
        "studio",
        "gymnasium"
    ],
    "wof:name":"Linton Weight Loss & Fitns Ctr",
    "wof:placetype":"venue"
},
  "geometry": {"coordinates":[-87.166049,39.033293],"type":"Point"}
}