{
  "type": "Feature",
  "properties": {
    "iso:country":"US",
    "sg:address":"210 S Bill St",
    "sg:city":"Francesville",
    "sg:classifiers":[
        {
            "category":"Professional",
            "subcategory":"Research",
            "type":"Services"
        }
    ],
    "sg:phone":"+1 219 567 9064",
    "sg:postcode":"47946",
    "sg:province":"IN",
    "sg:tags":[
        "foundation",
        "philanthropic"
    ],
    "wof:name":"Pace",
    "wof:placetype":"venue"
},
  "geometry": {"coordinates":[-86.88193800000001,40.983922],"type":"Point"}
}