{
  "type": "Feature",
  "properties": {
    "addr:full":"9227 Sussex Ter Apt 813 Indianapolis IN 46229",
    "addr:housenumber":"9227;813",
    "addr:postcode":"46229",
    "addr:street":"Sussex Ter Apt",
    "iso:country":"US",
    "sg:address":"9227 Sussex Ter Apt 813",
    "sg:city":"Indianapolis",
    "sg:classifiers":[
        {
            "category":"Professional",
            "subcategory":"Business Services",
            "type":"Services"
        }
    ],
    "sg:phone":"+1 317 333 2252",
    "sg:postcode":"46229",
    "sg:province":"IN",
    "sg:tags":[
        "holding"
    ],
    "wof:name":"Cmn Holdings Inc.",
    "wof:placetype":"venue"
},
  "geometry": {"coordinates":[-86.00543500000001,39.798994],"type":"Point"}
}