{
  "type": "Feature",
  "properties": {
    "iso:country":"US",
    "sg:address":"6808 W Shoaff Rd",
    "sg:city":"Fort Wayne",
    "sg:classifiers":[
        {
            "category":"Professional",
            "subcategory":"Business Services",
            "type":"Services"
        }
    ],
    "sg:phone":"+1 260 637 7204",
    "sg:postcode":"46818",
    "sg:province":"IN",
    "wof:name":"Wilson Farm Enterprises LLC",
    "wof:placetype":"venue"
},
  "geometry": {"coordinates":[-85.23641499999999,41.225754],"type":"Point"}
}