{
  "type": "Feature",
  "properties": {
    "iso:country":"US",
    "sg:address":"3045 E State Rd 8",
    "sg:city":"Albion",
    "sg:classifiers":[
        {
            "category":"Travel",
            "subcategory":"Hotels & Motels",
            "type":"Entertainment"
        }
    ],
    "sg:phone":"+1 260 636 7579",
    "sg:postcode":"46701",
    "sg:province":"IN",
    "sg:tags":[
        "inn"
    ],
    "wof:name":"Wonder Inn",
    "wof:placetype":"venue"
},
  "geometry": {"coordinates":[-85.367015,41.395923],"type":"Point"}
}