{
  "type": "Feature",
  "properties": {
    "addr:full":"200 W 53rd St Anderson IN 46013",
    "addr:housenumber":"200",
    "addr:postcode":"46013",
    "addr:street":"W 53Rd St",
    "iso:country":"US",
    "sg:address":"200 W 53rd St",
    "sg:city":"Anderson",
    "sg:classifiers":[
        {
            "category":"Retail",
            "subcategory":"Funeral Services",
            "type":"Services"
        }
    ],
    "sg:phone":"+1 765 649 5255",
    "sg:postcode":"46013",
    "sg:province":"IN",
    "sg:tags":[
        "director"
    ],
    "sg:website":"www.loosefuneralhomes.com",
    "wof:name":"Robert Loose Funeral Home",
    "wof:placetype":"venue"
},
  "geometry": {"coordinates":[-85.67980900000001,40.061673],"type":"Point"}
}