{
  "type": "Feature",
  "properties": {
    "iso:country":"US",
    "sg:address":"20876 Arcadia Dr",
    "sg:city":"Bristol",
    "sg:classifiers":[
        {
            "category":"Professional",
            "subcategory":"Management & Consulting",
            "type":"Services"
        }
    ],
    "sg:phone":"+1 574 848 9553",
    "sg:postcode":"46507",
    "sg:province":"IN",
    "sg:tags":[
        "telecommunication"
    ],
    "wof:name":"D&F Consulting Inc",
    "wof:placetype":"venue"
},
  "geometry": {"coordinates":[-85.867417,41.72273],"type":"Point"}
}