{
  "type": "Feature",
  "properties": {
    "iso:country":"US",
    "sg:address":"141 W Willow St",
    "sg:city":"Butler",
    "sg:classifiers":[
        {
            "category":"Government",
            "subcategory":"Office",
            "type":"Public Place"
        }
    ],
    "sg:phone":"+1 260 868 5023",
    "sg:postcode":"46721",
    "sg:province":"IN",
    "sg:tags":[
        "village"
    ],
    "wof:name":"Butler City Water Plant",
    "wof:placetype":"venue"
},
  "geometry": {"coordinates":[-84.872394,41.42632],"type":"Point"}
}