{
  "type": "Feature",
  "properties": {
    "iso:country":"US",
    "sg:address":"17 E Mill St",
    "sg:city":"New Palestine",
    "sg:classifiers":[
        {
            "category":"Wholesale",
            "subcategory":"Electrical",
            "type":"Manufacturing & Wholesale Goods"
        }
    ],
    "sg:phone":"+1 317 861 8839",
    "sg:postcode":"46163",
    "sg:province":"IN",
    "sg:tags":[
        "equipment",
        "testing",
        "electronic"
    ],
    "wof:name":"Bernd Associates Inc",
    "wof:placetype":"venue"
},
  "geometry": {"coordinates":[-85.888669,39.721992],"type":"Point"}
}