{
  "type": "Feature",
  "properties": {
    "iso:country":"US",
    "sg:address":"414 Douglas Ave",
    "sg:city":"Michigan City",
    "sg:classifiers":[
        {
            "category":"Retail",
            "subcategory":"Repair Shop",
            "type":"Services"
        }
    ],
    "sg:phone":"+1 219 874 7795",
    "sg:postcode":"46360",
    "sg:province":"IN",
    "sg:tags":[
        "welding"
    ],
    "wof:name":"Basic Machine and Welding Inc",
    "wof:placetype":"venue"
},
  "geometry": {"coordinates":[-86.916671,41.709082],"type":"Point"}
}