{
  "type": "Feature",
  "properties": {
    "iso:country":"US",
    "sg:address":"5119 Broadway",
    "sg:city":"Gary",
    "sg:classifiers":[
        {
            "category":"Cinema",
            "subcategory":"Movie Rental",
            "type":"Entertainment"
        }
    ],
    "sg:phone":"+1 219 884 8238",
    "sg:postcode":"46409",
    "sg:province":"IN",
    "sg:tags":[
        "leasing",
        "video",
        "disc",
        "tape"
    ],
    "wof:name":"Red Dragon",
    "wof:placetype":"venue"
},
  "geometry": {"coordinates":[-87.336119,41.524496],"type":"Point"}
}