{
  "type": "Feature",
  "properties": {
    "iso:country":"US",
    "sg:address":"6038 E 82nd St",
    "sg:city":"Indianapolis",
    "sg:classifiers":[
        {
            "category":"Shopping",
            "subcategory":"Computers & Home Electronics",
            "type":"Retail Goods"
        }
    ],
    "sg:phone":"+1 317 842 3888",
    "sg:postcode":"46250",
    "sg:province":"IN",
    "sg:tags":[
        "equipment",
        "dealer"
    ],
    "wof:name":"P C Club",
    "wof:placetype":"venue"
},
  "geometry": {"coordinates":[-86.063856,39.905353],"type":"Point"}
}