{
  "type": "Feature",
  "properties": {
    "iso:country":"US",
    "sg:address":"200 S Hobart Rd",
    "sg:city":"Hobart",
    "sg:classifiers":[
        {
            "category":"Social Services",
            "type":"Services"
        }
    ],
    "sg:phone":"+1 219 947 7779",
    "sg:postcode":"46342",
    "sg:province":"IN",
    "sg:tags":[
        "organization",
        "welfare"
    ],
    "wof:name":"Hobart Food Pantry Inc",
    "wof:placetype":"venue"
},
  "geometry": {"coordinates":[-87.23553699999999,41.53054],"type":"Point"}
}