{
  "type": "Feature",
  "properties": {
    "iso:country":"US",
    "sg:address":"1117 S 4th St",
    "sg:city":"Lafayette",
    "sg:classifiers":[
        {
            "category":"Social Services",
            "subcategory":"Child Care",
            "type":"Services"
        }
    ],
    "sg:phone":"+1 765 471 0339",
    "sg:postcode":"47905",
    "sg:province":"IN",
    "wof:name":"Char's Daycare",
    "wof:placetype":"venue"
},
  "geometry": {"coordinates":[-86.892902,40.40529],"type":"Point"}
}