{
  "type": "Feature",
  "properties": {
    "addr:full":"430 E Main St Greenwood IN 46143",
    "addr:housenumber":"430",
    "addr:postcode":"46143",
    "addr:street":"E Main St",
    "iso:country":"US",
    "sg:address":"430 E Main St",
    "sg:city":"Greenwood",
    "sg:classifiers":[
        {
            "category":"Manufacturing",
            "subcategory":"Tools & Machinery",
            "type":"Manufacturing & Wholesale Goods"
        }
    ],
    "sg:phone":"+1 317 881 9405",
    "sg:postcode":"46143",
    "sg:province":"IN",
    "sg:tags":[
        "machine",
        "shop"
    ],
    "wof:name":"Robertson Machine Co",
    "wof:placetype":"venue"
},
  "geometry": {"coordinates":[-86.09983800000001,39.613943],"type":"Point"}
}