{
  "type": "Feature",
  "properties": {
    "iso:country":"US",
    "sg:address":"640 Russell St",
    "sg:city":"West Lafayette",
    "sg:classifiers":[
        {
            "category":"Organizations",
            "subcategory":"Community Association",
            "type":"Services"
        }
    ],
    "sg:phone":"+1 765 743 1851",
    "sg:postcode":"47906",
    "sg:province":"IN",
    "sg:tags":[
        "sorority",
        "fraternity"
    ],
    "wof:name":"Phi Gamma Delta",
    "wof:placetype":"venue"
},
  "geometry": {"coordinates":[-86.919104,40.430947],"type":"Point"}
}