{
  "type": "Feature",
  "properties": {
    "iso:country":"US",
    "sg:address":"4907 W 1350 S",
    "sg:city":"Converse",
    "sg:classifiers":[
        {
            "category":"Personal",
            "subcategory":"Tanning Parlor",
            "type":"Services"
        }
    ],
    "sg:phone":"+1 765 628 2763",
    "sg:postcode":"46932",
    "sg:province":"IN",
    "sg:tags":[
        "salon"
    ],
    "wof:name":"Before The Beach",
    "wof:placetype":"venue"
},
  "geometry": {"coordinates":[-86.162802,40.569969],"type":"Point"}
}