{
  "type": "Feature",
  "properties": {
    "iso:country":"US",
    "sg:address":"6413 Constitution Dr",
    "sg:city":"Fort Wayne",
    "sg:classifiers":[
        {
            "category":"Personal",
            "subcategory":"Beauty Salon",
            "type":"Services"
        }
    ],
    "sg:phone":"+1 260 459 0098",
    "sg:postcode":"46804",
    "sg:province":"IN",
    "sg:tags":[
        "treatment",
        "skin"
    ],
    "wof:name":"Serenity Spa",
    "wof:placetype":"venue"
},
  "geometry": {"coordinates":[-85.224681,41.067952],"type":"Point"}
}