{
  "type": "Feature",
  "properties": {
    "iso:country":"US",
    "sg:address":"200 N Walnut St",
    "sg:city":"Edinburgh",
    "sg:classifiers":[
        {
            "category":"Education",
            "subcategory":"Dance Studio",
            "type":"Public Place"
        }
    ],
    "sg:phone":"+1 812 526 0285",
    "sg:postcode":"46124",
    "sg:province":"IN",
    "sg:tags":[
        "instruction",
        "dancing"
    ],
    "wof:name":"Dance Plus of Edinburgh",
    "wof:placetype":"venue"
},
  "geometry": {"coordinates":[-85.96664,39.35631],"type":"Point"}
}