{
  "type": "Feature",
  "properties": {
    "iso:country":"US",
    "sg:address":"11928 Westwind Dr",
    "sg:city":"Fort Wayne",
    "sg:classifiers":[
        {
            "category":"Real Estate",
            "subcategory":"Real Estate Agent",
            "type":"Services"
        }
    ],
    "sg:phone":"+1 260 637 8497",
    "sg:postcode":"46845",
    "sg:province":"IN",
    "sg:tags":[
        "management"
    ],
    "wof:name":"Mr G & Assoc",
    "wof:placetype":"venue"
},
  "geometry": {"coordinates":[-85.127367,41.194619],"type":"Point"}
}