{
  "type": "Feature",
  "properties": {
    "iso:country":"US",
    "sg:address":"118 N Main St",
    "sg:city":"Churubusco",
    "sg:classifiers":[
        {
            "category":"Food & Beverages",
            "subcategory":"Groceries & Convenience Stores",
            "type":"Retail Goods"
        }
    ],
    "sg:phone":"+1 260 693 3648",
    "sg:postcode":"46723",
    "sg:province":"IN",
    "wof:name":"Pride-C Stores Inc",
    "wof:placetype":"venue"
},
  "geometry": {"coordinates":[-85.319783,41.231283],"type":"Point"}
}