{
  "type": "Feature",
  "properties": {
    "addr:full":"423 S Dixie Way South Bend IN 46637",
    "addr:housenumber":"423",
    "addr:postcode":"46637",
    "addr:street":"S Dixie Way",
    "iso:country":"US",
    "sg:address":"423 S Dixie Way",
    "sg:city":"South Bend",
    "sg:classifiers":[
        {
            "category":"Bakery",
            "type":"Food & Drink"
        }
    ],
    "sg:menulink":"http://www.allmenus.com/in/georgetown/102280-perkins-restaurant--bakery/menu/",
    "sg:phone":"+1 574 272 0655",
    "sg:postcode":"46637",
    "sg:province":"IN",
    "sg:tags":[
        "sandwich",
        "salad",
        "soup",
        "american",
        "pastry",
        "wrap"
    ],
    "wof:name":"Perkins Restaurant & Bakery",
    "wof:placetype":"venue"
},
  "geometry": {"coordinates":[-86.250299,41.710529],"type":"Point"}
}