{
  "type": "Feature",
  "properties": {
    "iso:country":"US",
    "sg:address":"606 W 8th St",
    "sg:city":"Jasper",
    "sg:classifiers":[
        {
            "category":"Professional",
            "type":"Services"
        }
    ],
    "sg:phone":"+1 812 634 1048",
    "sg:postcode":"47546",
    "sg:province":"IN",
    "sg:tags":[
        "establishment"
    ],
    "wof:name":"Michelle Kersteins Independent",
    "wof:placetype":"venue"
},
  "geometry": {"coordinates":[-86.939021,38.393043],"type":"Point"}
}