{
  "type": "Feature",
  "properties": {
    "iso:country":"US",
    "sg:address":"2304 N Wayne St",
    "sg:city":"Angola",
    "sg:classifiers":[
        {
            "category":"Restaurant",
            "type":"Food & Drink"
        }
    ],
    "sg:menulink":"http://www.allmenus.com/in/angola/103601-ruby-tuesdays/menu/",
    "sg:phone":"+1 260 665 8791",
    "sg:postcode":"46703",
    "sg:province":"IN",
    "sg:tags":[
        "burger",
        "american"
    ],
    "wof:name":"Ruby Tuesdays",
    "wof:placetype":"venue"
},
  "geometry": {"coordinates":[-84.9996,41.661908],"type":"Point"}
}