{
  "type": "Feature",
  "properties": {
    "iso:country":"US",
    "sg:address":"3681 E Olean Rd",
    "sg:city":"Versailles",
    "sg:classifiers":[
        {
            "category":"Arts & Performance",
            "subcategory":"Theater",
            "type":"Entertainment"
        }
    ],
    "sg:phone":"+1 812 667 5571",
    "sg:postcode":"47042",
    "sg:province":"IN",
    "sg:tags":[
        "live",
        "music"
    ],
    "wof:name":"A To Z Music",
    "wof:placetype":"venue"
},
  "geometry": {"coordinates":[-85.171791,38.985193],"type":"Point"}
}