{
  "type": "Feature",
  "properties": {
    "iso:country":"US",
    "sg:address":"5325 Rogers Campground Rd SE",
    "sg:city":"Elizabeth",
    "sg:classifiers":[
        {
            "category":"Building & Trades",
            "subcategory":"Construction",
            "type":"Services"
        }
    ],
    "sg:phone":"+1 812 737 2375",
    "sg:postcode":"47117",
    "sg:province":"IN",
    "sg:tags":[
        "home",
        "builder"
    ],
    "wof:name":"Elliss Construction Inc",
    "wof:placetype":"venue"
},
  "geometry": {"coordinates":[-86.019355,38.102847],"type":"Point"}
}