{
  "type": "Feature",
  "properties": {
    "iso:country":"US",
    "sg:address":"2911 S Washington St",
    "sg:city":"Kokomo",
    "sg:classifiers":[
        {
            "category":"Personal",
            "subcategory":"Beauty Salon",
            "type":"Services"
        }
    ],
    "sg:phone":"+1 765 453 0743",
    "sg:postcode":"46902",
    "sg:province":"IN",
    "sg:tags":[
        "manicuring"
    ],
    "wof:name":"Star Nail",
    "wof:placetype":"venue"
},
  "geometry": {"coordinates":[-86.12832,40.452923],"type":"Point"}
}