{
  "type": "Feature",
  "properties": {
    "addr:full":"1476 E Hook Dr Terre Haute IN 47802",
    "addr:housenumber":"1476",
    "addr:postcode":"47802",
    "addr:street":"E Hook Dr",
    "iso:country":"US",
    "sg:address":"1476 E Hook Dr",
    "sg:city":"Terre Haute",
    "sg:classifiers":[
        {
            "category":"Professional",
            "subcategory":"Engineering",
            "type":"Services"
        }
    ],
    "sg:phone":"+1 812 299 4526",
    "sg:postcode":"47802",
    "sg:province":"IN",
    "sg:tags":[
        "vibration",
        "measurement"
    ],
    "wof:name":"EDS Inc",
    "wof:placetype":"venue"
},
  "geometry": {"coordinates":[-87.39706200000001,39.307548],"type":"Point"}
}