{
  "type": "Feature",
  "properties": {
    "addr:full":"3126 E Base Rd Greensburg IN 47240",
    "addr:housenumber":"3126",
    "addr:postcode":"47240",
    "addr:street":"E Base Rd",
    "iso:country":"US",
    "sg:address":"3126 E Base Rd",
    "sg:city":"Greensburg",
    "sg:classifiers":[
        {
            "category":"Travel",
            "subcategory":"Hotels & Motels",
            "type":"Entertainment"
        }
    ],
    "sg:phone":"+1 812 663 6607",
    "sg:postcode":"47240",
    "sg:province":"IN",
    "sg:tags":[
        "breakfast",
        "accommodation",
        "bed"
    ],
    "wof:name":"Nana's House Bed & Breakfast",
    "wof:placetype":"venue"
},
  "geometry": {"coordinates":[-85.41613099999999,39.337621],"type":"Point"}
}