{
  "type": "Feature",
  "properties": {
    "iso:country":"US",
    "sg:address":"6001 Southeastern Ave",
    "sg:city":"Indianapolis",
    "sg:classifiers":[
        {
            "category":"Retail",
            "subcategory":"Repair Shop",
            "type":"Services"
        }
    ],
    "sg:phone":"+1 317 357 2201",
    "sg:postcode":"46203",
    "sg:province":"IN",
    "sg:tags":[
        "television",
        "radio"
    ],
    "wof:name":"Charlie's TV & Appliances Sls",
    "wof:placetype":"venue"
},
  "geometry": {"coordinates":[-86.062063,39.733905],"type":"Point"}
}