{
  "type": "Feature",
  "properties": {
    "iso:country":"US",
    "sg:address":"9462 W State Rd 120",
    "sg:city":"Orland",
    "sg:classifiers":[
        {
            "category":"Government",
            "subcategory":"Post Office",
            "type":"Public Place"
        }
    ],
    "sg:phone":"+1 260 829 6435",
    "sg:postcode":"46776",
    "sg:province":"IN",
    "wof:name":"US Post Office",
    "wof:placetype":"venue"
},
  "geometry": {"coordinates":[-85.170627,41.73082],"type":"Point"}
}