{
  "type": "Feature",
  "properties": {
    "iso:country":"US",
    "sg:address":"519 E Markland Ave",
    "sg:city":"Kokomo",
    "sg:classifiers":[
        {
            "category":"Banks & Credit Unions",
            "subcategory":"Bank",
            "type":"Services"
        }
    ],
    "sg:phone":"+1 765 457 1161",
    "sg:postcode":"46901",
    "sg:province":"IN",
    "wof:name":"Security Federal Savings Bank",
    "wof:placetype":"venue"
},
  "geometry": {"coordinates":[-86.12651,40.476434],"type":"Point"}
}