{
  "type": "Feature",
  "properties": {
    "addr:full":"2500 S D St Elwood IN 46036",
    "addr:housenumber":"2500",
    "addr:postcode":"46036",
    "addr:street":"S D St",
    "iso:country":"US",
    "sg:address":"2500 S D St",
    "sg:city":"Elwood",
    "sg:classifiers":[
        {
            "category":"Autos & Motor Vehicles",
            "subcategory":"Auto Supplies",
            "type":"Retail Goods"
        }
    ],
    "sg:phone":"+1 765 552 2774",
    "sg:postcode":"46036",
    "sg:province":"IN",
    "sg:tags":[
        "tire"
    ],
    "wof:name":"Triple S Tire",
    "wof:placetype":"venue"
},
  "geometry": {"coordinates":[-85.82846499999999,40.273436],"type":"Point"}
}