{
  "type": "Feature",
  "properties": {
    "iso:country":"US",
    "sg:address":"23297 US Hwy 33",
    "sg:city":"Elkhart",
    "sg:classifiers":[
        {
            "category":"Autos & Motor Vehicles",
            "subcategory":"Automobile Sales",
            "type":"Retail Goods"
        }
    ],
    "sg:phone":"+1 574 875 7676",
    "sg:postcode":"46517",
    "sg:province":"IN",
    "sg:tags":[
        "car",
        "dealer"
    ],
    "wof:name":"Bob's Auto Ctr Inc",
    "wof:placetype":"venue"
},
  "geometry": {"coordinates":[-85.912715,41.630566],"type":"Point"}
}