{
  "type": "Feature",
  "properties": {
    "addr:full":"654 Magnolia Ct Danville IN 46122",
    "addr:housenumber":"654",
    "addr:postcode":"46122",
    "addr:street":"Magnolia Ct",
    "iso:country":"US",
    "sg:address":"654 Magnolia Ct",
    "sg:city":"Danville",
    "sg:classifiers":[
        {
            "category":"Building & Trades",
            "subcategory":"Construction",
            "type":"Services"
        }
    ],
    "sg:phone":"+1 317 745 2531",
    "sg:postcode":"46122",
    "sg:province":"IN",
    "sg:tags":[
        "general",
        "contractor"
    ],
    "wof:name":"D & G Homes",
    "wof:placetype":"venue"
},
  "geometry": {"coordinates":[-86.502861,39.769514],"type":"Point"}
}