{
  "type": "Feature",
  "properties": {
    "addr:full":"5900 National Rd E Richmond IN 47374",
    "addr:housenumber":"5900",
    "addr:postcode":"47374",
    "addr:street":"National Rd E",
    "iso:country":"US",
    "sg:address":"5900 National Rd E",
    "sg:city":"Richmond",
    "sg:classifiers":[
        {
            "category":"Retail",
            "subcategory":"Auto Rental",
            "type":"Services"
        }
    ],
    "sg:phone":"+1 765 935 4434",
    "sg:postcode":"47374",
    "sg:province":"IN",
    "sg:tags":[
        "renting",
        "truck",
        "leasing"
    ],
    "wof:name":"U-Haul Co",
    "wof:placetype":"venue"
},
  "geometry": {"coordinates":[-84.82050599999999,39.833092],"type":"Point"}
}