{
  "type": "Feature",
  "properties": {
    "iso:country":"US",
    "sg:address":"2631 Ryan Rd",
    "sg:city":"New Haven",
    "sg:classifiers":[
        {
            "category":"Farming",
            "subcategory":"Livestock Farm",
            "type":"Manufacturing & Wholesale Goods"
        }
    ],
    "sg:phone":"+1 260 493 1131",
    "sg:postcode":"46774",
    "sg:province":"IN",
    "sg:tags":[
        "raising",
        "cattle"
    ],
    "wof:name":"Roger Melcher",
    "wof:placetype":"venue"
},
  "geometry": {"coordinates":[-84.96188100000001,41.064642],"type":"Point"}
}