{
  "type": "Feature",
  "properties": {
    "iso:country":"US",
    "sg:address":"750 E Ohio St",
    "sg:city":"Jasonville",
    "sg:classifiers":[
        {
            "category":"Real Estate",
            "subcategory":"Real Estate Operator",
            "type":"Services"
        }
    ],
    "sg:phone":"+1 812 665 2430",
    "sg:postcode":"47438",
    "sg:province":"IN",
    "sg:tags":[
        "apartment"
    ],
    "wof:name":"Shakamak Good Samaritan Apts",
    "wof:placetype":"venue"
},
  "geometry": {"coordinates":[-87.190116,39.163837],"type":"Point"}
}