{
  "type": "Feature",
  "properties": {
    "iso:country":"US",
    "sg:address":"118 S Main St",
    "sg:city":"Milford",
    "sg:classifiers":[
        {
            "category":"Bars & Pubs",
            "type":"Food & Drink"
        }
    ],
    "sg:phone":"+1 574 658 4387",
    "sg:postcode":"46542",
    "sg:province":"IN",
    "wof:name":"Turf Bar",
    "wof:placetype":"venue"
},
  "geometry": {"coordinates":[-85.845933,41.409582],"type":"Point"}
}