{
  "type": "Feature",
  "properties": {
    "iso:country":"US",
    "sg:address":"3401 W 8th St",
    "sg:city":"Muncie",
    "sg:classifiers":[
        {
            "category":"Manufacturing",
            "subcategory":"Metals",
            "type":"Manufacturing & Wholesale Goods"
        }
    ],
    "sg:phone":"+1 765 288 1941",
    "sg:postcode":"47302",
    "sg:province":"IN",
    "sg:tags":[
        "stamping"
    ],
    "sg:website":"www.duffytool.com",
    "wof:name":"Duffy Tool & Stamping LLC",
    "wof:placetype":"venue"
},
  "geometry": {"coordinates":[-85.426579,40.181122],"type":"Point"}
}