{
  "type": "Feature",
  "properties": {
    "iso:country":"US",
    "sg:address":"1167 E Eisenhower Ave",
    "sg:city":"Jasper",
    "sg:classifiers":[
        {
            "category":"Insurance",
            "subcategory":"Insurance Agent",
            "type":"Services"
        }
    ],
    "sg:phone":"+1 812 482 6816",
    "sg:postcode":"47546",
    "sg:province":"IN",
    "wof:name":"Michael L Gates Insurance",
    "wof:placetype":"venue"
},
  "geometry": {"coordinates":[-86.91331,38.36955],"type":"Point"}
}