{
  "type": "Feature",
  "properties": {
    "iso:country":"US",
    "sg:address":"39 N Van Buren St",
    "sg:city":"Nashville",
    "sg:classifiers":[
        {
            "category":"Government",
            "subcategory":"Police Station",
            "type":"Public Place"
        }
    ],
    "sg:phone":"+1 812 988 6655",
    "sg:postcode":"47448",
    "sg:province":"IN",
    "sg:tags":[
        "sheriff"
    ],
    "wof:name":"Brown County Sheriff",
    "wof:placetype":"venue"
},
  "geometry": {"coordinates":[-86.24687,39.208126],"type":"Point"}
}