{
  "type": "Feature",
  "properties": {
    "iso:country":"US",
    "sg:address":"4232 Reas Ln",
    "sg:city":"New Albany",
    "sg:classifiers":[
        {
            "category":"Building & Trades",
            "subcategory":"Plumbing",
            "type":"Services"
        }
    ],
    "sg:phone":"+1 812 948 8828",
    "sg:postcode":"47150",
    "sg:province":"IN",
    "sg:tags":[
        "plumbing",
        "contractor"
    ],
    "wof:name":"Norton & Assoc Plumbing Inc",
    "wof:placetype":"venue"
},
  "geometry": {"coordinates":[-85.826723,38.344611],"type":"Point"}
}