{
  "type": "Feature",
  "properties": {
    "addr:full":"1205 E Fairwood Dr Bloomington IN 47408",
    "addr:housenumber":"1205",
    "addr:postcode":"47408",
    "addr:street":"E Fairwood Dr",
    "iso:country":"US",
    "sg:address":"1205 E Fairwood Dr",
    "sg:city":"Bloomington",
    "sg:classifiers":[
        {
            "category":"Building & Trades",
            "subcategory":"Cleaning & Sanitation",
            "type":"Services"
        }
    ],
    "sg:phone":"+1 812 336 0807",
    "sg:postcode":"47408",
    "sg:province":"IN",
    "sg:tags":[
        "carpet"
    ],
    "wof:name":"Esteemed Carpet Care",
    "wof:placetype":"venue"
},
  "geometry": {"coordinates":[-86.515474,39.221336],"type":"Point"}
}