{
  "type": "Feature",
  "properties": {
    "iso:country":"US",
    "sg:address":"528 Clark Rd",
    "sg:city":"Gary",
    "sg:classifiers":[
        {
            "category":"Organizations",
            "subcategory":"Religious Organization",
            "type":"Services"
        }
    ],
    "sg:phone":"+1 219 977 1657",
    "sg:postcode":"46406",
    "sg:province":"IN",
    "sg:tags":[
        "church"
    ],
    "wof:name":"House Of Prayer Faith In Jesus",
    "wof:placetype":"venue"
},
  "geometry": {"coordinates":[-87.393823,41.601082],"type":"Point"}
}