{
  "type": "Feature",
  "properties": {
    "iso:country":"US",
    "sg:address":"7999 Knue Rd",
    "sg:city":"Indianapolis",
    "sg:classifiers":[
        {
            "category":"Manufacturing",
            "subcategory":"Printing",
            "type":"Manufacturing & Wholesale Goods"
        }
    ],
    "sg:phone":"+1 317 955 9300",
    "sg:postcode":"46250",
    "sg:province":"IN",
    "sg:tags":[
        "multimedia"
    ],
    "wof:name":"Desktop Media Inc",
    "wof:placetype":"venue"
},
  "geometry": {"coordinates":[-86.060177,39.90031],"type":"Point"}
}