{
  "type": "Feature",
  "properties": {
    "iso:country":"US",
    "sg:address":"5137 W State Rd 54",
    "sg:city":"Sullivan",
    "sg:classifiers":[
        {
            "category":"Shopping",
            "subcategory":"Bicycles & Sporting Goods",
            "type":"Retail Goods"
        }
    ],
    "sg:phone":"+1 812 356 4743",
    "sg:postcode":"47882",
    "sg:province":"IN",
    "sg:tags":[
        "bait",
        "fishing"
    ],
    "wof:name":"Molly's Bait Shop",
    "wof:placetype":"venue"
},
  "geometry": {"coordinates":[-87.489267,39.055601],"type":"Point"}
}