{
  "type": "Feature",
  "properties": {
    "iso:country":"US",
    "sg:address":"1400 S Jefferson St",
    "sg:city":"Huntington",
    "sg:classifiers":[
        {
            "category":"Autos & Motor Vehicles",
            "subcategory":"Auto Supplies",
            "type":"Retail Goods"
        }
    ],
    "sg:phone":"+1 260 356 5400",
    "sg:postcode":"46750",
    "sg:province":"IN",
    "sg:tags":[
        "tire"
    ],
    "wof:name":"Wertenberger Tire Co",
    "wof:placetype":"venue"
},
  "geometry": {"coordinates":[-85.482131,40.869916],"type":"Point"}
}