{
  "type": "Feature",
  "properties": {
    "iso:country":"US",
    "sg:address":"210 E Broadway St",
    "sg:city":"Fortville",
    "sg:classifiers":[
        {
            "category":"Wholesale",
            "subcategory":"Construction Materials",
            "type":"Manufacturing & Wholesale Goods"
        }
    ],
    "sg:phone":"+1 317 485 4810",
    "sg:postcode":"46040",
    "sg:province":"IN",
    "sg:tags":[
        "marble"
    ],
    "wof:name":"Mr Marble Care TH Marble",
    "wof:placetype":"venue"
},
  "geometry": {"coordinates":[-85.846688,39.932006],"type":"Point"}
}