{
  "type": "Feature",
  "properties": {
    "iso:country":"US",
    "sg:address":"407 Center St",
    "sg:city":"Valparaiso",
    "sg:classifiers":[
        {
            "category":"Manufacturing",
            "subcategory":"Food",
            "type":"Manufacturing & Wholesale Goods"
        }
    ],
    "sg:phone":"+1 219 241 5674",
    "sg:postcode":"46385",
    "sg:province":"IN",
    "sg:tags":[
        "packaging",
        "beverage",
        "contract"
    ],
    "wof:name":"Xetex Bottling Group",
    "wof:placetype":"venue"
},
  "geometry": {"coordinates":[-87.072065,41.472257],"type":"Point"}
}