{
  "type": "Feature",
  "properties": {
    "iso:country":"US",
    "sg:address":"5519 S Western Ave",
    "sg:city":"Marion",
    "sg:classifiers":[
        {
            "category":"Organizations",
            "subcategory":"Non-profit Organization",
            "type":"Services"
        }
    ],
    "sg:phone":"+1 765 674 1555",
    "sg:postcode":"46953",
    "sg:province":"IN",
    "sg:tags":[
        "human"
    ],
    "wof:name":"AWS Postmasters",
    "wof:placetype":"venue"
},
  "geometry": {"coordinates":[-85.67063899999999,40.503125],"type":"Point"}
}