{
  "type": "Feature",
  "properties": {
    "iso:country":"US",
    "sg:address":"9035 E Division Rd",
    "sg:city":"Knox",
    "sg:classifiers":[
        {
            "category":"Education",
            "subcategory":"School",
            "type":"Public Place"
        }
    ],
    "sg:phone":"+1 574 772 0787",
    "sg:postcode":"46534",
    "sg:province":"IN",
    "sg:tags":[
        "academic",
        "special"
    ],
    "wof:name":"Save Program",
    "wof:placetype":"venue"
},
  "geometry": {"coordinates":[-86.523721,41.302406],"type":"Point"}
}