{
  "type": "Feature",
  "properties": {
    "addr:full":"1579 N Morton St Franklin IN 46131",
    "addr:housenumber":"1579",
    "addr:postcode":"46131",
    "addr:street":"N Morton St",
    "iso:country":"US",
    "sg:address":"1579 N Morton St",
    "sg:city":"Franklin",
    "sg:classifiers":[
        {
            "category":"Fast Food",
            "type":"Food & Drink"
        },
        {
            "category":"Restaurant",
            "type":"Food & Drink"
        }
    ],
    "sg:phone":"+1 317 736 6007",
    "sg:postcode":"46131",
    "sg:province":"IN",
    "sg:tags":[
        "mexican"
    ],
    "sg:website":"http://www.tacobell.com",
    "wof:name":"Taco Bell",
    "wof:placetype":"venue"
},
  "geometry": {"coordinates":[-86.061905,39.474005],"type":"Point"}
}