{
  "type": "Feature",
  "properties": {
    "iso:country":"US",
    "sg:address":"6030 Shiloh Rd",
    "sg:city":"Tell City",
    "sg:classifiers":[
        {
            "category":"Government",
            "subcategory":"Office",
            "type":"Public Place"
        }
    ],
    "sg:phone":"+1 812 836 4453",
    "sg:postcode":"47586",
    "sg:province":"IN",
    "sg:tags":[
        "village"
    ],
    "wof:name":"Troy Twp Trustee",
    "wof:placetype":"venue"
},
  "geometry": {"coordinates":[-86.69169599999999,37.993413],"type":"Point"}
}