{
  "type": "Feature",
  "properties": {
    "iso:country":"US",
    "sg:address":"484 W Plaza Dr",
    "sg:city":"Columbia City",
    "sg:classifiers":[
        {
            "category":"Professional",
            "subcategory":"Accounting & Tax Preparation",
            "type":"Services"
        }
    ],
    "sg:phone":"+1 260 244 6723",
    "sg:postcode":"46725",
    "sg:province":"IN",
    "sg:tags":[
        "return",
        "filing"
    ],
    "wof:name":"Jackson Hewitt Tax Svc",
    "wof:placetype":"venue"
},
  "geometry": {"coordinates":[-85.491829,41.170139],"type":"Point"}
}