{
  "type": "Feature",
  "properties": {
    "iso:country":"US",
    "sg:address":"1200 Clifty Dr",
    "sg:city":"Madison",
    "sg:classifiers":[
        {
            "category":"Manufacturing",
            "subcategory":"Metals",
            "type":"Manufacturing & Wholesale Goods"
        }
    ],
    "sg:phone":"+1 812 273 1121",
    "sg:postcode":"47250",
    "sg:province":"IN",
    "sg:tags":[
        "fabricated",
        "structural"
    ],
    "wof:name":"Armor Metal Fabricating Inc",
    "wof:placetype":"venue"
},
  "geometry": {"coordinates":[-85.411961,38.772663],"type":"Point"}
}