{
  "type": "Feature",
  "properties": {
    "iso:country":"US",
    "sg:address":"5920 S East St",
    "sg:city":"Indianapolis",
    "sg:classifiers":[
        {
            "category":"Manufacturing",
            "subcategory":"Musical Instruments",
            "type":"Manufacturing & Wholesale Goods"
        }
    ],
    "sg:phone":"+1 317 784 3012",
    "sg:postcode":"46227",
    "sg:province":"IN",
    "sg:website":"www.straubingerflutes.net",
    "wof:name":"Straubinger Flutes",
    "wof:placetype":"venue"
},
  "geometry": {"coordinates":[-86.149067,39.680225],"type":"Point"}
}