{
  "type": "Feature",
  "properties": {
    "addr:full":"12603 Southeastern Ave Indianapolis IN 46259",
    "addr:housenumber":"12603",
    "addr:postcode":"46259",
    "addr:street":"Southeastern Ave",
    "iso:country":"US",
    "sg:address":"12603 Southeastern Ave",
    "sg:city":"Indianapolis",
    "sg:classifiers":[
        {
            "category":"Shopping",
            "subcategory":"Clothing, Apparel, & Fashions",
            "type":"Retail Goods"
        }
    ],
    "sg:phone":"+1 317 862 3070",
    "sg:postcode":"46259",
    "sg:province":"IN",
    "sg:tags":[
        "riding",
        "equipment"
    ],
    "sg:website":"www.goldenroyal.com",
    "wof:name":"Golden Royal Saddlery Inc",
    "wof:placetype":"venue"
},
  "geometry": {"coordinates":[-85.942381,39.663757],"type":"Point"}
}