{
  "type": "Feature",
  "properties": {
    "iso:country":"US",
    "sg:address":"197 W State St",
    "sg:city":"East Brunswick",
    "sg:classifiers":[
        {
            "category":"Shopping",
            "subcategory":"Computers & Home Electronics",
            "type":"Retail Goods"
        }
    ],
    "sg:phone":"+1 732 846 4271",
    "sg:postcode":"47834",
    "sg:province":"IN",
    "sg:tags":[
        "equipment",
        "electronic",
        "supply"
    ],
    "sg:website":"www.alliedelec.com",
    "wof:name":"Allied Electronics",
    "wof:placetype":"venue"
},
  "geometry": {"coordinates":[-87.129763,39.523863],"type":"Point"}
}