{
  "type": "Feature",
  "properties": {
    "iso:country":"US",
    "sg:address":"2364 E Old Terre Haute Rd",
    "sg:city":"Vincennes",
    "sg:classifiers":[
        {
            "category":"Building & Trades",
            "subcategory":"Construction",
            "type":"Services"
        }
    ],
    "sg:phone":"+1 812 882 6011",
    "sg:postcode":"47591",
    "sg:province":"IN",
    "sg:tags":[
        "roofing",
        "installation",
        "windows-repair",
        "contractor",
        "replacement"
    ],
    "wof:name":"Stuckman Larry",
    "wof:placetype":"venue"
},
  "geometry": {"coordinates":[-87.507142,38.698541],"type":"Point"}
}