{
  "type": "Feature",
  "properties": {
    "iso:country":"US",
    "sg:address":"7771 W State Route 66",
    "sg:city":"Newburgh",
    "sg:classifiers":[
        {
            "category":"Shopping",
            "subcategory":"Jewelry",
            "type":"Retail Goods"
        },
        {
            "category":"Shopping",
            "subcategory":"Pawn Shop",
            "type":"Retail Goods"
        }
    ],
    "sg:phone":"+1 812 401 4367",
    "sg:postcode":"47630",
    "sg:province":"IN",
    "wof:name":"Master Jeweler Designs",
    "wof:placetype":"venue"
},
  "geometry": {"coordinates":[-87.393452,37.976373],"type":"Point"}
}