{
  "type": "Feature",
  "properties": {
    "iso:country":"US",
    "sg:address":"7323 State Rd 62",
    "sg:city":"Dale",
    "sg:classifiers":[
        {
            "category":"Retail",
            "subcategory":"Auto Repair",
            "type":"Services"
        }
    ],
    "sg:phone":"+1 812 937 2412",
    "sg:postcode":"47523",
    "sg:province":"IN",
    "sg:tags":[
        "repairing",
        "automobile"
    ],
    "wof:name":"D D Svc & Repair",
    "wof:placetype":"venue"
},
  "geometry": {"coordinates":[-86.92335,38.167018],"type":"Point"}
}