{
  "type": "Feature",
  "properties": {
    "iso:country":"US",
    "sg:address":"10450 College Ave N",
    "sg:city":"Indianapolis",
    "sg:classifiers":[
        {
            "category":"Food & Beverages",
            "subcategory":"Groceries & Convenience Stores",
            "type":"Retail Goods"
        }
    ],
    "sg:phone":"+1 317 846 3465",
    "sg:postcode":"46280",
    "sg:province":"IN",
    "sg:tags":[
        "grocer"
    ],
    "wof:name":"O'Malia Food Market",
    "wof:placetype":"venue"
},
  "geometry": {"coordinates":[-86.146004,39.93911],"type":"Point"}
}