{
  "type": "Feature",
  "properties": {
    "iso:country":"US",
    "sg:address":"1008 E Main St",
    "sg:city":"Brownsburg",
    "sg:classifiers":[
        {
            "category":"Restaurant",
            "type":"Food & Drink"
        }
    ],
    "sg:phone":"+1 317 858 3101",
    "sg:postcode":"46112",
    "sg:province":"IN",
    "sg:tags":[
        "eating"
    ],
    "wof:name":"El Toro Cantina",
    "wof:placetype":"venue"
},
  "geometry": {"coordinates":[-86.38163,39.83723],"type":"Point"}
}