{
  "type": "Feature",
  "properties": {
    "iso:country":"US",
    "sg:address":"13535 Cumberland Rd",
    "sg:city":"Fishers",
    "sg:classifiers":[
        {
            "category":"Education",
            "subcategory":"School",
            "type":"Public Place"
        }
    ],
    "sg:phone":"+1 317 594 4170",
    "sg:postcode":"46038",
    "sg:province":"IN",
    "sg:website":"www.hse.k12.in.us",
    "wof:name":"Cumberland Road Elementary",
    "wof:placetype":"venue"
},
  "geometry": {"coordinates":[-85.994207,39.983964],"type":"Point"}
}