{
  "type": "Feature",
  "properties": {
    "iso:country":"US",
    "sg:address":"600 S Cullen Ave",
    "sg:city":"Evansville",
    "sg:classifiers":[
        {
            "category":"Real Estate",
            "subcategory":"Real Estate Operator",
            "type":"Services"
        }
    ],
    "sg:phone":"+1 812 479 3341",
    "sg:postcode":"47715",
    "sg:province":"IN",
    "sg:tags":[
        "condominium"
    ],
    "wof:name":"Belle Manor Owners Assn",
    "wof:placetype":"venue"
},
  "geometry": {"coordinates":[-87.486898,37.967909],"type":"Point"}
}