{
  "type": "Feature",
  "properties": {
    "iso:country":"US",
    "sg:address":"702 Ridgeway St",
    "sg:city":"La Porte",
    "sg:classifiers":[
        {
            "category":"Manufacturing",
            "subcategory":"Metals",
            "type":"Manufacturing & Wholesale Goods"
        }
    ],
    "sg:phone":"+1 219 362 2863",
    "sg:postcode":"46350",
    "sg:province":"IN",
    "wof:name":"Dreskes Silver Plating",
    "wof:placetype":"venue"
},
  "geometry": {"coordinates":[-86.703741,41.618216],"type":"Point"}
}