{
  "type": "Feature",
  "properties": {
    "iso:country":"US",
    "sg:address":"7250 Clearvista Dr",
    "sg:city":"Indianapolis",
    "sg:classifiers":[
        {
            "category":"Health Services",
            "subcategory":"Doctor",
            "type":"Services"
        }
    ],
    "sg:phone":"+1 317 621 2211",
    "sg:postcode":"46256",
    "sg:province":"IN",
    "sg:tags":[
        "physician",
        "surgeon"
    ],
    "wof:name":"Matthew Davis MD",
    "wof:placetype":"venue"
},
  "geometry": {"coordinates":[-86.040791,39.899702],"type":"Point"}
}