{
  "type": "Feature",
  "properties": {
    "iso:country":"US",
    "sg:address":"21888 Beck Dr",
    "sg:city":"Elkhart",
    "sg:classifiers":[
        {
            "category":"Home & Garden",
            "subcategory":"Building Materials",
            "type":"Retail Goods"
        }
    ],
    "sg:phone":"+1 574 389 1129",
    "sg:postcode":"46516",
    "sg:province":"IN",
    "sg:tags":[
        "paint"
    ],
    "wof:name":"CLI Paint",
    "wof:placetype":"venue"
},
  "geometry": {"coordinates":[-85.885809,41.693771],"type":"Point"}
}