{
  "type": "Feature",
  "properties": {
    "iso:country":"US",
    "sg:address":"1901 Plantation Ct",
    "sg:city":"Evansville",
    "sg:classifiers":[
        {
            "category":"Real Estate",
            "subcategory":"Real Estate Operator",
            "type":"Services"
        }
    ],
    "sg:phone":"+1 812 477 8432",
    "sg:postcode":"47714",
    "sg:province":"IN",
    "sg:tags":[
        "apartment"
    ],
    "wof:name":"Maplewood Properties",
    "wof:placetype":"venue"
},
  "geometry": {"coordinates":[-87.530996,37.949586],"type":"Point"}
}