{
  "type": "Feature",
  "properties": {
    "iso:country":"US",
    "sg:address":"425 E Hawthorne St",
    "sg:city":"Fort Wayne",
    "sg:classifiers":[
        {
            "category":"Freight",
            "type":"Transportation"
        }
    ],
    "sg:phone":"+1 260 747 0748",
    "sg:postcode":"46806",
    "sg:province":"IN",
    "sg:tags":[
        "delivery"
    ],
    "wof:name":"Johnny On The Spot",
    "wof:placetype":"venue"
},
  "geometry": {"coordinates":[-85.130557,41.033289],"type":"Point"}
}