{
  "type": "Feature",
  "properties": {
    "iso:country":"US",
    "sg:address":"563 S Gilbert St",
    "sg:city":"Clinton",
    "sg:classifiers":[
        {
            "category":"Wholesale",
            "subcategory":"Stationery",
            "type":"Manufacturing & Wholesale Goods"
        }
    ],
    "sg:phone":"+1 765 832 2758",
    "sg:postcode":"47842",
    "sg:province":"IN",
    "sg:tags":[
        "paper"
    ],
    "wof:name":"Lungers Designs",
    "wof:placetype":"venue"
},
  "geometry": {"coordinates":[-87.416041,39.677675],"type":"Point"}
}