{
  "type": "Feature",
  "properties": {
    "addr:full":"6650 Nautical Dr Portage IN 46368",
    "addr:housenumber":"6650",
    "addr:postcode":"46368",
    "addr:street":"Nautical Dr",
    "iso:country":"US",
    "sg:address":"6650 Nautical Dr",
    "sg:city":"Portage",
    "sg:classifiers":[
        {
            "category":"Manufacturing",
            "subcategory":"Metals",
            "type":"Manufacturing & Wholesale Goods"
        }
    ],
    "sg:phone":"+1 219 787 8889",
    "sg:postcode":"46368",
    "sg:province":"IN",
    "sg:tags":[
        "steel",
        "processing"
    ],
    "wof:name":"Indiana Pickling & Processing",
    "wof:placetype":"venue"
},
  "geometry": {"coordinates":[-87.155913,41.630704],"type":"Point"}
}