{
  "type": "Feature",
  "properties": {
    "iso:country":"US",
    "sg:address":"13461 Clifty Falls Dr",
    "sg:city":"Carmel",
    "sg:classifiers":[
        {
            "category":"Sports & Exercise",
            "subcategory":"Gym",
            "type":"Entertainment"
        }
    ],
    "sg:phone":"+1 317 575 6400",
    "sg:postcode":"46032",
    "sg:province":"IN",
    "sg:tags":[
        "trainer"
    ],
    "wof:name":"Promotion Training Systems",
    "wof:placetype":"venue"
},
  "geometry": {"coordinates":[-86.15838100000001,39.983002],"type":"Point"}
}