{
  "type": "Feature",
  "properties": {
    "iso:country":"US",
    "sg:address":"1200 N Nappanee St",
    "sg:city":"Elkhart",
    "sg:classifiers":[
        {
            "category":"Banks & Credit Unions",
            "subcategory":"Bank",
            "type":"Services"
        }
    ],
    "sg:phone":"+1 574 262 8413",
    "sg:postcode":"46514",
    "sg:province":"IN",
    "wof:name":"National City Bank",
    "wof:placetype":"venue"
},
  "geometry": {"coordinates":[-86.002905,41.700649],"type":"Point"}
}