{
  "type": "Feature",
  "properties": {
    "iso:country":"US",
    "sg:address":"917 N 13th St",
    "sg:city":"Terre Haute",
    "sg:classifiers":[
        {
            "category":"Personal",
            "subcategory":"Barber",
            "type":"Services"
        }
    ],
    "sg:phone":"+1 812 235 7434",
    "sg:postcode":"47807",
    "sg:province":"IN",
    "wof:name":"Jeff's Family Hair Care Ctr",
    "wof:placetype":"venue"
},
  "geometry": {"coordinates":[-87.397683,39.478315],"type":"Point"}
}