{
  "type": "Feature",
  "properties": {
    "iso:country":"US",
    "sg:address":"3024 N Pennsylvania St",
    "sg:city":"Indianapolis",
    "sg:classifiers":[
        {
            "category":"Real Estate",
            "subcategory":"Real Estate Operator",
            "type":"Services"
        }
    ],
    "sg:phone":"+1 317 283 7827",
    "sg:postcode":"46205",
    "sg:province":"IN",
    "sg:tags":[
        "apartment"
    ],
    "wof:name":"Lodestar Properties",
    "wof:placetype":"venue"
},
  "geometry": {"coordinates":[-86.15554899999999,39.810427],"type":"Point"}
}