{
  "type": "Feature",
  "properties": {
    "iso:country":"US",
    "sg:address":"502 W Western Ave",
    "sg:city":"South Bend",
    "sg:classifiers":[
        {
            "category":"Home & Garden",
            "subcategory":"Building Materials",
            "type":"Retail Goods"
        }
    ],
    "sg:phone":"+1 574 232 4770",
    "sg:postcode":"46601",
    "sg:province":"IN",
    "sg:tags":[
        "glass",
        "window",
        "plate"
    ],
    "wof:name":"Harmon Auto Glass",
    "wof:placetype":"venue"
},
  "geometry": {"coordinates":[-86.256549,41.672181],"type":"Point"}
}