{
  "type": "Feature",
  "properties": {
    "iso:country":"US",
    "sg:address":"8807 Indianapolis Blvd",
    "sg:city":"Highland",
    "sg:classifiers":[
        {
            "category":"Banks & Credit Unions",
            "subcategory":"Bank",
            "type":"Services"
        }
    ],
    "sg:phone":"+1 219 922 9413",
    "sg:postcode":"46322",
    "sg:province":"IN",
    "sg:tags":[
        "financing"
    ],
    "wof:name":"Home Owners Security Corp",
    "wof:placetype":"venue"
},
  "geometry": {"coordinates":[-87.470256,41.460498],"type":"Point"}
}