{
  "type": "Feature",
  "properties": {
    "addr:full":"1555 N Green River Rd Evansville IN 47715",
    "addr:housenumber":"1555",
    "addr:postcode":"47715",
    "addr:street":"N Green River Rd",
    "iso:country":"US",
    "sg:address":"1555 N Green River Rd",
    "sg:city":"Evansville",
    "sg:classifiers":[
        {
            "category":"Communications",
            "subcategory":"News Services",
            "type":"Services"
        },
        {
            "category":"Transit Center",
            "subcategory":"Freight",
            "type":"Transportation"
        },
        {
            "category":"Professional",
            "subcategory":"Business Services",
            "type":"Services"
        },
        {
            "category":"Professional",
            "subcategory":"Printing & Photocopies",
            "type":"Services"
        }
    ],
    "sg:phone":"+1 812 471 4001",
    "sg:postcode":"47715",
    "sg:province":"IN",
    "sg:tags":[
        "cargo",
        "fax",
        "transparency",
        "package",
        "color",
        "express",
        "duplicating",
        "shipping",
        "air",
        "copying",
        "print",
        "mail",
        "photographic"
    ],
    "sg:website":"http://www.kinkos.com",
    "wof:name":"Fedex Kinko's",
    "wof:placetype":"venue"
},
  "geometry": {"coordinates":[-87.492592,37.990722],"type":"Point"}
}