{
  "type": "Feature",
  "properties": {
    "addr:full":"7002 Graham Rd Indianapolis IN 46220",
    "addr:housenumber":"7002",
    "addr:postcode":"46220",
    "addr:street":"Graham Rd",
    "iso:country":"US",
    "sg:address":"7002 Graham Rd",
    "sg:city":"Indianapolis",
    "sg:classifiers":[
        {
            "category":"Social Services",
            "type":"Services"
        },
        {
            "category":"Personal",
            "subcategory":"Adult",
            "type":"Services"
        }
    ],
    "sg:phone":"+1 317 842 8881",
    "sg:postcode":"46220",
    "sg:province":"IN",
    "sg:tags":[
        "marriage",
        "therapist",
        "coaching-business",
        "family"
    ],
    "sg:website":"http://www.CrossRoadsINDY.com",
    "wof:name":"Benton R Ruth Dr",
    "wof:placetype":"venue"
},
  "geometry": {"coordinates":[-86.069733,39.882],"type":"Point"}
}