{
  "type": "Feature",
  "properties": {
    "iso:country":"US",
    "sg:address":"9809 E 42nd St",
    "sg:city":"Indianapolis",
    "sg:classifiers":[
        {
            "category":"Organizations",
            "subcategory":"Religious Organization",
            "type":"Services"
        }
    ],
    "sg:phone":"+1 317 899 4992",
    "sg:postcode":"46235",
    "sg:province":"IN",
    "sg:tags":[
        "church"
    ],
    "wof:name":"Fountain Of Truth Christian",
    "wof:placetype":"venue"
},
  "geometry": {"coordinates":[-85.99389499999999,39.833533],"type":"Point"}
}