{
  "type": "Feature",
  "properties": {
    "iso:country":"US",
    "sg:address":"3901 N Highland Rd",
    "sg:city":"Salem",
    "sg:classifiers":[
        {
            "category":"Building & Trades",
            "subcategory":"Landscaping Services",
            "type":"Services"
        }
    ],
    "sg:phone":"+1 812 883 1170",
    "sg:postcode":"47167",
    "sg:province":"IN",
    "sg:tags":[
        "mowing"
    ],
    "wof:name":"Alexander Lawn Svc",
    "wof:placetype":"venue"
},
  "geometry": {"coordinates":[-86.145431,38.661933],"type":"Point"}
}