{
  "type": "Feature",
  "properties": {
    "iso:country":"US",
    "sg:address":"10849 Windermere Blvd",
    "sg:city":"Fishers",
    "sg:classifiers":[
        {
            "category":"Professional",
            "subcategory":"Engineering",
            "type":"Services"
        }
    ],
    "sg:phone":"+1 317 585 0779",
    "sg:postcode":"46037",
    "sg:province":"IN",
    "sg:tags":[
        "electrical",
        "electronic",
        "engineer"
    ],
    "wof:name":"Us Technoengineering",
    "wof:placetype":"venue"
},
  "geometry": {"coordinates":[-85.97559,39.934544],"type":"Point"}
}