{
  "type": "Feature",
  "properties": {
    "addr:full":"827 Lincolnway E Goshen IN 46526",
    "addr:housenumber":"827;e",
    "addr:postcode":"46526",
    "addr:street":"Lincolnway",
    "iso:country":"US",
    "sg:address":"827 Lincolnway E",
    "sg:city":"Goshen",
    "sg:classifiers":[
        {
            "category":"Restaurant",
            "type":"Food & Drink"
        }
    ],
    "sg:phone":"+1 574 533 1523",
    "sg:postcode":"46526",
    "sg:province":"IN",
    "wof:name":"Double D Inc",
    "wof:placetype":"venue"
},
  "geometry": {"coordinates":[-85.818759,41.578331],"type":"Point"}
}