{
  "type": "Feature",
  "properties": {
    "iso:country":"US",
    "sg:address":"14578 State Rd 4",
    "sg:city":"Goshen",
    "sg:classifiers":[
        {
            "category":"Shopping",
            "subcategory":"Gifts & Souvenirs",
            "type":"Retail Goods"
        }
    ],
    "sg:phone":"+1 574 537 0835",
    "sg:postcode":"46528",
    "sg:province":"IN",
    "wof:name":"Intrigue",
    "wof:placetype":"venue"
},
  "geometry": {"coordinates":[-85.740248,41.600346],"type":"Point"}
}