{
  "type": "Feature",
  "properties": {
    "iso:country":"US",
    "sg:address":"391 Carmelaire Ct",
    "sg:city":"Carmel",
    "sg:classifiers":[
        {
            "category":"Building & Trades",
            "subcategory":"Locksmith",
            "type":"Services"
        }
    ],
    "sg:phone":"+1 317 682 9090",
    "sg:postcode":"46032",
    "sg:province":"IN",
    "sg:tags":[
        "key"
    ],
    "wof:name":"Best Locksmith",
    "wof:placetype":"venue"
},
  "geometry": {"coordinates":[-86.122741,39.97281],"type":"Point"}
}