{
  "type": "Feature",
  "properties": {
    "iso:country":"US",
    "sg:address":"538 Wood St",
    "sg:city":"Kendallville",
    "sg:classifiers":[
        {
            "category":"Home & Garden",
            "subcategory":"Building Materials",
            "type":"Retail Goods"
        }
    ],
    "sg:phone":"+1 260 347 1157",
    "sg:postcode":"46755",
    "sg:province":"IN",
    "sg:tags":[
        "windows"
    ],
    "wof:name":"Northern Exteriors",
    "wof:placetype":"venue"
},
  "geometry": {"coordinates":[-85.257989,41.448832],"type":"Point"}
}