{
  "type": "Feature",
  "properties": {
    "addr:full":"2819 Hammond Ave Elkhart IN 46516",
    "addr:housenumber":"2819",
    "addr:postcode":"46516",
    "addr:street":"Hammond Ave",
    "iso:country":"US",
    "sg:address":"2819 Hammond Ave",
    "sg:city":"Elkhart",
    "sg:classifiers":[
        {
            "category":"Freight",
            "type":"Transportation"
        }
    ],
    "sg:phone":"+1 574 522 5250",
    "sg:postcode":"46516",
    "sg:province":"IN",
    "sg:tags":[
        "hauling",
        "trucking"
    ],
    "wof:name":"RDL Enterprises",
    "wof:placetype":"venue"
},
  "geometry": {"coordinates":[-85.943878,41.657871],"type":"Point"}
}