{
  "type": "Feature",
  "properties": {
    "iso:country":"US",
    "sg:address":"1609 E Greyhound Pass",
    "sg:city":"Carmel",
    "sg:classifiers":[
        {
            "category":"Social Services",
            "subcategory":"Child Care",
            "type":"Services"
        }
    ],
    "sg:phone":"+1 317 848 3580",
    "sg:postcode":"46032",
    "sg:province":"IN",
    "wof:name":"Little Lamb",
    "wof:placetype":"venue"
},
  "geometry": {"coordinates":[-86.129453,40.004725],"type":"Point"}
}