{
  "type": "Feature",
  "properties": {
    "iso:country":"US",
    "sg:address":"1408 E Chicago Ave",
    "sg:city":"East Chicago",
    "sg:classifiers":[
        {
            "category":"Professional",
            "subcategory":"Accounting & Tax Preparation",
            "type":"Services"
        }
    ],
    "sg:phone":"+1 219 397 1040",
    "sg:postcode":"46312",
    "sg:province":"IN",
    "sg:tags":[
        "return",
        "filing"
    ],
    "wof:name":"Computer Tax",
    "wof:placetype":"venue"
},
  "geometry": {"coordinates":[-87.453306,41.629205],"type":"Point"}
}