{
  "type": "Feature",
  "properties": {
    "iso:country":"US",
    "sg:address":"348 Orland Overlook",
    "sg:city":"Westfield",
    "sg:classifiers":[
        {
            "category":"Professional",
            "type":"Services"
        }
    ],
    "sg:phone":"+1 317 846 4059",
    "sg:postcode":"46074",
    "sg:province":"IN",
    "wof:name":"Martha Burrows Inc",
    "wof:placetype":"venue"
},
  "geometry": {"coordinates":[-86.162595,40.026958],"type":"Point"}
}