{
  "type": "Feature",
  "properties": {
    "iso:country":"US",
    "sg:address":"2910 Calumet Ave",
    "sg:city":"Valparaiso",
    "sg:classifiers":[
        {
            "category":"Restaurant",
            "type":"Food & Drink"
        }
    ],
    "sg:phone":"+1 219 548 9262",
    "sg:postcode":"46383",
    "sg:province":"IN",
    "wof:name":"WANA Pizza",
    "wof:placetype":"venue"
},
  "geometry": {"coordinates":[-87.044501,41.495909],"type":"Point"}
}