{
  "type": "Feature",
  "properties": {
    "iso:country":"US",
    "sg:address":"8831 W Mallory Rd",
    "sg:city":"Bloomington",
    "sg:classifiers":[
        {
            "category":"Building & Trades",
            "subcategory":"Construction",
            "type":"Services"
        }
    ],
    "sg:phone":"+1 812 876 1023",
    "sg:postcode":"47404",
    "sg:province":"IN",
    "sg:tags":[
        "house"
    ],
    "wof:name":"Walcott Construction Fran",
    "wof:placetype":"venue"
},
  "geometry": {"coordinates":[-86.682923,39.203394],"type":"Point"}
}