{
  "type": "Feature",
  "properties": {
    "iso:country":"US",
    "sg:address":"1130 Windhaven Cir",
    "sg:city":"Brownsburg",
    "sg:classifiers":[
        {
            "category":"Professional",
            "subcategory":"Computer Services",
            "type":"Services"
        }
    ],
    "sg:phone":"+1 317 858 0516",
    "sg:postcode":"46112",
    "sg:province":"IN",
    "sg:tags":[
        "consultant",
        "designer"
    ],
    "wof:name":"Techsys Advanced Resources",
    "wof:placetype":"venue"
},
  "geometry": {"coordinates":[-86.37929699999999,39.852562],"type":"Point"}
}