{
  "type": "Feature",
  "properties": {
    "addr:full":"417 E 3rd St Mt Vernon IN 47620",
    "addr:housenumber":"417",
    "addr:postcode":"47620",
    "addr:street":"E 3Rd St",
    "iso:country":"US",
    "sg:address":"417 E 3rd St",
    "sg:city":"Mt Vernon",
    "sg:classifiers":[
        {
            "category":"Personal",
            "subcategory":"Beauty Salon",
            "type":"Services"
        }
    ],
    "sg:phone":"+1 812 838 3546",
    "sg:postcode":"47620",
    "sg:province":"IN",
    "sg:tags":[
        "shop"
    ],
    "wof:name":"New Reflections Hair Design",
    "wof:placetype":"venue"
},
  "geometry": {"coordinates":[-87.890721,37.932435],"type":"Point"}
}