{
  "type": "Feature",
  "properties": {
    "addr:full":"7834 E 96th St Fishers IN 46038",
    "addr:housenumber":"7834",
    "addr:postcode":"46038",
    "addr:street":"E 96Th St",
    "iso:country":"US",
    "sg:address":"7834 E 96th St",
    "sg:city":"Fishers",
    "sg:classifiers":[
        {
            "category":"Restaurant",
            "type":"Food & Drink"
        }
    ],
    "sg:phone":"+1 317 842 3528",
    "sg:postcode":"46038",
    "sg:province":"IN",
    "sg:tags":[
        "mexican"
    ],
    "sg:website":"www.TijuanaFlats.com",
    "wof:name":"Tijuana Flats",
    "wof:placetype":"venue"
},
  "geometry": {"coordinates":[-86.026838,39.927224],"type":"Point"}
}