{
  "type": "Feature",
  "properties": {
    "iso:country":"US",
    "sg:address":"805 Sim Hodgin Pkwy",
    "sg:city":"Richmond",
    "sg:classifiers":[
        {
            "category":"Retail",
            "subcategory":"Auto Repair",
            "type":"Services"
        }
    ],
    "sg:phone":"+1 765 962 4381",
    "sg:postcode":"47374",
    "sg:province":"IN",
    "sg:tags":[
        "repairing",
        "automobile"
    ],
    "wof:name":"Haager Automotive & Truck Svc",
    "wof:placetype":"venue"
},
  "geometry": {"coordinates":[-84.89321200000001,39.839369],"type":"Point"}
}