{
  "type": "Feature",
  "properties": {
    "iso:country":"US",
    "sg:address":"1437 N New Jersey St",
    "sg:city":"Indianapolis",
    "sg:classifiers":[
        {
            "category":"Building & Trades",
            "subcategory":"Construction",
            "type":"Services"
        }
    ],
    "sg:phone":"+1 317 921 9510",
    "sg:postcode":"46202",
    "sg:province":"IN",
    "sg:tags":[
        "contractor"
    ],
    "wof:name":"Argonaut Builders LLC",
    "wof:placetype":"venue"
},
  "geometry": {"coordinates":[-86.150738,39.786768],"type":"Point"}
}