{
  "type": "Feature",
  "properties": {
    "iso:country":"US",
    "sg:address":"4203 N Oxford St",
    "sg:city":"Indianapolis",
    "sg:classifiers":[
        {
            "category":"Professional",
            "subcategory":"Art Services",
            "type":"Services"
        }
    ],
    "sg:phone":"+1 317 850 6510",
    "sg:postcode":"46205",
    "sg:province":"IN",
    "sg:tags":[
        "designer",
        "display",
        "producer"
    ],
    "wof:name":"Coaching By Design",
    "wof:placetype":"venue"
},
  "geometry": {"coordinates":[-86.11640199999999,39.832934],"type":"Point"}
}