{
  "type": "Feature",
  "properties": {
    "iso:country":"US",
    "sg:address":"206 S Main St",
    "sg:city":"Sheridan",
    "sg:classifiers":[
        {
            "category":"Restaurant",
            "type":"Food & Drink"
        }
    ],
    "sg:menulink":"http://www.allmenus.com/in/adams/16524-jans-village-pizza/menu/",
    "sg:phone":"+1 317 758 6660",
    "sg:postcode":"46069",
    "sg:province":"IN",
    "sg:tags":[
        "american",
        "pizza"
    ],
    "wof:name":"Jan's Village Pizza",
    "wof:placetype":"venue"
},
  "geometry": {"coordinates":[-86.220625,40.136925],"type":"Point"}
}