{
  "type": "Feature",
  "properties": {
    "iso:country":"US",
    "sg:address":"303 W Church St",
    "sg:city":"English",
    "sg:classifiers":[
        {
            "category":"Wholesale",
            "subcategory":"Machinery & Supplies",
            "type":"Manufacturing & Wholesale Goods"
        }
    ],
    "sg:phone":"+1 812 338 2732",
    "sg:postcode":"47118",
    "sg:province":"IN",
    "sg:tags":[
        "equipment",
        "railroad"
    ],
    "wof:name":"North American Tie & Timber",
    "wof:placetype":"venue"
},
  "geometry": {"coordinates":[-86.467736,38.330438],"type":"Point"}
}