{
  "type": "Feature",
  "properties": {
    "iso:country":"US",
    "sg:address":"907 Oakland Ave",
    "sg:city":"Elkhart",
    "sg:classifiers":[
        {
            "category":"Retail",
            "subcategory":"Car Wash",
            "type":"Services"
        }
    ],
    "sg:phone":"+1 574 522 7398",
    "sg:postcode":"46516",
    "sg:province":"IN",
    "sg:tags":[
        "automobile",
        "detail",
        "clean"
    ],
    "wof:name":"Robert's Detail Shop",
    "wof:placetype":"venue"
},
  "geometry": {"coordinates":[-85.984942,41.674099],"type":"Point"}
}