{
  "type": "Feature",
  "properties": {
    "iso:country":"US",
    "sg:address":"9655 Heim Rd",
    "sg:city":"Chandler",
    "sg:classifiers":[
        {
            "category":"Retail",
            "subcategory":"Auto Repair",
            "type":"Services"
        }
    ],
    "sg:phone":"+1 812 925 7721",
    "sg:postcode":"47610",
    "sg:province":"IN",
    "sg:tags":[
        "general"
    ],
    "wof:name":"Advanced Automotive Repair",
    "wof:placetype":"venue"
},
  "geometry": {"coordinates":[-87.423714,38.041891],"type":"Point"}
}