{
  "type": "Feature",
  "properties": {
    "iso:country":"US",
    "sg:address":"7 E Market St",
    "sg:city":"Indianapolis",
    "sg:classifiers":[
        {
            "category":"Shopping",
            "subcategory":"Florist",
            "type":"Retail Goods"
        }
    ],
    "sg:phone":"+1 317 423 2841",
    "sg:postcode":"46204",
    "sg:province":"IN",
    "sg:website":"www.berkshireflorist.com",
    "wof:name":"Berkshire Florists",
    "wof:placetype":"venue"
},
  "geometry": {"coordinates":[-86.15684,39.768491],"type":"Point"}
}