{
  "type": "Feature",
  "properties": {
    "iso:country":"US",
    "sg:address":"104 W Washington St",
    "sg:city":"Churubusco",
    "sg:classifiers":[
        {
            "category":"Shopping",
            "subcategory":"Crafts & Fabrics",
            "type":"Retail Goods"
        }
    ],
    "sg:phone":"+1 260 693 2438",
    "sg:postcode":"46723",
    "sg:province":"IN",
    "sg:tags":[
        "shop"
    ],
    "wof:name":"Howell House",
    "wof:placetype":"venue"
},
  "geometry": {"coordinates":[-85.320007,41.231437],"type":"Point"}
}