{
  "type": "Feature",
  "properties": {
    "addr:full":"4528 Old State Rd 46 Nashville IN 47448",
    "addr:housenumber":"4528;46",
    "addr:postcode":"47448",
    "addr:street":"Old State Rd",
    "iso:country":"US",
    "sg:address":"4528 Old State Rd 46",
    "sg:city":"Nashville",
    "sg:classifiers":[
        {
            "category":"Organizations",
            "subcategory":"Religious Organization",
            "type":"Services"
        }
    ],
    "sg:phone":"+1 812 988 0547",
    "sg:postcode":"47448",
    "sg:province":"IN",
    "sg:tags":[
        "church"
    ],
    "wof:name":"Brown County Vinyard Church",
    "wof:placetype":"venue"
},
  "geometry": {"coordinates":[-86.166234,39.187944],"type":"Point"}
}