{
  "type": "Feature",
  "properties": {
    "iso:country":"US",
    "sg:address":"68 S Sycamore St",
    "sg:city":"Campbellsburg",
    "sg:classifiers":[
        {
            "category":"Bars & Pubs",
            "type":"Food & Drink"
        }
    ],
    "sg:phone":"+1 812 755 5032",
    "sg:postcode":"47108",
    "sg:province":"IN",
    "wof:name":"Jimmy's Place",
    "wof:placetype":"venue"
},
  "geometry": {"coordinates":[-86.26112,38.650704],"type":"Point"}
}