{
  "type": "Feature",
  "properties": {
    "iso:country":"US",
    "sg:address":"508 Indiana Ave",
    "sg:city":"Indianapolis",
    "sg:classifiers":[
        {
            "category":"Health Services",
            "subcategory":"Dentist",
            "type":"Services"
        }
    ],
    "sg:phone":"+1 317 269 0402",
    "sg:postcode":"46202",
    "sg:province":"IN",
    "sg:tags":[
        "implant",
        "dentists-implantology",
        "dentists-pediatric",
        "dentists-periodontists",
        "dentistry"
    ],
    "sg:website":"http://www.sonrisadental.com",
    "wof:name":"Sonrisa Dental",
    "wof:placetype":"venue"
},
  "geometry": {"coordinates":[-86.165164,39.774343],"type":"Point"}
}