{
  "type": "Feature",
  "properties": {
    "iso:country":"US",
    "sg:address":"521 E 5th St",
    "sg:city":"Marion",
    "sg:classifiers":[
        {
            "category":"Government",
            "subcategory":"Office",
            "type":"Public Place"
        }
    ],
    "sg:phone":"+1 765 668 4520",
    "sg:postcode":"46953",
    "sg:province":"IN",
    "sg:tags":[
        "federal",
        "security"
    ],
    "wof:name":"US Army National Guard",
    "wof:placetype":"venue"
},
  "geometry": {"coordinates":[-85.653765,40.55697],"type":"Point"}
}