{
  "type": "Feature",
  "properties": {
    "addr:full":"475 N College Ave Bloomington IN 47404",
    "addr:housenumber":"475",
    "addr:postcode":"47404",
    "addr:street":"N College Ave",
    "iso:country":"US",
    "sg:address":"475 N College Ave",
    "sg:city":"Bloomington",
    "sg:classifiers":[
        {
            "category":"Sports & Exercise",
            "subcategory":"Gym",
            "type":"Entertainment"
        }
    ],
    "sg:phone":"+1 812 339 7865",
    "sg:postcode":"47404",
    "sg:province":"IN",
    "sg:tags":[
        "trainer",
        "club",
        "health",
        "studio",
        "gymnasium"
    ],
    "sg:website":"www.cardinalfitnessindy.com",
    "wof:name":"Cardinal Fitness",
    "wof:placetype":"venue"
},
  "geometry": {"coordinates":[-86.535009,39.170219],"type":"Point"}
}