{
  "type": "Feature",
  "properties": {
    "iso:country":"US",
    "sg:address":"101 N East St",
    "sg:city":"Crown Point",
    "sg:classifiers":[
        {
            "category":"Government",
            "subcategory":"Office",
            "type":"Public Place"
        }
    ],
    "sg:phone":"+1 219 662 3235",
    "sg:postcode":"46307",
    "sg:province":"IN",
    "sg:tags":[
        "city"
    ],
    "wof:name":"City Clerk",
    "wof:placetype":"venue"
},
  "geometry": {"coordinates":[-87.36318199999999,41.419084],"type":"Point"}
}