{
  "type": "Feature",
  "properties": {
    "iso:country":"US",
    "sg:address":"520 E Seminary St",
    "sg:city":"Greencastle",
    "sg:classifiers":[
        {
            "category":"Organizations",
            "subcategory":"Religious Organization",
            "type":"Services"
        }
    ],
    "sg:phone":"+1 765 653 3921",
    "sg:postcode":"46135",
    "sg:province":"IN",
    "sg:tags":[
        "church"
    ],
    "wof:name":"St Andrew's Episcopal Church",
    "wof:placetype":"venue"
},
  "geometry": {"coordinates":[-86.859043,39.641737],"type":"Point"}
}