{
  "type": "Feature",
  "properties": {
    "iso:country":"US",
    "sg:address":"1263 Co Rd 40",
    "sg:city":"Auburn",
    "sg:classifiers":[
        {
            "category":"Personal",
            "subcategory":"Beauty Salon",
            "type":"Services"
        }
    ],
    "sg:phone":"+1 260 357 5570",
    "sg:postcode":"46706",
    "sg:province":"IN",
    "sg:tags":[
        "cosmetologist"
    ],
    "wof:name":"Karen Cope Shay",
    "wof:placetype":"venue"
},
  "geometry": {"coordinates":[-85.133437,41.381089],"type":"Point"}
}