{
  "type": "Feature",
  "properties": {
    "iso:country":"US",
    "sg:address":"2120 Clay St",
    "sg:city":"Indianapolis",
    "sg:classifiers":[
        {
            "category":"Home & Garden",
            "subcategory":"Building Materials",
            "type":"Retail Goods"
        },
        {
            "category":"Building & Trades",
            "subcategory":"Construction",
            "type":"Services"
        }
    ],
    "sg:phone":"+1 317 546 4881",
    "sg:postcode":"46205",
    "sg:province":"IN",
    "sg:tags":[
        "insulation",
        "contractor"
    ],
    "sg:website":"http://www.fargoinsulation.com",
    "wof:name":"Fargo Insulation Company, Inc.",
    "wof:placetype":"venue"
},
  "geometry": {"coordinates":[-86.12463099999999,39.835651],"type":"Point"}
}