{
  "type": "Feature",
  "properties": {
    "iso:country":"US",
    "sg:address":"2787 W Co Rd 450 S",
    "sg:city":"Sullivan",
    "sg:classifiers":[
        {
            "category":"Real Estate",
            "subcategory":"Real Estate Operator",
            "type":"Services"
        }
    ],
    "sg:phone":"+1 812 356 4759",
    "sg:postcode":"47882",
    "sg:province":"IN",
    "sg:tags":[
        "farm",
        "corn",
        "property",
        "lessor"
    ],
    "wof:name":"Wm Lisman",
    "wof:placetype":"venue"
},
  "geometry": {"coordinates":[-87.4706,39.018996],"type":"Point"}
}