{
  "type": "Feature",
  "properties": {
    "iso:country":"US",
    "sg:address":"421 Airport North Office Park",
    "sg:city":"Fort Wayne",
    "sg:classifiers":[
        {
            "category":"Wholesale",
            "subcategory":"Durable Goods & Equipment",
            "type":"Manufacturing & Wholesale Goods"
        }
    ],
    "sg:phone":"+1 260 497 0350",
    "sg:postcode":"46825",
    "sg:province":"IN",
    "sg:tags":[
        "representative",
        "manufacturer"
    ],
    "wof:name":"Electronic Design & Sales Inc",
    "wof:placetype":"venue"
},
  "geometry": {"coordinates":[-85.16227499999999,41.146266],"type":"Point"}
}