{
  "type": "Feature",
  "properties": {
    "addr:full":"8230 E Washington St Indianapolis IN 46219",
    "addr:housenumber":"8230",
    "addr:postcode":"46219",
    "addr:street":"E Washington St",
    "iso:country":"US",
    "sg:address":"8230 E Washington St",
    "sg:city":"Indianapolis",
    "sg:classifiers":[
        {
            "category":"Recreation",
            "type":"Entertainment"
        }
    ],
    "sg:phone":"+1 317 897 1000",
    "sg:postcode":"46219",
    "sg:province":"IN",
    "wof:name":"Mudokwan Judo & Karate School",
    "wof:placetype":"venue"
},
  "geometry": {"coordinates":[-86.021692,39.773364],"type":"Point"}
}