{
  "type": "Feature",
  "properties": {
    "iso:country":"US",
    "sg:address":"911 Broad Ripple Ave",
    "sg:city":"Indianapolis",
    "sg:classifiers":[
        {
            "category":"Education",
            "subcategory":"Special Training",
            "type":"Public Place"
        }
    ],
    "sg:phone":"+1 317 255 4411",
    "sg:postcode":"46220",
    "sg:province":"IN",
    "sg:tags":[
        "instruction",
        "music"
    ],
    "wof:name":"About Music",
    "wof:placetype":"venue"
},
  "geometry": {"coordinates":[-86.141811,39.869657],"type":"Point"}
}