{
  "type": "Feature",
  "properties": {
    "addr:full":"712 N Wayne St Angola IN 46703",
    "addr:housenumber":"712",
    "addr:postcode":"46703",
    "addr:street":"N Wayne St",
    "iso:country":"US",
    "sg:address":"712 N Wayne St",
    "sg:city":"Angola",
    "sg:classifiers":[
        {
            "category":"Personal",
            "subcategory":"Beauty Salon",
            "type":"Services"
        }
    ],
    "sg:phone":"+1 260 665 3284",
    "sg:postcode":"46703",
    "sg:province":"IN",
    "wof:name":"Hair Happening",
    "wof:placetype":"venue"
},
  "geometry": {"coordinates":[-84.999387,41.643471],"type":"Point"}
}