{
  "type": "Feature",
  "properties": {
    "iso:country":"US",
    "sg:address":"807 S Green St",
    "sg:city":"Brownsburg",
    "sg:classifiers":[
        {
            "category":"Retail",
            "subcategory":"Portrait Studio",
            "type":"Services"
        }
    ],
    "sg:phone":"+1 317 852 7837",
    "sg:postcode":"46112",
    "sg:province":"IN",
    "sg:tags":[
        "photo"
    ],
    "wof:name":"Wilson Photography",
    "wof:placetype":"venue"
},
  "geometry": {"coordinates":[-86.401181,39.829799],"type":"Point"}
}