{
  "type": "Feature",
  "properties": {
    "addr:full":"8399 E 50 S Zionsville IN 46077",
    "addr:housenumber":"8399;50",
    "addr:postcode":"46077",
    "addr:street":"E;S Zionsville",
    "iso:country":"US",
    "sg:address":"8399 E 50 S",
    "sg:city":"Zionsville",
    "sg:classifiers":[
        {
            "category":"Shopping",
            "subcategory":"Department Store",
            "type":"Retail Goods"
        }
    ],
    "sg:phone":"+1 317 769 5050",
    "sg:postcode":"46077",
    "sg:province":"IN",
    "wof:name":"Only One Stop Shop Now",
    "wof:placetype":"venue"
},
  "geometry": {"coordinates":[-86.309658,40.03391],"type":"Point"}
}