{
  "type": "Feature",
  "properties": {
    "iso:country":"US",
    "sg:address":"6434 N College Ave",
    "sg:city":"Indianapolis",
    "sg:classifiers":[
        {
            "category":"Real Estate",
            "subcategory":"Real Estate Agent",
            "type":"Services"
        }
    ],
    "sg:phone":"+1 317 251 9393",
    "sg:postcode":"46220",
    "sg:province":"IN",
    "sg:tags":[
        "management"
    ],
    "wof:name":"Monon Management Svc",
    "wof:placetype":"venue"
},
  "geometry": {"coordinates":[-86.146304,39.87265],"type":"Point"}
}