{
  "type": "Feature",
  "properties": {
    "iso:country":"US",
    "sg:address":"4100 W 700 N",
    "sg:city":"Michigan City",
    "sg:classifiers":[
        {
            "category":"Retail",
            "subcategory":"Repair Shop",
            "type":"Services"
        }
    ],
    "sg:phone":"+1 219 872 7282",
    "sg:postcode":"46360",
    "sg:province":"IN",
    "sg:tags":[
        "welding"
    ],
    "wof:name":"J & J Welding",
    "wof:placetype":"venue"
},
  "geometry": {"coordinates":[-86.777503,41.708299],"type":"Point"}
}