{
  "type": "Feature",
  "properties": {
    "iso:country":"US",
    "sg:address":"6226 S Sandstone St",
    "sg:city":"Terre Haute",
    "sg:classifiers":[
        {
            "category":"Real Estate",
            "subcategory":"Real Estate Operator",
            "type":"Services"
        }
    ],
    "sg:phone":"+1 812 894 3525",
    "sg:postcode":"47802",
    "sg:province":"IN",
    "sg:tags":[
        "mobile",
        "home",
        "site",
        "community"
    ],
    "wof:name":"Castaways",
    "wof:placetype":"venue"
},
  "geometry": {"coordinates":[-87.317353,39.391219],"type":"Point"}
}