{
  "type": "Feature",
  "properties": {
    "iso:country":"US",
    "sg:address":"410 S Chestnut St",
    "sg:city":"Seymour",
    "sg:classifiers":[
        {
            "category":"Health Services",
            "subcategory":"Doctor",
            "type":"Services"
        }
    ],
    "sg:phone":"+1 812 522 5206",
    "sg:postcode":"47274",
    "sg:province":"IN",
    "sg:tags":[
        "dentist"
    ],
    "wof:name":"Charles J Durham PC",
    "wof:placetype":"venue"
},
  "geometry": {"coordinates":[-85.888759,38.954435],"type":"Point"}
}