{
  "type": "Feature",
  "properties": {
    "iso:country":"US",
    "sg:address":"1213 K St",
    "sg:city":"Bedford",
    "sg:classifiers":[
        {
            "category":"Wholesale",
            "subcategory":"Auto Parts",
            "type":"Manufacturing & Wholesale Goods"
        }
    ],
    "sg:phone":"+1 812 275 4424",
    "sg:postcode":"47421",
    "sg:province":"IN",
    "sg:tags":[
        "supply"
    ],
    "wof:name":"Fultz Auto Supplies-Napa",
    "wof:placetype":"venue"
},
  "geometry": {"coordinates":[-86.485725,38.865523],"type":"Point"}
}