{
  "type": "Feature",
  "properties": {
    "iso:country":"US",
    "sg:address":"1908 E Chicago Ave",
    "sg:city":"East Chicago",
    "sg:classifiers":[
        {
            "category":"Manufacturing",
            "subcategory":"Printing",
            "type":"Manufacturing & Wholesale Goods"
        }
    ],
    "sg:phone":"+1 219 398 1115",
    "sg:postcode":"46312",
    "sg:province":"IN",
    "sg:tags":[
        "newspaper",
        "publishing"
    ],
    "wof:name":"Hispanic Perspective",
    "wof:placetype":"venue"
},
  "geometry": {"coordinates":[-87.451939,41.629187],"type":"Point"}
}