{
  "type": "Feature",
  "properties": {
    "iso:country":"US",
    "sg:address":"4610 Bluff Rd",
    "sg:city":"Indianapolis",
    "sg:classifiers":[
        {
            "category":"Shopping",
            "subcategory":"Crafts & Fabrics",
            "type":"Retail Goods"
        },
        {
            "category":"Arena",
            "subcategory":"Bull Ring",
            "type":"Entertainment"
        }
    ],
    "sg:phone":"+1 317 780 9800",
    "sg:postcode":"46217",
    "sg:province":"IN",
    "sg:tags":[
        "canvas",
        "tarp"
    ],
    "wof:name":"Jimmy's Tarp Repair",
    "wof:placetype":"venue"
},
  "geometry": {"coordinates":[-86.172877,39.695894],"type":"Point"}
}