{
  "type": "Feature",
  "properties": {
    "addr:full":"24 Jefferson St N Nashville IN 47448",
    "addr:housenumber":"24",
    "addr:postcode":"47448",
    "addr:street":"Jefferson St N",
    "iso:country":"US",
    "sg:address":"24 Jefferson St N",
    "sg:city":"Nashville",
    "sg:classifiers":[
        {
            "category":"Insurance",
            "subcategory":"Insurance Agent",
            "type":"Services"
        }
    ],
    "sg:phone":"+1 812 988 2275",
    "sg:postcode":"47448",
    "sg:province":"IN",
    "wof:name":"Bright & Williamson Insurance",
    "wof:placetype":"venue"
},
  "geometry": {"coordinates":[-86.248222,39.207543],"type":"Point"}
}