{
  "type": "Feature",
  "properties": {
    "iso:country":"US",
    "sg:address":"1423 W 53rd St",
    "sg:city":"Anderson",
    "sg:classifiers":[
        {
            "category":"Food & Beverages",
            "subcategory":"Candy",
            "type":"Retail Goods"
        }
    ],
    "sg:phone":"+1 765 642 7247",
    "sg:postcode":"46013",
    "sg:province":"IN",
    "sg:tags":[
        "confectionery"
    ],
    "wof:name":"Goods Candy Shop",
    "wof:placetype":"venue"
},
  "geometry": {"coordinates":[-85.701474,40.06142],"type":"Point"}
}