{
  "type": "Feature",
  "properties": {
    "iso:country":"US",
    "sg:address":"915 W Howe St",
    "sg:city":"Bloomington",
    "sg:classifiers":[
        {
            "category":"Organizations",
            "subcategory":"Religious Organization",
            "type":"Services"
        }
    ],
    "sg:phone":"+1 812 824 6356",
    "sg:postcode":"47403",
    "sg:province":"IN",
    "wof:name":"West Side Pentecostal",
    "wof:placetype":"venue"
},
  "geometry": {"coordinates":[-86.54540299999999,39.162346],"type":"Point"}
}