{
  "type": "Feature",
  "properties": {
    "iso:country":"US",
    "sg:address":"801 N Main St",
    "sg:city":"Crown Point",
    "sg:classifiers":[
        {
            "category":"Restaurant",
            "type":"Food & Drink"
        }
    ],
    "sg:phone":"+1 219 226 9850",
    "sg:postcode":"46307",
    "sg:province":"IN",
    "wof:name":"Zel's Roast Beef",
    "wof:placetype":"venue"
},
  "geometry": {"coordinates":[-87.36460099999999,41.427399],"type":"Point"}
}