{
  "type": "Feature",
  "properties": {
    "iso:country":"US",
    "sg:address":"2504 N 200 E",
    "sg:city":"Hartford City",
    "sg:classifiers":[
        {
            "category":"Government",
            "subcategory":"Office",
            "type":"Public Place"
        }
    ],
    "sg:phone":"+1 765 348 0306",
    "sg:postcode":"47348",
    "sg:province":"IN",
    "wof:name":"County Highway Garage",
    "wof:placetype":"venue"
},
  "geometry": {"coordinates":[-85.331985,40.486808],"type":"Point"}
}