{
  "type": "Feature",
  "properties": {
    "iso:country":"US",
    "sg:address":"307 S Logan St",
    "sg:city":"Cayuga",
    "sg:classifiers":[
        {
            "category":"Shopping",
            "subcategory":"Department Store",
            "type":"Retail Goods"
        }
    ],
    "sg:phone":"+1 765 492 3562",
    "sg:postcode":"47928",
    "sg:province":"IN",
    "sg:tags":[
        "shop"
    ],
    "wof:name":"Dollar General",
    "wof:placetype":"venue"
},
  "geometry": {"coordinates":[-87.460085,39.947469],"type":"Point"}
}