{
  "type": "Feature",
  "properties": {
    "iso:country":"US",
    "sg:address":"703 Liberty Ave",
    "sg:city":"W College Corner",
    "sg:classifiers":[
        {
            "category":"Building & Trades",
            "subcategory":"Cleaning & Sanitation",
            "type":"Services"
        }
    ],
    "sg:phone":"+1 765 732 3893",
    "sg:postcode":"47003",
    "sg:province":"IN",
    "sg:tags":[
        "janitor"
    ],
    "wof:name":"New World Cleaning",
    "wof:placetype":"venue"
},
  "geometry": {"coordinates":[-84.826309,39.574535],"type":"Point"}
}