{
  "type": "Feature",
  "properties": {
    "iso:country":"US",
    "sg:address":"9235 Broadway",
    "sg:city":"Merrillville",
    "sg:classifiers":[
        {
            "category":"Wholesale",
            "subcategory":"Medical Equipment & Supplies",
            "type":"Manufacturing & Wholesale Goods"
        }
    ],
    "sg:phone":"+1 219 736 9044",
    "sg:postcode":"46410",
    "sg:province":"IN",
    "sg:tags":[
        "physician",
        "surgeon"
    ],
    "wof:name":"Micomed",
    "wof:placetype":"venue"
},
  "geometry": {"coordinates":[-87.335714,41.4502],"type":"Point"}
}