{
  "type": "Feature",
  "properties": {
    "addr:full":"206 S Elkhart Ave Elkhart IN 46516",
    "addr:housenumber":"206",
    "addr:postcode":"46516",
    "addr:street":"S Elkhart Ave",
    "iso:country":"US",
    "sg:address":"206 S Elkhart Ave",
    "sg:city":"Elkhart",
    "sg:classifiers":[
        {
            "category":"Retail",
            "subcategory":"Auto Repair",
            "type":"Services"
        }
    ],
    "sg:phone":"+1 574 295 3177",
    "sg:postcode":"46516",
    "sg:province":"IN",
    "sg:tags":[
        "body",
        "automobile",
        "painting"
    ],
    "wof:name":"Trendline Collision Svc",
    "wof:placetype":"venue"
},
  "geometry": {"coordinates":[-85.96827999999999,41.687216],"type":"Point"}
}