{
  "type": "Feature",
  "properties": {
    "iso:country":"US",
    "sg:address":"1815 N Greensburg Xing",
    "sg:city":"Greensburg",
    "sg:classifiers":[
        {
            "category":"Health Services",
            "subcategory":"Doctor",
            "type":"Services"
        }
    ],
    "sg:phone":"+1 812 663 6263",
    "sg:postcode":"47240",
    "sg:province":"IN",
    "sg:tags":[
        "dentist"
    ],
    "wof:name":"Gentle Dentist",
    "wof:placetype":"venue"
},
  "geometry": {"coordinates":[-85.619963,39.351958],"type":"Point"}
}