{
  "type": "Feature",
  "properties": {
    "iso:country":"US",
    "sg:address":"114 E Main St",
    "sg:city":"Delphi",
    "sg:classifiers":[
        {
            "category":"Communications",
            "type":"Services"
        }
    ],
    "sg:phone":"+1 765 564 6644",
    "sg:postcode":"46923",
    "sg:province":"IN",
    "wof:name":"Sunrise Communications",
    "wof:placetype":"venue"
},
  "geometry": {"coordinates":[-86.673511,40.586221],"type":"Point"}
}