{
  "type": "Feature",
  "properties": {
    "iso:country":"US",
    "sg:address":"3701 S Cowan Rd",
    "sg:city":"Muncie",
    "sg:classifiers":[
        {
            "category":"Manufacturing",
            "subcategory":"Metals",
            "type":"Manufacturing & Wholesale Goods"
        }
    ],
    "sg:phone":"+1 765 741 3136",
    "sg:postcode":"47302",
    "sg:province":"IN",
    "sg:tags":[
        "cage"
    ],
    "wof:name":"Mid-West Metal Product Co",
    "wof:placetype":"venue"
},
  "geometry": {"coordinates":[-85.405033,40.158551],"type":"Point"}
}