{
  "type": "Feature",
  "properties": {
    "iso:country":"US",
    "sg:address":"1316 N Main St",
    "sg:city":"Elkhart",
    "sg:classifiers":[
        {
            "category":"Personal",
            "subcategory":"Beauty Salon",
            "type":"Services"
        }
    ],
    "sg:phone":"+1 574 259 1191",
    "sg:postcode":"46514",
    "sg:province":"IN",
    "sg:tags":[
        "shop"
    ],
    "wof:name":"Florines Main Event",
    "wof:placetype":"venue"
},
  "geometry": {"coordinates":[-85.97644,41.700375],"type":"Point"}
}