{
  "type": "Feature",
  "properties": {
    "iso:country":"US",
    "sg:address":"228 S Halleck St",
    "sg:city":"Demotte",
    "sg:classifiers":[
        {
            "category":"Professional",
            "subcategory":"Accounting & Tax Preparation",
            "type":"Services"
        }
    ],
    "sg:phone":"+1 219 987 6014",
    "sg:postcode":"46310",
    "sg:province":"IN",
    "sg:tags":[
        "accountant"
    ],
    "wof:name":"Del Principe & Allie",
    "wof:placetype":"venue"
},
  "geometry": {"coordinates":[-87.19881700000001,41.201126],"type":"Point"}
}