{
  "type": "Feature",
  "properties": {
    "addr:full":"240 E 90th Dr Merrillville IN 46410",
    "addr:housenumber":"240",
    "addr:postcode":"46410",
    "addr:street":"E 90Th Dr",
    "iso:country":"US",
    "sg:address":"240 E 90th Dr",
    "sg:city":"Merrillville",
    "sg:classifiers":[
        {
            "category":"Banks & Credit Unions",
            "subcategory":"Financial Services",
            "type":"Services"
        }
    ],
    "sg:phone":"+1 219 793 9500",
    "sg:postcode":"46410",
    "sg:province":"IN",
    "sg:tags":[
        "company",
        "holding"
    ],
    "wof:name":"Braddock Management",
    "wof:placetype":"venue"
},
  "geometry": {"coordinates":[-87.327799,41.455189],"type":"Point"}
}