{
  "type": "Feature",
  "properties": {
    "iso:country":"US",
    "sg:address":"3126 N Clinton St",
    "sg:city":"Fort Wayne",
    "sg:classifiers":[
        {
            "category":"Autos & Motor Vehicles",
            "subcategory":"Automobile Sales",
            "type":"Retail Goods"
        }
    ],
    "sg:phone":"+1 260 483 1712",
    "sg:postcode":"46805",
    "sg:province":"IN",
    "sg:tags":[
        "used"
    ],
    "wof:name":"Nakos Auto Sales",
    "wof:placetype":"venue"
},
  "geometry": {"coordinates":[-85.138265,41.104922],"type":"Point"}
}