{
  "type": "Feature",
  "properties": {
    "iso:country":"US",
    "sg:address":"512 Morland Dr",
    "sg:city":"Lafayette",
    "sg:classifiers":[
        {
            "category":"Wholesale",
            "subcategory":"Hardware",
            "type":"Manufacturing & Wholesale Goods"
        }
    ],
    "sg:phone":"+1 765 447 8386",
    "sg:postcode":"47905",
    "sg:province":"IN",
    "sg:tags":[
        "fastener"
    ],
    "wof:name":"All State Fastener Corp",
    "wof:placetype":"venue"
},
  "geometry": {"coordinates":[-86.853827,40.411407],"type":"Point"}
}