{
  "type": "Feature",
  "properties": {
    "addr:full":"7941 Monroe Ave Munster IN 46321",
    "addr:housenumber":"7941",
    "addr:postcode":"46321",
    "addr:street":"Monroe Ave",
    "iso:country":"US",
    "sg:address":"7941 Monroe Ave",
    "sg:city":"Munster",
    "sg:classifiers":[
        {
            "category":"Freight",
            "type":"Transportation"
        }
    ],
    "sg:phone":"+1 219 836 9818",
    "sg:postcode":"46321",
    "sg:province":"IN",
    "sg:tags":[
        "operator",
        "local",
        "trucking"
    ],
    "wof:name":"Plina Inc",
    "wof:placetype":"venue"
},
  "geometry": {"coordinates":[-87.512621,41.566788],"type":"Point"}
}