{
  "type": "Feature",
  "properties": {
    "iso:country":"US",
    "sg:address":"1112 S 10th St",
    "sg:city":"Noblesville",
    "sg:classifiers":[
        {
            "category":"Food & Beverages",
            "subcategory":"Bakery",
            "type":"Retail Goods"
        }
    ],
    "sg:phone":"+1 317 770 9399",
    "sg:postcode":"46060",
    "sg:province":"IN",
    "sg:tags":[
        "baker"
    ],
    "wof:name":"Heavenly Sweets Wedding Cakes",
    "wof:placetype":"venue"
},
  "geometry": {"coordinates":[-86.012062,40.036338],"type":"Point"}
}