{
  "type": "Feature",
  "properties": {
    "addr:full":"1527 Bear Claw Ln Fort Wayne IN 46845",
    "addr:housenumber":"1527",
    "addr:postcode":"46845",
    "addr:street":"Bear Claw Ln",
    "iso:country":"US",
    "sg:address":"1527 Bear Claw Ln",
    "sg:city":"Fort Wayne",
    "sg:classifiers":[
        {
            "category":"Professional",
            "subcategory":"Detective & Security Services",
            "type":"Services"
        }
    ],
    "sg:phone":"+1 260 615 0378",
    "sg:postcode":"46845",
    "sg:province":"IN",
    "sg:tags":[
        "rec",
        "agency",
        "fugitive",
        "private",
        "indiana"
    ],
    "wof:name":"Nichols Investigations",
    "wof:placetype":"venue"
},
  "geometry": {"coordinates":[-85.161805,41.19333],"type":"Point"}
}