{
  "type": "Feature",
  "properties": {
    "iso:country":"US",
    "sg:address":"7669 S Wilbur Wright Rd",
    "sg:city":"Cambridge City",
    "sg:classifiers":[
        {
            "category":"Manufacturing",
            "subcategory":"Tools & Machinery",
            "type":"Manufacturing & Wholesale Goods"
        }
    ],
    "sg:phone":"+1 765 332 2924",
    "sg:postcode":"47327",
    "sg:province":"IN",
    "sg:tags":[
        "equipment",
        "pump",
        "pumping"
    ],
    "sg:website":"www.hyflexcorp.com",
    "wof:name":"Hy-Flex Corp",
    "wof:placetype":"venue"
},
  "geometry": {"coordinates":[-85.262736,39.823019],"type":"Point"}
}