{
  "type": "Feature",
  "properties": {
    "iso:country":"US",
    "sg:address":"112 N Monroe St",
    "sg:city":"Williamsport",
    "sg:classifiers":[
        {
            "category":"Professional",
            "subcategory":"Lawyer & Legal Services",
            "type":"Services"
        }
    ],
    "sg:phone":"+1 765 762 2404",
    "sg:postcode":"47993",
    "sg:province":"IN",
    "sg:tags":[
        "attorney"
    ],
    "sg:website":"www.mccabelaw.com",
    "wof:name":"Mc Cabe Law Office",
    "wof:placetype":"venue"
},
  "geometry": {"coordinates":[-87.29427,40.287653],"type":"Point"}
}