{
  "type": "Feature",
  "properties": {
    "addr:full":"2600 Grand Blvd Lake Station IN 46405",
    "addr:housenumber":"2600",
    "addr:postcode":"46405",
    "addr:street":"Grand Blvd Lake",
    "iso:country":"US",
    "sg:address":"2600 Grand Blvd",
    "sg:city":"Lake Station",
    "sg:classifiers":[
        {
            "category":"Organizations",
            "subcategory":"Religious Organization",
            "type":"Services"
        }
    ],
    "sg:phone":"+1 219 963 9652",
    "sg:postcode":"46405",
    "sg:province":"IN",
    "sg:tags":[
        "church"
    ],
    "wof:name":"Defenders Faith Ctr",
    "wof:placetype":"venue"
},
  "geometry": {"coordinates":[-87.260491,41.570571],"type":"Point"}
}