{
  "type": "Feature",
  "properties": {
    "iso:country":"US",
    "sg:address":"7367 E Co Rd 725 S",
    "sg:city":"Hardinsburg",
    "sg:phone":"+1 812 472 3925",
    "sg:postcode":"47125",
    "sg:province":"IN",
    "sg:tags":[
        "farm",
        "corn"
    ],
    "wof:name":"Charles Drury",
    "wof:placetype":"venue"
},
  "geometry": {"coordinates":[-86.318986,38.448581],"type":"Point"}
}