{
  "type": "Feature",
  "properties": {
    "iso:country":"US",
    "sg:address":"926 E McKinley Ave",
    "sg:city":"Mishawaka",
    "sg:classifiers":[
        {
            "category":"Manufacturing",
            "subcategory":"Tools & Machinery",
            "type":"Manufacturing & Wholesale Goods"
        }
    ],
    "sg:phone":"+1 574 256 5023",
    "sg:postcode":"46545",
    "sg:province":"IN",
    "sg:tags":[
        "machine",
        "shop"
    ],
    "wof:name":"K & L Machine Mfg Inc",
    "wof:placetype":"venue"
},
  "geometry": {"coordinates":[-86.16830299999999,41.68047],"type":"Point"}
}