{
  "type": "Feature",
  "properties": {
    "addr:full":"521 N Chauncey St Columbia City IN 46725",
    "addr:housenumber":"521",
    "addr:postcode":"46725",
    "addr:street":"N Chauncey St",
    "iso:country":"US",
    "sg:address":"521 N Chauncey St",
    "sg:city":"Columbia City",
    "sg:classifiers":[
        {
            "category":"Retail",
            "subcategory":"Auto Repair",
            "type":"Services"
        }
    ],
    "sg:phone":"+1 260 244 5904",
    "sg:postcode":"46725",
    "sg:province":"IN",
    "sg:tags":[
        "wrecker"
    ],
    "wof:name":"Smith Brothers Svc",
    "wof:placetype":"venue"
},
  "geometry": {"coordinates":[-85.490027,41.164092],"type":"Point"}
}