{
  "type": "Feature",
  "properties": {
    "addr:full":"126 Woodhill Ln South Bend IN 46619",
    "addr:housenumber":"126",
    "addr:postcode":"46619",
    "addr:street":"Woodhill Ln",
    "iso:country":"US",
    "sg:address":"126 Woodhill Ln",
    "sg:city":"South Bend",
    "sg:classifiers":[
        {
            "category":"Organizations",
            "subcategory":"Religious Organization",
            "type":"Services"
        }
    ],
    "sg:phone":"+1 574 233 2683",
    "sg:postcode":"46619",
    "sg:province":"IN",
    "wof:name":"Bethlhem Bptst Chrch In S Bend",
    "wof:placetype":"venue"
},
  "geometry": {"coordinates":[-86.31740600000001,41.678163],"type":"Point"}
}