{
  "type": "Feature",
  "properties": {
    "iso:country":"US",
    "sg:address":"1426 Canal Rd",
    "sg:city":"Lafayette",
    "sg:classifiers":[
        {
            "category":"Building & Trades",
            "subcategory":"Construction",
            "type":"Services"
        }
    ],
    "sg:phone":"+1 765 742 1717",
    "sg:postcode":"47904",
    "sg:province":"IN",
    "sg:tags":[
        "water",
        "well",
        "drilling"
    ],
    "wof:name":"Dilden Bros Well Drilling Inc",
    "wof:placetype":"venue"
},
  "geometry": {"coordinates":[-86.890048,40.430947],"type":"Point"}
}