{
  "type": "Feature",
  "properties": {
    "iso:country":"US",
    "sg:address":"1555 W Oak St",
    "sg:city":"Zionsville",
    "sg:classifiers":[
        {
            "category":"Professional",
            "subcategory":"Management & Consulting",
            "type":"Services"
        }
    ],
    "sg:phone":"+1 317 733 9770",
    "sg:postcode":"46077",
    "sg:province":"IN",
    "sg:tags":[
        "consultant",
        "writing"
    ],
    "wof:name":"Weintraut & Assoc Inc",
    "wof:placetype":"venue"
},
  "geometry": {"coordinates":[-86.280918,39.949992],"type":"Point"}
}