{
  "type": "Feature",
  "properties": {
    "addr:full":"1241 Avalon Cir Greenwood IN 46142",
    "addr:housenumber":"1241",
    "addr:postcode":"46142",
    "addr:street":"Avalon Cir",
    "iso:country":"US",
    "sg:address":"1241 Avalon Cir",
    "sg:city":"Greenwood",
    "sg:classifiers":[
        {
            "category":"Building & Trades",
            "subcategory":"Construction",
            "type":"Services"
        }
    ],
    "sg:phone":"+1 317 339 6116",
    "sg:postcode":"46142",
    "sg:province":"IN",
    "sg:tags":[
        "home",
        "general",
        "remodeling",
        "family",
        "contractor"
    ],
    "wof:name":"Indy's Best Remodeling Inc",
    "wof:placetype":"venue"
},
  "geometry": {"coordinates":[-86.14268,39.614],"type":"Point"}
}