{
  "type": "Feature",
  "properties": {
    "iso:country":"US",
    "sg:address":"14360 N Rock Run Church Rd",
    "sg:city":"Rosedale",
    "sg:classifiers":[
        {
            "category":"Organizations",
            "subcategory":"Religious Organization",
            "type":"Services"
        }
    ],
    "sg:phone":"+1 812 446 0234",
    "sg:postcode":"47874",
    "sg:province":"IN",
    "wof:name":"Rock Run Church",
    "wof:placetype":"venue"
},
  "geometry": {"coordinates":[-87.17435999999999,39.598784],"type":"Point"}
}