{
  "type": "Feature",
  "properties": {
    "iso:country":"US",
    "sg:address":"2909 E 28th St",
    "sg:city":"Indianapolis",
    "sg:classifiers":[
        {
            "category":"Organizations",
            "subcategory":"Religious Organization",
            "type":"Services"
        }
    ],
    "sg:phone":"+1 317 925 9753",
    "sg:postcode":"46218",
    "sg:province":"IN",
    "sg:tags":[
        "church"
    ],
    "wof:name":"Church Of The First Born Saint",
    "wof:placetype":"venue"
},
  "geometry": {"coordinates":[-86.114975,39.806921],"type":"Point"}
}