{
  "type": "Feature",
  "properties": {
    "iso:country":"US",
    "sg:address":"6950 W 34th St",
    "sg:city":"Indianapolis",
    "sg:classifiers":[
        {
            "category":"Education",
            "subcategory":"School",
            "type":"Public Place"
        }
    ],
    "sg:phone":"+1 317 387 7500",
    "sg:postcode":"46214",
    "sg:province":"IN",
    "wof:name":"North Wayne Elementary School",
    "wof:placetype":"venue"
},
  "geometry": {"coordinates":[-86.282502,39.816074],"type":"Point"}
}