{
  "type": "Feature",
  "properties": {
    "iso:country":"US",
    "sg:address":"3648 Commerce Dr",
    "sg:city":"Warsaw",
    "sg:classifiers":[
        {
            "category":"Shopping",
            "subcategory":"Department Store",
            "type":"Retail Goods"
        }
    ],
    "sg:phone":"+1 574 267 0005",
    "sg:postcode":"46580",
    "sg:province":"IN",
    "sg:tags":[
        "shop"
    ],
    "wof:name":"Dollar Tree",
    "wof:placetype":"venue"
},
  "geometry": {"coordinates":[-85.803059,41.231143],"type":"Point"}
}