{
  "type": "Feature",
  "properties": {
    "iso:country":"US",
    "sg:address":"2248 E 38th St",
    "sg:city":"Indianapolis",
    "sg:classifiers":[
        {
            "category":"Restaurant",
            "type":"Food & Drink"
        }
    ],
    "sg:phone":"+1 317 543 3500",
    "sg:postcode":"46218",
    "sg:province":"IN",
    "wof:name":"Nu World Cafe",
    "wof:placetype":"venue"
},
  "geometry": {"coordinates":[-86.123678,39.825461],"type":"Point"}
}