{
  "type": "Feature",
  "properties": {
    "iso:country":"US",
    "sg:address":"8919 Roberts Rd",
    "sg:city":"Woodburn",
    "sg:classifiers":[
        {
            "category":"Building & Trades",
            "subcategory":"Construction",
            "type":"Services"
        }
    ],
    "sg:phone":"+1 260 657 5262",
    "sg:postcode":"46797",
    "sg:province":"IN",
    "sg:tags":[
        "concrete",
        "contractor"
    ],
    "wof:name":"Todd Delagrange",
    "wof:placetype":"venue"
},
  "geometry": {"coordinates":[-84.92219,41.168504],"type":"Point"}
}