{
  "type": "Feature",
  "properties": {
    "iso:country":"US",
    "sg:address":"1049 E Tabor St",
    "sg:city":"Indianapolis",
    "sg:classifiers":[
        {
            "category":"Professional",
            "subcategory":"Business Services",
            "type":"Services"
        }
    ],
    "sg:phone":"+1 317 788 6978",
    "sg:postcode":"46203",
    "sg:province":"IN",
    "sg:tags":[
        "organizing"
    ],
    "wof:name":"Mexican Civic Assn Of Indiana",
    "wof:placetype":"venue"
},
  "geometry": {"coordinates":[-86.140633,39.736359],"type":"Point"}
}