{
  "type": "Feature",
  "properties": {
    "iso:country":"US",
    "sg:address":"8395 Keystone Xing",
    "sg:city":"Indianapolis",
    "sg:classifiers":[
        {
            "category":"Professional",
            "subcategory":"Lawyer & Legal Services",
            "type":"Services"
        }
    ],
    "sg:phone":"+1 317 479 2062",
    "sg:postcode":"46240",
    "sg:province":"IN",
    "sg:tags":[
        "attorney"
    ],
    "wof:name":"Weiss Law Office",
    "wof:placetype":"venue"
},
  "geometry": {"coordinates":[-86.117175,39.907207],"type":"Point"}
}