{
  "type": "Feature",
  "properties": {
    "iso:country":"US",
    "sg:address":"808 E Lyons St",
    "sg:city":"Swayzee",
    "sg:classifiers":[
        {
            "category":"Real Estate",
            "subcategory":"Real Estate Operator",
            "type":"Services"
        }
    ],
    "sg:phone":"+1 765 922 7007",
    "sg:postcode":"46986",
    "sg:province":"IN",
    "sg:tags":[
        "mobile",
        "home",
        "site"
    ],
    "wof:name":"Carters Mobile Home Park",
    "wof:placetype":"venue"
},
  "geometry": {"coordinates":[-85.816851,40.508225],"type":"Point"}
}