{
  "type": "Feature",
  "properties": {
    "addr:full":"11685 Belle Plaine Blvd Fishers IN 46037",
    "addr:housenumber":"11685",
    "addr:postcode":"46037",
    "addr:street":"Belle Plaine Blvd",
    "iso:country":"US",
    "sg:address":"11685 Belle Plaine Blvd",
    "sg:city":"Fishers",
    "sg:classifiers":[
        {
            "category":"Professional",
            "subcategory":"Business Services",
            "type":"Services"
        }
    ],
    "sg:phone":"+1 317 841 9353",
    "sg:postcode":"46037",
    "sg:province":"IN",
    "wof:name":"Myers Property Group LLC",
    "wof:placetype":"venue"
},
  "geometry": {"coordinates":[-85.96880899999999,39.959461],"type":"Point"}
}