{
  "type": "Feature",
  "properties": {
    "iso:country":"US",
    "sg:address":"180 Front St",
    "sg:city":"Rome City",
    "sg:classifiers":[
        {
            "category":"Personal",
            "subcategory":"Beauty Salon",
            "type":"Services"
        }
    ],
    "sg:phone":"+1 260 854 4140",
    "sg:postcode":"46784",
    "sg:province":"IN",
    "wof:name":"Nancy's Cutting Room",
    "wof:placetype":"venue"
},
  "geometry": {"coordinates":[-85.378091,41.496599],"type":"Point"}
}