{
  "type": "Feature",
  "properties": {
    "iso:country":"US",
    "sg:address":"317 Lincoln Way E",
    "sg:city":"Mishawaka",
    "sg:classifiers":[
        {
            "category":"Travel",
            "subcategory":"Hotels & Motels",
            "type":"Entertainment"
        }
    ],
    "sg:phone":"+1 574 255 3939",
    "sg:postcode":"46544",
    "sg:province":"IN",
    "sg:tags":[
        "breakfast",
        "accommodation",
        "bed"
    ],
    "sg:website":"www.beigermansion.com",
    "wof:name":"Beiger Mansion Inn",
    "wof:placetype":"venue"
},
  "geometry": {"coordinates":[-86.177001,41.661049],"type":"Point"}
}