{
  "type": "Feature",
  "properties": {
    "iso:country":"US",
    "sg:address":"547 Reed Ct",
    "sg:city":"Greenwood",
    "sg:classifiers":[
        {
            "category":"Building & Trades",
            "subcategory":"Landscaping Services",
            "type":"Services"
        }
    ],
    "sg:phone":"+1 317 882 2030",
    "sg:postcode":"46143",
    "sg:province":"IN",
    "sg:tags":[
        "landscape",
        "contractor"
    ],
    "wof:name":"Anderson Landscaping",
    "wof:placetype":"venue"
},
  "geometry": {"coordinates":[-86.116711,39.596078],"type":"Point"}
}