{
  "type": "Feature",
  "properties": {
    "iso:country":"US",
    "sg:address":"641 W Dragoon Trl",
    "sg:city":"Mishawaka",
    "sg:classifiers":[
        {
            "category":"Organizations",
            "subcategory":"Community Association",
            "type":"Services"
        }
    ],
    "sg:phone":"+1 574 258 9089",
    "sg:postcode":"46546",
    "sg:province":"IN",
    "wof:name":"Blair Hill Rec Ctr",
    "wof:placetype":"venue"
},
  "geometry": {"coordinates":[-86.187928,41.644511],"type":"Point"}
}