{
  "type": "Feature",
  "properties": {
    "iso:country":"US",
    "sg:address":"123 N Mc Creary St",
    "sg:city":"Fort Branch",
    "sg:classifiers":[
        {
            "category":"Health Services",
            "subcategory":"Doctor",
            "type":"Services"
        }
    ],
    "sg:phone":"+1 812 753 1039",
    "sg:postcode":"47648",
    "sg:province":"IN",
    "sg:tags":[
        "clinic"
    ],
    "wof:name":"Tulip Tree Health Svc",
    "wof:placetype":"venue"
},
  "geometry": {"coordinates":[-87.580003,38.247702],"type":"Point"}
}