{
  "type": "Feature",
  "properties": {
    "iso:country":"US",
    "sg:address":"6009 N State Rd 39",
    "sg:city":"La Porte",
    "sg:classifiers":[
        {
            "category":"Autos & Motor Vehicles",
            "subcategory":"Automobile Sales",
            "type":"Retail Goods"
        }
    ],
    "sg:phone":"+1 219 767 2846",
    "sg:postcode":"46350",
    "sg:province":"IN",
    "wof:name":"Car Corner",
    "wof:placetype":"venue"
},
  "geometry": {"coordinates":[-86.735561,41.693658],"type":"Point"}
}