{
  "type": "Feature",
  "properties": {
    "addr:full":"658 Eagle Creek Cir Zionsville IN 46077",
    "addr:housenumber":"658",
    "addr:postcode":"46077",
    "addr:street":"Eagle Creek Cir",
    "iso:country":"US",
    "sg:address":"658 Eagle Creek Cir",
    "sg:city":"Zionsville",
    "sg:classifiers":[
        {
            "category":"Retail",
            "subcategory":"Repair Shop",
            "type":"Services"
        }
    ],
    "sg:phone":"+1 317 873 2677",
    "sg:postcode":"46077",
    "sg:province":"IN",
    "sg:tags":[
        "electrical"
    ],
    "wof:name":"Appliance Parts Inc",
    "wof:placetype":"venue"
},
  "geometry": {"coordinates":[-86.254054,39.952538],"type":"Point"}
}