{
  "type": "Feature",
  "properties": {
    "iso:country":"US",
    "sg:address":"1302 State St",
    "sg:city":"New Albany",
    "sg:classifiers":[
        {
            "category":"Personal",
            "subcategory":"Barber",
            "type":"Services"
        }
    ],
    "sg:phone":"+1 812 945 0720",
    "sg:postcode":"47150",
    "sg:province":"IN",
    "wof:name":"De Jays Barber Shop",
    "wof:placetype":"venue"
},
  "geometry": {"coordinates":[-85.830665,38.296357],"type":"Point"}
}