{
  "type": "Feature",
  "properties": {
    "addr:full":"3401 Oregon St Lake Station IN 46405",
    "addr:housenumber":"3401",
    "addr:postcode":"46405",
    "addr:street":"Oregon St",
    "iso:country":"US",
    "sg:address":"3401 Oregon St",
    "sg:city":"Lake Station",
    "sg:classifiers":[
        {
            "category":"Recreation",
            "type":"Entertainment"
        }
    ],
    "sg:phone":"+1 219 962 6822",
    "sg:postcode":"46405",
    "sg:province":"IN",
    "sg:tags":[
        "parks"
    ],
    "wof:name":"Hobart Township Park Dept",
    "wof:placetype":"venue"
},
  "geometry": {"coordinates":[-87.302632,41.555099],"type":"Point"}
}