{
  "type": "Feature",
  "properties": {
    "addr:full":"3608 E Michigan Blvd Michigan City IN 46360",
    "addr:housenumber":"3608",
    "addr:postcode":"46360",
    "addr:street":"E Michigan Blvd",
    "iso:country":"US",
    "sg:address":"3608 E Michigan Blvd",
    "sg:city":"Michigan City",
    "sg:classifiers":[
        {
            "category":"Manufacturing",
            "subcategory":"Glass & Minerals",
            "type":"Manufacturing & Wholesale Goods"
        }
    ],
    "sg:phone":"+1 219 874 6219",
    "sg:postcode":"46360",
    "sg:province":"IN",
    "sg:tags":[
        "ready"
    ],
    "wof:name":"Smith Ready Mix Inc",
    "wof:placetype":"venue"
},
  "geometry": {"coordinates":[-86.845972,41.702791],"type":"Point"}
}