{
  "type": "Feature",
  "properties": {
    "iso:country":"US",
    "sg:address":"3100 John Hinkle Pl",
    "sg:city":"Bloomington",
    "sg:classifiers":[
        {
            "category":"Real Estate",
            "subcategory":"Real Estate Services",
            "type":"Services"
        }
    ],
    "sg:phone":"+1 812 333 2380",
    "sg:postcode":"47408",
    "sg:province":"IN",
    "sg:tags":[
        "company",
        "title"
    ],
    "wof:name":"Nations Title Agency",
    "wof:placetype":"venue"
},
  "geometry": {"coordinates":[-86.49378299999999,39.170353],"type":"Point"}
}