{
  "type": "Feature",
  "properties": {
    "addr:full":"1015 Wildwood Ln New Albany IN 47150",
    "addr:housenumber":"1015",
    "addr:postcode":"47150",
    "addr:street":"Wildwood Ln",
    "iso:country":"US",
    "sg:address":"1015 Wildwood Ln",
    "sg:city":"New Albany",
    "sg:classifiers":[
        {
            "category":"Restaurant",
            "type":"Food & Drink"
        }
    ],
    "sg:phone":"+1 812 949 1947",
    "sg:postcode":"47150",
    "sg:province":"IN",
    "sg:tags":[
        "eating"
    ],
    "wof:name":"Sweet Sensations LLC",
    "wof:placetype":"venue"
},
  "geometry": {"coordinates":[-85.85873599999999,38.299745],"type":"Point"}
}