{
  "type": "Feature",
  "properties": {
    "addr:full":"1502 Research Dr Jeffersonville IN 47130",
    "addr:housenumber":"1502",
    "addr:postcode":"47130",
    "addr:street":"Research Dr",
    "iso:country":"US",
    "sg:address":"1502 Research Dr",
    "sg:city":"Jeffersonville",
    "sg:classifiers":[
        {
            "category":"Autos & Motor Vehicles",
            "subcategory":"Auto Supplies",
            "type":"Retail Goods"
        },
        {
            "category":"Retail",
            "subcategory":"Car Wash",
            "type":"Services"
        },
        {
            "category":"Retail",
            "subcategory":"Auto Repair",
            "type":"Services"
        }
    ],
    "sg:phone":"+1 812 280 8400",
    "sg:postcode":"47130",
    "sg:province":"IN",
    "sg:tags":[
        "body",
        "automobile",
        "detailing",
        "part",
        "painting",
        "repairing"
    ],
    "sg:website":"http://Jeffersonville.maaco.com",
    "wof:name":"Maaco - Jeffersonville",
    "wof:placetype":"venue"
},
  "geometry": {"coordinates":[-85.750056,38.309059],"type":"Point"}
}