{
  "type": "Feature",
  "properties": {
    "iso:country":"US",
    "sg:address":"4217 Central Ave",
    "sg:city":"Indianapolis",
    "sg:classifiers":[
        {
            "category":"Social Services",
            "type":"Services"
        }
    ],
    "sg:phone":"+1 317 283 6710",
    "sg:postcode":"46205",
    "sg:province":"IN",
    "wof:name":"Sja Nighborhood Youth Outreach",
    "wof:placetype":"venue"
},
  "geometry": {"coordinates":[-86.149763,39.83355],"type":"Point"}
}