{
  "type": "Feature",
  "properties": {
    "iso:country":"US",
    "sg:address":"4302 W Western Ave",
    "sg:city":"South Bend",
    "sg:classifiers":[
        {
            "category":"Government",
            "subcategory":"Fire Station",
            "type":"Public Place"
        }
    ],
    "sg:phone":"+1 574 235 9691",
    "sg:postcode":"46619",
    "sg:province":"IN",
    "sg:tags":[
        "department"
    ],
    "wof:name":"South Bend Fire Dept",
    "wof:placetype":"venue"
},
  "geometry": {"coordinates":[-86.308043,41.671789],"type":"Point"}
}