{
  "type": "Feature",
  "properties": {
    "iso:country":"US",
    "sg:address":"108 W Jefferson St",
    "sg:city":"Franklin",
    "sg:classifiers":[
        {
            "category":"Personal",
            "subcategory":"Tanning Parlor",
            "type":"Services"
        }
    ],
    "sg:phone":"+1 317 736 9263",
    "sg:postcode":"46131",
    "sg:province":"IN",
    "sg:tags":[
        "salon"
    ],
    "wof:name":"Sun Star Tanning",
    "wof:placetype":"venue"
},
  "geometry": {"coordinates":[-86.05673,39.480542],"type":"Point"}
}