{
  "type": "Feature",
  "properties": {
    "iso:country":"US",
    "sg:address":"8995 S Main St",
    "sg:city":"Petroleum",
    "sg:classifiers":[
        {
            "category":"Arts & Performance",
            "subcategory":"Theater",
            "type":"Entertainment"
        }
    ],
    "sg:phone":"+1 260 346 2565",
    "sg:postcode":"46766",
    "sg:province":"IN",
    "sg:tags":[
        "live",
        "music"
    ],
    "wof:name":"Tony's Music For All Occasions",
    "wof:placetype":"venue"
},
  "geometry": {"coordinates":[-85.27904700000001,40.691144],"type":"Point"}
}