{
  "type": "Feature",
  "properties": {
    "iso:country":"US",
    "sg:address":"108 E Lincolnway",
    "sg:city":"Laporte",
    "sg:classifiers":[
        {
            "category":"Retail",
            "subcategory":"Auto Repair",
            "type":"Services"
        }
    ],
    "sg:phone":"+1 219 326 0009",
    "sg:postcode":"46350",
    "sg:province":"IN",
    "sg:tags":[
        "muffler",
        "exhaust",
        "system"
    ],
    "wof:name":"APEX",
    "wof:placetype":"venue"
},
  "geometry": {"coordinates":[-86.714016,41.614874],"type":"Point"}
}