{
  "type": "Feature",
  "properties": {
    "iso:country":"US",
    "sg:address":"5790 E 131st St",
    "sg:city":"Carmel",
    "sg:classifiers":[
        {
            "category":"Food & Beverages",
            "subcategory":"Specialty",
            "type":"Retail Goods"
        }
    ],
    "sg:phone":"+1 317 819 2770",
    "sg:postcode":"46033",
    "sg:province":"IN",
    "sg:tags":[
        "tea",
        "coffee"
    ],
    "wof:name":"Hubbard & Cravens Coffee Co",
    "wof:placetype":"venue"
},
  "geometry": {"coordinates":[-86.07352899999999,39.978537],"type":"Point"}
}