{
  "type": "Feature",
  "properties": {
    "iso:country":"US",
    "sg:address":"1033 W McKinley Ave",
    "sg:city":"Mishawaka",
    "sg:classifiers":[
        {
            "category":"Retail",
            "subcategory":"Auto Rental",
            "type":"Services"
        }
    ],
    "sg:phone":"+1 574 258 5612",
    "sg:postcode":"46545",
    "sg:province":"IN",
    "sg:tags":[
        "renting",
        "automobile"
    ],
    "wof:name":"Xxpert Rent-A-Car",
    "wof:placetype":"venue"
},
  "geometry": {"coordinates":[-86.195381,41.680203],"type":"Point"}
}