{
  "type": "Feature",
  "properties": {
    "addr:full":"419 Park Ave Chesterton IN 46304",
    "addr:housenumber":"419",
    "addr:postcode":"46304",
    "addr:street":"Park Ave",
    "iso:country":"US",
    "sg:address":"419 Park Ave",
    "sg:city":"Chesterton",
    "sg:classifiers":[
        {
            "category":"Building & Trades",
            "subcategory":"Plumbing",
            "type":"Services"
        }
    ],
    "sg:phone":"+1 219 926 6719",
    "sg:postcode":"46304",
    "sg:province":"IN",
    "sg:tags":[
        "contractor"
    ],
    "wof:name":"Dille Heating & Cooling",
    "wof:placetype":"venue"
},
  "geometry": {"coordinates":[-87.056454,41.604798],"type":"Point"}
}