{
  "type": "Feature",
  "properties": {
    "iso:country":"US",
    "sg:address":"8751 N 850 E",
    "sg:city":"Syracuse",
    "sg:classifiers":[
        {
            "category":"Professional",
            "type":"Services"
        }
    ],
    "sg:phone":"+1 574 834 2134",
    "sg:postcode":"46555",
    "sg:province":"IN",
    "wof:name":"Trebur Astheim Inc",
    "wof:placetype":"venue"
},
  "geometry": {"coordinates":[-85.682178,41.363181],"type":"Point"}
}