{
  "type": "Feature",
  "properties": {
    "addr:full":"8040 E Washington St Indianapolis IN 46219",
    "addr:housenumber":"8040",
    "addr:postcode":"46219",
    "addr:street":"E Washington St",
    "iso:country":"US",
    "sg:address":"8040 E Washington St",
    "sg:city":"Indianapolis",
    "sg:classifiers":[
        {
            "category":"Retail",
            "subcategory":"Veterinary Services",
            "type":"Services"
        }
    ],
    "sg:phone":"+1 317 897 0951",
    "sg:postcode":"46219",
    "sg:province":"IN",
    "sg:tags":[
        "hospital",
        "animal"
    ],
    "sg:website":"www.amcindy.com",
    "wof:name":"Animal Medical Ctr",
    "wof:placetype":"venue"
},
  "geometry": {"coordinates":[-86.02512299999999,39.77318],"type":"Point"}
}