{
  "type": "Feature",
  "properties": {
    "addr:full":"27084 Stipps Hill Rd Laurel IN 47024",
    "addr:postcode":"27084;47024",
    "addr:street":"Stipps Hill Rd",
    "iso:country":"US",
    "sg:address":"27084 Stipps Hill Rd",
    "sg:city":"Laurel",
    "sg:classifiers":[
        {
            "category":"Building & Trades",
            "subcategory":"Electrical",
            "type":"Services"
        }
    ],
    "sg:phone":"+1 812 527 2047",
    "sg:postcode":"47024",
    "sg:province":"IN",
    "sg:tags":[
        "electric",
        "contractor"
    ],
    "wof:name":"Robbins Electric",
    "wof:placetype":"venue"
},
  "geometry": {"coordinates":[-85.28722999999999,39.438545],"type":"Point"}
}