{
  "type": "Feature",
  "properties": {
    "iso:country":"US",
    "sg:address":"19816 Huber Rd",
    "sg:city":"Borden",
    "sg:classifiers":[
        {
            "category":"Farming",
            "subcategory":"Orchard",
            "type":"Manufacturing & Wholesale Goods"
        }
    ],
    "sg:phone":"+1 812 923 9813",
    "sg:postcode":"47106",
    "sg:province":"IN",
    "sg:tags":[
        "grove",
        "management"
    ],
    "wof:name":"Huber Orchard Winery & Gift",
    "wof:placetype":"venue"
},
  "geometry": {"coordinates":[-85.929839,38.423835],"type":"Point"}
}