{
  "type": "Feature",
  "properties": {
    "iso:country":"US",
    "sg:address":"11899 W Oakdale Dr",
    "sg:city":"Monticello",
    "sg:classifiers":[
        {
            "category":"Restaurant",
            "type":"Food & Drink"
        }
    ],
    "sg:phone":"+1 574 965 9104",
    "sg:postcode":"47960",
    "sg:province":"IN",
    "wof:name":"Oakdale Inn Restaurant & Bar",
    "wof:placetype":"venue"
},
  "geometry": {"coordinates":[-86.753534,40.653212],"type":"Point"}
}