{
  "type": "Feature",
  "properties": {
    "iso:country":"US",
    "sg:address":"10167 Watkins Dr",
    "sg:city":"Indianapolis",
    "sg:classifiers":[
        {
            "category":"Professional",
            "type":"Services"
        }
    ],
    "sg:phone":"+1 317 209 9904",
    "sg:postcode":"46234",
    "sg:province":"IN",
    "wof:name":"A1 Home Services LLC",
    "wof:placetype":"venue"
},
  "geometry": {"coordinates":[-86.342216,39.776079],"type":"Point"}
}