{
  "type": "Feature",
  "properties": {
    "iso:country":"US",
    "sg:address":"3103 N National Rd",
    "sg:city":"Columbus",
    "sg:classifiers":[
        {
            "category":"Autos & Motor Vehicles",
            "subcategory":"Auto Supplies",
            "type":"Retail Goods"
        }
    ],
    "sg:phone":"+1 812 378 0974",
    "sg:postcode":"47201",
    "sg:province":"IN",
    "sg:tags":[
        "automobile",
        "parts"
    ],
    "wof:name":"Southern Indiana Auto Parts",
    "wof:placetype":"venue"
},
  "geometry": {"coordinates":[-85.904191,39.229929],"type":"Point"}
}