{
  "type": "Feature",
  "properties": {
    "iso:country":"US",
    "sg:address":"10735 Pendleton Pike",
    "sg:city":"Indianapolis",
    "sg:classifiers":[
        {
            "category":"Restaurant",
            "type":"Food & Drink"
        }
    ],
    "sg:phone":"+1 317 826 0602",
    "sg:postcode":"46236",
    "sg:province":"IN",
    "wof:name":"Mc Donald's",
    "wof:placetype":"venue"
},
  "geometry": {"coordinates":[-85.981083,39.858473],"type":"Point"}
}