{
  "type": "Feature",
  "properties": {
    "iso:country":"US",
    "sg:address":"514 S Main St",
    "sg:city":"Elkhart",
    "sg:classifiers":[
        {
            "category":"Professional",
            "subcategory":"Lawyer & Legal Services",
            "type":"Services"
        }
    ],
    "sg:phone":"+1 574 295 6924",
    "sg:postcode":"46516",
    "sg:province":"IN",
    "sg:tags":[
        "attorney"
    ],
    "wof:name":"Charles C Wicks Law Offices",
    "wof:placetype":"venue"
},
  "geometry": {"coordinates":[-85.971219,41.682953],"type":"Point"}
}