{
  "type": "Feature",
  "properties": {
    "iso:country":"US",
    "sg:address":"2821 Sable Mill Ln",
    "sg:city":"Jeffersonville",
    "sg:classifiers":[
        {
            "category":"Wholesale",
            "subcategory":"Metals & Minerals",
            "type":"Manufacturing & Wholesale Goods"
        }
    ],
    "sg:phone":"+1 812 280 0100",
    "sg:postcode":"47130",
    "sg:province":"IN",
    "sg:tags":[
        "pipe"
    ],
    "wof:name":"Consolidated Pipe & Supply Co",
    "wof:placetype":"venue"
},
  "geometry": {"coordinates":[-85.742462,38.312091],"type":"Point"}
}