{
  "type": "Feature",
  "properties": {
    "iso:country":"US",
    "sg:address":"9333 Monique Dr",
    "sg:city":"Fort Wayne",
    "sg:classifiers":[
        {
            "category":"Organizations",
            "subcategory":"Religious Organization",
            "type":"Services"
        }
    ],
    "sg:phone":"+1 260 485 3061",
    "sg:postcode":"46835",
    "sg:province":"IN",
    "wof:name":"Hunters Point Community A",
    "wof:placetype":"venue"
},
  "geometry": {"coordinates":[-85.023443,41.148133],"type":"Point"}
}