{
  "type": "Feature",
  "properties": {
    "iso:country":"US",
    "sg:address":"2424 Teal Rd",
    "sg:city":"Lafayette",
    "sg:classifiers":[
        {
            "category":"Shopping",
            "subcategory":"Bicycles & Sporting Goods",
            "type":"Retail Goods"
        }
    ],
    "sg:phone":"+1 765 474 6478",
    "sg:postcode":"47905",
    "sg:province":"IN",
    "wof:name":"Athlete Inc",
    "wof:placetype":"venue"
},
  "geometry": {"coordinates":[-86.86870999999999,40.395565],"type":"Point"}
}