{
  "type": "Feature",
  "properties": {
    "iso:country":"US",
    "sg:address":"790 Washington St",
    "sg:city":"Tell City",
    "sg:classifiers":[
        {
            "category":"Retail",
            "subcategory":"Self-service Laundry",
            "type":"Services"
        }
    ],
    "sg:phone":"+1 812 547 8827",
    "sg:postcode":"47586",
    "sg:province":"IN",
    "sg:tags":[
        "coin"
    ],
    "wof:name":"Econ O Wash Laundry",
    "wof:placetype":"venue"
},
  "geometry": {"coordinates":[-86.769916,37.944678],"type":"Point"}
}