{
  "type": "Feature",
  "properties": {
    "iso:country":"US",
    "sg:address":"604 Tavern St",
    "sg:city":"New Harmony",
    "sg:classifiers":[
        {
            "category":"Professional",
            "type":"Services"
        }
    ],
    "sg:phone":"+1 812 682 4523",
    "sg:postcode":"47631",
    "sg:province":"IN",
    "sg:tags":[
        "establishment"
    ],
    "wof:name":"Scholle House",
    "wof:placetype":"venue"
},
  "geometry": {"coordinates":[-87.933312,38.129075],"type":"Point"}
}