{
  "type": "Feature",
  "properties": {
    "addr:full":"711 S Bend Ave South Bend IN 46617",
    "addr:housenumber":"711",
    "addr:postcode":"46617",
    "addr:street":"S Bend Ave",
    "iso:country":"US",
    "sg:address":"711 S Bend Ave",
    "sg:city":"South Bend",
    "sg:classifiers":[
        {
            "category":"Health Services",
            "subcategory":"Health Practitioner",
            "type":"Services"
        }
    ],
    "sg:phone":"+1 574 233 7653",
    "sg:postcode":"46617",
    "sg:province":"IN",
    "sg:tags":[
        "psychologist"
    ],
    "wof:name":"George Feden PHD",
    "wof:placetype":"venue"
},
  "geometry": {"coordinates":[-86.240656,41.684112],"type":"Point"}
}