{
  "type": "Feature",
  "properties": {
    "iso:country":"US",
    "sg:address":"718 N Spring St",
    "sg:city":"Hartford City",
    "sg:classifiers":[
        {
            "category":"Professional",
            "subcategory":"Computer Services",
            "type":"Services"
        }
    ],
    "sg:phone":"+1 765 348 5869",
    "sg:postcode":"47348",
    "sg:province":"IN",
    "sg:tags":[
        "repair"
    ],
    "wof:name":"Personal Computer Doctors",
    "wof:placetype":"venue"
},
  "geometry": {"coordinates":[-85.36193299999999,40.454917],"type":"Point"}
}