{
  "type": "Feature",
  "properties": {
    "iso:country":"US",
    "sg:address":"9595 State Rd 64",
    "sg:city":"Georgetown",
    "sg:classifiers":[
        {
            "category":"Building & Trades",
            "subcategory":"Electrical",
            "type":"Services"
        }
    ],
    "sg:phone":"+1 812 951 1656",
    "sg:postcode":"47122",
    "sg:province":"IN",
    "sg:tags":[
        "electric",
        "contractor"
    ],
    "wof:name":"Deuser Electric",
    "wof:placetype":"venue"
},
  "geometry": {"coordinates":[-85.986735,38.297067],"type":"Point"}
}