{
  "type": "Feature",
  "properties": {
    "addr:full":"901 E 30th St Indianapolis IN 46205",
    "addr:housenumber":"901",
    "addr:postcode":"46205",
    "addr:street":"E 30Th St",
    "iso:country":"US",
    "sg:address":"901 E 30th St",
    "sg:city":"Indianapolis",
    "sg:classifiers":[
        {
            "category":"Restaurant",
            "type":"Food & Drink"
        }
    ],
    "sg:phone":"+1 317 283 8257",
    "sg:postcode":"46205",
    "sg:province":"IN",
    "sg:tags":[
        "caterer"
    ],
    "wof:name":"Ducks Restaraunts & Catering",
    "wof:placetype":"venue"
},
  "geometry": {"coordinates":[-86.141066,39.810637],"type":"Point"}
}