{
  "type": "Feature",
  "properties": {
    "iso:country":"US",
    "sg:address":"2924 E 3rd St",
    "sg:city":"Bloomington",
    "sg:classifiers":[
        {
            "category":"Shopping",
            "subcategory":"Department Store",
            "type":"Retail Goods"
        }
    ],
    "sg:phone":"+1 812 336 2555",
    "sg:postcode":"47401",
    "sg:province":"IN",
    "sg:tags":[
        "shop"
    ],
    "wof:name":"Accessories Plus",
    "wof:placetype":"venue"
},
  "geometry": {"coordinates":[-86.493218,39.164131],"type":"Point"}
}