{
  "type": "Feature",
  "properties": {
    "iso:country":"US",
    "sg:address":"216 N Fulton Ave",
    "sg:city":"Evansville",
    "sg:classifiers":[
        {
            "category":"Organizations",
            "subcategory":"Labor Organization",
            "type":"Services"
        }
    ],
    "sg:phone":"+1 812 423 5624",
    "sg:postcode":"47710",
    "sg:province":"IN",
    "wof:name":"International Association-Mach",
    "wof:placetype":"venue"
},
  "geometry": {"coordinates":[-87.58126799999999,37.980181],"type":"Point"}
}