{
  "type": "Feature",
  "properties": {
    "addr:full":"154 W Carmel Dr Carmel IN 46032",
    "addr:housenumber":"154",
    "addr:postcode":"46032",
    "addr:street":"W Carmel Dr",
    "iso:country":"US",
    "sg:address":"154 W Carmel Dr",
    "sg:city":"Carmel",
    "sg:classifiers":[
        {
            "category":"Health Services",
            "subcategory":"Health Practitioner",
            "type":"Services"
        }
    ],
    "sg:phone":"+1 317 818 0404",
    "sg:postcode":"46032",
    "sg:province":"IN",
    "sg:tags":[
        "therapist",
        "physical"
    ],
    "wof:name":"Carmel Rehab",
    "wof:placetype":"venue"
},
  "geometry": {"coordinates":[-86.128557,39.961455],"type":"Point"}
}