{
  "type": "Feature",
  "properties": {
    "iso:country":"US",
    "sg:address":"900 W Market St",
    "sg:city":"Nappanee",
    "sg:classifiers":[
        {
            "category":"Organizations",
            "subcategory":"Religious Organization",
            "type":"Services"
        }
    ],
    "sg:phone":"+1 574 773 7294",
    "sg:postcode":"46550",
    "sg:province":"IN",
    "wof:name":"First Mennonite Church",
    "wof:placetype":"venue"
},
  "geometry": {"coordinates":[-86.011037,41.442762],"type":"Point"}
}