{
  "type": "Feature",
  "properties": {
    "iso:country":"US",
    "sg:address":"1827 N Madison Ave",
    "sg:city":"Anderson",
    "sg:classifiers":[
        {
            "category":"Health Services",
            "subcategory":"Doctor",
            "type":"Services"
        }
    ],
    "sg:phone":"+1 765 642 1882",
    "sg:postcode":"46011",
    "sg:province":"IN",
    "sg:tags":[
        "dentist"
    ],
    "wof:name":"Richard W Weinzapfel DDS",
    "wof:placetype":"venue"
},
  "geometry": {"coordinates":[-85.69152,40.13502],"type":"Point"}
}