{
  "type": "Feature",
  "properties": {
    "addr:full":"511 E 4th St Huntingburg IN 47542",
    "addr:housenumber":"511",
    "addr:postcode":"47542",
    "addr:street":"E 4Th St",
    "iso:country":"US",
    "sg:address":"511 E 4th St",
    "sg:city":"Huntingburg",
    "sg:classifiers":[
        {
            "category":"Personal",
            "subcategory":"Beauty Salon",
            "type":"Services"
        }
    ],
    "sg:phone":"+1 812 683 3940",
    "sg:postcode":"47542",
    "sg:province":"IN",
    "sg:tags":[
        "shop"
    ],
    "wof:name":"Anns Hair Studio",
    "wof:placetype":"venue"
},
  "geometry": {"coordinates":[-86.953209,38.295972],"type":"Point"}
}