{
  "type": "Feature",
  "properties": {
    "iso:country":"US",
    "sg:address":"1717 S Co Rd 450 W",
    "sg:city":"Danville",
    "sg:phone":"+1 317 745 1330",
    "sg:postcode":"46122",
    "sg:province":"IN",
    "sg:tags":[
        "farm",
        "grain",
        "cash"
    ],
    "wof:name":"Dwayne Lundy",
    "wof:placetype":"venue"
},
  "geometry": {"coordinates":[-86.60432900000001,39.735975],"type":"Point"}
}