{
  "type": "Feature",
  "properties": {
    "iso:country":"US",
    "sg:address":"3937 E 82nd St",
    "sg:city":"Indianapolis",
    "sg:classifiers":[
        {
            "category":"Shopping",
            "subcategory":"Gifts & Souvenirs",
            "type":"Retail Goods"
        }
    ],
    "sg:phone":"+1 317 849 7051",
    "sg:postcode":"46240",
    "sg:province":"IN",
    "sg:tags":[
        "shop"
    ],
    "wof:name":"J R Mac Meyer LTD",
    "wof:placetype":"venue"
},
  "geometry": {"coordinates":[-86.099384,39.908123],"type":"Point"}
}