{
  "type": "Feature",
  "properties": {
    "iso:country":"US",
    "sg:address":"4921 Selkirk Dr",
    "sg:city":"South Bend",
    "sg:classifiers":[
        {
            "category":"Shopping",
            "subcategory":"Gifts & Souvenirs",
            "type":"Retail Goods"
        }
    ],
    "sg:phone":"+1 574 315 5095",
    "sg:postcode":"46614",
    "sg:province":"IN",
    "wof:name":"Gift Program",
    "wof:placetype":"venue"
},
  "geometry": {"coordinates":[-86.227743,41.623691],"type":"Point"}
}