{
  "type": "Feature",
  "properties": {
    "iso:country":"US",
    "sg:address":"6624 N Tuxedo Ln",
    "sg:city":"Indianapolis",
    "sg:classifiers":[
        {
            "category":"Building & Trades",
            "subcategory":"Construction",
            "type":"Services"
        }
    ],
    "sg:phone":"+1 317 257 8751",
    "sg:postcode":"46220",
    "sg:province":"IN",
    "sg:tags":[
        "house",
        "nonresidential"
    ],
    "wof:name":"Brookscandoit Inc",
    "wof:placetype":"venue"
},
  "geometry": {"coordinates":[-86.110372,39.87856],"type":"Point"}
}