{
  "type": "Feature",
  "properties": {
    "iso:country":"US",
    "sg:address":"8738 Holliday Dr",
    "sg:city":"Indianapolis",
    "sg:classifiers":[
        {
            "category":"Professional",
            "type":"Services"
        }
    ],
    "sg:phone":"+1 317 848 2904",
    "sg:postcode":"46260",
    "sg:province":"IN",
    "wof:name":"Indyvestnik Inc",
    "wof:placetype":"venue"
},
  "geometry": {"coordinates":[-86.163501,39.915499],"type":"Point"}
}