{
  "type": "Feature",
  "properties": {
    "iso:country":"US",
    "sg:address":"607 Washington St",
    "sg:city":"Columbus",
    "sg:classifiers":[
        {
            "category":"Personal",
            "subcategory":"Beauty Salon",
            "type":"Services"
        }
    ],
    "sg:phone":"+1 812 372 5083",
    "sg:postcode":"47201",
    "sg:province":"IN",
    "wof:name":"LA Mode 607",
    "wof:placetype":"venue"
},
  "geometry": {"coordinates":[-85.921267,39.205556],"type":"Point"}
}