{
  "type": "Feature",
  "properties": {
    "iso:country":"US",
    "sg:address":"208 E Hackett St",
    "sg:city":"Frankfort",
    "sg:classifiers":[
        {
            "category":"Retail",
            "subcategory":"Auto Repair",
            "type":"Services"
        }
    ],
    "sg:phone":"+1 765 654 6216",
    "sg:postcode":"46041",
    "sg:province":"IN",
    "sg:tags":[
        "automobile",
        "electric"
    ],
    "wof:name":"Smith's Electric & Carburetor",
    "wof:placetype":"venue"
},
  "geometry": {"coordinates":[-86.510469,40.270828],"type":"Point"}
}