{
  "type": "Feature",
  "properties": {
    "iso:country":"US",
    "sg:address":"523 S Madison Ave",
    "sg:city":"Greenwood",
    "sg:classifiers":[
        {
            "category":"Education",
            "subcategory":"School",
            "type":"Public Place"
        }
    ],
    "sg:phone":"+1 317 889 4040",
    "sg:postcode":"46142",
    "sg:province":"IN",
    "wof:name":"Greenwood Middle School",
    "wof:placetype":"venue"
},
  "geometry": {"coordinates":[-86.107904,39.60869],"type":"Point"}
}