{
  "type": "Feature",
  "properties": {
    "iso:country":"US",
    "sg:address":"3605 Northgate Ct",
    "sg:city":"New Albany",
    "sg:classifiers":[
        {
            "category":"Health Services",
            "subcategory":"Doctor",
            "type":"Services"
        }
    ],
    "sg:phone":"+1 812 949 1612",
    "sg:postcode":"47150",
    "sg:province":"IN",
    "sg:tags":[
        "physician",
        "surgeon"
    ],
    "wof:name":"Commonwealth Ear Nose & Throat",
    "wof:placetype":"venue"
},
  "geometry": {"coordinates":[-85.816345,38.33203],"type":"Point"}
}