{
  "type": "Feature",
  "properties": {
    "addr:full":"856 N Sandhill Rd Covington IN 47932",
    "addr:housenumber":"856",
    "addr:postcode":"47932",
    "addr:street":"N Sandhill Rd",
    "iso:country":"US",
    "sg:address":"856 N Sandhill Rd",
    "sg:city":"Covington",
    "sg:classifiers":[
        {
            "category":"Building & Trades",
            "subcategory":"Construction",
            "type":"Services"
        }
    ],
    "sg:phone":"+1 765 793 0128",
    "sg:postcode":"47932",
    "sg:province":"IN",
    "sg:tags":[
        "contractor",
        "paving",
        "asphalt",
        "sealcoating"
    ],
    "wof:name":"Hesler Paving & Contracting Inc",
    "wof:placetype":"venue"
},
  "geometry": {"coordinates":[-87.41635599999999,40.157774],"type":"Point"}
}