{
  "type": "Feature",
  "properties": {
    "iso:country":"US",
    "sg:address":"250 Madison St",
    "sg:city":"Charlestown",
    "sg:classifiers":[
        {
            "category":"Building & Trades",
            "subcategory":"Electrical",
            "type":"Services"
        }
    ],
    "sg:phone":"+1 812 256 3042",
    "sg:postcode":"47111",
    "sg:province":"IN",
    "sg:tags":[
        "electric",
        "contractor"
    ],
    "wof:name":"Level II Electric LLC",
    "wof:placetype":"venue"
},
  "geometry": {"coordinates":[-85.658237,38.44424],"type":"Point"}
}