{
  "type": "Feature",
  "properties": {
    "iso:country":"US",
    "sg:address":"503 Gilmore St",
    "sg:city":"Plymouth",
    "sg:classifiers":[
        {
            "category":"Personal",
            "subcategory":"Beauty Salon",
            "type":"Services"
        }
    ],
    "sg:phone":"+1 574 936 3550",
    "sg:postcode":"46563",
    "sg:province":"IN",
    "wof:name":"Milady Salon",
    "wof:placetype":"venue"
},
  "geometry": {"coordinates":[-86.308466,41.336048],"type":"Point"}
}