{
  "type": "Feature",
  "properties": {
    "addr:full":"11899 N Bethel Rd Mooresville IN 46158",
    "addr:housenumber":"11899",
    "addr:postcode":"46158",
    "addr:street":"N Bethel Rd",
    "iso:country":"US",
    "sg:address":"11899 N Bethel Rd",
    "sg:city":"Mooresville",
    "sg:phone":"+1 317 831 3927",
    "sg:postcode":"46158",
    "sg:province":"IN",
    "sg:tags":[
        "beef",
        "farm",
        "corn",
        "soybean",
        "cattle",
        "feedlot"
    ],
    "wof:name":"Don Adams",
    "wof:placetype":"venue"
},
  "geometry": {"coordinates":[-86.38704799999999,39.594271],"type":"Point"}
}