{
  "type": "Feature",
  "properties": {
    "iso:country":"US",
    "sg:address":"1055 Park Ave",
    "sg:city":"Valparaiso",
    "sg:classifiers":[
        {
            "category":"Building & Trades",
            "subcategory":"Construction",
            "type":"Services"
        }
    ],
    "sg:phone":"+1 219 462 1272",
    "sg:postcode":"46385",
    "sg:province":"IN",
    "sg:tags":[
        "house"
    ],
    "wof:name":"Hometec Construction LLC",
    "wof:placetype":"venue"
},
  "geometry": {"coordinates":[-87.073814,41.473658],"type":"Point"}
}