{
  "type": "Feature",
  "properties": {
    "addr:full":"844 E Jefferson St Tipton IN 46072",
    "addr:housenumber":"844",
    "addr:postcode":"46072",
    "addr:street":"E Jefferson St",
    "iso:country":"US",
    "sg:address":"844 E Jefferson St",
    "sg:city":"Tipton",
    "sg:classifiers":[
        {
            "category":"Home & Garden",
            "subcategory":"Hardware",
            "type":"Retail Goods"
        }
    ],
    "sg:phone":"+1 765 675 6740",
    "sg:postcode":"46072",
    "sg:province":"IN",
    "wof:name":"Ace Hardware",
    "wof:placetype":"venue"
},
  "geometry": {"coordinates":[-86.032302,40.282624],"type":"Point"}
}