{
  "type": "Feature",
  "properties": {
    "iso:country":"US",
    "sg:address":"319 N Saint Joseph Ave",
    "sg:city":"Evansville",
    "sg:classifiers":[
        {
            "category":"Health Services",
            "subcategory":"Medical Lab",
            "type":"Services"
        }
    ],
    "sg:phone":"+1 812 423 9702",
    "sg:postcode":"47712",
    "sg:province":"IN",
    "sg:tags":[
        "x"
    ],
    "wof:name":"Advanced Diagnostic Imagining",
    "wof:placetype":"venue"
},
  "geometry": {"coordinates":[-87.60046,37.981306],"type":"Point"}
}