{
  "type": "Feature",
  "properties": {
    "addr:full":"3484 W Co Rd 1100 S Westport IN 47283",
    "addr:housenumber":"3484",
    "addr:postcode":"47283",
    "addr:street":"W Co Rd 1100 S",
    "iso:country":"US",
    "sg:address":"3484 W Co Rd 1100 S",
    "sg:city":"Westport",
    "sg:classifiers":[
        {
            "category":"Building & Trades",
            "subcategory":"Construction",
            "type":"Services"
        }
    ],
    "sg:phone":"+1 812 591 0299",
    "sg:postcode":"47283",
    "sg:province":"IN",
    "sg:tags":[
        "steel"
    ],
    "wof:name":"Priority Detailing",
    "wof:placetype":"venue"
},
  "geometry": {"coordinates":[-85.541568,39.16648],"type":"Point"}
}