{
  "type": "Feature",
  "properties": {
    "iso:country":"US",
    "sg:address":"512 Main St",
    "sg:city":"Mt Vernon",
    "sg:classifiers":[
        {
            "category":"Retail",
            "subcategory":"Funeral Services",
            "type":"Services"
        }
    ],
    "sg:phone":"+1 812 838 4331",
    "sg:postcode":"47620",
    "sg:province":"IN",
    "sg:tags":[
        "director"
    ],
    "wof:name":"Schneider Funeral Home",
    "wof:placetype":"venue"
},
  "geometry": {"coordinates":[-87.896072,37.933467],"type":"Point"}
}