{
  "type": "Feature",
  "properties": {
    "iso:country":"US",
    "sg:address":"3021 E 98th St",
    "sg:city":"Indianapolis",
    "sg:classifiers":[
        {
            "category":"Banks & Credit Unions",
            "subcategory":"Investment Brokerage",
            "type":"Services"
        }
    ],
    "sg:phone":"+1 317 581 7326",
    "sg:postcode":"46280",
    "sg:province":"IN",
    "sg:tags":[
        "advisory",
        "financial"
    ],
    "wof:name":"Peak Financialservices",
    "wof:placetype":"venue"
},
  "geometry": {"coordinates":[-86.109766,39.930724],"type":"Point"}
}