{
  "type": "Feature",
  "properties": {
    "iso:country":"US",
    "sg:address":"617 Indiana Ave",
    "sg:city":"Michigan City",
    "sg:classifiers":[
        {
            "category":"Retail",
            "subcategory":"Laundry & Dry Cleaning",
            "type":"Services"
        }
    ],
    "sg:phone":"+1 219 878 0800",
    "sg:postcode":"46360",
    "sg:province":"IN",
    "wof:name":"Alterations By Darlene",
    "wof:placetype":"venue"
},
  "geometry": {"coordinates":[-86.905857,41.69685],"type":"Point"}
}