{
  "type": "Feature",
  "properties": {
    "addr:full":"620 E 10th St Indianapolis IN 46202",
    "addr:housenumber":"620",
    "addr:postcode":"46202",
    "addr:street":"E 10Th St",
    "iso:country":"US",
    "sg:address":"620 E 10th St",
    "sg:city":"Indianapolis",
    "sg:classifiers":[
        {
            "category":"Organizations",
            "subcategory":"Non-profit Organization",
            "type":"Services"
        }
    ],
    "sg:phone":"+1 317 636 4560",
    "sg:postcode":"46202",
    "sg:province":"IN",
    "wof:name":"Indianapolis Christian School",
    "wof:placetype":"venue"
},
  "geometry": {"coordinates":[-86.14702699999999,39.780841],"type":"Point"}
}