{
  "type": "Feature",
  "properties": {
    "iso:country":"US",
    "sg:address":"636 S Main St",
    "sg:city":"Winchester",
    "sg:classifiers":[
        {
            "category":"Autos & Motor Vehicles",
            "subcategory":"Automobile Sales",
            "type":"Retail Goods"
        }
    ],
    "sg:phone":"+1 765 584 5591",
    "sg:postcode":"47394",
    "sg:province":"IN",
    "sg:tags":[
        "car",
        "dealer"
    ],
    "wof:name":"Grimm Pontiac-Buick-GMC Inc",
    "wof:placetype":"venue"
},
  "geometry": {"coordinates":[-84.981262,40.165592],"type":"Point"}
}