{
  "type": "Feature",
  "properties": {
    "iso:country":"US",
    "sg:address":"8202 Clearvista Pkwy",
    "sg:city":"Indianapolis",
    "sg:classifiers":[
        {
            "category":"Retail",
            "subcategory":"Laundry & Dry Cleaning",
            "type":"Services"
        },
        {
            "category":"Shopping",
            "subcategory":"Clothing, Apparel, & Fashions",
            "type":"Retail Goods"
        }
    ],
    "sg:phone":"+1 317 598 6288",
    "sg:postcode":"46256",
    "sg:province":"IN",
    "sg:tags":[
        "alteration"
    ],
    "sg:website":"www.smokingiron.com",
    "wof:name":"Smoking Iron Alterations",
    "wof:placetype":"venue"
},
  "geometry": {"coordinates":[-86.039659,39.906541],"type":"Point"}
}