{
  "type": "Feature",
  "properties": {
    "iso:country":"US",
    "sg:address":"8432 Indiana St",
    "sg:city":"Merrillville",
    "sg:classifiers":[
        {
            "category":"Wholesale",
            "subcategory":"Durable Goods & Equipment",
            "type":"Manufacturing & Wholesale Goods"
        }
    ],
    "sg:phone":"+1 219 736 1280",
    "sg:postcode":"46410",
    "sg:province":"IN",
    "sg:tags":[
        "representative",
        "manufacturer"
    ],
    "wof:name":"Lynxtron Inc",
    "wof:placetype":"venue"
},
  "geometry": {"coordinates":[-87.317723,41.463373],"type":"Point"}
}