{
  "type": "Feature",
  "properties": {
    "addr:full":"104 E Maple St Muncie IN 47305",
    "addr:housenumber":"104",
    "addr:postcode":"47305",
    "addr:street":"E Maple St",
    "iso:country":"US",
    "sg:address":"104 E Maple St",
    "sg:city":"Muncie",
    "sg:classifiers":[
        {
            "category":"Retail",
            "subcategory":"Auto Repair",
            "type":"Services"
        }
    ],
    "sg:phone":"+1 765 288 5851",
    "sg:postcode":"47305",
    "sg:province":"IN",
    "sg:tags":[
        "brake"
    ],
    "wof:name":"Fisher's Brake Svc",
    "wof:placetype":"venue"
},
  "geometry": {"coordinates":[-85.38515200000001,40.202805],"type":"Point"}
}