{
  "type": "Feature",
  "properties": {
    "addr:full":"1351 S Girls School Rd Indianapolis IN 46231",
    "addr:housenumber":"1351",
    "addr:postcode":"46231",
    "addr:street":"S Girls School Rd",
    "iso:country":"US",
    "sg:address":"1351 S Girls School Rd",
    "sg:city":"Indianapolis",
    "sg:classifiers":[
        {
            "category":"Manufacturing",
            "subcategory":"Metals",
            "type":"Manufacturing & Wholesale Goods"
        }
    ],
    "sg:phone":"+1 317 241 7600",
    "sg:postcode":"46231",
    "sg:province":"IN",
    "sg:tags":[
        "plating"
    ],
    "sg:website":"www.handyharmon.com",
    "wof:name":"Sumco Inc",
    "wof:placetype":"venue"
},
  "geometry": {"coordinates":[-86.289001,39.74959],"type":"Point"}
}