{
  "type": "Feature",
  "properties": {
    "addr:full":"6848 E Co Rd 151 N Avon IN 46123",
    "addr:housenumber":"6848",
    "addr:postcode":"46123",
    "addr:street":"E Co Rd 151 N",
    "iso:country":"US",
    "sg:address":"6848 E Co Rd 151 N",
    "sg:city":"Avon",
    "sg:classifiers":[
        {
            "category":"Wholesale",
            "subcategory":"Machinery & Supplies",
            "type":"Manufacturing & Wholesale Goods"
        }
    ],
    "sg:phone":"+1 317 272 7694",
    "sg:postcode":"46123",
    "sg:province":"IN",
    "sg:tags":[
        "machine",
        "tool"
    ],
    "wof:name":"Indianapolis Machine Tool Inc",
    "wof:placetype":"venue"
},
  "geometry": {"coordinates":[-86.402293,39.788856],"type":"Point"}
}