{
  "type": "Feature",
  "properties": {
    "addr:full":"1628 N 3rd St Terre Haute IN 47804",
    "addr:housenumber":"1628",
    "addr:postcode":"47804",
    "addr:street":"N 3Rd St",
    "iso:country":"US",
    "sg:address":"1628 N 3rd St",
    "sg:city":"Terre Haute",
    "sg:classifiers":[
        {
            "category":"Personal",
            "subcategory":"Beauty Salon",
            "type":"Services"
        }
    ],
    "sg:phone":"+1 812 232 8890",
    "sg:postcode":"47804",
    "sg:province":"IN",
    "sg:tags":[
        "shop"
    ],
    "wof:name":"Mirror Images Salon",
    "wof:placetype":"venue"
},
  "geometry": {"coordinates":[-87.414024,39.484865],"type":"Point"}
}