{
  "type": "Feature",
  "properties": {
    "iso:country":"US",
    "sg:address":"3320 N Saint Joseph Ave",
    "sg:city":"Evansville",
    "sg:classifiers":[
        {
            "category":"Shopping",
            "subcategory":"Department Store",
            "type":"Retail Goods"
        }
    ],
    "sg:phone":"+1 812 425 8464",
    "sg:postcode":"47720",
    "sg:province":"IN",
    "sg:tags":[
        "shop"
    ],
    "wof:name":"Dollar General",
    "wof:placetype":"venue"
},
  "geometry": {"coordinates":[-87.599943,38.008755],"type":"Point"}
}