{
  "type": "Feature",
  "properties": {
    "iso:country":"US",
    "sg:address":"2806 Frontage Rd",
    "sg:city":"Warsaw",
    "sg:classifiers":[
        {
            "category":"Shopping",
            "subcategory":"Bicycles & Sporting Goods",
            "type":"Retail Goods"
        }
    ],
    "sg:phone":"+1 574 268 9715",
    "sg:postcode":"46580",
    "sg:province":"IN",
    "wof:name":"Dunham's Sports",
    "wof:placetype":"venue"
},
  "geometry": {"coordinates":[-85.817353,41.23762],"type":"Point"}
}