{
  "type": "Feature",
  "properties": {
    "iso:country":"US",
    "sg:address":"218 E South St",
    "sg:city":"Shelbyville",
    "sg:classifiers":[
        {
            "category":"Organizations",
            "subcategory":"Religious Organization",
            "type":"Services"
        }
    ],
    "sg:phone":"+1 317 398 3481",
    "sg:postcode":"46176",
    "sg:province":"IN",
    "sg:tags":[
        "church"
    ],
    "wof:name":"Seventh Day Adventist Comm Svc",
    "wof:placetype":"venue"
},
  "geometry": {"coordinates":[-85.774686,39.520143],"type":"Point"}
}