{
  "type": "Feature",
  "properties": {
    "iso:country":"US",
    "sg:address":"14300 Clay Terrace Blvd",
    "sg:city":"Carmel",
    "sg:classifiers":[
        {
            "category":"Professional",
            "subcategory":"Business Services",
            "type":"Services"
        }
    ],
    "sg:phone":"+1 317 208 9010",
    "sg:postcode":"46032",
    "sg:province":"IN",
    "sg:tags":[
        "packaging"
    ],
    "wof:name":"Hartland Packaging",
    "wof:placetype":"venue"
},
  "geometry": {"coordinates":[-86.128962,39.996807],"type":"Point"}
}