{
  "type": "Feature",
  "properties": {
    "iso:country":"US",
    "sg:address":"1830 Meadow Rd",
    "sg:city":"Evansville",
    "sg:classifiers":[
        {
            "category":"Social Services",
            "subcategory":"Child Care",
            "type":"Services"
        }
    ],
    "sg:phone":"+1 812 477 2775",
    "sg:postcode":"47715",
    "sg:province":"IN",
    "sg:tags":[
        "day"
    ],
    "wof:name":"Haugs & Kisses Day Care",
    "wof:placetype":"venue"
},
  "geometry": {"coordinates":[-87.50043,37.993955],"type":"Point"}
}