{
  "type": "Feature",
  "properties": {
    "iso:country":"US",
    "sg:address":"123 W State St",
    "sg:city":"Kingman",
    "sg:classifiers":[
        {
            "category":"Education",
            "subcategory":"Library",
            "type":"Public Place"
        }
    ],
    "sg:phone":"+1 765 397 3138",
    "sg:postcode":"47952",
    "sg:province":"IN",
    "wof:name":"Kingman Public Library",
    "wof:placetype":"venue"
},
  "geometry": {"coordinates":[-87.282761,39.96749],"type":"Point"}
}