{
  "type": "Feature",
  "properties": {
    "addr:full":"7126 Camelot Ct Indianapolis IN 46214",
    "addr:housenumber":"7126",
    "addr:postcode":"46214",
    "addr:street":"Camelot Ct",
    "iso:country":"US",
    "sg:address":"7126 Camelot Ct",
    "sg:city":"Indianapolis",
    "sg:classifiers":[
        {
            "category":"Wholesale",
            "subcategory":"Durable Goods & Equipment",
            "type":"Manufacturing & Wholesale Goods"
        }
    ],
    "sg:phone":"+1 317 243 7175",
    "sg:postcode":"46214",
    "sg:province":"IN",
    "sg:tags":[
        "instrument",
        "musical"
    ],
    "wof:name":"Soundz Muzic",
    "wof:placetype":"venue"
},
  "geometry": {"coordinates":[-86.28549099999999,39.772611],"type":"Point"}
}