{
  "type": "Feature",
  "properties": {
    "iso:country":"US",
    "sg:address":"52 S Madison Ave",
    "sg:city":"Greenwood",
    "sg:classifiers":[
        {
            "category":"Shopping",
            "subcategory":"Florist",
            "type":"Retail Goods"
        }
    ],
    "sg:phone":"+1 317 881 8990",
    "sg:postcode":"46142",
    "sg:province":"IN",
    "wof:name":"Forever Flowers",
    "wof:placetype":"venue"
},
  "geometry": {"coordinates":[-86.110233,39.615064],"type":"Point"}
}