{
  "type": "Feature",
  "properties": {
    "iso:country":"US",
    "sg:address":"615 E Tennessee St",
    "sg:city":"Evansville",
    "sg:classifiers":[
        {
            "category":"Retail",
            "subcategory":"Auto Repair",
            "type":"Services"
        }
    ],
    "sg:phone":"+1 812 424 9238",
    "sg:postcode":"47711",
    "sg:province":"IN",
    "sg:tags":[
        "repairing",
        "automobile"
    ],
    "wof:name":"Mc Camish Garage",
    "wof:placetype":"venue"
},
  "geometry": {"coordinates":[-87.55414,37.990235],"type":"Point"}
}