{
  "type": "Feature",
  "properties": {
    "iso:country":"US",
    "sg:address":"1538 E 4th St",
    "sg:city":"Mishawaka",
    "sg:classifiers":[
        {
            "category":"Building & Trades",
            "subcategory":"Construction",
            "type":"Services"
        }
    ],
    "sg:phone":"+1 574 276 0723",
    "sg:postcode":"46544",
    "sg:province":"IN",
    "sg:tags":[
        "painter"
    ],
    "wof:name":"G B Painting & Home Imprvmts",
    "wof:placetype":"venue"
},
  "geometry": {"coordinates":[-86.153592,41.660696],"type":"Point"}
}