{
  "type": "Feature",
  "properties": {
    "iso:country":"US",
    "sg:address":"3400 Stocker Dr",
    "sg:city":"Evansville",
    "sg:classifiers":[
        {
            "category":"Health Services",
            "subcategory":"Nursing And Care Facility",
            "type":"Services"
        }
    ],
    "sg:phone":"+1 812 424 8100",
    "sg:postcode":"47720",
    "sg:province":"IN",
    "sg:tags":[
        "home",
        "convalescent"
    ],
    "wof:name":"Pine Haven Health & Rehab Ctr",
    "wof:placetype":"venue"
},
  "geometry": {"coordinates":[-87.615348,37.991223],"type":"Point"}
}