{
  "type": "Feature",
  "properties": {
    "iso:country":"US",
    "sg:address":"2404 U St",
    "sg:city":"Bedford",
    "sg:classifiers":[
        {
            "category":"Manufacturing",
            "subcategory":"Food",
            "type":"Manufacturing & Wholesale Goods"
        }
    ],
    "sg:phone":"+1 812 279 8930",
    "sg:postcode":"47421",
    "sg:province":"IN",
    "sg:tags":[
        "ice"
    ],
    "wof:name":"Cosner Ice Co",
    "wof:placetype":"venue"
},
  "geometry": {"coordinates":[-86.499428,38.852757],"type":"Point"}
}