{
  "type": "Feature",
  "properties": {
    "addr:full":"4263 Lafayette Rd Indianapolis IN 46254",
    "addr:housenumber":"4263",
    "addr:postcode":"46254",
    "iso:country":"US",
    "sg:address":"4263 Lafayette Rd",
    "sg:city":"Indianapolis",
    "sg:classifiers":[
        {
            "category":"Education",
            "subcategory":"Dance Studio",
            "type":"Public Place"
        }
    ],
    "sg:phone":"+1 317 293 6145",
    "sg:postcode":"46254",
    "sg:province":"IN",
    "sg:tags":[
        "instruction",
        "dancing"
    ],
    "wof:name":"Arthur Murray Dance Studio",
    "wof:placetype":"venue"
},
  "geometry": {"coordinates":[-86.24375499999999,39.832902],"type":"Point"}
}