{
  "type": "Feature",
  "properties": {
    "iso:country":"US",
    "sg:address":"4327 W 750 N",
    "sg:city":"Michigan City",
    "sg:phone":"+1 219 879 2950",
    "sg:postcode":"46360",
    "sg:province":"IN",
    "sg:tags":[
        "farm",
        "corn",
        "soybean"
    ],
    "wof:name":"Tim Corbett",
    "wof:placetype":"venue"
},
  "geometry": {"coordinates":[-86.783688,41.715765],"type":"Point"}
}