{
  "type": "Feature",
  "properties": {
    "iso:country":"US",
    "sg:address":"1202 N State St",
    "sg:city":"Greenfield",
    "sg:classifiers":[
        {
            "category":"Professional",
            "subcategory":"Advertising",
            "type":"Services"
        }
    ],
    "sg:phone":"+1 317 467 4044",
    "sg:postcode":"46140",
    "sg:province":"IN",
    "sg:tags":[
        "agency"
    ],
    "wof:name":"Pepper-Can Advertising",
    "wof:placetype":"venue"
},
  "geometry": {"coordinates":[-85.769888,39.800735],"type":"Point"}
}