{
  "type": "Feature",
  "properties": {
    "iso:country":"US",
    "sg:address":"1901 Winton Ave",
    "sg:city":"Indianapolis",
    "sg:classifiers":[
        {
            "category":"Building & Trades",
            "subcategory":"Construction",
            "type":"Services"
        }
    ],
    "sg:phone":"+1 317 241 2113",
    "sg:postcode":"46224",
    "sg:province":"IN",
    "sg:tags":[
        "house"
    ],
    "wof:name":"Schindler Remodeling",
    "wof:placetype":"venue"
},
  "geometry": {"coordinates":[-86.246782,39.791089],"type":"Point"}
}