{
  "type": "Feature",
  "properties": {
    "iso:country":"US",
    "sg:address":"444 Wabash St",
    "sg:city":"Michigan City",
    "sg:classifiers":[
        {
            "category":"Professional",
            "subcategory":"Management & Consulting",
            "type":"Services"
        }
    ],
    "sg:phone":"+1 219 879 9412",
    "sg:postcode":"46360",
    "sg:province":"IN",
    "sg:tags":[
        "business"
    ],
    "wof:name":"Safety & Environmental Resourc",
    "wof:placetype":"venue"
},
  "geometry": {"coordinates":[-86.904886,41.716955],"type":"Point"}
}