{
  "type": "Feature",
  "properties": {
    "iso:country":"US",
    "sg:address":"4217 McKean Ln",
    "sg:city":"Indianapolis",
    "sg:classifiers":[
        {
            "category":"Real Estate",
            "subcategory":"Real Estate Agent",
            "type":"Services"
        }
    ],
    "sg:phone":"+1 317 578 7417",
    "sg:postcode":"46250",
    "sg:province":"IN",
    "wof:name":"Estridge Co",
    "wof:placetype":"venue"
},
  "geometry": {"coordinates":[-86.095069,39.902986],"type":"Point"}
}