{
  "type": "Feature",
  "properties": {
    "iso:country":"US",
    "sg:address":"3031 State Rd 39",
    "sg:city":"Monrovia",
    "sg:classifiers":[
        {
            "category":"Building & Trades",
            "subcategory":"Landscaping Services",
            "type":"Services"
        }
    ],
    "sg:phone":"+1 317 996 3622",
    "sg:postcode":"46157",
    "sg:province":"IN",
    "sg:tags":[
        "landscape",
        "contractor"
    ],
    "wof:name":"American Lawn Care",
    "wof:placetype":"venue"
},
  "geometry": {"coordinates":[-86.479907,39.578239],"type":"Point"}
}