{
  "type": "Feature",
  "properties": {
    "iso:country":"US",
    "sg:address":"535 E Hendricks St",
    "sg:city":"Shelbyville",
    "sg:classifiers":[
        {
            "category":"Autos & Motor Vehicles",
            "subcategory":"Automobile Sales",
            "type":"Retail Goods"
        }
    ],
    "sg:phone":"+1 317 392 4825",
    "sg:postcode":"46176",
    "sg:province":"IN",
    "sg:tags":[
        "car",
        "dealer"
    ],
    "wof:name":"Chuck's Upfront Motors",
    "wof:placetype":"venue"
},
  "geometry": {"coordinates":[-85.772994,39.521939],"type":"Point"}
}