{
  "type": "Feature",
  "properties": {
    "addr:full":"1640 N US Hwy 421 Whitestown IN 46075",
    "addr:housenumber":"1640",
    "addr:postcode":"46075",
    "addr:street":"N Us Hwy 421",
    "iso:country":"US",
    "sg:address":"1640 N US Hwy 421",
    "sg:city":"Whitestown",
    "sg:classifiers":[
        {
            "category":"Manufacturing",
            "subcategory":"Printing",
            "type":"Manufacturing & Wholesale Goods"
        }
    ],
    "sg:phone":"+1 317 769 4751",
    "sg:postcode":"46075",
    "sg:province":"IN",
    "sg:tags":[
        "publisher"
    ],
    "wof:name":"Shepherd & David",
    "wof:placetype":"venue"
},
  "geometry": {"coordinates":[-86.29928700000001,40.069218],"type":"Point"}
}