{
  "type": "Feature",
  "properties": {
    "iso:country":"US",
    "sg:address":"219 W Broadway St",
    "sg:city":"Princeton",
    "sg:classifiers":[
        {
            "category":"Retail",
            "subcategory":"Portrait Studio",
            "type":"Services"
        }
    ],
    "sg:phone":"+1 812 385 2077",
    "sg:postcode":"47670",
    "sg:province":"IN",
    "sg:tags":[
        "photographer"
    ],
    "wof:name":"Don J Parker Photography",
    "wof:placetype":"venue"
},
  "geometry": {"coordinates":[-87.56984,38.355192],"type":"Point"}
}