{
  "type": "Feature",
  "properties": {
    "iso:country":"US",
    "sg:address":"522 Oolitic Rd",
    "sg:city":"Bedford",
    "sg:classifiers":[
        {
            "category":"Building & Trades",
            "subcategory":"Plumbing",
            "type":"Services"
        }
    ],
    "sg:phone":"+1 812 279 6662",
    "sg:postcode":"47421",
    "sg:province":"IN",
    "sg:tags":[
        "plumbing",
        "contractor"
    ],
    "wof:name":"Mr Plunger",
    "wof:placetype":"venue"
},
  "geometry": {"coordinates":[-86.502878,38.885398],"type":"Point"}
}