{
  "type": "Feature",
  "properties": {
    "iso:country":"US",
    "sg:address":"6640 Ridgeway Dr",
    "sg:city":"Mooresville",
    "sg:classifiers":[
        {
            "category":"Shopping",
            "subcategory":"Bicycles & Sporting Goods",
            "type":"Retail Goods"
        }
    ],
    "sg:phone":"+1 317 831 8829",
    "sg:postcode":"46158",
    "sg:province":"IN",
    "sg:tags":[
        "reloading",
        "equipment",
        "ammunition"
    ],
    "wof:name":"Fuller Munitions",
    "wof:placetype":"venue"
},
  "geometry": {"coordinates":[-86.303258,39.581812],"type":"Point"}
}