{
  "type": "Feature",
  "properties": {
    "iso:country":"US",
    "sg:address":"525 S Carr Rd",
    "sg:city":"Plainfield",
    "sg:classifiers":[
        {
            "category":"Building & Trades",
            "subcategory":"Electrical",
            "type":"Services"
        }
    ],
    "sg:phone":"+1 317 839 9085",
    "sg:postcode":"46168",
    "sg:province":"IN",
    "sg:tags":[
        "electric",
        "contractor"
    ],
    "wof:name":"D & M Enterprises",
    "wof:placetype":"venue"
},
  "geometry": {"coordinates":[-86.389944,39.702278],"type":"Point"}
}