{
  "type": "Feature",
  "properties": {
    "iso:country":"US",
    "sg:address":"4706 Wyland Dr",
    "sg:city":"Elkhart",
    "sg:classifiers":[
        {
            "category":"Manufacturing",
            "subcategory":"Glass & Minerals",
            "type":"Manufacturing & Wholesale Goods"
        }
    ],
    "sg:phone":"+1 574 293 5669",
    "sg:postcode":"46516",
    "sg:province":"IN",
    "sg:tags":[
        "for",
        "mfg",
        "mirror",
        "outside",
        "motor",
        "vehicle",
        "rear",
        "view"
    ],
    "wof:name":"B & R Manufacturing Inc",
    "wof:placetype":"venue"
},
  "geometry": {"coordinates":[-85.897838,41.691833],"type":"Point"}
}