{
  "type": "Feature",
  "properties": {
    "addr:full":"605 Michigan Ave Laporte IN 46350",
    "addr:housenumber":"605",
    "addr:postcode":"46350",
    "addr:street":"Michigan Ave",
    "iso:country":"US",
    "sg:address":"605 Michigan Ave",
    "sg:city":"Laporte",
    "sg:classifiers":[
        {
            "category":"Building & Trades",
            "subcategory":"Construction",
            "type":"Services"
        }
    ],
    "sg:phone":"+1 219 324 4946",
    "sg:postcode":"46350",
    "sg:province":"IN",
    "sg:tags":[
        "roofing",
        "contractor"
    ],
    "wof:name":"K C Enterprises",
    "wof:placetype":"venue"
},
  "geometry": {"coordinates":[-86.721906,41.611886],"type":"Point"}
}