{
  "type": "Feature",
  "properties": {
    "iso:country":"US",
    "sg:address":"97 Bracken Pkwy",
    "sg:city":"Hobart",
    "sg:classifiers":[
        {
            "category":"Organizations",
            "subcategory":"Religious Organization",
            "type":"Services"
        }
    ],
    "sg:phone":"+1 219 942 8016",
    "sg:postcode":"46342",
    "sg:province":"IN",
    "sg:tags":[
        "church"
    ],
    "wof:name":"Barrington Ridge Baptist Chr",
    "wof:placetype":"venue"
},
  "geometry": {"coordinates":[-87.255778,41.511776],"type":"Point"}
}