{
  "type": "Feature",
  "properties": {
    "addr:full":"3307 Klondike Rd West Lafayette IN 47906",
    "addr:housenumber":"3307",
    "addr:postcode":"47906",
    "addr:street":"Klondike Rd",
    "iso:country":"US",
    "sg:address":"3307 Klondike Rd",
    "sg:city":"West Lafayette",
    "sg:classifiers":[
        {
            "category":"Education",
            "subcategory":"School",
            "type":"Public Place"
        }
    ],
    "sg:phone":"+1 765 463 2544",
    "sg:postcode":"47906",
    "sg:province":"IN",
    "wof:name":"Klondike Middle School",
    "wof:placetype":"venue"
},
  "geometry": {"coordinates":[-86.962127,40.463831],"type":"Point"}
}