{
  "type": "Feature",
  "properties": {
    "iso:country":"US",
    "sg:address":"314 S Forest Ave",
    "sg:city":"Brazil",
    "sg:classifiers":[
        {
            "category":"Health Services",
            "subcategory":"Chiropractor",
            "type":"Services"
        }
    ],
    "sg:phone":"+1 812 448 1177",
    "sg:postcode":"47834",
    "sg:province":"IN",
    "wof:name":"Dalton Chiropractic Ctr",
    "wof:placetype":"venue"
},
  "geometry": {"coordinates":[-87.125136,39.520613],"type":"Point"}
}