{
  "type": "Feature",
  "properties": {
    "iso:country":"US",
    "sg:address":"2676 N Tiffin Pl",
    "sg:city":"West Terre Haute",
    "sg:classifiers":[
        {
            "category":"Organizations",
            "subcategory":"Religious Organization",
            "type":"Services"
        }
    ],
    "sg:phone":"+1 812 533 1071",
    "sg:postcode":"47885",
    "sg:province":"IN",
    "wof:name":"Sycamore Park Methodist Church",
    "wof:placetype":"venue"
},
  "geometry": {"coordinates":[-87.52671599999999,39.502782],"type":"Point"}
}