{
  "type": "Feature",
  "properties": {
    "addr:full":"7467 E 100 N Greenfield IN 46140",
    "addr:housenumber":"7467",
    "addr:postcode":"46140",
    "addr:street":"E 100 N",
    "iso:country":"US",
    "sg:address":"7467 E 100 N",
    "sg:city":"Greenfield",
    "sg:classifiers":[
        {
            "category":"Building & Trades",
            "subcategory":"Construction",
            "type":"Services"
        }
    ],
    "sg:phone":"+1 317 462 9622",
    "sg:postcode":"46140",
    "sg:province":"IN",
    "sg:tags":[
        "concrete",
        "contractor"
    ],
    "wof:name":"Zeyen Construction Co",
    "wof:placetype":"venue"
},
  "geometry": {"coordinates":[-85.660875,39.800506],"type":"Point"}
}