{
  "type": "Feature",
  "properties": {
    "iso:country":"US",
    "sg:address":"521 N Clark Blvd",
    "sg:city":"Clarksville",
    "sg:classifiers":[
        {
            "category":"Freight",
            "type":"Transportation"
        }
    ],
    "sg:phone":"+1 812 288 9025",
    "sg:postcode":"47129",
    "sg:province":"IN",
    "sg:tags":[
        "trucking"
    ],
    "wof:name":"Total Services Inc",
    "wof:placetype":"venue"
},
  "geometry": {"coordinates":[-85.769314,38.293753],"type":"Point"}
}