{
  "type": "Feature",
  "properties": {
    "iso:country":"US",
    "sg:address":"4535 Ohara Dr",
    "sg:city":"Evansville",
    "sg:classifiers":[
        {
            "category":"Professional",
            "subcategory":"Business Services",
            "type":"Services"
        }
    ],
    "sg:phone":"+1 812 422 6948",
    "sg:postcode":"47711",
    "sg:province":"IN",
    "sg:tags":[
        "auctioneer"
    ],
    "wof:name":"Shaffer Auction & Realty Co",
    "wof:placetype":"venue"
},
  "geometry": {"coordinates":[-87.521527,38.023861],"type":"Point"}
}