{
  "type": "Feature",
  "properties": {
    "iso:country":"US",
    "sg:address":"7615 Blacksmith Ct",
    "sg:city":"Plainfield",
    "sg:classifiers":[
        {
            "category":"Professional",
            "subcategory":"Business Services",
            "type":"Services"
        }
    ],
    "sg:phone":"+1 317 839 4204",
    "sg:postcode":"46168",
    "sg:province":"IN",
    "wof:name":"Zimmer Enterprises Inc",
    "wof:placetype":"venue"
},
  "geometry": {"coordinates":[-86.387802,39.721005],"type":"Point"}
}