{
  "type": "Feature",
  "properties": {
    "addr:full":"2116 W 2nd St Marion IN 46952",
    "addr:housenumber":"2116",
    "addr:postcode":"46952",
    "addr:street":"W 2Nd St",
    "iso:country":"US",
    "sg:address":"2116 W 2nd St",
    "sg:city":"Marion",
    "sg:classifiers":[
        {
            "category":"Real Estate",
            "subcategory":"Real Estate Operator",
            "type":"Services"
        }
    ],
    "sg:phone":"+1 765 662 9540",
    "sg:postcode":"46952",
    "sg:province":"IN",
    "sg:tags":[
        "apartment"
    ],
    "wof:name":"Turtle Creek Apartments",
    "wof:placetype":"venue"
},
  "geometry": {"coordinates":[-85.689509,40.559784],"type":"Point"}
}