{
  "type": "Feature",
  "properties": {
    "iso:country":"US",
    "sg:address":"701 Main St",
    "sg:city":"Vincennes",
    "sg:classifiers":[
        {
            "category":"Shopping",
            "subcategory":"Clothing, Apparel, & Fashions",
            "type":"Retail Goods"
        }
    ],
    "sg:phone":"+1 812 882 4201",
    "sg:postcode":"47591",
    "sg:province":"IN",
    "sg:tags":[
        "shop",
        "bridal"
    ],
    "wof:name":"Illusions Bridal & Party Shop",
    "wof:placetype":"venue"
},
  "geometry": {"coordinates":[-87.528553,38.676027],"type":"Point"}
}