{
  "type": "Feature",
  "properties": {
    "addr:full":"60 E Morgan St Martinsville IN 46151",
    "addr:housenumber":"60",
    "addr:postcode":"46151",
    "addr:street":"E Morgan St",
    "iso:country":"US",
    "sg:address":"60 E Morgan St",
    "sg:city":"Martinsville",
    "sg:classifiers":[
        {
            "category":"Professional",
            "subcategory":"Lawyer & Legal Services",
            "type":"Services"
        }
    ],
    "sg:phone":"+1 765 342 8474",
    "sg:postcode":"46151",
    "sg:province":"IN",
    "sg:tags":[
        "attorney"
    ],
    "wof:name":"Foley Foley & Peden",
    "wof:placetype":"venue"
},
  "geometry": {"coordinates":[-86.42800699999999,39.427927],"type":"Point"}
}