{
  "type": "Feature",
  "properties": {
    "addr:full":"2958 W Dunes Hwy Michigan City IN 46360",
    "addr:housenumber":"2958",
    "addr:postcode":"46360",
    "addr:street":"W Dunes Hwy",
    "iso:country":"US",
    "sg:address":"2958 W Dunes Hwy",
    "sg:city":"Michigan City",
    "sg:classifiers":[
        {
            "category":"Bars & Pubs",
            "type":"Food & Drink"
        }
    ],
    "sg:phone":"+1 219 879 9336",
    "sg:postcode":"46360",
    "sg:province":"IN",
    "wof:name":"Joe's Bar & Grill",
    "wof:placetype":"venue"
},
  "geometry": {"coordinates":[-86.940044,41.692164],"type":"Point"}
}