{
  "type": "Feature",
  "properties": {
    "addr:full":"4696 W Columbus Pike Freetown IN 47235",
    "addr:housenumber":"4696",
    "addr:postcode":"47235",
    "addr:street":"W Columbus Pike",
    "iso:country":"US",
    "sg:address":"4696 W Columbus Pike",
    "sg:city":"Freetown",
    "sg:classifiers":[
        {
            "category":"Education",
            "subcategory":"School",
            "type":"Public Place"
        }
    ],
    "sg:phone":"+1 812 497 2911",
    "sg:postcode":"47235",
    "sg:province":"IN",
    "sg:website":"www.btownccs.k12.in.us",
    "wof:name":"Freetown Elementary School",
    "wof:placetype":"venue"
},
  "geometry": {"coordinates":[-86.12994399999999,38.975731],"type":"Point"}
}