{
  "type": "Feature",
  "properties": {
    "iso:country":"US",
    "sg:address":"3300 W Sample St",
    "sg:city":"South Bend",
    "sg:classifiers":[
        {
            "category":"Manufacturing",
            "subcategory":"Furniture",
            "type":"Manufacturing & Wholesale Goods"
        }
    ],
    "sg:phone":"+1 574 289 1242",
    "sg:postcode":"46619",
    "sg:province":"IN",
    "sg:tags":[
        "bedding"
    ],
    "wof:name":"Ther A Pedic",
    "wof:placetype":"venue"
},
  "geometry": {"coordinates":[-86.295892,41.664699],"type":"Point"}
}