{
  "type": "Feature",
  "properties": {
    "iso:country":"US",
    "sg:address":"701 State Rd 131",
    "sg:city":"Clarksville",
    "sg:classifiers":[
        {
            "category":"Shopping",
            "type":"Retail Goods"
        }
    ],
    "sg:phone":"+1 812 283 1010",
    "sg:postcode":"47129",
    "sg:province":"IN",
    "sg:tags":[
        "telephone",
        "cellular"
    ],
    "wof:name":"Cellular Advantage Inc",
    "wof:placetype":"venue"
},
  "geometry": {"coordinates":[-85.76516599999999,38.312379],"type":"Point"}
}