{
  "type": "Feature",
  "properties": {
    "addr:full":"43 Brookhaven Rd Vincennes IN 47591",
    "addr:housenumber":"43",
    "addr:postcode":"47591",
    "addr:street":"Brookhaven Rd",
    "iso:country":"US",
    "sg:address":"43 Brookhaven Rd",
    "sg:city":"Vincennes",
    "sg:classifiers":[
        {
            "category":"Farming",
            "subcategory":"Farm",
            "type":"Manufacturing & Wholesale Goods"
        }
    ],
    "sg:phone":"+1 812 886 5411",
    "sg:postcode":"47591",
    "sg:province":"IN",
    "wof:name":"JMR Farm Inc",
    "wof:placetype":"venue"
},
  "geometry": {"coordinates":[-87.53285099999999,38.638309],"type":"Point"}
}