{
  "type": "Feature",
  "properties": {
    "iso:country":"US",
    "sg:address":"59827 Co Rd 11",
    "sg:city":"Elkhart",
    "sg:classifiers":[
        {
            "category":"Building & Trades",
            "subcategory":"Electrical",
            "type":"Services"
        }
    ],
    "sg:phone":"+1 574 875 6297",
    "sg:postcode":"46517",
    "sg:province":"IN",
    "sg:tags":[
        "electric",
        "contractor"
    ],
    "wof:name":"3 Phase Electrical Svc",
    "wof:placetype":"venue"
},
  "geometry": {"coordinates":[-85.945549,41.625882],"type":"Point"}
}