{
  "type": "Feature",
  "properties": {
    "iso:country":"US",
    "sg:address":"193 N Gardner St",
    "sg:city":"Scottsburg",
    "sg:classifiers":[
        {
            "category":"Retail",
            "subcategory":"Auto Repair",
            "type":"Services"
        }
    ],
    "sg:phone":"+1 812 752 2003",
    "sg:postcode":"47170",
    "sg:province":"IN",
    "sg:tags":[
        "repairing",
        "automobile"
    ],
    "wof:name":"Couch Auto Repair",
    "wof:placetype":"venue"
},
  "geometry": {"coordinates":[-85.778599,38.687618],"type":"Point"}
}