{
  "type": "Feature",
  "properties": {
    "addr:full":"1529 Wabash Ave Terre Haute IN 47807",
    "addr:housenumber":"1529",
    "addr:postcode":"47807",
    "addr:street":"Wabash Ave",
    "iso:country":"US",
    "sg:address":"1529 Wabash Ave",
    "sg:city":"Terre Haute",
    "sg:classifiers":[
        {
            "category":"Building & Trades",
            "subcategory":"Plumbing",
            "type":"Services"
        }
    ],
    "sg:phone":"+1 812 235 3089",
    "sg:postcode":"47807",
    "sg:province":"IN",
    "sg:tags":[
        "plumbing",
        "contractor"
    ],
    "wof:name":"Plumber",
    "wof:placetype":"venue"
},
  "geometry": {"coordinates":[-87.391998,39.468632],"type":"Point"}
}