{
  "type": "Feature",
  "properties": {
    "iso:country":"US",
    "sg:address":"1227 S Bloomington St",
    "sg:city":"Greencastle",
    "sg:classifiers":[
        {
            "category":"Autos & Motor Vehicles",
            "subcategory":"Automobile Sales",
            "type":"Retail Goods"
        }
    ],
    "sg:phone":"+1 765 653 1336",
    "sg:postcode":"46135",
    "sg:province":"IN",
    "sg:tags":[
        "car",
        "dealer"
    ],
    "wof:name":"A-1 Auto Sales",
    "wof:placetype":"venue"
},
  "geometry": {"coordinates":[-86.851526,39.631578],"type":"Point"}
}