{
  "type": "Feature",
  "properties": {
    "iso:country":"US",
    "sg:address":"7141 W Morris St",
    "sg:city":"Indianapolis",
    "sg:classifiers":[
        {
            "category":"Autos & Motor Vehicles",
            "subcategory":"Auto Supplies",
            "type":"Retail Goods"
        },
        {
            "category":"Retail",
            "subcategory":"Auto Repair",
            "type":"Services"
        }
    ],
    "sg:phone":"+1 317 241 5909",
    "sg:postcode":"46241",
    "sg:province":"IN",
    "sg:tags":[
        "body",
        "lettering",
        "automobile",
        "truck",
        "painting",
        "repairing"
    ],
    "wof:name":"DJs Autobody And Graphics",
    "wof:placetype":"venue"
},
  "geometry": {"coordinates":[-86.28638100000001,39.74965],"type":"Point"}
}