{
  "type": "Feature",
  "properties": {
    "iso:country":"US",
    "sg:address":"120 W la Salle Ave",
    "sg:city":"South Bend",
    "sg:classifiers":[
        {
            "category":"Professional",
            "subcategory":"Management & Consulting",
            "type":"Services"
        }
    ],
    "sg:phone":"+1 574 289 1331",
    "sg:postcode":"46601",
    "sg:province":"IN",
    "sg:tags":[
        "counselor",
        "public",
        "relations"
    ],
    "wof:name":"Catalyst Marketing Svc",
    "wof:placetype":"venue"
},
  "geometry": {"coordinates":[-86.372017,41.710572],"type":"Point"}
}