{
  "type": "Feature",
  "properties": {
    "iso:country":"US",
    "sg:address":"5105 W Bradburn Dr",
    "sg:city":"Muncie",
    "sg:classifiers":[
        {
            "category":"Building & Trades",
            "subcategory":"Construction",
            "type":"Services"
        }
    ],
    "sg:phone":"+1 765 288 1111",
    "sg:postcode":"47304",
    "sg:province":"IN",
    "sg:tags":[
        "general",
        "contractor"
    ],
    "sg:website":"www.judconstruction.com",
    "wof:name":"Jud Construction",
    "wof:placetype":"venue"
},
  "geometry": {"coordinates":[-85.444569,40.216492],"type":"Point"}
}