{
  "type": "Feature",
  "properties": {
    "iso:country":"US",
    "sg:address":"26589 Co Rd 4",
    "sg:city":"Elkhart",
    "sg:classifiers":[
        {
            "category":"Wholesale",
            "subcategory":"Hardware",
            "type":"Manufacturing & Wholesale Goods"
        }
    ],
    "sg:phone":"+1 574 262 1462",
    "sg:postcode":"46514",
    "sg:province":"IN",
    "sg:tags":[
        "plumbing"
    ],
    "wof:name":"PAR Water Conditioning",
    "wof:placetype":"venue"
},
  "geometry": {"coordinates":[-85.981943,41.738886],"type":"Point"}
}