{
  "type": "Feature",
  "properties": {
    "iso:country":"US",
    "sg:address":"302 E Main St",
    "sg:city":"New Washington",
    "sg:classifiers":[
        {
            "category":"Food & Beverages",
            "subcategory":"Groceries & Convenience Stores",
            "type":"Retail Goods"
        }
    ],
    "sg:phone":"+1 812 293 3557",
    "sg:postcode":"47162",
    "sg:province":"IN",
    "sg:tags":[
        "grocer"
    ],
    "wof:name":"Corner Grocery Store",
    "wof:placetype":"venue"
},
  "geometry": {"coordinates":[-85.539535,38.562968],"type":"Point"}
}