{
  "type": "Feature",
  "properties": {
    "iso:country":"US",
    "sg:address":"2720 Guilford St",
    "sg:city":"Huntington",
    "sg:classifiers":[
        {
            "category":"Banks & Credit Unions",
            "subcategory":"Bank",
            "type":"Services"
        }
    ],
    "sg:phone":"+1 260 356 6361",
    "sg:postcode":"46750",
    "sg:province":"IN",
    "wof:name":"Wells Fargo Bank",
    "wof:placetype":"venue"
},
  "geometry": {"coordinates":[-85.507696,40.902534],"type":"Point"}
}