{
  "type": "Feature",
  "properties": {
    "iso:country":"US",
    "sg:address":"575 Broadway",
    "sg:city":"Gary",
    "sg:classifiers":[
        {
            "category":"Banks & Credit Unions",
            "subcategory":"Bank",
            "type":"Services"
        }
    ],
    "sg:phone":"+1 219 881 1800",
    "sg:postcode":"46407",
    "sg:province":"IN",
    "sg:tags":[
        "loan",
        "real estate"
    ],
    "wof:name":"Upscale Mortgage",
    "wof:placetype":"venue"
},
  "geometry": {"coordinates":[-87.33707800000001,41.601091],"type":"Point"}
}