{
  "type": "Feature",
  "properties": {
    "iso:country":"US",
    "sg:address":"7050 E 21st St",
    "sg:city":"Indianapolis",
    "sg:classifiers":[
        {
            "category":"Restaurant",
            "type":"Food & Drink"
        }
    ],
    "sg:phone":"+1 317 352 0481",
    "sg:postcode":"46219",
    "sg:province":"IN",
    "sg:tags":[
        "eating"
    ],
    "wof:name":"Sandwich Shop",
    "wof:placetype":"venue"
},
  "geometry": {"coordinates":[-86.044784,39.7965],"type":"Point"}
}