{
  "type": "Feature",
  "properties": {
    "addr:full":"1449 119th St Whiting IN 46394",
    "addr:housenumber":"1449",
    "addr:postcode":"46394",
    "addr:street":"119Th St",
    "iso:country":"US",
    "sg:address":"1449 119th St",
    "sg:city":"Whiting",
    "sg:classifiers":[
        {
            "category":"Banks & Credit Unions",
            "subcategory":"Bank",
            "type":"Services"
        }
    ],
    "sg:phone":"+1 219 659 7720",
    "sg:postcode":"46394",
    "sg:province":"IN",
    "wof:name":"Bank One",
    "wof:placetype":"venue"
},
  "geometry": {"coordinates":[-87.49337199999999,41.679472],"type":"Point"}
}