{
  "type": "Feature",
  "properties": {
    "iso:country":"US",
    "sg:address":"64 E Market St",
    "sg:city":"Spencer",
    "sg:classifiers":[
        {
            "category":"Professional",
            "subcategory":"Lawyer & Legal Services",
            "type":"Services"
        }
    ],
    "sg:phone":"+1 812 323 6230",
    "sg:postcode":"47460",
    "sg:province":"IN",
    "sg:tags":[
        "attorney"
    ],
    "wof:name":"Michael K Bonnell",
    "wof:placetype":"venue"
},
  "geometry": {"coordinates":[-86.76198100000001,39.285055],"type":"Point"}
}