{
  "type": "Feature",
  "properties": {
    "addr:full":"9729 Kittrell Dr Indianapolis IN 46280",
    "addr:housenumber":"9729",
    "addr:postcode":"46280",
    "addr:street":"Kittrell Dr",
    "iso:country":"US",
    "sg:address":"9729 Kittrell Dr",
    "sg:city":"Indianapolis",
    "sg:classifiers":[
        {
            "category":"Building & Trades",
            "subcategory":"Plumbing",
            "type":"Services"
        }
    ],
    "sg:phone":"+1 317 846 2918",
    "sg:postcode":"46280",
    "sg:province":"IN",
    "sg:tags":[
        "heating",
        "contractor"
    ],
    "wof:name":"Comfort Tech",
    "wof:placetype":"venue"
},
  "geometry": {"coordinates":[-86.12540799999999,39.930527],"type":"Point"}
}