{
  "type": "Feature",
  "properties": {
    "iso:country":"US",
    "sg:address":"1105 N Ireland St",
    "sg:city":"Greensburg",
    "sg:classifiers":[
        {
            "category":"Government",
            "subcategory":"Office",
            "type":"Public Place"
        }
    ],
    "sg:phone":"+1 812 663 2641",
    "sg:postcode":"47240",
    "sg:province":"IN",
    "sg:tags":[
        "village"
    ],
    "wof:name":"Greensburg Pumping Station",
    "wof:placetype":"venue"
},
  "geometry": {"coordinates":[-85.488906,39.348192],"type":"Point"}
}