{
  "type": "Feature",
  "properties": {
    "iso:country":"US",
    "sg:address":"4845 Blum Dr",
    "sg:city":"Fort Wayne",
    "sg:classifiers":[
        {
            "category":"Real Estate",
            "subcategory":"Real Estate Agent",
            "type":"Services"
        }
    ],
    "sg:phone":"+1 260 492 2328",
    "sg:postcode":"46835",
    "sg:province":"IN",
    "wof:name":"McChessney Appraisal Services",
    "wof:placetype":"venue"
},
  "geometry": {"coordinates":[-85.089865,41.124397],"type":"Point"}
}