{
  "type": "Feature",
  "properties": {
    "iso:country":"US",
    "sg:address":"800 E Thompson St",
    "sg:city":"Edinburgh",
    "sg:classifiers":[
        {
            "category":"Building & Trades",
            "subcategory":"Construction",
            "type":"Services"
        }
    ],
    "sg:phone":"+1 812 526 5426",
    "sg:postcode":"46124",
    "sg:province":"IN",
    "sg:tags":[
        "residential"
    ],
    "wof:name":"Crider Associates Inc",
    "wof:placetype":"venue"
},
  "geometry": {"coordinates":[-85.956809,39.3535],"type":"Point"}
}