{
  "type": "Feature",
  "properties": {
    "iso:country":"US",
    "sg:address":"8113 Knollcreek Cir",
    "sg:city":"Indianapolis",
    "sg:classifiers":[
        {
            "category":"Professional",
            "subcategory":"Business Services",
            "type":"Services"
        }
    ],
    "sg:phone":"+1 317 577 0084",
    "sg:postcode":"46256",
    "sg:province":"IN",
    "wof:name":"Steven L Smiley & Assoc Inc",
    "wof:placetype":"venue"
},
  "geometry": {"coordinates":[-86.023507,39.880854],"type":"Point"}
}