{
  "type": "Feature",
  "properties": {
    "iso:country":"US",
    "sg:address":"18326 Spring Mill Rd",
    "sg:city":"Westfield",
    "sg:classifiers":[
        {
            "category":"Retail",
            "subcategory":"Animal Services",
            "type":"Services"
        }
    ],
    "sg:phone":"+1 317 867 0879",
    "sg:postcode":"46074",
    "sg:province":"IN",
    "sg:tags":[
        "horse",
        "training"
    ],
    "wof:name":"Equus Inc",
    "wof:placetype":"venue"
},
  "geometry": {"coordinates":[-86.165397,40.043237],"type":"Point"}
}