{
  "type": "Feature",
  "properties": {
    "iso:country":"US",
    "sg:address":"6234 Central Ave",
    "sg:city":"Portage",
    "sg:classifiers":[
        {
            "category":"Shopping",
            "subcategory":"Clothing, Apparel, & Fashions",
            "type":"Retail Goods"
        }
    ],
    "sg:phone":"+1 219 763 7117",
    "sg:postcode":"46368",
    "sg:province":"IN",
    "wof:name":"Jungul Clothing",
    "wof:placetype":"venue"
},
  "geometry": {"coordinates":[-87.168518,41.575925],"type":"Point"}
}