{
  "type": "Feature",
  "properties": {
    "iso:country":"US",
    "sg:address":"8259 Wicker Ave",
    "sg:city":"St John",
    "sg:classifiers":[
        {
            "category":"Education",
            "subcategory":"Dance Studio",
            "type":"Public Place"
        }
    ],
    "sg:phone":"+1 219 365 9449",
    "sg:postcode":"46373",
    "sg:province":"IN",
    "sg:tags":[
        "instruction",
        "dancing"
    ],
    "wof:name":"M 2 Dance Ctr",
    "wof:placetype":"venue"
},
  "geometry": {"coordinates":[-87.470315,41.467716],"type":"Point"}
}