{
  "type": "Feature",
  "properties": {
    "iso:country":"US",
    "sg:address":"7349 Van Buren Ave",
    "sg:city":"Hammond",
    "sg:classifiers":[
        {
            "category":"Professional",
            "type":"Services"
        }
    ],
    "sg:phone":"+1 219 933 0122",
    "sg:postcode":"46324",
    "sg:province":"IN",
    "sg:tags":[
        "establishment"
    ],
    "wof:name":"Ancestry Inc",
    "wof:placetype":"venue"
},
  "geometry": {"coordinates":[-87.515001,41.580035],"type":"Point"}
}