{
  "type": "Feature",
  "properties": {
    "iso:country":"US",
    "sg:address":"10064 N 600 E",
    "sg:city":"Roselawn",
    "sg:classifiers":[
        {
            "category":"Shopping",
            "subcategory":"Pharmacy",
            "type":"Retail Goods"
        }
    ],
    "sg:phone":"+1 219 345 2057",
    "sg:postcode":"46310",
    "sg:province":"IN",
    "wof:name":"Fagen Pharmacy",
    "wof:placetype":"venue"
},
  "geometry": {"coordinates":[-87.27579900000001,41.144506],"type":"Point"}
}