{
  "type": "Feature",
  "properties": {
    "iso:country":"US",
    "sg:address":"104 N Madison Ave",
    "sg:city":"Fowler",
    "sg:classifiers":[
        {
            "category":"Personal",
            "subcategory":"Beauty Salon",
            "type":"Services"
        }
    ],
    "sg:phone":"+1 765 884 8150",
    "sg:postcode":"47944",
    "sg:province":"IN",
    "wof:name":"Guys & Dolls Hair & Nail Salon",
    "wof:placetype":"venue"
},
  "geometry": {"coordinates":[-87.32101900000001,40.618606],"type":"Point"}
}