{
  "type": "Feature",
  "properties": {
    "iso:country":"US",
    "sg:address":"3415 E Marquette Ave",
    "sg:city":"Terre Haute",
    "sg:classifiers":[
        {
            "category":"Organizations",
            "subcategory":"Religious Organization",
            "type":"Services"
        }
    ],
    "sg:phone":"+1 812 466 2998",
    "sg:postcode":"47805",
    "sg:province":"IN",
    "sg:tags":[
        "church"
    ],
    "sg:website":"www.springcreekcommunitychurch.org",
    "wof:name":"Spring Creek Community Church",
    "wof:placetype":"venue"
},
  "geometry": {"coordinates":[-87.364958,39.560616],"type":"Point"}
}