{
  "type": "Feature",
  "properties": {
    "iso:country":"US",
    "sg:address":"1045 Main St",
    "sg:city":"Indianapolis",
    "sg:classifiers":[
        {
            "category":"Professional",
            "subcategory":"Business Services",
            "type":"Services"
        }
    ],
    "sg:phone":"+1 317 227 3720",
    "sg:postcode":"46224",
    "sg:province":"IN",
    "sg:tags":[
        "liquidator"
    ],
    "sg:website":"www.njgallivan.com",
    "wof:name":"Norman Gallivan Inc",
    "wof:placetype":"venue"
},
  "geometry": {"coordinates":[-86.240917,39.781647],"type":"Point"}
}