{
  "type": "Feature",
  "properties": {
    "iso:country":"US",
    "sg:address":"149 W Elbert St",
    "sg:city":"Indianapolis",
    "sg:classifiers":[
        {
            "category":"Building & Trades",
            "subcategory":"Cleaning & Sanitation",
            "type":"Services"
        }
    ],
    "sg:phone":"+1 317 783 1067",
    "sg:postcode":"46217",
    "sg:province":"IN",
    "sg:tags":[
        "house"
    ],
    "wof:name":"VLN Enterprises Inc",
    "wof:placetype":"venue"
},
  "geometry": {"coordinates":[-86.15962,39.694227],"type":"Point"}
}