{
  "type": "Feature",
  "properties": {
    "iso:country":"US",
    "sg:address":"301 N Harrisburg Ave",
    "sg:city":"Gas City",
    "sg:classifiers":[
        {
            "category":"Health Services",
            "subcategory":"Nursing And Care Facility",
            "type":"Services"
        }
    ],
    "sg:phone":"+1 765 674 3065",
    "sg:postcode":"46933",
    "sg:province":"IN",
    "sg:tags":[
        "home",
        "retirement",
        "community"
    ],
    "wof:name":"Let Freedom Ring",
    "wof:placetype":"venue"
},
  "geometry": {"coordinates":[-85.619044,40.490251],"type":"Point"}
}