{
  "type": "Feature",
  "properties": {
    "iso:country":"US",
    "sg:address":"302 E 5th St",
    "sg:city":"West Lebanon",
    "sg:classifiers":[
        {
            "category":"Freight",
            "type":"Transportation"
        }
    ],
    "sg:phone":"+1 765 893 8578",
    "sg:postcode":"47991",
    "sg:province":"IN",
    "sg:tags":[
        "operator",
        "local",
        "trucking"
    ],
    "wof:name":"Alexander Trucking",
    "wof:placetype":"venue"
},
  "geometry": {"coordinates":[-87.383796,40.268224],"type":"Point"}
}