{
  "type": "Feature",
  "properties": {
    "iso:country":"US",
    "sg:address":"6901 E 45th St",
    "sg:city":"Indianapolis",
    "sg:classifiers":[
        {
            "category":"Social Services",
            "subcategory":"Child Care",
            "type":"Services"
        }
    ],
    "sg:phone":"+1 317 546 3737",
    "sg:postcode":"46226",
    "sg:province":"IN",
    "sg:website":"www.kindercare.com",
    "wof:name":"Kinder Care Learning Ctr",
    "wof:placetype":"venue"
},
  "geometry": {"coordinates":[-86.04725000000001,39.837823],"type":"Point"}
}