{
  "type": "Feature",
  "properties": {
    "iso:country":"US",
    "sg:address":"135 Industrial Access Rd",
    "sg:city":"Rising Sun",
    "sg:classifiers":[
        {
            "category":"Sports & Exercise",
            "subcategory":"Golf",
            "type":"Entertainment"
        }
    ],
    "sg:phone":"+1 812 438 2242",
    "sg:postcode":"47040",
    "sg:province":"IN",
    "sg:tags":[
        "course"
    ],
    "wof:name":"Pro Shop & Admin Building",
    "wof:placetype":"venue"
},
  "geometry": {"coordinates":[-84.844943,38.957187],"type":"Point"}
}