{
  "type": "Feature",
  "properties": {
    "iso:country":"US",
    "sg:address":"2 N 8th St",
    "sg:city":"Richmond",
    "sg:classifiers":[
        {
            "category":"Professional",
            "subcategory":"Lawyer & Legal Services",
            "type":"Services"
        }
    ],
    "sg:phone":"+1 765 966 6688",
    "sg:postcode":"47374",
    "sg:province":"IN",
    "sg:tags":[
        "attorney"
    ],
    "wof:name":"Gardner Sayre & Weikart",
    "wof:placetype":"venue"
},
  "geometry": {"coordinates":[-84.891562,39.829609],"type":"Point"}
}