{
  "type": "Feature",
  "properties": {
    "iso:country":"US",
    "sg:address":"291 Valley Rd",
    "sg:city":"Corydon",
    "sg:classifiers":[
        {
            "category":"Retail",
            "subcategory":"Repair Shop",
            "type":"Services"
        }
    ],
    "sg:phone":"+1 812 738 2648",
    "sg:postcode":"47112",
    "sg:province":"IN",
    "sg:tags":[
        "water",
        "equipment",
        "softening"
    ],
    "wof:name":"Culligan Water Conditioning",
    "wof:placetype":"venue"
},
  "geometry": {"coordinates":[-86.12313399999999,38.208661],"type":"Point"}
}