{
  "type": "Feature",
  "properties": {
    "addr:full":"2551 Chaseway Ct Indianapolis IN 46268",
    "addr:housenumber":"2551",
    "addr:postcode":"46268",
    "addr:street":"Chaseway Ct",
    "iso:country":"US",
    "sg:address":"2551 Chaseway Ct",
    "sg:city":"Indianapolis",
    "sg:classifiers":[
        {
            "category":"Professional",
            "subcategory":"Secretarial Services",
            "type":"Services"
        }
    ],
    "sg:phone":"+1 317 228 9829",
    "sg:postcode":"46268",
    "sg:province":"IN",
    "sg:tags":[
        "reporting",
        "court"
    ],
    "wof:name":"Business Savvy Business Svc",
    "wof:placetype":"venue"
},
  "geometry": {"coordinates":[-86.20676400000001,39.925961],"type":"Point"}
}