{
  "type": "Feature",
  "properties": {
    "iso:country":"US",
    "sg:address":"60907 Ridgepoint Ct",
    "sg:city":"Elkhart",
    "sg:classifiers":[
        {
            "category":"Professional",
            "type":"Services"
        }
    ],
    "sg:phone":"+1 574 875 5254",
    "sg:postcode":"46517",
    "sg:province":"IN",
    "sg:tags":[
        "establishment"
    ],
    "wof:name":"L M Berry Co",
    "wof:placetype":"venue"
},
  "geometry": {"coordinates":[-85.917385,41.610902],"type":"Point"}
}