{
  "type": "Feature",
  "properties": {
    "iso:country":"US",
    "sg:address":"207 E Walnut St",
    "sg:city":"Odon",
    "sg:classifiers":[
        {
            "category":"Professional",
            "type":"Services"
        }
    ],
    "sg:phone":"+1 812 636 7132",
    "sg:postcode":"47562",
    "sg:province":"IN",
    "sg:tags":[
        "establishment"
    ],
    "wof:name":"Zone Transportation",
    "wof:placetype":"venue"
},
  "geometry": {"coordinates":[-86.987642,38.841936],"type":"Point"}
}