{
  "type": "Feature",
  "properties": {
    "iso:country":"US",
    "sg:address":"1204 Summit St",
    "sg:city":"New Haven",
    "sg:classifiers":[
        {
            "category":"Personal",
            "subcategory":"Beauty Salon",
            "type":"Services"
        }
    ],
    "sg:phone":"+1 260 748 4107",
    "sg:postcode":"46774",
    "sg:province":"IN",
    "sg:tags":[
        "shop"
    ],
    "wof:name":"Noggins Inc",
    "wof:placetype":"venue"
},
  "geometry": {"coordinates":[-85.012257,41.07299],"type":"Point"}
}