{
  "type": "Feature",
  "properties": {
    "iso:country":"US",
    "sg:address":"9914 E 100 N",
    "sg:city":"Lafayette",
    "sg:classifiers":[
        {
            "category":"Retail",
            "subcategory":"Repair Shop",
            "type":"Services"
        }
    ],
    "sg:phone":"+1 765 296 3101",
    "sg:postcode":"47905",
    "sg:province":"IN",
    "sg:tags":[
        "farm",
        "equipment"
    ],
    "wof:name":"Ronald Hamilton",
    "wof:placetype":"venue"
},
  "geometry": {"coordinates":[-86.713176,40.432293],"type":"Point"}
}