{
  "type": "Feature",
  "properties": {
    "iso:country":"US",
    "sg:address":"4135 W Smith Valley Rd",
    "sg:city":"Greenwood",
    "sg:classifiers":[
        {
            "category":"Education",
            "subcategory":"School",
            "type":"Public Place"
        }
    ],
    "sg:phone":"+1 317 887 4707",
    "sg:postcode":"46142",
    "sg:province":"IN",
    "sg:website":"www.centergrove.k12.in.us",
    "wof:name":"Sugar Grove Elementary School",
    "wof:placetype":"venue"
},
  "geometry": {"coordinates":[-86.181856,39.60538],"type":"Point"}
}