{
  "type": "Feature",
  "properties": {
    "iso:country":"US",
    "sg:address":"11747 N Executive Dr",
    "sg:city":"Edinburgh",
    "sg:classifiers":[
        {
            "category":"Shopping",
            "subcategory":"Clothing, Apparel, & Fashions",
            "type":"Retail Goods"
        }
    ],
    "sg:phone":"+1 812 526 0650",
    "sg:postcode":"46124",
    "sg:province":"IN",
    "sg:tags":[
        "furnishing"
    ],
    "wof:name":"Casual Male Big & Tall",
    "wof:placetype":"venue"
},
  "geometry": {"coordinates":[-85.964151,39.310302],"type":"Point"}
}