{
  "type": "Feature",
  "properties": {
    "iso:country":"US",
    "sg:address":"2307 E Chicago Ave",
    "sg:city":"East Chicago",
    "sg:classifiers":[
        {
            "category":"Food & Beverages",
            "subcategory":"Liquor & Beverages",
            "type":"Retail Goods"
        }
    ],
    "sg:phone":"+1 219 398 9309",
    "sg:postcode":"46312",
    "sg:province":"IN",
    "sg:tags":[
        "alcoholic"
    ],
    "wof:name":"Sanders Liquors",
    "wof:placetype":"venue"
},
  "geometry": {"coordinates":[-87.435135,41.628795],"type":"Point"}
}