{
  "type": "Feature",
  "properties": {
    "addr:full":"1500 N Webster St Kokomo IN 46901",
    "addr:housenumber":"1500",
    "addr:postcode":"46901",
    "addr:street":"N Webster St",
    "iso:country":"US",
    "sg:address":"1500 N Webster St",
    "sg:city":"Kokomo",
    "sg:classifiers":[
        {
            "category":"Manufacturing",
            "subcategory":"Soap",
            "type":"Manufacturing & Wholesale Goods"
        }
    ],
    "sg:phone":"+1 765 868 4488",
    "sg:postcode":"46901",
    "sg:province":"IN",
    "sg:tags":[
        "detergent"
    ],
    "wof:name":"Tate Soap Surfactant",
    "wof:placetype":"venue"
},
  "geometry": {"coordinates":[-86.13615799999999,40.499906],"type":"Point"}
}