{
  "type": "Feature",
  "properties": {
    "iso:country":"US",
    "sg:address":"842 N 12th St",
    "sg:city":"Elwood",
    "sg:classifiers":[
        {
            "category":"Freight",
            "type":"Transportation"
        }
    ],
    "sg:phone":"+1 765 552 0587",
    "sg:postcode":"46036",
    "sg:province":"IN",
    "sg:tags":[
        "operator",
        "local",
        "trucking"
    ],
    "wof:name":"Dave Cannon",
    "wof:placetype":"venue"
},
  "geometry": {"coordinates":[-85.845848,40.285215],"type":"Point"}
}