{
  "type": "Feature",
  "properties": {
    "addr:full":"2403 Broadway St Anderson IN 46012",
    "addr:housenumber":"2403",
    "addr:postcode":"46012",
    "addr:street":"Broadway St",
    "iso:country":"US",
    "sg:address":"2403 Broadway St",
    "sg:city":"Anderson",
    "sg:classifiers":[
        {
            "category":"Restaurant",
            "type":"Food & Drink"
        }
    ],
    "sg:menulink":"http://www.allmenus.com/in/lafayette/120069-subway/menu/",
    "sg:phone":"+1 765 649 8993",
    "sg:postcode":"46012",
    "sg:province":"IN",
    "sg:tags":[
        "american",
        "sandwich"
    ],
    "wof:name":"Subway",
    "wof:placetype":"venue"
},
  "geometry": {"coordinates":[-85.677476,40.140703],"type":"Point"}
}