{
  "type": "Feature",
  "properties": {
    "iso:country":"US",
    "sg:address":"167 S State Rd 135",
    "sg:city":"Franklin",
    "sg:classifiers":[
        {
            "category":"Retail",
            "subcategory":"Veterinary Services",
            "type":"Services"
        }
    ],
    "sg:phone":"+1 317 422 9251",
    "sg:postcode":"46131",
    "sg:province":"IN",
    "sg:tags":[
        "hospital",
        "animal"
    ],
    "wof:name":"Briarcrest Animal Hospital",
    "wof:placetype":"venue"
},
  "geometry": {"coordinates":[-86.157828,39.474836],"type":"Point"}
}