{
  "type": "Feature",
  "properties": {
    "iso:country":"US",
    "sg:address":"207 E Main St",
    "sg:city":"Crawfordsville",
    "sg:classifiers":[
        {
            "category":"Professional",
            "subcategory":"Accounting & Tax Preparation",
            "type":"Services"
        }
    ],
    "sg:phone":"+1 765 762 6733",
    "sg:postcode":"47933",
    "sg:province":"IN",
    "sg:tags":[
        "billing"
    ],
    "wof:name":"Tri Corp Of Indiana Inc",
    "wof:placetype":"venue"
},
  "geometry": {"coordinates":[-86.89981,40.041654],"type":"Point"}
}