{
  "type": "Feature",
  "properties": {
    "addr:full":"1403 Walnut St Anderson IN 46016",
    "addr:housenumber":"1403",
    "addr:postcode":"46016",
    "addr:street":"Walnut St",
    "iso:country":"US",
    "sg:address":"1403 Walnut St",
    "sg:city":"Anderson",
    "sg:classifiers":[
        {
            "category":"Retail",
            "subcategory":"Repair Shop",
            "type":"Services"
        }
    ],
    "sg:phone":"+1 765 643 5433",
    "sg:postcode":"46016",
    "sg:province":"IN",
    "wof:name":"AAA Authorized Service",
    "wof:placetype":"venue"
},
  "geometry": {"coordinates":[-85.672828,40.101232],"type":"Point"}
}