{
  "type": "Feature",
  "properties": {
    "iso:country":"US",
    "sg:address":"357 E Morgan St",
    "sg:city":"Knightstown",
    "sg:classifiers":[
        {
            "category":"Organizations",
            "subcategory":"Religious Organization",
            "type":"Services"
        }
    ],
    "sg:phone":"+1 765 345 2930",
    "sg:postcode":"46148",
    "sg:province":"IN",
    "sg:tags":[
        "clergy"
    ],
    "wof:name":"Church Of The Nazarene Prsnge",
    "wof:placetype":"venue"
},
  "geometry": {"coordinates":[-85.52258,39.801338],"type":"Point"}
}