{
  "type": "Feature",
  "properties": {
    "iso:country":"US",
    "sg:address":"1301 Meadowbrook Dr",
    "sg:city":"Indianapolis",
    "sg:classifiers":[
        {
            "category":"Professional",
            "subcategory":"Business Services",
            "type":"Services"
        }
    ],
    "sg:phone":"+1 317 254 3100",
    "sg:postcode":"46240",
    "sg:province":"IN",
    "sg:tags":[
        "information",
        "referral"
    ],
    "wof:name":"Advanced Information Svc Inc",
    "wof:placetype":"venue"
},
  "geometry": {"coordinates":[-86.136007,39.906719],"type":"Point"}
}