{
  "type": "Feature",
  "properties": {
    "iso:country":"US",
    "sg:address":"100 Indiana Dr",
    "sg:city":"New Albany",
    "sg:classifiers":[
        {
            "category":"Retail",
            "subcategory":"Auto Repair",
            "type":"Services"
        }
    ],
    "sg:phone":"+1 812 944 9932",
    "sg:postcode":"47150",
    "sg:province":"IN",
    "sg:tags":[
        "body",
        "automobile",
        "painting"
    ],
    "wof:name":"Greg Andres' New Albany Auto",
    "wof:placetype":"venue"
},
  "geometry": {"coordinates":[-85.81907099999999,38.346181],"type":"Point"}
}