{
  "type": "Feature",
  "properties": {
    "iso:country":"US",
    "sg:address":"1360 Crossroad Ave",
    "sg:city":"Jasper",
    "sg:classifiers":[
        {
            "category":"Autos & Motor Vehicles",
            "subcategory":"Boat Sales",
            "type":"Retail Goods"
        }
    ],
    "sg:phone":"+1 812 482 9191",
    "sg:postcode":"47546",
    "sg:province":"IN",
    "sg:tags":[
        "dealer",
        "sales"
    ],
    "wof:name":"Port Of Jasper Inc",
    "wof:placetype":"venue"
},
  "geometry": {"coordinates":[-86.903296,38.389814],"type":"Point"}
}