{
  "type": "Feature",
  "properties": {
    "iso:country":"US",
    "sg:address":"720 W Willard St",
    "sg:city":"Muncie",
    "sg:classifiers":[
        {
            "category":"Manufacturing",
            "subcategory":"Tools & Machinery",
            "type":"Manufacturing & Wholesale Goods"
        }
    ],
    "sg:phone":"+1 765 284 8351",
    "sg:postcode":"47302",
    "sg:province":"IN",
    "sg:tags":[
        "physician",
        "surgeon"
    ],
    "sg:website":"www.hiattmetal.com",
    "wof:name":"Hiatt Metal Products Co",
    "wof:placetype":"venue"
},
  "geometry": {"coordinates":[-85.393288,40.185686],"type":"Point"}
}