{
  "type": "Feature",
  "properties": {
    "iso:country":"US",
    "sg:address":"8037 N County Line Rd",
    "sg:city":"Deputy",
    "sg:classifiers":[
        {
            "category":"Farming",
            "subcategory":"Livestock Farm",
            "type":"Manufacturing & Wholesale Goods"
        }
    ],
    "sg:phone":"+1 812 794 4036",
    "sg:postcode":"47227",
    "sg:province":"IN",
    "sg:tags":[
        "beef",
        "feedlot",
        "cattle"
    ],
    "wof:name":"Hammersley Farm",
    "wof:placetype":"venue"
},
  "geometry": {"coordinates":[-85.573678,38.855654],"type":"Point"}
}