{
  "type": "Feature",
  "properties": {
    "iso:country":"US",
    "sg:address":"4330 Sulphur Valley Rd",
    "sg:city":"Tell City",
    "sg:classifiers":[
        {
            "category":"Food & Beverages",
            "subcategory":"Fruits & Vegetables",
            "type":"Retail Goods"
        }
    ],
    "sg:phone":"+1 812 836 2254",
    "sg:postcode":"47586",
    "sg:province":"IN",
    "sg:tags":[
        "produce"
    ],
    "wof:name":"Fallscraft Products",
    "wof:placetype":"venue"
},
  "geometry": {"coordinates":[-86.743792,38.09169],"type":"Point"}
}