{
  "type": "Feature",
  "properties": {
    "iso:country":"US",
    "sg:address":"7834 Queen Rd",
    "sg:city":"Plymouth",
    "sg:classifiers":[
        {
            "category":"Manufacturing",
            "subcategory":"Tools & Machinery",
            "type":"Manufacturing & Wholesale Goods"
        }
    ],
    "sg:phone":"+1 574 936 9574",
    "sg:postcode":"46563",
    "sg:province":"IN",
    "sg:tags":[
        "electrical",
        "apparatus"
    ],
    "wof:name":"Kay Industries Inc",
    "wof:placetype":"venue"
},
  "geometry": {"coordinates":[-86.376837,41.363242],"type":"Point"}
}