{
  "type": "Feature",
  "properties": {
    "iso:country":"US",
    "sg:address":"6005 N 600 E",
    "sg:city":"Falmouth",
    "sg:classifiers":[
        {
            "category":"Professional",
            "subcategory":"Business Services",
            "type":"Services"
        }
    ],
    "sg:phone":"+1 765 679 1412",
    "sg:postcode":"46127",
    "sg:province":"IN",
    "wof:name":"J C M W Co",
    "wof:placetype":"venue"
},
  "geometry": {"coordinates":[-85.339166,39.701064],"type":"Point"}
}