{
  "type": "Feature",
  "properties": {
    "iso:country":"US",
    "sg:address":"7009 E 56th St",
    "sg:city":"Indianapolis",
    "sg:classifiers":[
        {
            "category":"Building & Trades",
            "subcategory":"Cleaning & Sanitation",
            "type":"Services"
        }
    ],
    "sg:phone":"+1 317 545 9000",
    "sg:postcode":"46226",
    "sg:province":"IN",
    "sg:tags":[
        "chemical"
    ],
    "wof:name":"Concord Inndustrial Inc",
    "wof:placetype":"venue"
},
  "geometry": {"coordinates":[-86.04172699999999,39.855103],"type":"Point"}
}