{
  "type": "Feature",
  "properties": {
    "iso:country":"US",
    "sg:address":"1805 US Hwy 231 S",
    "sg:city":"Crawfordsville",
    "sg:classifiers":[
        {
            "category":"Retail",
            "subcategory":"Auto Rental",
            "type":"Services"
        }
    ],
    "sg:phone":"+1 765 361 8964",
    "sg:postcode":"47933",
    "sg:province":"IN",
    "sg:tags":[
        "renting",
        "automobile"
    ],
    "wof:name":"Enterprise Rent-A-Car",
    "wof:placetype":"venue"
},
  "geometry": {"coordinates":[-86.903941,40.013708],"type":"Point"}
}