{
  "type": "Feature",
  "properties": {
    "iso:country":"US",
    "sg:address":"9702 Pendleton Pike",
    "sg:city":"Oaklandon",
    "sg:classifiers":[
        {
            "category":"Autos & Motor Vehicles",
            "subcategory":"Recreational Vehicle Sales",
            "type":"Retail Goods"
        }
    ],
    "sg:phone":"+1 317 890 0791",
    "sg:postcode":"46236",
    "sg:province":"IN",
    "sg:website":"www.funtimecampers.com",
    "wof:name":"Braun's Fun Time Campers",
    "wof:placetype":"venue"
},
  "geometry": {"coordinates":[-85.996918,39.850905],"type":"Point"}
}