{
  "type": "Feature",
  "properties": {
    "iso:country":"US",
    "sg:address":"1121 W Washington Center Rd",
    "sg:city":"Fort Wayne",
    "sg:classifiers":[
        {
            "category":"Home & Garden",
            "subcategory":"Furniture",
            "type":"Retail Goods"
        }
    ],
    "sg:phone":"+1 260 489 7644",
    "sg:postcode":"46825",
    "sg:province":"IN",
    "wof:name":"Ethan Allen Furniture",
    "wof:placetype":"venue"
},
  "geometry": {"coordinates":[-85.158765,41.132341],"type":"Point"}
}