{
  "type": "Feature",
  "properties": {
    "addr:full":"5975 Castleway West Dr Indianapolis IN 46250",
    "addr:housenumber":"5975",
    "addr:postcode":"46250",
    "addr:street":"Castleway West Dr",
    "iso:country":"US",
    "sg:address":"5975 Castleway West Dr",
    "sg:city":"Indianapolis",
    "sg:classifiers":[
        {
            "category":"Professional",
            "subcategory":"Computer Services",
            "type":"Services"
        }
    ],
    "sg:phone":"+1 317 222 1211",
    "sg:postcode":"46250",
    "sg:province":"IN",
    "sg:tags":[
        "technical",
        "assistance",
        "support"
    ],
    "wof:name":"Worldwide Solutions Group",
    "wof:placetype":"venue"
},
  "geometry": {"coordinates":[-86.06698400000001,39.903839],"type":"Point"}
}