{
  "type": "Feature",
  "properties": {
    "iso:country":"US",
    "sg:address":"1760 Apple Glen Blvd",
    "sg:city":"Fort Wayne",
    "sg:classifiers":[
        {
            "category":"Shopping",
            "type":"Retail Goods"
        }
    ],
    "sg:phone":"+1 260 436 7323",
    "sg:postcode":"46804",
    "sg:province":"IN",
    "sg:tags":[
        "pet",
        "shop"
    ],
    "sg:website":"www.petsmart.com",
    "wof:name":"Petsmart",
    "wof:placetype":"venue"
},
  "geometry": {"coordinates":[-85.194574,41.073003],"type":"Point"}
}