{
  "type": "Feature",
  "properties": {
    "iso:country":"US",
    "sg:address":"981 S 100 E",
    "sg:city":"Portland",
    "sg:classifiers":[
        {
            "category":"Personal",
            "subcategory":"Beauty Salon",
            "type":"Services"
        }
    ],
    "sg:phone":"+1 260 726 3988",
    "sg:postcode":"47371",
    "sg:province":"IN",
    "sg:tags":[
        "manicuring"
    ],
    "wof:name":"Nail Illusions",
    "wof:placetype":"venue"
},
  "geometry": {"coordinates":[-84.958574,40.425702],"type":"Point"}
}