{
  "type": "Feature",
  "properties": {
    "addr:full":"2026 Davidson Pl Whiting IN 46394",
    "addr:housenumber":"2026",
    "addr:postcode":"46394",
    "addr:street":"Davidson Pl",
    "iso:country":"US",
    "sg:address":"2026 Davidson Pl",
    "sg:city":"Whiting",
    "sg:classifiers":[
        {
            "category":"Organizations",
            "subcategory":"Religious Organization",
            "type":"Services"
        }
    ],
    "sg:phone":"+1 219 659 8432",
    "sg:postcode":"46394",
    "sg:province":"IN",
    "sg:tags":[
        "church"
    ],
    "wof:name":"Whiting Church Of The Nazarene",
    "wof:placetype":"venue"
},
  "geometry": {"coordinates":[-87.494851,41.67573],"type":"Point"}
}