{
  "type": "Feature",
  "properties": {
    "iso:country":"US",
    "sg:address":"2221 N 6th St",
    "sg:city":"Vincennes",
    "sg:classifiers":[
        {
            "category":"Restaurant",
            "type":"Food & Drink"
        }
    ],
    "sg:phone":"+1 812 882 9304",
    "sg:postcode":"47591",
    "sg:province":"IN",
    "wof:name":"Mr Gatti's Pizza",
    "wof:placetype":"venue"
},
  "geometry": {"coordinates":[-87.506964,38.688323],"type":"Point"}
}