{
  "type": "Feature",
  "properties": {
    "iso:country":"US",
    "sg:address":"8140 Township Line Rd",
    "sg:city":"Indianapolis",
    "sg:classifiers":[
        {
            "category":"Personal",
            "subcategory":"Beauty Salon",
            "type":"Services"
        }
    ],
    "sg:phone":"+1 317 471 8537",
    "sg:postcode":"46260",
    "sg:province":"IN",
    "wof:name":"Hair Care Ctr",
    "wof:placetype":"venue"
},
  "geometry": {"coordinates":[-86.203102,39.901656],"type":"Point"}
}