{
  "type": "Feature",
  "properties": {
    "iso:country":"US",
    "sg:address":"4747 Western Ave",
    "sg:city":"Connersville",
    "sg:classifiers":[
        {
            "category":"Manufacturing",
            "subcategory":"Motor Vehicles & Parts",
            "type":"Manufacturing & Wholesale Goods"
        }
    ],
    "sg:phone":"+1 765 825 7551",
    "sg:postcode":"47331",
    "sg:province":"IN",
    "sg:tags":[
        "automobile",
        "supply"
    ],
    "wof:name":"Visteon Corp",
    "wof:placetype":"venue"
},
  "geometry": {"coordinates":[-85.138407,39.688945],"type":"Point"}
}