{
  "type": "Feature",
  "properties": {
    "iso:country":"US",
    "sg:address":"1600 W Beardsley Ave",
    "sg:city":"Elkhart",
    "sg:classifiers":[
        {
            "category":"Professional",
            "subcategory":"Management & Consulting",
            "type":"Services"
        }
    ],
    "sg:phone":"+1 574 389 3515",
    "sg:postcode":"46514",
    "sg:province":"IN",
    "sg:tags":[
        "consultant",
        "energy",
        "conservation"
    ],
    "wof:name":"Global Resource Management LTD",
    "wof:placetype":"venue"
},
  "geometry": {"coordinates":[-86.000907,41.692592],"type":"Point"}
}