{
  "type": "Feature",
  "properties": {
    "iso:country":"US",
    "sg:address":"7233 N Frontage Rd",
    "sg:city":"Fairland",
    "sg:classifiers":[
        {
            "category":"Real Estate",
            "subcategory":"Real Estate Agent",
            "type":"Services"
        }
    ],
    "sg:phone":"+1 317 357 8830",
    "sg:postcode":"46126",
    "sg:province":"IN",
    "sg:tags":[
        "inspection"
    ],
    "wof:name":"Mark Oliver & Assoc",
    "wof:placetype":"venue"
},
  "geometry": {"coordinates":[-85.886736,39.628639],"type":"Point"}
}