{
  "type": "Feature",
  "properties": {
    "addr:full":"1005 Coliseum Blvd N Fort Wayne IN 46805",
    "addr:housenumber":"1005",
    "addr:postcode":"46805",
    "addr:street":"Coliseum Blvd N",
    "iso:country":"US",
    "sg:address":"1005 Coliseum Blvd N",
    "sg:city":"Fort Wayne",
    "sg:classifiers":[
        {
            "category":"Shopping",
            "subcategory":"Musical Instruments",
            "type":"Retail Goods"
        }
    ],
    "sg:phone":"+1 260 483 1007",
    "sg:postcode":"46805",
    "sg:province":"IN",
    "wof:name":"Tri State Music",
    "wof:placetype":"venue"
},
  "geometry": {"coordinates":[-85.08781999999999,41.084192],"type":"Point"}
}