{
  "type": "Feature",
  "properties": {
    "iso:country":"US",
    "sg:address":"2496 Churchman Ave",
    "sg:city":"Indianapolis",
    "sg:classifiers":[
        {
            "category":"Retail",
            "subcategory":"Auto Repair",
            "type":"Services"
        }
    ],
    "sg:phone":"+1 317 782 0757",
    "sg:postcode":"46203",
    "sg:province":"IN",
    "sg:tags":[
        "repairing",
        "automobile"
    ],
    "wof:name":"Blue Point Garage",
    "wof:placetype":"venue"
},
  "geometry": {"coordinates":[-86.115742,39.734218],"type":"Point"}
}