{
  "type": "Feature",
  "properties": {
    "iso:country":"US",
    "sg:address":"433 Council Dr",
    "sg:city":"Fort Wayne",
    "sg:classifiers":[
        {
            "category":"Wholesale",
            "subcategory":"Machinery & Supplies",
            "type":"Manufacturing & Wholesale Goods"
        }
    ],
    "sg:phone":"+1 260 471 9372",
    "sg:postcode":"46825",
    "sg:province":"IN",
    "wof:name":"Machine Tool Technologies",
    "wof:placetype":"venue"
},
  "geometry": {"coordinates":[-85.148971,41.128082],"type":"Point"}
}