{
  "type": "Feature",
  "properties": {
    "iso:country":"US",
    "sg:address":"5622 US Hwy 41",
    "sg:city":"Terre Haute",
    "sg:classifiers":[
        {
            "category":"Freight",
            "type":"Transportation"
        }
    ],
    "sg:phone":"+1 812 466 7874",
    "sg:postcode":"47807",
    "sg:province":"IN",
    "sg:tags":[
        "warehouse"
    ],
    "wof:name":"E-Z System Inc",
    "wof:placetype":"venue"
},
  "geometry": {"coordinates":[-87.397715,39.541536],"type":"Point"}
}