{
  "type": "Feature",
  "properties": {
    "iso:country":"US",
    "sg:address":"5959 Gladden Dr",
    "sg:city":"Indianapolis",
    "sg:classifiers":[
        {
            "category":"Professional",
            "subcategory":"Management & Consulting",
            "type":"Services"
        }
    ],
    "sg:phone":"+1 317 253 6212",
    "sg:postcode":"46220",
    "sg:province":"IN",
    "wof:name":"Maxwell Associates Inc",
    "wof:placetype":"venue"
},
  "geometry": {"coordinates":[-86.156119,39.861671],"type":"Point"}
}