{
  "type": "Feature",
  "properties": {
    "iso:country":"US",
    "sg:address":"2155 Fields Blvd",
    "sg:city":"Greenfield",
    "sg:classifiers":[
        {
            "category":"Wholesale",
            "subcategory":"Groceries",
            "type":"Manufacturing & Wholesale Goods"
        }
    ],
    "sg:phone":"+1 317 468 1248",
    "sg:postcode":"46140",
    "sg:province":"IN",
    "sg:tags":[
        "food",
        "broker"
    ],
    "wof:name":"Rocque Perlman Co",
    "wof:placetype":"venue"
},
  "geometry": {"coordinates":[-85.773377,39.814662],"type":"Point"}
}