{
  "type": "Feature",
  "properties": {
    "iso:country":"US",
    "sg:address":"810 E 64th St",
    "sg:city":"Indianapolis",
    "sg:classifiers":[
        {
            "category":"Real Estate",
            "subcategory":"Real Estate Agent",
            "type":"Services"
        }
    ],
    "sg:phone":"+1 317 251 6529",
    "sg:postcode":"46220",
    "sg:province":"IN",
    "wof:name":"Apter Properties",
    "wof:placetype":"venue"
},
  "geometry": {"coordinates":[-86.144164,39.872628],"type":"Point"}
}