{
  "type": "Feature",
  "properties": {
    "iso:country":"US",
    "sg:address":"11216 Fall Creek Rd",
    "sg:city":"Indianapolis",
    "sg:classifiers":[
        {
            "category":"Health Services",
            "subcategory":"Doctor",
            "type":"Services"
        }
    ],
    "sg:phone":"+1 317 595 8824",
    "sg:postcode":"46256",
    "sg:province":"IN",
    "sg:tags":[
        "clinic"
    ],
    "wof:name":"Carepoint Immediate Medical",
    "wof:placetype":"venue"
},
  "geometry": {"coordinates":[-85.968261,39.931587],"type":"Point"}
}