{
  "type": "Feature",
  "properties": {
    "iso:country":"US",
    "sg:address":"8737 Monroe Ave",
    "sg:city":"Munster",
    "sg:classifiers":[
        {
            "category":"Home & Garden",
            "subcategory":"Hardware",
            "type":"Retail Goods"
        }
    ],
    "sg:phone":"+1 219 836 2215",
    "sg:postcode":"46321",
    "sg:province":"IN",
    "wof:name":"Dj Tool Sales",
    "wof:placetype":"venue"
},
  "geometry": {"coordinates":[-87.512856,41.554386],"type":"Point"}
}