{
  "type": "Feature",
  "properties": {
    "iso:country":"US",
    "sg:address":"400 S Buffalo St",
    "sg:city":"Warsaw",
    "sg:classifiers":[
        {
            "category":"Food & Beverages",
            "subcategory":"Groceries & Convenience Stores",
            "type":"Retail Goods"
        }
    ],
    "sg:phone":"+1 574 267 3088",
    "sg:postcode":"46580",
    "sg:province":"IN",
    "wof:name":"Village Pantry",
    "wof:placetype":"venue"
},
  "geometry": {"coordinates":[-85.85664800000001,41.235174],"type":"Point"}
}