{
  "type": "Feature",
  "properties": {
    "iso:country":"US",
    "sg:address":"11941 N Executive Dr",
    "sg:city":"Edinburgh",
    "sg:classifiers":[
        {
            "category":"Wholesale",
            "subcategory":"Apparel",
            "type":"Manufacturing & Wholesale Goods"
        }
    ],
    "sg:phone":"+1 812 526 9690",
    "sg:postcode":"46124",
    "sg:province":"IN",
    "sg:tags":[
        "infant",
        "wear"
    ],
    "wof:name":"Hartstrings",
    "wof:placetype":"venue"
},
  "geometry": {"coordinates":[-85.964317,39.311562],"type":"Point"}
}