{
  "type": "Feature",
  "properties": {
    "iso:country":"US",
    "sg:address":"14396 Sage Ct",
    "sg:city":"Mishawaka",
    "sg:classifiers":[
        {
            "category":"Professional",
            "subcategory":"Business Services",
            "type":"Services"
        }
    ],
    "sg:phone":"+1 574 257 8316",
    "sg:postcode":"46545",
    "sg:province":"IN",
    "wof:name":"Design Resource",
    "wof:placetype":"venue"
},
  "geometry": {"coordinates":[-86.14583500000001,41.700309],"type":"Point"}
}