{
  "type": "Feature",
  "properties": {
    "iso:country":"US",
    "sg:address":"1027 Sheffield Ave",
    "sg:city":"Dyer",
    "sg:classifiers":[
        {
            "category":"Restaurant",
            "type":"Food & Drink"
        }
    ],
    "sg:phone":"+1 219 322 2640",
    "sg:postcode":"46311",
    "sg:province":"IN",
    "wof:name":"Sheffields Restaurant & Sports",
    "wof:placetype":"venue"
},
  "geometry": {"coordinates":[-87.518702,41.511909],"type":"Point"}
}