{
  "type": "Feature",
  "properties": {
    "addr:full":"17427 State Rd 60 Borden IN 47106",
    "addr:housenumber":"17427;60",
    "addr:postcode":"47106",
    "addr:street":"State Rd",
    "iso:country":"US",
    "sg:address":"17427 State Rd 60",
    "sg:city":"Borden",
    "sg:classifiers":[
        {
            "category":"Professional",
            "subcategory":"Business Services",
            "type":"Services"
        }
    ],
    "sg:phone":"+1 812 967 1900",
    "sg:postcode":"47106",
    "sg:province":"IN",
    "sg:tags":[
        "process",
        "server"
    ],
    "wof:name":"Legal Process Svc",
    "wof:placetype":"venue"
},
  "geometry": {"coordinates":[-85.897733,38.444034],"type":"Point"}
}