{
  "type": "Feature",
  "properties": {
    "addr:full":"3324 George St Highland IN 46322",
    "addr:housenumber":"3324",
    "addr:postcode":"46322",
    "addr:street":"George St",
    "iso:country":"US",
    "sg:address":"3324 George St",
    "sg:city":"Highland",
    "sg:classifiers":[
        {
            "category":"Professional",
            "subcategory":"Computer Services",
            "type":"Services"
        }
    ],
    "sg:phone":"+1 219 922 6373",
    "sg:postcode":"46322",
    "sg:province":"IN",
    "wof:name":"Designwerks LLC",
    "wof:placetype":"venue"
},
  "geometry": {"coordinates":[-87.44940699999999,41.53872],"type":"Point"}
}