{
  "type": "Feature",
  "properties": {
    "iso:country":"US",
    "sg:address":"2322 Turnberry Ln",
    "sg:city":"Fort Wayne",
    "sg:classifiers":[
        {
            "category":"Wholesale",
            "subcategory":"Durable Goods & Equipment",
            "type":"Manufacturing & Wholesale Goods"
        }
    ],
    "sg:phone":"+1 260 625 3026",
    "sg:postcode":"46814",
    "sg:province":"IN",
    "sg:tags":[
        "representative",
        "manufacturer"
    ],
    "wof:name":"Midwest Specialty Products Inc",
    "wof:placetype":"venue"
},
  "geometry": {"coordinates":[-85.286115,41.067883],"type":"Point"}
}