{
  "type": "Feature",
  "properties": {
    "iso:country":"US",
    "sg:address":"1540 Blaine Ave",
    "sg:city":"Indianapolis",
    "sg:classifiers":[
        {
            "category":"Wholesale",
            "subcategory":"Motor Vehicles",
            "type":"Manufacturing & Wholesale Goods"
        }
    ],
    "sg:phone":"+1 317 635 4942",
    "sg:postcode":"46221",
    "sg:province":"IN",
    "sg:tags":[
        "trailer"
    ],
    "wof:name":"D & N Trailer Co",
    "wof:placetype":"venue"
},
  "geometry": {"coordinates":[-86.188363,39.743975],"type":"Point"}
}