{
  "type": "Feature",
  "properties": {
    "addr:full":"3341 State Rte 725 W Camden IN 45311",
    "addr:housenumber":"3341",
    "addr:postcode":"45311",
    "addr:street":"State Rte 725 W",
    "iso:country":"US",
    "sg:address":"3341 State Rte 725 W",
    "sg:city":"Camden",
    "sg:classifiers":[
        {
            "category":"Manufacturing",
            "subcategory":"Motor Vehicles & Parts",
            "type":"Manufacturing & Wholesale Goods"
        }
    ],
    "sg:phone":"+1 937 452 7251",
    "sg:postcode":"45311",
    "sg:province":"IN",
    "sg:tags":[
        "truck",
        "trailer",
        "mfg"
    ],
    "wof:name":"Rudy L Lunsford",
    "wof:placetype":"venue"
},
  "geometry": {"coordinates":[-84.708045,39.626197],"type":"Point"}
}