{
  "type": "Feature",
  "properties": {
    "iso:country":"US",
    "sg:address":"216 N Main St",
    "sg:city":"Lynnville",
    "sg:classifiers":[
        {
            "category":"Government",
            "subcategory":"Post Office",
            "type":"Public Place"
        }
    ],
    "sg:phone":"+1 812 922 3249",
    "sg:postcode":"47619",
    "sg:province":"IN",
    "wof:name":"US Post Office",
    "wof:placetype":"venue"
},
  "geometry": {"coordinates":[-87.298053,38.19853],"type":"Point"}
}