{
  "type": "Feature",
  "properties": {
    "iso:country":"US",
    "sg:address":"2800 Chase St",
    "sg:city":"Gary",
    "sg:classifiers":[
        {
            "category":"Wholesale",
            "subcategory":"Auto Parts",
            "type":"Manufacturing & Wholesale Goods"
        }
    ],
    "sg:phone":"+1 219 944 9200",
    "sg:postcode":"46404",
    "sg:province":"IN",
    "sg:tags":[
        "automobile",
        "wrecking"
    ],
    "wof:name":"Chase St Towing & Recovery",
    "wof:placetype":"venue"
},
  "geometry": {"coordinates":[-87.375337,41.566072],"type":"Point"}
}