{
  "type": "Feature",
  "properties": {
    "addr:full":"1207 Jefferson Ave Laporte IN 46350",
    "addr:housenumber":"1207",
    "addr:postcode":"46350",
    "addr:street":"Jefferson Ave",
    "iso:country":"US",
    "sg:address":"1207 Jefferson Ave",
    "sg:city":"Laporte",
    "sg:classifiers":[
        {
            "category":"Personal",
            "subcategory":"Beauty Salon",
            "type":"Services"
        }
    ],
    "sg:phone":"+1 219 362 8551",
    "sg:postcode":"46350",
    "sg:province":"IN",
    "wof:name":"Polly Ann's Hair Fashion Salon",
    "wof:placetype":"venue"
},
  "geometry": {"coordinates":[-86.72462899999999,41.608455],"type":"Point"}
}