{
  "type": "Feature",
  "properties": {
    "iso:country":"US",
    "sg:address":"476 E Burdick Rd",
    "sg:city":"Chesterton",
    "sg:classifiers":[
        {
            "category":"Building & Trades",
            "subcategory":"Construction",
            "type":"Services"
        }
    ],
    "sg:phone":"+1 219 926 7160",
    "sg:postcode":"46304",
    "sg:province":"IN",
    "sg:tags":[
        "water",
        "well",
        "drilling"
    ],
    "wof:name":"Zurek Well Service",
    "wof:placetype":"venue"
},
  "geometry": {"coordinates":[-86.972901,41.600885],"type":"Point"}
}