{
  "type": "Feature",
  "properties": {
    "iso:country":"US",
    "sg:address":"1817 Scheller Ln",
    "sg:city":"New Albany",
    "sg:classifiers":[
        {
            "category":"Building & Trades",
            "subcategory":"Landscaping Services",
            "type":"Services"
        }
    ],
    "sg:phone":"+1 812 945 0707",
    "sg:postcode":"47150",
    "sg:province":"IN",
    "sg:tags":[
        "landscape",
        "contractor"
    ],
    "wof:name":"Tinius Landscape & Aquatics",
    "wof:placetype":"venue"
},
  "geometry": {"coordinates":[-85.808815,38.321658],"type":"Point"}
}