{
  "type": "Feature",
  "properties": {
    "iso:country":"US",
    "sg:address":"4006 Hiawatha Blvd",
    "sg:city":"Fort Wayne",
    "sg:classifiers":[
        {
            "category":"Wholesale",
            "subcategory":"Machinery & Supplies",
            "type":"Manufacturing & Wholesale Goods"
        }
    ],
    "sg:phone":"+1 260 747 0912",
    "sg:postcode":"46809",
    "sg:province":"IN",
    "sg:tags":[
        "machine",
        "tool"
    ],
    "wof:name":"Welling Machinery Co Inc",
    "wof:placetype":"venue"
},
  "geometry": {"coordinates":[-85.172966,41.046645],"type":"Point"}
}