{
  "type": "Feature",
  "properties": {
    "iso:country":"US",
    "sg:address":"502 N Capitol Ave",
    "sg:city":"Indianapolis",
    "sg:classifiers":[
        {
            "category":"Health Services",
            "subcategory":"Clinic",
            "type":"Services"
        }
    ],
    "sg:phone":"+1 317 637 3294",
    "sg:postcode":"46204",
    "sg:province":"IN",
    "sg:tags":[
        "banks",
        "blood",
        "center"
    ],
    "sg:website":"www.plasmacare.com",
    "wof:name":"Indianapolis Blood Plasma Inc",
    "wof:placetype":"venue"
},
  "geometry": {"coordinates":[-86.161465,39.775568],"type":"Point"}
}