{
  "type": "Feature",
  "properties": {
    "iso:country":"US",
    "sg:address":"9297 Vine St",
    "sg:city":"Manilla",
    "sg:classifiers":[
        {
            "category":"Building & Trades",
            "subcategory":"Construction",
            "type":"Services"
        }
    ],
    "sg:phone":"+1 765 932 2625",
    "sg:postcode":"46150",
    "sg:province":"IN",
    "wof:name":"Truster Buildings Inc",
    "wof:placetype":"venue"
},
  "geometry": {"coordinates":[-85.617721,39.572273],"type":"Point"}
}