{
  "type": "Feature",
  "properties": {
    "iso:country":"US",
    "sg:address":"3600 State Rd 38 E",
    "sg:city":"Lafayette",
    "sg:classifiers":[
        {
            "category":"Autos & Motor Vehicles",
            "subcategory":"Recreational Vehicle Sales",
            "type":"Retail Goods"
        }
    ],
    "sg:phone":"+1 765 447 5111",
    "sg:postcode":"47905",
    "sg:province":"IN",
    "sg:website":"www.billgardinerrv.com",
    "wof:name":"Bill Gardiner RV Sales & Svc",
    "wof:placetype":"venue"
},
  "geometry": {"coordinates":[-86.84717499999999,40.393313],"type":"Point"}
}