{
  "type": "Feature",
  "properties": {
    "iso:country":"US",
    "sg:address":"16947 Co Rd 42",
    "sg:city":"Goshen",
    "sg:classifiers":[
        {
            "category":"Airport",
            "type":"Transportation"
        }
    ],
    "sg:phone":"+1 574 642 4202",
    "sg:postcode":"46526",
    "sg:province":"IN",
    "wof:name":"CTB Inc Corporate Hangar",
    "wof:placetype":"venue"
},
  "geometry": {"coordinates":[-85.77975,41.522785],"type":"Point"}
}