{
  "type": "Feature",
  "properties": {
    "addr:full":"405 Cottage St Delphi IN 46923",
    "addr:housenumber":"405",
    "addr:postcode":"46923",
    "addr:street":"Cottage St",
    "iso:country":"US",
    "sg:address":"405 Cottage St",
    "sg:city":"Delphi",
    "sg:classifiers":[
        {
            "category":"Organizations",
            "subcategory":"Religious Organization",
            "type":"Services"
        }
    ],
    "sg:phone":"+1 765 564 4488",
    "sg:postcode":"46923",
    "sg:province":"IN",
    "sg:tags":[
        "church"
    ],
    "wof:name":"Church Of Christ",
    "wof:placetype":"venue"
},
  "geometry": {"coordinates":[-86.66331099999999,40.589532],"type":"Point"}
}