{
  "type": "Feature",
  "properties": {
    "addr:full":"57721 State Rd 19 Elkhart IN 46517",
    "addr:housenumber":"57721;19",
    "addr:postcode":"46517",
    "addr:street":"State Rd",
    "iso:country":"US",
    "sg:address":"57721 State Rd 19",
    "sg:city":"Elkhart",
    "sg:classifiers":[
        {
            "category":"Autos & Motor Vehicles",
            "subcategory":"Fuel & Gas Station",
            "type":"Retail Goods"
        }
    ],
    "sg:phone":"+1 574 296 9806",
    "sg:postcode":"46517",
    "sg:province":"IN",
    "sg:tags":[
        "oil"
    ],
    "wof:name":"Speedway",
    "wof:placetype":"venue"
},
  "geometry": {"coordinates":[-86.003123,41.6557],"type":"Point"}
}