{
  "type": "Feature",
  "properties": {
    "addr:full":"7140 Georgetown Rd Indianapolis IN 46268",
    "addr:housenumber":"7140",
    "addr:postcode":"46268",
    "addr:street":"Georgetown Rd",
    "iso:country":"US",
    "sg:address":"7140 Georgetown Rd",
    "sg:city":"Indianapolis",
    "sg:classifiers":[
        {
            "category":"Restaurant",
            "type":"Food & Drink"
        }
    ],
    "sg:menulink":"http://www.allmenus.com/in/pike/167362-burger-king/menu/",
    "sg:phone":"+1 317 347 0908",
    "sg:postcode":"46268",
    "sg:province":"IN",
    "sg:tags":[
        "burger",
        "american"
    ],
    "wof:name":"Burger King",
    "wof:placetype":"venue"
},
  "geometry": {"coordinates":[-86.244974,39.883063],"type":"Point"}
}