{
  "type": "Feature",
  "properties": {
    "addr:full":"6025 W 300 S Lafayette IN 47909",
    "addr:housenumber":"6025",
    "addr:postcode":"47909",
    "addr:street":"W 300 S",
    "iso:country":"US",
    "sg:address":"6025 W 300 S",
    "sg:city":"Lafayette",
    "sg:classifiers":[
        {
            "category":"Shopping",
            "subcategory":"Florist",
            "type":"Retail Goods"
        }
    ],
    "sg:phone":"+1 765 572 2905",
    "sg:postcode":"47909",
    "sg:province":"IN",
    "sg:tags":[
        "plant"
    ],
    "wof:name":"Westbred",
    "wof:placetype":"venue"
},
  "geometry": {"coordinates":[-87.008517,40.374121],"type":"Point"}
}