{
  "type": "Feature",
  "properties": {
    "addr:full":"307 W Main St Madison IN 47250",
    "addr:housenumber":"307",
    "addr:postcode":"47250",
    "addr:street":"W Main St",
    "iso:country":"US",
    "sg:address":"307 W Main St",
    "sg:city":"Madison",
    "sg:classifiers":[
        {
            "category":"Restaurant",
            "type":"Food & Drink"
        }
    ],
    "sg:phone":"+1 812 273 1117",
    "sg:postcode":"47250",
    "sg:province":"IN",
    "wof:name":"Hard Body Cafe",
    "wof:placetype":"venue"
},
  "geometry": {"coordinates":[-85.383166,38.736762],"type":"Point"}
}