{
  "type": "Feature",
  "properties": {
    "iso:country":"US",
    "sg:address":"19 N Pennsylvania St",
    "sg:city":"Indianapolis",
    "sg:classifiers":[
        {
            "category":"Real Estate",
            "subcategory":"Real Estate Services",
            "type":"Services"
        },
        {
            "category":"Real Estate",
            "subcategory":"Real Estate Agent",
            "type":"Services"
        }
    ],
    "sg:phone":"+1 317 506 6971",
    "sg:postcode":"46204",
    "sg:province":"IN",
    "sg:tags":[
        "buyer",
        "broker"
    ],
    "wof:name":"Leonard Realty",
    "wof:placetype":"venue"
},
  "geometry": {"coordinates":[-86.15627000000001,39.767584],"type":"Point"}
}