{
  "type": "Feature",
  "properties": {
    "iso:country":"US",
    "sg:address":"14341 S 980 W",
    "sg:city":"Goodland",
    "sg:phone":"+1 219 297 4588",
    "sg:postcode":"47948",
    "sg:province":"IN",
    "sg:tags":[
        "farm",
        "corn",
        "soybean"
    ],
    "wof:name":"Dudley Spence",
    "wof:placetype":"venue"
},
  "geometry": {"coordinates":[-87.230896,40.841782],"type":"Point"}
}