{
  "type": "Feature",
  "properties": {
    "iso:country":"US",
    "sg:address":"311 E Tillman Rd",
    "sg:city":"Fort Wayne",
    "sg:classifiers":[
        {
            "category":"Personal",
            "subcategory":"Beauty Salon",
            "type":"Services"
        }
    ],
    "sg:phone":"+1 260 447 0773",
    "sg:postcode":"46816",
    "sg:province":"IN",
    "sg:tags":[
        "shop"
    ],
    "wof:name":"Mak n Waves",
    "wof:placetype":"venue"
},
  "geometry": {"coordinates":[-85.13277100000001,41.017033],"type":"Point"}
}