{
  "type": "Feature",
  "properties": {
    "iso:country":"US",
    "sg:address":"10850 Towne Rd",
    "sg:city":"Carmel",
    "sg:classifiers":[
        {
            "category":"Education",
            "subcategory":"School",
            "type":"Public Place"
        }
    ],
    "sg:phone":"+1 317 733 2645",
    "sg:postcode":"46032",
    "sg:province":"IN",
    "sg:tags":[
        "high",
        "middle",
        "elementary"
    ],
    "wof:name":"Public Schools",
    "wof:placetype":"venue"
},
  "geometry": {"coordinates":[-86.20331899999999,39.94549],"type":"Point"}
}