{
  "type": "Feature",
  "properties": {
    "addr:full":"3204 Olympia Dr Lafayette IN 47909",
    "addr:housenumber":"3204",
    "addr:postcode":"47909",
    "addr:street":"Olympia Dr",
    "iso:country":"US",
    "sg:address":"3204 Olympia Dr",
    "sg:city":"Lafayette",
    "sg:classifiers":[
        {
            "category":"Home & Garden",
            "subcategory":"Building Materials",
            "type":"Retail Goods"
        }
    ],
    "sg:phone":"+1 765 474 8833",
    "sg:postcode":"47909",
    "sg:province":"IN",
    "sg:tags":[
        "paint"
    ],
    "wof:name":"PPG Porter Paints",
    "wof:placetype":"venue"
},
  "geometry": {"coordinates":[-86.861532,40.376894],"type":"Point"}
}