{
  "type": "Feature",
  "properties": {
    "iso:country":"US",
    "sg:address":"718 US Hwy 31 N",
    "sg:city":"Greenwood",
    "sg:classifiers":[
        {
            "category":"Restaurant",
            "type":"Food & Drink"
        }
    ],
    "sg:phone":"+1 317 882 1913",
    "sg:postcode":"46142",
    "sg:province":"IN",
    "wof:name":"Captain D's Seafood",
    "wof:placetype":"venue"
},
  "geometry": {"coordinates":[-86.118936,39.624494],"type":"Point"}
}