{
  "type": "Feature",
  "properties": {
    "iso:country":"US",
    "sg:address":"5834 S Rome Rd",
    "sg:city":"Rome",
    "sg:classifiers":[
        {
            "category":"Building & Trades",
            "subcategory":"Landscaping Services",
            "type":"Services"
        }
    ],
    "sg:phone":"+1 812 836 2753",
    "sg:postcode":"47574",
    "sg:province":"IN",
    "sg:tags":[
        "tree"
    ],
    "wof:name":"Broomie's Tree Svc",
    "wof:placetype":"venue"
},
  "geometry": {"coordinates":[-86.523368,37.923728],"type":"Point"}
}