{
  "type": "Feature",
  "properties": {
    "iso:country":"US",
    "sg:address":"1742 E McKinley Ave",
    "sg:city":"Mishawaka",
    "sg:classifiers":[
        {
            "category":"Autos & Motor Vehicles",
            "subcategory":"Auto Supplies",
            "type":"Retail Goods"
        }
    ],
    "sg:phone":"+1 574 256 0540",
    "sg:postcode":"46545",
    "sg:province":"IN",
    "sg:tags":[
        "battery"
    ],
    "wof:name":"Valley Auto Electric",
    "wof:placetype":"venue"
},
  "geometry": {"coordinates":[-86.156971,41.680367],"type":"Point"}
}