{
  "type": "Feature",
  "properties": {
    "iso:country":"US",
    "sg:address":"111 W High St",
    "sg:city":"Rockville",
    "sg:classifiers":[
        {
            "category":"Health Services",
            "subcategory":"Doctor",
            "type":"Services"
        }
    ],
    "sg:phone":"+1 765 569 2057",
    "sg:postcode":"47872",
    "sg:province":"IN",
    "sg:tags":[
        "physician",
        "surgeon"
    ],
    "wof:name":"Rockville Town Square Clinic",
    "wof:placetype":"venue"
},
  "geometry": {"coordinates":[-87.227818,39.76129],"type":"Point"}
}