{
  "type": "Feature",
  "properties": {
    "iso:country":"US",
    "sg:address":"428 E 4th St",
    "sg:city":"Mt Vernon",
    "sg:classifiers":[
        {
            "category":"Utilities",
            "subcategory":"Mobile Phone",
            "type":"Services"
        }
    ],
    "sg:phone":"+1 812 838 5670",
    "sg:postcode":"47620",
    "sg:province":"IN",
    "sg:tags":[
        "telephone",
        "cellular"
    ],
    "wof:name":"Wireless World Inc",
    "wof:placetype":"venue"
},
  "geometry": {"coordinates":[-87.891249,37.933232],"type":"Point"}
}