{
  "type": "Feature",
  "properties": {
    "iso:country":"US",
    "sg:address":"932 Locust St",
    "sg:city":"Terre Haute",
    "sg:classifiers":[
        {
            "category":"Restaurant",
            "type":"Food & Drink"
        }
    ],
    "sg:phone":"+1 812 238 1148",
    "sg:postcode":"47807",
    "sg:province":"IN",
    "wof:name":"Bush",
    "wof:placetype":"venue"
},
  "geometry": {"coordinates":[-87.403845,39.477584],"type":"Point"}
}