{
  "type": "Feature",
  "properties": {
    "addr:full":"6700 E Virginia St Evansville IN 47715",
    "addr:housenumber":"6700",
    "addr:postcode":"47715",
    "addr:street":"E Virginia St",
    "iso:country":"US",
    "sg:address":"6700 E Virginia St",
    "sg:city":"Evansville",
    "sg:classifiers":[
        {
            "category":"Shopping",
            "subcategory":"Department Store",
            "type":"Retail Goods"
        }
    ],
    "sg:phone":"+1 812 473 2518",
    "sg:postcode":"47715",
    "sg:province":"IN",
    "sg:website":"www.samsclub.com",
    "wof:name":"Sam's Club",
    "wof:placetype":"venue"
},
  "geometry": {"coordinates":[-87.485325,37.98128],"type":"Point"}
}