{
  "type": "Feature",
  "properties": {
    "iso:country":"US",
    "sg:address":"711 E Thompson Rd",
    "sg:city":"Indianapolis",
    "sg:classifiers":[
        {
            "category":"Retail",
            "subcategory":"Laundry & Dry Cleaning",
            "type":"Services"
        }
    ],
    "sg:phone":"+1 317 784 9453",
    "sg:postcode":"46227",
    "sg:province":"IN",
    "sg:tags":[
        "cleaners"
    ],
    "wof:name":"Bettis Cleaners",
    "wof:placetype":"venue"
},
  "geometry": {"coordinates":[-86.144086,39.693325],"type":"Point"}
}