{
  "type": "Feature",
  "properties": {
    "addr:full":"45 Little Eagle Dr Warsaw IN 46580",
    "addr:housenumber":"45",
    "addr:postcode":"46580",
    "addr:street":"Little Eagle Dr",
    "iso:country":"US",
    "sg:address":"45 Little Eagle Dr",
    "sg:city":"Warsaw",
    "sg:classifiers":[
        {
            "category":"Social Services",
            "subcategory":"Child Care",
            "type":"Services"
        }
    ],
    "sg:phone":"+1 574 267 7082",
    "sg:postcode":"46580",
    "sg:province":"IN",
    "sg:tags":[
        "day"
    ],
    "wof:name":"Gail Olds",
    "wof:placetype":"venue"
},
  "geometry": {"coordinates":[-85.842675,41.230381],"type":"Point"}
}