{
  "type": "Feature",
  "properties": {
    "iso:country":"US",
    "sg:address":"9611 Allisonville Rd",
    "sg:city":"Indianapolis",
    "sg:classifiers":[
        {
            "category":"Autos & Motor Vehicles",
            "subcategory":"Fuel & Gas Station",
            "type":"Retail Goods"
        }
    ],
    "sg:phone":"+1 317 842 4046",
    "sg:postcode":"46250",
    "sg:province":"IN",
    "sg:tags":[
        "oil"
    ],
    "wof:name":"Woodbridge Shell",
    "wof:placetype":"venue"
},
  "geometry": {"coordinates":[-86.064207,39.928311],"type":"Point"}
}