{
  "type": "Feature",
  "properties": {
    "addr:full":"105 E Rochester St Akron IN 46910",
    "addr:housenumber":"105",
    "addr:postcode":"46910",
    "addr:street":"E Rochester St",
    "iso:country":"US",
    "sg:address":"105 E Rochester St",
    "sg:city":"Akron",
    "sg:classifiers":[
        {
            "category":"Shopping",
            "subcategory":"Computers & Home Electronics",
            "type":"Retail Goods"
        }
    ],
    "sg:phone":"+1 574 893 1195",
    "sg:postcode":"46910",
    "sg:province":"IN",
    "sg:tags":[
        "equipment",
        "dealer"
    ],
    "wof:name":"Country Computers",
    "wof:placetype":"venue"
},
  "geometry": {"coordinates":[-86.028235,41.038757],"type":"Point"}
}