{
  "type": "Feature",
  "properties": {
    "iso:country":"US",
    "sg:address":"107 W Vine St",
    "sg:city":"Sunman",
    "sg:classifiers":[
        {
            "category":"Retail",
            "subcategory":"Funeral Services",
            "type":"Services"
        }
    ],
    "sg:phone":"+1 812 623 2200",
    "sg:postcode":"47041",
    "sg:province":"IN",
    "sg:tags":[
        "director"
    ],
    "wof:name":"Cook Funeral Home",
    "wof:placetype":"venue"
},
  "geometry": {"coordinates":[-85.095101,39.235933],"type":"Point"}
}