{
  "type": "Feature",
  "properties": {
    "addr:full":"6108 Highgate Pl Fort Wayne IN 46815",
    "addr:housenumber":"6108",
    "addr:postcode":"46815",
    "addr:street":"Highgate Pl",
    "iso:country":"US",
    "sg:address":"6108 Highgate Pl",
    "sg:city":"Fort Wayne",
    "sg:classifiers":[
        {
            "category":"Wholesale",
            "subcategory":"Chemicals & Plastics",
            "type":"Manufacturing & Wholesale Goods"
        }
    ],
    "sg:phone":"+1 260 493 9731",
    "sg:postcode":"46815",
    "sg:province":"IN",
    "sg:tags":[
        "adhesive",
        "glue"
    ],
    "wof:name":"Lord Corp",
    "wof:placetype":"venue"
},
  "geometry": {"coordinates":[-85.063295,41.094639],"type":"Point"}
}