{
  "type": "Feature",
  "properties": {
    "iso:country":"US",
    "sg:address":"10799 Alliance Dr",
    "sg:city":"Camby",
    "sg:classifiers":[
        {
            "category":"Health Services",
            "subcategory":"Health Practitioner",
            "type":"Services"
        }
    ],
    "sg:phone":"+1 317 856 7414",
    "sg:postcode":"46113",
    "sg:province":"IN",
    "sg:tags":[
        "therapist",
        "physical"
    ],
    "wof:name":"Therapeak Inc",
    "wof:placetype":"venue"
},
  "geometry": {"coordinates":[-86.32945599999999,39.637077],"type":"Point"}
}