{
  "type": "Feature",
  "properties": {
    "addr:full":"332 N Capitol Ave Indianapolis IN 46204",
    "addr:housenumber":"332",
    "addr:postcode":"46204",
    "addr:street":"N Capitol Ave",
    "iso:country":"US",
    "sg:address":"332 N Capitol Ave",
    "sg:city":"Indianapolis",
    "sg:classifiers":[
        {
            "category":"Retail",
            "subcategory":"Repair Shop",
            "type":"Services"
        }
    ],
    "sg:phone":"+1 317 635 6274",
    "sg:postcode":"46204",
    "sg:province":"IN",
    "sg:tags":[
        "instrument",
        "musical"
    ],
    "sg:website":"www.musiciansrepair.com",
    "wof:name":"Musicians Repair & Sales",
    "wof:placetype":"venue"
},
  "geometry": {"coordinates":[-86.16159,39.772344],"type":"Point"}
}