{
  "type": "Feature",
  "properties": {
    "addr:full":"4850 N Crest Rd Marion IN 46952",
    "addr:housenumber":"4850",
    "addr:postcode":"46952",
    "addr:street":"N Crest Rd",
    "iso:country":"US",
    "sg:address":"4850 N Crest Rd",
    "sg:city":"Marion",
    "sg:classifiers":[
        {
            "category":"Organizations",
            "subcategory":"Professional Association",
            "type":"Services"
        }
    ],
    "sg:phone":"+1 765 384 7617",
    "sg:postcode":"46952",
    "sg:province":"IN",
    "wof:name":"Izaak Walton League-Grant Co",
    "wof:placetype":"venue"
},
  "geometry": {"coordinates":[-85.74642900000001,40.624456],"type":"Point"}
}