{
  "type": "Feature",
  "properties": {
    "iso:country":"US",
    "sg:address":"8921 W Co Rd 1075 S",
    "sg:city":"Reelsville",
    "sg:classifiers":[
        {
            "category":"Organizations",
            "subcategory":"Religious Organization",
            "type":"Services"
        }
    ],
    "sg:phone":"+1 812 986 3001",
    "sg:postcode":"46171",
    "sg:province":"IN",
    "sg:tags":[
        "church"
    ],
    "wof:name":"Croy's Creek Christian Church",
    "wof:placetype":"venue"
},
  "geometry": {"coordinates":[-87.012586,39.506524],"type":"Point"}
}