{
  "type": "Feature",
  "properties": {
    "iso:country":"US",
    "sg:address":"5245 Cheyenne Moon",
    "sg:city":"Carmel",
    "sg:classifiers":[
        {
            "category":"Wholesale",
            "subcategory":"Chemicals & Plastics",
            "type":"Manufacturing & Wholesale Goods"
        }
    ],
    "sg:phone":"+1 317 846 7236",
    "sg:postcode":"46033",
    "sg:province":"IN",
    "wof:name":"Si Concrete Systems",
    "wof:placetype":"venue"
},
  "geometry": {"coordinates":[-86.069845,39.984471],"type":"Point"}
}