{
  "type": "Feature",
  "properties": {
    "addr:full":"10248 Leeward Blvd Indianapolis IN 46256",
    "addr:housenumber":"10248",
    "addr:postcode":"46256",
    "addr:street":"Leeward Blvd",
    "iso:country":"US",
    "sg:address":"10248 Leeward Blvd",
    "sg:city":"Indianapolis",
    "sg:classifiers":[
        {
            "category":"Real Estate",
            "subcategory":"Real Estate Services",
            "type":"Services"
        }
    ],
    "sg:phone":"+1 317 288 0084",
    "sg:postcode":"46256",
    "sg:province":"IN",
    "sg:tags":[
        "home",
        "staging"
    ],
    "wof:name":"Staged Spaces",
    "wof:placetype":"venue"
},
  "geometry": {"coordinates":[-85.98738299999999,39.920513],"type":"Point"}
}