{
  "type": "Feature",
  "properties": {
    "addr:full":"4716 N 900 E New Carlisle IN 46552",
    "addr:housenumber":"4716",
    "addr:postcode":"46552",
    "addr:street":"N 900 E",
    "iso:country":"US",
    "sg:address":"4716 N 900 E",
    "sg:city":"New Carlisle",
    "sg:classifiers":[
        {
            "category":"Building & Trades",
            "subcategory":"Construction",
            "type":"Services"
        }
    ],
    "sg:phone":"+1 574 654 8035",
    "sg:postcode":"46552",
    "sg:province":"IN",
    "sg:tags":[
        "house"
    ],
    "wof:name":"Jim Boal Aluminum Sales",
    "wof:placetype":"venue"
},
  "geometry": {"coordinates":[-86.525987,41.675533],"type":"Point"}
}