{
  "type": "Feature",
  "properties": {
    "addr:full":"2028 Stafford Rd Plainfield IN 46168",
    "addr:housenumber":"2028",
    "addr:postcode":"46168",
    "addr:street":"Stafford Rd",
    "iso:country":"US",
    "sg:address":"2028 Stafford Rd",
    "sg:city":"Plainfield",
    "sg:classifiers":[
        {
            "category":"Shopping",
            "type":"Retail Goods"
        }
    ],
    "sg:phone":"+1 317 837 8848",
    "sg:postcode":"46168",
    "sg:province":"IN",
    "sg:tags":[
        "hearing",
        "equipment",
        "supply",
        "impaired"
    ],
    "wof:name":"Better Hearing Inc",
    "wof:placetype":"venue"
},
  "geometry": {"coordinates":[-86.37381000000001,39.697218],"type":"Point"}
}