{
  "type": "Feature",
  "properties": {
    "iso:country":"US",
    "sg:address":"12424 N Lena Rd",
    "sg:city":"Brazil",
    "sg:classifiers":[
        {
            "category":"Recreation",
            "type":"Entertainment"
        }
    ],
    "sg:phone":"+1 812 443 2903",
    "sg:postcode":"47834",
    "sg:province":"IN",
    "wof:name":"Dreams Come True Stables",
    "wof:placetype":"venue"
},
  "geometry": {"coordinates":[-87.022712,39.567053],"type":"Point"}
}