{
  "type": "Feature",
  "properties": {
    "iso:country":"US",
    "sg:address":"1035 E Main St",
    "sg:city":"Jasonville",
    "sg:classifiers":[
        {
            "category":"Autos & Motor Vehicles",
            "subcategory":"Fuel & Gas Station",
            "type":"Retail Goods"
        }
    ],
    "sg:phone":"+1 812 665 2944",
    "sg:postcode":"47438",
    "sg:province":"IN",
    "sg:tags":[
        "oil"
    ],
    "wof:name":"Hoosier Petes Union 76",
    "wof:placetype":"venue"
},
  "geometry": {"coordinates":[-87.185953,39.162743],"type":"Point"}
}