{
  "type": "Feature",
  "properties": {
    "addr:full":"798 N 500 E Rochester IN 46975",
    "addr:housenumber":"798",
    "addr:postcode":"46975",
    "addr:street":"N 500 E",
    "iso:country":"US",
    "sg:address":"798 N 500 E",
    "sg:city":"Rochester",
    "sg:classifiers":[
        {
            "category":"Social Services",
            "subcategory":"Child Care",
            "type":"Services"
        }
    ],
    "sg:phone":"+1 574 223 2772",
    "sg:postcode":"46975",
    "sg:province":"IN",
    "sg:tags":[
        "day"
    ],
    "wof:name":"Marilyn Peter",
    "wof:placetype":"venue"
},
  "geometry": {"coordinates":[-86.14936299999999,41.076299],"type":"Point"}
}