{
  "type": "Feature",
  "properties": {
    "iso:country":"US",
    "sg:address":"5515 Industrial Rd",
    "sg:city":"Fort Wayne",
    "sg:classifiers":[
        {
            "category":"Retail",
            "subcategory":"Auto Repair",
            "type":"Services"
        }
    ],
    "sg:phone":"+1 260 482 7775",
    "sg:postcode":"46825",
    "sg:province":"IN",
    "sg:tags":[
        "body",
        "automobile",
        "painting"
    ],
    "wof:name":"Dave Vorderman Auto Body",
    "wof:placetype":"venue"
},
  "geometry": {"coordinates":[-85.148103,41.128928],"type":"Point"}
}