{
  "type": "Feature",
  "properties": {
    "iso:country":"US",
    "sg:address":"301 Gospel Rd",
    "sg:city":"Charlestown",
    "sg:classifiers":[
        {
            "category":"Organizations",
            "subcategory":"Religious Organization",
            "type":"Services"
        }
    ],
    "sg:phone":"+1 812 256 3053",
    "sg:postcode":"47111",
    "sg:province":"IN",
    "sg:tags":[
        "church"
    ],
    "wof:name":"Pleasant Ridge Baptist Church",
    "wof:placetype":"venue"
},
  "geometry": {"coordinates":[-85.674583,38.450407],"type":"Point"}
}