{
  "type": "Feature",
  "properties": {
    "iso:country":"US",
    "sg:address":"6721 Nebraska Ave",
    "sg:city":"Hammond",
    "sg:classifiers":[
        {
            "category":"Wholesale",
            "subcategory":"Machinery & Supplies",
            "type":"Manufacturing & Wholesale Goods"
        }
    ],
    "sg:phone":"+1 219 989 0185",
    "sg:postcode":"46323",
    "sg:province":"IN",
    "sg:tags":[
        "janitor"
    ],
    "wof:name":"Clark Maintenance Products",
    "wof:placetype":"venue"
},
  "geometry": {"coordinates":[-87.440912,41.590368],"type":"Point"}
}