{
  "type": "Feature",
  "properties": {
    "iso:country":"US",
    "sg:address":"4555 Eagle Creek Pkwy",
    "sg:city":"Indianapolis",
    "sg:classifiers":[
        {
            "category":"Insurance",
            "subcategory":"Insurance Agent",
            "type":"Services"
        }
    ],
    "sg:phone":"+1 317 271 5650",
    "sg:postcode":"46254",
    "sg:province":"IN",
    "wof:name":"Eerie Insurance Co",
    "wof:placetype":"venue"
},
  "geometry": {"coordinates":[-86.28707199999999,39.836849],"type":"Point"}
}