{
  "type": "Feature",
  "properties": {
    "iso:country":"US",
    "sg:address":"1611 S Rogers St",
    "sg:city":"Bloomington",
    "sg:classifiers":[
        {
            "category":"Manufacturing",
            "subcategory":"Printing",
            "type":"Manufacturing & Wholesale Goods"
        }
    ],
    "sg:phone":"+1 812 334 8189",
    "sg:postcode":"47403",
    "sg:province":"IN",
    "sg:tags":[
        "commercial"
    ],
    "wof:name":"Baugh Enterprises Inc",
    "wof:placetype":"venue"
},
  "geometry": {"coordinates":[-86.538777,39.14706],"type":"Point"}
}