{
  "type": "Feature",
  "properties": {
    "addr:full":"1105 W State Rd 2 Laporte IN 46350",
    "addr:housenumber":"1105",
    "addr:postcode":"46350",
    "addr:street":"W State Rd 2",
    "iso:country":"US",
    "sg:address":"1105 W State Rd 2",
    "sg:city":"Laporte",
    "sg:classifiers":[
        {
            "category":"Home & Garden",
            "subcategory":"Household Appliances",
            "type":"Retail Goods"
        }
    ],
    "sg:phone":"+1 219 362 1702",
    "sg:postcode":"46350",
    "sg:province":"IN",
    "wof:name":"Maytag Home Appl Ctr Fackelman",
    "wof:placetype":"venue"
},
  "geometry": {"coordinates":[-86.73154700000001,41.600834],"type":"Point"}
}