{
  "type": "Feature",
  "properties": {
    "iso:country":"US",
    "sg:address":"27969 Co Rd 6",
    "sg:city":"Elkhart",
    "sg:classifiers":[
        {
            "category":"Autos & Motor Vehicles",
            "subcategory":"Fuel & Gas Station",
            "type":"Retail Goods"
        }
    ],
    "sg:phone":"+1 574 206 8824",
    "sg:postcode":"46514",
    "sg:province":"IN",
    "sg:tags":[
        "oil"
    ],
    "wof:name":"Bp Oil",
    "wof:placetype":"venue"
},
  "geometry": {"coordinates":[-86.005717,41.724337],"type":"Point"}
}