{
  "type": "Feature",
  "properties": {
    "iso:country":"US",
    "sg:address":"1357 W 86th St",
    "sg:city":"Indianapolis",
    "sg:classifiers":[
        {
            "category":"Shopping",
            "subcategory":"Crafts & Fabrics",
            "type":"Retail Goods"
        }
    ],
    "sg:phone":"+1 317 259 4699",
    "sg:postcode":"46260",
    "sg:province":"IN",
    "sg:tags":[
        "store"
    ],
    "wof:name":"Jo-Ann Fabrics and Crafts",
    "wof:placetype":"venue"
},
  "geometry": {"coordinates":[-86.183632,39.912154],"type":"Point"}
}