{
  "type": "Feature",
  "properties": {
    "iso:country":"US",
    "sg:address":"2001 E Pontiac St",
    "sg:city":"Fort Wayne",
    "sg:classifiers":[
        {
            "category":"Wholesale",
            "subcategory":"Scrap",
            "type":"Manufacturing & Wholesale Goods"
        }
    ],
    "sg:phone":"+1 260 745 3902",
    "sg:postcode":"46803",
    "sg:province":"IN",
    "sg:tags":[
        "recycling",
        "center"
    ],
    "wof:name":"Recovery Technologies",
    "wof:placetype":"venue"
},
  "geometry": {"coordinates":[-85.109177,41.061106],"type":"Point"}
}