{
  "type": "Feature",
  "properties": {
    "iso:country":"US",
    "sg:address":"3505 N Washington Blvd",
    "sg:city":"Indianapolis",
    "sg:classifiers":[
        {
            "category":"Social Services",
            "type":"Services"
        }
    ],
    "sg:phone":"+1 317 920 5900",
    "sg:postcode":"46205",
    "sg:province":"IN",
    "sg:tags":[
        "counseling"
    ],
    "sg:website":"www.reachforyouth.org",
    "wof:name":"Reach For Youth Inc",
    "wof:placetype":"venue"
},
  "geometry": {"coordinates":[-86.152,39.81918],"type":"Point"}
}