{
  "type": "Feature",
  "properties": {
    "addr:full":"258 N Park Ave Spencer IN 47460",
    "addr:housenumber":"258",
    "addr:postcode":"47460",
    "addr:street":"N Park Ave",
    "iso:country":"US",
    "sg:address":"258 N Park Ave",
    "sg:city":"Spencer",
    "sg:classifiers":[
        {
            "category":"Building & Trades",
            "subcategory":"Construction",
            "type":"Services"
        }
    ],
    "sg:phone":"+1 812 829 4950",
    "sg:postcode":"47460",
    "sg:province":"IN",
    "sg:tags":[
        "house"
    ],
    "wof:name":"Restorations Ltd",
    "wof:placetype":"venue"
},
  "geometry": {"coordinates":[-86.757746,39.288254],"type":"Point"}
}