{
  "type": "Feature",
  "properties": {
    "iso:country":"US",
    "sg:address":"3504 White Cedar Ct",
    "sg:city":"Indianapolis",
    "sg:classifiers":[
        {
            "category":"Shopping",
            "subcategory":"Discount & Variety Stores",
            "type":"Retail Goods"
        }
    ],
    "sg:phone":"+1 317 631 4131",
    "sg:postcode":"46222",
    "sg:province":"IN",
    "wof:name":"Johnson's Variety Store",
    "wof:placetype":"venue"
},
  "geometry": {"coordinates":[-86.220033,39.795563],"type":"Point"}
}