{
  "type": "Feature",
  "properties": {
    "iso:country":"US",
    "sg:address":"302 S Pearl St",
    "sg:city":"Knox",
    "sg:classifiers":[
        {
            "category":"Social Services",
            "type":"Services"
        }
    ],
    "sg:phone":"+1 219 464 0840",
    "sg:postcode":"46534",
    "sg:province":"IN",
    "wof:name":"Caring Place Inc",
    "wof:placetype":"venue"
},
  "geometry": {"coordinates":[-86.62193,41.294849],"type":"Point"}
}