{
  "type": "Feature",
  "properties": {
    "iso:country":"US",
    "sg:address":"600 N Huntington St",
    "sg:city":"Syracuse",
    "sg:classifiers":[
        {
            "category":"Shopping",
            "subcategory":"Clothing, Apparel, & Fashions",
            "type":"Retail Goods"
        }
    ],
    "sg:phone":"+1 574 457 5395",
    "sg:postcode":"46567",
    "sg:province":"IN",
    "sg:tags":[
        "infant",
        "wear"
    ],
    "wof:name":"Country Mouse",
    "wof:placetype":"venue"
},
  "geometry": {"coordinates":[-85.75210800000001,41.427066],"type":"Point"}
}