{
  "type": "Feature",
  "properties": {
    "addr:full":"308 S Cavin St Ligonier IN 46767",
    "addr:housenumber":"308",
    "addr:postcode":"46767",
    "addr:street":"S Cavin St",
    "iso:country":"US",
    "sg:address":"308 S Cavin St",
    "sg:city":"Ligonier",
    "sg:classifiers":[
        {
            "category":"Health Services",
            "subcategory":"Doctor",
            "type":"Services"
        }
    ],
    "sg:phone":"+1 260 894 3130",
    "sg:postcode":"46767",
    "sg:province":"IN",
    "sg:tags":[
        "dentist"
    ],
    "wof:name":"Richard D Brown DDS",
    "wof:placetype":"venue"
},
  "geometry": {"coordinates":[-85.587631,41.463772],"type":"Point"}
}