{
  "type": "Feature",
  "properties": {
    "addr:full":"12924 N Spades Rd Sunman IN 47041",
    "addr:housenumber":"12924",
    "addr:postcode":"47041",
    "addr:street":"N Spades Rd",
    "iso:country":"US",
    "sg:address":"12924 N Spades Rd",
    "sg:city":"Sunman",
    "sg:classifiers":[
        {
            "category":"Food & Beverages",
            "subcategory":"Specialty",
            "type":"Retail Goods"
        }
    ],
    "sg:phone":"+1 812 623 4348",
    "sg:postcode":"47041",
    "sg:province":"IN",
    "sg:tags":[
        "health",
        "diet"
    ],
    "wof:name":"Herbalife Distributor",
    "wof:placetype":"venue"
},
  "geometry": {"coordinates":[-85.11850699999999,39.265647],"type":"Point"}
}