{
  "type": "Feature",
  "properties": {
    "addr:full":"141 141st St Hammond IN 46327",
    "addr:housenumber":"141",
    "addr:postcode":"46327",
    "addr:street":"141St St",
    "iso:country":"US",
    "sg:address":"141 141st St",
    "sg:city":"Hammond",
    "sg:classifiers":[
        {
            "category":"Building & Trades",
            "subcategory":"Construction",
            "type":"Services"
        }
    ],
    "sg:phone":"+1 219 937 4653",
    "sg:postcode":"46327",
    "sg:province":"IN",
    "sg:tags":[
        "general",
        "contractor"
    ],
    "wof:name":"Golf Construction",
    "wof:placetype":"venue"
},
  "geometry": {"coordinates":[-87.521868,41.639375],"type":"Point"}
}