{
  "type": "Feature",
  "properties": {
    "addr:full":"222 W Broadway St Princeton IN 47670",
    "addr:housenumber":"222",
    "addr:postcode":"47670",
    "addr:street":"W Broadway St",
    "iso:country":"US",
    "sg:address":"222 W Broadway St",
    "sg:city":"Princeton",
    "sg:classifiers":[
        {
            "category":"Professional",
            "subcategory":"Lawyer & Legal Services",
            "type":"Services"
        }
    ],
    "sg:phone":"+1 812 386 7272",
    "sg:postcode":"47670",
    "sg:province":"IN",
    "sg:tags":[
        "information",
        "attorney",
        "trust",
        "wills",
        "practice",
        "planning",
        "real estate",
        "referral"
    ],
    "wof:name":"Stone Leon C Atty. at Law",
    "wof:placetype":"venue"
},
  "geometry": {"coordinates":[-87.566216,38.355228],"type":"Point"}
}