{
  "type": "Feature",
  "properties": {
    "iso:country":"US",
    "sg:address":"8620 Green Braes North Dr",
    "sg:city":"Indianapolis",
    "sg:classifiers":[
        {
            "category":"Professional",
            "subcategory":"Art Services",
            "type":"Services"
        }
    ],
    "sg:phone":"+1 317 291 6562",
    "sg:postcode":"46234",
    "sg:province":"IN",
    "sg:tags":[
        "photographer"
    ],
    "wof:name":"Ransburg Studio",
    "wof:placetype":"venue"
},
  "geometry": {"coordinates":[-86.314728,39.84771],"type":"Point"}
}