{
  "type": "Feature",
  "properties": {
    "iso:country":"US",
    "sg:address":"1450 W Dixie Bee Rd",
    "sg:city":"Covington",
    "sg:classifiers":[
        {
            "category":"Retail",
            "subcategory":"Repair Shop",
            "type":"Services"
        }
    ],
    "sg:phone":"+1 765 793 0133",
    "sg:postcode":"47932",
    "sg:province":"IN",
    "wof:name":"Weld R B Co",
    "wof:placetype":"venue"
},
  "geometry": {"coordinates":[-87.325475,40.112953],"type":"Point"}
}