{
  "type": "Feature",
  "properties": {
    "iso:country":"US",
    "sg:address":"3404 S Meridian St",
    "sg:city":"Indianapolis",
    "sg:classifiers":[
        {
            "category":"Education",
            "subcategory":"Special Training",
            "type":"Public Place"
        }
    ],
    "sg:phone":"+1 317 889 2597",
    "sg:postcode":"46217",
    "sg:province":"IN",
    "wof:name":"Bafford Aviation Svcs Inc",
    "wof:placetype":"venue"
},
  "geometry": {"coordinates":[-86.158686,39.716362],"type":"Point"}
}