{
  "type": "Feature",
  "properties": {
    "iso:country":"US",
    "sg:address":"5536 E Fall Creek Pkwy N Dr",
    "sg:city":"Indianapolis",
    "sg:classifiers":[
        {
            "category":"Shopping",
            "subcategory":"Pharmacy",
            "type":"Retail Goods"
        }
    ],
    "sg:phone":"+1 317 542 7303",
    "sg:postcode":"46226",
    "sg:province":"IN",
    "wof:name":"CVS Pharmacy",
    "wof:placetype":"venue"
},
  "geometry": {"coordinates":[-86.080697,39.856786],"type":"Point"}
}