{
  "type": "Feature",
  "properties": {
    "iso:country":"US",
    "sg:address":"1222 W 8th St",
    "sg:city":"Mishawaka",
    "sg:classifiers":[
        {
            "category":"Retail",
            "subcategory":"Auto Repair",
            "type":"Services"
        }
    ],
    "sg:phone":"+1 574 255 2700",
    "sg:postcode":"46544",
    "sg:province":"IN",
    "sg:tags":[
        "body",
        "automobile",
        "painting"
    ],
    "wof:name":"Demske's Body Shop",
    "wof:placetype":"venue"
},
  "geometry": {"coordinates":[-86.194682,41.65543],"type":"Point"}
}