{
  "type": "Feature",
  "properties": {
    "iso:country":"US",
    "sg:address":"363 E 300 S",
    "sg:city":"Valparaiso",
    "sg:classifiers":[
        {
            "category":"Building & Trades",
            "subcategory":"Construction",
            "type":"Services"
        }
    ],
    "sg:phone":"+1 219 464 4683",
    "sg:postcode":"46383",
    "sg:province":"IN",
    "sg:tags":[
        "house",
        "general",
        "contractor"
    ],
    "wof:name":"Custom Concepts Construction",
    "wof:placetype":"venue"
},
  "geometry": {"coordinates":[-87.002731,41.390847],"type":"Point"}
}