{
  "type": "Feature",
  "properties": {
    "iso:country":"US",
    "sg:address":"56616 Elk Park Dr",
    "sg:city":"Elkhart",
    "sg:classifiers":[
        {
            "category":"Wholesale",
            "subcategory":"Machinery & Supplies",
            "type":"Manufacturing & Wholesale Goods"
        }
    ],
    "sg:phone":"+1 574 266 2966",
    "sg:postcode":"46516",
    "sg:province":"IN",
    "sg:website":"www.teamspirittrailers.com",
    "wof:name":"Team Spirit Trailers Of Elkhar",
    "wof:placetype":"venue"
},
  "geometry": {"coordinates":[-86.036064,41.670885],"type":"Point"}
}