{
  "type": "Feature",
  "properties": {
    "iso:country":"US",
    "sg:address":"1707 Madison St",
    "sg:city":"Rochester",
    "sg:classifiers":[
        {
            "category":"Real Estate",
            "subcategory":"Real Estate Operator",
            "type":"Services"
        }
    ],
    "sg:phone":"+1 574 223 6456",
    "sg:postcode":"46975",
    "sg:province":"IN",
    "sg:tags":[
        "apartment"
    ],
    "wof:name":"Village Place Apartments",
    "wof:placetype":"venue"
},
  "geometry": {"coordinates":[-86.215665,41.055598],"type":"Point"}
}