{
  "type": "Feature",
  "properties": {
    "iso:country":"US",
    "sg:address":"81 W Plank Rd",
    "sg:city":"Vincennes",
    "sg:classifiers":[
        {
            "category":"Professional",
            "subcategory":"Lawyer & Legal Services",
            "type":"Services"
        }
    ],
    "sg:phone":"+1 812 882 2965",
    "sg:postcode":"47591",
    "sg:province":"IN",
    "sg:tags":[
        "planning",
        "estate"
    ],
    "wof:name":"D & M Rusch Inc",
    "wof:placetype":"venue"
},
  "geometry": {"coordinates":[-87.540969,38.587237],"type":"Point"}
}