{
  "type": "Feature",
  "properties": {
    "iso:country":"US",
    "sg:address":"401 S Main St",
    "sg:city":"Middlebury",
    "sg:classifiers":[
        {
            "category":"Personal",
            "subcategory":"Beauty Salon",
            "type":"Services"
        }
    ],
    "sg:phone":"+1 574 825 0064",
    "sg:postcode":"46540",
    "sg:province":"IN",
    "sg:tags":[
        "shop"
    ],
    "wof:name":"Nikki's On Mane",
    "wof:placetype":"venue"
},
  "geometry": {"coordinates":[-85.705982,41.671314],"type":"Point"}
}