{
  "type": "Feature",
  "properties": {
    "iso:country":"US",
    "sg:address":"9741 Ruth Dr",
    "sg:city":"Noblesville",
    "sg:classifiers":[
        {
            "category":"Building & Trades",
            "subcategory":"Construction",
            "type":"Services"
        }
    ],
    "sg:phone":"+1 317 773 3854",
    "sg:postcode":"46060",
    "sg:province":"IN",
    "sg:tags":[
        "concrete",
        "contractor"
    ],
    "wof:name":"Absher Concrete",
    "wof:placetype":"venue"
},
  "geometry": {"coordinates":[-85.99601199999999,40.061052],"type":"Point"}
}