{
  "type": "Feature",
  "properties": {
    "iso:country":"US",
    "sg:address":"6335 N College Ave",
    "sg:city":"Indianapolis",
    "sg:classifiers":[
        {
            "category":"Food & Beverages",
            "subcategory":"Fruits & Vegetables",
            "type":"Retail Goods"
        }
    ],
    "sg:phone":"+1 317 257 7663",
    "sg:postcode":"46220",
    "sg:province":"IN",
    "sg:tags":[
        "produce"
    ],
    "wof:name":"Johnny's Market I",
    "wof:placetype":"venue"
},
  "geometry": {"coordinates":[-86.14607100000001,39.869865],"type":"Point"}
}