{
  "type": "Feature",
  "properties": {
    "iso:country":"US",
    "sg:address":"546 Indian Boundary Rd",
    "sg:city":"Chesterton",
    "sg:classifiers":[
        {
            "category":"Shopping",
            "subcategory":"Books",
            "type":"Retail Goods"
        }
    ],
    "sg:phone":"+1 219 926 6311",
    "sg:postcode":"46304",
    "sg:province":"IN",
    "sg:tags":[
        "used",
        "merchandise"
    ],
    "wof:name":"Jennys Book Exchange Inc",
    "wof:placetype":"venue"
},
  "geometry": {"coordinates":[-87.04756,41.616743],"type":"Point"}
}