{
  "type": "Feature",
  "properties": {
    "iso:country":"US",
    "sg:address":"267 Kenwood St",
    "sg:city":"Hammond",
    "sg:classifiers":[
        {
            "category":"Communications",
            "type":"Services"
        }
    ],
    "sg:phone":"+1 219 853 9570",
    "sg:postcode":"46324",
    "sg:province":"IN",
    "wof:name":"Systems Two Communications",
    "wof:placetype":"venue"
},
  "geometry": {"coordinates":[-87.518434,41.599283],"type":"Point"}
}