{
  "type": "Feature",
  "properties": {
    "iso:country":"US",
    "sg:address":"429 Merino Ct",
    "sg:city":"Seymour",
    "sg:classifiers":[
        {
            "category":"Professional",
            "type":"Services"
        }
    ],
    "sg:phone":"+1 812 523 1836",
    "sg:postcode":"47274",
    "sg:province":"IN",
    "wof:name":"Seasons Essence",
    "wof:placetype":"venue"
},
  "geometry": {"coordinates":[-85.824151,38.965211],"type":"Point"}
}