{
  "type": "Feature",
  "properties": {
    "iso:country":"US",
    "sg:address":"653 S Co Rd 150 W",
    "sg:city":"Greensburg",
    "sg:classifiers":[
        {
            "category":"Building & Trades",
            "subcategory":"Landscaping Services",
            "type":"Services"
        }
    ],
    "sg:phone":"+1 812 662 6519",
    "sg:postcode":"47240",
    "sg:province":"IN",
    "sg:tags":[
        "tree"
    ],
    "wof:name":"Nelson's Tree Svc",
    "wof:placetype":"venue"
},
  "geometry": {"coordinates":[-85.510194,39.321168],"type":"Point"}
}