{
  "type": "Feature",
  "properties": {
    "iso:country":"US",
    "sg:address":"1250 S Jackson St",
    "sg:city":"Greencastle",
    "sg:classifiers":[
        {
            "category":"Sports & Exercise",
            "subcategory":"Bowling",
            "type":"Entertainment"
        }
    ],
    "sg:phone":"+1 765 653 8714",
    "sg:postcode":"46135",
    "sg:province":"IN",
    "sg:tags":[
        "center"
    ],
    "wof:name":"Varsity Lanes",
    "wof:placetype":"venue"
},
  "geometry": {"coordinates":[-86.872202,39.629881],"type":"Point"}
}