{
  "type": "Feature",
  "properties": {
    "iso:country":"US",
    "sg:address":"1700 Hwy 62 NW",
    "sg:city":"Corydon",
    "sg:classifiers":[
        {
            "category":"Retail",
            "subcategory":"Auto Repair",
            "type":"Services"
        }
    ],
    "sg:phone":"+1 812 738 0606",
    "sg:postcode":"47112",
    "sg:province":"IN",
    "sg:tags":[
        "wrecker"
    ],
    "wof:name":"A-1 Towing",
    "wof:placetype":"venue"
},
  "geometry": {"coordinates":[-86.15485099999999,38.221516],"type":"Point"}
}