{
  "type": "Feature",
  "properties": {
    "iso:country":"US",
    "sg:address":"2619 Weisser Park Ave",
    "sg:city":"Fort Wayne",
    "sg:classifiers":[
        {
            "category":"Restaurant",
            "type":"Food & Drink"
        }
    ],
    "sg:phone":"+1 260 456 2040",
    "sg:postcode":"46803",
    "sg:province":"IN",
    "wof:name":"Hawkins Fish",
    "wof:placetype":"venue"
},
  "geometry": {"coordinates":[-85.12694,41.063872],"type":"Point"}
}