{
  "type": "Feature",
  "properties": {
    "iso:country":"US",
    "sg:address":"8332 W 1050 S",
    "sg:city":"Fortville",
    "sg:classifiers":[
        {
            "category":"Building & Trades",
            "subcategory":"Landscaping Services",
            "type":"Services"
        }
    ],
    "sg:phone":"+1 317 485 6119",
    "sg:postcode":"46040",
    "sg:province":"IN",
    "wof:name":"Penticuff Lawn & Landscaping",
    "wof:placetype":"venue"
},
  "geometry": {"coordinates":[-85.83043600000001,39.951395],"type":"Point"}
}