{
  "type": "Feature",
  "properties": {
    "iso:country":"US",
    "sg:address":"2004 N Wayne St",
    "sg:city":"Angola",
    "sg:classifiers":[
        {
            "category":"Banks & Credit Unions",
            "subcategory":"Bank",
            "type":"Services"
        }
    ],
    "sg:phone":"+1 260 665 2151",
    "sg:postcode":"46703",
    "sg:province":"IN",
    "wof:name":"Star Financial Bank",
    "wof:placetype":"venue"
},
  "geometry": {"coordinates":[-84.999451,41.654974],"type":"Point"}
}