{
  "type": "Feature",
  "properties": {
    "addr:full":"7005 Goat Hollow Rd Martinsville IN 46151",
    "addr:housenumber":"7005",
    "addr:postcode":"46151",
    "addr:street":"Goat Hollow Rd",
    "iso:country":"US",
    "sg:address":"7005 Goat Hollow Rd",
    "sg:city":"Martinsville",
    "sg:classifiers":[
        {
            "category":"Real Estate",
            "subcategory":"Real Estate Agent",
            "type":"Services"
        }
    ],
    "sg:phone":"+1 317 831 2870",
    "sg:postcode":"46151",
    "sg:province":"IN",
    "sg:tags":[
        "inspection"
    ],
    "wof:name":"Hoosier Home Check Inc",
    "wof:placetype":"venue"
},
  "geometry": {"coordinates":[-86.408055,39.537697],"type":"Point"}
}