{
  "type": "Feature",
  "properties": {
    "iso:country":"US",
    "sg:address":"625 Gatewood Dr",
    "sg:city":"Lowell",
    "sg:classifiers":[
        {
            "category":"Social Services",
            "type":"Services"
        }
    ],
    "sg:phone":"+1 219 696 7869",
    "sg:postcode":"46356",
    "sg:province":"IN",
    "wof:name":"Roberta Thomas Ccsw",
    "wof:placetype":"venue"
},
  "geometry": {"coordinates":[-87.41172899999999,41.280563],"type":"Point"}
}