{
  "type": "Feature",
  "properties": {
    "iso:country":"US",
    "sg:address":"5810 Moeller Rd",
    "sg:city":"Fort Wayne",
    "sg:classifiers":[
        {
            "category":"Freight",
            "type":"Transportation"
        }
    ],
    "sg:phone":"+1 260 493 3821",
    "sg:postcode":"46806",
    "sg:province":"IN",
    "sg:tags":[
        "trucking"
    ],
    "wof:name":"Tower Trucking LLC",
    "wof:placetype":"venue"
},
  "geometry": {"coordinates":[-85.065964,41.054641],"type":"Point"}
}