{
  "type": "Feature",
  "properties": {
    "iso:country":"US",
    "sg:address":"500 W Main St",
    "sg:city":"Fort Wayne",
    "sg:classifiers":[
        {
            "category":"Professional",
            "subcategory":"Research",
            "type":"Services"
        }
    ],
    "sg:phone":"+1 260 969 2001",
    "sg:postcode":"46802",
    "sg:province":"IN",
    "sg:tags":[
        "foundation",
        "philanthropic"
    ],
    "wof:name":"St Joseph Community Health",
    "wof:placetype":"venue"
},
  "geometry": {"coordinates":[-85.147587,41.079105],"type":"Point"}
}