{
  "type": "Feature",
  "properties": {
    "iso:country":"US",
    "sg:address":"16301 State Rd 3 N",
    "sg:city":"Eaton",
    "sg:classifiers":[
        {
            "category":"Real Estate",
            "subcategory":"Developer",
            "type":"Services"
        }
    ],
    "sg:phone":"+1 765 396 3177",
    "sg:postcode":"47338",
    "sg:province":"IN",
    "sg:tags":[
        "cemetery"
    ],
    "wof:name":"Union Cemetery Assn",
    "wof:placetype":"venue"
},
  "geometry": {"coordinates":[-85.369557,40.338881],"type":"Point"}
}