{
  "type": "Feature",
  "properties": {
    "iso:country":"US",
    "sg:address":"116 Jefferson St",
    "sg:city":"Elkhart",
    "sg:classifiers":[
        {
            "category":"Wholesale",
            "subcategory":"Durable Goods & Equipment",
            "type":"Manufacturing & Wholesale Goods"
        }
    ],
    "sg:phone":"+1 574 293 5341",
    "sg:postcode":"46516",
    "sg:province":"IN",
    "sg:tags":[
        "fire",
        "extinguisher"
    ],
    "wof:name":"Extinguisher Sales & Svc",
    "wof:placetype":"venue"
},
  "geometry": {"coordinates":[-85.975352,41.688158],"type":"Point"}
}