{
  "type": "Feature",
  "properties": {
    "iso:country":"US",
    "sg:address":"1512 N Delaware St",
    "sg:city":"Indianapolis",
    "sg:classifiers":[
        {
            "category":"Professional",
            "subcategory":"Lawyer & Legal Services",
            "type":"Services"
        }
    ],
    "sg:phone":"+1 317 964 6000",
    "sg:postcode":"46202",
    "sg:province":"IN",
    "sg:tags":[
        "criminal",
        "attorney",
        "violence",
        "duo",
        "practice",
        "domestic",
        "sex",
        "appellate",
        "offense",
        "dwi",
        "law"
    ],
    "sg:website":"http://www.susanrayllaw.com",
    "wof:name":"Smith Rayl Law Office LLC",
    "wof:placetype":"venue"
},
  "geometry": {"coordinates":[-86.153961,39.787646],"type":"Point"}
}