{
  "type": "Feature",
  "properties": {
    "iso:country":"US",
    "sg:address":"428 S Oak St",
    "sg:city":"Bluffton",
    "sg:classifiers":[
        {
            "category":"Organizations",
            "subcategory":"Religious Organization",
            "type":"Services"
        }
    ],
    "sg:phone":"+1 260 824 2252",
    "sg:postcode":"46714",
    "sg:province":"IN",
    "sg:tags":[
        "church"
    ],
    "sg:website":"www.lifechurch.com",
    "wof:name":"Life Community Church",
    "wof:placetype":"venue"
},
  "geometry": {"coordinates":[-85.177784,40.736363],"type":"Point"}
}