{
  "type": "Feature",
  "properties": {
    "iso:country":"US",
    "sg:address":"530 Baxter Rd",
    "sg:city":"Anderson",
    "sg:classifiers":[
        {
            "category":"Government",
            "subcategory":"Office",
            "type":"Public Place"
        }
    ],
    "sg:phone":"+1 765 648 6400",
    "sg:postcode":"46011",
    "sg:province":"IN",
    "sg:tags":[
        "city",
        "program"
    ],
    "sg:website":"www.aml-p.com",
    "wof:name":"City-Anderson Transit System",
    "wof:placetype":"venue"
},
  "geometry": {"coordinates":[-85.720474,40.110513],"type":"Point"}
}