{
  "type": "Feature",
  "properties": {
    "iso:country":"US",
    "sg:address":"3700 S Reed Rd",
    "sg:city":"Kokomo",
    "sg:classifiers":[
        {
            "category":"Cinema",
            "subcategory":"Movie Rental",
            "type":"Entertainment"
        }
    ],
    "sg:phone":"+1 765 453 1100",
    "sg:postcode":"46902",
    "sg:province":"IN",
    "sg:tags":[
        "leasing",
        "video",
        "disc",
        "tape"
    ],
    "wof:name":"Movie Gallery",
    "wof:placetype":"venue"
},
  "geometry": {"coordinates":[-86.125787,40.441132],"type":"Point"}
}