{
  "type": "Feature",
  "properties": {
    "iso:country":"US",
    "sg:address":"1100 N Mitthoeffer Rd",
    "sg:city":"Cumberland",
    "sg:classifiers":[
        {
            "category":"Real Estate",
            "subcategory":"Real Estate Operator",
            "type":"Services"
        }
    ],
    "sg:phone":"+1 317 894 7170",
    "sg:postcode":"46229",
    "sg:province":"IN",
    "sg:tags":[
        "apartment"
    ],
    "wof:name":"Brookview Apartments",
    "wof:placetype":"venue"
},
  "geometry": {"coordinates":[-85.990287,39.784676],"type":"Point"}
}