{
  "type": "Feature",
  "properties": {
    "addr:full":"5321 Lanam Ridge Rd Nashville IN 47448",
    "addr:housenumber":"5321",
    "addr:postcode":"47448",
    "addr:street":"Lanam Ridge Rd",
    "iso:country":"US",
    "sg:address":"5321 Lanam Ridge Rd",
    "sg:city":"Nashville",
    "sg:classifiers":[
        {
            "category":"Retail",
            "subcategory":"Animal Services",
            "type":"Services"
        }
    ],
    "sg:phone":"+1 812 988 7700",
    "sg:postcode":"47448",
    "sg:province":"IN",
    "sg:tags":[
        "breeder",
        "horse"
    ],
    "wof:name":"Maple Heights Horse Farm",
    "wof:placetype":"venue"
},
  "geometry": {"coordinates":[-86.344154,39.233517],"type":"Point"}
}