{
  "type": "Feature",
  "properties": {
    "iso:country":"US",
    "sg:address":"101 W Jackson St",
    "sg:city":"Cicero",
    "sg:classifiers":[
        {
            "category":"Restaurant",
            "type":"Food & Drink"
        }
    ],
    "sg:phone":"+1 317 984 5720",
    "sg:postcode":"46034",
    "sg:province":"IN",
    "wof:name":"Pizza King",
    "wof:placetype":"venue"
},
  "geometry": {"coordinates":[-86.015823,40.132169],"type":"Point"}
}