{
  "type": "Feature",
  "properties": {
    "iso:country":"US",
    "sg:address":"8128 Castle Cove Rd",
    "sg:city":"Indianapolis",
    "sg:classifiers":[
        {
            "category":"Professional",
            "type":"Services"
        }
    ],
    "sg:phone":"+1 317 577 0319",
    "sg:postcode":"46256",
    "sg:province":"IN",
    "wof:name":"Frank J Campisano Co",
    "wof:placetype":"venue"
},
  "geometry": {"coordinates":[-86.025248,39.903554],"type":"Point"}
}