{
  "type": "Feature",
  "properties": {
    "iso:country":"US",
    "sg:address":"3749 W Washington St",
    "sg:city":"Indianapolis",
    "sg:classifiers":[
        {
            "category":"Food & Beverages",
            "subcategory":"Groceries & Convenience Stores",
            "type":"Retail Goods"
        }
    ],
    "sg:phone":"+1 317 243 3011",
    "sg:postcode":"46241",
    "sg:province":"IN",
    "sg:tags":[
        "grocer"
    ],
    "wof:name":"LA Raza Mexican Market",
    "wof:placetype":"venue"
},
  "geometry": {"coordinates":[-86.223288,39.761133],"type":"Point"}
}