{
  "type": "Feature",
  "properties": {
    "iso:country":"US",
    "sg:address":"6700 E 38th St",
    "sg:city":"Indianapolis",
    "sg:classifiers":[
        {
            "category":"Organizations",
            "subcategory":"Community Association",
            "type":"Services"
        }
    ],
    "sg:phone":"+1 317 545 4325",
    "sg:postcode":"46226",
    "sg:province":"IN",
    "sg:tags":[
        "club"
    ],
    "wof:name":"Club Escalade",
    "wof:placetype":"venue"
},
  "geometry": {"coordinates":[-86.049172,39.825737],"type":"Point"}
}