{
  "type": "Feature",
  "properties": {
    "iso:country":"US",
    "sg:address":"8250 Bash St",
    "sg:city":"Indianapolis",
    "sg:classifiers":[
        {
            "category":"Retail",
            "subcategory":"Veterinary Services",
            "type":"Services"
        }
    ],
    "sg:phone":"+1 317 849 4925",
    "sg:postcode":"46250",
    "sg:province":"IN",
    "sg:tags":[
        "veterinarian"
    ],
    "wof:name":"Animal Emergency Clinic",
    "wof:placetype":"venue"
},
  "geometry": {"coordinates":[-86.04821200000001,39.909611],"type":"Point"}
}