{
  "type": "Feature",
  "properties": {
    "addr:full":"6108 W 79th St Indianapolis IN 46278",
    "addr:housenumber":"6108",
    "addr:postcode":"46278",
    "addr:street":"W 79Th St",
    "iso:country":"US",
    "sg:address":"6108 W 79th St",
    "sg:city":"Indianapolis",
    "sg:classifiers":[
        {
            "category":"Professional",
            "subcategory":"Advertising",
            "type":"Services"
        }
    ],
    "sg:phone":"+1 317 228 0985",
    "sg:postcode":"46278",
    "sg:province":"IN",
    "sg:tags":[
        "distributing",
        "sample",
        "service-circular"
    ],
    "wof:name":"Quinlan Fulfillment",
    "wof:placetype":"venue"
},
  "geometry": {"coordinates":[-86.266678,39.89632],"type":"Point"}
}