{
  "type": "Feature",
  "properties": {
    "iso:country":"US",
    "sg:address":"879 W Snake Hill Rd",
    "sg:city":"Liberty",
    "sg:classifiers":[
        {
            "category":"Shopping",
            "subcategory":"Discount & Variety Stores",
            "type":"Retail Goods"
        }
    ],
    "sg:phone":"+1 765 458 7142",
    "sg:postcode":"47353",
    "sg:province":"IN",
    "sg:tags":[
        "merchandise",
        "general"
    ],
    "wof:name":"Smith's Country Fresh Prod",
    "wof:placetype":"venue"
},
  "geometry": {"coordinates":[-84.943878,39.63508],"type":"Point"}
}