{
  "type": "Feature",
  "properties": {
    "iso:country":"US",
    "sg:address":"7520 Freedom Way",
    "sg:city":"Fort Wayne",
    "sg:classifiers":[
        {
            "category":"Manufacturing",
            "subcategory":"Tools & Machinery",
            "type":"Manufacturing & Wholesale Goods"
        }
    ],
    "sg:phone":"+1 260 489 3031",
    "sg:postcode":"46818",
    "sg:province":"IN",
    "sg:tags":[
        "construction"
    ],
    "sg:website":"www.mcneiluscompanies.com",
    "wof:name":"Mc Neilus Truck & Mfg Inc",
    "wof:placetype":"venue"
},
  "geometry": {"coordinates":[-85.181181,41.149029],"type":"Point"}
}