{
  "type": "Feature",
  "properties": {
    "addr:full":"951 Level St Charlestown IN 47111",
    "addr:housenumber":"951",
    "addr:postcode":"47111",
    "addr:street":"Level St",
    "iso:country":"US",
    "sg:address":"951 Level St",
    "sg:city":"Charlestown",
    "sg:classifiers":[
        {
            "category":"Organizations",
            "subcategory":"Religious Organization",
            "type":"Services"
        }
    ],
    "sg:phone":"+1 812 256 5437",
    "sg:postcode":"47111",
    "sg:province":"IN",
    "sg:tags":[
        "church"
    ],
    "wof:name":"Charlestown Christian Church",
    "wof:placetype":"venue"
},
  "geometry": {"coordinates":[-85.664289,38.451972],"type":"Point"}
}