{
  "type": "Feature",
  "properties": {
    "iso:country":"US",
    "sg:address":"144 E Clinton St",
    "sg:city":"Logansport",
    "sg:phone":"+1 574 732 1735",
    "sg:postcode":"46947",
    "sg:province":"IN",
    "sg:tags":[
        "product",
        "petroleum"
    ],
    "wof:name":"S L Lubrication",
    "wof:placetype":"venue"
},
  "geometry": {"coordinates":[-86.372428,40.736098],"type":"Point"}
}