{
  "type": "Feature",
  "properties": {
    "iso:country":"US",
    "sg:address":"980 Arroyo Rd",
    "sg:city":"Greenwood",
    "sg:classifiers":[
        {
            "category":"Organizations",
            "subcategory":"Membership Organization",
            "type":"Services"
        }
    ],
    "sg:phone":"+1 317 889 4947",
    "sg:postcode":"46143",
    "sg:province":"IN",
    "wof:name":"Indiana Bowling Assoc Inc",
    "wof:placetype":"venue"
},
  "geometry": {"coordinates":[-86.08527,39.603478],"type":"Point"}
}