{
  "type": "Feature",
  "properties": {
    "iso:country":"US",
    "sg:address":"301 N Main St",
    "sg:city":"Huntingburg",
    "sg:classifiers":[
        {
            "category":"Retail",
            "subcategory":"Auto Repair",
            "type":"Services"
        }
    ],
    "sg:phone":"+1 812 683 5616",
    "sg:postcode":"47542",
    "sg:province":"IN",
    "sg:tags":[
        "repairing",
        "automobile"
    ],
    "wof:name":"B & S Repair",
    "wof:placetype":"venue"
},
  "geometry": {"coordinates":[-86.955478,38.295155],"type":"Point"}
}