{
  "type": "Feature",
  "properties": {
    "iso:country":"US",
    "sg:address":"489 Gardener Ave",
    "sg:city":"Martinsville",
    "sg:classifiers":[
        {
            "category":"Wholesale",
            "subcategory":"Electrical",
            "type":"Manufacturing & Wholesale Goods"
        }
    ],
    "sg:phone":"+1 765 342 7454",
    "sg:postcode":"46151",
    "sg:province":"IN",
    "sg:tags":[
        "equipment",
        "electric",
        "supply"
    ],
    "wof:name":"Peerless Electric Supply Co",
    "wof:placetype":"venue"
},
  "geometry": {"coordinates":[-86.42184,39.407172],"type":"Point"}
}