{
  "type": "Feature",
  "properties": {
    "addr:full":"378 N Line St Columbia City IN 46725",
    "addr:housenumber":"378",
    "addr:postcode":"46725",
    "addr:street":"N Line St",
    "iso:country":"US",
    "sg:address":"378 N Line St",
    "sg:city":"Columbia City",
    "sg:classifiers":[
        {
            "category":"Shopping",
            "type":"Retail Goods"
        }
    ],
    "sg:phone":"+1 260 244 6144",
    "sg:postcode":"46725",
    "sg:province":"IN",
    "sg:tags":[
        "hearing",
        "equipment",
        "supply",
        "merchandise",
        "impaired"
    ],
    "wof:name":"Miracle-Ear",
    "wof:placetype":"venue"
},
  "geometry": {"coordinates":[-85.49126800000001,41.160154],"type":"Point"}
}