{
  "type": "Feature",
  "properties": {
    "iso:country":"US",
    "sg:address":"413 Main St",
    "sg:city":"Hobart",
    "sg:classifiers":[
        {
            "category":"Personal",
            "subcategory":"Beauty Salon",
            "type":"Services"
        }
    ],
    "sg:phone":"+1 219 942 1555",
    "sg:postcode":"46342",
    "sg:province":"IN",
    "wof:name":"Lonna's Hair Design",
    "wof:placetype":"venue"
},
  "geometry": {"coordinates":[-87.253763,41.530404],"type":"Point"}
}