{
  "type": "Feature",
  "properties": {
    "iso:country":"US",
    "sg:address":"10 W Main St",
    "sg:city":"Flora",
    "sg:classifiers":[
        {
            "category":"Personal",
            "subcategory":"Beauty Salon",
            "type":"Services"
        }
    ],
    "sg:phone":"+1 574 967 4650",
    "sg:postcode":"46929",
    "sg:province":"IN",
    "wof:name":"Holly's Hair Hut",
    "wof:placetype":"venue"
},
  "geometry": {"coordinates":[-86.524748,40.548041],"type":"Point"}
}