{
  "type": "Feature",
  "properties": {
    "addr:full":"4200 S East St Indianapolis IN 46227",
    "addr:housenumber":"4200",
    "addr:postcode":"46227",
    "addr:street":"S East St",
    "iso:country":"US",
    "sg:address":"4200 S East St",
    "sg:city":"Indianapolis",
    "sg:classifiers":[
        {
            "category":"Restaurant",
            "type":"Food & Drink"
        }
    ],
    "sg:menulink":"http://www.allmenus.com/in/homecroft/104362-old-country-buffet/menu/",
    "sg:phone":"+1 317 781 0163",
    "sg:postcode":"46227",
    "sg:province":"IN",
    "sg:tags":[
        "american"
    ],
    "wof:name":"Old Country Buffet",
    "wof:placetype":"venue"
},
  "geometry": {"coordinates":[-86.148974,39.70532],"type":"Point"}
}