{
  "type": "Feature",
  "properties": {
    "iso:country":"US",
    "sg:address":"576 William St",
    "sg:city":"Huntington",
    "sg:classifiers":[
        {
            "category":"Social Services",
            "type":"Services"
        }
    ],
    "sg:phone":"+1 260 358 0748",
    "sg:postcode":"46750",
    "sg:province":"IN",
    "sg:tags":[
        "mission"
    ],
    "wof:name":"Community & Family Svc Shelter",
    "wof:placetype":"venue"
},
  "geometry": {"coordinates":[-85.49760999999999,40.876898],"type":"Point"}
}