{
  "type": "Feature",
  "properties": {
    "iso:country":"US",
    "sg:address":"3320 Main St",
    "sg:city":"Anderson",
    "sg:classifiers":[
        {
            "category":"Organizations",
            "subcategory":"Non-profit Organization",
            "type":"Services"
        }
    ],
    "sg:phone":"+1 765 646 9872",
    "sg:postcode":"46013",
    "sg:province":"IN",
    "sg:tags":[
        "medical",
        "management"
    ],
    "wof:name":"Individualized Care Management",
    "wof:placetype":"venue"
},
  "geometry": {"coordinates":[-85.677669,40.080966],"type":"Point"}
}