{
  "type": "Feature",
  "properties": {
    "iso:country":"US",
    "sg:address":"5750 Coventry Ln",
    "sg:city":"Fort Wayne",
    "sg:classifiers":[
        {
            "category":"Health Services",
            "subcategory":"Doctor",
            "type":"Services"
        }
    ],
    "sg:phone":"+1 260 436 9337",
    "sg:postcode":"46804",
    "sg:province":"IN",
    "sg:tags":[
        "physician",
        "surgeon"
    ],
    "wof:name":"Ft Wayne Physical Medicine",
    "wof:placetype":"venue"
},
  "geometry": {"coordinates":[-85.255858,41.036795],"type":"Point"}
}