{
  "type": "Feature",
  "properties": {
    "iso:country":"US",
    "sg:address":"542 W Main St",
    "sg:city":"Danville",
    "sg:classifiers":[
        {
            "category":"Personal",
            "subcategory":"Beauty Salon",
            "type":"Services"
        }
    ],
    "sg:phone":"+1 317 745 7830",
    "sg:postcode":"46122",
    "sg:province":"IN",
    "wof:name":"Lisa's Hair Studio",
    "wof:placetype":"venue"
},
  "geometry": {"coordinates":[-86.530355,39.760677],"type":"Point"}
}