{
  "type": "Feature",
  "properties": {
    "iso:country":"US",
    "sg:address":"1901 S Woodland Ave",
    "sg:city":"Michigan City",
    "sg:classifiers":[
        {
            "category":"Shopping",
            "subcategory":"Bicycles & Sporting Goods",
            "type":"Retail Goods"
        }
    ],
    "sg:phone":"+1 219 872 9930",
    "sg:postcode":"46360",
    "sg:province":"IN",
    "sg:tags":[
        "apparel",
        "bowling",
        "accessory"
    ],
    "sg:website":"www.kegleronline.com",
    "wof:name":"City Lanes Inc",
    "wof:placetype":"venue"
},
  "geometry": {"coordinates":[-86.874488,41.687312],"type":"Point"}
}