{
  "type": "Feature",
  "properties": {
    "addr:full":"5206 Indiana Ave Fort Wayne IN 46807",
    "addr:housenumber":"5206",
    "addr:postcode":"46807",
    "addr:street":"Indiana Ave",
    "iso:country":"US",
    "sg:address":"5206 Indiana Ave",
    "sg:city":"Fort Wayne",
    "sg:classifiers":[
        {
            "category":"Professional",
            "subcategory":"Business Services",
            "type":"Services"
        }
    ],
    "sg:phone":"+1 260 745 9932",
    "sg:postcode":"46807",
    "sg:province":"IN",
    "wof:name":"Hochstetler Enterprises Inc",
    "wof:placetype":"venue"
},
  "geometry": {"coordinates":[-85.149263,41.037133],"type":"Point"}
}