{
  "type": "Feature",
  "properties": {
    "addr:full":"402 S Richland Creek Dr Princeton IN 47670",
    "addr:housenumber":"402",
    "addr:postcode":"47670",
    "addr:street":"S Richland Creek Dr",
    "iso:country":"US",
    "sg:address":"402 S Richland Creek Dr",
    "sg:city":"Princeton",
    "sg:classifiers":[
        {
            "category":"Home & Garden",
            "subcategory":"Building Materials",
            "type":"Retail Goods"
        }
    ],
    "sg:phone":"+1 812 386 0508",
    "sg:postcode":"47670",
    "sg:province":"IN",
    "sg:tags":[
        "lumber"
    ],
    "wof:name":"Schafer Lumber & Supply",
    "wof:placetype":"venue"
},
  "geometry": {"coordinates":[-87.593688,38.350338],"type":"Point"}
}