{
  "type": "Feature",
  "properties": {
    "addr:full":"5 E Riverside Dr Evansville IN 47713",
    "addr:housenumber":"5",
    "addr:postcode":"47713",
    "addr:street":"E Riverside Dr",
    "iso:country":"US",
    "sg:address":"5 E Riverside Dr",
    "sg:city":"Evansville",
    "sg:classifiers":[
        {
            "category":"Building & Trades",
            "subcategory":"Plumbing",
            "type":"Services"
        }
    ],
    "sg:phone":"+1 812 423 5090",
    "sg:postcode":"47713",
    "sg:province":"IN",
    "sg:tags":[
        "sheet",
        "work",
        "metal",
        "contractor"
    ],
    "wof:name":"C K United Sheet Metal",
    "wof:placetype":"venue"
},
  "geometry": {"coordinates":[-87.56412899999999,37.955617],"type":"Point"}
}