{
  "type": "Feature",
  "properties": {
    "iso:country":"US",
    "sg:address":"217 Clifty Dr",
    "sg:city":"Madison",
    "sg:classifiers":[
        {
            "category":"Wholesale",
            "subcategory":"Machinery & Supplies",
            "type":"Manufacturing & Wholesale Goods"
        }
    ],
    "sg:phone":"+1 812 273 4222",
    "sg:postcode":"47250",
    "sg:province":"IN",
    "sg:tags":[
        "equipment",
        "welding"
    ],
    "wof:name":"Valley Industrial Supply Co",
    "wof:placetype":"venue"
},
  "geometry": {"coordinates":[-85.39008200000001,38.775102],"type":"Point"}
}