{
  "type": "Feature",
  "properties": {
    "iso:country":"US",
    "sg:address":"3550 Madison Ave",
    "sg:city":"Indianapolis",
    "sg:classifiers":[
        {
            "category":"Retail",
            "subcategory":"Auto Repair",
            "type":"Services"
        }
    ],
    "sg:phone":"+1 317 788 9354",
    "sg:postcode":"46227",
    "sg:province":"IN",
    "sg:tags":[
        "muffler",
        "exhaust",
        "system"
    ],
    "wof:name":"Kenny's Economy Muffler & Tire",
    "wof:placetype":"venue"
},
  "geometry": {"coordinates":[-86.145882,39.714393],"type":"Point"}
}