{
  "type": "Feature",
  "properties": {
    "iso:country":"US",
    "sg:address":"15371 Stoney Creek Way",
    "sg:city":"Noblesville",
    "sg:classifiers":[
        {
            "category":"Manufacturing",
            "subcategory":"Metals",
            "type":"Manufacturing & Wholesale Goods"
        }
    ],
    "sg:phone":"+1 317 776 1400",
    "sg:postcode":"46060",
    "sg:province":"IN",
    "sg:tags":[
        "hardware"
    ],
    "wof:name":"Motive Service/Supply Co",
    "wof:placetype":"venue"
},
  "geometry": {"coordinates":[-86.00778,40.010967],"type":"Point"}
}