{
  "type": "Feature",
  "properties": {
    "iso:country":"US",
    "sg:address":"28862 Co Rd 38",
    "sg:city":"Wakarusa",
    "sg:classifiers":[
        {
            "category":"Professional",
            "subcategory":"Management & Consulting",
            "type":"Services"
        }
    ],
    "sg:phone":"+1 574 862 1358",
    "sg:postcode":"46573",
    "sg:province":"IN",
    "sg:tags":[
        "consultant",
        "business"
    ],
    "wof:name":"Bush Group Inc",
    "wof:placetype":"venue"
},
  "geometry": {"coordinates":[-86.018128,41.550504],"type":"Point"}
}