{
  "type": "Feature",
  "properties": {
    "iso:country":"US",
    "sg:address":"2852 E 3rd St",
    "sg:city":"Bloomington",
    "sg:classifiers":[
        {
            "category":"Shopping",
            "subcategory":"Optician",
            "type":"Retail Goods"
        }
    ],
    "sg:phone":"+1 812 334 1872",
    "sg:postcode":"47401",
    "sg:province":"IN",
    "sg:tags":[
        "eyewear"
    ],
    "sg:website":"www.lenscrafters.com",
    "wof:name":"Lenscrafters",
    "wof:placetype":"venue"
},
  "geometry": {"coordinates":[-86.49530799999999,39.164203],"type":"Point"}
}