{
  "type": "Feature",
  "properties": {
    "iso:country":"US",
    "sg:address":"1121 Roseway Dr",
    "sg:city":"Indianapolis",
    "sg:classifiers":[
        {
            "category":"Professional",
            "subcategory":"Business Services",
            "type":"Services"
        }
    ],
    "sg:phone":"+1 317 352 1076",
    "sg:postcode":"46219",
    "sg:province":"IN",
    "wof:name":"James M Mc Ginley",
    "wof:placetype":"venue"
},
  "geometry": {"coordinates":[-86.02804399999999,39.78422],"type":"Point"}
}