{
  "type": "Feature",
  "properties": {
    "iso:country":"US",
    "sg:address":"2301 Franklin St",
    "sg:city":"Michigan City",
    "sg:classifiers":[
        {
            "category":"Retail",
            "subcategory":"Car Wash",
            "type":"Services"
        }
    ],
    "sg:phone":"+1 219 874 4409",
    "sg:postcode":"46360",
    "sg:province":"IN",
    "sg:tags":[
        "polishing",
        "washing"
    ],
    "wof:name":"Jackson Car Wash & Detail",
    "wof:placetype":"venue"
},
  "geometry": {"coordinates":[-86.894413,41.70245],"type":"Point"}
}