{
  "type": "Feature",
  "properties": {
    "addr:full":"2278 Montcalm St Indianapolis IN 46208",
    "addr:housenumber":"2278",
    "addr:postcode":"46208",
    "addr:street":"Montcalm St",
    "iso:country":"US",
    "sg:address":"2278 Montcalm St",
    "sg:city":"Indianapolis",
    "sg:classifiers":[
        {
            "category":"Retail",
            "subcategory":"Auto Repair",
            "type":"Services"
        }
    ],
    "sg:phone":"+1 317 231 9632",
    "sg:postcode":"46208",
    "sg:province":"IN",
    "sg:tags":[
        "repairing",
        "automobile"
    ],
    "wof:name":"Rob's Repairing",
    "wof:placetype":"venue"
},
  "geometry": {"coordinates":[-86.180869,39.800161],"type":"Point"}
}