{
  "type": "Feature",
  "properties": {
    "iso:country":"US",
    "sg:address":"7304 E 21st St",
    "sg:city":"Indianapolis",
    "sg:phone":"+1 317 359 1021",
    "sg:postcode":"46219",
    "sg:province":"IN",
    "sg:website":"http://redirect.searchignite.com/si/cm/tracking/DGTrackingRedirect.aspx?siclientid=2537&siredirect=http://www.lq.com/lq/properties/propertyProfile.do%3Fident%3DLQ224%26IATA%3D99020726%26WT.srch%3D1&sisearchengine=155&siproduct=LQ+Indianapolis+East",
    "wof:name":"La Quinta Inn Indianapolis - East",
    "wof:placetype":"venue"
},
  "geometry": {"coordinates":[-86.040109,39.796429],"type":"Point"}
}