{
  "type": "Feature",
  "properties": {
    "iso:country":"US",
    "sg:address":"3414 E Crystal Ave",
    "sg:city":"Terre Haute",
    "sg:classifiers":[
        {
            "category":"Wholesale",
            "subcategory":"Home Furnishings",
            "type":"Manufacturing & Wholesale Goods"
        }
    ],
    "sg:phone":"+1 812 466 1618",
    "sg:postcode":"47805",
    "sg:province":"IN",
    "wof:name":"Joan R Elliott",
    "wof:placetype":"venue"
},
  "geometry": {"coordinates":[-87.366579,39.542567],"type":"Point"}
}