{
  "type": "Feature",
  "properties": {
    "addr:full":"667 N 500 E Flora IN 46929",
    "addr:housenumber":"667",
    "addr:postcode":"46929",
    "addr:street":"N 500 E Flora",
    "iso:country":"US",
    "sg:address":"667 N 500 E",
    "sg:city":"Flora",
    "sg:classifiers":[
        {
            "category":"Personal",
            "subcategory":"Beauty Salon",
            "type":"Services"
        }
    ],
    "sg:phone":"+1 574 967 3453",
    "sg:postcode":"46929",
    "sg:province":"IN",
    "sg:tags":[
        "shop"
    ],
    "wof:name":"Pomanda Beauty Salon",
    "wof:placetype":"venue"
},
  "geometry": {"coordinates":[-86.429518,40.557771],"type":"Point"}
}