{
  "type": "Feature",
  "properties": {
    "addr:full":"1552 N State St Greenfield IN 46140",
    "addr:housenumber":"1552",
    "addr:postcode":"46140",
    "addr:street":"N State St",
    "iso:country":"US",
    "sg:address":"1552 N State St",
    "sg:city":"Greenfield",
    "sg:classifiers":[
        {
            "category":"Restaurant",
            "type":"Food & Drink"
        }
    ],
    "sg:menulink":"http://www.allmenus.com/in/greenfield/208030-taco-bell/menu/",
    "sg:phone":"+1 317 462 2728",
    "sg:postcode":"46140",
    "sg:province":"IN",
    "sg:tags":[
        "mexican"
    ],
    "wof:name":"Taco Bell",
    "wof:placetype":"venue"
},
  "geometry": {"coordinates":[-85.769857,39.809917],"type":"Point"}
}