{
  "type": "Feature",
  "properties": {
    "iso:country":"US",
    "sg:address":"8001 Shelby St",
    "sg:city":"Indianapolis",
    "sg:classifiers":[
        {
            "category":"Health Services",
            "subcategory":"Doctor",
            "type":"Services"
        }
    ],
    "sg:phone":"+1 317 888 7295",
    "sg:postcode":"46227",
    "sg:province":"IN",
    "sg:tags":[
        "dentist"
    ],
    "wof:name":"Charles D Paul & Assoc",
    "wof:placetype":"venue"
},
  "geometry": {"coordinates":[-86.13942299999999,39.64861],"type":"Point"}
}