{
  "type": "Feature",
  "properties": {
    "addr:full":"508 Jackson St Jasper IN 47546",
    "addr:housenumber":"508",
    "addr:postcode":"47546",
    "addr:street":"Jackson St",
    "iso:country":"US",
    "sg:address":"508 Jackson St",
    "sg:city":"Jasper",
    "sg:classifiers":[
        {
            "category":"Banks & Credit Unions",
            "subcategory":"Bank",
            "type":"Services"
        }
    ],
    "sg:phone":"+1 812 634 9929",
    "sg:postcode":"47546",
    "sg:province":"IN",
    "sg:tags":[
        "loan",
        "real estate"
    ],
    "wof:name":"Miramar Mortgage & Financial",
    "wof:placetype":"venue"
},
  "geometry": {"coordinates":[-86.92975800000001,38.391329],"type":"Point"}
}