{
  "type": "Feature",
  "properties": {
    "iso:country":"US",
    "sg:address":"725 Chestnut Hills Pkwy",
    "sg:city":"Fort Wayne",
    "sg:classifiers":[
        {
            "category":"Building & Trades",
            "subcategory":"Construction",
            "type":"Services"
        }
    ],
    "sg:phone":"+1 260 625 4546",
    "sg:postcode":"46814",
    "sg:province":"IN",
    "sg:tags":[
        "designer",
        "dealer",
        "pool",
        "swimming"
    ],
    "wof:name":"Chestnut Hills Bathhouse",
    "wof:placetype":"venue"
},
  "geometry": {"coordinates":[-85.29402399999999,41.076222],"type":"Point"}
}