{
  "type": "Feature",
  "properties": {
    "iso:country":"US",
    "sg:address":"2431 W Main St",
    "sg:city":"Fort Wayne",
    "sg:classifiers":[
        {
            "category":"Building & Trades",
            "subcategory":"Construction",
            "type":"Services"
        }
    ],
    "sg:phone":"+1 260 432 7543",
    "sg:postcode":"46808",
    "sg:province":"IN",
    "sg:tags":[
        "insulation",
        "heat",
        "contractor"
    ],
    "sg:website":"www.momper.com",
    "wof:name":"Momper Insulation",
    "wof:placetype":"venue"
},
  "geometry": {"coordinates":[-85.175114,41.074643],"type":"Point"}
}