{
  "type": "Feature",
  "properties": {
    "iso:country":"US",
    "sg:address":"1101 W 100 S",
    "sg:city":"Jasper",
    "sg:classifiers":[
        {
            "category":"Home & Garden",
            "subcategory":"Building Materials",
            "type":"Retail Goods"
        }
    ],
    "sg:phone":"+1 812 482 5727",
    "sg:postcode":"47546",
    "sg:province":"IN",
    "sg:tags":[
        "plywood",
        "veneer"
    ],
    "wof:name":"Indiana Laminate",
    "wof:placetype":"venue"
},
  "geometry": {"coordinates":[-86.94757199999999,38.364989],"type":"Point"}
}