{
  "type": "Feature",
  "properties": {
    "iso:country":"US",
    "sg:address":"437 N Halleck St",
    "sg:city":"Demotte",
    "sg:classifiers":[
        {
            "category":"Banks & Credit Unions",
            "subcategory":"Bank",
            "type":"Services"
        }
    ],
    "sg:phone":"+1 219 987 5812",
    "sg:postcode":"46310",
    "sg:province":"IN",
    "wof:name":"Lafayette Bank & Trust Co",
    "wof:placetype":"venue"
},
  "geometry": {"coordinates":[-87.198729,41.205396],"type":"Point"}
}