{
  "type": "Feature",
  "properties": {
    "iso:country":"US",
    "sg:address":"150 E 30th St",
    "sg:city":"Jasper",
    "sg:classifiers":[
        {
            "category":"Freight",
            "type":"Transportation"
        }
    ],
    "sg:phone":"+1 812 481 2122",
    "sg:postcode":"47546",
    "sg:province":"IN",
    "sg:tags":[
        "trucking"
    ],
    "wof:name":"Nancy Baer Trucking Inc",
    "wof:placetype":"venue"
},
  "geometry": {"coordinates":[-86.934002,38.415077],"type":"Point"}
}