{
  "type": "Feature",
  "properties": {
    "iso:country":"US",
    "sg:address":"110 Basket Factory Rd",
    "sg:city":"Butler",
    "sg:classifiers":[
        {
            "category":"Retail",
            "subcategory":"Auto Repair",
            "type":"Services"
        }
    ],
    "sg:phone":"+1 260 868 5242",
    "sg:postcode":"46721",
    "sg:province":"IN",
    "sg:tags":[
        "repairing",
        "automobile"
    ],
    "wof:name":"Tule's Service Ctr",
    "wof:placetype":"venue"
},
  "geometry": {"coordinates":[-84.886403,41.432611],"type":"Point"}
}