{
  "type": "Feature",
  "properties": {
    "iso:country":"US",
    "sg:address":"333 N Riverside Blvd",
    "sg:city":"Goshen",
    "sg:classifiers":[
        {
            "category":"Professional",
            "subcategory":"Business Services",
            "type":"Services"
        }
    ],
    "sg:phone":"+1 574 533 9014",
    "sg:postcode":"46526",
    "sg:province":"IN",
    "sg:tags":[
        "auctioneer"
    ],
    "wof:name":"Dwight Miller Auctnr & Real",
    "wof:placetype":"venue"
},
  "geometry": {"coordinates":[-85.8538,41.590459],"type":"Point"}
}