{
  "type": "Feature",
  "properties": {
    "addr:full":"1524 Flagstone Dr Fort Wayne IN 46815",
    "addr:housenumber":"1524",
    "addr:postcode":"46815",
    "addr:street":"Flagstone Dr",
    "iso:country":"US",
    "sg:address":"1524 Flagstone Dr",
    "sg:city":"Fort Wayne",
    "sg:classifiers":[
        {
            "category":"Professional",
            "subcategory":"Engineering",
            "type":"Services"
        }
    ],
    "sg:phone":"+1 260 748 4992",
    "sg:postcode":"46815",
    "sg:province":"IN",
    "sg:tags":[
        "engineer"
    ],
    "wof:name":"Brookshire PE",
    "wof:placetype":"venue"
},
  "geometry": {"coordinates":[-85.072236,41.092135],"type":"Point"}
}