{
  "type": "Feature",
  "properties": {
    "iso:country":"US",
    "sg:address":"9650 Willow View Rd",
    "sg:city":"Fishers",
    "sg:classifiers":[
        {
            "category":"Building & Trades",
            "subcategory":"Landscaping Services",
            "type":"Services"
        }
    ],
    "sg:phone":"+1 317 282 0316",
    "sg:postcode":"46038",
    "sg:province":"IN",
    "wof:name":"Shoemaker Properties",
    "wof:placetype":"venue"
},
  "geometry": {"coordinates":[-86.05135,39.929907],"type":"Point"}
}