{
  "type": "Feature",
  "properties": {
    "addr:full":"4410 Earth Dr Fort Wayne IN 46809",
    "addr:housenumber":"4410",
    "addr:postcode":"46809",
    "addr:street":"Earth Dr",
    "iso:country":"US",
    "sg:address":"4410 Earth Dr",
    "sg:city":"Fort Wayne",
    "sg:classifiers":[
        {
            "category":"Shopping",
            "subcategory":"Computers & Home Electronics",
            "type":"Retail Goods"
        }
    ],
    "sg:phone":"+1 260 747 0584",
    "sg:postcode":"46809",
    "sg:province":"IN",
    "sg:tags":[
        "radio"
    ],
    "wof:name":"Emergency Radio Svc",
    "wof:placetype":"venue"
},
  "geometry": {"coordinates":[-85.182782,41.043286],"type":"Point"}
}