{
  "type": "Feature",
  "properties": {
    "addr:full":"2510 Colfax St Gary IN 46406",
    "addr:housenumber":"2510",
    "addr:postcode":"46406",
    "addr:street":"Colfax St Gary",
    "iso:country":"US",
    "sg:address":"2510 Colfax St",
    "sg:city":"Gary",
    "sg:classifiers":[
        {
            "category":"Insurance",
            "subcategory":"Insurance Agent",
            "type":"Services"
        }
    ],
    "sg:phone":"+1 219 845 3060",
    "sg:postcode":"46406",
    "sg:province":"IN",
    "wof:name":"Keck Ridge Insurance Svc",
    "wof:placetype":"venue"
},
  "geometry": {"coordinates":[-87.413174,41.572292],"type":"Point"}
}