{
  "type": "Feature",
  "properties": {
    "iso:country":"US",
    "sg:address":"14480 Lowes Way",
    "sg:city":"Carmel",
    "sg:classifiers":[
        {
            "category":"Restaurant",
            "type":"Food & Drink"
        }
    ],
    "sg:menulink":"http://www.allmenus.com/in/carmel/10573-abuelos-mexican-food-embassy/menu/",
    "sg:phone":"+1 317 815 8175",
    "sg:postcode":"46033",
    "sg:province":"IN",
    "sg:tags":[
        "american",
        "mexican",
        "tex-mex"
    ],
    "wof:name":"Abuelo's Mexican Food Embassy",
    "wof:placetype":"venue"
},
  "geometry": {"coordinates":[-86.12260000000001,39.995454],"type":"Point"}
}