{
  "type": "Feature",
  "properties": {
    "iso:country":"US",
    "sg:address":"5018 Macy Ln",
    "sg:city":"Fort Wayne",
    "sg:classifiers":[
        {
            "category":"Real Estate",
            "subcategory":"Real Estate Agent",
            "type":"Services"
        }
    ],
    "sg:phone":"+1 260 490 9395",
    "sg:postcode":"46818",
    "sg:province":"IN",
    "wof:name":"Jeff Herr Rentals",
    "wof:placetype":"venue"
},
  "geometry": {"coordinates":[-85.207522,41.135843],"type":"Point"}
}