{
  "type": "Feature",
  "properties": {
    "addr:full":"970 Millpond Rd N Valparaiso IN 46385",
    "addr:housenumber":"970",
    "addr:postcode":"46385",
    "addr:street":"Millpond Rd N",
    "iso:country":"US",
    "sg:address":"970 Millpond Rd N",
    "sg:city":"Valparaiso",
    "sg:classifiers":[
        {
            "category":"Organizations",
            "subcategory":"Religious Organization",
            "type":"Services"
        }
    ],
    "sg:phone":"+1 219 462 0403",
    "sg:postcode":"46385",
    "sg:province":"IN",
    "wof:name":"Nw Indiana District Office",
    "wof:placetype":"venue"
},
  "geometry": {"coordinates":[-87.08379499999999,41.459939],"type":"Point"}
}