{
  "type": "Feature",
  "properties": {
    "iso:country":"US",
    "sg:address":"3216 W Grandview Rd",
    "sg:city":"Salem",
    "sg:classifiers":[
        {
            "category":"Farming",
            "subcategory":"Livestock Farm",
            "type":"Manufacturing & Wholesale Goods"
        }
    ],
    "sg:phone":"+1 812 472 3915",
    "sg:postcode":"47167",
    "sg:province":"IN",
    "sg:tags":[
        "beef",
        "corn",
        "field",
        "soybean",
        "cattle",
        "feedlot"
    ],
    "wof:name":"Paul Voyles",
    "wof:placetype":"venue"
},
  "geometry": {"coordinates":[-86.158946,38.485182],"type":"Point"}
}