{
  "type": "Feature",
  "properties": {
    "iso:country":"US",
    "sg:address":"1 Civic Sq",
    "sg:city":"Carmel",
    "sg:classifiers":[
        {
            "category":"Government",
            "subcategory":"Court House",
            "type":"Public Place"
        }
    ],
    "sg:phone":"+1 317 571 2440",
    "sg:postcode":"46032",
    "sg:province":"IN",
    "sg:tags":[
        "city"
    ],
    "wof:name":"Carmel City Court",
    "wof:placetype":"venue"
},
  "geometry": {"coordinates":[-86.128416,39.966079],"type":"Point"}
}