{
  "type": "Feature",
  "properties": {
    "addr:full":"906 N Delaware St Indianapolis IN 46202",
    "addr:housenumber":"906",
    "addr:postcode":"46202",
    "addr:street":"N Delaware St",
    "iso:country":"US",
    "sg:address":"906 N Delaware St",
    "sg:city":"Indianapolis",
    "sg:classifiers":[
        {
            "category":"Professional",
            "subcategory":"Lawyer & Legal Services",
            "type":"Services"
        }
    ],
    "sg:phone":"+1 317 636 0337",
    "sg:postcode":"46202",
    "sg:province":"IN",
    "sg:tags":[
        "attorney"
    ],
    "wof:name":"Dana E Daniels",
    "wof:placetype":"venue"
},
  "geometry": {"coordinates":[-86.15406299999999,39.779541],"type":"Point"}
}