{
  "type": "Feature",
  "properties": {
    "iso:country":"US",
    "sg:address":"360 Indian Boundary Rd",
    "sg:city":"Chesterton",
    "sg:classifiers":[
        {
            "category":"Food & Beverages",
            "subcategory":"Specialty",
            "type":"Retail Goods"
        }
    ],
    "sg:phone":"+1 219 921 0122",
    "sg:postcode":"46304",
    "sg:province":"IN",
    "wof:name":"Seattle Sutton Healthy Eating",
    "wof:placetype":"venue"
},
  "geometry": {"coordinates":[-87.04523500000001,41.616753],"type":"Point"}
}