{
  "type": "Feature",
  "properties": {
    "iso:country":"US",
    "sg:address":"13001 Cedar Lake Rd",
    "sg:city":"Crown Point",
    "sg:classifiers":[
        {
            "category":"Building & Trades",
            "subcategory":"Plumbing",
            "type":"Services"
        }
    ],
    "sg:phone":"+1 219 663 3905",
    "sg:postcode":"46307",
    "sg:province":"IN",
    "wof:name":"Naylor's Plumbing & Heating Inc",
    "wof:placetype":"venue"
},
  "geometry": {"coordinates":[-87.383449,41.383712],"type":"Point"}
}