{
  "type": "Feature",
  "properties": {
    "iso:country":"US",
    "sg:address":"826 Ewing St",
    "sg:city":"Fort Wayne",
    "sg:classifiers":[
        {
            "category":"Organizations",
            "subcategory":"Professional Association",
            "type":"Services"
        }
    ],
    "sg:phone":"+1 260 424 1435",
    "sg:postcode":"46802",
    "sg:province":"IN",
    "sg:tags":[
        "chambers",
        "commerce"
    ],
    "sg:website":"www.fwchamber.org",
    "wof:name":"Fort Wayne Chamber Of Commerce",
    "wof:placetype":"venue"
},
  "geometry": {"coordinates":[-85.144509,41.077734],"type":"Point"}
}