{
  "type": "Feature",
  "properties": {
    "iso:country":"US",
    "sg:address":"4121 W 100 N",
    "sg:city":"Angola",
    "sg:classifiers":[
        {
            "category":"Recreation",
            "subcategory":"Marina",
            "type":"Entertainment"
        }
    ],
    "sg:phone":"+1 260 665 9106",
    "sg:postcode":"46703",
    "sg:province":"IN",
    "sg:tags":[
        "repairing",
        "boat"
    ],
    "wof:name":"Angola Fiberglass Works",
    "wof:placetype":"venue"
},
  "geometry": {"coordinates":[-85.068971,41.656601],"type":"Point"}
}