{
  "type": "Feature",
  "properties": {
    "iso:country":"US",
    "sg:address":"401 Growth Pkwy",
    "sg:city":"Angola",
    "sg:classifiers":[
        {
            "category":"Manufacturing",
            "subcategory":"Chemicals & Compounds",
            "type":"Manufacturing & Wholesale Goods"
        }
    ],
    "sg:phone":"+1 260 665 8431",
    "sg:postcode":"46703",
    "sg:province":"IN",
    "sg:website":"www.fredainc.com",
    "wof:name":"Freda Inc",
    "wof:placetype":"venue"
},
  "geometry": {"coordinates":[-85.003855,41.665839],"type":"Point"}
}