{
  "type": "Feature",
  "properties": {
    "iso:country":"US",
    "sg:address":"18678 N Co Rd 225 E",
    "sg:city":"Dale",
    "sg:phone":"+1 812 937 2005",
    "sg:postcode":"47523",
    "sg:province":"IN",
    "sg:tags":[
        "farm",
        "corn",
        "soybean"
    ],
    "wof:name":"Bk Simmentals",
    "wof:placetype":"venue"
},
  "geometry": {"coordinates":[-87.012466,38.160272],"type":"Point"}
}