{
  "type": "Feature",
  "properties": {
    "addr:full":"7525 N Green River Rd Evansville IN 47725",
    "addr:housenumber":"7525",
    "addr:postcode":"47725",
    "addr:street":"N Green River Rd",
    "iso:country":"US",
    "sg:address":"7525 N Green River Rd",
    "sg:city":"Evansville",
    "sg:classifiers":[
        {
            "category":"Organizations",
            "subcategory":"Religious Organization",
            "type":"Services"
        }
    ],
    "sg:phone":"+1 812 867 7066",
    "sg:postcode":"47725",
    "sg:province":"IN",
    "sg:tags":[
        "church"
    ],
    "wof:name":"Emmanuel Baptist Church",
    "wof:placetype":"venue"
},
  "geometry": {"coordinates":[-87.491439,38.046896],"type":"Point"}
}