{
  "type": "Feature",
  "properties": {
    "iso:country":"US",
    "sg:address":"7881 Fox Run Path",
    "sg:city":"Plainfield",
    "sg:classifiers":[
        {
            "category":"Real Estate",
            "subcategory":"Real Estate Agent",
            "type":"Services"
        }
    ],
    "sg:phone":"+1 317 290 6336",
    "sg:postcode":"46168",
    "sg:province":"IN",
    "wof:name":"Liberty Realtors Inc",
    "wof:placetype":"venue"
},
  "geometry": {"coordinates":[-86.381742,39.670131],"type":"Point"}
}