{
  "type": "Feature",
  "properties": {
    "iso:country":"US",
    "sg:address":"1023 N US Hwy 27",
    "sg:city":"Decatur",
    "sg:classifiers":[
        {
            "category":"Shopping",
            "subcategory":"Department Store",
            "type":"Retail Goods"
        }
    ],
    "sg:phone":"+1 260 724 8999",
    "sg:postcode":"46733",
    "sg:province":"IN",
    "sg:tags":[
        "shop"
    ],
    "wof:name":"Dollar General",
    "wof:placetype":"venue"
},
  "geometry": {"coordinates":[-84.937262,40.761618],"type":"Point"}
}