{
  "type": "Feature",
  "properties": {
    "addr:full":"4577 Garfield St Gary IN 46408",
    "addr:housenumber":"4577",
    "addr:postcode":"46408",
    "addr:street":"Garfield St Gary",
    "iso:country":"US",
    "sg:address":"4577 Garfield St",
    "sg:city":"Gary",
    "sg:classifiers":[
        {
            "category":"Wholesale",
            "subcategory":"Electrical",
            "type":"Manufacturing & Wholesale Goods"
        }
    ],
    "sg:phone":"+1 219 985 8882",
    "sg:postcode":"46408",
    "sg:province":"IN",
    "sg:tags":[
        "alarm",
        "burglar",
        "system"
    ],
    "wof:name":"Bandit Alarm",
    "wof:placetype":"venue"
},
  "geometry": {"coordinates":[-87.357983,41.534684],"type":"Point"}
}