{
  "type": "Feature",
  "properties": {
    "addr:full":"3438 169th St Hammond IN 46323",
    "addr:housenumber":"3438",
    "addr:postcode":"46323",
    "addr:street":"169Th St",
    "iso:country":"US",
    "sg:address":"3438 169th St",
    "sg:city":"Hammond",
    "sg:classifiers":[
        {
            "category":"Social Services",
            "type":"Services"
        }
    ],
    "sg:phone":"+1 219 844 8702",
    "sg:postcode":"46323",
    "sg:province":"IN",
    "sg:tags":[
        "organization",
        "welfare"
    ],
    "wof:name":"Salvation Army",
    "wof:placetype":"venue"
},
  "geometry": {"coordinates":[-87.44572100000001,41.588134],"type":"Point"}
}