{
  "type": "Feature",
  "properties": {
    "iso:country":"US",
    "sg:address":"4221 Lincoln Way E",
    "sg:city":"Mishawaka",
    "sg:classifiers":[
        {
            "category":"Personal",
            "subcategory":"Beauty Salon",
            "type":"Services"
        },
        {
            "category":"Personal",
            "subcategory":"Barber",
            "type":"Services"
        }
    ],
    "sg:phone":"+1 574 259 4369",
    "sg:postcode":"46544",
    "sg:province":"IN",
    "sg:tags":[
        "shop"
    ],
    "wof:name":"Ron's Barber & Hair Styling",
    "wof:placetype":"venue"
},
  "geometry": {"coordinates":[-86.112342,41.663227],"type":"Point"}
}