{
  "type": "Feature",
  "properties": {
    "addr:full":"7244 Indianapolis Blvd Hammond IN 46324",
    "addr:housenumber":"7244",
    "addr:postcode":"46324",
    "addr:street":"Indianapolis Blvd",
    "iso:country":"US",
    "sg:address":"7244 Indianapolis Blvd",
    "sg:city":"Hammond",
    "sg:classifiers":[
        {
            "category":"Restaurant",
            "type":"Food & Drink"
        }
    ],
    "sg:menulink":"http://www.allmenus.com/in/north/83601-papa-johns-pizza/menu/",
    "sg:phone":"+1 219 844 7272",
    "sg:postcode":"46324",
    "sg:province":"IN",
    "sg:tags":[
        "american",
        "pizza"
    ],
    "wof:name":"Papa John's Pizza",
    "wof:placetype":"venue"
},
  "geometry": {"coordinates":[-87.481313,41.581508],"type":"Point"}
}