{
  "type": "Feature",
  "properties": {
    "addr:full":"1242 Fairfield Ave Fort Wayne IN 46802",
    "addr:housenumber":"1242",
    "addr:postcode":"46802",
    "addr:street":"Fairfield Ave",
    "iso:country":"US",
    "sg:address":"1242 Fairfield Ave",
    "sg:city":"Fort Wayne",
    "sg:classifiers":[
        {
            "category":"Retail",
            "subcategory":"Repair Shop",
            "type":"Services"
        }
    ],
    "sg:phone":"+1 260 422 2788",
    "sg:postcode":"46802",
    "sg:province":"IN",
    "sg:tags":[
        "appliance"
    ],
    "wof:name":"Home Appliance Leasing Corp",
    "wof:placetype":"venue"
},
  "geometry": {"coordinates":[-85.145298,41.074664],"type":"Point"}
}