{
  "type": "Feature",
  "properties": {
    "iso:country":"US",
    "sg:address":"4809 W Smith Valley Rd",
    "sg:city":"Greenwood",
    "sg:classifiers":[
        {
            "category":"Retail",
            "subcategory":"Auto Repair",
            "type":"Services"
        }
    ],
    "sg:phone":"+1 317 881 8819",
    "sg:postcode":"46142",
    "sg:province":"IN",
    "sg:tags":[
        "repairing",
        "automobile"
    ],
    "wof:name":"Walters Body Shop Inc",
    "wof:placetype":"venue"
},
  "geometry": {"coordinates":[-86.194884,39.605308],"type":"Point"}
}