{
  "type": "Feature",
  "properties": {
    "iso:country":"US",
    "sg:address":"1709 Flintlock Dr",
    "sg:city":"Jeffersonville",
    "sg:classifiers":[
        {
            "category":"Professional",
            "subcategory":"Business Services",
            "type":"Services"
        }
    ],
    "sg:phone":"+1 812 282 6349",
    "sg:postcode":"47130",
    "sg:province":"IN",
    "wof:name":"Bartholomai Enterprises Inc",
    "wof:placetype":"venue"
},
  "geometry": {"coordinates":[-85.698102,38.314476],"type":"Point"}
}