{
  "type": "Feature",
  "properties": {
    "iso:country":"US",
    "sg:address":"2214 Fletcher St",
    "sg:city":"Anderson",
    "sg:classifiers":[
        {
            "category":"Building & Trades",
            "subcategory":"Construction",
            "type":"Services"
        }
    ],
    "sg:phone":"+1 765 622 1235",
    "sg:postcode":"46016",
    "sg:province":"IN",
    "sg:tags":[
        "handyman"
    ],
    "wof:name":"Redd's Handyman Svc",
    "wof:placetype":"venue"
},
  "geometry": {"coordinates":[-85.675486,40.094624],"type":"Point"}
}