{
  "type": "Feature",
  "properties": {
    "iso:country":"US",
    "sg:address":"4519 S 50 W",
    "sg:city":"Anderson",
    "sg:classifiers":[
        {
            "category":"Professional",
            "subcategory":"Research",
            "type":"Services"
        }
    ],
    "sg:phone":"+1 765 354 9171",
    "sg:postcode":"46013",
    "sg:province":"IN",
    "sg:tags":[
        "environmental",
        "ecological"
    ],
    "wof:name":"Adams Environmental Corp",
    "wof:placetype":"venue"
},
  "geometry": {"coordinates":[-85.678039,40.039852],"type":"Point"}
}