{
  "type": "Feature",
  "properties": {
    "iso:country":"US",
    "sg:address":"316 E Kirkwood Ave",
    "sg:city":"Bloomington",
    "sg:classifiers":[
        {
            "category":"Shopping",
            "subcategory":"Photographic Equipment",
            "type":"Retail Goods"
        }
    ],
    "sg:phone":"+1 812 323 0888",
    "sg:postcode":"47408",
    "sg:province":"IN",
    "sg:tags":[
        "supply"
    ],
    "sg:website":"www.robertsonline.com",
    "wof:name":"Robert's Photographic Equip",
    "wof:placetype":"venue"
},
  "geometry": {"coordinates":[-86.529968,39.166473],"type":"Point"}
}