{
  "type": "Feature",
  "properties": {
    "addr:full":"4799 Co Rd 1750 N Elwood IN 46036",
    "addr:housenumber":"4799;1750 n",
    "addr:postcode":"46036",
    "addr:street":"Co Rd",
    "iso:country":"US",
    "sg:address":"4799 Co Rd 1750 N",
    "sg:city":"Elwood",
    "sg:classifiers":[
        {
            "category":"Farming",
            "subcategory":"Farm",
            "type":"Manufacturing & Wholesale Goods"
        }
    ],
    "sg:phone":"+1 765 536 2651",
    "sg:postcode":"46036",
    "sg:province":"IN",
    "sg:tags":[
        "crop",
        "general"
    ],
    "wof:name":"D & K Farms",
    "wof:placetype":"venue"
},
  "geometry": {"coordinates":[-85.757857,40.355582],"type":"Point"}
}