{
  "type": "Feature",
  "properties": {
    "iso:country":"US",
    "sg:address":"3600 S 9th St",
    "sg:city":"Lafayette",
    "sg:classifiers":[
        {
            "category":"Organizations",
            "subcategory":"Religious Organization",
            "type":"Services"
        }
    ],
    "sg:phone":"+1 765 474 4842",
    "sg:postcode":"47909",
    "sg:province":"IN",
    "sg:tags":[
        "church"
    ],
    "sg:website":"www.ecovenant.org",
    "wof:name":"Evangelical Covenant Church",
    "wof:placetype":"venue"
},
  "geometry": {"coordinates":[-86.885401,40.365919],"type":"Point"}
}