{
  "type": "Feature",
  "properties": {
    "iso:country":"US",
    "sg:address":"1997 E 37th Ave",
    "sg:city":"Hobart",
    "sg:classifiers":[
        {
            "category":"Autos & Motor Vehicles",
            "subcategory":"Auto Supplies",
            "type":"Retail Goods"
        }
    ],
    "sg:phone":"+1 219 947 2574",
    "sg:postcode":"46342",
    "sg:province":"IN",
    "wof:name":"Levin Tire Center",
    "wof:placetype":"venue"
},
  "geometry": {"coordinates":[-87.231057,41.550648],"type":"Point"}
}