{
  "type": "Feature",
  "properties": {
    "addr:full":"5223 Decatur Rd Fort Wayne IN 46806",
    "addr:housenumber":"5223",
    "addr:postcode":"46806",
    "addr:street":"Decatur Rd",
    "iso:country":"US",
    "sg:address":"5223 Decatur Rd",
    "sg:city":"Fort Wayne",
    "sg:classifiers":[
        {
            "category":"Manufacturing",
            "subcategory":"Apparel",
            "type":"Manufacturing & Wholesale Goods"
        }
    ],
    "sg:phone":"+1 260 456 9632",
    "sg:postcode":"46806",
    "sg:province":"IN",
    "sg:tags":[
        "awning",
        "canopy"
    ],
    "wof:name":"Knox's Custom Shop",
    "wof:placetype":"venue"
},
  "geometry": {"coordinates":[-85.127771,41.033611],"type":"Point"}
}