{
  "type": "Feature",
  "properties": {
    "iso:country":"US",
    "sg:address":"4347 State Rd 11",
    "sg:city":"Lanesville",
    "sg:classifiers":[
        {
            "category":"Wholesale",
            "subcategory":"Machinery & Supplies",
            "type":"Manufacturing & Wholesale Goods"
        }
    ],
    "sg:phone":"+1 812 952 3811",
    "sg:postcode":"47136",
    "sg:province":"IN",
    "sg:tags":[
        "vending"
    ],
    "wof:name":"D & M Vending",
    "wof:placetype":"venue"
},
  "geometry": {"coordinates":[-85.93442400000001,38.220945],"type":"Point"}
}