{
  "type": "Feature",
  "properties": {
    "iso:country":"US",
    "sg:address":"2130 45th St",
    "sg:city":"Highland",
    "sg:classifiers":[
        {
            "category":"Restaurant",
            "type":"Food & Drink"
        }
    ],
    "sg:phone":"+1 219 922 4534",
    "sg:postcode":"46322",
    "sg:province":"IN",
    "sg:tags":[
        "out"
    ],
    "wof:name":"Twenty-Four Carrot Cuisine",
    "wof:placetype":"venue"
},
  "geometry": {"coordinates":[-87.476531,41.53755],"type":"Point"}
}