{
  "type": "Feature",
  "properties": {
    "addr:full":"1530 N Meridian St Indianapolis IN 46202",
    "addr:housenumber":"1530",
    "addr:postcode":"46202",
    "addr:street":"N Meridian St",
    "iso:country":"US",
    "sg:address":"1530 N Meridian St",
    "sg:city":"Indianapolis",
    "sg:classifiers":[
        {
            "category":"Travel",
            "subcategory":"Hotels & Motels",
            "type":"Entertainment"
        }
    ],
    "sg:phone":"+1 317 634 6100",
    "sg:postcode":"46202",
    "sg:province":"IN",
    "sg:website":"www.choicehotels.com",
    "wof:name":"Econo Lodge",
    "wof:placetype":"venue"
},
  "geometry": {"coordinates":[-86.157403,39.78666],"type":"Point"}
}