{
  "type": "Feature",
  "properties": {
    "iso:country":"US",
    "sg:address":"211 N Perkins St",
    "sg:city":"Rushville",
    "sg:classifiers":[
        {
            "category":"Restaurant",
            "type":"Food & Drink"
        }
    ],
    "sg:menulink":"http://www.allmenus.com/in/rushville/237583-pizza-king/menu/",
    "sg:phone":"+1 765 932 2212",
    "sg:postcode":"46173",
    "sg:province":"IN",
    "sg:tags":[
        "american",
        "pizza"
    ],
    "wof:name":"Pizza King",
    "wof:placetype":"venue"
},
  "geometry": {"coordinates":[-85.443347,39.608324],"type":"Point"}
}