{
  "type": "Feature",
  "properties": {
    "iso:country":"US",
    "sg:address":"89 W Canal St",
    "sg:city":"Wabash",
    "sg:classifiers":[
        {
            "category":"Government",
            "subcategory":"Office",
            "type":"Public Place"
        }
    ],
    "sg:phone":"+1 260 563 8471",
    "sg:postcode":"46992",
    "sg:province":"IN",
    "sg:tags":[
        "state",
        "resource"
    ],
    "wof:name":"Child Protective Svc",
    "wof:placetype":"venue"
},
  "geometry": {"coordinates":[-85.82167699999999,40.795767],"type":"Point"}
}