{
  "type": "Feature",
  "properties": {
    "iso:country":"US",
    "sg:address":"3310 S Meadow Dr",
    "sg:city":"Indianapolis",
    "sg:classifiers":[
        {
            "category":"Education",
            "subcategory":"School",
            "type":"Public Place"
        }
    ],
    "sg:phone":"+1 317 357 1459",
    "sg:postcode":"46239",
    "sg:province":"IN",
    "sg:website":"www.nativityindy.org",
    "wof:name":"Nativity Catholic School",
    "wof:placetype":"venue"
},
  "geometry": {"coordinates":[-86.037799,39.71771],"type":"Point"}
}