{
  "type": "Feature",
  "properties": {
    "addr:full":"4663 State Rd 32 Chesterfield IN 46017",
    "addr:housenumber":"4663;32",
    "addr:postcode":"46017",
    "addr:street":"State Rd",
    "iso:country":"US",
    "sg:address":"4663 State Rd 32",
    "sg:city":"Chesterfield",
    "sg:classifiers":[
        {
            "category":"Retail",
            "subcategory":"Laundry & Dry Cleaning",
            "type":"Services"
        }
    ],
    "sg:phone":"+1 765 640 0342",
    "sg:postcode":"46017",
    "sg:province":"IN",
    "sg:tags":[
        "cleaners",
        "rug",
        "carpet"
    ],
    "wof:name":"Fifth Wall Chem Dry",
    "wof:placetype":"venue"
},
  "geometry": {"coordinates":[-85.58077,40.11434],"type":"Point"}
}