{
  "type": "Feature",
  "properties": {
    "addr:full":"10278 Front St Dillsboro IN 47018",
    "addr:housenumber":"10278",
    "addr:postcode":"47018",
    "addr:street":"Front St",
    "iso:country":"US",
    "sg:address":"10278 Front St",
    "sg:city":"Dillsboro",
    "sg:classifiers":[
        {
            "category":"Shopping",
            "subcategory":"Clothing, Apparel, & Fashions",
            "type":"Retail Goods"
        }
    ],
    "sg:phone":"+1 812 432 3968",
    "sg:postcode":"47018",
    "sg:province":"IN",
    "sg:tags":[
        "shop",
        "bridal"
    ],
    "wof:name":"Wedding Connection",
    "wof:placetype":"venue"
},
  "geometry": {"coordinates":[-85.060934,39.021298],"type":"Point"}
}