{
  "type": "Feature",
  "properties": {
    "iso:country":"US",
    "sg:address":"774 Baltimore Rd",
    "sg:city":"Valparaiso",
    "sg:classifiers":[
        {
            "category":"Building & Trades",
            "subcategory":"Construction",
            "type":"Services"
        }
    ],
    "sg:phone":"+1 219 759 4283",
    "sg:postcode":"46385",
    "sg:province":"IN",
    "sg:tags":[
        "hanging",
        "contractor"
    ],
    "wof:name":"Ultimate Painting Inc",
    "wof:placetype":"venue"
},
  "geometry": {"coordinates":[-87.126675,41.546491],"type":"Point"}
}