{
  "type": "Feature",
  "properties": {
    "addr:full":"431 N Pennsylvania St Indianapolis IN 46204",
    "addr:housenumber":"431",
    "addr:postcode":"46204",
    "addr:street":"N Pennsylvania St",
    "iso:country":"US",
    "sg:address":"431 N Pennsylvania St",
    "sg:city":"Indianapolis",
    "sg:classifiers":[
        {
            "category":"Banks & Credit Unions",
            "subcategory":"Financial Services",
            "type":"Services"
        }
    ],
    "sg:phone":"+1 317 917 7000",
    "sg:postcode":"46204",
    "sg:province":"IN",
    "sg:tags":[
        "management",
        "investment"
    ],
    "wof:name":"Ameriprime Funds",
    "wof:placetype":"venue"
},
  "geometry": {"coordinates":[-86.156021,39.773352],"type":"Point"}
}