{
  "type": "Feature",
  "properties": {
    "iso:country":"US",
    "sg:address":"2910 Grant Line Rd",
    "sg:city":"New Albany",
    "sg:classifiers":[
        {
            "category":"Restaurant",
            "type":"Food & Drink"
        }
    ],
    "sg:menulink":"http://www.allmenus.com/in/new-albany/120106-subway/menu/",
    "sg:phone":"+1 812 944 6523",
    "sg:postcode":"47150",
    "sg:province":"IN",
    "sg:tags":[
        "american",
        "sandwich"
    ],
    "wof:name":"Subway",
    "wof:placetype":"venue"
},
  "geometry": {"coordinates":[-85.820121,38.320066],"type":"Point"}
}