{
  "type": "Feature",
  "properties": {
    "addr:full":"4301 Grand Prix Dr Logansport IN 46947",
    "addr:housenumber":"4301",
    "addr:postcode":"46947",
    "addr:street":"Grand Prix Dr",
    "iso:country":"US",
    "sg:address":"4301 Grand Prix Dr",
    "sg:city":"Logansport",
    "sg:classifiers":[
        {
            "category":"Insurance",
            "subcategory":"Insurance Agent",
            "type":"Services"
        }
    ],
    "sg:phone":"+1 574 737 7467",
    "sg:postcode":"46947",
    "sg:province":"IN",
    "sg:website":"www.dicksimsinc.com",
    "wof:name":"Dick Sims Agency Inc",
    "wof:placetype":"venue"
},
  "geometry": {"coordinates":[-86.308048,40.754826],"type":"Point"}
}