{
  "type": "Feature",
  "properties": {
    "addr:full":"2049 Indiana Ave New Albany IN 47150",
    "addr:housenumber":"2049",
    "addr:postcode":"47150",
    "addr:street":"Indiana Ave",
    "iso:country":"US",
    "sg:address":"2049 Indiana Ave",
    "sg:city":"New Albany",
    "sg:classifiers":[
        {
            "category":"Manufacturing",
            "subcategory":"Chemicals & Compounds",
            "type":"Manufacturing & Wholesale Goods"
        }
    ],
    "sg:phone":"+1 812 948 2174",
    "sg:postcode":"47150",
    "sg:province":"IN",
    "sg:tags":[
        "fertilizer"
    ],
    "wof:name":"Spawn Mate",
    "wof:placetype":"venue"
},
  "geometry": {"coordinates":[-85.81326199999999,38.309714],"type":"Point"}
}