{
  "type": "Feature",
  "properties": {
    "iso:country":"US",
    "sg:address":"7637 Hayworth Rd",
    "sg:city":"Indianapolis",
    "sg:classifiers":[
        {
            "category":"Building & Trades",
            "subcategory":"Construction",
            "type":"Services"
        }
    ],
    "sg:phone":"+1 317 856 8105",
    "sg:postcode":"46221",
    "sg:province":"IN",
    "sg:tags":[
        "excavating",
        "contractor"
    ],
    "wof:name":"Greenwald Enterprises Inc",
    "wof:placetype":"venue"
},
  "geometry": {"coordinates":[-86.27535899999999,39.650622],"type":"Point"}
}