{
  "type": "Feature",
  "properties": {
    "addr:full":"445 University Dr Granger IN 46530",
    "addr:housenumber":"445",
    "addr:postcode":"46530",
    "addr:street":"University Dr",
    "iso:country":"US",
    "sg:address":"445 University Dr",
    "sg:city":"Granger",
    "sg:classifiers":[
        {
            "category":"Shopping",
            "subcategory":"Shoes",
            "type":"Retail Goods"
        }
    ],
    "sg:phone":"+1 574 243 0993",
    "sg:postcode":"46530",
    "sg:province":"IN",
    "wof:name":"Famous Footwear",
    "wof:placetype":"venue"
},
  "geometry": {"coordinates":[-86.187091,41.719324],"type":"Point"}
}