{
  "type": "Feature",
  "properties": {
    "iso:country":"US",
    "sg:address":"7255 W 10th St",
    "sg:city":"Indianapolis",
    "sg:classifiers":[
        {
            "category":"Professional",
            "subcategory":"Lawyer & Legal Services",
            "type":"Services"
        }
    ],
    "sg:phone":"+1 317 381 1100",
    "sg:postcode":"46214",
    "sg:province":"IN",
    "sg:tags":[
        "attorney"
    ],
    "wof:name":"Steven Lovern Law Office",
    "wof:placetype":"venue"
},
  "geometry": {"coordinates":[-86.287891,39.779169],"type":"Point"}
}