{
  "type": "Feature",
  "properties": {
    "iso:country":"US",
    "sg:address":"500 N Walnut St",
    "sg:city":"Edinburgh",
    "sg:classifiers":[
        {
            "category":"Manufacturing",
            "subcategory":"Rubber & Plastics",
            "type":"Manufacturing & Wholesale Goods"
        }
    ],
    "sg:phone":"+1 812 526 5561",
    "sg:postcode":"46124",
    "sg:province":"IN",
    "sg:website":"www.bowitt.com",
    "wof:name":"Bo-WITT Products Inc",
    "wof:placetype":"venue"
},
  "geometry": {"coordinates":[-85.966758,39.35744],"type":"Point"}
}