{
  "type": "Feature",
  "properties": {
    "addr:full":"1602 N Lynhurst Dr Indianapolis IN 46224",
    "addr:housenumber":"1602",
    "addr:postcode":"46224",
    "addr:street":"N Lynhurst Dr",
    "iso:country":"US",
    "sg:address":"1602 N Lynhurst Dr",
    "sg:city":"Indianapolis",
    "sg:classifiers":[
        {
            "category":"Shopping",
            "subcategory":"Clothing, Apparel, & Fashions",
            "type":"Retail Goods"
        }
    ],
    "sg:phone":"+1 317 247 1519",
    "sg:postcode":"46224",
    "sg:province":"IN",
    "wof:name":"ETC By Wham Bam",
    "wof:placetype":"venue"
},
  "geometry": {"coordinates":[-86.250873,39.791142],"type":"Point"}
}