{
  "type": "Feature",
  "properties": {
    "iso:country":"US",
    "sg:address":"216 Plaza Dr",
    "sg:city":"Evansville",
    "sg:classifiers":[
        {
            "category":"Banks & Credit Unions",
            "subcategory":"Investment Brokerage",
            "type":"Services"
        }
    ],
    "sg:phone":"+1 812 475 0582",
    "sg:postcode":"47715",
    "sg:province":"IN",
    "wof:name":"Performance Investment Group",
    "wof:placetype":"venue"
},
  "geometry": {"coordinates":[-87.467377,37.974105],"type":"Point"}
}