{
  "type": "Feature",
  "properties": {
    "addr:full":"4020 Weber Ln Floyds Knobs IN 47119",
    "addr:housenumber":"4020",
    "addr:postcode":"47119",
    "addr:street":"Weber Ln",
    "iso:country":"US",
    "sg:address":"4020 Weber Ln",
    "sg:city":"Floyds Knobs",
    "sg:classifiers":[
        {
            "category":"Building & Trades",
            "subcategory":"Construction",
            "type":"Services"
        }
    ],
    "sg:phone":"+1 812 923 9221",
    "sg:postcode":"47119",
    "sg:province":"IN",
    "sg:tags":[
        "builder",
        "operative"
    ],
    "wof:name":"Barry Sprigler Developmen",
    "wof:placetype":"venue"
},
  "geometry": {"coordinates":[-85.887542,38.339595],"type":"Point"}
}