{
  "type": "Feature",
  "properties": {
    "iso:country":"US",
    "sg:address":"1419 Stone Ct",
    "sg:city":"South Bend",
    "sg:classifiers":[
        {
            "category":"Banks & Credit Unions",
            "subcategory":"Bank",
            "type":"Services"
        }
    ],
    "sg:phone":"+1 574 532 1999",
    "sg:postcode":"46614",
    "sg:province":"IN",
    "sg:tags":[
        "financing"
    ],
    "wof:name":"T Michael Funding Group LLC",
    "wof:placetype":"venue"
},
  "geometry": {"coordinates":[-86.228314,41.60683],"type":"Point"}
}