{
  "type": "Feature",
  "properties": {
    "iso:country":"US",
    "sg:address":"14607 Bluffton Rd",
    "sg:city":"Yoder",
    "sg:classifiers":[
        {
            "category":"Education",
            "subcategory":"School",
            "type":"Public Place"
        }
    ],
    "sg:phone":"+1 260 622 7151",
    "sg:postcode":"46798",
    "sg:province":"IN",
    "wof:name":"St Aloysius School",
    "wof:placetype":"venue"
},
  "geometry": {"coordinates":[-85.167765,40.949243],"type":"Point"}
}