{
  "type": "Feature",
  "properties": {
    "iso:country":"US",
    "sg:address":"7837 Trotter Rd",
    "sg:city":"Camby",
    "sg:classifiers":[
        {
            "category":"Professional",
            "subcategory":"Business Services",
            "type":"Services"
        }
    ],
    "sg:phone":"+1 317 821 0416",
    "sg:postcode":"46113",
    "sg:province":"IN",
    "wof:name":"Plumb-Rite Inc",
    "wof:placetype":"venue"
},
  "geometry": {"coordinates":[-86.307423,39.652571],"type":"Point"}
}