{
  "type": "Feature",
  "properties": {
    "iso:country":"US",
    "sg:address":"1101 N Shadeland Ave",
    "sg:city":"Indianapolis",
    "sg:classifiers":[
        {
            "category":"Freight",
            "type":"Transportation"
        }
    ],
    "sg:phone":"+1 317 351 0177",
    "sg:postcode":"46219",
    "sg:province":"IN",
    "sg:tags":[
        "commercial",
        "storage"
    ],
    "wof:name":"U P & Away Storage System LLC",
    "wof:placetype":"venue"
},
  "geometry": {"coordinates":[-86.04542,39.784918],"type":"Point"}
}