{
  "type": "Feature",
  "properties": {
    "iso:country":"US",
    "sg:address":"200 Cross County Plz",
    "sg:city":"Batesville",
    "sg:classifiers":[
        {
            "category":"Travel",
            "subcategory":"Travel Agent",
            "type":"Entertainment"
        }
    ],
    "sg:phone":"+1 812 934 2222",
    "sg:postcode":"47006",
    "sg:province":"IN",
    "sg:tags":[
        "agency",
        "bureau"
    ],
    "wof:name":"Carousel Travel Agency",
    "wof:placetype":"venue"
},
  "geometry": {"coordinates":[-85.214294,39.310045],"type":"Point"}
}