{
  "type": "Feature",
  "properties": {
    "addr:full":"1038 E Commercial Ave Lowell IN 46356",
    "addr:housenumber":"1038",
    "addr:postcode":"46356",
    "addr:street":"E Commercial Ave",
    "iso:country":"US",
    "sg:address":"1038 E Commercial Ave",
    "sg:city":"Lowell",
    "sg:classifiers":[
        {
            "category":"Real Estate",
            "subcategory":"Real Estate Agent",
            "type":"Services"
        }
    ],
    "sg:phone":"+1 219 696 2001",
    "sg:postcode":"46356",
    "sg:province":"IN",
    "sg:website":"www.219ownahome.com",
    "wof:name":"Advance Realty Inc",
    "wof:placetype":"venue"
},
  "geometry": {"coordinates":[-87.411096,41.291052],"type":"Point"}
}