{
  "type": "Feature",
  "properties": {
    "addr:full":"10771 Independence Way Carmel IN 46032",
    "addr:housenumber":"10771",
    "addr:postcode":"46032",
    "addr:street":"Independence Way",
    "iso:country":"US",
    "sg:address":"10771 Independence Way",
    "sg:city":"Carmel",
    "sg:classifiers":[
        {
            "category":"Professional",
            "subcategory":"Management & Consulting",
            "type":"Services"
        }
    ],
    "sg:phone":"+1 317 733 0398",
    "sg:postcode":"46032",
    "sg:province":"IN",
    "sg:tags":[
        "business"
    ],
    "wof:name":"Bdg Business Dynamics Group",
    "wof:placetype":"venue"
},
  "geometry": {"coordinates":[-86.229174,39.942939],"type":"Point"}
}