{
  "type": "Feature",
  "properties": {
    "iso:country":"US",
    "sg:address":"12407 Leo Rd",
    "sg:city":"Fort Wayne",
    "sg:classifiers":[
        {
            "category":"Building & Trades",
            "subcategory":"Construction",
            "type":"Services"
        }
    ],
    "sg:phone":"+1 260 627 5879",
    "sg:postcode":"46845",
    "sg:province":"IN",
    "sg:tags":[
        "house"
    ],
    "wof:name":"RLB Construction",
    "wof:placetype":"venue"
},
  "geometry": {"coordinates":[-85.043391,41.198884],"type":"Point"}
}