{
  "type": "Feature",
  "properties": {
    "addr:full":"12903 W 81st Ave Dyer IN 46311",
    "addr:housenumber":"12903",
    "addr:postcode":"46311",
    "addr:street":"W 81St Ave",
    "iso:country":"US",
    "sg:address":"12903 W 81st Ave",
    "sg:city":"Dyer",
    "sg:classifiers":[
        {
            "category":"Building & Trades",
            "subcategory":"Construction",
            "type":"Services"
        }
    ],
    "sg:phone":"+1 219 365 9300",
    "sg:postcode":"46311",
    "sg:province":"IN",
    "sg:tags":[
        "contractor"
    ],
    "wof:name":"Lan Oak Aluminum & Vinyl",
    "wof:placetype":"venue"
},
  "geometry": {"coordinates":[-87.493317,41.471709],"type":"Point"}
}