{
  "type": "Feature",
  "properties": {
    "iso:country":"US",
    "sg:address":"704 York Woods Dr",
    "sg:city":"Elkhart",
    "sg:classifiers":[
        {
            "category":"Health Services",
            "subcategory":"Clinic",
            "type":"Services"
        }
    ],
    "sg:phone":"+1 574 293 8005",
    "sg:postcode":"46516",
    "sg:province":"IN",
    "wof:name":"Healthcare Consultants Intl",
    "wof:placetype":"venue"
},
  "geometry": {"coordinates":[-85.962547,41.688487],"type":"Point"}
}