{
  "type": "Feature",
  "properties": {
    "addr:full":"57236 Nagy Dr Elkhart IN 46517",
    "addr:postcode":"57236;46517",
    "addr:street":"Nagy Dr",
    "iso:country":"US",
    "sg:address":"57236 Nagy Dr",
    "sg:city":"Elkhart",
    "sg:classifiers":[
        {
            "category":"Manufacturing",
            "subcategory":"Rubber & Plastics",
            "type":"Manufacturing & Wholesale Goods"
        }
    ],
    "sg:phone":"+1 574 294 2988",
    "sg:postcode":"46517",
    "sg:province":"IN",
    "wof:name":"Torza Inc",
    "wof:placetype":"venue"
},
  "geometry": {"coordinates":[-86.016165,41.660737],"type":"Point"}
}