{
  "type": "Feature",
  "properties": {
    "iso:country":"US",
    "sg:address":"3140 Coppergate Cir",
    "sg:city":"Lafayette",
    "sg:classifiers":[
        {
            "category":"Real Estate",
            "subcategory":"Real Estate Operator",
            "type":"Services"
        }
    ],
    "sg:phone":"+1 765 477 0182",
    "sg:postcode":"47909",
    "sg:province":"IN",
    "sg:tags":[
        "apartment"
    ],
    "wof:name":"Copper Gate Apartments",
    "wof:placetype":"venue"
},
  "geometry": {"coordinates":[-86.897493,40.383123],"type":"Point"}
}