{
  "type": "Feature",
  "properties": {
    "addr:full":"2570 Central Ave Lake Station IN 46405",
    "addr:housenumber":"2570",
    "addr:postcode":"46405",
    "addr:street":"Central Ave Lake",
    "iso:country":"US",
    "sg:address":"2570 Central Ave",
    "sg:city":"Lake Station",
    "sg:classifiers":[
        {
            "category":"Insurance",
            "subcategory":"Insurance Agent",
            "type":"Services"
        }
    ],
    "sg:phone":"+1 219 962 5958",
    "sg:postcode":"46405",
    "sg:province":"IN",
    "wof:name":"Farmers Insurance Group",
    "wof:placetype":"venue"
},
  "geometry": {"coordinates":[-87.25335800000001,41.572081],"type":"Point"}
}