{
  "type": "Feature",
  "properties": {
    "addr:full":"2100 N Main St Bluffton IN 46714",
    "addr:housenumber":"2100",
    "addr:postcode":"46714",
    "addr:street":"N Main St",
    "iso:country":"US",
    "sg:address":"2100 N Main St",
    "sg:city":"Bluffton",
    "sg:classifiers":[
        {
            "category":"Restaurant",
            "type":"Food & Drink"
        }
    ],
    "sg:menulink":"http://www.allmenus.com/in/lancaster/120039-subway/menu/",
    "sg:phone":"+1 260 827 0115",
    "sg:postcode":"46714",
    "sg:province":"IN",
    "sg:tags":[
        "american",
        "sandwich"
    ],
    "wof:name":"Subway",
    "wof:placetype":"venue"
},
  "geometry": {"coordinates":[-85.165853,40.773191],"type":"Point"}
}