{
  "type": "Feature",
  "properties": {
    "iso:country":"US",
    "sg:address":"410 E Main St",
    "sg:city":"Washington",
    "sg:classifiers":[
        {
            "category":"Retail",
            "subcategory":"Repair Shop",
            "type":"Services"
        }
    ],
    "sg:phone":"+1 812 254 0725",
    "sg:postcode":"47501",
    "sg:province":"IN",
    "sg:tags":[
        "welding"
    ],
    "wof:name":"Bumgarner Welding & Inspection",
    "wof:placetype":"venue"
},
  "geometry": {"coordinates":[-87.170274,38.657028],"type":"Point"}
}