{
  "type": "Feature",
  "properties": {
    "iso:country":"US",
    "sg:address":"50501 State Rd 13",
    "sg:city":"Middlebury",
    "sg:classifiers":[
        {
            "category":"Utilities",
            "subcategory":"Natural Gas",
            "type":"Services"
        }
    ],
    "sg:phone":"+1 574 825 2300",
    "sg:postcode":"46540",
    "sg:province":"IN",
    "sg:tags":[
        "transmission"
    ],
    "wof:name":"Trunkline Gas Company LLC",
    "wof:placetype":"venue"
},
  "geometry": {"coordinates":[-85.677241,41.759043],"type":"Point"}
}