{
  "type": "Feature",
  "properties": {
    "iso:country":"US",
    "sg:address":"9929 S Holland Rd SW",
    "sg:city":"Holland",
    "sg:classifiers":[
        {
            "category":"Personal",
            "subcategory":"Beauty Salon",
            "type":"Services"
        }
    ],
    "sg:phone":"+1 812 536 4648",
    "sg:postcode":"47541",
    "sg:province":"IN",
    "wof:name":"Dianna's Country Cuts",
    "wof:placetype":"venue"
},
  "geometry": {"coordinates":[-87.052234,38.234867],"type":"Point"}
}