{
  "type": "Feature",
  "properties": {
    "addr:full":"5500 Hohman Ave Hammond IN 46320",
    "addr:housenumber":"5500",
    "addr:postcode":"46320",
    "addr:street":"Hohman Ave",
    "iso:country":"US",
    "sg:address":"5500 Hohman Ave",
    "sg:city":"Hammond",
    "sg:classifiers":[
        {
            "category":"Health Services",
            "subcategory":"Doctor",
            "type":"Services"
        }
    ],
    "sg:phone":"+1 219 852 2513",
    "sg:postcode":"46320",
    "sg:province":"IN",
    "sg:tags":[
        "psychiatrist"
    ],
    "sg:website":"www.smmhc.com",
    "wof:name":"Sabah Saima MD",
    "wof:placetype":"venue"
},
  "geometry": {"coordinates":[-87.522183,41.613862],"type":"Point"}
}