{
  "type": "Feature",
  "properties": {
    "iso:country":"US",
    "sg:address":"515 S Clark Blvd",
    "sg:city":"Clarksville",
    "sg:classifiers":[
        {
            "category":"Restaurant",
            "type":"Food & Drink"
        }
    ],
    "sg:phone":"+1 812 282 7174",
    "sg:postcode":"47129",
    "sg:province":"IN",
    "sg:tags":[
        "mexican"
    ],
    "wof:name":"El Caporal",
    "wof:placetype":"venue"
},
  "geometry": {"coordinates":[-85.76015,38.281921],"type":"Point"}
}