{
  "type": "Feature",
  "properties": {
    "addr:full":"721 Riverview Ave Elkhart IN 46516",
    "addr:housenumber":"721",
    "addr:postcode":"46516",
    "addr:street":"Riverview Ave",
    "iso:country":"US",
    "sg:address":"721 Riverview Ave",
    "sg:city":"Elkhart",
    "sg:classifiers":[
        {
            "category":"Social Services",
            "type":"Services"
        }
    ],
    "sg:phone":"+1 574 293 6519",
    "sg:postcode":"46516",
    "sg:province":"IN",
    "sg:tags":[
        "organization",
        "welfare"
    ],
    "wof:name":"American Red Cross",
    "wof:placetype":"venue"
},
  "geometry": {"coordinates":[-85.939153,41.684258],"type":"Point"}
}