{
  "type": "Feature",
  "properties": {
    "iso:country":"US",
    "sg:address":"68875 Beech Rd",
    "sg:city":"Nappanee",
    "sg:classifiers":[
        {
            "category":"Farming",
            "subcategory":"Livestock Farm",
            "type":"Manufacturing & Wholesale Goods"
        }
    ],
    "sg:phone":"+1 574 633 4721",
    "sg:postcode":"46550",
    "sg:province":"IN",
    "sg:tags":[
        "bearing",
        "fur",
        "animal"
    ],
    "wof:name":"Doug Truex",
    "wof:placetype":"venue"
},
  "geometry": {"coordinates":[-86.079086,41.495385],"type":"Point"}
}