{
  "type": "Feature",
  "properties": {
    "iso:country":"US",
    "sg:address":"1630 N Main St",
    "sg:city":"Rushville",
    "sg:classifiers":[
        {
            "category":"Food & Beverages",
            "subcategory":"Liquor & Beverages",
            "type":"Retail Goods"
        }
    ],
    "sg:phone":"+1 765 932 2060",
    "sg:postcode":"46173",
    "sg:province":"IN",
    "wof:name":"Aspen Spirits",
    "wof:placetype":"venue"
},
  "geometry": {"coordinates":[-85.444807,39.628502],"type":"Point"}
}