{
  "type": "Feature",
  "properties": {
    "iso:country":"US",
    "sg:address":"1004 N A St",
    "sg:city":"Richmond",
    "sg:classifiers":[
        {
            "category":"Organizations",
            "subcategory":"Religious Organization",
            "type":"Services"
        }
    ],
    "sg:phone":"+1 765 966 7618",
    "sg:postcode":"47374",
    "sg:province":"IN",
    "sg:tags":[
        "church"
    ],
    "sg:website":"www.reidpres.com",
    "wof:name":"Reid Memorial Presbyterian Chr",
    "wof:placetype":"venue"
},
  "geometry": {"coordinates":[-84.889054,39.830654],"type":"Point"}
}