{
  "type": "Feature",
  "properties": {
    "addr:full":"915 N Van Buren St Shipshewana IN 46565",
    "addr:housenumber":"915",
    "addr:postcode":"46565",
    "addr:street":"N Van Buren St",
    "iso:country":"US",
    "sg:address":"915 N Van Buren St",
    "sg:city":"Shipshewana",
    "sg:classifiers":[
        {
            "category":"Health Services",
            "subcategory":"Doctor",
            "type":"Services"
        }
    ],
    "sg:phone":"+1 260 768 4185",
    "sg:postcode":"46565",
    "sg:province":"IN",
    "sg:tags":[
        "physician",
        "surgeon"
    ],
    "wof:name":"Shipshewana Medical Clinic",
    "wof:placetype":"venue"
},
  "geometry": {"coordinates":[-85.58041900000001,41.669284],"type":"Point"}
}