{
  "type": "Feature",
  "properties": {
    "iso:country":"US",
    "sg:address":"395 S State Rd 135",
    "sg:city":"Greenwood",
    "sg:classifiers":[
        {
            "category":"Shopping",
            "type":"Retail Goods"
        }
    ],
    "sg:phone":"+1 317 882 9415",
    "sg:postcode":"46142",
    "sg:province":"IN",
    "sg:tags":[
        "equipment",
        "telephone",
        "supply"
    ],
    "wof:name":"Digital Universe",
    "wof:placetype":"venue"
},
  "geometry": {"coordinates":[-86.158424,39.622697],"type":"Point"}
}