{
  "type": "Feature",
  "properties": {
    "iso:country":"US",
    "sg:address":"1616 N Section St",
    "sg:city":"Sullivan",
    "sg:classifiers":[
        {
            "category":"Restaurant",
            "type":"Food & Drink"
        }
    ],
    "sg:phone":"+1 812 268 3388",
    "sg:postcode":"47882",
    "sg:province":"IN",
    "wof:name":"Patrick's Restaurant",
    "wof:placetype":"venue"
},
  "geometry": {"coordinates":[-87.409351,39.112395],"type":"Point"}
}