{
  "type": "Feature",
  "properties": {
    "addr:full":"630 E Ohio St Indianapolis IN 46202",
    "addr:housenumber":"630",
    "addr:postcode":"46202",
    "addr:street":"E Ohio St",
    "iso:country":"US",
    "sg:address":"630 E Ohio St",
    "sg:city":"Indianapolis",
    "sg:classifiers":[
        {
            "category":"Organizations",
            "subcategory":"Membership Organization",
            "type":"Services"
        }
    ],
    "sg:phone":"+1 317 951 8818",
    "sg:postcode":"46202",
    "sg:province":"IN",
    "sg:tags":[
        "environmental",
        "ecological",
        "conservation"
    ],
    "sg:website":"http://www.nature.org",
    "wof:name":"Nature Conservancy The",
    "wof:placetype":"venue"
},
  "geometry": {"coordinates":[-86.14671,39.769653],"type":"Point"}
}