{
  "type": "Feature",
  "properties": {
    "iso:country":"US",
    "sg:address":"140 S Maxwell Ct",
    "sg:city":"Zionsville",
    "sg:classifiers":[
        {
            "category":"Building & Trades",
            "subcategory":"Construction",
            "type":"Services"
        }
    ],
    "sg:phone":"+1 317 733 1293",
    "sg:postcode":"46077",
    "sg:province":"IN",
    "sg:tags":[
        "house"
    ],
    "wof:name":"CJ Builders & Designs Inc",
    "wof:placetype":"venue"
},
  "geometry": {"coordinates":[-86.274486,39.967417],"type":"Point"}
}