{
  "type": "Feature",
  "properties": {
    "iso:country":"US",
    "sg:address":"58 Valparaiso St",
    "sg:city":"Valparaiso",
    "sg:classifiers":[
        {
            "category":"Social Services",
            "type":"Services"
        }
    ],
    "sg:phone":"+1 219 476 1557",
    "sg:postcode":"46383",
    "sg:province":"IN",
    "sg:tags":[
        "organization",
        "welfare"
    ],
    "wof:name":"Partners In Opportunities",
    "wof:placetype":"venue"
},
  "geometry": {"coordinates":[-87.056305,41.466965],"type":"Point"}
}