{
  "type": "Feature",
  "properties": {
    "iso:country":"US",
    "sg:address":"9250 S State Rd 58",
    "sg:city":"Columbus",
    "sg:classifiers":[
        {
            "category":"Organizations",
            "subcategory":"Religious Organization",
            "type":"Services"
        }
    ],
    "sg:phone":"+1 812 342 4583",
    "sg:postcode":"47201",
    "sg:province":"IN",
    "sg:tags":[
        "church"
    ],
    "wof:name":"Ogilville United Methodist Chr",
    "wof:placetype":"venue"
},
  "geometry": {"coordinates":[-86.023833,39.115184],"type":"Point"}
}