{
  "type": "Feature",
  "properties": {
    "iso:country":"US",
    "sg:address":"3401 Fairfield Ct",
    "sg:city":"Lafayette",
    "sg:classifiers":[
        {
            "category":"Professional",
            "subcategory":"Business Services",
            "type":"Services"
        }
    ],
    "sg:phone":"+1 765 471 0188",
    "sg:postcode":"47909",
    "sg:province":"IN",
    "sg:tags":[
        "embroidery"
    ],
    "wof:name":"Advantage Embroidery",
    "wof:placetype":"venue"
},
  "geometry": {"coordinates":[-86.841096,40.303126],"type":"Point"}
}