{
  "type": "Feature",
  "properties": {
    "iso:country":"US",
    "sg:address":"1224 W 21st St",
    "sg:city":"Indianapolis",
    "sg:classifiers":[
        {
            "category":"Personal",
            "subcategory":"Beauty Salon",
            "type":"Services"
        }
    ],
    "sg:phone":"+1 317 955 3922",
    "sg:postcode":"46202",
    "sg:province":"IN",
    "wof:name":"Same Do Beauty Salon",
    "wof:placetype":"venue"
},
  "geometry": {"coordinates":[-86.183342,39.795544],"type":"Point"}
}