{
  "type": "Feature",
  "properties": {
    "iso:country":"US",
    "sg:address":"320 N Meridian St",
    "sg:city":"Indianapolis",
    "sg:classifiers":[
        {
            "category":"Cafe",
            "type":"Food & Drink"
        },
        {
            "category":"Restaurant",
            "type":"Food & Drink"
        }
    ],
    "sg:menulink":"http://www.allmenus.com/in/indianapolis/253567-gabriels-cafe/menu/",
    "sg:phone":"+1 317 635 0132",
    "sg:postcode":"46204",
    "sg:province":"IN",
    "sg:tags":[
        "american",
        "sandwich",
        "salad"
    ],
    "wof:name":"Gabriel's Cafe",
    "wof:placetype":"venue"
},
  "geometry": {"coordinates":[-86.157876,39.771889],"type":"Point"}
}