{
  "type": "Feature",
  "properties": {
    "iso:country":"US",
    "sg:address":"7908 S Anthony Blvd",
    "sg:city":"Fort Wayne",
    "sg:classifiers":[
        {
            "category":"Education",
            "subcategory":"School",
            "type":"Public Place"
        }
    ],
    "sg:phone":"+1 260 441 8727",
    "sg:postcode":"46816",
    "sg:province":"IN",
    "wof:name":"Timothy L Johnson Academy",
    "wof:placetype":"venue"
},
  "geometry": {"coordinates":[-85.112105,41.011195],"type":"Point"}
}