{
  "type": "Feature",
  "properties": {
    "iso:country":"US",
    "sg:address":"2658 Lake Circle Dr",
    "sg:city":"Indianapolis",
    "sg:classifiers":[
        {
            "category":"Restaurant",
            "type":"Food & Drink"
        }
    ],
    "sg:menulink":"http://www.allmenus.com/in/pike/10803-bravo!-cucina-italiana/menu/",
    "sg:phone":"+1 317 879 1444",
    "sg:postcode":"46268",
    "sg:province":"IN",
    "sg:tags":[
        "italian"
    ],
    "wof:name":"Bravo! Cucina Italiana",
    "wof:placetype":"venue"
},
  "geometry": {"coordinates":[-86.20803100000001,39.913256],"type":"Point"}
}