{
  "type": "Feature",
  "properties": {
    "iso:country":"US",
    "sg:address":"955 N Michigan Ave",
    "sg:city":"Greensburg",
    "sg:classifiers":[
        {
            "category":"Health Services",
            "subcategory":"Health Practitioner",
            "type":"Services"
        }
    ],
    "sg:phone":"+1 812 663 5072",
    "sg:postcode":"47240",
    "sg:province":"IN",
    "sg:tags":[
        "therapist",
        "physical"
    ],
    "wof:name":"Progressive Physical Therapy",
    "wof:placetype":"venue"
},
  "geometry": {"coordinates":[-85.495012,39.346037],"type":"Point"}
}