{
  "type": "Feature",
  "properties": {
    "iso:country":"US",
    "sg:address":"313 Main St",
    "sg:city":"Evansville",
    "sg:classifiers":[
        {
            "category":"Professional",
            "subcategory":"Lawyer & Legal Services",
            "type":"Services"
        }
    ],
    "sg:phone":"+1 812 425 8101",
    "sg:postcode":"47708",
    "sg:province":"IN",
    "sg:tags":[
        "attorney"
    ],
    "sg:website":"www.bergerlaw.com",
    "wof:name":"Berger & Berger",
    "wof:placetype":"venue"
},
  "geometry": {"coordinates":[-87.571177,37.971432],"type":"Point"}
}