{
  "type": "Feature",
  "properties": {
    "iso:country":"US",
    "sg:address":"1346 N Co Rd 150 E",
    "sg:city":"Connersville",
    "sg:classifiers":[
        {
            "category":"Shopping",
            "subcategory":"Florist",
            "type":"Retail Goods"
        }
    ],
    "sg:phone":"+1 765 825 8816",
    "sg:postcode":"47331",
    "sg:province":"IN",
    "wof:name":"Village Creek Greenhouse",
    "wof:placetype":"venue"
},
  "geometry": {"coordinates":[-85.110506,39.658791],"type":"Point"}
}