{
  "type": "Feature",
  "properties": {
    "iso:country":"US",
    "sg:address":"3768 N 525 W",
    "sg:city":"Laporte",
    "sg:classifiers":[
        {
            "category":"Manufacturing",
            "subcategory":"Building Materials",
            "type":"Manufacturing & Wholesale Goods"
        }
    ],
    "sg:phone":"+1 219 325 9910",
    "sg:postcode":"46350",
    "sg:province":"IN",
    "wof:name":"C & G Millwork Inc",
    "wof:placetype":"venue"
},
  "geometry": {"coordinates":[-86.801907,41.663729],"type":"Point"}
}