{
  "type": "Feature",
  "properties": {
    "iso:country":"US",
    "sg:address":"660 E State Rd 64",
    "sg:city":"English",
    "sg:classifiers":[
        {
            "category":"Food & Beverages",
            "subcategory":"Groceries & Convenience Stores",
            "type":"Retail Goods"
        }
    ],
    "sg:phone":"+1 812 338 9003",
    "sg:postcode":"47118",
    "sg:province":"IN",
    "wof:name":"64 Express Mart",
    "wof:placetype":"venue"
},
  "geometry": {"coordinates":[-86.463404,38.343011],"type":"Point"}
}