{
  "type": "Feature",
  "properties": {
    "addr:full":"308 E Mulberry St Westport IN 47283",
    "addr:housenumber":"308",
    "addr:postcode":"47283",
    "addr:street":"E Mulberry St",
    "iso:country":"US",
    "sg:address":"308 E Mulberry St",
    "sg:city":"Westport",
    "sg:classifiers":[
        {
            "category":"Health Services",
            "subcategory":"Doctor",
            "type":"Services"
        }
    ],
    "sg:phone":"+1 812 591 3452",
    "sg:postcode":"47283",
    "sg:province":"IN",
    "sg:tags":[
        "clinic"
    ],
    "wof:name":"Westport Clinic",
    "wof:placetype":"venue"
},
  "geometry": {"coordinates":[-85.57210000000001,39.176888],"type":"Point"}
}