{
  "type": "Feature",
  "properties": {
    "addr:full":"3235 N Anthony Blvd Fort Wayne IN 46805",
    "addr:housenumber":"3235",
    "addr:postcode":"46805",
    "addr:street":"N Anthony Blvd",
    "iso:country":"US",
    "sg:address":"3235 N Anthony Blvd",
    "sg:city":"Fort Wayne",
    "sg:classifiers":[
        {
            "category":"Restaurant",
            "type":"Food & Drink"
        }
    ],
    "sg:phone":"+1 260 483 3213",
    "sg:postcode":"46805",
    "sg:province":"IN",
    "wof:name":"Atz Ice Cream Shoppe",
    "wof:placetype":"venue"
},
  "geometry": {"coordinates":[-85.116011,41.108708],"type":"Point"}
}