{
  "type": "Feature",
  "properties": {
    "iso:country":"US",
    "sg:address":"1006 Seminary St",
    "sg:city":"Hope",
    "sg:classifiers":[
        {
            "category":"Manufacturing",
            "subcategory":"Lumber",
            "type":"Manufacturing & Wholesale Goods"
        }
    ],
    "sg:phone":"+1 812 546 4427",
    "sg:postcode":"47246",
    "sg:province":"IN",
    "sg:tags":[
        "sawmill"
    ],
    "wof:name":"Hope Hardwoods Inc",
    "wof:placetype":"venue"
},
  "geometry": {"coordinates":[-85.762946,39.299929],"type":"Point"}
}