{
  "type": "Feature",
  "properties": {
    "iso:country":"US",
    "sg:address":"8530 E Washington St",
    "sg:city":"Indianapolis",
    "sg:classifiers":[
        {
            "category":"Personal",
            "subcategory":"Beauty Salon",
            "type":"Services"
        }
    ],
    "sg:phone":"+1 317 898 9279",
    "sg:postcode":"46219",
    "sg:province":"IN",
    "wof:name":"Vickie Helms",
    "wof:placetype":"venue"
},
  "geometry": {"coordinates":[-86.017492,39.773576],"type":"Point"}
}