{
  "type": "Feature",
  "properties": {
    "iso:country":"US",
    "sg:address":"104 N Illinois St",
    "sg:city":"Monticello",
    "sg:classifiers":[
        {
            "category":"Organizations",
            "subcategory":"Religious Organization",
            "type":"Services"
        }
    ],
    "sg:phone":"+1 574 583 5787",
    "sg:postcode":"47960",
    "sg:province":"IN",
    "sg:tags":[
        "church"
    ],
    "wof:name":"Presbyterian Church",
    "wof:placetype":"venue"
},
  "geometry": {"coordinates":[-86.763515,40.745435],"type":"Point"}
}