{
  "type": "Feature",
  "properties": {
    "addr:full":"5621 S Meridian Rd Columbia City IN 46725",
    "addr:housenumber":"5621",
    "addr:postcode":"46725",
    "addr:street":"S Meridian Rd",
    "iso:country":"US",
    "sg:address":"5621 S Meridian Rd",
    "sg:city":"Columbia City",
    "sg:classifiers":[
        {
            "category":"Manufacturing",
            "subcategory":"Building Materials",
            "type":"Manufacturing & Wholesale Goods"
        }
    ],
    "sg:phone":"+1 260 396 2032",
    "sg:postcode":"46725",
    "sg:province":"IN",
    "sg:tags":[
        "mfg"
    ],
    "wof:name":"Terry B Ward",
    "wof:placetype":"venue"
},
  "geometry": {"coordinates":[-85.48941499999999,41.081615],"type":"Point"}
}