{
  "type": "Feature",
  "properties": {
    "iso:country":"US",
    "sg:address":"623 S Laurel St",
    "sg:city":"Mishawaka",
    "sg:classifiers":[
        {
            "category":"Professional",
            "subcategory":"Accounting & Tax Preparation",
            "type":"Services"
        }
    ],
    "sg:phone":"+1 574 257 0830",
    "sg:postcode":"46544",
    "sg:province":"IN",
    "sg:tags":[
        "return",
        "filing"
    ],
    "wof:name":"Common Cents Consulting Servic",
    "wof:placetype":"venue"
},
  "geometry": {"coordinates":[-86.171588,41.655968],"type":"Point"}
}