{
  "type": "Feature",
  "properties": {
    "addr:full":"1129 N Baldwin Ave Marion IN 46952",
    "addr:housenumber":"1129",
    "addr:postcode":"46952",
    "addr:street":"N Baldwin Ave",
    "iso:country":"US",
    "sg:address":"1129 N Baldwin Ave",
    "sg:city":"Marion",
    "sg:classifiers":[
        {
            "category":"Shopping",
            "subcategory":"Department Store",
            "type":"Retail Goods"
        }
    ],
    "sg:phone":"+1 765 662 2537",
    "sg:postcode":"46952",
    "sg:province":"IN",
    "wof:name":"J C Penney Co",
    "wof:placetype":"venue"
},
  "geometry": {"coordinates":[-85.676047,40.572068],"type":"Point"}
}