{
  "type": "Feature",
  "properties": {
    "iso:country":"US",
    "sg:address":"138 W Carmel Dr",
    "sg:city":"Carmel",
    "sg:classifiers":[
        {
            "category":"Recreation",
            "type":"Entertainment"
        }
    ],
    "sg:phone":"+1 317 587 1503",
    "sg:postcode":"46032",
    "sg:province":"IN",
    "sg:tags":[
        "instruction",
        "gymnastic"
    ],
    "wof:name":"Spectrum Sports",
    "wof:placetype":"venue"
},
  "geometry": {"coordinates":[-86.12843700000001,39.961457],"type":"Point"}
}