{
  "type": "Feature",
  "properties": {
    "iso:country":"US",
    "sg:address":"217 W Ohio St",
    "sg:city":"Rockville",
    "sg:classifiers":[
        {
            "category":"Professional",
            "subcategory":"Computer Services",
            "type":"Services"
        }
    ],
    "sg:phone":"+1 765 569 1075",
    "sg:postcode":"47872",
    "sg:province":"IN",
    "wof:name":"Computech",
    "wof:placetype":"venue"
},
  "geometry": {"coordinates":[-87.229804,39.762461],"type":"Point"}
}