{
  "type": "Feature",
  "properties": {
    "iso:country":"US",
    "sg:address":"1686 N National Rd",
    "sg:city":"Columbus",
    "sg:classifiers":[
        {
            "category":"Restaurant",
            "type":"Food & Drink"
        }
    ],
    "sg:phone":"+1 812 378 1077",
    "sg:postcode":"47201",
    "sg:province":"IN",
    "sg:website":"www.whitecastle.com",
    "wof:name":"White Castle",
    "wof:placetype":"venue"
},
  "geometry": {"coordinates":[-85.881968,39.214684],"type":"Point"}
}