{
  "type": "Feature",
  "properties": {
    "iso:country":"US",
    "sg:address":"3745 S Washington St",
    "sg:city":"Marion",
    "sg:classifiers":[
        {
            "category":"Retail",
            "subcategory":"Repair Shop",
            "type":"Services"
        }
    ],
    "sg:phone":"+1 765 674 3387",
    "sg:postcode":"46953",
    "sg:province":"IN",
    "sg:tags":[
        "cleaners",
        "parts",
        "vacuum"
    ],
    "wof:name":"Karnes' Sweeper Co",
    "wof:placetype":"venue"
},
  "geometry": {"coordinates":[-85.66591,40.522899],"type":"Point"}
}