{
  "type": "Feature",
  "properties": {
    "iso:country":"US",
    "sg:address":"62535 Co Rd 37",
    "sg:city":"Goshen",
    "sg:classifiers":[
        {
            "category":"Restaurant",
            "type":"Food & Drink"
        }
    ],
    "sg:phone":"+1 574 642 0191",
    "sg:postcode":"46528",
    "sg:province":"IN",
    "wof:name":"Citrus Restaurant",
    "wof:placetype":"venue"
},
  "geometry": {"coordinates":[-85.71392,41.587857],"type":"Point"}
}