{
  "type": "Feature",
  "properties": {
    "iso:country":"US",
    "sg:address":"53364 Marina Dr",
    "sg:city":"Elkhart",
    "sg:classifiers":[
        {
            "category":"Wholesale",
            "subcategory":"Durable Goods & Equipment",
            "type":"Manufacturing & Wholesale Goods"
        }
    ],
    "sg:phone":"+1 574 294 5611",
    "sg:postcode":"46514",
    "sg:province":"IN",
    "sg:tags":[
        "representative",
        "manufacturer"
    ],
    "sg:website":"www.journeymantrays.com",
    "wof:name":"Keyline Sales Inc",
    "wof:placetype":"venue"
},
  "geometry": {"coordinates":[-85.917006,41.719019],"type":"Point"}
}