{
  "type": "Feature",
  "properties": {
    "iso:country":"US",
    "sg:address":"714 N Wheeler Ave",
    "sg:city":"Griffith",
    "sg:classifiers":[
        {
            "category":"Building & Trades",
            "subcategory":"Landscaping Services",
            "type":"Services"
        }
    ],
    "sg:phone":"+1 219 924 3494",
    "sg:postcode":"46319",
    "sg:province":"IN",
    "sg:tags":[
        "designer",
        "landscape"
    ],
    "wof:name":"Greenwood Group Landscaping",
    "wof:placetype":"venue"
},
  "geometry": {"coordinates":[-87.414378,41.536965],"type":"Point"}
}