{
  "type": "Feature",
  "properties": {
    "iso:country":"US",
    "sg:address":"11611 N Meridian St",
    "sg:city":"Carmel",
    "sg:classifiers":[
        {
            "category":"Professional",
            "subcategory":"Lawyer & Legal Services",
            "type":"Services"
        }
    ],
    "sg:phone":"+1 317 569 2570",
    "sg:postcode":"46032",
    "sg:province":"IN",
    "wof:name":"Schultz Thomas R Atty",
    "wof:placetype":"venue"
},
  "geometry": {"coordinates":[-86.1576,39.9571],"type":"Point"}
}