{
  "type": "Feature",
  "properties": {
    "iso:country":"US",
    "sg:address":"1041 N 8th St",
    "sg:city":"Terre Haute",
    "sg:classifiers":[
        {
            "category":"Building & Trades",
            "subcategory":"Landscaping Services",
            "type":"Services"
        }
    ],
    "sg:phone":"+1 812 234 4166",
    "sg:postcode":"47807",
    "sg:province":"IN",
    "wof:name":"Gifford & Sons",
    "wof:placetype":"venue"
},
  "geometry": {"coordinates":[-87.405551,39.479676],"type":"Point"}
}