{
  "type": "Feature",
  "properties": {
    "iso:country":"US",
    "sg:address":"12975 Parkside Dr",
    "sg:city":"Fishers",
    "sg:classifiers":[
        {
            "category":"Wholesale",
            "subcategory":"Computers",
            "type":"Manufacturing & Wholesale Goods"
        }
    ],
    "sg:phone":"+1 317 913 4160",
    "sg:postcode":"46038",
    "sg:province":"IN",
    "sg:tags":[
        "equipment",
        "processing",
        "word"
    ],
    "sg:website":"www.computer-systems.com",
    "wof:name":"Csi Computer Systems",
    "wof:placetype":"venue"
},
  "geometry": {"coordinates":[-86.000523,39.976473],"type":"Point"}
}