{
  "type": "Feature",
  "properties": {
    "addr:full":"432 State St New Albany IN 47150",
    "addr:housenumber":"432",
    "addr:postcode":"47150",
    "addr:street":"State St",
    "iso:country":"US",
    "sg:address":"432 State St",
    "sg:city":"New Albany",
    "sg:classifiers":[
        {
            "category":"Professional",
            "subcategory":"Business Services",
            "type":"Services"
        }
    ],
    "sg:phone":"+1 812 949 4363",
    "sg:postcode":"47150",
    "sg:province":"IN",
    "sg:tags":[
        "paging",
        "answering"
    ],
    "wof:name":"Planet Telecom By ICIM Corp",
    "wof:placetype":"venue"
},
  "geometry": {"coordinates":[-85.82440099999999,38.286455],"type":"Point"}
}