{
  "type": "Feature",
  "properties": {
    "iso:country":"US",
    "sg:address":"1626 E Main St",
    "sg:city":"Richmond",
    "sg:classifiers":[
        {
            "category":"Shopping",
            "subcategory":"Pharmacy",
            "type":"Retail Goods"
        }
    ],
    "sg:phone":"+1 765 966 2225",
    "sg:postcode":"47374",
    "sg:province":"IN",
    "wof:name":"Richomd Apothecary Pharmacy",
    "wof:placetype":"venue"
},
  "geometry": {"coordinates":[-84.879952,39.829734],"type":"Point"}
}