{
  "type": "Feature",
  "properties": {
    "iso:country":"US",
    "sg:address":"5090 E 38th St",
    "sg:city":"Indianapolis",
    "sg:classifiers":[
        {
            "category":"Shopping",
            "type":"Retail Goods"
        }
    ],
    "sg:phone":"+1 317 547 9977",
    "sg:postcode":"46218",
    "sg:province":"IN",
    "sg:tags":[
        "salons-equipment",
        "supply",
        "cosmetic",
        "beauty",
        "perfume"
    ],
    "wof:name":"A-1 Beauty Supply",
    "wof:placetype":"venue"
},
  "geometry": {"coordinates":[-86.083958,39.825529],"type":"Point"}
}