{
  "type": "Feature",
  "properties": {
    "iso:country":"US",
    "sg:address":"1800 N Wabash Rd",
    "sg:city":"Marion",
    "sg:classifiers":[
        {
            "category":"Organizations",
            "subcategory":"Professional Association",
            "type":"Services"
        }
    ],
    "sg:phone":"+1 765 662 2620",
    "sg:postcode":"46952",
    "sg:province":"IN",
    "wof:name":"Marion Teacher's Assn",
    "wof:placetype":"venue"
},
  "geometry": {"coordinates":[-85.67971199999999,40.581804],"type":"Point"}
}