{
  "type": "Feature",
  "properties": {
    "iso:country":"US",
    "sg:address":"11505 Buente Rd",
    "sg:city":"Evansville",
    "sg:classifiers":[
        {
            "category":"Building & Trades",
            "subcategory":"Construction",
            "type":"Services"
        }
    ],
    "sg:phone":"+1 812 963 6205",
    "sg:postcode":"47720",
    "sg:province":"IN",
    "wof:name":"Garland Herrmann",
    "wof:placetype":"venue"
},
  "geometry": {"coordinates":[-87.666622,38.091054],"type":"Point"}
}