{
  "type": "Feature",
  "properties": {
    "iso:country":"US",
    "sg:address":"597 W 300 S",
    "sg:city":"Rochester",
    "sg:classifiers":[
        {
            "category":"Wholesale",
            "subcategory":"Farm Supplies",
            "type":"Manufacturing & Wholesale Goods"
        }
    ],
    "sg:phone":"+1 574 223 8644",
    "sg:postcode":"46975",
    "sg:province":"IN",
    "wof:name":"District Sales Manager",
    "wof:placetype":"venue"
},
  "geometry": {"coordinates":[-86.256616,41.010387],"type":"Point"}
}