{
  "type": "Feature",
  "properties": {
    "addr:full":"11979 N Baseline Road-57 Wolcottville IN 46795",
    "addr:housenumber":"11979",
    "addr:postcode":"46795",
    "addr:street":"N Baseline Road-57",
    "iso:country":"US",
    "sg:address":"11979 N Baseline Road-57",
    "sg:city":"Wolcottville",
    "sg:classifiers":[
        {
            "category":"Home & Garden",
            "subcategory":"Garden Supply",
            "type":"Retail Goods"
        }
    ],
    "sg:phone":"+1 260 854 4390",
    "sg:postcode":"46795",
    "sg:province":"IN",
    "sg:tags":[
        "engine"
    ],
    "wof:name":"County Line Engine Shop Inc",
    "wof:placetype":"venue"
},
  "geometry": {"coordinates":[-85.423574,41.524675],"type":"Point"}
}