{
  "type": "Feature",
  "properties": {
    "addr:full":"2025 Virginia Ave Connersville IN 47331",
    "addr:housenumber":"2025",
    "addr:postcode":"47331",
    "addr:street":"Virginia Ave",
    "iso:country":"US",
    "sg:address":"2025 Virginia Ave",
    "sg:city":"Connersville",
    "sg:classifiers":[
        {
            "category":"Health Services",
            "subcategory":"Doctor",
            "type":"Services"
        }
    ],
    "sg:phone":"+1 765 827 6612",
    "sg:postcode":"47331",
    "sg:province":"IN",
    "sg:tags":[
        "physician",
        "surgeon"
    ],
    "wof:name":"S Aurora Gardner DO",
    "wof:placetype":"venue"
},
  "geometry": {"coordinates":[-85.131995,39.658458],"type":"Point"}
}