{
  "type": "Feature",
  "properties": {
    "iso:country":"US",
    "sg:address":"7874 E State Rd 28",
    "sg:city":"Elwood",
    "sg:classifiers":[
        {
            "category":"Autos & Motor Vehicles",
            "subcategory":"Motorcycle Sales",
            "type":"Retail Goods"
        }
    ],
    "sg:phone":"+1 765 552 6380",
    "sg:postcode":"46036",
    "sg:province":"IN",
    "wof:name":"Jj Cycles",
    "wof:placetype":"venue"
},
  "geometry": {"coordinates":[-85.865574,40.276967],"type":"Point"}
}