{
  "type": "Feature",
  "properties": {
    "addr:full":"2800 W Harlan Dr Terre Haute IN 47802",
    "addr:housenumber":"2800",
    "addr:postcode":"47802",
    "addr:street":"W Harlan Dr",
    "iso:country":"US",
    "sg:address":"2800 W Harlan Dr",
    "sg:city":"Terre Haute",
    "sg:classifiers":[
        {
            "category":"Education",
            "subcategory":"School",
            "type":"Public Place"
        }
    ],
    "sg:phone":"+1 812 462 4236",
    "sg:postcode":"47802",
    "sg:province":"IN",
    "wof:name":"Hoosier Prairie Elementary",
    "wof:placetype":"venue"
},
  "geometry": {"coordinates":[-87.458501,39.346759],"type":"Point"}
}