{
  "type": "Feature",
  "properties": {
    "iso:country":"US",
    "sg:address":"219 W Sycamore St",
    "sg:city":"Kokomo",
    "sg:classifiers":[
        {
            "category":"Insurance",
            "subcategory":"Insurance Agent",
            "type":"Services"
        }
    ],
    "sg:phone":"+1 765 457 5314",
    "sg:postcode":"46901",
    "sg:province":"IN",
    "wof:name":"Ralph I Stewart Insurance Inc",
    "wof:placetype":"venue"
},
  "geometry": {"coordinates":[-86.133469,40.486384],"type":"Point"}
}