{
  "type": "Feature",
  "properties": {
    "iso:country":"US",
    "sg:address":"13967 Springmill Ponds Cir",
    "sg:city":"Carmel",
    "sg:classifiers":[
        {
            "category":"Professional",
            "subcategory":"Business Services",
            "type":"Services"
        }
    ],
    "sg:phone":"+1 317 575 8570",
    "sg:postcode":"46032",
    "sg:province":"IN",
    "wof:name":"St Loftus Inc",
    "wof:placetype":"venue"
},
  "geometry": {"coordinates":[-86.162826,39.995034],"type":"Point"}
}