{
  "type": "Feature",
  "properties": {
    "iso:country":"US",
    "sg:address":"9852 W State Rd 2",
    "sg:city":"Laporte",
    "sg:classifiers":[
        {
            "category":"Manufacturing",
            "subcategory":"Printing",
            "type":"Manufacturing & Wholesale Goods"
        }
    ],
    "sg:phone":"+1 219 785 2234",
    "sg:postcode":"46350",
    "sg:province":"IN",
    "sg:tags":[
        "newspaper"
    ],
    "wof:name":"Westville Indicator",
    "wof:placetype":"venue"
},
  "geometry": {"coordinates":[-86.894263,41.562847],"type":"Point"}
}