{
  "type": "Feature",
  "properties": {
    "iso:country":"US",
    "sg:address":"516 Wabash St",
    "sg:city":"Michigan City",
    "sg:classifiers":[
        {
            "category":"Shopping",
            "subcategory":"Clothing, Apparel, & Fashions",
            "type":"Retail Goods"
        }
    ],
    "sg:phone":"+1 219 874 0086",
    "sg:postcode":"46360",
    "sg:province":"IN",
    "sg:tags":[
        "alteration"
    ],
    "wof:name":"Alterations Plus",
    "wof:placetype":"venue"
},
  "geometry": {"coordinates":[-86.904211,41.715537],"type":"Point"}
}