{
  "type": "Feature",
  "properties": {
    "iso:country":"US",
    "sg:address":"25760 Old State Rte 1",
    "sg:city":"Guilford",
    "sg:classifiers":[
        {
            "category":"Professional",
            "type":"Services"
        }
    ],
    "sg:phone":"+1 812 576 2207",
    "sg:postcode":"47022",
    "sg:province":"IN",
    "sg:tags":[
        "establishment"
    ],
    "wof:name":"Paul A Girty Enterprises",
    "wof:placetype":"venue"
},
  "geometry": {"coordinates":[-84.945136,39.250127],"type":"Point"}
}