{
  "type": "Feature",
  "properties": {
    "iso:country":"US",
    "sg:address":"14330 US Hwy 20",
    "sg:city":"Middlebury",
    "sg:classifiers":[
        {
            "category":"Restaurant",
            "type":"Food & Drink"
        }
    ],
    "sg:phone":"+1 574 825 2040",
    "sg:postcode":"46540",
    "sg:province":"IN",
    "wof:name":"Hilltop Inn",
    "wof:placetype":"venue"
},
  "geometry": {"coordinates":[-85.741159,41.668004],"type":"Point"}
}