{
  "type": "Feature",
  "properties": {
    "iso:country":"US",
    "sg:address":"1701 N Market St",
    "sg:city":"Kokomo",
    "sg:classifiers":[
        {
            "category":"Freight",
            "type":"Transportation"
        }
    ],
    "sg:phone":"+1 765 457 8410",
    "sg:postcode":"46901",
    "sg:province":"IN",
    "sg:tags":[
        "mover"
    ],
    "wof:name":"Collins Moving Systems Inc",
    "wof:placetype":"venue"
},
  "geometry": {"coordinates":[-86.129218,40.503637],"type":"Point"}
}