{
  "type": "Feature",
  "properties": {
    "addr:full":"506 S State Rd 49 Valparaiso IN 46383",
    "addr:housenumber":"506;49",
    "addr:postcode":"46383",
    "addr:street":"S State Rd",
    "iso:country":"US",
    "sg:address":"506 S State Rd 49",
    "sg:city":"Valparaiso",
    "sg:classifiers":[
        {
            "category":"Food & Beverages",
            "subcategory":"Meat & Fish",
            "type":"Retail Goods"
        }
    ],
    "sg:phone":"+1 219 462 4150",
    "sg:postcode":"46383",
    "sg:province":"IN",
    "sg:website":"www.birkyfarms.com",
    "wof:name":"Birky Family Farms Country Mkt",
    "wof:placetype":"venue"
},
  "geometry": {"coordinates":[-87.02700299999999,41.354617],"type":"Point"}
}