{
  "type": "Feature",
  "properties": {
    "iso:country":"US",
    "sg:address":"6111 Churchman Byp",
    "sg:city":"Indianapolis",
    "sg:classifiers":[
        {
            "category":"Manufacturing",
            "subcategory":"Building Materials",
            "type":"Manufacturing & Wholesale Goods"
        }
    ],
    "sg:phone":"+1 317 786 1434",
    "sg:postcode":"46203",
    "sg:province":"IN",
    "sg:tags":[
        "cabinet"
    ],
    "sg:website":"www.corsicabinets.com",
    "wof:name":"Corsi Cabinet Co",
    "wof:placetype":"venue"
},
  "geometry": {"coordinates":[-86.06025099999999,39.711804],"type":"Point"}
}