{
  "type": "Feature",
  "properties": {
    "iso:country":"US",
    "sg:address":"11 E US Hwy 6",
    "sg:city":"Valparaiso",
    "sg:classifiers":[
        {
            "category":"Home & Garden",
            "subcategory":"Furniture",
            "type":"Retail Goods"
        }
    ],
    "sg:phone":"+1 219 464 9572",
    "sg:postcode":"46383",
    "sg:province":"IN",
    "wof:name":"Circles In Wind",
    "wof:placetype":"venue"
},
  "geometry": {"coordinates":[-87.064607,41.549999],"type":"Point"}
}