{
  "type": "Feature",
  "properties": {
    "iso:country":"US",
    "sg:address":"25609 Co Rd 24",
    "sg:city":"Elkhart",
    "sg:classifiers":[
        {
            "category":"Organizations",
            "subcategory":"Religious Organization",
            "type":"Services"
        }
    ],
    "sg:phone":"+1 574 370 3137",
    "sg:postcode":"46517",
    "sg:province":"IN",
    "sg:tags":[
        "church"
    ],
    "wof:name":"Solid Rock",
    "wof:placetype":"venue"
},
  "geometry": {"coordinates":[-85.952554,41.630557],"type":"Point"}
}