{
  "type": "Feature",
  "properties": {
    "iso:country":"US",
    "sg:address":"1225 Central Ave",
    "sg:city":"Indianapolis",
    "sg:classifiers":[
        {
            "category":"Building & Trades",
            "subcategory":"Plumbing",
            "type":"Services"
        }
    ],
    "sg:phone":"+1 317 634 2727",
    "sg:postcode":"46202",
    "sg:province":"IN",
    "sg:tags":[
        "conditioning",
        "air",
        "system",
        "contractor"
    ],
    "wof:name":"Indianapolis Furnace Co",
    "wof:placetype":"venue"
},
  "geometry": {"coordinates":[-86.149349,39.783307],"type":"Point"}
}