{
  "type": "Feature",
  "properties": {
    "iso:country":"US",
    "sg:address":"221 Pearl St",
    "sg:city":"Covington",
    "sg:classifiers":[
        {
            "category":"Autos & Motor Vehicles",
            "subcategory":"Automobile Sales",
            "type":"Retail Goods"
        }
    ],
    "sg:phone":"+1 765 793 3655",
    "sg:postcode":"47932",
    "sg:province":"IN",
    "sg:tags":[
        "car",
        "dealer"
    ],
    "wof:name":"D J Auto",
    "wof:placetype":"venue"
},
  "geometry": {"coordinates":[-87.39927900000001,40.142116],"type":"Point"}
}