{
  "type": "Feature",
  "properties": {
    "addr:full":"3309 45th St Highland IN 46322",
    "addr:housenumber":"3309",
    "addr:postcode":"46322",
    "addr:street":"45Th St",
    "iso:country":"US",
    "sg:address":"3309 45th St",
    "sg:city":"Highland",
    "sg:classifiers":[
        {
            "category":"Restaurant",
            "type":"Food & Drink"
        }
    ],
    "sg:phone":"+1 219 924 7208",
    "sg:postcode":"46322",
    "sg:province":"IN",
    "wof:name":"Zorba's Restaurant",
    "wof:placetype":"venue"
},
  "geometry": {"coordinates":[-87.449048,41.537491],"type":"Point"}
}