{
  "type": "Feature",
  "properties": {
    "iso:country":"US",
    "sg:address":"1204 Erie Ct",
    "sg:city":"Crown Point",
    "sg:classifiers":[
        {
            "category":"Professional",
            "type":"Services"
        }
    ],
    "sg:phone":"+1 219 663 5430",
    "sg:postcode":"46307",
    "sg:province":"IN",
    "sg:tags":[
        "establishment"
    ],
    "wof:name":"D Square Co",
    "wof:placetype":"venue"
},
  "geometry": {"coordinates":[-87.342659,41.424299],"type":"Point"}
}