{
  "type": "Feature",
  "properties": {
    "iso:country":"US",
    "sg:address":"301 E Carmel Dr Ste H400",
    "sg:city":"Carmel",
    "sg:classifiers":[
        {
            "category":"Health Services",
            "subcategory":"Doctor",
            "type":"Services"
        }
    ],
    "sg:phone":"+1 317 569 1651",
    "sg:postcode":"46032",
    "sg:province":"IN",
    "wof:name":"Smith Ernest E MD",
    "wof:placetype":"venue"
},
  "geometry": {"coordinates":[-86.12107,39.961893],"type":"Point"}
}