{
  "type": "Feature",
  "properties": {
    "iso:country":"US",
    "sg:address":"3470 Stellhorn Rd",
    "sg:city":"Fort Wayne",
    "sg:classifiers":[
        {
            "category":"Wholesale",
            "subcategory":"Stationery",
            "type":"Manufacturing & Wholesale Goods"
        }
    ],
    "sg:phone":"+1 260 486 3948",
    "sg:postcode":"46815",
    "sg:province":"IN",
    "sg:tags":[
        "supply"
    ],
    "wof:name":"Dentz",
    "wof:placetype":"venue"
},
  "geometry": {"coordinates":[-85.097969,41.119181],"type":"Point"}
}