{
  "type": "Feature",
  "properties": {
    "iso:country":"US",
    "sg:address":"6842 Alamo Rd",
    "sg:city":"Tell City",
    "sg:classifiers":[
        {
            "category":"Retail",
            "subcategory":"Auto Repair",
            "type":"Services"
        }
    ],
    "sg:phone":"+1 812 836 2087",
    "sg:postcode":"47586",
    "sg:province":"IN",
    "sg:tags":[
        "body"
    ],
    "wof:name":"Jans Auto Uphl Cnvrtible Tops",
    "wof:placetype":"venue"
},
  "geometry": {"coordinates":[-86.681539,38.013384],"type":"Point"}
}