{
  "type": "Feature",
  "properties": {
    "iso:country":"US",
    "sg:address":"14 S Judge St",
    "sg:city":"Bloomfield",
    "sg:classifiers":[
        {
            "category":"Personal",
            "subcategory":"Beauty Salon",
            "type":"Services"
        }
    ],
    "sg:phone":"+1 812 384 1435",
    "sg:postcode":"47424",
    "sg:province":"IN",
    "sg:tags":[
        "shop"
    ],
    "wof:name":"Superior Image",
    "wof:placetype":"venue"
},
  "geometry": {"coordinates":[-86.936534,39.026654],"type":"Point"}
}