{
  "type": "Feature",
  "properties": {
    "iso:country":"US",
    "sg:address":"56 Valparaiso St",
    "sg:city":"Valparaiso",
    "sg:classifiers":[
        {
            "category":"Professional",
            "subcategory":"Lawyer & Legal Services",
            "type":"Services"
        }
    ],
    "sg:phone":"+1 219 548 2444",
    "sg:postcode":"46383",
    "sg:province":"IN",
    "sg:tags":[
        "attorney"
    ],
    "wof:name":"Vis Kupsis Law Office",
    "wof:placetype":"venue"
},
  "geometry": {"coordinates":[-87.05630600000001,41.466923],"type":"Point"}
}