{
  "type": "Feature",
  "properties": {
    "iso:country":"US",
    "sg:address":"445 W 250 N",
    "sg:city":"Warsaw",
    "sg:classifiers":[
        {
            "category":"Banks & Credit Unions",
            "subcategory":"Bank",
            "type":"Services"
        }
    ],
    "sg:phone":"+1 574 267 3243",
    "sg:postcode":"46582",
    "sg:province":"IN",
    "sg:tags":[
        "loan"
    ],
    "wof:name":"Mutual Federal Savings Bank",
    "wof:placetype":"venue"
},
  "geometry": {"coordinates":[-85.852893,41.270134],"type":"Point"}
}