{
  "type": "Feature",
  "properties": {
    "iso:country":"US",
    "sg:address":"2805 Fairfield Ave",
    "sg:city":"Fort Wayne",
    "sg:classifiers":[
        {
            "category":"Health Services",
            "subcategory":"Doctor",
            "type":"Services"
        }
    ],
    "sg:phone":"+1 260 456 4880",
    "sg:postcode":"46807",
    "sg:province":"IN",
    "sg:tags":[
        "physician",
        "surgeon"
    ],
    "wof:name":"Pancner Psychiatric Assoc",
    "wof:placetype":"venue"
},
  "geometry": {"coordinates":[-85.144893,41.058776],"type":"Point"}
}