{
  "type": "Feature",
  "properties": {
    "addr:full":"930 E Washington St Winchester IN 47394",
    "addr:housenumber":"930",
    "addr:postcode":"47394",
    "addr:street":"E Washington St",
    "iso:country":"US",
    "sg:address":"930 E Washington St",
    "sg:city":"Winchester",
    "sg:classifiers":[
        {
            "category":"Banks & Credit Unions",
            "subcategory":"Bank",
            "type":"Services"
        }
    ],
    "sg:phone":"+1 765 584 4311",
    "sg:postcode":"47394",
    "sg:province":"IN",
    "wof:name":"Old National Bank",
    "wof:placetype":"venue"
},
  "geometry": {"coordinates":[-84.966437,40.172018],"type":"Point"}
}