{
  "type": "Feature",
  "properties": {
    "iso:country":"US",
    "sg:address":"6952 US Hwy 50",
    "sg:city":"Aurora",
    "sg:classifiers":[
        {
            "category":"Building & Trades",
            "subcategory":"Landscaping Services",
            "type":"Services"
        }
    ],
    "sg:phone":"+1 812 926 8133",
    "sg:postcode":"47001",
    "sg:province":"IN",
    "sg:tags":[
        "landscape",
        "contractor"
    ],
    "wof:name":"Cutter Landscaping",
    "wof:placetype":"venue"
},
  "geometry": {"coordinates":[-84.95017,39.0299],"type":"Point"}
}