{
  "type": "Feature",
  "properties": {
    "iso:country":"US",
    "sg:address":"159 E Washington St",
    "sg:city":"Shelbyville",
    "sg:classifiers":[
        {
            "category":"Health Services",
            "subcategory":"Clinic",
            "type":"Services"
        }
    ],
    "sg:phone":"+1 317 392 9378",
    "sg:postcode":"46176",
    "sg:province":"IN",
    "sg:tags":[
        "specialty",
        "outpatient"
    ],
    "wof:name":"West Group",
    "wof:placetype":"venue"
},
  "geometry": {"coordinates":[-85.773117,39.524358],"type":"Point"}
}