{
  "type": "Feature",
  "properties": {
    "iso:country":"US",
    "sg:address":"3000 Airport Rd",
    "sg:city":"Warsaw",
    "sg:classifiers":[
        {
            "category":"Airport",
            "type":"Transportation"
        }
    ],
    "sg:phone":"+1 574 269 1337",
    "sg:postcode":"46582",
    "sg:province":"IN",
    "wof:name":"City Of Warsaw Airport",
    "wof:placetype":"venue"
},
  "geometry": {"coordinates":[-85.84333100000001,41.277592],"type":"Point"}
}