{
  "type": "Feature",
  "properties": {
    "iso:country":"US",
    "sg:address":"1616 E Poplar St",
    "sg:city":"Terre Haute",
    "sg:classifiers":[
        {
            "category":"Wholesale",
            "subcategory":"Groceries",
            "type":"Manufacturing & Wholesale Goods"
        }
    ],
    "sg:phone":"+1 812 232 4208",
    "sg:postcode":"47807",
    "sg:province":"IN",
    "sg:tags":[
        "nut",
        "processing"
    ],
    "wof:name":"Uncle Al's Pecans Inc",
    "wof:placetype":"venue"
},
  "geometry": {"coordinates":[-87.39079,39.462958],"type":"Point"}
}