{
  "type": "Feature",
  "properties": {
    "iso:country":"US",
    "sg:address":"4730 Kessler View Dr",
    "sg:city":"Indianapolis",
    "sg:classifiers":[
        {
            "category":"Retail",
            "subcategory":"Laundry & Dry Cleaning",
            "type":"Services"
        }
    ],
    "sg:phone":"+1 317 236 9672",
    "sg:postcode":"46220",
    "sg:province":"IN",
    "sg:tags":[
        "cleaners",
        "rug",
        "carpet"
    ],
    "wof:name":"Thomas E Rossa Carpet Care",
    "wof:placetype":"venue"
},
  "geometry": {"coordinates":[-86.089316,39.856693],"type":"Point"}
}