{
  "type": "Feature",
  "properties": {
    "iso:country":"US",
    "sg:address":"6710 Chapel Hill Rd",
    "sg:city":"Borden",
    "sg:classifiers":[
        {
            "category":"Retail",
            "subcategory":"Auto Repair",
            "type":"Services"
        }
    ],
    "sg:phone":"+1 812 923 7490",
    "sg:postcode":"47106",
    "sg:province":"IN",
    "sg:tags":[
        "general"
    ],
    "wof:name":"Larrys Automotive",
    "wof:placetype":"venue"
},
  "geometry": {"coordinates":[-85.938264,38.396579],"type":"Point"}
}