{
  "type": "Feature",
  "properties": {
    "addr:full":"702 E Elm St Rensselaer IN 47978",
    "addr:housenumber":"702",
    "addr:postcode":"47978",
    "addr:street":"E Elm St",
    "iso:country":"US",
    "sg:address":"702 E Elm St",
    "sg:city":"Rensselaer",
    "sg:classifiers":[
        {
            "category":"Professional",
            "subcategory":"Business Services",
            "type":"Services"
        }
    ],
    "sg:phone":"+1 219 866 3365",
    "sg:postcode":"47978",
    "sg:province":"IN",
    "sg:tags":[
        "auctioneer"
    ],
    "wof:name":"Daniel Arnette Sr",
    "wof:placetype":"venue"
},
  "geometry": {"coordinates":[-87.14309900000001,40.941836],"type":"Point"}
}