{
  "type": "Feature",
  "properties": {
    "iso:country":"US",
    "sg:address":"2135 E Margaret Ave",
    "sg:city":"Terre Haute",
    "sg:classifiers":[
        {
            "category":"Bus Charters",
            "type":"Transportation"
        }
    ],
    "sg:phone":"+1 812 232 5252",
    "sg:postcode":"47802",
    "sg:province":"IN",
    "sg:tags":[
        "rental"
    ],
    "wof:name":"Turner Coaches Inc",
    "wof:placetype":"venue"
},
  "geometry": {"coordinates":[-87.384985,39.433702],"type":"Point"}
}