{
  "type": "Feature",
  "properties": {
    "iso:country":"US",
    "sg:address":"300 S State Road 446",
    "sg:city":"Bloomington",
    "sg:classifiers":[
        {
            "category":"Travel",
            "subcategory":"Hotels & Motels",
            "type":"Entertainment"
        }
    ],
    "sg:phone":"+1 812 336 7777",
    "sg:postcode":"47401",
    "sg:province":"IN",
    "sg:website":"www.centurysuites.com",
    "wof:name":"Century Suites",
    "wof:placetype":"venue"
},
  "geometry": {"coordinates":[-86.471497,39.1609],"type":"Point"}
}