{
  "type": "Feature",
  "properties": {
    "iso:country":"US",
    "sg:address":"3543 S Co Rd 300 W",
    "sg:city":"Vallonia",
    "sg:classifiers":[
        {
            "category":"Farming",
            "subcategory":"Livestock Farm",
            "type":"Manufacturing & Wholesale Goods"
        }
    ],
    "sg:phone":"+1 812 358 3198",
    "sg:postcode":"47281",
    "sg:province":"IN",
    "sg:tags":[
        "beef",
        "feedlot",
        "cattle"
    ],
    "wof:name":"Eugene Shoemaker",
    "wof:placetype":"venue"
},
  "geometry": {"coordinates":[-86.093006,38.826558],"type":"Point"}
}