{
  "type": "Feature",
  "properties": {
    "iso:country":"US",
    "sg:address":"750 Indian Boundary Rd",
    "sg:city":"Chesterton",
    "sg:classifiers":[
        {
            "category":"Shopping",
            "subcategory":"Department Store",
            "type":"Retail Goods"
        }
    ],
    "sg:phone":"+1 219 926 7521",
    "sg:postcode":"46304",
    "sg:province":"IN",
    "wof:name":"Kmart",
    "wof:placetype":"venue"
},
  "geometry": {"coordinates":[-87.041089,41.61677],"type":"Point"}
}