{
  "type": "Feature",
  "properties": {
    "iso:country":"US",
    "sg:address":"2951 Sand Point Rd",
    "sg:city":"Fort Wayne",
    "sg:classifiers":[
        {
            "category":"Organizations",
            "subcategory":"Religious Organization",
            "type":"Services"
        }
    ],
    "sg:phone":"+1 260 747 4811",
    "sg:postcode":"46809",
    "sg:province":"IN",
    "wof:name":"Elmhurst Church Of Nazarene",
    "wof:placetype":"venue"
},
  "geometry": {"coordinates":[-85.17623,41.035835],"type":"Point"}
}