{
  "type": "Feature",
  "properties": {
    "addr:full":"3225 S Meridian St Indianapolis IN 46217",
    "addr:housenumber":"3225",
    "addr:postcode":"46217",
    "addr:street":"S Meridian St",
    "iso:country":"US",
    "sg:address":"3225 S Meridian St",
    "sg:city":"Indianapolis",
    "sg:classifiers":[
        {
            "category":"Professional",
            "subcategory":"Business Services",
            "type":"Services"
        }
    ],
    "sg:phone":"+1 317 788 4706",
    "sg:postcode":"46217",
    "sg:province":"IN",
    "wof:name":"Brierwood Interiors",
    "wof:placetype":"venue"
},
  "geometry": {"coordinates":[-86.15860600000001,39.719093],"type":"Point"}
}