{
  "type": "Feature",
  "properties": {
    "addr:full":"302 W Washington St E114 Indianapolis IN 46204",
    "addr:housenumber":"302",
    "addr:postcode":"46204",
    "addr:street":"W Washington St",
    "iso:country":"US",
    "sg:address":"302 W Washington St E114",
    "sg:city":"Indianapolis",
    "sg:classifiers":[
        {
            "category":"Professional",
            "subcategory":"Management & Consulting",
            "type":"Services"
        },
        {
            "category":"Government",
            "subcategory":"Office",
            "type":"Public Place"
        }
    ],
    "sg:phone":"+1 317 232 2455",
    "sg:postcode":"46204",
    "sg:province":"IN",
    "sg:tags":[
        "food",
        "government-state",
        "beverage",
        "consultant"
    ],
    "wof:name":"Data Input/Bartender Permits",
    "wof:placetype":"venue"
},
  "geometry": {"coordinates":[-86.16350300000001,39.767201],"type":"Point"}
}