{
  "type": "Feature",
  "properties": {
    "iso:country":"US",
    "sg:address":"6201 W 25th Ave",
    "sg:city":"Gary",
    "sg:classifiers":[
        {
            "category":"Bars & Pubs",
            "type":"Food & Drink"
        }
    ],
    "sg:phone":"+1 219 844 1436",
    "sg:postcode":"46406",
    "sg:province":"IN",
    "wof:name":"Chip's Friendly Tap",
    "wof:placetype":"venue"
},
  "geometry": {"coordinates":[-87.41433499999999,41.573563],"type":"Point"}
}