{
  "type": "Feature",
  "properties": {
    "iso:country":"US",
    "sg:address":"4976 State Rd 32",
    "sg:city":"Chesterfield",
    "sg:classifiers":[
        {
            "category":"Retail",
            "subcategory":"Auto Repair",
            "type":"Services"
        }
    ],
    "sg:phone":"+1 765 378 0342",
    "sg:postcode":"46017",
    "sg:province":"IN",
    "sg:tags":[
        "automobile",
        "lubrication"
    ],
    "wof:name":"Q Lube",
    "wof:placetype":"venue"
},
  "geometry": {"coordinates":[-85.57884,40.114833],"type":"Point"}
}