{
  "type": "Feature",
  "properties": {
    "iso:country":"US",
    "sg:address":"607 S Parkway Dr",
    "sg:city":"Anderson",
    "sg:classifiers":[
        {
            "category":"Retail",
            "subcategory":"Laundry & Dry Cleaning",
            "type":"Services"
        }
    ],
    "sg:phone":"+1 765 649 4446",
    "sg:postcode":"46013",
    "sg:province":"IN",
    "sg:tags":[
        "cleaners",
        "rug",
        "carpet"
    ],
    "wof:name":"Talley's Carpet Cleaning",
    "wof:placetype":"venue"
},
  "geometry": {"coordinates":[-85.688495,40.078258],"type":"Point"}
}