{
  "type": "Feature",
  "properties": {
    "iso:country":"US",
    "sg:address":"200 E Washington St",
    "sg:city":"Hartford City",
    "sg:classifiers":[
        {
            "category":"Restaurant",
            "type":"Food & Drink"
        }
    ],
    "sg:phone":"+1 765 348 9965",
    "sg:postcode":"47348",
    "sg:province":"IN",
    "wof:name":"Sonny's",
    "wof:placetype":"venue"
},
  "geometry": {"coordinates":[-85.365708,40.451223],"type":"Point"}
}