{
  "type": "Feature",
  "properties": {
    "iso:country":"US",
    "sg:address":"21 Virginia Ave",
    "sg:city":"Indianapolis",
    "sg:classifiers":[
        {
            "category":"Social Services",
            "subcategory":"Job Training",
            "type":"Services"
        }
    ],
    "sg:phone":"+1 317 634 0111",
    "sg:postcode":"46204",
    "sg:province":"IN",
    "sg:tags":[
        "career",
        "counseling",
        "vocational"
    ],
    "sg:website":"www.inroads.org",
    "wof:name":"Inroads Indiana Inc",
    "wof:placetype":"venue"
},
  "geometry": {"coordinates":[-86.155548,39.766449],"type":"Point"}
}