{
  "type": "Feature",
  "properties": {
    "addr:full":"11709 W Railroad St Kewanna IN 46939",
    "addr:housenumber":"11709",
    "addr:postcode":"46939",
    "addr:street":"W Railroad St",
    "iso:country":"US",
    "sg:address":"11709 W Railroad St",
    "sg:city":"Kewanna",
    "sg:classifiers":[
        {
            "category":"Professional",
            "type":"Services"
        }
    ],
    "sg:phone":"+1 574 653 6822",
    "sg:postcode":"46939",
    "sg:province":"IN",
    "wof:name":"Donald Morning",
    "wof:placetype":"venue"
},
  "geometry": {"coordinates":[-86.464315,41.071227],"type":"Point"}
}