{
  "type": "Feature",
  "properties": {
    "iso:country":"US",
    "sg:address":"108 S Morton Ave",
    "sg:city":"Centerville",
    "sg:classifiers":[
        {
            "category":"Insurance",
            "subcategory":"Insurance Agent",
            "type":"Services"
        }
    ],
    "sg:phone":"+1 765 855 2300",
    "sg:postcode":"47330",
    "sg:province":"IN",
    "wof:name":"Turner Insurance",
    "wof:placetype":"venue"
},
  "geometry": {"coordinates":[-84.996377,39.817637],"type":"Point"}
}