{
  "type": "Feature",
  "properties": {
    "iso:country":"US",
    "sg:address":"565 N 625 W",
    "sg:city":"Winchester",
    "sg:classifiers":[
        {
            "category":"Real Estate",
            "subcategory":"Developer",
            "type":"Services"
        }
    ],
    "sg:phone":"+1 765 468 6292",
    "sg:postcode":"47394",
    "sg:province":"IN",
    "sg:tags":[
        "cemetery"
    ],
    "wof:name":"Woodlawn Cemetery",
    "wof:placetype":"venue"
},
  "geometry": {"coordinates":[-85.096277,40.171891],"type":"Point"}
}