{
  "type": "Feature",
  "properties": {
    "addr:full":"8563 S Old State Road 37 Bloomington IN 47403",
    "addr:housenumber":"8563",
    "addr:postcode":"47403",
    "addr:street":"S Old State Road 37",
    "iso:country":"US",
    "sg:address":"8563 S Old State Road 37",
    "sg:city":"Bloomington",
    "sg:classifiers":[
        {
            "category":"Retail",
            "subcategory":"Auto Repair",
            "type":"Services"
        }
    ],
    "sg:phone":"+1 812 824 9797",
    "sg:postcode":"47403",
    "sg:province":"IN",
    "sg:tags":[
        "general"
    ],
    "wof:name":"Hobbs Garage",
    "wof:placetype":"venue"
},
  "geometry": {"coordinates":[-86.54148499999999,39.033698],"type":"Point"}
}