{
  "type": "Feature",
  "properties": {
    "addr:full":"6201 W 29th Ave Gary IN 46406",
    "addr:housenumber":"6201",
    "addr:postcode":"46406",
    "addr:street":"W 29Th Ave",
    "iso:country":"US",
    "sg:address":"6201 W 29th Ave",
    "sg:city":"Gary",
    "sg:classifiers":[
        {
            "category":"Autos & Motor Vehicles",
            "subcategory":"Automobile Sales",
            "type":"Retail Goods"
        }
    ],
    "sg:phone":"+1 219 989 0579",
    "sg:postcode":"46406",
    "sg:province":"IN",
    "sg:tags":[
        "used"
    ],
    "wof:name":"Colfax Motors",
    "wof:placetype":"venue"
},
  "geometry": {"coordinates":[-87.415508,41.566334],"type":"Point"}
}