{
  "type": "Feature",
  "properties": {
    "iso:country":"US",
    "sg:address":"455 E Hospital Ln",
    "sg:city":"Terre Haute",
    "sg:classifiers":[
        {
            "category":"Health Services",
            "subcategory":"Doctor",
            "type":"Services"
        }
    ],
    "sg:phone":"+1 812 234 3278",
    "sg:postcode":"47802",
    "sg:province":"IN",
    "sg:tags":[
        "physician",
        "surgeon"
    ],
    "sg:website":"www.thheart.com",
    "wof:name":"Terre Haute Heart Ctr",
    "wof:placetype":"venue"
},
  "geometry": {"coordinates":[-87.410872,39.420142],"type":"Point"}
}