{
  "type": "Feature",
  "properties": {
    "iso:country":"US",
    "sg:address":"9075 E Orchard Ln",
    "sg:city":"Churubusco",
    "sg:classifiers":[
        {
            "category":"Building & Trades",
            "subcategory":"Plumbing",
            "type":"Services"
        }
    ],
    "sg:phone":"+1 260 693 3579",
    "sg:postcode":"46723",
    "sg:province":"IN",
    "sg:tags":[
        "contractor"
    ],
    "wof:name":"Gordon Gilbert",
    "wof:placetype":"venue"
},
  "geometry": {"coordinates":[-85.316312,41.220123],"type":"Point"}
}