{
  "type": "Feature",
  "properties": {
    "iso:country":"US",
    "sg:address":"2100 Liberty Dr",
    "sg:city":"Bloomington",
    "sg:classifiers":[
        {
            "category":"Restaurant",
            "type":"Food & Drink"
        }
    ],
    "sg:phone":"+1 812 323 8400",
    "sg:postcode":"47403",
    "sg:province":"IN",
    "wof:name":"Winterberry Cafe",
    "wof:placetype":"venue"
},
  "geometry": {"coordinates":[-86.57810600000001,39.146046],"type":"Point"}
}