{
  "type": "Feature",
  "properties": {
    "iso:country":"US",
    "sg:address":"7758 E US Hwy 30",
    "sg:city":"Pierceton",
    "sg:classifiers":[
        {
            "category":"Building & Trades",
            "subcategory":"Construction",
            "type":"Services"
        }
    ],
    "sg:phone":"+1 574 594 3137",
    "sg:postcode":"46562",
    "sg:province":"IN",
    "sg:tags":[
        "water",
        "well",
        "drilling"
    ],
    "wof:name":"Ousley Well Drilling",
    "wof:placetype":"venue"
},
  "geometry": {"coordinates":[-85.69419,41.198745],"type":"Point"}
}