{
  "type": "Feature",
  "properties": {
    "iso:country":"US",
    "sg:address":"2037 W Franklin St",
    "sg:city":"Evansville",
    "sg:classifiers":[
        {
            "category":"Bars & Pubs",
            "type":"Food & Drink"
        }
    ],
    "sg:phone":"+1 812 423 0796",
    "sg:postcode":"47712",
    "sg:province":"IN",
    "wof:name":"Hagedorn's Tavern",
    "wof:placetype":"venue"
},
  "geometry": {"coordinates":[-87.595098,37.980641],"type":"Point"}
}