{
  "type": "Feature",
  "properties": {
    "iso:country":"US",
    "sg:address":"6535 N 1150 W",
    "sg:city":"Shipshewana",
    "sg:classifiers":[
        {
            "category":"Banks & Credit Unions",
            "subcategory":"Financial Services",
            "type":"Services"
        }
    ],
    "sg:phone":"+1 574 825 1148",
    "sg:postcode":"46565",
    "sg:province":"IN",
    "sg:tags":[
        "trust",
        "investment",
        "real estate"
    ],
    "wof:name":"Cr 4 Properties Inc",
    "wof:placetype":"venue"
},
  "geometry": {"coordinates":[-85.646337,41.730333],"type":"Point"}
}