{
  "type": "Feature",
  "properties": {
    "addr:full":"1510 E Main St Richmond IN 47374",
    "addr:housenumber":"1510",
    "addr:postcode":"47374",
    "addr:street":"E Main St",
    "iso:country":"US",
    "sg:address":"1510 E Main St",
    "sg:city":"Richmond",
    "sg:classifiers":[
        {
            "category":"Personal",
            "subcategory":"Barber",
            "type":"Services"
        }
    ],
    "sg:phone":"+1 765 935 2808",
    "sg:postcode":"47374",
    "sg:province":"IN",
    "wof:name":"Main Street Barber Shop",
    "wof:placetype":"venue"
},
  "geometry": {"coordinates":[-84.880594,39.829701],"type":"Point"}
}