{
  "type": "Feature",
  "properties": {
    "iso:country":"US",
    "sg:address":"6116 Carrie Pl",
    "sg:city":"Indianapolis",
    "sg:classifiers":[
        {
            "category":"Retail",
            "subcategory":"Portrait Studio",
            "type":"Services"
        }
    ],
    "sg:phone":"+1 317 887 1996",
    "sg:postcode":"46237",
    "sg:province":"IN",
    "sg:tags":[
        "photo"
    ],
    "wof:name":"Duncan Photography",
    "wof:placetype":"venue"
},
  "geometry": {"coordinates":[-86.06042100000001,39.663993],"type":"Point"}
}