{
  "type": "Feature",
  "properties": {
    "iso:country":"US",
    "sg:address":"7487 Morton St",
    "sg:city":"Merrillville",
    "sg:classifiers":[
        {
            "category":"Freight",
            "type":"Transportation"
        }
    ],
    "sg:phone":"+1 219 736 0575",
    "sg:postcode":"46410",
    "sg:province":"IN",
    "sg:tags":[
        "operator",
        "local",
        "trucking"
    ],
    "wof:name":"Rafaels Trucking Inc",
    "wof:placetype":"venue"
},
  "geometry": {"coordinates":[-87.38845,41.481719],"type":"Point"}
}