{
  "type": "Feature",
  "properties": {
    "iso:country":"US",
    "sg:address":"3300 W Moore Rd",
    "sg:city":"Muncie",
    "sg:classifiers":[
        {
            "category":"Organizations",
            "subcategory":"Religious Organization",
            "type":"Services"
        }
    ],
    "sg:phone":"+1 765 289 8645",
    "sg:postcode":"47304",
    "sg:province":"IN",
    "wof:name":"People of Praise Muncie",
    "wof:placetype":"venue"
},
  "geometry": {"coordinates":[-85.424725,40.236902],"type":"Point"}
}