{
  "type": "Feature",
  "properties": {
    "iso:country":"US",
    "sg:address":"112 W Walnut St",
    "sg:city":"Albany",
    "sg:classifiers":[
        {
            "category":"Personal",
            "subcategory":"Beauty Salon",
            "type":"Services"
        }
    ],
    "sg:phone":"+1 765 789 8231",
    "sg:postcode":"47320",
    "sg:province":"IN",
    "sg:tags":[
        "shop"
    ],
    "wof:name":"Theresa's Hair Cottage",
    "wof:placetype":"venue"
},
  "geometry": {"coordinates":[-85.237402,40.303897],"type":"Point"}
}