{
  "type": "Feature",
  "properties": {
    "iso:country":"US",
    "sg:address":"2700 Lafayette St",
    "sg:city":"Fort Wayne",
    "sg:classifiers":[
        {
            "category":"Health Services",
            "subcategory":"Doctor",
            "type":"Services"
        }
    ],
    "sg:phone":"+1 260 744 2887",
    "sg:postcode":"46806",
    "sg:province":"IN",
    "sg:tags":[
        "physician",
        "surgeon"
    ],
    "wof:name":"Addo & Addo",
    "wof:placetype":"venue"
},
  "geometry": {"coordinates":[-85.13297799999999,41.059689],"type":"Point"}
}