{
  "type": "Feature",
  "properties": {
    "iso:country":"US",
    "sg:address":"5773 Chipmunks Run",
    "sg:city":"Indianapolis",
    "sg:classifiers":[
        {
            "category":"Social Services",
            "subcategory":"Child Care",
            "type":"Services"
        }
    ],
    "sg:phone":"+1 317 347 9107",
    "sg:postcode":"46254",
    "sg:province":"IN",
    "wof:name":"Small Miracle",
    "wof:placetype":"venue"
},
  "geometry": {"coordinates":[-86.246206,39.857356],"type":"Point"}
}