{
  "type": "Feature",
  "properties": {
    "iso:country":"US",
    "sg:address":"1439 E 85th Ave",
    "sg:city":"Merrillville",
    "sg:classifiers":[
        {
            "category":"Professional",
            "subcategory":"Business Services",
            "type":"Services"
        }
    ],
    "sg:phone":"+1 219 736 0020",
    "sg:postcode":"46410",
    "sg:province":"IN",
    "sg:tags":[
        "inventory"
    ],
    "wof:name":"RGIS Inventory Specialist",
    "wof:placetype":"venue"
},
  "geometry": {"coordinates":[-87.32076000000001,41.463208],"type":"Point"}
}