{
  "type": "Feature",
  "properties": {
    "addr:full":"2260 South Us Route 31 Greenwood IN 46143",
    "addr:housenumber":"2260",
    "addr:postcode":"46143",
    "addr:street":"South Us Route 31",
    "iso:country":"US",
    "sg:address":"2260 South Us Route 31",
    "sg:city":"Greenwood",
    "sg:classifiers":[
        {
            "category":"Restaurant",
            "type":"Food & Drink"
        }
    ],
    "sg:menulink":"http://www.allmenus.com/in/new-whiteland/69631-donatos-pizza/menu/",
    "sg:phone":"+1 317 884 3220",
    "sg:postcode":"46143",
    "sg:province":"IN",
    "sg:tags":[
        "sandwich",
        "salad",
        "soup",
        "american",
        "wrap",
        "pizza"
    ],
    "wof:name":"Donatos Pizza",
    "wof:placetype":"venue"
},
  "geometry": {"coordinates":[-86.09979199999999,39.583685],"type":"Point"}
}