{
  "type": "Feature",
  "properties": {
    "iso:country":"US",
    "sg:address":"4905 Bluffton Rd",
    "sg:city":"Fort Wayne",
    "sg:classifiers":[
        {
            "category":"Travel",
            "subcategory":"Hotels & Motels",
            "type":"Entertainment"
        }
    ],
    "sg:phone":"+1 260 747 7502",
    "sg:postcode":"46809",
    "sg:province":"IN",
    "sg:tags":[
        "operation"
    ],
    "wof:name":"Pine Haven Motel",
    "wof:placetype":"venue"
},
  "geometry": {"coordinates":[-85.166485,41.038281],"type":"Point"}
}