{
  "type": "Feature",
  "properties": {
    "addr:full":"6056 W 71st St Indianapolis IN 46278",
    "addr:housenumber":"6056",
    "addr:postcode":"46278",
    "addr:street":"W 71St St",
    "iso:country":"US",
    "sg:address":"6056 W 71st St",
    "sg:city":"Indianapolis",
    "sg:classifiers":[
        {
            "category":"Restaurant",
            "type":"Food & Drink"
        }
    ],
    "sg:menulink":"http://www.allmenus.com/in/pike/186435-mcdonalds/menu/",
    "sg:postcode":"46278",
    "sg:province":"IN",
    "sg:tags":[
        "burger",
        "american"
    ],
    "wof:name":"McDonald's",
    "wof:placetype":"venue"
},
  "geometry": {"coordinates":[-86.266172,39.882573],"type":"Point"}
}