{
  "type": "Feature",
  "properties": {
    "addr:full":"5001 N Wheeling Ave Muncie IN 47304",
    "addr:housenumber":"5001",
    "addr:postcode":"47304",
    "addr:street":"N Wheeling Ave",
    "iso:country":"US",
    "sg:address":"5001 N Wheeling Ave",
    "sg:city":"Muncie",
    "sg:classifiers":[
        {
            "category":"Professional",
            "subcategory":"Detective & Security Services",
            "type":"Services"
        }
    ],
    "sg:phone":"+1 765 286 4900",
    "sg:postcode":"47304",
    "sg:province":"IN",
    "wof:name":"Brentwood Detective Agency",
    "wof:placetype":"venue"
},
  "geometry": {"coordinates":[-85.41269200000001,40.235839],"type":"Point"}
}