{
  "type": "Feature",
  "properties": {
    "iso:country":"US",
    "sg:address":"15017 State Rd 23",
    "sg:city":"Granger",
    "sg:classifiers":[
        {
            "category":"Restaurant",
            "type":"Food & Drink"
        }
    ],
    "sg:phone":"+1 574 243 8771",
    "sg:postcode":"46530",
    "sg:province":"IN",
    "wof:name":"Yummy Pizza",
    "wof:placetype":"venue"
},
  "geometry": {"coordinates":[-86.160764,41.732297],"type":"Point"}
}