{
  "type": "Feature",
  "properties": {
    "iso:country":"US",
    "sg:address":"8702 Keystone Xing Ste 102",
    "sg:city":"Indianapolis",
    "sg:classifiers":[
        {
            "category":"Shopping",
            "subcategory":"Optician",
            "type":"Retail Goods"
        }
    ],
    "sg:phone":"+1 317 843 1484",
    "sg:postcode":"46240",
    "sg:province":"IN",
    "sg:tags":[
        "eyewear"
    ],
    "sg:website":"www2.sunglasshut.com",
    "wof:name":"Sunglass Hut International",
    "wof:placetype":"venue"
},
  "geometry": {"coordinates":[-86.111389,39.914349],"type":"Point"}
}