{
  "type": "Feature",
  "properties": {
    "iso:country":"US",
    "sg:address":"5115 S Country Club Rd",
    "sg:city":"Warsaw",
    "sg:classifiers":[
        {
            "category":"Farming",
            "subcategory":"Fish & Marine Products",
            "type":"Manufacturing & Wholesale Goods"
        }
    ],
    "sg:phone":"+1 574 267 6306",
    "sg:postcode":"46580",
    "sg:province":"IN",
    "sg:tags":[
        "management"
    ],
    "wof:name":"Ganderlanders Guide Service",
    "wof:placetype":"venue"
},
  "geometry": {"coordinates":[-85.81322,41.157537],"type":"Point"}
}