{
  "type": "Feature",
  "properties": {
    "iso:country":"US",
    "sg:address":"3210 Tempe Dr",
    "sg:city":"Indianapolis",
    "sg:classifiers":[
        {
            "category":"Retail",
            "subcategory":"Auto Repair",
            "type":"Services"
        }
    ],
    "sg:phone":"+1 317 247 1788",
    "sg:postcode":"46241",
    "sg:province":"IN",
    "sg:tags":[
        "wrecker"
    ],
    "wof:name":"Tracy Hash Wrecker Svc",
    "wof:placetype":"venue"
},
  "geometry": {"coordinates":[-86.24267999999999,39.716958],"type":"Point"}
}