{
  "type": "Feature",
  "properties": {
    "iso:country":"US",
    "sg:address":"70 W Madison St",
    "sg:city":"Franklin",
    "sg:classifiers":[
        {
            "category":"Health Services",
            "subcategory":"Doctor",
            "type":"Services"
        }
    ],
    "sg:phone":"+1 317 736 7531",
    "sg:postcode":"46131",
    "sg:province":"IN",
    "sg:tags":[
        "dentist"
    ],
    "wof:name":"George W Simpson DDS",
    "wof:placetype":"venue"
},
  "geometry": {"coordinates":[-86.05632900000001,39.481583],"type":"Point"}
}