{
  "type": "Feature",
  "properties": {
    "iso:country":"US",
    "sg:address":"1661 N Lebanon St",
    "sg:city":"Lebanon",
    "sg:classifiers":[
        {
            "category":"Professional",
            "subcategory":"Employment Agencies",
            "type":"Services"
        }
    ],
    "sg:phone":"+1 765 482 0300",
    "sg:postcode":"46052",
    "sg:province":"IN",
    "sg:tags":[
        "opportunity"
    ],
    "wof:name":"Rush Temporaries",
    "wof:placetype":"venue"
},
  "geometry": {"coordinates":[-86.471436,40.060472],"type":"Point"}
}