{
  "type": "Feature",
  "properties": {
    "iso:country":"US",
    "sg:address":"115 Waldron St",
    "sg:city":"West Lafayette",
    "sg:classifiers":[
        {
            "category":"Organizations",
            "subcategory":"Religious Organization",
            "type":"Services"
        }
    ],
    "sg:phone":"+1 765 743 0954",
    "sg:postcode":"47906",
    "sg:province":"IN",
    "sg:tags":[
        "church"
    ],
    "wof:name":"Christian Student Center",
    "wof:placetype":"venue"
},
  "geometry": {"coordinates":[-86.917995,40.426085],"type":"Point"}
}