{
  "type": "Feature",
  "properties": {
    "iso:country":"US",
    "sg:address":"5 US Hwy 150",
    "sg:city":"Fredericksburg",
    "sg:classifiers":[
        {
            "category":"Autos & Motor Vehicles",
            "subcategory":"Boat Sales",
            "type":"Retail Goods"
        }
    ],
    "sg:phone":"+1 812 472 3140",
    "sg:postcode":"47120",
    "sg:province":"IN",
    "sg:tags":[
        "canoe"
    ],
    "wof:name":"Old Mill Canoe Rental",
    "wof:placetype":"venue"
},
  "geometry": {"coordinates":[-86.191603,38.433789],"type":"Point"}
}