{
  "type": "Feature",
  "properties": {
    "iso:country":"US",
    "sg:address":"524 W Franklin St",
    "sg:city":"Berne",
    "sg:classifiers":[
        {
            "category":"Food & Beverages",
            "subcategory":"Meat & Fish",
            "type":"Retail Goods"
        }
    ],
    "sg:phone":"+1 260 589 2806",
    "sg:postcode":"46711",
    "sg:province":"IN",
    "wof:name":"Berne Locker Storage",
    "wof:placetype":"venue"
},
  "geometry": {"coordinates":[-84.95507,40.656727],"type":"Point"}
}