{
  "type": "Feature",
  "properties": {
    "iso:country":"US",
    "sg:address":"9301 W Windsor Rd",
    "sg:city":"Farmland",
    "sg:phone":"+1 765 468 8110",
    "sg:postcode":"47340",
    "sg:province":"IN",
    "sg:tags":[
        "farm",
        "corn",
        "soybean"
    ],
    "wof:name":"Darren Lacey",
    "wof:placetype":"venue"
},
  "geometry": {"coordinates":[-85.15251600000001,40.165045],"type":"Point"}
}