{
  "type": "Feature",
  "properties": {
    "iso:country":"US",
    "sg:address":"1000 S Kitley Ave",
    "sg:city":"Indianapolis",
    "sg:classifiers":[
        {
            "category":"Wholesale",
            "subcategory":"Auto Parts",
            "type":"Manufacturing & Wholesale Goods"
        }
    ],
    "sg:phone":"+1 317 352 1681",
    "sg:postcode":"46203",
    "sg:province":"IN",
    "sg:tags":[
        "automobile",
        "rebuilt"
    ],
    "wof:name":"Brothers Auto Salvage",
    "wof:placetype":"venue"
},
  "geometry": {"coordinates":[-86.054458,39.752187],"type":"Point"}
}