{
  "type": "Feature",
  "properties": {
    "iso:country":"US",
    "sg:address":"1849 Blore Heath",
    "sg:city":"Carmel",
    "sg:classifiers":[
        {
            "category":"Banks & Credit Unions",
            "subcategory":"Bank",
            "type":"Services"
        }
    ],
    "sg:phone":"+1 317 569 0406",
    "sg:postcode":"46032",
    "sg:province":"IN",
    "sg:tags":[
        "financing"
    ],
    "wof:name":"Arlin Mortgage",
    "wof:placetype":"venue"
},
  "geometry": {"coordinates":[-86.189303,39.970808],"type":"Point"}
}