{
  "type": "Feature",
  "properties": {
    "iso:country":"US",
    "sg:address":"36 W 2nd St",
    "sg:city":"Peru",
    "sg:classifiers":[
        {
            "category":"Education",
            "subcategory":"Library",
            "type":"Public Place"
        }
    ],
    "sg:phone":"+1 765 473 9095",
    "sg:postcode":"46970",
    "sg:province":"IN",
    "wof:name":"Our Fathers Library",
    "wof:placetype":"venue"
},
  "geometry": {"coordinates":[-86.068685,40.751588],"type":"Point"}
}