{
  "type": "Feature",
  "properties": {
    "iso:country":"US",
    "sg:address":"9125 Maple Dr",
    "sg:city":"St John",
    "sg:classifiers":[
        {
            "category":"Professional",
            "type":"Services"
        }
    ],
    "sg:phone":"+1 219 365 5285",
    "sg:postcode":"46373",
    "sg:province":"IN",
    "sg:tags":[
        "establishment"
    ],
    "wof:name":"Mikron US Corp Monroe",
    "wof:placetype":"venue"
},
  "geometry": {"coordinates":[-87.506433,41.451558],"type":"Point"}
}