{
  "type": "Feature",
  "properties": {
    "addr:full":"305 Gilliam Dr S Warsaw IN 46580",
    "addr:housenumber":"305",
    "addr:postcode":"46580",
    "addr:street":"Gilliam Dr S",
    "iso:country":"US",
    "sg:address":"305 Gilliam Dr S",
    "sg:city":"Warsaw",
    "sg:classifiers":[
        {
            "category":"Home & Garden",
            "subcategory":"Building Materials",
            "type":"Retail Goods"
        }
    ],
    "sg:phone":"+1 574 269 1774",
    "sg:postcode":"46580",
    "sg:province":"IN",
    "wof:name":"Artistic Glass Works Inc",
    "wof:placetype":"venue"
},
  "geometry": {"coordinates":[-85.85949599999999,41.251655],"type":"Point"}
}