{
  "type": "Feature",
  "properties": {
    "addr:full":"123 S Vine St Fairmount IN 46928",
    "addr:housenumber":"123",
    "addr:postcode":"46928",
    "addr:street":"S Vine St",
    "iso:country":"US",
    "sg:address":"123 S Vine St",
    "sg:city":"Fairmount",
    "sg:classifiers":[
        {
            "category":"Real Estate",
            "subcategory":"Real Estate Agent",
            "type":"Services"
        }
    ],
    "sg:phone":"+1 765 948 5800",
    "sg:postcode":"46928",
    "sg:province":"IN",
    "wof:name":"Historic Properties",
    "wof:placetype":"venue"
},
  "geometry": {"coordinates":[-85.64715700000001,40.415402],"type":"Point"}
}