{
  "type": "Feature",
  "properties": {
    "iso:country":"US",
    "sg:address":"3383 Kentucky Ave",
    "sg:city":"Indianapolis",
    "sg:classifiers":[
        {
            "category":"Restaurant",
            "type":"Food & Drink"
        }
    ],
    "sg:phone":"+1 317 227 0889",
    "sg:postcode":"46221",
    "sg:province":"IN",
    "wof:name":"Super China Buffet",
    "wof:placetype":"venue"
},
  "geometry": {"coordinates":[-86.237702,39.714567],"type":"Point"}
}