{
  "type": "Feature",
  "properties": {
    "iso:country":"US",
    "sg:address":"4854 W 24th St",
    "sg:city":"Indianapolis",
    "sg:classifiers":[
        {
            "category":"Real Estate",
            "subcategory":"Real Estate Agent",
            "type":"Services"
        }
    ],
    "sg:phone":"+1 317 243 8613",
    "sg:postcode":"46224",
    "sg:province":"IN",
    "wof:name":"Templin Real Estate Appraisals",
    "wof:placetype":"venue"
},
  "geometry": {"coordinates":[-86.241102,39.800823],"type":"Point"}
}