{
  "type": "Feature",
  "properties": {
    "iso:country":"US",
    "sg:address":"4622 Independence Sq",
    "sg:city":"Indianapolis",
    "sg:classifiers":[
        {
            "category":"Wholesale",
            "subcategory":"Machinery & Supplies",
            "type":"Manufacturing & Wholesale Goods"
        }
    ],
    "sg:phone":"+1 317 791 8290",
    "sg:postcode":"46203",
    "sg:province":"IN",
    "wof:name":"Modern Machinery Co",
    "wof:placetype":"venue"
},
  "geometry": {"coordinates":[-86.07798699999999,39.701304],"type":"Point"}
}