{
  "type": "Feature",
  "properties": {
    "iso:country":"US",
    "sg:address":"5155 W 106th St",
    "sg:city":"Zionsville",
    "sg:classifiers":[
        {
            "category":"Building & Trades",
            "subcategory":"Landscaping Services",
            "type":"Services"
        }
    ],
    "sg:phone":"+1 317 873 5886",
    "sg:postcode":"46077",
    "sg:province":"IN",
    "sg:tags":[
        "landscape",
        "contractor"
    ],
    "wof:name":"Landscapes Unlimited",
    "wof:placetype":"venue"
},
  "geometry": {"coordinates":[-86.243708,39.94064],"type":"Point"}
}