{
  "type": "Feature",
  "properties": {
    "iso:country":"US",
    "sg:address":"3865 Lake City Hwy",
    "sg:city":"Warsaw",
    "sg:classifiers":[
        {
            "category":"Restaurant",
            "type":"Food & Drink"
        }
    ],
    "sg:phone":"+1 574 269 9088",
    "sg:postcode":"46580",
    "sg:province":"IN",
    "wof:name":"China Buffet",
    "wof:placetype":"venue"
},
  "geometry": {"coordinates":[-85.795383,41.226635],"type":"Point"}
}