{
  "type": "Feature",
  "properties": {
    "iso:country":"US",
    "sg:address":"1504 Chestnut St",
    "sg:city":"Mishawaka",
    "sg:classifiers":[
        {
            "category":"Sports & Exercise",
            "subcategory":"Bowling",
            "type":"Entertainment"
        }
    ],
    "sg:phone":"+1 574 255 5424",
    "sg:postcode":"46545",
    "sg:province":"IN",
    "sg:tags":[
        "center"
    ],
    "wof:name":"Parkway Lanes East",
    "wof:placetype":"venue"
},
  "geometry": {"coordinates":[-86.17444,41.673568],"type":"Point"}
}