{
  "type": "Feature",
  "properties": {
    "iso:country":"US",
    "sg:address":"306 S Washington St",
    "sg:city":"Bloomington",
    "sg:classifiers":[
        {
            "category":"Wholesale",
            "subcategory":"Non-durable Goods",
            "type":"Manufacturing & Wholesale Goods"
        }
    ],
    "sg:phone":"+1 812 334 1646",
    "sg:postcode":"47401",
    "sg:province":"IN",
    "sg:tags":[
        "advertising"
    ],
    "wof:name":"Roberts Advertising",
    "wof:placetype":"venue"
},
  "geometry": {"coordinates":[-86.532462,39.162938],"type":"Point"}
}