{
  "type": "Feature",
  "properties": {
    "iso:country":"US",
    "sg:address":"805 Beachway Dr Ste 50",
    "sg:city":"Indianapolis",
    "sg:classifiers":[
        {
            "category":"Professional",
            "subcategory":"Business Services",
            "type":"Services"
        }
    ],
    "sg:phone":"+1 317 227 0300",
    "sg:postcode":"46224",
    "sg:province":"IN",
    "sg:tags":[
        "medical",
        "administration"
    ],
    "sg:website":"http://www.indianachildsupportadoptionlawyertonyzirkl",
    "wof:name":"Legal Affairs/Licensing",
    "wof:placetype":"venue"
},
  "geometry": {"coordinates":[-86.269042,39.777699],"type":"Point"}
}