{
  "type": "Feature",
  "properties": {
    "iso:country":"US",
    "sg:address":"55900 Bittersweet Rd",
    "sg:city":"Mishawaka",
    "sg:classifiers":[
        {
            "category":"Education",
            "subcategory":"Special Training",
            "type":"Public Place"
        }
    ],
    "sg:phone":"+1 574 254 1562",
    "sg:postcode":"46545",
    "sg:province":"IN",
    "sg:tags":[
        "educational"
    ],
    "wof:name":"Penn Harris Educational Svc",
    "wof:placetype":"venue"
},
  "geometry": {"coordinates":[-86.109592,41.682839],"type":"Point"}
}