{
  "type": "Feature",
  "properties": {
    "iso:country":"US",
    "sg:address":"7111 W Washington St",
    "sg:city":"Indianapolis",
    "sg:classifiers":[
        {
            "category":"Retail",
            "subcategory":"Auto Rental",
            "type":"Services"
        }
    ],
    "sg:phone":"+1 317 243 1166",
    "sg:postcode":"46241",
    "sg:province":"IN",
    "sg:tags":[
        "automobile",
        "leasing"
    ],
    "wof:name":"Execucar Leasing",
    "wof:placetype":"venue"
},
  "geometry": {"coordinates":[-86.286402,39.741641],"type":"Point"}
}