{
  "type": "Feature",
  "properties": {
    "iso:country":"US",
    "sg:address":"2912 Getz Rd",
    "sg:city":"Fort Wayne",
    "sg:classifiers":[
        {
            "category":"Restaurant",
            "type":"Food & Drink"
        }
    ],
    "sg:phone":"+1 260 432 0913",
    "sg:postcode":"46804",
    "sg:province":"IN",
    "wof:name":"Richards Family Restaurant",
    "wof:placetype":"venue"
},
  "geometry": {"coordinates":[-85.219385,41.057707],"type":"Point"}
}