{
  "type": "Feature",
  "properties": {
    "iso:country":"US",
    "sg:address":"1850 E 800 S",
    "sg:city":"La Fontaine",
    "sg:classifiers":[
        {
            "category":"Food & Beverages",
            "subcategory":"Dairy",
            "type":"Retail Goods"
        }
    ],
    "sg:phone":"+1 765 981 1466",
    "sg:postcode":"46940",
    "sg:province":"IN",
    "sg:tags":[
        "product"
    ],
    "wof:name":"New Szhoonebeea Dairy",
    "wof:placetype":"venue"
},
  "geometry": {"coordinates":[-85.757799,40.710223],"type":"Point"}
}