{
  "type": "Feature",
  "properties": {
    "iso:country":"US",
    "sg:address":"1634 Kendall St",
    "sg:city":"South Bend",
    "sg:classifiers":[
        {
            "category":"Organizations",
            "subcategory":"Religious Organization",
            "type":"Services"
        }
    ],
    "sg:phone":"+1 574 232 8579",
    "sg:postcode":"46613",
    "sg:province":"IN",
    "sg:tags":[
        "church"
    ],
    "wof:name":"Nueva Jerusalem",
    "wof:placetype":"venue"
},
  "geometry": {"coordinates":[-86.25998800000001,41.657755],"type":"Point"}
}