{
  "type": "Feature",
  "properties": {
    "iso:country":"US",
    "sg:address":"6415 Kennedy Ave",
    "sg:city":"Hammond",
    "sg:classifiers":[
        {
            "category":"Professional",
            "subcategory":"Advertising",
            "type":"Services"
        }
    ],
    "sg:phone":"+1 219 844 6156",
    "sg:postcode":"46323",
    "sg:province":"IN",
    "sg:tags":[
        "mail"
    ],
    "wof:name":"Labor Management Cooperative",
    "wof:placetype":"venue"
},
  "geometry": {"coordinates":[-87.46153099999999,41.596974],"type":"Point"}
}