{
  "type": "Feature",
  "properties": {
    "iso:country":"US",
    "sg:address":"1836 S Calhoun St",
    "sg:city":"Fort Wayne",
    "sg:classifiers":[
        {
            "category":"Shopping",
            "subcategory":"Clothing, Apparel, & Fashions",
            "type":"Retail Goods"
        }
    ],
    "sg:phone":"+1 260 745 5156",
    "sg:postcode":"46802",
    "sg:province":"IN",
    "sg:tags":[
        "western"
    ],
    "wof:name":"Los Tres Hermanos",
    "wof:placetype":"venue"
},
  "geometry": {"coordinates":[-85.13827999999999,41.069505],"type":"Point"}
}