{
  "type": "Feature",
  "properties": {
    "iso:country":"US",
    "sg:address":"6102 S Lincoln Blvd",
    "sg:city":"Marion",
    "sg:classifiers":[
        {
            "category":"Utilities",
            "subcategory":"Refuse",
            "type":"Services"
        }
    ],
    "sg:phone":"+1 765 674 9101",
    "sg:postcode":"46953",
    "sg:province":"IN",
    "sg:tags":[
        "garbage",
        "collection"
    ],
    "wof:name":"A & A Disposal",
    "wof:placetype":"venue"
},
  "geometry": {"coordinates":[-85.62717499999999,40.493679],"type":"Point"}
}