{
  "type": "Feature",
  "properties": {
    "iso:country":"US",
    "sg:address":"220 N Main St",
    "sg:city":"Linden",
    "sg:classifiers":[
        {
            "category":"Professional",
            "subcategory":"Lawyer & Legal Services",
            "type":"Services"
        }
    ],
    "sg:phone":"+1 765 362 2640",
    "sg:postcode":"47955",
    "sg:province":"IN",
    "sg:tags":[
        "attorney"
    ],
    "sg:website":"www.wralaw.com",
    "wof:name":"Wernle Ristine & Ayers",
    "wof:placetype":"venue"
},
  "geometry": {"coordinates":[-86.903932,40.18821],"type":"Point"}
}