{
  "type": "Feature",
  "properties": {
    "iso:country":"US",
    "sg:address":"2834 Nichol Ave",
    "sg:city":"Anderson",
    "sg:classifiers":[
        {
            "category":"Retail",
            "subcategory":"Auto Repair",
            "type":"Services"
        }
    ],
    "sg:phone":"+1 765 644 6544",
    "sg:postcode":"46011",
    "sg:province":"IN",
    "sg:tags":[
        "automobile",
        "lubrication"
    ],
    "wof:name":"Dave's Express Lube Inc",
    "wof:placetype":"venue"
},
  "geometry": {"coordinates":[-85.727446,40.101568],"type":"Point"}
}