{
  "type": "Feature",
  "properties": {
    "iso:country":"US",
    "sg:address":"940 N 13th St",
    "sg:city":"Decatur",
    "sg:classifiers":[
        {
            "category":"Professional",
            "type":"Services"
        }
    ],
    "sg:phone":"+1 260 728 9300",
    "sg:postcode":"46733",
    "sg:province":"IN",
    "sg:tags":[
        "establishment"
    ],
    "wof:name":"A Little Bit Of Everything",
    "wof:placetype":"venue"
},
  "geometry": {"coordinates":[-84.93766599999999,40.839108],"type":"Point"}
}