{
  "type": "Feature",
  "properties": {
    "addr:full":"2703 Brouse Ave Indianapolis IN 46218",
    "addr:housenumber":"2703",
    "addr:postcode":"46218",
    "addr:street":"Brouse Ave",
    "iso:country":"US",
    "sg:address":"2703 Brouse Ave",
    "sg:city":"Indianapolis",
    "sg:classifiers":[
        {
            "category":"Shopping",
            "subcategory":"Tobacco",
            "type":"Retail Goods"
        }
    ],
    "sg:phone":"+1 317 925 0787",
    "sg:postcode":"46218",
    "sg:province":"IN",
    "sg:tags":[
        "cigarette",
        "cigar"
    ],
    "wof:name":"Chas Tinder Rev",
    "wof:placetype":"venue"
},
  "geometry": {"coordinates":[-86.122749,39.805286],"type":"Point"}
}