{
  "type": "Feature",
  "properties": {
    "addr:full":"1091 Conner St Noblesville IN 46060",
    "addr:housenumber":"1091",
    "addr:postcode":"46060",
    "addr:street":"Conner St",
    "iso:country":"US",
    "sg:address":"1091 Conner St",
    "sg:city":"Noblesville",
    "sg:classifiers":[
        {
            "category":"Personal",
            "subcategory":"Beauty Salon",
            "type":"Services"
        }
    ],
    "sg:phone":"+1 317 774 9961",
    "sg:postcode":"46060",
    "sg:province":"IN",
    "wof:name":"Majestic Designs & Gifts",
    "wof:placetype":"venue"
},
  "geometry": {"coordinates":[-86.011213,40.045525],"type":"Point"}
}