{
  "type": "Feature",
  "properties": {
    "iso:country":"US",
    "sg:address":"3404 Grand Blvd",
    "sg:city":"Highland",
    "sg:classifiers":[
        {
            "category":"Wholesale",
            "subcategory":"Books, Periodicals, & Newspapers",
            "type":"Manufacturing & Wholesale Goods"
        }
    ],
    "sg:phone":"+1 219 972 2184",
    "sg:postcode":"46322",
    "sg:province":"IN",
    "sg:tags":[
        "publisher",
        "book"
    ],
    "wof:name":"M M Publishers",
    "wof:placetype":"venue"
},
  "geometry": {"coordinates":[-87.44696,41.56282],"type":"Point"}
}