{
  "type": "Feature",
  "properties": {
    "iso:country":"US",
    "sg:address":"57655 Pear Rd",
    "sg:city":"South Bend",
    "sg:classifiers":[
        {
            "category":"Building & Trades",
            "subcategory":"Electrical",
            "type":"Services"
        }
    ],
    "sg:phone":"+1 574 289 8086",
    "sg:postcode":"46619",
    "sg:province":"IN",
    "sg:tags":[
        "electrical",
        "contractor"
    ],
    "wof:name":"Eme Electric",
    "wof:placetype":"venue"
},
  "geometry": {"coordinates":[-86.385319,41.650772],"type":"Point"}
}