{
  "type": "Feature",
  "properties": {
    "iso:country":"US",
    "sg:address":"21330 Partridge Run",
    "sg:city":"Woodburn",
    "sg:classifiers":[
        {
            "category":"Building & Trades",
            "subcategory":"Construction",
            "type":"Services"
        }
    ],
    "sg:phone":"+1 260 632 1345",
    "sg:postcode":"46797",
    "sg:province":"IN",
    "sg:tags":[
        "hanging",
        "contractor"
    ],
    "wof:name":"Saul Meraz & Decorating",
    "wof:placetype":"venue"
},
  "geometry": {"coordinates":[-84.864265,41.123241],"type":"Point"}
}