{
  "type": "Feature",
  "properties": {
    "iso:country":"US",
    "sg:address":"2312 Shadowbrook Dr",
    "sg:city":"Plainfield",
    "sg:classifiers":[
        {
            "category":"Professional",
            "subcategory":"Lawyer & Legal Services",
            "type":"Services"
        }
    ],
    "sg:phone":"+1 317 837 7097",
    "sg:postcode":"46168",
    "sg:province":"IN",
    "sg:tags":[
        "attorney"
    ],
    "wof:name":"Bryant & Bruns Law Ofc",
    "wof:placetype":"venue"
},
  "geometry": {"coordinates":[-86.357484,39.729409],"type":"Point"}
}