{
  "type": "Feature",
  "properties": {
    "iso:country":"US",
    "sg:address":"302 Harrison St",
    "sg:city":"Liberty",
    "sg:classifiers":[
        {
            "category":"Social Services",
            "type":"Services"
        }
    ],
    "sg:phone":"+1 765 458 5819",
    "sg:postcode":"47353",
    "sg:province":"IN",
    "sg:tags":[
        "care",
        "center",
        "day"
    ],
    "wof:name":"Friendship Place Adult Day Svc",
    "wof:placetype":"venue"
},
  "geometry": {"coordinates":[-84.933225,39.63185],"type":"Point"}
}