{
  "type": "Feature",
  "properties": {
    "iso:country":"US",
    "sg:address":"330 New Albany Plz",
    "sg:city":"New Albany",
    "sg:classifiers":[
        {
            "category":"Building & Trades",
            "subcategory":"Equipment Rental",
            "type":"Services"
        }
    ],
    "sg:phone":"+1 812 949 1300",
    "sg:postcode":"47150",
    "sg:province":"IN",
    "sg:tags":[
        "leasing",
        "furniture"
    ],
    "wof:name":"Rent Way",
    "wof:placetype":"venue"
},
  "geometry": {"coordinates":[-85.84146,38.307143],"type":"Point"}
}