{
  "type": "Feature",
  "properties": {
    "iso:country":"US",
    "sg:address":"10930 Trentman Rd",
    "sg:city":"Fort Wayne",
    "sg:classifiers":[
        {
            "category":"Building & Trades",
            "subcategory":"Plumbing",
            "type":"Services"
        }
    ],
    "sg:phone":"+1 260 639 3024",
    "sg:postcode":"46816",
    "sg:province":"IN",
    "sg:tags":[
        "heating",
        "contractor"
    ],
    "wof:name":"Binkley Sales & Svc",
    "wof:placetype":"venue"
},
  "geometry": {"coordinates":[-85.075749,40.989715],"type":"Point"}
}