{
  "type": "Feature",
  "properties": {
    "iso:country":"US",
    "sg:address":"631 E Walnut St",
    "sg:city":"Evansville",
    "sg:classifiers":[
        {
            "category":"Restaurant",
            "type":"Food & Drink"
        }
    ],
    "sg:menulink":"http://www.allmenus.com/in/pigeon/120246-subway/menu/",
    "sg:phone":"+1 812 425 7585",
    "sg:postcode":"47713",
    "sg:province":"IN",
    "sg:tags":[
        "american",
        "sandwich"
    ],
    "wof:name":"Subway",
    "wof:placetype":"venue"
},
  "geometry": {"coordinates":[-87.555425,37.973394],"type":"Point"}
}