{
  "type": "Feature",
  "properties": {
    "addr:full":"10200 Wicker Ave Ste 2 Saint John IN 46373",
    "addr:housenumber":"10200",
    "addr:postcode":"46373",
    "addr:street":"Wicker Ave Ste 2",
    "iso:country":"US",
    "sg:address":"10200 Wicker Ave Ste 2",
    "sg:city":"Saint John",
    "sg:classifiers":[
        {
            "category":"Health Services",
            "subcategory":"Doctor",
            "type":"Services"
        }
    ],
    "sg:phone":"+1 219 365 0970",
    "sg:postcode":"46373",
    "sg:province":"IN",
    "sg:tags":[
        "medicine",
        "internal"
    ],
    "sg:website":"www.medspecindiana.com",
    "wof:name":"Adlard John M MD",
    "wof:placetype":"venue"
},
  "geometry": {"coordinates":[-87.469902,41.432701],"type":"Point"}
}