{
  "type": "Feature",
  "properties": {
    "iso:country":"US",
    "sg:address":"3200 Sycamore Ct",
    "sg:city":"Columbus",
    "sg:classifiers":[
        {
            "category":"Professional",
            "subcategory":"Engineering",
            "type":"Services"
        }
    ],
    "sg:phone":"+1 812 372 9511",
    "sg:postcode":"47203",
    "sg:province":"IN",
    "sg:tags":[
        "engineer"
    ],
    "wof:name":"Regional Services Corp",
    "wof:placetype":"venue"
},
  "geometry": {"coordinates":[-85.919453,39.232382],"type":"Point"}
}