{
  "type": "Feature",
  "properties": {
    "iso:country":"US",
    "sg:address":"516 E 86th Ave",
    "sg:city":"Merrillville",
    "sg:classifiers":[
        {
            "category":"Wholesale",
            "subcategory":"Durable Goods & Equipment",
            "type":"Manufacturing & Wholesale Goods"
        }
    ],
    "sg:phone":"+1 219 769 0605",
    "sg:postcode":"46410",
    "sg:province":"IN",
    "sg:tags":[
        "representative",
        "manufacturer"
    ],
    "wof:name":"ABSCO",
    "wof:placetype":"venue"
},
  "geometry": {"coordinates":[-87.326729,41.462849],"type":"Point"}
}