{
  "type": "Feature",
  "properties": {
    "addr:full":"5310 Coldwater Rd Fort Wayne IN 46825",
    "addr:housenumber":"5310",
    "addr:postcode":"46825",
    "addr:street":"Coldwater Rd",
    "iso:country":"US",
    "sg:address":"5310 Coldwater Rd",
    "sg:city":"Fort Wayne",
    "sg:classifiers":[
        {
            "category":"Shopping",
            "subcategory":"Musical Instruments",
            "type":"Retail Goods"
        }
    ],
    "sg:phone":"+1 260 482 3737",
    "sg:postcode":"46825",
    "sg:province":"IN",
    "sg:tags":[
        "piano"
    ],
    "sg:website":"www.fredmyers.com",
    "wof:name":"Fred Myers Pianos Organs Clock",
    "wof:placetype":"venue"
},
  "geometry": {"coordinates":[-85.135648,41.127425],"type":"Point"}
}