{
  "type": "Feature",
  "properties": {
    "addr:full":"920 Adams St Gary IN 46402",
    "addr:housenumber":"920",
    "addr:postcode":"46402",
    "addr:street":"Adams St Gary",
    "iso:country":"US",
    "sg:address":"920 Adams St",
    "sg:city":"Gary",
    "sg:classifiers":[
        {
            "category":"Retail",
            "subcategory":"Laundry & Dry Cleaning",
            "type":"Services"
        }
    ],
    "sg:phone":"+1 219 883 8513",
    "sg:postcode":"46402",
    "sg:province":"IN",
    "sg:tags":[
        "cleaners"
    ],
    "wof:name":"Peacock Cleaners",
    "wof:placetype":"venue"
},
  "geometry": {"coordinates":[-87.338368,41.593531],"type":"Point"}
}