{
  "type": "Feature",
  "properties": {
    "addr:full":"65 Dunn Ct Trafalgar IN 46181",
    "addr:housenumber":"65",
    "addr:postcode":"46181",
    "addr:street":"Dunn Ct",
    "iso:country":"US",
    "sg:address":"65 Dunn Ct",
    "sg:city":"Trafalgar",
    "sg:classifiers":[
        {
            "category":"Shopping",
            "subcategory":"Musical Instruments",
            "type":"Retail Goods"
        }
    ],
    "sg:phone":"+1 317 878 9131",
    "sg:postcode":"46181",
    "sg:province":"IN",
    "wof:name":"Guitar Tone",
    "wof:placetype":"venue"
},
  "geometry": {"coordinates":[-86.160099,39.419665],"type":"Point"}
}