{
  "type": "Feature",
  "properties": {
    "addr:full":"4972 Deer Ridge Dr S Carmel IN 46033",
    "addr:housenumber":"4972",
    "addr:postcode":"46033",
    "addr:street":"Deer Ridge Dr S",
    "iso:country":"US",
    "sg:address":"4972 Deer Ridge Dr S",
    "sg:city":"Carmel",
    "sg:classifiers":[
        {
            "category":"Education",
            "subcategory":"Special Training",
            "type":"Public Place"
        }
    ],
    "sg:phone":"+1 317 844 1438",
    "sg:postcode":"46033",
    "sg:province":"IN",
    "sg:tags":[
        "management"
    ],
    "wof:name":"Management Development Inc",
    "wof:placetype":"venue"
},
  "geometry": {"coordinates":[-86.083423,39.990053],"type":"Point"}
}