{
  "type": "Feature",
  "properties": {
    "iso:country":"US",
    "sg:address":"2000 N Illinois St",
    "sg:city":"Indianapolis",
    "sg:classifiers":[
        {
            "category":"Retail",
            "subcategory":"Photofinishing",
            "type":"Services"
        }
    ],
    "sg:phone":"+1 317 236 1747",
    "sg:postcode":"46202",
    "sg:province":"IN",
    "sg:tags":[
        "photo",
        "finishing"
    ],
    "sg:website":"www.fire-house.net",
    "wof:name":"Firehouse Image Ctr",
    "wof:placetype":"venue"
},
  "geometry": {"coordinates":[-86.159148,39.794996],"type":"Point"}
}