{
  "type": "Feature",
  "properties": {
    "iso:country":"US",
    "sg:address":"406 Ruddell Dr",
    "sg:city":"Kokomo",
    "sg:classifiers":[
        {
            "category":"Professional",
            "type":"Services"
        }
    ],
    "sg:phone":"+1 765 457 5641",
    "sg:postcode":"46901",
    "sg:province":"IN",
    "wof:name":"Kistler & Kistler Corp",
    "wof:placetype":"venue"
},
  "geometry": {"coordinates":[-86.15105800000001,40.489248],"type":"Point"}
}