{
  "type": "Feature",
  "properties": {
    "iso:country":"US",
    "sg:address":"308 Perry St",
    "sg:city":"Laporte",
    "sg:classifiers":[
        {
            "category":"Wholesale",
            "subcategory":"Beer",
            "type":"Manufacturing & Wholesale Goods"
        }
    ],
    "sg:phone":"+1 219 362 7623",
    "sg:postcode":"46350",
    "sg:province":"IN",
    "sg:tags":[
        "ale"
    ],
    "sg:website":"www.backroadbrewery.com",
    "wof:name":"Back Road Brewery",
    "wof:placetype":"venue"
},
  "geometry": {"coordinates":[-86.727015,41.612332],"type":"Point"}
}