{
  "type": "Feature",
  "properties": {
    "iso:country":"US",
    "sg:address":"9832 S 375 W",
    "sg:city":"Huntingburg",
    "sg:classifiers":[
        {
            "category":"Building & Trades",
            "subcategory":"Construction",
            "type":"Services"
        }
    ],
    "sg:phone":"+1 812 683 5809",
    "sg:postcode":"47542",
    "sg:province":"IN",
    "sg:tags":[
        "home",
        "builder"
    ],
    "wof:name":"Markwood Inc",
    "wof:placetype":"venue"
},
  "geometry": {"coordinates":[-86.974789,38.234058],"type":"Point"}
}