{
  "type": "Feature",
  "properties": {
    "addr:full":"700 Broadway Fort Wayne IN 46802",
    "addr:housenumber":"700",
    "addr:postcode":"46802",
    "addr:street":"Broadway",
    "iso:country":"US",
    "sg:address":"700 Broadway",
    "sg:city":"Fort Wayne",
    "sg:classifiers":[
        {
            "category":"Health Services",
            "subcategory":"Doctor",
            "type":"Services"
        }
    ],
    "sg:phone":"+1 260 425 3555",
    "sg:postcode":"46802",
    "sg:province":"IN",
    "sg:tags":[
        "physician",
        "surgeon"
    ],
    "wof:name":"St Joseph Hospital Wound Care",
    "wof:placetype":"venue"
},
  "geometry": {"coordinates":[-85.14860299999999,41.077892],"type":"Point"}
}