{
  "type": "Feature",
  "properties": {
    "iso:country":"US",
    "sg:address":"225 W Washington St",
    "sg:city":"Bluffton",
    "sg:classifiers":[
        {
            "category":"Health Services",
            "subcategory":"Hospital",
            "type":"Services"
        },
        {
            "category":"Health Services",
            "subcategory":"Clinic",
            "type":"Services"
        }
    ],
    "sg:phone":"+1 260 824 1514",
    "sg:postcode":"46714",
    "sg:province":"IN",
    "sg:tags":[
        "mental",
        "outpatient",
        "specialty"
    ],
    "wof:name":"Mental Health Assoc Wells C",
    "wof:placetype":"venue"
},
  "geometry": {"coordinates":[-85.173767,40.738789],"type":"Point"}
}