{
  "type": "Feature",
  "properties": {
    "iso:country":"US",
    "sg:address":"601 N Carroll Ave",
    "sg:city":"Michigan City",
    "sg:classifiers":[
        {
            "category":"Manufacturing",
            "subcategory":"Pottery",
            "type":"Manufacturing & Wholesale Goods"
        }
    ],
    "sg:phone":"+1 219 874 6447",
    "sg:postcode":"46360",
    "sg:province":"IN",
    "sg:tags":[
        "article",
        "fine",
        "earthenware"
    ],
    "sg:website":"www.bromwellhousewares.com",
    "wof:name":"Bromwell Housewares Inc",
    "wof:placetype":"venue"
},
  "geometry": {"coordinates":[-86.86982500000001,41.715558],"type":"Point"}
}