{
  "type": "Feature",
  "properties": {
    "iso:country":"US",
    "sg:address":"1832 S Calhoun St",
    "sg:city":"Fort Wayne",
    "sg:classifiers":[
        {
            "category":"Shopping",
            "subcategory":"Clothing, Apparel, & Fashions",
            "type":"Retail Goods"
        }
    ],
    "sg:phone":"+1 260 456 5025",
    "sg:postcode":"46802",
    "sg:province":"IN",
    "sg:tags":[
        "alteration"
    ],
    "wof:name":"Bangkok Alterations",
    "wof:placetype":"venue"
},
  "geometry": {"coordinates":[-85.138279,41.069483],"type":"Point"}
}