{
  "type": "Feature",
  "properties": {
    "addr:full":"9876 E Baseline Rd Avilla IN 46710",
    "addr:housenumber":"9876",
    "addr:postcode":"46710",
    "addr:street":"E Baseline Rd",
    "iso:country":"US",
    "sg:address":"9876 E Baseline Rd",
    "sg:city":"Avilla",
    "sg:classifiers":[
        {
            "category":"Retail",
            "subcategory":"Auto Repair",
            "type":"Services"
        }
    ],
    "sg:phone":"+1 260 897 3560",
    "sg:postcode":"46710",
    "sg:province":"IN",
    "sg:tags":[
        "body",
        "automobile",
        "painting"
    ],
    "wof:name":"Private Painter & Body Shop",
    "wof:placetype":"venue"
},
  "geometry": {"coordinates":[-85.214084,41.351089],"type":"Point"}
}