{
  "type": "Feature",
  "properties": {
    "iso:country":"US",
    "sg:address":"3604 Newberry Rd",
    "sg:city":"Plainfield",
    "sg:classifiers":[
        {
            "category":"Shopping",
            "subcategory":"Clothing, Apparel, & Fashions",
            "type":"Retail Goods"
        }
    ],
    "sg:phone":"+1 317 839 6468",
    "sg:postcode":"46168",
    "sg:province":"IN",
    "sg:tags":[
        "apparel",
        "racing",
        "sportswear",
        "merchandise",
        "women's"
    ],
    "wof:name":"Store 2",
    "wof:placetype":"venue"
},
  "geometry": {"coordinates":[-86.44026599999999,39.709126],"type":"Point"}
}