{
  "type": "Feature",
  "properties": {
    "addr:full":"1017 S Washington St Marion IN 46953",
    "addr:housenumber":"1017",
    "addr:postcode":"46953",
    "addr:street":"S Washington St",
    "iso:country":"US",
    "sg:address":"1017 S Washington St",
    "sg:city":"Marion",
    "sg:classifiers":[
        {
            "category":"Building & Trades",
            "subcategory":"Construction",
            "type":"Services"
        }
    ],
    "sg:phone":"+1 765 662 6212",
    "sg:postcode":"46953",
    "sg:province":"IN",
    "sg:tags":[
        "home",
        "improvement"
    ],
    "wof:name":"A Dave Widmeyer Roof & Windows",
    "wof:placetype":"venue"
},
  "geometry": {"coordinates":[-85.659723,40.551356],"type":"Point"}
}