{
  "type": "Feature",
  "properties": {
    "iso:country":"US",
    "sg:address":"4350 S East St",
    "sg:city":"Indianapolis",
    "sg:classifiers":[
        {
            "category":"Freight",
            "type":"Transportation"
        }
    ],
    "sg:phone":"+1 317 783 5164",
    "sg:postcode":"46227",
    "sg:province":"IN",
    "sg:tags":[
        "commercial",
        "storage"
    ],
    "wof:name":"Public Storage",
    "wof:placetype":"venue"
},
  "geometry": {"coordinates":[-86.148923,39.701967],"type":"Point"}
}