{
  "type": "Feature",
  "properties": {
    "iso:country":"US",
    "sg:address":"4075 Dartmoor Dr",
    "sg:city":"Greenwood",
    "sg:classifiers":[
        {
            "category":"Shopping",
            "type":"Retail Goods"
        }
    ],
    "sg:phone":"+1 317 885 9833",
    "sg:postcode":"46143",
    "sg:province":"IN",
    "sg:tags":[
        "cosmetic",
        "perfume"
    ],
    "wof:name":"Avon Recruiter Rep",
    "wof:placetype":"venue"
},
  "geometry": {"coordinates":[-86.178348,39.595494],"type":"Point"}
}