{
  "type": "Feature",
  "properties": {
    "iso:country":"US",
    "sg:address":"2705 S Kenyon Dr",
    "sg:city":"Indianapolis",
    "sg:classifiers":[
        {
            "category":"Retail",
            "subcategory":"Animal Services",
            "type":"Services"
        }
    ],
    "sg:phone":"+1 317 353 0335",
    "sg:postcode":"46203",
    "sg:province":"IN",
    "sg:tags":[
        "pet",
        "grooming",
        "washing"
    ],
    "wof:name":"Love Mobile Pet Grooming",
    "wof:placetype":"venue"
},
  "geometry": {"coordinates":[-86.056266,39.727808],"type":"Point"}
}