{
  "type": "Feature",
  "properties": {
    "iso:country":"US",
    "sg:address":"4623 Tyler St",
    "sg:city":"Gary",
    "sg:classifiers":[
        {
            "category":"Shopping",
            "subcategory":"Stationery & Office Supplies",
            "type":"Retail Goods"
        },
        {
            "category":"Shopping",
            "subcategory":"Gifts & Souvenirs",
            "type":"Retail Goods"
        }
    ],
    "sg:phone":"+1 219 980 3855",
    "sg:postcode":"46408",
    "sg:province":"IN",
    "sg:tags":[
        "shop",
        "store"
    ],
    "wof:name":"Carmens Unique Creations",
    "wof:placetype":"venue"
},
  "geometry": {"coordinates":[-87.347185,41.534075],"type":"Point"}
}