{
  "type": "Feature",
  "properties": {
    "iso:country":"US",
    "sg:address":"5064 W 300 N",
    "sg:city":"Earl Park",
    "sg:classifiers":[
        {
            "category":"Farming",
            "subcategory":"Livestock Farm",
            "type":"Manufacturing & Wholesale Goods"
        }
    ],
    "sg:phone":"+1 219 474 3575",
    "sg:postcode":"47942",
    "sg:province":"IN",
    "sg:tags":[
        "hay",
        "corn",
        "bean",
        "cattle"
    ],
    "wof:name":"Marvin Monjon",
    "wof:placetype":"venue"
},
  "geometry": {"coordinates":[-87.42030200000001,40.649939],"type":"Point"}
}