{
  "type": "Feature",
  "properties": {
    "iso:country":"US",
    "sg:address":"6752 E State Rd 64",
    "sg:city":"St Anthony",
    "sg:classifiers":[
        {
            "category":"Professional",
            "subcategory":"Engineering",
            "type":"Services"
        }
    ],
    "sg:phone":"+1 812 326 2983",
    "sg:postcode":"47575",
    "sg:province":"IN",
    "sg:tags":[
        "engineer"
    ],
    "wof:name":"Valley Engineering Inc",
    "wof:placetype":"venue"
},
  "geometry": {"coordinates":[-86.78101100000001,38.306064],"type":"Point"}
}