{
  "type": "Feature",
  "properties": {
    "iso:country":"US",
    "sg:address":"132 S Main St",
    "sg:city":"Milford",
    "sg:classifiers":[
        {
            "category":"Bars & Pubs",
            "type":"Food & Drink"
        }
    ],
    "sg:phone":"+1 574 658 4904",
    "sg:postcode":"46542",
    "sg:province":"IN",
    "wof:name":"Bud's Bar Inc",
    "wof:placetype":"venue"
},
  "geometry": {"coordinates":[-85.845932,41.409401],"type":"Point"}
}