{
  "type": "Feature",
  "properties": {
    "iso:country":"US",
    "sg:address":"6913 Spearsville Rd",
    "sg:city":"Morgantown",
    "sg:classifiers":[
        {
            "category":"Retail",
            "subcategory":"Repair Shop",
            "type":"Services"
        }
    ],
    "sg:phone":"+1 812 597 4355",
    "sg:postcode":"46160",
    "sg:province":"IN",
    "wof:name":"Minuteman Gunsmithing Inc",
    "wof:placetype":"venue"
},
  "geometry": {"coordinates":[-86.233648,39.289463],"type":"Point"}
}