{
  "type": "Feature",
  "properties": {
    "iso:country":"US",
    "sg:address":"605 Green Blvd",
    "sg:city":"Aurora",
    "sg:classifiers":[
        {
            "category":"Autos & Motor Vehicles",
            "subcategory":"Boat Sales",
            "type":"Retail Goods"
        }
    ],
    "sg:phone":"+1 812 926 0341",
    "sg:postcode":"47001",
    "sg:province":"IN",
    "sg:tags":[
        "dealer",
        "sales"
    ],
    "wof:name":"Tradewinds Marine Inc",
    "wof:placetype":"venue"
},
  "geometry": {"coordinates":[-84.89811,39.062081],"type":"Point"}
}