{
  "type": "Feature",
  "properties": {
    "iso:country":"US",
    "sg:address":"429 Blaine St",
    "sg:city":"Gary",
    "sg:classifiers":[
        {
            "category":"Freight",
            "type":"Transportation"
        }
    ],
    "sg:phone":"+1 219 944 1410",
    "sg:postcode":"46406",
    "sg:province":"IN",
    "sg:tags":[
        "trucking"
    ],
    "wof:name":"Arellano Trucking Inc",
    "wof:placetype":"venue"
},
  "geometry": {"coordinates":[-87.428071,41.602929],"type":"Point"}
}