{
  "type": "Feature",
  "properties": {
    "iso:country":"US",
    "sg:address":"1155 E Main St",
    "sg:city":"Plainfield",
    "sg:classifiers":[
        {
            "category":"Autos & Motor Vehicles",
            "subcategory":"Auto Supplies",
            "type":"Retail Goods"
        },
        {
            "category":"Retail",
            "subcategory":"Auto Repair",
            "type":"Services"
        }
    ],
    "sg:phone":"+1 317 839 3300",
    "sg:postcode":"46168",
    "sg:province":"IN",
    "sg:tags":[
        "automobile",
        "part",
        "truck"
    ],
    "sg:website":"http://clickserve.dartsearch.net/link/click?lid=43000000313870086&ds_s_kwgid=58000000006820725&ds_e_matchtype={MatchType}&ds_e_kwdid={OrderItemId}&ds_e_adid={AdId}&ds_url_v=2",
    "wof:name":"Plainfield Tire",
    "wof:placetype":"venue"
},
  "geometry": {"coordinates":[-86.386776,39.707782],"type":"Point"}
}