{
  "type": "Feature",
  "properties": {
    "iso:country":"US",
    "sg:address":"8035 S Strain Ridge Rd",
    "sg:city":"Bloomington",
    "sg:classifiers":[
        {
            "category":"Organizations",
            "subcategory":"Religious Organization",
            "type":"Services"
        }
    ],
    "sg:phone":"+1 812 824 2496",
    "sg:postcode":"47401",
    "sg:province":"IN",
    "sg:tags":[
        "church"
    ],
    "wof:name":"Bethel Apostolic Church",
    "wof:placetype":"venue"
},
  "geometry": {"coordinates":[-86.507695,39.058422],"type":"Point"}
}