{
  "type": "Feature",
  "properties": {
    "addr:full":"524 E 1st St Warren IN 46792",
    "addr:housenumber":"524",
    "addr:postcode":"46792",
    "addr:street":"E 1St St",
    "iso:country":"US",
    "sg:address":"524 E 1st St",
    "sg:city":"Warren",
    "sg:classifiers":[
        {
            "category":"Building & Trades",
            "subcategory":"Plumbing",
            "type":"Services"
        }
    ],
    "sg:phone":"+1 260 375 3512",
    "sg:postcode":"46792",
    "sg:province":"IN",
    "sg:tags":[
        "conditioning",
        "air",
        "system",
        "contractor"
    ],
    "wof:name":"Parks Heating & Air Service",
    "wof:placetype":"venue"
},
  "geometry": {"coordinates":[-85.421053,40.678185],"type":"Point"}
}