{
  "type": "Feature",
  "properties": {
    "iso:country":"US",
    "sg:address":"20 Boone Woods",
    "sg:city":"Zionsville",
    "sg:classifiers":[
        {
            "category":"Wholesale",
            "subcategory":"Durable Goods & Equipment",
            "type":"Manufacturing & Wholesale Goods"
        }
    ],
    "sg:phone":"+1 317 873 4056",
    "sg:postcode":"46077",
    "sg:province":"IN",
    "sg:tags":[
        "representative",
        "manufacturer"
    ],
    "wof:name":"Hoskins Associates Inc",
    "wof:placetype":"venue"
},
  "geometry": {"coordinates":[-86.28014899999999,39.949534],"type":"Point"}
}