{
  "type": "Feature",
  "properties": {
    "iso:country":"US",
    "sg:address":"220 W Main St",
    "sg:city":"Petersburg",
    "sg:classifiers":[
        {
            "category":"Shopping",
            "subcategory":"Bicycles & Sporting Goods",
            "type":"Retail Goods"
        }
    ],
    "sg:phone":"+1 812 354 9408",
    "sg:postcode":"47567",
    "sg:province":"IN",
    "sg:tags":[
        "tape",
        "video",
        "rental"
    ],
    "wof:name":"Patoka Bait & Tackle",
    "wof:placetype":"venue"
},
  "geometry": {"coordinates":[-87.288133,38.485594],"type":"Point"}
}