{
  "type": "Feature",
  "properties": {
    "iso:country":"US",
    "sg:address":"10364 S Co Rd 950 E",
    "sg:city":"Stendal",
    "sg:classifiers":[
        {
            "category":"Organizations",
            "subcategory":"Community Association",
            "type":"Services"
        }
    ],
    "sg:phone":"+1 812 536 2272",
    "sg:postcode":"47585",
    "sg:province":"IN",
    "sg:tags":[
        "environmental",
        "org"
    ],
    "wof:name":"Quail Unlimited",
    "wof:placetype":"venue"
},
  "geometry": {"coordinates":[-87.104381,38.269575],"type":"Point"}
}