{
  "type": "Feature",
  "properties": {
    "iso:country":"US",
    "sg:address":"794 W Center St",
    "sg:city":"Warsaw",
    "sg:classifiers":[
        {
            "category":"Government",
            "subcategory":"Office",
            "type":"Public Place"
        }
    ],
    "sg:phone":"+1 574 372 9560",
    "sg:postcode":"46580",
    "sg:province":"IN",
    "sg:tags":[
        "village"
    ],
    "wof:name":"Warsaw Sewage Collection Dept",
    "wof:placetype":"venue"
},
  "geometry": {"coordinates":[-85.868863,41.237358],"type":"Point"}
}