{
  "type": "Feature",
  "properties": {
    "iso:country":"US",
    "sg:address":"7342 W State Rd 28",
    "sg:city":"Tipton",
    "sg:classifiers":[
        {
            "category":"Retail",
            "subcategory":"Repair Shop",
            "type":"Services"
        }
    ],
    "sg:phone":"+1 765 963 6628",
    "sg:postcode":"46072",
    "sg:province":"IN",
    "sg:tags":[
        "tractor"
    ],
    "wof:name":"Motec Engineering",
    "wof:placetype":"venue"
},
  "geometry": {"coordinates":[-86.152907,40.275236],"type":"Point"}
}