{
  "type": "Feature",
  "properties": {
    "addr:full":"3429 Michigan St Hobart IN 46342",
    "addr:housenumber":"3429",
    "addr:postcode":"46342",
    "addr:street":"Michigan St",
    "iso:country":"US",
    "sg:address":"3429 Michigan St",
    "sg:city":"Hobart",
    "sg:classifiers":[
        {
            "category":"Building & Trades",
            "subcategory":"Construction",
            "type":"Services"
        }
    ],
    "sg:phone":"+1 219 962 9888",
    "sg:postcode":"46342",
    "sg:province":"IN",
    "sg:tags":[
        "sign",
        "contractor"
    ],
    "wof:name":"Sign Source One",
    "wof:placetype":"venue"
},
  "geometry": {"coordinates":[-87.274485,41.554588],"type":"Point"}
}