{
  "type": "Feature",
  "properties": {
    "iso:country":"US",
    "sg:address":"106 S Main St",
    "sg:city":"Fortville",
    "sg:classifiers":[
        {
            "category":"Manufacturing",
            "subcategory":"Signs",
            "type":"Manufacturing & Wholesale Goods"
        }
    ],
    "sg:phone":"+1 317 485 7787",
    "sg:postcode":"46040",
    "sg:province":"IN",
    "wof:name":"Sign Style",
    "wof:placetype":"venue"
},
  "geometry": {"coordinates":[-85.84918500000001,39.933244],"type":"Point"}
}