{
  "type": "Feature",
  "properties": {
    "addr:full":"7040 Whitewater River Ln Brookville IN 47012",
    "addr:housenumber":"7040",
    "addr:postcode":"47012",
    "addr:street":"Whitewater River Ln",
    "iso:country":"US",
    "sg:address":"7040 Whitewater River Ln",
    "sg:city":"Brookville",
    "sg:classifiers":[
        {
            "category":"Autos & Motor Vehicles",
            "subcategory":"Boat Sales",
            "type":"Retail Goods"
        }
    ],
    "sg:phone":"+1 765 647 4904",
    "sg:postcode":"47012",
    "sg:province":"IN",
    "sg:tags":[
        "canoe"
    ],
    "wof:name":"Morgan Brookville Canoe Ctr",
    "wof:placetype":"venue"
},
  "geometry": {"coordinates":[-85.013491,39.40783],"type":"Point"}
}