{
  "type": "Feature",
  "properties": {
    "addr:full":"15961 Madison Rd Mishawaka IN 46544",
    "addr:housenumber":"15961",
    "addr:postcode":"46544",
    "addr:street":"Madison Rd",
    "iso:country":"US",
    "sg:address":"15961 Madison Rd",
    "sg:city":"Mishawaka",
    "sg:classifiers":[
        {
            "category":"Organizations",
            "subcategory":"Religious Organization",
            "type":"Services"
        }
    ],
    "sg:phone":"+1 574 633 4921",
    "sg:postcode":"46544",
    "sg:province":"IN",
    "sg:tags":[
        "church"
    ],
    "wof:name":"Apostolic Christian Church",
    "wof:placetype":"venue"
},
  "geometry": {"coordinates":[-86.175984,41.579042],"type":"Point"}
}