{
  "type": "Feature",
  "properties": {
    "addr:full":"56 N Main St Martinsville IN 46151",
    "addr:housenumber":"56",
    "addr:postcode":"46151",
    "addr:street":"N Main St",
    "iso:country":"US",
    "sg:address":"56 N Main St",
    "sg:city":"Martinsville",
    "sg:classifiers":[
        {
            "category":"Real Estate",
            "subcategory":"Real Estate Services",
            "type":"Services"
        }
    ],
    "sg:phone":"+1 765 342 6100",
    "sg:postcode":"46151",
    "sg:province":"IN",
    "wof:name":"Land America Century Title Svc",
    "wof:placetype":"venue"
},
  "geometry": {"coordinates":[-86.428664,39.427301],"type":"Point"}
}