{
  "type": "Feature",
  "properties": {
    "iso:country":"US",
    "sg:address":"405 E Hoffer St",
    "sg:city":"Kokomo",
    "sg:classifiers":[
        {
            "category":"Shopping",
            "type":"Retail Goods"
        }
    ],
    "sg:phone":"+1 765 453 5175",
    "sg:postcode":"46902",
    "sg:province":"IN",
    "sg:tags":[
        "hearing",
        "equipment",
        "supply",
        "impaired"
    ],
    "wof:name":"Supreme Hearing Co Inc",
    "wof:placetype":"venue"
},
  "geometry": {"coordinates":[-86.126413,40.465834],"type":"Point"}
}