{
  "type": "Feature",
  "properties": {
    "iso:country":"US",
    "sg:address":"502 W 6th St",
    "sg:city":"Mishawaka",
    "sg:classifiers":[
        {
            "category":"Restaurant",
            "type":"Food & Drink"
        }
    ],
    "sg:phone":"+1 574 259 6786",
    "sg:postcode":"46544",
    "sg:province":"IN",
    "wof:name":"Squad's 2nd Precinct",
    "wof:placetype":"venue"
},
  "geometry": {"coordinates":[-86.18825099999999,41.65706],"type":"Point"}
}