{
  "type": "Feature",
  "properties": {
    "iso:country":"US",
    "sg:address":"1310 Broadway",
    "sg:city":"Gary",
    "sg:classifiers":[
        {
            "category":"Home & Garden",
            "subcategory":"Hardware",
            "type":"Retail Goods"
        }
    ],
    "sg:phone":"+1 219 886 3136",
    "sg:postcode":"46407",
    "sg:province":"IN",
    "wof:name":"Ace Hardware",
    "wof:placetype":"venue"
},
  "geometry": {"coordinates":[-87.337126,41.588784],"type":"Point"}
}