{
  "type": "Feature",
  "properties": {
    "iso:country":"US",
    "sg:address":"490 N Clark Blvd",
    "sg:city":"Clarksville",
    "sg:classifiers":[
        {
            "category":"Utilities",
            "subcategory":"Water",
            "type":"Services"
        },
        {
            "category":"Recreation",
            "subcategory":"Water Park",
            "type":"Entertainment"
        },
        {
            "category":"Food & Beverages",
            "subcategory":"Liquor & Beverages",
            "type":"Retail Goods"
        },
        {
            "category":"Home & Garden",
            "subcategory":"Hardware",
            "type":"Retail Goods"
        },
        {
            "category":"Wholesale",
            "subcategory":"Beer",
            "type":"Manufacturing & Wholesale Goods"
        }
    ],
    "sg:phone":"+1 812 283 7913",
    "sg:postcode":"47129",
    "sg:province":"IN",
    "sg:tags":[
        "filter",
        "filtration",
        "bottler",
        "softening",
        "supply",
        "companies-bottled",
        "purification",
        "bulk",
        "equipment",
        "fountain",
        "treatment",
        "equipment-service",
        "coolers",
        "conditioning"
    ],
    "sg:website":"http://www.culligan.com",
    "wof:name":"Culligan Water Systems",
    "wof:placetype":"venue"
},
  "geometry": {"coordinates":[-85.769166,38.29366],"type":"Point"}
}