{
  "type": "Feature",
  "properties": {
    "iso:country":"US",
    "sg:address":"1225 E 11th St",
    "sg:city":"Anderson",
    "sg:classifiers":[
        {
            "category":"Building & Trades",
            "subcategory":"Landscaping Services",
            "type":"Services"
        }
    ],
    "sg:phone":"+1 765 644 4220",
    "sg:postcode":"46012",
    "sg:province":"IN",
    "wof:name":"Rockhill Lawn Care",
    "wof:placetype":"venue"
},
  "geometry": {"coordinates":[-85.663832,40.104773],"type":"Point"}
}