{
  "type": "Feature",
  "properties": {
    "addr:full":"1520 S Airport Rd Monticello IN 47960",
    "addr:housenumber":"1520",
    "addr:postcode":"47960",
    "addr:street":"S Airport Rd",
    "iso:country":"US",
    "sg:address":"1520 S Airport Rd",
    "sg:city":"Monticello",
    "sg:classifiers":[
        {
            "category":"Recreation",
            "type":"Entertainment"
        }
    ],
    "sg:phone":"+1 574 583 3547",
    "sg:postcode":"47960",
    "sg:province":"IN",
    "sg:tags":[
        "instruction",
        "gymnastic"
    ],
    "wof:name":"Twin Lakes Gymnastics Inc",
    "wof:placetype":"venue"
},
  "geometry": {"coordinates":[-86.762078,40.726465],"type":"Point"}
}