{
  "type": "Feature",
  "properties": {
    "iso:country":"US",
    "sg:address":"1805 Calumet Ave",
    "sg:city":"Valparaiso",
    "sg:classifiers":[
        {
            "category":"Social Services",
            "subcategory":"Child Care",
            "type":"Services"
        }
    ],
    "sg:phone":"+1 219 462 7377",
    "sg:postcode":"46383",
    "sg:province":"IN",
    "wof:name":"Miracle's Child Care Ctr",
    "wof:placetype":"venue"
},
  "geometry": {"coordinates":[-87.051478,41.484699],"type":"Point"}
}