{
  "type": "Feature",
  "properties": {
    "addr:full":"400 Fisher St Munster IN 46321",
    "addr:housenumber":"400",
    "addr:postcode":"46321",
    "addr:street":"Fisher St",
    "iso:country":"US",
    "sg:address":"400 Fisher St",
    "sg:city":"Munster",
    "sg:classifiers":[
        {
            "category":"Professional",
            "subcategory":"Advertising",
            "type":"Services"
        }
    ],
    "sg:phone":"+1 219 836 3122",
    "sg:postcode":"46321",
    "sg:province":"IN",
    "sg:tags":[
        "mail"
    ],
    "wof:name":"Guru System",
    "wof:placetype":"venue"
},
  "geometry": {"coordinates":[-87.516322,41.551832],"type":"Point"}
}