{
  "type": "Feature",
  "properties": {
    "iso:country":"US",
    "sg:address":"7905 W 450 N",
    "sg:city":"Shipshewana",
    "sg:classifiers":[
        {
            "category":"Travel",
            "subcategory":"Hotels & Motels",
            "type":"Entertainment"
        }
    ],
    "sg:phone":"+1 260 768 4221",
    "sg:postcode":"46565",
    "sg:province":"IN",
    "wof:name":"Green Meadow Ranch",
    "wof:placetype":"venue"
},
  "geometry": {"coordinates":[-85.579683,41.705051],"type":"Point"}
}