{
  "type": "Feature",
  "properties": {
    "addr:full":"3615 E Market St Logansport IN 46947",
    "addr:housenumber":"3615",
    "addr:postcode":"46947",
    "addr:street":"E Market St",
    "iso:country":"US",
    "sg:address":"3615 E Market St",
    "sg:city":"Logansport",
    "sg:classifiers":[
        {
            "category":"Restaurant",
            "type":"Food & Drink"
        }
    ],
    "sg:menulink":"http://www.allmenus.com/in/eel/208082-taco-bell/menu/",
    "sg:phone":"+1 574 737 8037",
    "sg:postcode":"46947",
    "sg:province":"IN",
    "sg:tags":[
        "mexican"
    ],
    "wof:name":"Taco Bell",
    "wof:placetype":"venue"
},
  "geometry": {"coordinates":[-86.319023,40.757256],"type":"Point"}
}