{
  "type": "Feature",
  "properties": {
    "iso:country":"US",
    "sg:address":"416 W Main St",
    "sg:city":"Loogootee",
    "sg:classifiers":[
        {
            "category":"Personal",
            "subcategory":"Beauty Salon",
            "type":"Services"
        }
    ],
    "sg:phone":"+1 812 295 3813",
    "sg:postcode":"47553",
    "sg:province":"IN",
    "sg:tags":[
        "shop"
    ],
    "wof:name":"Carolyn's Hair Care",
    "wof:placetype":"venue"
},
  "geometry": {"coordinates":[-86.918639,38.675967],"type":"Point"}
}