{
  "type": "Feature",
  "properties": {
    "iso:country":"US",
    "sg:address":"610 Silhavy Rd",
    "sg:city":"Valparaiso",
    "sg:classifiers":[
        {
            "category":"Shopping",
            "subcategory":"Bicycles & Sporting Goods",
            "type":"Retail Goods"
        }
    ],
    "sg:phone":"+1 219 462 3411",
    "sg:postcode":"46383",
    "sg:province":"IN",
    "sg:website":"www.bucksbikeshop.com",
    "wof:name":"Buck's Bicycle Shop",
    "wof:placetype":"venue"
},
  "geometry": {"coordinates":[-87.02704900000001,41.474822],"type":"Point"}
}