{
  "type": "Feature",
  "properties": {
    "addr:full":"406 Washington St Columbus IN 47201",
    "addr:housenumber":"406",
    "addr:postcode":"47201",
    "addr:street":"Washington St",
    "iso:country":"US",
    "sg:address":"406 Washington St",
    "sg:city":"Columbus",
    "sg:classifiers":[
        {
            "category":"Shopping",
            "subcategory":"Used Merchandise",
            "type":"Retail Goods"
        }
    ],
    "sg:phone":"+1 812 376 6055",
    "sg:postcode":"47201",
    "sg:province":"IN",
    "sg:tags":[
        "book",
        "rare",
        "dealer"
    ],
    "wof:name":"Cummins Book Store",
    "wof:placetype":"venue"
},
  "geometry": {"coordinates":[-85.921193,39.203419],"type":"Point"}
}