{
  "type": "Feature",
  "properties": {
    "addr:full":"912 W Main St Peru IN 46970",
    "addr:housenumber":"912",
    "addr:postcode":"46970",
    "addr:street":"W Main St",
    "iso:country":"US",
    "sg:address":"912 W Main St",
    "sg:city":"Peru",
    "sg:classifiers":[
        {
            "category":"Restaurant",
            "type":"Food & Drink"
        }
    ],
    "sg:phone":"+1 765 472 3138",
    "sg:postcode":"46970",
    "sg:province":"IN",
    "sg:website":"www.longjohnsilvers.com",
    "wof:name":"Long John Silver's",
    "wof:placetype":"venue"
},
  "geometry": {"coordinates":[-86.09317299999999,40.744841],"type":"Point"}
}