{
  "type": "Feature",
  "properties": {
    "iso:country":"US",
    "sg:address":"6509 Constitution Dr",
    "sg:city":"Fort Wayne",
    "sg:classifiers":[
        {
            "category":"Insurance",
            "subcategory":"Insurance Agent",
            "type":"Services"
        }
    ],
    "sg:phone":"+1 260 471 4391",
    "sg:postcode":"46804",
    "sg:province":"IN",
    "sg:tags":[
        "adjuster"
    ],
    "wof:name":"Custard Insurance Adjusters",
    "wof:placetype":"venue"
},
  "geometry": {"coordinates":[-85.228423,41.067857],"type":"Point"}
}