{
  "type": "Feature",
  "properties": {
    "iso:country":"US",
    "sg:address":"1128 S 18th St",
    "sg:city":"New Castle",
    "sg:classifiers":[
        {
            "category":"Organizations",
            "subcategory":"Religious Organization",
            "type":"Services"
        }
    ],
    "sg:phone":"+1 765 521 8070",
    "sg:postcode":"47362",
    "sg:province":"IN",
    "sg:tags":[
        "church"
    ],
    "wof:name":"Fellowship Baptist Church NC",
    "wof:placetype":"venue"
},
  "geometry": {"coordinates":[-85.362951,39.921173],"type":"Point"}
}