{
  "type": "Feature",
  "properties": {
    "iso:country":"US",
    "sg:address":"2823 Bridlewood Cir",
    "sg:city":"Carmel",
    "sg:classifiers":[
        {
            "category":"Health Services",
            "subcategory":"Clinic",
            "type":"Services"
        }
    ],
    "sg:phone":"+1 317 574 0766",
    "sg:postcode":"46033",
    "sg:province":"IN",
    "sg:tags":[
        "wellness",
        "program"
    ],
    "wof:name":"Lifestyle Consulting",
    "wof:placetype":"venue"
},
  "geometry": {"coordinates":[-86.114274,40.003245],"type":"Point"}
}