{
  "type": "Feature",
  "properties": {
    "iso:country":"US",
    "sg:address":"300 N Chestnut St",
    "sg:city":"Seymour",
    "sg:classifiers":[
        {
            "category":"Personal",
            "subcategory":"Beauty Salon",
            "type":"Services"
        }
    ],
    "sg:phone":"+1 812 524 8631",
    "sg:postcode":"47274",
    "sg:province":"IN",
    "wof:name":"Res Que Cosmetology Permanent",
    "wof:placetype":"venue"
},
  "geometry": {"coordinates":[-85.891105,38.960971],"type":"Point"}
}