{
  "type": "Feature",
  "properties": {
    "iso:country":"US",
    "sg:address":"501 N Indiana St",
    "sg:city":"Greencastle",
    "sg:classifiers":[
        {
            "category":"Home & Garden",
            "subcategory":"Building Materials",
            "type":"Retail Goods"
        }
    ],
    "sg:phone":"+1 765 653 5171",
    "sg:postcode":"46135",
    "sg:province":"IN",
    "sg:tags":[
        "lumber"
    ],
    "wof:name":"Black Lumber Co",
    "wof:placetype":"venue"
},
  "geometry": {"coordinates":[-86.86446599999999,39.648818],"type":"Point"}
}