{
  "type": "Feature",
  "properties": {
    "addr:full":"1425 W Carmel Dr Carmel IN 46032",
    "addr:housenumber":"1425",
    "addr:postcode":"46032",
    "addr:street":"W Carmel Dr",
    "iso:country":"US",
    "sg:address":"1425 W Carmel Dr",
    "sg:city":"Carmel",
    "sg:classifiers":[
        {
            "category":"Banks & Credit Unions",
            "subcategory":"Bank",
            "type":"Services"
        }
    ],
    "sg:phone":"+1 317 574 3550",
    "sg:postcode":"46032",
    "sg:province":"IN",
    "sg:website":"tcunet.com",
    "wof:name":"Teachers Credit Union",
    "wof:placetype":"venue"
},
  "geometry": {"coordinates":[-86.156403,39.971401],"type":"Point"}
}