{
  "type": "Feature",
  "properties": {
    "iso:country":"US",
    "sg:address":"514 N Main St",
    "sg:city":"Princeton",
    "sg:classifiers":[
        {
            "category":"Health Services",
            "subcategory":"Doctor",
            "type":"Services"
        }
    ],
    "sg:phone":"+1 812 386 1220",
    "sg:postcode":"47670",
    "sg:province":"IN",
    "sg:tags":[
        "dentist"
    ],
    "wof:name":"J Ross Flaningam DDS",
    "wof:placetype":"venue"
},
  "geometry": {"coordinates":[-87.56737,38.359974],"type":"Point"}
}