{
  "type": "Feature",
  "properties": {
    "addr:full":"5055 English Ave Indianapolis IN 46201",
    "addr:housenumber":"5055",
    "addr:postcode":"46201",
    "addr:street":"English Ave",
    "iso:country":"US",
    "sg:address":"5055 English Ave",
    "sg:city":"Indianapolis",
    "sg:classifiers":[
        {
            "category":"Food & Beverages",
            "subcategory":"Groceries & Convenience Stores",
            "type":"Retail Goods"
        }
    ],
    "sg:phone":"+1 317 357 1610",
    "sg:postcode":"46201",
    "sg:province":"IN",
    "wof:name":"Super 7 Food Stores",
    "wof:placetype":"venue"
},
  "geometry": {"coordinates":[-86.083798,39.760231],"type":"Point"}
}