{
  "type": "Feature",
  "properties": {
    "iso:country":"US",
    "sg:address":"2620 Conner St",
    "sg:city":"Noblesville",
    "sg:classifiers":[
        {
            "category":"Health Services",
            "subcategory":"Chiropractor",
            "type":"Services"
        }
    ],
    "sg:phone":"+1 317 770 9003",
    "sg:postcode":"46060",
    "sg:province":"IN",
    "wof:name":"Priority 1 Medical",
    "wof:placetype":"venue"
},
  "geometry": {"coordinates":[-85.994536,40.045729],"type":"Point"}
}