{
  "type": "Feature",
  "properties": {
    "iso:country":"US",
    "sg:address":"923 S Walnut St",
    "sg:city":"Bloomington",
    "sg:classifiers":[
        {
            "category":"Retail",
            "subcategory":"Auto Repair",
            "type":"Services"
        }
    ],
    "sg:phone":"+1 812 336 2075",
    "sg:postcode":"47401",
    "sg:province":"IN",
    "sg:tags":[
        "repairing",
        "automobile",
        "radiator"
    ],
    "wof:name":"Bob Jones Radiator Repair",
    "wof:placetype":"venue"
},
  "geometry": {"coordinates":[-86.533615,39.155811],"type":"Point"}
}