{
  "type": "Feature",
  "properties": {
    "iso:country":"US",
    "sg:address":"59821 Co Rd 33",
    "sg:city":"Middlebury",
    "sg:classifiers":[
        {
            "category":"Building & Trades",
            "subcategory":"Pest Control",
            "type":"Services"
        }
    ],
    "sg:phone":"+1 260 625 3099",
    "sg:postcode":"46540",
    "sg:province":"IN",
    "wof:name":"Critter Control",
    "wof:placetype":"venue"
},
  "geometry": {"coordinates":[-85.75362199999999,41.629978],"type":"Point"}
}