{
  "type": "Feature",
  "properties": {
    "iso:country":"US",
    "sg:address":"359 W Baker St",
    "sg:city":"Fort Wayne",
    "sg:classifiers":[
        {
            "category":"Wholesale",
            "subcategory":"Furniture",
            "type":"Manufacturing & Wholesale Goods"
        }
    ],
    "sg:phone":"+1 260 424 8112",
    "sg:postcode":"46802",
    "sg:province":"IN",
    "wof:name":"Tri-R Office Svc",
    "wof:placetype":"venue"
},
  "geometry": {"coordinates":[-85.143376,41.072256],"type":"Point"}
}