{
  "type": "Feature",
  "properties": {
    "iso:country":"US",
    "sg:address":"619 Main St",
    "sg:city":"Vincennes",
    "sg:classifiers":[
        {
            "category":"Real Estate",
            "subcategory":"Real Estate Services",
            "type":"Services"
        }
    ],
    "sg:phone":"+1 812 895 1521",
    "sg:postcode":"47591",
    "sg:province":"IN",
    "sg:tags":[
        "company",
        "title"
    ],
    "wof:name":"Total Title Svc Of KNOX LLC",
    "wof:placetype":"venue"
},
  "geometry": {"coordinates":[-87.529267,38.67661],"type":"Point"}
}