{
  "type": "Feature",
  "properties": {
    "iso:country":"US",
    "sg:address":"259 Indiana Ave",
    "sg:city":"Valparaiso",
    "sg:classifiers":[
        {
            "category":"Shopping",
            "type":"Retail Goods"
        }
    ],
    "sg:phone":"+1 219 548 7607",
    "sg:postcode":"46383",
    "sg:province":"IN",
    "sg:tags":[
        "outdoor",
        "lighting",
        "specialty"
    ],
    "wof:name":"Christmas Decor",
    "wof:placetype":"venue"
},
  "geometry": {"coordinates":[-87.063509,41.466806],"type":"Point"}
}