{
  "type": "Feature",
  "properties": {
    "iso:country":"US",
    "sg:address":"1108 Keeneland Ct",
    "sg:city":"Indianapolis",
    "sg:classifiers":[
        {
            "category":"Professional",
            "type":"Services"
        }
    ],
    "sg:phone":"+1 317 705 0398",
    "sg:postcode":"46280",
    "sg:province":"IN",
    "sg:tags":[
        "establishment"
    ],
    "wof:name":"Rubendall Nate",
    "wof:placetype":"venue"
},
  "geometry": {"coordinates":[-86.137281,39.944639],"type":"Point"}
}