{
  "type": "Feature",
  "properties": {
    "iso:country":"US",
    "sg:address":"3224 Mallard Cove Ln",
    "sg:city":"Fort Wayne",
    "sg:classifiers":[
        {
            "category":"Wholesale",
            "subcategory":"Durable Goods & Equipment",
            "type":"Manufacturing & Wholesale Goods"
        }
    ],
    "sg:phone":"+1 260 435 1634",
    "sg:postcode":"46804",
    "sg:province":"IN",
    "sg:tags":[
        "exporter"
    ],
    "wof:name":"Belmont Technologies LTD",
    "wof:placetype":"venue"
},
  "geometry": {"coordinates":[-85.23031400000001,41.054243],"type":"Point"}
}