{
  "type": "Feature",
  "properties": {
    "iso:country":"US",
    "sg:address":"8820 S Meridian St",
    "sg:city":"Indianapolis",
    "sg:classifiers":[
        {
            "category":"Health Services",
            "subcategory":"Doctor",
            "type":"Services"
        }
    ],
    "sg:phone":"+1 317 885 7246",
    "sg:postcode":"46217",
    "sg:province":"IN",
    "sg:tags":[
        "physician",
        "surgeon",
        "management",
        "pain",
        "surgeons"
    ],
    "wof:name":"Pain Management Center",
    "wof:placetype":"venue"
},
  "geometry": {"coordinates":[-86.158429,39.638445],"type":"Point"}
}