{
  "type": "Feature",
  "properties": {
    "addr:full":"620 N Sherman Dr Indianapolis IN 46201",
    "addr:housenumber":"620",
    "addr:postcode":"46201",
    "addr:street":"N Sherman Dr",
    "iso:country":"US",
    "sg:address":"620 N Sherman Dr",
    "sg:city":"Indianapolis",
    "sg:classifiers":[
        {
            "category":"Government",
            "subcategory":"Fire Station",
            "type":"Public Place"
        }
    ],
    "sg:phone":"+1 317 327 6006",
    "sg:postcode":"46201",
    "sg:province":"IN",
    "sg:tags":[
        "protection"
    ],
    "wof:name":"Fire Dept",
    "wof:placetype":"venue"
},
  "geometry": {"coordinates":[-86.102349,39.776233],"type":"Point"}
}