{
  "type": "Feature",
  "properties": {
    "iso:country":"US",
    "sg:address":"4849 W Western Ave",
    "sg:city":"South Bend",
    "sg:classifiers":[
        {
            "category":"Retail",
            "subcategory":"Auto Rental",
            "type":"Services"
        }
    ],
    "sg:phone":"+1 574 289 5531",
    "sg:postcode":"46619",
    "sg:province":"IN",
    "sg:tags":[
        "renting",
        "truck",
        "leasing"
    ],
    "sg:website":"www.wiseinternational.com",
    "wof:name":"Wise Idealease",
    "wof:placetype":"venue"
},
  "geometry": {"coordinates":[-86.311385,41.671986],"type":"Point"}
}