{
  "type": "Feature",
  "properties": {
    "iso:country":"US",
    "sg:address":"64619 US Hwy 33",
    "sg:city":"Goshen",
    "sg:classifiers":[
        {
            "category":"Home & Garden",
            "subcategory":"Building Materials",
            "type":"Retail Goods"
        }
    ],
    "sg:phone":"+1 574 533 0491",
    "sg:postcode":"46526",
    "sg:province":"IN",
    "sg:tags":[
        "door"
    ],
    "sg:website":"www.hostetlerdoor.com",
    "wof:name":"Hostetler Door Inc",
    "wof:placetype":"venue"
},
  "geometry": {"coordinates":[-85.797657,41.562006],"type":"Point"}
}