{
  "type": "Feature",
  "properties": {
    "addr:full":"1741 Chessington Dr Mishawaka IN 46544",
    "addr:housenumber":"1741",
    "addr:postcode":"46544",
    "addr:street":"Chessington Dr",
    "iso:country":"US",
    "sg:address":"1741 Chessington Dr",
    "sg:city":"Mishawaka",
    "sg:classifiers":[
        {
            "category":"Building & Trades",
            "subcategory":"Plumbing",
            "type":"Services"
        }
    ],
    "sg:phone":"+1 574 299 0009",
    "sg:postcode":"46544",
    "sg:province":"IN",
    "sg:tags":[
        "plumbing",
        "contractor"
    ],
    "wof:name":"Action Rooter Inc",
    "wof:placetype":"venue"
},
  "geometry": {"coordinates":[-86.14887299999999,41.649363],"type":"Point"}
}