{
  "type": "Feature",
  "properties": {
    "addr:full":"736 W Main St Greensburg IN 47240",
    "addr:housenumber":"736",
    "addr:postcode":"47240",
    "addr:street":"W Main St",
    "iso:country":"US",
    "sg:address":"736 W Main St",
    "sg:city":"Greensburg",
    "sg:classifiers":[
        {
            "category":"Food & Beverages",
            "subcategory":"Groceries & Convenience Stores",
            "type":"Retail Goods"
        }
    ],
    "sg:phone":"+1 812 663 9411",
    "sg:postcode":"47240",
    "sg:province":"IN",
    "wof:name":"IGA",
    "wof:placetype":"venue"
},
  "geometry": {"coordinates":[-85.498091,39.336529],"type":"Point"}
}