{
  "type": "Feature",
  "properties": {
    "iso:country":"US",
    "sg:address":"203 S Main St",
    "sg:city":"Kendallville",
    "sg:classifiers":[
        {
            "category":"Retail",
            "subcategory":"Photofinishing",
            "type":"Services"
        }
    ],
    "sg:phone":"+1 260 347 1716",
    "sg:postcode":"46755",
    "sg:province":"IN",
    "sg:tags":[
        "photo",
        "finishing"
    ],
    "wof:name":"Custom Image",
    "wof:placetype":"venue"
},
  "geometry": {"coordinates":[-85.26533999999999,41.442602],"type":"Point"}
}