{
  "type": "Feature",
  "properties": {
    "iso:country":"US",
    "sg:address":"1583 W State Rd 32",
    "sg:city":"Veedersburg",
    "sg:classifiers":[
        {
            "category":"Organizations",
            "subcategory":"Religious Organization",
            "type":"Services"
        }
    ],
    "sg:phone":"+1 765 294 2968",
    "sg:postcode":"47987",
    "sg:province":"IN",
    "wof:name":"Coopers Chapel Parsonage",
    "wof:placetype":"venue"
},
  "geometry": {"coordinates":[-87.33573800000001,40.047032],"type":"Point"}
}