{
  "type": "Feature",
  "properties": {
    "iso:country":"US",
    "sg:address":"5465 Willow Grove Rd",
    "sg:city":"Centerville",
    "sg:classifiers":[
        {
            "category":"Real Estate",
            "subcategory":"Real Estate Operator",
            "type":"Services"
        }
    ],
    "sg:phone":"+1 765 855 5398",
    "sg:postcode":"47330",
    "sg:province":"IN",
    "sg:tags":[
        "farm",
        "property",
        "crop",
        "lessor",
        "general"
    ],
    "wof:name":"Franklin Westover",
    "wof:placetype":"venue"
},
  "geometry": {"coordinates":[-85.034061,39.753024],"type":"Point"}
}