{
  "type": "Feature",
  "properties": {
    "iso:country":"US",
    "sg:address":"107 S Pennsylvania St",
    "sg:city":"Indianapolis",
    "sg:classifiers":[
        {
            "category":"Building & Trades",
            "subcategory":"Cleaning & Sanitation",
            "type":"Services"
        }
    ],
    "sg:phone":"+1 317 262 4952",
    "sg:postcode":"46204",
    "sg:province":"IN",
    "sg:tags":[
        "janitorial"
    ],
    "wof:name":"Gsf Safeway Inc",
    "wof:placetype":"venue"
},
  "geometry": {"coordinates":[-86.15632600000001,39.765386],"type":"Point"}
}