{
  "type": "Feature",
  "properties": {
    "iso:country":"US",
    "sg:address":"3031 E 450 N",
    "sg:city":"Marion",
    "sg:classifiers":[
        {
            "category":"Education",
            "subcategory":"School",
            "type":"Public Place"
        }
    ],
    "sg:phone":"+1 765 664 8620",
    "sg:postcode":"46952",
    "sg:province":"IN",
    "wof:name":"Washington Elementary School",
    "wof:placetype":"venue"
},
  "geometry": {"coordinates":[-85.61548,40.618118],"type":"Point"}
}