{
  "type": "Feature",
  "properties": {
    "iso:country":"US",
    "sg:address":"6167 W Jefferson Blvd",
    "sg:city":"Fort Wayne",
    "sg:classifiers":[
        {
            "category":"Building & Trades",
            "subcategory":"Construction",
            "type":"Services"
        }
    ],
    "sg:phone":"+1 260 432 8283",
    "sg:postcode":"46804",
    "sg:province":"IN",
    "sg:tags":[
        "tile",
        "dealer"
    ],
    "wof:name":"Fort Wayne Tile's Abbey",
    "wof:placetype":"venue"
},
  "geometry": {"coordinates":[-85.220871,41.058023],"type":"Point"}
}