{
  "type": "Feature",
  "properties": {
    "iso:country":"US",
    "sg:address":"10791 S 450 E",
    "sg:city":"Geneva",
    "sg:classifiers":[
        {
            "category":"Building & Trades",
            "subcategory":"Construction",
            "type":"Services"
        }
    ],
    "sg:phone":"+1 260 525 0900",
    "sg:postcode":"46740",
    "sg:province":"IN",
    "sg:tags":[
        "excavating",
        "contractor"
    ],
    "wof:name":"Jones Excavating",
    "wof:placetype":"venue"
},
  "geometry": {"coordinates":[-84.84926900000001,40.589396],"type":"Point"}
}