{
  "type": "Feature",
  "properties": {
    "iso:country":"US",
    "sg:address":"3670 Co Rd 35",
    "sg:city":"Auburn",
    "sg:classifiers":[
        {
            "category":"Retail",
            "subcategory":"Auto Repair",
            "type":"Services"
        }
    ],
    "sg:phone":"+1 260 927 9967",
    "sg:postcode":"46706",
    "sg:province":"IN",
    "sg:tags":[
        "automotive"
    ],
    "wof:name":"Longs Auto Repair",
    "wof:placetype":"venue"
},
  "geometry": {"coordinates":[-85.02415999999999,41.39811],"type":"Point"}
}