{
  "type": "Feature",
  "properties": {
    "addr:full":"834 S Indiana Ave Sellersburg IN 47172",
    "addr:housenumber":"834",
    "addr:postcode":"47172",
    "addr:street":"S Indiana Ave",
    "iso:country":"US",
    "sg:address":"834 S Indiana Ave",
    "sg:city":"Sellersburg",
    "sg:classifiers":[
        {
            "category":"Manufacturing",
            "subcategory":"Printing",
            "type":"Manufacturing & Wholesale Goods"
        }
    ],
    "sg:phone":"+1 812 246 6311",
    "sg:postcode":"47172",
    "sg:province":"IN",
    "sg:tags":[
        "commercial"
    ],
    "wof:name":"Superior Print",
    "wof:placetype":"venue"
},
  "geometry": {"coordinates":[-85.753169,38.389177],"type":"Point"}
}