{
  "type": "Feature",
  "properties": {
    "iso:country":"US",
    "sg:address":"6525 Daniel Burnham Dr",
    "sg:city":"Portage",
    "sg:classifiers":[
        {
            "category":"Professional",
            "subcategory":"Research",
            "type":"Services"
        }
    ],
    "sg:phone":"+1 219 764 0924",
    "sg:postcode":"46368",
    "sg:province":"IN",
    "wof:name":"Diversified Research & Dev",
    "wof:placetype":"venue"
},
  "geometry": {"coordinates":[-87.167836,41.607715],"type":"Point"}
}