{
  "type": "Feature",
  "properties": {
    "iso:country":"US",
    "sg:address":"2040 W 900 N-90",
    "sg:city":"Markle",
    "sg:classifiers":[
        {
            "category":"Wholesale",
            "subcategory":"Machinery & Supplies",
            "type":"Manufacturing & Wholesale Goods"
        }
    ],
    "sg:phone":"+1 260 638 4978",
    "sg:postcode":"46770",
    "sg:province":"IN",
    "sg:tags":[
        "detergent",
        "soap"
    ],
    "wof:name":"Heartstrings Lather-Up",
    "wof:placetype":"venue"
},
  "geometry": {"coordinates":[-85.270046,40.873759],"type":"Point"}
}