{
  "type": "Feature",
  "properties": {
    "iso:country":"US",
    "sg:address":"2941 Alexander St",
    "sg:city":"Fort Wayne",
    "sg:classifiers":[
        {
            "category":"Social Services",
            "subcategory":"Child Care",
            "type":"Services"
        }
    ],
    "sg:phone":"+1 260 745 9499",
    "sg:postcode":"46806",
    "sg:province":"IN",
    "sg:tags":[
        "day"
    ],
    "wof:name":"Dawson Christina Child Care",
    "wof:placetype":"venue"
},
  "geometry": {"coordinates":[-85.10898299999999,41.058363],"type":"Point"}
}