{
  "type": "Feature",
  "properties": {
    "iso:country":"US",
    "sg:address":"889 W McClain St",
    "sg:city":"Scottsburg",
    "sg:classifiers":[
        {
            "category":"Organizations",
            "subcategory":"Religious Organization",
            "type":"Services"
        }
    ],
    "sg:phone":"+1 812 752 7857",
    "sg:postcode":"47170",
    "sg:province":"IN",
    "sg:tags":[
        "church"
    ],
    "wof:name":"Scottsburg First Baptist Chr",
    "wof:placetype":"venue"
},
  "geometry": {"coordinates":[-85.779634,38.685542],"type":"Point"}
}