{
  "type": "Feature",
  "properties": {
    "addr:full":"7325 Pendleton Pike Indianapolis IN 46226",
    "addr:housenumber":"7325",
    "addr:postcode":"46226",
    "addr:street":"Pendleton Pike",
    "iso:country":"US",
    "sg:address":"7325 Pendleton Pike",
    "sg:city":"Indianapolis",
    "sg:classifiers":[
        {
            "category":"Utilities",
            "subcategory":"Electric",
            "type":"Services"
        }
    ],
    "sg:phone":"+1 317 543 9302",
    "sg:postcode":"46226",
    "sg:province":"IN",
    "sg:tags":[
        "system",
        "power"
    ],
    "wof:name":"Batteries Plus",
    "wof:placetype":"venue"
},
  "geometry": {"coordinates":[-86.039424,39.830281],"type":"Point"}
}