{
  "type": "Feature",
  "properties": {
    "addr:full":"125 N Harrison St Warsaw IN 46580",
    "addr:housenumber":"125",
    "addr:postcode":"46580",
    "addr:street":"N Harrison St",
    "iso:country":"US",
    "sg:address":"125 N Harrison St",
    "sg:city":"Warsaw",
    "sg:classifiers":[
        {
            "category":"Organizations",
            "subcategory":"Religious Organization",
            "type":"Services"
        }
    ],
    "sg:phone":"+1 574 267 5842",
    "sg:postcode":"46580",
    "sg:province":"IN",
    "sg:tags":[
        "church"
    ],
    "wof:name":"Sacred Heart Catholic Church",
    "wof:placetype":"venue"
},
  "geometry": {"coordinates":[-85.829038,41.239664],"type":"Point"}
}