{
  "type": "Feature",
  "properties": {
    "iso:country":"US",
    "sg:address":"2937 S 18th St",
    "sg:city":"Lafayette",
    "sg:classifiers":[
        {
            "category":"Restaurant",
            "type":"Food & Drink"
        }
    ],
    "sg:phone":"+1 765 446 9798",
    "sg:postcode":"47909",
    "sg:province":"IN",
    "wof:name":"Taco Rico",
    "wof:placetype":"venue"
},
  "geometry": {"coordinates":[-86.876194,40.386381],"type":"Point"}
}