{
  "type": "Feature",
  "properties": {
    "iso:country":"US",
    "sg:address":"6432 Oaklandon Rd",
    "sg:city":"Indianapolis",
    "sg:classifiers":[
        {
            "category":"Shopping",
            "subcategory":"Computers & Home Electronics",
            "type":"Retail Goods"
        }
    ],
    "sg:phone":"+1 317 826 2365",
    "sg:postcode":"46236",
    "sg:province":"IN",
    "sg:tags":[
        "consulting",
        "management"
    ],
    "wof:name":"Home Video Studio Inc",
    "wof:placetype":"venue"
},
  "geometry": {"coordinates":[-85.95710099999999,39.875765],"type":"Point"}
}