{
  "type": "Feature",
  "properties": {
    "addr:full":"376 W 550 S Valparaiso IN 46385",
    "addr:housenumber":"376",
    "addr:postcode":"46385",
    "addr:street":"W 550 S",
    "iso:country":"US",
    "sg:address":"376 W 550 S",
    "sg:city":"Valparaiso",
    "sg:classifiers":[
        {
            "category":"Real Estate",
            "subcategory":"Real Estate Operator",
            "type":"Services"
        }
    ],
    "sg:phone":"+1 219 462 9030",
    "sg:postcode":"46385",
    "sg:province":"IN",
    "sg:tags":[
        "property",
        "lessor"
    ],
    "wof:name":"Philip Casbon",
    "wof:placetype":"venue"
},
  "geometry": {"coordinates":[-87.137888,41.354616],"type":"Point"}
}