{
  "type": "Feature",
  "properties": {
    "iso:country":"US",
    "sg:address":"8810 W Co Rd 400 N",
    "sg:city":"Gaston",
    "sg:classifiers":[
        {
            "category":"Manufacturing",
            "subcategory":"Printing",
            "type":"Manufacturing & Wholesale Goods"
        }
    ],
    "sg:phone":"+1 765 759 8437",
    "sg:postcode":"47342",
    "sg:province":"IN",
    "sg:tags":[
        "printer"
    ],
    "wof:name":"Tri K Printing & Packaging",
    "wof:placetype":"venue"
},
  "geometry": {"coordinates":[-85.489761,40.2481],"type":"Point"}
}