{
  "type": "Feature",
  "properties": {
    "iso:country":"US",
    "sg:address":"801 E Markland Ave",
    "sg:city":"Kokomo",
    "sg:classifiers":[
        {
            "category":"Autos & Motor Vehicles",
            "subcategory":"Automobile Sales",
            "type":"Retail Goods"
        }
    ],
    "sg:phone":"+1 765 452 6582",
    "sg:postcode":"46901",
    "sg:province":"IN",
    "sg:tags":[
        "car",
        "dealer"
    ],
    "wof:name":"Bob Boruff Auto Sales",
    "wof:placetype":"venue"
},
  "geometry": {"coordinates":[-86.122806,40.476539],"type":"Point"}
}