{
  "type": "Feature",
  "properties": {
    "addr:full":"245 Northridge Dr Shelbyville IN 46176",
    "addr:housenumber":"245",
    "addr:postcode":"46176",
    "addr:street":"Northridge Dr",
    "iso:country":"US",
    "sg:address":"245 Northridge Dr",
    "sg:city":"Shelbyville",
    "sg:classifiers":[
        {
            "category":"Professional",
            "type":"Services"
        }
    ],
    "sg:phone":"+1 317 398 8716",
    "sg:postcode":"46176",
    "sg:province":"IN",
    "sg:tags":[
        "establishment"
    ],
    "wof:name":"Highlift Equipment Of Indiana",
    "wof:placetype":"venue"
},
  "geometry": {"coordinates":[-85.786914,39.545659],"type":"Point"}
}