{
  "type": "Feature",
  "properties": {
    "addr:full":"17271 Darden Rd South Bend IN 46635",
    "addr:housenumber":"17271",
    "addr:postcode":"46635",
    "addr:street":"Darden Rd",
    "iso:country":"US",
    "sg:address":"17271 Darden Rd",
    "sg:city":"South Bend",
    "sg:classifiers":[
        {
            "category":"Insurance",
            "subcategory":"Insurance Agent",
            "type":"Services"
        }
    ],
    "sg:phone":"+1 574 272 7745",
    "sg:postcode":"46635",
    "sg:province":"IN",
    "wof:name":"Moutray & Assoc",
    "wof:placetype":"venue"
},
  "geometry": {"coordinates":[-86.202932,41.730527],"type":"Point"}
}