{
  "type": "Feature",
  "properties": {
    "iso:country":"US",
    "sg:address":"4271 E Station Rd",
    "sg:city":"Roanoke",
    "sg:classifiers":[
        {
            "category":"Sports & Exercise",
            "subcategory":"Golf",
            "type":"Entertainment"
        }
    ],
    "sg:phone":"+1 260 672 3577",
    "sg:postcode":"46783",
    "sg:province":"IN",
    "sg:tags":[
        "course"
    ],
    "wof:name":"Fantom Hollow Golf Course",
    "wof:placetype":"venue"
},
  "geometry": {"coordinates":[-85.370691,40.958704],"type":"Point"}
}