{
  "type": "Feature",
  "properties": {
    "addr:full":"5125 Tyrone Rd Fort Wayne IN 46809",
    "addr:housenumber":"5125",
    "addr:postcode":"46809",
    "addr:street":"Tyrone Rd",
    "iso:country":"US",
    "sg:address":"5125 Tyrone Rd",
    "sg:city":"Fort Wayne",
    "sg:classifiers":[
        {
            "category":"Professional",
            "subcategory":"Business Services",
            "type":"Services"
        },
        {
            "category":"Building & Trades",
            "subcategory":"Construction",
            "type":"Services"
        }
    ],
    "sg:phone":"+1 260 747 3430",
    "sg:postcode":"46809",
    "sg:province":"IN",
    "sg:tags":[
        "consultant",
        "contractor",
        "design",
        "hanging",
        "interior",
        "decorator"
    ],
    "wof:name":"Hill's Decorating Inc",
    "wof:placetype":"venue"
},
  "geometry": {"coordinates":[-85.180263,41.035267],"type":"Point"}
}