{
  "type": "Feature",
  "properties": {
    "iso:country":"US",
    "sg:address":"9389 N Co Rd 100 E",
    "sg:city":"Seymour",
    "sg:classifiers":[
        {
            "category":"Manufacturing",
            "subcategory":"Printing",
            "type":"Manufacturing & Wholesale Goods"
        }
    ],
    "sg:phone":"+1 812 524 9292",
    "sg:postcode":"47274",
    "sg:province":"IN",
    "sg:tags":[
        "screen"
    ],
    "wof:name":"J Tee's",
    "wof:placetype":"venue"
},
  "geometry": {"coordinates":[-86.022223,39.011855],"type":"Point"}
}