{
  "type": "Feature",
  "properties": {
    "iso:country":"US",
    "sg:address":"9098 W 800 S",
    "sg:city":"Brookston",
    "sg:classifiers":[
        {
            "category":"Wholesale",
            "subcategory":"Machinery & Supplies",
            "type":"Manufacturing & Wholesale Goods"
        }
    ],
    "sg:phone":"+1 219 279 2801",
    "sg:postcode":"47923",
    "sg:province":"IN",
    "sg:tags":[
        "farm",
        "equipment"
    ],
    "wof:name":"Tuthill Transport Technologies",
    "wof:placetype":"venue"
},
  "geometry": {"coordinates":[-87.041563,40.635536],"type":"Point"}
}