{
  "type": "Feature",
  "properties": {
    "addr:full":"7130 E 86th Ct Merrillville IN 46410",
    "addr:housenumber":"7130",
    "addr:postcode":"46410",
    "addr:street":"E 86Th Ct",
    "iso:country":"US",
    "sg:address":"7130 E 86th Ct",
    "sg:city":"Merrillville",
    "sg:classifiers":[
        {
            "category":"Building & Trades",
            "subcategory":"Construction",
            "type":"Services"
        }
    ],
    "sg:phone":"+1 219 947 2606",
    "sg:postcode":"46410",
    "sg:province":"IN",
    "sg:tags":[
        "house"
    ],
    "wof:name":"DCK Construction Inc",
    "wof:placetype":"venue"
},
  "geometry": {"coordinates":[-87.252205,41.461778],"type":"Point"}
}