{
  "type": "Feature",
  "properties": {
    "iso:country":"US",
    "sg:address":"104 S Main St",
    "sg:city":"Zionsville",
    "sg:classifiers":[
        {
            "category":"Arts & Performance",
            "subcategory":"Art Gallery",
            "type":"Entertainment"
        },
        {
            "category":"Professional",
            "subcategory":"Art Services",
            "type":"Services"
        },
        {
            "category":"Shopping",
            "subcategory":"Crafts & Fabrics",
            "type":"Retail Goods"
        }
    ],
    "sg:phone":"+1 317 873 3288",
    "sg:postcode":"46077",
    "sg:province":"IN",
    "sg:tags":[
        "picture",
        "frame",
        "galleries",
        "instruction",
        "consultant"
    ],
    "sg:website":"http://www.indygalleries.com",
    "wof:name":"Thomas Kinkade At The Zionsvi",
    "wof:placetype":"venue"
},
  "geometry": {"coordinates":[-86.261707,39.950647],"type":"Point"}
}