{
  "type": "Feature",
  "properties": {
    "iso:country":"US",
    "sg:address":"5008 Drexel Dr",
    "sg:city":"Anderson",
    "sg:classifiers":[
        {
            "category":"Retail",
            "subcategory":"Repair Shop",
            "type":"Services"
        }
    ],
    "sg:phone":"+1 765 643 4266",
    "sg:postcode":"46011",
    "sg:province":"IN",
    "wof:name":"Artisan Furniture Repair",
    "wof:placetype":"venue"
},
  "geometry": {"coordinates":[-85.721081,40.062512],"type":"Point"}
}