{
  "type": "Feature",
  "properties": {
    "addr:full":"720 E Main St Richmond IN 47374",
    "addr:housenumber":"720",
    "addr:postcode":"47374",
    "addr:street":"E Main St",
    "iso:country":"US",
    "sg:address":"720 E Main St",
    "sg:city":"Richmond",
    "sg:classifiers":[
        {
            "category":"Shopping",
            "subcategory":"Clothing, Apparel, & Fashions",
            "type":"Retail Goods"
        }
    ],
    "sg:phone":"+1 765 966 0990",
    "sg:postcode":"47374",
    "sg:province":"IN",
    "wof:name":"Secret Ingredient",
    "wof:placetype":"venue"
},
  "geometry": {"coordinates":[-84.892588,39.829136],"type":"Point"}
}