{
  "type": "Feature",
  "properties": {
    "iso:country":"US",
    "sg:address":"1018 S Three Mile Rd",
    "sg:city":"Batesville",
    "sg:classifiers":[
        {
            "category":"Farming",
            "subcategory":"Farm",
            "type":"Manufacturing & Wholesale Goods"
        }
    ],
    "sg:phone":"+1 812 934 2360",
    "sg:postcode":"47006",
    "sg:province":"IN",
    "sg:tags":[
        "crop",
        "general"
    ],
    "wof:name":"Dierckman Farms",
    "wof:placetype":"venue"
},
  "geometry": {"coordinates":[-85.258615,39.307944],"type":"Point"}
}