{
  "type": "Feature",
  "properties": {
    "iso:country":"US",
    "sg:address":"22507 Daisy Hill Rd",
    "sg:city":"Borden",
    "sg:classifiers":[
        {
            "category":"Freight",
            "type":"Transportation"
        }
    ],
    "sg:phone":"+1 812 967 2731",
    "sg:postcode":"47106",
    "sg:province":"IN",
    "sg:tags":[
        "operator",
        "trucking"
    ],
    "wof:name":"Scenic Valley Trucking",
    "wof:placetype":"venue"
},
  "geometry": {"coordinates":[-85.942623,38.494903],"type":"Point"}
}