{
  "type": "Feature",
  "properties": {
    "iso:country":"US",
    "sg:address":"2675 Fox Pointe Dr",
    "sg:city":"Columbus",
    "sg:classifiers":[
        {
            "category":"Health Services",
            "subcategory":"Doctor",
            "type":"Services"
        }
    ],
    "sg:phone":"+1 812 375 0000",
    "sg:postcode":"47203",
    "sg:province":"IN",
    "sg:tags":[
        "physician",
        "surgeon"
    ],
    "wof:name":"Columbus Spine & Neurosurgery",
    "wof:placetype":"venue"
},
  "geometry": {"coordinates":[-85.870287,39.22529],"type":"Point"}
}