{
  "type": "Feature",
  "properties": {
    "addr:full":"4635 W Perry St Indianapolis IN 46241",
    "addr:housenumber":"4635",
    "addr:postcode":"46241",
    "addr:street":"W Perry St",
    "iso:country":"US",
    "sg:address":"4635 W Perry St",
    "sg:city":"Indianapolis",
    "sg:classifiers":[
        {
            "category":"Personal",
            "subcategory":"Beauty Salon",
            "type":"Services"
        }
    ],
    "sg:phone":"+1 317 390 1996",
    "sg:postcode":"46241",
    "sg:province":"IN",
    "wof:name":"Who's Hair",
    "wof:placetype":"venue"
},
  "geometry": {"coordinates":[-86.240624,39.719795],"type":"Point"}
}