{
  "type": "Feature",
  "properties": {
    "iso:country":"US",
    "sg:address":"9273 Castlegate Dr",
    "sg:city":"Indianapolis",
    "sg:classifiers":[
        {
            "category":"Wholesale",
            "subcategory":"Electrical",
            "type":"Manufacturing & Wholesale Goods"
        }
    ],
    "sg:phone":"+1 317 579 1260",
    "sg:postcode":"46256",
    "sg:province":"IN",
    "sg:tags":[
        "control",
        "security",
        "system"
    ],
    "wof:name":"Brink's Home Security Inc",
    "wof:placetype":"venue"
},
  "geometry": {"coordinates":[-86.026631,39.922845],"type":"Point"}
}