{
  "type": "Feature",
  "properties": {
    "iso:country":"US",
    "sg:address":"4405 Primrose Ave",
    "sg:city":"Indianapolis",
    "sg:classifiers":[
        {
            "category":"Social Services",
            "subcategory":"Child Care",
            "type":"Services"
        }
    ],
    "sg:phone":"+1 317 253 1073",
    "sg:postcode":"46205",
    "sg:province":"IN",
    "wof:name":"Danyelle's Day Care",
    "wof:placetype":"venue"
},
  "geometry": {"coordinates":[-86.132401,39.838294],"type":"Point"}
}