{
  "type": "Feature",
  "properties": {
    "addr:full":"1300 Waterworks Rd Evansville IN 47713",
    "addr:housenumber":"1300",
    "addr:postcode":"47713",
    "addr:street":"Waterworks Rd",
    "iso:country":"US",
    "sg:address":"1300 Waterworks Rd",
    "sg:city":"Evansville",
    "sg:classifiers":[
        {
            "category":"Government",
            "subcategory":"Office",
            "type":"Public Place"
        }
    ],
    "sg:phone":"+1 812 423 5985",
    "sg:postcode":"47713",
    "sg:province":"IN",
    "sg:tags":[
        "village"
    ],
    "wof:name":"Vanderburgh Levee Authority",
    "wof:placetype":"venue"
},
  "geometry": {"coordinates":[-87.562417,37.934477],"type":"Point"}
}