{
  "type": "Feature",
  "properties": {
    "addr:full":"215 E 9th St Auburn IN 46706",
    "addr:housenumber":"215",
    "addr:postcode":"46706",
    "addr:street":"E 9Th St",
    "iso:country":"US",
    "sg:address":"215 E 9th St",
    "sg:city":"Auburn",
    "sg:classifiers":[
        {
            "category":"Social Services",
            "type":"Services"
        }
    ],
    "sg:phone":"+1 260 925 4566",
    "sg:postcode":"46706",
    "sg:province":"IN",
    "sg:tags":[
        "organization",
        "welfare"
    ],
    "wof:name":"American Red Cross",
    "wof:placetype":"venue"
},
  "geometry": {"coordinates":[-85.053421,41.365798],"type":"Point"}
}