{
  "type": "Feature",
  "properties": {
    "addr:full":"124 E Main St Boonville IN 47601",
    "addr:housenumber":"124",
    "addr:postcode":"47601",
    "addr:street":"E Main St",
    "iso:country":"US",
    "sg:address":"124 E Main St",
    "sg:city":"Boonville",
    "sg:classifiers":[
        {
            "category":"Social Services",
            "type":"Services"
        }
    ],
    "sg:phone":"+1 812 897 4437",
    "sg:postcode":"47601",
    "sg:province":"IN",
    "sg:tags":[
        "senior",
        "citizen"
    ],
    "wof:name":"Warrick County Senior Citizens",
    "wof:placetype":"venue"
},
  "geometry": {"coordinates":[-87.273965,38.050078],"type":"Point"}
}