{
  "type": "Feature",
  "properties": {
    "iso:country":"US",
    "sg:address":"449 W Eads Pkwy",
    "sg:city":"Lawrenceburg",
    "sg:classifiers":[
        {
            "category":"Restaurant",
            "type":"Food & Drink"
        }
    ],
    "sg:phone":"+1 812 537 5327",
    "sg:postcode":"47025",
    "sg:province":"IN",
    "wof:name":"Wendy's",
    "wof:placetype":"venue"
},
  "geometry": {"coordinates":[-84.861284,39.095459],"type":"Point"}
}