{
  "type": "Feature",
  "properties": {
    "addr:full":"1417 N Hawthorne Ln Indianapolis IN 46219",
    "addr:housenumber":"1417",
    "addr:postcode":"46219",
    "addr:street":"N Hawthorne Ln",
    "iso:country":"US",
    "sg:address":"1417 N Hawthorne Ln",
    "sg:city":"Indianapolis",
    "sg:classifiers":[
        {
            "category":"Social Services",
            "type":"Services"
        }
    ],
    "sg:phone":"+1 317 353 6709",
    "sg:postcode":"46219",
    "sg:province":"IN",
    "sg:tags":[
        "recovery",
        "relief",
        "disaster"
    ],
    "wof:name":"Nehemiah House Inc",
    "wof:placetype":"venue"
},
  "geometry": {"coordinates":[-86.079066,39.787275],"type":"Point"}
}