{
  "type": "Feature",
  "properties": {
    "addr:full":"4035 Botanical Ln Lafayette IN 47905",
    "addr:housenumber":"4035",
    "addr:postcode":"47905",
    "addr:street":"Botanical Ln",
    "iso:country":"US",
    "sg:address":"4035 Botanical Ln",
    "sg:city":"Lafayette",
    "sg:classifiers":[
        {
            "category":"Insurance",
            "subcategory":"Insurance Agent",
            "type":"Services"
        }
    ],
    "sg:phone":"+1 765 420 8222",
    "sg:postcode":"47905",
    "sg:province":"IN",
    "wof:name":"A M Bough Insurance",
    "wof:placetype":"venue"
},
  "geometry": {"coordinates":[-86.826691,40.44365],"type":"Point"}
}