{
  "type": "Feature",
  "properties": {
    "iso:country":"US",
    "sg:address":"3401 Halls Corner Rd",
    "sg:city":"Underwood",
    "sg:classifiers":[
        {
            "category":"Building & Trades",
            "subcategory":"Construction",
            "type":"Services"
        }
    ],
    "sg:phone":"+1 812 294 1833",
    "sg:postcode":"47177",
    "sg:province":"IN",
    "sg:tags":[
        "excavation",
        "contractor"
    ],
    "wof:name":"Collings Excavating",
    "wof:placetype":"venue"
},
  "geometry": {"coordinates":[-85.763639,38.591175],"type":"Point"}
}