{
  "type": "Feature",
  "properties": {
    "addr:full":"2400 N Heidelbach Ave Evansville IN 47711",
    "addr:housenumber":"2400",
    "addr:postcode":"47711",
    "addr:street":"N Heidelbach Ave",
    "iso:country":"US",
    "sg:address":"2400 N Heidelbach Ave",
    "sg:city":"Evansville",
    "sg:classifiers":[
        {
            "category":"Autos & Motor Vehicles",
            "subcategory":"Automobile Sales",
            "type":"Retail Goods"
        }
    ],
    "sg:phone":"+1 812 471 4967",
    "sg:postcode":"47711",
    "sg:province":"IN",
    "sg:tags":[
        "car",
        "dealer"
    ],
    "wof:name":"Kelley's Northside Chevrolet",
    "wof:placetype":"venue"
},
  "geometry": {"coordinates":[-87.560739,38.001048],"type":"Point"}
}