{
  "type": "Feature",
  "properties": {
    "iso:country":"US",
    "sg:address":"1202 Parkview Dr",
    "sg:city":"Salem",
    "sg:classifiers":[
        {
            "category":"Building & Trades",
            "subcategory":"Construction",
            "type":"Services"
        }
    ],
    "sg:phone":"+1 812 883 4976",
    "sg:postcode":"47167",
    "sg:province":"IN",
    "sg:tags":[
        "house"
    ],
    "wof:name":"John Mithcell Constr",
    "wof:placetype":"venue"
},
  "geometry": {"coordinates":[-86.089166,38.616002],"type":"Point"}
}