{
  "type": "Feature",
  "properties": {
    "iso:country":"US",
    "sg:address":"16351 Fairfield Ln",
    "sg:city":"Granger",
    "sg:classifiers":[
        {
            "category":"Building & Trades",
            "subcategory":"Construction",
            "type":"Services"
        }
    ],
    "sg:phone":"+1 574 247 1942",
    "sg:postcode":"46530",
    "sg:province":"IN",
    "sg:tags":[
        "hanging",
        "contractor"
    ],
    "wof:name":"Satin Finish",
    "wof:placetype":"venue"
},
  "geometry": {"coordinates":[-86.185501,41.742629],"type":"Point"}
}