{
  "type": "Feature",
  "properties": {
    "iso:country":"US",
    "sg:address":"6300 Brookville Rd",
    "sg:city":"Indianapolis",
    "sg:classifiers":[
        {
            "category":"Shopping",
            "type":"Retail Goods"
        }
    ],
    "sg:phone":"+1 317 375 7540",
    "sg:postcode":"46219",
    "sg:province":"IN",
    "sg:tags":[
        "candle"
    ],
    "wof:name":"Heavenly Scents Candle Co",
    "wof:placetype":"venue"
},
  "geometry": {"coordinates":[-86.055856,39.756303],"type":"Point"}
}