{
  "type": "Feature",
  "properties": {
    "iso:country":"US",
    "sg:address":"3430 W 3rd St",
    "sg:city":"Bloomington",
    "sg:classifiers":[
        {
            "category":"Retail",
            "subcategory":"Car Wash",
            "type":"Services"
        }
    ],
    "sg:phone":"+1 812 331 9900",
    "sg:postcode":"47404",
    "sg:province":"IN",
    "wof:name":"Third Street Car Wash the",
    "wof:placetype":"venue"
},
  "geometry": {"coordinates":[-86.57710299999999,39.1647],"type":"Point"}
}