{
  "type": "Feature",
  "properties": {
    "addr:full":"733 E Broadway St Fortville IN 46040",
    "addr:housenumber":"733",
    "addr:postcode":"46040",
    "addr:street":"E Broadway St",
    "iso:country":"US",
    "sg:address":"733 E Broadway St",
    "sg:city":"Fortville",
    "sg:classifiers":[
        {
            "category":"Personal",
            "subcategory":"Beauty Salon",
            "type":"Services"
        }
    ],
    "sg:phone":"+1 317 485 5295",
    "sg:postcode":"46040",
    "sg:province":"IN",
    "wof:name":"C J & Co Hair Design",
    "wof:placetype":"venue"
},
  "geometry": {"coordinates":[-85.83975,39.936659],"type":"Point"}
}