{
  "type": "Feature",
  "properties": {
    "iso:country":"US",
    "sg:address":"1831 Fisher Ave",
    "sg:city":"Indianapolis",
    "sg:classifiers":[
        {
            "category":"Organizations",
            "subcategory":"Membership Organization",
            "type":"Services"
        }
    ],
    "sg:phone":"+1 317 244 9554",
    "sg:postcode":"46224",
    "sg:province":"IN",
    "wof:name":"Latest Craze Inc",
    "wof:placetype":"venue"
},
  "geometry": {"coordinates":[-86.245504,39.79209],"type":"Point"}
}