{
  "type": "Feature",
  "properties": {
    "addr:full":"220 E Sycamore St Kokomo IN 46901",
    "addr:housenumber":"220",
    "addr:postcode":"46901",
    "addr:street":"E Sycamore St",
    "iso:country":"US",
    "sg:address":"220 E Sycamore St",
    "sg:city":"Kokomo",
    "sg:classifiers":[
        {
            "category":"Professional",
            "subcategory":"Advertising",
            "type":"Services"
        }
    ],
    "sg:phone":"+1 765 868 3210",
    "sg:postcode":"46901",
    "sg:province":"IN",
    "sg:tags":[
        "guide"
    ],
    "wof:name":"Yellowbook USA",
    "wof:placetype":"venue"
},
  "geometry": {"coordinates":[-86.128947,40.486559],"type":"Point"}
}