{
  "type": "Feature",
  "properties": {
    "iso:country":"US",
    "sg:address":"426 Bank St",
    "sg:city":"New Albany",
    "sg:classifiers":[
        {
            "category":"Health Services",
            "subcategory":"Nursing And Care Facility",
            "type":"Services"
        }
    ],
    "sg:phone":"+1 812 948 9161",
    "sg:postcode":"47150",
    "sg:province":"IN",
    "sg:tags":[
        "skilled"
    ],
    "wof:name":"Nursing Home Pre Admission",
    "wof:placetype":"venue"
},
  "geometry": {"coordinates":[-85.82232999999999,38.287187],"type":"Point"}
}