{
  "type": "Feature",
  "properties": {
    "iso:country":"US",
    "sg:address":"12355 Michigan Rd",
    "sg:city":"Plymouth",
    "sg:classifiers":[
        {
            "category":"Restaurant",
            "type":"Food & Drink"
        }
    ],
    "sg:phone":"+1 574 936 7173",
    "sg:postcode":"46563",
    "sg:province":"IN",
    "wof:name":"Cindy's Restaurant",
    "wof:placetype":"venue"
},
  "geometry": {"coordinates":[-86.276824,41.300064],"type":"Point"}
}