{
  "type": "Feature",
  "properties": {
    "iso:country":"US",
    "sg:address":"4739 Indianapolis Blvd",
    "sg:city":"East Chicago",
    "sg:classifiers":[
        {
            "category":"Restaurant",
            "type":"Food & Drink"
        }
    ],
    "sg:phone":"+1 219 397 0068",
    "sg:postcode":"46312",
    "sg:province":"IN",
    "sg:tags":[
        "pizza"
    ],
    "sg:website":"littlecaesars.com",
    "wof:name":"Little Caesars Pizza",
    "wof:placetype":"venue"
},
  "geometry": {"coordinates":[-87.480797,41.628471],"type":"Point"}
}