{
  "type": "Feature",
  "properties": {
    "iso:country":"US",
    "sg:address":"409 E Eichel Ave",
    "sg:city":"Evansville",
    "sg:classifiers":[
        {
            "category":"Organizations",
            "subcategory":"Religious Organization",
            "type":"Services"
        }
    ],
    "sg:phone":"+1 812 401 4031",
    "sg:postcode":"47711",
    "sg:province":"IN",
    "wof:name":"Full Gospel Mission Inc",
    "wof:placetype":"venue"
},
  "geometry": {"coordinates":[-87.558531,37.991125],"type":"Point"}
}