{
  "type": "Feature",
  "properties": {
    "iso:country":"US",
    "sg:address":"210 W Whitley St",
    "sg:city":"Churubusco",
    "sg:classifiers":[
        {
            "category":"Health Services",
            "subcategory":"Doctor",
            "type":"Services"
        }
    ],
    "sg:phone":"+1 260 693 3921",
    "sg:postcode":"46723",
    "sg:province":"IN",
    "sg:tags":[
        "dentist"
    ],
    "wof:name":"David W Bolinger DDS",
    "wof:placetype":"venue"
},
  "geometry": {"coordinates":[-85.31997699999999,41.23038],"type":"Point"}
}