{
  "type": "Feature",
  "properties": {
    "iso:country":"US",
    "sg:address":"733 Meridian Rd",
    "sg:city":"Valparaiso",
    "sg:classifiers":[
        {
            "category":"Professional",
            "subcategory":"Accounting & Tax Preparation",
            "type":"Services"
        }
    ],
    "sg:phone":"+1 219 531 5587",
    "sg:postcode":"46385",
    "sg:province":"IN",
    "sg:tags":[
        "return",
        "filing"
    ],
    "wof:name":"Marcy's Tax Svc",
    "wof:placetype":"venue"
},
  "geometry": {"coordinates":[-87.066125,41.539923],"type":"Point"}
}