{
  "type": "Feature",
  "properties": {
    "addr:full":"319 Black Oak Dr Michigan City IN 46360",
    "addr:housenumber":"319",
    "addr:postcode":"46360",
    "addr:street":"Black Oak Dr",
    "iso:country":"US",
    "sg:address":"319 Black Oak Dr",
    "sg:city":"Michigan City",
    "sg:classifiers":[
        {
            "category":"Manufacturing",
            "subcategory":"Signs",
            "type":"Manufacturing & Wholesale Goods"
        }
    ],
    "sg:phone":"+1 219 872 8467",
    "sg:postcode":"46360",
    "sg:province":"IN",
    "sg:tags":[
        "specialty",
        "mfg"
    ],
    "wof:name":"Sweet Keepsakes",
    "wof:placetype":"venue"
},
  "geometry": {"coordinates":[-86.858034,41.698115],"type":"Point"}
}