{
  "type": "Feature",
  "properties": {
    "iso:country":"US",
    "sg:address":"101 S State Rd 3",
    "sg:city":"Westport",
    "sg:classifiers":[
        {
            "category":"Organizations",
            "subcategory":"Religious Organization",
            "type":"Services"
        }
    ],
    "sg:phone":"+1 812 591 2107",
    "sg:postcode":"47283",
    "sg:province":"IN",
    "sg:tags":[
        "church"
    ],
    "wof:name":"Life Apostolic Ministries",
    "wof:placetype":"venue"
},
  "geometry": {"coordinates":[-85.583126,39.175388],"type":"Point"}
}