{
  "type": "Feature",
  "properties": {
    "iso:country":"US",
    "sg:address":"6090 S Boundary Pike",
    "sg:city":"Portland",
    "sg:classifiers":[
        {
            "category":"Professional",
            "type":"Services"
        }
    ],
    "sg:phone":"+1 260 726 9769",
    "sg:postcode":"47371",
    "sg:province":"IN",
    "sg:tags":[
        "establishment"
    ],
    "wof:name":"Link Brothers",
    "wof:placetype":"venue"
},
  "geometry": {"coordinates":[-84.93271900000001,40.351323],"type":"Point"}
}