{
  "type": "Feature",
  "properties": {
    "addr:full":"1201 Michigan Ave Logansport IN 46947",
    "addr:housenumber":"1201",
    "addr:postcode":"46947",
    "addr:street":"Michigan Ave",
    "iso:country":"US",
    "sg:address":"1201 Michigan Ave",
    "sg:city":"Logansport",
    "sg:classifiers":[
        {
            "category":"Health Services",
            "subcategory":"Doctor",
            "type":"Services"
        }
    ],
    "sg:phone":"+1 574 722 1313",
    "sg:postcode":"46947",
    "sg:province":"IN",
    "sg:tags":[
        "physician",
        "surgeon"
    ],
    "wof:name":"Associated Radiologists Inc",
    "wof:placetype":"venue"
},
  "geometry": {"coordinates":[-86.360142,40.764286],"type":"Point"}
}