{
  "type": "Feature",
  "properties": {
    "iso:country":"US",
    "sg:address":"620 McKinnie Ave",
    "sg:city":"Fort Wayne",
    "sg:classifiers":[
        {
            "category":"Food & Beverages",
            "subcategory":"Groceries & Convenience Stores",
            "type":"Retail Goods"
        }
    ],
    "sg:phone":"+1 260 456 2093",
    "sg:postcode":"46806",
    "sg:province":"IN",
    "wof:name":"Kirk's Mini Mart",
    "wof:placetype":"venue"
},
  "geometry": {"coordinates":[-85.127797,41.0461],"type":"Point"}
}