{
  "type": "Feature",
  "properties": {
    "iso:country":"US",
    "sg:address":"12131 State Rd 23",
    "sg:city":"Granger",
    "sg:classifiers":[
        {
            "category":"Shopping",
            "subcategory":"Used Merchandise",
            "type":"Retail Goods"
        }
    ],
    "sg:phone":"+1 574 271 8791",
    "sg:postcode":"46530",
    "sg:province":"IN",
    "sg:tags":[
        "flea",
        "market"
    ],
    "wof:name":"Michiana's Flea Market & Antqs",
    "wof:placetype":"venue"
},
  "geometry": {"coordinates":[-86.109422,41.753599],"type":"Point"}
}