{
  "type": "Feature",
  "properties": {
    "iso:country":"US",
    "sg:address":"15810 River Birch Rd",
    "sg:city":"Westfield",
    "sg:classifiers":[
        {
            "category":"Real Estate",
            "subcategory":"Architect",
            "type":"Services"
        }
    ],
    "sg:phone":"+1 317 867 0880",
    "sg:postcode":"46074",
    "sg:province":"IN",
    "sg:tags":[
        "home",
        "planning",
        "design"
    ],
    "wof:name":"Schneider Designs Inc",
    "wof:placetype":"venue"
},
  "geometry": {"coordinates":[-86.162133,40.016092],"type":"Point"}
}