{
  "type": "Feature",
  "properties": {
    "iso:country":"US",
    "sg:address":"11836 Woodmar Pl",
    "sg:city":"Cedar Lake",
    "sg:classifiers":[
        {
            "category":"Real Estate",
            "subcategory":"Real Estate Agent",
            "type":"Services"
        }
    ],
    "sg:phone":"+1 219 374 7430",
    "sg:postcode":"46303",
    "sg:province":"IN",
    "wof:name":"Woodmar Street Properties",
    "wof:placetype":"venue"
},
  "geometry": {"coordinates":[-87.476009,41.404213],"type":"Point"}
}