{
  "type": "Feature",
  "properties": {
    "iso:country":"US",
    "sg:address":"1221 Appletree Ln",
    "sg:city":"Kokomo",
    "sg:classifiers":[
        {
            "category":"Manufacturing",
            "subcategory":"Retail Goods",
            "type":"Manufacturing & Wholesale Goods"
        }
    ],
    "sg:phone":"+1 765 457 9344",
    "sg:postcode":"46902",
    "sg:province":"IN",
    "sg:tags":[
        "assembly",
        "fabricating"
    ],
    "sg:website":"www.productaction.com",
    "wof:name":"Product Action Intl",
    "wof:placetype":"venue"
},
  "geometry": {"coordinates":[-86.117571,40.465195],"type":"Point"}
}