{
  "type": "Feature",
  "properties": {
    "addr:full":"4902 N College Ave Indianapolis IN 46205",
    "addr:housenumber":"4902",
    "addr:postcode":"46205",
    "addr:street":"N College Ave",
    "iso:country":"US",
    "sg:address":"4902 N College Ave",
    "sg:city":"Indianapolis",
    "sg:classifiers":[
        {
            "category":"Restaurant",
            "type":"Food & Drink"
        }
    ],
    "sg:phone":"+1 317 931 0932",
    "sg:postcode":"46205",
    "sg:province":"IN",
    "wof:name":"Original Queen Fish & More",
    "wof:placetype":"venue"
},
  "geometry": {"coordinates":[-86.145794,39.843907],"type":"Point"}
}