{
  "type": "Feature",
  "properties": {
    "iso:country":"US",
    "sg:address":"1206 W Main St",
    "sg:city":"Mitchell",
    "sg:classifiers":[
        {
            "category":"Shopping",
            "subcategory":"Department Store",
            "type":"Retail Goods"
        }
    ],
    "sg:phone":"+1 812 849 2777",
    "sg:postcode":"47446",
    "sg:province":"IN",
    "sg:tags":[
        "shop"
    ],
    "wof:name":"Ben Franklin",
    "wof:placetype":"venue"
},
  "geometry": {"coordinates":[-86.482648,38.73159],"type":"Point"}
}