{
  "type": "Feature",
  "properties": {
    "iso:country":"US",
    "sg:address":"135 E Main St",
    "sg:city":"Atlanta",
    "sg:classifiers":[
        {
            "category":"Shopping",
            "subcategory":"Musical Instruments",
            "type":"Retail Goods"
        }
    ],
    "sg:phone":"+1 765 292 2312",
    "sg:postcode":"46031",
    "sg:province":"IN",
    "wof:name":"Atlanta Music Hall",
    "wof:placetype":"venue"
},
  "geometry": {"coordinates":[-86.025796,40.216212],"type":"Point"}
}