{
  "type": "Feature",
  "properties": {
    "addr:full":"1797 W US Hwy 30 Hanna IN 46340",
    "addr:housenumber":"1797",
    "addr:postcode":"46340",
    "addr:street":"W Us Hwy 30",
    "iso:country":"US",
    "sg:address":"1797 W US Hwy 30",
    "sg:city":"Hanna",
    "sg:classifiers":[
        {
            "category":"Restaurant",
            "type":"Food & Drink"
        }
    ],
    "sg:phone":"+1 219 797 2417",
    "sg:postcode":"46340",
    "sg:province":"IN",
    "sg:tags":[
        "eating"
    ],
    "wof:name":"Arbys",
    "wof:placetype":"venue"
},
  "geometry": {"coordinates":[-86.732364,41.405041],"type":"Point"}
}