{
  "type": "Feature",
  "properties": {
    "iso:country":"US",
    "sg:address":"1600 Osolo Rd",
    "sg:city":"Elkhart",
    "sg:classifiers":[
        {
            "category":"Professional",
            "subcategory":"Research",
            "type":"Services"
        }
    ],
    "sg:phone":"+1 574 262 3811",
    "sg:postcode":"46514",
    "sg:province":"IN",
    "sg:tags":[
        "environmental",
        "ecological"
    ],
    "wof:name":"Romcraft Inc",
    "wof:placetype":"venue"
},
  "geometry": {"coordinates":[-85.94671099999999,41.70607],"type":"Point"}
}