{
  "type": "Feature",
  "properties": {
    "iso:country":"US",
    "sg:address":"862 Westfield Dr",
    "sg:city":"Bluffton",
    "sg:classifiers":[
        {
            "category":"Retail",
            "subcategory":"Laundry & Dry Cleaning",
            "type":"Services"
        }
    ],
    "sg:phone":"+1 260 824 3845",
    "sg:postcode":"46714",
    "sg:province":"IN",
    "wof:name":"Toms Carpet & Upholstery Clg",
    "wof:placetype":"venue"
},
  "geometry": {"coordinates":[-85.160773,40.74615],"type":"Point"}
}