{
  "type": "Feature",
  "properties": {
    "iso:country":"US",
    "sg:address":"2405 Station St",
    "sg:city":"Indianapolis",
    "sg:classifiers":[
        {
            "category":"Retail",
            "subcategory":"Auto Repair",
            "type":"Services"
        }
    ],
    "sg:phone":"+1 317 546 7094",
    "sg:postcode":"46218",
    "sg:province":"IN",
    "sg:tags":[
        "repairing",
        "automobile"
    ],
    "wof:name":"Irons Auto",
    "wof:placetype":"venue"
},
  "geometry": {"coordinates":[-86.104005,39.802408],"type":"Point"}
}