{
  "type": "Feature",
  "properties": {
    "addr:full":"607 E Main St Fowler IN 47944",
    "addr:housenumber":"607",
    "addr:postcode":"47944",
    "addr:street":"E Main St",
    "iso:country":"US",
    "sg:address":"607 E Main St",
    "sg:city":"Fowler",
    "sg:classifiers":[
        {
            "category":"Building & Trades",
            "subcategory":"Construction",
            "type":"Services"
        }
    ],
    "sg:phone":"+1 765 884 0999",
    "sg:postcode":"47944",
    "sg:province":"IN",
    "sg:tags":[
        "heavy"
    ],
    "wof:name":"Kenbuild Construction",
    "wof:placetype":"venue"
},
  "geometry": {"coordinates":[-87.31439399999999,40.622569],"type":"Point"}
}