{
  "type": "Feature",
  "properties": {
    "iso:country":"US",
    "sg:address":"110 S Taylor St",
    "sg:city":"South Bend",
    "sg:classifiers":[
        {
            "category":"Professional",
            "subcategory":"Lawyer & Legal Services",
            "type":"Services"
        }
    ],
    "sg:phone":"+1 574 289 7112",
    "sg:postcode":"46601",
    "sg:province":"IN",
    "sg:tags":[
        "attorney"
    ],
    "wof:name":"Berger & Gammage",
    "wof:placetype":"venue"
},
  "geometry": {"coordinates":[-86.257133,41.675788],"type":"Point"}
}