{
  "type": "Feature",
  "properties": {
    "iso:country":"US",
    "sg:address":"4625 W 86th St",
    "sg:city":"Indianapolis",
    "sg:classifiers":[
        {
            "category":"Professional",
            "subcategory":"Computer Services",
            "type":"Services"
        }
    ],
    "sg:phone":"+1 317 802 0758",
    "sg:postcode":"46268",
    "sg:province":"IN",
    "sg:tags":[
        "developer"
    ],
    "sg:website":"www.manatron.com",
    "wof:name":"Manatron Inc",
    "wof:placetype":"venue"
},
  "geometry": {"coordinates":[-86.237729,39.911409],"type":"Point"}
}