{
  "type": "Feature",
  "properties": {
    "iso:country":"US",
    "sg:address":"5821 Coppock Dr",
    "sg:city":"Indianapolis",
    "sg:classifiers":[
        {
            "category":"Professional",
            "subcategory":"Management & Consulting",
            "type":"Services"
        }
    ],
    "sg:phone":"+1 317 627 8515",
    "sg:postcode":"46221",
    "sg:province":"IN",
    "sg:tags":[
        "business"
    ],
    "wof:name":"Service Management Consulting",
    "wof:placetype":"venue"
},
  "geometry": {"coordinates":[-86.262035,39.680086],"type":"Point"}
}