{
  "type": "Feature",
  "properties": {
    "iso:country":"US",
    "sg:address":"225 Heady Ln",
    "sg:city":"Fishers",
    "sg:classifiers":[
        {
            "category":"Shopping",
            "subcategory":"Computers & Home Electronics",
            "type":"Retail Goods"
        }
    ],
    "sg:phone":"+1 317 842 3813",
    "sg:postcode":"46038",
    "sg:province":"IN",
    "wof:name":"Daves In Home Computer Servic",
    "wof:placetype":"venue"
},
  "geometry": {"coordinates":[-86.031257,39.967661],"type":"Point"}
}