{
  "type": "Feature",
  "properties": {
    "iso:country":"US",
    "sg:address":"802 E Lewis and Clark Pkwy",
    "sg:city":"Clarksville",
    "sg:classifiers":[
        {
            "category":"Restaurant",
            "type":"Food & Drink"
        }
    ],
    "sg:menulink":"http://www.allmenus.com/in/jeffersonville/79484-pizza-hut/menu/",
    "sg:phone":"+1 812 282 8411",
    "sg:postcode":"47129",
    "sg:province":"IN",
    "sg:tags":[
        "american",
        "pizza"
    ],
    "wof:name":"Pizza Hut",
    "wof:placetype":"venue"
},
  "geometry": {"coordinates":[-85.76237500000001,38.313757],"type":"Point"}
}