{
  "type": "Feature",
  "properties": {
    "iso:country":"US",
    "sg:address":"215 E Indiana Ave",
    "sg:city":"Elkhart",
    "sg:classifiers":[
        {
            "category":"Education",
            "subcategory":"School",
            "type":"Public Place"
        }
    ],
    "sg:phone":"+1 574 295 4840",
    "sg:postcode":"46516",
    "sg:province":"IN",
    "wof:name":"Roosevelt Elementary School",
    "wof:placetype":"venue"
},
  "geometry": {"coordinates":[-85.963144,41.673844],"type":"Point"}
}