{
  "type": "Feature",
  "properties": {
    "iso:country":"US",
    "sg:address":"19068 Duck Creek Rd",
    "sg:city":"Metamora",
    "sg:classifiers":[
        {
            "category":"Shopping",
            "subcategory":"Crafts & Fabrics",
            "type":"Retail Goods"
        }
    ],
    "sg:phone":"+1 765 647 5786",
    "sg:postcode":"47030",
    "sg:province":"IN",
    "sg:tags":[
        "material",
        "quilting",
        "supply"
    ],
    "wof:name":"Needle & Thread Creations",
    "wof:placetype":"venue"
},
  "geometry": {"coordinates":[-85.131969,39.475096],"type":"Point"}
}