{
  "type": "Feature",
  "properties": {
    "iso:country":"US",
    "sg:address":"9577 W 400 N",
    "sg:city":"Farmland",
    "sg:classifiers":[
        {
            "category":"Sports & Exercise",
            "subcategory":"Golf",
            "type":"Entertainment"
        }
    ],
    "sg:phone":"+1 765 468 6321",
    "sg:postcode":"47340",
    "sg:province":"IN",
    "sg:tags":[
        "course"
    ],
    "wof:name":"Hickory Hills Golf Club",
    "wof:placetype":"venue"
},
  "geometry": {"coordinates":[-85.159549,40.22079],"type":"Point"}
}