{
  "type": "Feature",
  "properties": {
    "iso:country":"US",
    "sg:address":"101 E 2nd St",
    "sg:city":"Marion",
    "sg:classifiers":[
        {
            "category":"Government",
            "subcategory":"Court House",
            "type":"Public Place"
        }
    ],
    "sg:phone":"+1 765 664 5527",
    "sg:postcode":"46952",
    "sg:province":"IN",
    "sg:tags":[
        "county"
    ],
    "wof:name":"Grant County Circuit Court",
    "wof:placetype":"venue"
},
  "geometry": {"coordinates":[-85.658532,40.559747],"type":"Point"}
}