{
  "type": "Feature",
  "properties": {
    "addr:full":"1400 E Ireland Rd South Bend IN 46614",
    "addr:housenumber":"1400",
    "addr:postcode":"46614",
    "addr:street":"E Ireland Rd",
    "iso:country":"US",
    "sg:address":"1400 E Ireland Rd",
    "sg:city":"South Bend",
    "sg:classifiers":[
        {
            "category":"Coffee & Tea",
            "type":"Food & Drink"
        }
    ],
    "sg:menulink":"http://www.allmenus.com/in/centre/112273-starbucks-coffee/menu/",
    "sg:phone":"+1 579 299 1402",
    "sg:postcode":"46614",
    "sg:province":"IN",
    "sg:tags":[
        "american"
    ],
    "wof:name":"Starbucks Coffee",
    "wof:placetype":"venue"
},
  "geometry": {"coordinates":[-86.226895,41.629446],"type":"Point"}
}