{
  "type": "Feature",
  "properties": {
    "iso:country":"US",
    "sg:address":"800 Main St",
    "sg:city":"Clay City",
    "sg:classifiers":[
        {
            "category":"Professional",
            "type":"Services"
        }
    ],
    "sg:phone":"+1 812 939 2159",
    "sg:postcode":"47841",
    "sg:province":"IN",
    "sg:tags":[
        "establishment"
    ],
    "wof:name":"L & S Sports",
    "wof:placetype":"venue"
},
  "geometry": {"coordinates":[-87.112789,39.276497],"type":"Point"}
}