{
  "type": "Feature",
  "properties": {
    "addr:full":"5140 Old Boonville Hwy Evansville IN 47715",
    "addr:housenumber":"5140",
    "addr:postcode":"47715",
    "addr:street":"Old Boonville Hwy",
    "iso:country":"US",
    "sg:address":"5140 Old Boonville Hwy",
    "sg:city":"Evansville",
    "sg:classifiers":[
        {
            "category":"Home & Garden",
            "subcategory":"Household Appliances",
            "type":"Retail Goods"
        }
    ],
    "sg:phone":"+1 812 473 3960",
    "sg:postcode":"47715",
    "sg:province":"IN",
    "sg:tags":[
        "cleaners",
        "vacuum"
    ],
    "wof:name":"Kirby's Service Inc",
    "wof:placetype":"venue"
},
  "geometry": {"coordinates":[-87.48849,37.994394],"type":"Point"}
}