{
  "type": "Feature",
  "properties": {
    "addr:full":"415 Prion Ct Lafayette IN 47909",
    "addr:housenumber":"415",
    "addr:postcode":"47909",
    "addr:street":"Prion Ct",
    "iso:country":"US",
    "sg:address":"415 Prion Ct",
    "sg:city":"Lafayette",
    "sg:classifiers":[
        {
            "category":"Professional",
            "subcategory":"Accounting & Tax Preparation",
            "type":"Services"
        }
    ],
    "sg:phone":"+1 765 538 3637",
    "sg:postcode":"47909",
    "sg:province":"IN",
    "sg:tags":[
        "accountant"
    ],
    "wof:name":"Dunten & Co",
    "wof:placetype":"venue"
},
  "geometry": {"coordinates":[-86.91288900000001,40.347325],"type":"Point"}
}