{
  "type": "Feature",
  "properties": {
    "iso:country":"US",
    "sg:address":"1888 Olde Mill Ct",
    "sg:city":"Newburgh",
    "sg:classifiers":[
        {
            "category":"Professional",
            "subcategory":"Management & Consulting",
            "type":"Services"
        }
    ],
    "sg:phone":"+1 812 490 3147",
    "sg:postcode":"47630",
    "sg:province":"IN",
    "sg:tags":[
        "business"
    ],
    "wof:name":"Tm",
    "wof:placetype":"venue"
},
  "geometry": {"coordinates":[-87.370631,38.005036],"type":"Point"}
}