{
  "type": "Feature",
  "properties": {
    "iso:country":"US",
    "sg:address":"1060 S Old Hwy 27",
    "sg:city":"Winchester",
    "sg:classifiers":[
        {
            "category":"Organizations",
            "subcategory":"Religious Organization",
            "type":"Services"
        }
    ],
    "sg:phone":"+1 765 584 3199",
    "sg:postcode":"47394",
    "sg:province":"IN",
    "sg:tags":[
        "church"
    ],
    "wof:name":"Wesleyan Holiness Church",
    "wof:placetype":"venue"
},
  "geometry": {"coordinates":[-84.975149,40.153856],"type":"Point"}
}