{
  "type": "Feature",
  "properties": {
    "iso:country":"US",
    "sg:address":"1013 W Commerce Dr",
    "sg:city":"Decatur",
    "sg:classifiers":[
        {
            "category":"Manufacturing",
            "subcategory":"Metals",
            "type":"Manufacturing & Wholesale Goods"
        }
    ],
    "sg:phone":"+1 260 728 4222",
    "sg:postcode":"46733",
    "sg:province":"IN",
    "sg:tags":[
        "coating",
        "powder"
    ],
    "wof:name":"Panacea Paints & Coatings Inc",
    "wof:placetype":"venue"
},
  "geometry": {"coordinates":[-84.959732,40.822046],"type":"Point"}
}