{
  "type": "Feature",
  "properties": {
    "iso:country":"US",
    "sg:address":"4202 Grant Line Rd",
    "sg:city":"New Albany",
    "sg:classifiers":[
        {
            "category":"Real Estate",
            "subcategory":"Real Estate Operator",
            "type":"Services"
        }
    ],
    "sg:phone":"+1 812 944 0941",
    "sg:postcode":"47150",
    "sg:province":"IN",
    "sg:tags":[
        "apartment"
    ],
    "wof:name":"Carriage House Apartments",
    "wof:placetype":"venue"
},
  "geometry": {"coordinates":[-85.81791,38.33533],"type":"Point"}
}