{
  "type": "Feature",
  "properties": {
    "iso:country":"US",
    "sg:address":"1522 E 10th St",
    "sg:city":"Jeffersonville",
    "sg:classifiers":[
        {
            "category":"Autos & Motor Vehicles",
            "subcategory":"Automobile Sales",
            "type":"Retail Goods"
        }
    ],
    "sg:phone":"+1 812 285 8929",
    "sg:postcode":"47130",
    "sg:province":"IN",
    "sg:tags":[
        "car",
        "dealer"
    ],
    "sg:website":"www.byridercars.com",
    "wof:name":"J D Byrider Auto Sales",
    "wof:placetype":"venue"
},
  "geometry": {"coordinates":[-85.72738,38.292012],"type":"Point"}
}