{
  "type": "Feature",
  "properties": {
    "iso:country":"US",
    "sg:address":"7960 E Co Rd 250 S",
    "sg:city":"Dugger",
    "sg:classifiers":[
        {
            "category":"Organizations",
            "subcategory":"Religious Organization",
            "type":"Services"
        }
    ],
    "sg:phone":"+1 812 648 2873",
    "sg:postcode":"47848",
    "sg:province":"IN",
    "sg:tags":[
        "church"
    ],
    "wof:name":"Bethel Community Church",
    "wof:placetype":"venue"
},
  "geometry": {"coordinates":[-87.260407,39.04554],"type":"Point"}
}