{
  "type": "Feature",
  "properties": {
    "iso:country":"US",
    "sg:address":"720 Reid St",
    "sg:city":"Connersville",
    "sg:classifiers":[
        {
            "category":"Farming",
            "subcategory":"Farm",
            "type":"Manufacturing & Wholesale Goods"
        }
    ],
    "sg:phone":"+1 765 825 2397",
    "sg:postcode":"47331",
    "sg:province":"IN",
    "sg:tags":[
        "crop",
        "general"
    ],
    "wof:name":"Harry Hermann",
    "wof:placetype":"venue"
},
  "geometry": {"coordinates":[-85.14278,39.645634],"type":"Point"}
}