{
  "type": "Feature",
  "properties": {
    "iso:country":"US",
    "sg:address":"1438 Janette Ct",
    "sg:city":"Danville",
    "sg:classifiers":[
        {
            "category":"Shopping",
            "subcategory":"Stationery & Office Supplies",
            "type":"Retail Goods"
        }
    ],
    "sg:phone":"+1 317 536 2972",
    "sg:postcode":"46122",
    "sg:province":"IN",
    "wof:name":"Keystone Office",
    "wof:placetype":"venue"
},
  "geometry": {"coordinates":[-86.500379,39.774543],"type":"Point"}
}