{
  "type": "Feature",
  "properties": {
    "iso:country":"US",
    "sg:address":"346 W Cleveland Rd",
    "sg:city":"Granger",
    "sg:classifiers":[
        {
            "category":"Banks & Credit Unions",
            "subcategory":"Bank",
            "type":"Services"
        }
    ],
    "sg:phone":"+1 574 277 9342",
    "sg:postcode":"46530",
    "sg:province":"IN",
    "wof:name":"Teacher Credit Union",
    "wof:placetype":"venue"
},
  "geometry": {"coordinates":[-86.18542600000001,41.723979],"type":"Point"}
}