{
  "type": "Feature",
  "properties": {
    "iso:country":"US",
    "sg:address":"2703 S Meridian St",
    "sg:city":"Indianapolis",
    "sg:classifiers":[
        {
            "category":"Real Estate",
            "subcategory":"Developer",
            "type":"Services"
        }
    ],
    "sg:phone":"+1 317 786 7733",
    "sg:postcode":"46225",
    "sg:province":"IN",
    "sg:tags":[
        "cemetery"
    ],
    "wof:name":"Concordia Cemetery",
    "wof:placetype":"venue"
},
  "geometry": {"coordinates":[-86.158772,39.727346],"type":"Point"}
}