{
  "type": "Feature",
  "properties": {
    "iso:country":"US",
    "sg:address":"5770 Broadway",
    "sg:city":"Merrillville",
    "sg:classifiers":[
        {
            "category":"Professional",
            "subcategory":"Management & Consulting",
            "type":"Services"
        }
    ],
    "sg:phone":"+1 219 980 4252",
    "sg:postcode":"46410",
    "sg:province":"IN",
    "sg:tags":[
        "consultant"
    ],
    "sg:website":"www.kandlconsultants.com",
    "wof:name":"K & L Consultants",
    "wof:placetype":"venue"
},
  "geometry": {"coordinates":[-87.33616499999999,41.511385],"type":"Point"}
}