{
  "type": "Feature",
  "properties": {
    "iso:country":"US",
    "sg:address":"133 SW I St",
    "sg:city":"Richmond",
    "sg:classifiers":[
        {
            "category":"Retail",
            "subcategory":"Repair Shop",
            "type":"Services"
        }
    ],
    "sg:phone":"+1 765 966 7881",
    "sg:postcode":"47374",
    "sg:province":"IN",
    "sg:tags":[
        "appliance"
    ],
    "wof:name":"Bob's Appliance Svc",
    "wof:placetype":"venue"
},
  "geometry": {"coordinates":[-84.90526,39.817738],"type":"Point"}
}