{
  "type": "Feature",
  "properties": {
    "iso:country":"US",
    "sg:address":"5230 S Western Ave",
    "sg:city":"Marion",
    "sg:classifiers":[
        {
            "category":"Health Services",
            "subcategory":"Hospital",
            "type":"Services"
        }
    ],
    "sg:phone":"+1 765 674 2208",
    "sg:postcode":"46953",
    "sg:province":"IN",
    "sg:tags":[
        "mental"
    ],
    "wof:name":"Life Center Counseling Svc",
    "wof:placetype":"venue"
},
  "geometry": {"coordinates":[-85.672403,40.506512],"type":"Point"}
}