{
  "type": "Feature",
  "properties": {
    "iso:country":"US",
    "sg:address":"119 N Main St",
    "sg:city":"Monticello",
    "sg:classifiers":[
        {
            "category":"Banks & Credit Unions",
            "subcategory":"Bank",
            "type":"Services"
        }
    ],
    "sg:phone":"+1 574 583 5141",
    "sg:postcode":"47960",
    "sg:province":"IN",
    "sg:website":"www.wellsfargo.com",
    "wof:name":"Wells Fargo Bank",
    "wof:placetype":"venue"
},
  "geometry": {"coordinates":[-86.761855,40.747217],"type":"Point"}
}