{
  "type": "Feature",
  "properties": {
    "iso:country":"US",
    "sg:address":"320 S Range Line Rd",
    "sg:city":"Carmel",
    "sg:classifiers":[
        {
            "category":"Professional",
            "subcategory":"Lawyer & Legal Services",
            "type":"Services"
        }
    ],
    "sg:phone":"+1 317 575 0320",
    "sg:postcode":"46032",
    "sg:province":"IN",
    "sg:website":"www.smarshalllaw.com",
    "wof:name":"Marshall Sheila Atty",
    "wof:placetype":"venue"
},
  "geometry": {"coordinates":[-86.12724300000001,39.975742],"type":"Point"}
}