{
  "type": "Feature",
  "properties": {
    "iso:country":"US",
    "sg:address":"1551 S Woodland Ave",
    "sg:city":"Michigan City",
    "sg:classifiers":[
        {
            "category":"Government",
            "subcategory":"Office",
            "type":"Public Place"
        }
    ],
    "sg:phone":"+1 219 872 8440",
    "sg:postcode":"46360",
    "sg:province":"IN",
    "sg:tags":[
        "state",
        "resource"
    ],
    "sg:website":"www.state.in.us/fssa",
    "wof:name":"Child Protective Svc",
    "wof:placetype":"venue"
},
  "geometry": {"coordinates":[-86.874394,41.688864],"type":"Point"}
}