{
  "type": "Feature",
  "properties": {
    "iso:country":"US",
    "sg:address":"368 Bielby Rd",
    "sg:city":"Lawrenceburg",
    "sg:classifiers":[
        {
            "category":"Health Services",
            "subcategory":"Doctor",
            "type":"Services"
        }
    ],
    "sg:phone":"+1 812 539 4105",
    "sg:postcode":"47025",
    "sg:province":"IN",
    "sg:tags":[
        "dentist"
    ],
    "wof:name":"Cincinnati Oral-Maxillofacial",
    "wof:placetype":"venue"
},
  "geometry": {"coordinates":[-84.884623,39.112714],"type":"Point"}
}