{
  "type": "Feature",
  "properties": {
    "iso:country":"US",
    "sg:address":"106 S Center St",
    "sg:city":"Boswell",
    "sg:classifiers":[
        {
            "category":"Organizations",
            "subcategory":"Religious Organization",
            "type":"Services"
        }
    ],
    "sg:phone":"+1 765 869 5407",
    "sg:postcode":"47921",
    "sg:province":"IN",
    "sg:tags":[
        "church"
    ],
    "wof:name":"Free Methodist Parsonage",
    "wof:placetype":"venue"
},
  "geometry": {"coordinates":[-87.38081200000001,40.518277],"type":"Point"}
}