{
  "type": "Feature",
  "properties": {
    "addr:full":"2520 E Michigan Blvd Michigan City IN 46360",
    "addr:housenumber":"2520",
    "addr:postcode":"46360",
    "addr:street":"E Michigan Blvd",
    "iso:country":"US",
    "sg:address":"2520 E Michigan Blvd",
    "sg:city":"Michigan City",
    "sg:classifiers":[
        {
            "category":"Wholesale",
            "subcategory":"Machinery & Supplies",
            "type":"Manufacturing & Wholesale Goods"
        }
    ],
    "sg:phone":"+1 219 871 0530",
    "sg:postcode":"46360",
    "sg:province":"IN",
    "sg:tags":[
        "equipment",
        "hydraulic"
    ],
    "wof:name":"Hydraulic Connection",
    "wof:placetype":"venue"
},
  "geometry": {"coordinates":[-86.86650400000001,41.707949],"type":"Point"}
}