{
  "type": "Feature",
  "properties": {
    "iso:country":"US",
    "sg:address":"57995 Co Rd 9",
    "sg:city":"Elkhart",
    "sg:classifiers":[
        {
            "category":"Restaurant",
            "type":"Food & Drink"
        }
    ],
    "sg:phone":"+1 574 389 7441",
    "sg:postcode":"46517",
    "sg:province":"IN",
    "wof:name":"Ricky's Taqueria",
    "wof:placetype":"venue"
},
  "geometry": {"coordinates":[-85.96529200000001,41.653942],"type":"Point"}
}