{
  "type": "Feature",
  "properties": {
    "addr:full":"18091 Hedgewood Dr Goshen IN 46526",
    "addr:housenumber":"18091",
    "addr:postcode":"46526",
    "addr:street":"Hedgewood Dr",
    "iso:country":"US",
    "sg:address":"18091 Hedgewood Dr",
    "sg:city":"Goshen",
    "sg:classifiers":[
        {
            "category":"Professional",
            "subcategory":"Research",
            "type":"Services"
        }
    ],
    "sg:phone":"+1 574 903 9432",
    "sg:postcode":"46526",
    "sg:province":"IN",
    "sg:tags":[
        "development"
    ],
    "wof:name":"Estrella Solutions",
    "wof:placetype":"venue"
},
  "geometry": {"coordinates":[-85.810079,41.530369],"type":"Point"}
}