{
  "type": "Feature",
  "properties": {
    "iso:country":"US",
    "sg:address":"157 W 200 N",
    "sg:city":"Bluffton",
    "sg:classifiers":[
        {
            "category":"Restaurant",
            "type":"Food & Drink"
        }
    ],
    "sg:phone":"+1 260 824 1608",
    "sg:postcode":"46714",
    "sg:province":"IN",
    "sg:tags":[
        "caterer"
    ],
    "wof:name":"Lana's Country Kitchen",
    "wof:placetype":"venue"
},
  "geometry": {"coordinates":[-85.225436,40.771618],"type":"Point"}
}