{
  "type": "Feature",
  "properties": {
    "addr:full":"1800 N Shadeland Ave Indianapolis IN 46219",
    "addr:housenumber":"1800",
    "addr:postcode":"46219",
    "addr:street":"N Shadeland Ave",
    "iso:country":"US",
    "sg:address":"1800 N Shadeland Ave",
    "sg:city":"Indianapolis",
    "sg:classifiers":[
        {
            "category":"Autos & Motor Vehicles",
            "subcategory":"Automobile Sales",
            "type":"Retail Goods"
        },
        {
            "category":"Autos & Motor Vehicles",
            "subcategory":"Auto Supplies",
            "type":"Retail Goods"
        },
        {
            "category":"Retail",
            "subcategory":"Auto Repair",
            "type":"Services"
        }
    ],
    "sg:phone":"+1 317 357 1121",
    "sg:postcode":"46219",
    "sg:province":"IN",
    "sg:tags":[
        "used",
        "car",
        "lube",
        "oil",
        "new",
        "part"
    ],
    "sg:website":"http://www.blossomchevy.com",
    "wof:name":"Blossom Chevrolet",
    "wof:placetype":"venue"
},
  "geometry": {"coordinates":[-86.045486,39.792099],"type":"Point"}
}