{
  "type": "Feature",
  "properties": {
    "addr:full":"855 E Market St Huntington IN 46750",
    "addr:housenumber":"855",
    "addr:postcode":"46750",
    "addr:street":"E Market St",
    "iso:country":"US",
    "sg:address":"855 E Market St",
    "sg:city":"Huntington",
    "sg:classifiers":[
        {
            "category":"Bars & Pubs",
            "type":"Food & Drink"
        }
    ],
    "sg:phone":"+1 260 356 9811",
    "sg:postcode":"46750",
    "sg:province":"IN",
    "wof:name":"Young's Cafe",
    "wof:placetype":"venue"
},
  "geometry": {"coordinates":[-85.486435,40.884444],"type":"Point"}
}