{
  "type": "Feature",
  "properties": {
    "addr:full":"141 Spring St Charlestown IN 47111",
    "addr:housenumber":"141",
    "addr:postcode":"47111",
    "addr:street":"Spring St",
    "iso:country":"US",
    "sg:address":"141 Spring St",
    "sg:city":"Charlestown",
    "sg:classifiers":[
        {
            "category":"Organizations",
            "subcategory":"Religious Organization",
            "type":"Services"
        }
    ],
    "sg:phone":"+1 812 256 3654",
    "sg:postcode":"47111",
    "sg:province":"IN",
    "wof:name":"Pleasant Ridge 1st Church God",
    "wof:placetype":"venue"
},
  "geometry": {"coordinates":[-85.66678400000001,38.444204],"type":"Point"}
}