{
  "type": "Feature",
  "properties": {
    "iso:country":"US",
    "sg:address":"4105 N Co Rd 900 E",
    "sg:city":"Brownsburg",
    "sg:classifiers":[
        {
            "category":"Manufacturing",
            "subcategory":"Printing",
            "type":"Manufacturing & Wholesale Goods"
        }
    ],
    "sg:phone":"+1 317 858 3882",
    "sg:postcode":"46112",
    "sg:province":"IN",
    "sg:tags":[
        "publishing"
    ],
    "wof:name":"Vivid Internet Publishing",
    "wof:placetype":"venue"
},
  "geometry": {"coordinates":[-86.362982,39.824598],"type":"Point"}
}