{
  "type": "Feature",
  "properties": {
    "iso:country":"US",
    "sg:address":"202 E Washington St",
    "sg:city":"Rensselaer",
    "sg:classifiers":[
        {
            "category":"Personal",
            "subcategory":"Beauty Salon",
            "type":"Services"
        }
    ],
    "sg:phone":"+1 219 866 4538",
    "sg:postcode":"47978",
    "sg:province":"IN",
    "wof:name":"Nails & Etc",
    "wof:placetype":"venue"
},
  "geometry": {"coordinates":[-87.149261,40.937218],"type":"Point"}
}