{
  "type": "Feature",
  "properties": {
    "addr:full":"2027 W 500 S Morocco IN 47963",
    "addr:housenumber":"2027",
    "addr:postcode":"47963",
    "addr:street":"W 500 S Morocco",
    "iso:country":"US",
    "sg:address":"2027 W 500 S",
    "sg:city":"Morocco",
    "sg:classifiers":[
        {
            "category":"Home & Garden",
            "subcategory":"Building Materials",
            "type":"Retail Goods"
        }
    ],
    "sg:phone":"+1 219 285 6029",
    "sg:postcode":"47963",
    "sg:province":"IN",
    "wof:name":"Harris Building Materials",
    "wof:placetype":"venue"
},
  "geometry": {"coordinates":[-87.43515499999999,40.926132],"type":"Point"}
}