{
  "type": "Feature",
  "properties": {
    "iso:country":"US",
    "sg:address":"4738 Coldwater Rd",
    "sg:city":"Fort Wayne",
    "sg:classifiers":[
        {
            "category":"Restaurant",
            "type":"Food & Drink"
        }
    ],
    "sg:phone":"+1 260 484 3894",
    "sg:postcode":"46825",
    "sg:province":"IN",
    "sg:tags":[
        "eating"
    ],
    "wof:name":"Vrbas",
    "wof:placetype":"venue"
},
  "geometry": {"coordinates":[-85.13539,41.122418],"type":"Point"}
}