{
  "type": "Feature",
  "properties": {
    "iso:country":"US",
    "sg:address":"312 4th St",
    "sg:city":"Covington",
    "sg:classifiers":[
        {
            "category":"Health Services",
            "subcategory":"Clinic",
            "type":"Services"
        }
    ],
    "sg:phone":"+1 765 793 1234",
    "sg:postcode":"47932",
    "sg:province":"IN",
    "sg:tags":[
        "home",
        "care"
    ],
    "wof:name":"Indiana Homecare Plus Co Inc",
    "wof:placetype":"venue"
},
  "geometry": {"coordinates":[-87.396511,40.137524],"type":"Point"}
}