{
  "type": "Feature",
  "properties": {
    "iso:country":"US",
    "sg:address":"707 N 400 E",
    "sg:city":"Winchester",
    "sg:classifiers":[
        {
            "category":"Manufacturing",
            "subcategory":"Tools & Machinery",
            "type":"Manufacturing & Wholesale Goods"
        }
    ],
    "sg:phone":"+1 765 584 6225",
    "sg:postcode":"47394",
    "sg:province":"IN",
    "sg:tags":[
        "machine",
        "shop"
    ],
    "wof:name":"Glass Components Inc",
    "wof:placetype":"venue"
},
  "geometry": {"coordinates":[-84.901016,40.157047],"type":"Point"}
}