{
  "type": "Feature",
  "properties": {
    "addr:full":"58 N Harrison St Greenfield IN 46140",
    "addr:housenumber":"58",
    "addr:postcode":"46140",
    "addr:street":"N Harrison St",
    "iso:country":"US",
    "sg:address":"58 N Harrison St",
    "sg:city":"Greenfield",
    "sg:classifiers":[
        {
            "category":"Recreation",
            "type":"Entertainment"
        }
    ],
    "sg:phone":"+1 317 462 9341",
    "sg:postcode":"46140",
    "sg:province":"IN",
    "sg:tags":[
        "instruction",
        "gymnastic"
    ],
    "wof:name":"Indiana Gym-Nest",
    "wof:placetype":"venue"
},
  "geometry": {"coordinates":[-85.785269,39.784853],"type":"Point"}
}