{
  "type": "Feature",
  "properties": {
    "iso:country":"US",
    "sg:address":"675 N Co Rd 850 W",
    "sg:city":"Shipshewana",
    "sg:classifiers":[
        {
            "category":"Building & Trades",
            "subcategory":"Construction",
            "type":"Services"
        }
    ],
    "sg:phone":"+1 260 768 7420",
    "sg:postcode":"46565",
    "sg:province":"IN",
    "sg:tags":[
        "excavation",
        "contractor"
    ],
    "wof:name":"M Miller Excavating",
    "wof:placetype":"venue"
},
  "geometry": {"coordinates":[-85.589753,41.647407],"type":"Point"}
}