{
  "type": "Feature",
  "properties": {
    "iso:country":"US",
    "sg:address":"11558 W 100 S",
    "sg:city":"Francesville",
    "sg:classifiers":[
        {
            "category":"Real Estate",
            "subcategory":"Real Estate Operator",
            "type":"Services"
        }
    ],
    "sg:phone":"+1 219 567 9590",
    "sg:postcode":"47946",
    "sg:province":"IN",
    "sg:tags":[
        "farm",
        "corn",
        "property",
        "soybean",
        "lessor"
    ],
    "wof:name":"Younglove John",
    "wof:placetype":"venue"
},
  "geometry": {"coordinates":[-86.824647,41.041594],"type":"Point"}
}