{
  "type": "Feature",
  "properties": {
    "addr:full":"1030 Oak St Brownstown IN 47220",
    "addr:housenumber":"1030",
    "addr:postcode":"47220",
    "addr:street":"Oak St",
    "iso:country":"US",
    "sg:address":"1030 Oak St",
    "sg:city":"Brownstown",
    "sg:classifiers":[
        {
            "category":"Professional",
            "subcategory":"Management & Consulting",
            "type":"Services"
        }
    ],
    "sg:phone":"+1 812 358 4589",
    "sg:postcode":"47220",
    "sg:province":"IN",
    "sg:tags":[
        "marketing",
        "consultant"
    ],
    "wof:name":"Robertson Corp",
    "wof:placetype":"venue"
},
  "geometry": {"coordinates":[-86.053719,38.885046],"type":"Point"}
}