{
  "type": "Feature",
  "properties": {
    "iso:country":"US",
    "sg:address":"802 S Emerson Ave",
    "sg:city":"Indianapolis",
    "sg:classifiers":[
        {
            "category":"Wholesale",
            "subcategory":"Motor Vehicles",
            "type":"Manufacturing & Wholesale Goods"
        }
    ],
    "sg:phone":"+1 317 356 4614",
    "sg:postcode":"46203",
    "sg:province":"IN",
    "sg:tags":[
        "truck"
    ],
    "wof:name":"Beelman Truck Co",
    "wof:placetype":"venue"
},
  "geometry": {"coordinates":[-86.082987,39.755705],"type":"Point"}
}