{
  "type": "Feature",
  "properties": {
    "iso:country":"US",
    "sg:address":"500 Ohio St",
    "sg:city":"Terre Haute",
    "sg:classifiers":[
        {
            "category":"Professional",
            "subcategory":"Lawyer & Legal Services",
            "type":"Services"
        }
    ],
    "sg:phone":"+1 812 232 3388",
    "sg:postcode":"47807",
    "sg:province":"IN",
    "sg:tags":[
        "attorney"
    ],
    "sg:website":"www.wslfirm.com",
    "wof:name":"Wright Shagley & Lowery",
    "wof:placetype":"venue"
},
  "geometry": {"coordinates":[-87.40999600000001,39.465439],"type":"Point"}
}