{
  "type": "Feature",
  "properties": {
    "iso:country":"US",
    "sg:address":"7190 Rockville Rd",
    "sg:city":"Indianapolis",
    "sg:classifiers":[
        {
            "category":"Shopping",
            "type":"Retail Goods"
        }
    ],
    "sg:phone":"+1 317 241 1400",
    "sg:postcode":"46214",
    "sg:province":"IN",
    "sg:tags":[
        "pet",
        "food",
        "supply"
    ],
    "wof:name":"Pet Supplies Plus",
    "wof:placetype":"venue"
},
  "geometry": {"coordinates":[-86.287964,39.764396],"type":"Point"}
}