{
  "type": "Feature",
  "properties": {
    "iso:country":"US",
    "sg:address":"725 Burlington Ave",
    "sg:city":"Logansport",
    "sg:classifiers":[
        {
            "category":"Home & Garden",
            "subcategory":"Garden Supply",
            "type":"Retail Goods"
        }
    ],
    "sg:phone":"+1 574 753 7535",
    "sg:postcode":"46947",
    "sg:province":"IN",
    "sg:tags":[
        "lawn",
        "mower"
    ],
    "sg:website":"www.greenpowerdeere.com",
    "wof:name":"Green Power Inc",
    "wof:placetype":"venue"
},
  "geometry": {"coordinates":[-86.370655,40.741361],"type":"Point"}
}