{
  "type": "Feature",
  "properties": {
    "addr:full":"417 S Main St Bluffton IN 46714",
    "addr:housenumber":"417",
    "addr:postcode":"46714",
    "addr:street":"S Main St",
    "iso:country":"US",
    "sg:address":"417 S Main St",
    "sg:city":"Bluffton",
    "sg:classifiers":[
        {
            "category":"Building & Trades",
            "subcategory":"Construction",
            "type":"Services"
        }
    ],
    "sg:phone":"+1 260 824 5989",
    "sg:postcode":"46714",
    "sg:province":"IN",
    "sg:tags":[
        "contractor"
    ],
    "wof:name":"Steve E Plastering Helmuth",
    "wof:placetype":"venue"
},
  "geometry": {"coordinates":[-85.17151699999999,40.736076],"type":"Point"}
}