{
  "type": "Feature",
  "properties": {
    "iso:country":"US",
    "sg:address":"605 Westlane Rd",
    "sg:city":"Greencastle",
    "sg:classifiers":[
        {
            "category":"Organizations",
            "subcategory":"Religious Organization",
            "type":"Services"
        }
    ],
    "sg:phone":"+1 765 653 2744",
    "sg:postcode":"46135",
    "sg:province":"IN",
    "sg:tags":[
        "church"
    ],
    "wof:name":"First Assembly Of God",
    "wof:placetype":"venue"
},
  "geometry": {"coordinates":[-86.837416,39.620607],"type":"Point"}
}