{
  "type": "Feature",
  "properties": {
    "iso:country":"US",
    "sg:address":"4931 E Mann Rd",
    "sg:city":"Pekin",
    "sg:classifiers":[
        {
            "category":"Building & Trades",
            "subcategory":"Electrical",
            "type":"Services"
        }
    ],
    "sg:phone":"+1 812 967 3818",
    "sg:postcode":"47165",
    "sg:province":"IN",
    "sg:tags":[
        "electric",
        "contractor"
    ],
    "wof:name":"Keith's Mechanical Inc",
    "wof:placetype":"venue"
},
  "geometry": {"coordinates":[-86.014223,38.438367],"type":"Point"}
}