{
  "type": "Feature",
  "properties": {
    "iso:country":"US",
    "sg:address":"601 E Main St",
    "sg:city":"Greenwood",
    "sg:classifiers":[
        {
            "category":"Professional",
            "subcategory":"Computer Services",
            "type":"Services"
        }
    ],
    "sg:phone":"+1 317 885 7049",
    "sg:postcode":"46143",
    "sg:province":"IN",
    "sg:tags":[
        "repair"
    ],
    "wof:name":"Innovativetech Of Indiana Inc",
    "wof:placetype":"venue"
},
  "geometry": {"coordinates":[-86.09805,39.6139],"type":"Point"}
}