{
  "type": "Feature",
  "properties": {
    "iso:country":"US",
    "sg:address":"687 N Green River Rd",
    "sg:city":"Evansville",
    "sg:classifiers":[
        {
            "category":"Restaurant",
            "type":"Food & Drink"
        }
    ],
    "sg:phone":"+1 812 471 4888",
    "sg:postcode":"47715",
    "sg:province":"IN",
    "wof:name":"Samuel Mancino's Itln Eatery",
    "wof:placetype":"venue"
},
  "geometry": {"coordinates":[-87.49261,37.982115],"type":"Point"}
}