{
  "type": "Feature",
  "properties": {
    "iso:country":"US",
    "sg:address":"6211 W 30th St",
    "sg:city":"Indianapolis",
    "sg:classifiers":[
        {
            "category":"Health Services",
            "subcategory":"Doctor",
            "type":"Services"
        }
    ],
    "sg:phone":"+1 317 299 0353",
    "sg:postcode":"46224",
    "sg:province":"IN",
    "sg:tags":[
        "dentist"
    ],
    "wof:name":"Mark A Kahn PC",
    "wof:placetype":"venue"
},
  "geometry": {"coordinates":[-86.269308,39.809204],"type":"Point"}
}