{
  "type": "Feature",
  "properties": {
    "iso:country":"US",
    "sg:address":"2755 Woodbine Dr",
    "sg:city":"Valparaiso",
    "sg:classifiers":[
        {
            "category":"Building & Trades",
            "subcategory":"Construction",
            "type":"Services"
        }
    ],
    "sg:phone":"+1 219 926 2605",
    "sg:postcode":"46383",
    "sg:province":"IN",
    "sg:tags":[
        "house"
    ],
    "wof:name":"Rick Wilemon",
    "wof:placetype":"venue"
},
  "geometry": {"coordinates":[-87.038826,41.440923],"type":"Point"}
}