{
  "type": "Feature",
  "properties": {
    "iso:country":"US",
    "sg:address":"1206 Broad St",
    "sg:city":"New Castle",
    "sg:classifiers":[
        {
            "category":"Shopping",
            "subcategory":"Florist",
            "type":"Retail Goods"
        }
    ],
    "sg:phone":"+1 765 521 2254",
    "sg:postcode":"47362",
    "sg:province":"IN",
    "wof:name":"Sherry's Custom Creations",
    "wof:placetype":"venue"
},
  "geometry": {"coordinates":[-85.371573,39.931288],"type":"Point"}
}