{
  "type": "Feature",
  "properties": {
    "addr:full":"16763 Clover Rd Noblesville IN 46060",
    "addr:housenumber":"16763",
    "addr:postcode":"46060",
    "addr:street":"Clover Rd",
    "iso:country":"US",
    "sg:address":"16763 Clover Rd",
    "sg:city":"Noblesville",
    "sg:classifiers":[
        {
            "category":"Shopping",
            "subcategory":"Hobbies, Toys, & Games",
            "type":"Retail Goods"
        }
    ],
    "sg:phone":"+1 317 773 1718",
    "sg:postcode":"46060",
    "sg:province":"IN",
    "sg:tags":[
        "video",
        "supply"
    ],
    "sg:website":"http://www.gamestop.com",
    "wof:name":"Game Stop",
    "wof:placetype":"venue"
},
  "geometry": {"coordinates":[-85.996559,40.033391],"type":"Point"}
}