{
  "type": "Feature",
  "properties": {
    "iso:country":"US",
    "sg:address":"5808 Seneca Trl",
    "sg:city":"Kokomo",
    "sg:classifiers":[
        {
            "category":"Insurance",
            "subcategory":"Insurance Agent",
            "type":"Services"
        }
    ],
    "sg:phone":"+1 765 453 1781",
    "sg:postcode":"46902",
    "sg:province":"IN",
    "wof:name":"C Fink Insurance",
    "wof:placetype":"venue"
},
  "geometry": {"coordinates":[-86.122916,40.423463],"type":"Point"}
}