{
  "type": "Feature",
  "properties": {
    "addr:full":"5720 W Washington St Indianapolis IN 46241",
    "addr:housenumber":"5720",
    "addr:postcode":"46241",
    "addr:street":"W Washington St",
    "iso:country":"US",
    "sg:address":"5720 W Washington St",
    "sg:city":"Indianapolis",
    "sg:classifiers":[
        {
            "category":"Wholesale",
            "subcategory":"Medical Equipment & Supplies",
            "type":"Manufacturing & Wholesale Goods"
        },
        {
            "category":"Shopping",
            "subcategory":"Beauty & Cosmetics",
            "type":"Retail Goods"
        },
        {
            "category":"Food & Beverages",
            "subcategory":"Specialty",
            "type":"Retail Goods"
        },
        {
            "category":"Shopping",
            "subcategory":"Computers & Home Electronics",
            "type":"Retail Goods"
        },
        {
            "category":"Shopping",
            "subcategory":"Optical Goods",
            "type":"Retail Goods"
        },
        {
            "category":"Personal",
            "subcategory":"Skin Care",
            "type":"Services"
        },
        {
            "category":"Manufacturing",
            "subcategory":"Chemicals & Compounds",
            "type":"Manufacturing & Wholesale Goods"
        },
        {
            "category":"Retail",
            "subcategory":"Photofinishing",
            "type":"Services"
        },
        {
            "category":"Shopping",
            "subcategory":"Pharmacy",
            "type":"Retail Goods"
        },
        {
            "category":"Health Services",
            "subcategory":"Optometrist",
            "type":"Services"
        },
        {
            "category":"Food & Beverages",
            "subcategory":"Groceries & Convenience Stores",
            "type":"Retail Goods"
        }
    ],
    "sg:phone":"+1 317 484 1240",
    "sg:postcode":"46241",
    "sg:province":"IN",
    "sg:tags":[
        "pharmaceutical",
        "product",
        "photo",
        "wheelchair",
        "vitamin",
        "perfume",
        "lens",
        "supplement",
        "contact",
        "wellness",
        "finishing",
        "consumer"
    ],
    "sg:website":"http://www.walgreens.com/default.jsp?ec=iyp_yellowpages_trademark",
    "wof:name":"Walgreens Pharmacies",
    "wof:placetype":"venue"
},
  "geometry": {"coordinates":[-86.257796,39.750515],"type":"Point"}
}