{
  "type": "Feature",
  "properties": {
    "iso:country":"US",
    "sg:address":"208 N Main St",
    "sg:city":"Kokomo",
    "sg:classifiers":[
        {
            "category":"Professional",
            "subcategory":"Lawyer & Legal Services",
            "type":"Services"
        }
    ],
    "sg:phone":"+1 765 452 2014",
    "sg:postcode":"46901",
    "sg:province":"IN",
    "sg:tags":[
        "attorney"
    ],
    "wof:name":"Menges Law Offices",
    "wof:placetype":"venue"
},
  "geometry": {"coordinates":[-86.131158,40.48827],"type":"Point"}
}