{
  "type": "Feature",
  "properties": {
    "iso:country":"US",
    "sg:address":"4624 Van Buren St",
    "sg:city":"Gary",
    "sg:classifiers":[
        {
            "category":"Professional",
            "subcategory":"Business Services",
            "type":"Services"
        }
    ],
    "sg:phone":"+1 219 887 8134",
    "sg:postcode":"46408",
    "sg:province":"IN",
    "wof:name":"Strategic Connection",
    "wof:placetype":"venue"
},
  "geometry": {"coordinates":[-87.344788,41.533612],"type":"Point"}
}