{
  "type": "Feature",
  "properties": {
    "addr:full":"856 Sibley St Hammond IN 46320",
    "addr:housenumber":"856",
    "addr:postcode":"46320",
    "addr:street":"Sibley St",
    "iso:country":"US",
    "sg:address":"856 Sibley St",
    "sg:city":"Hammond",
    "sg:classifiers":[
        {
            "category":"Education",
            "subcategory":"School",
            "type":"Public Place"
        }
    ],
    "sg:phone":"+1 219 933 2472",
    "sg:postcode":"46320",
    "sg:province":"IN",
    "sg:tags":[
        "high",
        "middle",
        "elementary"
    ],
    "wof:name":"Schools Public",
    "wof:placetype":"venue"
},
  "geometry": {"coordinates":[-87.507373,41.613853],"type":"Point"}
}