{
  "type": "Feature",
  "properties": {
    "iso:country":"US",
    "sg:address":"4917 Dawn St",
    "sg:city":"Anderson",
    "sg:classifiers":[
        {
            "category":"Real Estate",
            "subcategory":"Surveying",
            "type":"Services"
        }
    ],
    "sg:phone":"+1 765 622 9737",
    "sg:postcode":"46013",
    "sg:province":"IN",
    "wof:name":"Servies Stephen D & Assoc",
    "wof:placetype":"venue"
},
  "geometry": {"coordinates":[-85.695037,40.064077],"type":"Point"}
}