{
  "type": "Feature",
  "properties": {
    "iso:country":"US",
    "sg:address":"310 N 19th St",
    "sg:city":"Vincennes",
    "sg:classifiers":[
        {
            "category":"Shopping",
            "subcategory":"Computers & Home Electronics",
            "type":"Retail Goods"
        }
    ],
    "sg:phone":"+1 812 886 5356",
    "sg:postcode":"47591",
    "sg:province":"IN",
    "wof:name":"Diamond Tinting",
    "wof:placetype":"venue"
},
  "geometry": {"coordinates":[-87.513697,38.667094],"type":"Point"}
}