{
  "type": "Feature",
  "properties": {
    "addr:full":"616 Paradise Ave Lafayette IN 47905",
    "addr:housenumber":"616",
    "addr:postcode":"47905",
    "addr:street":"Paradise Ave",
    "iso:country":"US",
    "sg:address":"616 Paradise Ave",
    "sg:city":"Lafayette",
    "sg:classifiers":[
        {
            "category":"Shopping",
            "subcategory":"Crafts & Fabrics",
            "type":"Retail Goods"
        }
    ],
    "sg:phone":"+1 765 449 0132",
    "sg:postcode":"47905",
    "sg:province":"IN",
    "sg:tags":[
        "monogram"
    ],
    "wof:name":"M Bumbleburg",
    "wof:placetype":"venue"
},
  "geometry": {"coordinates":[-86.827848,40.427829],"type":"Point"}
}