{
  "type": "Feature",
  "properties": {
    "iso:country":"US",
    "sg:address":"700 N Harrison St",
    "sg:city":"Salem",
    "sg:classifiers":[
        {
            "category":"Organizations",
            "subcategory":"Community Association",
            "type":"Services"
        }
    ],
    "sg:phone":"+1 812 883 9919",
    "sg:postcode":"47167",
    "sg:province":"IN",
    "sg:tags":[
        "educational"
    ],
    "wof:name":"Cape School-2-Career",
    "wof:placetype":"venue"
},
  "geometry": {"coordinates":[-86.106137,38.611327],"type":"Point"}
}