{
  "type": "Feature",
  "properties": {
    "iso:country":"US",
    "sg:address":"9282 S 600 W",
    "sg:city":"Brook",
    "sg:classifiers":[
        {
            "category":"Farming",
            "subcategory":"Farm",
            "type":"Manufacturing & Wholesale Goods"
        }
    ],
    "sg:phone":"+1 219 275 7454",
    "sg:postcode":"47922",
    "sg:province":"IN",
    "wof:name":"PJW Farms",
    "wof:placetype":"venue"
},
  "geometry": {"coordinates":[-87.505864,40.862184],"type":"Point"}
}