{
  "type": "Feature",
  "properties": {
    "iso:country":"US",
    "sg:address":"29522 Co Rd 52",
    "sg:city":"Nappanee",
    "sg:classifiers":[
        {
            "category":"Education",
            "subcategory":"School",
            "type":"Public Place"
        }
    ],
    "sg:phone":"+1 574 773 7505",
    "sg:postcode":"46550",
    "sg:province":"IN",
    "wof:name":"United Christian School",
    "wof:placetype":"venue"
},
  "geometry": {"coordinates":[-86.039648,41.457124],"type":"Point"}
}