{
  "type": "Feature",
  "properties": {
    "iso:country":"US",
    "sg:address":"213 E Market St",
    "sg:city":"Jeffersonville",
    "sg:classifiers":[
        {
            "category":"Education",
            "subcategory":"Vocational School",
            "type":"Public Place"
        }
    ],
    "sg:phone":"+1 812 284 2930",
    "sg:postcode":"47130",
    "sg:province":"IN",
    "sg:tags":[
        "technical",
        "trade"
    ],
    "wof:name":"Drivetek",
    "wof:placetype":"venue"
},
  "geometry": {"coordinates":[-85.737173,38.271873],"type":"Point"}
}