{
  "type": "Feature",
  "properties": {
    "iso:country":"US",
    "sg:address":"318 E Florida St",
    "sg:city":"Evansville",
    "sg:classifiers":[
        {
            "category":"Wholesale",
            "subcategory":"Electrical",
            "type":"Manufacturing & Wholesale Goods"
        }
    ],
    "sg:phone":"+1 812 425 5626",
    "sg:postcode":"47711",
    "sg:province":"IN",
    "sg:tags":[
        "control",
        "security",
        "system"
    ],
    "wof:name":"Security Mortgage",
    "wof:placetype":"venue"
},
  "geometry": {"coordinates":[-87.558631,37.98946],"type":"Point"}
}