{
  "type": "Feature",
  "properties": {
    "iso:country":"US",
    "sg:address":"409 S College Ave Ste B",
    "sg:city":"Bloomington",
    "sg:classifiers":[
        {
            "category":"Professional",
            "subcategory":"Lawyer & Legal Services",
            "type":"Services"
        }
    ],
    "sg:phone":"+1 812 339 4502",
    "sg:postcode":"47403",
    "sg:province":"IN",
    "wof:name":"Stewart Daniel C Atty",
    "wof:placetype":"venue"
},
  "geometry": {"coordinates":[-86.53479799999999,39.1623],"type":"Point"}
}