{
  "type": "Feature",
  "properties": {
    "iso:country":"US",
    "sg:address":"332 N Snowden St",
    "sg:city":"Andrews",
    "sg:classifiers":[
        {
            "category":"Real Estate",
            "subcategory":"Real Estate Operator",
            "type":"Services"
        }
    ],
    "sg:phone":"+1 260 786 0104",
    "sg:postcode":"46702",
    "sg:province":"IN",
    "sg:tags":[
        "building",
        "apartment"
    ],
    "wof:name":"Andrews Senior Citizens Apts",
    "wof:placetype":"venue"
},
  "geometry": {"coordinates":[-85.602753,40.860943],"type":"Point"}
}