{
  "type": "Feature",
  "properties": {
    "iso:country":"US",
    "sg:address":"707 N Hobart Rd",
    "sg:city":"Hobart",
    "sg:classifiers":[
        {
            "category":"Building & Trades",
            "subcategory":"Plumbing",
            "type":"Services"
        }
    ],
    "sg:phone":"+1 219 759 6590",
    "sg:postcode":"46342",
    "sg:province":"IN",
    "sg:tags":[
        "conditioning",
        "air",
        "system",
        "contractor"
    ],
    "wof:name":"Fostcorp Heating & Cooling",
    "wof:placetype":"venue"
},
  "geometry": {"coordinates":[-87.240628,41.550558],"type":"Point"}
}