{
  "type": "Feature",
  "properties": {
    "iso:country":"US",
    "sg:address":"1814 O St",
    "sg:city":"Bedford",
    "sg:classifiers":[
        {
            "category":"Social Services",
            "subcategory":"Child Care",
            "type":"Services"
        }
    ],
    "sg:phone":"+1 812 279 5576",
    "sg:postcode":"47421",
    "sg:province":"IN",
    "wof:name":"A Happy Heart Daycare Inc",
    "wof:placetype":"venue"
},
  "geometry": {"coordinates":[-86.491445,38.858481],"type":"Point"}
}