{
  "type": "Feature",
  "properties": {
    "iso:country":"US",
    "sg:address":"1911 W 575 S",
    "sg:city":"Williamsport",
    "sg:classifiers":[
        {
            "category":"Home & Garden",
            "subcategory":"Carpets & Floor Coverings",
            "type":"Retail Goods"
        }
    ],
    "sg:phone":"+1 765 893 4550",
    "sg:postcode":"47993",
    "sg:province":"IN",
    "wof:name":"Total Coverage Service",
    "wof:placetype":"venue"
},
  "geometry": {"coordinates":[-87.354858,40.232487],"type":"Point"}
}