{
  "type": "Feature",
  "properties": {
    "iso:country":"US",
    "sg:address":"87 E Berry Ave",
    "sg:city":"Upland",
    "sg:classifiers":[
        {
            "category":"Retail",
            "subcategory":"Self-service Laundry",
            "type":"Services"
        }
    ],
    "sg:phone":"+1 765 998 1110",
    "sg:postcode":"46989",
    "sg:province":"IN",
    "wof:name":"Upland Maytag Village",
    "wof:placetype":"venue"
},
  "geometry": {"coordinates":[-85.493054,40.466631],"type":"Point"}
}