{
  "type": "Feature",
  "properties": {
    "iso:country":"US",
    "sg:address":"220 N Center St",
    "sg:city":"Plymouth",
    "sg:classifiers":[
        {
            "category":"Recreation",
            "type":"Entertainment"
        }
    ],
    "sg:phone":"+1 574 936 5020",
    "sg:postcode":"46563",
    "sg:province":"IN",
    "sg:tags":[
        "carnival"
    ],
    "wof:name":"Blueberry Festival Information",
    "wof:placetype":"venue"
},
  "geometry": {"coordinates":[-86.310451,41.341473],"type":"Point"}
}