{
  "type": "Feature",
  "properties": {
    "addr:full":"2201 W Maryland St Evansville IN 47712",
    "addr:housenumber":"2201",
    "addr:postcode":"47712",
    "addr:street":"W Maryland St",
    "iso:country":"US",
    "sg:address":"2201 W Maryland St",
    "sg:city":"Evansville",
    "sg:classifiers":[
        {
            "category":"Manufacturing",
            "subcategory":"Chemicals & Compounds",
            "type":"Manufacturing & Wholesale Goods"
        }
    ],
    "sg:phone":"+1 812 428 2160",
    "sg:postcode":"47712",
    "sg:province":"IN",
    "sg:tags":[
        "printing",
        "ink"
    ],
    "wof:name":"INX International Ink Co",
    "wof:placetype":"venue"
},
  "geometry": {"coordinates":[-87.598826,37.985702],"type":"Point"}
}