{
  "type": "Feature",
  "properties": {
    "iso:country":"US",
    "sg:address":"210 Allhands Ave",
    "sg:city":"Sellersburg",
    "sg:classifiers":[
        {
            "category":"Home & Garden",
            "subcategory":"Furniture",
            "type":"Retail Goods"
        }
    ],
    "sg:phone":"+1 812 246 4863",
    "sg:postcode":"47172",
    "sg:province":"IN",
    "sg:tags":[
        "cabinet"
    ],
    "wof:name":"M & M Amish Custom Cabinets",
    "wof:placetype":"venue"
},
  "geometry": {"coordinates":[-85.758148,38.398888],"type":"Point"}
}