{
  "type": "Feature",
  "properties": {
    "addr:full":"929 S Indiana Ave Sellersburg IN 47172",
    "addr:housenumber":"929",
    "addr:postcode":"47172",
    "addr:street":"S Indiana Ave",
    "iso:country":"US",
    "sg:address":"929 S Indiana Ave",
    "sg:city":"Sellersburg",
    "sg:classifiers":[
        {
            "category":"Sports & Exercise",
            "subcategory":"Bowling",
            "type":"Entertainment"
        }
    ],
    "sg:phone":"+1 812 246 9527",
    "sg:postcode":"47172",
    "sg:province":"IN",
    "sg:tags":[
        "center"
    ],
    "wof:name":"Silver Creek Lanes",
    "wof:placetype":"venue"
},
  "geometry": {"coordinates":[-85.75098300000001,38.386887],"type":"Point"}
}