{
  "type": "Feature",
  "properties": {
    "iso:country":"US",
    "sg:address":"1451 N Eel River Cemetery Rd",
    "sg:city":"Peru",
    "sg:classifiers":[
        {
            "category":"Government",
            "subcategory":"Police Station",
            "type":"Public Place"
        }
    ],
    "sg:phone":"+1 765 473 6666",
    "sg:postcode":"46970",
    "sg:province":"IN",
    "sg:tags":[
        "state"
    ],
    "sg:website":"www.in.gov",
    "wof:name":"State Police Dept",
    "wof:placetype":"venue"
},
  "geometry": {"coordinates":[-86.12939799999999,40.783761],"type":"Point"}
}