{
  "type": "Feature",
  "properties": {
    "iso:country":"US",
    "sg:address":"295 N Elm St",
    "sg:city":"Zionsville",
    "sg:classifiers":[
        {
            "category":"Professional",
            "type":"Services"
        }
    ],
    "sg:phone":"+1 317 769 4818",
    "sg:postcode":"46077",
    "sg:province":"IN",
    "sg:tags":[
        "establishment"
    ],
    "wof:name":"Masoncup & Co",
    "wof:placetype":"venue"
},
  "geometry": {"coordinates":[-86.260919,39.954849],"type":"Point"}
}