{
  "type": "Feature",
  "properties": {
    "addr:full":"1163 McKinley Ave Frankfort IN 46041",
    "addr:housenumber":"1163",
    "addr:postcode":"46041",
    "addr:street":"Mckinley Ave",
    "iso:country":"US",
    "sg:address":"1163 McKinley Ave",
    "sg:city":"Frankfort",
    "sg:classifiers":[
        {
            "category":"Personal",
            "subcategory":"Beauty Salon",
            "type":"Services"
        }
    ],
    "sg:phone":"+1 765 654 5816",
    "sg:postcode":"46041",
    "sg:province":"IN",
    "wof:name":"New Dimensions",
    "wof:placetype":"venue"
},
  "geometry": {"coordinates":[-86.52583300000001,40.278986],"type":"Point"}
}