{
  "type": "Feature",
  "properties": {
    "addr:full":"217 Garrettson Ave Michigan City IN 46360",
    "addr:housenumber":"217",
    "addr:postcode":"46360",
    "addr:street":"Garrettson Ave",
    "iso:country":"US",
    "sg:address":"217 Garrettson Ave",
    "sg:city":"Michigan City",
    "sg:classifiers":[
        {
            "category":"Building & Trades",
            "subcategory":"Landscaping Services",
            "type":"Services"
        }
    ],
    "sg:phone":"+1 219 872 9829",
    "sg:postcode":"46360",
    "sg:province":"IN",
    "wof:name":"AAA Lawn Maintenance",
    "wof:placetype":"venue"
},
  "geometry": {"coordinates":[-86.891842,41.690834],"type":"Point"}
}