{
  "type": "Feature",
  "properties": {
    "addr:full":"3641 Mayflower Dr Indianapolis IN 46221",
    "addr:housenumber":"3641",
    "addr:postcode":"46221",
    "addr:street":"Mayflower Dr",
    "iso:country":"US",
    "sg:address":"3641 Mayflower Dr",
    "sg:city":"Indianapolis",
    "sg:classifiers":[
        {
            "category":"Building & Trades",
            "subcategory":"Construction",
            "type":"Services"
        }
    ],
    "sg:phone":"+1 317 243 8671",
    "sg:postcode":"46221",
    "sg:province":"IN",
    "sg:tags":[
        "hanging",
        "contractor"
    ],
    "wof:name":"Rupe Painting Michael",
    "wof:placetype":"venue"
},
  "geometry": {"coordinates":[-86.235843,39.710808],"type":"Point"}
}