{
  "type": "Feature",
  "properties": {
    "addr:full":"5501 S Anthony Blvd Fort Wayne IN 46806",
    "addr:housenumber":"5501",
    "addr:postcode":"46806",
    "addr:street":"S Anthony Blvd",
    "iso:country":"US",
    "sg:address":"5501 S Anthony Blvd",
    "sg:city":"Fort Wayne",
    "sg:classifiers":[
        {
            "category":"Food & Beverages",
            "subcategory":"Groceries & Convenience Stores",
            "type":"Retail Goods"
        }
    ],
    "sg:phone":"+1 260 432 9346",
    "sg:postcode":"46806",
    "sg:province":"IN",
    "sg:tags":[
        "grocer"
    ],
    "wof:name":"Hoosier Foods",
    "wof:placetype":"venue"
},
  "geometry": {"coordinates":[-85.112785,41.034369],"type":"Point"}
}