{
  "type": "Feature",
  "properties": {
    "iso:country":"US",
    "sg:address":"232 E 500 N",
    "sg:city":"Valparaiso",
    "sg:classifiers":[
        {
            "category":"Professional",
            "subcategory":"Business Services",
            "type":"Services"
        }
    ],
    "sg:phone":"+1 219 465 1115",
    "sg:postcode":"46383",
    "sg:province":"IN",
    "wof:name":"Meeting Achievments",
    "wof:placetype":"venue"
},
  "geometry": {"coordinates":[-87.021878,41.507242],"type":"Point"}
}