{
  "type": "Feature",
  "properties": {
    "iso:country":"US",
    "sg:address":"15560 N Co Rd 850 E",
    "sg:city":"Sunman",
    "sg:classifiers":[
        {
            "category":"Home & Garden",
            "subcategory":"Garden Supply",
            "type":"Retail Goods"
        }
    ],
    "sg:phone":"+1 812 623 3442",
    "sg:postcode":"47041",
    "sg:province":"IN",
    "sg:tags":[
        "farm"
    ],
    "wof:name":"Gutapfel Brothers",
    "wof:placetype":"venue"
},
  "geometry": {"coordinates":[-85.10510499999999,39.306168],"type":"Point"}
}