{
  "type": "Feature",
  "properties": {
    "iso:country":"US",
    "sg:address":"3208 E Michigan St",
    "sg:city":"Indianapolis",
    "sg:classifiers":[
        {
            "category":"Social Services",
            "type":"Services"
        }
    ],
    "sg:phone":"+1 317 687 3630",
    "sg:postcode":"46201",
    "sg:province":"IN",
    "sg:tags":[
        "organization",
        "welfare"
    ],
    "sg:website":"www.wmm.org",
    "wof:name":"Wheeler Mission Ministry",
    "wof:placetype":"venue"
},
  "geometry": {"coordinates":[-86.10975000000001,39.774651],"type":"Point"}
}