{
  "type": "Feature",
  "properties": {
    "iso:country":"US",
    "sg:address":"2765 Van Buren Pl",
    "sg:city":"Gary",
    "sg:classifiers":[
        {
            "category":"Organizations",
            "subcategory":"Religious Organization",
            "type":"Services"
        }
    ],
    "sg:phone":"+1 219 886 2351",
    "sg:postcode":"46407",
    "sg:province":"IN",
    "sg:tags":[
        "church"
    ],
    "wof:name":"Peter Rock Chr-God In Christ",
    "wof:placetype":"venue"
},
  "geometry": {"coordinates":[-87.345654,41.569099],"type":"Point"}
}