{
  "type": "Feature",
  "properties": {
    "addr:full":"1904 Maumee Ave Fort Wayne IN 46803",
    "addr:housenumber":"1904",
    "addr:postcode":"46803",
    "addr:street":"Maumee Ave",
    "iso:country":"US",
    "sg:address":"1904 Maumee Ave",
    "sg:city":"Fort Wayne",
    "sg:classifiers":[
        {
            "category":"Autos & Motor Vehicles",
            "subcategory":"Automobile Sales",
            "type":"Retail Goods"
        }
    ],
    "sg:phone":"+1 260 424 1249",
    "sg:postcode":"46803",
    "sg:province":"IN",
    "sg:tags":[
        "car",
        "dealer"
    ],
    "wof:name":"L & L Auto Sales",
    "wof:placetype":"venue"
},
  "geometry": {"coordinates":[-85.111964,41.075451],"type":"Point"}
}