{
  "type": "Feature",
  "properties": {
    "addr:full":"1475 Cedar Ln NW Corydon IN 47112",
    "addr:housenumber":"1475",
    "addr:postcode":"47112",
    "addr:street":"Cedar Ln Nw",
    "iso:country":"US",
    "sg:address":"1475 Cedar Ln NW",
    "sg:city":"Corydon",
    "sg:classifiers":[
        {
            "category":"Real Estate",
            "subcategory":"Real Estate Agent",
            "type":"Services"
        }
    ],
    "sg:phone":"+1 812 738 1128",
    "sg:postcode":"47112",
    "sg:province":"IN",
    "wof:name":"Albers Realty Group",
    "wof:placetype":"venue"
},
  "geometry": {"coordinates":[-86.152191,38.222362],"type":"Point"}
}