{
  "type": "Feature",
  "properties": {
    "iso:country":"US",
    "sg:address":"518 S 21st St",
    "sg:city":"Richmond",
    "sg:classifiers":[
        {
            "category":"Social Services",
            "subcategory":"Child Care",
            "type":"Services"
        }
    ],
    "sg:phone":"+1 765 983 3610",
    "sg:postcode":"47374",
    "sg:province":"IN",
    "wof:name":"Childcare Connection",
    "wof:placetype":"venue"
},
  "geometry": {"coordinates":[-84.874411,39.81925],"type":"Point"}
}