{
  "type": "Feature",
  "properties": {
    "iso:country":"US",
    "sg:address":"9462 N State Rd 19",
    "sg:city":"Etna Green",
    "sg:classifiers":[
        {
            "category":"Real Estate",
            "subcategory":"Real Estate Operator",
            "type":"Services"
        }
    ],
    "sg:phone":"+1 574 646 2733",
    "sg:postcode":"46524",
    "sg:province":"IN",
    "sg:tags":[
        "mobile",
        "home",
        "site"
    ],
    "wof:name":"Mikel Mobile Est",
    "wof:placetype":"venue"
},
  "geometry": {"coordinates":[-86.001797,41.361275],"type":"Point"}
}