{
  "type": "Feature",
  "properties": {
    "iso:country":"US",
    "sg:address":"51186 State Rd 19",
    "sg:city":"Elkhart",
    "sg:classifiers":[
        {
            "category":"Retail",
            "subcategory":"Animal Services",
            "type":"Services"
        }
    ],
    "sg:phone":"+1 574 206 8690",
    "sg:postcode":"46514",
    "sg:province":"IN",
    "sg:tags":[
        "pet",
        "grooming",
        "washing"
    ],
    "wof:name":"Pretty Paws",
    "wof:placetype":"venue"
},
  "geometry": {"coordinates":[-85.975016,41.75004],"type":"Point"}
}