{
  "type": "Feature",
  "properties": {
    "iso:country":"US",
    "sg:address":"447 N Old State Road 2",
    "sg:city":"Valparaiso",
    "sg:classifiers":[
        {
            "category":"Freight",
            "type":"Transportation"
        }
    ],
    "sg:phone":"+1 219 462 6946",
    "sg:postcode":"46383",
    "sg:province":"IN",
    "sg:tags":[
        "hauling",
        "trucking"
    ],
    "wof:name":"Young Brothers",
    "wof:placetype":"venue"
},
  "geometry": {"coordinates":[-86.951774,41.507783],"type":"Point"}
}