{
  "type": "Feature",
  "properties": {
    "addr:full":"757 N Clark Blvd Clarksville IN 47129",
    "addr:housenumber":"757",
    "addr:postcode":"47129",
    "addr:street":"N Clark Blvd",
    "iso:country":"US",
    "sg:address":"757 N Clark Blvd",
    "sg:city":"Clarksville",
    "sg:classifiers":[
        {
            "category":"Food & Beverages",
            "subcategory":"Specialty",
            "type":"Retail Goods"
        }
    ],
    "sg:phone":"+1 812 288 8970",
    "sg:postcode":"47129",
    "sg:province":"IN",
    "sg:tags":[
        "health",
        "diet"
    ],
    "wof:name":"GNC",
    "wof:placetype":"venue"
},
  "geometry": {"coordinates":[-85.772166,38.296768],"type":"Point"}
}