{
  "type": "Feature",
  "properties": {
    "iso:country":"US",
    "sg:address":"3609 Fritcha Ave",
    "sg:city":"Fort Wayne",
    "sg:classifiers":[
        {
            "category":"Building & Trades",
            "subcategory":"Construction",
            "type":"Services"
        }
    ],
    "sg:phone":"+1 260 749 5578",
    "sg:postcode":"46806",
    "sg:province":"IN",
    "sg:tags":[
        "contractor"
    ],
    "wof:name":"D&D Roofing",
    "wof:placetype":"venue"
},
  "geometry": {"coordinates":[-85.042155,41.052577],"type":"Point"}
}