{
  "type": "Feature",
  "properties": {
    "iso:country":"US",
    "sg:address":"3961 S Meridian St",
    "sg:city":"Indianapolis",
    "sg:classifiers":[
        {
            "category":"Personal",
            "subcategory":"Beauty Salon",
            "type":"Services"
        }
    ],
    "sg:phone":"+1 317 782 8737",
    "sg:postcode":"46217",
    "sg:province":"IN",
    "wof:name":"Master Hair Design",
    "wof:placetype":"venue"
},
  "geometry": {"coordinates":[-86.158393,39.708524],"type":"Point"}
}