{
  "type": "Feature",
  "properties": {
    "iso:country":"US",
    "sg:address":"151 S High St",
    "sg:city":"Warsaw",
    "sg:classifiers":[
        {
            "category":"Retail",
            "subcategory":"Photofinishing",
            "type":"Services"
        }
    ],
    "sg:phone":"+1 574 269 3686",
    "sg:postcode":"46580",
    "sg:province":"IN",
    "sg:tags":[
        "photo",
        "finishing"
    ],
    "wof:name":"Apollo One Hour Photo Ctr",
    "wof:placetype":"venue"
},
  "geometry": {"coordinates":[-85.854008,41.237579],"type":"Point"}
}