{
  "type": "Feature",
  "properties": {
    "addr:full":"509 E Walnut St Boonville IN 47601",
    "addr:housenumber":"509",
    "addr:postcode":"47601",
    "addr:street":"E Walnut St",
    "iso:country":"US",
    "sg:address":"509 E Walnut St",
    "sg:city":"Boonville",
    "sg:classifiers":[
        {
            "category":"Organizations",
            "subcategory":"Religious Organization",
            "type":"Services"
        }
    ],
    "sg:phone":"+1 812 897 2063",
    "sg:postcode":"47601",
    "sg:province":"IN",
    "sg:tags":[
        "church"
    ],
    "sg:website":"www.wesleyan.org",
    "wof:name":"Wesleyan Church",
    "wof:placetype":"venue"
},
  "geometry": {"coordinates":[-87.26950100000001,38.0481],"type":"Point"}
}