{
  "type": "Feature",
  "properties": {
    "iso:country":"US",
    "sg:address":"104 Elmhurst Dr",
    "sg:city":"Richmond",
    "sg:classifiers":[
        {
            "category":"Retail",
            "subcategory":"Laundry & Dry Cleaning",
            "type":"Services"
        }
    ],
    "sg:phone":"+1 765 962 7818",
    "sg:postcode":"47374",
    "sg:province":"IN",
    "wof:name":"Dewey Williams Crpt Svc",
    "wof:placetype":"venue"
},
  "geometry": {"coordinates":[-84.822191,39.835134],"type":"Point"}
}