{
  "type": "Feature",
  "properties": {
    "iso:country":"US",
    "sg:address":"6810 Koester Dr",
    "sg:city":"Fort Wayne",
    "sg:classifiers":[
        {
            "category":"Wholesale",
            "subcategory":"Durable Goods & Equipment",
            "type":"Manufacturing & Wholesale Goods"
        }
    ],
    "sg:phone":"+1 260 747 0127",
    "sg:postcode":"46819",
    "sg:province":"IN",
    "wof:name":"William Larimore",
    "wof:placetype":"venue"
},
  "geometry": {"coordinates":[-85.16504399999999,41.019715],"type":"Point"}
}