{
  "type": "Feature",
  "properties": {
    "addr:full":"2050 Wood St Madison IN 47250",
    "addr:housenumber":"2050",
    "addr:postcode":"47250",
    "addr:street":"Wood St",
    "iso:country":"US",
    "sg:address":"2050 Wood St",
    "sg:city":"Madison",
    "sg:classifiers":[
        {
            "category":"Real Estate",
            "subcategory":"Real Estate Operator",
            "type":"Services"
        }
    ],
    "sg:phone":"+1 812 273 3322",
    "sg:postcode":"47250",
    "sg:province":"IN",
    "sg:tags":[
        "building",
        "apartment"
    ],
    "wof:name":"F M Eversole Apartments",
    "wof:placetype":"venue"
},
  "geometry": {"coordinates":[-85.40189599999999,38.765585],"type":"Point"}
}