{
  "type": "Feature",
  "properties": {
    "addr:full":"16500 E Co Rd 400 N Hope IN 47246",
    "addr:housenumber":"16500",
    "addr:postcode":"47246",
    "addr:street":"E Co Rd 400 N",
    "iso:country":"US",
    "sg:address":"16500 E Co Rd 400 N",
    "sg:city":"Hope",
    "sg:phone":"+1 812 546 4229",
    "sg:postcode":"47246",
    "sg:province":"IN",
    "sg:tags":[
        "farm",
        "corn",
        "soybean"
    ],
    "wof:name":"Paul Ketner",
    "wof:placetype":"venue"
},
  "geometry": {"coordinates":[-85.742819,39.261586],"type":"Point"}
}