{
  "type": "Feature",
  "properties": {
    "addr:full":"100 Central Ave Salem IN 47167",
    "addr:housenumber":"100",
    "addr:postcode":"47167",
    "addr:street":"Central Ave",
    "iso:country":"US",
    "sg:address":"100 Central Ave",
    "sg:city":"Salem",
    "sg:classifiers":[
        {
            "category":"Real Estate",
            "subcategory":"Real Estate Operator",
            "type":"Services"
        }
    ],
    "sg:phone":"+1 812 883 4765",
    "sg:postcode":"47167",
    "sg:province":"IN",
    "sg:tags":[
        "mobile",
        "home",
        "community"
    ],
    "wof:name":"Southway Villa",
    "wof:placetype":"venue"
},
  "geometry": {"coordinates":[-86.06363899999999,38.586875],"type":"Point"}
}