{
  "type": "Feature",
  "properties": {
    "addr:full":"913 W Co Rd 850 N Orleans IN 47452",
    "addr:housenumber":"913;850",
    "addr:postcode":"47452",
    "addr:street":"W Co Rd;N Orleans",
    "iso:country":"US",
    "sg:address":"913 W Co Rd 850 N",
    "sg:city":"Orleans",
    "sg:classifiers":[
        {
            "category":"Food & Beverages",
            "subcategory":"Specialty",
            "type":"Retail Goods"
        }
    ],
    "sg:phone":"+1 812 865 3194",
    "sg:postcode":"47452",
    "sg:province":"IN",
    "sg:tags":[
        "herb"
    ],
    "wof:name":"Herbalife Distributor",
    "wof:placetype":"venue"
},
  "geometry": {"coordinates":[-86.47628,38.681932],"type":"Point"}
}