{
  "type": "Feature",
  "properties": {
    "addr:full":"3820 W Jackson St Muncie IN 47304",
    "addr:housenumber":"3820",
    "addr:postcode":"47304",
    "addr:street":"W Jackson St",
    "iso:country":"US",
    "sg:address":"3820 W Jackson St",
    "sg:city":"Muncie",
    "sg:classifiers":[
        {
            "category":"Health Services",
            "subcategory":"Nursing And Care Facility",
            "type":"Services"
        }
    ],
    "sg:phone":"+1 765 289 3451",
    "sg:postcode":"47304",
    "sg:province":"IN",
    "sg:tags":[
        "home",
        "convalescent"
    ],
    "wof:name":"Woodlands",
    "wof:placetype":"venue"
},
  "geometry": {"coordinates":[-85.43032100000001,40.193061],"type":"Point"}
}