{
  "type": "Feature",
  "properties": {
    "iso:country":"US",
    "sg:address":"2207 E Morgan Ave",
    "sg:city":"Evansville",
    "sg:classifiers":[
        {
            "category":"Social Services",
            "type":"Services"
        }
    ],
    "sg:phone":"+1 812 477 9002",
    "sg:postcode":"47711",
    "sg:province":"IN",
    "sg:tags":[
        "organization",
        "welfare"
    ],
    "wof:name":"Evansville Center For Womens",
    "wof:placetype":"venue"
},
  "geometry": {"coordinates":[-87.524213,37.991555],"type":"Point"}
}