{
  "type": "Feature",
  "properties": {
    "iso:country":"US",
    "sg:address":"1112 W 7th St",
    "sg:city":"Auburn",
    "sg:classifiers":[
        {
            "category":"Building & Trades",
            "subcategory":"Construction",
            "type":"Services"
        }
    ],
    "sg:phone":"+1 260 925 4414",
    "sg:postcode":"46706",
    "sg:province":"IN",
    "wof:name":"Auburn Mobile Homes",
    "wof:placetype":"venue"
},
  "geometry": {"coordinates":[-85.076452,41.366707],"type":"Point"}
}