{
  "type": "Feature",
  "properties": {
    "iso:country":"US",
    "sg:address":"1431 W 75th Pl",
    "sg:city":"Merrillville",
    "sg:classifiers":[
        {
            "category":"Shopping",
            "subcategory":"Gifts & Souvenirs",
            "type":"Retail Goods"
        }
    ],
    "sg:phone":"+1 219 769 0072",
    "sg:postcode":"46410",
    "sg:province":"IN",
    "sg:tags":[
        "indian"
    ],
    "wof:name":"Affordable Treasures",
    "wof:placetype":"venue"
},
  "geometry": {"coordinates":[-87.353744,41.481339],"type":"Point"}
}