{
  "type": "Feature",
  "properties": {
    "iso:country":"US",
    "sg:address":"3411 E 36th Ave",
    "sg:city":"Lake Station",
    "sg:classifiers":[
        {
            "category":"Building & Trades",
            "subcategory":"Plumbing",
            "type":"Services"
        }
    ],
    "sg:phone":"+1 219 963 3152",
    "sg:postcode":"46405",
    "sg:province":"IN",
    "sg:tags":[
        "conditioning",
        "air",
        "system",
        "contractor"
    ],
    "wof:name":"Scotty's Heating & Cooling",
    "wof:placetype":"venue"
},
  "geometry": {"coordinates":[-87.288267,41.552531],"type":"Point"}
}