{
  "type": "Feature",
  "properties": {
    "iso:country":"US",
    "sg:address":"509 John St",
    "sg:city":"Crawfordsville",
    "sg:classifiers":[
        {
            "category":"Building & Trades",
            "subcategory":"Construction",
            "type":"Services"
        }
    ],
    "sg:phone":"+1 765 361 9181",
    "sg:postcode":"47933",
    "sg:province":"IN",
    "sg:tags":[
        "general",
        "contractor"
    ],
    "wof:name":"Thomas Cotten & Assoc Inc",
    "wof:placetype":"venue"
},
  "geometry": {"coordinates":[-86.89301,40.036986],"type":"Point"}
}