{
  "type": "Feature",
  "properties": {
    "addr:full":"415 Meigs Ave Jeffersonville IN 47130",
    "addr:housenumber":"415",
    "addr:postcode":"47130",
    "addr:street":"Meigs Ave",
    "iso:country":"US",
    "sg:address":"415 Meigs Ave",
    "sg:city":"Jeffersonville",
    "sg:classifiers":[
        {
            "category":"Retail",
            "subcategory":"Event Space",
            "type":"Services"
        }
    ],
    "sg:phone":"+1 502 548 7836",
    "sg:postcode":"47130",
    "sg:province":"IN",
    "sg:tags":[
        "facility",
        "hall",
        "reception",
        "banquet"
    ],
    "wof:name":"Eberts 1864 Cottage",
    "wof:placetype":"venue"
},
  "geometry": {"coordinates":[-85.73524399999999,38.27621],"type":"Point"}
}