{
  "type": "Feature",
  "properties": {
    "iso:country":"US",
    "sg:address":"3318 Lake City Hwy",
    "sg:city":"Warsaw",
    "sg:classifiers":[
        {
            "category":"Wholesale",
            "subcategory":"Machinery & Supplies",
            "type":"Manufacturing & Wholesale Goods"
        }
    ],
    "sg:phone":"+1 574 267 0015",
    "sg:postcode":"46580",
    "sg:province":"IN",
    "sg:tags":[
        "salon",
        "beauty"
    ],
    "wof:name":"Sally Beauty Supply",
    "wof:placetype":"venue"
},
  "geometry": {"coordinates":[-85.809775,41.235543],"type":"Point"}
}