{
  "type": "Feature",
  "properties": {
    "addr:full":"3453 Chamberlin Dr Indianapolis IN 46237",
    "addr:housenumber":"3453",
    "addr:postcode":"46237",
    "addr:street":"Chamberlin Dr",
    "iso:country":"US",
    "sg:address":"3453 Chamberlin Dr",
    "sg:city":"Indianapolis",
    "sg:classifiers":[
        {
            "category":"Professional",
            "subcategory":"Computer Services",
            "type":"Services"
        }
    ],
    "sg:phone":"+1 317 783 3683",
    "sg:postcode":"46237",
    "sg:province":"IN",
    "sg:tags":[
        "business"
    ],
    "wof:name":"Kge Enterprises",
    "wof:placetype":"venue"
},
  "geometry": {"coordinates":[-86.102546,39.698588],"type":"Point"}
}