{
  "type": "Feature",
  "properties": {
    "iso:country":"US",
    "sg:address":"12302 Covered Bridge Rd",
    "sg:city":"Sellersburg",
    "sg:classifiers":[
        {
            "category":"Building & Trades",
            "subcategory":"Construction",
            "type":"Services"
        }
    ],
    "sg:phone":"+1 812 246 8006",
    "sg:postcode":"47172",
    "sg:province":"IN",
    "sg:tags":[
        "general",
        "contractor"
    ],
    "wof:name":"Tom Ballage Builders Inc",
    "wof:placetype":"venue"
},
  "geometry": {"coordinates":[-85.794645,38.433617],"type":"Point"}
}