{
  "type": "Feature",
  "properties": {
    "iso:country":"US",
    "sg:address":"3723 Main St",
    "sg:city":"East Chicago",
    "sg:classifiers":[
        {
            "category":"Health Services",
            "subcategory":"Doctor",
            "type":"Services"
        }
    ],
    "sg:phone":"+1 219 397 4071",
    "sg:postcode":"46312",
    "sg:province":"IN",
    "sg:tags":[
        "clinic"
    ],
    "wof:name":"Planned Parenthood",
    "wof:placetype":"venue"
},
  "geometry": {"coordinates":[-87.44489,41.644788],"type":"Point"}
}