{
  "type": "Feature",
  "properties": {
    "iso:country":"US",
    "sg:address":"1268 Waterworks Rd",
    "sg:city":"Huntington",
    "sg:classifiers":[
        {
            "category":"Building & Trades",
            "subcategory":"Electrical",
            "type":"Services"
        }
    ],
    "sg:phone":"+1 260 356 5431",
    "sg:postcode":"46750",
    "sg:province":"IN",
    "sg:tags":[
        "electric",
        "contractor"
    ],
    "wof:name":"Fulton Electric Inc",
    "wof:placetype":"venue"
},
  "geometry": {"coordinates":[-85.486325,40.859797],"type":"Point"}
}