{
  "type": "Feature",
  "properties": {
    "iso:country":"US",
    "sg:address":"833 E Main St",
    "sg:city":"Albion",
    "sg:classifiers":[
        {
            "category":"Organizations",
            "subcategory":"Community Association",
            "type":"Services"
        }
    ],
    "sg:phone":"+1 260 636 7011",
    "sg:postcode":"46701",
    "sg:province":"IN",
    "sg:tags":[
        "educational"
    ],
    "wof:name":"Leap Of Noble Co Inc",
    "wof:placetype":"venue"
},
  "geometry": {"coordinates":[-85.41478,41.395991],"type":"Point"}
}