{
  "type": "Feature",
  "properties": {
    "addr:full":"2336 N Alabama St Indianapolis IN 46205",
    "addr:housenumber":"2336",
    "addr:postcode":"46205",
    "addr:street":"N Alabama St",
    "iso:country":"US",
    "sg:address":"2336 N Alabama St",
    "sg:city":"Indianapolis",
    "sg:classifiers":[
        {
            "category":"Retail",
            "subcategory":"Laundry & Dry Cleaning",
            "type":"Services"
        },
        {
            "category":"Shopping",
            "subcategory":"Clothing, Apparel, & Fashions",
            "type":"Retail Goods"
        }
    ],
    "sg:phone":"+1 317 923 9171",
    "sg:postcode":"46205",
    "sg:province":"IN",
    "sg:tags":[
        "alteration"
    ],
    "wof:name":"Lennie's Alterations",
    "wof:placetype":"venue"
},
  "geometry": {"coordinates":[-86.152027,39.800475],"type":"Point"}
}