{
  "type": "Feature",
  "properties": {
    "iso:country":"US",
    "sg:address":"1124 State Rd 66",
    "sg:city":"Rockport",
    "sg:classifiers":[
        {
            "category":"Organizations",
            "subcategory":"Religious Organization",
            "type":"Services"
        }
    ],
    "sg:phone":"+1 812 649 4135",
    "sg:postcode":"47635",
    "sg:province":"IN",
    "wof:name":"Apostolic Bible Church",
    "wof:placetype":"venue"
},
  "geometry": {"coordinates":[-87.074844,37.894838],"type":"Point"}
}