{
  "type": "Feature",
  "properties": {
    "addr:full":"375 Elston Rd Lafayette IN 47909",
    "addr:housenumber":"375",
    "addr:postcode":"47909",
    "addr:street":"Elston Rd",
    "iso:country":"US",
    "sg:address":"375 Elston Rd",
    "sg:city":"Lafayette",
    "sg:classifiers":[
        {
            "category":"Organizations",
            "subcategory":"Religious Organization",
            "type":"Services"
        }
    ],
    "sg:phone":"+1 765 474 3881",
    "sg:postcode":"47909",
    "sg:province":"IN",
    "sg:tags":[
        "church"
    ],
    "wof:name":"Elston Presbyterian Church",
    "wof:placetype":"venue"
},
  "geometry": {"coordinates":[-86.910808,40.39303],"type":"Point"}
}