{
  "type": "Feature",
  "properties": {
    "iso:country":"US",
    "sg:address":"1780 McCall Dr",
    "sg:city":"Shelbyville",
    "sg:classifiers":[
        {
            "category":"Building & Trades",
            "subcategory":"Construction",
            "type":"Services"
        }
    ],
    "sg:phone":"+1 317 392 3536",
    "sg:postcode":"46176",
    "sg:province":"IN",
    "wof:name":"American Building Components",
    "wof:placetype":"venue"
},
  "geometry": {"coordinates":[-85.783355,39.553369],"type":"Point"}
}