{
  "type": "Feature",
  "properties": {
    "iso:country":"US",
    "sg:address":"12005 N Executive Dr",
    "sg:city":"Edinburgh",
    "sg:classifiers":[
        {
            "category":"Restaurant",
            "type":"Food & Drink"
        }
    ],
    "sg:phone":"+1 812 526 6250",
    "sg:postcode":"46124",
    "sg:province":"IN",
    "wof:name":"Max & Erma's",
    "wof:placetype":"venue"
},
  "geometry": {"coordinates":[-85.964387,39.311724],"type":"Point"}
}