{
  "type": "Feature",
  "properties": {
    "iso:country":"US",
    "sg:address":"411 S Co Rd 550 E",
    "sg:city":"Selma",
    "sg:classifiers":[
        {
            "category":"Retail",
            "subcategory":"Animal Services",
            "type":"Services"
        }
    ],
    "sg:phone":"+1 765 284 0953",
    "sg:postcode":"47383",
    "sg:province":"IN",
    "sg:tags":[
        "pet",
        "boarding",
        "sitting"
    ],
    "wof:name":"Talawanda Kennels",
    "wof:placetype":"venue"
},
  "geometry": {"coordinates":[-85.283007,40.189537],"type":"Point"}
}