{
  "type": "Feature",
  "properties": {
    "iso:country":"US",
    "sg:address":"9903 Neil Armstrong Ct",
    "sg:city":"Fort Wayne",
    "sg:classifiers":[
        {
            "category":"Wholesale",
            "subcategory":"Stationery",
            "type":"Manufacturing & Wholesale Goods"
        }
    ],
    "sg:phone":"+1 260 436 5980",
    "sg:postcode":"46804",
    "sg:province":"IN",
    "sg:tags":[
        "product",
        "paper"
    ],
    "wof:name":"Foundation Inc",
    "wof:placetype":"venue"
},
  "geometry": {"coordinates":[-85.272604,41.036241],"type":"Point"}
}