{
  "type": "Feature",
  "properties": {
    "iso:country":"US",
    "sg:address":"740 E 81st Ave",
    "sg:city":"Merrillville",
    "sg:classifiers":[
        {
            "category":"Restaurant",
            "type":"Food & Drink"
        }
    ],
    "sg:menulink":"http://www.allmenus.com/in/ross/101107-smokey-bones/menu/",
    "sg:phone":"+1 219 736 0885",
    "sg:postcode":"46410",
    "sg:province":"IN",
    "sg:tags":[
        "barbecue",
        "american"
    ],
    "wof:name":"Smokey Bones",
    "wof:placetype":"venue"
},
  "geometry": {"coordinates":[-87.328337,41.471236],"type":"Point"}
}