{
  "type": "Feature",
  "properties": {
    "iso:country":"US",
    "sg:address":"7863 Broadway",
    "sg:city":"Merrillville",
    "sg:classifiers":[
        {
            "category":"Real Estate",
            "subcategory":"Real Estate Operator",
            "type":"Services"
        }
    ],
    "sg:phone":"+1 219 736 8289",
    "sg:postcode":"46410",
    "sg:province":"IN",
    "sg:tags":[
        "building",
        "parks"
    ],
    "wof:name":"Chapel Square",
    "wof:placetype":"venue"
},
  "geometry": {"coordinates":[-87.335907,41.476383],"type":"Point"}
}