{
  "type": "Feature",
  "properties": {
    "iso:country":"US",
    "sg:address":"8645 E State Rd 32",
    "sg:city":"Zionsville",
    "sg:phone":"+1 317 769 4593",
    "sg:postcode":"46077",
    "sg:province":"IN",
    "sg:tags":[
        "beef",
        "farm",
        "corn",
        "soybean",
        "cattle",
        "feedlot"
    ],
    "wof:name":"Fannie Wright Belle",
    "wof:placetype":"venue"
},
  "geometry": {"coordinates":[-86.299436,40.040659],"type":"Point"}
}