{
  "type": "Feature",
  "properties": {
    "addr:full":"434 Merkler St Fort Wayne IN 46825",
    "addr:housenumber":"434",
    "addr:postcode":"46825",
    "addr:street":"Merkler St",
    "iso:country":"US",
    "sg:address":"434 Merkler St",
    "sg:city":"Fort Wayne",
    "sg:classifiers":[
        {
            "category":"Retail",
            "subcategory":"Auto Repair",
            "type":"Services"
        }
    ],
    "sg:phone":"+1 260 482 6430",
    "sg:postcode":"46825",
    "sg:province":"IN",
    "sg:tags":[
        "lettering",
        "truck"
    ],
    "wof:name":"Morgan Commercial Lettering",
    "wof:placetype":"venue"
},
  "geometry": {"coordinates":[-85.148494,41.119896],"type":"Point"}
}