{
  "type": "Feature",
  "properties": {
    "iso:country":"US",
    "sg:address":"3602 W Washington St",
    "sg:city":"Indianapolis",
    "sg:classifiers":[
        {
            "category":"Manufacturing",
            "subcategory":"Food",
            "type":"Manufacturing & Wholesale Goods"
        }
    ],
    "sg:phone":"+1 317 926 2451",
    "sg:postcode":"46241",
    "sg:province":"IN",
    "sg:tags":[
        "ice"
    ],
    "wof:name":"Home City Ice",
    "wof:placetype":"venue"
},
  "geometry": {"coordinates":[-86.222901,39.761336],"type":"Point"}
}