{
  "type": "Feature",
  "properties": {
    "iso:country":"US",
    "sg:address":"2059 N Grand Ave",
    "sg:city":"Connersville",
    "sg:classifiers":[
        {
            "category":"Food & Beverages",
            "subcategory":"Groceries & Convenience Stores",
            "type":"Retail Goods"
        }
    ],
    "sg:phone":"+1 765 825 9616",
    "sg:postcode":"47331",
    "sg:province":"IN",
    "wof:name":"Daum's Dairy Mart",
    "wof:placetype":"venue"
},
  "geometry": {"coordinates":[-85.134914,39.658767],"type":"Point"}
}