{
  "type": "Feature",
  "properties": {
    "iso:country":"US",
    "sg:address":"5500 Melton Rd",
    "sg:city":"Portage",
    "sg:classifiers":[
        {
            "category":"Travel",
            "subcategory":"Hotels & Motels",
            "type":"Entertainment"
        }
    ],
    "sg:phone":"+1 219 762 3317",
    "sg:postcode":"46368",
    "sg:province":"IN",
    "wof:name":"Don's Motel & Mobile Home Park",
    "wof:placetype":"venue"
},
  "geometry": {"coordinates":[-87.20656,41.591964],"type":"Point"}
}