{
  "type": "Feature",
  "properties": {
    "iso:country":"US",
    "sg:address":"398 N 600 E",
    "sg:city":"Portland",
    "sg:classifiers":[
        {
            "category":"Building & Trades",
            "subcategory":"Electrical",
            "type":"Services"
        }
    ],
    "sg:phone":"+1 260 726 2544",
    "sg:postcode":"47371",
    "sg:province":"IN",
    "sg:tags":[
        "contractor",
        "electrical",
        "supply"
    ],
    "wof:name":"Portland Electric Inc",
    "wof:placetype":"venue"
},
  "geometry": {"coordinates":[-84.863833,40.445569],"type":"Point"}
}