{
  "type": "Feature",
  "properties": {
    "iso:country":"US",
    "sg:address":"2037 Main St",
    "sg:city":"Tell City",
    "sg:classifiers":[
        {
            "category":"Home & Garden",
            "subcategory":"Building Materials",
            "type":"Retail Goods"
        }
    ],
    "sg:phone":"+1 812 547 8929",
    "sg:postcode":"47586",
    "sg:province":"IN",
    "sg:website":"www.information.net",
    "wof:name":"Thriftway",
    "wof:placetype":"venue"
},
  "geometry": {"coordinates":[-86.799267,37.997471],"type":"Point"}
}