{
  "type": "Feature",
  "properties": {
    "iso:country":"US",
    "sg:address":"1920 Dr Martin Luther King St",
    "sg:city":"Indianapolis",
    "sg:classifiers":[
        {
            "category":"Freight",
            "type":"Transportation"
        }
    ],
    "sg:phone":"+1 317 921 2229",
    "sg:postcode":"46202",
    "sg:province":"IN",
    "sg:tags":[
        "trucking"
    ],
    "wof:name":"K & L Transport",
    "wof:placetype":"venue"
},
  "geometry": {"coordinates":[-86.168515,39.791643],"type":"Point"}
}