{
  "type": "Feature",
  "properties": {
    "iso:country":"US",
    "sg:address":"730 S 5th St",
    "sg:city":"Clinton",
    "sg:classifiers":[
        {
            "category":"Personal",
            "subcategory":"Beauty Salon",
            "type":"Services"
        }
    ],
    "sg:phone":"+1 765 832 2888",
    "sg:postcode":"47842",
    "sg:province":"IN",
    "wof:name":"Shear Madness Hair Salon",
    "wof:placetype":"venue"
},
  "geometry": {"coordinates":[-87.402382,39.653744],"type":"Point"}
}