{
  "type": "Feature",
  "properties": {
    "addr:full":"10251 Hague Rd Indianapolis IN 46256",
    "addr:housenumber":"10251",
    "addr:postcode":"46256",
    "addr:street":"Hague Rd",
    "iso:country":"US",
    "sg:address":"10251 Hague Rd",
    "sg:city":"Indianapolis",
    "sg:classifiers":[
        {
            "category":"Retail",
            "subcategory":"Car Wash",
            "type":"Services"
        }
    ],
    "sg:phone":"+1 317 359 1818",
    "sg:postcode":"46256",
    "sg:province":"IN",
    "wof:name":"Mike's Express Carwash",
    "wof:placetype":"venue"
},
  "geometry": {"coordinates":[-86.033096,39.936401],"type":"Point"}
}