{
  "type": "Feature",
  "properties": {
    "iso:country":"US",
    "sg:address":"854 N Depot Hill Rd",
    "sg:city":"Milltown",
    "sg:classifiers":[
        {
            "category":"Building & Trades",
            "subcategory":"Construction",
            "type":"Services"
        }
    ],
    "sg:phone":"+1 812 365 2422",
    "sg:postcode":"47145",
    "sg:province":"IN",
    "sg:tags":[
        "repairing",
        "remodeling",
        "contractor"
    ],
    "wof:name":"Home Services",
    "wof:placetype":"venue"
},
  "geometry": {"coordinates":[-86.336229,38.351112],"type":"Point"}
}