{
  "type": "Feature",
  "properties": {
    "iso:country":"US",
    "sg:address":"201 N 3rd St",
    "sg:city":"Kentland",
    "sg:classifiers":[
        {
            "category":"Professional",
            "subcategory":"Business Services",
            "type":"Services"
        }
    ],
    "sg:phone":"+1 219 474 9511",
    "sg:postcode":"47951",
    "sg:province":"IN",
    "sg:tags":[
        "information",
        "referral"
    ],
    "wof:name":"Quest Info System",
    "wof:placetype":"venue"
},
  "geometry": {"coordinates":[-87.44512400000001,40.770137],"type":"Point"}
}