{
  "type": "Feature",
  "properties": {
    "iso:country":"US",
    "sg:address":"3929 E Jackson Blvd",
    "sg:city":"Elkhart",
    "sg:classifiers":[
        {
            "category":"Retail",
            "subcategory":"Veterinary Services",
            "type":"Services"
        }
    ],
    "sg:phone":"+1 574 293 4555",
    "sg:postcode":"46516",
    "sg:province":"IN",
    "sg:tags":[
        "veterinarian"
    ],
    "wof:name":"Noah's Landing Pet Care Clinic",
    "wof:placetype":"venue"
},
  "geometry": {"coordinates":[-85.91473999999999,41.693268],"type":"Point"}
}