{
  "type": "Feature",
  "properties": {
    "iso:country":"US",
    "sg:address":"3916 Frisse Ave",
    "sg:city":"Evansville",
    "sg:classifiers":[
        {
            "category":"Social Services",
            "subcategory":"Child Care",
            "type":"Services"
        }
    ],
    "sg:phone":"+1 812 401 8623",
    "sg:postcode":"47714",
    "sg:province":"IN",
    "sg:tags":[
        "day"
    ],
    "wof:name":"Saras Daycare",
    "wof:placetype":"venue"
},
  "geometry": {"coordinates":[-87.499906,37.944316],"type":"Point"}
}