{
  "type": "Feature",
  "properties": {
    "iso:country":"US",
    "sg:address":"12540 McKinley Hwy",
    "sg:city":"Mishawaka",
    "sg:classifiers":[
        {
            "category":"Autos & Motor Vehicles",
            "subcategory":"Automobile Sales",
            "type":"Retail Goods"
        }
    ],
    "sg:phone":"+1 574 254 0080",
    "sg:postcode":"46545",
    "sg:province":"IN",
    "sg:tags":[
        "car",
        "dealer"
    ],
    "wof:name":"J V Automotive Inc",
    "wof:placetype":"venue"
},
  "geometry": {"coordinates":[-86.111733,41.684253],"type":"Point"}
}