{
  "type": "Feature",
  "properties": {
    "iso:country":"US",
    "sg:address":"2067 Rollett Ln",
    "sg:city":"Evansville",
    "sg:classifiers":[
        {
            "category":"Professional",
            "subcategory":"Engineering",
            "type":"Services"
        }
    ],
    "sg:phone":"+1 812 421 9907",
    "sg:postcode":"47712",
    "sg:province":"IN",
    "wof:name":"Geo-Tech Environmental Service",
    "wof:placetype":"venue"
},
  "geometry": {"coordinates":[-87.63403099999999,37.95942],"type":"Point"}
}