{
  "type": "Feature",
  "properties": {
    "iso:country":"US",
    "sg:address":"704 E Pearl St",
    "sg:city":"Batesville",
    "sg:classifiers":[
        {
            "category":"Autos & Motor Vehicles",
            "subcategory":"Auto Supplies",
            "type":"Retail Goods"
        }
    ],
    "sg:phone":"+1 812 934 2115",
    "sg:postcode":"47006",
    "sg:province":"IN",
    "sg:tags":[
        "automobile",
        "parts"
    ],
    "wof:name":"Indiana Auto Parts",
    "wof:placetype":"venue"
},
  "geometry": {"coordinates":[-85.217212,39.295905],"type":"Point"}
}