{
  "type": "Feature",
  "properties": {
    "addr:full":"2036 E US Hwy 20 Michigan City IN 46360",
    "addr:housenumber":"2036",
    "addr:postcode":"46360",
    "addr:street":"E Us Hwy 20",
    "iso:country":"US",
    "sg:address":"2036 E US Hwy 20",
    "sg:city":"Michigan City",
    "sg:classifiers":[
        {
            "category":"Home & Garden",
            "subcategory":"Carpets & Floor Coverings",
            "type":"Retail Goods"
        }
    ],
    "sg:phone":"+1 219 874 2300",
    "sg:postcode":"46360",
    "sg:province":"IN",
    "sg:tags":[
        "material"
    ],
    "wof:name":"Flooring Center",
    "wof:placetype":"venue"
},
  "geometry": {"coordinates":[-86.852295,41.68746],"type":"Point"}
}