{
  "type": "Feature",
  "properties": {
    "iso:country":"US",
    "sg:address":"11710 Gumbel Rd",
    "sg:city":"Evansville",
    "sg:classifiers":[
        {
            "category":"Building & Trades",
            "subcategory":"Construction",
            "type":"Services"
        }
    ],
    "sg:phone":"+1 812 985 3899",
    "sg:postcode":"47712",
    "sg:province":"IN",
    "sg:tags":[
        "excavating",
        "contractor"
    ],
    "wof:name":"Weber Excavating Inc",
    "wof:placetype":"venue"
},
  "geometry": {"coordinates":[-87.704319,37.956393],"type":"Point"}
}