{
  "type": "Feature",
  "properties": {
    "iso:country":"US",
    "sg:address":"4233 Lafayette Rd",
    "sg:city":"Indianapolis",
    "sg:classifiers":[
        {
            "category":"Shopping",
            "subcategory":"Musical Instruments",
            "type":"Retail Goods"
        }
    ],
    "sg:phone":"+1 317 291 3608",
    "sg:postcode":"46254",
    "sg:province":"IN",
    "sg:website":"www.indyproaudio.com",
    "wof:name":"Indy Pro Audio Music Store",
    "wof:placetype":"venue"
},
  "geometry": {"coordinates":[-86.244379,39.833618],"type":"Point"}
}