{
  "type": "Feature",
  "properties": {
    "addr:full":"618 Front St Hebron IN 46341",
    "addr:housenumber":"618",
    "addr:postcode":"46341",
    "addr:street":"Front St",
    "iso:country":"US",
    "sg:address":"618 Front St",
    "sg:city":"Hebron",
    "sg:classifiers":[
        {
            "category":"Retail",
            "subcategory":"Repair Shop",
            "type":"Services"
        }
    ],
    "sg:phone":"+1 219 996 4743",
    "sg:postcode":"46341",
    "sg:province":"IN",
    "sg:tags":[
        "water",
        "equipment",
        "softening"
    ],
    "wof:name":"Osby Water Conditioning",
    "wof:placetype":"venue"
},
  "geometry": {"coordinates":[-87.200526,41.327839],"type":"Point"}
}