{
  "type": "Feature",
  "properties": {
    "addr:full":"10746 E Co Rd 125 S Seymour IN 47274",
    "addr:housenumber":"10746;125",
    "addr:postcode":"47274",
    "addr:street":"E Co Rd;S Seymour",
    "iso:country":"US",
    "sg:address":"10746 E Co Rd 125 S",
    "sg:city":"Seymour",
    "sg:classifiers":[
        {
            "category":"Wholesale",
            "subcategory":"Scrap",
            "type":"Manufacturing & Wholesale Goods"
        }
    ],
    "sg:phone":"+1 812 523 8107",
    "sg:postcode":"47274",
    "sg:province":"IN",
    "sg:tags":[
        "recycling",
        "center"
    ],
    "wof:name":"Helt Enterprises-Recycling",
    "wof:placetype":"venue"
},
  "geometry": {"coordinates":[-85.837181,38.863212],"type":"Point"}
}