{
  "type": "Feature",
  "properties": {
    "iso:country":"US",
    "sg:address":"29 S Sycamore St",
    "sg:city":"Campbellsburg",
    "sg:classifiers":[
        {
            "category":"Restaurant",
            "type":"Food & Drink"
        }
    ],
    "sg:phone":"+1 812 755 5400",
    "sg:postcode":"47108",
    "sg:province":"IN",
    "wof:name":"T J's Country Cafe",
    "wof:placetype":"venue"
},
  "geometry": {"coordinates":[-86.26128199999999,38.651074],"type":"Point"}
}