{
  "type": "Feature",
  "properties": {
    "iso:country":"US",
    "sg:address":"6034 W 800 S",
    "sg:city":"Pendleton",
    "sg:classifiers":[
        {
            "category":"Building & Trades",
            "subcategory":"Construction",
            "type":"Services"
        }
    ],
    "sg:phone":"+1 765 778 7183",
    "sg:postcode":"46064",
    "sg:province":"IN",
    "sg:tags":[
        "house"
    ],
    "wof:name":"Benbow Construction",
    "wof:placetype":"venue"
},
  "geometry": {"coordinates":[-85.787475,39.987595],"type":"Point"}
}