{
  "type": "Feature",
  "properties": {
    "iso:country":"US",
    "sg:address":"177 Blackthorn Dr",
    "sg:city":"Valparaiso",
    "sg:classifiers":[
        {
            "category":"Building & Trades",
            "subcategory":"Construction",
            "type":"Services"
        }
    ],
    "sg:phone":"+1 219 405 7569",
    "sg:postcode":"46383",
    "sg:province":"IN",
    "sg:tags":[
        "residential",
        "contractor"
    ],
    "wof:name":"Brian C Schuck",
    "wof:placetype":"venue"
},
  "geometry": {"coordinates":[-87.030831,41.401031],"type":"Point"}
}