{
  "type": "Feature",
  "properties": {
    "iso:country":"US",
    "sg:address":"5015 W State Rd 46",
    "sg:city":"Bloomington",
    "sg:classifiers":[
        {
            "category":"Recreation",
            "type":"Entertainment"
        }
    ],
    "sg:phone":"+1 812 876 0141",
    "sg:postcode":"47404",
    "sg:province":"IN",
    "sg:tags":[
        "martial",
        "arts",
        "instruction"
    ],
    "wof:name":"Gentry Martial Arts",
    "wof:placetype":"venue"
},
  "geometry": {"coordinates":[-86.605249,39.220878],"type":"Point"}
}