{
  "type": "Feature",
  "properties": {
    "iso:country":"US",
    "sg:address":"3201 Portage Blvd",
    "sg:city":"Fort Wayne",
    "sg:classifiers":[
        {
            "category":"Arena",
            "subcategory":"Sports Club",
            "type":"Entertainment"
        }
    ],
    "sg:phone":"+1 260 432 7447",
    "sg:postcode":"46802",
    "sg:province":"IN",
    "sg:tags":[
        "soccer"
    ],
    "wof:name":"Inner City Soccer",
    "wof:placetype":"venue"
},
  "geometry": {"coordinates":[-85.18086099999999,41.071244],"type":"Point"}
}