{
  "type": "Feature",
  "properties": {
    "iso:country":"US",
    "sg:address":"6421 E 82nd St",
    "sg:city":"Fishers",
    "sg:classifiers":[
        {
            "category":"Restaurant",
            "type":"Food & Drink"
        }
    ],
    "sg:phone":"+1 317 842 4912",
    "sg:postcode":"46038",
    "sg:province":"IN",
    "wof:name":"Arby's Roast Beef Drive-In",
    "wof:placetype":"venue"
},
  "geometry": {"coordinates":[-86.01619700000001,39.9604],"type":"Point"}
}