{
  "type": "Feature",
  "properties": {
    "iso:country":"US",
    "sg:address":"905 W Western Ave",
    "sg:city":"South Bend",
    "sg:classifiers":[
        {
            "category":"Building & Trades",
            "subcategory":"Construction",
            "type":"Services"
        }
    ],
    "sg:phone":"+1 574 288 2801",
    "sg:postcode":"46601",
    "sg:province":"IN",
    "sg:tags":[
        "contractor"
    ],
    "wof:name":"High Tech Construction Co",
    "wof:placetype":"venue"
},
  "geometry": {"coordinates":[-86.263676,41.672216],"type":"Point"}
}