{
  "type": "Feature",
  "properties": {
    "iso:country":"US",
    "sg:address":"6325 Queen Rd",
    "sg:city":"Plymouth",
    "sg:classifiers":[
        {
            "category":"Wholesale",
            "subcategory":"Construction Materials",
            "type":"Manufacturing & Wholesale Goods"
        },
        {
            "category":"Building & Trades",
            "subcategory":"Construction",
            "type":"Services"
        }
    ],
    "sg:phone":"+1 574 936 9755",
    "sg:postcode":"46563",
    "sg:province":"IN",
    "sg:tags":[
        "fence",
        "contractor"
    ],
    "wof:name":"Mark Don Fence Contractor",
    "wof:placetype":"venue"
},
  "geometry": {"coordinates":[-86.377094,41.385743],"type":"Point"}
}