{
  "type": "Feature",
  "properties": {
    "iso:country":"US",
    "sg:address":"3020 Hillegas Rd",
    "sg:city":"Fort Wayne",
    "sg:classifiers":[
        {
            "category":"Government",
            "subcategory":"Office",
            "type":"Public Place"
        }
    ],
    "sg:phone":"+1 260 422 7387",
    "sg:postcode":"46808",
    "sg:province":"IN",
    "sg:tags":[
        "village"
    ],
    "wof:name":"Fort Wayne Animal Adoption",
    "wof:placetype":"venue"
},
  "geometry": {"coordinates":[-85.192021,41.098189],"type":"Point"}
}