{
  "type": "Feature",
  "properties": {
    "iso:country":"US",
    "sg:address":"203 S Holiday Dr",
    "sg:city":"South Bend",
    "sg:classifiers":[
        {
            "category":"Professional",
            "subcategory":"Lawyer & Legal Services",
            "type":"Services"
        }
    ],
    "sg:phone":"+1 574 288 2080",
    "sg:postcode":"46615",
    "sg:province":"IN",
    "sg:tags":[
        "attorney"
    ],
    "wof:name":"Raymond H Berndt",
    "wof:placetype":"venue"
},
  "geometry": {"coordinates":[-86.211696,41.674349],"type":"Point"}
}