{
  "type": "Feature",
  "properties": {
    "iso:country":"US",
    "sg:address":"918 S Poplar St",
    "sg:city":"Dugger",
    "sg:classifiers":[
        {
            "category":"Personal",
            "subcategory":"Beauty Salon",
            "type":"Services"
        }
    ],
    "sg:phone":"+1 812 648 3054",
    "sg:postcode":"47848",
    "sg:province":"IN",
    "wof:name":"Scissors",
    "wof:placetype":"venue"
},
  "geometry": {"coordinates":[-87.261337,39.069169],"type":"Point"}
}