{
  "type": "Feature",
  "properties": {
    "iso:country":"US",
    "sg:address":"1921 Patterson St",
    "sg:city":"Decatur",
    "sg:classifiers":[
        {
            "category":"Manufacturing",
            "subcategory":"Tools & Machinery",
            "type":"Manufacturing & Wholesale Goods"
        }
    ],
    "sg:phone":"+1 260 728 9272",
    "sg:postcode":"46733",
    "sg:province":"IN",
    "sg:tags":[
        "equipment",
        "wire",
        "drawing"
    ],
    "wof:name":"Decatur Wire Die Svc Inc",
    "wof:placetype":"venue"
},
  "geometry": {"coordinates":[-84.938667,40.824773],"type":"Point"}
}