{
  "type": "Feature",
  "properties": {
    "addr:full":"5601 Davis Rd Mt Vernon IN 47620",
    "addr:housenumber":"5601",
    "addr:postcode":"47620",
    "addr:street":"Davis Rd",
    "iso:country":"US",
    "sg:address":"5601 Davis Rd",
    "sg:city":"Mt Vernon",
    "sg:classifiers":[
        {
            "category":"Building & Trades",
            "subcategory":"Construction",
            "type":"Services"
        }
    ],
    "sg:phone":"+1 812 985 9330",
    "sg:postcode":"47620",
    "sg:province":"IN",
    "sg:tags":[
        "roofing",
        "contractor"
    ],
    "wof:name":"J & L Roofing Inc",
    "wof:placetype":"venue"
},
  "geometry": {"coordinates":[-87.773582,37.954805],"type":"Point"}
}