{
  "type": "Feature",
  "properties": {
    "addr:full":"3040 State Rd 9 Howe IN 46746",
    "addr:housenumber":"3040;9",
    "addr:postcode":"46746",
    "addr:street":"State Rd",
    "iso:country":"US",
    "sg:address":"3040 State Rd 9",
    "sg:city":"Howe",
    "sg:classifiers":[
        {
            "category":"Retail",
            "subcategory":"Auto Repair",
            "type":"Services"
        }
    ],
    "sg:phone":"+1 260 463 3163",
    "sg:postcode":"46746",
    "sg:province":"IN",
    "sg:tags":[
        "repairing",
        "automobile"
    ],
    "wof:name":"Owen Enterprise",
    "wof:placetype":"venue"
},
  "geometry": {"coordinates":[-85.425651,41.685253],"type":"Point"}
}