{
  "type": "Feature",
  "properties": {
    "iso:country":"US",
    "sg:address":"2444 Lafayette Rd",
    "sg:city":"Indianapolis",
    "sg:classifiers":[
        {
            "category":"Personal",
            "subcategory":"Barber",
            "type":"Services"
        }
    ],
    "sg:phone":"+1 317 687 8566",
    "sg:postcode":"46222",
    "sg:province":"IN",
    "wof:name":"Roberts Barber Style Shop",
    "wof:placetype":"venue"
},
  "geometry": {"coordinates":[-86.214069,39.803027],"type":"Point"}
}