{
  "type": "Feature",
  "properties": {
    "iso:country":"US",
    "sg:address":"675 S Ford Rd",
    "sg:city":"Zionsville",
    "sg:classifiers":[
        {
            "category":"Health Services",
            "subcategory":"Nursing And Care Facility",
            "type":"Services"
        }
    ],
    "sg:phone":"+1 317 873 5205",
    "sg:postcode":"46077",
    "sg:province":"IN",
    "sg:tags":[
        "home",
        "retirement",
        "community"
    ],
    "sg:website":"www.americansrcommunities.com",
    "wof:name":"Zionsville Meadows",
    "wof:placetype":"venue"
},
  "geometry": {"coordinates":[-86.278745,39.948487],"type":"Point"}
}