{
  "type": "Feature",
  "properties": {
    "iso:country":"US",
    "sg:address":"4199 Gateway Blvd Ste 2300",
    "sg:city":"Newburgh",
    "sg:classifiers":[
        {
            "category":"Health Services",
            "subcategory":"Hospital",
            "type":"Services"
        }
    ],
    "sg:phone":"+1 812 450 2121",
    "sg:postcode":"47630",
    "sg:province":"IN",
    "wof:name":"The Women's Hospital & Health Pavilion",
    "wof:placetype":"venue"
},
  "geometry": {"coordinates":[-87.44609800000001,37.9753],"type":"Point"}
}