{
  "type": "Feature",
  "properties": {
    "iso:country":"US",
    "sg:address":"2450 E Business 30",
    "sg:city":"Columbia City",
    "sg:classifiers":[
        {
            "category":"Building & Trades",
            "subcategory":"Landscaping Services",
            "type":"Services"
        }
    ],
    "sg:phone":"+1 260 244 3399",
    "sg:postcode":"46725",
    "sg:province":"IN",
    "sg:tags":[
        "landscape",
        "contractor"
    ],
    "wof:name":"Daniel Landscape Design",
    "wof:placetype":"venue"
},
  "geometry": {"coordinates":[-85.439454,41.139984],"type":"Point"}
}