{
  "type": "Feature",
  "properties": {
    "iso:country":"US",
    "sg:address":"1414 E 10th St",
    "sg:city":"Jeffersonville",
    "sg:classifiers":[
        {
            "category":"Home & Garden",
            "subcategory":"Carpets & Floor Coverings",
            "type":"Retail Goods"
        }
    ],
    "sg:phone":"+1 812 282 1414",
    "sg:postcode":"47130",
    "sg:province":"IN",
    "sg:tags":[
        "dealer",
        "rug"
    ],
    "wof:name":"Bradley's Carpet Outlets",
    "wof:placetype":"venue"
},
  "geometry": {"coordinates":[-85.72796,38.290081],"type":"Point"}
}