{
  "type": "Feature",
  "properties": {
    "iso:country":"US",
    "sg:address":"666 River Ave",
    "sg:city":"Indianapolis",
    "sg:classifiers":[
        {
            "category":"Retail",
            "subcategory":"Repair Shop",
            "type":"Services"
        },
        {
            "category":"Manufacturing",
            "subcategory":"Tools & Machinery",
            "type":"Manufacturing & Wholesale Goods"
        }
    ],
    "sg:phone":"+1 317 631 6385",
    "sg:postcode":"46221",
    "sg:province":"IN",
    "sg:tags":[
        "engine",
        "automotive",
        "testing",
        "comb",
        "equipment"
    ],
    "wof:name":"Graves Electronics Service",
    "wof:placetype":"venue"
},
  "geometry": {"coordinates":[-86.17927,39.754906],"type":"Point"}
}