{
  "type": "Feature",
  "properties": {
    "iso:country":"US",
    "sg:address":"52 Public Sq",
    "sg:city":"Salem",
    "sg:classifiers":[
        {
            "category":"Shopping",
            "type":"Retail Goods"
        }
    ],
    "sg:phone":"+1 812 883 0301",
    "sg:postcode":"47167",
    "sg:province":"IN",
    "sg:tags":[
        "telephone",
        "cellular"
    ],
    "wof:name":"Wireless Connection",
    "wof:placetype":"venue"
},
  "geometry": {"coordinates":[-86.101353,38.605394],"type":"Point"}
}