{
  "type": "Feature",
  "properties": {
    "addr:full":"4600 Drummond P.O. Box 432 East Chicago IN 46795",
    "addr:housenumber":"4600;p.o. box 432",
    "addr:postcode":"46795",
    "addr:street":"Drummond",
    "iso:country":"US",
    "sg:address":"4600 Drummond P.O. Box 432",
    "sg:city":"East Chicago",
    "sg:classifiers":[
        {
            "category":"Personal",
            "type":"Services"
        }
    ],
    "sg:phone":"+1 219 313 6070",
    "sg:postcode":"46795",
    "sg:province":"IN",
    "sg:tags":[
        "towing"
    ],
    "wof:name":"Road Rescue Towing",
    "wof:placetype":"venue"
},
  "geometry": {"coordinates":[-87.455716,41.629967],"type":"Point"}
}