{
  "type": "Feature",
  "properties": {
    "iso:country":"US",
    "sg:address":"2302 Meridian St",
    "sg:city":"Anderson",
    "sg:classifiers":[
        {
            "category":"Professional",
            "subcategory":"Accounting & Tax Preparation",
            "type":"Services"
        }
    ],
    "sg:phone":"+1 765 642 1661",
    "sg:postcode":"46016",
    "sg:province":"IN",
    "sg:tags":[
        "accountant"
    ],
    "wof:name":"Couch & Co",
    "wof:placetype":"venue"
},
  "geometry": {"coordinates":[-85.679069,40.092552],"type":"Point"}
}