{
  "type": "Feature",
  "properties": {
    "addr:full":"3900 E Market St Logansport IN 46947",
    "addr:housenumber":"3900",
    "addr:postcode":"46947",
    "addr:street":"E Market St",
    "iso:country":"US",
    "sg:address":"3900 E Market St",
    "sg:city":"Logansport",
    "sg:classifiers":[
        {
            "category":"Shopping",
            "subcategory":"Department Store",
            "type":"Retail Goods"
        }
    ],
    "sg:phone":"+1 574 753 8884",
    "sg:postcode":"46947",
    "sg:province":"IN",
    "wof:name":"Sears Roebuck & Co",
    "wof:placetype":"venue"
},
  "geometry": {"coordinates":[-86.32886000000001,40.758604],"type":"Point"}
}