{
  "type": "Feature",
  "properties": {
    "iso:country":"US",
    "sg:address":"2232 Wabash Ave",
    "sg:city":"Terre Haute",
    "sg:classifiers":[
        {
            "category":"Personal",
            "subcategory":"Beauty Salon",
            "type":"Services"
        }
    ],
    "sg:phone":"+1 812 232 8334",
    "sg:postcode":"47807",
    "sg:province":"IN",
    "sg:tags":[
        "school"
    ],
    "wof:name":"Harrold Beauty Academy Inc",
    "wof:placetype":"venue"
},
  "geometry": {"coordinates":[-87.38403,39.470086],"type":"Point"}
}