{
  "type": "Feature",
  "properties": {
    "iso:country":"US",
    "sg:address":"8777 W Old Fort Rd",
    "sg:city":"Fortville",
    "sg:classifiers":[
        {
            "category":"Home & Garden",
            "subcategory":"Building Materials",
            "type":"Retail Goods"
        }
    ],
    "sg:phone":"+1 317 485 6878",
    "sg:postcode":"46040",
    "sg:province":"IN",
    "sg:tags":[
        "type",
        "door"
    ],
    "wof:name":"Doormasters",
    "wof:placetype":"venue"
},
  "geometry": {"coordinates":[-85.839245,39.945667],"type":"Point"}
}