{
  "type": "Feature",
  "properties": {
    "iso:country":"US",
    "sg:address":"118 W Columbia St",
    "sg:city":"Fort Wayne",
    "sg:classifiers":[
        {
            "category":"Bars & Pubs",
            "type":"Food & Drink"
        }
    ],
    "sg:phone":"+1 260 422 5292",
    "sg:postcode":"46802",
    "sg:province":"IN",
    "sg:tags":[
        "club",
        "night"
    ],
    "wof:name":"Flashback On The Landing",
    "wof:placetype":"venue"
},
  "geometry": {"coordinates":[-85.140551,41.081332],"type":"Point"}
}