{
  "type": "Feature",
  "properties": {
    "addr:full":"1706 E Wheeler St Kokomo IN 46902",
    "addr:housenumber":"1706",
    "addr:postcode":"46902",
    "addr:street":"E Wheeler St",
    "iso:country":"US",
    "sg:address":"1706 E Wheeler St",
    "sg:city":"Kokomo",
    "sg:classifiers":[
        {
            "category":"Retail",
            "subcategory":"Auto Repair",
            "type":"Services"
        }
    ],
    "sg:phone":"+1 765 868 9148",
    "sg:postcode":"46902",
    "sg:province":"IN",
    "sg:tags":[
        "repairing",
        "automobile"
    ],
    "wof:name":"Stoney's Auto Repair",
    "wof:placetype":"venue"
},
  "geometry": {"coordinates":[-86.10813,40.467183],"type":"Point"}
}