{
  "type": "Feature",
  "properties": {
    "iso:country":"US",
    "sg:address":"5639 W Co Rd 450 S",
    "sg:city":"Greensburg",
    "sg:classifiers":[
        {
            "category":"Retail",
            "subcategory":"Portrait Studio",
            "type":"Services"
        }
    ],
    "sg:phone":"+1 812 663 2118",
    "sg:postcode":"47240",
    "sg:province":"IN",
    "sg:tags":[
        "photo"
    ],
    "wof:name":"Photography By Ann",
    "wof:placetype":"venue"
},
  "geometry": {"coordinates":[-85.58642,39.269513],"type":"Point"}
}