{
  "type": "Feature",
  "properties": {
    "iso:country":"US",
    "sg:address":"1130 N Baldwin Ave",
    "sg:city":"Marion",
    "sg:classifiers":[
        {
            "category":"Personal",
            "subcategory":"Tanning Parlor",
            "type":"Services"
        },
        {
            "category":"Personal",
            "type":"Services"
        }
    ],
    "sg:phone":"+1 765 662 8287",
    "sg:postcode":"46952",
    "sg:province":"IN",
    "sg:tags":[
        "salon"
    ],
    "wof:name":"Malibu Tanning",
    "wof:placetype":"venue"
},
  "geometry": {"coordinates":[-85.675898,40.572025],"type":"Point"}
}