{
  "type": "Feature",
  "properties": {
    "iso:country":"US",
    "sg:address":"6200 Maxwell Ave",
    "sg:city":"Evansville",
    "sg:classifiers":[
        {
            "category":"Building & Trades",
            "subcategory":"Electrical",
            "type":"Services"
        }
    ],
    "sg:phone":"+1 812 425 1128",
    "sg:postcode":"47715",
    "sg:province":"IN",
    "sg:tags":[
        "electric",
        "contractor"
    ],
    "wof:name":"Newman Electric",
    "wof:placetype":"venue"
},
  "geometry": {"coordinates":[-87.476158,37.99305],"type":"Point"}
}