{
  "type": "Feature",
  "properties": {
    "iso:country":"US",
    "sg:address":"125 E Lincoln Ave",
    "sg:city":"Goshen",
    "sg:classifiers":[
        {
            "category":"Professional",
            "subcategory":"Business Services",
            "type":"Services"
        }
    ],
    "sg:phone":"+1 574 533 2720",
    "sg:postcode":"46528",
    "sg:province":"IN",
    "sg:tags":[
        "translator",
        "interpreter"
    ],
    "wof:name":"Ludy Diaz",
    "wof:placetype":"venue"
},
  "geometry": {"coordinates":[-85.833957,41.586519],"type":"Point"}
}