{
  "type": "Feature",
  "properties": {
    "iso:country":"US",
    "sg:address":"498 S Section St",
    "sg:city":"Sullivan",
    "sg:classifiers":[
        {
            "category":"Retail",
            "subcategory":"Repair Shop",
            "type":"Services"
        }
    ],
    "sg:phone":"+1 812 268 5758",
    "sg:postcode":"47882",
    "sg:province":"IN",
    "sg:tags":[
        "electrical"
    ],
    "wof:name":"Bells Appliance Parts & Repr",
    "wof:placetype":"venue"
},
  "geometry": {"coordinates":[-87.409887,39.088169],"type":"Point"}
}