{
  "type": "Feature",
  "properties": {
    "iso:country":"US",
    "sg:address":"3700 E Lilac Ln",
    "sg:city":"Muncie",
    "sg:classifiers":[
        {
            "category":"Freight",
            "type":"Transportation"
        }
    ],
    "sg:phone":"+1 765 644 7615",
    "sg:postcode":"47302",
    "sg:province":"IN",
    "sg:tags":[
        "commercial",
        "storage",
        "general"
    ],
    "wof:name":"H E R Enterprises",
    "wof:placetype":"venue"
},
  "geometry": {"coordinates":[-85.378165,40.158899],"type":"Point"}
}