{
  "type": "Feature",
  "properties": {
    "addr:full":"6082 Lute Rd Portage IN 46368",
    "addr:postcode":"6082;46368",
    "addr:street":"Lute Rd",
    "iso:country":"US",
    "sg:address":"6082 Lute Rd",
    "sg:city":"Portage",
    "sg:classifiers":[
        {
            "category":"Professional",
            "subcategory":"Lawyer & Legal Services",
            "type":"Services"
        }
    ],
    "sg:phone":"+1 219 762 9129",
    "sg:postcode":"46368",
    "sg:province":"IN",
    "sg:tags":[
        "attorney"
    ],
    "wof:name":"Hodges & Davis",
    "wof:placetype":"venue"
},
  "geometry": {"coordinates":[-87.180044,41.557867],"type":"Point"}
}