{
  "type": "Feature",
  "properties": {
    "iso:country":"US",
    "sg:address":"4951 W 96th St",
    "sg:city":"Indianapolis",
    "sg:classifiers":[
        {
            "category":"Manufacturing",
            "subcategory":"Tools & Machinery",
            "type":"Manufacturing & Wholesale Goods"
        }
    ],
    "sg:phone":"+1 317 872 4877",
    "sg:postcode":"46268",
    "sg:province":"IN",
    "sg:website":"www.southeasternequip.com",
    "wof:name":"Southeastern Equipment Co",
    "wof:placetype":"venue"
},
  "geometry": {"coordinates":[-86.236744,39.926018],"type":"Point"}
}