{
  "type": "Feature",
  "properties": {
    "iso:country":"US",
    "sg:address":"12409 Old Meridian St",
    "sg:city":"Carmel",
    "sg:classifiers":[
        {
            "category":"Real Estate",
            "subcategory":"Real Estate Services",
            "type":"Services"
        }
    ],
    "sg:phone":"+1 317 815 2121",
    "sg:postcode":"46032",
    "sg:province":"IN",
    "sg:tags":[
        "company",
        "title"
    ],
    "wof:name":"Brown & Assoc",
    "wof:placetype":"venue"
},
  "geometry": {"coordinates":[-86.152565,39.970725],"type":"Point"}
}