{
  "type": "Feature",
  "properties": {
    "iso:country":"US",
    "sg:address":"6350 E 25 N",
    "sg:city":"Knox",
    "sg:classifiers":[
        {
            "category":"Organizations",
            "subcategory":"Religious Organization",
            "type":"Services"
        }
    ],
    "sg:phone":"+1 574 772 3972",
    "sg:postcode":"46534",
    "sg:province":"IN",
    "sg:tags":[
        "clergy"
    ],
    "wof:name":"Edward L Hasnerl",
    "wof:placetype":"venue"
},
  "geometry": {"coordinates":[-86.57555,41.307304],"type":"Point"}
}