{
  "type": "Feature",
  "properties": {
    "addr:full":"1831 Greentree Ct Fort Wayne IN 46803",
    "addr:housenumber":"1831",
    "addr:postcode":"46803",
    "addr:street":"Greentree Ct",
    "iso:country":"US",
    "sg:address":"1831 Greentree Ct",
    "sg:city":"Fort Wayne",
    "sg:classifiers":[
        {
            "category":"Social Services",
            "subcategory":"Child Care",
            "type":"Services"
        }
    ],
    "sg:phone":"+1 260 744 9071",
    "sg:postcode":"46803",
    "sg:province":"IN",
    "wof:name":"Little Kiddie Care",
    "wof:placetype":"venue"
},
  "geometry": {"coordinates":[-85.127163,41.06693],"type":"Point"}
}