{
  "type": "Feature",
  "properties": {
    "iso:country":"US",
    "sg:address":"12207 Burr St",
    "sg:city":"Crown Point",
    "sg:classifiers":[
        {
            "category":"Retail",
            "subcategory":"Repair Shop",
            "type":"Services"
        }
    ],
    "sg:phone":"+1 219 663 2668",
    "sg:postcode":"46307",
    "sg:province":"IN",
    "sg:tags":[
        "welding"
    ],
    "wof:name":"Glen's Mobile Welding",
    "wof:placetype":"venue"
},
  "geometry": {"coordinates":[-87.402223,41.396827],"type":"Point"}
}