{
  "type": "Feature",
  "properties": {
    "iso:country":"US",
    "sg:address":"614 E Vaile Ave",
    "sg:city":"Kokomo",
    "sg:classifiers":[
        {
            "category":"Shopping",
            "subcategory":"Clothing, Apparel, & Fashions",
            "type":"Retail Goods"
        }
    ],
    "sg:phone":"+1 765 452 6850",
    "sg:postcode":"46901",
    "sg:province":"IN",
    "sg:tags":[
        "tailor"
    ],
    "wof:name":"Luigi Bilella Tailor Shop",
    "wof:placetype":"venue"
},
  "geometry": {"coordinates":[-86.125429,40.481568],"type":"Point"}
}