{
  "type": "Feature",
  "properties": {
    "iso:country":"US",
    "sg:address":"5319 S Emerson Ave",
    "sg:city":"Indianapolis",
    "sg:classifiers":[
        {
            "category":"Insurance",
            "subcategory":"Insurance Agent",
            "type":"Services"
        }
    ],
    "sg:phone":"+1 317 786 1800",
    "sg:postcode":"46237",
    "sg:province":"IN",
    "wof:name":"Gary Schonfeld Agency Inc",
    "wof:placetype":"venue"
},
  "geometry": {"coordinates":[-86.082465,39.689231],"type":"Point"}
}