{
  "type": "Feature",
  "properties": {
    "addr:full":"1006 Frederick Dr S Indianapolis IN 46260",
    "addr:housenumber":"1006",
    "addr:postcode":"46260",
    "addr:street":"Frederick Dr S",
    "iso:country":"US",
    "sg:address":"1006 Frederick Dr S",
    "sg:city":"Indianapolis",
    "sg:classifiers":[
        {
            "category":"Professional",
            "subcategory":"Engineering",
            "type":"Services"
        }
    ],
    "sg:phone":"+1 317 259 1116",
    "sg:postcode":"46260",
    "sg:province":"IN",
    "sg:tags":[
        "statistical",
        "witness"
    ],
    "wof:name":"Benzion Boukai PHD",
    "wof:placetype":"venue"
},
  "geometry": {"coordinates":[-86.17744999999999,39.887592],"type":"Point"}
}