{
  "type": "Feature",
  "properties": {
    "iso:country":"US",
    "sg:address":"1772 US Hwy 421",
    "sg:city":"Delphi",
    "sg:classifiers":[
        {
            "category":"Bars & Pubs",
            "type":"Food & Drink"
        }
    ],
    "sg:phone":"+1 765 564 4985",
    "sg:postcode":"46923",
    "sg:province":"IN",
    "wof:name":"Keysters Bar",
    "wof:placetype":"venue"
},
  "geometry": {"coordinates":[-86.662414,40.573198],"type":"Point"}
}