{
  "type": "Feature",
  "properties": {
    "addr:full":"701 Collins Rd Elkhart IN 46516",
    "addr:housenumber":"701",
    "addr:postcode":"46516",
    "addr:street":"Collins Rd",
    "iso:country":"US",
    "sg:address":"701 Collins Rd",
    "sg:city":"Elkhart",
    "sg:classifiers":[
        {
            "category":"Professional",
            "subcategory":"Engineering",
            "type":"Services"
        }
    ],
    "sg:phone":"+1 574 293 1352",
    "sg:postcode":"46516",
    "sg:province":"IN",
    "sg:tags":[
        "engineer"
    ],
    "wof:name":"Banks Engineering",
    "wof:placetype":"venue"
},
  "geometry": {"coordinates":[-85.92215,41.685771],"type":"Point"}
}