{
  "type": "Feature",
  "properties": {
    "iso:country":"US",
    "sg:address":"1382 Autumn Dr",
    "sg:city":"Mooresville",
    "sg:classifiers":[
        {
            "category":"Personal",
            "subcategory":"Beauty Salon",
            "type":"Services"
        }
    ],
    "sg:phone":"+1 317 831 2997",
    "sg:postcode":"46158",
    "sg:province":"IN",
    "sg:tags":[
        "shop"
    ],
    "wof:name":"Hair Care By Carol",
    "wof:placetype":"venue"
},
  "geometry": {"coordinates":[-86.343869,39.615874],"type":"Point"}
}