{
  "type": "Feature",
  "properties": {
    "iso:country":"US",
    "sg:address":"3130 N Carroll Rd",
    "sg:city":"Indianapolis",
    "sg:classifiers":[
        {
            "category":"Personal",
            "subcategory":"Beauty Salon",
            "type":"Services"
        }
    ],
    "sg:phone":"+1 317 894 0187",
    "sg:postcode":"46140",
    "sg:province":"IN",
    "sg:tags":[
        "shop"
    ],
    "wof:name":"Nu Look Hair Design",
    "wof:placetype":"venue"
},
  "geometry": {"coordinates":[-85.953141,39.83008],"type":"Point"}
}