{
  "type": "Feature",
  "properties": {
    "iso:country":"US",
    "sg:address":"460 E 450 S",
    "sg:city":"Warsaw",
    "sg:classifiers":[
        {
            "category":"Building & Trades",
            "subcategory":"Landscaping Services",
            "type":"Services"
        }
    ],
    "sg:phone":"+1 574 269 4558",
    "sg:postcode":"46580",
    "sg:province":"IN",
    "sg:tags":[
        "landscape",
        "contractor"
    ],
    "wof:name":"Schue's Landscaping Inc",
    "wof:placetype":"venue"
},
  "geometry": {"coordinates":[-85.82709800000001,41.166849],"type":"Point"}
}