{
  "type": "Feature",
  "properties": {
    "iso:country":"US",
    "sg:address":"1951 Washington Ave",
    "sg:city":"Evansville",
    "sg:classifiers":[
        {
            "category":"Food & Beverages",
            "subcategory":"Liquor & Beverages",
            "type":"Retail Goods"
        }
    ],
    "sg:phone":"+1 812 476 8141",
    "sg:postcode":"47714",
    "sg:province":"IN",
    "wof:name":"Winetree Liquors",
    "wof:placetype":"venue"
},
  "geometry": {"coordinates":[-87.530372,37.962635],"type":"Point"}
}