{
  "type": "Feature",
  "properties": {
    "iso:country":"US",
    "sg:address":"2515 Lincoln Dr",
    "sg:city":"Clarksville",
    "sg:classifiers":[
        {
            "category":"Professional",
            "subcategory":"Engineering",
            "type":"Services"
        }
    ],
    "sg:phone":"+1 812 941 5650",
    "sg:postcode":"47129",
    "sg:province":"IN",
    "sg:tags":[
        "engineer"
    ],
    "wof:name":"Indiana Controls Engineering",
    "wof:placetype":"venue"
},
  "geometry": {"coordinates":[-85.776472,38.301664],"type":"Point"}
}