{
  "type": "Feature",
  "properties": {
    "addr:full":"4128 S Clinton St Fort Wayne IN 46806",
    "addr:housenumber":"4128",
    "addr:postcode":"46806",
    "addr:street":"S Clinton St",
    "iso:country":"US",
    "sg:address":"4128 S Clinton St",
    "sg:city":"Fort Wayne",
    "sg:classifiers":[
        {
            "category":"Education",
            "subcategory":"School",
            "type":"Public Place"
        }
    ],
    "sg:phone":"+1 260 456 2992",
    "sg:postcode":"46806",
    "sg:province":"IN",
    "wof:name":"American Christian Training",
    "wof:placetype":"venue"
},
  "geometry": {"coordinates":[-85.13339499999999,41.047357],"type":"Point"}
}