{
  "type": "Feature",
  "properties": {
    "iso:country":"US",
    "sg:address":"1014 W Pike St",
    "sg:city":"Goshen",
    "sg:classifiers":[
        {
            "category":"Autos & Motor Vehicles",
            "subcategory":"Automobile Sales",
            "type":"Retail Goods"
        }
    ],
    "sg:phone":"+1 574 533 7774",
    "sg:postcode":"46526",
    "sg:province":"IN",
    "sg:tags":[
        "car",
        "dealer"
    ],
    "wof:name":"Pep Auto Sales",
    "wof:placetype":"venue"
},
  "geometry": {"coordinates":[-85.849378,41.588896],"type":"Point"}
}