{
  "type": "Feature",
  "properties": {
    "addr:full":"116 G St Laporte IN 46350",
    "addr:housenumber":"116",
    "addr:postcode":"46350",
    "addr:street":"G St Laporte",
    "iso:country":"US",
    "sg:address":"116 G St",
    "sg:city":"Laporte",
    "sg:classifiers":[
        {
            "category":"Farming",
            "subcategory":"Livestock Farm",
            "type":"Manufacturing & Wholesale Goods"
        }
    ],
    "sg:phone":"+1 219 362 7997",
    "sg:postcode":"46350",
    "sg:province":"IN",
    "sg:tags":[
        "producer"
    ],
    "wof:name":"Airy Breeding Srv",
    "wof:placetype":"venue"
},
  "geometry": {"coordinates":[-86.726561,41.606158],"type":"Point"}
}