{
  "type": "Feature",
  "properties": {
    "iso:country":"US",
    "sg:address":"3516 E 75 S",
    "sg:city":"Albion",
    "sg:classifiers":[
        {
            "category":"Government",
            "subcategory":"Office",
            "type":"Public Place"
        }
    ],
    "sg:phone":"+1 260 636 3114",
    "sg:postcode":"46701",
    "sg:province":"IN",
    "wof:name":"Chain O'Lakes Crrctnl Facility",
    "wof:placetype":"venue"
},
  "geometry": {"coordinates":[-85.358575,41.342561],"type":"Point"}
}