{
  "type": "Feature",
  "properties": {
    "iso:country":"US",
    "sg:address":"1203 S Plate St",
    "sg:city":"Kokomo",
    "sg:classifiers":[
        {
            "category":"Retail",
            "subcategory":"Auto Repair",
            "type":"Services"
        }
    ],
    "sg:phone":"+1 765 459 5020",
    "sg:postcode":"46902",
    "sg:province":"IN",
    "sg:tags":[
        "body",
        "automobile",
        "painting"
    ],
    "wof:name":"Fred's Body Shop Inc",
    "wof:placetype":"venue"
},
  "geometry": {"coordinates":[-86.115822,40.471963],"type":"Point"}
}