{
  "type": "Feature",
  "properties": {
    "iso:country":"US",
    "sg:address":"2378 E Cottom Dr",
    "sg:city":"Pimento",
    "sg:classifiers":[
        {
            "category":"Government",
            "subcategory":"Post Office",
            "type":"Public Place"
        }
    ],
    "sg:phone":"+1 812 299 9297",
    "sg:postcode":"47866",
    "sg:province":"IN",
    "wof:name":"US Post Office",
    "wof:placetype":"venue"
},
  "geometry": {"coordinates":[-87.380996,39.310216],"type":"Point"}
}