{
  "type": "Feature",
  "properties": {
    "iso:country":"US",
    "sg:address":"9144 N Co Rd 200 E",
    "sg:city":"Batesville",
    "sg:classifiers":[
        {
            "category":"Professional",
            "type":"Services"
        }
    ],
    "sg:phone":"+1 812 934 2417",
    "sg:postcode":"47006",
    "sg:province":"IN",
    "wof:name":"David Ahrens",
    "wof:placetype":"venue"
},
  "geometry": {"coordinates":[-85.226398,39.209966],"type":"Point"}
}