{
  "type": "Feature",
  "properties": {
    "iso:country":"US",
    "sg:address":"1400 N Wayne St",
    "sg:city":"Angola",
    "sg:classifiers":[
        {
            "category":"Banks & Credit Unions",
            "subcategory":"Bank",
            "type":"Services"
        }
    ],
    "sg:phone":"+1 260 624 2773",
    "sg:postcode":"46703",
    "sg:province":"IN",
    "sg:tags":[
        "cashing",
        "check"
    ],
    "wof:name":"Check Into Cash",
    "wof:placetype":"venue"
},
  "geometry": {"coordinates":[-84.99943500000001,41.652303],"type":"Point"}
}