{
  "type": "Feature",
  "properties": {
    "addr:full":"505 W Pennsylvania St Shelbyville IN 46176",
    "addr:housenumber":"505",
    "addr:postcode":"46176",
    "addr:street":"W Pennsylvania St",
    "iso:country":"US",
    "sg:address":"505 W Pennsylvania St",
    "sg:city":"Shelbyville",
    "sg:classifiers":[
        {
            "category":"Organizations",
            "subcategory":"Religious Organization",
            "type":"Services"
        }
    ],
    "sg:phone":"+1 317 398 9280",
    "sg:postcode":"46176",
    "sg:province":"IN",
    "sg:tags":[
        "church"
    ],
    "wof:name":"Faith Trinity Pentecostal Chr",
    "wof:placetype":"venue"
},
  "geometry": {"coordinates":[-85.786187,39.526886],"type":"Point"}
}