{
  "type": "Feature",
  "properties": {
    "iso:country":"US",
    "sg:address":"671 Dowling St",
    "sg:city":"Kendallville",
    "sg:classifiers":[
        {
            "category":"Personal",
            "subcategory":"Beauty Salon",
            "type":"Services"
        }
    ],
    "sg:phone":"+1 260 347 4599",
    "sg:postcode":"46755",
    "sg:province":"IN",
    "wof:name":"First Impressions Salon",
    "wof:placetype":"venue"
},
  "geometry": {"coordinates":[-85.256204,41.446985],"type":"Point"}
}