{
  "type": "Feature",
  "properties": {
    "iso:country":"US",
    "sg:address":"900 Broadway",
    "sg:city":"Gary",
    "sg:classifiers":[
        {
            "category":"Restaurant",
            "type":"Food & Drink"
        }
    ],
    "sg:menulink":"http://www.allmenus.com/in/calumet/198837-kfc---kentucky-fried-chicken/menu/",
    "sg:phone":"+1 219 882 1164",
    "sg:postcode":"46402",
    "sg:province":"IN",
    "sg:tags":[
        "american",
        "chicken"
    ],
    "wof:name":"KFC - Kentucky Fried Chicken",
    "wof:placetype":"venue"
},
  "geometry": {"coordinates":[-87.337076,41.594907],"type":"Point"}
}