{
  "type": "Feature",
  "properties": {
    "addr:full":"746 Clifty Dr Madison IN 47250",
    "addr:housenumber":"746",
    "addr:postcode":"47250",
    "addr:street":"Clifty Dr",
    "iso:country":"US",
    "sg:address":"746 Clifty Dr",
    "sg:city":"Madison",
    "sg:classifiers":[
        {
            "category":"Utilities",
            "subcategory":"Mobile Phone",
            "type":"Services"
        }
    ],
    "sg:phone":"+1 812 273 6370",
    "sg:postcode":"47250",
    "sg:province":"IN",
    "sg:tags":[
        "telephone",
        "cellular"
    ],
    "wof:name":"Cingular Wireless",
    "wof:placetype":"venue"
},
  "geometry": {"coordinates":[-85.404214,38.77474],"type":"Point"}
}