{
  "type": "Feature",
  "properties": {
    "iso:country":"US",
    "sg:address":"8904 Otis Ave",
    "sg:city":"Indianapolis",
    "sg:classifiers":[
        {
            "category":"Government",
            "subcategory":"Office",
            "type":"Public Place"
        }
    ],
    "sg:phone":"+1 317 377 6146",
    "sg:postcode":"46216",
    "sg:province":"IN",
    "wof:name":"Us Govt Ditco",
    "wof:placetype":"venue"
},
  "geometry": {"coordinates":[-86.011155,39.856783],"type":"Point"}
}