{
  "type": "Feature",
  "properties": {
    "iso:country":"US",
    "sg:address":"1015 E Chicago Ave",
    "sg:city":"East Chicago",
    "sg:classifiers":[
        {
            "category":"Personal",
            "subcategory":"Beauty Salon",
            "type":"Services"
        }
    ],
    "sg:phone":"+1 219 398 9780",
    "sg:postcode":"46312",
    "sg:province":"IN",
    "wof:name":"Styles Hair Salon",
    "wof:placetype":"venue"
},
  "geometry": {"coordinates":[-87.458203,41.629114],"type":"Point"}
}