{
  "type": "Feature",
  "properties": {
    "iso:country":"US",
    "sg:address":"6436 W 800 S",
    "sg:city":"Pendleton",
    "sg:classifiers":[
        {
            "category":"Personal",
            "subcategory":"Beauty Salon",
            "type":"Services"
        }
    ],
    "sg:phone":"+1 765 778 4724",
    "sg:postcode":"46064",
    "sg:province":"IN",
    "sg:tags":[
        "hairdresser"
    ],
    "wof:name":"New Attitude Hair Salon",
    "wof:placetype":"venue"
},
  "geometry": {"coordinates":[-85.794928,39.987799],"type":"Point"}
}