{
  "type": "Feature",
  "properties": {
    "addr:full":"405 S 9th St Elwood IN 46036",
    "addr:housenumber":"405",
    "addr:postcode":"46036",
    "addr:street":"S 9Th St",
    "iso:country":"US",
    "sg:address":"405 S 9th St",
    "sg:city":"Elwood",
    "sg:classifiers":[
        {
            "category":"Personal",
            "subcategory":"Tanning Parlor",
            "type":"Services"
        },
        {
            "category":"Personal",
            "type":"Services"
        }
    ],
    "sg:phone":"+1 765 552 3391",
    "sg:postcode":"46036",
    "sg:province":"IN",
    "sg:tags":[
        "salon"
    ],
    "wof:name":"Key West Tanning Inc",
    "wof:placetype":"venue"
},
  "geometry": {"coordinates":[-85.850155,40.274165],"type":"Point"}
}