{
  "type": "Feature",
  "properties": {
    "iso:country":"US",
    "sg:address":"5343 W Minnesota St",
    "sg:city":"Indianapolis",
    "sg:classifiers":[
        {
            "category":"Shopping",
            "subcategory":"News",
            "type":"Retail Goods"
        },
        {
            "category":"Manufacturing",
            "subcategory":"Printing",
            "type":"Manufacturing & Wholesale Goods"
        }
    ],
    "sg:phone":"+1 317 240 8730",
    "sg:postcode":"46241",
    "sg:province":"IN",
    "sg:tags":[
        "magazine",
        "publishing"
    ],
    "sg:website":"www.forrent.com",
    "wof:name":"For Rent Magazines",
    "wof:placetype":"venue"
},
  "geometry": {"coordinates":[-86.251061,39.743088],"type":"Point"}
}