{
  "type": "Feature",
  "properties": {
    "iso:country":"US",
    "sg:address":"5323 E 11th Pl",
    "sg:city":"Gary",
    "sg:classifiers":[
        {
            "category":"Retail",
            "subcategory":"Repair Shop",
            "type":"Services"
        }
    ],
    "sg:phone":"+1 219 939 0689",
    "sg:postcode":"46403",
    "sg:province":"IN",
    "sg:tags":[
        "cleaning"
    ],
    "wof:name":"Georgia M Louellen",
    "wof:placetype":"venue"
},
  "geometry": {"coordinates":[-87.274084,41.592131],"type":"Point"}
}