{
  "type": "Feature",
  "properties": {
    "addr:full":"239 S Lindberg St Griffith IN 46319",
    "addr:housenumber":"239",
    "addr:postcode":"46319",
    "addr:street":"S Lindberg St",
    "iso:country":"US",
    "sg:address":"239 S Lindberg St",
    "sg:city":"Griffith",
    "sg:classifiers":[
        {
            "category":"Government",
            "subcategory":"City Hall",
            "type":"Public Place"
        },
        {
            "category":"Utilities",
            "subcategory":"Water",
            "type":"Services"
        },
        {
            "category":"Building & Trades",
            "subcategory":"Cleaning & Sanitation",
            "type":"Services"
        },
        {
            "category":"Retail",
            "subcategory":"Laundry & Dry Cleaning",
            "type":"Services"
        }
    ],
    "sg:phone":"+1 219 922 9300",
    "sg:postcode":"46319",
    "sg:province":"IN",
    "sg:tags":[
        "town",
        "cleaner",
        "planner",
        "emergency",
        "duct",
        "damage",
        "rug",
        "fire",
        "restoration",
        "remediation",
        "air",
        "mold",
        "carpet"
    ],
    "sg:website":"http://www.servproofwesternlakecounty.com",
    "wof:name":"Servpro Of Western Lake County",
    "wof:placetype":"venue"
},
  "geometry": {"coordinates":[-87.433943,41.521199],"type":"Point"}
}