{
  "type": "Feature",
  "properties": {
    "iso:country":"US",
    "sg:address":"2137 S 4th St",
    "sg:city":"Lafayette",
    "sg:classifiers":[
        {
            "category":"Bars & Pubs",
            "type":"Food & Drink"
        }
    ],
    "sg:phone":"+1 765 474 4745",
    "sg:postcode":"47905",
    "sg:province":"IN",
    "sg:tags":[
        "club",
        "night"
    ],
    "wof:name":"Mirage",
    "wof:placetype":"venue"
},
  "geometry": {"coordinates":[-86.895418,40.396209],"type":"Point"}
}