{
  "type": "Feature",
  "properties": {
    "iso:country":"US",
    "sg:address":"231 Waterfall Dr",
    "sg:city":"Elkhart",
    "sg:classifiers":[
        {
            "category":"Government",
            "subcategory":"Office",
            "type":"Public Place"
        }
    ],
    "sg:phone":"+1 574 294 5667",
    "sg:postcode":"46516",
    "sg:province":"IN",
    "sg:tags":[
        "federal",
        "human"
    ],
    "wof:name":"US Social Security Adm",
    "wof:placetype":"venue"
},
  "geometry": {"coordinates":[-85.96749199999999,41.684582],"type":"Point"}
}