{
  "type": "Feature",
  "properties": {
    "iso:country":"US",
    "sg:address":"36 E National Ave",
    "sg:city":"Brazil",
    "sg:classifiers":[
        {
            "category":"Professional",
            "subcategory":"Accounting & Tax Preparation",
            "type":"Services"
        }
    ],
    "sg:phone":"+1 812 442 1040",
    "sg:postcode":"47834",
    "sg:province":"IN",
    "sg:tags":[
        "return",
        "filing"
    ],
    "wof:name":"Premier Tax Svc",
    "wof:placetype":"venue"
},
  "geometry": {"coordinates":[-87.127413,39.523187],"type":"Point"}
}