{
  "type": "Feature",
  "properties": {
    "iso:country":"US",
    "sg:address":"11345 W 950 S",
    "sg:city":"Akron",
    "sg:classifiers":[
        {
            "category":"Real Estate",
            "subcategory":"Real Estate Operator",
            "type":"Services"
        }
    ],
    "sg:phone":"+1 574 893 4190",
    "sg:postcode":"46910",
    "sg:province":"IN",
    "sg:tags":[
        "property",
        "lessor"
    ],
    "wof:name":"Gene Black",
    "wof:placetype":"venue"
},
  "geometry": {"coordinates":[-86.042611,41.092721],"type":"Point"}
}