{
  "type": "Feature",
  "properties": {
    "iso:country":"US",
    "sg:address":"1627 Kossuth St",
    "sg:city":"Lafayette",
    "sg:classifiers":[
        {
            "category":"Insurance",
            "subcategory":"Insurance Agent",
            "type":"Services"
        }
    ],
    "sg:phone":"+1 765 742 1601",
    "sg:postcode":"47905",
    "sg:province":"IN",
    "wof:name":"State Farm Insurance",
    "wof:placetype":"venue"
},
  "geometry": {"coordinates":[-86.877191,40.409974],"type":"Point"}
}