{
  "type": "Feature",
  "properties": {
    "iso:country":"US",
    "sg:address":"2882 Grandma Barnes Rd",
    "sg:city":"Nashville",
    "sg:classifiers":[
        {
            "category":"Building & Trades",
            "subcategory":"Construction",
            "type":"Services"
        }
    ],
    "sg:phone":"+1 812 988 2060",
    "sg:postcode":"47448",
    "sg:province":"IN",
    "sg:tags":[
        "house"
    ],
    "wof:name":"David Gore Builder",
    "wof:placetype":"venue"
},
  "geometry": {"coordinates":[-86.265011,39.237726],"type":"Point"}
}