{
  "type": "Feature",
  "properties": {
    "iso:country":"US",
    "sg:address":"814 Broad Ripple Ave",
    "sg:city":"Indianapolis",
    "sg:classifiers":[
        {
            "category":"Bars & Pubs",
            "type":"Food & Drink"
        },
        {
            "category":"Restaurant",
            "type":"Food & Drink"
        },
        {
            "category":"Bars & Pubs",
            "subcategory":"Sports Bar",
            "type":"Food & Drink"
        }
    ],
    "sg:phone":"+1 317 253 5844",
    "sg:postcode":"46220",
    "sg:province":"IN",
    "sg:tags":[
        "brew"
    ],
    "wof:name":"Average Joe's Sports Pub",
    "wof:placetype":"venue"
},
  "geometry": {"coordinates":[-86.144514,39.869694],"type":"Point"}
}