{
  "type": "Feature",
  "properties": {
    "addr:full":"86 W Court St Franklin IN 46131",
    "addr:housenumber":"86",
    "addr:postcode":"46131",
    "addr:street":"W Court",
    "iso:country":"US",
    "sg:address":"86 W Court St",
    "sg:city":"Franklin",
    "sg:classifiers":[
        {
            "category":"Government",
            "subcategory":"Office",
            "type":"Public Place"
        }
    ],
    "sg:phone":"+1 317 736 3708",
    "sg:postcode":"46131",
    "sg:province":"IN",
    "sg:tags":[
        "county"
    ],
    "wof:name":"Johnson County Clerk",
    "wof:placetype":"venue"
},
  "geometry": {"coordinates":[-86.05576600000001,39.479697],"type":"Point"}
}