{
  "type": "Feature",
  "properties": {
    "iso:country":"US",
    "sg:address":"1617 3rd St",
    "sg:city":"Osceola",
    "sg:classifiers":[
        {
            "category":"Building & Trades",
            "subcategory":"Construction",
            "type":"Services"
        }
    ],
    "sg:phone":"+1 574 674 9204",
    "sg:postcode":"46561",
    "sg:province":"IN",
    "sg:tags":[
        "excavating",
        "contractor"
    ],
    "wof:name":"R J Excavating",
    "wof:placetype":"venue"
},
  "geometry": {"coordinates":[-86.081476,41.660943],"type":"Point"}
}