{
  "type": "Feature",
  "properties": {
    "iso:country":"US",
    "sg:address":"30 S Meridian St",
    "sg:city":"Indianapolis",
    "sg:classifiers":[
        {
            "category":"Military Area",
            "type":"Public Place"
        }
    ],
    "sg:phone":"+1 317 275 1212",
    "sg:postcode":"46204",
    "sg:province":"IN",
    "sg:tags":[
        "force",
        "armed",
        "recruiting"
    ],
    "wof:name":"Drums Corps Intl.",
    "wof:placetype":"venue"
},
  "geometry": {"coordinates":[-86.15812200000001,39.766265],"type":"Point"}
}