{
  "type": "Feature",
  "properties": {
    "iso:country":"US",
    "sg:address":"2750 E Main St",
    "sg:city":"Plainfield",
    "sg:classifiers":[
        {
            "category":"Autos & Motor Vehicles",
            "subcategory":"Automobile Sales",
            "type":"Retail Goods"
        }
    ],
    "sg:phone":"+1 317 839 4601",
    "sg:postcode":"46168",
    "sg:province":"IN",
    "sg:tags":[
        "car",
        "dealer"
    ],
    "wof:name":"Fine Auto Sales",
    "wof:placetype":"venue"
},
  "geometry": {"coordinates":[-86.348538,39.721363],"type":"Point"}
}