{
  "type": "Feature",
  "properties": {
    "iso:country":"US",
    "sg:address":"2340 S State Rd 135",
    "sg:city":"Greenwood",
    "sg:classifiers":[
        {
            "category":"Organizations",
            "subcategory":"Religious Organization",
            "type":"Services"
        }
    ],
    "sg:phone":"+1 317 535 9007",
    "sg:postcode":"46143",
    "sg:province":"IN",
    "sg:tags":[
        "church"
    ],
    "sg:website":"www.centergrovechurch.org",
    "wof:name":"Center Grove Presbyterian Chr",
    "wof:placetype":"venue"
},
  "geometry": {"coordinates":[-86.159067,39.580728],"type":"Point"}
}