{
  "type": "Feature",
  "properties": {
    "iso:country":"US",
    "sg:address":"45 E Market St",
    "sg:city":"Huntington",
    "sg:classifiers":[
        {
            "category":"Cinema",
            "subcategory":"Movie Rental",
            "type":"Entertainment"
        }
    ],
    "sg:phone":"+1 260 358 1980",
    "sg:postcode":"46750",
    "sg:province":"IN",
    "sg:tags":[
        "video",
        "tape"
    ],
    "wof:name":"Video Plus",
    "wof:placetype":"venue"
},
  "geometry": {"coordinates":[-85.494245,40.882145],"type":"Point"}
}