{
  "type": "Feature",
  "properties": {
    "iso:country":"US",
    "sg:address":"314 N Illinois St",
    "sg:city":"Monticello",
    "sg:classifiers":[
        {
            "category":"Professional",
            "subcategory":"Engineering",
            "type":"Services"
        }
    ],
    "sg:phone":"+1 574 583 9563",
    "sg:postcode":"47960",
    "sg:province":"IN",
    "sg:tags":[
        "engineer"
    ],
    "wof:name":"Donald W Ward & Assoc",
    "wof:placetype":"venue"
},
  "geometry": {"coordinates":[-86.763535,40.747543],"type":"Point"}
}