{
  "type": "Feature",
  "properties": {
    "addr:full":"4465 N Fortville Pike Greenfield IN 46140",
    "addr:housenumber":"4465",
    "addr:postcode":"46140",
    "addr:street":"N Fortville Pike",
    "iso:country":"US",
    "sg:address":"4465 N Fortville Pike",
    "sg:city":"Greenfield",
    "sg:classifiers":[
        {
            "category":"Organizations",
            "subcategory":"Religious Organization",
            "type":"Services"
        }
    ],
    "sg:phone":"+1 317 462 9404",
    "sg:postcode":"46140",
    "sg:province":"IN",
    "sg:tags":[
        "church"
    ],
    "wof:name":"Church Of The Bible Covenant",
    "wof:placetype":"venue"
},
  "geometry": {"coordinates":[-85.814871,39.853077],"type":"Point"}
}