{
  "type": "Feature",
  "properties": {
    "iso:country":"US",
    "sg:address":"815 N Sterling Ave",
    "sg:city":"Veedersburg",
    "sg:classifiers":[
        {
            "category":"Retail",
            "subcategory":"Auto Repair",
            "type":"Services"
        }
    ],
    "sg:phone":"+1 765 294 2884",
    "sg:postcode":"47987",
    "sg:province":"IN",
    "sg:tags":[
        "repairing",
        "automobile"
    ],
    "wof:name":"Papa's Auto Repair",
    "wof:placetype":"venue"
},
  "geometry": {"coordinates":[-87.249545,40.119782],"type":"Point"}
}