{
  "type": "Feature",
  "properties": {
    "iso:country":"US",
    "sg:address":"1355 W Plymouth St",
    "sg:city":"Bremen",
    "sg:classifiers":[
        {
            "category":"Organizations",
            "subcategory":"Professional Association",
            "type":"Services"
        }
    ],
    "sg:phone":"+1 574 546 4971",
    "sg:postcode":"46506",
    "sg:province":"IN",
    "wof:name":"Veterans Of Foreign Wars",
    "wof:placetype":"venue"
},
  "geometry": {"coordinates":[-86.16449299999999,41.446489],"type":"Point"}
}