{
  "type": "Feature",
  "properties": {
    "addr:full":"3440 N Shadeland Ave # 1 Indianapolis IN 46226",
    "addr:housenumber":"3440",
    "addr:postcode":"46226",
    "addr:street":"N Shadeland Ave # 1",
    "iso:country":"US",
    "sg:address":"3440 N Shadeland Ave # 1",
    "sg:city":"Indianapolis",
    "sg:classifiers":[
        {
            "category":"Professional",
            "subcategory":"Business Services",
            "type":"Services"
        }
    ],
    "sg:phone":"+1 317 547 9937",
    "sg:postcode":"46226",
    "sg:province":"IN",
    "sg:tags":[
        "mail",
        "shipping"
    ],
    "sg:website":"http://www.midwestpresort.com",
    "wof:name":"Midwest Presort Service",
    "wof:placetype":"venue"
},
  "geometry": {"coordinates":[-86.045789,39.819196],"type":"Point"}
}