{
  "type": "Feature",
  "properties": {
    "addr:full":"111 E Railroad St Garrett IN 46738",
    "addr:housenumber":"111",
    "addr:postcode":"46738",
    "addr:street":"E Railroad St",
    "iso:country":"US",
    "sg:address":"111 E Railroad St",
    "sg:city":"Garrett",
    "sg:classifiers":[
        {
            "category":"Retail",
            "subcategory":"Auto Repair",
            "type":"Services"
        }
    ],
    "sg:phone":"+1 260 357 5565",
    "sg:postcode":"46738",
    "sg:province":"IN",
    "sg:tags":[
        "body",
        "automobile",
        "painting"
    ],
    "wof:name":"Northside Body Shop",
    "wof:placetype":"venue"
},
  "geometry": {"coordinates":[-85.135127,41.353564],"type":"Point"}
}