{
  "type": "Feature",
  "properties": {
    "iso:country":"US",
    "sg:address":"2104 Miner St",
    "sg:city":"Fort Wayne",
    "sg:classifiers":[
        {
            "category":"Organizations",
            "subcategory":"Religious Organization",
            "type":"Services"
        }
    ],
    "sg:phone":"+1 260 456 9990",
    "sg:postcode":"46802",
    "sg:province":"IN",
    "sg:tags":[
        "church"
    ],
    "wof:name":"New World Outreach",
    "wof:placetype":"venue"
},
  "geometry": {"coordinates":[-85.15081,41.066047],"type":"Point"}
}