{
  "type": "Feature",
  "properties": {
    "iso:country":"US",
    "sg:address":"865 E Harrison St",
    "sg:city":"Martinsville",
    "sg:classifiers":[
        {
            "category":"Shopping",
            "subcategory":"Clothing, Apparel, & Fashions",
            "type":"Retail Goods"
        }
    ],
    "sg:phone":"+1 765 342 0900",
    "sg:postcode":"46151",
    "sg:province":"IN",
    "wof:name":"Frog Pond",
    "wof:placetype":"venue"
},
  "geometry": {"coordinates":[-86.418316,39.42954],"type":"Point"}
}