{
  "type": "Feature",
  "properties": {
    "iso:country":"US",
    "sg:address":"14054 Co Rd 4",
    "sg:city":"Bristol",
    "sg:classifiers":[
        {
            "category":"Manufacturing",
            "subcategory":"Motor Vehicles & Parts",
            "type":"Manufacturing & Wholesale Goods"
        }
    ],
    "sg:phone":"+1 574 825 5867",
    "sg:postcode":"46507",
    "sg:province":"IN",
    "sg:tags":[
        "designer",
        "trailer"
    ],
    "wof:name":"Haulmark Industries",
    "wof:placetype":"venue"
},
  "geometry": {"coordinates":[-85.73825100000001,41.73979],"type":"Point"}
}