{
  "type": "Feature",
  "properties": {
    "addr:full":"141 W Ireland Rd South Bend IN 46614",
    "addr:housenumber":"141",
    "addr:postcode":"46614",
    "addr:street":"W Ireland Rd",
    "iso:country":"US",
    "sg:address":"141 W Ireland Rd",
    "sg:city":"South Bend",
    "sg:classifiers":[
        {
            "category":"Retail",
            "subcategory":"Auto Repair",
            "type":"Services"
        }
    ],
    "sg:phone":"+1 574 231 1574",
    "sg:postcode":"46614",
    "sg:province":"IN",
    "sg:tags":[
        "repairing",
        "automobile"
    ],
    "wof:name":"Tim's Auto Repair",
    "wof:placetype":"venue"
},
  "geometry": {"coordinates":[-86.25191,41.629035],"type":"Point"}
}