{
  "type": "Feature",
  "properties": {
    "iso:country":"US",
    "sg:address":"100 Suzie Ln",
    "sg:city":"Attica",
    "sg:classifiers":[
        {
            "category":"Real Estate",
            "subcategory":"Real Estate Operator",
            "type":"Services"
        }
    ],
    "sg:phone":"+1 765 793 4881",
    "sg:postcode":"47918",
    "sg:province":"IN",
    "sg:tags":[
        "apartment"
    ],
    "wof:name":"Community Action Program Inc",
    "wof:placetype":"venue"
},
  "geometry": {"coordinates":[-87.24078799999999,40.288976],"type":"Point"}
}