{
  "type": "Feature",
  "properties": {
    "iso:country":"US",
    "sg:address":"1201 N Troy Ave",
    "sg:city":"Delphi",
    "sg:classifiers":[
        {
            "category":"Sports & Exercise",
            "subcategory":"Race Track",
            "type":"Entertainment"
        }
    ],
    "sg:phone":"+1 765 564 9239",
    "sg:postcode":"46923",
    "sg:province":"IN",
    "wof:name":"Finish Line Entertainment Inc",
    "wof:placetype":"venue"
},
  "geometry": {"coordinates":[-86.730049,40.585639],"type":"Point"}
}