{
  "type": "Feature",
  "properties": {
    "iso:country":"US",
    "sg:address":"1716 E Washington St",
    "sg:city":"Indianapolis",
    "sg:classifiers":[
        {
            "category":"Autos & Motor Vehicles",
            "subcategory":"Automobile Sales",
            "type":"Retail Goods"
        }
    ],
    "sg:phone":"+1 317 264 0226",
    "sg:postcode":"46201",
    "sg:province":"IN",
    "sg:tags":[
        "car",
        "used",
        "dealer"
    ],
    "wof:name":"Will's Auto Sales",
    "wof:placetype":"venue"
},
  "geometry": {"coordinates":[-86.12961199999999,39.76747],"type":"Point"}
}