{
  "type": "Feature",
  "properties": {
    "iso:country":"US",
    "sg:address":"118 E North St",
    "sg:city":"Lebanon",
    "sg:classifiers":[
        {
            "category":"Food & Beverages",
            "subcategory":"Supermarket",
            "type":"Retail Goods"
        },
        {
            "category":"Food & Beverages",
            "subcategory":"Groceries & Convenience Stores",
            "type":"Retail Goods"
        }
    ],
    "sg:phone":"+1 765 482 3298",
    "sg:postcode":"46052",
    "sg:province":"IN",
    "sg:tags":[
        "super"
    ],
    "wof:name":"Railer's IGA",
    "wof:placetype":"venue"
},
  "geometry": {"coordinates":[-86.46794300000001,40.049358],"type":"Point"}
}