{
  "type": "Feature",
  "properties": {
    "iso:country":"US",
    "sg:address":"136 Windemere Rd",
    "sg:city":"Whiteland",
    "sg:classifiers":[
        {
            "category":"Building & Trades",
            "subcategory":"Construction",
            "type":"Services"
        }
    ],
    "sg:phone":"+1 317 535 2502",
    "sg:postcode":"46184",
    "sg:province":"IN",
    "sg:tags":[
        "residential",
        "contractor"
    ],
    "wof:name":"Cassin Construction",
    "wof:placetype":"venue"
},
  "geometry": {"coordinates":[-86.099735,39.569384],"type":"Point"}
}