{
  "type": "Feature",
  "properties": {
    "iso:country":"US",
    "sg:address":"6718 E 38th St",
    "sg:city":"Indianapolis",
    "sg:classifiers":[
        {
            "category":"Personal",
            "subcategory":"Beauty Salon",
            "type":"Services"
        }
    ],
    "sg:phone":"+1 317 542 7776",
    "sg:postcode":"46226",
    "sg:province":"IN",
    "wof:name":"Sudden Change Hair Gallery",
    "wof:placetype":"venue"
},
  "geometry": {"coordinates":[-86.049358,39.825811],"type":"Point"}
}