{
  "type": "Feature",
  "properties": {
    "iso:country":"US",
    "sg:address":"109 W Deffenbaugh St",
    "sg:city":"Kokomo",
    "sg:classifiers":[
        {
            "category":"Health Services",
            "subcategory":"Medical Lab",
            "type":"Services"
        }
    ],
    "sg:phone":"+1 765 456 3705",
    "sg:postcode":"46902",
    "sg:province":"IN",
    "sg:tags":[
        "laboratory"
    ],
    "wof:name":"Techniques Dental Lab",
    "wof:placetype":"venue"
},
  "geometry": {"coordinates":[-86.131585,40.469389],"type":"Point"}
}