{
  "type": "Feature",
  "properties": {
    "iso:country":"US",
    "sg:address":"1402 H St",
    "sg:city":"Bedford",
    "sg:classifiers":[
        {
            "category":"Building & Trades",
            "subcategory":"Construction",
            "type":"Services"
        }
    ],
    "sg:phone":"+1 812 279 3071",
    "sg:postcode":"47421",
    "sg:province":"IN",
    "sg:tags":[
        "paving",
        "contractor"
    ],
    "wof:name":"Arthur Paving & Excavating",
    "wof:placetype":"venue"
},
  "geometry": {"coordinates":[-86.48113,38.863268],"type":"Point"}
}