{
  "type": "Feature",
  "properties": {
    "iso:country":"US",
    "sg:address":"402 Illinois St",
    "sg:city":"Walkerton",
    "sg:classifiers":[
        {
            "category":"Personal",
            "subcategory":"Beauty Salon",
            "type":"Services"
        }
    ],
    "sg:phone":"+1 574 586 2185",
    "sg:postcode":"46574",
    "sg:province":"IN",
    "wof:name":"Hidden Bu-Tee Salon",
    "wof:placetype":"venue"
},
  "geometry": {"coordinates":[-86.48237,41.466234],"type":"Point"}
}