{
  "type": "Feature",
  "properties": {
    "iso:country":"US",
    "sg:address":"3512 Rockville Rd Ste 141C",
    "sg:city":"Indianapolis",
    "sg:classifiers":[
        {
            "category":"Taxi",
            "type":"Transportation"
        }
    ],
    "sg:phone":"+1 317 247 8888",
    "sg:postcode":"46222",
    "sg:province":"IN",
    "wof:name":"Airport Taxicab",
    "wof:placetype":"venue"
},
  "geometry": {"coordinates":[-86.21967100000001,39.762679],"type":"Point"}
}