{
  "type": "Feature",
  "properties": {
    "addr:full":"2850 N Routiers Ave Indianapolis IN 46219",
    "addr:housenumber":"2850",
    "addr:postcode":"46219",
    "addr:street":"N Routiers Ave",
    "iso:country":"US",
    "sg:address":"2850 N Routiers Ave",
    "sg:city":"Indianapolis",
    "sg:classifiers":[
        {
            "category":"Professional",
            "subcategory":"Accounting & Tax Preparation",
            "type":"Services"
        }
    ],
    "sg:phone":"+1 317 898 0387",
    "sg:postcode":"46219",
    "sg:province":"IN",
    "sg:tags":[
        "accountant"
    ],
    "wof:name":"Helen Haywood",
    "wof:placetype":"venue"
},
  "geometry": {"coordinates":[-86.014062,39.809656],"type":"Point"}
}