{
  "type": "Feature",
  "properties": {
    "iso:country":"US",
    "sg:address":"333 N Grandstaff Dr",
    "sg:city":"Auburn",
    "sg:classifiers":[
        {
            "category":"Autos & Motor Vehicles",
            "subcategory":"Automobile Sales",
            "type":"Retail Goods"
        }
    ],
    "sg:phone":"+1 260 925 9655",
    "sg:postcode":"46706",
    "sg:province":"IN",
    "sg:tags":[
        "car",
        "dealer"
    ],
    "wof:name":"Preferred Auto",
    "wof:placetype":"venue"
},
  "geometry": {"coordinates":[-85.071701,41.368828],"type":"Point"}
}