{
  "type": "Feature",
  "properties": {
    "iso:country":"US",
    "sg:address":"646 Guilford St",
    "sg:city":"Huntington",
    "sg:classifiers":[
        {
            "category":"Insurance",
            "subcategory":"Insurance Agent",
            "type":"Services"
        }
    ],
    "sg:phone":"+1 260 356 2550",
    "sg:postcode":"46750",
    "sg:province":"IN",
    "wof:name":"American Family Insurance",
    "wof:placetype":"venue"
},
  "geometry": {"coordinates":[-85.494106,40.884102],"type":"Point"}
}