{
  "type": "Feature",
  "properties": {
    "iso:country":"US",
    "sg:address":"2835 S Holt Rd",
    "sg:city":"Indianapolis",
    "sg:classifiers":[
        {
            "category":"Retail",
            "subcategory":"Auto Rental",
            "type":"Services"
        }
    ],
    "sg:phone":"+1 317 899 3556",
    "sg:postcode":"46241",
    "sg:province":"IN",
    "sg:tags":[
        "renting",
        "truck",
        "leasing"
    ],
    "wof:name":"Palmer Leasing Group",
    "wof:placetype":"venue"
},
  "geometry": {"coordinates":[-86.225098,39.723331],"type":"Point"}
}