{
  "type": "Feature",
  "properties": {
    "iso:country":"US",
    "sg:address":"347 Melton Rd",
    "sg:city":"Burns Harbor",
    "sg:classifiers":[
        {
            "category":"Autos & Motor Vehicles",
            "subcategory":"Automobile Sales",
            "type":"Retail Goods"
        }
    ],
    "sg:phone":"+1 219 787 9414",
    "sg:postcode":"46304",
    "sg:province":"IN",
    "sg:tags":[
        "car",
        "dealer"
    ],
    "wof:name":"Dean's Auto Sales & Svc",
    "wof:placetype":"venue"
},
  "geometry": {"coordinates":[-87.131553,41.6003],"type":"Point"}
}