{
  "type": "Feature",
  "properties": {
    "iso:country":"US",
    "sg:address":"1011 W Weber Dr",
    "sg:city":"Muncie",
    "sg:classifiers":[
        {
            "category":"Retail",
            "subcategory":"Portrait Studio",
            "type":"Services"
        }
    ],
    "sg:phone":"+1 765 284 7596",
    "sg:postcode":"47303",
    "sg:province":"IN",
    "sg:tags":[
        "photographer"
    ],
    "wof:name":"Davis Photography",
    "wof:placetype":"venue"
},
  "geometry": {"coordinates":[-85.40108,40.210542],"type":"Point"}
}