{
  "type": "Feature",
  "properties": {
    "iso:country":"US",
    "sg:address":"209 S Grant St",
    "sg:city":"Martinsville",
    "sg:classifiers":[
        {
            "category":"Restaurant",
            "type":"Food & Drink"
        }
    ],
    "sg:phone":"+1 765 352 0952",
    "sg:postcode":"46151",
    "sg:province":"IN",
    "wof:name":"Wendy's",
    "wof:placetype":"venue"
},
  "geometry": {"coordinates":[-86.41995900000001,39.42488],"type":"Point"}
}