{
  "type": "Feature",
  "properties": {
    "iso:country":"US",
    "sg:address":"2200 W Monroe St",
    "sg:city":"Decatur",
    "sg:classifiers":[
        {
            "category":"Manufacturing",
            "subcategory":"Watercraft",
            "type":"Manufacturing & Wholesale Goods"
        }
    ],
    "sg:phone":"+1 260 724 9111",
    "sg:postcode":"46733",
    "sg:province":"IN",
    "sg:tags":[
        "boat"
    ],
    "sg:website":"www.formulaboats.com",
    "wof:name":"Thunderbird Products",
    "wof:placetype":"venue"
},
  "geometry": {"coordinates":[-84.951454,40.827174],"type":"Point"}
}