{
  "type": "Feature",
  "properties": {
    "iso:country":"US",
    "sg:address":"5522 W Popcorn Rd",
    "sg:city":"Springville",
    "sg:classifiers":[
        {
            "category":"Government",
            "subcategory":"Office",
            "type":"Public Place"
        }
    ],
    "sg:phone":"+1 812 824 4981",
    "sg:postcode":"47462",
    "sg:province":"IN",
    "sg:tags":[
        "village"
    ],
    "wof:name":"Indian Creek Township",
    "wof:placetype":"venue"
},
  "geometry": {"coordinates":[-86.611987,38.999341],"type":"Point"}
}