{
  "type": "Feature",
  "properties": {
    "addr:full":"1115 S Jefferson St Huntington IN 46750",
    "addr:housenumber":"1115",
    "addr:postcode":"46750",
    "addr:street":"S Jefferson",
    "iso:country":"US",
    "sg:address":"1115 S Jefferson St",
    "sg:city":"Huntington",
    "sg:classifiers":[
        {
            "category":"Home & Garden",
            "subcategory":"Garden Supply",
            "type":"Retail Goods"
        }
    ],
    "sg:phone":"+1 260 356 1188",
    "sg:postcode":"46750",
    "sg:province":"IN",
    "sg:tags":[
        "lawn",
        "mower"
    ],
    "wof:name":"Beckler Power Equipment",
    "wof:placetype":"venue"
},
  "geometry": {"coordinates":[-85.48558199999999,40.872752],"type":"Point"}
}