{
  "type": "Feature",
  "properties": {
    "iso:country":"US",
    "sg:address":"10525 N 900 W",
    "sg:city":"Monticello",
    "sg:classifiers":[
        {
            "category":"Banks & Credit Unions",
            "subcategory":"Bank",
            "type":"Services"
        }
    ],
    "sg:phone":"+1 574 965 2020",
    "sg:postcode":"47960",
    "sg:province":"IN",
    "sg:tags":[
        "loan",
        "real estate"
    ],
    "wof:name":"Around The Clock Bail Bonds",
    "wof:placetype":"venue"
},
  "geometry": {"coordinates":[-86.696756,40.702095],"type":"Point"}
}