{
  "type": "Feature",
  "properties": {
    "addr:full":"202 S Wood St Brookston IN 47923",
    "addr:housenumber":"202",
    "addr:postcode":"47923",
    "addr:street":"S Wood St",
    "iso:country":"US",
    "sg:address":"202 S Wood St",
    "sg:city":"Brookston",
    "sg:classifiers":[
        {
            "category":"Organizations",
            "subcategory":"Religious Organization",
            "type":"Services"
        }
    ],
    "sg:phone":"+1 765 563 6323",
    "sg:postcode":"47923",
    "sg:province":"IN",
    "sg:tags":[
        "church"
    ],
    "wof:name":"Federated Church",
    "wof:placetype":"venue"
},
  "geometry": {"coordinates":[-86.865044,40.60367],"type":"Point"}
}