{
  "type": "Feature",
  "properties": {
    "iso:country":"US",
    "sg:address":"14425 E Hazel St",
    "sg:city":"Daleville",
    "sg:classifiers":[
        {
            "category":"Personal",
            "subcategory":"Beauty Salon",
            "type":"Services"
        }
    ],
    "sg:phone":"+1 765 378 0317",
    "sg:postcode":"47334",
    "sg:province":"IN",
    "wof:name":"Lesley Hair Salon",
    "wof:placetype":"venue"
},
  "geometry": {"coordinates":[-85.556429,40.122142],"type":"Point"}
}