{
  "type": "Feature",
  "properties": {
    "addr:full":"1803 S Jimtown Ln Scottsburg IN 47170",
    "addr:housenumber":"1803",
    "addr:postcode":"47170",
    "addr:street":"S Jimtown Ln",
    "iso:country":"US",
    "sg:address":"1803 S Jimtown Ln",
    "sg:city":"Scottsburg",
    "sg:classifiers":[
        {
            "category":"Building & Trades",
            "subcategory":"Cleaning & Sanitation",
            "type":"Services"
        }
    ],
    "sg:phone":"+1 812 752 8102",
    "sg:postcode":"47170",
    "sg:province":"IN",
    "sg:tags":[
        "protection",
        "fabric",
        "furniture"
    ],
    "wof:name":"S & D Carpet Care",
    "wof:placetype":"venue"
},
  "geometry": {"coordinates":[-85.718808,38.657315],"type":"Point"}
}