{
  "type": "Feature",
  "properties": {
    "addr:full":"123 NW 4th St Evansville IN 47708",
    "addr:housenumber":"123",
    "addr:postcode":"47708",
    "addr:street":"Nw 4Th St",
    "iso:country":"US",
    "sg:address":"123 NW 4th St",
    "sg:city":"Evansville",
    "sg:classifiers":[
        {
            "category":"Organizations",
            "subcategory":"Membership Organization",
            "type":"Services"
        }
    ],
    "sg:phone":"+1 812 464 2219",
    "sg:postcode":"47708",
    "sg:province":"IN",
    "wof:name":"Al-Anon",
    "wof:placetype":"venue"
},
  "geometry": {"coordinates":[-87.572273,37.973101],"type":"Point"}
}