{
  "type": "Feature",
  "properties": {
    "iso:country":"US",
    "sg:address":"2124 W 96th Ave",
    "sg:city":"Crown Point",
    "sg:classifiers":[
        {
            "category":"Building & Trades",
            "subcategory":"Landscaping Services",
            "type":"Services"
        }
    ],
    "sg:phone":"+1 219 663 6175",
    "sg:postcode":"46307",
    "sg:province":"IN",
    "sg:tags":[
        "landscape",
        "contractor"
    ],
    "wof:name":"G & G Landscape & Lawn Care",
    "wof:placetype":"venue"
},
  "geometry": {"coordinates":[-87.362081,41.443573],"type":"Point"}
}