{
  "type": "Feature",
  "properties": {
    "iso:country":"US",
    "sg:address":"4430 W Jonathan Moore Pike",
    "sg:city":"Columbus",
    "sg:classifiers":[
        {
            "category":"Organizations",
            "subcategory":"Religious Organization",
            "type":"Services"
        }
    ],
    "sg:phone":"+1 812 342 8464",
    "sg:postcode":"47201",
    "sg:province":"IN",
    "sg:tags":[
        "church"
    ],
    "wof:name":"Westside Community Church Inc",
    "wof:placetype":"venue"
},
  "geometry": {"coordinates":[-85.972441,39.199732],"type":"Point"}
}