{
  "type": "Feature",
  "properties": {
    "iso:country":"US",
    "sg:address":"2576 Portage Mall",
    "sg:city":"Portage",
    "sg:classifiers":[
        {
            "category":"Professional",
            "subcategory":"Lawyer & Legal Services",
            "type":"Services"
        }
    ],
    "sg:phone":"+1 219 762 8521",
    "sg:postcode":"46368",
    "sg:province":"IN",
    "sg:tags":[
        "attorney"
    ],
    "wof:name":"Donald E Cochran",
    "wof:placetype":"venue"
},
  "geometry": {"coordinates":[-87.176502,41.577442],"type":"Point"}
}