{
  "type": "Feature",
  "properties": {
    "addr:full":"5410 State Rd 160 Charlestown IN 47111",
    "addr:housenumber":"5410;160",
    "addr:postcode":"47111",
    "addr:street":"State Rd",
    "iso:country":"US",
    "sg:address":"5410 State Rd 160",
    "sg:city":"Charlestown",
    "sg:classifiers":[
        {
            "category":"Wholesale",
            "subcategory":"Auto Parts",
            "type":"Manufacturing & Wholesale Goods"
        }
    ],
    "sg:phone":"+1 812 294 7200",
    "sg:postcode":"47111",
    "sg:province":"IN",
    "sg:tags":[
        "automobile",
        "rebuilt"
    ],
    "wof:name":"Traders Auto World Inc",
    "wof:placetype":"venue"
},
  "geometry": {"coordinates":[-85.727082,38.512765],"type":"Point"}
}