{
  "type": "Feature",
  "properties": {
    "iso:country":"US",
    "sg:address":"1016 W 7th St",
    "sg:city":"Auburn",
    "sg:classifiers":[
        {
            "category":"Personal",
            "subcategory":"Beauty Salon",
            "type":"Services"
        }
    ],
    "sg:phone":"+1 260 927 0150",
    "sg:postcode":"46706",
    "sg:province":"IN",
    "sg:tags":[
        "manicuring"
    ],
    "wof:name":"Nail Trix",
    "wof:placetype":"venue"
},
  "geometry": {"coordinates":[-85.071996,41.366763],"type":"Point"}
}