{
  "type": "Feature",
  "properties": {
    "iso:country":"US",
    "sg:address":"1140 Cinnamon Rd",
    "sg:city":"Fort Wayne",
    "sg:classifiers":[
        {
            "category":"Professional",
            "subcategory":"Management & Consulting",
            "type":"Services"
        }
    ],
    "sg:phone":"+1 260 483 6795",
    "sg:postcode":"46825",
    "sg:province":"IN",
    "sg:tags":[
        "new",
        "product",
        "consultant"
    ],
    "wof:name":"Ralir Inc",
    "wof:placetype":"venue"
},
  "geometry": {"coordinates":[-85.124478,41.141279],"type":"Point"}
}