{
  "type": "Feature",
  "properties": {
    "iso:country":"US",
    "sg:address":"681 Hale Cir",
    "sg:city":"Richmond",
    "sg:classifiers":[
        {
            "category":"Health Services",
            "subcategory":"Doctor",
            "type":"Services"
        }
    ],
    "sg:phone":"+1 765 962 3808",
    "sg:postcode":"47374",
    "sg:province":"IN",
    "sg:tags":[
        "medical"
    ],
    "wof:name":"Charles A Browning",
    "wof:placetype":"venue"
},
  "geometry": {"coordinates":[-84.854116,39.82017],"type":"Point"}
}