{
  "type": "Feature",
  "properties": {
    "iso:country":"US",
    "sg:address":"7925 S Walnut St",
    "sg:city":"Daleville",
    "sg:classifiers":[
        {
            "category":"Food & Beverages",
            "subcategory":"Groceries & Convenience Stores",
            "type":"Retail Goods"
        }
    ],
    "sg:phone":"+1 765 378 1027",
    "sg:postcode":"47334",
    "sg:province":"IN",
    "sg:tags":[
        "grocer"
    ],
    "wof:name":"Ross Food Market Inc",
    "wof:placetype":"venue"
},
  "geometry": {"coordinates":[-85.557255,40.121704],"type":"Point"}
}