{
  "type": "Feature",
  "properties": {
    "addr:full":"4550 W 116th St Zionsville IN 46077",
    "addr:housenumber":"4550",
    "addr:postcode":"46077",
    "addr:street":"W 116Th St",
    "iso:country":"US",
    "sg:address":"4550 W 116th St",
    "sg:city":"Zionsville",
    "sg:classifiers":[
        {
            "category":"Building & Trades",
            "subcategory":"Construction",
            "type":"Services"
        }
    ],
    "sg:phone":"+1 317 733 4100",
    "sg:postcode":"46077",
    "sg:province":"IN",
    "sg:tags":[
        "general",
        "contractor"
    ],
    "wof:name":"KB Home",
    "wof:placetype":"venue"
},
  "geometry": {"coordinates":[-86.238326,39.955424],"type":"Point"}
}