{
  "type": "Feature",
  "properties": {
    "addr:full":"4092 State Road 26 E Lafayette IN 47905",
    "addr:housenumber":"4092",
    "addr:postcode":"47905",
    "addr:street":"State Road 26 E",
    "iso:country":"US",
    "sg:address":"4092 State Road 26 E",
    "sg:city":"Lafayette",
    "sg:classifiers":[
        {
            "category":"Restaurant",
            "type":"Food & Drink"
        }
    ],
    "sg:menulink":"http://www.allmenus.com/in/fairfield/167382-burger-king/menu/",
    "sg:phone":"+1 765 447 3652",
    "sg:postcode":"47905",
    "sg:province":"IN",
    "sg:tags":[
        "burger",
        "american"
    ],
    "wof:name":"Burger King",
    "wof:placetype":"venue"
},
  "geometry": {"coordinates":[-86.828238,40.417788],"type":"Point"}
}