{
  "type": "Feature",
  "properties": {
    "iso:country":"US",
    "sg:address":"6518 Columbia Ave",
    "sg:city":"Hammond",
    "sg:classifiers":[
        {
            "category":"Food & Beverages",
            "subcategory":"Groceries & Convenience Stores",
            "type":"Retail Goods"
        }
    ],
    "sg:phone":"+1 219 000 1111",
    "sg:postcode":"46320",
    "sg:province":"IN",
    "sg:tags":[
        "grocer"
    ],
    "wof:name":"Aldi",
    "wof:placetype":"venue"
},
  "geometry": {"coordinates":[-87.500249,41.593737],"type":"Point"}
}