{
  "type": "Feature",
  "properties": {
    "addr:full":"816 W Beardsley Ave Elkhart IN 46514",
    "addr:housenumber":"816",
    "addr:postcode":"46514",
    "addr:street":"W Beardsley Ave",
    "iso:country":"US",
    "sg:address":"816 W Beardsley Ave",
    "sg:city":"Elkhart",
    "sg:classifiers":[
        {
            "category":"Manufacturing",
            "subcategory":"Retail Goods",
            "type":"Manufacturing & Wholesale Goods"
        }
    ],
    "sg:phone":"+1 574 293 0113",
    "sg:postcode":"46514",
    "sg:province":"IN",
    "sg:tags":[
        "marking",
        "devices"
    ],
    "wof:name":"JVC Rubber Stamp Co",
    "wof:placetype":"venue"
},
  "geometry": {"coordinates":[-85.987683,41.692807],"type":"Point"}
}