{
  "type": "Feature",
  "properties": {
    "iso:country":"US",
    "sg:address":"1220 Medical Park Dr",
    "sg:city":"Fort Wayne",
    "sg:classifiers":[
        {
            "category":"Professional",
            "subcategory":"Accounting & Tax Preparation",
            "type":"Services"
        }
    ],
    "sg:phone":"+1 260 484 8629",
    "sg:postcode":"46825",
    "sg:province":"IN",
    "sg:tags":[
        "billing"
    ],
    "wof:name":"Medical Payment Ctr",
    "wof:placetype":"venue"
},
  "geometry": {"coordinates":[-85.12491799999999,41.12427],"type":"Point"}
}