{
  "type": "Feature",
  "properties": {
    "iso:country":"US",
    "sg:address":"212 Vernon St",
    "sg:city":"North Vernon",
    "sg:classifiers":[
        {
            "category":"Social Services",
            "type":"Services"
        }
    ],
    "sg:phone":"+1 812 346 4461",
    "sg:postcode":"47265",
    "sg:province":"IN",
    "wof:name":"Birthline",
    "wof:placetype":"venue"
},
  "geometry": {"coordinates":[-85.622014,39.003415],"type":"Point"}
}