{
  "type": "Feature",
  "properties": {
    "iso:country":"US",
    "sg:address":"5806 Stringtown Rd",
    "sg:city":"Evansville",
    "sg:classifiers":[
        {
            "category":"Restaurant",
            "type":"Food & Drink"
        }
    ],
    "sg:phone":"+1 812 425 1455",
    "sg:postcode":"47711",
    "sg:province":"IN",
    "wof:name":"Pizza Oven",
    "wof:placetype":"venue"
},
  "geometry": {"coordinates":[-87.562302,38.031055],"type":"Point"}
}