{
  "type": "Feature",
  "properties": {
    "iso:country":"US",
    "sg:address":"73 Quartermaster Ct",
    "sg:city":"Jeffersonville",
    "sg:phone":"+1 812 288 8360",
    "sg:postcode":"47130",
    "sg:province":"IN",
    "wof:name":"Wall Street Internal Medicine",
    "wof:placetype":"venue"
},
  "geometry": {"coordinates":[-85.740076,38.283518],"type":"Point"}
}