{
  "type": "Feature",
  "properties": {
    "iso:country":"US",
    "sg:address":"305 N Main St",
    "sg:city":"Liberty",
    "sg:classifiers":[
        {
            "category":"Shopping",
            "subcategory":"Computers & Home Electronics",
            "type":"Retail Goods"
        }
    ],
    "sg:phone":"+1 765 458 7961",
    "sg:postcode":"47353",
    "sg:province":"IN",
    "sg:tags":[
        "equipment",
        "electronic",
        "supply"
    ],
    "wof:name":"Radioshack",
    "wof:placetype":"venue"
},
  "geometry": {"coordinates":[-84.930875,39.639059],"type":"Point"}
}