{
  "type": "Feature",
  "properties": {
    "addr:full":"6825 S 325 W Ridgeville IN 47380",
    "addr:housenumber":"6825;325",
    "addr:postcode":"47380",
    "addr:street":"S;W Ridgeville",
    "iso:country":"US",
    "sg:address":"6825 S 325 W",
    "sg:city":"Ridgeville",
    "sg:phone":"+1 765 857 2429",
    "sg:postcode":"47380",
    "sg:province":"IN",
    "sg:tags":[
        "farm",
        "field",
        "corn",
        "soybean",
        "crop"
    ],
    "wof:name":"Mike Timmerman",
    "wof:placetype":"venue"
},
  "geometry": {"coordinates":[-85.04182299999999,40.340323],"type":"Point"}
}