{
  "type": "Feature",
  "properties": {
    "iso:country":"US",
    "sg:address":"2120 Sagamore Pkwy S",
    "sg:city":"Lafayette",
    "sg:classifiers":[
        {
            "category":"Utilities",
            "subcategory":"Mobile Phone",
            "type":"Services"
        }
    ],
    "sg:phone":"+1 765 471 0417",
    "sg:postcode":"47905",
    "sg:province":"IN",
    "sg:tags":[
        "telephone",
        "cellular"
    ],
    "wof:name":"Cingular Wireless",
    "wof:placetype":"venue"
},
  "geometry": {"coordinates":[-86.856906,40.397186],"type":"Point"}
}