{
  "type": "Feature",
  "properties": {
    "iso:country":"US",
    "sg:address":"205 Adams St",
    "sg:city":"Decatur",
    "sg:classifiers":[
        {
            "category":"Autos & Motor Vehicles",
            "subcategory":"Fuel & Gas Station",
            "type":"Retail Goods"
        }
    ],
    "sg:phone":"+1 260 724 9271",
    "sg:postcode":"46733",
    "sg:province":"IN",
    "sg:tags":[
        "oil"
    ],
    "wof:name":"S Y Clark",
    "wof:placetype":"venue"
},
  "geometry": {"coordinates":[-84.923404,40.827425],"type":"Point"}
}