{
  "type": "Feature",
  "properties": {
    "iso:country":"US",
    "sg:address":"2212 N 13th St",
    "sg:city":"Terre Haute",
    "sg:classifiers":[
        {
            "category":"Organizations",
            "subcategory":"Religious Organization",
            "type":"Services"
        }
    ],
    "sg:phone":"+1 812 234 2747",
    "sg:postcode":"47804",
    "sg:province":"IN",
    "sg:tags":[
        "clergy"
    ],
    "wof:name":"Mark H Blade",
    "wof:placetype":"venue"
},
  "geometry": {"coordinates":[-87.397913,39.493783],"type":"Point"}
}