{
  "type": "Feature",
  "properties": {
    "iso:country":"US",
    "sg:address":"14326 Worthington Blvd",
    "sg:city":"Fishers",
    "sg:classifiers":[
        {
            "category":"Place Of Worship",
            "type":"Public Place"
        }
    ],
    "sg:phone":"+1 317 538 2624",
    "sg:postcode":"46038",
    "sg:province":"IN",
    "sg:tags":[
        "church"
    ],
    "wof:name":"Emmanuel Cme Church",
    "wof:placetype":"venue"
},
  "geometry": {"coordinates":[-85.991225,39.996776],"type":"Point"}
}