{
  "type": "Feature",
  "properties": {
    "iso:country":"US",
    "sg:address":"3014 Lakeside Dr",
    "sg:city":"Highland",
    "sg:classifiers":[
        {
            "category":"Bars & Pubs",
            "type":"Food & Drink"
        }
    ],
    "sg:phone":"+1 219 924 7961",
    "sg:postcode":"46322",
    "sg:province":"IN",
    "sg:tags":[
        "tavern"
    ],
    "wof:name":"Dave's Emergency Room",
    "wof:placetype":"venue"
},
  "geometry": {"coordinates":[-87.45661800000001,41.528495],"type":"Point"}
}