{
  "type": "Feature",
  "properties": {
    "addr:full":"1500 Broadway St Anderson IN 46012",
    "addr:housenumber":"1500",
    "addr:postcode":"46012",
    "addr:street":"Broadway St",
    "iso:country":"US",
    "sg:address":"1500 Broadway St",
    "sg:city":"Anderson",
    "sg:classifiers":[
        {
            "category":"Shopping",
            "subcategory":"Computers & Home Electronics",
            "type":"Retail Goods"
        }
    ],
    "sg:phone":"+1 765 642 2200",
    "sg:postcode":"46012",
    "sg:province":"IN",
    "sg:tags":[
        "equipment",
        "dealer"
    ],
    "sg:website":"www.saturncomputers.com",
    "wof:name":"Saturn Computers Inc",
    "wof:placetype":"venue"
},
  "geometry": {"coordinates":[-85.677899,40.13157],"type":"Point"}
}