{
  "type": "Feature",
  "properties": {
    "iso:country":"US",
    "sg:address":"7391 N Shadeland Ave",
    "sg:city":"Indianapolis",
    "sg:classifiers":[
        {
            "category":"Food & Beverages",
            "subcategory":"Specialty",
            "type":"Retail Goods"
        }
    ],
    "sg:phone":"+1 317 842 1032",
    "sg:postcode":"46250",
    "sg:province":"IN",
    "sg:tags":[
        "health"
    ],
    "wof:name":"Vintage Health & Whole Foods",
    "wof:placetype":"venue"
},
  "geometry": {"coordinates":[-86.046031,39.889632],"type":"Point"}
}