{
  "type": "Feature",
  "properties": {
    "iso:country":"US",
    "sg:address":"3831 S Madison St",
    "sg:city":"Muncie",
    "sg:classifiers":[
        {
            "category":"Health Services",
            "subcategory":"Doctor",
            "type":"Services"
        }
    ],
    "sg:phone":"+1 765 747 1164",
    "sg:postcode":"47302",
    "sg:province":"IN",
    "sg:tags":[
        "clinic"
    ],
    "wof:name":"Southway Urgentcare",
    "wof:placetype":"venue"
},
  "geometry": {"coordinates":[-85.382015,40.158216],"type":"Point"}
}