{
  "type": "Feature",
  "properties": {
    "iso:country":"US",
    "sg:address":"122 Demaree Dr",
    "sg:city":"Madison",
    "sg:classifiers":[
        {
            "category":"Health Services",
            "subcategory":"Doctor",
            "type":"Services"
        }
    ],
    "sg:phone":"+1 812 265 9191",
    "sg:postcode":"47250",
    "sg:province":"IN",
    "sg:tags":[
        "physician",
        "surgeon"
    ],
    "wof:name":"Madison Dermatology",
    "wof:placetype":"venue"
},
  "geometry": {"coordinates":[-85.384957,38.778455],"type":"Point"}
}