{
  "type": "Feature",
  "properties": {
    "iso:country":"US",
    "sg:address":"6470 N Shadeland Ave",
    "sg:city":"Indianapolis",
    "sg:classifiers":[
        {
            "category":"Health Services",
            "subcategory":"Doctor",
            "type":"Services"
        }
    ],
    "sg:phone":"+1 317 849 9509",
    "sg:postcode":"46250",
    "sg:province":"IN",
    "sg:tags":[
        "physician",
        "surgeon"
    ],
    "wof:name":"Maria Valena & Assoc",
    "wof:placetype":"venue"
},
  "geometry": {"coordinates":[-86.045638,39.86919],"type":"Point"}
}