{
  "type": "Feature",
  "properties": {
    "iso:country":"US",
    "sg:address":"4728 Alexandria Pike",
    "sg:city":"Anderson",
    "sg:classifiers":[
        {
            "category":"Wholesale",
            "subcategory":"Construction Materials",
            "type":"Manufacturing & Wholesale Goods"
        }
    ],
    "sg:phone":"+1 765 644 0267",
    "sg:postcode":"46012",
    "sg:province":"IN",
    "sg:tags":[
        "sand",
        "gravel"
    ],
    "wof:name":"Stanley R Stiers Screen Dirt",
    "wof:placetype":"venue"
},
  "geometry": {"coordinates":[-85.660841,40.165572],"type":"Point"}
}