{
  "type": "Feature",
  "properties": {
    "iso:country":"US",
    "sg:address":"1298 N Madison Ave",
    "sg:city":"Greenwood",
    "sg:classifiers":[
        {
            "category":"Autos & Motor Vehicles",
            "subcategory":"Auto Supplies",
            "type":"Retail Goods"
        }
    ],
    "sg:phone":"+1 317 881 5066",
    "sg:postcode":"46142",
    "sg:province":"IN",
    "sg:tags":[
        "tire"
    ],
    "sg:website":"www.goodyear.com",
    "wof:name":"Goodyear Auto Svc Ctr",
    "wof:placetype":"venue"
},
  "geometry": {"coordinates":[-86.115986,39.632356],"type":"Point"}
}