{
  "type": "Feature",
  "properties": {
    "addr:full":"9705 Decatur Dr Indianapolis IN 46256",
    "addr:housenumber":"9705",
    "addr:postcode":"46256",
    "addr:street":"Decatur Dr",
    "iso:country":"US",
    "sg:address":"9705 Decatur Dr",
    "sg:city":"Indianapolis",
    "sg:classifiers":[
        {
            "category":"Home & Garden",
            "subcategory":"Household Appliances",
            "type":"Retail Goods"
        }
    ],
    "sg:phone":"+1 317 849 5521",
    "sg:postcode":"46256",
    "sg:province":"IN",
    "sg:tags":[
        "iron"
    ],
    "wof:name":"Accucast Inc",
    "wof:placetype":"venue"
},
  "geometry": {"coordinates":[-85.969414,39.930511],"type":"Point"}
}