{
  "type": "Feature",
  "properties": {
    "iso:country":"US",
    "sg:address":"3004 N Gale St",
    "sg:city":"Indianapolis",
    "sg:classifiers":[
        {
            "category":"Social Services",
            "subcategory":"Child Care",
            "type":"Services"
        }
    ],
    "sg:phone":"+1 317 546 7517",
    "sg:postcode":"46218",
    "sg:province":"IN",
    "wof:name":"Anoited Touch Daycare Ministry",
    "wof:placetype":"venue"
},
  "geometry": {"coordinates":[-86.105917,39.814332],"type":"Point"}
}