{
  "type": "Feature",
  "properties": {
    "iso:country":"US",
    "sg:address":"415 W Marion St",
    "sg:city":"Monticello",
    "sg:classifiers":[
        {
            "category":"Retail",
            "subcategory":"Auto Repair",
            "type":"Services"
        }
    ],
    "sg:phone":"+1 574 583 6398",
    "sg:postcode":"47960",
    "sg:province":"IN",
    "sg:tags":[
        "automotive"
    ],
    "wof:name":"River City Repair",
    "wof:placetype":"venue"
},
  "geometry": {"coordinates":[-86.766432,40.747198],"type":"Point"}
}