{
  "type": "Feature",
  "properties": {
    "iso:country":"US",
    "sg:address":"1204 E Tipton St",
    "sg:city":"Seymour",
    "sg:classifiers":[
        {
            "category":"Professional",
            "subcategory":"Employment Agencies",
            "type":"Services"
        }
    ],
    "sg:phone":"+1 812 524 1804",
    "sg:postcode":"47274",
    "sg:province":"IN",
    "sg:tags":[
        "help",
        "contractor"
    ],
    "wof:name":"Elwood Staffing Svc",
    "wof:placetype":"venue"
},
  "geometry": {"coordinates":[-85.872417,38.958021],"type":"Point"}
}