{
  "type": "Feature",
  "properties": {
    "addr:full":"828 Logan St Noblesville IN 46060",
    "addr:housenumber":"828",
    "addr:postcode":"46060",
    "addr:street":"Logan St",
    "iso:country":"US",
    "sg:address":"828 Logan St",
    "sg:city":"Noblesville",
    "sg:classifiers":[
        {
            "category":"Insurance",
            "subcategory":"Insurance Agent",
            "type":"Services"
        }
    ],
    "sg:phone":"+1 317 773 5455",
    "sg:postcode":"46060",
    "sg:province":"IN",
    "wof:name":"Allstate Insurance",
    "wof:placetype":"venue"
},
  "geometry": {"coordinates":[-86.01375899999999,40.046614],"type":"Point"}
}