{
  "type": "Feature",
  "properties": {
    "iso:country":"US",
    "sg:address":"390 N Madison Ave",
    "sg:city":"Greenwood",
    "sg:classifiers":[
        {
            "category":"Banks & Credit Unions",
            "subcategory":"Investment Brokerage",
            "type":"Services"
        }
    ],
    "sg:phone":"+1 317 884 3899",
    "sg:postcode":"46142",
    "sg:province":"IN",
    "sg:tags":[
        "advisory",
        "financial"
    ],
    "wof:name":"Thrivent Financial-Lutherans",
    "wof:placetype":"venue"
},
  "geometry": {"coordinates":[-86.111786,39.619711],"type":"Point"}
}