{
  "type": "Feature",
  "properties": {
    "addr:full":"2 S 16th St Lafayette IN 47905",
    "addr:housenumber":"2",
    "addr:postcode":"47905",
    "addr:street":"S 16Th St",
    "iso:country":"US",
    "sg:address":"2 S 16th St",
    "sg:city":"Lafayette",
    "sg:classifiers":[
        {
            "category":"Personal",
            "subcategory":"Beauty Salon",
            "type":"Services"
        }
    ],
    "sg:phone":"+1 765 742 4655",
    "sg:postcode":"47905",
    "sg:province":"IN",
    "sg:tags":[
        "manicuring"
    ],
    "wof:name":"Finger Paints Nail Salon",
    "wof:placetype":"venue"
},
  "geometry": {"coordinates":[-86.87864999999999,40.416405],"type":"Point"}
}