{
  "type": "Feature",
  "properties": {
    "addr:full":"9595 Whitley Dr Ste 208 Indianapolis IN 46240",
    "addr:housenumber":"9595",
    "addr:postcode":"46240",
    "addr:street":"Whitley Dr Ste 208",
    "iso:country":"US",
    "sg:address":"9595 Whitley Dr Ste 208",
    "sg:city":"Indianapolis",
    "sg:classifiers":[
        {
            "category":"Building & Trades",
            "subcategory":"Plumbing",
            "type":"Services"
        }
    ],
    "sg:phone":"+1 317 575 9292",
    "sg:postcode":"46240",
    "sg:province":"IN",
    "wof:name":"Ind Association of Plumbing Heating-Colng Cntrctrs",
    "wof:placetype":"venue"
},
  "geometry": {"coordinates":[-86.11509700000001,39.926998],"type":"Point"}
}