{
  "type": "Feature",
  "properties": {
    "iso:country":"US",
    "sg:address":"1201 Washington St",
    "sg:city":"Columbus",
    "sg:classifiers":[
        {
            "category":"Travel",
            "subcategory":"Travel Agent",
            "type":"Entertainment"
        }
    ],
    "sg:phone":"+1 812 376 8966",
    "sg:postcode":"47201",
    "sg:province":"IN",
    "sg:tags":[
        "cruise"
    ],
    "wof:name":"Carlson Wagonlit Travel",
    "wof:placetype":"venue"
},
  "geometry": {"coordinates":[-85.921475,39.210639],"type":"Point"}
}