{
  "type": "Feature",
  "properties": {
    "addr:full":"804 S 575 W Hebron IN 46341",
    "addr:housenumber":"804;575",
    "addr:postcode":"46341",
    "addr:street":"S;W Hebron",
    "iso:country":"US",
    "sg:address":"804 S 575 W",
    "sg:city":"Hebron",
    "sg:classifiers":[
        {
            "category":"Farming",
            "subcategory":"Farm",
            "type":"Manufacturing & Wholesale Goods"
        }
    ],
    "sg:phone":"+1 219 996 3345",
    "sg:postcode":"46341",
    "sg:province":"IN",
    "sg:tags":[
        "crop",
        "general"
    ],
    "wof:name":"Tom Jacobs",
    "wof:placetype":"venue"
},
  "geometry": {"coordinates":[-87.176226,41.317562],"type":"Point"}
}