{
  "type": "Feature",
  "properties": {
    "addr:full":"7430 Madison Ave Indianapolis IN 46227",
    "addr:housenumber":"7430",
    "addr:postcode":"46227",
    "addr:street":"Madison Ave",
    "iso:country":"US",
    "sg:address":"7430 Madison Ave",
    "sg:city":"Indianapolis",
    "sg:classifiers":[
        {
            "category":"Freight",
            "type":"Transportation"
        }
    ],
    "sg:phone":"+1 317 781 9843",
    "sg:postcode":"46227",
    "sg:province":"IN",
    "sg:tags":[
        "commercial",
        "storage"
    ],
    "wof:name":"Public Storage",
    "wof:placetype":"venue"
},
  "geometry": {"coordinates":[-86.125609,39.660669],"type":"Point"}
}