{
  "type": "Feature",
  "properties": {
    "iso:country":"US",
    "sg:address":"8627 Plymouth Goshen Trl",
    "sg:city":"Bremen",
    "sg:classifiers":[
        {
            "category":"Building & Trades",
            "subcategory":"Construction",
            "type":"Services"
        }
    ],
    "sg:phone":"+1 574 936 8879",
    "sg:postcode":"46506",
    "sg:province":"IN",
    "sg:tags":[
        "home",
        "builder"
    ],
    "wof:name":"Higgins Home Management",
    "wof:placetype":"venue"
},
  "geometry": {"coordinates":[-86.22606,41.405859],"type":"Point"}
}