{
  "type": "Feature",
  "properties": {
    "iso:country":"US",
    "sg:address":"1072 Windsor Rd",
    "sg:city":"Terre Haute",
    "sg:classifiers":[
        {
            "category":"Health Services",
            "subcategory":"Clinic",
            "type":"Services"
        }
    ],
    "sg:phone":"+1 812 232 1610",
    "sg:postcode":"47802",
    "sg:province":"IN",
    "sg:tags":[
        "home"
    ],
    "sg:website":"www.intrepidusa.com",
    "wof:name":"Intrepid USA Healthcare Svc",
    "wof:placetype":"venue"
},
  "geometry": {"coordinates":[-87.400919,39.411691],"type":"Point"}
}