{
  "type": "Feature",
  "properties": {
    "iso:country":"US",
    "sg:address":"1826 Georgetown Rd",
    "sg:city":"Indianapolis",
    "sg:classifiers":[
        {
            "category":"Real Estate",
            "subcategory":"Real Estate Operator",
            "type":"Services"
        }
    ],
    "sg:phone":"+1 317 248 1311",
    "sg:postcode":"46224",
    "sg:province":"IN",
    "sg:tags":[
        "mobile",
        "home",
        "community"
    ],
    "wof:name":"Wilcox Mobile Home Park",
    "wof:placetype":"venue"
},
  "geometry": {"coordinates":[-86.239628,39.789657],"type":"Point"}
}