{
  "type": "Feature",
  "properties": {
    "iso:country":"US",
    "sg:address":"456 Berne St",
    "sg:city":"Berne",
    "sg:classifiers":[
        {
            "category":"Retail",
            "subcategory":"Auto Repair",
            "type":"Services"
        }
    ],
    "sg:phone":"+1 260 589 8030",
    "sg:postcode":"46711",
    "sg:province":"IN",
    "sg:tags":[
        "automobile",
        "lubrication"
    ],
    "wof:name":"K & R Auto Care",
    "wof:placetype":"venue"
},
  "geometry": {"coordinates":[-84.945525,40.661558],"type":"Point"}
}