{
  "type": "Feature",
  "properties": {
    "iso:country":"US",
    "sg:address":"2200 W Kilgore Ave",
    "sg:city":"Muncie",
    "sg:classifiers":[
        {
            "category":"Restaurant",
            "type":"Food & Drink"
        }
    ],
    "sg:phone":"+1 765 288 2711",
    "sg:postcode":"47304",
    "sg:province":"IN",
    "wof:name":"Bruner's Family Restaurant",
    "wof:placetype":"venue"
},
  "geometry": {"coordinates":[-85.418928,40.18275],"type":"Point"}
}