{
  "type": "Feature",
  "properties": {
    "iso:country":"US",
    "sg:address":"6848 Hillsdale Ct",
    "sg:city":"Indianapolis",
    "sg:classifiers":[
        {
            "category":"Professional",
            "subcategory":"Engineering",
            "type":"Services"
        }
    ],
    "sg:phone":"+1 317 585 8277",
    "sg:postcode":"46250",
    "sg:province":"IN",
    "sg:tags":[
        "engineer"
    ],
    "wof:name":"CTL Of Indiana",
    "wof:placetype":"venue"
},
  "geometry": {"coordinates":[-86.049656,39.896242],"type":"Point"}
}