{
  "type": "Feature",
  "properties": {
    "iso:country":"US",
    "sg:address":"8935 N Meridian St",
    "sg:city":"Indianapolis",
    "sg:classifiers":[
        {
            "category":"Real Estate",
            "subcategory":"Real Estate Operator",
            "type":"Services"
        }
    ],
    "sg:phone":"+1 317 582 0484",
    "sg:postcode":"46260",
    "sg:province":"IN",
    "sg:tags":[
        "building",
        "parks"
    ],
    "wof:name":"Waterplace Office Park",
    "wof:placetype":"venue"
},
  "geometry": {"coordinates":[-86.157847,39.918039],"type":"Point"}
}