{
  "type": "Feature",
  "properties": {
    "iso:country":"US",
    "sg:address":"5625 N Post Rd",
    "sg:city":"Indianapolis",
    "sg:classifiers":[
        {
            "category":"Banks & Credit Unions",
            "subcategory":"Investment Brokerage",
            "type":"Services"
        },
        {
            "category":"Banks & Credit Unions",
            "subcategory":"Financial Services",
            "type":"Services"
        }
    ],
    "sg:phone":"+1 317 585 6100",
    "sg:postcode":"46216",
    "sg:province":"IN",
    "sg:tags":[
        "management"
    ],
    "wof:name":"316 Investments",
    "wof:placetype":"venue"
},
  "geometry": {"coordinates":[-86.010374,39.855503],"type":"Point"}
}