{
  "type": "Feature",
  "properties": {
    "iso:country":"US",
    "sg:address":"705 N Main St",
    "sg:city":"Kokomo",
    "sg:classifiers":[
        {
            "category":"Building & Trades",
            "subcategory":"Plumbing",
            "type":"Services"
        }
    ],
    "sg:phone":"+1 765 457 9379",
    "sg:postcode":"46901",
    "sg:province":"IN",
    "sg:tags":[
        "conditioning",
        "air",
        "system",
        "contractor"
    ],
    "wof:name":"Thermodyn Inc",
    "wof:placetype":"venue"
},
  "geometry": {"coordinates":[-86.131331,40.492248],"type":"Point"}
}