{
  "type": "Feature",
  "properties": {
    "addr:full":"1800 Churchman Ave # 200 Indianapolis IN 46203",
    "addr:housenumber":"1800",
    "addr:postcode":"46203",
    "addr:street":"Churchman Ave # 200",
    "iso:country":"US",
    "sg:address":"1800 Churchman Ave # 200",
    "sg:city":"Indianapolis",
    "sg:classifiers":[
        {
            "category":"Shopping",
            "subcategory":"Computers & Home Electronics",
            "type":"Retail Goods"
        }
    ],
    "sg:phone":"+1 317 789 9415",
    "sg:postcode":"46203",
    "sg:province":"IN",
    "sg:tags":[
        "equipment",
        "audio-visual"
    ],
    "wof:name":"Advanced Audio And Video",
    "wof:placetype":"venue"
},
  "geometry": {"coordinates":[-86.12357299999999,39.743389],"type":"Point"}
}