{
  "type": "Feature",
  "properties": {
    "addr:full":"1016 US Hwy 27 N Berne IN 46711",
    "addr:housenumber":"1016",
    "addr:postcode":"in 46711",
    "addr:street":"Us Hwy 27 N",
    "iso:country":"US",
    "sg:address":"1016 US Hwy 27 N",
    "sg:city":"Berne",
    "sg:classifiers":[
        {
            "category":"Autos & Motor Vehicles",
            "subcategory":"Auto Supplies",
            "type":"Retail Goods"
        }
    ],
    "sg:phone":"+1 260 589 8219",
    "sg:postcode":"46711",
    "sg:province":"IN",
    "sg:tags":[
        "automobile",
        "parts"
    ],
    "wof:name":"South Adams Motor Parts",
    "wof:placetype":"venue"
},
  "geometry": {"coordinates":[-84.955505,40.666489],"type":"Point"}
}