{
  "type": "Feature",
  "properties": {
    "iso:country":"US",
    "sg:address":"1900 E US Hwy 20",
    "sg:city":"Michigan City",
    "sg:classifiers":[
        {
            "category":"Wholesale",
            "subcategory":"Meat",
            "type":"Manufacturing & Wholesale Goods"
        }
    ],
    "sg:phone":"+1 219 883 5700",
    "sg:postcode":"46360",
    "sg:province":"IN",
    "wof:name":"Evergreen Wholesale",
    "wof:placetype":"venue"
},
  "geometry": {"coordinates":[-86.84965099999999,41.687454],"type":"Point"}
}