{
  "type": "Feature",
  "properties": {
    "addr:full":"101 Eberts Rd Logansport IN 46947",
    "addr:housenumber":"101",
    "addr:postcode":"46947",
    "addr:street":"Eberts Rd",
    "iso:country":"US",
    "sg:address":"101 Eberts Rd",
    "sg:city":"Logansport",
    "sg:classifiers":[
        {
            "category":"Sports & Exercise",
            "subcategory":"Golf",
            "type":"Entertainment"
        }
    ],
    "sg:phone":"+1 574 753 0222",
    "sg:postcode":"46947",
    "sg:province":"IN",
    "sg:tags":[
        "course"
    ],
    "wof:name":"Dykeman Park Golf Course",
    "wof:placetype":"venue"
},
  "geometry": {"coordinates":[-86.382063,40.768108],"type":"Point"}
}