{
  "type": "Feature",
  "properties": {
    "iso:country":"US",
    "sg:address":"701 Wabash Ave",
    "sg:city":"Terre Haute",
    "sg:classifiers":[
        {
            "category":"Insurance",
            "subcategory":"Insurance Agent",
            "type":"Services"
        }
    ],
    "sg:phone":"+1 812 462 7000",
    "sg:postcode":"47807",
    "sg:province":"IN",
    "wof:name":"ONB Insurance",
    "wof:placetype":"venue"
},
  "geometry": {"coordinates":[-87.40573500000001,39.466488],"type":"Point"}
}