{
  "type": "Feature",
  "properties": {
    "iso:country":"US",
    "sg:address":"5126 Ralston Ave",
    "sg:city":"Indianapolis",
    "sg:classifiers":[
        {
            "category":"Shopping",
            "subcategory":"Clothing, Apparel, & Fashions",
            "type":"Retail Goods"
        }
    ],
    "sg:phone":"+1 317 466 0818",
    "sg:postcode":"46205",
    "sg:province":"IN",
    "sg:tags":[
        "item",
        "boutique"
    ],
    "wof:name":"Wizzie Boutique",
    "wof:placetype":"venue"
},
  "geometry": {"coordinates":[-86.131584,39.846984],"type":"Point"}
}