{
  "type": "Feature",
  "properties": {
    "iso:country":"US",
    "sg:address":"1937 N Sparks Ferry Rd",
    "sg:city":"Salem",
    "sg:classifiers":[
        {
            "category":"Professional",
            "subcategory":"Business Services",
            "type":"Services"
        }
    ],
    "sg:phone":"+1 812 883 1534",
    "sg:postcode":"47167",
    "sg:province":"IN",
    "wof:name":"Journell Enterprises Inc",
    "wof:placetype":"venue"
},
  "geometry": {"coordinates":[-86.114555,38.639691],"type":"Point"}
}