{
  "type": "Feature",
  "properties": {
    "iso:country":"US",
    "sg:address":"125 N Green St",
    "sg:city":"Crawfordsville",
    "sg:classifiers":[
        {
            "category":"Bars & Pubs",
            "type":"Food & Drink"
        }
    ],
    "sg:phone":"+1 765 362 5900",
    "sg:postcode":"47933",
    "sg:province":"IN",
    "sg:tags":[
        "club",
        "night"
    ],
    "wof:name":"Showdown Saloon",
    "wof:placetype":"venue"
},
  "geometry": {"coordinates":[-86.89994,40.042608],"type":"Point"}
}