{
  "type": "Feature",
  "properties": {
    "addr:full":"8783 Bono Rd Terre Haute IN 47802",
    "addr:postcode":"8783;47802",
    "addr:street":"Bono Rd",
    "iso:country":"US",
    "sg:address":"8783 Bono Rd",
    "sg:city":"Terre Haute",
    "sg:classifiers":[
        {
            "category":"Real Estate",
            "subcategory":"Real Estate Operator",
            "type":"Services"
        }
    ],
    "sg:phone":"+1 812 299 4723",
    "sg:postcode":"47802",
    "sg:province":"IN",
    "sg:tags":[
        "apartment"
    ],
    "wof:name":"E & R Construction",
    "wof:placetype":"venue"
},
  "geometry": {"coordinates":[-87.38148,39.361229],"type":"Point"}
}