{
  "type": "Feature",
  "properties": {
    "iso:country":"US",
    "sg:address":"6601 Grandview Dr",
    "sg:city":"Indianapolis",
    "sg:classifiers":[
        {
            "category":"Social Services",
            "subcategory":"Child Care",
            "type":"Services"
        }
    ],
    "sg:phone":"+1 317 254 1946",
    "sg:postcode":"46260",
    "sg:province":"IN",
    "wof:name":"Daycare Ministry",
    "wof:placetype":"venue"
},
  "geometry": {"coordinates":[-86.188678,39.88032],"type":"Point"}
}