{
  "type": "Feature",
  "properties": {
    "iso:country":"US",
    "sg:address":"300 Daniels Way",
    "sg:city":"Bloomington",
    "sg:classifiers":[
        {
            "category":"Manufacturing",
            "subcategory":"Rubber & Plastics",
            "type":"Manufacturing & Wholesale Goods"
        }
    ],
    "sg:phone":"+1 812 333 6500",
    "sg:postcode":"47404",
    "sg:province":"IN",
    "sg:tags":[
        "product"
    ],
    "sg:website":"www.tasus.com",
    "wof:name":"Tasus Corp",
    "wof:placetype":"venue"
},
  "geometry": {"coordinates":[-86.599058,39.166607],"type":"Point"}
}