{
  "type": "Feature",
  "properties": {
    "iso:country":"US",
    "sg:address":"604 S Eddy St",
    "sg:city":"South Bend",
    "sg:classifiers":[
        {
            "category":"Health Services",
            "subcategory":"Doctor",
            "type":"Services"
        }
    ],
    "sg:phone":"+1 574 234 1081",
    "sg:postcode":"46615",
    "sg:province":"IN",
    "sg:tags":[
        "dentist"
    ],
    "wof:name":"Julie A Gaydos Plagens DDS",
    "wof:placetype":"venue"
},
  "geometry": {"coordinates":[-86.234789,41.669323],"type":"Point"}
}