{
  "type": "Feature",
  "properties": {
    "iso:country":"US",
    "sg:address":"103 S 1st Ave",
    "sg:city":"Haubstadt",
    "sg:classifiers":[
        {
            "category":"Personal",
            "subcategory":"Beauty Salon",
            "type":"Services"
        }
    ],
    "sg:phone":"+1 812 768 6292",
    "sg:postcode":"47639",
    "sg:province":"IN",
    "wof:name":"Hairizons",
    "wof:placetype":"venue"
},
  "geometry": {"coordinates":[-87.572892,38.205066],"type":"Point"}
}