{
  "type": "Feature",
  "properties": {
    "iso:country":"US",
    "sg:address":"2516 Covington St",
    "sg:city":"West Lafayette",
    "sg:classifiers":[
        {
            "category":"Health Services",
            "subcategory":"Optometrist",
            "type":"Services"
        }
    ],
    "sg:phone":"+1 765 463 4558",
    "sg:postcode":"47906",
    "sg:province":"IN",
    "wof:name":"William R Morton OD",
    "wof:placetype":"venue"
},
  "geometry": {"coordinates":[-86.914169,40.454703],"type":"Point"}
}