{
  "type": "Feature",
  "properties": {
    "iso:country":"US",
    "sg:address":"12103 Hwy 62",
    "sg:city":"Charlestown",
    "sg:classifiers":[
        {
            "category":"Shopping",
            "type":"Retail Goods"
        }
    ],
    "sg:phone":"+1 812 256 6907",
    "sg:postcode":"47111",
    "sg:province":"IN",
    "sg:tags":[
        "monument"
    ],
    "wof:name":"Charlestown Monument Co",
    "wof:placetype":"venue"
},
  "geometry": {"coordinates":[-85.653436,38.445296],"type":"Point"}
}