{
  "type": "Feature",
  "properties": {
    "iso:country":"US",
    "sg:address":"1216 Washington Sq",
    "sg:city":"Evansville",
    "sg:classifiers":[
        {
            "category":"Restaurant",
            "type":"Food & Drink"
        }
    ],
    "sg:phone":"+1 812 473 4606",
    "sg:postcode":"47715",
    "sg:province":"IN",
    "sg:tags":[
        "pizza"
    ],
    "wof:name":"Noble Roman's Inc",
    "wof:placetype":"venue"
},
  "geometry": {"coordinates":[-87.49175700000001,37.964926],"type":"Point"}
}