{
  "type": "Feature",
  "properties": {
    "addr:full":"53048 Paul Dr Elkhart IN 46514",
    "addr:housenumber":"53048",
    "addr:postcode":"46514",
    "addr:street":"Paul Dr",
    "iso:country":"US",
    "sg:address":"53048 Paul Dr",
    "sg:city":"Elkhart",
    "sg:classifiers":[
        {
            "category":"Manufacturing",
            "subcategory":"Printing",
            "type":"Manufacturing & Wholesale Goods"
        }
    ],
    "sg:phone":"+1 574 264 9030",
    "sg:postcode":"46514",
    "sg:province":"IN",
    "sg:tags":[
        "printer"
    ],
    "wof:name":"Label-It",
    "wof:placetype":"venue"
},
  "geometry": {"coordinates":[-86.01966,41.729436],"type":"Point"}
}