{
  "type": "Feature",
  "properties": {
    "iso:country":"US",
    "sg:address":"25 Artist Dr",
    "sg:city":"Nashville",
    "sg:classifiers":[
        {
            "category":"Real Estate",
            "subcategory":"Real Estate Agent",
            "type":"Services"
        }
    ],
    "sg:phone":"+1 812 988 4485",
    "sg:postcode":"47448",
    "sg:province":"IN",
    "sg:website":"www.browncountyremax.com",
    "wof:name":"Re/Max Team",
    "wof:placetype":"venue"
},
  "geometry": {"coordinates":[-86.24295499999999,39.207374],"type":"Point"}
}