{
  "type": "Feature",
  "properties": {
    "iso:country":"US",
    "sg:address":"290 Blacketor Dr",
    "sg:city":"Rochester",
    "sg:classifiers":[
        {
            "category":"Wholesale",
            "subcategory":"Toys & Hobbies",
            "type":"Manufacturing & Wholesale Goods"
        }
    ],
    "sg:phone":"+1 574 223 5420",
    "sg:postcode":"46975",
    "sg:province":"IN",
    "wof:name":"Funds-For-You Inc",
    "wof:placetype":"venue"
},
  "geometry": {"coordinates":[-86.199253,41.073673],"type":"Point"}
}