{
  "type": "Feature",
  "properties": {
    "iso:country":"US",
    "sg:address":"311 N Curry Pike",
    "sg:city":"Bloomington",
    "sg:classifiers":[
        {
            "category":"Retail",
            "subcategory":"Auto Rental",
            "type":"Services"
        }
    ],
    "sg:phone":"+1 812 323 1110",
    "sg:postcode":"47404",
    "sg:province":"IN",
    "sg:tags":[
        "renting",
        "truck",
        "leasing"
    ],
    "sg:website":"www.firstleaseinc.com",
    "wof:name":"Firstlease Inc",
    "wof:placetype":"venue"
},
  "geometry": {"coordinates":[-86.58309199999999,39.173877],"type":"Point"}
}