{
  "type": "Feature",
  "properties": {
    "iso:country":"US",
    "sg:address":"4121 Central Ave",
    "sg:city":"Indianapolis",
    "sg:classifiers":[
        {
            "category":"Professional",
            "subcategory":"Computer Services",
            "type":"Services"
        }
    ],
    "sg:phone":"+1 317 925 7773",
    "sg:postcode":"46205",
    "sg:province":"IN",
    "sg:tags":[
        "technical",
        "assistance",
        "support"
    ],
    "wof:name":"Advant Packaging Solutions Inc",
    "wof:placetype":"venue"
},
  "geometry": {"coordinates":[-86.149809,39.830741],"type":"Point"}
}