{
  "type": "Feature",
  "properties": {
    "addr:full":"4245 Railroad Ave East Chicago IN 46312",
    "addr:housenumber":"4245",
    "addr:postcode":"46312",
    "addr:street":"Railroad Ave",
    "iso:country":"US",
    "sg:address":"4245 Railroad Ave",
    "sg:city":"East Chicago",
    "sg:classifiers":[
        {
            "category":"Building & Trades",
            "subcategory":"Construction",
            "type":"Services"
        }
    ],
    "sg:phone":"+1 219 397 5448",
    "sg:postcode":"46312",
    "sg:province":"IN",
    "sg:tags":[
        "railroad",
        "contractor"
    ],
    "wof:name":"GATX Rail",
    "wof:placetype":"venue"
},
  "geometry": {"coordinates":[-87.47606,41.635957],"type":"Point"}
}