{
  "type": "Feature",
  "properties": {
    "iso:country":"US",
    "sg:address":"15533 State Rd 13",
    "sg:city":"Elwood",
    "sg:classifiers":[
        {
            "category":"Building & Trades",
            "subcategory":"Construction",
            "type":"Services"
        }
    ],
    "sg:phone":"+1 765 552 2228",
    "sg:postcode":"46036",
    "sg:province":"IN",
    "sg:tags":[
        "house"
    ],
    "wof:name":"Pierce Construction",
    "wof:placetype":"venue"
},
  "geometry": {"coordinates":[-85.842634,40.32713],"type":"Point"}
}