{
  "type": "Feature",
  "properties": {
    "iso:country":"US",
    "sg:address":"1804 E 8th St",
    "sg:city":"Anderson",
    "sg:classifiers":[
        {
            "category":"Real Estate",
            "subcategory":"Real Estate Agent",
            "type":"Services"
        }
    ],
    "sg:phone":"+1 765 649 0221",
    "sg:postcode":"46012",
    "sg:province":"IN",
    "wof:name":"Auto Auction Real Estate",
    "wof:placetype":"venue"
},
  "geometry": {"coordinates":[-85.656812,40.107978],"type":"Point"}
}