{
  "type": "Feature",
  "properties": {
    "iso:country":"US",
    "sg:address":"5420 Victory Dr",
    "sg:city":"Indianapolis",
    "sg:classifiers":[
        {
            "category":"Retail",
            "subcategory":"Auto Repair",
            "type":"Services"
        }
    ],
    "sg:phone":"+1 317 791 0688",
    "sg:postcode":"46203",
    "sg:province":"IN",
    "sg:tags":[
        "repairing",
        "automobile"
    ],
    "wof:name":"Car Tech",
    "wof:placetype":"venue"
},
  "geometry": {"coordinates":[-86.071344,39.702232],"type":"Point"}
}