{
  "type": "Feature",
  "properties": {
    "iso:country":"US",
    "sg:address":"456 N Meridian St 44498",
    "sg:city":"Indianapolis",
    "sg:classifiers":[
        {
            "category":"Professional",
            "subcategory":"Management & Consulting",
            "type":"Services"
        },
        {
            "category":"Banks & Credit Unions",
            "subcategory":"Financial Services",
            "type":"Services"
        }
    ],
    "sg:phone":"+1 317 413 5266",
    "sg:postcode":"46204",
    "sg:province":"IN",
    "sg:tags":[
        "consultant",
        "financing",
        "planning"
    ],
    "wof:name":"Sabrina's Fidelity & Banking Financial",
    "wof:placetype":"venue"
},
  "geometry": {"coordinates":[-86.157815,39.773792],"type":"Point"}
}