{
  "type": "Feature",
  "properties": {
    "iso:country":"US",
    "sg:address":"4004 S East St",
    "sg:city":"Indianapolis",
    "sg:classifiers":[
        {
            "category":"Food & Beverages",
            "subcategory":"Groceries & Convenience Stores",
            "type":"Retail Goods"
        }
    ],
    "sg:phone":"+1 317 783 2907",
    "sg:postcode":"46227",
    "sg:province":"IN",
    "sg:tags":[
        "product"
    ],
    "wof:name":"Classic Us Foods",
    "wof:placetype":"venue"
},
  "geometry": {"coordinates":[-86.148972,39.705457],"type":"Point"}
}