{
  "type": "Feature",
  "properties": {
    "iso:country":"US",
    "sg:address":"9190 S 600 E",
    "sg:city":"Saint Paul",
    "sg:classifiers":[
        {
            "category":"Building & Trades",
            "subcategory":"Plumbing",
            "type":"Services"
        }
    ],
    "sg:phone":"+1 765 525 6475",
    "sg:postcode":"47272",
    "sg:province":"IN",
    "sg:tags":[
        "contractor"
    ],
    "wof:name":"McCain Heating & AC",
    "wof:placetype":"venue"
},
  "geometry": {"coordinates":[-85.668622,39.39188],"type":"Point"}
}