{
  "type": "Feature",
  "properties": {
    "iso:country":"US",
    "sg:address":"9102 W Morraine Hills Rd",
    "sg:city":"Michigan City",
    "sg:classifiers":[
        {
            "category":"Real Estate",
            "subcategory":"Real Estate Agent",
            "type":"Services"
        }
    ],
    "sg:phone":"+1 219 879 4724",
    "sg:postcode":"46360",
    "sg:province":"IN",
    "wof:name":"Sunrise Properties Group Inc",
    "wof:placetype":"venue"
},
  "geometry": {"coordinates":[-86.877633,41.636694],"type":"Point"}
}