{
  "type": "Feature",
  "properties": {
    "iso:country":"US",
    "sg:address":"5137 Ralston Ave",
    "sg:city":"Indianapolis",
    "sg:classifiers":[
        {
            "category":"Personal",
            "subcategory":"Beauty Salon",
            "type":"Services"
        }
    ],
    "sg:phone":"+1 317 259 8244",
    "sg:postcode":"46205",
    "sg:province":"IN",
    "wof:name":"Braids",
    "wof:placetype":"venue"
},
  "geometry": {"coordinates":[-86.131431,39.846743],"type":"Point"}
}