{
  "type": "Feature",
  "properties": {
    "iso:country":"US",
    "sg:address":"53 Chigger Hollow Dr",
    "sg:city":"Crawfordsville",
    "sg:classifiers":[
        {
            "category":"Freight",
            "type":"Transportation"
        }
    ],
    "sg:phone":"+1 765 362 4398",
    "sg:postcode":"47933",
    "sg:province":"IN",
    "sg:tags":[
        "operator",
        "local",
        "trucking"
    ],
    "wof:name":"D & J Hauling",
    "wof:placetype":"venue"
},
  "geometry": {"coordinates":[-86.82610099999999,40.012485],"type":"Point"}
}