{
  "type": "Feature",
  "properties": {
    "iso:country":"US",
    "sg:address":"844 Parkway Dr",
    "sg:city":"Bluffton",
    "sg:classifiers":[
        {
            "category":"Insurance",
            "subcategory":"Hazard Insurance",
            "type":"Services"
        }
    ],
    "sg:phone":"+1 260 824 1360",
    "sg:postcode":"46714",
    "sg:province":"IN",
    "sg:tags":[
        "bond"
    ],
    "wof:name":"Addington Bail Bonding",
    "wof:placetype":"venue"
},
  "geometry": {"coordinates":[-85.160146,40.72965],"type":"Point"}
}