{
  "type": "Feature",
  "properties": {
    "iso:country":"US",
    "sg:address":"315 Canal St",
    "sg:city":"Evansville",
    "sg:classifiers":[
        {
            "category":"Education",
            "subcategory":"Special Training",
            "type":"Public Place"
        }
    ],
    "sg:phone":"+1 812 421 0654",
    "sg:postcode":"47713",
    "sg:province":"IN",
    "sg:tags":[
        "center"
    ],
    "wof:name":"Lincoln Erie Headstart",
    "wof:placetype":"venue"
},
  "geometry": {"coordinates":[-87.55987399999999,37.97068],"type":"Point"}
}