{
  "type": "Feature",
  "properties": {
    "iso:country":"US",
    "sg:address":"309 W Washington St",
    "sg:city":"Indianapolis",
    "sg:classifiers":[
        {
            "category":"Real Estate",
            "subcategory":"Real Estate Operator",
            "type":"Services"
        }
    ],
    "sg:phone":"+1 317 638 2969",
    "sg:postcode":"46204",
    "sg:province":"IN",
    "sg:tags":[
        "building",
        "parks"
    ],
    "wof:name":"Fair Building",
    "wof:placetype":"venue"
},
  "geometry": {"coordinates":[-86.16472,39.767149],"type":"Point"}
}