{
  "type": "Feature",
  "properties": {
    "iso:country":"US",
    "sg:address":"211 N Washington St",
    "sg:city":"Crawfordsville",
    "sg:classifiers":[
        {
            "category":"Home & Garden",
            "subcategory":"Furniture",
            "type":"Retail Goods"
        }
    ],
    "sg:phone":"+1 765 362 1540",
    "sg:postcode":"47933",
    "sg:province":"IN",
    "wof:name":"Schloot Furniture Co",
    "wof:placetype":"venue"
},
  "geometry": {"coordinates":[-86.90147,40.043374],"type":"Point"}
}