{
  "type": "Feature",
  "properties": {
    "addr:full":"1600 W Washington St Bluffton IN 46714",
    "addr:housenumber":"1600",
    "addr:postcode":"46714",
    "addr:street":"W Washington St",
    "iso:country":"US",
    "sg:address":"1600 W Washington St",
    "sg:city":"Bluffton",
    "sg:classifiers":[
        {
            "category":"Government",
            "subcategory":"Office",
            "type":"Public Place"
        }
    ],
    "sg:phone":"+1 260 824 6430",
    "sg:postcode":"46714",
    "sg:province":"IN",
    "wof:name":"Wells County Highway Sprvsr",
    "wof:placetype":"venue"
},
  "geometry": {"coordinates":[-85.191665,40.738749],"type":"Point"}
}