{
  "type": "Feature",
  "properties": {
    "iso:country":"US",
    "sg:address":"200 S Van Buren St",
    "sg:city":"Auburn",
    "sg:classifiers":[
        {
            "category":"Banks & Credit Unions",
            "subcategory":"Bank",
            "type":"Services"
        }
    ],
    "sg:phone":"+1 260 925 0960",
    "sg:postcode":"46706",
    "sg:province":"IN",
    "wof:name":"Wells Fargo Bank",
    "wof:placetype":"venue"
},
  "geometry": {"coordinates":[-85.058424,41.366336],"type":"Point"}
}