{
  "type": "Feature",
  "properties": {
    "iso:country":"US",
    "sg:address":"1738 Lincoln Ave",
    "sg:city":"Whiting",
    "sg:classifiers":[
        {
            "category":"Professional",
            "subcategory":"Computer Services",
            "type":"Services"
        }
    ],
    "sg:phone":"+1 219 659 7621",
    "sg:postcode":"46394",
    "sg:province":"IN",
    "sg:tags":[
        "related"
    ],
    "wof:name":"Alacrity Comp Cnsltng Svc",
    "wof:placetype":"venue"
},
  "geometry": {"coordinates":[-87.504515,41.682036],"type":"Point"}
}