{
  "type": "Feature",
  "properties": {
    "addr:full":"1 Eel River Ave Logansport IN 46947",
    "addr:housenumber":"1",
    "addr:postcode":"46947",
    "addr:street":"Eel River Ave",
    "iso:country":"US",
    "sg:address":"1 Eel River Ave",
    "sg:city":"Logansport",
    "sg:classifiers":[
        {
            "category":"Building & Trades",
            "subcategory":"Construction",
            "type":"Services"
        }
    ],
    "sg:phone":"+1 574 753 5959",
    "sg:postcode":"46947",
    "sg:province":"IN",
    "sg:tags":[
        "roofing",
        "contractor"
    ],
    "wof:name":"Werst Inc",
    "wof:placetype":"venue"
},
  "geometry": {"coordinates":[-86.371082,40.751546],"type":"Point"}
}