{
  "type": "Feature",
  "properties": {
    "iso:country":"US",
    "sg:address":"2225 Broadway St",
    "sg:city":"Anderson",
    "sg:classifiers":[
        {
            "category":"Professional",
            "subcategory":"Advertising",
            "type":"Services"
        }
    ],
    "sg:phone":"+1 765 642 2929",
    "sg:postcode":"46012",
    "sg:province":"IN",
    "sg:tags":[
        "distribution"
    ],
    "wof:name":"Fireside Distributors Inc",
    "wof:placetype":"venue"
},
  "geometry": {"coordinates":[-85.677649,40.137977],"type":"Point"}
}