{
  "type": "Feature",
  "properties": {
    "iso:country":"US",
    "sg:address":"5860 E Co Rd 50 S",
    "sg:city":"Fillmore",
    "sg:classifiers":[
        {
            "category":"Farming",
            "subcategory":"Farm",
            "type":"Manufacturing & Wholesale Goods"
        }
    ],
    "sg:phone":"+1 765 246 6293",
    "sg:postcode":"46128",
    "sg:province":"IN",
    "sg:tags":[
        "crop",
        "general"
    ],
    "wof:name":"Gordon Arnold",
    "wof:placetype":"venue"
},
  "geometry": {"coordinates":[-86.74888,39.65249],"type":"Point"}
}