{
  "type": "Feature",
  "properties": {
    "iso:country":"US",
    "sg:address":"6246 Cedar Rd",
    "sg:city":"Bremen",
    "sg:phone":"+1 574 646 2057",
    "sg:postcode":"46506",
    "sg:province":"IN",
    "sg:tags":[
        "farm",
        "corn",
        "soybean"
    ],
    "wof:name":"Unsicker Farms",
    "wof:placetype":"venue"
},
  "geometry": {"coordinates":[-86.097212,41.386665],"type":"Point"}
}