{
  "type": "Feature",
  "properties": {
    "iso:country":"US",
    "sg:address":"721 E 81st Ave",
    "sg:city":"Merrillville",
    "sg:classifiers":[
        {
            "category":"Autos & Motor Vehicles",
            "subcategory":"Fuel & Gas Station",
            "type":"Retail Goods"
        }
    ],
    "sg:phone":"+1 219 769 2117",
    "sg:postcode":"46410",
    "sg:province":"IN",
    "sg:tags":[
        "oil"
    ],
    "wof:name":"Ih 65 Shell",
    "wof:placetype":"venue"
},
  "geometry": {"coordinates":[-87.329599,41.471091],"type":"Point"}
}