{
  "type": "Feature",
  "properties": {
    "iso:country":"US",
    "sg:address":"7702 Woodland Dr",
    "sg:city":"Indianapolis",
    "sg:classifiers":[
        {
            "category":"Banks & Credit Unions",
            "subcategory":"Investment Brokerage",
            "type":"Services"
        }
    ],
    "sg:phone":"+1 317 875 0202",
    "sg:postcode":"46278",
    "sg:province":"IN",
    "sg:tags":[
        "consultant",
        "planning",
        "financial"
    ],
    "wof:name":"Halter Ferguson Financial Inc",
    "wof:placetype":"venue"
},
  "geometry": {"coordinates":[-86.265607,39.890649],"type":"Point"}
}