{
  "type": "Feature",
  "properties": {
    "iso:country":"US",
    "sg:address":"110 Industrial Dr",
    "sg:city":"Edinburgh",
    "sg:classifiers":[
        {
            "category":"Manufacturing",
            "subcategory":"Rubber & Plastics",
            "type":"Manufacturing & Wholesale Goods"
        }
    ],
    "sg:phone":"+1 812 526 0582",
    "sg:postcode":"46131",
    "sg:province":"IN",
    "sg:website":"www.fishingbuckets.com",
    "wof:name":"Challenge Plastic Products Inc",
    "wof:placetype":"venue"
},
  "geometry": {"coordinates":[-86.069647,39.51425],"type":"Point"}
}