{
  "type": "Feature",
  "properties": {
    "iso:country":"US",
    "sg:address":"9182 W State Rd 244",
    "sg:city":"Waldron",
    "sg:classifiers":[
        {
            "category":"Retail",
            "subcategory":"Repair Shop",
            "type":"Services"
        }
    ],
    "sg:phone":"+1 765 525 9400",
    "sg:postcode":"46182",
    "sg:province":"IN",
    "sg:tags":[
        "truck"
    ],
    "wof:name":"Fisher's Garage Rush Co",
    "wof:placetype":"venue"
},
  "geometry": {"coordinates":[-85.61489899999999,39.49751],"type":"Point"}
}