{
  "type": "Feature",
  "properties": {
    "iso:country":"US",
    "sg:address":"11081 S Packerton Rd",
    "sg:city":"Claypool",
    "sg:classifiers":[
        {
            "category":"Freight",
            "type":"Transportation"
        }
    ],
    "sg:phone":"+1 260 839 3392",
    "sg:postcode":"46510",
    "sg:province":"IN",
    "sg:tags":[
        "operator",
        "repair",
        "local",
        "trucking"
    ],
    "wof:name":"Kline Stone & Lime",
    "wof:placetype":"venue"
},
  "geometry": {"coordinates":[-85.796503,41.071451],"type":"Point"}
}