{
  "type": "Feature",
  "properties": {
    "iso:country":"US",
    "sg:address":"45 E 650 N",
    "sg:city":"Attica",
    "sg:classifiers":[
        {
            "category":"Social Services",
            "subcategory":"Job Training",
            "type":"Services"
        }
    ],
    "sg:phone":"+1 765 762 6791",
    "sg:postcode":"47918",
    "sg:province":"IN",
    "sg:tags":[
        "rehabilitation"
    ],
    "wof:name":"Shawnee Center & Workshop",
    "wof:placetype":"venue"
},
  "geometry": {"coordinates":[-87.313215,40.410915],"type":"Point"}
}