{
  "type": "Feature",
  "properties": {
    "addr:full":"19066 Co Rd 46 New Paris IN 46553",
    "addr:housenumber":"19066;46",
    "addr:postcode":"in 46553",
    "addr:street":"Co Rd",
    "iso:country":"US",
    "sg:address":"19066 Co Rd 46",
    "sg:city":"New Paris",
    "sg:classifiers":[
        {
            "category":"Utilities",
            "subcategory":"Cable",
            "type":"Services"
        }
    ],
    "sg:phone":"+1 574 831 2225",
    "sg:postcode":"46553",
    "sg:province":"IN",
    "sg:tags":[
        "television"
    ],
    "wof:name":"Quality Cablevision",
    "wof:placetype":"venue"
},
  "geometry": {"coordinates":[-85.836044,41.500469],"type":"Point"}
}