{
  "type": "Feature",
  "properties": {
    "iso:country":"US",
    "sg:address":"27453 Co Rd 150",
    "sg:city":"Nappanee",
    "sg:classifiers":[
        {
            "category":"Building & Trades",
            "subcategory":"Construction",
            "type":"Services"
        }
    ],
    "sg:phone":"+1 574 773 3502",
    "sg:postcode":"46550",
    "sg:province":"IN",
    "sg:tags":[
        "general",
        "contractor"
    ],
    "wof:name":"R Yoder Construction",
    "wof:placetype":"venue"
},
  "geometry": {"coordinates":[-85.994174,41.46447],"type":"Point"}
}