{
  "type": "Feature",
  "properties": {
    "iso:country":"US",
    "sg:address":"4315 Wyland Dr",
    "sg:city":"Elkhart",
    "sg:classifiers":[
        {
            "category":"Manufacturing",
            "subcategory":"Motor Vehicles & Parts",
            "type":"Manufacturing & Wholesale Goods"
        }
    ],
    "sg:phone":"+1 574 293 1775",
    "sg:postcode":"46516",
    "sg:province":"IN",
    "sg:tags":[
        "home"
    ],
    "wof:name":"Xplorer Motor Home",
    "wof:placetype":"venue"
},
  "geometry": {"coordinates":[-85.902513,41.691889],"type":"Point"}
}