{
  "type": "Feature",
  "properties": {
    "iso:country":"US",
    "sg:address":"6303 English Ave",
    "sg:city":"Indianapolis",
    "sg:classifiers":[
        {
            "category":"Manufacturing",
            "subcategory":"Tools & Machinery",
            "type":"Manufacturing & Wholesale Goods"
        }
    ],
    "sg:phone":"+1 317 356 3556",
    "sg:postcode":"46219",
    "sg:province":"IN",
    "sg:tags":[
        "machine"
    ],
    "wof:name":"Precision Grinding & Shrpng",
    "wof:placetype":"venue"
},
  "geometry": {"coordinates":[-86.05824800000001,39.761033],"type":"Point"}
}