{
  "type": "Feature",
  "properties": {
    "iso:country":"US",
    "sg:address":"5860 N Michigan Rd",
    "sg:city":"Indianapolis",
    "sg:classifiers":[
        {
            "category":"Wholesale",
            "subcategory":"Toys & Hobbies",
            "type":"Manufacturing & Wholesale Goods"
        }
    ],
    "sg:phone":"+1 317 257 9446",
    "sg:postcode":"46228",
    "sg:province":"IN",
    "sg:tags":[
        "firework"
    ],
    "sg:website":"www.celebrationinc.com",
    "wof:name":"Celebration Fireworks",
    "wof:placetype":"venue"
},
  "geometry": {"coordinates":[-86.19789299999999,39.860129],"type":"Point"}
}