{
  "type": "Feature",
  "properties": {
    "addr:full":"3085 W Co Rd 675 N North Vernon IN 47265",
    "addr:housenumber":"3085;675 n",
    "addr:postcode":"47265",
    "addr:street":"W Co Rd",
    "iso:country":"US",
    "sg:address":"3085 W Co Rd 675 N",
    "sg:city":"North Vernon",
    "sg:classifiers":[
        {
            "category":"Farming",
            "subcategory":"Livestock Farm",
            "type":"Manufacturing & Wholesale Goods"
        }
    ],
    "sg:phone":"+1 812 346 8739",
    "sg:postcode":"47265",
    "sg:province":"IN",
    "sg:tags":[
        "general"
    ],
    "wof:name":"Evelin Powers",
    "wof:placetype":"venue"
},
  "geometry": {"coordinates":[-85.622483,39.003109],"type":"Point"}
}