{
  "type": "Feature",
  "properties": {
    "iso:country":"US",
    "sg:address":"4068 E 450 S",
    "sg:city":"St Anthony",
    "sg:classifiers":[
        {
            "category":"Government",
            "subcategory":"Fire Station",
            "type":"Public Place"
        }
    ],
    "sg:phone":"+1 812 326 2208",
    "sg:postcode":"47575",
    "sg:province":"IN",
    "sg:tags":[
        "department"
    ],
    "wof:name":"St Anthony Fire Dept",
    "wof:placetype":"venue"
},
  "geometry": {"coordinates":[-86.827979,38.314633],"type":"Point"}
}