{
  "type": "Feature",
  "properties": {
    "iso:country":"US",
    "sg:address":"6910 N Main St",
    "sg:city":"Granger",
    "sg:classifiers":[
        {
            "category":"Banks & Credit Unions",
            "subcategory":"Bank",
            "type":"Services"
        }
    ],
    "sg:phone":"+1 574 272 0710",
    "sg:postcode":"46530",
    "sg:province":"IN",
    "sg:tags":[
        "loan",
        "real estate"
    ],
    "wof:name":"Seniors Equity Income Inc",
    "wof:placetype":"venue"
},
  "geometry": {"coordinates":[-86.17803000000001,41.722915],"type":"Point"}
}