{
  "type": "Feature",
  "properties": {
    "iso:country":"US",
    "sg:address":"1212 Magnavox Way",
    "sg:city":"Fort Wayne",
    "sg:classifiers":[
        {
            "category":"Personal",
            "subcategory":"Beauty Salon",
            "type":"Services"
        }
    ],
    "sg:phone":"+1 260 459 2217",
    "sg:postcode":"46804",
    "sg:province":"IN",
    "wof:name":"Wine Cellar Hair Design",
    "wof:placetype":"venue"
},
  "geometry": {"coordinates":[-85.221922,41.068065],"type":"Point"}
}