{
  "type": "Feature",
  "properties": {
    "iso:country":"US",
    "sg:address":"245 N Meridian St",
    "sg:city":"Greenwood",
    "sg:classifiers":[
        {
            "category":"Building & Trades",
            "subcategory":"Plumbing",
            "type":"Services"
        }
    ],
    "sg:phone":"+1 317 881 7738",
    "sg:postcode":"46143",
    "sg:province":"IN",
    "sg:tags":[
        "heating",
        "contractor"
    ],
    "wof:name":"Johnson Heating & Cooling Inc",
    "wof:placetype":"venue"
},
  "geometry": {"coordinates":[-86.10632,39.61954],"type":"Point"}
}