{
  "type": "Feature",
  "properties": {
    "iso:country":"US",
    "sg:address":"208 19th St",
    "sg:city":"Columbus",
    "sg:classifiers":[
        {
            "category":"Professional",
            "subcategory":"Business Services",
            "type":"Services"
        }
    ],
    "sg:phone":"+1 812 376 6213",
    "sg:postcode":"47201",
    "sg:province":"IN",
    "wof:name":"Edw Joseph & Associates Inc",
    "wof:placetype":"venue"
},
  "geometry": {"coordinates":[-85.92160800000001,39.217178],"type":"Point"}
}