{
  "type": "Feature",
  "properties": {
    "iso:country":"US",
    "sg:address":"13012 Duval Dr",
    "sg:city":"Fishers",
    "sg:classifiers":[
        {
            "category":"Building & Trades",
            "subcategory":"Construction",
            "type":"Services"
        }
    ],
    "sg:phone":"+1 317 577 0835",
    "sg:postcode":"46037",
    "sg:province":"IN",
    "sg:tags":[
        "contractor"
    ],
    "wof:name":"North American Roofing Systems",
    "wof:placetype":"venue"
},
  "geometry": {"coordinates":[-85.93676000000001,39.965171],"type":"Point"}
}