{
  "type": "Feature",
  "properties": {
    "iso:country":"US",
    "sg:address":"1015 Division St",
    "sg:city":"Goshen",
    "sg:classifiers":[
        {
            "category":"Organizations",
            "subcategory":"Religious Organization",
            "type":"Services"
        }
    ],
    "sg:phone":"+1 574 534 1485",
    "sg:postcode":"46528",
    "sg:province":"IN",
    "sg:tags":[
        "church"
    ],
    "wof:name":"Central District Conference",
    "wof:placetype":"venue"
},
  "geometry": {"coordinates":[-85.848787,41.591486],"type":"Point"}
}