{
  "type": "Feature",
  "properties": {
    "addr:full":"2399 W Jefferson St Plymouth IN 46563",
    "addr:housenumber":"2399",
    "addr:postcode":"46563",
    "addr:street":"W Jefferson St",
    "iso:country":"US",
    "sg:address":"2399 W Jefferson St",
    "sg:city":"Plymouth",
    "sg:classifiers":[
        {
            "category":"Building & Trades",
            "subcategory":"Construction",
            "type":"Services"
        }
    ],
    "sg:phone":"+1 574 936 2140",
    "sg:postcode":"46563",
    "sg:province":"IN",
    "sg:tags":[
        "concrete",
        "pumping"
    ],
    "wof:name":"Concrete Pumping Of Michiana",
    "wof:placetype":"venue"
},
  "geometry": {"coordinates":[-86.33449400000001,41.343622],"type":"Point"}
}