{
  "type": "Feature",
  "properties": {
    "iso:country":"US",
    "sg:address":"6836 Mercedes Ave",
    "sg:city":"Portage",
    "sg:classifiers":[
        {
            "category":"Professional",
            "subcategory":"Management & Consulting",
            "type":"Services"
        }
    ],
    "sg:phone":"+1 219 763 6700",
    "sg:postcode":"46368",
    "sg:province":"IN",
    "wof:name":"Pacific Regent Inc",
    "wof:placetype":"venue"
},
  "geometry": {"coordinates":[-87.149479,41.592125],"type":"Point"}
}