{
  "type": "Feature",
  "properties": {
    "iso:country":"US",
    "sg:address":"275 S State Rd 135",
    "sg:city":"Greenwood",
    "sg:classifiers":[
        {
            "category":"Shopping",
            "subcategory":"Bicycles & Sporting Goods",
            "type":"Retail Goods"
        }
    ],
    "sg:phone":"+1 317 888 3010",
    "sg:postcode":"46142",
    "sg:province":"IN",
    "sg:tags":[
        "equipment",
        "golf",
        "supply"
    ],
    "wof:name":"Pro Golf Distributors-Indiana",
    "wof:placetype":"venue"
},
  "geometry": {"coordinates":[-86.158378,39.612627],"type":"Point"}
}