{
  "type": "Feature",
  "properties": {
    "addr:full":"1018 W 7th St Auburn IN 46706",
    "addr:housenumber":"1018",
    "addr:postcode":"46706",
    "addr:street":"W 7Th St",
    "iso:country":"US",
    "sg:address":"1018 W 7th St",
    "sg:city":"Auburn",
    "sg:classifiers":[
        {
            "category":"Ice Cream",
            "type":"Food & Drink"
        }
    ],
    "sg:menulink":"http://www.allmenus.com/in/union/161546-dairy-queen/menu/",
    "sg:phone":"+1 260 925 1233",
    "sg:postcode":"46706",
    "sg:province":"IN",
    "sg:tags":[
        "burger",
        "american"
    ],
    "wof:name":"Dairy Queen",
    "wof:placetype":"venue"
},
  "geometry": {"coordinates":[-85.068714,41.366749],"type":"Point"}
}