{
  "type": "Feature",
  "properties": {
    "iso:country":"US",
    "sg:address":"3840 N Sherman Dr",
    "sg:city":"Indianapolis",
    "sg:classifiers":[
        {
            "category":"Shopping",
            "subcategory":"Clothing, Apparel, & Fashions",
            "type":"Retail Goods"
        }
    ],
    "sg:phone":"+1 317 547 2223",
    "sg:postcode":"46226",
    "sg:province":"IN",
    "sg:tags":[
        "baby",
        "accessory"
    ],
    "wof:name":"Babe Store",
    "wof:placetype":"venue"
},
  "geometry": {"coordinates":[-86.102804,39.82664],"type":"Point"}
}