{
  "type": "Feature",
  "properties": {
    "iso:country":"US",
    "sg:address":"4415 Indianapolis Blvd",
    "sg:city":"East Chicago",
    "sg:classifiers":[
        {
            "category":"Retail",
            "subcategory":"Car Wash",
            "type":"Services"
        }
    ],
    "sg:phone":"+1 219 378 9274",
    "sg:postcode":"46312",
    "sg:province":"IN",
    "wof:name":"Ec Autospa",
    "wof:placetype":"venue"
},
  "geometry": {"coordinates":[-87.48065699999999,41.633701],"type":"Point"}
}