{
  "type": "Feature",
  "properties": {
    "iso:country":"US",
    "sg:address":"2504 N Co Rd 525 E",
    "sg:city":"Milan",
    "sg:classifiers":[
        {
            "category":"Wholesale",
            "subcategory":"Plants",
            "type":"Manufacturing & Wholesale Goods"
        }
    ],
    "sg:phone":"+1 812 654 2887",
    "sg:postcode":"47031",
    "sg:province":"IN",
    "sg:tags":[
        "nursery",
        "tree"
    ],
    "wof:name":"Henneke Nursery",
    "wof:placetype":"venue"
},
  "geometry": {"coordinates":[-85.164016,39.109119],"type":"Point"}
}