{
  "type": "Feature",
  "properties": {
    "iso:country":"US",
    "sg:address":"480 W 580 N",
    "sg:city":"Crawfordsville",
    "sg:classifiers":[
        {
            "category":"Education",
            "subcategory":"School",
            "type":"Public Place"
        }
    ],
    "sg:phone":"+1 765 359 2112",
    "sg:postcode":"47933",
    "sg:province":"IN",
    "sg:website":"www.nm.k12.in.us",
    "wof:name":"North Montgomery Comm School",
    "wof:placetype":"venue"
},
  "geometry": {"coordinates":[-86.91214600000001,40.123081],"type":"Point"}
}