{
  "type": "Feature",
  "properties": {
    "iso:country":"US",
    "sg:address":"720 Osage St",
    "sg:city":"Fort Wayne",
    "sg:classifiers":[
        {
            "category":"Building & Trades",
            "subcategory":"Landscaping Services",
            "type":"Services"
        }
    ],
    "sg:phone":"+1 260 423 9634",
    "sg:postcode":"46808",
    "sg:province":"IN",
    "sg:tags":[
        "tree"
    ],
    "wof:name":"Asplundh Tree Expert Co",
    "wof:placetype":"venue"
},
  "geometry": {"coordinates":[-85.160809,41.080682],"type":"Point"}
}