{
  "type": "Feature",
  "properties": {
    "iso:country":"US",
    "sg:address":"106 N Detroit St",
    "sg:city":"Lagrange",
    "sg:classifiers":[
        {
            "category":"Shopping",
            "subcategory":"Florist",
            "type":"Retail Goods"
        }
    ],
    "sg:phone":"+1 260 499 3300",
    "sg:postcode":"46761",
    "sg:province":"IN",
    "wof:name":"Country Rose",
    "wof:placetype":"venue"
},
  "geometry": {"coordinates":[-85.417928,41.644367],"type":"Point"}
}