{
  "type": "Feature",
  "properties": {
    "addr:full":"900 Connexion Way Columbia City IN 46725",
    "addr:housenumber":"900",
    "addr:postcode":"46725",
    "addr:street":"Connexion Way",
    "iso:country":"US",
    "sg:address":"900 Connexion Way",
    "sg:city":"Columbia City",
    "sg:classifiers":[
        {
            "category":"Manufacturing",
            "subcategory":"Tools & Machinery",
            "type":"Manufacturing & Wholesale Goods"
        }
    ],
    "sg:phone":"+1 260 244 5193",
    "sg:postcode":"46725",
    "sg:province":"IN",
    "sg:tags":[
        "die",
        "maker"
    ],
    "sg:website":"www.pplastic.com",
    "wof:name":"Columbia Die Mold",
    "wof:placetype":"venue"
},
  "geometry": {"coordinates":[-85.51167700000001,41.170542],"type":"Point"}
}