{
  "type": "Feature",
  "properties": {
    "iso:country":"US",
    "sg:address":"711 Green Ridge Dr",
    "sg:city":"Brownsburg",
    "sg:classifiers":[
        {
            "category":"Real Estate",
            "subcategory":"Real Estate Operator",
            "type":"Services"
        }
    ],
    "sg:phone":"+1 317 852 1400",
    "sg:postcode":"46168",
    "sg:province":"IN",
    "sg:tags":[
        "apartment"
    ],
    "wof:name":"Bay Berry Place Apartments",
    "wof:placetype":"venue"
},
  "geometry": {"coordinates":[-86.425145,39.752895],"type":"Point"}
}