{
  "type": "Feature",
  "properties": {
    "iso:country":"US",
    "sg:address":"5146 Riverview Dr",
    "sg:city":"Indianapolis",
    "sg:classifiers":[
        {
            "category":"Building & Trades",
            "subcategory":"Construction",
            "type":"Services"
        }
    ],
    "sg:phone":"+1 317 257 7724",
    "sg:postcode":"46208",
    "sg:province":"IN",
    "sg:tags":[
        "house"
    ],
    "wof:name":"Brosius Construction",
    "wof:placetype":"venue"
},
  "geometry": {"coordinates":[-86.178524,39.84576],"type":"Point"}
}