{
  "type": "Feature",
  "properties": {
    "iso:country":"US",
    "sg:address":"428 4th St",
    "sg:city":"Aurora",
    "sg:classifiers":[
        {
            "category":"Recreation",
            "type":"Entertainment"
        }
    ],
    "sg:phone":"+1 812 926 0698",
    "sg:postcode":"47001",
    "sg:province":"IN",
    "wof:name":"Creative Stitching",
    "wof:placetype":"venue"
},
  "geometry": {"coordinates":[-84.90235800000001,39.055114],"type":"Point"}
}