{
  "type": "Feature",
  "properties": {
    "iso:country":"US",
    "sg:address":"1148 Lafayette Ave",
    "sg:city":"Terre Haute",
    "sg:classifiers":[
        {
            "category":"Professional",
            "subcategory":"Computer Services",
            "type":"Services"
        }
    ],
    "sg:phone":"+1 812 238 2730",
    "sg:postcode":"47804",
    "sg:province":"IN",
    "sg:tags":[
        "consultant",
        "designer"
    ],
    "wof:name":"Budget PC",
    "wof:placetype":"venue"
},
  "geometry": {"coordinates":[-87.400958,39.488837],"type":"Point"}
}