{
  "type": "Feature",
  "properties": {
    "iso:country":"US",
    "sg:address":"4787 E Noos",
    "sg:city":"Kokomo",
    "sg:classifiers":[
        {
            "category":"Building & Trades",
            "subcategory":"Construction",
            "type":"Services"
        }
    ],
    "sg:phone":"+1 765 452 9589",
    "sg:postcode":"46953",
    "sg:province":"IN",
    "sg:tags":[
        "carpenter"
    ],
    "wof:name":"Concus Carpentry Svc LLC",
    "wof:placetype":"venue"
},
  "geometry": {"coordinates":[-85.59836799999999,40.552961],"type":"Point"}
}