{
  "type": "Feature",
  "properties": {
    "iso:country":"US",
    "sg:address":"2303 W Franklin St",
    "sg:city":"Evansville",
    "sg:classifiers":[
        {
            "category":"Professional",
            "subcategory":"Accounting & Tax Preparation",
            "type":"Services"
        }
    ],
    "sg:phone":"+1 812 423 4533",
    "sg:postcode":"47712",
    "sg:province":"IN",
    "sg:tags":[
        "accountant"
    ],
    "wof:name":"Weinzapfel Roselle",
    "wof:placetype":"venue"
},
  "geometry": {"coordinates":[-87.600505,37.980705],"type":"Point"}
}