{
  "type": "Feature",
  "properties": {
    "iso:country":"US",
    "sg:address":"1100 S Ohio St",
    "sg:city":"Kokomo",
    "sg:classifiers":[
        {
            "category":"Wholesale",
            "subcategory":"Hardware",
            "type":"Manufacturing & Wholesale Goods"
        }
    ],
    "sg:phone":"+1 765 452 5628",
    "sg:postcode":"46902",
    "sg:province":"IN",
    "sg:tags":[
        "parts",
        "refrigerating"
    ],
    "sg:website":"www.duncansupply.com",
    "wof:name":"Duncan Supply Co",
    "wof:placetype":"venue"
},
  "geometry": {"coordinates":[-86.118421,40.475567],"type":"Point"}
}