{
  "type": "Feature",
  "properties": {
    "addr:full":"267 W 80th Pl Merrillville IN 46410",
    "addr:housenumber":"267",
    "addr:postcode":"46410",
    "addr:street":"W 80Th Pl",
    "iso:country":"US",
    "sg:address":"267 W 80th Pl",
    "sg:city":"Merrillville",
    "sg:classifiers":[
        {
            "category":"Health Services",
            "subcategory":"Chiropractor",
            "type":"Services"
        }
    ],
    "sg:phone":"+1 219 769 2222",
    "sg:postcode":"46410",
    "sg:province":"IN",
    "sg:tags":[
        "chiropractic"
    ],
    "wof:name":"Refkin Joseph P",
    "wof:placetype":"venue"
},
  "geometry": {"coordinates":[-87.338847,41.4734],"type":"Point"}
}