{
  "type": "Feature",
  "properties": {
    "iso:country":"US",
    "sg:address":"207 State Rd 131",
    "sg:city":"Clarksville",
    "sg:classifiers":[
        {
            "category":"Banks & Credit Unions",
            "subcategory":"Bank",
            "type":"Services"
        }
    ],
    "sg:phone":"+1 812 949 0400",
    "sg:postcode":"47129",
    "sg:province":"IN",
    "sg:tags":[
        "loan"
    ],
    "wof:name":"Cash Tyme",
    "wof:placetype":"venue"
},
  "geometry": {"coordinates":[-85.776237,38.306019],"type":"Point"}
}