{
  "type": "Feature",
  "properties": {
    "iso:country":"US",
    "sg:address":"2140 Greenfield Ave",
    "sg:city":"Noblesville",
    "sg:classifiers":[
        {
            "category":"Organizations",
            "subcategory":"Religious Organization",
            "type":"Services"
        }
    ],
    "sg:phone":"+1 317 773 4630",
    "sg:postcode":"46060",
    "sg:province":"IN",
    "sg:tags":[
        "church"
    ],
    "sg:website":"www.familypraisecenter.com",
    "wof:name":"Family Praise Ctr",
    "wof:placetype":"venue"
},
  "geometry": {"coordinates":[-86.000336,40.026498],"type":"Point"}
}