{
  "type": "Feature",
  "properties": {
    "iso:country":"US",
    "sg:address":"6415 Debonair Ln",
    "sg:city":"Indianapolis",
    "sg:classifiers":[
        {
            "category":"Travel",
            "subcategory":"Hotels & Motels",
            "type":"Entertainment"
        }
    ],
    "sg:phone":"+1 317 293 6881",
    "sg:postcode":"46224",
    "sg:province":"IN",
    "wof:name":"Red Roof Inn",
    "wof:placetype":"venue"
},
  "geometry": {"coordinates":[-86.273966,39.801604],"type":"Point"}
}