{
  "type": "Feature",
  "properties": {
    "iso:country":"US",
    "sg:address":"370 W Carlisle St",
    "sg:city":"Mooresville",
    "sg:classifiers":[
        {
            "category":"Social Services",
            "type":"Services"
        }
    ],
    "sg:phone":"+1 317 834 2010",
    "sg:postcode":"46158",
    "sg:province":"IN",
    "sg:tags":[
        "counselor",
        "marriage",
        "family"
    ],
    "wof:name":"Transitions Counseling Svc",
    "wof:placetype":"venue"
},
  "geometry": {"coordinates":[-86.381747,39.617514],"type":"Point"}
}