{
  "type": "Feature",
  "properties": {
    "iso:country":"US",
    "sg:address":"1402 E Chicago Ave",
    "sg:city":"East Chicago",
    "sg:classifiers":[
        {
            "category":"Education",
            "subcategory":"School",
            "type":"Public Place"
        }
    ],
    "sg:phone":"+1 219 397 4480",
    "sg:postcode":"46312",
    "sg:province":"IN",
    "wof:name":"American Quality Schools",
    "wof:placetype":"venue"
},
  "geometry": {"coordinates":[-87.45441099999999,41.629286],"type":"Point"}
}