{
  "type": "Feature",
  "properties": {
    "iso:country":"US",
    "sg:address":"708 N College Ave",
    "sg:city":"Salem",
    "sg:classifiers":[
        {
            "category":"Home & Garden",
            "subcategory":"Garden Supply",
            "type":"Retail Goods"
        }
    ],
    "sg:phone":"+1 812 883 5200",
    "sg:postcode":"47167",
    "sg:province":"IN",
    "wof:name":"Persingers Lawn & Garden",
    "wof:placetype":"venue"
},
  "geometry": {"coordinates":[-86.098341,38.612025],"type":"Point"}
}