{
  "type": "Feature",
  "properties": {
    "iso:country":"US",
    "sg:address":"119 State Rd 350",
    "sg:city":"Osgood",
    "sg:classifiers":[
        {
            "category":"Building & Trades",
            "subcategory":"Construction",
            "type":"Services"
        }
    ],
    "sg:phone":"+1 812 689 3011",
    "sg:postcode":"47037",
    "sg:province":"IN",
    "sg:tags":[
        "repairing",
        "house",
        "remodeling",
        "contractor"
    ],
    "wof:name":"Flint's Remodeling",
    "wof:placetype":"venue"
},
  "geometry": {"coordinates":[-85.258493,39.145593],"type":"Point"}
}