{
  "type": "Feature",
  "properties": {
    "addr:full":"7169 State Rd 3 Huntertown IN 46748",
    "addr:housenumber":"7169",
    "addr:postcode":"46748",
    "addr:street":"State Rd 3",
    "iso:country":"US",
    "sg:address":"7169 State Rd 3",
    "sg:city":"Huntertown",
    "sg:classifiers":[
        {
            "category":"Wholesale",
            "subcategory":"Stationery",
            "type":"Manufacturing & Wholesale Goods"
        }
    ],
    "sg:phone":"+1 260 637 8805",
    "sg:postcode":"46748",
    "sg:province":"IN",
    "sg:tags":[
        "product",
        "paper"
    ],
    "wof:name":"Fort Wayne Paper Products",
    "wof:placetype":"venue"
},
  "geometry": {"coordinates":[-85.18933,41.267848],"type":"Point"}
}