{
  "type": "Feature",
  "properties": {
    "iso:country":"US",
    "sg:address":"1047 E State Rd 44",
    "sg:city":"Shelbyville",
    "sg:classifiers":[
        {
            "category":"Restaurant",
            "type":"Food & Drink"
        }
    ],
    "sg:phone":"+1 317 392 1377",
    "sg:postcode":"46176",
    "sg:province":"IN",
    "wof:name":"Long John Silver's",
    "wof:placetype":"venue"
},
  "geometry": {"coordinates":[-85.760784,39.520979],"type":"Point"}
}