{
  "type": "Feature",
  "properties": {
    "addr:full":"221 Timbercrest Rd West Lafayette IN 47906",
    "addr:housenumber":"221",
    "addr:postcode":"47906",
    "addr:street":"Timbercrest Rd",
    "iso:country":"US",
    "sg:address":"221 Timbercrest Rd",
    "sg:city":"West Lafayette",
    "sg:classifiers":[
        {
            "category":"Health Services",
            "subcategory":"Health Practitioner",
            "type":"Services"
        }
    ],
    "sg:phone":"+1 765 743 7879",
    "sg:postcode":"47906",
    "sg:province":"IN",
    "sg:tags":[
        "pathologist",
        "speech"
    ],
    "wof:name":"Brennan Speech Svc",
    "wof:placetype":"venue"
},
  "geometry": {"coordinates":[-87.004013,40.418121],"type":"Point"}
}