{
  "type": "Feature",
  "properties": {
    "iso:country":"US",
    "sg:address":"201 N Indiana St",
    "sg:city":"Roachdale",
    "sg:classifiers":[
        {
            "category":"Personal",
            "subcategory":"Beauty Salon",
            "type":"Services"
        }
    ],
    "sg:phone":"+1 765 522 1607",
    "sg:postcode":"46172",
    "sg:province":"IN",
    "wof:name":"Niks-N-Cuts",
    "wof:placetype":"venue"
},
  "geometry": {"coordinates":[-86.802279,39.853037],"type":"Point"}
}