{
  "type": "Feature",
  "properties": {
    "iso:country":"US",
    "sg:address":"3645 Broadway",
    "sg:city":"Gary",
    "sg:classifiers":[
        {
            "category":"Organizations",
            "subcategory":"Membership Organization",
            "type":"Services"
        }
    ],
    "sg:phone":"+1 219 884 5602",
    "sg:postcode":"46409",
    "sg:province":"IN",
    "wof:name":"Cloud Pink Sex Kittens",
    "wof:placetype":"venue"
},
  "geometry": {"coordinates":[-87.33647,41.552093],"type":"Point"}
}