{
  "type": "Feature",
  "properties": {
    "iso:country":"US",
    "sg:address":"5765 Cantigny Way S",
    "sg:city":"Carmel",
    "sg:classifiers":[
        {
            "category":"Professional",
            "subcategory":"Management & Consulting",
            "type":"Services"
        }
    ],
    "sg:phone":"+1 317 574 9096",
    "sg:postcode":"46033",
    "sg:province":"IN",
    "sg:tags":[
        "business"
    ],
    "wof:name":"McMan International Inc",
    "wof:placetype":"venue"
},
  "geometry": {"coordinates":[-86.058829,39.976088],"type":"Point"}
}