{
  "type": "Feature",
  "properties": {
    "iso:country":"US",
    "sg:address":"1920 Clark St",
    "sg:city":"Whiting",
    "sg:classifiers":[
        {
            "category":"Organizations",
            "subcategory":"Religious Organization",
            "type":"Services"
        }
    ],
    "sg:phone":"+1 219 659 3773",
    "sg:postcode":"46394",
    "sg:province":"IN",
    "sg:tags":[
        "church"
    ],
    "wof:name":"Whiting United Methodist",
    "wof:placetype":"venue"
},
  "geometry": {"coordinates":[-87.496109,41.678603],"type":"Point"}
}