{
  "type": "Feature",
  "properties": {
    "addr:full":"1220 Edsall Ave Fort Wayne IN 46803",
    "addr:housenumber":"1220",
    "addr:postcode":"46803",
    "addr:street":"Edsall Ave",
    "iso:country":"US",
    "sg:address":"1220 Edsall Ave",
    "sg:city":"Fort Wayne",
    "sg:classifiers":[
        {
            "category":"Retail",
            "subcategory":"Laundry & Dry Cleaning",
            "type":"Services"
        }
    ],
    "sg:phone":"+1 260 422 7447",
    "sg:postcode":"46803",
    "sg:province":"IN",
    "sg:tags":[
        "cleaners",
        "rug",
        "carpet"
    ],
    "sg:website":"www.steamatic.com",
    "wof:name":"Steamatic Inc",
    "wof:placetype":"venue"
},
  "geometry": {"coordinates":[-85.099569,41.075786],"type":"Point"}
}