{
  "type": "Feature",
  "properties": {
    "iso:country":"US",
    "sg:address":"785 State St",
    "sg:city":"Franklin",
    "sg:classifiers":[
        {
            "category":"Building & Trades",
            "subcategory":"Construction",
            "type":"Services"
        }
    ],
    "sg:phone":"+1 317 736 6024",
    "sg:postcode":"46131",
    "sg:province":"IN",
    "sg:tags":[
        "bridge",
        "builder"
    ],
    "wof:name":"Duncan Robertson Inc",
    "wof:placetype":"venue"
},
  "geometry": {"coordinates":[-86.044057,39.4724],"type":"Point"}
}