{
  "type": "Feature",
  "properties": {
    "iso:country":"US",
    "sg:address":"11693 Fall Creek Rd",
    "sg:city":"Indianapolis",
    "sg:classifiers":[
        {
            "category":"Retail",
            "subcategory":"Laundry & Dry Cleaning",
            "type":"Services"
        }
    ],
    "sg:phone":"+1 317 594 8996",
    "sg:postcode":"46256",
    "sg:province":"IN",
    "sg:tags":[
        "cleaners"
    ],
    "wof:name":"Martinizing",
    "wof:placetype":"venue"
},
  "geometry": {"coordinates":[-85.95938599999999,39.932708],"type":"Point"}
}