{
  "type": "Feature",
  "properties": {
    "iso:country":"US",
    "sg:address":"8250 Woodfield Xing Blvd",
    "sg:city":"Indianapolis",
    "sg:classifiers":[
        {
            "category":"Banks & Credit Unions",
            "subcategory":"Financial Services",
            "type":"Services"
        }
    ],
    "sg:phone":"+1 317 469 1000",
    "sg:postcode":"46240",
    "sg:province":"IN",
    "sg:tags":[
        "broker",
        "mortgage"
    ],
    "wof:name":"Hartland Security Mortgage",
    "wof:placetype":"venue"
},
  "geometry": {"coordinates":[-86.118599,39.9077],"type":"Point"}
}