{
  "type": "Feature",
  "properties": {
    "iso:country":"US",
    "sg:address":"1500 S Keystone Ave",
    "sg:city":"Indianapolis",
    "sg:classifiers":[
        {
            "category":"Retail",
            "subcategory":"Auto Repair",
            "type":"Services"
        }
    ],
    "sg:phone":"+1 317 782 8869",
    "sg:postcode":"46203",
    "sg:province":"IN",
    "sg:tags":[
        "wrecker"
    ],
    "wof:name":"Metro Towing",
    "wof:placetype":"venue"
},
  "geometry": {"coordinates":[-86.121157,39.746936],"type":"Point"}
}