{
  "type": "Feature",
  "properties": {
    "addr:full":"3703 S Main St Elkhart IN 46517",
    "addr:housenumber":"3703",
    "addr:postcode":"46517",
    "addr:street":"S Main St",
    "iso:country":"US",
    "sg:address":"3703 S Main St",
    "sg:city":"Elkhart",
    "sg:classifiers":[
        {
            "category":"Retail",
            "subcategory":"Auto Repair",
            "type":"Services"
        }
    ],
    "sg:phone":"+1 574 875 5146",
    "sg:postcode":"46517",
    "sg:province":"IN",
    "sg:tags":[
        "repairing",
        "automobile"
    ],
    "wof:name":"Tuffy Auto Svc Ctr",
    "wof:placetype":"venue"
},
  "geometry": {"coordinates":[-85.928049,41.64222],"type":"Point"}
}