{
  "type": "Feature",
  "properties": {
    "iso:country":"US",
    "sg:address":"1825 Jefferson Dr W",
    "sg:city":"Carmel",
    "sg:classifiers":[
        {
            "category":"Real Estate",
            "subcategory":"Real Estate Operator",
            "type":"Services"
        }
    ],
    "sg:phone":"+1 317 846 4227",
    "sg:postcode":"46032",
    "sg:province":"IN",
    "sg:tags":[
        "apartment"
    ],
    "wof:name":"Governor Square",
    "wof:placetype":"venue"
},
  "geometry": {"coordinates":[-86.12191,39.957043],"type":"Point"}
}