{
  "type": "Feature",
  "properties": {
    "iso:country":"US",
    "sg:address":"9421 Holliday Dr",
    "sg:city":"Indianapolis",
    "sg:classifiers":[
        {
            "category":"Communications",
            "subcategory":"Radio Station",
            "type":"Services"
        }
    ],
    "sg:phone":"+1 317 844 7502",
    "sg:postcode":"46260",
    "sg:province":"IN",
    "sg:tags":[
        "company",
        "broadcasting"
    ],
    "wof:name":"Alliance Broadcasting Inc",
    "wof:placetype":"venue"
},
  "geometry": {"coordinates":[-86.16326599999999,39.924708],"type":"Point"}
}