{
  "type": "Feature",
  "properties": {
    "iso:country":"US",
    "sg:address":"2200 Scott St",
    "sg:city":"Lafayette",
    "sg:classifiers":[
        {
            "category":"Professional",
            "type":"Services"
        }
    ],
    "sg:phone":"+1 765 449 7004",
    "sg:postcode":"47904",
    "sg:province":"IN",
    "sg:tags":[
        "establishment"
    ],
    "wof:name":"Hutchison Institute",
    "wof:placetype":"venue"
},
  "geometry": {"coordinates":[-86.86912599999999,40.417448],"type":"Point"}
}