{
  "type": "Feature",
  "properties": {
    "iso:country":"US",
    "sg:address":"931 N Southland Dr",
    "sg:city":"Lafayette",
    "sg:classifiers":[
        {
            "category":"Retail",
            "subcategory":"Portrait Studio",
            "type":"Services"
        }
    ],
    "sg:phone":"+1 765 477 2153",
    "sg:postcode":"47909",
    "sg:province":"IN",
    "sg:tags":[
        "photography"
    ],
    "wof:name":"Mc Greevy-Marks Photography",
    "wof:placetype":"venue"
},
  "geometry": {"coordinates":[-86.883348,40.378904],"type":"Point"}
}