{
  "type": "Feature",
  "properties": {
    "iso:country":"US",
    "sg:address":"14101 Saltwell Rd",
    "sg:city":"Brookville",
    "sg:classifiers":[
        {
            "category":"Manufacturing",
            "subcategory":"Buildings",
            "type":"Manufacturing & Wholesale Goods"
        }
    ],
    "sg:phone":"+1 765 647 5329",
    "sg:postcode":"47012",
    "sg:province":"IN",
    "sg:tags":[
        "home",
        "log",
        "cabin"
    ],
    "wof:name":"Dennis Ward Construction",
    "wof:placetype":"venue"
},
  "geometry": {"coordinates":[-85.022996,39.504955],"type":"Point"}
}