{
  "type": "Feature",
  "properties": {
    "iso:country":"US",
    "sg:address":"5428 N Keystone Ave",
    "sg:city":"Indianapolis",
    "sg:classifiers":[
        {
            "category":"Building & Trades",
            "subcategory":"Construction",
            "type":"Services"
        }
    ],
    "sg:phone":"+1 317 254 8145",
    "sg:postcode":"46220",
    "sg:province":"IN",
    "sg:tags":[
        "fire",
        "restoration",
        "damage"
    ],
    "wof:name":"S L & N Corp",
    "wof:placetype":"venue"
},
  "geometry": {"coordinates":[-86.122158,39.852284],"type":"Point"}
}