{
  "type": "Feature",
  "properties": {
    "addr:full":"2500 S High School Rd Indianapolis IN 46241",
    "addr:housenumber":"2500",
    "addr:postcode":"46241",
    "addr:street":"S High School Rd",
    "iso:country":"US",
    "sg:address":"2500 S High School Rd",
    "sg:city":"Indianapolis",
    "sg:classifiers":[
        {
            "category":"Fast Food",
            "type":"Food & Drink"
        },
        {
            "category":"Coffee & Tea",
            "type":"Food & Drink"
        },
        {
            "category":"Restaurant",
            "type":"Food & Drink"
        },
        {
            "category":"Bakery",
            "type":"Food & Drink"
        },
        {
            "category":"Food & Beverages",
            "subcategory":"Groceries & Convenience Stores",
            "type":"Retail Goods"
        }
    ],
    "sg:phone":"+1 317 244 9641",
    "sg:postcode":"46241",
    "sg:province":"IN",
    "sg:tags":[
        "shop",
        "american",
        "sandwich",
        "espresso",
        "take"
    ],
    "sg:website":"http://www.aubonpain.com",
    "wof:name":"Au Bon Pain",
    "wof:placetype":"venue"
},
  "geometry": {"coordinates":[-86.26989,39.729931],"type":"Point"}
}