{
  "type": "Feature",
  "properties": {
    "iso:country":"US",
    "sg:address":"1331 US Hwy 27 N",
    "sg:city":"Berne",
    "sg:classifiers":[
        {
            "category":"Wholesale",
            "subcategory":"Furniture",
            "type":"Manufacturing & Wholesale Goods"
        }
    ],
    "sg:phone":"+1 260 589 8324",
    "sg:postcode":"46711",
    "sg:province":"IN",
    "wof:name":"Bernhaus Furniture",
    "wof:placetype":"venue"
},
  "geometry": {"coordinates":[-84.955533,40.669774],"type":"Point"}
}