{
  "type": "Feature",
  "properties": {
    "iso:country":"US",
    "sg:address":"586 S State Rd 135",
    "sg:city":"Greenwood",
    "sg:classifiers":[
        {
            "category":"Insurance",
            "subcategory":"Insurance Agent",
            "type":"Services"
        }
    ],
    "sg:phone":"+1 317 888 0101",
    "sg:postcode":"46142",
    "sg:province":"IN",
    "wof:name":"State Farm Insurance",
    "wof:placetype":"venue"
},
  "geometry": {"coordinates":[-86.15865100000001,39.607721],"type":"Point"}
}