{
  "type": "Feature",
  "properties": {
    "iso:country":"US",
    "sg:address":"7710 Evanwood Ct",
    "sg:city":"Fort Wayne",
    "sg:classifiers":[
        {
            "category":"Personal",
            "subcategory":"Beauty Salon",
            "type":"Services"
        }
    ],
    "sg:phone":"+1 260 447 7625",
    "sg:postcode":"46816",
    "sg:province":"IN",
    "sg:tags":[
        "shop"
    ],
    "wof:name":"Village People Hair Designers",
    "wof:placetype":"venue"
},
  "geometry": {"coordinates":[-85.09877,41.016092],"type":"Point"}
}