{
  "type": "Feature",
  "properties": {
    "iso:country":"US",
    "sg:address":"1817 Perkins St",
    "sg:city":"Elkhart",
    "sg:classifiers":[
        {
            "category":"Freight",
            "type":"Transportation"
        }
    ],
    "sg:phone":"+1 574 295 8052",
    "sg:postcode":"46516",
    "sg:province":"IN",
    "sg:tags":[
        "hauling",
        "trucking"
    ],
    "wof:name":"Willis Trash Removal",
    "wof:placetype":"venue"
},
  "geometry": {"coordinates":[-85.943348,41.663051],"type":"Point"}
}