{
  "type": "Feature",
  "properties": {
    "addr:full":"711 E Cleveland Ave Hobart IN 46342",
    "addr:housenumber":"711",
    "addr:postcode":"46342",
    "addr:street":"E Cleveland Ave",
    "iso:country":"US",
    "sg:address":"711 E Cleveland Ave",
    "sg:city":"Hobart",
    "sg:classifiers":[
        {
            "category":"Professional",
            "subcategory":"Computer Services",
            "type":"Services"
        }
    ],
    "sg:phone":"+1 219 947 7086",
    "sg:postcode":"46342",
    "sg:province":"IN",
    "sg:tags":[
        "consultant",
        "designer"
    ],
    "sg:website":"www.act2001.com",
    "wof:name":"Applied Computer Techniques",
    "wof:placetype":"venue"
},
  "geometry": {"coordinates":[-87.25094900000001,41.536152],"type":"Point"}
}