{
  "type": "Feature",
  "properties": {
    "iso:country":"US",
    "sg:address":"3001 Dickey Rd",
    "sg:city":"East Chicago",
    "sg:classifiers":[
        {
            "category":"Manufacturing",
            "subcategory":"Building Materials",
            "type":"Manufacturing & Wholesale Goods"
        }
    ],
    "sg:phone":"+1 219 398 0417",
    "sg:postcode":"46312",
    "sg:province":"IN",
    "wof:name":"International Mills Svc",
    "wof:placetype":"venue"
},
  "geometry": {"coordinates":[-87.464412,41.658803],"type":"Point"}
}