{
  "type": "Feature",
  "properties": {
    "iso:country":"US",
    "sg:address":"312 Fairbanks Pl",
    "sg:city":"Munster",
    "sg:classifiers":[
        {
            "category":"Personal",
            "subcategory":"Beauty Salon",
            "type":"Services"
        },
        {
            "category":"Personal",
            "subcategory":"Skin Care",
            "type":"Services"
        }
    ],
    "sg:phone":"+1 219 836 5148",
    "sg:postcode":"46321",
    "sg:province":"IN",
    "sg:tags":[
        "cosmetologist",
        "cosmetic"
    ],
    "wof:name":"Susanne K Kooy",
    "wof:placetype":"venue"
},
  "geometry": {"coordinates":[-87.52025,41.572021],"type":"Point"}
}