{
  "type": "Feature",
  "properties": {
    "iso:country":"US",
    "sg:address":"109 Navarre Ct",
    "sg:city":"Auburn",
    "sg:classifiers":[
        {
            "category":"Autos & Motor Vehicles",
            "subcategory":"Automobile Sales",
            "type":"Retail Goods"
        }
    ],
    "sg:phone":"+1 260 925 4161",
    "sg:postcode":"46706",
    "sg:province":"IN",
    "sg:tags":[
        "car",
        "dealer"
    ],
    "wof:name":"Shull Auto Sales",
    "wof:placetype":"venue"
},
  "geometry": {"coordinates":[-85.04026,41.362207],"type":"Point"}
}