{
  "type": "Feature",
  "properties": {
    "iso:country":"US",
    "sg:address":"6010 Armstrong Rd",
    "sg:city":"Evansville",
    "sg:classifiers":[
        {
            "category":"Home & Garden",
            "subcategory":"Furniture",
            "type":"Retail Goods"
        }
    ],
    "sg:phone":"+1 812 963 3428",
    "sg:postcode":"47720",
    "sg:province":"IN",
    "sg:tags":[
        "store"
    ],
    "wof:name":"Plastisol Furniture",
    "wof:placetype":"venue"
},
  "geometry": {"coordinates":[-87.643635,38.10922],"type":"Point"}
}