{
  "type": "Feature",
  "properties": {
    "iso:country":"US",
    "sg:address":"1185 N Gardner St",
    "sg:city":"Scottsburg",
    "sg:classifiers":[
        {
            "category":"Professional",
            "type":"Services"
        }
    ],
    "sg:phone":"+1 812 752 7578",
    "sg:postcode":"47170",
    "sg:province":"IN",
    "sg:tags":[
        "establishment"
    ],
    "wof:name":"Marie's Gone Country Western",
    "wof:placetype":"venue"
},
  "geometry": {"coordinates":[-85.784816,38.702834],"type":"Point"}
}