{
  "type": "Feature",
  "properties": {
    "iso:country":"US",
    "sg:address":"9709 E Washington St",
    "sg:city":"Indianapolis",
    "sg:classifiers":[
        {
            "category":"Wholesale",
            "subcategory":"Machinery & Supplies",
            "type":"Manufacturing & Wholesale Goods"
        }
    ],
    "sg:phone":"+1 317 897 3399",
    "sg:postcode":"46229",
    "sg:province":"IN",
    "sg:tags":[
        "salon",
        "beauty"
    ],
    "wof:name":"Sally Beauty Supply",
    "wof:placetype":"venue"
},
  "geometry": {"coordinates":[-85.992964,39.77464],"type":"Point"}
}