{
  "type": "Feature",
  "properties": {
    "iso:country":"US",
    "sg:address":"51677 Highland Shores Dr",
    "sg:city":"Granger",
    "sg:classifiers":[
        {
            "category":"Retail",
            "subcategory":"Auto Repair",
            "type":"Services"
        }
    ],
    "sg:phone":"+1 574 277 8071",
    "sg:postcode":"46530",
    "sg:province":"IN",
    "sg:tags":[
        "transmission"
    ],
    "wof:name":"Dodge Power Systems",
    "wof:placetype":"venue"
},
  "geometry": {"coordinates":[-86.18277399999999,41.744324],"type":"Point"}
}