{
  "type": "Feature",
  "properties": {
    "addr:full":"538 S Bell St Sullivan IN 47882",
    "addr:housenumber":"538",
    "addr:postcode":"47882",
    "addr:street":"S Bell St",
    "iso:country":"US",
    "sg:address":"538 S Bell St",
    "sg:city":"Sullivan",
    "sg:classifiers":[
        {
            "category":"Professional",
            "type":"Services"
        }
    ],
    "sg:phone":"+1 812 268 6419",
    "sg:postcode":"47882",
    "sg:province":"IN",
    "sg:tags":[
        "establishment"
    ],
    "wof:name":"Four Rivers",
    "wof:placetype":"venue"
},
  "geometry": {"coordinates":[-87.414681,39.087298],"type":"Point"}
}