{
  "type": "Feature",
  "properties": {
    "iso:country":"US",
    "sg:address":"1640 E Main St",
    "sg:city":"Griffith",
    "sg:classifiers":[
        {
            "category":"Manufacturing",
            "subcategory":"Metals",
            "type":"Manufacturing & Wholesale Goods"
        }
    ],
    "sg:phone":"+1 219 934 8500",
    "sg:postcode":"46319",
    "sg:province":"IN",
    "sg:tags":[
        "steel"
    ],
    "wof:name":"Omega Steel & Contractor Supl",
    "wof:placetype":"venue"
},
  "geometry": {"coordinates":[-87.396049,41.522697],"type":"Point"}
}