{
  "type": "Feature",
  "properties": {
    "iso:country":"US",
    "sg:address":"9700 US Hwy 35",
    "sg:city":"Losantville",
    "sg:classifiers":[
        {
            "category":"Banks & Credit Unions",
            "subcategory":"Bank",
            "type":"Services"
        }
    ],
    "sg:phone":"+1 765 853 5471",
    "sg:postcode":"47354",
    "sg:province":"IN",
    "wof:name":"Old National Bank",
    "wof:placetype":"venue"
},
  "geometry": {"coordinates":[-85.189593,40.023111],"type":"Point"}
}