{
  "type": "Feature",
  "properties": {
    "iso:country":"US",
    "sg:address":"5155 N Shadeland Ave",
    "sg:city":"Indianapolis",
    "sg:classifiers":[
        {
            "category":"Insurance",
            "subcategory":"Insurance Agent",
            "type":"Services"
        }
    ],
    "sg:phone":"+1 317 542 7211",
    "sg:postcode":"46226",
    "sg:province":"IN",
    "sg:tags":[
        "processing"
    ],
    "wof:name":"MOST",
    "wof:placetype":"venue"
},
  "geometry": {"coordinates":[-86.04608399999999,39.846608],"type":"Point"}
}