{
  "type": "Feature",
  "properties": {
    "iso:country":"US",
    "sg:address":"3337 Robson St",
    "sg:city":"Indianapolis",
    "sg:classifiers":[
        {
            "category":"Personal",
            "subcategory":"Beauty Salon",
            "type":"Services"
        }
    ],
    "sg:phone":"+1 317 635 8637",
    "sg:postcode":"46201",
    "sg:province":"IN",
    "wof:name":"Black & Beauty",
    "wof:placetype":"venue"
},
  "geometry": {"coordinates":[-86.108019,39.773674],"type":"Point"}
}