{
  "type": "Feature",
  "properties": {
    "addr:full":"1015 Eastern Blvd Clarksville IN 47129",
    "addr:housenumber":"1015",
    "addr:postcode":"47129",
    "addr:street":"Eastern Blvd",
    "iso:country":"US",
    "sg:address":"1015 Eastern Blvd",
    "sg:city":"Clarksville",
    "sg:classifiers":[
        {
            "category":"Restaurant",
            "type":"Food & Drink"
        }
    ],
    "sg:phone":"+1 812 258 0254",
    "sg:postcode":"47129",
    "sg:province":"IN",
    "wof:name":"Taqueria",
    "wof:placetype":"venue"
},
  "geometry": {"coordinates":[-85.764634,38.30284],"type":"Point"}
}