{
  "type": "Feature",
  "properties": {
    "addr:full":"1800 N Capitol Ave Indianapolis IN 46202",
    "addr:housenumber":"1800",
    "addr:postcode":"46202",
    "addr:street":"N Capitol Ave",
    "iso:country":"US",
    "sg:address":"1800 N Capitol Ave",
    "sg:city":"Indianapolis",
    "sg:classifiers":[
        {
            "category":"Professional",
            "type":"Services"
        }
    ],
    "sg:phone":"+1 317 962 0555",
    "sg:postcode":"46202",
    "sg:province":"IN",
    "sg:tags":[
        "lecturer"
    ],
    "wof:name":"Indiana Cardiac",
    "wof:placetype":"venue"
},
  "geometry": {"coordinates":[-86.161485,39.791914],"type":"Point"}
}