{
  "type": "Feature",
  "properties": {
    "iso:country":"US",
    "sg:address":"717 S Grand Ave",
    "sg:city":"Indianapolis",
    "sg:classifiers":[
        {
            "category":"Manufacturing",
            "subcategory":"Pet Food",
            "type":"Manufacturing & Wholesale Goods"
        },
        {
            "category":"Ice Cream",
            "type":"Food & Drink"
        }
    ],
    "sg:phone":"+1 317 357 4917",
    "sg:postcode":"46219",
    "sg:province":"IN",
    "sg:tags":[
        "ice-wholesale",
        "manufacturer"
    ],
    "wof:name":"Clear Cube Ice Co",
    "wof:placetype":"venue"
},
  "geometry": {"coordinates":[-86.08144,39.757719],"type":"Point"}
}