{
  "type": "Feature",
  "properties": {
    "iso:country":"US",
    "sg:address":"1421 S Holt Rd",
    "sg:city":"Indianapolis",
    "sg:classifiers":[
        {
            "category":"Manufacturing",
            "subcategory":"Tools & Machinery",
            "type":"Manufacturing & Wholesale Goods"
        }
    ],
    "sg:phone":"+1 317 241 9903",
    "sg:postcode":"46241",
    "sg:province":"IN",
    "sg:tags":[
        "machine",
        "shop"
    ],
    "wof:name":"Mercer Machine Co",
    "wof:placetype":"venue"
},
  "geometry": {"coordinates":[-86.225168,39.745826],"type":"Point"}
}