{
  "type": "Feature",
  "properties": {
    "addr:full":"8355 W Co Rd 350 N Greencastle IN 46135",
    "addr:housenumber":"8355;350",
    "addr:postcode":"46135",
    "addr:street":"W Co Rd;N Greencastle",
    "iso:country":"US",
    "sg:address":"8355 W Co Rd 350 N",
    "sg:city":"Greencastle",
    "sg:phone":"+1 765 739 6316",
    "sg:postcode":"46135",
    "sg:province":"IN",
    "sg:tags":[
        "farm",
        "corn",
        "soybean"
    ],
    "wof:name":"Louis Ridgway",
    "wof:placetype":"venue"
},
  "geometry": {"coordinates":[-87.010259,39.713523],"type":"Point"}
}