{
  "type": "Feature",
  "properties": {
    "addr:full":"3103 Cannongate Dr Fort Wayne IN 46808",
    "addr:housenumber":"3103",
    "addr:postcode":"46808",
    "addr:street":"Cannongate Dr",
    "iso:country":"US",
    "sg:address":"3103 Cannongate Dr",
    "sg:city":"Fort Wayne",
    "sg:classifiers":[
        {
            "category":"Professional",
            "subcategory":"Business Services",
            "type":"Services"
        }
    ],
    "sg:phone":"+1 260 471 1436",
    "sg:postcode":"46808",
    "sg:province":"IN",
    "sg:tags":[
        "inspection"
    ],
    "sg:website":"www.preferredsourcing.com",
    "wof:name":"Preferred Sourcing Inc",
    "wof:placetype":"venue"
},
  "geometry": {"coordinates":[-85.18244300000001,41.104795],"type":"Point"}
}