{
  "type": "Feature",
  "properties": {
    "iso:country":"US",
    "sg:address":"6001 Industrial Hwy",
    "sg:city":"Gary",
    "sg:classifiers":[
        {
            "category":"Government",
            "subcategory":"Fire Station",
            "type":"Public Place"
        }
    ],
    "sg:phone":"+1 219 949 5139",
    "sg:postcode":"46406",
    "sg:province":"IN",
    "sg:tags":[
        "protection"
    ],
    "wof:name":"Fire Dept- Station 14",
    "wof:placetype":"venue"
},
  "geometry": {"coordinates":[-87.401322,41.614911],"type":"Point"}
}