{
  "type": "Feature",
  "properties": {
    "addr:full":"1231 W Troy Ave Indianapolis IN 46225",
    "addr:housenumber":"1231",
    "addr:postcode":"46225",
    "addr:street":"W Troy Ave",
    "iso:country":"US",
    "sg:address":"1231 W Troy Ave",
    "sg:city":"Indianapolis",
    "sg:classifiers":[
        {
            "category":"Utilities",
            "subcategory":"Water",
            "type":"Services"
        }
    ],
    "sg:phone":"+1 317 782 4415",
    "sg:postcode":"46225",
    "sg:province":"IN",
    "sg:tags":[
        "company",
        "sewage"
    ],
    "wof:name":"United Water Svc",
    "wof:placetype":"venue"
},
  "geometry": {"coordinates":[-86.184287,39.72196],"type":"Point"}
}