{
  "type": "Feature",
  "properties": {
    "iso:country":"US",
    "sg:address":"127 E Washington Ave",
    "sg:city":"Peru",
    "sg:classifiers":[
        {
            "category":"Government",
            "subcategory":"Office",
            "type":"Public Place"
        }
    ],
    "sg:phone":"+1 765 473 5835",
    "sg:postcode":"46970",
    "sg:province":"IN",
    "sg:tags":[
        "village"
    ],
    "wof:name":"Peru Township Trustee",
    "wof:placetype":"venue"
},
  "geometry": {"coordinates":[-86.070432,40.763949],"type":"Point"}
}