{
  "type": "Feature",
  "properties": {
    "iso:country":"US",
    "sg:address":"3508 W 200 N",
    "sg:city":"Wabash",
    "sg:phone":"+1 260 563 7565",
    "sg:postcode":"46992",
    "sg:province":"IN",
    "sg:tags":[
        "farm",
        "corn",
        "soybean"
    ],
    "wof:name":"Shoemaker Farms",
    "wof:placetype":"venue"
},
  "geometry": {"coordinates":[-85.858097,40.85352],"type":"Point"}
}