{
  "type": "Feature",
  "properties": {
    "iso:country":"US",
    "sg:address":"2563 Willowcreek Rd",
    "sg:city":"Portage",
    "sg:classifiers":[
        {
            "category":"Personal",
            "subcategory":"Tanning Parlor",
            "type":"Services"
        }
    ],
    "sg:phone":"+1 219 764 4000",
    "sg:postcode":"46368",
    "sg:province":"IN",
    "sg:tags":[
        "salon"
    ],
    "wof:name":"Aztec Sunshop",
    "wof:placetype":"venue"
},
  "geometry": {"coordinates":[-87.18307299999999,41.579491],"type":"Point"}
}