{
  "type": "Feature",
  "properties": {
    "iso:country":"US",
    "sg:address":"12 E Cedar St",
    "sg:city":"Zionsville",
    "sg:classifiers":[
        {
            "category":"Shopping",
            "type":"Retail Goods"
        }
    ],
    "sg:phone":"+1 317 733 0955",
    "sg:postcode":"46077",
    "sg:province":"IN",
    "sg:tags":[
        "wedding",
        "supply"
    ],
    "wof:name":"Wedding Gallery",
    "wof:placetype":"venue"
},
  "geometry": {"coordinates":[-86.262124,39.951472],"type":"Point"}
}