{
  "type": "Feature",
  "properties": {
    "iso:country":"US",
    "sg:address":"2636 W Michigan St",
    "sg:city":"Indianapolis",
    "sg:classifiers":[
        {
            "category":"Shopping",
            "subcategory":"Department Store",
            "type":"Retail Goods"
        }
    ],
    "sg:phone":"+1 317 634 1694",
    "sg:postcode":"46222",
    "sg:province":"IN",
    "sg:tags":[
        "shop"
    ],
    "wof:name":"Family Dollar Store",
    "wof:placetype":"venue"
},
  "geometry": {"coordinates":[-86.204804,39.774693],"type":"Point"}
}