{
  "type": "Feature",
  "properties": {
    "iso:country":"US",
    "sg:address":"1284 S State Rd 61",
    "sg:city":"Winslow",
    "sg:classifiers":[
        {
            "category":"Education",
            "subcategory":"School",
            "type":"Public Place"
        }
    ],
    "sg:phone":"+1 812 354 3999",
    "sg:postcode":"47598",
    "sg:province":"IN",
    "wof:name":"Play & Learn Preschool",
    "wof:placetype":"venue"
},
  "geometry": {"coordinates":[-87.226281,38.402914],"type":"Point"}
}