{
  "type": "Feature",
  "properties": {
    "iso:country":"US",
    "sg:address":"1603 E Broadway",
    "sg:city":"Logansport",
    "sg:classifiers":[
        {
            "category":"Retail",
            "subcategory":"Funeral Services",
            "type":"Services"
        }
    ],
    "sg:phone":"+1 574 753 3138",
    "sg:postcode":"46947",
    "sg:province":"IN",
    "sg:tags":[
        "director"
    ],
    "wof:name":"Gundrum Funeral Home",
    "wof:placetype":"venue"
},
  "geometry": {"coordinates":[-86.34788,40.757021],"type":"Point"}
}