{
  "type": "Feature",
  "properties": {
    "iso:country":"US",
    "sg:address":"135 S Morgan St",
    "sg:city":"Rushville",
    "sg:classifiers":[
        {
            "category":"Personal",
            "subcategory":"Beauty Salon",
            "type":"Services"
        }
    ],
    "sg:phone":"+1 765 932 3464",
    "sg:postcode":"46173",
    "sg:province":"IN",
    "sg:tags":[
        "shop"
    ],
    "wof:name":"Shampoo Bowl",
    "wof:placetype":"venue"
},
  "geometry": {"coordinates":[-85.446314,39.607143],"type":"Point"}
}