{
  "type": "Feature",
  "properties": {
    "iso:country":"US",
    "sg:address":"2710 E 27th St",
    "sg:city":"Indianapolis",
    "sg:classifiers":[
        {
            "category":"Social Services",
            "subcategory":"Child Care",
            "type":"Services"
        }
    ],
    "sg:phone":"+1 317 926 1649",
    "sg:postcode":"46218",
    "sg:province":"IN",
    "wof:name":"Sandra Brandy",
    "wof:placetype":"venue"
},
  "geometry": {"coordinates":[-86.117882,39.805312],"type":"Point"}
}