{
  "type": "Feature",
  "properties": {
    "addr:full":"1095 US Hwy 136 Pittsboro IN 46167",
    "addr:housenumber":"1095",
    "addr:postcode":"46167",
    "addr:street":"Us Hwy 136",
    "iso:country":"US",
    "sg:address":"1095 US Hwy 136",
    "sg:city":"Pittsboro",
    "sg:classifiers":[
        {
            "category":"Retail",
            "subcategory":"Repair Shop",
            "type":"Services"
        }
    ],
    "sg:phone":"+1 317 892 4615",
    "sg:postcode":"46167",
    "sg:province":"IN",
    "wof:name":"Hughes Upholstery",
    "wof:placetype":"venue"
},
  "geometry": {"coordinates":[-86.50388,39.871],"type":"Point"}
}