{
  "type": "Feature",
  "properties": {
    "iso:country":"US",
    "sg:address":"16300 Chandler Blvd",
    "sg:city":"Mishawaka",
    "sg:classifiers":[
        {
            "category":"Arts & Performance",
            "subcategory":"Theater",
            "type":"Entertainment"
        }
    ],
    "sg:phone":"+1 574 256 5236",
    "sg:postcode":"46544",
    "sg:province":"IN",
    "sg:tags":[
        "group"
    ],
    "wof:name":"Heather Thistle Bagpipe Band",
    "wof:placetype":"venue"
},
  "geometry": {"coordinates":[-86.178962,41.641535],"type":"Point"}
}