{
  "type": "Feature",
  "properties": {
    "iso:country":"US",
    "sg:address":"2534 N Oak Rd",
    "sg:city":"Plymouth",
    "sg:classifiers":[
        {
            "category":"Shopping",
            "subcategory":"Gifts & Souvenirs",
            "type":"Retail Goods"
        }
    ],
    "sg:phone":"+1 574 936 9497",
    "sg:postcode":"46563",
    "sg:province":"IN",
    "sg:tags":[
        "shop"
    ],
    "wof:name":"Dorothy's Hallmark Shop",
    "wof:placetype":"venue"
},
  "geometry": {"coordinates":[-86.328861,41.364006],"type":"Point"}
}