{
  "type": "Feature",
  "properties": {
    "addr:full":"6349 S Co Rd 830 E Kirklin IN 46050",
    "addr:housenumber":"6349",
    "addr:postcode":"46050",
    "addr:street":"S Co Rd 830 E Kirklin",
    "iso:country":"US",
    "sg:address":"6349 S Co Rd 830 E",
    "sg:city":"Kirklin",
    "sg:classifiers":[
        {
            "category":"Real Estate",
            "subcategory":"Real Estate Operator",
            "type":"Services"
        }
    ],
    "sg:phone":"+1 765 279 8718",
    "sg:postcode":"46050",
    "sg:province":"IN",
    "sg:tags":[
        "property",
        "lessor"
    ],
    "wof:name":"Fred Rhinehart",
    "wof:placetype":"venue"
},
  "geometry": {"coordinates":[-86.351877,40.198902],"type":"Point"}
}