{
  "type": "Feature",
  "properties": {
    "iso:country":"US",
    "sg:address":"6211 US Hwy 6",
    "sg:city":"Portage",
    "sg:classifiers":[
        {
            "category":"Restaurant",
            "type":"Food & Drink"
        }
    ],
    "sg:phone":"+1 219 762 3243",
    "sg:postcode":"46368",
    "sg:province":"IN",
    "sg:website":"www.applesauceinc.com",
    "wof:name":"Applebee's Neighborhood Grill",
    "wof:placetype":"venue"
},
  "geometry": {"coordinates":[-87.174604,41.55045],"type":"Point"}
}