{
  "type": "Feature",
  "properties": {
    "addr:full":"2283 N State St Greenfield IN 46140",
    "addr:housenumber":"2283",
    "addr:postcode":"46140",
    "addr:street":"N State St",
    "iso:country":"US",
    "sg:address":"2283 N State St",
    "sg:city":"Greenfield",
    "sg:classifiers":[
        {
            "category":"Restaurant",
            "type":"Food & Drink"
        }
    ],
    "sg:menulink":"http://www.allmenus.com/in/greenfield/240912-white-castle/menu/",
    "sg:postcode":"46140",
    "sg:province":"IN",
    "sg:tags":[
        "burger",
        "american"
    ],
    "wof:name":"White Castle",
    "wof:placetype":"venue"
},
  "geometry": {"coordinates":[-85.76984299999999,39.818343],"type":"Point"}
}