{
  "type": "Feature",
  "properties": {
    "addr:full":"3743 41st Ln Highland IN 46322",
    "addr:housenumber":"3743",
    "addr:postcode":"46322",
    "addr:street":"41St Ln",
    "iso:country":"US",
    "sg:address":"3743 41st Ln",
    "sg:city":"Highland",
    "sg:classifiers":[
        {
            "category":"Professional",
            "subcategory":"Business Services",
            "type":"Services"
        }
    ],
    "sg:phone":"+1 219 922 9162",
    "sg:postcode":"46322",
    "sg:province":"IN",
    "wof:name":"First Line Business Services L",
    "wof:placetype":"venue"
},
  "geometry": {"coordinates":[-87.438478,41.543298],"type":"Point"}
}