{
  "type": "Feature",
  "properties": {
    "addr:full":"27306 Lamplighter Ln Elkhart IN 46514",
    "addr:postcode":"27306;46514",
    "addr:street":"Lamplighter Ln",
    "iso:country":"US",
    "sg:address":"27306 Lamplighter Ln",
    "sg:city":"Elkhart",
    "sg:classifiers":[
        {
            "category":"Professional",
            "subcategory":"Business Services",
            "type":"Services"
        }
    ],
    "sg:phone":"+1 574 266 5343",
    "sg:postcode":"46514",
    "sg:province":"IN",
    "wof:name":"Scheretie Enterprises Inc",
    "wof:placetype":"venue"
},
  "geometry": {"coordinates":[-85.995724,41.736595],"type":"Point"}
}