{
  "type": "Feature",
  "properties": {
    "iso:country":"US",
    "sg:address":"7910 W Jefferson Blvd",
    "sg:city":"Fort Wayne",
    "sg:classifiers":[
        {
            "category":"Health Services",
            "subcategory":"Doctor",
            "type":"Services"
        }
    ],
    "sg:phone":"+1 260 436 2424",
    "sg:postcode":"46804",
    "sg:province":"IN",
    "sg:tags":[
        "physician",
        "surgeon"
    ],
    "wof:name":"Indiana-Ohio Heart",
    "wof:placetype":"venue"
},
  "geometry": {"coordinates":[-85.243039,41.039672],"type":"Point"}
}