{
  "type": "Feature",
  "properties": {
    "iso:country":"US",
    "sg:address":"1000 N F St",
    "sg:city":"Richmond",
    "sg:classifiers":[
        {
            "category":"Wholesale",
            "subcategory":"Construction Materials",
            "type":"Manufacturing & Wholesale Goods"
        }
    ],
    "sg:phone":"+1 765 966 7771",
    "sg:postcode":"47374",
    "sg:province":"IN",
    "sg:tags":[
        "brick",
        "common",
        "face"
    ],
    "sg:website":"www.barkersinc.com",
    "wof:name":"Barker's Inc",
    "wof:placetype":"venue"
},
  "geometry": {"coordinates":[-84.886095,39.83631],"type":"Point"}
}