{
  "type": "Feature",
  "properties": {
    "iso:country":"US",
    "sg:address":"4100 Grant St",
    "sg:city":"Gary",
    "sg:classifiers":[
        {
            "category":"Wholesale",
            "subcategory":"Durable Goods & Equipment",
            "type":"Manufacturing & Wholesale Goods"
        }
    ],
    "sg:phone":"+1 219 985 1197",
    "sg:postcode":"46408",
    "sg:province":"IN",
    "sg:tags":[
        "importer"
    ],
    "wof:name":"Indiana Imports",
    "wof:placetype":"venue"
},
  "geometry": {"coordinates":[-87.355721,41.541389],"type":"Point"}
}