{
  "type": "Feature",
  "properties": {
    "addr:full":"10321 US Hwy 36 Avon IN 46123",
    "addr:housenumber":"10321",
    "addr:postcode":"46123",
    "addr:street":"Us Hwy 36",
    "iso:country":"US",
    "sg:address":"10321 US Hwy 36",
    "sg:city":"Avon",
    "sg:classifiers":[
        {
            "category":"Home & Garden",
            "subcategory":"Home Furnishings",
            "type":"Retail Goods"
        }
    ],
    "sg:phone":"+1 317 209 9580",
    "sg:postcode":"46123",
    "sg:province":"IN",
    "sg:tags":[
        "linen"
    ],
    "sg:website":"www.linensnthings.com",
    "wof:name":"Linens 'n Things",
    "wof:placetype":"venue"
},
  "geometry": {"coordinates":[-86.340943,39.763572],"type":"Point"}
}