{
  "type": "Feature",
  "properties": {
    "iso:country":"US",
    "sg:address":"111 N A St",
    "sg:city":"Elwood",
    "sg:classifiers":[
        {
            "category":"Organizations",
            "subcategory":"Religious Organization",
            "type":"Services"
        }
    ],
    "sg:phone":"+1 765 552 5222",
    "sg:postcode":"46036",
    "sg:province":"IN",
    "sg:tags":[
        "church"
    ],
    "wof:name":"United Pentecostal Church",
    "wof:placetype":"venue"
},
  "geometry": {"coordinates":[-85.860573,40.277825],"type":"Point"}
}