{
  "type": "Feature",
  "properties": {
    "addr:full":"410 W Miami Ave Logansport IN 46947",
    "addr:housenumber":"410",
    "addr:postcode":"46947",
    "addr:street":"W Miami Ave",
    "iso:country":"US",
    "sg:address":"410 W Miami Ave",
    "sg:city":"Logansport",
    "sg:classifiers":[
        {
            "category":"Education",
            "subcategory":"School",
            "type":"Public Place"
        }
    ],
    "sg:phone":"+1 574 722 3200",
    "sg:postcode":"46947",
    "sg:province":"IN",
    "wof:name":"Franklin Elementary School",
    "wof:placetype":"venue"
},
  "geometry": {"coordinates":[-86.375715,40.755989],"type":"Point"}
}