{
  "type": "Feature",
  "properties": {
    "iso:country":"US",
    "sg:address":"3101 N Anthony Blvd",
    "sg:city":"Fort Wayne",
    "sg:classifiers":[
        {
            "category":"Restaurant",
            "type":"Food & Drink"
        }
    ],
    "sg:phone":"+1 260 471 1288",
    "sg:postcode":"46805",
    "sg:province":"IN",
    "sg:tags":[
        "eating"
    ],
    "wof:name":"Chung King Express Gourmet",
    "wof:placetype":"venue"
},
  "geometry": {"coordinates":[-85.115775,41.104662],"type":"Point"}
}