{
  "type": "Feature",
  "properties": {
    "iso:country":"US",
    "sg:address":"320 E Morgan St",
    "sg:city":"Martinsville",
    "sg:classifiers":[
        {
            "category":"Retail",
            "subcategory":"Auto Repair",
            "type":"Services"
        }
    ],
    "sg:phone":"+1 765 342 9358",
    "sg:postcode":"46151",
    "sg:province":"IN",
    "sg:tags":[
        "repairing",
        "automobile",
        "radiator"
    ],
    "wof:name":"Thompson's Radiator-Ace Mfflr",
    "wof:placetype":"venue"
},
  "geometry": {"coordinates":[-86.424709,39.427917],"type":"Point"}
}