{
  "type": "Feature",
  "properties": {
    "iso:country":"US",
    "sg:address":"2333 Canvasback Dr",
    "sg:city":"Indianapolis",
    "sg:classifiers":[
        {
            "category":"Professional",
            "subcategory":"Detective & Security Services",
            "type":"Services"
        }
    ],
    "sg:phone":"+1 317 223 5752",
    "sg:postcode":"46234",
    "sg:province":"IN",
    "sg:tags":[
        "private",
        "investigator"
    ],
    "sg:website":"http://www.badboyspi.net",
    "wof:name":"Bad Boys Private Investigators",
    "wof:placetype":"venue"
},
  "geometry": {"coordinates":[-86.319328,39.79695],"type":"Point"}
}