{
  "type": "Feature",
  "properties": {
    "iso:country":"US",
    "sg:address":"1627 Prospect St",
    "sg:city":"Indianapolis",
    "sg:classifiers":[
        {
            "category":"Shopping",
            "subcategory":"Tobacco",
            "type":"Retail Goods"
        }
    ],
    "sg:phone":"+1 317 685 2757",
    "sg:postcode":"46203",
    "sg:province":"IN",
    "sg:tags":[
        "cigarette",
        "cigar",
        "dealer"
    ],
    "wof:name":"Tobacco 4 Less",
    "wof:placetype":"venue"
},
  "geometry": {"coordinates":[-86.130983,39.752324],"type":"Point"}
}