{
  "type": "Feature",
  "properties": {
    "iso:country":"US",
    "sg:address":"926 Greer St",
    "sg:city":"Indianapolis",
    "sg:classifiers":[
        {
            "category":"Banks & Credit Unions",
            "subcategory":"Bank",
            "type":"Services"
        }
    ],
    "sg:phone":"+1 317 507 1693",
    "sg:postcode":"46203",
    "sg:province":"IN",
    "sg:tags":[
        "loan",
        "real estate"
    ],
    "wof:name":"American Fletcher Funding",
    "wof:placetype":"venue"
},
  "geometry": {"coordinates":[-86.148404,39.755588],"type":"Point"}
}