{
  "type": "Feature",
  "properties": {
    "iso:country":"US",
    "sg:address":"107 N Main St",
    "sg:city":"Hebron",
    "sg:classifiers":[
        {
            "category":"Professional",
            "subcategory":"Lawyer & Legal Services",
            "type":"Services"
        }
    ],
    "sg:phone":"+1 219 996 2300",
    "sg:postcode":"46341",
    "sg:province":"IN",
    "sg:tags":[
        "attorney"
    ],
    "wof:name":"Petry Fitzgerald & Less",
    "wof:placetype":"venue"
},
  "geometry": {"coordinates":[-87.19991,41.319265],"type":"Point"}
}