{
  "type": "Feature",
  "properties": {
    "iso:country":"US",
    "sg:address":"3600 Calumet Ave",
    "sg:city":"Hammond",
    "sg:classifiers":[
        {
            "category":"Professional",
            "subcategory":"Business Services",
            "type":"Services"
        }
    ],
    "sg:phone":"+1 219 933 6700",
    "sg:postcode":"46320",
    "sg:province":"IN",
    "sg:tags":[
        "delivery",
        "courier"
    ],
    "sg:website":"www.shipgreyhound.com",
    "wof:name":"Greyhound Package Express",
    "wof:placetype":"venue"
},
  "geometry": {"coordinates":[-87.508703,41.648722],"type":"Point"}
}