{
  "type": "Feature",
  "properties": {
    "iso:country":"US",
    "sg:address":"5000 W 96th St",
    "sg:city":"Indianapolis",
    "sg:classifiers":[
        {
            "category":"Shopping",
            "subcategory":"Used Merchandise",
            "type":"Retail Goods"
        }
    ],
    "sg:phone":"+1 317 873 2727",
    "sg:postcode":"46268",
    "sg:province":"IN",
    "sg:tags":[
        "antique"
    ],
    "sg:website":"www.antiquearchitectural.com",
    "wof:name":"Colonial Antiques",
    "wof:placetype":"venue"
},
  "geometry": {"coordinates":[-86.236477,39.926022],"type":"Point"}
}