{
  "type": "Feature",
  "properties": {
    "iso:country":"US",
    "sg:address":"1230 Field Dr",
    "sg:city":"Noblesville",
    "sg:classifiers":[
        {
            "category":"Retail",
            "subcategory":"Repair Shop",
            "type":"Services"
        }
    ],
    "sg:phone":"+1 317 776 2682",
    "sg:postcode":"46060",
    "sg:province":"IN",
    "sg:tags":[
        "lock",
        "locksmith"
    ],
    "wof:name":"Erney's Lock & Key",
    "wof:placetype":"venue"
},
  "geometry": {"coordinates":[-86.008735,40.058537],"type":"Point"}
}