{
  "type": "Feature",
  "properties": {
    "iso:country":"US",
    "sg:address":"1771 McDonald Ln",
    "sg:city":"New Albany",
    "sg:classifiers":[
        {
            "category":"Wholesale",
            "subcategory":"Machinery & Supplies",
            "type":"Manufacturing & Wholesale Goods"
        }
    ],
    "sg:phone":"+1 812 945 8263",
    "sg:postcode":"47150",
    "sg:province":"IN",
    "sg:tags":[
        "director",
        "funeral"
    ],
    "wof:name":"Hughes Supplies",
    "wof:placetype":"venue"
},
  "geometry": {"coordinates":[-85.811506,38.319112],"type":"Point"}
}