{
  "type": "Feature",
  "properties": {
    "iso:country":"US",
    "sg:address":"2126 N Meridian St",
    "sg:city":"Indianapolis",
    "sg:classifiers":[
        {
            "category":"Organizations",
            "subcategory":"Membership Organization",
            "type":"Services"
        }
    ],
    "sg:phone":"+1 317 921 2671",
    "sg:postcode":"46202",
    "sg:province":"IN",
    "wof:name":"IRMSDC",
    "wof:placetype":"venue"
},
  "geometry": {"coordinates":[-86.15743999999999,39.795531],"type":"Point"}
}