{
  "type": "Feature",
  "properties": {
    "iso:country":"US",
    "sg:address":"3520 Smith Rd",
    "sg:city":"Fort Wayne",
    "sg:classifiers":[
        {
            "category":"Building & Trades",
            "subcategory":"Landscaping Services",
            "type":"Services"
        }
    ],
    "sg:phone":"+1 260 432 6223",
    "sg:postcode":"46804",
    "sg:province":"IN",
    "sg:tags":[
        "counseling",
        "planning",
        "landscape"
    ],
    "wof:name":"Rwk Landscaping",
    "wof:placetype":"venue"
},
  "geometry": {"coordinates":[-85.209763,41.054127],"type":"Point"}
}