{
  "type": "Feature",
  "properties": {
    "iso:country":"US",
    "sg:address":"55 S State Ave",
    "sg:city":"Indianapolis",
    "sg:classifiers":[
        {
            "category":"Professional",
            "subcategory":"Management & Consulting",
            "type":"Services"
        }
    ],
    "sg:phone":"+1 317 423 0009",
    "sg:postcode":"46201",
    "sg:province":"IN",
    "sg:tags":[
        "consultant",
        "hygiene",
        "industrial"
    ],
    "wof:name":"Occupational Health & Hygiene",
    "wof:placetype":"venue"
},
  "geometry": {"coordinates":[-86.130608,39.76568],"type":"Point"}
}