{
  "type": "Feature",
  "properties": {
    "addr:full":"1407 Spring St Jeffersonville IN 47130",
    "addr:housenumber":"1407",
    "addr:postcode":"47130",
    "addr:street":"Spring St",
    "iso:country":"US",
    "sg:address":"1407 Spring St",
    "sg:city":"Jeffersonville",
    "sg:classifiers":[
        {
            "category":"Health Services",
            "subcategory":"Doctor",
            "type":"Services"
        }
    ],
    "sg:phone":"+1 812 288 9646",
    "sg:postcode":"47130",
    "sg:province":"IN",
    "sg:tags":[
        "physician",
        "surgeon"
    ],
    "wof:name":"Total Health Care For Women",
    "wof:placetype":"venue"
},
  "geometry": {"coordinates":[-85.748436,38.28421],"type":"Point"}
}