{
  "type": "Feature",
  "properties": {
    "iso:country":"US",
    "sg:address":"711 W 17th St",
    "sg:city":"Bloomington",
    "sg:classifiers":[
        {
            "category":"Restaurant",
            "type":"Food & Drink"
        }
    ],
    "sg:phone":"+1 812 333 3030",
    "sg:postcode":"47404",
    "sg:province":"IN",
    "sg:website":"www.buffalouies.com",
    "wof:name":"Buffa Louie's",
    "wof:placetype":"venue"
},
  "geometry": {"coordinates":[-86.541298,39.178902],"type":"Point"}
}