{
  "type": "Feature",
  "properties": {
    "iso:country":"US",
    "sg:address":"6065 N State Rd 19",
    "sg:city":"Warsaw",
    "sg:classifiers":[
        {
            "category":"Building & Trades",
            "subcategory":"Construction",
            "type":"Services"
        }
    ],
    "sg:phone":"+1 574 372 0207",
    "sg:postcode":"46524",
    "sg:province":"IN",
    "sg:tags":[
        "general",
        "contractor"
    ],
    "wof:name":"Premium Building Contractors",
    "wof:placetype":"venue"
},
  "geometry": {"coordinates":[-86.038641,41.323984],"type":"Point"}
}