{
  "type": "Feature",
  "properties": {
    "iso:country":"US",
    "sg:address":"8551 Walden Trace Dr",
    "sg:city":"Indianapolis",
    "sg:classifiers":[
        {
            "category":"Real Estate",
            "subcategory":"Real Estate Agent",
            "type":"Services"
        }
    ],
    "sg:phone":"+1 317 299 6844",
    "sg:postcode":"46278",
    "sg:province":"IN",
    "wof:name":"Vo Real Estate PC",
    "wof:placetype":"venue"
},
  "geometry": {"coordinates":[-86.306941,39.909424],"type":"Point"}
}