{
  "type": "Feature",
  "properties": {
    "addr:full":"29934 Riviera Dr Elkhart IN 46514",
    "addr:housenumber":"29934",
    "addr:postcode":"46514",
    "addr:street":"Riviera Dr",
    "iso:country":"US",
    "sg:address":"29934 Riviera Dr",
    "sg:city":"Elkhart",
    "sg:classifiers":[
        {
            "category":"Real Estate",
            "subcategory":"Real Estate Agent",
            "type":"Services"
        }
    ],
    "sg:phone":"+1 574 522 0030",
    "sg:postcode":"46514",
    "sg:province":"IN",
    "wof:name":"Frances Foster",
    "wof:placetype":"venue"
},
  "geometry": {"coordinates":[-86.04104700000001,41.685126],"type":"Point"}
}