{
  "type": "Feature",
  "properties": {
    "addr:full":"7801 Sweetwater Dr Nineveh IN 46164",
    "addr:housenumber":"7801",
    "addr:postcode":"46164",
    "addr:street":"Sweetwater Dr",
    "iso:country":"US",
    "sg:address":"7801 Sweetwater Dr",
    "sg:city":"Nineveh",
    "sg:classifiers":[
        {
            "category":"Real Estate",
            "subcategory":"Architect",
            "type":"Services"
        }
    ],
    "sg:phone":"+1 317 878 5043",
    "sg:postcode":"46164",
    "sg:province":"IN",
    "wof:name":"CSO",
    "wof:placetype":"venue"
},
  "geometry": {"coordinates":[-86.136442,39.317547],"type":"Point"}
}