{
  "type": "Feature",
  "properties": {
    "iso:country":"US",
    "sg:address":"132 W State St",
    "sg:city":"Pendleton",
    "sg:classifiers":[
        {
            "category":"Home & Garden",
            "subcategory":"Home Furnishings",
            "type":"Retail Goods"
        }
    ],
    "sg:phone":"+1 765 778 7936",
    "sg:postcode":"46064",
    "sg:province":"IN",
    "sg:tags":[
        "quilting"
    ],
    "wof:name":"Needle In A Quilt",
    "wof:placetype":"venue"
},
  "geometry": {"coordinates":[-85.746443,40.002548],"type":"Point"}
}