{
  "type": "Feature",
  "properties": {
    "iso:country":"US",
    "sg:address":"54 N Belleview Pl",
    "sg:city":"Indianapolis",
    "sg:classifiers":[
        {
            "category":"Professional",
            "subcategory":"Business Services",
            "type":"Services"
        }
    ],
    "sg:phone":"+1 317 632 0188",
    "sg:postcode":"46222",
    "sg:province":"IN",
    "wof:name":"Ice Sculptures & Block By Jose",
    "wof:placetype":"venue"
},
  "geometry": {"coordinates":[-86.202999,39.767391],"type":"Point"}
}