{
  "type": "Feature",
  "properties": {
    "iso:country":"US",
    "sg:address":"2860 N National Rd",
    "sg:city":"Columbus",
    "sg:classifiers":[
        {
            "category":"Wholesale",
            "subcategory":"Machinery & Supplies",
            "type":"Manufacturing & Wholesale Goods"
        }
    ],
    "sg:phone":"+1 812 372 6000",
    "sg:postcode":"47201",
    "sg:province":"IN",
    "wof:name":"Machinery Mounting Systems Inc",
    "wof:placetype":"venue"
},
  "geometry": {"coordinates":[-85.894627,39.225961],"type":"Point"}
}