{
  "type": "Feature",
  "properties": {
    "iso:country":"US",
    "sg:address":"13510 13th Rd",
    "sg:city":"Plymouth",
    "sg:phone":"+1 574 936 6132",
    "sg:postcode":"46563",
    "sg:province":"IN",
    "sg:tags":[
        "farm",
        "corn",
        "grain",
        "cash"
    ],
    "wof:name":"Karl Hartman",
    "wof:placetype":"venue"
},
  "geometry": {"coordinates":[-86.31901000000001,41.288704],"type":"Point"}
}