{
  "type": "Feature",
  "properties": {
    "iso:country":"US",
    "sg:address":"2537 W Co Rd 100 N",
    "sg:city":"Versailles",
    "sg:classifiers":[
        {
            "category":"Wholesale",
            "subcategory":"Construction Materials",
            "type":"Manufacturing & Wholesale Goods"
        }
    ],
    "sg:phone":"+1 812 689 1565",
    "sg:postcode":"47042",
    "sg:province":"IN",
    "sg:tags":[
        "pallet",
        "skid"
    ],
    "wof:name":"Pallet Depot",
    "wof:placetype":"venue"
},
  "geometry": {"coordinates":[-85.30127,39.089002],"type":"Point"}
}