{
  "type": "Feature",
  "properties": {
    "iso:country":"US",
    "sg:address":"6010 Norwaldo Ave",
    "sg:city":"Indianapolis",
    "sg:classifiers":[
        {
            "category":"Banks & Credit Unions",
            "subcategory":"Bank",
            "type":"Services"
        }
    ],
    "sg:phone":"+1 317 876 9056",
    "sg:postcode":"46220",
    "sg:province":"IN",
    "sg:tags":[
        "loan",
        "real estate"
    ],
    "wof:name":"Old Indiana Mortgage Corp",
    "wof:placetype":"venue"
},
  "geometry": {"coordinates":[-86.12947200000001,39.86533],"type":"Point"}
}