{
  "type": "Feature",
  "properties": {
    "addr:full":"1305 E Markland Ave Kokomo IN 46901",
    "addr:housenumber":"1305",
    "addr:postcode":"46901",
    "addr:street":"E Markland Ave",
    "iso:country":"US",
    "sg:address":"1305 E Markland Ave",
    "sg:city":"Kokomo",
    "sg:classifiers":[
        {
            "category":"Shopping",
            "subcategory":"Gifts & Souvenirs",
            "type":"Retail Goods"
        }
    ],
    "sg:phone":"+1 765 459 8511",
    "sg:postcode":"46901",
    "sg:province":"IN",
    "sg:tags":[
        "shop"
    ],
    "wof:name":"Scent Of Sage",
    "wof:placetype":"venue"
},
  "geometry": {"coordinates":[-86.115686,40.476603],"type":"Point"}
}