{
  "type": "Feature",
  "properties": {
    "iso:country":"US",
    "sg:address":"1824 N 16th St",
    "sg:city":"New Castle",
    "sg:classifiers":[
        {
            "category":"Building & Trades",
            "subcategory":"Construction",
            "type":"Services"
        }
    ],
    "sg:phone":"+1 765 529 4351",
    "sg:postcode":"47362",
    "sg:province":"IN",
    "sg:tags":[
        "general",
        "contractor"
    ],
    "wof:name":"Alan Smith Builders",
    "wof:placetype":"venue"
},
  "geometry": {"coordinates":[-85.361473,39.947901],"type":"Point"}
}