{
  "type": "Feature",
  "properties": {
    "iso:country":"US",
    "sg:address":"5737 S Ironwood Dr",
    "sg:city":"South Bend",
    "sg:classifiers":[
        {
            "category":"Retail",
            "subcategory":"Portrait Studio",
            "type":"Services"
        }
    ],
    "sg:phone":"+1 574 232 2003",
    "sg:postcode":"46614",
    "sg:province":"IN",
    "sg:tags":[
        "photographer"
    ],
    "sg:website":"www.mcdonaldstudio.com",
    "wof:name":"Mc Donald Studio Inc",
    "wof:placetype":"venue"
},
  "geometry": {"coordinates":[-86.21565099999999,41.629493],"type":"Point"}
}