{
  "type": "Feature",
  "properties": {
    "iso:country":"US",
    "sg:address":"5280 E 400 S",
    "sg:city":"Peru",
    "sg:classifiers":[
        {
            "category":"Farming",
            "subcategory":"Livestock Farm",
            "type":"Manufacturing & Wholesale Goods"
        }
    ],
    "sg:phone":"+1 765 473 6373",
    "sg:postcode":"46992",
    "sg:province":"IN",
    "sg:tags":[
        "feedlot",
        "hog",
        "or",
        "beef",
        "cattle"
    ],
    "wof:name":"Jack Windsor",
    "wof:placetype":"venue"
},
  "geometry": {"coordinates":[-85.70034,40.768794],"type":"Point"}
}