{
  "type": "Feature",
  "properties": {
    "iso:country":"US",
    "sg:address":"6535 W Ison Rd",
    "sg:city":"Bloomington",
    "sg:classifiers":[
        {
            "category":"Building & Trades",
            "subcategory":"Construction",
            "type":"Services"
        }
    ],
    "sg:phone":"+1 812 825 2758",
    "sg:postcode":"47403",
    "sg:province":"IN",
    "sg:tags":[
        "product",
        "asphalt"
    ],
    "wof:name":"Groomer Asphalt Paving",
    "wof:placetype":"venue"
},
  "geometry": {"coordinates":[-86.605598,39.122305],"type":"Point"}
}