{
  "type": "Feature",
  "properties": {
    "iso:country":"US",
    "sg:address":"11110 Haverstick Rd E",
    "sg:city":"Carmel",
    "sg:classifiers":[
        {
            "category":"Professional",
            "subcategory":"Computer Services",
            "type":"Services"
        }
    ],
    "sg:phone":"+1 317 569 1725",
    "sg:postcode":"46033",
    "sg:province":"IN",
    "sg:tags":[
        "programing",
        "custom"
    ],
    "wof:name":"Pillsbury Enterprises",
    "wof:placetype":"venue"
},
  "geometry": {"coordinates":[-86.096704,39.952155],"type":"Point"}
}