{
  "type": "Feature",
  "properties": {
    "iso:country":"US",
    "sg:address":"6093 E Co Rd 1100 S",
    "sg:city":"Galveston",
    "sg:classifiers":[
        {
            "category":"Shopping",
            "type":"Retail Goods"
        }
    ],
    "sg:phone":"+1 574 626 2225",
    "sg:postcode":"46932",
    "sg:province":"IN",
    "sg:tags":[
        "feed",
        "apparel",
        "horse",
        "boot",
        "saddle"
    ],
    "wof:name":"Broken B Tack Shop",
    "wof:placetype":"venue"
},
  "geometry": {"coordinates":[-86.254846,40.605795],"type":"Point"}
}