{
  "type": "Feature",
  "properties": {
    "iso:country":"US",
    "sg:address":"603 N Baldwin Ave",
    "sg:city":"Marion",
    "sg:classifiers":[
        {
            "category":"Health Services",
            "subcategory":"Doctor",
            "type":"Services"
        }
    ],
    "sg:phone":"+1 765 664 7273",
    "sg:postcode":"46952",
    "sg:province":"IN",
    "sg:tags":[
        "dentist"
    ],
    "wof:name":"Charles C Mc Gee DDS",
    "wof:placetype":"venue"
},
  "geometry": {"coordinates":[-85.675949,40.566069],"type":"Point"}
}