{
  "type": "Feature",
  "properties": {
    "iso:country":"US",
    "sg:address":"421 E 3rd St",
    "sg:city":"Bloomington",
    "sg:classifiers":[
        {
            "category":"Shopping",
            "subcategory":"Clothing, Apparel, & Fashions",
            "type":"Retail Goods"
        }
    ],
    "sg:phone":"+1 812 334 2026",
    "sg:postcode":"47401",
    "sg:province":"IN",
    "sg:tags":[
        "uniform"
    ],
    "wof:name":"Rose's Scrubs & Uniforms",
    "wof:placetype":"venue"
},
  "geometry": {"coordinates":[-86.528158,39.164534],"type":"Point"}
}