{
  "type": "Feature",
  "properties": {
    "iso:country":"US",
    "sg:address":"4132 W 800 S",
    "sg:city":"Warren",
    "sg:classifiers":[
        {
            "category":"Real Estate",
            "subcategory":"Real Estate Agent",
            "type":"Services"
        }
    ],
    "sg:phone":"+1 260 359 1930",
    "sg:postcode":"46792",
    "sg:province":"IN",
    "sg:tags":[
        "inspection"
    ],
    "wof:name":"Homepro",
    "wof:placetype":"venue"
},
  "geometry": {"coordinates":[-85.528686,40.711243],"type":"Point"}
}