{
  "type": "Feature",
  "properties": {
    "addr:full":"8431 Thorn Bend Dr Indianapolis IN 46278",
    "addr:housenumber":"8431",
    "addr:postcode":"46278",
    "addr:street":"Thorn Bend Dr",
    "iso:country":"US",
    "sg:address":"8431 Thorn Bend Dr",
    "sg:city":"Indianapolis",
    "sg:classifiers":[
        {
            "category":"Professional",
            "subcategory":"Accounting & Tax Preparation",
            "type":"Services"
        }
    ],
    "sg:phone":"+1 317 293 4614",
    "sg:postcode":"46278",
    "sg:province":"IN",
    "sg:tags":[
        "accountant",
        "public",
        "certified"
    ],
    "wof:name":"Kanzler & Associates Cpas PC",
    "wof:placetype":"venue"
},
  "geometry": {"coordinates":[-86.309995,39.920998],"type":"Point"}
}