{
  "type": "Feature",
  "properties": {
    "iso:country":"US",
    "sg:address":"2221 W Wallen Rd",
    "sg:city":"Fort Wayne",
    "sg:classifiers":[
        {
            "category":"Building & Trades",
            "subcategory":"Cleaning & Sanitation",
            "type":"Services"
        }
    ],
    "sg:phone":"+1 260 490 9021",
    "sg:postcode":"46818",
    "sg:province":"IN",
    "sg:tags":[
        "janitor"
    ],
    "wof:name":"General Job",
    "wof:placetype":"venue"
},
  "geometry": {"coordinates":[-85.171352,41.161082],"type":"Point"}
}