{
  "type": "Feature",
  "properties": {
    "iso:country":"US",
    "sg:address":"444 W Plaza Dr",
    "sg:city":"Columbia City",
    "sg:classifiers":[
        {
            "category":"Shopping",
            "subcategory":"Books",
            "type":"Retail Goods"
        }
    ],
    "sg:phone":"+1 260 244 7580",
    "sg:postcode":"46725",
    "sg:province":"IN",
    "sg:tags":[
        "dealer"
    ],
    "wof:name":"H & B Bookstore",
    "wof:placetype":"venue"
},
  "geometry": {"coordinates":[-85.49255599999999,41.170242],"type":"Point"}
}