{
  "type": "Feature",
  "properties": {
    "iso:country":"US",
    "sg:address":"809 Mount Tabor Rd",
    "sg:city":"New Albany",
    "sg:classifiers":[
        {
            "category":"Health Services",
            "subcategory":"Doctor",
            "type":"Services"
        }
    ],
    "sg:phone":"+1 812 944 5155",
    "sg:postcode":"47150",
    "sg:province":"IN",
    "sg:tags":[
        "dentist"
    ],
    "wof:name":"Todd A Carter DDS",
    "wof:placetype":"venue"
},
  "geometry": {"coordinates":[-85.817705,38.332059],"type":"Point"}
}