{
  "type": "Feature",
  "properties": {
    "iso:country":"US",
    "sg:address":"57813 State Rd 19",
    "sg:city":"Elkhart",
    "sg:classifiers":[
        {
            "category":"Shopping",
            "subcategory":"Jewelry",
            "type":"Retail Goods"
        }
    ],
    "sg:phone":"+1 574 293 5620",
    "sg:postcode":"46517",
    "sg:province":"IN",
    "sg:tags":[
        "platinum",
        "silver",
        "gold"
    ],
    "wof:name":"Solid Gold Inc",
    "wof:placetype":"venue"
},
  "geometry": {"coordinates":[-86.003074,41.65597],"type":"Point"}
}