{
  "type": "Feature",
  "properties": {
    "iso:country":"US",
    "sg:address":"128 S Main St",
    "sg:city":"Monticello",
    "sg:classifiers":[
        {
            "category":"Professional",
            "subcategory":"Lawyer & Legal Services",
            "type":"Services"
        }
    ],
    "sg:phone":"+1 574 583 0784",
    "sg:postcode":"47960",
    "sg:province":"IN",
    "sg:tags":[
        "attorney"
    ],
    "wof:name":"Hoover Law Office",
    "wof:placetype":"venue"
},
  "geometry": {"coordinates":[-86.761994,40.74459],"type":"Point"}
}