{
  "type": "Feature",
  "properties": {
    "iso:country":"US",
    "sg:address":"101 Community Dr",
    "sg:city":"Seymour",
    "sg:classifiers":[
        {
            "category":"Restaurant",
            "type":"Food & Drink"
        }
    ],
    "sg:phone":"+1 812 524 7500",
    "sg:postcode":"47274",
    "sg:province":"IN",
    "wof:name":"Fast Stop Pizza",
    "wof:placetype":"venue"
},
  "geometry": {"coordinates":[-85.903629,38.954226],"type":"Point"}
}