{
  "type": "Feature",
  "properties": {
    "iso:country":"US",
    "sg:address":"318 W Main St",
    "sg:city":"Berne",
    "sg:classifiers":[
        {
            "category":"Shopping",
            "subcategory":"Gifts & Souvenirs",
            "type":"Retail Goods"
        }
    ],
    "sg:phone":"+1 260 589 8629",
    "sg:postcode":"46711",
    "sg:province":"IN",
    "sg:tags":[
        "shop"
    ],
    "wof:name":"Colonial Designs",
    "wof:placetype":"venue"
},
  "geometry": {"coordinates":[-84.952877,40.657721],"type":"Point"}
}