{
  "type": "Feature",
  "properties": {
    "addr:full":"3025 N Home St Mishawaka IN 46545",
    "addr:housenumber":"3025",
    "addr:postcode":"46545",
    "addr:street":"N Home St",
    "iso:country":"US",
    "sg:address":"3025 N Home St",
    "sg:city":"Mishawaka",
    "sg:classifiers":[
        {
            "category":"Local Transit",
            "type":"Transportation"
        }
    ],
    "sg:phone":"+1 574 254 5000",
    "sg:postcode":"46545",
    "sg:province":"IN",
    "sg:tags":[
        "line"
    ],
    "wof:name":"Airport Bus Svc",
    "wof:placetype":"venue"
},
  "geometry": {"coordinates":[-86.149722,41.693684],"type":"Point"}
}