{
  "type": "Feature",
  "properties": {
    "iso:country":"US",
    "sg:address":"2950 N Prow Rd",
    "sg:city":"Bloomington",
    "sg:classifiers":[
        {
            "category":"Manufacturing",
            "subcategory":"Glass & Minerals",
            "type":"Manufacturing & Wholesale Goods"
        }
    ],
    "sg:phone":"+1 812 330 9773",
    "sg:postcode":"47404",
    "sg:province":"IN",
    "sg:tags":[
        "stone",
        "cutter"
    ],
    "wof:name":"Sawyer Hoosier",
    "wof:placetype":"venue"
},
  "geometry": {"coordinates":[-86.552244,39.193455],"type":"Point"}
}