{
  "type": "Feature",
  "properties": {
    "iso:country":"US",
    "sg:address":"7130 Barth Ave",
    "sg:city":"Indianapolis",
    "sg:classifiers":[
        {
            "category":"Building & Trades",
            "subcategory":"Construction",
            "type":"Services"
        }
    ],
    "sg:phone":"+1 317 889 0365",
    "sg:postcode":"46227",
    "sg:province":"IN",
    "sg:tags":[
        "general",
        "contractor"
    ],
    "wof:name":"P L Construction",
    "wof:placetype":"venue"
},
  "geometry": {"coordinates":[-86.141066,39.66332],"type":"Point"}
}