{
  "type": "Feature",
  "properties": {
    "iso:country":"US",
    "sg:address":"201 E Rudisill Blvd",
    "sg:city":"Fort Wayne",
    "sg:classifiers":[
        {
            "category":"Government",
            "subcategory":"Office",
            "type":"Public Place"
        }
    ],
    "sg:phone":"+1 260 423 1696",
    "sg:postcode":"46806",
    "sg:province":"IN",
    "sg:tags":[
        "federal",
        "program"
    ],
    "wof:name":"US Health & Human Svc Dept",
    "wof:placetype":"venue"
},
  "geometry": {"coordinates":[-85.133524,41.050093],"type":"Point"}
}