{
  "type": "Feature",
  "properties": {
    "addr:full":"612 W 42nd St Indianapolis IN 46208",
    "addr:housenumber":"612",
    "addr:postcode":"46208",
    "addr:street":"W 42Nd St",
    "iso:country":"US",
    "sg:address":"612 W 42nd St",
    "sg:city":"Indianapolis",
    "sg:classifiers":[
        {
            "category":"Education",
            "subcategory":"Special Training",
            "type":"Public Place"
        }
    ],
    "sg:phone":"+1 317 926 0043",
    "sg:postcode":"46208",
    "sg:province":"IN",
    "sg:tags":[
        "educational"
    ],
    "wof:name":"The Independence Academy Of Indiana Inc",
    "wof:placetype":"venue"
},
  "geometry": {"coordinates":[-86.169608,39.832059],"type":"Point"}
}