{
  "type": "Feature",
  "properties": {
    "iso:country":"US",
    "sg:address":"408 Lark Ct",
    "sg:city":"Carmel",
    "sg:classifiers":[
        {
            "category":"Professional",
            "subcategory":"Management & Consulting",
            "type":"Services"
        }
    ],
    "sg:phone":"+1 317 575 9804",
    "sg:postcode":"46032",
    "sg:province":"IN",
    "sg:tags":[
        "business"
    ],
    "wof:name":"Idea Yield Inc",
    "wof:placetype":"venue"
},
  "geometry": {"coordinates":[-86.13235299999999,39.980422],"type":"Point"}
}