{
  "type": "Feature",
  "properties": {
    "addr:full":"1105 R St Bedford IN 47421",
    "addr:housenumber":"1105",
    "addr:postcode":"47421",
    "addr:street":"R St",
    "iso:country":"US",
    "sg:address":"1105 R St",
    "sg:city":"Bedford",
    "sg:classifiers":[
        {
            "category":"Professional",
            "subcategory":"Accounting & Tax Preparation",
            "type":"Services"
        }
    ],
    "sg:phone":"+1 812 275 1016",
    "sg:postcode":"47421",
    "sg:province":"IN",
    "sg:tags":[
        "return",
        "filing"
    ],
    "wof:name":"Chent Inc",
    "wof:placetype":"venue"
},
  "geometry": {"coordinates":[-86.49513,38.866543],"type":"Point"}
}