{
  "type": "Feature",
  "properties": {
    "addr:full":"143 Green Meadows Dr Greenfield IN 46140",
    "addr:housenumber":"143",
    "addr:postcode":"46140",
    "addr:street":"Green Meadows Dr",
    "iso:country":"US",
    "sg:address":"143 Green Meadows Dr",
    "sg:city":"Greenfield",
    "sg:classifiers":[
        {
            "category":"Sports & Exercise",
            "subcategory":"Race Track",
            "type":"Entertainment"
        },
        {
            "category":"Retail",
            "subcategory":"Animal Services",
            "type":"Services"
        }
    ],
    "sg:phone":"+1 317 462 6616",
    "sg:postcode":"46140",
    "sg:province":"IN",
    "sg:tags":[
        "breeder",
        "horse",
        "racing",
        "operation",
        "or"
    ],
    "wof:name":"Indiana Standardbred Assoc",
    "wof:placetype":"venue"
},
  "geometry": {"coordinates":[-85.77134,39.80435],"type":"Point"}
}