{
  "type": "Feature",
  "properties": {
    "iso:country":"US",
    "sg:address":"1201 E Vaile Ave",
    "sg:city":"Kokomo",
    "sg:classifiers":[
        {
            "category":"Shopping",
            "subcategory":"Used Merchandise",
            "type":"Retail Goods"
        }
    ],
    "sg:phone":"+1 765 459 3148",
    "sg:postcode":"46901",
    "sg:province":"IN",
    "sg:tags":[
        "antique"
    ],
    "wof:name":"Treasure Mart",
    "wof:placetype":"venue"
},
  "geometry": {"coordinates":[-86.116832,40.480309],"type":"Point"}
}