{
  "type": "Feature",
  "properties": {
    "addr:full":"922 N 13th St Decatur IN 46733",
    "addr:housenumber":"922",
    "addr:postcode":"46733",
    "addr:street":"N 13Th St",
    "iso:country":"US",
    "sg:address":"922 N 13th St",
    "sg:city":"Decatur",
    "sg:classifiers":[
        {
            "category":"Travel",
            "subcategory":"Hotels & Motels",
            "type":"Entertainment"
        }
    ],
    "sg:phone":"+1 260 728 2101",
    "sg:postcode":"46733",
    "sg:province":"IN",
    "wof:name":"Matador Inn",
    "wof:placetype":"venue"
},
  "geometry": {"coordinates":[-84.93767,40.839397],"type":"Point"}
}