{
  "type": "Feature",
  "properties": {
    "iso:country":"US",
    "sg:address":"5430 Skyridge Dr",
    "sg:city":"Indianapolis",
    "sg:classifiers":[
        {
            "category":"Building & Trades",
            "subcategory":"Electrical",
            "type":"Services"
        }
    ],
    "sg:phone":"+1 317 849 0891",
    "sg:postcode":"46250",
    "sg:province":"IN",
    "sg:tags":[
        "electric",
        "contractor"
    ],
    "wof:name":"C & I Kreisher Inc",
    "wof:placetype":"venue"
},
  "geometry": {"coordinates":[-86.07112600000001,39.901917],"type":"Point"}
}