{
  "type": "Feature",
  "properties": {
    "iso:country":"US",
    "sg:address":"620 W Spring St",
    "sg:city":"New Albany",
    "sg:classifiers":[
        {
            "category":"Wholesale",
            "subcategory":"Machinery & Supplies",
            "type":"Manufacturing & Wholesale Goods"
        }
    ],
    "sg:phone":"+1 812 945 8173",
    "sg:postcode":"47150",
    "sg:province":"IN",
    "sg:tags":[
        "casket"
    ],
    "wof:name":"Affordable Casket",
    "wof:placetype":"venue"
},
  "geometry": {"coordinates":[-85.83176,38.282615],"type":"Point"}
}