{
  "type": "Feature",
  "properties": {
    "iso:country":"US",
    "sg:address":"2326 N Co Rd 850 E",
    "sg:city":"Seymour",
    "sg:classifiers":[
        {
            "category":"Building & Trades",
            "subcategory":"Construction",
            "type":"Services"
        }
    ],
    "sg:phone":"+1 812 522 4537",
    "sg:postcode":"47274",
    "sg:province":"IN",
    "sg:tags":[
        "general",
        "contractor"
    ],
    "wof:name":"Robert H Woodard",
    "wof:placetype":"venue"
},
  "geometry": {"coordinates":[-85.880122,38.916771],"type":"Point"}
}