{
  "type": "Feature",
  "properties": {
    "iso:country":"US",
    "sg:address":"211 Morgan St",
    "sg:city":"Crawfordsville",
    "sg:classifiers":[
        {
            "category":"Communications",
            "subcategory":"Film & Video Production",
            "type":"Services"
        },
        {
            "category":"Cinema",
            "subcategory":"Movie Rental",
            "type":"Entertainment"
        }
    ],
    "sg:phone":"+1 765 364 1286",
    "sg:postcode":"47933",
    "sg:province":"IN",
    "sg:tags":[
        "tape",
        "taping"
    ],
    "wof:name":"Ray's Video Productions",
    "wof:placetype":"venue"
},
  "geometry": {"coordinates":[-86.893635,40.043299],"type":"Point"}
}