{
  "type": "Feature",
  "properties": {
    "addr:full":"2612 Taylor St Fort Wayne IN 46802",
    "addr:housenumber":"2612",
    "addr:postcode":"46802",
    "addr:street":"Taylor St",
    "iso:country":"US",
    "sg:address":"2612 Taylor St",
    "sg:city":"Fort Wayne",
    "sg:classifiers":[
        {
            "category":"Manufacturing",
            "subcategory":"Tools & Machinery",
            "type":"Manufacturing & Wholesale Goods"
        }
    ],
    "sg:phone":"+1 260 436 4751",
    "sg:postcode":"46802",
    "sg:province":"IN",
    "sg:tags":[
        "machine",
        "shop"
    ],
    "wof:name":"Machinist Building Corp",
    "wof:placetype":"venue"
},
  "geometry": {"coordinates":[-85.174767,41.067705],"type":"Point"}
}