{
  "type": "Feature",
  "properties": {
    "iso:country":"US",
    "sg:address":"927 Shields Ave",
    "sg:city":"Seymour",
    "sg:classifiers":[
        {
            "category":"Retail",
            "subcategory":"Auto Repair",
            "type":"Services"
        }
    ],
    "sg:phone":"+1 812 522 4460",
    "sg:postcode":"47274",
    "sg:province":"IN",
    "sg:tags":[
        "repairing",
        "engine"
    ],
    "wof:name":"Engine Air Inc",
    "wof:placetype":"venue"
},
  "geometry": {"coordinates":[-85.892561,38.968591],"type":"Point"}
}