{
  "type": "Feature",
  "properties": {
    "iso:country":"US",
    "sg:address":"7505 Taft St",
    "sg:city":"Merrillville",
    "sg:classifiers":[
        {
            "category":"Bars & Pubs",
            "type":"Food & Drink"
        }
    ],
    "sg:phone":"+1 219 769 2351",
    "sg:postcode":"46410",
    "sg:province":"IN",
    "wof:name":"Mule Too",
    "wof:placetype":"venue"
},
  "geometry": {"coordinates":[-87.364924,41.485386],"type":"Point"}
}