{
  "type": "Feature",
  "properties": {
    "iso:country":"US",
    "sg:address":"1511 Kossuth St",
    "sg:city":"Lafayette",
    "sg:classifiers":[
        {
            "category":"Professional",
            "subcategory":"Lawyer & Legal Services",
            "type":"Services"
        }
    ],
    "sg:phone":"+1 765 742 8565",
    "sg:postcode":"47905",
    "sg:province":"IN",
    "sg:tags":[
        "attorney"
    ],
    "wof:name":"Harold E Amstutz Law Office",
    "wof:placetype":"venue"
},
  "geometry": {"coordinates":[-86.878509,40.409935],"type":"Point"}
}