{
  "type": "Feature",
  "properties": {
    "iso:country":"US",
    "sg:address":"325 W Main St",
    "sg:city":"Greensburg",
    "sg:classifiers":[
        {
            "category":"Social Services",
            "type":"Services"
        }
    ],
    "sg:phone":"+1 812 662 0857",
    "sg:postcode":"47240",
    "sg:province":"IN",
    "sg:tags":[
        "organization",
        "welfare"
    ],
    "wof:name":"Healthy Families-Decatur Cnty",
    "wof:placetype":"venue"
},
  "geometry": {"coordinates":[-85.487597,39.336479],"type":"Point"}
}