{
  "type": "Feature",
  "properties": {
    "iso:country":"US",
    "sg:address":"6535 N 950 E",
    "sg:city":"Howe",
    "sg:phone":"+1 260 367 2389",
    "sg:postcode":"46746",
    "sg:province":"IN",
    "sg:tags":[
        "farm",
        "corn",
        "soybean"
    ],
    "wof:name":"Barrows Weir",
    "wof:placetype":"venue"
},
  "geometry": {"coordinates":[-85.244248,41.735792],"type":"Point"}
}