{
  "type": "Feature",
  "properties": {
    "iso:country":"US",
    "sg:address":"234 N Oakland Ave",
    "sg:city":"Indianapolis",
    "sg:classifiers":[
        {
            "category":"Social Services",
            "subcategory":"Child Care",
            "type":"Services"
        }
    ],
    "sg:phone":"+1 317 916 2411",
    "sg:postcode":"46201",
    "sg:province":"IN",
    "wof:name":"Juinta Day Care",
    "wof:placetype":"venue"
},
  "geometry": {"coordinates":[-86.113235,39.769829],"type":"Point"}
}