{
  "type": "Feature",
  "properties": {
    "iso:country":"US",
    "sg:address":"10845 N Co Rd 200 W",
    "sg:city":"Brazil",
    "sg:classifiers":[
        {
            "category":"Building & Trades",
            "subcategory":"Landscaping Services",
            "type":"Services"
        }
    ],
    "sg:phone":"+1 812 442 6053",
    "sg:postcode":"47834",
    "sg:province":"IN",
    "wof:name":"Frank Beasleys Heavy Hauling",
    "wof:placetype":"venue"
},
  "geometry": {"coordinates":[-87.143659,39.546508],"type":"Point"}
}