{
  "type": "Feature",
  "properties": {
    "iso:country":"US",
    "sg:address":"2841 Madison Ave",
    "sg:city":"Indianapolis",
    "sg:classifiers":[
        {
            "category":"Banks & Credit Unions",
            "subcategory":"Bank",
            "type":"Services"
        }
    ],
    "sg:phone":"+1 317 788 1224",
    "sg:postcode":"46225",
    "sg:province":"IN",
    "sg:tags":[
        "cashing",
        "check"
    ],
    "wof:name":"Liquor Cabinet",
    "wof:placetype":"venue"
},
  "geometry": {"coordinates":[-86.151253,39.724642],"type":"Point"}
}