{
  "type": "Feature",
  "properties": {
    "iso:country":"US",
    "sg:address":"325 W Seymour St",
    "sg:city":"Kentland",
    "sg:classifiers":[
        {
            "category":"Retail",
            "subcategory":"Repair Shop",
            "type":"Services"
        }
    ],
    "sg:phone":"+1 219 474 9030",
    "sg:postcode":"47951",
    "sg:province":"IN",
    "sg:tags":[
        "repairing",
        "lawn",
        "mower"
    ],
    "wof:name":"Dale's Repair Plus",
    "wof:placetype":"venue"
},
  "geometry": {"coordinates":[-87.45736599999999,40.768334],"type":"Point"}
}