{
  "type": "Feature",
  "properties": {
    "iso:country":"US",
    "sg:address":"140 E 161st St",
    "sg:city":"Westfield",
    "sg:classifiers":[
        {
            "category":"Building & Trades",
            "subcategory":"Construction",
            "type":"Services"
        }
    ],
    "sg:phone":"+1 317 867 1367",
    "sg:postcode":"46074",
    "sg:province":"IN",
    "sg:tags":[
        "concrete",
        "contractor"
    ],
    "wof:name":"Meyers Construction",
    "wof:placetype":"venue"
},
  "geometry": {"coordinates":[-86.15680999999999,40.021287],"type":"Point"}
}