{
  "type": "Feature",
  "properties": {
    "iso:country":"US",
    "sg:address":"819 E 4th St",
    "sg:city":"Mt Vernon",
    "sg:classifiers":[
        {
            "category":"Food & Beverages",
            "subcategory":"Liquor & Beverages",
            "type":"Retail Goods"
        }
    ],
    "sg:phone":"+1 812 838 2099",
    "sg:postcode":"47620",
    "sg:province":"IN",
    "sg:tags":[
        "wine"
    ],
    "wof:name":"Roadhouse Wines & Spirits",
    "wof:placetype":"venue"
},
  "geometry": {"coordinates":[-87.886467,37.934565],"type":"Point"}
}