{
  "type": "Feature",
  "properties": {
    "iso:country":"US",
    "sg:address":"2150 N Oak Rd",
    "sg:city":"Plymouth",
    "sg:classifiers":[
        {
            "category":"Autos & Motor Vehicles",
            "subcategory":"Auto Supplies",
            "type":"Retail Goods"
        }
    ],
    "sg:phone":"+1 574 936 5504",
    "sg:postcode":"46563",
    "sg:province":"IN",
    "sg:tags":[
        "tire"
    ],
    "wof:name":"Plymouth Tire & Svc Ctr",
    "wof:placetype":"venue"
},
  "geometry": {"coordinates":[-86.328797,41.360166],"type":"Point"}
}