{
  "type": "Feature",
  "properties": {
    "iso:country":"US",
    "sg:address":"632 N Center St",
    "sg:city":"Bremen",
    "sg:classifiers":[
        {
            "category":"Wholesale",
            "subcategory":"Farm Supplies",
            "type":"Manufacturing & Wholesale Goods"
        }
    ],
    "sg:phone":"+1 574 546 2457",
    "sg:postcode":"46506",
    "sg:province":"IN",
    "sg:tags":[
        "grain"
    ],
    "wof:name":"Cargill Inc",
    "wof:placetype":"venue"
},
  "geometry": {"coordinates":[-86.146463,41.451923],"type":"Point"}
}