{
  "type": "Feature",
  "properties": {
    "iso:country":"US",
    "sg:address":"15570 Stoney Creek Way",
    "sg:city":"Noblesville",
    "sg:classifiers":[
        {
            "category":"Wholesale",
            "subcategory":"Hardware",
            "type":"Manufacturing & Wholesale Goods"
        }
    ],
    "sg:phone":"+1 317 776 3095",
    "sg:postcode":"46060",
    "sg:province":"IN",
    "sg:tags":[
        "seal"
    ],
    "wof:name":"Sterling Seal",
    "wof:placetype":"venue"
},
  "geometry": {"coordinates":[-86.005647,40.014519],"type":"Point"}
}