{
  "type": "Feature",
  "properties": {
    "iso:country":"US",
    "sg:address":"9325 Saratoga Rd",
    "sg:city":"Fort Wayne",
    "sg:classifiers":[
        {
            "category":"Professional",
            "subcategory":"Management & Consulting",
            "type":"Services"
        }
    ],
    "sg:phone":"+1 260 436 9962",
    "sg:postcode":"46804",
    "sg:province":"IN",
    "wof:name":"Q Plus",
    "wof:placetype":"venue"
},
  "geometry": {"coordinates":[-85.26325199999999,41.037197],"type":"Point"}
}