{
  "type": "Feature",
  "properties": {
    "iso:country":"US",
    "sg:address":"306 State St",
    "sg:city":"Newburgh",
    "sg:classifiers":[
        {
            "category":"Education",
            "subcategory":"School",
            "type":"Public Place"
        }
    ],
    "sg:phone":"+1 812 853 8921",
    "sg:postcode":"47630",
    "sg:province":"IN",
    "wof:name":"Newburgh Elementary School",
    "wof:placetype":"venue"
},
  "geometry": {"coordinates":[-87.405002,37.946434],"type":"Point"}
}