{
  "type": "Feature",
  "properties": {
    "addr:full":"2765 S State Rd 9 Lagrange IN 46761",
    "addr:housenumber":"2765",
    "addr:postcode":"46761",
    "addr:street":"S State Rd 9 Lagrange",
    "iso:country":"US",
    "sg:address":"2765 S State Rd 9",
    "sg:city":"Lagrange",
    "sg:classifiers":[
        {
            "category":"Real Estate",
            "subcategory":"Real Estate Agent",
            "type":"Services"
        }
    ],
    "sg:phone":"+1 260 463 7478",
    "sg:postcode":"46761",
    "sg:province":"IN",
    "sg:tags":[
        "management"
    ],
    "wof:name":"Central Management Group LLC",
    "wof:placetype":"venue"
},
  "geometry": {"coordinates":[-85.398563,41.601445],"type":"Point"}
}