{
  "type": "Feature",
  "properties": {
    "iso:country":"US",
    "sg:address":"4530 Southport Crossings Way",
    "sg:city":"Indianapolis",
    "sg:classifiers":[
        {
            "category":"Restaurant",
            "type":"Food & Drink"
        }
    ],
    "sg:menulink":"http://www.allmenus.com/in/homecroft/17038-damons-grill/menu/",
    "sg:phone":"+1 317 884 1900",
    "sg:postcode":"46237",
    "sg:province":"IN",
    "sg:tags":[
        "barbecue",
        "american",
        "steakhouse",
        "burger"
    ],
    "wof:name":"Damon's Grill",
    "wof:placetype":"venue"
},
  "geometry": {"coordinates":[-86.09210899999999,39.663706],"type":"Point"}
}