{
  "type": "Feature",
  "properties": {
    "iso:country":"US",
    "sg:address":"1021 25th St",
    "sg:city":"Columbus",
    "sg:classifiers":[
        {
            "category":"Retail",
            "subcategory":"Auto Repair",
            "type":"Services"
        }
    ],
    "sg:phone":"+1 812 379 4999",
    "sg:postcode":"47201",
    "sg:province":"IN",
    "sg:tags":[
        "automobile",
        "lubrication"
    ],
    "wof:name":"Grease Pit",
    "wof:placetype":"venue"
},
  "geometry": {"coordinates":[-85.914127,39.222808],"type":"Point"}
}