{
  "type": "Feature",
  "properties": {
    "iso:country":"US",
    "sg:address":"540 E Lincoln St",
    "sg:city":"Millersburg",
    "sg:phone":"+1 574 642 3823",
    "sg:postcode":"46543",
    "sg:province":"IN",
    "sg:tags":[
        "oil"
    ],
    "wof:name":"C & P Oil Co",
    "wof:placetype":"venue"
},
  "geometry": {"coordinates":[-85.691953,41.523167],"type":"Point"}
}