{
  "type": "Feature",
  "properties": {
    "iso:country":"US",
    "sg:address":"1524 E Markland Ave",
    "sg:city":"Kokomo",
    "sg:classifiers":[
        {
            "category":"Retail",
            "subcategory":"Auto Repair",
            "type":"Services"
        }
    ],
    "sg:phone":"+1 765 452 2245",
    "sg:postcode":"46901",
    "sg:province":"IN",
    "sg:tags":[
        "muffler",
        "exhaust",
        "system"
    ],
    "wof:name":"Thrifty Muffler & Automotive",
    "wof:placetype":"venue"
},
  "geometry": {"coordinates":[-86.112864,40.476711],"type":"Point"}
}