{
  "type": "Feature",
  "properties": {
    "iso:country":"US",
    "sg:address":"4229 N Emerson Ave",
    "sg:city":"Indianapolis",
    "sg:classifiers":[
        {
            "category":"Shopping",
            "subcategory":"Clothing, Apparel, & Fashions",
            "type":"Retail Goods"
        }
    ],
    "sg:phone":"+1 317 549 2473",
    "sg:postcode":"46226",
    "sg:province":"IN",
    "sg:tags":[
        "item",
        "boutique"
    ],
    "wof:name":"J J Fashion & Fragrances",
    "wof:placetype":"venue"
},
  "geometry": {"coordinates":[-86.083715,39.833895],"type":"Point"}
}