{
  "type": "Feature",
  "properties": {
    "iso:country":"US",
    "sg:address":"2817 Larwill Ct",
    "sg:city":"Fort Wayne",
    "sg:classifiers":[
        {
            "category":"Shopping",
            "subcategory":"Used Merchandise",
            "type":"Retail Goods"
        }
    ],
    "sg:phone":"+1 260 745 4286",
    "sg:postcode":"46806",
    "sg:province":"IN",
    "sg:tags":[
        "antique"
    ],
    "wof:name":"Putman's Antique Shop",
    "wof:placetype":"venue"
},
  "geometry": {"coordinates":[-85.101563,41.058911],"type":"Point"}
}