{
  "type": "Feature",
  "properties": {
    "addr:full":"7505 Crews Dr Indianapolis IN 46226",
    "addr:housenumber":"7505",
    "addr:postcode":"46226",
    "addr:street":"Crews Dr",
    "iso:country":"US",
    "sg:address":"7505 Crews Dr",
    "sg:city":"Indianapolis",
    "sg:classifiers":[
        {
            "category":"Wholesale",
            "subcategory":"Vending Machines",
            "type":"Manufacturing & Wholesale Goods"
        }
    ],
    "sg:phone":"+1 317 377 1690",
    "sg:postcode":"46226",
    "sg:province":"IN",
    "sg:website":"www.avifoodsystems.com",
    "wof:name":"AVI Foodsystems Inc",
    "wof:placetype":"venue"
},
  "geometry": {"coordinates":[-86.035719,39.835308],"type":"Point"}
}