{
  "type": "Feature",
  "properties": {
    "iso:country":"US",
    "sg:address":"11160 S 990 E",
    "sg:city":"Upland",
    "sg:classifiers":[
        {
            "category":"Organizations",
            "subcategory":"Community Association",
            "type":"Services"
        }
    ],
    "sg:phone":"+1 765 998 1459",
    "sg:postcode":"46989",
    "sg:province":"IN",
    "sg:tags":[
        "club"
    ],
    "wof:name":"Matthews Lions Club",
    "wof:placetype":"venue"
},
  "geometry": {"coordinates":[-85.485535,40.385673],"type":"Point"}
}