{
  "type": "Feature",
  "properties": {
    "iso:country":"US",
    "sg:address":"10792 Woodmont Ln",
    "sg:city":"Fishers",
    "sg:classifiers":[
        {
            "category":"Education",
            "subcategory":"Vocational School",
            "type":"Public Place"
        }
    ],
    "sg:phone":"+1 317 842 4315",
    "sg:postcode":"46037",
    "sg:province":"IN",
    "sg:tags":[
        "processing",
        "datum"
    ],
    "wof:name":"S V I Training Products",
    "wof:placetype":"venue"
},
  "geometry": {"coordinates":[-85.976867,39.93104],"type":"Point"}
}