{
  "type": "Feature",
  "properties": {
    "iso:country":"US",
    "sg:address":"2960 State Rd 62",
    "sg:city":"Jeffersonville",
    "sg:classifiers":[
        {
            "category":"Shopping",
            "subcategory":"Department Store",
            "type":"Retail Goods"
        }
    ],
    "sg:phone":"+1 812 288 9081",
    "sg:postcode":"47130",
    "sg:province":"IN",
    "wof:name":"Kmart",
    "wof:placetype":"venue"
},
  "geometry": {"coordinates":[-85.713301,38.321458],"type":"Point"}
}