{
  "type": "Feature",
  "properties": {
    "addr:full":"307 Walnut St Lawrenceburg IN 47025",
    "addr:housenumber":"307",
    "addr:postcode":"47025",
    "addr:street":"Walnut St",
    "iso:country":"US",
    "sg:address":"307 Walnut St",
    "sg:city":"Lawrenceburg",
    "sg:classifiers":[
        {
            "category":"Insurance",
            "subcategory":"Insurance Agent",
            "type":"Services"
        }
    ],
    "sg:phone":"+1 812 537 0311",
    "sg:postcode":"47025",
    "sg:province":"IN",
    "wof:name":"Tri-State Insurance",
    "wof:placetype":"venue"
},
  "geometry": {"coordinates":[-84.851041,39.095142],"type":"Point"}
}