{
  "type": "Feature",
  "properties": {
    "iso:country":"US",
    "sg:address":"217 E 5th St",
    "sg:city":"Fowler",
    "sg:classifiers":[
        {
            "category":"Shopping",
            "subcategory":"Florist",
            "type":"Retail Goods"
        }
    ],
    "sg:phone":"+1 765 884 0403",
    "sg:postcode":"47944",
    "sg:province":"IN",
    "wof:name":"Blossom Corner",
    "wof:placetype":"venue"
},
  "geometry": {"coordinates":[-87.322038,40.617766],"type":"Point"}
}