{
  "type": "Feature",
  "properties": {
    "iso:country":"US",
    "sg:address":"405 Mason St",
    "sg:city":"Cannelton",
    "sg:classifiers":[
        {
            "category":"Government",
            "subcategory":"Office",
            "type":"Public Place"
        }
    ],
    "sg:phone":"+1 812 548 2287",
    "sg:postcode":"47520",
    "sg:province":"IN",
    "sg:tags":[
        "village"
    ],
    "wof:name":"Cannelton City Trash Bldg",
    "wof:placetype":"venue"
},
  "geometry": {"coordinates":[-86.746186,37.914764],"type":"Point"}
}