{
  "type": "Feature",
  "properties": {
    "iso:country":"US",
    "sg:address":"915 E Willard St",
    "sg:city":"Muncie",
    "sg:classifiers":[
        {
            "category":"Retail",
            "subcategory":"Funeral Services",
            "type":"Services"
        }
    ],
    "sg:phone":"+1 765 284 4449",
    "sg:postcode":"47302",
    "sg:province":"IN",
    "sg:tags":[
        "director"
    ],
    "wof:name":"Faulkner's Mortuary",
    "wof:placetype":"venue"
},
  "geometry": {"coordinates":[-85.376181,40.185517],"type":"Point"}
}