{
  "type": "Feature",
  "properties": {
    "iso:country":"US",
    "sg:address":"2201 E Troy Ave",
    "sg:city":"Indianapolis",
    "sg:classifiers":[
        {
            "category":"Autos & Motor Vehicles",
            "subcategory":"Automobile Sales",
            "type":"Retail Goods"
        }
    ],
    "sg:phone":"+1 317 791 1401",
    "sg:postcode":"46203",
    "sg:province":"IN",
    "sg:tags":[
        "used"
    ],
    "wof:name":"E Z Car Sales",
    "wof:placetype":"venue"
},
  "geometry": {"coordinates":[-86.122424,39.723056],"type":"Point"}
}