{
  "type": "Feature",
  "properties": {
    "addr:full":"20 Highland St Hammond IN 46320",
    "addr:housenumber":"20",
    "addr:postcode":"46320",
    "addr:street":"Highland St",
    "iso:country":"US",
    "sg:address":"20 Highland St",
    "sg:city":"Hammond",
    "sg:classifiers":[
        {
            "category":"Banks & Credit Unions",
            "subcategory":"Investment Brokerage",
            "type":"Services"
        }
    ],
    "sg:phone":"+1 219 931 6031",
    "sg:postcode":"46320",
    "sg:province":"IN",
    "wof:name":"Wealth Investment",
    "wof:placetype":"venue"
},
  "geometry": {"coordinates":[-87.5222,41.604108],"type":"Point"}
}