{
  "type": "Feature",
  "properties": {
    "iso:country":"US",
    "sg:address":"5980 N Main St",
    "sg:city":"Uniondale",
    "sg:classifiers":[
        {
            "category":"Government",
            "subcategory":"Office",
            "type":"Public Place"
        }
    ],
    "sg:phone":"+1 260 543 2208",
    "sg:postcode":"46791",
    "sg:province":"IN",
    "sg:tags":[
        "village"
    ],
    "wof:name":"Uniondale City Office",
    "wof:placetype":"venue"
},
  "geometry": {"coordinates":[-85.242112,40.82919],"type":"Point"}
}