{
  "type": "Feature",
  "properties": {
    "iso:country":"US",
    "sg:address":"702 S Bloomington St",
    "sg:city":"Greencastle",
    "sg:classifiers":[
        {
            "category":"Shopping",
            "subcategory":"Tobacco",
            "type":"Retail Goods"
        }
    ],
    "sg:phone":"+1 765 653 1976",
    "sg:postcode":"46135",
    "sg:province":"IN",
    "sg:tags":[
        "cigarette",
        "cigar",
        "dealer"
    ],
    "wof:name":"Kocolene Marketing LLC",
    "wof:placetype":"venue"
},
  "geometry": {"coordinates":[-86.853289,39.6353],"type":"Point"}
}