{
  "type": "Feature",
  "properties": {
    "addr:full":"9105 Clubridge Dr Fort Wayne IN 46809",
    "addr:postcode":"9105;46809",
    "addr:street":"Clubridge Dr",
    "iso:country":"US",
    "sg:address":"9105 Clubridge Dr",
    "sg:city":"Fort Wayne",
    "sg:classifiers":[
        {
            "category":"Manufacturing",
            "subcategory":"Tools & Machinery",
            "type":"Manufacturing & Wholesale Goods"
        }
    ],
    "sg:phone":"+1 260 479 2383",
    "sg:postcode":"46809",
    "sg:province":"IN",
    "sg:tags":[
        "equipment",
        "hydraulic"
    ],
    "wof:name":"Mantech Manifold",
    "wof:placetype":"venue"
},
  "geometry": {"coordinates":[-85.180785,40.999532],"type":"Point"}
}