{
  "type": "Feature",
  "properties": {
    "iso:country":"US",
    "sg:address":"45 E State Rd 218",
    "sg:city":"Berne",
    "sg:classifiers":[
        {
            "category":"Building & Trades",
            "subcategory":"Construction",
            "type":"Services"
        }
    ],
    "sg:phone":"+1 260 589 8831",
    "sg:postcode":"46711",
    "sg:province":"IN",
    "sg:tags":[
        "general",
        "contractor"
    ],
    "wof:name":"Tom Jones Construction",
    "wof:placetype":"venue"
},
  "geometry": {"coordinates":[-84.93545899999999,40.658251],"type":"Point"}
}