{
  "type": "Feature",
  "properties": {
    "iso:country":"US",
    "sg:address":"3325 Bexley Ct",
    "sg:city":"Evansville",
    "sg:classifiers":[
        {
            "category":"Retail",
            "subcategory":"Laundry & Dry Cleaning",
            "type":"Services"
        }
    ],
    "sg:phone":"+1 812 473 4787",
    "sg:postcode":"47711",
    "sg:province":"IN",
    "sg:tags":[
        "cleaners",
        "rug",
        "carpet"
    ],
    "wof:name":"Superior Carpet Cleaning Svc",
    "wof:placetype":"venue"
},
  "geometry": {"coordinates":[-87.507124,38.024825],"type":"Point"}
}