{
  "type": "Feature",
  "properties": {
    "iso:country":"US",
    "sg:address":"620 N Mulberry St",
    "sg:city":"Muncie",
    "sg:classifiers":[
        {
            "category":"Government",
            "subcategory":"Police Station",
            "type":"Public Place"
        }
    ],
    "sg:phone":"+1 765 747 4710",
    "sg:postcode":"47305",
    "sg:province":"IN",
    "sg:tags":[
        "department"
    ],
    "wof:name":"Police Horse Barn",
    "wof:placetype":"venue"
},
  "geometry": {"coordinates":[-85.385173,40.198128],"type":"Point"}
}