{
  "type": "Feature",
  "properties": {
    "iso:country":"US",
    "sg:address":"321 E 8th St",
    "sg:city":"Rochester",
    "sg:classifiers":[
        {
            "category":"Social Services",
            "type":"Services"
        }
    ],
    "sg:phone":"+1 574 223 8929",
    "sg:postcode":"46975",
    "sg:province":"IN",
    "sg:tags":[
        "organization",
        "welfare"
    ],
    "wof:name":"United Way",
    "wof:placetype":"venue"
},
  "geometry": {"coordinates":[-86.212777,41.065943],"type":"Point"}
}