{
  "type": "Feature",
  "properties": {
    "addr:full":"3400 Broadway Gary IN 46408",
    "addr:housenumber":"3400",
    "addr:postcode":"46408",
    "addr:street":"Broadway",
    "iso:country":"US",
    "sg:address":"3400 Broadway",
    "sg:city":"Gary",
    "sg:classifiers":[
        {
            "category":"Education",
            "subcategory":"Library",
            "type":"Public Place"
        }
    ],
    "sg:phone":"+1 219 980 6797",
    "sg:postcode":"46408",
    "sg:province":"IN",
    "wof:name":"Lake County Central Law L",
    "wof:placetype":"venue"
},
  "geometry": {"coordinates":[-87.336563,41.556702],"type":"Point"}
}