{
  "type": "Feature",
  "properties": {
    "iso:country":"US",
    "sg:address":"2925 S Co Rd 400 W",
    "sg:city":"New Castle",
    "sg:classifiers":[
        {
            "category":"Building & Trades",
            "subcategory":"Construction",
            "type":"Services"
        }
    ],
    "sg:phone":"+1 765 987 7015",
    "sg:postcode":"47362",
    "sg:province":"IN",
    "sg:tags":[
        "pipe",
        "line",
        "contractor"
    ],
    "wof:name":"Mid-States Construction Co",
    "wof:placetype":"venue"
},
  "geometry": {"coordinates":[-85.462373,39.887968],"type":"Point"}
}