{
  "type": "Feature",
  "properties": {
    "addr:full":"2513 S Roena St Indianapolis IN 46241",
    "addr:housenumber":"2513",
    "addr:postcode":"46241",
    "addr:street":"S Roena St",
    "iso:country":"US",
    "sg:address":"2513 S Roena St",
    "sg:city":"Indianapolis",
    "sg:classifiers":[
        {
            "category":"Shopping",
            "subcategory":"Pets & Pet Supplies",
            "type":"Retail Goods"
        },
        {
            "category":"Retail",
            "subcategory":"Animal Services",
            "type":"Services"
        }
    ],
    "sg:phone":"+1 317 248 2858",
    "sg:postcode":"46241",
    "sg:province":"IN",
    "sg:tags":[
        "grooming",
        "dog",
        "cat"
    ],
    "wof:name":"Southwest Dog Grooming",
    "wof:placetype":"venue"
},
  "geometry": {"coordinates":[-86.234596,39.729194],"type":"Point"}
}