{
  "type": "Feature",
  "properties": {
    "iso:country":"US",
    "sg:address":"10605 Memphis Charlestown Rd",
    "sg:city":"Memphis",
    "sg:classifiers":[
        {
            "category":"Building & Trades",
            "subcategory":"Plumbing",
            "type":"Services"
        }
    ],
    "sg:phone":"+1 812 246 6263",
    "sg:postcode":"47143",
    "sg:province":"IN",
    "wof:name":"Lindley Plumbing Inc",
    "wof:placetype":"venue"
},
  "geometry": {"coordinates":[-85.733369,38.46409],"type":"Point"}
}