{
  "type": "Feature",
  "properties": {
    "iso:country":"US",
    "sg:address":"2511 E 46th St",
    "sg:city":"Indianapolis",
    "sg:classifiers":[
        {
            "category":"Social Services",
            "type":"Services"
        }
    ],
    "sg:phone":"+1 317 541 1005",
    "sg:postcode":"46205",
    "sg:province":"IN",
    "sg:tags":[
        "counseling"
    ],
    "wof:name":"Alpha Counseling",
    "wof:placetype":"venue"
},
  "geometry": {"coordinates":[-86.119612,39.840176],"type":"Point"}
}