{
  "type": "Feature",
  "properties": {
    "addr:full":"2222 S Rogers St Bloomington IN 47403",
    "addr:housenumber":"2222",
    "addr:postcode":"47403",
    "addr:street":"S Rogers St",
    "iso:country":"US",
    "sg:address":"2222 S Rogers St",
    "sg:city":"Bloomington",
    "sg:classifiers":[
        {
            "category":"Banks & Credit Unions",
            "subcategory":"Bank",
            "type":"Services"
        }
    ],
    "sg:phone":"+1 812 339 9006",
    "sg:postcode":"47403",
    "sg:province":"IN",
    "sg:tags":[
        "loan",
        "real estate"
    ],
    "wof:name":"Homeowners Mortgage Co",
    "wof:placetype":"venue"
},
  "geometry": {"coordinates":[-86.538982,39.143028],"type":"Point"}
}