{
  "type": "Feature",
  "properties": {
    "iso:country":"US",
    "sg:address":"7909 Teel Way",
    "sg:city":"Indianapolis",
    "sg:classifiers":[
        {
            "category":"Health Services",
            "subcategory":"Clinic",
            "type":"Services"
        }
    ],
    "sg:phone":"+1 317 522 6179",
    "sg:postcode":"46256",
    "sg:province":"IN",
    "sg:tags":[
        "organization",
        "medical",
        "surgical"
    ],
    "wof:name":"Dasco Technologies Inc",
    "wof:placetype":"venue"
},
  "geometry": {"coordinates":[-86.019806,39.897439],"type":"Point"}
}