{
  "type": "Feature",
  "properties": {
    "iso:country":"US",
    "sg:address":"1113 E National Ave",
    "sg:city":"Brazil",
    "sg:classifiers":[
        {
            "category":"Banks & Credit Unions",
            "subcategory":"Bank",
            "type":"Services"
        }
    ],
    "sg:phone":"+1 812 443 0403",
    "sg:postcode":"47834",
    "sg:province":"IN",
    "sg:tags":[
        "cashing",
        "check"
    ],
    "wof:name":"First Cash Advance",
    "wof:placetype":"venue"
},
  "geometry": {"coordinates":[-87.111822,39.52675],"type":"Point"}
}