{
  "type": "Feature",
  "properties": {
    "addr:full":"9905 W 133rd Ave Cedar Lake IN 46303",
    "addr:housenumber":"9905",
    "addr:postcode":"46303",
    "addr:street":"W 133Rd Ave",
    "iso:country":"US",
    "sg:address":"9905 W 133rd Ave",
    "sg:city":"Cedar Lake",
    "sg:classifiers":[
        {
            "category":"Shopping",
            "subcategory":"Pharmacy",
            "type":"Retail Goods"
        }
    ],
    "sg:phone":"+1 219 374 4537",
    "sg:postcode":"46303",
    "sg:province":"IN",
    "wof:name":"CVS Pharmacy",
    "wof:placetype":"venue"
},
  "geometry": {"coordinates":[-87.45401,41.377222],"type":"Point"}
}