{
  "type": "Feature",
  "properties": {
    "iso:country":"US",
    "sg:address":"3500 Depauw Blvd",
    "sg:city":"Indianapolis",
    "sg:classifiers":[
        {
            "category":"Professional",
            "subcategory":"Management & Consulting",
            "type":"Services"
        }
    ],
    "sg:phone":"+1 317 228 6336",
    "sg:postcode":"46268",
    "sg:province":"IN",
    "sg:tags":[
        "marketing",
        "consultant"
    ],
    "wof:name":"SMS Group Inc",
    "wof:placetype":"venue"
},
  "geometry": {"coordinates":[-86.22490999999999,39.920215],"type":"Point"}
}