{
  "type": "Feature",
  "properties": {
    "iso:country":"US",
    "sg:address":"401 W 23rd St",
    "sg:city":"Muncie",
    "sg:classifiers":[
        {
            "category":"Manufacturing",
            "subcategory":"Tools & Machinery",
            "type":"Manufacturing & Wholesale Goods"
        }
    ],
    "sg:phone":"+1 765 282 2261",
    "sg:postcode":"47302",
    "sg:province":"IN",
    "sg:tags":[
        "power",
        "mechanical"
    ],
    "sg:website":"www.beckettbronze.com",
    "wof:name":"Beckett Bronze Co",
    "wof:placetype":"venue"
},
  "geometry": {"coordinates":[-85.39092599999999,40.167415],"type":"Point"}
}