{
  "type": "Feature",
  "properties": {
    "iso:country":"US",
    "sg:address":"311 W 8th St",
    "sg:city":"Peru",
    "sg:classifiers":[
        {
            "category":"Manufacturing",
            "subcategory":"Printing",
            "type":"Manufacturing & Wholesale Goods"
        }
    ],
    "sg:phone":"+1 765 473 4460",
    "sg:postcode":"46970",
    "sg:province":"IN",
    "sg:tags":[
        "screen"
    ],
    "wof:name":"Action Gear",
    "wof:placetype":"venue"
},
  "geometry": {"coordinates":[-86.080893,40.752862],"type":"Point"}
}