{
  "type": "Feature",
  "properties": {
    "iso:country":"US",
    "sg:address":"1020 W State Blvd",
    "sg:city":"Fort Wayne",
    "sg:classifiers":[
        {
            "category":"Professional",
            "subcategory":"Accounting & Tax Preparation",
            "type":"Services"
        }
    ],
    "sg:phone":"+1 260 483 3339",
    "sg:postcode":"46808",
    "sg:province":"IN",
    "sg:tags":[
        "accountant"
    ],
    "wof:name":"Richard E Walker CPA",
    "wof:placetype":"venue"
},
  "geometry": {"coordinates":[-85.15590899999999,41.096055],"type":"Point"}
}