{
  "type": "Feature",
  "properties": {
    "iso:country":"US",
    "sg:address":"736 Middleton Run Rd",
    "sg:city":"Elkhart",
    "sg:classifiers":[
        {
            "category":"Restaurant",
            "type":"Food & Drink"
        }
    ],
    "sg:phone":"+1 574 293 4604",
    "sg:postcode":"46516",
    "sg:province":"IN",
    "wof:name":"Mayberry Cafe",
    "wof:placetype":"venue"
},
  "geometry": {"coordinates":[-85.9172,41.685045],"type":"Point"}
}