{
  "type": "Feature",
  "properties": {
    "iso:country":"US",
    "sg:address":"5910 Prophets Rock Rd",
    "sg:city":"West Lafayette",
    "sg:classifiers":[
        {
            "category":"Professional",
            "subcategory":"Advertising",
            "type":"Services"
        }
    ],
    "sg:phone":"+1 765 567 2242",
    "sg:postcode":"47906",
    "sg:province":"IN",
    "sg:tags":[
        "counselor"
    ],
    "wof:name":"Circle Advertising Assoc",
    "wof:placetype":"venue"
},
  "geometry": {"coordinates":[-86.855729,40.50099],"type":"Point"}
}