{
  "type": "Feature",
  "properties": {
    "iso:country":"US",
    "sg:address":"4218 Hobson Rd",
    "sg:city":"Fort Wayne",
    "sg:classifiers":[
        {
            "category":"Real Estate",
            "subcategory":"Real Estate Agent",
            "type":"Services"
        }
    ],
    "sg:phone":"+1 260 485 0667",
    "sg:postcode":"46815",
    "sg:province":"IN",
    "wof:name":"Appraisers Brokers & Conslnts",
    "wof:placetype":"venue"
},
  "geometry": {"coordinates":[-85.099689,41.116695],"type":"Point"}
}