{
  "type": "Feature",
  "properties": {
    "iso:country":"US",
    "sg:address":"9601 E 21st St",
    "sg:city":"Indianapolis",
    "sg:classifiers":[
        {
            "category":"Education",
            "subcategory":"School",
            "type":"Public Place"
        }
    ],
    "sg:phone":"+1 317 532 2850",
    "sg:postcode":"46229",
    "sg:province":"IN",
    "wof:name":"Lakeside Elementary School",
    "wof:placetype":"venue"
},
  "geometry": {"coordinates":[-85.99594399999999,39.796853],"type":"Point"}
}