{
  "type": "Feature",
  "properties": {
    "iso:country":"US",
    "sg:address":"9487 W State Rd 120",
    "sg:city":"Orland",
    "sg:classifiers":[
        {
            "category":"Government",
            "subcategory":"Office",
            "type":"Public Place"
        }
    ],
    "sg:phone":"+1 260 829 6411",
    "sg:postcode":"46776",
    "sg:province":"IN",
    "sg:tags":[
        "village"
    ],
    "wof:name":"Orland Clerk's Office",
    "wof:placetype":"venue"
},
  "geometry": {"coordinates":[-85.171014,41.7306],"type":"Point"}
}