{
  "type": "Feature",
  "properties": {
    "addr:full":"124 Melchoir Dr S Santa Claus IN 47579",
    "addr:housenumber":"124",
    "addr:postcode":"47579",
    "addr:street":"Melchoir Dr S",
    "iso:country":"US",
    "sg:address":"124 Melchoir Dr S",
    "sg:city":"Santa Claus",
    "sg:classifiers":[
        {
            "category":"Organizations",
            "subcategory":"Religious Organization",
            "type":"Services"
        }
    ],
    "sg:phone":"+1 812 544 2273",
    "sg:postcode":"47579",
    "sg:province":"IN",
    "wof:name":"Ralph Kempski Rev",
    "wof:placetype":"venue"
},
  "geometry": {"coordinates":[-86.92812499999999,38.104903],"type":"Point"}
}