{
  "type": "Feature",
  "properties": {
    "iso:country":"US",
    "sg:address":"230 W 200 N",
    "sg:city":"Lagrange",
    "sg:classifiers":[
        {
            "category":"Wholesale",
            "subcategory":"Machinery & Supplies",
            "type":"Manufacturing & Wholesale Goods"
        }
    ],
    "sg:phone":"+1 260 463 4019",
    "sg:postcode":"46761",
    "sg:province":"IN",
    "sg:tags":[
        "equipment",
        "irrigation",
        "system"
    ],
    "wof:name":"Miller Irrigation Inc",
    "wof:placetype":"venue"
},
  "geometry": {"coordinates":[-85.429143,41.670339],"type":"Point"}
}