{
  "type": "Feature",
  "properties": {
    "iso:country":"US",
    "sg:address":"515 45th St",
    "sg:city":"Munster",
    "sg:classifiers":[
        {
            "category":"Professional",
            "subcategory":"Advertising",
            "type":"Services"
        }
    ],
    "sg:phone":"+1 219 922 2880",
    "sg:postcode":"46321",
    "sg:province":"IN",
    "wof:name":"NWI.COM",
    "wof:placetype":"venue"
},
  "geometry": {"coordinates":[-87.509456,41.539703],"type":"Point"}
}