{
  "type": "Feature",
  "properties": {
    "iso:country":"US",
    "sg:address":"4300 Division St",
    "sg:city":"Evansville",
    "sg:classifiers":[
        {
            "category":"Autos & Motor Vehicles",
            "subcategory":"Automobile Sales",
            "type":"Retail Goods"
        }
    ],
    "sg:phone":"+1 812 477 6201",
    "sg:postcode":"47715",
    "sg:province":"IN",
    "sg:tags":[
        "car",
        "dealer"
    ],
    "sg:website":"www.lindsaylincolnmercury.com",
    "wof:name":"D-Patrick Lincoln Mercury",
    "wof:placetype":"venue"
},
  "geometry": {"coordinates":[-87.494329,37.976873],"type":"Point"}
}