{
  "type": "Feature",
  "properties": {
    "addr:full":"13312 Wicker Ave Cedar Lake IN 46303",
    "addr:housenumber":"13312",
    "addr:postcode":"46303",
    "addr:street":"Wicker Ave",
    "iso:country":"US",
    "sg:address":"13312 Wicker Ave",
    "sg:city":"Cedar Lake",
    "sg:classifiers":[
        {
            "category":"Restaurant",
            "type":"Food & Drink"
        }
    ],
    "sg:menulink":"http://www.allmenus.com/in/hanover/186281-mcdonalds/menu/",
    "sg:postcode":"46303",
    "sg:province":"IN",
    "sg:tags":[
        "burger",
        "american"
    ],
    "wof:name":"McDonald's",
    "wof:placetype":"venue"
},
  "geometry": {"coordinates":[-87.469995,41.376978],"type":"Point"}
}