{
  "type": "Feature",
  "properties": {
    "iso:country":"US",
    "sg:address":"2208 E Paulding Rd",
    "sg:city":"Fort Wayne",
    "sg:classifiers":[
        {
            "category":"Personal",
            "subcategory":"Beauty Salon",
            "type":"Services"
        }
    ],
    "sg:phone":"+1 260 441 2535",
    "sg:postcode":"46816",
    "sg:province":"IN",
    "sg:tags":[
        "shop"
    ],
    "wof:name":"Linda House of Nails",
    "wof:placetype":"venue"
},
  "geometry": {"coordinates":[-85.108189,41.032036],"type":"Point"}
}