{
  "type": "Feature",
  "properties": {
    "iso:country":"US",
    "sg:address":"524 W Exchange St",
    "sg:city":"Crete",
    "sg:classifiers":[
        {
            "category":"Government",
            "subcategory":"Office",
            "type":"Public Place"
        }
    ],
    "sg:phone":"+1 708 672 3148",
    "sg:postcode":"60417",
    "sg:province":"IN",
    "sg:tags":[
        "village"
    ],
    "wof:name":"Crete Village Hall",
    "wof:placetype":"venue"
},
  "geometry": {"coordinates":[-87.63269,41.444442],"type":"Point"}
}