{
  "type": "Feature",
  "properties": {
    "iso:country":"US",
    "sg:address":"628 Michigan Ave",
    "sg:city":"Jeffersonville",
    "sg:classifiers":[
        {
            "category":"Retail",
            "subcategory":"Auto Repair",
            "type":"Services"
        }
    ],
    "sg:phone":"+1 812 283 8219",
    "sg:postcode":"47130",
    "sg:province":"IN",
    "sg:tags":[
        "body",
        "repairing",
        "painting",
        "automobile"
    ],
    "sg:website":"http://www.grayandwellsbodyshop.com",
    "wof:name":"Gray & Wells Body Shop Inc",
    "wof:placetype":"venue"
},
  "geometry": {"coordinates":[-85.744592,38.274499],"type":"Point"}
}