{
  "type": "Feature",
  "properties": {
    "iso:country":"US",
    "sg:address":"1607 S Rogers St",
    "sg:city":"Bloomington",
    "sg:classifiers":[
        {
            "category":"Freight",
            "type":"Transportation"
        }
    ],
    "sg:phone":"+1 812 333 4755",
    "sg:postcode":"47403",
    "sg:province":"IN",
    "sg:tags":[
        "mover"
    ],
    "wof:name":"A Soft Touch Moving & Storage",
    "wof:placetype":"venue"
},
  "geometry": {"coordinates":[-86.538778,39.147024],"type":"Point"}
}