{
  "type": "Feature",
  "properties": {
    "iso:country":"US",
    "sg:address":"234 W Pearl St",
    "sg:city":"Dunkirk",
    "sg:classifiers":[
        {
            "category":"Education",
            "subcategory":"School",
            "type":"Public Place"
        }
    ],
    "sg:phone":"+1 765 768 6075",
    "sg:postcode":"47336",
    "sg:province":"IN",
    "wof:name":"Westlawn Elementary School",
    "wof:placetype":"venue"
},
  "geometry": {"coordinates":[-85.215327,40.370379],"type":"Point"}
}