{
  "type": "Feature",
  "properties": {
    "iso:country":"US",
    "sg:address":"3206 Cascade Dr",
    "sg:city":"Valparaiso",
    "sg:classifiers":[
        {
            "category":"Professional",
            "type":"Services"
        }
    ],
    "sg:phone":"+1 219 465 5147",
    "sg:postcode":"46383",
    "sg:province":"IN",
    "sg:tags":[
        "establishment"
    ],
    "wof:name":"VIP America",
    "wof:placetype":"venue"
},
  "geometry": {"coordinates":[-87.026222,41.474845],"type":"Point"}
}