{
  "type": "Feature",
  "properties": {
    "iso:country":"US",
    "sg:address":"2507 W 3rd St",
    "sg:city":"Bloomington",
    "sg:classifiers":[
        {
            "category":"Food & Beverages",
            "subcategory":"Bakery",
            "type":"Retail Goods"
        }
    ],
    "sg:phone":"+1 812 323 9747",
    "sg:postcode":"47404",
    "sg:province":"IN",
    "sg:tags":[
        "doughnut"
    ],
    "wof:name":"Doughworks",
    "wof:placetype":"venue"
},
  "geometry": {"coordinates":[-86.566744,39.164438],"type":"Point"}
}