{
  "type": "Feature",
  "properties": {
    "iso:country":"US",
    "sg:address":"3428 Bowser Ave",
    "sg:city":"Fort Wayne",
    "sg:classifiers":[
        {
            "category":"Personal",
            "subcategory":"Beauty Salon",
            "type":"Services"
        }
    ],
    "sg:phone":"+1 260 456 7397",
    "sg:postcode":"46806",
    "sg:province":"IN",
    "wof:name":"Swift Styles & Smiles",
    "wof:placetype":"venue"
},
  "geometry": {"coordinates":[-85.120267,41.054461],"type":"Point"}
}