{
  "type": "Feature",
  "properties": {
    "iso:country":"US",
    "sg:address":"498 W Jefferson St",
    "sg:city":"Spencer",
    "sg:classifiers":[
        {
            "category":"Real Estate",
            "subcategory":"Developer",
            "type":"Services"
        }
    ],
    "sg:phone":"+1 812 829 2840",
    "sg:postcode":"47460",
    "sg:province":"IN",
    "sg:tags":[
        "cemetery"
    ],
    "wof:name":"Riverside Cemetery Assn",
    "wof:placetype":"venue"
},
  "geometry": {"coordinates":[-86.767706,39.284166],"type":"Point"}
}