{
  "type": "Feature",
  "properties": {
    "addr:full":"514 E Washington Blvd Fort Wayne IN 46802",
    "addr:housenumber":"514",
    "addr:postcode":"46802",
    "addr:street":"E Washington Blvd",
    "iso:country":"US",
    "sg:address":"514 E Washington Blvd",
    "sg:city":"Fort Wayne",
    "sg:classifiers":[
        {
            "category":"Organizations",
            "subcategory":"Non-profit Organization",
            "type":"Services"
        }
    ],
    "sg:phone":"+1 260 422 2450",
    "sg:postcode":"46802",
    "sg:province":"IN",
    "sg:tags":[
        "lesbian",
        "gay"
    ],
    "wof:name":"Up The Stairs Community",
    "wof:placetype":"venue"
},
  "geometry": {"coordinates":[-85.13111600000001,41.078384],"type":"Point"}
}