{
  "type": "Feature",
  "properties": {
    "iso:country":"US",
    "sg:address":"704 Main St",
    "sg:city":"Clay City",
    "sg:classifiers":[
        {
            "category":"Shopping",
            "subcategory":"Jewelry",
            "type":"Retail Goods"
        }
    ],
    "sg:phone":"+1 812 939 2819",
    "sg:postcode":"47841",
    "sg:province":"IN",
    "sg:tags":[
        "jeweler"
    ],
    "wof:name":"Chris Jewelry Repair",
    "wof:placetype":"venue"
},
  "geometry": {"coordinates":[-87.112881,39.27762],"type":"Point"}
}