{
  "type": "Feature",
  "properties": {
    "iso:country":"US",
    "sg:address":"4815 Speedway Dr",
    "sg:city":"Fort Wayne",
    "sg:classifiers":[
        {
            "category":"Home & Garden",
            "subcategory":"Building Materials",
            "type":"Retail Goods"
        }
    ],
    "sg:phone":"+1 260 484 7759",
    "sg:postcode":"46825",
    "sg:province":"IN",
    "sg:tags":[
        "roofing"
    ],
    "sg:website":"www.reesewholesale.com",
    "wof:name":"Reese Central Wholesale Inc",
    "wof:placetype":"venue"
},
  "geometry": {"coordinates":[-85.14265,41.122271],"type":"Point"}
}