{
  "type": "Feature",
  "properties": {
    "iso:country":"US",
    "sg:address":"2051 N College Ave",
    "sg:city":"Indianapolis",
    "sg:classifiers":[
        {
            "category":"Social Services",
            "type":"Services"
        }
    ],
    "sg:phone":"+1 317 283 5730",
    "sg:postcode":"46202",
    "sg:province":"IN",
    "sg:tags":[
        "organization",
        "welfare"
    ],
    "sg:website":"www.q4e.org",
    "wof:name":"Quest For Excellence",
    "wof:placetype":"venue"
},
  "geometry": {"coordinates":[-86.144669,39.794897],"type":"Point"}
}