{
  "type": "Feature",
  "properties": {
    "iso:country":"US",
    "sg:address":"5429 S Anthony Blvd",
    "sg:city":"Fort Wayne",
    "sg:classifiers":[
        {
            "category":"Retail",
            "subcategory":"Self-service Laundry",
            "type":"Services"
        }
    ],
    "sg:phone":"+1 260 447 5111",
    "sg:postcode":"46806",
    "sg:province":"IN",
    "sg:tags":[
        "coin"
    ],
    "wof:name":"Peerless Cleaners",
    "wof:placetype":"venue"
},
  "geometry": {"coordinates":[-85.112758,41.033775],"type":"Point"}
}