{
  "type": "Feature",
  "properties": {
    "addr:full":"11711 N College Ave Carmel IN 46032",
    "addr:housenumber":"11711",
    "addr:postcode":"46032",
    "addr:street":"N College Ave",
    "iso:country":"US",
    "sg:address":"11711 N College Ave",
    "sg:city":"Carmel",
    "sg:classifiers":[
        {
            "category":"Professional",
            "subcategory":"Management & Consulting",
            "type":"Services"
        }
    ],
    "sg:phone":"+1 317 848 7966",
    "sg:postcode":"46032",
    "sg:province":"IN",
    "sg:tags":[
        "employment",
        "screening"
    ],
    "wof:name":"Hire Sucess",
    "wof:placetype":"venue"
},
  "geometry": {"coordinates":[-86.145852,39.959607],"type":"Point"}
}