{
  "type": "Feature",
  "properties": {
    "iso:country":"US",
    "sg:address":"500 W Simpson Chapel Rd",
    "sg:city":"Bloomington",
    "sg:classifiers":[
        {
            "category":"Education",
            "subcategory":"Special Training",
            "type":"Public Place"
        }
    ],
    "sg:phone":"+1 812 876 4903",
    "sg:postcode":"47404",
    "sg:province":"IN",
    "sg:tags":[
        "instruction",
        "music"
    ],
    "wof:name":"Star Of Indiana Brass",
    "wof:placetype":"venue"
},
  "geometry": {"coordinates":[-86.53181499999999,39.273313],"type":"Point"}
}