{
  "type": "Feature",
  "properties": {
    "iso:country":"US",
    "sg:address":"9515 Indianapolis Blvd",
    "sg:city":"Highland",
    "sg:classifiers":[
        {
            "category":"Banks & Credit Unions",
            "subcategory":"Investment Brokerage",
            "type":"Services"
        }
    ],
    "sg:phone":"+1 219 922 0767",
    "sg:postcode":"46322",
    "sg:province":"IN",
    "sg:tags":[
        "security"
    ],
    "wof:name":"Edward Jones Investments",
    "wof:placetype":"venue"
},
  "geometry": {"coordinates":[-87.471153,41.540599],"type":"Point"}
}