{
  "type": "Feature",
  "properties": {
    "iso:country":"US",
    "sg:address":"4216 N College Ave",
    "sg:city":"Indianapolis",
    "sg:classifiers":[
        {
            "category":"Professional",
            "subcategory":"Management & Consulting",
            "type":"Services"
        }
    ],
    "sg:phone":"+1 317 283 4909",
    "sg:postcode":"46205",
    "sg:province":"IN",
    "sg:tags":[
        "fuel"
    ],
    "wof:name":"Bryrod Management",
    "wof:placetype":"venue"
},
  "geometry": {"coordinates":[-86.145223,39.83568],"type":"Point"}
}