{
  "type": "Feature",
  "properties": {
    "addr:full":"1009 Wabash Ave Terre Haute IN 47807",
    "addr:housenumber":"1009",
    "addr:postcode":"47807",
    "addr:street":"Wabash Ave",
    "iso:country":"US",
    "sg:address":"1009 Wabash Ave",
    "sg:city":"Terre Haute",
    "sg:classifiers":[
        {
            "category":"Health Services",
            "subcategory":"Clinic",
            "type":"Services"
        }
    ],
    "sg:phone":"+1 812 232 6442",
    "sg:postcode":"47807",
    "sg:province":"IN",
    "sg:tags":[
        "home"
    ],
    "wof:name":"Meadows Home Health Care Inc",
    "wof:placetype":"venue"
},
  "geometry": {"coordinates":[-87.401483,39.467063],"type":"Point"}
}