{
  "type": "Feature",
  "properties": {
    "iso:country":"US",
    "sg:address":"300 S Meridian St",
    "sg:city":"Indianapolis",
    "sg:classifiers":[
        {
            "category":"Real Estate",
            "subcategory":"Architect",
            "type":"Services"
        }
    ],
    "sg:phone":"+1 317 388 8850",
    "sg:postcode":"46225",
    "sg:province":"IN",
    "sg:tags":[
        "architects'",
        "specification",
        "construction",
        "builders'",
        "architectural"
    ],
    "wof:name":"A2so4 Architecture",
    "wof:placetype":"venue"
},
  "geometry": {"coordinates":[-86.15823399999999,39.762901],"type":"Point"}
}