{
  "type": "Feature",
  "properties": {
    "addr:full":"25943 Co Rd 22 Elkhart IN 46517",
    "addr:housenumber":"25943;22",
    "addr:postcode":"46517",
    "addr:street":"Co Rd",
    "iso:country":"US",
    "sg:address":"25943 Co Rd 22",
    "sg:city":"Elkhart",
    "sg:classifiers":[
        {
            "category":"Education",
            "subcategory":"School",
            "type":"Public Place"
        }
    ],
    "sg:phone":"+1 574 293 1609",
    "sg:postcode":"46517",
    "sg:province":"IN",
    "sg:website":"www.ebcs.com",
    "wof:name":"Elkhart Baptist Christian Schl",
    "wof:placetype":"venue"
},
  "geometry": {"coordinates":[-85.964007,41.637804],"type":"Point"}
}