{
  "type": "Feature",
  "properties": {
    "iso:country":"US",
    "sg:address":"116 W Main St",
    "sg:city":"Madison",
    "sg:classifiers":[
        {
            "category":"Personal",
            "subcategory":"Beauty Salon",
            "type":"Services"
        }
    ],
    "sg:phone":"+1 812 265 4003",
    "sg:postcode":"47250",
    "sg:province":"IN",
    "wof:name":"Mane Attractions",
    "wof:placetype":"venue"
},
  "geometry": {"coordinates":[-85.380541,38.736307],"type":"Point"}
}