{
  "type": "Feature",
  "properties": {
    "iso:country":"US",
    "sg:address":"4120 E 600 N",
    "sg:city":"Decatur",
    "sg:classifiers":[
        {
            "category":"Wholesale",
            "subcategory":"Durable Goods & Equipment",
            "type":"Manufacturing & Wholesale Goods"
        }
    ],
    "sg:phone":"+1 260 724 2301",
    "sg:postcode":"46733",
    "sg:province":"IN",
    "sg:tags":[
        "fire",
        "extinguisher"
    ],
    "wof:name":"Fail-Safe Alarm & Pager Co",
    "wof:placetype":"venue"
},
  "geometry": {"coordinates":[-84.857588,40.833584],"type":"Point"}
}