{
  "type": "Feature",
  "properties": {
    "iso:country":"US",
    "sg:address":"11636 County Farm Rd",
    "sg:city":"Aurora",
    "sg:classifiers":[
        {
            "category":"Government",
            "subcategory":"Office",
            "type":"Public Place"
        }
    ],
    "sg:phone":"+1 812 926 0110",
    "sg:postcode":"47001",
    "sg:province":"IN",
    "wof:name":"YES",
    "wof:placetype":"venue"
},
  "geometry": {"coordinates":[-85.035343,39.150758],"type":"Point"}
}