{
  "type": "Feature",
  "properties": {
    "iso:country":"US",
    "sg:address":"5810 E Schnellville Rd",
    "sg:city":"St Anthony",
    "sg:classifiers":[
        {
            "category":"Building & Trades",
            "subcategory":"Construction",
            "type":"Services"
        }
    ],
    "sg:phone":"+1 812 326 2535",
    "sg:postcode":"47575",
    "sg:province":"IN",
    "sg:tags":[
        "project"
    ],
    "wof:name":"Verkamp Construction",
    "wof:placetype":"venue"
},
  "geometry": {"coordinates":[-86.797114,38.345147],"type":"Point"}
}