{
  "type": "Feature",
  "properties": {
    "iso:country":"US",
    "sg:address":"601 S Orchard St",
    "sg:city":"Kendallville",
    "sg:classifiers":[
        {
            "category":"Social Services",
            "type":"Services"
        }
    ],
    "sg:phone":"+1 260 343 9902",
    "sg:postcode":"46755",
    "sg:province":"IN",
    "sg:tags":[
        "care",
        "center",
        "day"
    ],
    "wof:name":"Kendallville Day Care",
    "wof:placetype":"venue"
},
  "geometry": {"coordinates":[-85.266131,41.436734],"type":"Point"}
}