{
  "type": "Feature",
  "properties": {
    "addr:full":"11119 Grabill Rd Leo IN 46765",
    "addr:housenumber":"11119",
    "addr:postcode":"46765",
    "addr:street":"Grabill Rd Leo",
    "iso:country":"US",
    "sg:address":"11119 Grabill Rd",
    "sg:city":"Leo",
    "sg:classifiers":[
        {
            "category":"Education",
            "subcategory":"Dance Studio",
            "type":"Public Place"
        }
    ],
    "sg:phone":"+1 260 627 3684",
    "sg:postcode":"46765",
    "sg:province":"IN",
    "sg:tags":[
        "instruction",
        "dancing"
    ],
    "wof:name":"Dance NY Style",
    "wof:placetype":"venue"
},
  "geometry": {"coordinates":[-85.003417,41.221678],"type":"Point"}
}