{
  "type": "Feature",
  "properties": {
    "iso:country":"US",
    "sg:address":"6010 W 89th Ln",
    "sg:city":"Crown Point",
    "sg:classifiers":[
        {
            "category":"Professional",
            "type":"Services"
        }
    ],
    "sg:phone":"+1 219 365 8939",
    "sg:postcode":"46307",
    "sg:province":"IN",
    "wof:name":"Unique Events of Northwes",
    "wof:placetype":"venue"
},
  "geometry": {"coordinates":[-87.406757,41.45634],"type":"Point"}
}