{
  "type": "Feature",
  "properties": {
    "iso:country":"US",
    "sg:address":"1407 N Main St",
    "sg:city":"Monticello",
    "sg:classifiers":[
        {
            "category":"Food & Beverages",
            "subcategory":"Meat & Fish",
            "type":"Retail Goods"
        }
    ],
    "sg:phone":"+1 574 583 5152",
    "sg:postcode":"47960",
    "sg:province":"IN",
    "sg:tags":[
        "seafood"
    ],
    "wof:name":"Key West Shrimp",
    "wof:placetype":"venue"
},
  "geometry": {"coordinates":[-86.769158,40.763842],"type":"Point"}
}