{
  "type": "Feature",
  "properties": {
    "iso:country":"US",
    "sg:address":"402 N Hillcrest St",
    "sg:city":"Fort Branch",
    "sg:classifiers":[
        {
            "category":"Building & Trades",
            "subcategory":"Plumbing",
            "type":"Services"
        }
    ],
    "sg:phone":"+1 812 753 4535",
    "sg:postcode":"47648",
    "sg:province":"IN",
    "sg:tags":[
        "heating",
        "contractor"
    ],
    "wof:name":"Sokeland's Heating & Air Cond",
    "wof:placetype":"venue"
},
  "geometry": {"coordinates":[-87.570504,38.25052],"type":"Point"}
}