{
  "type": "Feature",
  "properties": {
    "iso:country":"US",
    "sg:address":"1001 Lincoln Way W",
    "sg:city":"Osceola",
    "sg:classifiers":[
        {
            "category":"Food & Beverages",
            "subcategory":"Groceries & Convenience Stores",
            "type":"Retail Goods"
        }
    ],
    "sg:phone":"+1 574 674 0300",
    "sg:postcode":"46561",
    "sg:province":"IN",
    "wof:name":"Charlies",
    "wof:placetype":"venue"
},
  "geometry": {"coordinates":[-86.084294,41.663219],"type":"Point"}
}