{
  "type": "Feature",
  "properties": {
    "iso:country":"US",
    "sg:address":"947 Monument Dr",
    "sg:city":"Lebanon",
    "sg:classifiers":[
        {
            "category":"Wholesale",
            "subcategory":"Groceries",
            "type":"Manufacturing & Wholesale Goods"
        }
    ],
    "sg:phone":"+1 765 483 9287",
    "sg:postcode":"46052",
    "sg:province":"IN",
    "sg:tags":[
        "tea",
        "coffee"
    ],
    "wof:name":"Brewmaster Coffee Inc",
    "wof:placetype":"venue"
},
  "geometry": {"coordinates":[-86.451338,40.031605],"type":"Point"}
}