{
  "type": "Feature",
  "properties": {
    "iso:country":"US",
    "sg:address":"1770 N River Rd",
    "sg:city":"West Lafayette",
    "sg:classifiers":[
        {
            "category":"Professional",
            "subcategory":"Secretarial Services",
            "type":"Services"
        }
    ],
    "sg:phone":"+1 765 463 0035",
    "sg:postcode":"47906",
    "sg:province":"IN",
    "sg:tags":[
        "convention",
        "court",
        "reporter"
    ],
    "wof:name":"Professional Reporting Svc",
    "wof:placetype":"venue"
},
  "geometry": {"coordinates":[-86.896621,40.444042],"type":"Point"}
}