{
  "type": "Feature",
  "properties": {
    "addr:full":"7411 N Keystone Ave Indianapolis IN 46240",
    "addr:housenumber":"7411",
    "addr:postcode":"46240",
    "addr:street":"N Keystone Ave",
    "iso:country":"US",
    "sg:address":"7411 N Keystone Ave",
    "sg:city":"Indianapolis",
    "sg:classifiers":[
        {
            "category":"Professional",
            "type":"Services"
        }
    ],
    "sg:phone":"+1 317 722 0301",
    "sg:postcode":"46240",
    "sg:province":"IN",
    "sg:tags":[
        "establishment"
    ],
    "wof:name":"INB",
    "wof:placetype":"venue"
},
  "geometry": {"coordinates":[-86.12187299999999,39.890478],"type":"Point"}
}