{
  "type": "Feature",
  "properties": {
    "iso:country":"US",
    "sg:address":"1118 Scatterfield Rd",
    "sg:city":"Anderson",
    "sg:classifiers":[
        {
            "category":"Retail",
            "subcategory":"Auto Repair",
            "type":"Services"
        }
    ],
    "sg:phone":"+1 765 642 3333",
    "sg:postcode":"46012",
    "sg:province":"IN",
    "sg:tags":[
        "automobile",
        "lubrication"
    ],
    "sg:website":"www.greasemonkeyintl.com",
    "wof:name":"Master Express Lube Ctr",
    "wof:placetype":"venue"
},
  "geometry": {"coordinates":[-85.6526,40.105141],"type":"Point"}
}