{
  "type": "Feature",
  "properties": {
    "iso:country":"US",
    "sg:address":"925 Nichol Ave",
    "sg:city":"Anderson",
    "sg:classifiers":[
        {
            "category":"Retail",
            "subcategory":"Car Wash",
            "type":"Services"
        }
    ],
    "sg:phone":"+1 765 642 3475",
    "sg:postcode":"46016",
    "sg:province":"IN",
    "sg:tags":[
        "polishing",
        "washing"
    ],
    "wof:name":"Zalo-Kar Wash",
    "wof:placetype":"venue"
},
  "geometry": {"coordinates":[-85.691692,40.104238],"type":"Point"}
}