{
  "type": "Feature",
  "properties": {
    "iso:country":"US",
    "sg:address":"5119 Executive Blvd",
    "sg:city":"Fort Wayne",
    "sg:classifiers":[
        {
            "category":"Wholesale",
            "subcategory":"Electrical",
            "type":"Manufacturing & Wholesale Goods"
        }
    ],
    "sg:phone":"+1 260 482 3583",
    "sg:postcode":"46808",
    "sg:province":"IN",
    "sg:tags":[
        "battery",
        "repairing",
        "rebuilding"
    ],
    "sg:website":"www.tricitypower.com",
    "wof:name":"Tri City Ind Power",
    "wof:placetype":"venue"
},
  "geometry": {"coordinates":[-85.165997,41.127347],"type":"Point"}
}