{
  "type": "Feature",
  "properties": {
    "iso:country":"US",
    "sg:address":"502 N Riverside Dr",
    "sg:city":"Winamac",
    "sg:classifiers":[
        {
            "category":"Freight",
            "type":"Transportation"
        }
    ],
    "sg:phone":"+1 574 946 4501",
    "sg:postcode":"46996",
    "sg:province":"IN",
    "sg:tags":[
        "operator",
        "local",
        "trucking"
    ],
    "wof:name":"Armstrong Trucking",
    "wof:placetype":"venue"
},
  "geometry": {"coordinates":[-86.603959,41.056156],"type":"Point"}
}