{
  "type": "Feature",
  "properties": {
    "iso:country":"US",
    "sg:address":"5742 Coventry Ln",
    "sg:city":"Fort Wayne",
    "sg:classifiers":[
        {
            "category":"Professional",
            "subcategory":"Accounting & Tax Preparation",
            "type":"Services"
        }
    ],
    "sg:phone":"+1 260 432 9996",
    "sg:postcode":"46804",
    "sg:province":"IN",
    "sg:tags":[
        "accountant"
    ],
    "sg:website":"www.sipecpa.com",
    "wof:name":"Roger Sipe CPA Firm",
    "wof:placetype":"venue"
},
  "geometry": {"coordinates":[-85.255927,41.036716],"type":"Point"}
}