{
  "type": "Feature",
  "properties": {
    "iso:country":"US",
    "sg:address":"832 State Rd 129",
    "sg:city":"Vevay",
    "sg:classifiers":[
        {
            "category":"Organizations",
            "subcategory":"Religious Organization",
            "type":"Services"
        }
    ],
    "sg:phone":"+1 812 427 3437",
    "sg:postcode":"47043",
    "sg:province":"IN",
    "wof:name":"Caledonia Presbyterian Manse",
    "wof:placetype":"venue"
},
  "geometry": {"coordinates":[-85.172501,38.807557],"type":"Point"}
}