{
  "type": "Feature",
  "properties": {
    "iso:country":"US",
    "sg:address":"9502 W Bailey Rd",
    "sg:city":"Wanatah",
    "sg:classifiers":[
        {
            "category":"Retail",
            "subcategory":"Repair Shop",
            "type":"Services"
        }
    ],
    "sg:phone":"+1 219 733 2373",
    "sg:postcode":"46390",
    "sg:province":"IN",
    "wof:name":"Renesaince Refinishing",
    "wof:placetype":"venue"
},
  "geometry": {"coordinates":[-86.887698,41.427694],"type":"Point"}
}