{
  "type": "Feature",
  "properties": {
    "addr:full":"2931 N Warman Ave Indianapolis IN 46222",
    "addr:housenumber":"2931",
    "addr:postcode":"46222",
    "addr:street":"N Warman Ave",
    "iso:country":"US",
    "sg:address":"2931 N Warman Ave",
    "sg:city":"Indianapolis",
    "sg:classifiers":[
        {
            "category":"Real Estate",
            "subcategory":"Real Estate Agent",
            "type":"Services"
        }
    ],
    "sg:phone":"+1 317 924 0218",
    "sg:postcode":"46222",
    "sg:province":"IN",
    "wof:name":"Seven Flags Inc",
    "wof:placetype":"venue"
},
  "geometry": {"coordinates":[-86.20717399999999,39.807999],"type":"Point"}
}