{
  "type": "Feature",
  "properties": {
    "iso:country":"US",
    "sg:address":"1708 Richardt Ave",
    "sg:city":"Evansville",
    "sg:classifiers":[
        {
            "category":"Shopping",
            "type":"Retail Goods"
        },
        {
            "category":"Shopping",
            "subcategory":"Beauty & Cosmetics",
            "type":"Retail Goods"
        }
    ],
    "sg:phone":"+1 812 422 2998",
    "sg:postcode":"47711",
    "sg:province":"IN",
    "sg:tags":[
        "merchandise",
        "perfume"
    ],
    "wof:name":"Viviane Woodard Skin Care Inc",
    "wof:placetype":"venue"
},
  "geometry": {"coordinates":[-87.533457,37.998078],"type":"Point"}
}