{
  "type": "Feature",
  "properties": {
    "iso:country":"US",
    "sg:address":"324 E 36th St",
    "sg:city":"Indianapolis",
    "sg:classifiers":[
        {
            "category":"Professional",
            "subcategory":"Business Services",
            "type":"Services"
        }
    ],
    "sg:phone":"+1 317 926 1913",
    "sg:postcode":"46205",
    "sg:province":"IN",
    "wof:name":"Toni M Reiner",
    "wof:placetype":"venue"
},
  "geometry": {"coordinates":[-86.149945,39.821059],"type":"Point"}
}