{
  "type": "Feature",
  "properties": {
    "iso:country":"US",
    "sg:address":"8152 Meadow Bend Dr",
    "sg:city":"Indianapolis",
    "sg:classifiers":[
        {
            "category":"Manufacturing",
            "subcategory":"Printing",
            "type":"Manufacturing & Wholesale Goods"
        }
    ],
    "sg:phone":"+1 317 862 0806",
    "sg:postcode":"46259",
    "sg:province":"IN",
    "sg:tags":[
        "publishing"
    ],
    "wof:name":"Folk Art To Go",
    "wof:placetype":"venue"
},
  "geometry": {"coordinates":[-86.022586,39.652593],"type":"Point"}
}