{
  "type": "Feature",
  "properties": {
    "iso:country":"US",
    "sg:address":"10800 N State Rd 67-28",
    "sg:city":"Albany",
    "sg:classifiers":[
        {
            "category":"Organizations",
            "subcategory":"Religious Organization",
            "type":"Services"
        }
    ],
    "sg:phone":"+1 765 289 7113",
    "sg:postcode":"47320",
    "sg:province":"IN",
    "sg:tags":[
        "church"
    ],
    "wof:name":"Eastside Missionary Baptist",
    "wof:placetype":"venue"
},
  "geometry": {"coordinates":[-85.305527,40.28753],"type":"Point"}
}