{
  "type": "Feature",
  "properties": {
    "addr:full":"7565 N 1000 W Shipshewana IN 46565",
    "addr:housenumber":"7565",
    "addr:postcode":"46565",
    "addr:street":"N 1000 W",
    "iso:country":"US",
    "sg:address":"7565 N 1000 W",
    "sg:city":"Shipshewana",
    "sg:classifiers":[
        {
            "category":"Professional",
            "subcategory":"Business Services",
            "type":"Services"
        }
    ],
    "sg:phone":"+1 260 463 1229",
    "sg:postcode":"46565",
    "sg:province":"IN",
    "wof:name":"Thomas R Doliste",
    "wof:placetype":"venue"
},
  "geometry": {"coordinates":[-85.62179999999999,41.751253],"type":"Point"}
}