{
  "type": "Feature",
  "properties": {
    "addr:full":"6625 E 425 S Waldron IN 46182",
    "addr:housenumber":"6625",
    "addr:postcode":"46182",
    "addr:street":"E 425 S Waldron",
    "iso:country":"US",
    "sg:address":"6625 E 425 S",
    "sg:city":"Waldron",
    "sg:classifiers":[
        {
            "category":"Building & Trades",
            "subcategory":"Construction",
            "type":"Services"
        }
    ],
    "sg:phone":"+1 765 525 9712",
    "sg:postcode":"46182",
    "sg:province":"IN",
    "sg:tags":[
        "house"
    ],
    "wof:name":"Gw Gahmier Construction",
    "wof:placetype":"venue"
},
  "geometry": {"coordinates":[-85.655428,39.462953],"type":"Point"}
}