{
  "type": "Feature",
  "properties": {
    "iso:country":"US",
    "sg:address":"3002 E 56th St",
    "sg:city":"Indianapolis",
    "sg:classifiers":[
        {
            "category":"Real Estate",
            "subcategory":"Real Estate Agent",
            "type":"Services"
        }
    ],
    "sg:phone":"+1 317 253 1401",
    "sg:postcode":"46220",
    "sg:province":"IN",
    "sg:tags":[
        "management"
    ],
    "sg:website":"www.ardsleymgmt.com",
    "wof:name":"Ardsley Management Corp",
    "wof:placetype":"venue"
},
  "geometry": {"coordinates":[-86.112951,39.855117],"type":"Point"}
}