{
  "type": "Feature",
  "properties": {
    "iso:country":"US",
    "sg:address":"2004 E 91st St",
    "sg:city":"Indianapolis",
    "sg:classifiers":[
        {
            "category":"Arts & Performance",
            "subcategory":"Theater",
            "type":"Entertainment"
        }
    ],
    "sg:phone":"+1 317 848 8928",
    "sg:postcode":"46240",
    "sg:province":"IN",
    "sg:tags":[
        "musician",
        "group"
    ],
    "wof:name":"Jazz Club Of Indianapolis Inc",
    "wof:placetype":"venue"
},
  "geometry": {"coordinates":[-86.126546,39.919679],"type":"Point"}
}