{
  "type": "Feature",
  "properties": {
    "iso:country":"US",
    "sg:address":"903 N 6th St",
    "sg:city":"Logansport",
    "sg:classifiers":[
        {
            "category":"Retail",
            "subcategory":"Auto Repair",
            "type":"Services"
        }
    ],
    "sg:phone":"+1 574 753 3631",
    "sg:postcode":"46947",
    "sg:province":"IN",
    "sg:tags":[
        "automobile",
        "top",
        "upholstery"
    ],
    "wof:name":"Midwest Auto Trim/Accessories",
    "wof:placetype":"venue"
},
  "geometry": {"coordinates":[-86.366042,40.761031],"type":"Point"}
}