{
  "type": "Feature",
  "properties": {
    "iso:country":"US",
    "sg:address":"3138 S 25 E",
    "sg:city":"Shelbyville",
    "sg:classifiers":[
        {
            "category":"Professional",
            "subcategory":"Business Services",
            "type":"Services"
        }
    ],
    "sg:phone":"+1 317 398 3261",
    "sg:postcode":"46176",
    "sg:province":"IN",
    "sg:tags":[
        "inspection"
    ],
    "wof:name":"Best Home Inspection Co",
    "wof:placetype":"venue"
},
  "geometry": {"coordinates":[-85.775781,39.486534],"type":"Point"}
}