{
  "type": "Feature",
  "properties": {
    "iso:country":"US",
    "sg:address":"7305 Grand Blvd",
    "sg:city":"Hobart",
    "sg:classifiers":[
        {
            "category":"Professional",
            "subcategory":"Advertising",
            "type":"Services"
        }
    ],
    "sg:phone":"+1 219 945 0858",
    "sg:postcode":"46342",
    "sg:province":"IN",
    "sg:tags":[
        "counselor"
    ],
    "wof:name":"Big Mouth Advertise & Design",
    "wof:placetype":"venue"
},
  "geometry": {"coordinates":[-87.258485,41.48316],"type":"Point"}
}