{
  "type": "Feature",
  "properties": {
    "addr:full":"100 Eastshore Ct Laporte IN 46350",
    "addr:housenumber":"100",
    "addr:postcode":"46350",
    "addr:street":"Eastshore Ct",
    "iso:country":"US",
    "sg:address":"100 Eastshore Ct",
    "sg:city":"Laporte",
    "sg:classifiers":[
        {
            "category":"Travel",
            "subcategory":"Hotels & Motels",
            "type":"Entertainment"
        }
    ],
    "sg:phone":"+1 219 326 7900",
    "sg:postcode":"46350",
    "sg:province":"IN",
    "sg:website":"www.focushotels.com",
    "wof:name":"Holiday Inn Express Laporte",
    "wof:placetype":"venue"
},
  "geometry": {"coordinates":[-86.735478,41.630012],"type":"Point"}
}