{
  "type": "Feature",
  "properties": {
    "iso:country":"US",
    "sg:address":"4005 Collier St",
    "sg:city":"Indianapolis",
    "sg:classifiers":[
        {
            "category":"Wholesale",
            "subcategory":"Construction Materials",
            "type":"Manufacturing & Wholesale Goods"
        }
    ],
    "sg:phone":"+1 317 244 0027",
    "sg:postcode":"46221",
    "sg:province":"IN",
    "sg:tags":[
        "pallet",
        "skid"
    ],
    "wof:name":"Judd Pallet Recycling",
    "wof:placetype":"venue"
},
  "geometry": {"coordinates":[-86.230244,39.703368],"type":"Point"}
}