{
  "type": "Feature",
  "properties": {
    "iso:country":"US",
    "sg:address":"7381 Ewbank Ct",
    "sg:city":"Camby",
    "sg:classifiers":[
        {
            "category":"Organizations",
            "subcategory":"Religious Organization",
            "type":"Services"
        }
    ],
    "sg:phone":"+1 317 856 8764",
    "sg:postcode":"46113",
    "sg:province":"IN",
    "wof:name":"Apostolic Bible Church",
    "wof:placetype":"venue"
},
  "geometry": {"coordinates":[-86.334707,39.655383],"type":"Point"}
}