{
  "type": "Feature",
  "properties": {
    "iso:country":"US",
    "sg:address":"259 South St",
    "sg:city":"Hagerstown",
    "sg:classifiers":[
        {
            "category":"Retail",
            "subcategory":"Auto Repair",
            "type":"Services"
        }
    ],
    "sg:phone":"+1 765 489 5575",
    "sg:postcode":"47346",
    "sg:province":"IN",
    "sg:tags":[
        "repairing",
        "automobile"
    ],
    "wof:name":"M & D Auto Svc",
    "wof:placetype":"venue"
},
  "geometry": {"coordinates":[-85.15843,39.903293],"type":"Point"}
}