{
  "type": "Feature",
  "properties": {
    "iso:country":"US",
    "sg:address":"10109 Kennedy Ave",
    "sg:city":"Highland",
    "sg:classifiers":[
        {
            "category":"Home & Garden",
            "subcategory":"Building Materials",
            "type":"Retail Goods"
        }
    ],
    "sg:phone":"+1 219 924 7787",
    "sg:postcode":"46322",
    "sg:province":"IN",
    "sg:tags":[
        "door"
    ],
    "wof:name":"Crawford Door Sales Co",
    "wof:placetype":"venue"
},
  "geometry": {"coordinates":[-87.46146299999999,41.532136],"type":"Point"}
}