{
  "type": "Feature",
  "properties": {
    "iso:country":"US",
    "sg:address":"2321 Sunnyside Dr",
    "sg:city":"Elkhart",
    "sg:classifiers":[
        {
            "category":"Shopping",
            "subcategory":"Clothing, Apparel, & Fashions",
            "type":"Retail Goods"
        }
    ],
    "sg:phone":"+1 574 293 1787",
    "sg:postcode":"46516",
    "sg:province":"IN",
    "sg:tags":[
        "navy",
        "army"
    ],
    "wof:name":"Army Store",
    "wof:placetype":"venue"
},
  "geometry": {"coordinates":[-85.94068900000001,41.693064],"type":"Point"}
}