{
  "type": "Feature",
  "properties": {
    "iso:country":"US",
    "sg:address":"705 Plaza Dr",
    "sg:city":"Chesterton",
    "sg:classifiers":[
        {
            "category":"Cinema",
            "subcategory":"Movie Rental",
            "type":"Entertainment"
        }
    ],
    "sg:phone":"+1 219 921 0761",
    "sg:postcode":"46304",
    "sg:province":"IN",
    "sg:tags":[
        "leasing",
        "video",
        "disc",
        "tape"
    ],
    "sg:website":"www.blockbuster.com",
    "wof:name":"Blockbuster Video",
    "wof:placetype":"venue"
},
  "geometry": {"coordinates":[-87.043503,41.616961],"type":"Point"}
}