{
  "type": "Feature",
  "properties": {
    "addr:full":"301 E 3rd St Huntingburg IN 47542",
    "addr:housenumber":"301",
    "addr:postcode":"47542",
    "addr:street":"E 3Rd St",
    "iso:country":"US",
    "sg:address":"301 E 3rd St",
    "sg:city":"Huntingburg",
    "sg:classifiers":[
        {
            "category":"Restaurant",
            "type":"Food & Drink"
        }
    ],
    "sg:phone":"+1 812 683 0588",
    "sg:postcode":"47542",
    "sg:province":"IN",
    "wof:name":"Rosita's Restaurant",
    "wof:placetype":"venue"
},
  "geometry": {"coordinates":[-86.956321,38.294461],"type":"Point"}
}