{
  "type": "Feature",
  "properties": {
    "iso:country":"US",
    "sg:address":"4628 Northwestern Dr",
    "sg:city":"Zionsville",
    "sg:classifiers":[
        {
            "category":"Freight",
            "type":"Transportation"
        }
    ],
    "sg:phone":"+1 317 334 9445",
    "sg:postcode":"46077",
    "sg:province":"IN",
    "sg:tags":[
        "commercial",
        "storage"
    ],
    "wof:name":"Simply Self Storage",
    "wof:placetype":"venue"
},
  "geometry": {"coordinates":[-86.23413,39.933274],"type":"Point"}
}