{
  "type": "Feature",
  "properties": {
    "iso:country":"US",
    "sg:address":"3209 Cascade Dr",
    "sg:city":"Valparaiso",
    "sg:classifiers":[
        {
            "category":"Professional",
            "type":"Services"
        }
    ],
    "sg:phone":"+1 219 548 0816",
    "sg:postcode":"46383",
    "sg:province":"IN",
    "sg:tags":[
        "establishment"
    ],
    "wof:name":"Magnetics International Inc",
    "wof:placetype":"venue"
},
  "geometry": {"coordinates":[-87.026236,41.474995],"type":"Point"}
}