{
  "type": "Feature",
  "properties": {
    "iso:country":"US",
    "sg:address":"2025 Olladale Dr",
    "sg:city":"Fort Wayne",
    "sg:classifiers":[
        {
            "category":"Organizations",
            "subcategory":"Community Association",
            "type":"Services"
        }
    ],
    "sg:phone":"+1 260 459 6820",
    "sg:postcode":"46808",
    "sg:province":"IN",
    "sg:tags":[
        "military"
    ],
    "wof:name":"Army & Navy Union Garrison",
    "wof:placetype":"venue"
},
  "geometry": {"coordinates":[-85.183634,41.094636],"type":"Point"}
}