{
  "type": "Feature",
  "properties": {
    "addr:full":"1218 W Franklin St Elkhart IN 46516",
    "addr:housenumber":"1218",
    "addr:postcode":"46516",
    "addr:street":"W Franklin St",
    "iso:country":"US",
    "sg:address":"1218 W Franklin St",
    "sg:city":"Elkhart",
    "sg:classifiers":[
        {
            "category":"Professional",
            "subcategory":"Accounting & Tax Preparation",
            "type":"Services"
        }
    ],
    "sg:phone":"+1 574 294 4685",
    "sg:postcode":"46516",
    "sg:province":"IN",
    "sg:tags":[
        "accountant"
    ],
    "wof:name":"Koons & Koons",
    "wof:placetype":"venue"
},
  "geometry": {"coordinates":[-85.986469,41.67905],"type":"Point"}
}