{
  "type": "Feature",
  "properties": {
    "iso:country":"US",
    "sg:address":"2221 E 44th St",
    "sg:city":"Indianapolis",
    "sg:classifiers":[
        {
            "category":"Building & Trades",
            "subcategory":"Landscaping Services",
            "type":"Services"
        }
    ],
    "sg:phone":"+1 317 547 7610",
    "sg:postcode":"46205",
    "sg:province":"IN",
    "sg:tags":[
        "landscape",
        "contractor"
    ],
    "wof:name":"James E Mahan Turf Svc",
    "wof:placetype":"venue"
},
  "geometry": {"coordinates":[-86.122099,39.836479],"type":"Point"}
}