{
  "type": "Feature",
  "properties": {
    "iso:country":"US",
    "sg:address":"7750 W 200 S",
    "sg:city":"Topeka",
    "sg:classifiers":[
        {
            "category":"Health Services",
            "subcategory":"Doctor",
            "type":"Services"
        }
    ],
    "sg:phone":"+1 260 768 7918",
    "sg:postcode":"46571",
    "sg:province":"IN",
    "sg:tags":[
        "dentist"
    ],
    "wof:name":"Community Dental Clinic",
    "wof:placetype":"venue"
},
  "geometry": {"coordinates":[-85.574306,41.611133],"type":"Point"}
}