{
  "type": "Feature",
  "properties": {
    "addr:full":"768 S 250 W Flora IN 46929",
    "addr:housenumber":"768;250",
    "addr:postcode":"46929",
    "addr:street":"S;W Flora",
    "iso:country":"US",
    "sg:address":"768 S 250 W",
    "sg:city":"Flora",
    "sg:phone":"+1 574 967 3231",
    "sg:postcode":"46929",
    "sg:province":"IN",
    "sg:tags":[
        "farm",
        "corn",
        "soybean"
    ],
    "wof:name":"Gary Duff",
    "wof:placetype":"venue"
},
  "geometry": {"coordinates":[-86.57256,40.541864],"type":"Point"}
}