{
  "type": "Feature",
  "properties": {
    "addr:full":"3810 N High School Rd Indianapolis IN 46254",
    "addr:housenumber":"3810",
    "addr:postcode":"46254",
    "addr:street":"N High School Rd",
    "iso:country":"US",
    "sg:address":"3810 N High School Rd",
    "sg:city":"Indianapolis",
    "sg:classifiers":[
        {
            "category":"Travel",
            "subcategory":"Hotels & Motels",
            "type":"Entertainment"
        }
    ],
    "sg:phone":"+1 317 783 5555",
    "sg:postcode":"46254",
    "sg:province":"IN",
    "sg:tags":[
        "lodging"
    ],
    "sg:website":"http://www.daysinn.com",
    "wof:name":"Days Inn",
    "wof:placetype":"venue"
},
  "geometry": {"coordinates":[-86.270287,39.823684],"type":"Point"}
}