{
  "type": "Feature",
  "properties": {
    "addr:full":"1200 S Decker Rd Boonville IN 47601",
    "addr:housenumber":"1200",
    "addr:postcode":"47601",
    "addr:street":"S Decker Rd",
    "iso:country":"US",
    "sg:address":"1200 S Decker Rd",
    "sg:city":"Boonville",
    "sg:classifiers":[
        {
            "category":"Retail",
            "subcategory":"Animal Services",
            "type":"Services"
        }
    ],
    "sg:phone":"+1 812 897 4575",
    "sg:postcode":"47601",
    "sg:province":"IN",
    "wof:name":"Country Kennels",
    "wof:placetype":"venue"
},
  "geometry": {"coordinates":[-87.21347799999999,38.009581],"type":"Point"}
}