{
  "type": "Feature",
  "properties": {
    "iso:country":"US",
    "sg:address":"6060 S Old State Rd 15",
    "sg:city":"Wabash",
    "sg:classifiers":[
        {
            "category":"Building & Trades",
            "subcategory":"Construction",
            "type":"Services"
        }
    ],
    "sg:phone":"+1 260 563 2646",
    "sg:postcode":"46992",
    "sg:province":"IN",
    "sg:tags":[
        "general",
        "contractor"
    ],
    "wof:name":"Mark Draper Construction",
    "wof:placetype":"venue"
},
  "geometry": {"coordinates":[-85.752293,40.73832],"type":"Point"}
}