{
  "type": "Feature",
  "properties": {
    "iso:country":"US",
    "sg:address":"551 Circle Dr",
    "sg:city":"Fairmount",
    "sg:classifiers":[
        {
            "category":"Recreation",
            "type":"Entertainment"
        }
    ],
    "sg:phone":"+1 765 948 5071",
    "sg:postcode":"46928",
    "sg:province":"IN",
    "sg:tags":[
        "club",
        "membership"
    ],
    "wof:name":"Mets Flying Club Inc",
    "wof:placetype":"venue"
},
  "geometry": {"coordinates":[-85.654687,40.414173],"type":"Point"}
}