{
  "type": "Feature",
  "properties": {
    "iso:country":"US",
    "sg:address":"541 Eastern Blvd",
    "sg:city":"Clarksville",
    "sg:classifiers":[
        {
            "category":"Health Services",
            "subcategory":"Doctor",
            "type":"Services"
        },
        {
            "category":"Health Services",
            "subcategory":"Clinic",
            "type":"Services"
        },
        {
            "category":"Health Services",
            "subcategory":"Chiropractor",
            "type":"Services"
        }
    ],
    "sg:phone":"+1 812 280 8420",
    "sg:postcode":"47129",
    "sg:province":"IN",
    "sg:tags":[
        "physician",
        "medical",
        "surgeon",
        "chiropractic"
    ],
    "sg:website":"http://www.neeleychiropractic.com",
    "wof:name":"Neeley Chiropractic",
    "wof:placetype":"venue"
},
  "geometry": {"coordinates":[-85.760616,38.297716],"type":"Point"}
}