{
  "type": "Feature",
  "properties": {
    "iso:country":"US",
    "sg:address":"1905 Kentfield Way",
    "sg:city":"Goshen",
    "sg:classifiers":[
        {
            "category":"Professional",
            "subcategory":"Accounting & Tax Preparation",
            "type":"Services"
        }
    ],
    "sg:phone":"+1 574 534 2715",
    "sg:postcode":"46526",
    "sg:province":"IN",
    "sg:tags":[
        "consultant"
    ],
    "wof:name":"Tax Recovery Specialists",
    "wof:placetype":"venue"
},
  "geometry": {"coordinates":[-85.806608,41.566189],"type":"Point"}
}