{
  "type": "Feature",
  "properties": {
    "addr:full":"2501 Oriole Trl Long Beach IN 46360",
    "addr:housenumber":"2501",
    "addr:postcode":"46360",
    "addr:street":"Oriole Trl",
    "iso:country":"US",
    "sg:address":"2501 Oriole Trl",
    "sg:city":"Long Beach",
    "sg:classifiers":[
        {
            "category":"Sports & Exercise",
            "subcategory":"Gym",
            "type":"Entertainment"
        }
    ],
    "sg:phone":"+1 219 879 1395",
    "sg:postcode":"46360",
    "sg:province":"IN",
    "sg:tags":[
        "club",
        "health",
        "studio",
        "gymnasium"
    ],
    "wof:name":"Long Beach Fitness Ctr",
    "wof:placetype":"venue"
},
  "geometry": {"coordinates":[-86.849176,41.746227],"type":"Point"}
}