{
  "type": "Feature",
  "properties": {
    "iso:country":"US",
    "sg:address":"201 E Water St",
    "sg:city":"Pendleton",
    "sg:classifiers":[
        {
            "category":"Freight",
            "type":"Transportation"
        }
    ],
    "sg:phone":"+1 765 778 2621",
    "sg:postcode":"46064",
    "sg:province":"IN",
    "sg:tags":[
        "commercial",
        "storage"
    ],
    "wof:name":"Pendleton Lock-Up Self Storage",
    "wof:placetype":"venue"
},
  "geometry": {"coordinates":[-85.744716,40.003826],"type":"Point"}
}