{
  "type": "Feature",
  "properties": {
    "iso:country":"US",
    "sg:address":"1231 E Main St",
    "sg:city":"Gas City",
    "sg:classifiers":[
        {
            "category":"Freight",
            "type":"Transportation"
        }
    ],
    "sg:phone":"+1 765 674 7689",
    "sg:postcode":"46933",
    "sg:province":"IN",
    "sg:tags":[
        "trucking"
    ],
    "wof:name":"Thompson Trucking",
    "wof:placetype":"venue"
},
  "geometry": {"coordinates":[-85.591711,40.487243],"type":"Point"}
}