{
  "type": "Feature",
  "properties": {
    "addr:full":"3211 W Mansfield Dr Muncie IN 47304",
    "addr:housenumber":"3211",
    "addr:postcode":"47304",
    "addr:street":"W Mansfield Dr",
    "iso:country":"US",
    "sg:address":"3211 W Mansfield Dr",
    "sg:city":"Muncie",
    "sg:classifiers":[
        {
            "category":"Education",
            "subcategory":"School",
            "type":"Public Place"
        }
    ],
    "sg:phone":"+1 765 747 5360",
    "sg:postcode":"47304",
    "sg:province":"IN",
    "wof:name":"Storer Elementary School",
    "wof:placetype":"venue"
},
  "geometry": {"coordinates":[-85.424727,40.208444],"type":"Point"}
}