{
  "type": "Feature",
  "properties": {
    "iso:country":"US",
    "sg:address":"1116 E 3rd St",
    "sg:city":"Mt Vernon",
    "sg:classifiers":[
        {
            "category":"Personal",
            "subcategory":"Beauty Salon",
            "type":"Services"
        }
    ],
    "sg:phone":"+1 812 838 8834",
    "sg:postcode":"47620",
    "sg:province":"IN",
    "sg:tags":[
        "shop"
    ],
    "wof:name":"Family Hair Fashion Center",
    "wof:placetype":"venue"
},
  "geometry": {"coordinates":[-87.881364,37.934613],"type":"Point"}
}