{
  "type": "Feature",
  "properties": {
    "iso:country":"US",
    "sg:address":"30913 US Hwy 20",
    "sg:city":"Elkhart",
    "sg:classifiers":[
        {
            "category":"Professional",
            "subcategory":"Credit Reporting & Collection",
            "type":"Services"
        }
    ],
    "sg:phone":"+1 574 675 7376",
    "sg:postcode":"46514",
    "sg:province":"IN",
    "sg:tags":[
        "agency"
    ],
    "wof:name":"Final Notice Recovery Inc",
    "wof:placetype":"venue"
},
  "geometry": {"coordinates":[-86.061305,41.688515],"type":"Point"}
}