{
  "type": "Feature",
  "properties": {
    "iso:country":"US",
    "sg:address":"3916 N Washington Blvd",
    "sg:city":"Indianapolis",
    "sg:classifiers":[
        {
            "category":"Real Estate",
            "subcategory":"Real Estate Agent",
            "type":"Services"
        }
    ],
    "sg:phone":"+1 317 257 0357",
    "sg:postcode":"46205",
    "sg:province":"IN",
    "sg:tags":[
        "appraiser"
    ],
    "wof:name":"Home Guide Realty Svc",
    "wof:placetype":"venue"
},
  "geometry": {"coordinates":[-86.152219,39.826459],"type":"Point"}
}