{
  "type": "Feature",
  "properties": {
    "addr:full":"915 Logan St Hammond IN 46320",
    "addr:housenumber":"915",
    "addr:postcode":"46320",
    "addr:street":"Logan St",
    "iso:country":"US",
    "sg:address":"915 Logan St",
    "sg:city":"Hammond",
    "sg:classifiers":[
        {
            "category":"Home & Garden",
            "subcategory":"Building Materials",
            "type":"Retail Goods"
        }
    ],
    "sg:phone":"+1 219 931 1137",
    "sg:postcode":"46320",
    "sg:province":"IN",
    "sg:tags":[
        "windows"
    ],
    "wof:name":"Creative Windows & Siding",
    "wof:placetype":"venue"
},
  "geometry": {"coordinates":[-87.503508,41.614879],"type":"Point"}
}