{
  "type": "Feature",
  "properties": {
    "addr:full":"1018 E Tipton St Seymour IN 47274",
    "addr:housenumber":"1018",
    "addr:postcode":"47274",
    "addr:street":"E Tipton St",
    "iso:country":"US",
    "sg:address":"1018 E Tipton St",
    "sg:city":"Seymour",
    "sg:classifiers":[
        {
            "category":"Health Services",
            "subcategory":"Clinic",
            "type":"Services"
        }
    ],
    "sg:phone":"+1 812 523 7651",
    "sg:postcode":"47274",
    "sg:province":"IN",
    "sg:tags":[
        "home"
    ],
    "wof:name":"Addus Healthcare",
    "wof:placetype":"venue"
},
  "geometry": {"coordinates":[-85.8755,38.958034],"type":"Point"}
}