{
  "type": "Feature",
  "properties": {
    "addr:full":"841 S State Rd 3 Rushville IN 46173",
    "addr:housenumber":"841",
    "addr:postcode":"46173",
    "addr:street":"S State Rd 3 Rushville",
    "iso:country":"US",
    "sg:address":"841 S State Rd 3",
    "sg:city":"Rushville",
    "sg:classifiers":[
        {
            "category":"Banks & Credit Unions",
            "subcategory":"Bank",
            "type":"Services"
        }
    ],
    "sg:phone":"+1 765 932 5991",
    "sg:postcode":"46173",
    "sg:province":"IN",
    "sg:tags":[
        "loan"
    ],
    "wof:name":"Farm Credit Svc",
    "wof:placetype":"venue"
},
  "geometry": {"coordinates":[-85.444834,39.615748],"type":"Point"}
}