{
  "type": "Feature",
  "properties": {
    "addr:full":"1229 Bellemeade Ave Evansville IN 47714",
    "addr:housenumber":"1229",
    "addr:postcode":"47714",
    "addr:street":"Bellemeade Ave",
    "iso:country":"US",
    "sg:address":"1229 Bellemeade Ave",
    "sg:city":"Evansville",
    "sg:classifiers":[
        {
            "category":"Social Services",
            "type":"Services"
        }
    ],
    "sg:phone":"+1 812 477 2260",
    "sg:postcode":"47714",
    "sg:province":"IN",
    "sg:tags":[
        "counselor",
        "marriage",
        "family"
    ],
    "sg:website":"www.marryright.org",
    "wof:name":"Community Marriage Builders",
    "wof:placetype":"venue"
},
  "geometry": {"coordinates":[-87.542897,37.968114],"type":"Point"}
}