{
  "type": "Feature",
  "properties": {
    "addr:full":"2835 N Gladstone Ave Indianapolis IN 46218",
    "addr:housenumber":"2835",
    "addr:postcode":"46218",
    "addr:street":"N Gladstone Ave",
    "iso:country":"US",
    "sg:address":"2835 N Gladstone Ave",
    "sg:city":"Indianapolis",
    "sg:classifiers":[
        {
            "category":"Shopping",
            "type":"Retail Goods"
        }
    ],
    "sg:phone":"+1 317 546 7503",
    "sg:postcode":"46218",
    "sg:province":"IN",
    "sg:tags":[
        "cosmetic",
        "perfume"
    ],
    "wof:name":"Kiona Cessil Beauty Supplies",
    "wof:placetype":"venue"
},
  "geometry": {"coordinates":[-86.096332,39.808109],"type":"Point"}
}