{
  "type": "Feature",
  "properties": {
    "addr:full":"107 N 4th St Jeffersonville IN 47130",
    "addr:housenumber":"107",
    "addr:postcode":"47130",
    "addr:street":"N 4Th St",
    "iso:country":"US",
    "sg:address":"107 N 4th St",
    "sg:city":"Jeffersonville",
    "sg:classifiers":[
        {
            "category":"Government",
            "subcategory":"Police Station",
            "type":"Public Place"
        },
        {
            "category":"Government",
            "subcategory":"Office",
            "type":"Public Place"
        }
    ],
    "sg:phone":"+1 812 288 4357",
    "sg:postcode":"47130",
    "sg:province":"IN",
    "sg:tags":[
        "department",
        "township",
        "government-city",
        "village"
    ],
    "wof:name":"Utica Police Department",
    "wof:placetype":"venue"
},
  "geometry": {"coordinates":[-85.65256599999999,38.336429],"type":"Point"}
}