{
  "type": "Feature",
  "properties": {
    "iso:country":"US",
    "sg:address":"1016 N Jackson St",
    "sg:city":"Huntingburg",
    "sg:classifiers":[
        {
            "category":"Building & Trades",
            "subcategory":"Construction",
            "type":"Services"
        }
    ],
    "sg:phone":"+1 812 683 3053",
    "sg:postcode":"47542",
    "sg:province":"IN",
    "sg:tags":[
        "siding",
        "contractor"
    ],
    "wof:name":"Tri County Insulation & Siding",
    "wof:placetype":"venue"
},
  "geometry": {"coordinates":[-86.953813,38.305878],"type":"Point"}
}