{
  "type": "Feature",
  "properties": {
    "iso:country":"US",
    "sg:address":"15424 Siena Ct",
    "sg:city":"Granger",
    "sg:classifiers":[
        {
            "category":"Insurance",
            "subcategory":"Insurance Agent",
            "type":"Services"
        }
    ],
    "sg:phone":"+1 574 277 0263",
    "sg:postcode":"46530",
    "sg:province":"IN",
    "sg:tags":[
        "agency"
    ],
    "wof:name":"Robert L Sindy Insurance Svcs",
    "wof:placetype":"venue"
},
  "geometry": {"coordinates":[-86.167776,41.739207],"type":"Point"}
}