{
  "type": "Feature",
  "properties": {
    "addr:full":"1109 S Martin St Ligonier IN 46767",
    "addr:housenumber":"1109",
    "addr:postcode":"46767",
    "addr:street":"S Martin St",
    "iso:country":"US",
    "sg:address":"1109 S Martin St",
    "sg:city":"Ligonier",
    "sg:classifiers":[
        {
            "category":"Personal",
            "subcategory":"Beauty Salon",
            "type":"Services"
        }
    ],
    "sg:phone":"+1 260 894 3979",
    "sg:postcode":"46767",
    "sg:province":"IN",
    "wof:name":"His & Her Styling",
    "wof:placetype":"venue"
},
  "geometry": {"coordinates":[-85.590474,41.457302],"type":"Point"}
}