{
  "type": "Feature",
  "properties": {
    "iso:country":"US",
    "sg:address":"1644 173rd Pl",
    "sg:city":"Hammond",
    "sg:classifiers":[
        {
            "category":"Building & Trades",
            "subcategory":"Electrical",
            "type":"Services"
        }
    ],
    "sg:phone":"+1 219 988 5762",
    "sg:postcode":"46324",
    "sg:province":"IN",
    "sg:tags":[
        "electric",
        "contractor"
    ],
    "wof:name":"All Fields Electric Inc",
    "wof:placetype":"venue"
},
  "geometry": {"coordinates":[-87.488733,41.580199],"type":"Point"}
}