{
  "type": "Feature",
  "properties": {
    "iso:country":"US",
    "sg:address":"300 W Hillside Dr",
    "sg:city":"Bloomington",
    "sg:classifiers":[
        {
            "category":"Wholesale",
            "subcategory":"Hardware",
            "type":"Manufacturing & Wholesale Goods"
        }
    ],
    "sg:phone":"+1 812 333 5400",
    "sg:postcode":"47403",
    "sg:province":"IN",
    "sg:tags":[
        "fastener"
    ],
    "wof:name":"American Fasteners Inc",
    "wof:placetype":"venue"
},
  "geometry": {"coordinates":[-86.537677,39.150573],"type":"Point"}
}