{
  "type": "Feature",
  "properties": {
    "iso:country":"US",
    "sg:address":"1853 Indianapolis Blvd",
    "sg:city":"Whiting",
    "sg:classifiers":[
        {
            "category":"Recreation",
            "type":"Entertainment"
        }
    ],
    "sg:phone":"+1 219 473 0940",
    "sg:postcode":"46394",
    "sg:province":"IN",
    "sg:tags":[
        "astrologer"
    ],
    "wof:name":"Tarot Cards Palm Reading",
    "wof:placetype":"venue"
},
  "geometry": {"coordinates":[-87.49933900000001,41.679397],"type":"Point"}
}