{
  "type": "Feature",
  "properties": {
    "iso:country":"US",
    "sg:address":"1916 Jackson St",
    "sg:city":"Anderson",
    "sg:classifiers":[
        {
            "category":"Health Services",
            "subcategory":"Doctor",
            "type":"Services"
        }
    ],
    "sg:phone":"+1 765 683 3162",
    "sg:postcode":"46016",
    "sg:province":"IN",
    "sg:tags":[
        "physician",
        "surgeon"
    ],
    "wof:name":"Joan D Crockett MD",
    "wof:placetype":"venue"
},
  "geometry": {"coordinates":[-85.680385,40.096536],"type":"Point"}
}