{
  "type": "Feature",
  "properties": {
    "addr:full":"1101 S Burlington Dr Muncie IN 47302",
    "addr:housenumber":"1101",
    "addr:postcode":"47302",
    "addr:street":"S Burlington Dr",
    "iso:country":"US",
    "sg:address":"1101 S Burlington Dr",
    "sg:city":"Muncie",
    "sg:classifiers":[
        {
            "category":"Restaurant",
            "type":"Food & Drink"
        }
    ],
    "sg:phone":"+1 765 289 1611",
    "sg:postcode":"47302",
    "sg:province":"IN",
    "sg:tags":[
        "parlor",
        "ice",
        "cream"
    ],
    "wof:name":"Hunnicutt's Dairy Bar",
    "wof:placetype":"venue"
},
  "geometry": {"coordinates":[-85.358355,40.18514],"type":"Point"}
}