{
  "type": "Feature",
  "properties": {
    "iso:country":"US",
    "sg:address":"2139 S Co Rd 350 W",
    "sg:city":"Danville",
    "sg:classifiers":[
        {
            "category":"Building & Trades",
            "subcategory":"Construction",
            "type":"Services"
        }
    ],
    "sg:phone":"+1 317 539 6848",
    "sg:postcode":"46122",
    "sg:province":"IN",
    "sg:tags":[
        "water",
        "well",
        "drilling"
    ],
    "wof:name":"Harness Well Drilling Co",
    "wof:placetype":"venue"
},
  "geometry": {"coordinates":[-86.58560199999999,39.729263],"type":"Point"}
}