{
  "type": "Feature",
  "properties": {
    "iso:country":"US",
    "sg:address":"1570 Countryside Dr",
    "sg:city":"Greenwood",
    "sg:classifiers":[
        {
            "category":"Real Estate",
            "subcategory":"Real Estate Operator",
            "type":"Services"
        }
    ],
    "sg:phone":"+1 317 887 0517",
    "sg:postcode":"46143",
    "sg:province":"IN",
    "sg:tags":[
        "apartment"
    ],
    "wof:name":"Yorktowne Farms Apartments",
    "wof:placetype":"venue"
},
  "geometry": {"coordinates":[-86.110454,39.593992],"type":"Point"}
}