{
  "type": "Feature",
  "properties": {
    "iso:country":"US",
    "sg:address":"2 Hoosier Ave",
    "sg:city":"Oolitic",
    "sg:classifiers":[
        {
            "category":"Bars & Pubs",
            "type":"Food & Drink"
        }
    ],
    "sg:phone":"+1 812 277 1126",
    "sg:postcode":"47451",
    "sg:province":"IN",
    "wof:name":"Cycle Shack Bar & Grill",
    "wof:placetype":"venue"
},
  "geometry": {"coordinates":[-86.527306,38.903711],"type":"Point"}
}