{
  "type": "Feature",
  "properties": {
    "iso:country":"US",
    "sg:address":"53893 Kershner Ln",
    "sg:city":"Elkhart",
    "sg:classifiers":[
        {
            "category":"Building & Trades",
            "subcategory":"Landscaping Services",
            "type":"Services"
        }
    ],
    "sg:phone":"+1 574 266 0358",
    "sg:postcode":"46514",
    "sg:province":"IN",
    "wof:name":"Classic Lawn Care & Landscape",
    "wof:placetype":"venue"
},
  "geometry": {"coordinates":[-85.918427,41.711738],"type":"Point"}
}