{
  "type": "Feature",
  "properties": {
    "iso:country":"US",
    "sg:address":"2000 W Winona Ave",
    "sg:city":"Warsaw",
    "sg:classifiers":[
        {
            "category":"Utilities",
            "subcategory":"Mobile Phone",
            "type":"Services"
        }
    ],
    "sg:phone":"+1 574 269 4999",
    "sg:postcode":"46580",
    "sg:province":"IN",
    "sg:tags":[
        "telephone",
        "cellular"
    ],
    "sg:website":"www.sprintnorthsupply.com",
    "wof:name":"Sprint North Supply",
    "wof:placetype":"venue"
},
  "geometry": {"coordinates":[-85.886107,41.233498],"type":"Point"}
}