{
  "type": "Feature",
  "properties": {
    "iso:country":"US",
    "sg:address":"401 Middlebury St",
    "sg:city":"Elkhart",
    "sg:classifiers":[
        {
            "category":"Food & Beverages",
            "subcategory":"Groceries & Convenience Stores",
            "type":"Retail Goods"
        }
    ],
    "sg:phone":"+1 574 293 8705",
    "sg:postcode":"46516",
    "sg:province":"IN",
    "sg:tags":[
        "grocer"
    ],
    "wof:name":"Saleh's Supermarket",
    "wof:placetype":"venue"
},
  "geometry": {"coordinates":[-85.963421,41.681188],"type":"Point"}
}