{
  "type": "Feature",
  "properties": {
    "iso:country":"US",
    "sg:address":"6544 N 445 E",
    "sg:city":"Dubois",
    "sg:classifiers":[
        {
            "category":"Retail",
            "subcategory":"Auto Repair",
            "type":"Services"
        }
    ],
    "sg:phone":"+1 812 678 4505",
    "sg:postcode":"47527",
    "sg:province":"IN",
    "sg:tags":[
        "muffler",
        "exhaust",
        "system"
    ],
    "wof:name":"Troy's Exhaust & Svc Ctr",
    "wof:placetype":"venue"
},
  "geometry": {"coordinates":[-86.821519,38.471942],"type":"Point"}
}