{
  "type": "Feature",
  "properties": {
    "addr:full":"12432 Aboite Rd Roanoke IN 46783",
    "addr:housenumber":"12432",
    "addr:postcode":"46783",
    "addr:street":"Aboite Rd",
    "iso:country":"US",
    "sg:address":"12432 Aboite Rd",
    "sg:city":"Roanoke",
    "sg:classifiers":[
        {
            "category":"Building & Trades",
            "subcategory":"Cleaning & Sanitation",
            "type":"Services"
        }
    ],
    "sg:phone":"+1 260 672 3867",
    "sg:postcode":"46783",
    "sg:province":"IN",
    "sg:tags":[
        "janitor"
    ],
    "wof:name":"Bridge & Bridge",
    "wof:placetype":"venue"
},
  "geometry": {"coordinates":[-85.319762,40.967357],"type":"Point"}
}