{
  "type": "Feature",
  "properties": {
    "iso:country":"US",
    "sg:address":"855 Missouri St",
    "sg:city":"Ferdinand",
    "sg:classifiers":[
        {
            "category":"Real Estate",
            "subcategory":"Real Estate Agent",
            "type":"Services"
        }
    ],
    "sg:phone":"+1 812 367 1156",
    "sg:postcode":"47532",
    "sg:province":"IN",
    "sg:tags":[
        "authorities",
        "housing"
    ],
    "wof:name":"Ferdinand Housing Inc Phase I",
    "wof:placetype":"venue"
},
  "geometry": {"coordinates":[-86.86411699999999,38.223422],"type":"Point"}
}