{
  "type": "Feature",
  "properties": {
    "iso:country":"US",
    "sg:address":"3704 W 97th St",
    "sg:city":"Carmel",
    "sg:classifiers":[
        {
            "category":"Retail",
            "subcategory":"Repair Shop",
            "type":"Services"
        }
    ],
    "sg:phone":"+1 317 872 4257",
    "sg:postcode":"46032",
    "sg:province":"IN",
    "sg:tags":[
        "piano",
        "restoration",
        "organ-tuning"
    ],
    "sg:website":"http://www.bonnerpiano.com",
    "wof:name":"Bonner Piano Service",
    "wof:placetype":"venue"
},
  "geometry": {"coordinates":[-86.22758899999999,39.92788],"type":"Point"}
}