{
  "type": "Feature",
  "properties": {
    "iso:country":"US",
    "sg:address":"21 W Canal St",
    "sg:city":"Peru",
    "sg:classifiers":[
        {
            "category":"Organizations",
            "subcategory":"Community Association",
            "type":"Services"
        }
    ],
    "sg:phone":"+1 765 472 4726",
    "sg:postcode":"46970",
    "sg:province":"IN",
    "sg:tags":[
        "club"
    ],
    "wof:name":"Literary Aid Society",
    "wof:placetype":"venue"
},
  "geometry": {"coordinates":[-86.06755,40.750843],"type":"Point"}
}