{
  "type": "Feature",
  "properties": {
    "iso:country":"US",
    "sg:address":"22 Commerce Dr",
    "sg:city":"Huntington",
    "sg:classifiers":[
        {
            "category":"Wholesale",
            "subcategory":"Machinery & Supplies",
            "type":"Manufacturing & Wholesale Goods"
        }
    ],
    "sg:phone":"+1 260 358 1879",
    "sg:postcode":"46750",
    "sg:province":"IN",
    "sg:tags":[
        "equipment",
        "industrial"
    ],
    "wof:name":"Fastenal Co",
    "wof:placetype":"venue"
},
  "geometry": {"coordinates":[-85.519491,40.893434],"type":"Point"}
}