{
  "type": "Feature",
  "properties": {
    "addr:full":"1903 S Liberty Dr Bloomington IN 47403",
    "addr:housenumber":"1903",
    "addr:postcode":"47403",
    "addr:street":"S Liberty Dr",
    "iso:country":"US",
    "sg:address":"1903 S Liberty Dr",
    "sg:city":"Bloomington",
    "sg:classifiers":[
        {
            "category":"Personal",
            "subcategory":"Massage",
            "type":"Services"
        },
        {
            "category":"Personal",
            "subcategory":"Beauty Salon",
            "type":"Services"
        },
        {
            "category":"Personal",
            "subcategory":"Day Spa",
            "type":"Services"
        },
        {
            "category":"Personal",
            "subcategory":"Nail Salon",
            "type":"Services"
        }
    ],
    "sg:phone":"+1 812 335 0690",
    "sg:postcode":"47403",
    "sg:province":"IN",
    "sg:tags":[
        "therapist"
    ],
    "sg:website":"http://www.hairtechniquessalonandspa.com",
    "wof:name":"Hair Techniques Salon & Spa Llc Bloomington",
    "wof:placetype":"venue"
},
  "geometry": {"coordinates":[-86.57710299999999,39.146808],"type":"Point"}
}