{
  "type": "Feature",
  "properties": {
    "iso:country":"US",
    "sg:address":"409 E 3rd St",
    "sg:city":"Bloomington",
    "sg:classifiers":[
        {
            "category":"Shopping",
            "subcategory":"Shoes",
            "type":"Retail Goods"
        }
    ],
    "sg:phone":"+1 812 335 8277",
    "sg:postcode":"47401",
    "sg:province":"IN",
    "wof:name":"Dancetime Bodywear & Shoes Inc",
    "wof:placetype":"venue"
},
  "geometry": {"coordinates":[-86.529844,39.16458],"type":"Point"}
}