{
  "type": "Feature",
  "properties": {
    "iso:country":"US",
    "sg:address":"1527 S Co Rd 925 W",
    "sg:city":"Logansport",
    "sg:classifiers":[
        {
            "category":"Home & Garden",
            "subcategory":"Hardware",
            "type":"Retail Goods"
        }
    ],
    "sg:phone":"+1 574 826 2094",
    "sg:postcode":"46947",
    "sg:province":"IN",
    "wof:name":"Tcm Tool",
    "wof:placetype":"venue"
},
  "geometry": {"coordinates":[-86.548437,40.742465],"type":"Point"}
}