{
  "type": "Feature",
  "properties": {
    "iso:country":"US",
    "sg:address":"7101 E Edgewood Ave",
    "sg:city":"Indianapolis",
    "sg:classifiers":[
        {
            "category":"Organizations",
            "subcategory":"Religious Organization",
            "type":"Services"
        }
    ],
    "sg:phone":"+1 317 862 4122",
    "sg:postcode":"46239",
    "sg:province":"IN",
    "wof:name":"Indianapolis Gospel Hall",
    "wof:placetype":"venue"
},
  "geometry": {"coordinates":[-86.04018600000001,39.681259],"type":"Point"}
}