{
  "type": "Feature",
  "properties": {
    "iso:country":"US",
    "sg:address":"6920 Tonia Ct",
    "sg:city":"Evansville",
    "sg:classifiers":[
        {
            "category":"Retail",
            "subcategory":"Car Wash",
            "type":"Services"
        }
    ],
    "sg:phone":"+1 812 402 9274",
    "sg:postcode":"47710",
    "sg:province":"IN",
    "sg:tags":[
        "truck",
        "cleaning"
    ],
    "wof:name":"E & S Mobil Wash",
    "wof:placetype":"venue"
},
  "geometry": {"coordinates":[-87.587331,38.04244],"type":"Point"}
}