{
  "type": "Feature",
  "properties": {
    "iso:country":"US",
    "sg:address":"607 S Orange St",
    "sg:city":"Albion",
    "sg:classifiers":[
        {
            "category":"Retail",
            "subcategory":"Self-service Laundry",
            "type":"Services"
        }
    ],
    "sg:phone":"+1 260 636 7848",
    "sg:postcode":"46701",
    "sg:province":"IN",
    "wof:name":"Clean Spot Laundrymat",
    "wof:placetype":"venue"
},
  "geometry": {"coordinates":[-85.424145,41.391142],"type":"Point"}
}