{
  "type": "Feature",
  "properties": {
    "iso:country":"US",
    "sg:address":"10898 N 850 W",
    "sg:city":"Delphi",
    "sg:classifiers":[
        {
            "category":"Farming",
            "subcategory":"Farm",
            "type":"Manufacturing & Wholesale Goods"
        }
    ],
    "sg:phone":"+1 574 965 2801",
    "sg:postcode":"46923",
    "sg:province":"IN",
    "wof:name":"Granny's Farm",
    "wof:placetype":"venue"
},
  "geometry": {"coordinates":[-86.687527,40.705644],"type":"Point"}
}