{
  "type": "Feature",
  "properties": {
    "iso:country":"US",
    "sg:address":"1406 W Winona Ave",
    "sg:city":"Warsaw",
    "sg:classifiers":[
        {
            "category":"Shopping",
            "subcategory":"Clothing, Apparel, & Fashions",
            "type":"Retail Goods"
        }
    ],
    "sg:phone":"+1 574 269 1884",
    "sg:postcode":"46580",
    "sg:province":"IN",
    "sg:tags":[
        "tack",
        "western",
        "wear"
    ],
    "wof:name":"Sisters The Inc",
    "wof:placetype":"venue"
},
  "geometry": {"coordinates":[-85.87640500000001,41.233649],"type":"Point"}
}