{
  "type": "Feature",
  "properties": {
    "iso:country":"US",
    "sg:address":"1401 E Market St",
    "sg:city":"Nappanee",
    "sg:classifiers":[
        {
            "category":"Restaurant",
            "type":"Food & Drink"
        }
    ],
    "sg:phone":"+1 574 773 2201",
    "sg:postcode":"46550",
    "sg:province":"IN",
    "wof:name":"Country Table",
    "wof:placetype":"venue"
},
  "geometry": {"coordinates":[-85.985394,41.442594],"type":"Point"}
}