{
  "type": "Feature",
  "properties": {
    "iso:country":"US",
    "sg:address":"3900 Co Rd 62",
    "sg:city":"Auburn",
    "sg:classifiers":[
        {
            "category":"Travel",
            "subcategory":"Travel Agent",
            "type":"Entertainment"
        }
    ],
    "sg:phone":"+1 260 925 0442",
    "sg:postcode":"46706",
    "sg:province":"IN",
    "sg:tags":[
        "tours",
        "promoter"
    ],
    "wof:name":"Classic Tours Inc",
    "wof:placetype":"venue"
},
  "geometry": {"coordinates":[-85.016414,41.302706],"type":"Point"}
}