{
  "type": "Feature",
  "properties": {
    "iso:country":"US",
    "sg:address":"4627 E Morningside Dr",
    "sg:city":"Bloomington",
    "sg:classifiers":[
        {
            "category":"Professional",
            "subcategory":"Employment Agencies",
            "type":"Services"
        }
    ],
    "sg:phone":"+1 812 331 0645",
    "sg:postcode":"47408",
    "sg:province":"IN",
    "sg:tags":[
        "consultant",
        "search",
        "executive"
    ],
    "sg:website":"www.careersearchonline.com",
    "wof:name":"Curare Group",
    "wof:placetype":"venue"
},
  "geometry": {"coordinates":[-86.474858,39.167254],"type":"Point"}
}