{
  "type": "Feature",
  "properties": {
    "iso:country":"US",
    "sg:address":"98 Swanson Rd",
    "sg:city":"Patriot",
    "sg:classifiers":[
        {
            "category":"Travel",
            "subcategory":"Hotels & Motels",
            "type":"Entertainment"
        }
    ],
    "sg:phone":"+1 812 594 2876",
    "sg:postcode":"47038",
    "sg:province":"IN",
    "sg:tags":[
        "breakfast",
        "accommodation",
        "bed"
    ],
    "wof:name":"Schenck Mansion",
    "wof:placetype":"venue"
},
  "geometry": {"coordinates":[-84.87385500000001,38.83246],"type":"Point"}
}