{
  "type": "Feature",
  "properties": {
    "iso:country":"US",
    "sg:address":"555 Sycamore St",
    "sg:city":"Evansville",
    "sg:classifiers":[
        {
            "category":"Banks & Credit Unions",
            "subcategory":"Bank",
            "type":"Services"
        }
    ],
    "sg:phone":"+1 812 424 6464",
    "sg:postcode":"47708",
    "sg:province":"IN",
    "wof:name":"Banc Serv Consultants LLC",
    "wof:placetype":"venue"
},
  "geometry": {"coordinates":[-87.57004499999999,37.973145],"type":"Point"}
}