{
  "type": "Feature",
  "properties": {
    "addr:full":"726 Adams St Ste 23 Carmel IN 46032",
    "addr:housenumber":"726",
    "addr:postcode":"46032",
    "addr:street":"Adams St Ste 23",
    "iso:country":"US",
    "sg:address":"726 Adams St Ste 23",
    "sg:city":"Carmel",
    "sg:classifiers":[
        {
            "category":"Personal",
            "subcategory":"Beauty Salon",
            "type":"Services"
        }
    ],
    "sg:phone":"+1 317 385 0732",
    "sg:postcode":"46032",
    "sg:province":"IN",
    "sg:tags":[
        "hair"
    ],
    "sg:website":"www.jamikinghairdesigns.com",
    "wof:name":"Jamie King Hair Designs",
    "wof:placetype":"venue"
},
  "geometry": {"coordinates":[-86.14499600000001,39.968347],"type":"Point"}
}