{
  "type": "Feature",
  "properties": {
    "iso:country":"US",
    "sg:address":"1413 N Park Ave",
    "sg:city":"Alexandria",
    "sg:classifiers":[
        {
            "category":"Banks & Credit Unions",
            "subcategory":"Bank",
            "type":"Services"
        }
    ],
    "sg:phone":"+1 765 724 4944",
    "sg:postcode":"46001",
    "sg:province":"IN",
    "sg:tags":[
        "loan",
        "real estate"
    ],
    "sg:website":"www.fcnmortgage.com",
    "wof:name":"Finance Consolidation Network",
    "wof:placetype":"venue"
},
  "geometry": {"coordinates":[-85.671069,40.275741],"type":"Point"}
}