{
  "type": "Feature",
  "properties": {
    "iso:country":"US",
    "sg:address":"4462 W 300 N",
    "sg:city":"Warsaw",
    "sg:classifiers":[
        {
            "category":"Personal",
            "subcategory":"Beauty Salon",
            "type":"Services"
        }
    ],
    "sg:phone":"+1 574 267 7346",
    "sg:postcode":"46582",
    "sg:province":"IN",
    "wof:name":"Touch Of Class",
    "wof:placetype":"venue"
},
  "geometry": {"coordinates":[-85.929984,41.276214],"type":"Point"}
}