{
  "type": "Feature",
  "properties": {
    "iso:country":"US",
    "sg:address":"870 E Washington St",
    "sg:city":"Winchester",
    "sg:classifiers":[
        {
            "category":"Banks & Credit Unions",
            "subcategory":"Bank",
            "type":"Services"
        }
    ],
    "sg:phone":"+1 765 584 3185",
    "sg:postcode":"47394",
    "sg:province":"IN",
    "wof:name":"Community First Bank & Trust",
    "wof:placetype":"venue"
},
  "geometry": {"coordinates":[-84.967285,40.172006],"type":"Point"}
}