{
  "type": "Feature",
  "properties": {
    "iso:country":"US",
    "sg:address":"3840 Prospect St",
    "sg:city":"Indianapolis",
    "sg:classifiers":[
        {
            "category":"Building & Trades",
            "subcategory":"Construction",
            "type":"Services"
        }
    ],
    "sg:phone":"+1 317 353 8801",
    "sg:postcode":"46203",
    "sg:province":"IN",
    "sg:tags":[
        "concrete",
        "contractor"
    ],
    "wof:name":"Concrete Forming Specialist",
    "wof:placetype":"venue"
},
  "geometry": {"coordinates":[-86.101939,39.752704],"type":"Point"}
}