{
  "type": "Feature",
  "properties": {
    "iso:country":"US",
    "sg:address":"54107 Co Rd 5",
    "sg:city":"Elkhart",
    "sg:classifiers":[
        {
            "category":"Shopping",
            "subcategory":"Florist",
            "type":"Retail Goods"
        }
    ],
    "sg:phone":"+1 574 264 3536",
    "sg:postcode":"46514",
    "sg:province":"IN",
    "sg:tags":[
        "business"
    ],
    "wof:name":"Florals By Jacque",
    "wof:placetype":"venue"
},
  "geometry": {"coordinates":[-85.994679,41.708852],"type":"Point"}
}