{
  "type": "Feature",
  "properties": {
    "iso:country":"US",
    "sg:address":"142 W Mill St",
    "sg:city":"Bloomfield",
    "sg:classifiers":[
        {
            "category":"Autos & Motor Vehicles",
            "subcategory":"Motorcycle Sales",
            "type":"Retail Goods"
        }
    ],
    "sg:phone":"+1 812 384 3612",
    "sg:postcode":"47424",
    "sg:province":"IN",
    "wof:name":"R & D May Co",
    "wof:placetype":"venue"
},
  "geometry": {"coordinates":[-86.940483,39.020406],"type":"Point"}
}