{
  "type": "Feature",
  "properties": {
    "iso:country":"US",
    "sg:address":"7520 E 88th Pl",
    "sg:city":"Indianapolis",
    "sg:classifiers":[
        {
            "category":"Wholesale",
            "subcategory":"Electrical",
            "type":"Manufacturing & Wholesale Goods"
        }
    ],
    "sg:phone":"+1 317 842 7799",
    "sg:postcode":"46256",
    "sg:province":"IN",
    "sg:tags":[
        "alarm",
        "burglar",
        "system"
    ],
    "sg:website":"www.sentinelalarm.net",
    "wof:name":"Sentinel Alarm Systems Inc",
    "wof:placetype":"venue"
},
  "geometry": {"coordinates":[-86.035312,39.916878],"type":"Point"}
}