{
  "type": "Feature",
  "properties": {
    "iso:country":"US",
    "sg:address":"4400 W 16th St",
    "sg:city":"Indianapolis",
    "sg:classifiers":[
        {
            "category":"Sports & Exercise",
            "subcategory":"Golf",
            "type":"Entertainment"
        },
        {
            "category":"Recreation",
            "type":"Entertainment"
        },
        {
            "category":"Travel",
            "subcategory":"Hotels & Motels",
            "type":"Entertainment"
        }
    ],
    "sg:phone":"+1 317 241 2500",
    "sg:postcode":"46222",
    "sg:province":"IN",
    "sg:tags":[
        "course",
        "instruction"
    ],
    "wof:name":"Brickyard Crossing Golf Course",
    "wof:placetype":"venue"
},
  "geometry": {"coordinates":[-86.233853,39.787509],"type":"Point"}
}