{
  "type": "Feature",
  "properties": {
    "iso:country":"US",
    "sg:address":"1811 Bundy Ave",
    "sg:city":"New Castle",
    "sg:classifiers":[
        {
            "category":"Professional",
            "subcategory":"Lawyer & Legal Services",
            "type":"Services"
        }
    ],
    "sg:phone":"+1 765 529 0501",
    "sg:postcode":"47362",
    "sg:province":"IN",
    "sg:tags":[
        "attorney"
    ],
    "wof:name":"Miller Law Office",
    "wof:placetype":"venue"
},
  "geometry": {"coordinates":[-85.380018,39.915164],"type":"Point"}
}