{
  "type": "Feature",
  "properties": {
    "iso:country":"US",
    "sg:address":"209 E Raymond St",
    "sg:city":"Indianapolis",
    "sg:classifiers":[
        {
            "category":"Organizations",
            "subcategory":"Religious Organization",
            "type":"Services"
        }
    ],
    "sg:phone":"+1 317 787 2764",
    "sg:postcode":"46225",
    "sg:province":"IN",
    "sg:tags":[
        "place",
        "worship",
        "church"
    ],
    "sg:website":"www.vidacristiana.net",
    "wof:name":"Vida Cristiana Asamblea De Dios",
    "wof:placetype":"venue"
},
  "geometry": {"coordinates":[-86.15371399999999,39.737171],"type":"Point"}
}