{
  "type": "Feature",
  "properties": {
    "iso:country":"US",
    "sg:address":"514 E Co Rd 300 N",
    "sg:city":"Sullivan",
    "sg:classifiers":[
        {
            "category":"Wholesale",
            "subcategory":"Vending Machines",
            "type":"Manufacturing & Wholesale Goods"
        }
    ],
    "sg:phone":"+1 812 268 3009",
    "sg:postcode":"47882",
    "sg:province":"IN",
    "sg:tags":[
        "operator"
    ],
    "wof:name":"Hale's Vending",
    "wof:placetype":"venue"
},
  "geometry": {"coordinates":[-87.39960600000001,39.128156],"type":"Point"}
}