{
  "type": "Feature",
  "properties": {
    "iso:country":"US",
    "sg:address":"901 W 47th Ave",
    "sg:city":"Gary",
    "sg:classifiers":[
        {
            "category":"Organizations",
            "subcategory":"Religious Organization",
            "type":"Services"
        }
    ],
    "sg:phone":"+1 219 887 9547",
    "sg:postcode":"46408",
    "sg:province":"IN",
    "sg:tags":[
        "church"
    ],
    "wof:name":"Advancing Christ's Kingdom",
    "wof:placetype":"venue"
},
  "geometry": {"coordinates":[-87.34836799999999,41.533191],"type":"Point"}
}