{
  "type": "Feature",
  "properties": {
    "iso:country":"US",
    "sg:address":"1530 W Western Ave",
    "sg:city":"South Bend",
    "sg:classifiers":[
        {
            "category":"Shopping",
            "subcategory":"Used Merchandise",
            "type":"Retail Goods"
        }
    ],
    "sg:phone":"+1 574 287 7550",
    "sg:postcode":"46619",
    "sg:province":"IN",
    "sg:tags":[
        "pawnbroker"
    ],
    "wof:name":"Ozark's Pawn Shop",
    "wof:placetype":"venue"
},
  "geometry": {"coordinates":[-86.274144,41.672096],"type":"Point"}
}