{
  "type": "Feature",
  "properties": {
    "iso:country":"US",
    "sg:address":"147 E 50 S",
    "sg:city":"Valparaiso",
    "sg:classifiers":[
        {
            "category":"Shopping",
            "subcategory":"Used Merchandise",
            "type":"Retail Goods"
        }
    ],
    "sg:phone":"+1 219 477 6629",
    "sg:postcode":"46383",
    "sg:province":"IN",
    "sg:tags":[
        "antique"
    ],
    "wof:name":"Old Country Barn",
    "wof:placetype":"venue"
},
  "geometry": {"coordinates":[-87.042039,41.427433],"type":"Point"}
}