{
  "type": "Feature",
  "properties": {
    "iso:country":"US",
    "sg:address":"1212 E Sycamore St",
    "sg:city":"Kokomo",
    "sg:classifiers":[
        {
            "category":"Restaurant",
            "type":"Food & Drink"
        }
    ],
    "sg:phone":"+1 765 452 4244",
    "sg:postcode":"46901",
    "sg:province":"IN",
    "sg:tags":[
        "caterer"
    ],
    "wof:name":"Chorrushi's Catering",
    "wof:placetype":"venue"
},
  "geometry": {"coordinates":[-86.114511,40.487629],"type":"Point"}
}