{
  "type": "Feature",
  "properties": {
    "iso:country":"US",
    "sg:address":"2340 Shelby St",
    "sg:city":"Indianapolis",
    "sg:classifiers":[
        {
            "category":"Building & Trades",
            "subcategory":"Pest Control",
            "type":"Services"
        }
    ],
    "sg:phone":"+1 317 245 8241",
    "sg:postcode":"46203",
    "sg:province":"IN",
    "wof:name":"Affordapro Pest Control",
    "wof:placetype":"venue"
},
  "geometry": {"coordinates":[-86.139709,39.734619],"type":"Point"}
}