{
  "type": "Feature",
  "properties": {
    "iso:country":"US",
    "sg:address":"4844 N 700 W",
    "sg:city":"Mc Cordsville",
    "sg:classifiers":[
        {
            "category":"Building & Trades",
            "subcategory":"Plumbing",
            "type":"Services"
        }
    ],
    "sg:phone":"+1 317 335 3836",
    "sg:postcode":"46055",
    "sg:province":"IN",
    "sg:tags":[
        "plumbing",
        "contractor"
    ],
    "wof:name":"Turner & Richey Plumbing Inc",
    "wof:placetype":"venue"
},
  "geometry": {"coordinates":[-85.934781,39.851618],"type":"Point"}
}