{
  "type": "Feature",
  "properties": {
    "iso:country":"US",
    "sg:address":"3150 E Thompson Rd",
    "sg:city":"Indianapolis",
    "sg:classifiers":[
        {
            "category":"Shopping",
            "subcategory":"Florist",
            "type":"Retail Goods"
        }
    ],
    "sg:phone":"+1 317 872 7038",
    "sg:postcode":"46227",
    "sg:province":"IN",
    "sg:website":"www.stevesflowers.com",
    "wof:name":"Steve's Flowers & Gifts",
    "wof:placetype":"venue"
},
  "geometry": {"coordinates":[-86.111449,39.694083],"type":"Point"}
}