{
  "type": "Feature",
  "properties": {
    "iso:country":"US",
    "sg:address":"8722 N Meridian St",
    "sg:city":"Indianapolis",
    "sg:classifiers":[
        {
            "category":"Real Estate",
            "subcategory":"Real Estate Services",
            "type":"Services"
        }
    ],
    "sg:phone":"+1 317 844 4400",
    "sg:postcode":"46260",
    "sg:province":"IN",
    "wof:name":"Boston Tim Rl Est",
    "wof:placetype":"venue"
},
  "geometry": {"coordinates":[-86.157898,39.9151],"type":"Point"}
}