{
  "type": "Feature",
  "properties": {
    "iso:country":"US",
    "sg:address":"5739 Bluespruce Dr",
    "sg:city":"Indianapolis",
    "sg:classifiers":[
        {
            "category":"Wholesale",
            "subcategory":"Medical Equipment & Supplies",
            "type":"Manufacturing & Wholesale Goods"
        }
    ],
    "sg:phone":"+1 317 784 7530",
    "sg:postcode":"46237",
    "sg:province":"IN",
    "sg:tags":[
        "microscope"
    ],
    "wof:name":"Scientific Instrument Svc Co",
    "wof:placetype":"venue"
},
  "geometry": {"coordinates":[-86.06864400000001,39.682812],"type":"Point"}
}