{
  "type": "Feature",
  "properties": {
    "iso:country":"US",
    "sg:address":"1523 E Bristol St",
    "sg:city":"Elkhart",
    "sg:classifiers":[
        {
            "category":"Food & Beverages",
            "subcategory":"Groceries & Convenience Stores",
            "type":"Retail Goods"
        }
    ],
    "sg:phone":"+1 574 264 1246",
    "sg:postcode":"46514",
    "sg:province":"IN",
    "sg:tags":[
        "grocer"
    ],
    "wof:name":"Phil's Grocery",
    "wof:placetype":"venue"
},
  "geometry": {"coordinates":[-85.95648799999999,41.702516],"type":"Point"}
}