{
  "type": "Feature",
  "properties": {
    "iso:country":"US",
    "sg:address":"211 Main St",
    "sg:city":"Rising Sun",
    "sg:classifiers":[
        {
            "category":"Shopping",
            "type":"Retail Goods"
        }
    ],
    "sg:phone":"+1 812 438 4300",
    "sg:postcode":"47040",
    "sg:province":"IN",
    "sg:tags":[
        "art",
        "gallery",
        "dealer"
    ],
    "wof:name":"Vera Curnow Gallery & Fine Art",
    "wof:placetype":"venue"
},
  "geometry": {"coordinates":[-84.853126,38.948557],"type":"Point"}
}