{
  "type": "Feature",
  "properties": {
    "iso:country":"US",
    "sg:address":"3051 W 900 N",
    "sg:city":"Edinburgh",
    "sg:classifiers":[
        {
            "category":"Home & Garden",
            "subcategory":"Carpets & Floor Coverings",
            "type":"Retail Goods"
        }
    ],
    "sg:phone":"+1 812 526 9200",
    "sg:postcode":"46124",
    "sg:province":"IN",
    "sg:tags":[
        "dealer",
        "rug"
    ],
    "wof:name":"Action Carpet",
    "wof:placetype":"venue"
},
  "geometry": {"coordinates":[-85.959717,39.332685],"type":"Point"}
}