{
  "type": "Feature",
  "properties": {
    "iso:country":"US",
    "sg:address":"925 E Albion St",
    "sg:city":"Avilla",
    "sg:classifiers":[
        {
            "category":"Building & Trades",
            "subcategory":"Construction",
            "type":"Services"
        }
    ],
    "sg:phone":"+1 260 897 3977",
    "sg:postcode":"46710",
    "sg:province":"IN",
    "sg:tags":[
        "company"
    ],
    "wof:name":"Norden Construction Inc",
    "wof:placetype":"venue"
},
  "geometry": {"coordinates":[-85.23590299999999,41.365823],"type":"Point"}
}