{
  "type": "Feature",
  "properties": {
    "iso:country":"US",
    "sg:address":"13762 Wyandotte Pl",
    "sg:city":"Fishers",
    "sg:classifiers":[
        {
            "category":"Retail",
            "subcategory":"Portrait Studio",
            "type":"Services"
        }
    ],
    "sg:phone":"+1 317 577 0999",
    "sg:postcode":"46038",
    "sg:province":"IN",
    "sg:tags":[
        "photographer"
    ],
    "wof:name":"Steve Gray Photography",
    "wof:placetype":"venue"
},
  "geometry": {"coordinates":[-86.012546,39.987636],"type":"Point"}
}