{
  "type": "Feature",
  "properties": {
    "addr:full":"6035 N State Rd 327 Orland IN 46776",
    "addr:housenumber":"6035;327",
    "addr:postcode":"46776",
    "addr:street":"N State Rd",
    "iso:country":"US",
    "sg:address":"6035 N State Rd 327",
    "sg:city":"Orland",
    "sg:classifiers":[
        {
            "category":"Education",
            "subcategory":"Library",
            "type":"Public Place"
        }
    ],
    "sg:phone":"+1 260 829 6329",
    "sg:postcode":"46776",
    "sg:province":"IN",
    "wof:name":"Joyce Public Library",
    "wof:placetype":"venue"
},
  "geometry": {"coordinates":[-85.171357,41.730336],"type":"Point"}
}