{
  "type": "Feature",
  "properties": {
    "iso:country":"US",
    "sg:address":"523 E Chicago Ave",
    "sg:city":"East Chicago",
    "sg:classifiers":[
        {
            "category":"Health Services",
            "subcategory":"Health Practitioner",
            "type":"Services"
        }
    ],
    "sg:phone":"+1 219 397 6488",
    "sg:postcode":"46312",
    "sg:province":"IN",
    "wof:name":"Physical Therapy Of E Chicago",
    "wof:placetype":"venue"
},
  "geometry": {"coordinates":[-87.466025,41.62921],"type":"Point"}
}