{
  "type": "Feature",
  "properties": {
    "addr:full":"1107 4th St Covington IN 47932",
    "addr:housenumber":"1107",
    "addr:postcode":"47932",
    "addr:street":"4Th St",
    "iso:country":"US",
    "sg:address":"1107 4th St",
    "sg:city":"Covington",
    "sg:classifiers":[
        {
            "category":"Professional",
            "subcategory":"Lawyer & Legal Services",
            "type":"Services"
        }
    ],
    "sg:phone":"+1 765 793 2341",
    "sg:postcode":"47932",
    "sg:province":"IN",
    "sg:tags":[
        "attorney"
    ],
    "wof:name":"Williams & Williams",
    "wof:placetype":"venue"
},
  "geometry": {"coordinates":[-87.397882,40.144735],"type":"Point"}
}