{
  "type": "Feature",
  "properties": {
    "addr:full":"1156 Cope Rd Martinsville IN 46151",
    "addr:housenumber":"1156",
    "addr:postcode":"46151",
    "addr:street":"Cope Rd",
    "iso:country":"US",
    "sg:address":"1156 Cope Rd",
    "sg:city":"Martinsville",
    "sg:classifiers":[
        {
            "category":"Wholesale",
            "subcategory":"Chemicals & Plastics",
            "type":"Manufacturing & Wholesale Goods"
        }
    ],
    "sg:phone":"+1 765 352 0554",
    "sg:postcode":"46151",
    "sg:province":"IN",
    "sg:tags":[
        "product"
    ],
    "wof:name":"Fabricating Plus Inc",
    "wof:placetype":"venue"
},
  "geometry": {"coordinates":[-86.314779,39.449187],"type":"Point"}
}