{
  "type": "Feature",
  "properties": {
    "iso:country":"US",
    "sg:address":"29805 Grant Rd",
    "sg:city":"New Carlisle",
    "sg:classifiers":[
        {
            "category":"Home & Garden",
            "subcategory":"Garden Supply",
            "type":"Retail Goods"
        }
    ],
    "sg:phone":"+1 574 654 0344",
    "sg:postcode":"46552",
    "sg:province":"IN",
    "sg:tags":[
        "landscaping",
        "equipment"
    ],
    "wof:name":"Millennium Curbing",
    "wof:placetype":"venue"
},
  "geometry": {"coordinates":[-86.452422,41.664943],"type":"Point"}
}