{
  "type": "Feature",
  "properties": {
    "addr:full":"6217 Heritage Oaks Pl Fort Wayne IN 46835",
    "addr:housenumber":"6217",
    "addr:postcode":"46835",
    "addr:street":"Heritage Oaks Pl",
    "iso:country":"US",
    "sg:address":"6217 Heritage Oaks Pl",
    "sg:city":"Fort Wayne",
    "sg:classifiers":[
        {
            "category":"Building & Trades",
            "subcategory":"Electrical",
            "type":"Services"
        }
    ],
    "sg:phone":"+1 260 485 6181",
    "sg:postcode":"46835",
    "sg:province":"IN",
    "sg:tags":[
        "electric",
        "contractor"
    ],
    "wof:name":"J & N Performance Electric",
    "wof:placetype":"venue"
},
  "geometry": {"coordinates":[-85.056628,41.137356],"type":"Point"}
}