{
  "type": "Feature",
  "properties": {
    "iso:country":"US",
    "sg:address":"2500 Spy Run Ave",
    "sg:city":"Fort Wayne",
    "sg:classifiers":[
        {
            "category":"Autos & Motor Vehicles",
            "subcategory":"Automobile Sales",
            "type":"Retail Goods"
        }
    ],
    "sg:phone":"+1 260 496 9022",
    "sg:postcode":"46805",
    "sg:province":"IN",
    "sg:tags":[
        "car",
        "dealer"
    ],
    "wof:name":"Old Crown Auto Sales Inc",
    "wof:placetype":"venue"
},
  "geometry": {"coordinates":[-85.137669,41.097943],"type":"Point"}
}