{
  "type": "Feature",
  "properties": {
    "iso:country":"US",
    "sg:address":"116 E North A St",
    "sg:city":"Gas City",
    "sg:classifiers":[
        {
            "category":"Health Services",
            "subcategory":"Doctor",
            "type":"Services"
        }
    ],
    "sg:phone":"+1 765 674 8581",
    "sg:postcode":"46933",
    "sg:province":"IN",
    "sg:tags":[
        "physician",
        "surgeon"
    ],
    "wof:name":"Dharam Raj MD",
    "wof:placetype":"venue"
},
  "geometry": {"coordinates":[-85.61336900000001,40.488767],"type":"Point"}
}