{
  "type": "Feature",
  "properties": {
    "iso:country":"US",
    "sg:address":"6756 E Old 56",
    "sg:city":"Salem",
    "sg:classifiers":[
        {
            "category":"Farming",
            "subcategory":"Poultry Farm",
            "type":"Manufacturing & Wholesale Goods"
        }
    ],
    "sg:phone":"+1 812 883 4898",
    "sg:postcode":"47167",
    "sg:province":"IN",
    "sg:tags":[
        "egg"
    ],
    "wof:name":"Lyles Turkey Farm",
    "wof:placetype":"venue"
},
  "geometry": {"coordinates":[-85.98062,38.648442],"type":"Point"}
}