{
  "type": "Feature",
  "properties": {
    "iso:country":"US",
    "sg:address":"4287 W 96th St",
    "sg:city":"Indianapolis",
    "sg:classifiers":[
        {
            "category":"Wholesale",
            "subcategory":"Electrical",
            "type":"Manufacturing & Wholesale Goods"
        }
    ],
    "sg:phone":"+1 317 704 0440",
    "sg:postcode":"46268",
    "sg:province":"IN",
    "sg:tags":[
        "alarm",
        "burglar",
        "system"
    ],
    "wof:name":"Itech Digital",
    "wof:placetype":"venue"
},
  "geometry": {"coordinates":[-86.232479,39.92607],"type":"Point"}
}