{
  "type": "Feature",
  "properties": {
    "iso:country":"US",
    "sg:address":"52 E Washington St",
    "sg:city":"Knox",
    "sg:classifiers":[
        {
            "category":"Restaurant",
            "type":"Food & Drink"
        }
    ],
    "sg:phone":"+1 574 772 9050",
    "sg:postcode":"46534",
    "sg:province":"IN",
    "wof:name":"Dog-Dickity Good",
    "wof:placetype":"venue"
},
  "geometry": {"coordinates":[-86.622018,41.298365],"type":"Point"}
}