{
  "type": "Feature",
  "properties": {
    "addr:full":"830 E Main St Richmond IN 47374",
    "addr:housenumber":"830",
    "addr:postcode":"47374",
    "addr:street":"E Main St",
    "iso:country":"US",
    "sg:address":"830 E Main St",
    "sg:city":"Richmond",
    "sg:classifiers":[
        {
            "category":"Professional",
            "subcategory":"Computer Services",
            "type":"Services"
        }
    ],
    "sg:phone":"+1 765 962 2420",
    "sg:postcode":"47374",
    "sg:province":"IN",
    "sg:tags":[
        "programing",
        "custom"
    ],
    "wof:name":"Systems Solutions",
    "wof:placetype":"venue"
},
  "geometry": {"coordinates":[-84.890626,39.829117],"type":"Point"}
}