{
  "type": "Feature",
  "properties": {
    "iso:country":"US",
    "sg:address":"3737 Waldemere Ave",
    "sg:city":"Indianapolis",
    "sg:classifiers":[
        {
            "category":"Wholesale",
            "subcategory":"Non-durable Goods",
            "type":"Manufacturing & Wholesale Goods"
        }
    ],
    "sg:phone":"+1 317 612 3195",
    "sg:postcode":"46241",
    "sg:province":"IN",
    "sg:tags":[
        "advertising"
    ],
    "wof:name":"Vision Concepts",
    "wof:placetype":"venue"
},
  "geometry": {"coordinates":[-86.261219,39.710151],"type":"Point"}
}