{
  "type": "Feature",
  "properties": {
    "iso:country":"US",
    "sg:address":"5017 Gibbs Rd",
    "sg:city":"Plainfield",
    "sg:classifiers":[
        {
            "category":"Building & Trades",
            "subcategory":"Construction",
            "type":"Services"
        }
    ],
    "sg:phone":"+1 317 837 8047",
    "sg:postcode":"46168",
    "sg:province":"IN",
    "sg:tags":[
        "general",
        "contractor"
    ],
    "wof:name":"Weaver Construction Inc",
    "wof:placetype":"venue"
},
  "geometry": {"coordinates":[-86.43585,39.719187],"type":"Point"}
}