{
  "type": "Feature",
  "properties": {
    "addr:full":"639 Conner St Noblesville IN 46060",
    "addr:housenumber":"639",
    "addr:postcode":"46060",
    "addr:street":"Conner St",
    "iso:country":"US",
    "sg:address":"639 Conner St",
    "sg:city":"Noblesville",
    "sg:classifiers":[
        {
            "category":"Building & Trades",
            "subcategory":"Locksmith",
            "type":"Services"
        }
    ],
    "sg:phone":"+1 317 565 1100",
    "sg:postcode":"46060",
    "sg:province":"IN",
    "sg:tags":[
        "key"
    ],
    "wof:name":"24 Hour Emergency Locksmith",
    "wof:placetype":"venue"
},
  "geometry": {"coordinates":[-86.01541400000001,40.045477],"type":"Point"}
}