{
  "type": "Feature",
  "properties": {
    "iso:country":"US",
    "sg:address":"4623 S Lynhurst Dr",
    "sg:city":"Indianapolis",
    "sg:classifiers":[
        {
            "category":"Banks & Credit Unions",
            "subcategory":"Investment Brokerage",
            "type":"Services"
        }
    ],
    "sg:phone":"+1 317 247 7853",
    "sg:postcode":"46221",
    "sg:province":"IN",
    "sg:tags":[
        "advisory",
        "financial"
    ],
    "wof:name":"Hampton Blade Financial Svc",
    "wof:placetype":"venue"
},
  "geometry": {"coordinates":[-86.250409,39.696471],"type":"Point"}
}