{
  "type": "Feature",
  "properties": {
    "iso:country":"US",
    "sg:address":"1151 N Hartford St",
    "sg:city":"Eaton",
    "sg:classifiers":[
        {
            "category":"Manufacturing",
            "subcategory":"Paper Products",
            "type":"Manufacturing & Wholesale Goods"
        }
    ],
    "sg:phone":"+1 765 396 3351",
    "sg:postcode":"47338",
    "sg:province":"IN",
    "sg:tags":[
        "bag",
        "coated",
        "plastic"
    ],
    "wof:name":"Grayson Enterprises",
    "wof:placetype":"venue"
},
  "geometry": {"coordinates":[-85.356457,40.350583],"type":"Point"}
}