{
  "type": "Feature",
  "properties": {
    "addr:full":"8450 N Payne Rd Indianapolis IN 46268",
    "addr:housenumber":"8450",
    "addr:postcode":"46268",
    "addr:street":"N Payne Rd",
    "iso:country":"US",
    "sg:address":"8450 N Payne Rd",
    "sg:city":"Indianapolis",
    "sg:classifiers":[
        {
            "category":"Organizations",
            "subcategory":"Non-profit Organization",
            "type":"Services"
        }
    ],
    "sg:phone":"+1 317 872 4210",
    "sg:postcode":"46268",
    "sg:province":"IN",
    "sg:website":"www.stvincent.org",
    "wof:name":"St Vincent New Hope",
    "wof:placetype":"venue"
},
  "geometry": {"coordinates":[-86.22707200000001,39.907599],"type":"Point"}
}