{
  "type": "Feature",
  "properties": {
    "iso:country":"US",
    "sg:address":"6211 W 30th St",
    "sg:city":"Indianapolis",
    "sg:classifiers":[
        {
            "category":"Health Services",
            "subcategory":"Clinic",
            "type":"Services"
        }
    ],
    "sg:phone":"+1 317 291 1111",
    "sg:postcode":"46224",
    "sg:province":"IN",
    "sg:tags":[
        "information",
        "dentist",
        "bureau"
    ],
    "sg:website":"www.indydentists.com",
    "wof:name":"INDYDENTISTS.COM",
    "wof:placetype":"venue"
},
  "geometry": {"coordinates":[-86.269308,39.809204],"type":"Point"}
}