{
  "type": "Feature",
  "properties": {
    "iso:country":"US",
    "sg:address":"306 E 4th St",
    "sg:city":"Huntingburg",
    "sg:classifiers":[
        {
            "category":"Health Services",
            "subcategory":"Doctor",
            "type":"Services"
        }
    ],
    "sg:phone":"+1 812 683 4314",
    "sg:postcode":"47542",
    "sg:province":"IN",
    "sg:tags":[
        "medical"
    ],
    "wof:name":"Louis B Kastan MD",
    "wof:placetype":"venue"
},
  "geometry": {"coordinates":[-86.957076,38.296144],"type":"Point"}
}