{
  "type": "Feature",
  "properties": {
    "iso:country":"US",
    "sg:address":"7518 Hearthstone Way",
    "sg:city":"Indianapolis",
    "sg:classifiers":[
        {
            "category":"Manufacturing",
            "subcategory":"Glass & Minerals",
            "type":"Manufacturing & Wholesale Goods"
        }
    ],
    "sg:phone":"+1 317 882 1084",
    "sg:postcode":"46227",
    "sg:province":"IN",
    "sg:tags":[
        "decoration",
        "glassware"
    ],
    "wof:name":"Sandcarvers",
    "wof:placetype":"venue"
},
  "geometry": {"coordinates":[-86.105719,39.657449],"type":"Point"}
}