{
  "type": "Feature",
  "properties": {
    "addr:full":"6330 E State Blvd Fort Wayne IN 46815",
    "addr:housenumber":"6330",
    "addr:postcode":"46815",
    "addr:street":"E State Blvd",
    "iso:country":"US",
    "sg:address":"6330 E State Blvd",
    "sg:city":"Fort Wayne",
    "sg:classifiers":[
        {
            "category":"Restaurant",
            "type":"Food & Drink"
        }
    ],
    "sg:phone":"+1 260 493 2025",
    "sg:postcode":"46815",
    "sg:province":"IN",
    "wof:name":"Jeff's Coney",
    "wof:placetype":"venue"
},
  "geometry": {"coordinates":[-85.05959199999999,41.100802],"type":"Point"}
}