{
  "type": "Feature",
  "properties": {
    "iso:country":"US",
    "sg:address":"1250 N 290 W",
    "sg:city":"Angola",
    "sg:classifiers":[
        {
            "category":"Health Services",
            "subcategory":"Chiropractor",
            "type":"Services"
        }
    ],
    "sg:phone":"+1 260 665 7576",
    "sg:postcode":"46703",
    "sg:province":"IN",
    "wof:name":"John F Hammel DC",
    "wof:placetype":"venue"
},
  "geometry": {"coordinates":[-85.045382,41.66182],"type":"Point"}
}