{
  "type": "Feature",
  "properties": {
    "iso:country":"US",
    "sg:address":"809 1st St",
    "sg:city":"Plymouth",
    "sg:classifiers":[
        {
            "category":"Retail",
            "subcategory":"Auto Repair",
            "type":"Services"
        }
    ],
    "sg:phone":"+1 574 936 9484",
    "sg:postcode":"46563",
    "sg:province":"IN",
    "sg:tags":[
        "wrecker"
    ],
    "wof:name":"Carnegie Towing",
    "wof:placetype":"venue"
},
  "geometry": {"coordinates":[-86.31433699999999,41.345497],"type":"Point"}
}