{
  "type": "Feature",
  "properties": {
    "iso:country":"US",
    "sg:address":"1220 N 1st Ave",
    "sg:city":"Evansville",
    "sg:classifiers":[
        {
            "category":"Manufacturing",
            "subcategory":"Glass & Minerals",
            "type":"Manufacturing & Wholesale Goods"
        }
    ],
    "sg:phone":"+1 812 425 8658",
    "sg:postcode":"47710",
    "sg:province":"IN",
    "sg:tags":[
        "prod",
        "made"
    ],
    "wof:name":"Stained Glass Specialties Inc",
    "wof:placetype":"venue"
},
  "geometry": {"coordinates":[-87.57486400000001,37.989832],"type":"Point"}
}