{
  "type": "Feature",
  "properties": {
    "iso:country":"US",
    "sg:address":"2512 Potawatomi Dr",
    "sg:city":"Lafayette",
    "sg:classifiers":[
        {
            "category":"Home & Garden",
            "subcategory":"Home Furnishings",
            "type":"Retail Goods"
        }
    ],
    "sg:phone":"+1 765 474 3875",
    "sg:postcode":"47909",
    "sg:province":"IN",
    "sg:tags":[
        "sporting"
    ],
    "wof:name":"Everyday Gourmet The",
    "wof:placetype":"venue"
},
  "geometry": {"coordinates":[-86.87221099999999,40.390887],"type":"Point"}
}