{
  "type": "Feature",
  "properties": {
    "iso:country":"US",
    "sg:address":"5399 Vanada Rd",
    "sg:city":"Newburgh",
    "sg:classifiers":[
        {
            "category":"Farming",
            "subcategory":"Nursery",
            "type":"Manufacturing & Wholesale Goods"
        }
    ],
    "sg:phone":"+1 812 853 8060",
    "sg:postcode":"47630",
    "sg:province":"IN",
    "sg:tags":[
        "greenhouse"
    ],
    "wof:name":"Prow's Greenhouses & Florist",
    "wof:placetype":"venue"
},
  "geometry": {"coordinates":[-87.35003,37.940676],"type":"Point"}
}