{
  "type": "Feature",
  "properties": {
    "iso:country":"US",
    "sg:address":"1345 Clifty Dr",
    "sg:city":"Madison",
    "sg:classifiers":[
        {
            "category":"Shopping",
            "subcategory":"Department Store",
            "type":"Retail Goods"
        }
    ],
    "sg:phone":"+1 812 273 4233",
    "sg:postcode":"47250",
    "sg:province":"IN",
    "sg:tags":[
        "shop"
    ],
    "wof:name":"Big Lots",
    "wof:placetype":"venue"
},
  "geometry": {"coordinates":[-85.414159,38.771997],"type":"Point"}
}