{
  "type": "Feature",
  "properties": {
    "iso:country":"US",
    "sg:address":"6225 S Franklin Rd",
    "sg:city":"Indianapolis",
    "sg:classifiers":[
        {
            "category":"Social Services",
            "subcategory":"Child Care",
            "type":"Services"
        }
    ],
    "sg:phone":"+1 317 862 1111",
    "sg:postcode":"46259",
    "sg:province":"IN",
    "wof:name":"Heaven To Eleven",
    "wof:placetype":"venue"
},
  "geometry": {"coordinates":[-86.01853699999999,39.677157],"type":"Point"}
}