{
  "type": "Feature",
  "properties": {
    "iso:country":"US",
    "sg:address":"324 Rusher Creek Rd",
    "sg:city":"Evansville",
    "sg:classifiers":[
        {
            "category":"Travel",
            "subcategory":"Hotels & Motels",
            "type":"Entertainment"
        }
    ],
    "sg:phone":"+1 877 574 2464",
    "sg:postcode":"47725",
    "sg:province":"IN",
    "sg:tags":[
        "lodging"
    ],
    "sg:website":"http://book.bestwestern.com/bestwestern/priceAvail.do?propertyCode=15086&cm_mmc=IYP-_-YP-_-property-_-15086",
    "wof:name":"Best Western Gateway Inn & Suites",
    "wof:placetype":"venue"
},
  "geometry": {"coordinates":[-87.549679,38.157606],"type":"Point"}
}