{
  "type": "Feature",
  "properties": {
    "addr:full":"16971 Clover Rd Noblesville IN 46060",
    "addr:housenumber":"16971",
    "addr:postcode":"46060",
    "addr:street":"Clover Rd",
    "iso:country":"US",
    "sg:address":"16971 Clover Rd",
    "sg:city":"Noblesville",
    "sg:classifiers":[
        {
            "category":"Food & Beverages",
            "subcategory":"Groceries & Convenience Stores",
            "type":"Retail Goods"
        }
    ],
    "sg:phone":"+1 317 000 1111",
    "sg:postcode":"46060",
    "sg:province":"IN",
    "sg:tags":[
        "grocer"
    ],
    "wof:name":"Aldi",
    "wof:placetype":"venue"
},
  "geometry": {"coordinates":[-85.998065,40.038236],"type":"Point"}
}