{
  "type": "Feature",
  "properties": {
    "iso:country":"US",
    "sg:address":"200 E Line St",
    "sg:city":"Geneva",
    "sg:classifiers":[
        {
            "category":"Government",
            "subcategory":"Fire Station",
            "type":"Public Place"
        }
    ],
    "sg:phone":"+1 260 000 1111",
    "sg:postcode":"46740",
    "sg:province":"IN",
    "sg:tags":[
        "department"
    ],
    "wof:name":"Geneva Fire Dept",
    "wof:placetype":"venue"
},
  "geometry": {"coordinates":[-84.959381,40.59202],"type":"Point"}
}