{
  "type": "Feature",
  "properties": {
    "addr:full":"427 W 11th St Bicknell IN 47512",
    "addr:housenumber":"427",
    "addr:postcode":"47512",
    "addr:street":"W 11Th St",
    "iso:country":"US",
    "sg:address":"427 W 11th St",
    "sg:city":"Bicknell",
    "sg:classifiers":[
        {
            "category":"Restaurant",
            "type":"Food & Drink"
        }
    ],
    "sg:phone":"+1 812 735 1782",
    "sg:postcode":"47512",
    "sg:province":"IN",
    "wof:name":"Subway Sandwiches & Salads",
    "wof:placetype":"venue"
},
  "geometry": {"coordinates":[-87.314626,38.780209],"type":"Point"}
}