{
  "type": "Feature",
  "properties": {
    "addr:full":"14390 Clay Terrace Blvd. Suite 130 Carmel IN 46032",
    "addr:housenumber":"14390",
    "addr:postcode":"46032",
    "addr:street":"Clay Terrace Blvd. Suite 130",
    "iso:country":"US",
    "sg:address":"14390 Clay Terrace Blvd. Suite 130",
    "sg:city":"Carmel",
    "sg:classifiers":[
        {
            "category":"Shopping",
            "subcategory":"Clothing, Apparel, & Fashions",
            "type":"Retail Goods"
        }
    ],
    "sg:phone":"+1 317 575 0842",
    "sg:postcode":"46032",
    "sg:province":"IN",
    "sg:tags":[
        "clothing",
        "women's"
    ],
    "sg:website":"www.whitehouseblackmarket.com",
    "wof:name":"White House Black Market",
    "wof:placetype":"venue"
},
  "geometry": {"coordinates":[-86.130064,39.99681],"type":"Point"}
}