{
  "type": "Feature",
  "properties": {
    "iso:country":"US",
    "sg:address":"1720 Baker Dr",
    "sg:city":"Ossian",
    "sg:classifiers":[
        {
            "category":"Manufacturing",
            "subcategory":"Pet Food",
            "type":"Manufacturing & Wholesale Goods"
        }
    ],
    "sg:phone":"+1 260 622 6216",
    "sg:postcode":"46777",
    "sg:province":"IN",
    "sg:tags":[
        "flour",
        "prepared",
        "dough",
        "mix"
    ],
    "wof:name":"Dawn Food Products Inc",
    "wof:placetype":"venue"
},
  "geometry": {"coordinates":[-85.172873,40.866815],"type":"Point"}
}