{
  "type": "Feature",
  "properties": {
    "iso:country":"US",
    "sg:address":"12201 State Rd 238",
    "sg:city":"Noblesville",
    "sg:classifiers":[
        {
            "category":"Building & Trades",
            "subcategory":"Construction",
            "type":"Services"
        }
    ],
    "sg:phone":"+1 317 774 7174",
    "sg:postcode":"46060",
    "sg:province":"IN",
    "sg:tags":[
        "general",
        "contractor"
    ],
    "wof:name":"Olynger Construction",
    "wof:placetype":"venue"
},
  "geometry": {"coordinates":[-85.949173,40.006771],"type":"Point"}
}