{
  "type": "Feature",
  "properties": {
    "iso:country":"US",
    "sg:address":"5421 N Co Rd 330 E",
    "sg:city":"Muncie",
    "sg:classifiers":[
        {
            "category":"Personal",
            "subcategory":"Beauty Salon",
            "type":"Services"
        }
    ],
    "sg:phone":"+1 765 741 8306",
    "sg:postcode":"47303",
    "sg:province":"IN",
    "sg:tags":[
        "cosmetologist"
    ],
    "wof:name":"Penny Auker",
    "wof:placetype":"venue"
},
  "geometry": {"coordinates":[-85.324595,40.238501],"type":"Point"}
}