{
  "type": "Feature",
  "properties": {
    "iso:country":"US",
    "sg:address":"2110 Oakwoods Ln",
    "sg:city":"Westfield",
    "sg:classifiers":[
        {
            "category":"Professional",
            "type":"Services"
        }
    ],
    "sg:phone":"+1 317 867 0990",
    "sg:postcode":"46074",
    "sg:province":"IN",
    "sg:tags":[
        "establishment"
    ],
    "wof:name":"Creative Solutions",
    "wof:placetype":"venue"
},
  "geometry": {"coordinates":[-86.118315,40.024514],"type":"Point"}
}