{
  "type": "Feature",
  "properties": {
    "addr:full":"325 Blackman St Clinton IN 47842",
    "addr:housenumber":"325",
    "addr:postcode":"47842",
    "addr:street":"Blackman St",
    "iso:country":"US",
    "sg:address":"325 Blackman St",
    "sg:city":"Clinton",
    "sg:classifiers":[
        {
            "category":"Social Services",
            "subcategory":"Child Care",
            "type":"Services"
        }
    ],
    "sg:phone":"+1 765 832 2273",
    "sg:postcode":"47842",
    "sg:province":"IN",
    "sg:tags":[
        "kindergarten",
        "academic",
        "school"
    ],
    "wof:name":"Valley Day Care",
    "wof:placetype":"venue"
},
  "geometry": {"coordinates":[-87.400823,39.658316],"type":"Point"}
}