{
  "type": "Feature",
  "properties": {
    "iso:country":"US",
    "sg:address":"1410 S 8th St",
    "sg:city":"Richmond",
    "sg:classifiers":[
        {
            "category":"Retail",
            "subcategory":"Auto Repair",
            "type":"Services"
        }
    ],
    "sg:phone":"+1 765 935 9008",
    "sg:postcode":"47374",
    "sg:province":"IN",
    "sg:tags":[
        "body",
        "automobile",
        "painting"
    ],
    "wof:name":"Duke's Kustom Auto",
    "wof:placetype":"venue"
},
  "geometry": {"coordinates":[-84.89187099999999,39.811433],"type":"Point"}
}