{
  "type": "Feature",
  "properties": {
    "iso:country":"US",
    "sg:address":"3704 W Washington St",
    "sg:city":"Indianapolis",
    "sg:classifiers":[
        {
            "category":"Restaurant",
            "type":"Food & Drink"
        }
    ],
    "sg:menulink":"http://www.allmenus.com/in/speedway/198423-kfc---kentucky-fried-chicken/menu/",
    "sg:phone":"+1 317 241 6295",
    "sg:postcode":"46241",
    "sg:province":"IN",
    "sg:tags":[
        "american",
        "chicken"
    ],
    "wof:name":"KFC - Kentucky Fried Chicken",
    "wof:placetype":"venue"
},
  "geometry": {"coordinates":[-86.223,39.761202],"type":"Point"}
}