{
  "type": "Feature",
  "properties": {
    "iso:country":"US",
    "sg:address":"459 S Court St",
    "sg:city":"Sullivan",
    "sg:classifiers":[
        {
            "category":"Retail",
            "subcategory":"Repair Shop",
            "type":"Services"
        }
    ],
    "sg:phone":"+1 812 268 4292",
    "sg:postcode":"47882",
    "sg:province":"IN",
    "sg:tags":[
        "sharpening",
        "tool",
        "locksmith"
    ],
    "wof:name":"Daves Sharpening & Lock Shop",
    "wof:placetype":"venue"
},
  "geometry": {"coordinates":[-87.408615,39.088636],"type":"Point"}
}