{
  "type": "Feature",
  "properties": {
    "addr:full":"4000 W Peachtree Ln Muncie IN 47304",
    "addr:housenumber":"4000",
    "addr:postcode":"47304",
    "addr:street":"W Peachtree Ln",
    "iso:country":"US",
    "sg:address":"4000 W Peachtree Ln",
    "sg:city":"Muncie",
    "sg:classifiers":[
        {
            "category":"Building & Trades",
            "subcategory":"Construction",
            "type":"Services"
        }
    ],
    "sg:phone":"+1 765 288 1445",
    "sg:postcode":"47304",
    "sg:province":"IN",
    "sg:tags":[
        "ceiling"
    ],
    "wof:name":"Devoe Systems Inc",
    "wof:placetype":"venue"
},
  "geometry": {"coordinates":[-85.432839,40.191027],"type":"Point"}
}