{
  "type": "Feature",
  "properties": {
    "iso:country":"US",
    "sg:address":"1399 W Main St",
    "sg:city":"Paoli",
    "sg:classifiers":[
        {
            "category":"Restaurant",
            "type":"Food & Drink"
        }
    ],
    "sg:phone":"+1 812 723 2768",
    "sg:postcode":"47454",
    "sg:province":"IN",
    "sg:tags":[
        "sandwich"
    ],
    "wof:name":"Shakeburger Drive-In",
    "wof:placetype":"venue"
},
  "geometry": {"coordinates":[-86.48589800000001,38.557973],"type":"Point"}
}