{
  "type": "Feature",
  "properties": {
    "iso:country":"US",
    "sg:address":"4004 E 700 N",
    "sg:city":"Rolling Prairie",
    "sg:classifiers":[
        {
            "category":"Autos & Motor Vehicles",
            "subcategory":"Fuel & Gas Station",
            "type":"Retail Goods"
        }
    ],
    "sg:phone":"+1 219 778 1002",
    "sg:postcode":"46371",
    "sg:province":"IN",
    "sg:tags":[
        "oil"
    ],
    "wof:name":"BP Products North America",
    "wof:placetype":"venue"
},
  "geometry": {"coordinates":[-86.618875,41.709806],"type":"Point"}
}