{
  "type": "Feature",
  "properties": {
    "iso:country":"US",
    "sg:address":"917 Conner St",
    "sg:city":"Noblesville",
    "sg:classifiers":[
        {
            "category":"Home & Garden",
            "subcategory":"Building Materials",
            "type":"Retail Goods"
        }
    ],
    "sg:phone":"+1 317 773 7355",
    "sg:postcode":"46060",
    "sg:province":"IN",
    "sg:tags":[
        "door"
    ],
    "wof:name":"Collector's Door",
    "wof:placetype":"venue"
},
  "geometry": {"coordinates":[-86.013327,40.045526],"type":"Point"}
}