{
  "type": "Feature",
  "properties": {
    "iso:country":"US",
    "sg:address":"3235 W 39th Pl",
    "sg:city":"Indianapolis",
    "sg:classifiers":[
        {
            "category":"Building & Trades",
            "subcategory":"Landscaping Services",
            "type":"Services"
        }
    ],
    "sg:phone":"+1 317 258 6959",
    "sg:postcode":"46228",
    "sg:province":"IN",
    "sg:tags":[
        "lawn",
        "maintenance",
        "grounds"
    ],
    "wof:name":"Hendricks & Son Lawn Svc Inc",
    "wof:placetype":"venue"
},
  "geometry": {"coordinates":[-86.215521,39.827308],"type":"Point"}
}