{
  "type": "Feature",
  "properties": {
    "iso:country":"US",
    "sg:address":"1150 Southpoint Dr",
    "sg:city":"Valparaiso",
    "sg:classifiers":[
        {
            "category":"Wholesale",
            "subcategory":"Machinery & Supplies",
            "type":"Manufacturing & Wholesale Goods"
        }
    ],
    "sg:phone":"+1 219 465 4197",
    "sg:postcode":"46385",
    "sg:province":"IN",
    "sg:tags":[
        "equipment",
        "hydraulic"
    ],
    "sg:website":"www.yuken.org",
    "wof:name":"ALA Industries LTD",
    "wof:placetype":"venue"
},
  "geometry": {"coordinates":[-87.076486,41.45839],"type":"Point"}
}