{
  "type": "Feature",
  "properties": {
    "iso:country":"US",
    "sg:address":"791 E Empire Mill Rd",
    "sg:city":"Bloomington",
    "sg:classifiers":[
        {
            "category":"Home & Garden",
            "subcategory":"Building Materials",
            "type":"Retail Goods"
        }
    ],
    "sg:phone":"+1 812 824 6504",
    "sg:postcode":"47401",
    "sg:province":"IN",
    "sg:tags":[
        "lumber"
    ],
    "wof:name":"Imperial Lumber Co",
    "wof:placetype":"venue"
},
  "geometry": {"coordinates":[-86.529089,39.086907],"type":"Point"}
}