{
  "type": "Feature",
  "properties": {
    "addr:full":"2413 Meyer Rd Fort Wayne IN 46803",
    "addr:housenumber":"2413",
    "addr:postcode":"46803",
    "addr:street":"Meyer Rd",
    "iso:country":"US",
    "sg:address":"2413 Meyer Rd",
    "sg:city":"Fort Wayne",
    "sg:classifiers":[
        {
            "category":"Manufacturing",
            "subcategory":"Metals",
            "type":"Manufacturing & Wholesale Goods"
        }
    ],
    "sg:phone":"+1 260 422 5426",
    "sg:postcode":"46803",
    "sg:province":"IN",
    "sg:tags":[
        "finisher"
    ],
    "wof:name":"METAL Plate Polishing",
    "wof:placetype":"venue"
},
  "geometry": {"coordinates":[-85.077918,41.065415],"type":"Point"}
}