{
  "type": "Feature",
  "properties": {
    "iso:country":"US",
    "sg:address":"300 W Wabash Ave",
    "sg:city":"Crawfordsville",
    "sg:classifiers":[
        {
            "category":"Organizations",
            "subcategory":"Religious Organization",
            "type":"Services"
        }
    ],
    "sg:phone":"+1 765 361 0980",
    "sg:postcode":"47933",
    "sg:province":"IN",
    "wof:name":"Covenant Christian Church",
    "wof:placetype":"venue"
},
  "geometry": {"coordinates":[-86.90573500000001,40.039446],"type":"Point"}
}