{
  "type": "Feature",
  "properties": {
    "addr:full":"2827 Moffitt Ln Bloomington IN 47401",
    "addr:housenumber":"2827",
    "addr:postcode":"47401",
    "addr:street":"Moffitt Ln",
    "iso:country":"US",
    "sg:address":"2827 Moffitt Ln",
    "sg:city":"Bloomington",
    "sg:classifiers":[
        {
            "category":"Shopping",
            "subcategory":"Bicycles & Sporting Goods",
            "type":"Retail Goods"
        }
    ],
    "sg:phone":"+1 812 824 9361",
    "sg:postcode":"47401",
    "sg:province":"IN",
    "sg:tags":[
        "bait",
        "fishing"
    ],
    "wof:name":"Buddy Bills Bait Barn",
    "wof:placetype":"venue"
},
  "geometry": {"coordinates":[-86.50790499999999,39.09985],"type":"Point"}
}