{
  "type": "Feature",
  "properties": {
    "iso:country":"US",
    "sg:address":"111 N Broad St",
    "sg:city":"Griffith",
    "sg:classifiers":[
        {
            "category":"Government",
            "subcategory":"Fire Station",
            "type":"Public Place"
        }
    ],
    "sg:phone":"+1 219 000 1111",
    "sg:postcode":"46319",
    "sg:province":"IN",
    "sg:tags":[
        "department"
    ],
    "wof:name":"Griffith Fire Dept",
    "wof:placetype":"venue"
},
  "geometry": {"coordinates":[-87.427588,41.524397],"type":"Point"}
}