{
  "type": "Feature",
  "properties": {
    "iso:country":"US",
    "sg:address":"447 E Main St",
    "sg:city":"Hagerstown",
    "sg:classifiers":[
        {
            "category":"Professional",
            "subcategory":"Art Services",
            "type":"Services"
        }
    ],
    "sg:phone":"+1 765 489 6332",
    "sg:postcode":"47346",
    "sg:province":"IN",
    "sg:tags":[
        "commercial",
        "design"
    ],
    "wof:name":"Freedonia Studios",
    "wof:placetype":"venue"
},
  "geometry": {"coordinates":[-85.15525599999999,39.910564],"type":"Point"}
}