{
  "type": "Feature",
  "properties": {
    "iso:country":"US",
    "sg:address":"2017 W Franklin St",
    "sg:city":"Evansville",
    "sg:classifiers":[
        {
            "category":"Wholesale",
            "subcategory":"Photographic Equipment",
            "type":"Manufacturing & Wholesale Goods"
        }
    ],
    "sg:phone":"+1 812 425 1998",
    "sg:postcode":"47712",
    "sg:province":"IN",
    "sg:tags":[
        "identification"
    ],
    "sg:website":"www.topcoid.com",
    "wof:name":"Topco Inc",
    "wof:placetype":"venue"
},
  "geometry": {"coordinates":[-87.595362,37.980645],"type":"Point"}
}