{
  "type": "Feature",
  "properties": {
    "iso:country":"US",
    "sg:address":"5030 Doren Rd",
    "sg:city":"Richmond",
    "sg:phone":"+1 765 966 1412",
    "sg:postcode":"47374",
    "sg:province":"IN",
    "sg:tags":[
        "farm",
        "corn"
    ],
    "wof:name":"Toby Lafuze",
    "wof:placetype":"venue"
},
  "geometry": {"coordinates":[-84.82377700000001,39.758172],"type":"Point"}
}