{
  "type": "Feature",
  "properties": {
    "iso:country":"US",
    "sg:address":"605 S 25th St",
    "sg:city":"Terre Haute",
    "sg:classifiers":[
        {
            "category":"Retail",
            "subcategory":"Funeral Services",
            "type":"Services"
        }
    ],
    "sg:phone":"+1 812 232 1365",
    "sg:postcode":"47803",
    "sg:province":"IN",
    "sg:tags":[
        "director"
    ],
    "wof:name":"Callahan & Hughes Funeral Home",
    "wof:placetype":"venue"
},
  "geometry": {"coordinates":[-87.378924,39.459322],"type":"Point"}
}