{
  "type": "Feature",
  "properties": {
    "addr:full":"4957 N 825 W Andrews IN 46702",
    "addr:housenumber":"4957",
    "addr:postcode":"46702",
    "addr:street":"N 825 W Andrews",
    "iso:country":"US",
    "sg:address":"4957 N 825 W",
    "sg:city":"Andrews",
    "sg:classifiers":[
        {
            "category":"Professional",
            "subcategory":"Business Services",
            "type":"Services"
        }
    ],
    "sg:phone":"+1 260 786 3466",
    "sg:postcode":"46702",
    "sg:province":"IN",
    "wof:name":"Egolf Enterprises Inc",
    "wof:placetype":"venue"
},
  "geometry": {"coordinates":[-85.60823000000001,40.889974],"type":"Point"}
}