{
  "type": "Feature",
  "properties": {
    "iso:country":"US",
    "sg:address":"23 W Franklin St",
    "sg:city":"Greencastle",
    "sg:classifiers":[
        {
            "category":"Shopping",
            "type":"Retail Goods"
        }
    ],
    "sg:phone":"+1 765 653 2968",
    "sg:postcode":"46135",
    "sg:province":"IN",
    "sg:tags":[
        "telephone",
        "cellular"
    ],
    "wof:name":"Totalcom Inc",
    "wof:placetype":"venue"
},
  "geometry": {"coordinates":[-86.86523,39.644776],"type":"Point"}
}