{
  "type": "Feature",
  "properties": {
    "iso:country":"US",
    "sg:address":"811 E Ridge Rd",
    "sg:city":"Griffith",
    "sg:classifiers":[
        {
            "category":"Restaurant",
            "type":"Food & Drink"
        }
    ],
    "sg:phone":"+1 219 923 0118",
    "sg:postcode":"46319",
    "sg:province":"IN",
    "wof:name":"Ricky's Lounge",
    "wof:placetype":"venue"
},
  "geometry": {"coordinates":[-87.418128,41.549968],"type":"Point"}
}