{
  "type": "Feature",
  "properties": {
    "iso:country":"US",
    "sg:address":"2346 Hwy 64 NW",
    "sg:city":"Ramsey",
    "sg:classifiers":[
        {
            "category":"Autos & Motor Vehicles",
            "subcategory":"Automobile Sales",
            "type":"Retail Goods"
        }
    ],
    "sg:phone":"+1 812 347 3731",
    "sg:postcode":"47166",
    "sg:province":"IN",
    "sg:tags":[
        "car",
        "dealer"
    ],
    "wof:name":"Scott Auto Sales",
    "wof:placetype":"venue"
},
  "geometry": {"coordinates":[-86.170851,38.326099],"type":"Point"}
}