{
  "type": "Feature",
  "properties": {
    "iso:country":"US",
    "sg:address":"1512 Joliet St",
    "sg:city":"Dyer",
    "sg:classifiers":[
        {
            "category":"Professional",
            "subcategory":"Business Services",
            "type":"Services"
        }
    ],
    "sg:phone":"+1 219 322 7999",
    "sg:postcode":"46311",
    "sg:province":"IN",
    "sg:tags":[
        "drafting"
    ],
    "wof:name":"Classic Design",
    "wof:placetype":"venue"
},
  "geometry": {"coordinates":[-87.495189,41.491438],"type":"Point"}
}