{
  "type": "Feature",
  "properties": {
    "iso:country":"US",
    "sg:address":"1650 Brookwood Dr",
    "sg:city":"Elkhart",
    "sg:classifiers":[
        {
            "category":"Building & Trades",
            "subcategory":"Construction",
            "type":"Services"
        }
    ],
    "sg:phone":"+1 574 262 2345",
    "sg:postcode":"46514",
    "sg:province":"IN",
    "sg:tags":[
        "general",
        "contractor"
    ],
    "wof:name":"Baldwin Construction",
    "wof:placetype":"venue"
},
  "geometry": {"coordinates":[-85.938361,41.706631],"type":"Point"}
}