{
  "type": "Feature",
  "properties": {
    "iso:country":"US",
    "sg:address":"6203 E 52nd Pl",
    "sg:city":"Indianapolis",
    "sg:classifiers":[
        {
            "category":"Building & Trades",
            "subcategory":"Landscaping Services",
            "type":"Services"
        }
    ],
    "sg:phone":"+1 317 545 9292",
    "sg:postcode":"46226",
    "sg:province":"IN",
    "sg:tags":[
        "lawn",
        "garden"
    ],
    "wof:name":"Five Star Builders and Assoc",
    "wof:placetype":"venue"
},
  "geometry": {"coordinates":[-86.059356,39.848094],"type":"Point"}
}