{
  "type": "Feature",
  "properties": {
    "iso:country":"US",
    "sg:address":"151 E Market St",
    "sg:city":"Nappanee",
    "sg:classifiers":[
        {
            "category":"Home & Garden",
            "subcategory":"Hardware",
            "type":"Retail Goods"
        }
    ],
    "sg:phone":"+1 574 773 3541",
    "sg:postcode":"46550",
    "sg:province":"IN",
    "wof:name":"Martin Hardware Your Sports",
    "wof:placetype":"venue"
},
  "geometry": {"coordinates":[-86.00062200000001,41.442648],"type":"Point"}
}