{
  "type": "Feature",
  "properties": {
    "iso:country":"US",
    "sg:address":"652 Cross St",
    "sg:city":"Evansville",
    "sg:classifiers":[
        {
            "category":"Professional",
            "subcategory":"Research",
            "type":"Services"
        }
    ],
    "sg:phone":"+1 812 423 6332",
    "sg:postcode":"47713",
    "sg:province":"IN",
    "wof:name":"United Research Co",
    "wof:placetype":"venue"
},
  "geometry": {"coordinates":[-87.554938,37.950807],"type":"Point"}
}