{
  "type": "Feature",
  "properties": {
    "iso:country":"US",
    "sg:address":"2469 Woods Edge Dr",
    "sg:city":"Madison",
    "sg:classifiers":[
        {
            "category":"Building & Trades",
            "subcategory":"Construction",
            "type":"Services"
        }
    ],
    "sg:phone":"+1 812 273 2574",
    "sg:postcode":"47250",
    "sg:province":"IN",
    "sg:tags":[
        "house",
        "contractor"
    ],
    "wof:name":"S & P Builders Inc",
    "wof:placetype":"venue"
},
  "geometry": {"coordinates":[-85.373631,38.773143],"type":"Point"}
}