{
  "type": "Feature",
  "properties": {
    "iso:country":"US",
    "sg:address":"2144 W White River Blvd",
    "sg:city":"Muncie",
    "sg:classifiers":[
        {
            "category":"Shopping",
            "subcategory":"Used Merchandise",
            "type":"Retail Goods"
        }
    ],
    "sg:phone":"+1 765 284 7494",
    "sg:postcode":"47303",
    "sg:province":"IN",
    "sg:tags":[
        "furniture"
    ],
    "wof:name":"R & W Furniture",
    "wof:placetype":"venue"
},
  "geometry": {"coordinates":[-85.410412,40.187249],"type":"Point"}
}