{
  "type": "Feature",
  "properties": {
    "iso:country":"US",
    "sg:address":"2309 W Franklin St",
    "sg:city":"Evansville",
    "sg:classifiers":[
        {
            "category":"Health Services",
            "subcategory":"Doctor",
            "type":"Services"
        }
    ],
    "sg:phone":"+1 812 421 9112",
    "sg:postcode":"47712",
    "sg:province":"IN",
    "sg:tags":[
        "clinic"
    ],
    "wof:name":"Freedom Medical",
    "wof:placetype":"venue"
},
  "geometry": {"coordinates":[-87.600426,37.980704],"type":"Point"}
}