{
  "type": "Feature",
  "properties": {
    "addr:full":"110 W Jersey St Westfield IN 46074",
    "addr:housenumber":"110",
    "addr:postcode":"46074",
    "addr:street":"W Jersey St",
    "iso:country":"US",
    "sg:address":"110 W Jersey St",
    "sg:city":"Westfield",
    "sg:classifiers":[
        {
            "category":"Home & Garden",
            "subcategory":"Building Materials",
            "type":"Retail Goods"
        }
    ],
    "sg:phone":"+1 317 896 5094",
    "sg:postcode":"46074",
    "sg:province":"IN",
    "sg:tags":[
        "door"
    ],
    "wof:name":"Open Doors Of Washington Twn",
    "wof:placetype":"venue"
},
  "geometry": {"coordinates":[-86.128067,40.041804],"type":"Point"}
}