{
  "type": "Feature",
  "properties": {
    "iso:country":"US",
    "sg:address":"429 W US Hwy 20",
    "sg:city":"Michigan City",
    "sg:classifiers":[
        {
            "category":"Restaurant",
            "type":"Food & Drink"
        }
    ],
    "sg:phone":"+1 219 872 1116",
    "sg:postcode":"46360",
    "sg:province":"IN",
    "wof:name":"Nettie's Hot Dogs",
    "wof:placetype":"venue"
},
  "geometry": {"coordinates":[-86.900037,41.680458],"type":"Point"}
}