{
  "type": "Feature",
  "properties": {
    "iso:country":"US",
    "sg:address":"111 SE 5th St",
    "sg:city":"Washington",
    "sg:classifiers":[
        {
            "category":"Home & Garden",
            "subcategory":"Building Materials",
            "type":"Retail Goods"
        }
    ],
    "sg:phone":"+1 812 254 0562",
    "sg:postcode":"47501",
    "sg:province":"IN",
    "sg:tags":[
        "glass",
        "window",
        "plate"
    ],
    "wof:name":"Washington Glass",
    "wof:placetype":"venue"
},
  "geometry": {"coordinates":[-87.170129,38.656029],"type":"Point"}
}