{
  "type": "Feature",
  "properties": {
    "iso:country":"US",
    "sg:address":"1510 E Chicago Ave",
    "sg:city":"East Chicago",
    "sg:classifiers":[
        {
            "category":"Building & Trades",
            "subcategory":"Cleaning & Sanitation",
            "type":"Services"
        }
    ],
    "sg:phone":"+1 219 397 6307",
    "sg:postcode":"46312",
    "sg:province":"IN",
    "sg:tags":[
        "snow",
        "removal"
    ],
    "wof:name":"Regional Landscaping",
    "wof:placetype":"venue"
},
  "geometry": {"coordinates":[-87.452125,41.629191],"type":"Point"}
}