{
  "type": "Feature",
  "properties": {
    "iso:country":"US",
    "sg:address":"132 S Main St",
    "sg:city":"Goshen",
    "sg:classifiers":[
        {
            "category":"Professional",
            "subcategory":"Art Services",
            "type":"Services"
        }
    ],
    "sg:phone":"+1 574 534 2220",
    "sg:postcode":"46526",
    "sg:province":"IN",
    "sg:tags":[
        "commercial",
        "design"
    ],
    "wof:name":"Identity Graphic Design",
    "wof:placetype":"venue"
},
  "geometry": {"coordinates":[-85.83441000000001,41.585569],"type":"Point"}
}