{
  "type": "Feature",
  "properties": {
    "iso:country":"US",
    "sg:address":"1801 E 30th St",
    "sg:city":"Indianapolis",
    "sg:classifiers":[
        {
            "category":"Shopping",
            "subcategory":"Computers & Home Electronics",
            "type":"Retail Goods"
        }
    ],
    "sg:phone":"+1 317 924 6413",
    "sg:postcode":"46218",
    "sg:province":"IN",
    "sg:tags":[
        "equipment",
        "dealer"
    ],
    "wof:name":"Po Boys Computers & Print",
    "wof:placetype":"venue"
},
  "geometry": {"coordinates":[-86.128151,39.810739],"type":"Point"}
}