{
  "type": "Feature",
  "properties": {
    "iso:country":"US",
    "sg:address":"1410 S Post Rd",
    "sg:city":"Indianapolis",
    "sg:classifiers":[
        {
            "category":"Manufacturing",
            "subcategory":"Building Materials",
            "type":"Manufacturing & Wholesale Goods"
        }
    ],
    "sg:phone":"+1 317 897 7000",
    "sg:postcode":"46239",
    "sg:province":"IN",
    "sg:tags":[
        "cabinet"
    ],
    "sg:website":"www.generaldevices.com",
    "wof:name":"General Devices Co",
    "wof:placetype":"venue"
},
  "geometry": {"coordinates":[-86.008903,39.753906],"type":"Point"}
}