{
  "type": "Feature",
  "properties": {
    "iso:country":"US",
    "sg:address":"208 E Chicago St",
    "sg:city":"Columbia City",
    "sg:classifiers":[
        {
            "category":"Building & Trades",
            "subcategory":"Plumbing",
            "type":"Services"
        }
    ],
    "sg:phone":"+1 260 248 2021",
    "sg:postcode":"46725",
    "sg:province":"IN",
    "sg:tags":[
        "heating",
        "contractor"
    ],
    "wof:name":"Flow-Tech Plumbing & Heating",
    "wof:placetype":"venue"
},
  "geometry": {"coordinates":[-85.486158,41.149923],"type":"Point"}
}