{
  "type": "Feature",
  "properties": {
    "iso:country":"US",
    "sg:address":"2550 Brandywine Ct",
    "sg:city":"Indianapolis",
    "sg:classifiers":[
        {
            "category":"Social Services",
            "subcategory":"Child Care",
            "type":"Services"
        }
    ],
    "sg:phone":"+1 317 244 6310",
    "sg:postcode":"46241",
    "sg:province":"IN",
    "wof:name":"Jennifer's Day Care",
    "wof:placetype":"venue"
},
  "geometry": {"coordinates":[-86.247187,39.729617],"type":"Point"}
}