{
  "type": "Feature",
  "properties": {
    "iso:country":"US",
    "sg:address":"1877 W Shelton Rd",
    "sg:city":"Boonville",
    "sg:classifiers":[
        {
            "category":"Organizations",
            "subcategory":"Religious Organization",
            "type":"Services"
        }
    ],
    "sg:phone":"+1 812 897 3040",
    "sg:postcode":"47601",
    "sg:province":"IN",
    "sg:tags":[
        "church"
    ],
    "wof:name":"Living Hope Community Church",
    "wof:placetype":"venue"
},
  "geometry": {"coordinates":[-87.264969,38.090999],"type":"Point"}
}