{
  "type": "Feature",
  "properties": {
    "iso:country":"US",
    "sg:address":"4118 N Sheridan Ave",
    "sg:city":"Indianapolis",
    "sg:classifiers":[
        {
            "category":"Social Services",
            "subcategory":"Child Care",
            "type":"Services"
        }
    ],
    "sg:phone":"+1 317 547 7323",
    "sg:postcode":"46226",
    "sg:province":"IN",
    "sg:tags":[
        "day"
    ],
    "wof:name":"Kidz Luv",
    "wof:placetype":"venue"
},
  "geometry": {"coordinates":[-86.060221,39.832771],"type":"Point"}
}