{
  "type": "Feature",
  "properties": {
    "addr:full":"5550 W 74th St Indianapolis IN 46268",
    "addr:housenumber":"5550",
    "addr:postcode":"46268",
    "addr:street":"W 74Th St",
    "iso:country":"US",
    "sg:address":"5550 W 74th St",
    "sg:city":"Indianapolis",
    "sg:classifiers":[
        {
            "category":"Wholesale",
            "subcategory":"Books, Periodicals, & Newspapers",
            "type":"Manufacturing & Wholesale Goods"
        },
        {
            "category":"Manufacturing",
            "subcategory":"Printing",
            "type":"Manufacturing & Wholesale Goods"
        }
    ],
    "sg:phone":"+1 317 715 2150",
    "sg:postcode":"46268",
    "sg:province":"IN",
    "sg:tags":[
        "dealer"
    ],
    "sg:website":"www.pearson.com",
    "wof:name":"Pearson Education Inc",
    "wof:placetype":"venue"
},
  "geometry": {"coordinates":[-86.258385,39.887491],"type":"Point"}
}