{
  "type": "Feature",
  "properties": {
    "addr:full":"3418 S Main St Elkhart IN 46517",
    "addr:housenumber":"3418",
    "addr:postcode":"46517",
    "addr:street":"S Main St",
    "iso:country":"US",
    "sg:address":"3418 S Main St",
    "sg:city":"Elkhart",
    "sg:classifiers":[
        {
            "category":"Professional",
            "subcategory":"Employment Agencies",
            "type":"Services"
        }
    ],
    "sg:phone":"+1 574 294 5133",
    "sg:postcode":"46517",
    "sg:province":"IN",
    "sg:tags":[
        "help",
        "contractor"
    ],
    "wof:name":"Kelly Services Inc",
    "wof:placetype":"venue"
},
  "geometry": {"coordinates":[-85.93797499999999,41.648953],"type":"Point"}
}