{
  "type": "Feature",
  "properties": {
    "iso:country":"US",
    "sg:address":"9791 N by NW Blvd",
    "sg:city":"Indianapolis",
    "sg:classifiers":[
        {
            "category":"Travel",
            "subcategory":"Hotels & Motels",
            "type":"Entertainment"
        }
    ],
    "sg:phone":"+1 317 558 4100",
    "sg:postcode":"46201",
    "sg:province":"IN",
    "sg:website":"www.sleepinn.com",
    "wof:name":"Sleep Inn Northeast",
    "wof:placetype":"venue"
},
  "geometry": {"coordinates":[-86.02024,39.93071],"type":"Point"}
}