{
  "type": "Feature",
  "properties": {
    "addr:full":"11631 Fishers Station Dr Fishers IN 46038",
    "addr:housenumber":"11631",
    "addr:postcode":"46038",
    "addr:street":"Fishers Station Dr",
    "iso:country":"US",
    "sg:address":"11631 Fishers Station Dr",
    "sg:city":"Fishers",
    "sg:classifiers":[
        {
            "category":"Shopping",
            "subcategory":"Hobbies, Toys, & Games",
            "type":"Retail Goods"
        },
        {
            "category":"Shopping",
            "subcategory":"Books",
            "type":"Retail Goods"
        }
    ],
    "sg:phone":"+1 317 579 9822",
    "sg:postcode":"46038",
    "sg:province":"IN",
    "sg:tags":[
        "bookstore",
        "toy",
        "store"
    ],
    "sg:website":"mudsockbooks.com",
    "wof:name":"Mudsock Books & Curiosity Shoppe",
    "wof:placetype":"venue"
},
  "geometry": {"coordinates":[-86.038456,39.957505],"type":"Point"}
}