{
  "type": "Feature",
  "properties": {
    "iso:country":"US",
    "sg:address":"1405 S Western Ave",
    "sg:city":"Marion",
    "sg:classifiers":[
        {
            "category":"Home & Garden",
            "subcategory":"Carpets & Floor Coverings",
            "type":"Retail Goods"
        }
    ],
    "sg:phone":"+1 765 662 3906",
    "sg:postcode":"46953",
    "sg:province":"IN",
    "sg:tags":[
        "material"
    ],
    "wof:name":"Abbey Carpet Co",
    "wof:placetype":"venue"
},
  "geometry": {"coordinates":[-85.673693,40.545619],"type":"Point"}
}