{
  "type": "Feature",
  "properties": {
    "iso:country":"US",
    "sg:address":"2001 Cosby Rd",
    "sg:city":"Washington",
    "sg:classifiers":[
        {
            "category":"Professional",
            "type":"Services"
        }
    ],
    "sg:phone":"+1 812 254 6846",
    "sg:postcode":"47501",
    "sg:province":"IN",
    "sg:tags":[
        "establishment"
    ],
    "wof:name":"Hoosier Magnetics Inc",
    "wof:placetype":"venue"
},
  "geometry": {"coordinates":[-87.203616,38.655944],"type":"Point"}
}