{
  "type": "Feature",
  "properties": {
    "iso:country":"US",
    "sg:address":"3203 Clearfield Ct",
    "sg:city":"Fort Wayne",
    "sg:classifiers":[
        {
            "category":"Home & Garden",
            "subcategory":"Building Materials",
            "type":"Retail Goods"
        }
    ],
    "sg:phone":"+1 260 483 5600",
    "sg:postcode":"46808",
    "sg:province":"IN",
    "sg:tags":[
        "door",
        "gate",
        "operating",
        "devices"
    ],
    "wof:name":"Fort Wayne Door Inc",
    "wof:placetype":"venue"
},
  "geometry": {"coordinates":[-85.184186,41.103765],"type":"Point"}
}