{
  "type": "Feature",
  "properties": {
    "iso:country":"US",
    "sg:address":"1879 E Smithville Rd",
    "sg:city":"Bloomington",
    "sg:classifiers":[
        {
            "category":"Autos & Motor Vehicles",
            "subcategory":"Boat Sales",
            "type":"Retail Goods"
        }
    ],
    "sg:phone":"+1 812 824 8079",
    "sg:postcode":"47401",
    "sg:province":"IN",
    "sg:tags":[
        "dealer",
        "sales"
    ],
    "wof:name":"Marine Center Of Indianapolis",
    "wof:placetype":"venue"
},
  "geometry": {"coordinates":[-86.515535,39.071182],"type":"Point"}
}