{
  "type": "Feature",
  "properties": {
    "iso:country":"US",
    "sg:address":"111 Jarit Dr",
    "sg:city":"Sheridan",
    "sg:classifiers":[
        {
            "category":"Building & Trades",
            "subcategory":"Construction",
            "type":"Services"
        }
    ],
    "sg:phone":"+1 317 758 4134",
    "sg:postcode":"46069",
    "sg:province":"IN",
    "sg:tags":[
        "new",
        "general",
        "commercial",
        "contractor"
    ],
    "wof:name":"Childers Construction Co",
    "wof:placetype":"venue"
},
  "geometry": {"coordinates":[-86.21213899999999,40.138688],"type":"Point"}
}