{
  "type": "Feature",
  "properties": {
    "addr:full":"1833 Alliger St Fort Wayne IN 46803",
    "addr:housenumber":"1833",
    "addr:postcode":"46803",
    "addr:street":"Alliger St",
    "iso:country":"US",
    "sg:address":"1833 Alliger St",
    "sg:city":"Fort Wayne",
    "sg:classifiers":[
        {
            "category":"Professional",
            "subcategory":"Lawyer & Legal Services",
            "type":"Services"
        }
    ],
    "sg:phone":"+1 260 424 1756",
    "sg:postcode":"46803",
    "sg:province":"IN",
    "sg:tags":[
        "attorney"
    ],
    "wof:name":"Thomas Essex Atty At Law",
    "wof:placetype":"venue"
},
  "geometry": {"coordinates":[-85.113435,41.074208],"type":"Point"}
}