{
  "type": "Feature",
  "properties": {
    "iso:country":"US",
    "sg:address":"8813 Robbins Rd",
    "sg:city":"Indianapolis",
    "sg:classifiers":[
        {
            "category":"Manufacturing",
            "subcategory":"Metals",
            "type":"Manufacturing & Wholesale Goods"
        }
    ],
    "sg:phone":"+1 317 872 2783",
    "sg:postcode":"46268",
    "sg:province":"IN",
    "sg:tags":[
        "fabricator",
        "sheet"
    ],
    "wof:name":"Indy Sheet Metal",
    "wof:placetype":"venue"
},
  "geometry": {"coordinates":[-86.254052,39.912313],"type":"Point"}
}