{
  "type": "Feature",
  "properties": {
    "iso:country":"US",
    "sg:address":"1077 State Rd 39",
    "sg:city":"Danville",
    "sg:classifiers":[
        {
            "category":"Farming",
            "subcategory":"Orchard",
            "type":"Manufacturing & Wholesale Goods"
        }
    ],
    "sg:phone":"+1 317 745 6314",
    "sg:postcode":"46122",
    "sg:province":"IN",
    "sg:tags":[
        "grove",
        "management"
    ],
    "wof:name":"Wes Davis Orchard",
    "wof:placetype":"venue"
},
  "geometry": {"coordinates":[-86.528356,39.744234],"type":"Point"}
}