{
  "type": "Feature",
  "properties": {
    "iso:country":"US",
    "sg:address":"6324 S High School Rd",
    "sg:city":"Indianapolis",
    "sg:classifiers":[
        {
            "category":"Professional",
            "subcategory":"Business Services",
            "type":"Services"
        }
    ],
    "sg:phone":"+1 317 856 8496",
    "sg:postcode":"46221",
    "sg:province":"IN",
    "wof:name":"Tomcyn Enterprises Inc",
    "wof:placetype":"venue"
},
  "geometry": {"coordinates":[-86.269301,39.673433],"type":"Point"}
}