{
  "type": "Feature",
  "properties": {
    "iso:country":"US",
    "sg:address":"57 N Beasley St",
    "sg:city":"Sullivan",
    "sg:classifiers":[
        {
            "category":"Organizations",
            "subcategory":"Religious Organization",
            "type":"Services"
        }
    ],
    "sg:phone":"+1 812 268 8090",
    "sg:postcode":"47882",
    "sg:province":"IN",
    "sg:tags":[
        "church"
    ],
    "wof:name":"Calvary Apostlc Fellowship",
    "wof:placetype":"venue"
},
  "geometry": {"coordinates":[-87.395777,39.09625],"type":"Point"}
}