{
  "type": "Feature",
  "properties": {
    "iso:country":"US",
    "sg:address":"1201 Sycamore Ln",
    "sg:city":"Danville",
    "sg:classifiers":[
        {
            "category":"Organizations",
            "subcategory":"Non-profit Organization",
            "type":"Services"
        }
    ],
    "sg:phone":"+1 317 745 4303",
    "sg:postcode":"46122",
    "sg:province":"IN",
    "wof:name":"Hendricks County Senior Servic",
    "wof:placetype":"venue"
},
  "geometry": {"coordinates":[-86.50251400000001,39.767647],"type":"Point"}
}