{
  "type": "Feature",
  "properties": {
    "iso:country":"US",
    "sg:address":"212 S Rogers St",
    "sg:city":"Bloomington",
    "sg:classifiers":[
        {
            "category":"Shopping",
            "subcategory":"Gifts & Souvenirs",
            "type":"Retail Goods"
        }
    ],
    "sg:phone":"+1 812 355 8950",
    "sg:postcode":"47404",
    "sg:province":"IN",
    "sg:tags":[
        "shop"
    ],
    "wof:name":"T J's Gifts & Guitars",
    "wof:placetype":"venue"
},
  "geometry": {"coordinates":[-86.538775,39.164754],"type":"Point"}
}