{
  "type": "Feature",
  "properties": {
    "addr:full":"17187 State Rd 23 South Bend IN 46635",
    "addr:housenumber":"17187;23",
    "addr:postcode":"46635",
    "addr:street":"State Rd",
    "iso:country":"US",
    "sg:address":"17187 State Rd 23",
    "sg:city":"South Bend",
    "sg:classifiers":[
        {
            "category":"Wholesale",
            "subcategory":"Medical Equipment & Supplies",
            "type":"Manufacturing & Wholesale Goods"
        }
    ],
    "sg:phone":"+1 574 675 9000",
    "sg:postcode":"46635",
    "sg:province":"IN",
    "sg:tags":[
        "hospital"
    ],
    "wof:name":"Alick's Home Medical Equipment",
    "wof:placetype":"venue"
},
  "geometry": {"coordinates":[-86.20266599999999,41.710984],"type":"Point"}
}