{
  "type": "Feature",
  "properties": {
    "iso:country":"US",
    "sg:address":"599 Industrial Dr",
    "sg:city":"Carmel",
    "sg:classifiers":[
        {
            "category":"Shopping",
            "subcategory":"Computers & Home Electronics",
            "type":"Retail Goods"
        }
    ],
    "sg:phone":"+1 317 571 1840",
    "sg:postcode":"46032",
    "sg:province":"IN",
    "sg:tags":[
        "software"
    ],
    "wof:name":"Net Results",
    "wof:placetype":"venue"
},
  "geometry": {"coordinates":[-86.13118799999999,39.974751],"type":"Point"}
}