{
  "type": "Feature",
  "properties": {
    "iso:country":"US",
    "sg:address":"58654 Glenriver Dr",
    "sg:city":"Goshen",
    "sg:classifiers":[
        {
            "category":"Manufacturing",
            "subcategory":"Electronics",
            "type":"Manufacturing & Wholesale Goods"
        }
    ],
    "sg:phone":"+1 574 875 3889",
    "sg:postcode":"46528",
    "sg:province":"IN",
    "sg:tags":[
        "semiconductor",
        "devices"
    ],
    "wof:name":"Fairchild Semiconductor",
    "wof:placetype":"venue"
},
  "geometry": {"coordinates":[-85.90602800000001,41.642645],"type":"Point"}
}