{
  "type": "Feature",
  "properties": {
    "addr:full":"4350 S US Hwy 41 Terre Haute IN 47802",
    "addr:housenumber":"4350",
    "addr:postcode":"47802",
    "addr:street":"S Us Hwy 41",
    "iso:country":"US",
    "sg:address":"4350 S US Hwy 41",
    "sg:city":"Terre Haute",
    "sg:classifiers":[
        {
            "category":"Shopping",
            "subcategory":"Department Store",
            "type":"Retail Goods"
        }
    ],
    "sg:phone":"+1 812 235 5660",
    "sg:postcode":"47802",
    "sg:province":"IN",
    "sg:website":"www.samsclub.com",
    "wof:name":"Sam's Club",
    "wof:placetype":"venue"
},
  "geometry": {"coordinates":[-87.415065,39.413998],"type":"Point"}
}