{
  "type": "Feature",
  "properties": {
    "iso:country":"US",
    "sg:address":"3766 S 400 E",
    "sg:city":"Albion",
    "sg:classifiers":[
        {
            "category":"Wholesale",
            "subcategory":"Office Equipment",
            "type":"Manufacturing & Wholesale Goods"
        }
    ],
    "sg:phone":"+1 260 693 3848",
    "sg:postcode":"46701",
    "sg:province":"IN",
    "sg:tags":[
        "bank",
        "supply"
    ],
    "wof:name":"Indiana Bankers Supply",
    "wof:placetype":"venue"
},
  "geometry": {"coordinates":[-85.346448,41.294256],"type":"Point"}
}