{
  "type": "Feature",
  "properties": {
    "addr:full":"10630 W 133rd Ave Cedar Lake IN 46303",
    "addr:housenumber":"10630",
    "addr:postcode":"46303",
    "addr:street":"W 133Rd Ave",
    "iso:country":"US",
    "sg:address":"10630 W 133rd Ave",
    "sg:city":"Cedar Lake",
    "sg:classifiers":[
        {
            "category":"Building & Trades",
            "subcategory":"Equipment Rental",
            "type":"Services"
        }
    ],
    "sg:phone":"+1 219 374 9195",
    "sg:postcode":"46303",
    "sg:province":"IN",
    "sg:tags":[
        "moving",
        "supply"
    ],
    "wof:name":"U-Haul Co",
    "wof:placetype":"venue"
},
  "geometry": {"coordinates":[-87.463481,41.377417],"type":"Point"}
}