{
  "type": "Feature",
  "properties": {
    "iso:country":"US",
    "sg:address":"1000 Parkway St",
    "sg:city":"Berne",
    "sg:classifiers":[
        {
            "category":"Education",
            "subcategory":"School",
            "type":"Public Place"
        }
    ],
    "sg:phone":"+1 260 589 3131",
    "sg:postcode":"46711",
    "sg:province":"IN",
    "sg:website":"www.southadams.k12.in.us",
    "wof:name":"South Adams High School",
    "wof:placetype":"venue"
},
  "geometry": {"coordinates":[-84.96135200000001,40.648353],"type":"Point"}
}