{
  "type": "Feature",
  "properties": {
    "iso:country":"US",
    "sg:address":"1091 Co Rd 350 W",
    "sg:city":"Rockport",
    "sg:classifiers":[
        {
            "category":"Real Estate",
            "subcategory":"Real Estate Agent",
            "type":"Services"
        }
    ],
    "sg:phone":"+1 812 649 2077",
    "sg:postcode":"47635",
    "sg:province":"IN",
    "sg:tags":[
        "appraiser"
    ],
    "wof:name":"Bob's Appraisal Svc LLC",
    "wof:placetype":"venue"
},
  "geometry": {"coordinates":[-87.119197,37.860847],"type":"Point"}
}