{
  "type": "Feature",
  "properties": {
    "iso:country":"US",
    "sg:address":"1263 N State Rd 135",
    "sg:city":"Greenwood",
    "sg:classifiers":[
        {
            "category":"Shopping",
            "subcategory":"Jewelry",
            "type":"Retail Goods"
        }
    ],
    "sg:phone":"+1 317 888 7662",
    "sg:postcode":"46142",
    "sg:province":"IN",
    "sg:tags":[
        "jeweler"
    ],
    "wof:name":"J L Johnson's Inc",
    "wof:placetype":"venue"
},
  "geometry": {"coordinates":[-86.158319,39.634581],"type":"Point"}
}