{
  "type": "Feature",
  "properties": {
    "iso:country":"US",
    "sg:address":"1900 S Miller St",
    "sg:city":"Shelbyville",
    "sg:classifiers":[
        {
            "category":"Retail",
            "subcategory":"Veterinary Services",
            "type":"Services"
        }
    ],
    "sg:phone":"+1 317 392 7945",
    "sg:postcode":"46176",
    "sg:province":"IN",
    "sg:tags":[
        "veterinarian"
    ],
    "wof:name":"Shelton Pet Hospital",
    "wof:placetype":"venue"
},
  "geometry": {"coordinates":[-85.785929,39.507833],"type":"Point"}
}