{
  "type": "Feature",
  "properties": {
    "addr:full":"517 Country Ln Monticello IN 47960",
    "addr:housenumber":"517",
    "addr:postcode":"47960",
    "addr:street":"Country Ln",
    "iso:country":"US",
    "sg:address":"517 Country Ln",
    "sg:city":"Monticello",
    "sg:classifiers":[
        {
            "category":"Government",
            "subcategory":"Office",
            "type":"Public Place"
        }
    ],
    "sg:phone":"+1 574 583 5641",
    "sg:postcode":"47960",
    "sg:province":"IN",
    "sg:tags":[
        "federal",
        "planning",
        "dev"
    ],
    "wof:name":"USDA Rural Development",
    "wof:placetype":"venue"
},
  "geometry": {"coordinates":[-86.78379200000001,40.742159],"type":"Point"}
}