{
  "type": "Feature",
  "properties": {
    "iso:country":"US",
    "sg:address":"4000 W Lincoln Hwy",
    "sg:city":"Merrillville",
    "sg:classifiers":[
        {
            "category":"Banks & Credit Unions",
            "subcategory":"Bank",
            "type":"Services"
        }
    ],
    "sg:phone":"+1 219 769 4840",
    "sg:postcode":"46410",
    "sg:province":"IN",
    "sg:tags":[
        "loan",
        "real estate"
    ],
    "sg:website":"www.lakemortgage.com",
    "wof:name":"Lake Mortgage Co",
    "wof:placetype":"venue"
},
  "geometry": {"coordinates":[-87.387252,41.47232],"type":"Point"}
}