{
  "type": "Feature",
  "properties": {
    "iso:country":"US",
    "sg:address":"53168 Juday Creek Blvd",
    "sg:city":"Granger",
    "sg:classifiers":[
        {
            "category":"Professional",
            "subcategory":"Accounting & Tax Preparation",
            "type":"Services"
        }
    ],
    "sg:phone":"+1 574 272 3333",
    "sg:postcode":"46530",
    "sg:province":"IN",
    "sg:tags":[
        "consultant"
    ],
    "wof:name":"Oakdale Enterprises",
    "wof:placetype":"venue"
},
  "geometry": {"coordinates":[-86.152969,41.72112],"type":"Point"}
}