{
  "type": "Feature",
  "properties": {
    "iso:country":"US",
    "sg:address":"108 N State Road 267",
    "sg:city":"Avon",
    "sg:classifiers":[
        {
            "category":"Food & Beverages",
            "subcategory":"Supermarket",
            "type":"Retail Goods"
        },
        {
            "category":"Shopping",
            "subcategory":"Pharmacy",
            "type":"Retail Goods"
        },
        {
            "category":"Food & Beverages",
            "subcategory":"Groceries & Convenience Stores",
            "type":"Retail Goods"
        }
    ],
    "sg:phone":"+1 317 272 4130",
    "sg:postcode":"46123",
    "sg:province":"IN",
    "sg:tags":[
        "super"
    ],
    "sg:website":"http://www.kroger.com/",
    "wof:name":"Kroger",
    "wof:placetype":"venue"
},
  "geometry": {"coordinates":[-86.399745,39.764412],"type":"Point"}
}