{
  "type": "Feature",
  "properties": {
    "addr:full":"1604 Orinoco Ave Columbus IN 47201",
    "addr:housenumber":"1604",
    "addr:postcode":"47201",
    "addr:street":"Orinoco Ave",
    "iso:country":"US",
    "sg:address":"1604 Orinoco Ave",
    "sg:city":"Columbus",
    "sg:classifiers":[
        {
            "category":"Building & Trades",
            "subcategory":"Construction",
            "type":"Services"
        }
    ],
    "sg:phone":"+1 812 372 0241",
    "sg:postcode":"47201",
    "sg:province":"IN",
    "sg:tags":[
        "home",
        "improvement"
    ],
    "wof:name":"Carr Construction Corp",
    "wof:placetype":"venue"
},
  "geometry": {"coordinates":[-85.906691,39.21508],"type":"Point"}
}