{
  "type": "Feature",
  "properties": {
    "iso:country":"US",
    "sg:address":"7115 Mariner Way",
    "sg:city":"Indianapolis",
    "sg:classifiers":[
        {
            "category":"Shopping",
            "subcategory":"Discount & Variety Stores",
            "type":"Retail Goods"
        }
    ],
    "sg:phone":"+1 317 295 8037",
    "sg:postcode":"46214",
    "sg:province":"IN",
    "wof:name":"Martins Variety Store",
    "wof:placetype":"venue"
},
  "geometry": {"coordinates":[-86.285803,39.810756],"type":"Point"}
}