{
  "type": "Feature",
  "properties": {
    "iso:country":"US",
    "sg:address":"1779 E Brookside Trl",
    "sg:city":"Columbia City",
    "sg:classifiers":[
        {
            "category":"Real Estate",
            "subcategory":"Real Estate Agent",
            "type":"Services"
        }
    ],
    "sg:phone":"+1 260 248 4372",
    "sg:postcode":"46725",
    "sg:province":"IN",
    "wof:name":"Kolkman Real Estate Inc",
    "wof:placetype":"venue"
},
  "geometry": {"coordinates":[-85.457,41.159662],"type":"Point"}
}