{
  "type": "Feature",
  "properties": {
    "iso:country":"US",
    "sg:address":"1313 Wabash Ave",
    "sg:city":"Terre Haute",
    "sg:classifiers":[
        {
            "category":"Professional",
            "subcategory":"Accounting & Tax Preparation",
            "type":"Services"
        }
    ],
    "sg:phone":"+1 812 242 9545",
    "sg:postcode":"47807",
    "sg:province":"IN",
    "sg:tags":[
        "accountant"
    ],
    "wof:name":"Terre Haute Tax Svc Inc",
    "wof:placetype":"venue"
},
  "geometry": {"coordinates":[-87.39687000000001,39.467822],"type":"Point"}
}