{
  "type": "Feature",
  "properties": {
    "iso:country":"US",
    "sg:address":"1051 Laclede St",
    "sg:city":"Indianapolis",
    "sg:classifiers":[
        {
            "category":"Retail",
            "subcategory":"Auto Repair",
            "type":"Services"
        }
    ],
    "sg:phone":"+1 317 487 5969",
    "sg:postcode":"46241",
    "sg:province":"IN",
    "sg:tags":[
        "repairing",
        "tire"
    ],
    "wof:name":"Central Indiana Tire & Retread",
    "wof:placetype":"venue"
},
  "geometry": {"coordinates":[-86.242341,39.754719],"type":"Point"}
}