{
  "type": "Feature",
  "properties": {
    "addr:full":"816 W Main St Carmel IN 46032",
    "addr:housenumber":"816",
    "addr:postcode":"46032",
    "addr:street":"W Main St",
    "iso:country":"US",
    "sg:address":"816 W Main St",
    "sg:city":"Carmel",
    "sg:classifiers":[
        {
            "category":"Shopping",
            "subcategory":"Pets & Pet Supplies",
            "type":"Retail Goods"
        }
    ],
    "sg:phone":"+1 317 582 1364",
    "sg:postcode":"46032",
    "sg:province":"IN",
    "sg:tags":[
        "store"
    ],
    "sg:website":"www.izzysplacecarmel.com",
    "wof:name":"Izzy's Place a Dog bakery",
    "wof:placetype":"venue"
},
  "geometry": {"coordinates":[-86.14200700000001,39.978145],"type":"Point"}
}