{
  "type": "Feature",
  "properties": {
    "iso:country":"US",
    "sg:address":"40 S Alabama St",
    "sg:city":"Indianapolis",
    "sg:classifiers":[
        {
            "category":"Government",
            "subcategory":"Office",
            "type":"Public Place"
        }
    ],
    "sg:phone":"+1 317 327 3670",
    "sg:postcode":"46204",
    "sg:province":"IN",
    "sg:tags":[
        "village"
    ],
    "wof:name":"Indianapolis Forensic Svc",
    "wof:placetype":"venue"
},
  "geometry": {"coordinates":[-86.152766,39.766027],"type":"Point"}
}