{
  "type": "Feature",
  "properties": {
    "addr:full":"1310 Park Ave Winona Lake IN 46590",
    "addr:housenumber":"1310",
    "addr:postcode":"46590",
    "addr:street":"Park Ave",
    "iso:country":"US",
    "sg:address":"1310 Park Ave",
    "sg:city":"Winona Lake",
    "sg:classifiers":[
        {
            "category":"Government",
            "subcategory":"Office",
            "type":"Public Place"
        }
    ],
    "sg:phone":"+1 574 269 5112",
    "sg:postcode":"46590",
    "sg:province":"IN",
    "sg:tags":[
        "village"
    ],
    "wof:name":"Winona Lake Town Coordinator",
    "wof:placetype":"venue"
},
  "geometry": {"coordinates":[-85.821067,41.22361],"type":"Point"}
}