{
  "type": "Feature",
  "properties": {
    "iso:country":"US",
    "sg:address":"906 S Main St",
    "sg:city":"Bicknell",
    "sg:classifiers":[
        {
            "category":"Building & Trades",
            "subcategory":"Electrical",
            "type":"Services"
        }
    ],
    "sg:phone":"+1 812 735 2224",
    "sg:postcode":"47512",
    "sg:province":"IN",
    "wof:name":"Indiana Cable Assoicates LTD",
    "wof:placetype":"venue"
},
  "geometry": {"coordinates":[-87.305655,38.765841],"type":"Point"}
}