{
  "type": "Feature",
  "properties": {
    "iso:country":"US",
    "sg:address":"5921 Hessen Cassel Rd",
    "sg:city":"Fort Wayne",
    "sg:classifiers":[
        {
            "category":"Organizations",
            "subcategory":"Community Association",
            "type":"Services"
        }
    ],
    "sg:phone":"+1 260 447 3303",
    "sg:postcode":"46816",
    "sg:province":"IN",
    "sg:tags":[
        "fraternal"
    ],
    "wof:name":"Knights Of Pythias Strotarin",
    "wof:placetype":"venue"
},
  "geometry": {"coordinates":[-85.096029,41.028498],"type":"Point"}
}