{
  "type": "Feature",
  "properties": {
    "addr:full":"391 W Eads Pkwy Lawrenceburg IN 47025",
    "addr:housenumber":"391",
    "addr:postcode":"47025",
    "addr:street":"W Eads Pkwy",
    "iso:country":"US",
    "sg:address":"391 W Eads Pkwy",
    "sg:city":"Lawrenceburg",
    "sg:classifiers":[
        {
            "category":"Restaurant",
            "type":"Food & Drink"
        }
    ],
    "sg:phone":"+1 812 537 9598",
    "sg:postcode":"47025",
    "sg:province":"IN",
    "wof:name":"New China Restaurant",
    "wof:placetype":"venue"
},
  "geometry": {"coordinates":[-84.85971000000001,39.095872],"type":"Point"}
}