{
  "type": "Feature",
  "properties": {
    "iso:country":"US",
    "sg:address":"205 Grandstand Way",
    "sg:city":"Fort Wayne",
    "sg:classifiers":[
        {
            "category":"Sports & Exercise",
            "subcategory":"Gym",
            "type":"Entertainment"
        }
    ],
    "sg:phone":"+1 260 471 1285",
    "sg:postcode":"46825",
    "sg:province":"IN",
    "sg:tags":[
        "fitness",
        "physical",
        "facility"
    ],
    "wof:name":"Cmac",
    "wof:placetype":"venue"
},
  "geometry": {"coordinates":[-85.140312,41.120165],"type":"Point"}
}