{
  "type": "Feature",
  "properties": {
    "addr:full":"5718 W 9th Ave Gary IN 46406",
    "addr:housenumber":"5718",
    "addr:postcode":"46406",
    "addr:street":"W 9Th Ave",
    "iso:country":"US",
    "sg:address":"5718 W 9th Ave",
    "sg:city":"Gary",
    "sg:classifiers":[
        {
            "category":"Organizations",
            "subcategory":"Religious Organization",
            "type":"Services"
        }
    ],
    "sg:phone":"+1 219 949 2626",
    "sg:postcode":"46406",
    "sg:province":"IN",
    "sg:tags":[
        "church"
    ],
    "wof:name":"Church Of God In Christ",
    "wof:placetype":"venue"
},
  "geometry": {"coordinates":[-87.408097,41.595291],"type":"Point"}
}