{
  "type": "Feature",
  "properties": {
    "iso:country":"US",
    "sg:address":"747 Treyburn Green Dr",
    "sg:city":"Indianapolis",
    "sg:classifiers":[
        {
            "category":"Travel",
            "subcategory":"Travel Agent",
            "type":"Entertainment"
        }
    ],
    "sg:phone":"+1 317 898 1747",
    "sg:postcode":"46239",
    "sg:province":"IN",
    "sg:tags":[
        "agency",
        "bureau"
    ],
    "wof:name":"Personal Travel",
    "wof:placetype":"venue"
},
  "geometry": {"coordinates":[-85.996058,39.758846],"type":"Point"}
}