{
  "type": "Feature",
  "properties": {
    "iso:country":"US",
    "sg:address":"3526 N Washington Rd",
    "sg:city":"Fort Wayne",
    "sg:classifiers":[
        {
            "category":"Professional",
            "subcategory":"Employment Agencies",
            "type":"Services"
        }
    ],
    "sg:phone":"+1 260 436 7470",
    "sg:postcode":"46802",
    "sg:province":"IN",
    "wof:name":"Execu Search",
    "wof:placetype":"venue"
},
  "geometry": {"coordinates":[-85.184015,41.072829],"type":"Point"}
}