{
  "type": "Feature",
  "properties": {
    "iso:country":"US",
    "sg:address":"301 Detroit St",
    "sg:city":"Laporte",
    "sg:classifiers":[
        {
            "category":"Manufacturing",
            "subcategory":"Aerospace",
            "type":"Manufacturing & Wholesale Goods"
        }
    ],
    "sg:phone":"+1 219 362 9707",
    "sg:postcode":"46350",
    "sg:province":"IN",
    "sg:tags":[
        "engine",
        "aircraft",
        "parts"
    ],
    "sg:website":"www.harrisonengine.com",
    "wof:name":"Harrison Engine Svc",
    "wof:placetype":"venue"
},
  "geometry": {"coordinates":[-86.720563,41.616336],"type":"Point"}
}