{
  "type": "Feature",
  "properties": {
    "iso:country":"US",
    "sg:address":"5868 Stiller Rd",
    "sg:city":"Floyds Knobs",
    "sg:classifiers":[
        {
            "category":"Building & Trades",
            "subcategory":"Landscaping Services",
            "type":"Services"
        }
    ],
    "sg:phone":"+1 812 923 8386",
    "sg:postcode":"47119",
    "sg:province":"IN",
    "sg:tags":[
        "landscape",
        "contractor"
    ],
    "sg:website":"www.jacobisod.com",
    "wof:name":"F D Jacobi Sodding Svc",
    "wof:placetype":"venue"
},
  "geometry": {"coordinates":[-85.91971100000001,38.35977],"type":"Point"}
}