{
  "type": "Feature",
  "properties": {
    "iso:country":"US",
    "sg:address":"211 N Main St",
    "sg:city":"Monticello",
    "sg:classifiers":[
        {
            "category":"Food & Beverages",
            "subcategory":"Liquor & Beverages",
            "type":"Retail Goods"
        }
    ],
    "sg:phone":"+1 574 583 7341",
    "sg:postcode":"47960",
    "sg:province":"IN",
    "wof:name":"Ricketts Liquor Store",
    "wof:placetype":"venue"
},
  "geometry": {"coordinates":[-86.761863,40.746658],"type":"Point"}
}