{
  "type": "Feature",
  "properties": {
    "iso:country":"US",
    "sg:address":"2746 W 5th Ave",
    "sg:city":"Gary",
    "sg:classifiers":[
        {
            "category":"Banks & Credit Unions",
            "subcategory":"Bank",
            "type":"Services"
        }
    ],
    "sg:phone":"+1 219 886 1352",
    "sg:postcode":"46404",
    "sg:province":"IN",
    "sg:tags":[
        "saving",
        "commercial"
    ],
    "wof:name":"N A Harris",
    "wof:placetype":"venue"
},
  "geometry": {"coordinates":[-87.37119199999999,41.601929],"type":"Point"}
}