{
  "type": "Feature",
  "properties": {
    "iso:country":"US",
    "sg:address":"1320 N 1st Ave",
    "sg:city":"Evansville",
    "sg:classifiers":[
        {
            "category":"Retail",
            "subcategory":"Auto Repair",
            "type":"Services"
        }
    ],
    "sg:phone":"+1 812 425 4406",
    "sg:postcode":"47710",
    "sg:province":"IN",
    "sg:tags":[
        "automobile",
        "top",
        "upholstery"
    ],
    "wof:name":"First Avenue Trim Shop Inc",
    "wof:placetype":"venue"
},
  "geometry": {"coordinates":[-87.574838,37.990623],"type":"Point"}
}