{
  "type": "Feature",
  "properties": {
    "addr:full":"11711 N Meridian St Carmel IN 46032",
    "addr:housenumber":"11711",
    "addr:postcode":"46032",
    "addr:street":"N Meridian St",
    "iso:country":"US",
    "sg:address":"11711 N Meridian St",
    "sg:city":"Carmel",
    "sg:classifiers":[
        {
            "category":"Professional",
            "type":"Services"
        }
    ],
    "sg:phone":"+1 317 571 2100",
    "sg:postcode":"46032",
    "sg:province":"IN",
    "sg:tags":[
        "establishment"
    ],
    "wof:name":"Sprint",
    "wof:placetype":"venue"
},
  "geometry": {"coordinates":[-86.15755299999999,39.958139],"type":"Point"}
}