{
  "type": "Feature",
  "properties": {
    "iso:country":"US",
    "sg:address":"2529 Commerce Dr",
    "sg:city":"Kokomo",
    "sg:classifiers":[
        {
            "category":"Wholesale",
            "subcategory":"Electrical",
            "type":"Manufacturing & Wholesale Goods"
        }
    ],
    "sg:phone":"+1 765 456 3138",
    "sg:postcode":"46902",
    "sg:province":"IN",
    "sg:tags":[
        "equipment",
        "electronic",
        "supply"
    ],
    "wof:name":"NEC Electronics Inc",
    "wof:placetype":"venue"
},
  "geometry": {"coordinates":[-86.096574,40.45295],"type":"Point"}
}