{
  "type": "Feature",
  "properties": {
    "iso:country":"US",
    "sg:address":"4337 Ohio St",
    "sg:city":"Michigan City",
    "sg:classifiers":[
        {
            "category":"Organizations",
            "subcategory":"Labor Organization",
            "type":"Services"
        }
    ],
    "sg:phone":"+1 219 874 5269",
    "sg:postcode":"46360",
    "sg:province":"IN",
    "wof:name":"Teamsters Local Union",
    "wof:placetype":"venue"
},
  "geometry": {"coordinates":[-86.90374300000001,41.675985],"type":"Point"}
}