{
  "type": "Feature",
  "properties": {
    "iso:country":"US",
    "sg:address":"1513 E Lincoln Ave",
    "sg:city":"Goshen",
    "sg:classifiers":[
        {
            "category":"Retail",
            "subcategory":"Auto Repair",
            "type":"Services"
        }
    ],
    "sg:phone":"+1 574 537 1200",
    "sg:postcode":"46528",
    "sg:province":"IN",
    "sg:tags":[
        "repairing",
        "automobile"
    ],
    "wof:name":"Car Center",
    "wof:placetype":"venue"
},
  "geometry": {"coordinates":[-85.813743,41.590216],"type":"Point"}
}