{
  "type": "Feature",
  "properties": {
    "iso:country":"US",
    "sg:address":"2120 W Franklin St",
    "sg:city":"Elkhart",
    "sg:classifiers":[
        {
            "category":"Manufacturing",
            "subcategory":"Tools & Machinery",
            "type":"Manufacturing & Wholesale Goods"
        }
    ],
    "sg:phone":"+1 574 293 0494",
    "sg:postcode":"46516",
    "sg:province":"IN",
    "sg:tags":[
        "machine",
        "shop"
    ],
    "wof:name":"Custom Laser Svc Corp",
    "wof:placetype":"venue"
},
  "geometry": {"coordinates":[-86.0004,41.671186],"type":"Point"}
}