{
  "type": "Feature",
  "properties": {
    "iso:country":"US",
    "sg:address":"1230 S Halleck St",
    "sg:city":"Demotte",
    "sg:classifiers":[
        {
            "category":"Retail",
            "subcategory":"Veterinary Services",
            "type":"Services"
        }
    ],
    "sg:phone":"+1 219 987 2271",
    "sg:postcode":"46310",
    "sg:province":"IN",
    "sg:tags":[
        "hospital",
        "animal"
    ],
    "wof:name":"De Motte Animal Clinic",
    "wof:placetype":"venue"
},
  "geometry": {"coordinates":[-87.19854100000001,41.189437],"type":"Point"}
}