{
  "type": "Feature",
  "properties": {
    "addr:full":"1200 W 2nd St Madison IN 47250",
    "addr:housenumber":"1200",
    "addr:postcode":"47250",
    "addr:street":"W 2Nd St",
    "iso:country":"US",
    "sg:address":"1200 W 2nd St",
    "sg:city":"Madison",
    "sg:classifiers":[
        {
            "category":"Autos & Motor Vehicles",
            "subcategory":"Boat Sales",
            "type":"Retail Goods"
        }
    ],
    "sg:phone":"+1 812 273 5787",
    "sg:postcode":"47250",
    "sg:province":"IN",
    "sg:tags":[
        "equipment",
        "marine",
        "supply"
    ],
    "wof:name":"Diamond G Marine Rentals",
    "wof:placetype":"venue"
},
  "geometry": {"coordinates":[-85.401921,38.739322],"type":"Point"}
}