{
  "type": "Feature",
  "properties": {
    "iso:country":"US",
    "sg:address":"3816 W Co Rd 200 N",
    "sg:city":"Logansport",
    "sg:phone":"+1 574 735 2746",
    "sg:postcode":"46947",
    "sg:province":"IN",
    "sg:tags":[
        "farm",
        "corn",
        "soybean"
    ],
    "wof:name":"Carl Sell",
    "wof:placetype":"venue"
},
  "geometry": {"coordinates":[-86.441101,40.793542],"type":"Point"}
}