{
  "type": "Feature",
  "properties": {
    "iso:country":"US",
    "sg:address":"5222 S East St",
    "sg:city":"Indianapolis",
    "sg:classifiers":[
        {
            "category":"Health Services",
            "subcategory":"Hospital",
            "type":"Services"
        }
    ],
    "sg:phone":"+1 317 781 0447",
    "sg:postcode":"46227",
    "sg:province":"IN",
    "sg:tags":[
        "mental"
    ],
    "wof:name":"Jo Ann Owen Lmhc",
    "wof:placetype":"venue"
},
  "geometry": {"coordinates":[-86.148882,39.691475],"type":"Point"}
}