{
  "type": "Feature",
  "properties": {
    "iso:country":"US",
    "sg:address":"1041 N Luther Rd",
    "sg:city":"Georgetown",
    "sg:classifiers":[
        {
            "category":"Personal",
            "subcategory":"Barber",
            "type":"Services"
        }
    ],
    "sg:phone":"+1 812 923 7669",
    "sg:postcode":"47122",
    "sg:province":"IN",
    "wof:name":"Nudu's",
    "wof:placetype":"venue"
},
  "geometry": {"coordinates":[-85.91379499999999,38.290521],"type":"Point"}
}