{
  "type": "Feature",
  "properties": {
    "iso:country":"US",
    "sg:address":"837 S Bend Ave",
    "sg:city":"South Bend",
    "sg:classifiers":[
        {
            "category":"Health Services",
            "subcategory":"Doctor",
            "type":"Services"
        }
    ],
    "sg:phone":"+1 574 234 9050",
    "sg:postcode":"46617",
    "sg:province":"IN",
    "sg:tags":[
        "physician",
        "surgeon"
    ],
    "sg:website":"www.obgynni.com",
    "wof:name":"Ob/Gyn Associates-Northern In",
    "wof:placetype":"venue"
},
  "geometry": {"coordinates":[-86.238285,41.685624],"type":"Point"}
}