{
  "type": "Feature",
  "properties": {
    "addr:full":"2556 East 3rd Street Bloomington IN 47401",
    "addr:housenumber":"2556",
    "addr:postcode":"47401",
    "addr:street":"East 3Rd Street",
    "iso:country":"US",
    "sg:address":"2556 East 3rd Street",
    "sg:city":"Bloomington",
    "sg:classifiers":[
        {
            "category":"Food & Beverages",
            "subcategory":"Groceries & Convenience Stores",
            "type":"Retail Goods"
        }
    ],
    "sg:phone":"+1 812 335 1833",
    "sg:postcode":"47401",
    "sg:province":"IN",
    "wof:name":"Obo's Oriental Grocery",
    "wof:placetype":"venue"
},
  "geometry": {"coordinates":[-86.502011,39.164211],"type":"Point"}
}