{
  "type": "Feature",
  "properties": {
    "iso:country":"US",
    "sg:address":"1036 S Oden Dr",
    "sg:city":"Greenfield",
    "sg:classifiers":[
        {
            "category":"Building & Trades",
            "subcategory":"Cleaning & Sanitation",
            "type":"Services"
        }
    ],
    "sg:phone":"+1 317 462 4759",
    "sg:postcode":"46140",
    "sg:province":"IN",
    "sg:tags":[
        "fireplace",
        "chimney"
    ],
    "wof:name":"T J's Chimney Sweep",
    "wof:placetype":"venue"
},
  "geometry": {"coordinates":[-85.749003,39.769722],"type":"Point"}
}