{
  "type": "Feature",
  "properties": {
    "addr:full":"7784 Foxtail Ct Fishers IN 46038",
    "addr:housenumber":"7784",
    "addr:postcode":"46038",
    "addr:street":"Foxtail Ct",
    "iso:country":"US",
    "sg:address":"7784 Foxtail Ct",
    "sg:city":"Fishers",
    "sg:classifiers":[
        {
            "category":"Professional",
            "subcategory":"Art Services",
            "type":"Services"
        }
    ],
    "sg:phone":"+1 317 570 6700",
    "sg:postcode":"46038",
    "sg:province":"IN",
    "sg:tags":[
        "photographer"
    ],
    "wof:name":"Gregory W Puls Photography",
    "wof:placetype":"venue"
},
  "geometry": {"coordinates":[-86.023905,39.947759],"type":"Point"}
}