{
  "type": "Feature",
  "properties": {
    "iso:country":"US",
    "sg:address":"5170 S 3rd St",
    "sg:city":"St Anthony",
    "sg:classifiers":[
        {
            "category":"Manufacturing",
            "subcategory":"Furniture",
            "type":"Manufacturing & Wholesale Goods"
        }
    ],
    "sg:phone":"+1 812 326 2626",
    "sg:postcode":"47575",
    "sg:province":"IN",
    "wof:name":"Woodmaster Inc",
    "wof:placetype":"venue"
},
  "geometry": {"coordinates":[-86.818688,38.30506],"type":"Point"}
}