{
  "type": "Feature",
  "properties": {
    "iso:country":"US",
    "sg:address":"17 S Westside Dr",
    "sg:city":"New Palestine",
    "sg:classifiers":[
        {
            "category":"Government",
            "subcategory":"Post Office",
            "type":"Public Place"
        }
    ],
    "sg:phone":"+1 317 000 1111",
    "sg:postcode":"46163",
    "sg:province":"IN",
    "wof:name":"US Post Office",
    "wof:placetype":"venue"
},
  "geometry": {"coordinates":[-85.898539,39.721038],"type":"Point"}
}