{
  "type": "Feature",
  "properties": {
    "iso:country":"US",
    "sg:address":"4696 W 250 N",
    "sg:city":"Rochester",
    "sg:classifiers":[
        {
            "category":"Farming",
            "subcategory":"Farm",
            "type":"Manufacturing & Wholesale Goods"
        }
    ],
    "sg:phone":"+1 574 223 8305",
    "sg:postcode":"46975",
    "sg:province":"IN",
    "sg:tags":[
        "crop",
        "general"
    ],
    "wof:name":"McGaughey Paul",
    "wof:placetype":"venue"
},
  "geometry": {"coordinates":[-86.337739,41.0919],"type":"Point"}
}