{
  "type": "Feature",
  "properties": {
    "iso:country":"US",
    "sg:address":"115 E Jefferson St",
    "sg:city":"Culver",
    "sg:classifiers":[
        {
            "category":"Shopping",
            "subcategory":"Used Merchandise",
            "type":"Retail Goods"
        }
    ],
    "sg:phone":"+1 574 842 3159",
    "sg:postcode":"46511",
    "sg:province":"IN",
    "sg:tags":[
        "antique"
    ],
    "wof:name":"Treasures Near The Cove",
    "wof:placetype":"venue"
},
  "geometry": {"coordinates":[-86.422797,41.216616],"type":"Point"}
}