{
  "type": "Feature",
  "properties": {
    "iso:country":"US",
    "sg:address":"712 N Lincoln St",
    "sg:city":"Greensburg",
    "sg:classifiers":[
        {
            "category":"Health Services",
            "subcategory":"Doctor",
            "type":"Services"
        }
    ],
    "sg:phone":"+1 812 663 8079",
    "sg:postcode":"47240",
    "sg:province":"IN",
    "sg:tags":[
        "physician",
        "surgeon"
    ],
    "wof:name":"Greensburg Medical Group",
    "wof:placetype":"venue"
},
  "geometry": {"coordinates":[-85.479361,39.342944],"type":"Point"}
}