{
  "type": "Feature",
  "properties": {
    "iso:country":"US",
    "sg:address":"3501 Conner St",
    "sg:city":"Noblesville",
    "sg:classifiers":[
        {
            "category":"Manufacturing",
            "subcategory":"Textiles",
            "type":"Manufacturing & Wholesale Goods"
        }
    ],
    "sg:phone":"+1 317 773 1443",
    "sg:postcode":"46060",
    "sg:province":"IN",
    "sg:tags":[
        "rubberized",
        "coated",
        "fabric"
    ],
    "sg:website":"www.rjhanlon.com",
    "wof:name":"R J Hanlon Co",
    "wof:placetype":"venue"
},
  "geometry": {"coordinates":[-85.99059800000001,40.045618],"type":"Point"}
}