{
  "type": "Feature",
  "properties": {
    "iso:country":"US",
    "sg:address":"560 Bond Ave",
    "sg:city":"Valparaiso",
    "sg:classifiers":[
        {
            "category":"Home & Garden",
            "subcategory":"Furniture",
            "type":"Retail Goods"
        }
    ],
    "sg:phone":"+1 219 531 5876",
    "sg:postcode":"46385",
    "sg:province":"IN",
    "sg:tags":[
        "top",
        "counter"
    ],
    "wof:name":"EXC Remodeling",
    "wof:placetype":"venue"
},
  "geometry": {"coordinates":[-87.067657,41.477021],"type":"Point"}
}