{
  "type": "Feature",
  "properties": {
    "iso:country":"US",
    "sg:address":"150 W Washington St",
    "sg:city":"Shelbyville",
    "sg:classifiers":[
        {
            "category":"Health Services",
            "subcategory":"Doctor",
            "type":"Services"
        }
    ],
    "sg:phone":"+1 317 398 5248",
    "sg:postcode":"46176",
    "sg:province":"IN",
    "wof:name":"Inlow Imaging",
    "wof:placetype":"venue"
},
  "geometry": {"coordinates":[-85.780731,39.524518],"type":"Point"}
}