{
  "type": "Feature",
  "properties": {
    "iso:country":"US",
    "sg:address":"606 W Superior St",
    "sg:city":"Fort Wayne",
    "sg:classifiers":[
        {
            "category":"Building & Trades",
            "subcategory":"Plumbing",
            "type":"Services"
        }
    ],
    "sg:phone":"+1 260 426 8457",
    "sg:postcode":"46802",
    "sg:province":"IN",
    "sg:tags":[
        "heating",
        "contractor"
    ],
    "wof:name":"G D Smith Inc",
    "wof:placetype":"venue"
},
  "geometry": {"coordinates":[-85.148944,41.080973],"type":"Point"}
}