{
  "type": "Feature",
  "properties": {
    "iso:country":"US",
    "sg:address":"12200 Lafayette Center Rd",
    "sg:city":"Roanoke",
    "sg:classifiers":[
        {
            "category":"Manufacturing",
            "subcategory":"Tools & Machinery",
            "type":"Manufacturing & Wholesale Goods"
        }
    ],
    "sg:phone":"+1 260 672 0348",
    "sg:postcode":"46783",
    "sg:province":"IN",
    "sg:tags":[
        "equipment",
        "conveyor",
        "conveying"
    ],
    "wof:name":"Overhead Conveyor Co",
    "wof:placetype":"venue"
},
  "geometry": {"coordinates":[-85.301235,40.960385],"type":"Point"}
}