{
  "type": "Feature",
  "properties": {
    "iso:country":"US",
    "sg:address":"2722 W Western Ave",
    "sg:city":"South Bend",
    "sg:classifiers":[
        {
            "category":"Organizations",
            "subcategory":"Religious Organization",
            "type":"Services"
        }
    ],
    "sg:phone":"+1 574 288 7523",
    "sg:postcode":"46619",
    "sg:province":"IN",
    "sg:tags":[
        "church"
    ],
    "wof:name":"Local Quartet Union",
    "wof:placetype":"venue"
},
  "geometry": {"coordinates":[-86.288699,41.671932],"type":"Point"}
}