{
  "type": "Feature",
  "properties": {
    "iso:country":"US",
    "sg:address":"255 W Main St",
    "sg:city":"Danville",
    "sg:classifiers":[
        {
            "category":"Professional",
            "subcategory":"Accounting & Tax Preparation",
            "type":"Services"
        }
    ],
    "sg:phone":"+1 317 745 6411",
    "sg:postcode":"46122",
    "sg:province":"IN",
    "sg:tags":[
        "accountant"
    ],
    "sg:website":"www.donovanthomas.com",
    "wof:name":"Donovan & Thomas PC",
    "wof:placetype":"venue"
},
  "geometry": {"coordinates":[-86.52691,39.760689],"type":"Point"}
}