{
  "type": "Feature",
  "properties": {
    "iso:country":"US",
    "sg:address":"3723 Main St",
    "sg:city":"East Chicago",
    "sg:classifiers":[
        {
            "category":"Health Services",
            "subcategory":"Optometrist",
            "type":"Services"
        }
    ],
    "sg:phone":"+1 219 398 1832",
    "sg:postcode":"46312",
    "sg:province":"IN",
    "sg:tags":[
        "ophthalmologist"
    ],
    "wof:name":"Merrillville Eye Clinic",
    "wof:placetype":"venue"
},
  "geometry": {"coordinates":[-87.444801,41.645302],"type":"Point"}
}