{
  "type": "Feature",
  "properties": {
    "iso:country":"US",
    "sg:address":"205 E Chestnut St",
    "sg:city":"Jeffersonville",
    "sg:classifiers":[
        {
            "category":"Insurance",
            "subcategory":"Insurance Agent",
            "type":"Services"
        }
    ],
    "sg:phone":"+1 812 284 4612",
    "sg:postcode":"47130",
    "sg:province":"IN",
    "wof:name":"Farmers Insurance Group",
    "wof:placetype":"venue"
},
  "geometry": {"coordinates":[-85.737994,38.273103],"type":"Point"}
}