{
  "type": "Feature",
  "properties": {
    "addr:full":"5925 Calumet Ave Hammond IN 46320",
    "addr:housenumber":"5925",
    "addr:postcode":"46320",
    "addr:street":"Calumet Ave",
    "iso:country":"US",
    "sg:address":"5925 Calumet Ave",
    "sg:city":"Hammond",
    "sg:classifiers":[
        {
            "category":"Building & Trades",
            "subcategory":"Construction",
            "type":"Services"
        }
    ],
    "sg:phone":"+1 219 853 6382",
    "sg:postcode":"46320",
    "sg:province":"IN",
    "sg:tags":[
        "marking",
        "maintenance",
        "parking"
    ],
    "wof:name":"Hammond Board Of Public Works",
    "wof:placetype":"venue"
},
  "geometry": {"coordinates":[-87.508723,41.606188],"type":"Point"}
}