{
  "type": "Feature",
  "properties": {
    "iso:country":"US",
    "sg:address":"8700 W Vernal Pike",
    "sg:city":"Bloomington",
    "sg:classifiers":[
        {
            "category":"Utilities",
            "subcategory":"Refuse",
            "type":"Services"
        },
        {
            "category":"Manufacturing",
            "subcategory":"Chemicals & Compounds",
            "type":"Manufacturing & Wholesale Goods"
        }
    ],
    "sg:phone":"+1 812 876 7645",
    "sg:postcode":"47404",
    "sg:province":"IN",
    "sg:tags":[
        "farm",
        "compost",
        "system",
        "supply"
    ],
    "sg:website":"www.earth-maker.com",
    "wof:name":"Top Soil Composting Service",
    "wof:placetype":"venue"
},
  "geometry": {"coordinates":[-86.658572,39.17293],"type":"Point"}
}