{
  "type": "Feature",
  "properties": {
    "iso:country":"US",
    "sg:address":"2025 Cedar Crest Dr",
    "sg:city":"Kokomo",
    "sg:classifiers":[
        {
            "category":"Professional",
            "subcategory":"Computer Services",
            "type":"Services"
        }
    ],
    "sg:phone":"+1 765 454 9649",
    "sg:postcode":"46902",
    "sg:province":"IN",
    "sg:tags":[
        "repair"
    ],
    "wof:name":"Inkjet Refill Express",
    "wof:placetype":"venue"
},
  "geometry": {"coordinates":[-86.099637,40.463125],"type":"Point"}
}