{
  "type": "Feature",
  "properties": {
    "iso:country":"US",
    "sg:address":"2333 Lafayette Rd",
    "sg:city":"Indianapolis",
    "sg:classifiers":[
        {
            "category":"Organizations",
            "subcategory":"Religious Organization",
            "type":"Services"
        }
    ],
    "sg:phone":"+1 317 925 5563",
    "sg:postcode":"46222",
    "sg:province":"IN",
    "sg:tags":[
        "church"
    ],
    "wof:name":"Joy Tabernacle Christian",
    "wof:placetype":"venue"
},
  "geometry": {"coordinates":[-86.208502,39.797405],"type":"Point"}
}