{
  "type": "Feature",
  "properties": {
    "iso:country":"US",
    "sg:address":"755 E Carmel Dr",
    "sg:city":"Carmel",
    "sg:classifiers":[
        {
            "category":"Professional",
            "subcategory":"Management & Consulting",
            "type":"Services"
        }
    ],
    "sg:phone":"+1 317 571 9930",
    "sg:postcode":"46032",
    "sg:province":"IN",
    "sg:tags":[
        "consultant",
        "business"
    ],
    "wof:name":"SOITIS LLC",
    "wof:placetype":"venue"
},
  "geometry": {"coordinates":[-86.113961,39.961956],"type":"Point"}
}