{
  "type": "Feature",
  "properties": {
    "iso:country":"US",
    "sg:address":"945 S 34th St",
    "sg:city":"South Bend",
    "sg:classifiers":[
        {
            "category":"Home & Garden",
            "subcategory":"Household Appliances",
            "type":"Retail Goods"
        }
    ],
    "sg:phone":"+1 574 287 1985",
    "sg:postcode":"46615",
    "sg:province":"IN",
    "wof:name":"A Appliance Sales & Svc",
    "wof:placetype":"venue"
},
  "geometry": {"coordinates":[-86.20034200000001,41.66483],"type":"Point"}
}