{
  "type": "Feature",
  "properties": {
    "iso:country":"US",
    "sg:address":"5131 W Thompson Rd",
    "sg:city":"Indianapolis",
    "sg:classifiers":[
        {
            "category":"Education",
            "subcategory":"Dance Studio",
            "type":"Public Place"
        }
    ],
    "sg:phone":"+1 317 856 4566",
    "sg:postcode":"46221",
    "sg:province":"IN",
    "sg:tags":[
        "instruction",
        "dancing"
    ],
    "wof:name":"Beth Lucas School Of Dance",
    "wof:placetype":"venue"
},
  "geometry": {"coordinates":[-86.245854,39.691716],"type":"Point"}
}