{
  "type": "Feature",
  "properties": {
    "iso:country":"US",
    "sg:address":"159 W Market St",
    "sg:city":"Nappanee",
    "sg:classifiers":[
        {
            "category":"Retail",
            "subcategory":"Auto Repair",
            "type":"Services"
        }
    ],
    "sg:phone":"+1 574 773 4500",
    "sg:postcode":"46550",
    "sg:province":"IN",
    "sg:tags":[
        "repairing",
        "automobile"
    ],
    "wof:name":"Market Street Auto Svc",
    "wof:placetype":"venue"
},
  "geometry": {"coordinates":[-86.002512,41.442577],"type":"Point"}
}