{
  "type": "Feature",
  "properties": {
    "iso:country":"US",
    "sg:address":"700 W King St",
    "sg:city":"Garrett",
    "sg:classifiers":[
        {
            "category":"Retail",
            "subcategory":"Self-service Laundry",
            "type":"Services"
        }
    ],
    "sg:phone":"+1 260 357 3030",
    "sg:postcode":"46738",
    "sg:province":"IN",
    "wof:name":"Hannah's",
    "wof:placetype":"venue"
},
  "geometry": {"coordinates":[-85.143025,41.350356],"type":"Point"}
}