{
  "type": "Feature",
  "properties": {
    "iso:country":"US",
    "sg:address":"9 E Maple St",
    "sg:city":"Brazil",
    "sg:classifiers":[
        {
            "category":"Personal",
            "subcategory":"Beauty Salon",
            "type":"Services"
        }
    ],
    "sg:phone":"+1 812 448 8477",
    "sg:postcode":"47834",
    "sg:province":"IN",
    "sg:tags":[
        "shop"
    ],
    "wof:name":"Silver Tip Beauty Salon",
    "wof:placetype":"venue"
},
  "geometry": {"coordinates":[-87.12629,39.519023],"type":"Point"}
}