{
  "type": "Feature",
  "properties": {
    "iso:country":"US",
    "sg:address":"1839 Robin Rd",
    "sg:city":"Martinsville",
    "sg:classifiers":[
        {
            "category":"Government",
            "subcategory":"Office",
            "type":"Public Place"
        }
    ],
    "sg:phone":"+1 765 342 3324",
    "sg:postcode":"46151",
    "sg:province":"IN",
    "sg:tags":[
        "state",
        "resource"
    ],
    "wof:name":"Indiana Workforce Development",
    "wof:placetype":"venue"
},
  "geometry": {"coordinates":[-86.441598,39.411453],"type":"Point"}
}