{
  "type": "Feature",
  "properties": {
    "addr:full":"4193 Englewood Dr Indianapolis IN 46226",
    "addr:housenumber":"4193",
    "addr:postcode":"46226",
    "addr:street":"Englewood Dr",
    "iso:country":"US",
    "sg:address":"4193 Englewood Dr",
    "sg:city":"Indianapolis",
    "sg:classifiers":[
        {
            "category":"Professional",
            "subcategory":"Testing Lab",
            "type":"Services"
        }
    ],
    "sg:phone":"+1 317 562 0417",
    "sg:postcode":"46226",
    "sg:province":"IN",
    "sg:tags":[
        "analytical",
        "laboratory"
    ],
    "wof:name":"Diamondhead Laboratories Inc",
    "wof:placetype":"venue"
},
  "geometry": {"coordinates":[-86.04442,39.833032],"type":"Point"}
}