{
  "type": "Feature",
  "properties": {
    "addr:full":"809 S Elizabeth St Kokomo IN 46901",
    "addr:housenumber":"809",
    "addr:postcode":"46901",
    "addr:street":"S Elizabeth St",
    "iso:country":"US",
    "sg:address":"809 S Elizabeth St",
    "sg:city":"Kokomo",
    "sg:classifiers":[
        {
            "category":"Organizations",
            "subcategory":"Religious Organization",
            "type":"Services"
        }
    ],
    "sg:phone":"+1 765 459 0064",
    "sg:postcode":"46901",
    "sg:province":"IN",
    "wof:name":"Stars of Light Baptist Church",
    "wof:placetype":"venue"
},
  "geometry": {"coordinates":[-86.11435,40.477128],"type":"Point"}
}