{
  "type": "Feature",
  "properties": {
    "iso:country":"US",
    "sg:address":"13060 Jefferson Blvd",
    "sg:city":"Mishawaka",
    "sg:classifiers":[
        {
            "category":"Food & Beverages",
            "subcategory":"Groceries & Convenience Stores",
            "type":"Retail Goods"
        }
    ],
    "sg:phone":"+1 574 258 0021",
    "sg:postcode":"46545",
    "sg:province":"IN",
    "wof:name":"Marsh",
    "wof:placetype":"venue"
},
  "geometry": {"coordinates":[-86.121841,41.67343],"type":"Point"}
}