{
  "type": "Feature",
  "properties": {
    "iso:country":"US",
    "sg:address":"618 W Superior St",
    "sg:city":"Kokomo",
    "sg:classifiers":[
        {
            "category":"Organizations",
            "subcategory":"Religious Organization",
            "type":"Services"
        }
    ],
    "sg:phone":"+1 765 452 0383",
    "sg:postcode":"46901",
    "sg:province":"IN",
    "sg:tags":[
        "synagogue"
    ],
    "wof:name":"Temple B'Nai Israel",
    "wof:placetype":"venue"
},
  "geometry": {"coordinates":[-86.13592800000001,40.485549],"type":"Point"}
}