{
  "type": "Feature",
  "properties": {
    "iso:country":"US",
    "sg:address":"26891 Co Rd 4",
    "sg:city":"Elkhart",
    "sg:classifiers":[
        {
            "category":"Personal",
            "subcategory":"Beauty Salon",
            "type":"Services"
        }
    ],
    "sg:phone":"+1 574 264 5317",
    "sg:postcode":"46514",
    "sg:province":"IN",
    "sg:tags":[
        "shop"
    ],
    "wof:name":"Diamond Cut Inc",
    "wof:placetype":"venue"
},
  "geometry": {"coordinates":[-85.982895,41.738897],"type":"Point"}
}