{
  "type": "Feature",
  "properties": {
    "iso:country":"US",
    "sg:address":"414 S Taylor St",
    "sg:city":"South Bend",
    "sg:classifiers":[
        {
            "category":"Professional",
            "subcategory":"Lawyer & Legal Services",
            "type":"Services"
        }
    ],
    "sg:phone":"+1 574 287 3090",
    "sg:postcode":"46601",
    "sg:province":"IN",
    "sg:tags":[
        "attorney"
    ],
    "wof:name":"John J Roper",
    "wof:placetype":"venue"
},
  "geometry": {"coordinates":[-86.25703900000001,41.671543],"type":"Point"}
}