{
  "type": "Feature",
  "properties": {
    "iso:country":"US",
    "sg:address":"4410 N Old State Rd 3",
    "sg:city":"Muncie",
    "sg:classifiers":[
        {
            "category":"Shopping",
            "subcategory":"Clothing, Apparel, & Fashions",
            "type":"Retail Goods"
        }
    ],
    "sg:phone":"+1 765 587 0038",
    "sg:postcode":"47303",
    "sg:province":"IN",
    "sg:tags":[
        "used",
        "merchandise"
    ],
    "wof:name":"Ready To Wear",
    "wof:placetype":"venue"
},
  "geometry": {"coordinates":[-85.367897,40.229716],"type":"Point"}
}