{
  "type": "Feature",
  "properties": {
    "iso:country":"US",
    "sg:address":"27 E Main St",
    "sg:city":"New Palestine",
    "sg:classifiers":[
        {
            "category":"Personal",
            "subcategory":"Beauty Salon",
            "type":"Services"
        }
    ],
    "sg:phone":"+1 317 861 0606",
    "sg:postcode":"46163",
    "sg:province":"IN",
    "wof:name":"Styles & Files Salon",
    "wof:placetype":"venue"
},
  "geometry": {"coordinates":[-85.888201,39.720814],"type":"Point"}
}