{
  "type": "Feature",
  "properties": {
    "iso:country":"US",
    "sg:address":"6421 Ware St",
    "sg:city":"Indianapolis",
    "sg:classifiers":[
        {
            "category":"Building & Trades",
            "subcategory":"Plumbing",
            "type":"Services"
        }
    ],
    "sg:phone":"+1 317 826 9808",
    "sg:postcode":"46236",
    "sg:province":"IN",
    "sg:tags":[
        "heating",
        "contractor"
    ],
    "wof:name":"Addison & Spatig Heating",
    "wof:placetype":"venue"
},
  "geometry": {"coordinates":[-85.959355,39.87494],"type":"Point"}
}