{
  "type": "Feature",
  "properties": {
    "iso:country":"US",
    "sg:address":"3637 Nichol Ave",
    "sg:city":"Anderson",
    "sg:classifiers":[
        {
            "category":"Shopping",
            "subcategory":"Musical Instruments",
            "type":"Retail Goods"
        }
    ],
    "sg:phone":"+1 765 642 0229",
    "sg:postcode":"46011",
    "sg:province":"IN",
    "wof:name":"Dan's Music",
    "wof:placetype":"venue"
},
  "geometry": {"coordinates":[-85.73522199999999,40.101389],"type":"Point"}
}