{
  "type": "Feature",
  "properties": {
    "iso:country":"US",
    "sg:address":"1209 W Coolspring Ave",
    "sg:city":"Michigan City",
    "sg:classifiers":[
        {
            "category":"Building & Trades",
            "subcategory":"Landscaping Services",
            "type":"Services"
        }
    ],
    "sg:phone":"+1 219 879 2455",
    "sg:postcode":"46360",
    "sg:province":"IN",
    "sg:tags":[
        "tree"
    ],
    "wof:name":"Denny's Tree Svc",
    "wof:placetype":"venue"
},
  "geometry": {"coordinates":[-86.909477,41.694777],"type":"Point"}
}