{
  "type": "Feature",
  "properties": {
    "addr:full":"8526 Woodsmall Dr Terre Haute IN 47802",
    "addr:housenumber":"8526",
    "addr:postcode":"47802",
    "addr:street":"Woodsmall Dr",
    "iso:country":"US",
    "sg:address":"8526 Woodsmall Dr",
    "sg:city":"Terre Haute",
    "sg:classifiers":[
        {
            "category":"Farming",
            "subcategory":"Farm",
            "type":"Manufacturing & Wholesale Goods"
        }
    ],
    "sg:phone":"+1 812 894 2977",
    "sg:postcode":"47802",
    "sg:province":"IN",
    "sg:tags":[
        "crop",
        "general"
    ],
    "wof:name":"Jeffers Hay and Straw",
    "wof:placetype":"venue"
},
  "geometry": {"coordinates":[-87.28871599999999,39.375826],"type":"Point"}
}