{
  "type": "Feature",
  "properties": {
    "iso:country":"US",
    "sg:address":"117 W Mulberry St",
    "sg:city":"Marion",
    "sg:classifiers":[
        {
            "category":"Health Services",
            "subcategory":"Doctor",
            "type":"Services"
        }
    ],
    "sg:phone":"+1 765 664 0028",
    "sg:postcode":"46952",
    "sg:province":"IN",
    "sg:tags":[
        "dentist"
    ],
    "wof:name":"K & L Dental",
    "wof:placetype":"venue"
},
  "geometry": {"coordinates":[-85.665414,40.565877],"type":"Point"}
}