{
  "type": "Feature",
  "properties": {
    "iso:country":"US",
    "sg:address":"1436 W 86th St",
    "sg:city":"Indianapolis",
    "sg:classifiers":[
        {
            "category":"Restaurant",
            "type":"Food & Drink"
        }
    ],
    "sg:menulink":"http://www.allmenus.com/in/meridian-hills/88588-applebees/menu/",
    "sg:phone":"+1 317 872 4470",
    "sg:postcode":"46260",
    "sg:province":"IN",
    "sg:tags":[
        "burger",
        "american",
        "sandwich",
        "soup"
    ],
    "wof:name":"Applebee's",
    "wof:placetype":"venue"
},
  "geometry": {"coordinates":[-86.18563,39.912253],"type":"Point"}
}