{
  "type": "Feature",
  "properties": {
    "addr:full":"11703 Lantern Rd Fishers IN 46038",
    "addr:housenumber":"11703",
    "addr:postcode":"46038",
    "addr:street":"Lantern Rd",
    "iso:country":"US",
    "sg:address":"11703 Lantern Rd",
    "sg:city":"Fishers",
    "sg:classifiers":[
        {
            "category":"Insurance",
            "subcategory":"Insurance Agent",
            "type":"Services"
        }
    ],
    "sg:phone":"+1 317 845 8858",
    "sg:postcode":"46038",
    "sg:province":"IN",
    "wof:name":"American Family Insurance",
    "wof:placetype":"venue"
},
  "geometry": {"coordinates":[-86.01336000000001,39.957866],"type":"Point"}
}