{
  "type": "Feature",
  "properties": {
    "iso:country":"US",
    "sg:address":"13201 S 800 W",
    "sg:city":"New Richmond",
    "sg:classifiers":[
        {
            "category":"Building & Trades",
            "subcategory":"Construction",
            "type":"Services"
        }
    ],
    "sg:phone":"+1 765 275 2741",
    "sg:postcode":"47967",
    "sg:province":"IN",
    "sg:tags":[
        "general",
        "contractor"
    ],
    "wof:name":"Padgett Remodeling & Contr",
    "wof:placetype":"venue"
},
  "geometry": {"coordinates":[-87.05466300000001,40.226465],"type":"Point"}
}