{
  "type": "Feature",
  "properties": {
    "iso:country":"US",
    "sg:address":"2963 Parker St",
    "sg:city":"Portage",
    "sg:classifiers":[
        {
            "category":"Building & Trades",
            "subcategory":"Construction",
            "type":"Services"
        }
    ],
    "sg:phone":"+1 219 763 6860",
    "sg:postcode":"46368",
    "sg:province":"IN",
    "sg:tags":[
        "house"
    ],
    "wof:name":"Authentic Construction Inc",
    "wof:placetype":"venue"
},
  "geometry": {"coordinates":[-87.197985,41.565811],"type":"Point"}
}