{
  "type": "Feature",
  "properties": {
    "addr:full":"431 E 4th Ave Huntingburg IN 47542",
    "addr:housenumber":"431",
    "addr:postcode":"47542",
    "addr:street":"E 4Th Ave",
    "iso:country":"US",
    "sg:address":"431 E 4th Ave",
    "sg:city":"Huntingburg",
    "sg:classifiers":[
        {
            "category":"Banks & Credit Unions",
            "subcategory":"Investment Brokerage",
            "type":"Services"
        }
    ],
    "sg:phone":"+1 812 683 4370",
    "sg:postcode":"47542",
    "sg:province":"IN",
    "sg:tags":[
        "stock",
        "bond"
    ],
    "wof:name":"Edward Jones Co",
    "wof:placetype":"venue"
},
  "geometry": {"coordinates":[-86.955161,38.28663],"type":"Point"}
}