{
  "type": "Feature",
  "properties": {
    "iso:country":"US",
    "sg:address":"309 N Kingston Rd",
    "sg:city":"Plymouth",
    "sg:classifiers":[
        {
            "category":"Health Services",
            "subcategory":"Health Practitioner",
            "type":"Services"
        }
    ],
    "sg:phone":"+1 574 936 9025",
    "sg:postcode":"46563",
    "sg:province":"IN",
    "sg:tags":[
        "therapist",
        "physical"
    ],
    "wof:name":"Walnut Creek At Plymouth",
    "wof:placetype":"venue"
},
  "geometry": {"coordinates":[-86.296313,41.343758],"type":"Point"}
}