{
  "type": "Feature",
  "properties": {
    "iso:country":"US",
    "sg:address":"1070 S Wayne St",
    "sg:city":"Waterloo",
    "sg:classifiers":[
        {
            "category":"Government",
            "subcategory":"Office",
            "type":"Public Place"
        }
    ],
    "sg:phone":"+1 260 837 4041",
    "sg:postcode":"46793",
    "sg:province":"IN",
    "sg:tags":[
        "village"
    ],
    "wof:name":"Grant Twp Trustee",
    "wof:placetype":"venue"
},
  "geometry": {"coordinates":[-85.024721,41.422815],"type":"Point"}
}