{
  "type": "Feature",
  "properties": {
    "iso:country":"US",
    "sg:address":"640 E 1100 N",
    "sg:city":"Knightstown",
    "sg:classifiers":[
        {
            "category":"Farming",
            "subcategory":"Farm",
            "type":"Manufacturing & Wholesale Goods"
        }
    ],
    "sg:phone":"+1 765 345 5621",
    "sg:postcode":"46148",
    "sg:province":"IN",
    "sg:tags":[
        "crop",
        "general"
    ],
    "wof:name":"Eugene Meek",
    "wof:placetype":"venue"
},
  "geometry": {"coordinates":[-85.434941,39.772721],"type":"Point"}
}