{
  "type": "Feature",
  "properties": {
    "iso:country":"US",
    "sg:address":"6529 Madison Ave",
    "sg:city":"Anderson",
    "sg:classifiers":[
        {
            "category":"Freight",
            "type":"Transportation"
        }
    ],
    "sg:phone":"+1 765 644 4470",
    "sg:postcode":"46013",
    "sg:province":"IN",
    "sg:tags":[
        "commercial",
        "storage"
    ],
    "wof:name":"D V Multi-Purpose Self Storage",
    "wof:placetype":"venue"
},
  "geometry": {"coordinates":[-85.692273,40.047251],"type":"Point"}
}