{
  "type": "Feature",
  "properties": {
    "iso:country":"US",
    "sg:address":"309 E Spring St",
    "sg:city":"New Albany",
    "sg:classifiers":[
        {
            "category":"Professional",
            "subcategory":"Business Services",
            "type":"Services"
        }
    ],
    "sg:phone":"+1 812 945 1234",
    "sg:postcode":"47150",
    "sg:province":"IN",
    "wof:name":"Hope Line",
    "wof:placetype":"venue"
},
  "geometry": {"coordinates":[-85.820016,38.287068],"type":"Point"}
}