{
  "type": "Feature",
  "properties": {
    "iso:country":"US",
    "sg:address":"206 Chippewa Dr",
    "sg:city":"Jeffersonville",
    "sg:classifiers":[
        {
            "category":"Professional",
            "type":"Services"
        }
    ],
    "sg:phone":"+1 812 282 5612",
    "sg:postcode":"47130",
    "sg:province":"IN",
    "wof:name":"Xmas 365 Foundation Inc",
    "wof:placetype":"venue"
},
  "geometry": {"coordinates":[-85.713324,38.286561],"type":"Point"}
}