{
  "type": "Feature",
  "properties": {
    "iso:country":"US",
    "sg:address":"75 E Pine St",
    "sg:city":"Zionsville",
    "sg:classifiers":[
        {
            "category":"Shopping",
            "subcategory":"Used Merchandise",
            "type":"Retail Goods"
        }
    ],
    "sg:phone":"+1 317 873 3409",
    "sg:postcode":"46077",
    "sg:province":"IN",
    "sg:tags":[
        "antique"
    ],
    "wof:name":"Jackson Run Antiques",
    "wof:placetype":"venue"
},
  "geometry": {"coordinates":[-86.26048299999999,39.950016],"type":"Point"}
}