{
  "type": "Feature",
  "properties": {
    "iso:country":"US",
    "sg:address":"10540 Coldwater Rd",
    "sg:city":"Fort Wayne",
    "sg:classifiers":[
        {
            "category":"Health Services",
            "subcategory":"Doctor",
            "type":"Services"
        }
    ],
    "sg:phone":"+1 260 637 4648",
    "sg:postcode":"46845",
    "sg:province":"IN",
    "sg:tags":[
        "dentist"
    ],
    "wof:name":"Rick A Warner DDS",
    "wof:placetype":"venue"
},
  "geometry": {"coordinates":[-85.13144,41.178618],"type":"Point"}
}