{
  "type": "Feature",
  "properties": {
    "iso:country":"US",
    "sg:address":"824 Hoffman St",
    "sg:city":"Hammond",
    "sg:classifiers":[
        {
            "category":"Retail",
            "subcategory":"Funeral Services",
            "type":"Services"
        }
    ],
    "sg:phone":"+1 219 844 1020",
    "sg:postcode":"46327",
    "sg:province":"IN",
    "sg:tags":[
        "director"
    ],
    "wof:name":"Virgil Huber Funeral Home",
    "wof:placetype":"venue"
},
  "geometry": {"coordinates":[-87.508797,41.626518],"type":"Point"}
}