{
  "type": "Feature",
  "properties": {
    "iso:country":"US",
    "sg:address":"10327 Calverton Pass",
    "sg:city":"Fort Wayne",
    "sg:classifiers":[
        {
            "category":"Insurance",
            "subcategory":"Insurance Agent",
            "type":"Services"
        }
    ],
    "sg:phone":"+1 260 489 6095",
    "sg:postcode":"46825",
    "sg:province":"IN",
    "wof:name":"Allied Insurance",
    "wof:placetype":"venue"
},
  "geometry": {"coordinates":[-85.126537,41.175678],"type":"Point"}
}