{
  "type": "Feature",
  "properties": {
    "iso:country":"US",
    "sg:address":"3910 Culligan Ave",
    "sg:city":"Indianapolis",
    "sg:classifiers":[
        {
            "category":"Wholesale",
            "subcategory":"Machinery & Supplies",
            "type":"Manufacturing & Wholesale Goods"
        }
    ],
    "sg:phone":"+1 317 358 1641",
    "sg:postcode":"46218",
    "sg:province":"IN",
    "sg:tags":[
        "pump"
    ],
    "wof:name":"Duraflo Equipment Co",
    "wof:placetype":"venue"
},
  "geometry": {"coordinates":[-86.101594,39.790899],"type":"Point"}
}