{
  "type": "Feature",
  "properties": {
    "iso:country":"US",
    "sg:address":"410 Main St",
    "sg:city":"New Harmony",
    "sg:classifiers":[
        {
            "category":"Government",
            "subcategory":"Office",
            "type":"Public Place"
        }
    ],
    "sg:phone":"+1 812 682 3271",
    "sg:postcode":"47631",
    "sg:province":"IN",
    "wof:name":"New Harmony State Historic",
    "wof:placetype":"venue"
},
  "geometry": {"coordinates":[-87.934919,38.129755],"type":"Point"}
}