{
  "type": "Feature",
  "properties": {
    "addr:full":"8755 W 250 N Shipshewana IN 46565",
    "addr:housenumber":"8755",
    "addr:postcode":"46565",
    "addr:street":"W 250 N",
    "iso:country":"US",
    "sg:address":"8755 W 250 N",
    "sg:city":"Shipshewana",
    "sg:classifiers":[
        {
            "category":"Autos & Motor Vehicles",
            "subcategory":"Boat Sales",
            "type":"Retail Goods"
        }
    ],
    "sg:phone":"+1 260 768 8094",
    "sg:postcode":"46565",
    "sg:province":"IN",
    "sg:tags":[
        "dealer",
        "sales"
    ],
    "wof:name":"L & R Marine LLC",
    "wof:placetype":"venue"
},
  "geometry": {"coordinates":[-85.595507,41.676296],"type":"Point"}
}