{
  "type": "Feature",
  "properties": {
    "iso:country":"US",
    "sg:address":"905 Ridge Rd",
    "sg:city":"Munster",
    "sg:classifiers":[
        {
            "category":"Health Services",
            "subcategory":"Dentist",
            "type":"Services"
        }
    ],
    "sg:phone":"+1 219 836 2141",
    "sg:postcode":"46321",
    "sg:province":"IN",
    "wof:name":"Gordon Michael A DDS PC",
    "wof:placetype":"venue"
},
  "geometry": {"coordinates":[-87.506579,41.561102],"type":"Point"}
}