{
  "type": "Feature",
  "properties": {
    "iso:country":"US",
    "sg:address":"8774 W 700 N",
    "sg:city":"Winamac",
    "sg:classifiers":[
        {
            "category":"Museum",
            "type":"Entertainment"
        }
    ],
    "sg:phone":"+1 574 896 3172",
    "sg:postcode":"46996",
    "sg:province":"IN",
    "wof:name":"World Of Motorcycles Museum",
    "wof:placetype":"venue"
},
  "geometry": {"coordinates":[-86.758137,41.157429],"type":"Point"}
}