{
  "type": "Feature",
  "properties": {
    "iso:country":"US",
    "sg:address":"511 Madison Ave",
    "sg:city":"Indianapolis",
    "sg:classifiers":[
        {
            "category":"Professional",
            "subcategory":"Advertising",
            "type":"Services"
        }
    ],
    "sg:phone":"+1 317 634 1900",
    "sg:postcode":"46225",
    "sg:province":"IN",
    "wof:name":"Clear Channel Outdoor",
    "wof:placetype":"venue"
},
  "geometry": {"coordinates":[-86.157544,39.75982],"type":"Point"}
}