{
  "type": "Feature",
  "properties": {
    "iso:country":"US",
    "sg:address":"63061 Co Rd 13",
    "sg:city":"Goshen",
    "sg:classifiers":[
        {
            "category":"Government",
            "subcategory":"Office",
            "type":"Public Place"
        }
    ],
    "sg:phone":"+1 574 875 5039",
    "sg:postcode":"46526",
    "sg:province":"IN",
    "sg:tags":[
        "village"
    ],
    "wof:name":"Harrison Twp Trustee",
    "wof:placetype":"venue"
},
  "geometry": {"coordinates":[-85.925146,41.579339],"type":"Point"}
}