{
  "type": "Feature",
  "properties": {
    "iso:country":"US",
    "sg:address":"478 W Glendale St",
    "sg:city":"Princeton",
    "sg:classifiers":[
        {
            "category":"Professional",
            "subcategory":"Computer Services",
            "type":"Services"
        }
    ],
    "sg:phone":"+1 812 385 2819",
    "sg:postcode":"47670",
    "sg:province":"IN",
    "sg:tags":[
        "repair"
    ],
    "wof:name":"Computerwerks",
    "wof:placetype":"venue"
},
  "geometry": {"coordinates":[-87.574544,38.36284],"type":"Point"}
}