{
  "type": "Feature",
  "properties": {
    "iso:country":"US",
    "sg:address":"8015 Pendleton Pike",
    "sg:city":"Lawrence",
    "sg:classifiers":[
        {
            "category":"Retail",
            "subcategory":"Laundry & Dry Cleaning",
            "type":"Services"
        }
    ],
    "sg:phone":"+1 317 898 4600",
    "sg:postcode":"46226",
    "sg:province":"IN",
    "sg:tags":[
        "cleaners"
    ],
    "wof:name":"Classic Tan & Laundry",
    "wof:placetype":"venue"
},
  "geometry": {"coordinates":[-86.025208,39.837154],"type":"Point"}
}