{
  "type": "Feature",
  "properties": {
    "iso:country":"US",
    "sg:address":"417 S Main St",
    "sg:city":"Jonesboro",
    "sg:classifiers":[
        {
            "category":"Bars & Pubs",
            "type":"Food & Drink"
        }
    ],
    "sg:phone":"+1 765 674 9606",
    "sg:postcode":"46938",
    "sg:province":"IN",
    "wof:name":"Down On Main Street",
    "wof:placetype":"venue"
},
  "geometry": {"coordinates":[-85.627778,40.481538],"type":"Point"}
}