{
  "type": "Feature",
  "properties": {
    "iso:country":"US",
    "sg:address":"2915 E 35th Ave",
    "sg:city":"Lake Station",
    "sg:classifiers":[
        {
            "category":"Education",
            "subcategory":"School",
            "type":"Public Place"
        }
    ],
    "sg:phone":"+1 219 962 1608",
    "sg:postcode":"46405",
    "sg:province":"IN",
    "wof:name":"Henry S Evans Elementary Schl",
    "wof:placetype":"venue"
},
  "geometry": {"coordinates":[-87.30134200000001,41.554633],"type":"Point"}
}