{
  "type": "Feature",
  "properties": {
    "iso:country":"US",
    "sg:address":"1515 Kossuth St",
    "sg:city":"Lafayette",
    "sg:classifiers":[
        {
            "category":"Professional",
            "subcategory":"Business Services",
            "type":"Services"
        }
    ],
    "sg:phone":"+1 765 742 8967",
    "sg:postcode":"47905",
    "sg:province":"IN",
    "sg:tags":[
        "water",
        "treatment"
    ],
    "wof:name":"Rayne Water Conditioning",
    "wof:placetype":"venue"
},
  "geometry": {"coordinates":[-86.87859,40.409913],"type":"Point"}
}