{
  "type": "Feature",
  "properties": {
    "iso:country":"US",
    "sg:address":"1403 S 9th St",
    "sg:city":"Richmond",
    "sg:classifiers":[
        {
            "category":"Organizations",
            "subcategory":"Religious Organization",
            "type":"Services"
        }
    ],
    "sg:phone":"+1 765 939 2327",
    "sg:postcode":"47374",
    "sg:province":"IN",
    "wof:name":"Kings Highway Holiness",
    "wof:placetype":"venue"
},
  "geometry": {"coordinates":[-84.8899,39.811527],"type":"Point"}
}