{
  "type": "Feature",
  "properties": {
    "iso:country":"US",
    "sg:address":"11759 S 400 W",
    "sg:city":"Converse",
    "sg:classifiers":[
        {
            "category":"Wholesale",
            "subcategory":"Apparel",
            "type":"Manufacturing & Wholesale Goods"
        }
    ],
    "sg:phone":"+1 765 395 1427",
    "sg:postcode":"46919",
    "sg:province":"IN",
    "sg:tags":[
        "clothing"
    ],
    "wof:name":"MPH Inc",
    "wof:placetype":"venue"
},
  "geometry": {"coordinates":[-85.874077,40.655451],"type":"Point"}
}