{
  "type": "Feature",
  "properties": {
    "iso:country":"US",
    "sg:address":"6930 Doris Dr",
    "sg:city":"Indianapolis",
    "sg:classifiers":[
        {
            "category":"Building & Trades",
            "subcategory":"Construction",
            "type":"Services"
        }
    ],
    "sg:phone":"+1 317 247 8744",
    "sg:postcode":"46214",
    "sg:province":"IN",
    "sg:tags":[
        "builder",
        "patio",
        "deck"
    ],
    "wof:name":"Beartooth Decks Inc",
    "wof:placetype":"venue"
},
  "geometry": {"coordinates":[-86.280953,39.789063],"type":"Point"}
}