{
  "type": "Feature",
  "properties": {
    "addr:full":"125 E Main St Twelve Mile IN 46947",
    "addr:housenumber":"125",
    "addr:postcode":"46947",
    "addr:street":"E Main St",
    "iso:country":"US",
    "sg:address":"125 E Main St",
    "sg:city":"Twelve Mile",
    "sg:classifiers":[
        {
            "category":"Government",
            "subcategory":"Fire Station",
            "type":"Public Place"
        }
    ],
    "sg:phone":"+1 574 664 2401",
    "sg:postcode":"46947",
    "sg:province":"IN",
    "sg:tags":[
        "department"
    ],
    "wof:name":"Fire Department",
    "wof:placetype":"venue"
},
  "geometry": {"coordinates":[-86.35567899999999,40.757804],"type":"Point"}
}