{
  "type": "Feature",
  "properties": {
    "iso:country":"US",
    "sg:address":"220 S Perry St",
    "sg:city":"Attica",
    "sg:classifiers":[
        {
            "category":"Autos & Motor Vehicles",
            "subcategory":"Fuel & Gas Station",
            "type":"Retail Goods"
        }
    ],
    "sg:phone":"+1 765 764 4197",
    "sg:postcode":"47918",
    "sg:province":"IN",
    "sg:tags":[
        "oil"
    ],
    "wof:name":"Watson Tire & Auto Svc",
    "wof:placetype":"venue"
},
  "geometry": {"coordinates":[-87.249264,40.29357],"type":"Point"}
}