{
  "type": "Feature",
  "properties": {
    "iso:country":"US",
    "sg:address":"2105 Biomet Dr",
    "sg:city":"Warsaw",
    "sg:classifiers":[
        {
            "category":"Autos & Motor Vehicles",
            "subcategory":"Automobile Sales",
            "type":"Retail Goods"
        }
    ],
    "sg:phone":"+1 574 372 3325",
    "sg:postcode":"46582",
    "sg:province":"IN",
    "sg:tags":[
        "car",
        "dealer"
    ],
    "wof:name":"R & B Car Co",
    "wof:placetype":"venue"
},
  "geometry": {"coordinates":[-85.840862,41.266003],"type":"Point"}
}