{
  "type": "Feature",
  "properties": {
    "iso:country":"US",
    "sg:address":"104 N Buckeye St",
    "sg:city":"Kokomo",
    "sg:classifiers":[
        {
            "category":"Social Services",
            "type":"Services"
        }
    ],
    "sg:phone":"+1 765 456 2224",
    "sg:postcode":"46901",
    "sg:province":"IN",
    "sg:tags":[
        "probation"
    ],
    "wof:name":"Howard County Probation Office",
    "wof:placetype":"venue"
},
  "geometry": {"coordinates":[-86.132374,40.487364],"type":"Point"}
}