{
  "type": "Feature",
  "properties": {
    "iso:country":"US",
    "sg:address":"505 Edgeknoll Ln",
    "sg:city":"Fort Wayne",
    "sg:classifiers":[
        {
            "category":"Building & Trades",
            "subcategory":"Cleaning & Sanitation",
            "type":"Services"
        }
    ],
    "sg:phone":"+1 260 744 1709",
    "sg:postcode":"46816",
    "sg:province":"IN",
    "sg:tags":[
        "flue"
    ],
    "wof:name":"R & A Industrial Cleaning",
    "wof:placetype":"venue"
},
  "geometry": {"coordinates":[-85.131648,41.023964],"type":"Point"}
}