{
  "type": "Feature",
  "properties": {
    "iso:country":"US",
    "sg:address":"1512 W Main St",
    "sg:city":"Greensburg",
    "sg:classifiers":[
        {
            "category":"Banks & Credit Unions",
            "subcategory":"Bank",
            "type":"Services"
        }
    ],
    "sg:phone":"+1 812 663 2454",
    "sg:postcode":"47240",
    "sg:province":"IN",
    "sg:tags":[
        "loan"
    ],
    "wof:name":"Farm Credit Svc",
    "wof:placetype":"venue"
},
  "geometry": {"coordinates":[-85.506617,39.33636],"type":"Point"}
}