{
  "type": "Feature",
  "properties": {
    "iso:country":"US",
    "sg:address":"8410 Conarroe Rd",
    "sg:city":"Indianapolis",
    "sg:classifiers":[
        {
            "category":"Insurance",
            "subcategory":"Insurance Agent",
            "type":"Services"
        }
    ],
    "sg:phone":"+1 317 228 9865",
    "sg:postcode":"46278",
    "sg:province":"IN",
    "sg:tags":[
        "accident"
    ],
    "wof:name":"A Acceptable Answers To Health",
    "wof:placetype":"venue"
},
  "geometry": {"coordinates":[-86.278554,39.910037],"type":"Point"}
}