{
  "type": "Feature",
  "properties": {
    "iso:country":"US",
    "sg:address":"13435 Darmstadt Rd",
    "sg:city":"Evansville",
    "sg:classifiers":[
        {
            "category":"Building & Trades",
            "subcategory":"Equipment Rental",
            "type":"Services"
        }
    ],
    "sg:phone":"+1 812 867 1040",
    "sg:postcode":"47725",
    "sg:province":"IN",
    "sg:tags":[
        "party",
        "supply"
    ],
    "sg:website":"www.bauerstents.com",
    "wof:name":"Bauer's Tents & Fast Structure",
    "wof:placetype":"venue"
},
  "geometry": {"coordinates":[-87.57798,38.101922],"type":"Point"}
}