{
  "type": "Feature",
  "properties": {
    "iso:country":"US",
    "sg:address":"1904 Circle Dr",
    "sg:city":"Bedford",
    "sg:classifiers":[
        {
            "category":"Real Estate",
            "subcategory":"Surveying",
            "type":"Services"
        }
    ],
    "sg:phone":"+1 812 279 4213",
    "sg:postcode":"47421",
    "sg:province":"IN",
    "sg:tags":[
        "surveyor"
    ],
    "wof:name":"Michael D Arena Land Surveyor",
    "wof:placetype":"venue"
},
  "geometry": {"coordinates":[-86.50615500000001,38.857096],"type":"Point"}
}