{
  "type": "Feature",
  "properties": {
    "addr:full":"698 Valley Dr Valparaiso IN 46383",
    "addr:housenumber":"698",
    "addr:postcode":"46383",
    "addr:street":"Valley Dr",
    "iso:country":"US",
    "sg:address":"698 Valley Dr",
    "sg:city":"Valparaiso",
    "sg:phone":"+1 219 462 2416",
    "sg:postcode":"46383",
    "sg:province":"IN",
    "sg:tags":[
        "farm",
        "corn"
    ],
    "wof:name":"Larry Wright",
    "wof:placetype":"venue"
},
  "geometry": {"coordinates":[-87.039439,41.533494],"type":"Point"}
}