{
  "type": "Feature",
  "properties": {
    "addr:full":"1033 Co Rd 9a Corunna IN 46730",
    "addr:housenumber":"1033",
    "addr:postcode":"46730",
    "addr:street":"Co Rd 9A",
    "iso:country":"US",
    "sg:address":"1033 Co Rd 9a",
    "sg:city":"Corunna",
    "sg:classifiers":[
        {
            "category":"Farming",
            "subcategory":"Livestock Farm",
            "type":"Manufacturing & Wholesale Goods"
        }
    ],
    "sg:phone":"+1 260 281 2855",
    "sg:postcode":"46730",
    "sg:province":"IN",
    "sg:tags":[
        "feedlot",
        "field",
        "crop",
        "beef",
        "cattle"
    ],
    "wof:name":"Donald Perlich",
    "wof:placetype":"venue"
},
  "geometry": {"coordinates":[-85.13267399999999,41.491602],"type":"Point"}
}