{
  "type": "Feature",
  "properties": {
    "addr:full":"10330 N Meridian St Indianapolis IN 46290",
    "addr:housenumber":"10330",
    "addr:postcode":"46290",
    "addr:street":"N Meridian St",
    "iso:country":"US",
    "sg:address":"10330 N Meridian St",
    "sg:city":"Indianapolis",
    "sg:classifiers":[
        {
            "category":"Building & Trades",
            "subcategory":"Locksmith",
            "type":"Services"
        }
    ],
    "sg:phone":"+1 317 682 4874",
    "sg:postcode":"46290",
    "sg:province":"IN",
    "sg:tags":[
        "key"
    ],
    "wof:name":"15 Minute Response Locksmith",
    "wof:placetype":"venue"
},
  "geometry": {"coordinates":[-86.158185,39.936675],"type":"Point"}
}