{
  "type": "Feature",
  "properties": {
    "addr:full":"1655 W Oakdale Dr Bloomington IN 47403",
    "addr:housenumber":"1655",
    "addr:postcode":"47403",
    "addr:street":"W Oakdale Dr",
    "iso:country":"US",
    "sg:address":"1655 W Oakdale Dr",
    "sg:city":"Bloomington",
    "sg:classifiers":[
        {
            "category":"Real Estate",
            "subcategory":"Real Estate Operator",
            "type":"Services"
        }
    ],
    "sg:phone":"+1 812 339 5063",
    "sg:postcode":"47403",
    "sg:province":"IN",
    "sg:tags":[
        "apartment"
    ],
    "wof:name":"Oakdale Square Apts",
    "wof:placetype":"venue"
},
  "geometry": {"coordinates":[-86.58260300000001,39.130901],"type":"Point"}
}