{
  "type": "Feature",
  "properties": {
    "addr:full":"2903 Gary Dr Plymouth IN 46563",
    "addr:housenumber":"2903",
    "addr:postcode":"46563",
    "addr:street":"Gary Dr",
    "iso:country":"US",
    "sg:address":"2903 Gary Dr",
    "sg:city":"Plymouth",
    "sg:classifiers":[
        {
            "category":"Real Estate",
            "subcategory":"Developer",
            "type":"Services"
        }
    ],
    "sg:phone":"+1 574 936 2024",
    "sg:postcode":"46563",
    "sg:province":"IN",
    "wof:name":"Rural Development",
    "wof:placetype":"venue"
},
  "geometry": {"coordinates":[-86.347999,41.362655],"type":"Point"}
}