{
  "type": "Feature",
  "properties": {
    "iso:country":"US",
    "sg:address":"515 E Warren St",
    "sg:city":"Middlebury",
    "sg:classifiers":[
        {
            "category":"Retail",
            "subcategory":"Veterinary Services",
            "type":"Services"
        }
    ],
    "sg:phone":"+1 574 825 5255",
    "sg:postcode":"46540",
    "sg:province":"IN",
    "sg:tags":[
        "veterinarian"
    ],
    "wof:name":"Middlebury Animal Clinic",
    "wof:placetype":"venue"
},
  "geometry": {"coordinates":[-85.698678,41.675717],"type":"Point"}
}