{
  "type": "Feature",
  "properties": {
    "iso:country":"US",
    "sg:address":"801 N 4th Ave",
    "sg:city":"Evansville",
    "sg:classifiers":[
        {
            "category":"Real Estate",
            "subcategory":"Real Estate Agent",
            "type":"Services"
        }
    ],
    "sg:phone":"+1 812 424 7668",
    "sg:postcode":"47710",
    "sg:province":"IN",
    "wof:name":"Real Estate Book",
    "wof:placetype":"venue"
},
  "geometry": {"coordinates":[-87.578985,37.985654],"type":"Point"}
}