{
  "type": "Feature",
  "properties": {
    "iso:country":"US",
    "sg:address":"2900 E Markland Ave",
    "sg:city":"Kokomo",
    "sg:classifiers":[
        {
            "category":"Organizations",
            "subcategory":"Religious Organization",
            "type":"Services"
        }
    ],
    "sg:phone":"+1 765 452 7166",
    "sg:postcode":"46901",
    "sg:province":"IN",
    "sg:tags":[
        "church"
    ],
    "sg:website":"www.morningstarkokomo.com",
    "wof:name":"Morning Star Church",
    "wof:placetype":"venue"
},
  "geometry": {"coordinates":[-86.091553,40.476895],"type":"Point"}
}