{
  "type": "Feature",
  "properties": {
    "addr:full":"100 W 3rd St Ligonier IN 46767",
    "addr:housenumber":"100",
    "addr:postcode":"46767",
    "addr:street":"W 3Rd St",
    "iso:country":"US",
    "sg:address":"100 W 3rd St",
    "sg:city":"Ligonier",
    "sg:classifiers":[
        {
            "category":"Building & Trades",
            "subcategory":"Construction",
            "type":"Services"
        }
    ],
    "sg:phone":"+1 260 894 3548",
    "sg:postcode":"46767",
    "sg:province":"IN",
    "sg:tags":[
        "contractor"
    ],
    "wof:name":"City Of Ligonier Building Dept",
    "wof:placetype":"venue"
},
  "geometry": {"coordinates":[-85.588376,41.46378],"type":"Point"}
}