{
  "type": "Feature",
  "properties": {
    "iso:country":"US",
    "sg:address":"2675 Cathy Ln",
    "sg:city":"Jasper",
    "sg:classifiers":[
        {
            "category":"Recreation",
            "type":"Entertainment"
        }
    ],
    "sg:phone":"+1 812 634 0803",
    "sg:postcode":"47546",
    "sg:province":"IN",
    "sg:tags":[
        "amusement"
    ],
    "wof:name":"Us Motor Sports",
    "wof:placetype":"venue"
},
  "geometry": {"coordinates":[-86.92649,38.414988],"type":"Point"}
}