{
  "type": "Feature",
  "properties": {
    "iso:country":"US",
    "sg:address":"1315 N Willow St",
    "sg:city":"Rushville",
    "sg:classifiers":[
        {
            "category":"Retail",
            "subcategory":"Repair Shop",
            "type":"Services"
        }
    ],
    "sg:phone":"+1 765 938 3052",
    "sg:postcode":"46173",
    "sg:province":"IN",
    "sg:tags":[
        "upholsterer"
    ],
    "wof:name":"Dollarhide Upholstery",
    "wof:placetype":"venue"
},
  "geometry": {"coordinates":[-85.442423,39.621596],"type":"Point"}
}