{
  "type": "Feature",
  "properties": {
    "iso:country":"US",
    "sg:address":"1108 5th St",
    "sg:city":"Bedford",
    "sg:classifiers":[
        {
            "category":"Real Estate",
            "subcategory":"Real Estate Agent",
            "type":"Services"
        }
    ],
    "sg:phone":"+1 812 277 1861",
    "sg:postcode":"47421",
    "sg:province":"IN",
    "wof:name":"Bedford Board Of Realtors Inc",
    "wof:placetype":"venue"
},
  "geometry": {"coordinates":[-86.485868,38.874091],"type":"Point"}
}