{
  "type": "Feature",
  "properties": {
    "iso:country":"US",
    "sg:address":"8870 N State Rd 9",
    "sg:city":"Morristown",
    "sg:classifiers":[
        {
            "category":"Farming",
            "subcategory":"Farm",
            "type":"Manufacturing & Wholesale Goods"
        }
    ],
    "sg:phone":"+1 765 763 6602",
    "sg:postcode":"46161",
    "sg:province":"IN",
    "sg:tags":[
        "crop",
        "general"
    ],
    "wof:name":"Pierson Farm",
    "wof:placetype":"venue"
},
  "geometry": {"coordinates":[-85.77275299999999,39.653919],"type":"Point"}
}