{
  "type": "Feature",
  "properties": {
    "addr:full":"806 W 4th St Mt Vernon IN 47620",
    "addr:housenumber":"806",
    "addr:postcode":"47620",
    "addr:street":"W 4Th St",
    "iso:country":"US",
    "sg:address":"806 W 4th St",
    "sg:city":"Mt Vernon",
    "sg:classifiers":[
        {
            "category":"Autos & Motor Vehicles",
            "subcategory":"Auto Supplies",
            "type":"Retail Goods"
        }
    ],
    "sg:phone":"+1 812 838 4074",
    "sg:postcode":"47620",
    "sg:province":"IN",
    "sg:tags":[
        "automobile",
        "stereo",
        "radio"
    ],
    "wof:name":"Tom's CB Sales",
    "wof:placetype":"venue"
},
  "geometry": {"coordinates":[-87.90428900000001,37.929851],"type":"Point"}
}