{
  "type": "Feature",
  "properties": {
    "iso:country":"US",
    "sg:address":"734 Saratoga Dr",
    "sg:city":"Jeffersonville",
    "sg:classifiers":[
        {
            "category":"Building & Trades",
            "subcategory":"Construction",
            "type":"Services"
        }
    ],
    "sg:phone":"+1 812 288 8475",
    "sg:postcode":"47130",
    "sg:province":"IN",
    "sg:tags":[
        "carpentry",
        "contractor"
    ],
    "wof:name":"Brooks Trim Carpentry",
    "wof:placetype":"venue"
},
  "geometry": {"coordinates":[-85.685655,38.306768],"type":"Point"}
}