{
  "type": "Feature",
  "properties": {
    "addr:full":"3936 Franklin St Michigan City IN 46360",
    "addr:housenumber":"3936",
    "addr:postcode":"46360",
    "addr:street":"Franklin St",
    "iso:country":"US",
    "sg:address":"3936 Franklin St",
    "sg:city":"Michigan City",
    "sg:classifiers":[
        {
            "category":"Restaurant",
            "type":"Food & Drink"
        }
    ],
    "sg:menulink":"http://www.allmenus.com/in/coolspring/208088-taco-bell/menu/",
    "sg:phone":"+1 219 879 4022",
    "sg:postcode":"46360",
    "sg:province":"IN",
    "sg:tags":[
        "mexican"
    ],
    "wof:name":"Taco Bell",
    "wof:placetype":"venue"
},
  "geometry": {"coordinates":[-86.89388099999999,41.682699],"type":"Point"}
}