{
  "type": "Feature",
  "properties": {
    "iso:country":"US",
    "sg:address":"115 W Jefferson St",
    "sg:city":"Goshen",
    "sg:classifiers":[
        {
            "category":"Home & Garden",
            "subcategory":"Furniture",
            "type":"Retail Goods"
        }
    ],
    "sg:phone":"+1 574 534 5000",
    "sg:postcode":"46526",
    "sg:province":"IN",
    "wof:name":"Home Again",
    "wof:placetype":"venue"
},
  "geometry": {"coordinates":[-85.835092,41.58376],"type":"Point"}
}