{
  "type": "Feature",
  "properties": {
    "iso:country":"US",
    "sg:address":"1944 E Southport Rd",
    "sg:city":"Indianapolis",
    "sg:classifiers":[
        {
            "category":"Personal",
            "subcategory":"Barber",
            "type":"Services"
        }
    ],
    "sg:phone":"+1 317 784 9245",
    "sg:postcode":"46227",
    "sg:province":"IN",
    "sg:tags":[
        "shop"
    ],
    "wof:name":"Larry's Barber Shop",
    "wof:placetype":"venue"
},
  "geometry": {"coordinates":[-86.125157,39.665021],"type":"Point"}
}