{
  "type": "Feature",
  "properties": {
    "iso:country":"US",
    "sg:address":"9 Edwards Ct",
    "sg:city":"Beech Grove",
    "sg:classifiers":[
        {
            "category":"Building & Trades",
            "subcategory":"Construction",
            "type":"Services"
        }
    ],
    "sg:phone":"+1 317 787 0612",
    "sg:postcode":"46107",
    "sg:province":"IN",
    "sg:tags":[
        "concrete",
        "contractor"
    ],
    "wof:name":"Concrete Works Inc",
    "wof:placetype":"venue"
},
  "geometry": {"coordinates":[-86.08818599999999,39.705201],"type":"Point"}
}