{
  "type": "Feature",
  "properties": {
    "addr:full":"103 E Main St Odon IN 47562",
    "addr:housenumber":"103",
    "addr:postcode":"47562",
    "addr:street":"E Main St",
    "iso:country":"US",
    "sg:address":"103 E Main St",
    "sg:city":"Odon",
    "sg:classifiers":[
        {
            "category":"Home & Garden",
            "subcategory":"Household Appliances",
            "type":"Retail Goods"
        }
    ],
    "sg:phone":"+1 812 636 7547",
    "sg:postcode":"47562",
    "sg:province":"IN",
    "wof:name":"Clark Heating & Cooling",
    "wof:placetype":"venue"
},
  "geometry": {"coordinates":[-86.991201,38.842583],"type":"Point"}
}