{
  "type": "Feature",
  "properties": {
    "iso:country":"US",
    "sg:address":"803 N 3rd St",
    "sg:city":"Vincennes",
    "sg:classifiers":[
        {
            "category":"Restaurant",
            "type":"Food & Drink"
        }
    ],
    "sg:phone":"+1 812 882 9464",
    "sg:postcode":"47591",
    "sg:province":"IN",
    "wof:name":"Wingers",
    "wof:placetype":"venue"
},
  "geometry": {"coordinates":[-87.523354,38.683471],"type":"Point"}
}