{
  "type": "Feature",
  "properties": {
    "iso:country":"US",
    "sg:address":"809 S Calhoun St",
    "sg:city":"Fort Wayne",
    "sg:classifiers":[
        {
            "category":"Banks & Credit Unions",
            "subcategory":"Bank",
            "type":"Services"
        }
    ],
    "sg:phone":"+1 260 424 6644",
    "sg:postcode":"46802",
    "sg:province":"IN",
    "sg:tags":[
        "mortgage"
    ],
    "wof:name":"Bank of America Mortgage",
    "wof:placetype":"venue"
},
  "geometry": {"coordinates":[-85.139278,41.078353],"type":"Point"}
}