{
  "type": "Feature",
  "properties": {
    "addr:full":"1950 Ridgedale Rd South Bend IN 46614",
    "addr:housenumber":"1950",
    "addr:postcode":"46614",
    "addr:street":"Ridgedale Rd",
    "iso:country":"US",
    "sg:address":"1950 Ridgedale Rd",
    "sg:city":"South Bend",
    "sg:classifiers":[
        {
            "category":"Health Services",
            "subcategory":"Nursing And Care Facility",
            "type":"Services"
        }
    ],
    "sg:phone":"+1 574 291 6722",
    "sg:postcode":"46614",
    "sg:province":"IN",
    "sg:tags":[
        "home",
        "convalescent"
    ],
    "wof:name":"Ironwood Health & Rehab Ctr",
    "wof:placetype":"venue"
},
  "geometry": {"coordinates":[-86.217082,41.644039],"type":"Point"}
}