{
  "type": "Feature",
  "properties": {
    "iso:country":"US",
    "sg:address":"2010 S P St",
    "sg:city":"Elwood",
    "sg:classifiers":[
        {
            "category":"Building & Trades",
            "subcategory":"Construction",
            "type":"Services"
        }
    ],
    "sg:phone":"+1 765 552 3990",
    "sg:postcode":"46036",
    "sg:province":"IN",
    "sg:tags":[
        "general",
        "contractor"
    ],
    "wof:name":"Virgil Green & Sons Inc",
    "wof:placetype":"venue"
},
  "geometry": {"coordinates":[-85.835552,40.262597],"type":"Point"}
}