{
  "type": "Feature",
  "properties": {
    "iso:country":"US",
    "sg:address":"101 W Van Buren St",
    "sg:city":"Columbia City",
    "sg:classifiers":[
        {
            "category":"Government",
            "subcategory":"Office",
            "type":"Public Place"
        }
    ],
    "sg:phone":"+1 260 248 3110",
    "sg:postcode":"46725",
    "sg:province":"IN",
    "sg:tags":[
        "city",
        "taxation"
    ],
    "wof:name":"Columbia Twp Assessor",
    "wof:placetype":"venue"
},
  "geometry": {"coordinates":[-85.489818,41.157022],"type":"Point"}
}