{
  "type": "Feature",
  "properties": {
    "iso:country":"US",
    "sg:address":"2 W Seminary St",
    "sg:city":"Greencastle",
    "sg:classifiers":[
        {
            "category":"Travel",
            "subcategory":"Hotels & Motels",
            "type":"Entertainment"
        }
    ],
    "sg:phone":"+1 765 653 2761",
    "sg:postcode":"46135",
    "sg:province":"IN",
    "sg:website":"www.waldeninn.com",
    "wof:name":"Walden Inn",
    "wof:placetype":"venue"
},
  "geometry": {"coordinates":[-86.865431,39.641808],"type":"Point"}
}