{
  "type": "Feature",
  "properties": {
    "iso:country":"US",
    "sg:address":"115 N West St",
    "sg:city":"Lebanon",
    "sg:classifiers":[
        {
            "category":"Retail",
            "subcategory":"Repair Shop",
            "type":"Services"
        }
    ],
    "sg:phone":"+1 765 482 3211",
    "sg:postcode":"46052",
    "sg:province":"IN",
    "wof:name":"Treva J Iddings",
    "wof:placetype":"venue"
},
  "geometry": {"coordinates":[-86.470315,40.047889],"type":"Point"}
}