{
  "type": "Feature",
  "properties": {
    "iso:country":"US",
    "sg:address":"2510 N Morton St",
    "sg:city":"Franklin",
    "sg:classifiers":[
        {
            "category":"Organizations",
            "subcategory":"Religious Organization",
            "type":"Services"
        }
    ],
    "sg:phone":"+1 317 738 5922",
    "sg:postcode":"46131",
    "sg:province":"IN",
    "wof:name":"Kingdom Hall Jehovahs Witness",
    "wof:placetype":"venue"
},
  "geometry": {"coordinates":[-86.07111399999999,39.50867],"type":"Point"}
}