{
  "type": "Feature",
  "properties": {
    "iso:country":"US",
    "sg:address":"109 W Whitley St",
    "sg:city":"Churubusco",
    "sg:classifiers":[
        {
            "category":"Restaurant",
            "type":"Food & Drink"
        }
    ],
    "sg:phone":"+1 260 693 9607",
    "sg:postcode":"46723",
    "sg:province":"IN",
    "sg:tags":[
        "tea",
        "rooms"
    ],
    "wof:name":"Simple Pleasures Remembered",
    "wof:placetype":"venue"
},
  "geometry": {"coordinates":[-85.319312,41.230496],"type":"Point"}
}