{
  "type": "Feature",
  "properties": {
    "iso:country":"US",
    "sg:address":"106 W 6th St",
    "sg:city":"Auburn",
    "sg:classifiers":[
        {
            "category":"Shopping",
            "subcategory":"Used Merchandise",
            "type":"Retail Goods"
        }
    ],
    "sg:phone":"+1 260 925 3433",
    "sg:postcode":"46706",
    "sg:province":"IN",
    "sg:tags":[
        "antique"
    ],
    "wof:name":"Sixthstreet Emporium",
    "wof:placetype":"venue"
},
  "geometry": {"coordinates":[-85.055937,41.367538],"type":"Point"}
}