{
  "type": "Feature",
  "properties": {
    "iso:country":"US",
    "sg:address":"325 S Oak St",
    "sg:city":"Winchester",
    "sg:classifiers":[
        {
            "category":"Government",
            "subcategory":"Office",
            "type":"Public Place"
        }
    ],
    "sg:phone":"+1 765 584 0609",
    "sg:postcode":"47394",
    "sg:province":"IN",
    "wof:name":"Randolph County Surveyor",
    "wof:placetype":"venue"
},
  "geometry": {"coordinates":[-84.973356,40.170105],"type":"Point"}
}