{
  "type": "Feature",
  "properties": {
    "iso:country":"US",
    "sg:address":"2425 Sherman St",
    "sg:city":"Evansville",
    "sg:classifiers":[
        {
            "category":"Home & Garden",
            "subcategory":"Building Materials",
            "type":"Retail Goods"
        }
    ],
    "sg:phone":"+1 812 424 2901",
    "sg:postcode":"47711",
    "sg:province":"IN",
    "sg:tags":[
        "door"
    ],
    "wof:name":"BSH Of Evansville",
    "wof:placetype":"venue"
},
  "geometry": {"coordinates":[-87.55491600000001,38.000617],"type":"Point"}
}