{
  "type": "Feature",
  "properties": {
    "iso:country":"US",
    "sg:address":"8137 Franke Rd",
    "sg:city":"Fort Wayne",
    "sg:classifiers":[
        {
            "category":"Home & Garden",
            "subcategory":"Garden Supply",
            "type":"Retail Goods"
        }
    ],
    "sg:phone":"+1 260 623 6134",
    "sg:postcode":"46816",
    "sg:province":"IN",
    "sg:tags":[
        "fertilizer"
    ],
    "wof:name":"Maples AG Concepts",
    "wof:placetype":"venue"
},
  "geometry": {"coordinates":[-84.9694,41.014241],"type":"Point"}
}