{
  "type": "Feature",
  "properties": {
    "iso:country":"US",
    "sg:address":"574 W Co Rd 725 S",
    "sg:city":"Lewisville",
    "sg:classifiers":[
        {
            "category":"Building & Trades",
            "subcategory":"Cleaning & Sanitation",
            "type":"Services"
        }
    ],
    "sg:phone":"+1 765 987 8824",
    "sg:postcode":"47352",
    "sg:province":"IN",
    "sg:tags":[
        "fireplace",
        "chimney"
    ],
    "wof:name":"Top Hat & Brush Chimney Sweep",
    "wof:placetype":"venue"
},
  "geometry": {"coordinates":[-85.399531,39.827351],"type":"Point"}
}