{
  "type": "Feature",
  "properties": {
    "iso:country":"US",
    "sg:address":"9405 Kleinman Rd",
    "sg:city":"Highland",
    "sg:classifiers":[
        {
            "category":"Social Services",
            "type":"Services"
        }
    ],
    "sg:phone":"+1 219 924 2237",
    "sg:postcode":"46322",
    "sg:province":"IN",
    "sg:tags":[
        "counselor",
        "marriage",
        "family"
    ],
    "wof:name":"Fathers United Of Indiana Inc",
    "wof:placetype":"venue"
},
  "geometry": {"coordinates":[-87.43726100000001,41.542719],"type":"Point"}
}