{
  "type": "Feature",
  "properties": {
    "iso:country":"US",
    "sg:address":"3822 S Calhoun St",
    "sg:city":"Fort Wayne",
    "sg:classifiers":[
        {
            "category":"Shopping",
            "subcategory":"Clothing, Apparel, & Fashions",
            "type":"Retail Goods"
        }
    ],
    "sg:phone":"+1 260 745 7291",
    "sg:postcode":"46807",
    "sg:province":"IN",
    "wof:name":"Weekend",
    "wof:placetype":"venue"
},
  "geometry": {"coordinates":[-85.137473,41.051134],"type":"Point"}
}