{
  "type": "Feature",
  "properties": {
    "iso:country":"US",
    "sg:address":"971 W 500 N",
    "sg:city":"Whiteland",
    "sg:classifiers":[
        {
            "category":"Education",
            "subcategory":"Special Training",
            "type":"Public Place"
        }
    ],
    "sg:phone":"+1 317 535 8489",
    "sg:postcode":"46184",
    "sg:province":"IN",
    "wof:name":"Shady Oaks Studio",
    "wof:placetype":"venue"
},
  "geometry": {"coordinates":[-86.13234,39.54902],"type":"Point"}
}