{
  "type": "Feature",
  "properties": {
    "iso:country":"US",
    "sg:address":"13522 N 200 E",
    "sg:city":"North Manchester",
    "sg:classifiers":[
        {
            "category":"Government",
            "subcategory":"Office",
            "type":"Public Place"
        }
    ],
    "sg:phone":"+1 260 982 2287",
    "sg:postcode":"46962",
    "sg:province":"IN",
    "sg:tags":[
        "village"
    ],
    "wof:name":"Chester Twp Trustee",
    "wof:placetype":"venue"
},
  "geometry": {"coordinates":[-85.760876,41.023536],"type":"Point"}
}