{
  "type": "Feature",
  "properties": {
    "iso:country":"US",
    "sg:address":"4629 S State Rd 9",
    "sg:city":"Shelbyville",
    "sg:classifiers":[
        {
            "category":"Professional",
            "type":"Services"
        }
    ],
    "sg:phone":"+1 317 398 6829",
    "sg:postcode":"46176",
    "sg:province":"IN",
    "wof:name":"1st Choice Closing Service",
    "wof:placetype":"venue"
},
  "geometry": {"coordinates":[-85.761445,39.460813],"type":"Point"}
}