{
  "type": "Feature",
  "properties": {
    "addr:full":"53066 Lily Creek Dr Elkhart IN 46514",
    "addr:housenumber":"53066",
    "addr:postcode":"46514",
    "addr:street":"Lily Creek Dr",
    "iso:country":"US",
    "sg:address":"53066 Lily Creek Dr",
    "sg:city":"Elkhart",
    "sg:classifiers":[
        {
            "category":"Food & Beverages",
            "subcategory":"Groceries & Convenience Stores",
            "type":"Retail Goods"
        }
    ],
    "sg:phone":"+1 574 266 6173",
    "sg:postcode":"46514",
    "sg:province":"IN",
    "wof:name":"EAK Inc",
    "wof:placetype":"venue"
},
  "geometry": {"coordinates":[-85.96463900000001,41.722626],"type":"Point"}
}