{
  "type": "Feature",
  "properties": {
    "iso:country":"US",
    "sg:address":"5420 W Southern Ave",
    "sg:city":"Indianapolis",
    "sg:classifiers":[
        {
            "category":"Insurance",
            "subcategory":"Insurance Agent",
            "type":"Services"
        }
    ],
    "sg:phone":"+1 317 487 1970",
    "sg:postcode":"46241",
    "sg:province":"IN",
    "sg:website":"www.autoowners.com",
    "wof:name":"Auto-Owners Mutual Ins Co",
    "wof:placetype":"venue"
},
  "geometry": {"coordinates":[-86.254417,39.728128],"type":"Point"}
}