{
  "type": "Feature",
  "properties": {
    "iso:country":"US",
    "sg:address":"30 N 8th St",
    "sg:city":"Terre Haute",
    "sg:classifiers":[
        {
            "category":"Government",
            "subcategory":"Office",
            "type":"Public Place"
        }
    ],
    "sg:phone":"+1 812 232 7864",
    "sg:postcode":"47807",
    "sg:province":"IN",
    "sg:tags":[
        "state",
        "program"
    ],
    "wof:name":"Vocational Rehabilitation Div",
    "wof:placetype":"venue"
},
  "geometry": {"coordinates":[-87.405819,39.46744],"type":"Point"}
}