{
  "type": "Feature",
  "properties": {
    "addr:full":"325 S Gardener St Scottsburg IN 47170",
    "addr:housenumber":"325",
    "addr:postcode":"47170",
    "addr:street":"S Gardener St",
    "iso:country":"US",
    "sg:address":"325 S Gardener St",
    "sg:city":"Scottsburg",
    "sg:classifiers":[
        {
            "category":"Food & Beverages",
            "subcategory":"Bakery",
            "type":"Retail Goods"
        }
    ],
    "sg:phone":"+1 812 752 5198",
    "sg:postcode":"47170",
    "sg:province":"IN",
    "sg:tags":[
        "doughnut"
    ],
    "wof:name":"Lon's Donut Shop",
    "wof:placetype":"venue"
},
  "geometry": {"coordinates":[-85.77827600000001,38.682961],"type":"Point"}
}