{
  "type": "Feature",
  "properties": {
    "iso:country":"US",
    "sg:address":"1750 Maple Turn Rd",
    "sg:city":"Martinsville",
    "sg:classifiers":[
        {
            "category":"Sports & Exercise",
            "subcategory":"Golf",
            "type":"Entertainment"
        }
    ],
    "sg:phone":"+1 765 342 0409",
    "sg:postcode":"46151",
    "sg:province":"IN",
    "sg:tags":[
        "course"
    ],
    "wof:name":"Foxcliff Golf Course",
    "wof:placetype":"venue"
},
  "geometry": {"coordinates":[-86.391467,39.476911],"type":"Point"}
}