{
  "type": "Feature",
  "properties": {
    "addr:full":"3582 Village Ct Gary IN 46408",
    "addr:housenumber":"3582",
    "addr:postcode":"46408",
    "addr:street":"Village Ct",
    "iso:country":"US",
    "sg:address":"3582 Village Ct",
    "sg:city":"Gary",
    "sg:classifiers":[
        {
            "category":"Shopping",
            "subcategory":"Computers & Home Electronics",
            "type":"Retail Goods"
        }
    ],
    "sg:phone":"+1 219 887 0264",
    "sg:postcode":"46408",
    "sg:province":"IN",
    "sg:tags":[
        "equipment",
        "electronic",
        "supply"
    ],
    "wof:name":"Radio Shack",
    "wof:placetype":"venue"
},
  "geometry": {"coordinates":[-87.355974,41.554648],"type":"Point"}
}