{
  "type": "Feature",
  "properties": {
    "iso:country":"US",
    "sg:address":"248 S Main St",
    "sg:city":"Clinton",
    "sg:classifiers":[
        {
            "category":"Organizations",
            "subcategory":"Community Association",
            "type":"Services"
        }
    ],
    "sg:phone":"+1 765 832 5183",
    "sg:postcode":"47842",
    "sg:province":"IN",
    "sg:tags":[
        "military"
    ],
    "wof:name":"American Legion",
    "wof:placetype":"venue"
},
  "geometry": {"coordinates":[-87.398218,39.658824],"type":"Point"}
}