{
  "type": "Feature",
  "properties": {
    "iso:country":"US",
    "sg:address":"4505 Redstone Ct",
    "sg:city":"Fort Wayne",
    "sg:classifiers":[
        {
            "category":"Professional",
            "subcategory":"Business Services",
            "type":"Services"
        }
    ],
    "sg:phone":"+1 260 486 8225",
    "sg:postcode":"46835",
    "sg:province":"IN",
    "wof:name":"David A Dilts",
    "wof:placetype":"venue"
},
  "geometry": {"coordinates":[-85.036996,41.122911],"type":"Point"}
}