{
  "type": "Feature",
  "properties": {
    "iso:country":"US",
    "sg:address":"904 Vega Dr",
    "sg:city":"Flora",
    "sg:classifiers":[
        {
            "category":"Professional",
            "subcategory":"Business Services",
            "type":"Services"
        }
    ],
    "sg:phone":"+1 574 967 4925",
    "sg:postcode":"46929",
    "sg:province":"IN",
    "wof:name":"Wagoner Enterprises Ltd P",
    "wof:placetype":"venue"
},
  "geometry": {"coordinates":[-86.507851,40.545004],"type":"Point"}
}