{
  "type": "Feature",
  "properties": {
    "iso:country":"US",
    "sg:address":"2152 S Co Rd 200 W",
    "sg:city":"Rockport",
    "sg:classifiers":[
        {
            "category":"Travel",
            "subcategory":"Hotels & Motels",
            "type":"Entertainment"
        }
    ],
    "sg:phone":"+1 812 649 9579",
    "sg:postcode":"47635",
    "sg:province":"IN",
    "sg:tags":[
        "breakfast",
        "accommodation",
        "bed"
    ],
    "wof:name":"Friendly Farms Bed & Breakfast",
    "wof:placetype":"venue"
},
  "geometry": {"coordinates":[-87.092204,37.857769],"type":"Point"}
}