{
  "type": "Feature",
  "properties": {
    "addr:full":"7318 Thornmill Ct Avon IN 46123",
    "addr:housenumber":"7318",
    "addr:postcode":"46123",
    "addr:street":"Thornmill Ct",
    "iso:country":"US",
    "sg:address":"7318 Thornmill Ct",
    "sg:city":"Avon",
    "sg:classifiers":[
        {
            "category":"Professional",
            "subcategory":"Computer Services",
            "type":"Services"
        }
    ],
    "sg:phone":"+1 317 439 0849",
    "sg:postcode":"46123",
    "sg:province":"IN",
    "sg:tags":[
        "home",
        "consulting",
        "page",
        "dev",
        "internet"
    ],
    "sg:website":"www.sterlyn-group.com",
    "wof:name":"Sterlyn Group Inc",
    "wof:placetype":"venue"
},
  "geometry": {"coordinates":[-86.39440500000001,39.749241],"type":"Point"}
}