{
  "type": "Feature",
  "properties": {
    "iso:country":"US",
    "sg:address":"801 Uhlhorn St",
    "sg:city":"Evansville",
    "sg:classifiers":[
        {
            "category":"Professional",
            "type":"Services"
        }
    ],
    "sg:phone":"+1 812 421 0995",
    "sg:postcode":"47710",
    "sg:province":"IN",
    "sg:tags":[
        "establishment"
    ],
    "wof:name":"Pigeon Creek Greenway Passage",
    "wof:placetype":"venue"
},
  "geometry": {"coordinates":[-87.577118,37.99516],"type":"Point"}
}