{
  "type": "Feature",
  "properties": {
    "addr:full":"6916 S Maddox Pl Terre Haute IN 47802",
    "addr:housenumber":"6916",
    "addr:postcode":"47802",
    "addr:street":"S Maddox Pl",
    "iso:country":"US",
    "sg:address":"6916 S Maddox Pl",
    "sg:city":"Terre Haute",
    "sg:classifiers":[
        {
            "category":"Organizations",
            "subcategory":"Religious Organization",
            "type":"Services"
        }
    ],
    "sg:phone":"+1 812 299 4202",
    "sg:postcode":"47802",
    "sg:province":"IN",
    "wof:name":"Pentecostal House of Pray",
    "wof:placetype":"venue"
},
  "geometry": {"coordinates":[-87.451843,39.380311],"type":"Point"}
}