{
  "type": "Feature",
  "properties": {
    "iso:country":"US",
    "sg:address":"220 Clifty Dr",
    "sg:city":"Madison",
    "sg:classifiers":[
        {
            "category":"Professional",
            "subcategory":"Business Services",
            "type":"Services"
        }
    ],
    "sg:phone":"+1 812 265 2143",
    "sg:postcode":"47250",
    "sg:province":"IN",
    "sg:tags":[
        "packaging"
    ],
    "wof:name":"Mailboxes & Parcel Depot",
    "wof:placetype":"venue"
},
  "geometry": {"coordinates":[-85.390162,38.775175],"type":"Point"}
}