{
  "type": "Feature",
  "properties": {
    "addr:full":"7052 E 250 N Rushville IN 46173",
    "addr:housenumber":"7052",
    "addr:postcode":"46173",
    "addr:street":"E 250 N Rushville",
    "iso:country":"US",
    "sg:address":"7052 E 250 N",
    "sg:city":"Rushville",
    "sg:classifiers":[
        {
            "category":"Professional",
            "subcategory":"Employment Agencies",
            "type":"Services"
        }
    ],
    "sg:phone":"+1 765 679 1505",
    "sg:postcode":"46173",
    "sg:province":"IN",
    "sg:tags":[
        "consultant"
    ],
    "wof:name":"Sheridan Quinn",
    "wof:placetype":"venue"
},
  "geometry": {"coordinates":[-85.31858,39.648846],"type":"Point"}
}