{
  "type": "Feature",
  "properties": {
    "iso:country":"US",
    "sg:address":"20 N State St",
    "sg:city":"Greenfield",
    "sg:classifiers":[
        {
            "category":"Professional",
            "subcategory":"Business Services",
            "type":"Services"
        }
    ],
    "sg:phone":"+1 317 468 1733",
    "sg:postcode":"46140",
    "sg:province":"IN",
    "sg:tags":[
        "auctioneer"
    ],
    "wof:name":"Craney & Co Auction & Apraisal",
    "wof:placetype":"venue"
},
  "geometry": {"coordinates":[-85.769451,39.785974],"type":"Point"}
}