{
  "type": "Feature",
  "properties": {
    "iso:country":"US",
    "sg:address":"1209 W 2nd St",
    "sg:city":"Bloomington",
    "sg:classifiers":[
        {
            "category":"Autos & Motor Vehicles",
            "subcategory":"Automobile Sales",
            "type":"Retail Goods"
        }
    ],
    "sg:phone":"+1 812 332 3740",
    "sg:postcode":"47403",
    "sg:province":"IN",
    "sg:tags":[
        "car",
        "dealer"
    ],
    "wof:name":"R & S Auto Sales",
    "wof:placetype":"venue"
},
  "geometry": {"coordinates":[-86.55067200000001,39.160307],"type":"Point"}
}