{
  "type": "Feature",
  "properties": {
    "addr:full":"3105 N Blanton Rd Scottsburg IN 47170",
    "addr:housenumber":"3105",
    "addr:postcode":"47170",
    "addr:street":"N Blanton Rd",
    "iso:country":"US",
    "sg:address":"3105 N Blanton Rd",
    "sg:city":"Scottsburg",
    "sg:classifiers":[
        {
            "category":"Building & Trades",
            "subcategory":"Construction",
            "type":"Services"
        }
    ],
    "sg:phone":"+1 812 794 3374",
    "sg:postcode":"47170",
    "sg:province":"IN",
    "sg:tags":[
        "general",
        "contractor"
    ],
    "wof:name":"Hargett Contracting & Design",
    "wof:placetype":"venue"
},
  "geometry": {"coordinates":[-85.692875,38.744429],"type":"Point"}
}