{
  "type": "Feature",
  "properties": {
    "iso:country":"US",
    "sg:address":"620 W Berry St",
    "sg:city":"Fort Wayne",
    "sg:classifiers":[
        {
            "category":"Health Services",
            "subcategory":"Doctor",
            "type":"Services"
        }
    ],
    "sg:phone":"+1 260 424 6311",
    "sg:postcode":"46802",
    "sg:province":"IN",
    "sg:tags":[
        "physician",
        "surgeon"
    ],
    "wof:name":"Larry Bledsoe DO",
    "wof:placetype":"venue"
},
  "geometry": {"coordinates":[-85.148354,41.078001],"type":"Point"}
}