{
  "type": "Feature",
  "properties": {
    "iso:country":"US",
    "sg:address":"106 S Holland St",
    "sg:city":"Edinburgh",
    "sg:classifiers":[
        {
            "category":"Social Services",
            "type":"Services"
        }
    ],
    "sg:phone":"+1 812 526 5013",
    "sg:postcode":"46124",
    "sg:province":"IN",
    "sg:tags":[
        "organization",
        "welfare"
    ],
    "wof:name":"Edinburgh Senior Citizens Inc",
    "wof:placetype":"venue"
},
  "geometry": {"coordinates":[-85.965494,39.354256],"type":"Point"}
}