{
  "type": "Feature",
  "properties": {
    "iso:country":"US",
    "sg:address":"240 Growth Pkwy",
    "sg:city":"Angola",
    "sg:classifiers":[
        {
            "category":"Manufacturing",
            "subcategory":"Tools & Machinery",
            "type":"Manufacturing & Wholesale Goods"
        }
    ],
    "sg:phone":"+1 260 624 3123",
    "sg:postcode":"46703",
    "sg:province":"IN",
    "sg:tags":[
        "die",
        "maker"
    ],
    "wof:name":"C & K Tool",
    "wof:placetype":"venue"
},
  "geometry": {"coordinates":[-85.001585,41.665972],"type":"Point"}
}