{
  "type": "Feature",
  "properties": {
    "iso:country":"US",
    "sg:address":"405 S Meridian St",
    "sg:city":"Holland",
    "sg:classifiers":[
        {
            "category":"Banks & Credit Unions",
            "subcategory":"Bank",
            "type":"Services"
        }
    ],
    "sg:phone":"+1 812 536 3131",
    "sg:postcode":"47541",
    "sg:province":"IN",
    "wof:name":"German American Bank",
    "wof:placetype":"venue"
},
  "geometry": {"coordinates":[-87.035934,38.244135],"type":"Point"}
}