{
  "type": "Feature",
  "properties": {
    "addr:full":"9801 W 225 S Columbus IN 47201",
    "addr:housenumber":"9801",
    "addr:postcode":"47201",
    "addr:street":"W 225 S",
    "iso:country":"US",
    "sg:address":"9801 W 225 S",
    "sg:city":"Columbus",
    "sg:classifiers":[
        {
            "category":"Building & Trades",
            "subcategory":"Electrical",
            "type":"Services"
        }
    ],
    "sg:phone":"+1 812 342 9696",
    "sg:postcode":"47201",
    "sg:province":"IN",
    "sg:tags":[
        "electrical",
        "contractor"
    ],
    "wof:name":"Matthews Systems",
    "wof:placetype":"venue"
},
  "geometry": {"coordinates":[-86.026611,39.164969],"type":"Point"}
}