{
  "type": "Feature",
  "properties": {
    "addr:full":"135 S Chauncey Ave West Lafayette IN 47906",
    "addr:housenumber":"135",
    "addr:postcode":"47906",
    "addr:street":"S Chauncey Ave",
    "iso:country":"US",
    "sg:address":"135 S Chauncey Ave",
    "sg:city":"West Lafayette",
    "sg:classifiers":[
        {
            "category":"Restaurant",
            "type":"Food & Drink"
        }
    ],
    "sg:menulink":"http://www.allmenus.com/in/wabash/18847-the-pita-pit/menu/",
    "sg:phone":"+1 765 743 8743",
    "sg:postcode":"47906",
    "sg:province":"IN",
    "sg:tags":[
        "salad",
        "soup",
        "eastern",
        "mediterranean",
        "middle",
        "american",
        "greek",
        "pita"
    ],
    "wof:name":"The Pita Pit",
    "wof:placetype":"venue"
},
  "geometry": {"coordinates":[-86.906943,40.424263],"type":"Point"}
}