{
  "type": "Feature",
  "properties": {
    "iso:country":"US",
    "sg:address":"214 W Water St",
    "sg:city":"Newburgh",
    "sg:classifiers":[
        {
            "category":"Organizations",
            "subcategory":"Membership Organization",
            "type":"Services"
        }
    ],
    "sg:phone":"+1 812 853 8985",
    "sg:postcode":"47630",
    "sg:province":"IN",
    "sg:tags":[
        "personal",
        "interest"
    ],
    "wof:name":"Martys Inc",
    "wof:placetype":"venue"
},
  "geometry": {"coordinates":[-87.409441,37.94484],"type":"Point"}
}