{
  "type": "Feature",
  "properties": {
    "addr:full":"1117 E Main St Richmond IN 47374",
    "addr:housenumber":"1117",
    "addr:postcode":"47374",
    "addr:street":"E Main St",
    "iso:country":"US",
    "sg:address":"1117 E Main St",
    "sg:city":"Richmond",
    "sg:classifiers":[
        {
            "category":"Bars & Pubs",
            "type":"Food & Drink"
        }
    ],
    "sg:phone":"+1 765 962 2706",
    "sg:postcode":"47374",
    "sg:province":"IN",
    "sg:tags":[
        "lounge",
        "cocktail"
    ],
    "wof:name":"Mingles Lounge",
    "wof:placetype":"venue"
},
  "geometry": {"coordinates":[-84.88638400000001,39.829147],"type":"Point"}
}