{
  "type": "Feature",
  "properties": {
    "iso:country":"US",
    "sg:address":"4600 N 13th St",
    "sg:city":"Terre Haute",
    "sg:classifiers":[
        {
            "category":"Manufacturing",
            "subcategory":"Glass & Minerals",
            "type":"Manufacturing & Wholesale Goods"
        }
    ],
    "sg:phone":"+1 812 466 1234",
    "sg:postcode":"47805",
    "sg:province":"IN",
    "sg:tags":[
        "concrete",
        "brick"
    ],
    "wof:name":"Cheetah Building Products",
    "wof:placetype":"venue"
},
  "geometry": {"coordinates":[-87.39796200000001,39.522145],"type":"Point"}
}