{
  "type": "Feature",
  "properties": {
    "iso:country":"US",
    "sg:address":"18001 Wicker Ave",
    "sg:city":"Lowell",
    "sg:phone":"+1 219 696 7822",
    "sg:postcode":"46356",
    "sg:province":"IN",
    "sg:tags":[
        "farm",
        "corn",
        "soybean"
    ],
    "wof:name":"James Hayden",
    "wof:placetype":"venue"
},
  "geometry": {"coordinates":[-87.468497,41.292054],"type":"Point"}
}