{
  "type": "Feature",
  "properties": {
    "iso:country":"US",
    "sg:address":"1122 S Morton St",
    "sg:city":"Bloomington",
    "sg:classifiers":[
        {
            "category":"Retail",
            "subcategory":"Auto Repair",
            "type":"Services"
        }
    ],
    "sg:phone":"+1 812 336 9945",
    "sg:postcode":"47403",
    "sg:province":"IN",
    "sg:tags":[
        "machine",
        "automobile",
        "shop"
    ],
    "wof:name":"Davis Automotive",
    "wof:placetype":"venue"
},
  "geometry": {"coordinates":[-86.536439,39.155108],"type":"Point"}
}