{
  "type": "Feature",
  "properties": {
    "iso:country":"US",
    "sg:address":"1809 Main St",
    "sg:city":"Mt Vernon",
    "sg:classifiers":[
        {
            "category":"Social Services",
            "type":"Services"
        }
    ],
    "sg:phone":"+1 812 838 4429",
    "sg:postcode":"47620",
    "sg:province":"IN",
    "sg:tags":[
        "government"
    ],
    "wof:name":"Family & Children Div",
    "wof:placetype":"venue"
},
  "geometry": {"coordinates":[-87.897139,37.950717],"type":"Point"}
}