{
  "type": "Feature",
  "properties": {
    "iso:country":"US",
    "sg:address":"5330 Washington Ave",
    "sg:city":"Evansville",
    "sg:classifiers":[
        {
            "category":"Retail",
            "subcategory":"Funeral Services",
            "type":"Services"
        }
    ],
    "sg:phone":"+1 812 473 5300",
    "sg:postcode":"47715",
    "sg:province":"IN",
    "sg:tags":[
        "director"
    ],
    "wof:name":"Boone Funeral Homes",
    "wof:placetype":"venue"
},
  "geometry": {"coordinates":[-87.486047,37.962406],"type":"Point"}
}