{
  "type": "Feature",
  "properties": {
    "iso:country":"US",
    "sg:address":"405 E Main St",
    "sg:city":"Vevay",
    "sg:classifiers":[
        {
            "category":"Autos & Motor Vehicles",
            "subcategory":"Auto Supplies",
            "type":"Retail Goods"
        }
    ],
    "sg:phone":"+1 812 427 3103",
    "sg:postcode":"47043",
    "sg:province":"IN",
    "sg:tags":[
        "automobile",
        "parts"
    ],
    "wof:name":"East End Auto Parts",
    "wof:placetype":"venue"
},
  "geometry": {"coordinates":[-85.06237,38.750071],"type":"Point"}
}