{
  "type": "Feature",
  "properties": {
    "iso:country":"US",
    "sg:address":"1025 E Dupont Rd",
    "sg:city":"Fort Wayne",
    "sg:classifiers":[
        {
            "category":"Food & Beverages",
            "subcategory":"Liquor & Beverages",
            "type":"Retail Goods"
        }
    ],
    "sg:phone":"+1 260 497 8777",
    "sg:postcode":"46825",
    "sg:province":"IN",
    "sg:tags":[
        "alcoholic"
    ],
    "wof:name":"S & V Liquor Inc",
    "wof:placetype":"venue"
},
  "geometry": {"coordinates":[-85.1263,41.178431],"type":"Point"}
}