{
  "type": "Feature",
  "properties": {
    "addr:full":"1605 E 106th St Indianapolis IN 46280",
    "addr:housenumber":"1605",
    "addr:postcode":"46280",
    "addr:street":"E 106Th St",
    "iso:country":"US",
    "sg:address":"1605 E 106th St",
    "sg:city":"Indianapolis",
    "sg:classifiers":[
        {
            "category":"Organizations",
            "subcategory":"Religious Organization",
            "type":"Services"
        }
    ],
    "sg:phone":"+1 317 844 1107",
    "sg:postcode":"46280",
    "sg:province":"IN",
    "sg:website":"www.orchardpark.org",
    "wof:name":"Orchard Park Presbyterian Church",
    "wof:placetype":"venue"
},
  "geometry": {"coordinates":[-86.127899,39.9417],"type":"Point"}
}