{
  "type": "Feature",
  "properties": {
    "iso:country":"US",
    "sg:address":"1005 McCord Rd",
    "sg:city":"Valparaiso",
    "sg:classifiers":[
        {
            "category":"Retail",
            "subcategory":"Photofinishing",
            "type":"Services"
        }
    ],
    "sg:phone":"+1 219 464 8861",
    "sg:postcode":"46383",
    "sg:province":"IN",
    "sg:tags":[
        "photo"
    ],
    "wof:name":"Sew N Sews",
    "wof:placetype":"venue"
},
  "geometry": {"coordinates":[-87.047798,41.481901],"type":"Point"}
}