{
  "type": "Feature",
  "properties": {
    "iso:country":"US",
    "sg:address":"7002 Madison Ave",
    "sg:city":"Indianapolis",
    "sg:classifiers":[
        {
            "category":"Autos & Motor Vehicles",
            "subcategory":"Fuel & Gas Station",
            "type":"Retail Goods"
        }
    ],
    "sg:phone":"+1 317 782 0883",
    "sg:postcode":"46227",
    "sg:province":"IN",
    "sg:website":"http://www.bpamoco.com",
    "wof:name":"Bp Corporation North America Inc.",
    "wof:placetype":"venue"
},
  "geometry": {"coordinates":[-86.127008,39.6649],"type":"Point"}
}