{
  "type": "Feature",
  "properties": {
    "addr:full":"212 Shorewood Dr Valparaiso IN 46385",
    "addr:housenumber":"212",
    "addr:postcode":"46385",
    "addr:street":"Shorewood Dr",
    "iso:country":"US",
    "sg:address":"212 Shorewood Dr",
    "sg:city":"Valparaiso",
    "sg:classifiers":[
        {
            "category":"Professional",
            "subcategory":"Research",
            "type":"Services"
        }
    ],
    "sg:phone":"+1 219 464 4075",
    "sg:postcode":"46385",
    "sg:province":"IN",
    "wof:name":"Ductile Iron Pipe Research",
    "wof:placetype":"venue"
},
  "geometry": {"coordinates":[-87.148613,41.463274],"type":"Point"}
}