{
  "type": "Feature",
  "properties": {
    "iso:country":"US",
    "sg:address":"430 St Clair St",
    "sg:city":"Mooresville",
    "sg:classifiers":[
        {
            "category":"Social Services",
            "subcategory":"Child Care",
            "type":"Services"
        }
    ],
    "sg:phone":"+1 317 834 4722",
    "sg:postcode":"46158",
    "sg:province":"IN",
    "wof:name":"Children's Christian Playhouse",
    "wof:placetype":"venue"
},
  "geometry": {"coordinates":[-86.366023,39.618809],"type":"Point"}
}