{
  "type": "Feature",
  "properties": {
    "addr:full":"251 E Washington Ave Peru IN 46970",
    "addr:housenumber":"251",
    "addr:postcode":"46970",
    "addr:street":"E Washington Ave",
    "iso:country":"US",
    "sg:address":"251 E Washington Ave",
    "sg:city":"Peru",
    "sg:classifiers":[
        {
            "category":"Shopping",
            "subcategory":"Bicycles & Sporting Goods",
            "type":"Retail Goods"
        }
    ],
    "sg:phone":"+1 765 472 7780",
    "sg:postcode":"46970",
    "sg:province":"IN",
    "sg:tags":[
        "gun",
        "gunsmith"
    ],
    "wof:name":"Patriot's Gun Shop",
    "wof:placetype":"venue"
},
  "geometry": {"coordinates":[-86.06286900000001,40.764151],"type":"Point"}
}