{
  "type": "Feature",
  "properties": {
    "addr:full":"1606 Dutch Ln Jeffersonville IN 47130",
    "addr:housenumber":"1606",
    "addr:postcode":"47130",
    "addr:street":"Dutch Ln",
    "iso:country":"US",
    "sg:address":"1606 Dutch Ln",
    "sg:city":"Jeffersonville",
    "sg:classifiers":[
        {
            "category":"Manufacturing",
            "subcategory":"Rubber & Plastics",
            "type":"Manufacturing & Wholesale Goods"
        },
        {
            "category":"Manufacturing",
            "subcategory":"Petroleum Products",
            "type":"Manufacturing & Wholesale Goods"
        },
        {
            "category":"Manufacturing",
            "subcategory":"Paper Products",
            "type":"Manufacturing & Wholesale Goods"
        }
    ],
    "sg:phone":"+1 812 280 7474",
    "sg:postcode":"47130",
    "sg:province":"IN",
    "sg:tags":[
        "plastics-vacuum",
        "plastics-fabricating",
        "plastics-fabrics",
        "plastics-molders",
        "laminations",
        "etc-producers",
        "pressure",
        "film",
        "forming-manufacturers",
        "sheets",
        "decorating",
        "finishing",
        "rods"
    ],
    "sg:website":"http://www.siplastics.com",
    "wof:name":"Southern Indiana Plastics Inc",
    "wof:placetype":"venue"
},
  "geometry": {"coordinates":[-85.741142,38.28899],"type":"Point"}
}