{
  "type": "Feature",
  "properties": {
    "iso:country":"US",
    "sg:address":"12610 Ford Dr",
    "sg:city":"Fishers",
    "sg:classifiers":[
        {
            "category":"Autos & Motor Vehicles",
            "subcategory":"Automobile Sales",
            "type":"Retail Goods"
        }
    ],
    "sg:phone":"+1 317 849 9000",
    "sg:postcode":"46038",
    "sg:province":"IN",
    "sg:tags":[
        "car",
        "dealer"
    ],
    "sg:website":"www.donhindsford.com",
    "wof:name":"Don Hinds Ford",
    "wof:placetype":"venue"
},
  "geometry": {"coordinates":[-86.00630700000001,39.972791],"type":"Point"}
}