{
  "type": "Feature",
  "properties": {
    "addr:full":"10450 E Washington St Indianapolis IN 46229",
    "addr:housenumber":"10450",
    "addr:postcode":"46229",
    "addr:street":"E Washington St",
    "iso:country":"US",
    "sg:address":"10450 E Washington St",
    "sg:city":"Indianapolis",
    "sg:classifiers":[
        {
            "category":"Food & Beverages",
            "subcategory":"Groceries & Convenience Stores",
            "type":"Retail Goods"
        }
    ],
    "sg:phone":"+1 317 895 2245",
    "sg:postcode":"46229",
    "sg:province":"IN",
    "sg:tags":[
        "grocer"
    ],
    "wof:name":"Kroger",
    "wof:placetype":"venue"
},
  "geometry": {"coordinates":[-85.980867,39.775405],"type":"Point"}
}