{
  "type": "Feature",
  "properties": {
    "iso:country":"US",
    "sg:address":"710 E 46th St",
    "sg:city":"Indianapolis",
    "sg:classifiers":[
        {
            "category":"Food & Beverages",
            "subcategory":"Groceries & Convenience Stores",
            "type":"Retail Goods"
        }
    ],
    "sg:phone":"+1 317 925 2768",
    "sg:postcode":"46205",
    "sg:province":"IN",
    "sg:tags":[
        "product"
    ],
    "wof:name":"D's Tasteful Foods",
    "wof:placetype":"venue"
},
  "geometry": {"coordinates":[-86.143882,39.839724],"type":"Point"}
}