{
  "type": "Feature",
  "properties": {
    "iso:country":"US",
    "sg:address":"100 N Saint Joseph Ave",
    "sg:city":"Evansville",
    "sg:classifiers":[
        {
            "category":"Professional",
            "subcategory":"Testing Lab",
            "type":"Services"
        }
    ],
    "sg:phone":"+1 812 421 0692",
    "sg:postcode":"47712",
    "sg:province":"IN",
    "sg:tags":[
        "laboratory"
    ],
    "wof:name":"CSA Holdings",
    "wof:placetype":"venue"
},
  "geometry": {"coordinates":[-87.60055699999999,37.979609],"type":"Point"}
}