{
  "type": "Feature",
  "properties": {
    "iso:country":"US",
    "sg:address":"4313 S 125 W",
    "sg:city":"Tipton",
    "sg:classifiers":[
        {
            "category":"Building & Trades",
            "subcategory":"Construction",
            "type":"Services"
        }
    ],
    "sg:phone":"+1 765 675 7073",
    "sg:postcode":"46072",
    "sg:province":"IN",
    "sg:tags":[
        "clearing",
        "land",
        "leveling"
    ],
    "wof:name":"B & B Earthworks",
    "wof:placetype":"venue"
},
  "geometry": {"coordinates":[-86.036356,40.242384],"type":"Point"}
}