{
  "type": "Feature",
  "properties": {
    "iso:country":"US",
    "sg:address":"1400 S Nebo Rd",
    "sg:city":"Yorktown",
    "sg:classifiers":[
        {
            "category":"Restaurant",
            "type":"Food & Drink"
        }
    ],
    "sg:phone":"+1 765 254 1397",
    "sg:postcode":"47396",
    "sg:province":"IN",
    "sg:website":"www.mcdonalds.com",
    "wof:name":"Mc Donald's",
    "wof:placetype":"venue"
},
  "geometry": {"coordinates":[-85.461762,40.175032],"type":"Point"}
}