{
  "type": "Feature",
  "properties": {
    "iso:country":"US",
    "sg:address":"4015 N Home St",
    "sg:city":"Mishawaka",
    "sg:classifiers":[
        {
            "category":"Building & Trades",
            "subcategory":"Construction",
            "type":"Services"
        }
    ],
    "sg:phone":"+1 574 252 7719",
    "sg:postcode":"46545",
    "sg:province":"IN",
    "sg:tags":[
        "downspouts",
        "gutter"
    ],
    "wof:name":"Vanderheyden Eavestrough Inc",
    "wof:placetype":"venue"
},
  "geometry": {"coordinates":[-86.149766,41.695951],"type":"Point"}
}