{
  "type": "Feature",
  "properties": {
    "iso:country":"US",
    "sg:address":"8035 Craig St",
    "sg:city":"Indianapolis",
    "sg:classifiers":[
        {
            "category":"Sports & Exercise",
            "subcategory":"Gym",
            "type":"Entertainment"
        }
    ],
    "sg:phone":"+1 317 576 5440",
    "sg:postcode":"46250",
    "sg:province":"IN",
    "wof:name":"Castleton Health & Fitness Center",
    "wof:placetype":"venue"
},
  "geometry": {"coordinates":[-86.053057,39.903168],"type":"Point"}
}