{
  "type": "Feature",
  "properties": {
    "addr:full":"12800 N Meridian St Carmel IN 46032",
    "addr:housenumber":"12800",
    "addr:postcode":"46032",
    "addr:street":"N Meridian St",
    "iso:country":"US",
    "sg:address":"12800 N Meridian St",
    "sg:city":"Carmel",
    "sg:classifiers":[
        {
            "category":"Professional",
            "subcategory":"Lawyer & Legal Services",
            "type":"Services"
        }
    ],
    "sg:phone":"+1 317 238 6219",
    "sg:postcode":"46032",
    "sg:province":"IN",
    "sg:tags":[
        "attorney",
        "practice"
    ],
    "wof:name":"Merkle Mark",
    "wof:placetype":"venue"
},
  "geometry": {"coordinates":[-86.13103099999999,40.01898],"type":"Point"}
}