{
  "type": "Feature",
  "properties": {
    "addr:full":"4508 Vistula Rd Mishawaka IN 46544",
    "addr:housenumber":"4508",
    "addr:postcode":"46544",
    "addr:street":"Vistula Rd",
    "iso:country":"US",
    "sg:address":"4508 Vistula Rd",
    "sg:city":"Mishawaka",
    "sg:classifiers":[
        {
            "category":"Organizations",
            "subcategory":"Religious Organization",
            "type":"Services"
        }
    ],
    "sg:phone":"+1 574 255 0392",
    "sg:postcode":"46544",
    "sg:province":"IN",
    "wof:name":"Religious Education Dept",
    "wof:placetype":"venue"
},
  "geometry": {"coordinates":[-86.109452,41.667808],"type":"Point"}
}