{
  "type": "Feature",
  "properties": {
    "iso:country":"US",
    "sg:address":"201 W Main St",
    "sg:city":"Madison",
    "sg:classifiers":[
        {
            "category":"Real Estate",
            "subcategory":"Real Estate Agent",
            "type":"Services"
        }
    ],
    "sg:phone":"+1 812 265 6800",
    "sg:postcode":"47250",
    "sg:province":"IN",
    "wof:name":"Madison Realty Co",
    "wof:placetype":"venue"
},
  "geometry": {"coordinates":[-85.38157,38.736516],"type":"Point"}
}