{
  "type": "Feature",
  "properties": {
    "iso:country":"US",
    "sg:address":"110 S 1st St",
    "sg:city":"Ellettsville",
    "sg:classifiers":[
        {
            "category":"Real Estate",
            "subcategory":"Surveying",
            "type":"Services"
        }
    ],
    "sg:phone":"+1 812 876 2305",
    "sg:postcode":"47429",
    "sg:province":"IN",
    "sg:tags":[
        "surveyor"
    ],
    "sg:website":"www.tricosurveying.com",
    "wof:name":"Trico Surveying & Mapping",
    "wof:placetype":"venue"
},
  "geometry": {"coordinates":[-86.622038,39.230836],"type":"Point"}
}