{
  "type": "Feature",
  "properties": {
    "iso:country":"US",
    "sg:address":"2800 Kotter Ave",
    "sg:city":"Evansville",
    "sg:classifiers":[
        {
            "category":"Arena",
            "subcategory":"Sports Club",
            "type":"Entertainment"
        }
    ],
    "sg:phone":"+1 812 476 6654",
    "sg:postcode":"47715",
    "sg:province":"IN",
    "sg:tags":[
        "basketball"
    ],
    "sg:website":"www.ebahoops.com",
    "wof:name":"Evansville Basketball Academy",
    "wof:placetype":"venue"
},
  "geometry": {"coordinates":[-87.481604,37.998361],"type":"Point"}
}