{
  "type": "Feature",
  "properties": {
    "iso:country":"US",
    "sg:address":"79 W 250 N",
    "sg:city":"Warsaw",
    "sg:classifiers":[
        {
            "category":"Wholesale",
            "subcategory":"Hardware",
            "type":"Manufacturing & Wholesale Goods"
        }
    ],
    "sg:phone":"+1 574 269 2603",
    "sg:postcode":"46582",
    "sg:province":"IN",
    "sg:tags":[
        "equipment",
        "heating",
        "system"
    ],
    "wof:name":"Hoosier Energy Assoc Inc",
    "wof:placetype":"venue"
},
  "geometry": {"coordinates":[-85.85395,41.270165],"type":"Point"}
}