{
  "type": "Feature",
  "properties": {
    "iso:country":"US",
    "sg:address":"14182 Co Rd 52",
    "sg:city":"Syracuse",
    "sg:classifiers":[
        {
            "category":"Building & Trades",
            "subcategory":"Construction",
            "type":"Services"
        }
    ],
    "sg:phone":"+1 574 642 3734",
    "sg:postcode":"46567",
    "sg:province":"IN",
    "sg:tags":[
        "excavating",
        "contractor"
    ],
    "wof:name":"Miller Excavating Inc",
    "wof:placetype":"venue"
},
  "geometry": {"coordinates":[-85.733973,41.457928],"type":"Point"}
}