{
  "type": "Feature",
  "properties": {
    "iso:country":"US",
    "sg:address":"9988 Donavan Ln",
    "sg:city":"Fishers",
    "sg:classifiers":[
        {
            "category":"Professional",
            "subcategory":"Management & Consulting",
            "type":"Services"
        }
    ],
    "sg:phone":"+1 317 915 8770",
    "sg:postcode":"46038",
    "sg:province":"IN",
    "sg:tags":[
        "consultant"
    ],
    "wof:name":"Be Inspired Consultant Group",
    "wof:placetype":"venue"
},
  "geometry": {"coordinates":[-85.990524,39.983133],"type":"Point"}
}