{
  "type": "Feature",
  "properties": {
    "iso:country":"US",
    "sg:address":"600 Anson St",
    "sg:city":"Salem",
    "sg:classifiers":[
        {
            "category":"Government",
            "subcategory":"Office",
            "type":"Public Place"
        }
    ],
    "sg:phone":"+1 812 883 2190",
    "sg:postcode":"47167",
    "sg:province":"IN",
    "wof:name":"Washington County Highway Shop",
    "wof:placetype":"venue"
},
  "geometry": {"coordinates":[-86.09442799999999,38.610476],"type":"Point"}
}