{
  "type": "Feature",
  "properties": {
    "iso:country":"US",
    "sg:address":"302 E Allen St",
    "sg:city":"Kentland",
    "sg:classifiers":[
        {
            "category":"Retail",
            "subcategory":"Repair Shop",
            "type":"Services"
        }
    ],
    "sg:phone":"+1 219 474 5853",
    "sg:postcode":"47951",
    "sg:province":"IN",
    "wof:name":"Dennies Repair Improvement",
    "wof:placetype":"venue"
},
  "geometry": {"coordinates":[-87.445311,40.766229],"type":"Point"}
}