{
  "type": "Feature",
  "properties": {
    "iso:country":"US",
    "sg:address":"6100 Maxwell Ave",
    "sg:city":"Evansville",
    "sg:classifiers":[
        {
            "category":"Shopping",
            "type":"Retail Goods"
        }
    ],
    "sg:phone":"+1 812 479 3161",
    "sg:postcode":"47715",
    "sg:province":"IN",
    "sg:tags":[
        "spa",
        "hot",
        "tub"
    ],
    "wof:name":"Spa City USA",
    "wof:placetype":"venue"
},
  "geometry": {"coordinates":[-87.474926,37.99306],"type":"Point"}
}