{
  "type": "Feature",
  "properties": {
    "addr:full":"402 Oberreich St Laporte IN 46350",
    "addr:housenumber":"402",
    "addr:postcode":"46350",
    "addr:street":"Oberreich St Laporte",
    "iso:country":"US",
    "sg:address":"402 Oberreich St",
    "sg:city":"Laporte",
    "sg:classifiers":[
        {
            "category":"Retail",
            "subcategory":"Auto Rental",
            "type":"Services"
        }
    ],
    "sg:phone":"+1 219 325 8525",
    "sg:postcode":"46350",
    "sg:province":"IN",
    "sg:tags":[
        "renting",
        "automobile"
    ],
    "wof:name":"Enterprise Rent-A-Car",
    "wof:placetype":"venue"
},
  "geometry": {"coordinates":[-86.69915399999999,41.622161],"type":"Point"}
}