{
  "type": "Feature",
  "properties": {
    "iso:country":"US",
    "sg:address":"1711 H St",
    "sg:city":"Bedford",
    "sg:classifiers":[
        {
            "category":"Banks & Credit Unions",
            "subcategory":"Investment Brokerage",
            "type":"Services"
        }
    ],
    "sg:phone":"+1 812 275 1000",
    "sg:postcode":"47421",
    "sg:province":"IN",
    "sg:tags":[
        "consultant",
        "planning",
        "financial"
    ],
    "wof:name":"Compas Financial Group",
    "wof:placetype":"venue"
},
  "geometry": {"coordinates":[-86.48127599999999,38.859705],"type":"Point"}
}