{
  "type": "Feature",
  "properties": {
    "addr:full":"10865 Lehe Rd Brookston IN 47923",
    "addr:housenumber":"10865",
    "addr:postcode":"47923",
    "addr:street":"Lehe Rd",
    "iso:country":"US",
    "sg:address":"10865 Lehe Rd",
    "sg:city":"Brookston",
    "sg:classifiers":[
        {
            "category":"Professional",
            "subcategory":"Management & Consulting",
            "type":"Services"
        }
    ],
    "sg:phone":"+1 765 563 6526",
    "sg:postcode":"47923",
    "sg:province":"IN",
    "sg:tags":[
        "consultant",
        "business"
    ],
    "wof:name":"Curt Griffin & Assoc",
    "wof:placetype":"venue"
},
  "geometry": {"coordinates":[-86.848361,40.593763],"type":"Point"}
}