{
  "type": "Feature",
  "properties": {
    "addr:full":"4841 N Pennsylvania St Indianapolis IN 46205",
    "addr:housenumber":"4841",
    "addr:postcode":"46205",
    "addr:street":"N Pennsylvania St",
    "iso:country":"US",
    "sg:address":"4841 N Pennsylvania St",
    "sg:city":"Indianapolis",
    "sg:classifiers":[
        {
            "category":"Food & Beverages",
            "subcategory":"Groceries & Convenience Stores",
            "type":"Retail Goods"
        }
    ],
    "sg:phone":"+1 317 926 3078",
    "sg:postcode":"46205",
    "sg:province":"IN",
    "wof:name":"CMSI",
    "wof:placetype":"venue"
},
  "geometry": {"coordinates":[-86.15458700000001,39.842234],"type":"Point"}
}