{
  "type": "Feature",
  "properties": {
    "iso:country":"US",
    "sg:address":"4763 E State Rd 252",
    "sg:city":"Franklin",
    "sg:classifiers":[
        {
            "category":"Professional",
            "subcategory":"Engineering",
            "type":"Services"
        },
        {
            "category":"Manufacturing",
            "subcategory":"Tools & Machinery",
            "type":"Manufacturing & Wholesale Goods"
        }
    ],
    "sg:phone":"+1 317 738 0501",
    "sg:postcode":"46131",
    "sg:province":"IN",
    "sg:tags":[
        "plastic"
    ],
    "wof:name":"Engineering & Design Service",
    "wof:placetype":"venue"
},
  "geometry": {"coordinates":[-86.014624,39.411485],"type":"Point"}
}