{
  "type": "Feature",
  "properties": {
    "iso:country":"US",
    "sg:address":"1662 Hartzell Rd",
    "sg:city":"New Haven",
    "sg:classifiers":[
        {
            "category":"Building & Trades",
            "subcategory":"Construction",
            "type":"Services"
        }
    ],
    "sg:phone":"+1 260 749 2550",
    "sg:postcode":"46774",
    "sg:province":"IN",
    "sg:tags":[
        "excavating",
        "contractor"
    ],
    "wof:name":"Fritcha's Construction",
    "wof:placetype":"venue"
},
  "geometry": {"coordinates":[-85.030073,41.058281],"type":"Point"}
}