{
  "type": "Feature",
  "properties": {
    "iso:country":"US",
    "sg:address":"3024 Fairfield Ave",
    "sg:city":"Fort Wayne",
    "sg:classifiers":[
        {
            "category":"Social Services",
            "type":"Services"
        }
    ],
    "sg:phone":"+1 260 458 2005",
    "sg:postcode":"46807",
    "sg:province":"IN",
    "sg:tags":[
        "organization",
        "welfare"
    ],
    "wof:name":"RSVP/Retired Senior Vlntr",
    "wof:placetype":"venue"
},
  "geometry": {"coordinates":[-85.144983,41.057166],"type":"Point"}
}