{
  "type": "Feature",
  "properties": {
    "addr:full":"5715 Winterwind Ln Indianapolis IN 46237",
    "addr:housenumber":"5715",
    "addr:postcode":"46237",
    "addr:street":"Winterwind Ln",
    "iso:country":"US",
    "sg:address":"5715 Winterwind Ln",
    "sg:city":"Indianapolis",
    "sg:classifiers":[
        {
            "category":"Building & Trades",
            "subcategory":"Cleaning & Sanitation",
            "type":"Services"
        },
        {
            "category":"Retail",
            "subcategory":"Car Wash",
            "type":"Services"
        },
        {
            "category":"Building & Trades",
            "subcategory":"Construction",
            "type":"Services"
        }
    ],
    "sg:phone":"+1 317 865 0400",
    "sg:postcode":"46237",
    "sg:province":"IN",
    "sg:tags":[
        "industrial",
        "washing",
        "power",
        "pressure",
        "cleaning-exterior",
        "contractor",
        "equipment",
        "contractors-commercial",
        "painting"
    ],
    "sg:website":"http://www.jahnkepainting.com",
    "wof:name":"Jahnke Painting Inc",
    "wof:placetype":"venue"
},
  "geometry": {"coordinates":[-86.068774,39.663564],"type":"Point"}
}