{
  "type": "Feature",
  "properties": {
    "iso:country":"US",
    "sg:address":"3813 E Winston St",
    "sg:city":"Bloomington",
    "sg:classifiers":[
        {
            "category":"Professional",
            "subcategory":"Art Services",
            "type":"Services"
        }
    ],
    "sg:phone":"+1 812 333 9307",
    "sg:postcode":"47401",
    "sg:province":"IN",
    "sg:tags":[
        "commercial",
        "design"
    ],
    "wof:name":"Rsn Ltd",
    "wof:placetype":"venue"
},
  "geometry": {"coordinates":[-86.482801,39.14581],"type":"Point"}
}