{
  "type": "Feature",
  "properties": {
    "iso:country":"US",
    "sg:address":"2102 Hawksbury Ln",
    "sg:city":"Indianapolis",
    "sg:classifiers":[
        {
            "category":"Real Estate",
            "subcategory":"Real Estate Operator",
            "type":"Services"
        }
    ],
    "sg:phone":"+1 317 295 9845",
    "sg:postcode":"46260",
    "sg:province":"IN",
    "sg:tags":[
        "apartment"
    ],
    "wof:name":"Woodridge Apartments JBM",
    "wof:placetype":"venue"
},
  "geometry": {"coordinates":[-86.196421,39.882959],"type":"Point"}
}