{
  "type": "Feature",
  "properties": {
    "iso:country":"US",
    "sg:address":"3276 Ross Rd",
    "sg:city":"Lafayette",
    "sg:classifiers":[
        {
            "category":"Building & Trades",
            "subcategory":"Construction",
            "type":"Services"
        }
    ],
    "sg:phone":"+1 765 474 0713",
    "sg:postcode":"47905",
    "sg:province":"IN",
    "sg:tags":[
        "fence",
        "contractor"
    ],
    "sg:website":"www.bluesfence.com",
    "wof:name":"Blue's Fence",
    "wof:placetype":"venue"
},
  "geometry": {"coordinates":[-86.83886,40.379359],"type":"Point"}
}