{
  "type": "Feature",
  "properties": {
    "addr:full":"34 W Main St Peru IN 46970",
    "addr:housenumber":"34",
    "addr:postcode":"46970",
    "addr:street":"W Main St",
    "iso:country":"US",
    "sg:address":"34 W Main St",
    "sg:city":"Peru",
    "sg:classifiers":[
        {
            "category":"Shopping",
            "type":"Retail Goods"
        }
    ],
    "sg:phone":"+1 765 473 9271",
    "sg:postcode":"46970",
    "sg:province":"IN",
    "sg:tags":[
        "church",
        "supply"
    ],
    "wof:name":"Holy Trinity Altar Bread",
    "wof:placetype":"venue"
},
  "geometry": {"coordinates":[-86.069926,40.753316],"type":"Point"}
}