{
  "type": "Feature",
  "properties": {
    "addr:full":"3605 N National Rd Columbus IN 47201",
    "addr:housenumber":"3605",
    "addr:postcode":"47201",
    "addr:street":"N National Rd",
    "iso:country":"US",
    "sg:address":"3605 N National Rd",
    "sg:city":"Columbus",
    "sg:classifiers":[
        {
            "category":"Retail",
            "subcategory":"Auto Repair",
            "type":"Services"
        }
    ],
    "sg:phone":"+1 812 376 9683",
    "sg:postcode":"47201",
    "sg:province":"IN",
    "sg:tags":[
        "repairing",
        "automobile"
    ],
    "wof:name":"Hawkins Auto Ctr",
    "wof:placetype":"venue"
},
  "geometry": {"coordinates":[-85.932658,39.238371],"type":"Point"}
}