{
  "type": "Feature",
  "properties": {
    "iso:country":"US",
    "sg:address":"382 Woodview Dr",
    "sg:city":"Noblesville",
    "sg:classifiers":[
        {
            "category":"Professional",
            "subcategory":"Computer Services",
            "type":"Services"
        }
    ],
    "sg:phone":"+1 317 773 5030",
    "sg:postcode":"46060",
    "sg:province":"IN",
    "wof:name":"Dac Solutions Inc",
    "wof:placetype":"venue"
},
  "geometry": {"coordinates":[-86.025552,40.052191],"type":"Point"}
}