{
  "type": "Feature",
  "properties": {
    "iso:country":"US",
    "sg:address":"2305 Lake Shore Dr",
    "sg:city":"Michigan City",
    "sg:classifiers":[
        {
            "category":"Professional",
            "subcategory":"Business Services",
            "type":"Services"
        }
    ],
    "sg:phone":"+1 219 879 9894",
    "sg:postcode":"46360",
    "sg:province":"IN",
    "wof:name":"Harris Interior Design",
    "wof:placetype":"venue"
},
  "geometry": {"coordinates":[-86.853804,41.746634],"type":"Point"}
}