{
  "type": "Feature",
  "properties": {
    "iso:country":"US",
    "sg:address":"2565 Broadway",
    "sg:city":"Gary",
    "sg:classifiers":[
        {
            "category":"Retail",
            "subcategory":"Car Wash",
            "type":"Services"
        }
    ],
    "sg:phone":"+1 219 886 1138",
    "sg:postcode":"46407",
    "sg:province":"IN",
    "sg:tags":[
        "polishing",
        "washing"
    ],
    "wof:name":"Red's Car Wash",
    "wof:placetype":"venue"
},
  "geometry": {"coordinates":[-87.336888,41.572579],"type":"Point"}
}