{
  "type": "Feature",
  "properties": {
    "iso:country":"US",
    "sg:address":"201 W 7th St",
    "sg:city":"Rochester",
    "sg:classifiers":[
        {
            "category":"Organizations",
            "subcategory":"Religious Organization",
            "type":"Services"
        }
    ],
    "sg:phone":"+1 574 223 5619",
    "sg:postcode":"46975",
    "sg:province":"IN",
    "sg:tags":[
        "church"
    ],
    "wof:name":"Grace United Methodist Church",
    "wof:placetype":"venue"
},
  "geometry": {"coordinates":[-86.218886,41.06722],"type":"Point"}
}