{
  "type": "Feature",
  "properties": {
    "iso:country":"US",
    "sg:address":"2049 Prairie Ave",
    "sg:city":"South Bend",
    "sg:classifiers":[
        {
            "category":"Social Services",
            "subcategory":"Child Care",
            "type":"Services"
        }
    ],
    "sg:phone":"+1 574 233 3353",
    "sg:postcode":"46613",
    "sg:province":"IN",
    "wof:name":"Believers Child Care Ministry",
    "wof:placetype":"venue"
},
  "geometry": {"coordinates":[-86.27890499999999,41.651112],"type":"Point"}
}