{
  "type": "Feature",
  "properties": {
    "addr:full":"810 E McKinley Ave Mishawaka IN 46545",
    "addr:housenumber":"810",
    "addr:postcode":"46545",
    "addr:street":"E Mckinley Ave",
    "iso:country":"US",
    "sg:address":"810 E McKinley Ave",
    "sg:city":"Mishawaka",
    "sg:classifiers":[
        {
            "category":"Home & Garden",
            "subcategory":"Household Appliances",
            "type":"Retail Goods"
        }
    ],
    "sg:phone":"+1 574 257 1933",
    "sg:postcode":"46545",
    "sg:province":"IN",
    "sg:website":"www.acemaytag.com",
    "wof:name":"Ace Maytag Home Appliance Ctr",
    "wof:placetype":"venue"
},
  "geometry": {"coordinates":[-86.1737,41.680507],"type":"Point"}
}