{
  "type": "Feature",
  "properties": {
    "iso:country":"US",
    "sg:address":"9236 Main St",
    "sg:city":"Fairbanks",
    "sg:classifiers":[
        {
            "category":"Government",
            "subcategory":"Post Office",
            "type":"Public Place"
        }
    ],
    "sg:phone":"+1 812 394 2250",
    "sg:postcode":"47849",
    "sg:province":"IN",
    "wof:name":"US Post Office",
    "wof:placetype":"venue"
},
  "geometry": {"coordinates":[-87.521316,39.218572],"type":"Point"}
}