{
  "type": "Feature",
  "properties": {
    "iso:country":"US",
    "sg:address":"5000 N Isabella Ln",
    "sg:city":"Muncie",
    "sg:classifiers":[
        {
            "category":"Building & Trades",
            "subcategory":"Construction",
            "type":"Services"
        }
    ],
    "sg:phone":"+1 765 759 0973",
    "sg:postcode":"47304",
    "sg:province":"IN",
    "sg:tags":[
        "general",
        "contractor"
    ],
    "wof:name":"RSL Case",
    "wof:placetype":"venue"
},
  "geometry": {"coordinates":[-85.476977,40.234624],"type":"Point"}
}