{
  "type": "Feature",
  "properties": {
    "iso:country":"US",
    "sg:address":"3606 E Jefferson Blvd",
    "sg:city":"South Bend",
    "sg:classifiers":[
        {
            "category":"Health Services",
            "subcategory":"Health Practitioner",
            "type":"Services"
        }
    ],
    "sg:phone":"+1 574 472 1000",
    "sg:postcode":"46615",
    "sg:province":"IN",
    "sg:tags":[
        "psychologist"
    ],
    "wof:name":"Northern Indiana Assoc",
    "wof:placetype":"venue"
},
  "geometry": {"coordinates":[-86.197236,41.672863],"type":"Point"}
}