{
  "type": "Feature",
  "properties": {
    "iso:country":"US",
    "sg:address":"626 N Market St",
    "sg:city":"Winamac",
    "sg:classifiers":[
        {
            "category":"Social Services",
            "subcategory":"Child Care",
            "type":"Services"
        }
    ],
    "sg:phone":"+1 574 946 6507",
    "sg:postcode":"46996",
    "sg:province":"IN",
    "sg:tags":[
        "day"
    ],
    "wof:name":"Vicky Sobczak",
    "wof:placetype":"venue"
},
  "geometry": {"coordinates":[-86.606618,41.057316],"type":"Point"}
}