{
  "type": "Feature",
  "properties": {
    "iso:country":"US",
    "sg:address":"428 5th St",
    "sg:city":"Columbus",
    "sg:classifiers":[
        {
            "category":"Insurance",
            "subcategory":"Insurance Agent",
            "type":"Services"
        }
    ],
    "sg:phone":"+1 812 372 3268",
    "sg:postcode":"47201",
    "sg:province":"IN",
    "wof:name":"Fox Insurance Inc",
    "wof:placetype":"venue"
},
  "geometry": {"coordinates":[-85.920161,39.203594],"type":"Point"}
}