{
  "type": "Feature",
  "properties": {
    "iso:country":"US",
    "sg:address":"311 N Woodlawn Ave",
    "sg:city":"Griffith",
    "sg:classifiers":[
        {
            "category":"Shopping",
            "subcategory":"Catalog Store",
            "type":"Retail Goods"
        }
    ],
    "sg:phone":"+1 219 789 1299",
    "sg:postcode":"46319",
    "sg:province":"IN",
    "sg:tags":[
        "mail",
        "house"
    ],
    "wof:name":"Keepsake Publishing",
    "wof:placetype":"venue"
},
  "geometry": {"coordinates":[-87.431213,41.52805],"type":"Point"}
}