{
  "type": "Feature",
  "properties": {
    "iso:country":"US",
    "sg:address":"4005 S Michigan St",
    "sg:city":"South Bend",
    "sg:classifiers":[
        {
            "category":"Autos & Motor Vehicles",
            "subcategory":"Auto Supplies",
            "type":"Retail Goods"
        }
    ],
    "sg:phone":"+1 574 291 6056",
    "sg:postcode":"46614",
    "sg:province":"IN",
    "sg:tags":[
        "tire"
    ],
    "wof:name":"Discount Tire Co Inc",
    "wof:placetype":"venue"
},
  "geometry": {"coordinates":[-86.250399,41.635721],"type":"Point"}
}