{
  "type": "Feature",
  "properties": {
    "iso:country":"US",
    "sg:address":"6621 US Hwy 35",
    "sg:city":"Muncie",
    "sg:classifiers":[
        {
            "category":"Building & Trades",
            "subcategory":"Construction",
            "type":"Services"
        }
    ],
    "sg:phone":"+1 765 288 1238",
    "sg:postcode":"47302",
    "sg:province":"IN",
    "sg:tags":[
        "general",
        "contractor"
    ],
    "wof:name":"David Stamper Construction",
    "wof:placetype":"venue"
},
  "geometry": {"coordinates":[-85.331498,40.132212],"type":"Point"}
}