{
  "type": "Feature",
  "properties": {
    "iso:country":"US",
    "sg:address":"2938 W 450 S",
    "sg:city":"Lafayette",
    "sg:classifiers":[
        {
            "category":"Building & Trades",
            "subcategory":"Construction",
            "type":"Services"
        }
    ],
    "sg:phone":"+1 765 474 1030",
    "sg:postcode":"47909",
    "sg:province":"IN",
    "sg:tags":[
        "water",
        "well",
        "drilling"
    ],
    "wof:name":"Bir & Son Well Drilling",
    "wof:placetype":"venue"
},
  "geometry": {"coordinates":[-86.959784,40.352285],"type":"Point"}
}