{
  "type": "Feature",
  "properties": {
    "iso:country":"US",
    "sg:address":"4134 Surrey Way",
    "sg:city":"Evansville",
    "sg:classifiers":[
        {
            "category":"Professional",
            "subcategory":"Business Services",
            "type":"Services"
        }
    ],
    "sg:phone":"+1 812 867 1725",
    "sg:postcode":"47711",
    "sg:province":"IN",
    "wof:name":"Berkey Provost Stein Assoc LLP",
    "wof:placetype":"venue"
},
  "geometry": {"coordinates":[-87.49944,38.05299],"type":"Point"}
}