{
  "type": "Feature",
  "properties": {
    "iso:country":"US",
    "sg:address":"7452 S 1200 E",
    "sg:city":"Otterbein",
    "sg:classifiers":[
        {
            "category":"Building & Trades",
            "subcategory":"Construction",
            "type":"Services"
        }
    ],
    "sg:phone":"+1 765 583 0045",
    "sg:postcode":"47970",
    "sg:province":"IN",
    "sg:tags":[
        "resurfacing",
        "laying",
        "refinishing",
        "floor"
    ],
    "wof:name":"Senesac Flooring & Install",
    "wof:placetype":"venue"
},
  "geometry": {"coordinates":[-87.094097,40.497417],"type":"Point"}
}