{
  "type": "Feature",
  "properties": {
    "iso:country":"US",
    "sg:address":"5151 W 14th St",
    "sg:city":"Indianapolis",
    "sg:classifiers":[
        {
            "category":"Education",
            "subcategory":"School",
            "type":"Public Place"
        }
    ],
    "sg:phone":"+1 317 244 3359",
    "sg:postcode":"46224",
    "sg:province":"IN",
    "sg:tags":[
        "middle"
    ],
    "sg:website":"www.speedway.k12.in.us",
    "wof:name":"Speedway Junior High School",
    "wof:placetype":"venue"
},
  "geometry": {"coordinates":[-86.24763,39.78515],"type":"Point"}
}