{
  "type": "Feature",
  "properties": {
    "iso:country":"US",
    "sg:address":"219 Airport North Office Park",
    "sg:city":"Fort Wayne",
    "sg:classifiers":[
        {
            "category":"Professional",
            "subcategory":"Accounting & Tax Preparation",
            "type":"Services"
        }
    ],
    "sg:phone":"+1 260 489 8620",
    "sg:postcode":"46825",
    "sg:province":"IN",
    "sg:tags":[
        "return",
        "filing"
    ],
    "wof:name":"A M Hasselman & Company",
    "wof:placetype":"venue"
},
  "geometry": {"coordinates":[-85.162131,41.145215],"type":"Point"}
}