{
  "type": "Feature",
  "properties": {
    "addr:full":"320 S 25th St Terre Haute IN 47803",
    "addr:housenumber":"320",
    "addr:postcode":"47803",
    "addr:street":"S 25Th St",
    "iso:country":"US",
    "sg:address":"320 S 25th St",
    "sg:city":"Terre Haute",
    "sg:classifiers":[
        {
            "category":"Manufacturing",
            "subcategory":"Paper Products",
            "type":"Manufacturing & Wholesale Goods"
        }
    ],
    "sg:phone":"+1 812 234 0991",
    "sg:postcode":"47803",
    "sg:province":"IN",
    "sg:tags":[
        "corrugated",
        "solid",
        "fiber",
        "box"
    ],
    "wof:name":"Weyerhaeuser Paper Co",
    "wof:placetype":"venue"
},
  "geometry": {"coordinates":[-87.378862,39.463808],"type":"Point"}
}