{
  "type": "Feature",
  "properties": {
    "iso:country":"US",
    "sg:address":"1325 W 30th St",
    "sg:city":"Indianapolis",
    "sg:classifiers":[
        {
            "category":"Building & Trades",
            "subcategory":"Plumbing",
            "type":"Services"
        }
    ],
    "sg:phone":"+1 317 924 4042",
    "sg:postcode":"46208",
    "sg:province":"IN",
    "sg:tags":[
        "plumbing",
        "contractor"
    ],
    "wof:name":"Preferred Mechanical Svc",
    "wof:placetype":"venue"
},
  "geometry": {"coordinates":[-86.186721,39.809942],"type":"Point"}
}