{
  "type": "Feature",
  "properties": {
    "iso:country":"US",
    "sg:address":"218 E 2nd St",
    "sg:city":"Bremen",
    "sg:classifiers":[
        {
            "category":"Retail",
            "subcategory":"Auto Repair",
            "type":"Services"
        }
    ],
    "sg:phone":"+1 574 546 4473",
    "sg:postcode":"46506",
    "sg:province":"IN",
    "sg:tags":[
        "body",
        "automobile",
        "painting"
    ],
    "sg:website":"www.precisionpainting.com",
    "wof:name":"Precision Painting Inc",
    "wof:placetype":"venue"
},
  "geometry": {"coordinates":[-86.145191,41.453714],"type":"Point"}
}