{
  "type": "Feature",
  "properties": {
    "iso:country":"US",
    "sg:address":"4032 E 82nd St",
    "sg:city":"Indianapolis",
    "sg:classifiers":[
        {
            "category":"Shopping",
            "subcategory":"Stationery & Office Supplies",
            "type":"Retail Goods"
        }
    ],
    "sg:phone":"+1 317 578 8316",
    "sg:postcode":"46250",
    "sg:province":"IN",
    "sg:tags":[
        "equipment"
    ],
    "sg:website":"www.officedepot.com",
    "wof:name":"Office Depot",
    "wof:placetype":"venue"
},
  "geometry": {"coordinates":[-86.09699999999999,39.907501],"type":"Point"}
}