{
  "type": "Feature",
  "properties": {
    "iso:country":"US",
    "sg:address":"2726 Lynn Ave",
    "sg:city":"Fort Wayne",
    "sg:classifiers":[
        {
            "category":"Social Services",
            "subcategory":"Child Care",
            "type":"Services"
        }
    ],
    "sg:phone":"+1 260 482 1743",
    "sg:postcode":"46805",
    "sg:province":"IN",
    "sg:tags":[
        "kindergarten",
        "academic",
        "school"
    ],
    "wof:name":"Pine Hill Country Day School",
    "wof:placetype":"venue"
},
  "geometry": {"coordinates":[-85.104355,41.098048],"type":"Point"}
}