{
  "type": "Feature",
  "properties": {
    "iso:country":"US",
    "sg:address":"9151 N 1200 W",
    "sg:city":"Demotte",
    "sg:classifiers":[
        {
            "category":"Real Estate",
            "subcategory":"Real Estate Operator",
            "type":"Services"
        }
    ],
    "sg:phone":"+1 219 345 4426",
    "sg:postcode":"46310",
    "sg:province":"IN",
    "sg:tags":[
        "mobile",
        "home",
        "community"
    ],
    "wof:name":"Rosewood Manor Estates",
    "wof:placetype":"venue"
},
  "geometry": {"coordinates":[-87.275757,41.136594],"type":"Point"}
}