{
  "type": "Feature",
  "properties": {
    "iso:country":"US",
    "sg:address":"2016 Edgewood Dr",
    "sg:city":"Anderson",
    "sg:classifiers":[
        {
            "category":"Government",
            "subcategory":"Office",
            "type":"Public Place"
        }
    ],
    "sg:phone":"+1 317 510 4567",
    "sg:postcode":"46011",
    "sg:province":"IN",
    "sg:tags":[
        "national",
        "security"
    ],
    "wof:name":"Department of Defense",
    "wof:placetype":"venue"
},
  "geometry": {"coordinates":[-85.732553,40.094724],"type":"Point"}
}