{
  "type": "Feature",
  "properties": {
    "iso:country":"US",
    "sg:address":"14 E Washington St",
    "sg:city":"Knox",
    "sg:classifiers":[
        {
            "category":"Insurance",
            "subcategory":"Title Insurance",
            "type":"Services"
        }
    ],
    "sg:phone":"+1 574 772 3733",
    "sg:postcode":"46534",
    "sg:province":"IN",
    "wof:name":"Starke County Abstract Co",
    "wof:placetype":"venue"
},
  "geometry": {"coordinates":[-86.622743,41.298296],"type":"Point"}
}