{
  "type": "Feature",
  "properties": {
    "iso:country":"US",
    "sg:address":"1176 W Eads Pkwy",
    "sg:city":"Lawrenceburg",
    "sg:classifiers":[
        {
            "category":"Autos & Motor Vehicles",
            "subcategory":"Auto Supplies",
            "type":"Retail Goods"
        }
    ],
    "sg:phone":"+1 812 539 1880",
    "sg:postcode":"47025",
    "sg:province":"IN",
    "sg:tags":[
        "equipment",
        "racing",
        "car",
        "automobile"
    ],
    "wof:name":"Lawrence Motorsports Trailer",
    "wof:placetype":"venue"
},
  "geometry": {"coordinates":[-84.882076,39.082573],"type":"Point"}
}