{
  "type": "Feature",
  "properties": {
    "iso:country":"US",
    "sg:address":"1111 Market St",
    "sg:city":"Charlestown",
    "sg:classifiers":[
        {
            "category":"Banks & Credit Unions",
            "subcategory":"Bank",
            "type":"Services"
        }
    ],
    "sg:phone":"+1 812 256 3344",
    "sg:postcode":"47111",
    "sg:province":"IN",
    "sg:tags":[
        "state",
        "commercial"
    ],
    "wof:name":"PNC",
    "wof:placetype":"venue"
},
  "geometry": {"coordinates":[-85.670559,38.454576],"type":"Point"}
}