{
  "type": "Feature",
  "properties": {
    "iso:country":"US",
    "sg:address":"39 E Market St",
    "sg:city":"Huntington",
    "sg:classifiers":[
        {
            "category":"Bars & Pubs",
            "type":"Food & Drink"
        }
    ],
    "sg:phone":"+1 260 356 9997",
    "sg:postcode":"46750",
    "sg:province":"IN",
    "wof:name":"Market Street Inc",
    "wof:placetype":"venue"
},
  "geometry": {"coordinates":[-85.494197,40.882181],"type":"Point"}
}