{
  "type": "Feature",
  "properties": {
    "addr:full":"508 E 5th St Hartford City IN 47348",
    "addr:housenumber":"508",
    "addr:postcode":"47348",
    "addr:street":"E 5Th St",
    "iso:country":"US",
    "sg:address":"508 E 5th St",
    "sg:city":"Hartford City",
    "sg:classifiers":[
        {
            "category":"Building & Trades",
            "subcategory":"Construction",
            "type":"Services"
        }
    ],
    "sg:phone":"+1 765 348 1415",
    "sg:postcode":"47348",
    "sg:province":"IN",
    "sg:tags":[
        "residential"
    ],
    "wof:name":"Cando Construction",
    "wof:placetype":"venue"
},
  "geometry": {"coordinates":[-85.363294,40.439185],"type":"Point"}
}