{
  "type": "Feature",
  "properties": {
    "iso:country":"US",
    "sg:address":"618 N Range Line Rd",
    "sg:city":"Carmel",
    "sg:classifiers":[
        {
            "category":"Taxi",
            "type":"Transportation"
        }
    ],
    "sg:phone":"+1 317 848 5757",
    "sg:postcode":"46032",
    "sg:province":"IN",
    "sg:tags":[
        "taxicab"
    ],
    "sg:website":"www.carmelcirclecitycab.com",
    "wof:name":"Carmel Circle City Cab",
    "wof:placetype":"venue"
},
  "geometry": {"coordinates":[-86.12715900000001,39.983451],"type":"Point"}
}