{
  "type": "Feature",
  "properties": {
    "iso:country":"US",
    "sg:address":"9492 E Co Rd 200 N",
    "sg:city":"Michigantown",
    "sg:classifiers":[
        {
            "category":"Farming",
            "subcategory":"Farm & Veterinary Services",
            "type":"Manufacturing & Wholesale Goods"
        }
    ],
    "sg:phone":"+1 765 249 2351",
    "sg:postcode":"46057",
    "sg:province":"IN",
    "sg:tags":[
        "crop",
        "harvesting"
    ],
    "wof:name":"Richard Wyrick",
    "wof:placetype":"venue"
},
  "geometry": {"coordinates":[-86.328082,40.316024],"type":"Point"}
}