{
  "type": "Feature",
  "properties": {
    "iso:country":"US",
    "sg:address":"6608 Longwoods Cir",
    "sg:city":"Indianapolis",
    "sg:classifiers":[
        {
            "category":"Professional",
            "type":"Services"
        }
    ],
    "sg:phone":"+1 317 280 0010",
    "sg:postcode":"46254",
    "sg:province":"IN",
    "wof:name":"Lori Bowser",
    "wof:placetype":"venue"
},
  "geometry": {"coordinates":[-86.278152,39.849331],"type":"Point"}
}