{
  "type": "Feature",
  "properties": {
    "iso:country":"US",
    "sg:address":"8051 S Emerson Ave",
    "sg:city":"Indianapolis",
    "sg:classifiers":[
        {
            "category":"Health Services",
            "subcategory":"Doctor",
            "type":"Services"
        }
    ],
    "sg:phone":"+1 317 859 3095",
    "sg:postcode":"46237",
    "sg:province":"IN",
    "sg:tags":[
        "physician",
        "surgeon"
    ],
    "wof:name":"Cardiac & Vascular Physicians",
    "wof:placetype":"venue"
},
  "geometry": {"coordinates":[-86.082577,39.650816],"type":"Point"}
}