{
  "type": "Feature",
  "properties": {
    "iso:country":"US",
    "sg:address":"54194 Adams St",
    "sg:city":"Elkhart",
    "sg:classifiers":[
        {
            "category":"Manufacturing",
            "subcategory":"Metals",
            "type":"Manufacturing & Wholesale Goods"
        }
    ],
    "sg:phone":"+1 574 262 3430",
    "sg:postcode":"46514",
    "sg:province":"IN",
    "sg:tags":[
        "polishing",
        "buffing"
    ],
    "wof:name":"Precision Buffing",
    "wof:placetype":"venue"
},
  "geometry": {"coordinates":[-85.96201000000001,41.706847],"type":"Point"}
}