{
  "type": "Feature",
  "properties": {
    "iso:country":"US",
    "sg:address":"212 Hamilton St",
    "sg:city":"Crawfordsville",
    "sg:classifiers":[
        {
            "category":"Building & Trades",
            "subcategory":"Construction",
            "type":"Services"
        }
    ],
    "sg:phone":"+1 765 362 1355",
    "sg:postcode":"47933",
    "sg:province":"IN",
    "sg:tags":[
        "downspouts",
        "gutter"
    ],
    "wof:name":"Custom Flo Gutter Systems",
    "wof:placetype":"venue"
},
  "geometry": {"coordinates":[-86.88581,40.043937],"type":"Point"}
}