{
  "type": "Feature",
  "properties": {
    "iso:country":"US",
    "sg:address":"1110 W 10th St",
    "sg:city":"Muncie",
    "sg:classifiers":[
        {
            "category":"Recreation",
            "type":"Entertainment"
        }
    ],
    "sg:phone":"+1 765 747 4741",
    "sg:postcode":"47302",
    "sg:province":"IN",
    "sg:tags":[
        "hall",
        "auditorium"
    ],
    "wof:name":"Muncie Ross Ctr",
    "wof:placetype":"venue"
},
  "geometry": {"coordinates":[-85.39968,40.180253],"type":"Point"}
}