{
  "type": "Feature",
  "properties": {
    "iso:country":"US",
    "sg:address":"5424 W 1240 S",
    "sg:city":"Romney",
    "sg:phone":"+1 765 538 3339",
    "sg:postcode":"47981",
    "sg:province":"IN",
    "sg:tags":[
        "farm",
        "grain",
        "cash"
    ],
    "wof:name":"Charles Stafford",
    "wof:placetype":"venue"
},
  "geometry": {"coordinates":[-87.00748,40.238965],"type":"Point"}
}