{
  "type": "Feature",
  "properties": {
    "iso:country":"US",
    "sg:address":"4861 E 600 S",
    "sg:city":"Cutler",
    "sg:classifiers":[
        {
            "category":"Building & Trades",
            "subcategory":"Landscaping Services",
            "type":"Services"
        }
    ],
    "sg:phone":"+1 765 566 2351",
    "sg:postcode":"46920",
    "sg:province":"IN",
    "sg:tags":[
        "landscape",
        "contractor"
    ],
    "wof:name":"Miller's Maintenance & Lndscpg",
    "wof:placetype":"venue"
},
  "geometry": {"coordinates":[-86.432522,40.460447],"type":"Point"}
}