{
  "type": "Feature",
  "properties": {
    "iso:country":"US",
    "sg:address":"2901 Northwestern Ave",
    "sg:city":"West Lafayette",
    "sg:classifiers":[
        {
            "category":"Personal",
            "subcategory":"Beauty Salon",
            "type":"Services"
        }
    ],
    "sg:phone":"+1 765 463 0349",
    "sg:postcode":"47906",
    "sg:province":"IN",
    "sg:website":"www.christinaspa.com",
    "wof:name":"Christina & Co",
    "wof:placetype":"venue"
},
  "geometry": {"coordinates":[-86.93158200000001,40.458019],"type":"Point"}
}