{
  "type": "Feature",
  "properties": {
    "iso:country":"US",
    "sg:address":"9442 W Oler Rd",
    "sg:city":"Williamsburg",
    "sg:phone":"+1 765 886 5435",
    "sg:postcode":"47393",
    "sg:province":"IN",
    "sg:tags":[
        "farm",
        "corn",
        "soybean"
    ],
    "wof:name":"David Williamson",
    "wof:placetype":"venue"
},
  "geometry": {"coordinates":[-85.055234,39.94687],"type":"Point"}
}