{
  "type": "Feature",
  "properties": {
    "iso:country":"US",
    "sg:address":"7603 Foxwood Dr",
    "sg:city":"Schererville",
    "sg:classifiers":[
        {
            "category":"Professional",
            "subcategory":"Management & Consulting",
            "type":"Services"
        }
    ],
    "sg:phone":"+1 219 322 0508",
    "sg:postcode":"46375",
    "sg:province":"IN",
    "sg:tags":[
        "personnel",
        "consultant"
    ],
    "sg:website":"www.odonnellstaffingresearch.com",
    "wof:name":"O'Donnell Staffing Research",
    "wof:placetype":"venue"
},
  "geometry": {"coordinates":[-87.401979,41.479295],"type":"Point"}
}