{
  "type": "Feature",
  "properties": {
    "iso:country":"US",
    "sg:address":"1111 D I Dr",
    "sg:city":"Elkhart",
    "sg:classifiers":[
        {
            "category":"Building & Trades",
            "subcategory":"Construction",
            "type":"Services"
        }
    ],
    "sg:phone":"+1 574 266 6021",
    "sg:postcode":"46514",
    "sg:province":"IN",
    "sg:tags":[
        "water",
        "well",
        "drilling"
    ],
    "wof:name":"Bohs Well Drilling Inc",
    "wof:placetype":"venue"
},
  "geometry": {"coordinates":[-85.992071,41.726718],"type":"Point"}
}