{
  "type": "Feature",
  "properties": {
    "iso:country":"US",
    "sg:address":"806 Cedar Pkwy",
    "sg:city":"Schererville",
    "sg:classifiers":[
        {
            "category":"Shopping",
            "subcategory":"Florist",
            "type":"Retail Goods"
        }
    ],
    "sg:phone":"+1 219 864 1947",
    "sg:postcode":"46375",
    "sg:province":"IN",
    "wof:name":"A Time To Remember",
    "wof:placetype":"venue"
},
  "geometry": {"coordinates":[-87.474519,41.514249],"type":"Point"}
}