{
  "type": "Feature",
  "properties": {
    "iso:country":"US",
    "sg:address":"140 Maple Ln",
    "sg:city":"Mooresville",
    "sg:classifiers":[
        {
            "category":"Real Estate",
            "subcategory":"Real Estate Agent",
            "type":"Services"
        }
    ],
    "sg:phone":"+1 317 831 9799",
    "sg:postcode":"46158",
    "sg:province":"IN",
    "wof:name":"Mathis Real Estate",
    "wof:placetype":"venue"
},
  "geometry": {"coordinates":[-86.370498,39.614412],"type":"Point"}
}