{
  "type": "Feature",
  "properties": {
    "iso:country":"US",
    "sg:address":"208 W Harcourt Rd",
    "sg:city":"Angola",
    "sg:classifiers":[
        {
            "category":"Building & Trades",
            "subcategory":"Equipment Rental",
            "type":"Services"
        }
    ],
    "sg:phone":"+1 260 665 5820",
    "sg:postcode":"46703",
    "sg:province":"IN",
    "sg:tags":[
        "contractor"
    ],
    "wof:name":"Halmark Sales/Rental Ctr Inc",
    "wof:placetype":"venue"
},
  "geometry": {"coordinates":[-85.000793,41.657277],"type":"Point"}
}