{
  "type": "Feature",
  "properties": {
    "iso:country":"US",
    "sg:address":"8060 Madison Ave",
    "sg:city":"Indianapolis",
    "sg:classifiers":[
        {
            "category":"Building & Trades",
            "subcategory":"Construction",
            "type":"Services"
        }
    ],
    "sg:phone":"+1 317 882 9292",
    "sg:postcode":"46227",
    "sg:province":"IN",
    "sg:tags":[
        "contractor"
    ],
    "wof:name":"R J Construction",
    "wof:placetype":"venue"
},
  "geometry": {"coordinates":[-86.12183400000001,39.649613],"type":"Point"}
}