{
  "type": "Feature",
  "properties": {
    "iso:country":"US",
    "sg:address":"815 Main St",
    "sg:city":"Indianapolis",
    "sg:classifiers":[
        {
            "category":"Personal",
            "type":"Services"
        }
    ],
    "sg:phone":"+1 317 255 8973",
    "sg:postcode":"46220",
    "sg:province":"IN",
    "sg:tags":[
        "professional",
        "therapist",
        "counselors-licensed",
        "massage"
    ],
    "wof:name":"A Peaceful Path",
    "wof:placetype":"venue"
},
  "geometry": {"coordinates":[-86.143837,39.872108],"type":"Point"}
}