{
  "type": "Feature",
  "properties": {
    "iso:country":"US",
    "sg:address":"10170 Glenwood Ave",
    "sg:city":"Osceola",
    "sg:classifiers":[
        {
            "category":"Manufacturing",
            "subcategory":"Signs",
            "type":"Manufacturing & Wholesale Goods"
        }
    ],
    "sg:phone":"+1 574 674 9672",
    "sg:postcode":"46561",
    "sg:province":"IN",
    "sg:tags":[
        "specialty",
        "mfg"
    ],
    "sg:website":"www.signs-etc.net",
    "wof:name":"Signs Etc",
    "wof:placetype":"venue"
},
  "geometry": {"coordinates":[-86.065668,41.669318],"type":"Point"}
}