{
  "type": "Feature",
  "properties": {
    "addr:full":"3366 W 200 S Huntington IN 46750",
    "addr:housenumber":"3366",
    "addr:postcode":"46750",
    "addr:street":"W 200 S Huntington",
    "iso:country":"US",
    "sg:address":"3366 W 200 S",
    "sg:city":"Huntington",
    "sg:classifiers":[
        {
            "category":"Farming",
            "subcategory":"Farm",
            "type":"Manufacturing & Wholesale Goods"
        }
    ],
    "sg:phone":"+1 260 468 2475",
    "sg:postcode":"46750",
    "sg:province":"IN",
    "sg:tags":[
        "crop",
        "general"
    ],
    "wof:name":"Dudley Campbell",
    "wof:placetype":"venue"
},
  "geometry": {"coordinates":[-85.514172,40.799726],"type":"Point"}
}