{
  "type": "Feature",
  "properties": {
    "addr:full":"6431 Columbia Ave Hammond IN 46320",
    "addr:housenumber":"6431",
    "addr:postcode":"46320",
    "addr:street":"Columbia Ave",
    "iso:country":"US",
    "sg:address":"6431 Columbia Ave",
    "sg:city":"Hammond",
    "sg:classifiers":[
        {
            "category":"Government",
            "subcategory":"Office",
            "type":"Public Place"
        }
    ],
    "sg:phone":"+1 219 937 0381",
    "sg:postcode":"46320",
    "sg:province":"IN",
    "sg:tags":[
        "state",
        "resource"
    ],
    "wof:name":"Workforce Development Svc",
    "wof:placetype":"venue"
},
  "geometry": {"coordinates":[-87.50013800000001,41.597486],"type":"Point"}
}