{
  "type": "Feature",
  "properties": {
    "iso:country":"US",
    "sg:address":"7125 New Augusta Rd",
    "sg:city":"Indianapolis",
    "sg:classifiers":[
        {
            "category":"Manufacturing",
            "subcategory":"Printing",
            "type":"Manufacturing & Wholesale Goods"
        }
    ],
    "sg:phone":"+1 317 329 8198",
    "sg:postcode":"46268",
    "sg:province":"IN",
    "sg:tags":[
        "publisher"
    ],
    "wof:name":"Indy House Hunters",
    "wof:placetype":"venue"
},
  "geometry": {"coordinates":[-86.23646,39.883725],"type":"Point"}
}