{
  "type": "Feature",
  "properties": {
    "iso:country":"US",
    "sg:address":"701 W National Ave",
    "sg:city":"West Terre Haute",
    "sg:classifiers":[
        {
            "category":"Home & Garden",
            "subcategory":"Hardware",
            "type":"Retail Goods"
        }
    ],
    "sg:phone":"+1 812 533 2154",
    "sg:postcode":"47885",
    "sg:province":"IN",
    "wof:name":"Jacks Hardware",
    "wof:placetype":"venue"
},
  "geometry": {"coordinates":[-87.452266,39.464496],"type":"Point"}
}