{
  "type": "Feature",
  "properties": {
    "iso:country":"US",
    "sg:address":"9780 Lantern Rd",
    "sg:city":"Fishers",
    "sg:classifiers":[
        {
            "category":"Health Services",
            "subcategory":"Health Practitioner",
            "type":"Services"
        }
    ],
    "sg:phone":"+1 317 578 4213",
    "sg:postcode":"46037",
    "sg:province":"IN",
    "sg:tags":[
        "psychologist"
    ],
    "wof:name":"Medical Psychology Assoc",
    "wof:placetype":"venue"
},
  "geometry": {"coordinates":[-86.013717,39.930337],"type":"Point"}
}