{
  "type": "Feature",
  "properties": {
    "addr:full":"117 Cicero Rd Noblesville IN 46060",
    "addr:housenumber":"117",
    "addr:postcode":"46060",
    "addr:street":"Cicero Rd",
    "iso:country":"US",
    "sg:address":"117 Cicero Rd",
    "sg:city":"Noblesville",
    "sg:classifiers":[
        {
            "category":"Manufacturing",
            "subcategory":"Motor Vehicles & Parts",
            "type":"Manufacturing & Wholesale Goods"
        }
    ],
    "sg:phone":"+1 317 773 2608",
    "sg:postcode":"46060",
    "sg:province":"IN",
    "sg:tags":[
        "equipment",
        "transportation"
    ],
    "wof:name":"Schwartz's Trailer Sales",
    "wof:placetype":"venue"
},
  "geometry": {"coordinates":[-86.01618999999999,40.048738],"type":"Point"}
}