{
  "type": "Feature",
  "properties": {
    "iso:country":"US",
    "sg:address":"2107 Franklin St",
    "sg:city":"Michigan City",
    "sg:classifiers":[
        {
            "category":"Manufacturing",
            "subcategory":"Printing",
            "type":"Manufacturing & Wholesale Goods"
        }
    ],
    "sg:phone":"+1 219 874 2223",
    "sg:postcode":"46360",
    "sg:province":"IN",
    "sg:tags":[
        "printer"
    ],
    "wof:name":"Express Press",
    "wof:placetype":"venue"
},
  "geometry": {"coordinates":[-86.89536,41.704352],"type":"Point"}
}