{
  "type": "Feature",
  "properties": {
    "iso:country":"US",
    "sg:address":"2929 16th St",
    "sg:city":"Bedford",
    "sg:classifiers":[
        {
            "category":"Building & Trades",
            "subcategory":"Electrical",
            "type":"Services"
        }
    ],
    "sg:phone":"+1 812 277 3153",
    "sg:postcode":"47421",
    "sg:province":"IN",
    "sg:tags":[
        "electrical",
        "contractor"
    ],
    "wof:name":"Wo Public Service of",
    "wof:placetype":"venue"
},
  "geometry": {"coordinates":[-86.512053,38.861041],"type":"Point"}
}