{
  "type": "Feature",
  "properties": {
    "iso:country":"US",
    "sg:address":"51 Jefferson St",
    "sg:city":"Valparaiso",
    "sg:classifiers":[
        {
            "category":"Professional",
            "subcategory":"Management & Consulting",
            "type":"Services"
        }
    ],
    "sg:phone":"+1 219 548 8677",
    "sg:postcode":"46383",
    "sg:province":"IN",
    "sg:tags":[
        "consultant",
        "industrial"
    ],
    "wof:name":"Vanguard Solutions Inc",
    "wof:placetype":"venue"
},
  "geometry": {"coordinates":[-87.061526,41.468863],"type":"Point"}
}