{
  "type": "Feature",
  "properties": {
    "iso:country":"US",
    "sg:address":"6634 Victoria Ct",
    "sg:city":"Demotte",
    "sg:classifiers":[
        {
            "category":"Professional",
            "type":"Services"
        }
    ],
    "sg:phone":"+1 219 987 2605",
    "sg:postcode":"46310",
    "sg:province":"IN",
    "wof:name":"R & C Applications Inc",
    "wof:placetype":"venue"
},
  "geometry": {"coordinates":[-87.173463,41.201972],"type":"Point"}
}