{
  "type": "Feature",
  "properties": {
    "addr:full":"11874 E Co Rd 50 N Seymour IN 47274",
    "addr:housenumber":"11874;50 n",
    "addr:postcode":"47274",
    "addr:street":"E Co Rd",
    "iso:country":"US",
    "sg:address":"11874 E Co Rd 50 N",
    "sg:city":"Seymour",
    "sg:classifiers":[
        {
            "category":"Organizations",
            "subcategory":"Religious Organization",
            "type":"Services"
        }
    ],
    "sg:phone":"+1 812 523 3717",
    "sg:postcode":"47274",
    "sg:province":"IN",
    "sg:tags":[
        "church"
    ],
    "wof:name":"New Hope Ch Of The Brethren",
    "wof:placetype":"venue"
},
  "geometry": {"coordinates":[-85.817043,38.889327],"type":"Point"}
}