{
  "type": "Feature",
  "properties": {
    "addr:full":"12109 Broadway St Indianapolis IN 46236",
    "addr:housenumber":"12109",
    "addr:postcode":"46236",
    "addr:street":"Broadway St",
    "iso:country":"US",
    "sg:address":"12109 Broadway St",
    "sg:city":"Indianapolis",
    "sg:classifiers":[
        {
            "category":"Manufacturing",
            "subcategory":"Metals",
            "type":"Manufacturing & Wholesale Goods"
        }
    ],
    "sg:phone":"+1 317 826 4894",
    "sg:postcode":"46236",
    "sg:province":"IN",
    "sg:tags":[
        "fire",
        "hydrant"
    ],
    "wof:name":"Burton's Hydrant Svc",
    "wof:placetype":"venue"
},
  "geometry": {"coordinates":[-85.95199100000001,39.878931],"type":"Point"}
}