{
  "type": "Feature",
  "properties": {
    "iso:country":"US",
    "sg:address":"1497 S Jackson St",
    "sg:city":"Salem",
    "sg:classifiers":[
        {
            "category":"Personal",
            "subcategory":"Beauty Salon",
            "type":"Services"
        }
    ],
    "sg:phone":"+1 812 883 6300",
    "sg:postcode":"47167",
    "sg:province":"IN",
    "wof:name":"Suburban Styles",
    "wof:placetype":"venue"
},
  "geometry": {"coordinates":[-86.082898,38.597439],"type":"Point"}
}