{
  "type": "Feature",
  "properties": {
    "iso:country":"US",
    "sg:address":"7489 State Rd 135",
    "sg:city":"Pekin",
    "sg:classifiers":[
        {
            "category":"Retail",
            "subcategory":"Auto Repair",
            "type":"Services"
        }
    ],
    "sg:phone":"+1 812 883 5252",
    "sg:postcode":"47165",
    "sg:province":"IN",
    "sg:tags":[
        "repairing",
        "automobile"
    ],
    "wof:name":"J & J Complete Automotive Svc",
    "wof:placetype":"venue"
},
  "geometry": {"coordinates":[-86.10021999999999,38.492436],"type":"Point"}
}