{
  "type": "Feature",
  "properties": {
    "iso:country":"US",
    "sg:address":"8325 Covington Rd",
    "sg:city":"Fort Wayne",
    "sg:classifiers":[
        {
            "category":"Retail",
            "subcategory":"Funeral Services",
            "type":"Services"
        }
    ],
    "sg:phone":"+1 260 426 9494",
    "sg:postcode":"46804",
    "sg:province":"IN",
    "sg:tags":[
        "director"
    ],
    "wof:name":"D O Mc Comb & Sons Funeral Hms",
    "wof:placetype":"venue"
},
  "geometry": {"coordinates":[-85.252432,41.059648],"type":"Point"}
}