{
  "type": "Feature",
  "properties": {
    "iso:country":"US",
    "sg:address":"6882 E Co Rd 100 S",
    "sg:city":"Avon",
    "sg:classifiers":[
        {
            "category":"Building & Trades",
            "subcategory":"Cleaning & Sanitation",
            "type":"Services"
        }
    ],
    "sg:phone":"+1 317 839 0799",
    "sg:postcode":"46123",
    "sg:province":"IN",
    "sg:tags":[
        "polishing",
        "waxing",
        "floor"
    ],
    "wof:name":"Executive Maintenance",
    "wof:placetype":"venue"
},
  "geometry": {"coordinates":[-86.399673,39.748064],"type":"Point"}
}