{
  "type": "Feature",
  "properties": {
    "iso:country":"US",
    "sg:address":"3501 N Granville Ave",
    "sg:city":"Muncie",
    "sg:classifiers":[
        {
            "category":"Shopping",
            "subcategory":"Jewelry",
            "type":"Retail Goods"
        }
    ],
    "sg:phone":"+1 765 282 7628",
    "sg:postcode":"47303",
    "sg:province":"IN",
    "sg:tags":[
        "jeweler"
    ],
    "wof:name":"Y J 333 Fashion",
    "wof:placetype":"venue"
},
  "geometry": {"coordinates":[-85.37379199999999,40.219741],"type":"Point"}
}