{
  "type": "Feature",
  "properties": {
    "addr:full":"8354 S Shoreview Dr Trafalgar IN 46181",
    "addr:housenumber":"8354",
    "addr:postcode":"46181",
    "addr:street":"S Shoreview Dr",
    "iso:country":"US",
    "sg:address":"8354 S Shoreview Dr",
    "sg:city":"Trafalgar",
    "sg:classifiers":[
        {
            "category":"Retail",
            "subcategory":"Repair Shop",
            "type":"Services"
        }
    ],
    "sg:phone":"+1 317 878 4728",
    "sg:postcode":"46181",
    "sg:province":"IN",
    "sg:tags":[
        "welding"
    ],
    "wof:name":"Southeastern Welding Supply",
    "wof:placetype":"venue"
},
  "geometry": {"coordinates":[-86.19097600000001,39.354001],"type":"Point"}
}