{
  "type": "Feature",
  "properties": {
    "iso:country":"US",
    "sg:address":"502 Glasgow Ave",
    "sg:city":"Fort Wayne",
    "sg:classifiers":[
        {
            "category":"Shopping",
            "type":"Retail Goods"
        }
    ],
    "sg:phone":"+1 260 422 7961",
    "sg:postcode":"46803",
    "sg:province":"IN",
    "sg:tags":[
        "monument"
    ],
    "wof:name":"Straub Bros Inc",
    "wof:placetype":"venue"
},
  "geometry": {"coordinates":[-85.109363,41.081034],"type":"Point"}
}