{
  "type": "Feature",
  "properties": {
    "addr:full":"2705 E Walnut St Evansville IN 47714",
    "addr:housenumber":"2705",
    "addr:postcode":"47714",
    "addr:street":"E Walnut St",
    "iso:country":"US",
    "sg:address":"2705 E Walnut St",
    "sg:city":"Evansville",
    "sg:classifiers":[
        {
            "category":"Building & Trades",
            "subcategory":"Construction",
            "type":"Services"
        }
    ],
    "sg:phone":"+1 812 477 4051",
    "sg:postcode":"47714",
    "sg:province":"IN",
    "sg:tags":[
        "painter"
    ],
    "wof:name":"Mayes Coatings Inc",
    "wof:placetype":"venue"
},
  "geometry": {"coordinates":[-87.51522,37.973352],"type":"Point"}
}