{
  "type": "Feature",
  "properties": {
    "iso:country":"US",
    "sg:address":"6417 Lilac Rd",
    "sg:city":"Plymouth",
    "sg:classifiers":[
        {
            "category":"Organizations",
            "subcategory":"Religious Organization",
            "type":"Services"
        }
    ],
    "sg:phone":"+1 574 935 4343",
    "sg:postcode":"46563",
    "sg:province":"IN",
    "wof:name":"Pete Wardlow Pastor",
    "wof:placetype":"venue"
},
  "geometry": {"coordinates":[-86.290813,41.384711],"type":"Point"}
}