{
  "type": "Feature",
  "properties": {
    "iso:country":"US",
    "sg:address":"3565 S 500 W",
    "sg:city":"New Palestine",
    "sg:classifiers":[
        {
            "category":"Organizations",
            "subcategory":"Religious Organization",
            "type":"Services"
        }
    ],
    "sg:phone":"+1 317 861 4390",
    "sg:postcode":"46163",
    "sg:province":"IN",
    "sg:tags":[
        "church"
    ],
    "sg:website":"www.npumc.com",
    "wof:name":"New Palestine United Methodist",
    "wof:placetype":"venue"
},
  "geometry": {"coordinates":[-85.895593,39.731597],"type":"Point"}
}