{
  "type": "Feature",
  "properties": {
    "iso:country":"US",
    "sg:address":"9895 State Rd 11",
    "sg:city":"Seymour",
    "sg:classifiers":[
        {
            "category":"Autos & Motor Vehicles",
            "subcategory":"Automobile Sales",
            "type":"Retail Goods"
        }
    ],
    "sg:phone":"+1 812 524 8000",
    "sg:postcode":"47274",
    "sg:province":"IN",
    "sg:tags":[
        "car",
        "dealer"
    ],
    "wof:name":"Luedeman's Auto Sales",
    "wof:placetype":"venue"
},
  "geometry": {"coordinates":[-85.891266,39.024298],"type":"Point"}
}