{
  "type": "Feature",
  "properties": {
    "iso:country":"US",
    "sg:address":"13304 W 181st Ave",
    "sg:city":"Lowell",
    "sg:classifiers":[
        {
            "category":"Professional",
            "subcategory":"Business Services",
            "type":"Services"
        }
    ],
    "sg:phone":"+1 219 696 7212",
    "sg:postcode":"46356",
    "sg:province":"IN",
    "sg:tags":[
        "auctioneer"
    ],
    "wof:name":"Rick Niemeyer Auctioneer",
    "wof:placetype":"venue"
},
  "geometry": {"coordinates":[-87.49193200000001,41.290171],"type":"Point"}
}