{
  "type": "Feature",
  "properties": {
    "iso:country":"US",
    "sg:address":"404 S Main St",
    "sg:city":"Elkhart",
    "sg:classifiers":[
        {
            "category":"Personal",
            "subcategory":"Beauty Salon",
            "type":"Services"
        }
    ],
    "sg:phone":"+1 574 293 2651",
    "sg:postcode":"46516",
    "sg:province":"IN",
    "sg:tags":[
        "school"
    ],
    "wof:name":"Elkhart Beauty College",
    "wof:placetype":"venue"
},
  "geometry": {"coordinates":[-85.97145,41.683386],"type":"Point"}
}