{
  "type": "Feature",
  "properties": {
    "iso:country":"US",
    "sg:address":"3241 N Raceway Rd",
    "sg:city":"Indianapolis",
    "sg:classifiers":[
        {
            "category":"Home & Garden",
            "subcategory":"Furniture",
            "type":"Retail Goods"
        }
    ],
    "sg:phone":"+1 317 298 7594",
    "sg:postcode":"46234",
    "sg:province":"IN",
    "wof:name":"Bentleys Mattress & Box Co",
    "wof:placetype":"venue"
},
  "geometry": {"coordinates":[-86.327148,39.815476],"type":"Point"}
}