{
  "type": "Feature",
  "properties": {
    "iso:country":"US",
    "sg:address":"55667 Currant Rd",
    "sg:city":"Mishawaka",
    "sg:classifiers":[
        {
            "category":"Wholesale",
            "subcategory":"Computers",
            "type":"Manufacturing & Wholesale Goods"
        }
    ],
    "sg:phone":"+1 574 234 1334",
    "sg:postcode":"46545",
    "sg:province":"IN",
    "sg:tags":[
        "peripheral",
        "mfg"
    ],
    "wof:name":"Cat Com Corporation",
    "wof:placetype":"venue"
},
  "geometry": {"coordinates":[-86.129067,41.681546],"type":"Point"}
}