{
  "type": "Feature",
  "properties": {
    "iso:country":"US",
    "sg:address":"11815 Technology Dr",
    "sg:city":"Fishers",
    "sg:classifiers":[
        {
            "category":"Home & Garden",
            "subcategory":"Home Furnishings",
            "type":"Retail Goods"
        }
    ],
    "sg:phone":"+1 317 577 2670",
    "sg:postcode":"46038",
    "sg:province":"IN",
    "sg:tags":[
        "venetian",
        "blind"
    ],
    "wof:name":"MCL Window Coverings",
    "wof:placetype":"venue"
},
  "geometry": {"coordinates":[-86.012115,39.962484],"type":"Point"}
}