{
  "type": "Feature",
  "properties": {
    "iso:country":"US",
    "sg:address":"119 N 2nd St",
    "sg:city":"Decatur",
    "sg:classifiers":[
        {
            "category":"Shopping",
            "subcategory":"Used Merchandise",
            "type":"Retail Goods"
        }
    ],
    "sg:phone":"+1 260 724 9774",
    "sg:postcode":"46733",
    "sg:province":"IN",
    "sg:tags":[
        "shop",
        "consignment"
    ],
    "wof:name":"Hope Chest",
    "wof:placetype":"venue"
},
  "geometry": {"coordinates":[-84.924412,40.831103],"type":"Point"}
}