{
  "type": "Feature",
  "properties": {
    "iso:country":"US",
    "sg:address":"216 Lafayette Ave",
    "sg:city":"Crawfordsville",
    "sg:classifiers":[
        {
            "category":"Professional",
            "subcategory":"Business Services",
            "type":"Services"
        }
    ],
    "sg:phone":"+1 765 362 6340",
    "sg:postcode":"47933",
    "sg:province":"IN",
    "sg:tags":[
        "water",
        "treatment"
    ],
    "wof:name":"Puritan Water Conditioning Inc",
    "wof:placetype":"venue"
},
  "geometry": {"coordinates":[-86.904062,40.043421],"type":"Point"}
}