{
  "type": "Feature",
  "properties": {
    "iso:country":"US",
    "sg:address":"218 Cross County Plz",
    "sg:city":"Batesville",
    "sg:classifiers":[
        {
            "category":"Shopping",
            "subcategory":"Department Store",
            "type":"Retail Goods"
        }
    ],
    "sg:phone":"+1 812 934 5475",
    "sg:postcode":"47006",
    "sg:province":"IN",
    "wof:name":"Peebles",
    "wof:placetype":"venue"
},
  "geometry": {"coordinates":[-85.214257,39.309995],"type":"Point"}
}