{
  "type": "Feature",
  "properties": {
    "iso:country":"US",
    "sg:address":"6842 E Co Rd 350 N",
    "sg:city":"Brownsburg",
    "sg:classifiers":[
        {
            "category":"Home & Garden",
            "subcategory":"Building Materials",
            "type":"Retail Goods"
        }
    ],
    "sg:phone":"+1 317 852 6382",
    "sg:postcode":"46112",
    "sg:province":"IN",
    "sg:tags":[
        "door"
    ],
    "wof:name":"All Doors Ind Coml Residential",
    "wof:placetype":"venue"
},
  "geometry": {"coordinates":[-86.40372,39.810526],"type":"Point"}
}