{
  "type": "Feature",
  "properties": {
    "iso:country":"US",
    "sg:address":"749 N 9th St",
    "sg:city":"Clinton",
    "sg:classifiers":[
        {
            "category":"Shopping",
            "type":"Retail Goods"
        }
    ],
    "sg:phone":"+1 765 832 9561",
    "sg:postcode":"47842",
    "sg:province":"IN",
    "sg:tags":[
        "pet",
        "food",
        "supply"
    ],
    "wof:name":"9th Street Feed Mart",
    "wof:placetype":"venue"
},
  "geometry": {"coordinates":[-87.408157,39.667308],"type":"Point"}
}