{
  "type": "Feature",
  "properties": {
    "iso:country":"US",
    "sg:address":"8320 Kennedy Ave",
    "sg:city":"Highland",
    "sg:classifiers":[
        {
            "category":"Health Services",
            "subcategory":"Doctor",
            "type":"Services"
        }
    ],
    "sg:phone":"+1 219 923 5318",
    "sg:postcode":"46322",
    "sg:province":"IN",
    "sg:tags":[
        "physician",
        "surgeon"
    ],
    "wof:name":"Wahbi Adad MD",
    "wof:placetype":"venue"
},
  "geometry": {"coordinates":[-87.461728,41.562693],"type":"Point"}
}