{
  "type": "Feature",
  "properties": {
    "addr:full":"3930 E Curby Rd English IN 47118",
    "addr:housenumber":"3930",
    "addr:postcode":"47118",
    "addr:street":"E Curby Rd",
    "iso:country":"US",
    "sg:address":"3930 E Curby Rd",
    "sg:city":"English",
    "sg:classifiers":[
        {
            "category":"Wholesale",
            "subcategory":"Meat",
            "type":"Manufacturing & Wholesale Goods"
        }
    ],
    "sg:phone":"+1 812 739 4406",
    "sg:postcode":"47118",
    "sg:province":"IN",
    "sg:tags":[
        "poultry",
        "plant",
        "processing"
    ],
    "wof:name":"Tyson Foods Inc",
    "wof:placetype":"venue"
},
  "geometry": {"coordinates":[-86.38153200000001,38.283747],"type":"Point"}
}