{
  "type": "Feature",
  "properties": {
    "iso:country":"US",
    "sg:address":"4635 W 30th St",
    "sg:city":"Indianapolis",
    "sg:classifiers":[
        {
            "category":"Social Services",
            "subcategory":"Child Care",
            "type":"Services"
        }
    ],
    "sg:phone":"+1 317 280 0057",
    "sg:postcode":"46222",
    "sg:province":"IN",
    "wof:name":"Lil Dreamerz R First LLC",
    "wof:placetype":"venue"
},
  "geometry": {"coordinates":[-86.239052,39.809298],"type":"Point"}
}