{
  "type": "Feature",
  "properties": {
    "iso:country":"US",
    "sg:address":"333 W Washington St",
    "sg:city":"Martinsville",
    "sg:classifiers":[
        {
            "category":"Recreation",
            "type":"Entertainment"
        }
    ],
    "sg:phone":"+1 765 349 8980",
    "sg:postcode":"46151",
    "sg:province":"IN",
    "sg:tags":[
        "instruction",
        "gymnastic"
    ],
    "wof:name":"Martinsville Academy",
    "wof:placetype":"venue"
},
  "geometry": {"coordinates":[-86.432756,39.42683],"type":"Point"}
}