{
  "type": "Feature",
  "properties": {
    "addr:full":"9105 E 56th St Indianapolis IN 46226",
    "addr:housenumber":"9105",
    "addr:postcode":"46226",
    "addr:street":"E 56Th St",
    "iso:country":"US",
    "sg:address":"9105 E 56th St",
    "sg:city":"Indianapolis",
    "sg:classifiers":[
        {
            "category":"Restaurant",
            "type":"Food & Drink"
        }
    ],
    "sg:phone":"+1 317 545 4200",
    "sg:postcode":"46226",
    "sg:province":"IN",
    "wof:name":"Mozzi's Pizza",
    "wof:placetype":"venue"
},
  "geometry": {"coordinates":[-86.00582199999999,39.855421],"type":"Point"}
}