{
  "type": "Feature",
  "properties": {
    "iso:country":"US",
    "sg:address":"244 N College Ave",
    "sg:city":"Indianapolis",
    "sg:classifiers":[
        {
            "category":"Professional",
            "subcategory":"Lawyer & Legal Services",
            "type":"Services"
        }
    ],
    "sg:phone":"+1 317 634 2332",
    "sg:postcode":"46202",
    "sg:province":"IN",
    "sg:tags":[
        "attorney"
    ],
    "wof:name":"C Jefferson Cragen",
    "wof:placetype":"venue"
},
  "geometry": {"coordinates":[-86.145598,39.770493],"type":"Point"}
}