{
  "type": "Feature",
  "properties": {
    "iso:country":"US",
    "sg:address":"1155 W Jefferson St",
    "sg:city":"Franklin",
    "sg:classifiers":[
        {
            "category":"Health Services",
            "subcategory":"Doctor",
            "type":"Services"
        }
    ],
    "sg:phone":"+1 317 346 3883",
    "sg:postcode":"46131",
    "sg:province":"IN",
    "sg:tags":[
        "physician",
        "surgeon"
    ],
    "wof:name":"JMH Health Affiliates",
    "wof:placetype":"venue"
},
  "geometry": {"coordinates":[-86.075312,39.480109],"type":"Point"}
}