{
  "type": "Feature",
  "properties": {
    "iso:country":"US",
    "sg:address":"10400 Clifford Ct",
    "sg:city":"Brownsburg",
    "sg:phone":"+1 317 297 4631",
    "sg:postcode":"46112",
    "sg:province":"IN",
    "wof:name":"Hiland Inventory Specialists",
    "wof:placetype":"venue"
},
  "geometry": {"coordinates":[-86.340022,39.828789],"type":"Point"}
}