{
  "type": "Feature",
  "properties": {
    "iso:country":"US",
    "sg:address":"4230 Madison Ave",
    "sg:city":"Indianapolis",
    "sg:classifiers":[
        {
            "category":"Shopping",
            "subcategory":"Computers & Home Electronics",
            "type":"Retail Goods"
        }
    ],
    "sg:phone":"+1 317 582 0077",
    "sg:postcode":"46227",
    "sg:province":"IN",
    "sg:tags":[
        "equipment",
        "satellite",
        "system"
    ],
    "wof:name":"Dr Dish's Selective Satellite",
    "wof:placetype":"venue"
},
  "geometry": {"coordinates":[-86.140733,39.704587],"type":"Point"}
}