{
  "type": "Feature",
  "properties": {
    "iso:country":"US",
    "sg:address":"5917 Lima Rd",
    "sg:city":"Fort Wayne",
    "sg:classifiers":[
        {
            "category":"Autos & Motor Vehicles",
            "subcategory":"Fuel & Gas Station",
            "type":"Retail Goods"
        }
    ],
    "sg:phone":"+1 260 489 3027",
    "sg:postcode":"46818",
    "sg:province":"IN",
    "sg:tags":[
        "oil"
    ],
    "sg:website":"www.lassus.com",
    "wof:name":"Lassus Bros Handy Dandy Bp",
    "wof:placetype":"venue"
},
  "geometry": {"coordinates":[-85.161744,41.136442],"type":"Point"}
}