{
  "type": "Feature",
  "properties": {
    "addr:full":"57696 8th St Elkhart IN 46517",
    "addr:housenumber":"57696",
    "addr:postcode":"46517",
    "addr:street":"8Th St",
    "iso:country":"US",
    "sg:address":"57696 8th St",
    "sg:city":"Elkhart",
    "sg:classifiers":[
        {
            "category":"Wholesale",
            "subcategory":"Motor Vehicles",
            "type":"Manufacturing & Wholesale Goods"
        }
    ],
    "sg:phone":"+1 574 295 3550",
    "sg:postcode":"46517",
    "sg:province":"IN",
    "wof:name":"Drepin Motors Inc",
    "wof:placetype":"venue"
},
  "geometry": {"coordinates":[-85.97733100000001,41.655123],"type":"Point"}
}