{
  "type": "Feature",
  "properties": {
    "addr:full":"526 W 30th St Connersville IN 47331",
    "addr:housenumber":"526",
    "addr:postcode":"47331",
    "addr:street":"W 30Th St",
    "iso:country":"US",
    "sg:address":"526 W 30th St",
    "sg:city":"Connersville",
    "sg:classifiers":[
        {
            "category":"Personal",
            "subcategory":"Barber",
            "type":"Services"
        }
    ],
    "sg:phone":"+1 765 825 8815",
    "sg:postcode":"47331",
    "sg:province":"IN",
    "wof:name":"Bruce's Grandview Barber Ctr",
    "wof:placetype":"venue"
},
  "geometry": {"coordinates":[-85.135848,39.671662],"type":"Point"}
}