{
  "type": "Feature",
  "properties": {
    "iso:country":"US",
    "sg:address":"5833 W 5th Ave",
    "sg:city":"Gary",
    "sg:classifiers":[
        {
            "category":"Personal",
            "subcategory":"Beauty Salon",
            "type":"Services"
        }
    ],
    "sg:phone":"+1 219 977 9422",
    "sg:postcode":"46406",
    "sg:province":"IN",
    "wof:name":"Images Barber Shop",
    "wof:placetype":"venue"
},
  "geometry": {"coordinates":[-87.408562,41.601816],"type":"Point"}
}