{
  "type": "Feature",
  "properties": {
    "iso:country":"US",
    "sg:address":"6501 Grape Rd",
    "sg:city":"Mishawaka",
    "sg:classifiers":[
        {
            "category":"Restaurant",
            "type":"Food & Drink"
        }
    ],
    "sg:phone":"+1 574 243 1893",
    "sg:postcode":"46545",
    "sg:province":"IN",
    "sg:website":"www.mcdonald.com",
    "wof:name":"Mc Donald's",
    "wof:placetype":"venue"
},
  "geometry": {"coordinates":[-86.187781,41.716898],"type":"Point"}
}