{
  "type": "Feature",
  "properties": {
    "iso:country":"US",
    "sg:address":"6350 E 82nd St",
    "sg:city":"Indianapolis",
    "sg:classifiers":[
        {
            "category":"Utilities",
            "subcategory":"Telephone",
            "type":"Services"
        }
    ],
    "sg:phone":"+1 317 578 3517",
    "sg:postcode":"46250",
    "sg:province":"IN",
    "sg:tags":[
        "telecommunication"
    ],
    "wof:name":"Imagen Telecom",
    "wof:placetype":"venue"
},
  "geometry": {"coordinates":[-86.059525,39.905394],"type":"Point"}
}