{
  "type": "Feature",
  "properties": {
    "iso:country":"US",
    "sg:address":"712 E 7th St",
    "sg:city":"Auburn",
    "sg:classifiers":[
        {
            "category":"Freight",
            "type":"Transportation"
        }
    ],
    "sg:phone":"+1 260 927 1248",
    "sg:postcode":"46706",
    "sg:province":"IN",
    "sg:tags":[
        "hauling",
        "trucking"
    ],
    "wof:name":"Mcdowell Express Inc",
    "wof:placetype":"venue"
},
  "geometry": {"coordinates":[-85.04614599999999,41.367465],"type":"Point"}
}