{
  "type": "Feature",
  "properties": {
    "iso:country":"US",
    "sg:address":"9880 E 30th St",
    "sg:city":"Indianapolis",
    "sg:classifiers":[
        {
            "category":"Manufacturing",
            "subcategory":"Tools & Machinery",
            "type":"Manufacturing & Wholesale Goods"
        }
    ],
    "sg:phone":"+1 317 897 9880",
    "sg:postcode":"46229",
    "sg:province":"IN",
    "sg:tags":[
        "construction"
    ],
    "sg:website":"www.myte.com",
    "wof:name":"My-Te Products Inc",
    "wof:placetype":"venue"
},
  "geometry": {"coordinates":[-85.995588,39.811603],"type":"Point"}
}