{
  "type": "Feature",
  "properties": {
    "iso:country":"US",
    "sg:address":"8221 Stahl Dr",
    "sg:city":"Evansville",
    "sg:classifiers":[
        {
            "category":"Travel",
            "subcategory":"Hotels & Motels",
            "type":"Entertainment"
        }
    ],
    "sg:phone":"+1 812 853 0900",
    "sg:postcode":"47715",
    "sg:province":"IN",
    "sg:website":"valueplace.com",
    "wof:name":"Value Place Evansville",
    "wof:placetype":"venue"
},
  "geometry": {"coordinates":[-87.454031,37.963843],"type":"Point"}
}