{
  "type": "Feature",
  "properties": {
    "iso:country":"US",
    "sg:address":"8101 E Co Rd 400 N",
    "sg:city":"Muncie",
    "sg:classifiers":[
        {
            "category":"Freight",
            "type":"Transportation"
        }
    ],
    "sg:phone":"+1 765 744 0686",
    "sg:postcode":"47303",
    "sg:province":"IN",
    "sg:tags":[
        "operator",
        "local",
        "trucking"
    ],
    "wof:name":"Mathews Ron Trucking",
    "wof:placetype":"venue"
},
  "geometry": {"coordinates":[-85.292026,40.248535],"type":"Point"}
}