{
  "type": "Feature",
  "properties": {
    "addr:full":"1607 N Fares Ave Evansville IN 47711",
    "addr:housenumber":"1607",
    "addr:postcode":"47711",
    "addr:street":"N Fares Ave",
    "iso:country":"US",
    "sg:address":"1607 N Fares Ave",
    "sg:city":"Evansville",
    "sg:classifiers":[
        {
            "category":"Autos & Motor Vehicles",
            "subcategory":"Automobile Sales",
            "type":"Retail Goods"
        }
    ],
    "sg:phone":"+1 812 421 0027",
    "sg:postcode":"47711",
    "sg:province":"IN",
    "sg:tags":[
        "car",
        "dealer"
    ],
    "wof:name":"Brickyard Auto Sales",
    "wof:placetype":"venue"
},
  "geometry": {"coordinates":[-87.542813,37.992266],"type":"Point"}
}