{
  "type": "Feature",
  "properties": {
    "iso:country":"US",
    "sg:address":"65615 State Rd 15",
    "sg:city":"Goshen",
    "sg:classifiers":[
        {
            "category":"Food & Beverages",
            "subcategory":"Groceries & Convenience Stores",
            "type":"Retail Goods"
        }
    ],
    "sg:phone":"+1 574 534 1189",
    "sg:postcode":"46526",
    "sg:province":"IN",
    "wof:name":"Shaver's Stop & Shop",
    "wof:placetype":"venue"
},
  "geometry": {"coordinates":[-85.82818,41.537968],"type":"Point"}
}