{
  "type": "Feature",
  "properties": {
    "iso:country":"US",
    "sg:address":"515 Southbrook Dr",
    "sg:city":"Evansville",
    "sg:classifiers":[
        {
            "category":"Retail",
            "subcategory":"Repair Shop",
            "type":"Services"
        }
    ],
    "sg:phone":"+1 812 867 3191",
    "sg:postcode":"47711",
    "sg:province":"IN",
    "wof:name":"Dade Sharpening",
    "wof:placetype":"venue"
},
  "geometry": {"coordinates":[-87.554296,38.065834],"type":"Point"}
}