{
  "type": "Feature",
  "properties": {
    "iso:country":"US",
    "sg:address":"1080 S Indiana Ave",
    "sg:city":"Sellersburg",
    "sg:classifiers":[
        {
            "category":"Home & Garden",
            "subcategory":"Mobile Homes",
            "type":"Retail Goods"
        }
    ],
    "sg:phone":"+1 812 246 2949",
    "sg:postcode":"47172",
    "sg:province":"IN",
    "wof:name":"Dickson Mobile Homes Inc",
    "wof:placetype":"venue"
},
  "geometry": {"coordinates":[-85.75154,38.387429],"type":"Point"}
}