{
  "type": "Feature",
  "properties": {
    "iso:country":"US",
    "sg:address":"7732 S 500 W",
    "sg:city":"Trafalgar",
    "sg:classifiers":[
        {
            "category":"Professional",
            "type":"Services"
        }
    ],
    "sg:phone":"+1 317 878 5074",
    "sg:postcode":"46181",
    "sg:province":"IN",
    "wof:name":"Janice Fowler",
    "wof:placetype":"venue"
},
  "geometry": {"coordinates":[-86.19613,39.35888],"type":"Point"}
}