{
  "type": "Feature",
  "properties": {
    "addr:full":"9616 E 42nd St Indianapolis IN 46226",
    "addr:housenumber":"9616",
    "addr:postcode":"46226",
    "addr:street":"E 42Nd St",
    "iso:country":"US",
    "sg:address":"9616 E 42nd St",
    "sg:city":"Indianapolis",
    "sg:classifiers":[
        {
            "category":"Place Of Worship",
            "subcategory":"Church",
            "type":"Public Place"
        }
    ],
    "sg:phone":"+1 317 890 2740",
    "sg:postcode":"46226",
    "sg:province":"IN",
    "sg:tags":[
        "churches-baptist"
    ],
    "wof:name":"Mount Carmel Baptist Church",
    "wof:placetype":"venue"
},
  "geometry": {"coordinates":[-86.04637099999999,39.83308],"type":"Point"}
}