{
  "type": "Feature",
  "properties": {
    "addr:full":"105 N Gospel St Paoli IN 47454",
    "addr:housenumber":"105",
    "addr:postcode":"47454",
    "addr:street":"N Gospel St",
    "iso:country":"US",
    "sg:address":"105 N Gospel St",
    "sg:city":"Paoli",
    "sg:classifiers":[
        {
            "category":"Shopping",
            "subcategory":"Clothing, Apparel, & Fashions",
            "type":"Retail Goods"
        }
    ],
    "sg:phone":"+1 812 723 4111",
    "sg:postcode":"47454",
    "sg:province":"IN",
    "wof:name":"Lilysun Female Fashions",
    "wof:placetype":"venue"
},
  "geometry": {"coordinates":[-86.468524,38.557164],"type":"Point"}
}