{
  "type": "Feature",
  "properties": {
    "iso:country":"US",
    "sg:address":"6303 S Anthony Blvd",
    "sg:city":"Fort Wayne",
    "sg:classifiers":[
        {
            "category":"Organizations",
            "subcategory":"Non-profit Organization",
            "type":"Services"
        }
    ],
    "sg:phone":"+1 260 422 9999",
    "sg:postcode":"46816",
    "sg:province":"IN",
    "sg:tags":[
        "social"
    ],
    "wof:name":"Old Landmark Social Services &",
    "wof:placetype":"venue"
},
  "geometry": {"coordinates":[-85.112478,41.02715],"type":"Point"}
}