{
  "type": "Feature",
  "properties": {
    "iso:country":"US",
    "sg:address":"303 E 9th St",
    "sg:city":"Auburn",
    "sg:classifiers":[
        {
            "category":"Professional",
            "subcategory":"Business Services",
            "type":"Services"
        }
    ],
    "sg:phone":"+1 260 925 3899",
    "sg:postcode":"46706",
    "sg:province":"IN",
    "wof:name":"Claude Wallen Bail Bonds",
    "wof:placetype":"venue"
},
  "geometry": {"coordinates":[-85.052369,41.365814],"type":"Point"}
}