{
  "type": "Feature",
  "properties": {
    "iso:country":"US",
    "sg:address":"8844 Ruffian Ln",
    "sg:city":"Newburgh",
    "sg:classifiers":[
        {
            "category":"Real Estate",
            "subcategory":"Real Estate Agent",
            "type":"Services"
        }
    ],
    "sg:phone":"+1 812 490 6800",
    "sg:postcode":"47630",
    "sg:province":"IN",
    "wof:name":"Realty Group",
    "wof:placetype":"venue"
},
  "geometry": {"coordinates":[-87.411608,37.975686],"type":"Point"}
}