{
  "type": "Feature",
  "properties": {
    "iso:country":"US",
    "sg:address":"1131 N J St",
    "sg:city":"Richmond",
    "sg:classifiers":[
        {
            "category":"Personal",
            "subcategory":"Barber",
            "type":"Services"
        }
    ],
    "sg:phone":"+1 765 962 7154",
    "sg:postcode":"47374",
    "sg:province":"IN",
    "wof:name":"Wright's Barber Shop",
    "wof:placetype":"venue"
},
  "geometry": {"coordinates":[-84.885511,39.840517],"type":"Point"}
}