{
  "type": "Feature",
  "properties": {
    "iso:country":"US",
    "sg:address":"1065 E Waits Rd",
    "sg:city":"Kendallville",
    "sg:classifiers":[
        {
            "category":"Real Estate",
            "subcategory":"Real Estate Agent",
            "type":"Services"
        }
    ],
    "sg:phone":"+1 260 347 0598",
    "sg:postcode":"46755",
    "sg:province":"IN",
    "wof:name":"Hayden Realty Inc",
    "wof:placetype":"venue"
},
  "geometry": {"coordinates":[-85.248121,41.423628],"type":"Point"}
}