{
  "type": "Feature",
  "properties": {
    "iso:country":"US",
    "sg:address":"11080 N Pine Bluff Rd",
    "sg:city":"Bicknell",
    "sg:classifiers":[
        {
            "category":"Professional",
            "subcategory":"Business Services",
            "type":"Services"
        }
    ],
    "sg:phone":"+1 812 735 4438",
    "sg:postcode":"47512",
    "sg:province":"IN",
    "sg:tags":[
        "appraiser"
    ],
    "wof:name":"Stephen B Smith Appraiser",
    "wof:placetype":"venue"
},
  "geometry": {"coordinates":[-87.287859,38.841992],"type":"Point"}
}