{
  "type": "Feature",
  "properties": {
    "iso:country":"US",
    "sg:address":"6854 Hillsdale Ct",
    "sg:city":"Indianapolis",
    "sg:classifiers":[
        {
            "category":"Manufacturing",
            "subcategory":"Signs",
            "type":"Manufacturing & Wholesale Goods"
        }
    ],
    "sg:phone":"+1 317 577 1995",
    "sg:postcode":"46250",
    "sg:province":"IN",
    "wof:name":"Hightech Signs",
    "wof:placetype":"venue"
},
  "geometry": {"coordinates":[-86.049554,39.896242],"type":"Point"}
}