{
  "type": "Feature",
  "properties": {
    "addr:full":"11315 Rohrbach Rd Fort Wayne IN 46816",
    "addr:postcode":"11315;46816",
    "addr:street":"Rohrbach Rd",
    "iso:country":"US",
    "sg:address":"11315 Rohrbach Rd",
    "sg:city":"Fort Wayne",
    "sg:classifiers":[
        {
            "category":"Retail",
            "subcategory":"Auto Repair",
            "type":"Services"
        }
    ],
    "sg:phone":"+1 260 639 6002",
    "sg:postcode":"46816",
    "sg:province":"IN",
    "sg:tags":[
        "repairing",
        "automobile"
    ],
    "wof:name":"William's Service Ctr Inc",
    "wof:placetype":"venue"
},
  "geometry": {"coordinates":[-84.981712,40.999488],"type":"Point"}
}