{
  "type": "Feature",
  "properties": {
    "iso:country":"US",
    "sg:address":"2430 Riviera Dr",
    "sg:city":"Mishawaka",
    "sg:classifiers":[
        {
            "category":"Building & Trades",
            "subcategory":"Plumbing",
            "type":"Services"
        }
    ],
    "sg:phone":"+1 574 255 9067",
    "sg:postcode":"46544",
    "sg:province":"IN",
    "sg:tags":[
        "plumbing",
        "contractor"
    ],
    "wof:name":"G & E Plumbing Inc",
    "wof:placetype":"venue"
},
  "geometry": {"coordinates":[-86.139164,41.663311],"type":"Point"}
}