{
  "type": "Feature",
  "properties": {
    "iso:country":"US",
    "sg:address":"826 A St",
    "sg:city":"Portage",
    "sg:classifiers":[
        {
            "category":"Building & Trades",
            "subcategory":"Landscaping Services",
            "type":"Services"
        }
    ],
    "sg:phone":"+1 219 462 5293",
    "sg:postcode":"46350",
    "sg:province":"IN",
    "sg:tags":[
        "tree"
    ],
    "wof:name":"Terry Edmonds Tree Svc",
    "wof:placetype":"venue"
},
  "geometry": {"coordinates":[-86.719374,41.599659],"type":"Point"}
}