{
  "type": "Feature",
  "properties": {
    "iso:country":"US",
    "sg:address":"1105 Arundel Dr",
    "sg:city":"Kokomo",
    "sg:classifiers":[
        {
            "category":"Restaurant",
            "type":"Food & Drink"
        }
    ],
    "sg:phone":"+1 765 457 9156",
    "sg:postcode":"46901",
    "sg:province":"IN",
    "sg:tags":[
        "eating"
    ],
    "wof:name":"Chicken Place & More Inc",
    "wof:placetype":"venue"
},
  "geometry": {"coordinates":[-86.196806,40.474109],"type":"Point"}
}