{
  "type": "Feature",
  "properties": {
    "iso:country":"US",
    "sg:address":"1209 Bates St",
    "sg:city":"Indianapolis",
    "sg:classifiers":[
        {
            "category":"Manufacturing",
            "subcategory":"Tools & Machinery",
            "type":"Manufacturing & Wholesale Goods"
        }
    ],
    "sg:phone":"+1 317 636 8648",
    "sg:postcode":"46202",
    "sg:province":"IN",
    "sg:tags":[
        "pattern",
        "industrial"
    ],
    "wof:name":"Pattern Service Co",
    "wof:placetype":"venue"
},
  "geometry": {"coordinates":[-86.13694099999999,39.762776],"type":"Point"}
}