{
  "type": "Feature",
  "properties": {
    "iso:country":"US",
    "sg:address":"6510 Broadway",
    "sg:city":"Merrillville",
    "sg:classifiers":[
        {
            "category":"Wholesale",
            "subcategory":"Dairy",
            "type":"Manufacturing & Wholesale Goods"
        }
    ],
    "sg:phone":"+1 219 980 0800",
    "sg:postcode":"46410",
    "sg:province":"IN",
    "sg:tags":[
        "frozen",
        "dessert",
        "ice",
        "cream"
    ],
    "wof:name":"Dairy Rich Ice Cream",
    "wof:placetype":"venue"
},
  "geometry": {"coordinates":[-87.336119,41.49882],"type":"Point"}
}