{
  "type": "Feature",
  "properties": {
    "iso:country":"US",
    "sg:address":"420 E Jackson Blvd",
    "sg:city":"Elkhart",
    "sg:classifiers":[
        {
            "category":"Shopping",
            "subcategory":"Photographic Equipment",
            "type":"Retail Goods"
        }
    ],
    "sg:phone":"+1 574 295 1040",
    "sg:postcode":"46516",
    "sg:province":"IN",
    "sg:tags":[
        "supply"
    ],
    "sg:website":"www.elkhart-camera.com",
    "wof:name":"Elkhart Camera Ctr",
    "wof:placetype":"venue"
},
  "geometry": {"coordinates":[-85.967807,41.689015],"type":"Point"}
}