{
  "type": "Feature",
  "properties": {
    "iso:country":"US",
    "sg:address":"707 Pillsbury Ln",
    "sg:city":"New Albany",
    "sg:classifiers":[
        {
            "category":"Building & Trades",
            "subcategory":"Construction",
            "type":"Services"
        }
    ],
    "sg:phone":"+1 812 948 1398",
    "sg:postcode":"47150",
    "sg:province":"IN",
    "sg:tags":[
        "general",
        "contractor"
    ],
    "wof:name":"Merrick Construction Co",
    "wof:placetype":"venue"
},
  "geometry": {"coordinates":[-85.820693,38.327548],"type":"Point"}
}