{
  "type": "Feature",
  "properties": {
    "addr:full":"257 W 800 N Huntington IN 46750",
    "addr:housenumber":"257",
    "addr:postcode":"46750",
    "addr:street":"W 800 N",
    "iso:country":"US",
    "sg:address":"257 W 800 N",
    "sg:city":"Huntington",
    "sg:classifiers":[
        {
            "category":"Building & Trades",
            "subcategory":"Landscaping Services",
            "type":"Services"
        }
    ],
    "sg:phone":"+1 260 356 4429",
    "sg:postcode":"46750",
    "sg:province":"IN",
    "sg:tags":[
        "landscape",
        "contractor"
    ],
    "wof:name":"Lahr's Mowing & Landscape Svc",
    "wof:placetype":"venue"
},
  "geometry": {"coordinates":[-85.45654,40.94674],"type":"Point"}
}