{
  "type": "Feature",
  "properties": {
    "iso:country":"US",
    "sg:address":"611 Michigan Ave",
    "sg:city":"Laporte",
    "sg:classifiers":[
        {
            "category":"Wholesale",
            "subcategory":"Machinery & Supplies",
            "type":"Manufacturing & Wholesale Goods"
        }
    ],
    "sg:phone":"+1 219 362 1322",
    "sg:postcode":"46350",
    "sg:province":"IN",
    "sg:tags":[
        "forestry",
        "timber"
    ],
    "wof:name":"R & D Forest Products",
    "wof:placetype":"venue"
},
  "geometry": {"coordinates":[-86.721902,41.611857],"type":"Point"}
}