{
  "type": "Feature",
  "properties": {
    "addr:full":"12129 Ted Davis Rd Greens Fork IN 47345",
    "addr:housenumber":"12129",
    "addr:postcode":"47345",
    "addr:street":"Ted Davis Rd",
    "iso:country":"US",
    "sg:address":"12129 Ted Davis Rd",
    "sg:city":"Greens Fork",
    "sg:phone":"+1 765 478 6122",
    "sg:postcode":"47345",
    "sg:province":"IN",
    "sg:tags":[
        "farm",
        "corn",
        "soybean"
    ],
    "wof:name":"Robert Klein",
    "wof:placetype":"venue"
},
  "geometry": {"coordinates":[-85.099979,39.873617],"type":"Point"}
}