{
  "type": "Feature",
  "properties": {
    "addr:full":"5757 E Inlow Springs Rd Muncie IN 47302",
    "addr:housenumber":"5757",
    "addr:postcode":"47302",
    "addr:street":"E Inlow Springs Rd",
    "iso:country":"US",
    "sg:address":"5757 E Inlow Springs Rd",
    "sg:city":"Muncie",
    "sg:classifiers":[
        {
            "category":"Social Services",
            "type":"Services"
        }
    ],
    "sg:phone":"+1 765 288 0724",
    "sg:postcode":"47302",
    "sg:province":"IN",
    "sg:tags":[
        "youth",
        "organization",
        "center"
    ],
    "wof:name":"Boy Scouts Of America",
    "wof:placetype":"venue"
},
  "geometry": {"coordinates":[-85.313902,40.152366],"type":"Point"}
}