{
  "type": "Feature",
  "properties": {
    "iso:country":"US",
    "sg:address":"825 W Catalpa Dr",
    "sg:city":"Mishawaka",
    "sg:classifiers":[
        {
            "category":"Professional",
            "subcategory":"Research",
            "type":"Services"
        }
    ],
    "sg:phone":"+1 574 254 0506",
    "sg:postcode":"46545",
    "sg:province":"IN",
    "sg:tags":[
        "environmental",
        "ecological"
    ],
    "wof:name":"Advanced Sampling Tech Inc",
    "wof:placetype":"venue"
},
  "geometry": {"coordinates":[-86.18561099999999,41.69115],"type":"Point"}
}