{
  "type": "Feature",
  "properties": {
    "iso:country":"US",
    "sg:address":"723 E Market St",
    "sg:city":"Jeffersonville",
    "sg:classifiers":[
        {
            "category":"Building & Trades",
            "subcategory":"Plumbing",
            "type":"Services"
        }
    ],
    "sg:phone":"+1 812 288 9343",
    "sg:postcode":"47130",
    "sg:province":"IN",
    "sg:tags":[
        "heating",
        "contractor"
    ],
    "wof:name":"Kempf Heating & Cooling",
    "wof:placetype":"venue"
},
  "geometry": {"coordinates":[-85.730455,38.275108],"type":"Point"}
}