{
  "type": "Feature",
  "properties": {
    "iso:country":"US",
    "sg:address":"701 S 13th St",
    "sg:city":"Vincennes",
    "sg:classifiers":[
        {
            "category":"Real Estate",
            "subcategory":"Real Estate Operator",
            "type":"Services"
        }
    ],
    "sg:phone":"+1 812 882 2641",
    "sg:postcode":"47591",
    "sg:province":"IN",
    "sg:tags":[
        "building",
        "nonresidential",
        "general"
    ],
    "wof:name":"Slender You",
    "wof:placetype":"venue"
},
  "geometry": {"coordinates":[-87.52966,38.667054],"type":"Point"}
}