{
  "type": "Feature",
  "properties": {
    "iso:country":"US",
    "sg:address":"352 Chicago St",
    "sg:city":"Valparaiso",
    "sg:classifiers":[
        {
            "category":"Education",
            "subcategory":"School",
            "type":"Public Place"
        }
    ],
    "sg:phone":"+1 219 462 3374",
    "sg:postcode":"46383",
    "sg:province":"IN",
    "sg:website":"www.stpaulvalpo.org",
    "wof:name":"St Paul's Elementary School",
    "wof:placetype":"venue"
},
  "geometry": {"coordinates":[-87.517822,41.628356],"type":"Point"}
}