{
  "type": "Feature",
  "properties": {
    "iso:country":"US",
    "sg:address":"303 S 3rd St",
    "sg:city":"Elkhart",
    "sg:classifiers":[
        {
            "category":"Banks & Credit Unions",
            "subcategory":"Bank",
            "type":"Services"
        }
    ],
    "sg:phone":"+1 574 295 9600",
    "sg:postcode":"46516",
    "sg:province":"IN",
    "sg:website":"www.elkhartbank.com",
    "wof:name":"Elkhart Community Bank",
    "wof:placetype":"venue"
},
  "geometry": {"coordinates":[-85.97487,41.683368],"type":"Point"}
}