{
  "type": "Feature",
  "properties": {
    "iso:country":"US",
    "sg:address":"155 N Main St",
    "sg:city":"Linton",
    "sg:classifiers":[
        {
            "category":"Travel",
            "subcategory":"Travel Agent",
            "type":"Entertainment"
        }
    ],
    "sg:phone":"+1 812 847 8851",
    "sg:postcode":"47441",
    "sg:province":"IN",
    "sg:tags":[
        "agency",
        "bureau"
    ],
    "wof:name":"Travel Network",
    "wof:placetype":"venue"
},
  "geometry": {"coordinates":[-87.166054,39.035355],"type":"Point"}
}