{
  "type": "Feature",
  "properties": {
    "iso:country":"US",
    "sg:address":"2449 State St",
    "sg:city":"Lafayette",
    "sg:classifiers":[
        {
            "category":"Shopping",
            "subcategory":"Clothing, Apparel, & Fashions",
            "type":"Retail Goods"
        }
    ],
    "sg:phone":"+1 765 474 0662",
    "sg:postcode":"47905",
    "sg:province":"IN",
    "sg:tags":[
        "alteration"
    ],
    "wof:name":"Sewing Shop",
    "wof:placetype":"venue"
},
  "geometry": {"coordinates":[-86.868255,40.400582],"type":"Point"}
}