{
  "type": "Feature",
  "properties": {
    "iso:country":"US",
    "sg:address":"206 N Meridian St",
    "sg:city":"Pittsboro",
    "sg:classifiers":[
        {
            "category":"Education",
            "subcategory":"School",
            "type":"Public Place"
        }
    ],
    "sg:phone":"+1 317 892 2001",
    "sg:postcode":"46167",
    "sg:province":"IN",
    "wof:name":"Pittsboro Elementary School",
    "wof:placetype":"venue"
},
  "geometry": {"coordinates":[-86.46795899999999,39.865097],"type":"Point"}
}