{
  "type": "Feature",
  "properties": {
    "iso:country":"US",
    "sg:address":"2800 Wayne Trce",
    "sg:city":"Fort Wayne",
    "sg:classifiers":[
        {
            "category":"Manufacturing",
            "subcategory":"Printing",
            "type":"Manufacturing & Wholesale Goods"
        }
    ],
    "sg:phone":"+1 260 456 9600",
    "sg:postcode":"46803",
    "sg:province":"IN",
    "sg:tags":[
        "screen"
    ],
    "wof:name":"Custom Art Screen Printing Inc",
    "wof:placetype":"venue"
},
  "geometry": {"coordinates":[-85.101948,41.063378],"type":"Point"}
}