{
  "type": "Feature",
  "properties": {
    "iso:country":"US",
    "sg:address":"1301 Cliff Dr",
    "sg:city":"Logansport",
    "sg:classifiers":[
        {
            "category":"Building & Trades",
            "subcategory":"Construction",
            "type":"Services"
        }
    ],
    "sg:phone":"+1 574 753 9894",
    "sg:postcode":"46947",
    "sg:province":"IN",
    "sg:tags":[
        "house"
    ],
    "wof:name":"Wayne Builders",
    "wof:placetype":"venue"
},
  "geometry": {"coordinates":[-86.385928,40.745532],"type":"Point"}
}