{
  "type": "Feature",
  "properties": {
    "addr:full":"7001 Old State Rd 3 Otisco IN 47163",
    "addr:housenumber":"7001",
    "addr:postcode":"47163",
    "addr:street":"Old State Rd 3 Otisco",
    "iso:country":"US",
    "sg:address":"7001 Old State Rd 3",
    "sg:city":"Otisco",
    "sg:classifiers":[
        {
            "category":"Food & Beverages",
            "subcategory":"Groceries & Convenience Stores",
            "type":"Retail Goods"
        }
    ],
    "sg:phone":"+1 812 256 5518",
    "sg:postcode":"47163",
    "sg:province":"IN",
    "sg:tags":[
        "grocer"
    ],
    "wof:name":"H & B Grocery",
    "wof:placetype":"venue"
},
  "geometry": {"coordinates":[-85.6671,38.544622],"type":"Point"}
}