{
  "type": "Feature",
  "properties": {
    "iso:country":"US",
    "sg:address":"7659 Noel Rd",
    "sg:city":"Indianapolis",
    "sg:classifiers":[
        {
            "category":"Professional",
            "subcategory":"Management & Consulting",
            "type":"Services"
        },
        {
            "category":"Professional",
            "subcategory":"Employment Agencies",
            "type":"Services"
        }
    ],
    "sg:phone":"+1 317 872 6278",
    "sg:postcode":"46278",
    "sg:province":"IN",
    "sg:tags":[
        "consultant",
        "resource",
        "human"
    ],
    "wof:name":"Willie A Bush",
    "wof:placetype":"venue"
},
  "geometry": {"coordinates":[-86.29225099999999,39.891733],"type":"Point"}
}