{
  "type": "Feature",
  "properties": {
    "addr:full":"786 S State Rd 203 Lexington IN 47138",
    "addr:housenumber":"786;203",
    "addr:postcode":"47138",
    "addr:street":"S State Rd",
    "iso:country":"US",
    "sg:address":"786 S State Rd 203",
    "sg:city":"Lexington",
    "sg:phone":"+1 812 889 2053",
    "sg:postcode":"47138",
    "sg:province":"IN",
    "sg:tags":[
        "farm",
        "tobacco"
    ],
    "wof:name":"Shady Mirror Farm",
    "wof:placetype":"venue"
},
  "geometry": {"coordinates":[-85.65085500000001,38.67544],"type":"Point"}
}