{
  "type": "Feature",
  "properties": {
    "iso:country":"US",
    "sg:address":"319 Bank St",
    "sg:city":"New Albany",
    "sg:classifiers":[
        {
            "category":"Real Estate",
            "subcategory":"Architect",
            "type":"Services"
        }
    ],
    "sg:phone":"+1 812 945 2324",
    "sg:postcode":"47150",
    "sg:province":"IN",
    "wof:name":"Michell Timperman Ritz",
    "wof:placetype":"venue"
},
  "geometry": {"coordinates":[-85.821968,38.286132],"type":"Point"}
}