{
  "type": "Feature",
  "properties": {
    "iso:country":"US",
    "sg:address":"557 S Locke St",
    "sg:city":"Nappanee",
    "sg:classifiers":[
        {
            "category":"Building & Trades",
            "subcategory":"Construction",
            "type":"Services"
        }
    ],
    "sg:phone":"+1 574 773 4192",
    "sg:postcode":"46550",
    "sg:province":"IN",
    "sg:tags":[
        "house",
        "improvement",
        "home"
    ],
    "wof:name":"Rod's Trademark Remodeling Inc",
    "wof:placetype":"venue"
},
  "geometry": {"coordinates":[-86.00385,41.438476],"type":"Point"}
}