{
  "type": "Feature",
  "properties": {
    "iso:country":"US",
    "sg:address":"4249 Meadowlark Ct",
    "sg:city":"Indianapolis",
    "sg:classifiers":[
        {
            "category":"Shopping",
            "subcategory":"Music",
            "type":"Retail Goods"
        }
    ],
    "sg:phone":"+1 317 895 8545",
    "sg:postcode":"46226",
    "sg:province":"IN",
    "wof:name":"Fase Records Entertainment",
    "wof:placetype":"venue"
},
  "geometry": {"coordinates":[-86.021664,39.835644],"type":"Point"}
}