{
  "type": "Feature",
  "properties": {
    "iso:country":"US",
    "sg:address":"26 N Grant St",
    "sg:city":"Peru",
    "sg:classifiers":[
        {
            "category":"Restaurant",
            "type":"Food & Drink"
        }
    ],
    "sg:phone":"+1 765 472 3997",
    "sg:postcode":"46970",
    "sg:province":"IN",
    "wof:name":"Grant Street Bar & Grill",
    "wof:placetype":"venue"
},
  "geometry": {"coordinates":[-86.078537,40.750083],"type":"Point"}
}