{
  "type": "Feature",
  "properties": {
    "iso:country":"US",
    "sg:address":"3501 Winter St",
    "sg:city":"Fort Wayne",
    "sg:classifiers":[
        {
            "category":"Retail",
            "subcategory":"Auto Repair",
            "type":"Services"
        }
    ],
    "sg:phone":"+1 260 745 7547",
    "sg:postcode":"46806",
    "sg:province":"IN",
    "sg:tags":[
        "muffler",
        "exhaust",
        "system"
    ],
    "wof:name":"Butch's Exhaust",
    "wof:placetype":"venue"
},
  "geometry": {"coordinates":[-85.115945,41.051619],"type":"Point"}
}