{
  "type": "Feature",
  "properties": {
    "addr:full":"420 Main St Rochester IN 46975",
    "addr:housenumber":"420",
    "addr:postcode":"46975",
    "addr:street":"Main St",
    "iso:country":"US",
    "sg:address":"420 Main St",
    "sg:city":"Rochester",
    "sg:classifiers":[
        {
            "category":"Health Services",
            "subcategory":"Nursing And Care Facility",
            "type":"Services"
        }
    ],
    "sg:phone":"+1 574 224 4673",
    "sg:postcode":"46975",
    "sg:province":"IN",
    "sg:tags":[
        "hospice"
    ],
    "wof:name":"Hope Hospice Of Fulton County",
    "wof:placetype":"venue"
},
  "geometry": {"coordinates":[-86.215864,41.07006],"type":"Point"}
}