{
  "type": "Feature",
  "properties": {
    "iso:country":"US",
    "sg:address":"621 S Sugar St",
    "sg:city":"Brownstown",
    "sg:classifiers":[
        {
            "category":"Health Services",
            "subcategory":"Nursing And Care Facility",
            "type":"Services"
        }
    ],
    "sg:phone":"+1 812 358 2504",
    "sg:postcode":"47220",
    "sg:province":"IN",
    "sg:tags":[
        "home",
        "convalescent"
    ],
    "wof:name":"Hoosier Christian Village",
    "wof:placetype":"venue"
},
  "geometry": {"coordinates":[-86.043409,38.872093],"type":"Point"}
}