{
  "type": "Feature",
  "properties": {
    "addr:full":"2065 N 450 W Columbia City IN 46725",
    "addr:housenumber":"2065",
    "addr:postcode":"46725",
    "addr:street":"N 450 W",
    "iso:country":"US",
    "sg:address":"2065 N 450 W",
    "sg:city":"Columbia City",
    "sg:classifiers":[
        {
            "category":"Social Services",
            "type":"Services"
        }
    ],
    "sg:phone":"+1 260 327 3323",
    "sg:postcode":"46725",
    "sg:province":"IN",
    "sg:tags":[
        "organization",
        "welfare"
    ],
    "wof:name":"Black Lake Lodge-South",
    "wof:placetype":"venue"
},
  "geometry": {"coordinates":[-85.57768,41.193102],"type":"Point"}
}