{
  "type": "Feature",
  "properties": {
    "iso:country":"US",
    "sg:address":"30 N Emerson Ave",
    "sg:city":"Greenwood",
    "sg:classifiers":[
        {
            "category":"Health Services",
            "subcategory":"Doctor",
            "type":"Services"
        }
    ],
    "sg:phone":"+1 317 887 4004",
    "sg:postcode":"46143",
    "sg:province":"IN",
    "sg:tags":[
        "clinic"
    ],
    "sg:website":"www.indianaeyeclinic.com",
    "wof:name":"Indiana Eye Clinic Optical",
    "wof:placetype":"venue"
},
  "geometry": {"coordinates":[-86.08274,39.615771],"type":"Point"}
}