{
  "type": "Feature",
  "properties": {
    "addr:full":"7912 State Rd 32 Farmland IN 47340",
    "addr:housenumber":"7912;32;in",
    "addr:postcode":"47340",
    "addr:street":"State Rd",
    "iso:country":"US",
    "sg:address":"7912 State Rd 32",
    "sg:city":"Farmland",
    "sg:classifiers":[
        {
            "category":"Wholesale",
            "subcategory":"Farm Supplies",
            "type":"Manufacturing & Wholesale Goods"
        }
    ],
    "sg:phone":"+1 765 468 8320",
    "sg:postcode":"47340",
    "sg:province":"IN",
    "sg:tags":[
        "feed"
    ],
    "wof:name":"FPC Feed & Mfg",
    "wof:placetype":"venue"
},
  "geometry": {"coordinates":[-85.127122,40.175085],"type":"Point"}
}