{
  "type": "Feature",
  "properties": {
    "addr:full":"2511 E 46th St Indianapolis IN 46205",
    "addr:housenumber":"2511",
    "addr:postcode":"46205",
    "addr:street":"E 46Th St",
    "iso:country":"US",
    "sg:address":"2511 E 46th St",
    "sg:city":"Indianapolis",
    "sg:classifiers":[
        {
            "category":"Professional",
            "subcategory":"Employment Agencies",
            "type":"Services"
        }
    ],
    "sg:phone":"+1 317 541 9762",
    "sg:postcode":"46205",
    "sg:province":"IN",
    "sg:tags":[
        "opportunity"
    ],
    "wof:name":"Metro Staffing",
    "wof:placetype":"venue"
},
  "geometry": {"coordinates":[-86.119612,39.840176],"type":"Point"}
}