{
  "type": "Feature",
  "properties": {
    "iso:country":"US",
    "sg:address":"953 Maple Ave",
    "sg:city":"Noblesville",
    "sg:classifiers":[
        {
            "category":"Professional",
            "subcategory":"Lawyer & Legal Services",
            "type":"Services"
        }
    ],
    "sg:phone":"+1 317 773 4999",
    "sg:postcode":"46060",
    "sg:province":"IN",
    "sg:tags":[
        "attorney"
    ],
    "wof:name":"Murphy & Ziliak",
    "wof:placetype":"venue"
},
  "geometry": {"coordinates":[-86.012982,40.044597],"type":"Point"}
}