{
  "type": "Feature",
  "properties": {
    "iso:country":"US",
    "sg:address":"111 W Kirkwood Ave",
    "sg:city":"Bloomington",
    "sg:classifiers":[
        {
            "category":"Shopping",
            "subcategory":"Books",
            "type":"Retail Goods"
        }
    ],
    "sg:phone":"+1 812 336 7662",
    "sg:postcode":"47404",
    "sg:province":"IN",
    "sg:tags":[
        "dealer"
    ],
    "wof:name":"Howard's Bookstore",
    "wof:placetype":"venue"
},
  "geometry": {"coordinates":[-86.534772,39.166513],"type":"Point"}
}