{
  "type": "Feature",
  "properties": {
    "iso:country":"US",
    "sg:address":"1311 S School House Rd",
    "sg:city":"Vincennes",
    "sg:classifiers":[
        {
            "category":"Professional",
            "subcategory":"Employment Agencies",
            "type":"Services"
        }
    ],
    "sg:phone":"+1 812 886 5339",
    "sg:postcode":"47591",
    "sg:province":"IN",
    "sg:tags":[
        "help",
        "supply"
    ],
    "wof:name":"Vincennes Aviation Inc",
    "wof:placetype":"venue"
},
  "geometry": {"coordinates":[-87.562821,38.668735],"type":"Point"}
}