{
  "type": "Feature",
  "properties": {
    "iso:country":"US",
    "sg:address":"109 E Broadway St",
    "sg:city":"Loogootee",
    "sg:classifiers":[
        {
            "category":"Autos & Motor Vehicles",
            "subcategory":"Auto Supplies",
            "type":"Retail Goods"
        }
    ],
    "sg:phone":"+1 812 295 3140",
    "sg:postcode":"47553",
    "sg:province":"IN",
    "sg:tags":[
        "tire"
    ],
    "wof:name":"Smith's Tire & Lube",
    "wof:placetype":"venue"
},
  "geometry": {"coordinates":[-86.912038,38.675813],"type":"Point"}
}