{
  "type": "Feature",
  "properties": {
    "iso:country":"US",
    "sg:address":"64656 State Rd 19",
    "sg:city":"Goshen",
    "sg:classifiers":[
        {
            "category":"Building & Trades",
            "subcategory":"Construction",
            "type":"Services"
        }
    ],
    "sg:phone":"+1 574 862 4696",
    "sg:postcode":"46526",
    "sg:province":"IN",
    "sg:tags":[
        "residential",
        "nonresidential"
    ],
    "wof:name":"Zim Man Construction",
    "wof:placetype":"venue"
},
  "geometry": {"coordinates":[-86.001793,41.55974],"type":"Point"}
}