{
  "type": "Feature",
  "properties": {
    "iso:country":"US",
    "sg:address":"310 N 19th St",
    "sg:city":"Richmond",
    "sg:classifiers":[
        {
            "category":"Organizations",
            "subcategory":"Religious Organization",
            "type":"Services"
        }
    ],
    "sg:phone":"+1 765 939 2975",
    "sg:postcode":"47374",
    "sg:province":"IN",
    "sg:tags":[
        "church"
    ],
    "sg:website":"www.bethesdarichmond.org",
    "wof:name":"Bethesda Ministries",
    "wof:placetype":"venue"
},
  "geometry": {"coordinates":[-84.8765,39.834302],"type":"Point"}
}