{
  "type": "Feature",
  "properties": {
    "iso:country":"US",
    "sg:address":"637 E Washington St",
    "sg:city":"Orleans",
    "sg:classifiers":[
        {
            "category":"Arena",
            "subcategory":"Sports Club",
            "type":"Entertainment"
        }
    ],
    "sg:phone":"+1 812 865 2253",
    "sg:postcode":"47452",
    "sg:province":"IN",
    "sg:tags":[
        "athletic",
        "fields",
        "stadium"
    ],
    "wof:name":"Patton Field Ball Park",
    "wof:placetype":"venue"
},
  "geometry": {"coordinates":[-86.442959,38.661564],"type":"Point"}
}