{
  "type": "Feature",
  "properties": {
    "addr:full":"300 N West St Odon IN 47562",
    "addr:housenumber":"300",
    "addr:postcode":"47562",
    "addr:street":"N West St",
    "iso:country":"US",
    "sg:address":"300 N West St",
    "sg:city":"Odon",
    "sg:classifiers":[
        {
            "category":"Real Estate",
            "subcategory":"Real Estate Operator",
            "type":"Services"
        }
    ],
    "sg:phone":"+1 812 636 4996",
    "sg:postcode":"47562",
    "sg:province":"IN",
    "sg:tags":[
        "apartment"
    ],
    "wof:name":"Capehart Manor",
    "wof:placetype":"venue"
},
  "geometry": {"coordinates":[-86.996887,38.845341],"type":"Point"}
}