{
  "type": "Feature",
  "properties": {
    "iso:country":"US",
    "sg:address":"3619 Columbus Ave",
    "sg:city":"Anderson",
    "sg:classifiers":[
        {
            "category":"Retail",
            "subcategory":"Auto Repair",
            "type":"Services"
        }
    ],
    "sg:phone":"+1 765 643 4038",
    "sg:postcode":"46013",
    "sg:province":"IN",
    "sg:tags":[
        "automotive",
        "business"
    ],
    "wof:name":"Beldan Inc",
    "wof:placetype":"venue"
},
  "geometry": {"coordinates":[-85.667054,40.07812],"type":"Point"}
}