{
  "type": "Feature",
  "properties": {
    "addr:full":"620 Sawyer Rd Kendallville IN 46755",
    "addr:housenumber":"620",
    "addr:postcode":"46755",
    "addr:street":"Sawyer Rd",
    "iso:country":"US",
    "sg:address":"620 Sawyer Rd",
    "sg:city":"Kendallville",
    "sg:classifiers":[
        {
            "category":"Personal",
            "subcategory":"Beauty Salon",
            "type":"Services"
        }
    ],
    "sg:phone":"+1 260 599 0991",
    "sg:postcode":"46755",
    "sg:province":"IN",
    "sg:tags":[
        "manicuring"
    ],
    "wof:name":"Pro Nail",
    "wof:placetype":"venue"
},
  "geometry": {"coordinates":[-85.293944,41.452173],"type":"Point"}
}