{
  "type": "Feature",
  "properties": {
    "addr:full":"4636 St John Cir Zionsville IN 46077",
    "addr:housenumber":"4636",
    "addr:postcode":"46077",
    "addr:street":"St John Cir",
    "iso:country":"US",
    "sg:address":"4636 St John Cir",
    "sg:city":"Zionsville",
    "sg:classifiers":[
        {
            "category":"Farming",
            "subcategory":"Farm",
            "type":"Manufacturing & Wholesale Goods"
        }
    ],
    "sg:phone":"+1 317 873 4763",
    "sg:postcode":"46077",
    "sg:province":"IN",
    "sg:tags":[
        "crop",
        "general"
    ],
    "wof:name":"Allen Farm LLC",
    "wof:placetype":"venue"
},
  "geometry": {"coordinates":[-86.27764999999999,39.972128],"type":"Point"}
}