{
  "type": "Feature",
  "properties": {
    "iso:country":"US",
    "sg:address":"7025 Kensington Dr",
    "sg:city":"Indianapolis",
    "sg:classifiers":[
        {
            "category":"Personal",
            "subcategory":"Beauty Salon",
            "type":"Services"
        }
    ],
    "sg:phone":"+1 317 536 0056",
    "sg:postcode":"46226",
    "sg:province":"IN",
    "wof:name":"One Stop Pro Beauty Salon Svc",
    "wof:placetype":"venue"
},
  "geometry": {"coordinates":[-86.044798,39.820254],"type":"Point"}
}