{
  "type": "Feature",
  "properties": {
    "iso:country":"US",
    "sg:address":"114 N Mulberry St",
    "sg:city":"Muncie",
    "sg:classifiers":[
        {
            "category":"Restaurant",
            "type":"Food & Drink"
        }
    ],
    "sg:phone":"+1 765 282 3273",
    "sg:postcode":"47305",
    "sg:province":"IN",
    "wof:name":"Stirling's Bar & Eatery",
    "wof:placetype":"venue"
},
  "geometry": {"coordinates":[-85.385296,40.194403],"type":"Point"}
}