{
  "type": "Feature",
  "properties": {
    "addr:city":"Terre Haute",
    "addr:full":"1411 S 6Th St Terre Haute, In 47802-1114",
    "addr:house_number":"1411",
    "addr:housenumber":"1411",
    "addr:phone":"+1 812-235-9717",
    "addr:postcode":"47802-1114",
    "addr:road":"S 6Th St",
    "addr:state":"IN",
    "addr:street":"S 6Th St",
    "iso:country":"US",
    "sg:address":"1411 S 6th St",
    "sg:city":"Terre Haute",
    "sg:classifiers":[
        {
            "category":"Museum",
            "type":"Entertainment"
        }
    ],
    "sg:phone":"+1 812 235 9717",
    "sg:postcode":"47802",
    "sg:province":"IN",
    "sg:website":"www.vigohistory.com",
    "wof:airports":[
        102533957
    ],
    "wof:name":"Vigo County Historical Society",
    "wof:placetype":"venue"
},
  "geometry": {"coordinates":[-87.40997,39.45195],"type":"Point"}
}