{
  "type": "Feature",
  "properties": {
    "iso:country":"US",
    "sg:address":"1411 S 6th St",
    "sg:city":"Terre Haute",
    "sg:classifiers":[
        {
            "category":"Museum",
            "type":"Entertainment"
        }
    ],
    "sg:phone":"+1 812 235 9717",
    "sg:postcode":"47802",
    "sg:province":"IN",
    "sg:website":"www.vigohistory.com",
    "wof:name":"Museum Vigo County Historical",
    "wof:placetype":"venue"
},
  "geometry": {"coordinates":[-87.40994499999999,39.451258],"type":"Point"}
}