{
  "type": "Feature",
  "properties": {
    "iso:country":"US",
    "sg:address":"130 W Ireland Rd",
    "sg:city":"South Bend",
    "sg:classifiers":[
        {
            "category":"Autos & Motor Vehicles",
            "subcategory":"Auto Supplies",
            "type":"Retail Goods"
        }
    ],
    "sg:phone":"+1 574 231 9404",
    "sg:postcode":"46614",
    "sg:province":"IN",
    "sg:tags":[
        "automobile",
        "parts"
    ],
    "sg:website":"www.advanceautoparts.com",
    "wof:name":"Advance Auto Parts Inc",
    "wof:placetype":"venue"
},
  "geometry": {"coordinates":[-86.252005,41.62888],"type":"Point"}
}