{
  "type": "Feature",
  "properties": {
    "iso:country":"US",
    "sg:address":"7338 S Nineveh Rd",
    "sg:city":"Nineveh",
    "sg:classifiers":[
        {
            "category":"Insurance",
            "subcategory":"Insurance Agent",
            "type":"Services"
        }
    ],
    "sg:phone":"+1 317 933 2325",
    "sg:postcode":"46164",
    "sg:province":"IN",
    "wof:name":"Nineveh Insurance Inc",
    "wof:placetype":"venue"
},
  "geometry": {"coordinates":[-86.085171,39.365565],"type":"Point"}
}