{
  "type": "Feature",
  "properties": {
    "addr:full":"401 Porterfield Ave Richmond IN 47374",
    "addr:housenumber":"401",
    "addr:postcode":"47374",
    "addr:street":"Porterfield Ave",
    "iso:country":"US",
    "sg:address":"401 Porterfield Ave",
    "sg:city":"Richmond",
    "sg:classifiers":[
        {
            "category":"Freight",
            "type":"Transportation"
        }
    ],
    "sg:phone":"+1 765 962 5778",
    "sg:postcode":"47374",
    "sg:province":"IN",
    "sg:tags":[
        "commercial",
        "storage"
    ],
    "wof:name":"Westside Storage",
    "wof:placetype":"venue"
},
  "geometry": {"coordinates":[-84.93548199999999,39.825739],"type":"Point"}
}