{
  "type": "Feature",
  "properties": {
    "iso:country":"US",
    "sg:address":"930 Spring St",
    "sg:city":"Jeffersonville",
    "sg:classifiers":[
        {
            "category":"Health Services",
            "subcategory":"Doctor",
            "type":"Services"
        }
    ],
    "sg:phone":"+1 812 282 0443",
    "sg:postcode":"47130",
    "sg:province":"IN",
    "sg:tags":[
        "physician",
        "surgeon"
    ],
    "wof:name":"Brahmbhatt, Vipul",
    "wof:placetype":"venue"
},
  "geometry": {"coordinates":[-85.74527999999999,38.278151],"type":"Point"}
}