{
  "type": "Feature",
  "properties": {
    "iso:country":"US",
    "sg:address":"3612 N Wheeling Ave",
    "sg:city":"Muncie",
    "sg:classifiers":[
        {
            "category":"Building & Trades",
            "subcategory":"Construction",
            "type":"Services"
        }
    ],
    "sg:phone":"+1 765 286 4481",
    "sg:postcode":"47304",
    "sg:province":"IN",
    "sg:tags":[
        "excavating",
        "contractor"
    ],
    "wof:name":"Townsend Excavating",
    "wof:placetype":"venue"
},
  "geometry": {"coordinates":[-85.403623,40.220286],"type":"Point"}
}