{
  "type": "Feature",
  "properties": {
    "iso:country":"US",
    "sg:address":"313 S Chicago St",
    "sg:city":"Royal Center",
    "sg:classifiers":[
        {
            "category":"Organizations",
            "subcategory":"Religious Organization",
            "type":"Services"
        }
    ],
    "sg:phone":"+1 574 643 6545",
    "sg:postcode":"46978",
    "sg:province":"IN",
    "sg:tags":[
        "church"
    ],
    "wof:name":"Baptist Christian Church",
    "wof:placetype":"venue"
},
  "geometry": {"coordinates":[-86.502106,40.866565],"type":"Point"}
}