{
  "type": "Feature",
  "properties": {
    "iso:country":"US",
    "sg:address":"9085 Bath Rd",
    "sg:city":"Brookville",
    "sg:classifiers":[
        {
            "category":"Manufacturing",
            "subcategory":"Printing",
            "type":"Manufacturing & Wholesale Goods"
        }
    ],
    "sg:phone":"+1 765 647 3947",
    "sg:postcode":"47012",
    "sg:province":"IN",
    "sg:tags":[
        "printer"
    ],
    "wof:name":"GRAPHIC Enterprises",
    "wof:placetype":"venue"
},
  "geometry": {"coordinates":[-84.963321,39.517312],"type":"Point"}
}