{
  "type": "Feature",
  "properties": {
    "iso:country":"US",
    "sg:address":"4310 S High School Rd",
    "sg:city":"Indianapolis",
    "sg:classifiers":[
        {
            "category":"Building & Trades",
            "subcategory":"Pest Control",
            "type":"Services"
        }
    ],
    "sg:phone":"+1 317 291 5136",
    "sg:postcode":"46241",
    "sg:province":"IN",
    "wof:name":"Campbell's Exterminating Svc",
    "wof:placetype":"venue"
},
  "geometry": {"coordinates":[-86.268393,39.701793],"type":"Point"}
}