{
  "type": "Feature",
  "properties": {
    "iso:country":"US",
    "sg:address":"1717 S Main St",
    "sg:city":"New Castle",
    "sg:classifiers":[
        {
            "category":"Personal",
            "subcategory":"Beauty Salon",
            "type":"Services"
        }
    ],
    "sg:phone":"+1 765 521 4351",
    "sg:postcode":"47362",
    "sg:province":"IN",
    "wof:name":"Cut Above",
    "wof:placetype":"venue"
},
  "geometry": {"coordinates":[-85.370808,39.915584],"type":"Point"}
}