{
  "type": "Feature",
  "properties": {
    "iso:country":"US",
    "sg:address":"3020 N Post Rd",
    "sg:city":"Indianapolis",
    "sg:classifiers":[
        {
            "category":"Retail",
            "subcategory":"Car Wash",
            "type":"Services"
        }
    ],
    "sg:phone":"+1 317 869 0165",
    "sg:postcode":"46226",
    "sg:province":"IN",
    "sg:tags":[
        "automobile",
        "detail",
        "clean"
    ],
    "wof:name":"J C Detail",
    "wof:placetype":"venue"
},
  "geometry": {"coordinates":[-86.009822,39.812732],"type":"Point"}
}