{
  "type": "Feature",
  "properties": {
    "iso:country":"US",
    "sg:address":"6700 Hwy 62 NE",
    "sg:city":"Lanesville",
    "sg:classifiers":[
        {
            "category":"Government",
            "subcategory":"Office",
            "type":"Public Place"
        }
    ],
    "sg:phone":"+1 812 952 3037",
    "sg:postcode":"47136",
    "sg:province":"IN",
    "sg:tags":[
        "village"
    ],
    "wof:name":"Lanesville City Sewer Plant",
    "wof:placetype":"venue"
},
  "geometry": {"coordinates":[-85.99862299999999,38.231167],"type":"Point"}
}