{
  "type": "Feature",
  "properties": {
    "iso:country":"US",
    "sg:address":"11102 Marlin Rd",
    "sg:city":"Indianapolis",
    "sg:classifiers":[
        {
            "category":"Wholesale",
            "subcategory":"Construction Materials",
            "type":"Manufacturing & Wholesale Goods"
        }
    ],
    "sg:phone":"+1 317 862 9854",
    "sg:postcode":"46239",
    "sg:province":"IN",
    "sg:tags":[
        "sand",
        "gravel"
    ],
    "wof:name":"Brookfield Sand & Gravel Inc",
    "wof:placetype":"venue"
},
  "geometry": {"coordinates":[-85.971367,39.70425],"type":"Point"}
}