{
  "type": "Feature",
  "properties": {
    "iso:country":"US",
    "sg:address":"2501 W Morris St",
    "sg:city":"Indianapolis",
    "sg:classifiers":[
        {
            "category":"Freight",
            "type":"Transportation"
        }
    ],
    "sg:phone":"+1 317 635 7755",
    "sg:postcode":"46221",
    "sg:province":"IN",
    "sg:tags":[
        "cartage",
        "trucking"
    ],
    "wof:name":"Superior Traffic & Trnsprtn",
    "wof:placetype":"venue"
},
  "geometry": {"coordinates":[-86.203009,39.750683],"type":"Point"}
}