{
  "type": "Feature",
  "properties": {
    "iso:country":"US",
    "sg:address":"7648 Indian Cherry Dr",
    "sg:city":"Nineveh",
    "sg:classifiers":[
        {
            "category":"Social Services",
            "subcategory":"Job Training",
            "type":"Services"
        }
    ],
    "sg:phone":"+1 317 933 3961",
    "sg:postcode":"46164",
    "sg:province":"IN",
    "sg:tags":[
        "employment"
    ],
    "sg:website":"www.wizardsofwork.com",
    "wof:name":"Job Search Training Systems",
    "wof:placetype":"venue"
},
  "geometry": {"coordinates":[-86.10961,39.307924],"type":"Point"}
}