{
  "type": "Feature",
  "properties": {
    "iso:country":"US",
    "sg:address":"1424 W Sumner Ave",
    "sg:city":"Indianapolis",
    "sg:classifiers":[
        {
            "category":"Shopping",
            "subcategory":"Bicycles & Sporting Goods",
            "type":"Retail Goods"
        }
    ],
    "sg:phone":"+1 317 784 2500",
    "sg:postcode":"46217",
    "sg:province":"IN",
    "sg:tags":[
        "saddlery",
        "harness"
    ],
    "wof:name":"American Royal Saddlery",
    "wof:placetype":"venue"
},
  "geometry": {"coordinates":[-86.186747,39.714793],"type":"Point"}
}