{
  "type": "Feature",
  "properties": {
    "iso:country":"US",
    "sg:address":"230 Walnut St",
    "sg:city":"Lafayette",
    "sg:classifiers":[
        {
            "category":"Building & Trades",
            "subcategory":"Construction",
            "type":"Services"
        }
    ],
    "sg:phone":"+1 765 742 0293",
    "sg:postcode":"47905",
    "sg:province":"IN",
    "sg:tags":[
        "fabricator",
        "metal"
    ],
    "sg:website":"www.cartcorp.com",
    "wof:name":"Cartesian Corp",
    "wof:placetype":"venue"
},
  "geometry": {"coordinates":[-86.894603,40.413184],"type":"Point"}
}