{
  "type": "Feature",
  "properties": {
    "iso:country":"US",
    "sg:address":"5161 S Indianapolis Rd",
    "sg:city":"Whitestown",
    "sg:classifiers":[
        {
            "category":"Autos & Motor Vehicles",
            "subcategory":"Automobile Sales",
            "type":"Retail Goods"
        }
    ],
    "sg:phone":"+1 317 769 7000",
    "sg:postcode":"46075",
    "sg:province":"IN",
    "sg:tags":[
        "car",
        "dealer"
    ],
    "wof:name":"Hockett Motor Inc",
    "wof:placetype":"venue"
},
  "geometry": {"coordinates":[-86.38102,39.965467],"type":"Point"}
}