{
  "type": "Feature",
  "properties": {
    "iso:country":"US",
    "sg:address":"3137 Wabash Ave",
    "sg:city":"Terre Haute",
    "sg:classifiers":[
        {
            "category":"Insurance",
            "subcategory":"Insurance Agent",
            "type":"Services"
        }
    ],
    "sg:phone":"+1 812 234 0705",
    "sg:postcode":"47803",
    "sg:province":"IN",
    "wof:name":"State Farm Insurance",
    "wof:placetype":"venue"
},
  "geometry": {"coordinates":[-87.369157,39.472371],"type":"Point"}
}