{
  "type": "Feature",
  "properties": {
    "iso:country":"US",
    "sg:address":"508 School St",
    "sg:city":"Winona Lake",
    "sg:classifiers":[
        {
            "category":"Organizations",
            "subcategory":"Non-profit Organization",
            "type":"Services"
        }
    ],
    "sg:phone":"+1 574 269 2376",
    "sg:postcode":"46590",
    "sg:province":"IN",
    "sg:website":"www.hephzibahhouse.org",
    "wof:name":"Hephzibah House",
    "wof:placetype":"venue"
},
  "geometry": {"coordinates":[-85.81624100000001,41.229156],"type":"Point"}
}