{
  "type": "Feature",
  "properties": {
    "iso:country":"US",
    "sg:address":"6110 Stellhorn Rd",
    "sg:city":"Fort Wayne",
    "sg:classifiers":[
        {
            "category":"Personal",
            "subcategory":"Beauty Salon",
            "type":"Services"
        }
    ],
    "sg:phone":"+1 260 486 8868",
    "sg:postcode":"46815",
    "sg:province":"IN",
    "sg:tags":[
        "school"
    ],
    "wof:name":"Ravenscroft Beauty College",
    "wof:placetype":"venue"
},
  "geometry": {"coordinates":[-85.06393,41.120187],"type":"Point"}
}