{
  "type": "Feature",
  "properties": {
    "iso:country":"US",
    "sg:address":"625 Meridian St",
    "sg:city":"Anderson",
    "sg:classifiers":[
        {
            "category":"Personal",
            "subcategory":"Beauty Salon",
            "type":"Services"
        }
    ],
    "sg:phone":"+1 765 644 4363",
    "sg:postcode":"46016",
    "sg:province":"IN",
    "wof:name":"Dezigns On Meridian",
    "wof:placetype":"venue"
},
  "geometry": {"coordinates":[-85.679311,40.109136],"type":"Point"}
}