{
  "type": "Feature",
  "properties": {
    "iso:country":"US",
    "sg:address":"5425 Distribution Dr",
    "sg:city":"Fort Wayne",
    "sg:classifiers":[
        {
            "category":"Wholesale",
            "subcategory":"Electrical",
            "type":"Manufacturing & Wholesale Goods"
        }
    ],
    "sg:phone":"+1 260 484 7751",
    "sg:postcode":"46825",
    "sg:province":"IN",
    "sg:tags":[
        "equipment",
        "electric",
        "supply"
    ],
    "sg:website":"www.graybar.com",
    "wof:name":"Graybar Electric Co",
    "wof:placetype":"venue"
},
  "geometry": {"coordinates":[-85.15437,41.12762],"type":"Point"}
}