{
  "type": "Feature",
  "properties": {
    "iso:country":"US",
    "sg:address":"205 Ferry St",
    "sg:city":"Vevay",
    "sg:classifiers":[
        {
            "category":"Education",
            "subcategory":"Library",
            "type":"Public Place"
        }
    ],
    "sg:phone":"+1 812 427 3363",
    "sg:postcode":"47043",
    "sg:province":"IN",
    "wof:name":"Switzerland Public Library",
    "wof:placetype":"venue"
},
  "geometry": {"coordinates":[-85.066262,38.746901],"type":"Point"}
}