{
  "type": "Feature",
  "properties": {
    "addr:full":"3495 Broadway Gary IN 46409",
    "addr:housenumber":"3495",
    "addr:postcode":"46409",
    "addr:street":"Broadway",
    "iso:country":"US",
    "sg:address":"3495 Broadway",
    "sg:city":"Gary",
    "sg:classifiers":[
        {
            "category":"Retail",
            "subcategory":"Laundry & Dry Cleaning",
            "type":"Services"
        }
    ],
    "sg:phone":"+1 219 887 2222",
    "sg:postcode":"46409",
    "sg:province":"IN",
    "sg:tags":[
        "cleaners"
    ],
    "wof:name":"Doo Sik Choe",
    "wof:placetype":"venue"
},
  "geometry": {"coordinates":[-87.336527,41.556639],"type":"Point"}
}