{
  "type": "Feature",
  "properties": {
    "iso:country":"US",
    "sg:address":"646 E 52nd St",
    "sg:city":"Indianapolis",
    "sg:classifiers":[
        {
            "category":"Retail",
            "subcategory":"Portrait Studio",
            "type":"Services"
        }
    ],
    "sg:phone":"+1 317 920 9112",
    "sg:postcode":"46205",
    "sg:province":"IN",
    "sg:tags":[
        "photographer"
    ],
    "wof:name":"Liz Art Photography",
    "wof:placetype":"venue"
},
  "geometry": {"coordinates":[-86.14592399999999,39.847008],"type":"Point"}
}