{
  "type": "Feature",
  "properties": {
    "iso:country":"US",
    "sg:address":"4529 E Edgewood Ave",
    "sg:city":"Indianapolis",
    "sg:classifiers":[
        {
            "category":"Sports & Exercise",
            "subcategory":"Gym",
            "type":"Entertainment"
        }
    ],
    "sg:phone":"+1 317 784 4949",
    "sg:postcode":"46237",
    "sg:province":"IN",
    "wof:name":"Quailcreeks Gymnastics Fitnes",
    "wof:placetype":"venue"
},
  "geometry": {"coordinates":[-86.087643,39.680472],"type":"Point"}
}