{
  "type": "Feature",
  "properties": {
    "iso:country":"US",
    "sg:address":"706 Broadmore Ests",
    "sg:city":"Goshen",
    "sg:classifiers":[
        {
            "category":"Building & Trades",
            "subcategory":"Construction",
            "type":"Services"
        }
    ],
    "sg:phone":"+1 219 596 3458",
    "sg:postcode":"46528",
    "sg:province":"IN",
    "sg:tags":[
        "house"
    ],
    "wof:name":"Reed Mark L",
    "wof:placetype":"venue"
},
  "geometry": {"coordinates":[-85.822847,41.640948],"type":"Point"}
}