{
  "type": "Feature",
  "properties": {
    "iso:country":"US",
    "sg:address":"2211 Glenview Dr",
    "sg:city":"Evansville",
    "sg:classifiers":[
        {
            "category":"Manufacturing",
            "subcategory":"Metals",
            "type":"Manufacturing & Wholesale Goods"
        }
    ],
    "sg:phone":"+1 812 422 7057",
    "sg:postcode":"47720",
    "sg:province":"IN",
    "sg:tags":[
        "steel"
    ],
    "wof:name":"Schucker's Steel Erectors",
    "wof:placetype":"venue"
},
  "geometry": {"coordinates":[-87.596974,38.017491],"type":"Point"}
}