{
  "type": "Feature",
  "properties": {
    "addr:full":"5546 Shorewood Dr Indianapolis IN 46220",
    "addr:housenumber":"5546",
    "addr:postcode":"46220",
    "addr:street":"Shorewood Dr",
    "iso:country":"US",
    "sg:address":"5546 Shorewood Dr",
    "sg:city":"Indianapolis",
    "sg:classifiers":[
        {
            "category":"Manufacturing",
            "subcategory":"Printing",
            "type":"Manufacturing & Wholesale Goods"
        }
    ],
    "sg:phone":"+1 317 542 9829",
    "sg:postcode":"46220",
    "sg:province":"IN",
    "sg:tags":[
        "publisher"
    ],
    "wof:name":"Endowment Development Svc Inc",
    "wof:placetype":"venue"
},
  "geometry": {"coordinates":[-86.112898,39.854072],"type":"Point"}
}