{
  "type": "Feature",
  "properties": {
    "iso:country":"US",
    "sg:address":"931 East Ave",
    "sg:city":"Kendallville",
    "sg:classifiers":[
        {
            "category":"Communications",
            "subcategory":"Radio Station",
            "type":"Services"
        }
    ],
    "sg:phone":"+1 260 347 2400",
    "sg:postcode":"46755",
    "sg:province":"IN",
    "sg:tags":[
        "company",
        "broadcasting"
    ],
    "sg:website":"www.wawk.com",
    "wof:name":"WAWK AM Radio Station",
    "wof:placetype":"venue"
},
  "geometry": {"coordinates":[-85.26259,41.45411],"type":"Point"}
}