{
  "type": "Feature",
  "properties": {
    "iso:country":"US",
    "sg:address":"2701 E State Blvd",
    "sg:city":"Fort Wayne",
    "sg:classifiers":[
        {
            "category":"Real Estate",
            "subcategory":"Real Estate Agent",
            "type":"Services"
        }
    ],
    "sg:phone":"+1 260 426 1175",
    "sg:postcode":"46805",
    "sg:province":"IN",
    "wof:name":"3 Rivers Realty",
    "wof:placetype":"venue"
},
  "geometry": {"coordinates":[-85.103602,41.097277],"type":"Point"}
}