{
  "type": "Feature",
  "properties": {
    "iso:country":"US",
    "sg:address":"3350 N High School Rd",
    "sg:city":"Indianapolis",
    "sg:classifiers":[
        {
            "category":"Bars & Pubs",
            "type":"Food & Drink"
        }
    ],
    "sg:phone":"+1 317 297 7083",
    "sg:postcode":"46224",
    "sg:province":"IN",
    "wof:name":"Pepe's Bar & Bar",
    "wof:placetype":"venue"
},
  "geometry": {"coordinates":[-86.270211,39.815526],"type":"Point"}
}