{
  "type": "Feature",
  "properties": {
    "addr:full":"2361 N 6th St Vincennes IN 47591",
    "addr:housenumber":"2361",
    "addr:postcode":"47591",
    "addr:street":"N 6Th St",
    "iso:country":"US",
    "sg:address":"2361 N 6th St",
    "sg:city":"Vincennes",
    "sg:classifiers":[
        {
            "category":"Banks & Credit Unions",
            "subcategory":"Investment Brokerage",
            "type":"Services"
        }
    ],
    "sg:phone":"+1 812 886 1178",
    "sg:postcode":"47591",
    "sg:province":"IN",
    "sg:tags":[
        "security"
    ],
    "wof:name":"Edward Jones Co",
    "wof:placetype":"venue"
},
  "geometry": {"coordinates":[-87.504102,38.689668],"type":"Point"}
}