{
  "type": "Feature",
  "properties": {
    "iso:country":"US",
    "sg:address":"1209 13th St",
    "sg:city":"Bedford",
    "sg:classifiers":[
        {
            "category":"Social Services",
            "subcategory":"Adult Care",
            "type":"Services"
        }
    ],
    "sg:phone":"+1 812 275 6614",
    "sg:postcode":"47421",
    "sg:province":"IN",
    "sg:tags":[
        "home",
        "group"
    ],
    "wof:name":"Res-Care Group Home",
    "wof:placetype":"venue"
},
  "geometry": {"coordinates":[-86.488649,38.864578],"type":"Point"}
}