{
  "type": "Feature",
  "properties": {
    "iso:country":"US",
    "sg:address":"410 W. 10th St.",
    "sg:city":"Indianapolis",
    "sg:classifiers":[
        {
            "category":"Professional",
            "subcategory":"Computer Services",
            "type":"Services"
        }
    ],
    "sg:phone":"+1 281 673 6677",
    "sg:postcode":"46202-3012",
    "sg:province":"IN",
    "sg:tags":[
        "software",
        "opensource",
        "healthcare"
    ],
    "sg:website":"http://openmrs.org/",
    "wof:name":"OpenMRS",
    "wof:placetype":"venue"
},
  "geometry": {"coordinates":[-86.16712800000001,39.781011],"type":"Point"}
}