{
  "type": "Feature",
  "properties": {
    "iso:country":"US",
    "sg:address":"1601 W 8th St",
    "sg:city":"Muncie",
    "sg:classifiers":[
        {
            "category":"Building & Trades",
            "subcategory":"Plumbing",
            "type":"Services"
        }
    ],
    "sg:phone":"+1 765 289 6606",
    "sg:postcode":"47302",
    "sg:province":"IN",
    "sg:tags":[
        "heating",
        "contractor"
    ],
    "wof:name":"Willco Wholesale Distributors",
    "wof:placetype":"venue"
},
  "geometry": {"coordinates":[-85.404613,40.181911],"type":"Point"}
}