{
  "type": "Feature",
  "properties": {
    "iso:country":"US",
    "sg:address":"1389 Gull Ct",
    "sg:city":"Cicero",
    "sg:classifiers":[
        {
            "category":"Retail",
            "subcategory":"Repair Shop",
            "type":"Services"
        }
    ],
    "sg:phone":"+1 317 913 7233",
    "sg:postcode":"46034",
    "sg:province":"IN",
    "sg:tags":[
        "lock",
        "locksmith"
    ],
    "wof:name":"Seagull Ventures",
    "wof:placetype":"venue"
},
  "geometry": {"coordinates":[-86.030572,40.110858],"type":"Point"}
}