{
  "type": "Feature",
  "properties": {
    "iso:country":"US",
    "sg:address":"7190 S Strain Ridge Rd",
    "sg:city":"Bloomington",
    "sg:classifiers":[
        {
            "category":"Manufacturing",
            "subcategory":"Apparel",
            "type":"Manufacturing & Wholesale Goods"
        }
    ],
    "sg:phone":"+1 812 824 9382",
    "sg:postcode":"47401",
    "sg:province":"IN",
    "sg:tags":[
        "sewing",
        "contractor"
    ],
    "wof:name":"God Is Sew Great",
    "wof:placetype":"venue"
},
  "geometry": {"coordinates":[-86.50622,39.07319],"type":"Point"}
}