{
  "type": "Feature",
  "properties": {
    "iso:country":"US",
    "sg:address":"8192 W 700 N",
    "sg:city":"Fairland",
    "sg:classifiers":[
        {
            "category":"Manufacturing",
            "subcategory":"Tools & Machinery",
            "type":"Manufacturing & Wholesale Goods"
        }
    ],
    "sg:phone":"+1 317 835 7824",
    "sg:postcode":"46126",
    "sg:province":"IN",
    "sg:tags":[
        "industry",
        "special"
    ],
    "wof:name":"Wehr Engineering",
    "wof:placetype":"venue"
},
  "geometry": {"coordinates":[-85.937655,39.624054],"type":"Point"}
}