{
  "type": "Feature",
  "properties": {
    "iso:country":"US",
    "sg:address":"1728 W 4th St",
    "sg:city":"Marion",
    "sg:classifiers":[
        {
            "category":"Manufacturing",
            "subcategory":"Metals",
            "type":"Manufacturing & Wholesale Goods"
        }
    ],
    "sg:phone":"+1 765 651 9160",
    "sg:postcode":"46952",
    "sg:province":"IN",
    "sg:tags":[
        "fabricator",
        "sheet"
    ],
    "wof:name":"Precision Sheet Metal",
    "wof:placetype":"venue"
},
  "geometry": {"coordinates":[-85.682911,40.557792],"type":"Point"}
}