{
  "type": "Feature",
  "properties": {
    "addr:full":"2593 Hamstrom Rd Portage IN 46368",
    "addr:housenumber":"2593",
    "addr:postcode":"46368",
    "addr:street":"Hamstrom Rd",
    "iso:country":"US",
    "sg:address":"2593 Hamstrom Rd",
    "sg:city":"Portage",
    "sg:classifiers":[
        {
            "category":"Building & Trades",
            "subcategory":"Construction",
            "type":"Services"
        },
        {
            "category":"Building & Trades",
            "subcategory":"Electrical",
            "type":"Services"
        }
    ],
    "sg:phone":"+1 219 763 4247",
    "sg:postcode":"46368",
    "sg:province":"IN",
    "sg:tags":[
        "system",
        "specialty",
        "heating",
        "furnaces-heating",
        "contractor",
        "air conditioning"
    ],
    "sg:website":"http://www.trane.com",
    "wof:name":"Lovings Heating & Cooling Inc",
    "wof:placetype":"venue"
},
  "geometry": {"coordinates":[-87.168533,41.576529],"type":"Point"}
}