{
  "type": "Feature",
  "properties": {
    "iso:country":"US",
    "sg:address":"1709 E Greener Rd",
    "sg:city":"Jasper",
    "sg:classifiers":[
        {
            "category":"Wholesale",
            "subcategory":"Electrical",
            "type":"Manufacturing & Wholesale Goods"
        }
    ],
    "sg:phone":"+1 812 482 4528",
    "sg:postcode":"47546",
    "sg:province":"IN",
    "sg:tags":[
        "communications",
        "equipment"
    ],
    "wof:name":"USA Mobile Communications",
    "wof:placetype":"venue"
},
  "geometry": {"coordinates":[-86.873901,38.384047],"type":"Point"}
}