{
  "type": "Feature",
  "properties": {
    "addr:full":"9718 Treyburn Green Way Indianapolis IN 46239",
    "addr:housenumber":"9718",
    "addr:postcode":"46239",
    "addr:street":"Treyburn Green Way",
    "iso:country":"US",
    "sg:address":"9718 Treyburn Green Way",
    "sg:city":"Indianapolis",
    "sg:classifiers":[
        {
            "category":"Professional",
            "subcategory":"Computer Services",
            "type":"Services"
        }
    ],
    "sg:phone":"+1 317 898 0820",
    "sg:postcode":"46239",
    "sg:province":"IN",
    "sg:tags":[
        "publisher",
        "software",
        "developer"
    ],
    "wof:name":"Gideon Vi",
    "wof:placetype":"venue"
},
  "geometry": {"coordinates":[-85.995407,39.755829],"type":"Point"}
}