{
  "type": "Feature",
  "properties": {
    "iso:country":"US",
    "sg:address":"59 W Washington St",
    "sg:city":"Martinsville",
    "sg:classifiers":[
        {
            "category":"Banks & Credit Unions",
            "subcategory":"Bank",
            "type":"Services"
        }
    ],
    "sg:phone":"+1 765 342 6695",
    "sg:postcode":"46151",
    "sg:province":"IN",
    "sg:website":"www.homebanksb.com",
    "wof:name":"Home Bank",
    "wof:placetype":"venue"
},
  "geometry": {"coordinates":[-86.429247,39.426802],"type":"Point"}
}