{
  "type": "Feature",
  "properties": {
    "addr:full":"5056 E 894 S Brook IN 47922",
    "addr:housenumber":"5056",
    "addr:postcode":"47922",
    "addr:street":"E 894 S",
    "iso:country":"US",
    "sg:address":"5056 E 894 S",
    "sg:city":"Brook",
    "sg:classifiers":[
        {
            "category":"Shopping",
            "subcategory":"Hobbies, Toys, & Games",
            "type":"Retail Goods"
        }
    ],
    "sg:phone":"+1 219 275 6639",
    "sg:postcode":"47922",
    "sg:province":"IN",
    "sg:tags":[
        "equipment",
        "ceramic",
        "supply"
    ],
    "wof:name":"Mrs Rusty's Ceramics",
    "wof:placetype":"venue"
},
  "geometry": {"coordinates":[-87.293905,40.8668],"type":"Point"}
}