{
  "type": "Feature",
  "properties": {
    "addr:full":"10898 US Hwy 36 Avon IN 46123",
    "addr:housenumber":"10898",
    "addr:postcode":"46123",
    "addr:street":"Us Hwy 36",
    "iso:country":"US",
    "sg:address":"10898 US Hwy 36",
    "sg:city":"Avon",
    "sg:classifiers":[
        {
            "category":"Building & Trades",
            "subcategory":"Landscaping Services",
            "type":"Services"
        }
    ],
    "sg:phone":"+1 317 271 4800",
    "sg:postcode":"46123",
    "sg:province":"IN",
    "sg:tags":[
        "landscape",
        "contractor"
    ],
    "wof:name":"Four Seasons Landscaping",
    "wof:placetype":"venue"
},
  "geometry": {"coordinates":[-86.32863399999999,39.763834],"type":"Point"}
}