{
  "type": "Feature",
  "properties": {
    "iso:country":"US",
    "sg:address":"155 S Meridian St",
    "sg:city":"Scottsburg",
    "sg:classifiers":[
        {
            "category":"Professional",
            "subcategory":"Accounting & Tax Preparation",
            "type":"Services"
        }
    ],
    "sg:phone":"+1 812 752 3003",
    "sg:postcode":"47170",
    "sg:province":"IN",
    "sg:tags":[
        "return",
        "filing"
    ],
    "sg:website":"www.qualityadvertisingproducts.com",
    "wof:name":"A Tax Office",
    "wof:placetype":"venue"
},
  "geometry": {"coordinates":[-85.773548,38.68432],"type":"Point"}
}