{
  "type": "Feature",
  "properties": {
    "addr:full":"474 S Range Line Rd Carmel IN 46032",
    "addr:housenumber":"474",
    "addr:postcode":"46032",
    "addr:street":"S Range Line Rd",
    "iso:country":"US",
    "sg:address":"474 S Range Line Rd",
    "sg:city":"Carmel",
    "sg:classifiers":[
        {
            "category":"Shopping",
            "subcategory":"Bicycles & Sporting Goods",
            "type":"Retail Goods"
        }
    ],
    "sg:phone":"+1 317 843 9980",
    "sg:postcode":"46032",
    "sg:province":"IN",
    "sg:tags":[
        "equipment",
        "skateboard"
    ],
    "wof:name":"Rise Skateboard Shop",
    "wof:placetype":"venue"
},
  "geometry": {"coordinates":[-86.127133,39.97512],"type":"Point"}
}