{
  "type": "Feature",
  "properties": {
    "addr:full":"2033 State Rd 54 Linton IN 47441",
    "addr:housenumber":"2033;54",
    "addr:postcode":"47441",
    "addr:street":"State Rd",
    "iso:country":"US",
    "sg:address":"2033 State Rd 54",
    "sg:city":"Linton",
    "sg:classifiers":[
        {
            "category":"Banks & Credit Unions",
            "subcategory":"Bank",
            "type":"Services"
        }
    ],
    "sg:phone":"+1 812 847 0777",
    "sg:postcode":"47441",
    "sg:province":"IN",
    "wof:name":"Crane Credit Union",
    "wof:placetype":"venue"
},
  "geometry": {"coordinates":[-87.108193,39.038108],"type":"Point"}
}