{
  "type": "Feature",
  "properties": {
    "addr:full":"217 E Main St North Manchester IN 46962",
    "addr:housenumber":"217",
    "addr:postcode":"46962",
    "addr:street":"E Main St",
    "iso:country":"US",
    "sg:address":"217 E Main St",
    "sg:city":"North Manchester",
    "sg:classifiers":[
        {
            "category":"Retail",
            "subcategory":"Portrait Studio",
            "type":"Services"
        }
    ],
    "sg:phone":"+1 260 982 4205",
    "sg:postcode":"46962",
    "sg:province":"IN",
    "sg:tags":[
        "photographer"
    ],
    "wof:name":"Werking Studio Phtgrphy-Dave",
    "wof:placetype":"venue"
},
  "geometry": {"coordinates":[-85.81636,40.798163],"type":"Point"}
}