{
  "type": "Feature",
  "properties": {
    "iso:country":"US",
    "sg:address":"1520 Springmill Ponds Blvd",
    "sg:city":"Carmel",
    "sg:classifiers":[
        {
            "category":"Banks & Credit Unions",
            "subcategory":"Investment Brokerage",
            "type":"Services"
        }
    ],
    "sg:phone":"+1 317 580 9592",
    "sg:postcode":"46032",
    "sg:province":"IN",
    "sg:tags":[
        "advisory"
    ],
    "wof:name":"Online Investment Advisors LLC",
    "wof:placetype":"venue"
},
  "geometry": {"coordinates":[-86.160714,39.995798],"type":"Point"}
}