{
  "type": "Feature",
  "properties": {
    "iso:country":"US",
    "sg:address":"2024 N Park Rd",
    "sg:city":"Connersville",
    "sg:classifiers":[
        {
            "category":"Education",
            "subcategory":"Vocational School",
            "type":"Public Place"
        }
    ],
    "sg:phone":"+1 765 825 0306",
    "sg:postcode":"47331",
    "sg:province":"IN",
    "sg:tags":[
        "secretarial"
    ],
    "wof:name":"H & R Block Tax Svc",
    "wof:placetype":"venue"
},
  "geometry": {"coordinates":[-85.12915700000001,39.657313],"type":"Point"}
}