{
  "type": "Feature",
  "properties": {
    "iso:country":"US",
    "sg:address":"3496 E Base Rd",
    "sg:city":"Greensburg",
    "sg:classifiers":[
        {
            "category":"Building & Trades",
            "subcategory":"Construction",
            "type":"Services"
        }
    ],
    "sg:phone":"+1 812 663 5589",
    "sg:postcode":"47240",
    "sg:province":"IN",
    "sg:tags":[
        "general",
        "contractor"
    ],
    "wof:name":"Hellmich Inc",
    "wof:placetype":"venue"
},
  "geometry": {"coordinates":[-85.422839,39.337508],"type":"Point"}
}