{
  "type": "Feature",
  "properties": {
    "iso:country":"US",
    "sg:address":"286 S Shore Dr",
    "sg:city":"Culver",
    "sg:classifiers":[
        {
            "category":"Real Estate",
            "subcategory":"Real Estate Agent",
            "type":"Services"
        }
    ],
    "sg:phone":"+1 574 842 5116",
    "sg:postcode":"46511",
    "sg:province":"IN",
    "wof:name":"Aloha Realty Inc",
    "wof:placetype":"venue"
},
  "geometry": {"coordinates":[-86.406623,41.188089],"type":"Point"}
}