{
  "type": "Feature",
  "properties": {
    "addr:full":"2717 N 1st Ave Evansville IN 47710",
    "addr:housenumber":"2717",
    "addr:postcode":"47710",
    "addr:street":"N 1St Ave",
    "iso:country":"US",
    "sg:address":"2717 N 1st Ave",
    "sg:city":"Evansville",
    "sg:classifiers":[
        {
            "category":"Insurance",
            "subcategory":"Insurance Agent",
            "type":"Services"
        }
    ],
    "sg:phone":"+1 812 422 1883",
    "sg:postcode":"47710",
    "sg:province":"IN",
    "wof:name":"State Farm Insurance",
    "wof:placetype":"venue"
},
  "geometry": {"coordinates":[-87.57433399999999,38.003696],"type":"Point"}
}