{
  "type": "Feature",
  "properties": {
    "iso:country":"US",
    "sg:address":"961 2nd Ave",
    "sg:city":"Jasper",
    "sg:classifiers":[
        {
            "category":"Insurance",
            "subcategory":"Hazard Insurance",
            "type":"Services"
        }
    ],
    "sg:phone":"+1 812 482 6236",
    "sg:postcode":"47546",
    "sg:province":"IN",
    "sg:tags":[
        "bond"
    ],
    "wof:name":"Williams Bail Bonds Co",
    "wof:placetype":"venue"
},
  "geometry": {"coordinates":[-86.91613599999999,38.387497],"type":"Point"}
}