{
  "type": "Feature",
  "properties": {
    "iso:country":"US",
    "sg:address":"418 N Calumet Ave",
    "sg:city":"Michigan City",
    "sg:classifiers":[
        {
            "category":"Manufacturing",
            "subcategory":"Furniture",
            "type":"Manufacturing & Wholesale Goods"
        }
    ],
    "sg:phone":"+1 219 874 5236",
    "sg:postcode":"46360",
    "sg:province":"IN",
    "sg:tags":[
        "top",
        "counter"
    ],
    "sg:website":"www.dwyerkitchens.com",
    "wof:name":"Dwyer Products Corp",
    "wof:placetype":"venue"
},
  "geometry": {"coordinates":[-86.87179500000001,41.711928],"type":"Point"}
}