{
  "type": "Feature",
  "properties": {
    "iso:country":"US",
    "sg:address":"1130 Industrial Rd",
    "sg:city":"Columbus",
    "sg:classifiers":[
        {
            "category":"Building & Trades",
            "subcategory":"Plumbing",
            "type":"Services"
        }
    ],
    "sg:phone":"+1 812 375 1645",
    "sg:postcode":"47203",
    "sg:province":"IN",
    "sg:tags":[
        "plumbing",
        "contractor"
    ],
    "wof:name":"Barker Brothers Plumbing",
    "wof:placetype":"venue"
},
  "geometry": {"coordinates":[-85.939552,39.24911],"type":"Point"}
}