{
  "type": "Feature",
  "properties": {
    "iso:country":"US",
    "sg:address":"2619 N Michigan St",
    "sg:city":"Plymouth",
    "sg:classifiers":[
        {
            "category":"Travel",
            "subcategory":"Hotels & Motels",
            "type":"Entertainment"
        }
    ],
    "sg:phone":"+1 574 936 2444",
    "sg:postcode":"46563",
    "sg:province":"IN",
    "wof:name":"Holiday Inn Express Plymouth",
    "wof:placetype":"venue"
},
  "geometry": {"coordinates":[-86.31243,41.364635],"type":"Point"}
}