{
  "type": "Feature",
  "properties": {
    "iso:country":"US",
    "sg:address":"1898 Corniche Dr",
    "sg:city":"Zionsville",
    "sg:classifiers":[
        {
            "category":"Wholesale",
            "subcategory":"Jewelry",
            "type":"Manufacturing & Wholesale Goods"
        }
    ],
    "sg:phone":"+1 317 873 2903",
    "sg:postcode":"46077",
    "sg:province":"IN",
    "sg:tags":[
        "stone"
    ],
    "wof:name":"Beads & Bangles",
    "wof:placetype":"venue"
},
  "geometry": {"coordinates":[-86.28850799999999,39.945868],"type":"Point"}
}