{
  "type": "Feature",
  "properties": {
    "iso:country":"US",
    "sg:address":"311 E Jefferson St",
    "sg:city":"Plymouth",
    "sg:classifiers":[
        {
            "category":"Insurance",
            "subcategory":"Insurance Agent",
            "type":"Services"
        }
    ],
    "sg:phone":"+1 574 936 2556",
    "sg:postcode":"46563",
    "sg:province":"IN",
    "wof:name":"State Farm Insurance",
    "wof:placetype":"venue"
},
  "geometry": {"coordinates":[-86.306322,41.343742],"type":"Point"}
}