{
  "type": "Feature",
  "properties": {
    "addr:full":"216 Wheatridge Ct Valparaiso IN 46385",
    "addr:housenumber":"216",
    "addr:postcode":"46385",
    "addr:street":"Wheatridge Ct",
    "iso:country":"US",
    "sg:address":"216 Wheatridge Ct",
    "sg:city":"Valparaiso",
    "sg:classifiers":[
        {
            "category":"Professional",
            "type":"Services"
        }
    ],
    "sg:phone":"+1 219 465 0313",
    "sg:postcode":"46385",
    "sg:province":"IN",
    "sg:tags":[
        "establishment"
    ],
    "wof:name":"Henkle Corp-Emry Group",
    "wof:placetype":"venue"
},
  "geometry": {"coordinates":[-87.107553,41.451181],"type":"Point"}
}