{
  "type": "Feature",
  "properties": {
    "iso:country":"US",
    "sg:address":"2612 Charlestown Rd",
    "sg:city":"New Albany",
    "sg:classifiers":[
        {
            "category":"Restaurant",
            "type":"Food & Drink"
        }
    ],
    "sg:phone":"+1 812 944 9199",
    "sg:postcode":"47150",
    "sg:province":"IN",
    "wof:name":"B C's Original Ranch House",
    "wof:placetype":"venue"
},
  "geometry": {"coordinates":[-85.804407,38.316098],"type":"Point"}
}