{
  "type": "Feature",
  "properties": {
    "iso:country":"US",
    "sg:address":"10506 Coldwater Rd",
    "sg:city":"Fort Wayne",
    "sg:classifiers":[
        {
            "category":"Health Services",
            "subcategory":"Doctor",
            "type":"Services"
        }
    ],
    "sg:phone":"+1 260 637 6976",
    "sg:postcode":"46845",
    "sg:province":"IN",
    "sg:tags":[
        "dentist"
    ],
    "wof:name":"Pine Valley Dental Group",
    "wof:placetype":"venue"
},
  "geometry": {"coordinates":[-85.131597,41.17894],"type":"Point"}
}