{
  "type": "Feature",
  "properties": {
    "iso:country":"US",
    "sg:address":"704 Countryside Dr",
    "sg:city":"Columbia City",
    "sg:classifiers":[
        {
            "category":"Freight",
            "type":"Transportation"
        }
    ],
    "sg:phone":"+1 260 403 9566",
    "sg:postcode":"46725",
    "sg:province":"IN",
    "sg:tags":[
        "operator",
        "local",
        "trucking"
    ],
    "wof:name":"Newell Trucking Company Inc",
    "wof:placetype":"venue"
},
  "geometry": {"coordinates":[-85.480957,41.170582],"type":"Point"}
}