{
  "type": "Feature",
  "properties": {
    "iso:country":"US",
    "sg:address":"957 J St",
    "sg:city":"Bedford",
    "sg:classifiers":[
        {
            "category":"Manufacturing",
            "subcategory":"Metals",
            "type":"Manufacturing & Wholesale Goods"
        }
    ],
    "sg:phone":"+1 812 275 3363",
    "sg:postcode":"47421",
    "sg:province":"IN",
    "sg:tags":[
        "steel"
    ],
    "wof:name":"Indiana Steel & Engineering",
    "wof:placetype":"venue"
},
  "geometry": {"coordinates":[-86.48412999999999,38.8681],"type":"Point"}
}