{
  "type": "Feature",
  "properties": {
    "iso:country":"US",
    "sg:address":"2610 Conner St",
    "sg:city":"Noblesville",
    "sg:classifiers":[
        {
            "category":"Personal",
            "subcategory":"Beauty Salon",
            "type":"Services"
        }
    ],
    "sg:phone":"+1 317 770 9855",
    "sg:postcode":"46060",
    "sg:province":"IN",
    "wof:name":"Supercuts",
    "wof:placetype":"venue"
},
  "geometry": {"coordinates":[-85.994421,40.045732],"type":"Point"}
}