{
  "type": "Feature",
  "properties": {
    "iso:country":"US",
    "sg:address":"648 N 400 E",
    "sg:city":"Valparaiso",
    "sg:classifiers":[
        {
            "category":"Insurance",
            "subcategory":"Insurance Agent",
            "type":"Services"
        }
    ],
    "sg:phone":"+1 219 464 3456",
    "sg:postcode":"46383",
    "sg:province":"IN",
    "wof:name":"Northwestern Mutual Financial",
    "wof:placetype":"venue"
},
  "geometry": {"coordinates":[-86.985679,41.528416],"type":"Point"}
}