{
  "type": "Feature",
  "properties": {
    "iso:country":"US",
    "sg:address":"818 E Franklin St",
    "sg:city":"Evansville",
    "sg:classifiers":[
        {
            "category":"Mining & Drilling",
            "type":"Manufacturing & Wholesale Goods"
        }
    ],
    "sg:phone":"+1 812 477 7625",
    "sg:postcode":"47711",
    "sg:province":"IN",
    "sg:tags":[
        "stone"
    ],
    "wof:name":"Sticks & Stones Landscape",
    "wof:placetype":"venue"
},
  "geometry": {"coordinates":[-87.552743,37.980039],"type":"Point"}
}