{
  "type": "Feature",
  "properties": {
    "iso:country":"US",
    "sg:address":"17123 Aboite Rd",
    "sg:city":"Roanoke",
    "sg:classifiers":[
        {
            "category":"Farming",
            "subcategory":"Farm",
            "type":"Manufacturing & Wholesale Goods"
        }
    ],
    "sg:phone":"+1 260 638 4826",
    "sg:postcode":"46783",
    "sg:province":"IN",
    "sg:tags":[
        "crop",
        "general"
    ],
    "wof:name":"Lynn Nicholson",
    "wof:placetype":"venue"
},
  "geometry": {"coordinates":[-85.31158000000001,40.931474],"type":"Point"}
}