{
  "type": "Feature",
  "properties": {
    "iso:country":"US",
    "sg:address":"1631 Oakland Ave",
    "sg:city":"Elkhart",
    "sg:classifiers":[
        {
            "category":"Manufacturing",
            "subcategory":"Printing",
            "type":"Manufacturing & Wholesale Goods"
        }
    ],
    "sg:phone":"+1 574 293 9088",
    "sg:postcode":"46516",
    "sg:province":"IN",
    "sg:tags":[
        "screen"
    ],
    "wof:name":"ANEWCO",
    "wof:placetype":"venue"
},
  "geometry": {"coordinates":[-85.984941,41.67229],"type":"Point"}
}