{
  "type": "Feature",
  "properties": {
    "iso:country":"US",
    "sg:address":"119 Locust St",
    "sg:city":"Terre Haute",
    "sg:classifiers":[
        {
            "category":"Social Services",
            "subcategory":"Child Care",
            "type":"Services"
        }
    ],
    "sg:phone":"+1 812 478 7570",
    "sg:postcode":"47807",
    "sg:province":"IN",
    "wof:name":"Albrecht's Pansy Day Care",
    "wof:placetype":"venue"
},
  "geometry": {"coordinates":[-87.41633899999999,39.4774],"type":"Point"}
}