{
  "type": "Feature",
  "properties": {
    "iso:country":"US",
    "sg:address":"6273 Venus Ave",
    "sg:city":"Portage",
    "sg:classifiers":[
        {
            "category":"Retail",
            "subcategory":"Repair Shop",
            "type":"Services"
        }
    ],
    "sg:phone":"+1 219 763 4898",
    "sg:postcode":"46368",
    "sg:province":"IN",
    "wof:name":"C&S Cleaning",
    "wof:placetype":"venue"
},
  "geometry": {"coordinates":[-87.171373,41.58123],"type":"Point"}
}