{
  "type": "Feature",
  "properties": {
    "iso:country":"US",
    "sg:address":"7455 W 350 N",
    "sg:city":"Shipshewana",
    "sg:classifiers":[
        {
            "category":"Travel",
            "subcategory":"Hotels & Motels",
            "type":"Entertainment"
        }
    ],
    "sg:phone":"+1 260 768 4422",
    "sg:postcode":"46565",
    "sg:province":"IN",
    "sg:tags":[
        "breakfast",
        "accommodation",
        "bed"
    ],
    "wof:name":"Poverty Acres Enterprises Inc",
    "wof:placetype":"venue"
},
  "geometry": {"coordinates":[-85.570415,41.689999],"type":"Point"}
}