{
  "type": "Feature",
  "properties": {
    "iso:country":"US",
    "sg:address":"3731 Ridge Rd",
    "sg:city":"Highland",
    "sg:classifiers":[
        {
            "category":"Shopping",
            "subcategory":"Bicycles & Sporting Goods",
            "type":"Retail Goods"
        }
    ],
    "sg:phone":"+1 219 923 2555",
    "sg:postcode":"46322",
    "sg:province":"IN",
    "sg:tags":[
        "bike",
        "rental"
    ],
    "sg:website":"www.ridgecycle.com",
    "wof:name":"Ridge Cyclery",
    "wof:placetype":"venue"
},
  "geometry": {"coordinates":[-87.438301,41.5522],"type":"Point"}
}