{
  "type": "Feature",
  "properties": {
    "addr:full":"10400 W State Rte 662 Newburgh IN 47630",
    "addr:housenumber":"10400",
    "addr:postcode":"47630",
    "addr:street":"W State Rte 662",
    "iso:country":"US",
    "sg:address":"10400 W State Rte 662",
    "sg:city":"Newburgh",
    "sg:classifiers":[
        {
            "category":"Shopping",
            "type":"Retail Goods"
        }
    ],
    "sg:phone":"+1 812 853 2537",
    "sg:postcode":"47630",
    "sg:province":"IN",
    "sg:tags":[
        "art",
        "gallery",
        "dealer"
    ],
    "sg:website":"www.riverwindgallery.com",
    "wof:name":"Riverwind Gallery",
    "wof:placetype":"venue"
},
  "geometry": {"coordinates":[-87.439218,37.953497],"type":"Point"}
}