{
  "type": "Feature",
  "properties": {
    "iso:country":"US",
    "sg:address":"1109 Alexandria St",
    "sg:city":"Bicknell",
    "sg:classifiers":[
        {
            "category":"Personal",
            "subcategory":"Beauty Salon",
            "type":"Services"
        }
    ],
    "sg:phone":"+1 812 735 2555",
    "sg:postcode":"47512",
    "sg:province":"IN",
    "sg:tags":[
        "shop"
    ],
    "wof:name":"Mane Wave",
    "wof:placetype":"venue"
},
  "geometry": {"coordinates":[-87.31496799999999,38.781239],"type":"Point"}
}