{
  "type": "Feature",
  "properties": {
    "iso:country":"US",
    "sg:address":"70 N Broadway",
    "sg:city":"Peru",
    "sg:classifiers":[
        {
            "category":"Shopping",
            "subcategory":"Used Merchandise",
            "type":"Retail Goods"
        }
    ],
    "sg:phone":"+1 765 472 2995",
    "sg:postcode":"46970",
    "sg:province":"IN",
    "wof:name":"Happy Pawn Shop",
    "wof:placetype":"venue"
},
  "geometry": {"coordinates":[-86.070238,40.755048],"type":"Point"}
}