{
  "type": "Feature",
  "properties": {
    "iso:country":"US",
    "sg:address":"6001 Broadway",
    "sg:city":"Merrillville",
    "sg:classifiers":[
        {
            "category":"Banks & Credit Unions",
            "subcategory":"Bank",
            "type":"Services"
        }
    ],
    "sg:phone":"+1 219 980 6260",
    "sg:postcode":"46410",
    "sg:province":"IN",
    "wof:name":"Bank Calumet",
    "wof:placetype":"venue"
},
  "geometry": {"coordinates":[-87.335984,41.507581],"type":"Point"}
}