{
  "type": "Feature",
  "properties": {
    "iso:country":"US",
    "sg:address":"1203 College St",
    "sg:city":"Logansport",
    "sg:classifiers":[
        {
            "category":"Social Services",
            "type":"Services"
        }
    ],
    "sg:phone":"+1 574 753 3500",
    "sg:postcode":"46947",
    "sg:province":"IN",
    "sg:tags":[
        "organization",
        "welfare"
    ],
    "wof:name":"Emmaus Benevolence Facility",
    "wof:placetype":"venue"
},
  "geometry": {"coordinates":[-86.37385,40.761071],"type":"Point"}
}