{
  "type": "Feature",
  "properties": {
    "addr:full":"10215 Saint Johns Rd Borden IN 47106",
    "addr:housenumber":"10215",
    "addr:postcode":"47106",
    "addr:street":"Saint Johns Rd",
    "iso:country":"US",
    "sg:address":"10215 Saint Johns Rd",
    "sg:city":"Borden",
    "sg:classifiers":[
        {
            "category":"Wholesale",
            "subcategory":"Meat",
            "type":"Manufacturing & Wholesale Goods"
        }
    ],
    "sg:phone":"+1 812 923 5601",
    "sg:postcode":"47106",
    "sg:province":"IN",
    "sg:tags":[
        "packer"
    ],
    "wof:name":"Faske Wood Moulding Inc",
    "wof:placetype":"venue"
},
  "geometry": {"coordinates":[-85.92949,38.418594],"type":"Point"}
}