{
  "type": "Feature",
  "properties": {
    "iso:country":"US",
    "sg:address":"5323 US Hwy 35",
    "sg:city":"La Porte",
    "sg:classifiers":[
        {
            "category":"Professional",
            "subcategory":"Computer Services",
            "type":"Services"
        }
    ],
    "sg:phone":"+1 219 873 0673",
    "sg:postcode":"46350",
    "sg:province":"IN",
    "sg:tags":[
        "machinery",
        "automation"
    ],
    "wof:name":"Adtec Solutions Inc",
    "wof:placetype":"venue"
},
  "geometry": {"coordinates":[-86.79303,41.683678],"type":"Point"}
}