{
  "type": "Feature",
  "properties": {
    "iso:country":"US",
    "sg:address":"5121 Hillside Ave",
    "sg:city":"Indianapolis",
    "sg:classifiers":[
        {
            "category":"Professional",
            "subcategory":"Computer Services",
            "type":"Services"
        }
    ],
    "sg:phone":"+1 317 251 5965",
    "sg:postcode":"46205",
    "sg:province":"IN",
    "sg:tags":[
        "datum",
        "commercial",
        "desi"
    ],
    "wof:name":"Man Made Graphx Inc",
    "wof:placetype":"venue"
},
  "geometry": {"coordinates":[-86.12424,39.846101],"type":"Point"}
}