{
  "type": "Feature",
  "properties": {
    "addr:full":"3100 Periwinkle Way New Albany IN 47150",
    "addr:housenumber":"3100",
    "addr:postcode":"47150",
    "addr:street":"Periwinkle Way",
    "iso:country":"US",
    "sg:address":"3100 Periwinkle Way",
    "sg:city":"New Albany",
    "sg:classifiers":[
        {
            "category":"Wholesale",
            "subcategory":"Durable Goods & Equipment",
            "type":"Manufacturing & Wholesale Goods"
        }
    ],
    "sg:phone":"+1 812 941 0805",
    "sg:postcode":"47150",
    "sg:province":"IN",
    "sg:tags":[
        "representative",
        "manufacturer"
    ],
    "wof:name":"Tri-State Coating & Machine",
    "wof:placetype":"venue"
},
  "geometry": {"coordinates":[-85.773138,38.355965],"type":"Point"}
}