{
  "type": "Feature",
  "properties": {
    "iso:country":"US",
    "sg:address":"2863 N Co Rd 775 E",
    "sg:city":"Coatesville",
    "sg:classifiers":[
        {
            "category":"Professional",
            "subcategory":"Management & Consulting",
            "type":"Services"
        }
    ],
    "sg:phone":"+1 765 386 6777",
    "sg:postcode":"46121",
    "sg:province":"IN",
    "sg:tags":[
        "business"
    ],
    "wof:name":"The Cavalry II",
    "wof:placetype":"venue"
},
  "geometry": {"coordinates":[-86.710514,39.696647],"type":"Point"}
}