{
  "type": "Feature",
  "properties": {
    "iso:country":"US",
    "sg:address":"185 Jefferson St N",
    "sg:city":"Nashville",
    "sg:classifiers":[
        {
            "category":"Shopping",
            "subcategory":"Used Merchandise",
            "type":"Retail Goods"
        }
    ],
    "sg:phone":"+1 812 988 9086",
    "sg:postcode":"47448",
    "sg:province":"IN",
    "sg:tags":[
        "antique"
    ],
    "wof:name":"Remember When",
    "wof:placetype":"venue"
},
  "geometry": {"coordinates":[-86.24809,39.209067],"type":"Point"}
}