{
  "type": "Feature",
  "properties": {
    "iso:country":"US",
    "sg:address":"110 NW 1st St",
    "sg:city":"Paoli",
    "sg:classifiers":[
        {
            "category":"Retail",
            "subcategory":"Repair Shop",
            "type":"Services"
        }
    ],
    "sg:phone":"+1 812 723 2975",
    "sg:postcode":"47454",
    "sg:province":"IN",
    "sg:tags":[
        "lock",
        "locksmith"
    ],
    "wof:name":"Wellman Lock & Security",
    "wof:placetype":"venue"
},
  "geometry": {"coordinates":[-86.469712,38.557095],"type":"Point"}
}