{
  "type": "Feature",
  "properties": {
    "iso:country":"US",
    "sg:address":"9599 Heim Rd",
    "sg:city":"Chandler",
    "sg:classifiers":[
        {
            "category":"Building & Trades",
            "subcategory":"Construction",
            "type":"Services"
        }
    ],
    "sg:phone":"+1 812 925 6837",
    "sg:postcode":"47610",
    "sg:province":"IN",
    "sg:tags":[
        "house"
    ],
    "wof:name":"Williamson General Contracting",
    "wof:placetype":"venue"
},
  "geometry": {"coordinates":[-87.425477,38.041899],"type":"Point"}
}