{
  "type": "Feature",
  "properties": {
    "iso:country":"US",
    "sg:address":"14435 Leo Rd",
    "sg:city":"Leo",
    "sg:classifiers":[
        {
            "category":"Building & Trades",
            "subcategory":"Landscaping Services",
            "type":"Services"
        }
    ],
    "sg:phone":"+1 260 627 0411",
    "sg:postcode":"46765",
    "sg:province":"IN",
    "sg:tags":[
        "tree"
    ],
    "wof:name":"Arborstar Alpine",
    "wof:placetype":"venue"
},
  "geometry": {"coordinates":[-85.015134,41.217355],"type":"Point"}
}