{
  "type": "Feature",
  "properties": {
    "iso:country":"US",
    "sg:address":"5687 N Co Rd 700 W",
    "sg:city":"St Paul",
    "sg:classifiers":[
        {
            "category":"Retail",
            "subcategory":"Auto Repair",
            "type":"Services"
        }
    ],
    "sg:phone":"+1 765 525 6109",
    "sg:postcode":"47272",
    "sg:province":"IN",
    "sg:tags":[
        "repairing",
        "automobile",
        "general"
    ],
    "wof:name":"T & K Performance & Parts",
    "wof:placetype":"venue"
},
  "geometry": {"coordinates":[-85.625959,39.415874],"type":"Point"}
}