{
  "type": "Feature",
  "properties": {
    "addr:full":"521 N 13th St Decatur IN 46733",
    "addr:housenumber":"521",
    "addr:postcode":"46733",
    "addr:street":"N 13Th St",
    "iso:country":"US",
    "sg:address":"521 N 13th St",
    "sg:city":"Decatur",
    "sg:classifiers":[
        {
            "category":"Building & Trades",
            "subcategory":"Equipment Rental",
            "type":"Services"
        }
    ],
    "sg:phone":"+1 260 728 9494",
    "sg:postcode":"46733",
    "sg:province":"IN",
    "sg:tags":[
        "yard"
    ],
    "wof:name":"Rent-A-Center",
    "wof:placetype":"venue"
},
  "geometry": {"coordinates":[-84.93783500000001,40.834768],"type":"Point"}
}