{
  "type": "Feature",
  "properties": {
    "iso:country":"US",
    "sg:address":"9404 W 2100 S",
    "sg:city":"La Crosse",
    "sg:classifiers":[
        {
            "category":"Manufacturing",
            "subcategory":"Toys & Sporting Goods",
            "type":"Manufacturing & Wholesale Goods"
        }
    ],
    "sg:phone":"+1 219 754 2501",
    "sg:postcode":"46348",
    "sg:province":"IN",
    "sg:tags":[
        "fund",
        "game",
        "raising",
        "mdse"
    ],
    "wof:name":"Labraid Inc",
    "wof:placetype":"venue"
},
  "geometry": {"coordinates":[-86.883955,41.302698],"type":"Point"}
}