{
  "type": "Feature",
  "properties": {
    "iso:country":"US",
    "sg:address":"8825 Elmonte Dr",
    "sg:city":"Indianapolis",
    "sg:classifiers":[
        {
            "category":"Personal",
            "subcategory":"Beauty Salon",
            "type":"Services"
        }
    ],
    "sg:phone":"+1 317 899 8994",
    "sg:postcode":"46226",
    "sg:province":"IN",
    "wof:name":"Options Hair Design",
    "wof:placetype":"venue"
},
  "geometry": {"coordinates":[-86.012851,39.829497],"type":"Point"}
}