{
  "type": "Feature",
  "properties": {
    "iso:country":"US",
    "sg:address":"430 Co Rd 28",
    "sg:city":"Corunna",
    "sg:classifiers":[
        {
            "category":"Wholesale",
            "subcategory":"Machinery & Supplies",
            "type":"Manufacturing & Wholesale Goods"
        }
    ],
    "sg:phone":"+1 260 281 2211",
    "sg:postcode":"46730",
    "sg:province":"IN",
    "sg:tags":[
        "repairing"
    ],
    "wof:name":"DRG Enterprises",
    "wof:placetype":"venue"
},
  "geometry": {"coordinates":[-85.170104,41.424135],"type":"Point"}
}