{
  "type": "Feature",
  "properties": {
    "iso:country":"US",
    "sg:address":"212 S Main St",
    "sg:city":"Crown Point",
    "sg:classifiers":[
        {
            "category":"Personal",
            "subcategory":"Massage",
            "type":"Services"
        },
        {
            "category":"Health Services",
            "subcategory":"Chiropractor",
            "type":"Services"
        }
    ],
    "sg:phone":"+1 219 662 2345",
    "sg:postcode":"46307",
    "sg:province":"IN",
    "wof:name":"Crown Point Chiropractic Ctr",
    "wof:placetype":"venue"
},
  "geometry": {"coordinates":[-87.364304,41.416801],"type":"Point"}
}