{
  "type": "Feature",
  "properties": {
    "iso:country":"US",
    "sg:address":"5528 Wayne Trce",
    "sg:city":"Fort Wayne",
    "sg:classifiers":[
        {
            "category":"Building & Trades",
            "subcategory":"Construction",
            "type":"Services"
        }
    ],
    "sg:phone":"+1 260 447 9419",
    "sg:postcode":"46806",
    "sg:province":"IN",
    "sg:tags":[
        "house"
    ],
    "wof:name":"Andrew Johnson Fine Carptry",
    "wof:placetype":"venue"
},
  "geometry": {"coordinates":[-85.085919,41.036707],"type":"Point"}
}