{
  "type": "Feature",
  "properties": {
    "iso:country":"US",
    "sg:address":"10134 Brooks School Rd",
    "sg:city":"Fishers",
    "sg:classifiers":[
        {
            "category":"Shopping",
            "type":"Retail Goods"
        }
    ],
    "sg:phone":"+1 317 913 1254",
    "sg:postcode":"46037",
    "sg:province":"IN",
    "sg:tags":[
        "art",
        "gallery",
        "dealer"
    ],
    "wof:name":"Art & Soul Inc",
    "wof:placetype":"venue"
},
  "geometry": {"coordinates":[-85.947582,39.93508],"type":"Point"}
}