{
  "type": "Feature",
  "properties": {
    "iso:country":"US",
    "sg:address":"814 E Main St",
    "sg:city":"Richmond",
    "sg:classifiers":[
        {
            "category":"Banks & Credit Unions",
            "subcategory":"Investment Brokerage",
            "type":"Services"
        }
    ],
    "sg:phone":"+1 765 935 3014",
    "sg:postcode":"47374",
    "sg:province":"IN",
    "sg:tags":[
        "consultant",
        "planning",
        "financial"
    ],
    "wof:name":"Faith Financial Planners",
    "wof:placetype":"venue"
},
  "geometry": {"coordinates":[-84.890475,39.829117],"type":"Point"}
}