{
  "type": "Feature",
  "properties": {
    "addr:full":"3028 Indiana Ave Connersville IN 47331",
    "addr:housenumber":"3028",
    "addr:postcode":"47331",
    "addr:street":"Indiana Ave",
    "iso:country":"US",
    "sg:address":"3028 Indiana Ave",
    "sg:city":"Connersville",
    "sg:classifiers":[
        {
            "category":"Shopping",
            "type":"Retail Goods"
        },
        {
            "category":"Building & Trades",
            "subcategory":"Construction",
            "type":"Services"
        }
    ],
    "sg:phone":"+1 765 825 7170",
    "sg:postcode":"47331",
    "sg:province":"IN",
    "sg:tags":[
        "equipment",
        "swimming",
        "merchandise",
        "pool",
        "contractor"
    ],
    "wof:name":"R & G Pools Inc",
    "wof:placetype":"venue"
},
  "geometry": {"coordinates":[-85.133199,39.672976],"type":"Point"}
}