{
  "type": "Feature",
  "properties": {
    "iso:country":"US",
    "sg:address":"715 S Alabama St",
    "sg:city":"Brazil",
    "sg:classifiers":[
        {
            "category":"Personal",
            "subcategory":"Beauty Salon",
            "type":"Services"
        }
    ],
    "sg:phone":"+1 812 443 0181",
    "sg:postcode":"47834",
    "sg:province":"IN",
    "wof:name":"Hairport Beauty Salon",
    "wof:placetype":"venue"
},
  "geometry": {"coordinates":[-87.11971200000001,39.51804],"type":"Point"}
}