{
  "type": "Feature",
  "properties": {
    "iso:country":"US",
    "sg:address":"4239 Earnings Way",
    "sg:city":"New Albany",
    "sg:classifiers":[
        {
            "category":"Manufacturing",
            "subcategory":"Tools & Machinery",
            "type":"Manufacturing & Wholesale Goods"
        }
    ],
    "sg:phone":"+1 812 944 9368",
    "sg:postcode":"47150",
    "sg:province":"IN",
    "sg:tags":[
        "machine",
        "shop"
    ],
    "wof:name":"S & J Precision",
    "wof:placetype":"venue"
},
  "geometry": {"coordinates":[-85.835714,38.34403],"type":"Point"}
}