{
  "type": "Feature",
  "properties": {
    "addr:full":"719 E 8th St New Albany IN 47150",
    "addr:housenumber":"719",
    "addr:postcode":"47150",
    "addr:street":"E 8Th St",
    "iso:country":"US",
    "sg:address":"719 E 8th St",
    "sg:city":"New Albany",
    "sg:classifiers":[
        {
            "category":"Professional",
            "subcategory":"Advertising",
            "type":"Services"
        }
    ],
    "sg:phone":"+1 812 941 8897",
    "sg:postcode":"47150",
    "sg:province":"IN",
    "wof:name":"NETPOINTE.COM",
    "wof:placetype":"venue"
},
  "geometry": {"coordinates":[-85.81770299999999,38.292373],"type":"Point"}
}