{
  "type": "Feature",
  "properties": {
    "iso:country":"US",
    "sg:address":"9414 Kennedy Ave",
    "sg:city":"Highland",
    "sg:classifiers":[
        {
            "category":"Organizations",
            "subcategory":"Religious Organization",
            "type":"Services"
        }
    ],
    "sg:phone":"+1 219 924 6714",
    "sg:postcode":"46322",
    "sg:province":"IN",
    "wof:name":"Highland Assembly of God",
    "wof:placetype":"venue"
},
  "geometry": {"coordinates":[-87.46169999999999,41.542099],"type":"Point"}
}