{
  "type": "Feature",
  "properties": {
    "iso:country":"US",
    "sg:address":"9977 Wicker Ave",
    "sg:city":"St John",
    "sg:classifiers":[
        {
            "category":"Retail",
            "subcategory":"Auto Repair",
            "type":"Services"
        }
    ],
    "sg:phone":"+1 219 365 9009",
    "sg:postcode":"46373",
    "sg:province":"IN",
    "sg:tags":[
        "lubricating"
    ],
    "wof:name":"Oil Exchange Inc",
    "wof:placetype":"venue"
},
  "geometry": {"coordinates":[-87.469909,41.43725],"type":"Point"}
}