{
  "type": "Feature",
  "properties": {
    "iso:country":"US",
    "sg:address":"716 W Franklin St",
    "sg:city":"Evansville",
    "sg:classifiers":[
        {
            "category":"Autos & Motor Vehicles",
            "subcategory":"Motorcycle Sales",
            "type":"Retail Goods"
        }
    ],
    "sg:phone":"+1 812 464 2326",
    "sg:postcode":"47710",
    "sg:province":"IN",
    "sg:tags":[
        "scooter"
    ],
    "wof:name":"Franklin Cycle Sales",
    "wof:placetype":"venue"
},
  "geometry": {"coordinates":[-87.574811,37.98024],"type":"Point"}
}