{
  "type": "Feature",
  "properties": {
    "addr:full":"616 Payton Ave Indianapolis IN 46219",
    "addr:housenumber":"616",
    "addr:postcode":"46219",
    "addr:street":"Payton Ave",
    "iso:country":"US",
    "sg:address":"616 Payton Ave",
    "sg:city":"Indianapolis",
    "sg:classifiers":[
        {
            "category":"Professional",
            "subcategory":"Accounting & Tax Preparation",
            "type":"Services"
        }
    ],
    "sg:phone":"+1 317 359 2569",
    "sg:postcode":"46219",
    "sg:province":"IN",
    "wof:name":"Fred Wiseman Accounting",
    "wof:placetype":"venue"
},
  "geometry": {"coordinates":[-86.032819,39.780522],"type":"Point"}
}