{
  "type": "Feature",
  "properties": {
    "addr:full":"2945 Jewett Ave Highland IN 46322",
    "addr:housenumber":"2945",
    "addr:postcode":"46322",
    "addr:street":"Jewett Ave",
    "iso:country":"US",
    "sg:address":"2945 Jewett Ave",
    "sg:city":"Highland",
    "sg:classifiers":[
        {
            "category":"Education",
            "subcategory":"Special Training",
            "type":"Public Place"
        }
    ],
    "sg:phone":"+1 219 365 7037",
    "sg:postcode":"46322",
    "sg:province":"IN",
    "sg:tags":[
        "school",
        "instruction",
        "driving"
    ],
    "wof:name":"Rite-Way Driving School Inc Schl",
    "wof:placetype":"venue"
},
  "geometry": {"coordinates":[-87.4571,41.554699],"type":"Point"}
}