{
  "type": "Feature",
  "properties": {
    "iso:country":"US",
    "sg:address":"2808 Nordholme Ave",
    "sg:city":"Fort Wayne",
    "sg:classifiers":[
        {
            "category":"Building & Trades",
            "subcategory":"Construction",
            "type":"Services"
        }
    ],
    "sg:phone":"+1 260 433 6757",
    "sg:postcode":"46805",
    "sg:province":"IN",
    "sg:tags":[
        "roofing",
        "contractor"
    ],
    "wof:name":"Home Team Roofing",
    "wof:placetype":"venue"
},
  "geometry": {"coordinates":[-85.096376,41.101954],"type":"Point"}
}