{
  "type": "Feature",
  "properties": {
    "addr:full":"1222 E Pontiac St Fort Wayne IN 46803",
    "addr:housenumber":"1222",
    "addr:postcode":"46803",
    "addr:street":"E Pontiac St",
    "iso:country":"US",
    "sg:address":"1222 E Pontiac St",
    "sg:city":"Fort Wayne",
    "sg:classifiers":[
        {
            "category":"Personal",
            "subcategory":"Beauty Salon",
            "type":"Services"
        }
    ],
    "sg:phone":"+1 260 745 8559",
    "sg:postcode":"46803",
    "sg:province":"IN",
    "wof:name":"Changing Faces",
    "wof:placetype":"venue"
},
  "geometry": {"coordinates":[-85.120446,41.060592],"type":"Point"}
}