{
  "type": "Feature",
  "properties": {
    "addr:full":"1995 E State Rd 10 Knox IN 46534",
    "addr:housenumber":"1995;10",
    "addr:postcode":"46534",
    "addr:street":"E State Rd",
    "iso:country":"US",
    "sg:address":"1995 E State Rd 10",
    "sg:city":"Knox",
    "sg:classifiers":[
        {
            "category":"Shopping",
            "subcategory":"Gifts & Souvenirs",
            "type":"Retail Goods"
        }
    ],
    "sg:phone":"+1 574 772 5740",
    "sg:postcode":"46534",
    "sg:province":"IN",
    "wof:name":"Treasure Box",
    "wof:placetype":"venue"
},
  "geometry": {"coordinates":[-86.668769,41.215152],"type":"Point"}
}