{
  "type": "Feature",
  "properties": {
    "iso:country":"US",
    "sg:address":"1800 Jim Neu Dr",
    "sg:city":"Plymouth",
    "sg:classifiers":[
        {
            "category":"Education",
            "subcategory":"School",
            "type":"Public Place"
        }
    ],
    "sg:phone":"+1 574 936 8834",
    "sg:postcode":"46563",
    "sg:province":"IN",
    "sg:tags":[
        "educational",
        "program"
    ],
    "wof:name":"Crossroads Academy-Work One",
    "wof:placetype":"venue"
},
  "geometry": {"coordinates":[-86.330013,41.354579],"type":"Point"}
}