{
  "type": "Feature",
  "properties": {
    "iso:country":"US",
    "sg:address":"111 W Main St",
    "sg:city":"Portland",
    "sg:classifiers":[
        {
            "category":"Organizations",
            "subcategory":"Non-profit Organization",
            "type":"Services"
        }
    ],
    "sg:phone":"+1 260 726 8636",
    "sg:postcode":"47371",
    "sg:province":"IN",
    "sg:tags":[
        "alternative",
        "abortion"
    ],
    "wof:name":"Pregnancy Care Ctr Of Jay Co",
    "wof:placetype":"venue"
},
  "geometry": {"coordinates":[-84.977998,40.433281],"type":"Point"}
}