{
  "type": "Feature",
  "properties": {
    "addr:full":"611 W Park Ave Kokomo IN 46901",
    "addr:housenumber":"611",
    "addr:postcode":"46901",
    "addr:street":"W Park Ave",
    "iso:country":"US",
    "sg:address":"611 W Park Ave",
    "sg:city":"Kokomo",
    "sg:classifiers":[
        {
            "category":"Restaurant",
            "type":"Food & Drink"
        }
    ],
    "sg:phone":"+1 574 722 3591",
    "sg:postcode":"46901",
    "sg:province":"IN",
    "sg:tags":[
        "eating",
        "caterer"
    ],
    "wof:name":"Rozzi's Catering",
    "wof:placetype":"venue"
},
  "geometry": {"coordinates":[-86.138339,40.482499],"type":"Point"}
}