{
  "type": "Feature",
  "properties": {
    "iso:country":"US",
    "sg:address":"711 E Lake St",
    "sg:city":"Knox",
    "sg:classifiers":[
        {
            "category":"Building & Trades",
            "subcategory":"Plumbing",
            "type":"Services"
        }
    ],
    "sg:phone":"+1 574 772 4151",
    "sg:postcode":"46534",
    "sg:province":"IN",
    "sg:tags":[
        "contractor"
    ],
    "wof:name":"E & B Plumbing",
    "wof:placetype":"venue"
},
  "geometry": {"coordinates":[-86.614615,41.297527],"type":"Point"}
}