{
  "type": "Feature",
  "properties": {
    "iso:country":"US",
    "sg:address":"3368 US Hwy 36",
    "sg:city":"Middletown",
    "sg:classifiers":[
        {
            "category":"Organizations",
            "subcategory":"Religious Organization",
            "type":"Services"
        }
    ],
    "sg:phone":"+1 765 533 4249",
    "sg:postcode":"47356",
    "sg:province":"IN",
    "sg:tags":[
        "church"
    ],
    "wof:name":"Sulphur Springs United Church",
    "wof:placetype":"venue"
},
  "geometry": {"coordinates":[-85.451908,40.004884],"type":"Point"}
}