{
  "type": "Feature",
  "properties": {
    "iso:country":"US",
    "sg:address":"812 S Baldwin Ave",
    "sg:city":"Marion",
    "sg:classifiers":[
        {
            "category":"Utilities",
            "subcategory":"Mobile Phone",
            "type":"Services"
        }
    ],
    "sg:phone":"+1 765 664 1500",
    "sg:postcode":"46953",
    "sg:province":"IN",
    "sg:tags":[
        "telephone",
        "cellular"
    ],
    "wof:name":"Centennial Wireless",
    "wof:placetype":"venue"
},
  "geometry": {"coordinates":[-85.675745,40.552854],"type":"Point"}
}