{
  "type": "Feature",
  "properties": {
    "iso:country":"US",
    "sg:address":"1069 Fillmore St",
    "sg:city":"Gary",
    "sg:classifiers":[
        {
            "category":"Organizations",
            "subcategory":"Religious Organization",
            "type":"Services"
        }
    ],
    "sg:phone":"+1 219 882 4264",
    "sg:postcode":"46402",
    "sg:province":"IN",
    "sg:tags":[
        "church"
    ],
    "wof:name":"Bethel Church Of God",
    "wof:placetype":"venue"
},
  "geometry": {"coordinates":[-87.350486,41.593342],"type":"Point"}
}