{
  "type": "Feature",
  "properties": {
    "iso:country":"US",
    "sg:address":"1628 State Rd 114",
    "sg:city":"Rensselaer",
    "sg:classifiers":[
        {
            "category":"Manufacturing",
            "subcategory":"Motor Vehicles & Parts",
            "type":"Manufacturing & Wholesale Goods"
        }
    ],
    "sg:phone":"+1 219 866 7141",
    "sg:postcode":"47978",
    "sg:province":"IN",
    "sg:tags":[
        "truck"
    ],
    "sg:website":"www.talbertmfg.com",
    "wof:name":"Talbert Manufacturing Inc",
    "wof:placetype":"venue"
},
  "geometry": {"coordinates":[-87.006378,40.934125],"type":"Point"}
}