{
  "type": "Feature",
  "properties": {
    "iso:country":"US",
    "sg:address":"5370 W 46th St",
    "sg:city":"Indianapolis",
    "sg:classifiers":[
        {
            "category":"Education",
            "subcategory":"College",
            "type":"Public Place"
        },
        {
            "category":"Organizations",
            "subcategory":"Membership Organization",
            "type":"Services"
        }
    ],
    "sg:phone":"+1 317 298 8956",
    "sg:postcode":"46254",
    "sg:province":"IN",
    "sg:tags":[
        "fraternal",
        "sorority",
        "housing",
        "student",
        "fraternity"
    ],
    "wof:name":"Evergreen Oriental Lodge",
    "wof:placetype":"venue"
},
  "geometry": {"coordinates":[-86.252067,39.838459],"type":"Point"}
}