{
  "type": "Feature",
  "properties": {
    "iso:country":"US",
    "sg:address":"8151 S Range Rd",
    "sg:city":"Kingsford Hts",
    "sg:classifiers":[
        {
            "category":"Manufacturing",
            "subcategory":"Glass & Minerals",
            "type":"Manufacturing & Wholesale Goods"
        }
    ],
    "sg:phone":"+1 219 393 5585",
    "sg:postcode":"46366",
    "sg:province":"IN",
    "sg:tags":[
        "slag"
    ],
    "wof:name":"Performix Technologies",
    "wof:placetype":"venue"
},
  "geometry": {"coordinates":[-86.698468,41.184519],"type":"Point"}
}