{
  "type": "Feature",
  "properties": {
    "iso:country":"US",
    "sg:address":"16 E 5th St",
    "sg:city":"Peru",
    "sg:classifiers":[
        {
            "category":"Banks & Credit Unions",
            "subcategory":"Investment Brokerage",
            "type":"Services"
        }
    ],
    "sg:phone":"+1 765 472 3845",
    "sg:postcode":"46970",
    "sg:province":"IN",
    "sg:tags":[
        "consultant",
        "planning",
        "financial"
    ],
    "wof:name":"American Express Financial Adv",
    "wof:placetype":"venue"
},
  "geometry": {"coordinates":[-86.069303,40.754799],"type":"Point"}
}