{
  "type": "Feature",
  "properties": {
    "addr:full":"906 16th St Bedford IN 47421",
    "addr:housenumber":"906",
    "addr:postcode":"47421",
    "addr:street":"16Th St",
    "iso:country":"US",
    "sg:address":"906 16th St",
    "sg:city":"Bedford",
    "sg:classifiers":[
        {
            "category":"Sports & Exercise",
            "subcategory":"Gym",
            "type":"Entertainment"
        }
    ],
    "sg:phone":"+1 812 275 0855",
    "sg:postcode":"47421",
    "sg:province":"IN",
    "sg:tags":[
        "club",
        "health",
        "studio",
        "gymnasium"
    ],
    "wof:name":"Johnathan's Inc",
    "wof:placetype":"venue"
},
  "geometry": {"coordinates":[-86.48407400000001,38.860932],"type":"Point"}
}