{
  "type": "Feature",
  "properties": {
    "iso:country":"US",
    "sg:address":"2012 Graham Ave",
    "sg:city":"Evansville",
    "sg:classifiers":[
        {
            "category":"Personal",
            "subcategory":"Beauty Salon",
            "type":"Services"
        }
    ],
    "sg:phone":"+1 812 476 3724",
    "sg:postcode":"47714",
    "sg:province":"IN",
    "wof:name":"Irene Martin Beauty Parlor",
    "wof:placetype":"venue"
},
  "geometry": {"coordinates":[-87.52811,37.949198],"type":"Point"}
}