{
  "type": "Feature",
  "properties": {
    "iso:country":"US",
    "sg:address":"6333 Hollister Dr",
    "sg:city":"Indianapolis",
    "sg:classifiers":[
        {
            "category":"Banks & Credit Unions",
            "subcategory":"Bank",
            "type":"Services"
        }
    ],
    "sg:phone":"+1 317 243 3007",
    "sg:postcode":"46224",
    "sg:province":"IN",
    "sg:tags":[
        "loan",
        "real estate"
    ],
    "sg:website":"www.americanacceptance.com",
    "wof:name":"American Acceptance Mortgage",
    "wof:placetype":"venue"
},
  "geometry": {"coordinates":[-86.27099,39.807336],"type":"Point"}
}