{
  "type": "Feature",
  "properties": {
    "iso:country":"US",
    "sg:address":"55 N Keystone Ave",
    "sg:city":"Indianapolis",
    "sg:classifiers":[
        {
            "category":"Shopping",
            "subcategory":"Pharmacy",
            "type":"Retail Goods"
        }
    ],
    "sg:phone":"+1 317 253 7063",
    "sg:postcode":"46201",
    "sg:province":"IN",
    "wof:name":"Osco Drug 5390",
    "wof:placetype":"venue"
},
  "geometry": {"coordinates":[-86.121818,39.768644],"type":"Point"}
}