{
  "type": "Feature",
  "properties": {
    "iso:country":"US",
    "sg:address":"22 Dorothy Dr",
    "sg:city":"Evansville",
    "sg:classifiers":[
        {
            "category":"Retail",
            "subcategory":"Repair Shop",
            "type":"Services"
        }
    ],
    "sg:phone":"+1 812 422 6475",
    "sg:postcode":"47712",
    "sg:province":"IN",
    "wof:name":"Myac Inc",
    "wof:placetype":"venue"
},
  "geometry": {"coordinates":[-87.62302,37.978703],"type":"Point"}
}