{
  "type": "Feature",
  "properties": {
    "iso:country":"US",
    "sg:address":"521 E Lincoln Ave",
    "sg:city":"Goshen",
    "sg:classifiers":[
        {
            "category":"Wholesale",
            "subcategory":"Vending Machines",
            "type":"Manufacturing & Wholesale Goods"
        }
    ],
    "sg:phone":"+1 574 533 1197",
    "sg:postcode":"46528",
    "sg:province":"IN",
    "wof:name":"Steve's Snack & Soda",
    "wof:placetype":"venue"
},
  "geometry": {"coordinates":[-85.827721,41.586613],"type":"Point"}
}