{
  "type": "Feature",
  "properties": {
    "iso:country":"US",
    "sg:address":"451 Oak St",
    "sg:city":"Connersville",
    "sg:classifiers":[
        {
            "category":"Professional",
            "type":"Services"
        }
    ],
    "sg:phone":"+1 765 827 1332",
    "sg:postcode":"47331",
    "sg:province":"IN",
    "wof:name":"Umbrella Family Waiver Service",
    "wof:placetype":"venue"
},
  "geometry": {"coordinates":[-85.147093,39.642244],"type":"Point"}
}