{
  "type": "Feature",
  "properties": {
    "addr:full":"520 N 6th St Richmond IN 47374",
    "addr:housenumber":"520",
    "addr:postcode":"47374",
    "addr:street":"N 6Th St",
    "iso:country":"US",
    "sg:address":"520 N 6th St",
    "sg:city":"Richmond",
    "sg:classifiers":[
        {
            "category":"Manufacturing",
            "subcategory":"Food",
            "type":"Manufacturing & Wholesale Goods"
        }
    ],
    "sg:phone":"+1 765 962 8535",
    "sg:postcode":"47374",
    "sg:province":"IN",
    "sg:tags":[
        "cookie",
        "cracker"
    ],
    "sg:website":"www.richmondbaking.com",
    "wof:name":"Richmond Baking Co",
    "wof:placetype":"venue"
},
  "geometry": {"coordinates":[-84.893828,39.834609],"type":"Point"}
}