{
  "type": "Feature",
  "properties": {
    "iso:country":"US",
    "sg:address":"201 N Main St",
    "sg:city":"Salem",
    "sg:classifiers":[
        {
            "category":"Professional",
            "subcategory":"Lawyer & Legal Services",
            "type":"Services"
        }
    ],
    "sg:phone":"+1 812 883 2291",
    "sg:postcode":"47167",
    "sg:province":"IN",
    "sg:tags":[
        "attorney"
    ],
    "wof:name":"Leatherbury Law Office",
    "wof:placetype":"venue"
},
  "geometry": {"coordinates":[-86.100816,38.607239],"type":"Point"}
}