{
  "type": "Feature",
  "properties": {
    "iso:country":"US",
    "sg:address":"2325 Schuyler Ave",
    "sg:city":"Lafayette",
    "sg:classifiers":[
        {
            "category":"Building & Trades",
            "subcategory":"Plumbing",
            "type":"Services"
        }
    ],
    "sg:phone":"+1 765 429 6959",
    "sg:postcode":"47904",
    "sg:province":"IN",
    "sg:tags":[
        "conditioning",
        "air",
        "system",
        "contractor"
    ],
    "wof:name":"American Diamond Heating",
    "wof:placetype":"venue"
},
  "geometry": {"coordinates":[-86.86995899999999,40.443338],"type":"Point"}
}