{
  "type": "Feature",
  "properties": {
    "iso:country":"US",
    "sg:address":"879 Joliet St",
    "sg:city":"Dyer",
    "sg:classifiers":[
        {
            "category":"Professional",
            "subcategory":"Printing & Photocopies",
            "type":"Services"
        }
    ],
    "sg:phone":"+1 219 322 9004",
    "sg:postcode":"46311",
    "sg:province":"IN",
    "sg:tags":[
        "duplicating",
        "copying"
    ],
    "wof:name":"UPS Store",
    "wof:placetype":"venue"
},
  "geometry": {"coordinates":[-87.502002,41.492157],"type":"Point"}
}