{
  "type": "Feature",
  "properties": {
    "iso:country":"US",
    "sg:address":"743 E Franklin St",
    "sg:city":"Spencer",
    "sg:classifiers":[
        {
            "category":"Insurance",
            "subcategory":"Insurance Agent",
            "type":"Services"
        }
    ],
    "sg:phone":"+1 812 829 2293",
    "sg:postcode":"47460",
    "sg:province":"IN",
    "wof:name":"Farm Bureau Insurance",
    "wof:placetype":"venue"
},
  "geometry": {"coordinates":[-86.75390299999999,39.286253],"type":"Point"}
}