{
  "type": "Feature",
  "properties": {
    "iso:country":"US",
    "sg:address":"114 N Market St",
    "sg:city":"Winamac",
    "sg:classifiers":[
        {
            "category":"Real Estate",
            "subcategory":"Real Estate Agent",
            "type":"Services"
        },
        {
            "category":"Professional",
            "subcategory":"Business Services",
            "type":"Services"
        }
    ],
    "sg:phone":"+1 574 946 7300",
    "sg:postcode":"46996",
    "sg:province":"IN",
    "sg:tags":[
        "auctioneer"
    ],
    "wof:name":"Murray Auction & Realty LLC",
    "wof:placetype":"venue"
},
  "geometry": {"coordinates":[-86.60442,41.051741],"type":"Point"}
}