{
  "type": "Feature",
  "properties": {
    "iso:country":"US",
    "sg:address":"8909 Marx Rd",
    "sg:city":"Evansville",
    "sg:classifiers":[
        {
            "category":"Autos & Motor Vehicles",
            "subcategory":"Auto Supplies",
            "type":"Retail Goods"
        }
    ],
    "sg:phone":"+1 812 464 0500",
    "sg:postcode":"47720",
    "sg:province":"IN",
    "sg:tags":[
        "automobile",
        "parts"
    ],
    "wof:name":"Auto Parts & Equipment",
    "wof:placetype":"venue"
},
  "geometry": {"coordinates":[-87.677564,38.015678],"type":"Point"}
}