{
  "type": "Feature",
  "properties": {
    "iso:country":"US",
    "sg:address":"5767 Dividend Rd",
    "sg:city":"Indianapolis",
    "sg:classifiers":[
        {
            "category":"Manufacturing",
            "subcategory":"Food",
            "type":"Manufacturing & Wholesale Goods"
        }
    ],
    "sg:phone":"+1 317 241 7422",
    "sg:postcode":"46241",
    "sg:province":"IN",
    "sg:tags":[
        "corn",
        "chips",
        "potato"
    ],
    "wof:name":"Mike-Sell's Indiana",
    "wof:placetype":"venue"
},
  "geometry": {"coordinates":[-86.25722399999999,39.739112],"type":"Point"}
}