{
  "type": "Feature",
  "properties": {
    "iso:country":"US",
    "sg:address":"2924 Frontage Rd",
    "sg:city":"Warsaw",
    "sg:classifiers":[
        {
            "category":"Restaurant",
            "type":"Food & Drink"
        }
    ],
    "sg:menulink":"http://www.allmenus.com/in/warsaw/208132-taco-bell/menu/",
    "sg:phone":"+1 574 269 1119",
    "sg:postcode":"46580",
    "sg:province":"IN",
    "sg:tags":[
        "mexican"
    ],
    "wof:name":"Taco Bell",
    "wof:placetype":"venue"
},
  "geometry": {"coordinates":[-85.812969,41.236741],"type":"Point"}
}