{
  "type": "Feature",
  "properties": {
    "iso:country":"US",
    "sg:address":"2755 S 600 E",
    "sg:city":"Waldron",
    "sg:phone":"+1 765 525 6190",
    "sg:postcode":"46182",
    "sg:province":"IN",
    "sg:tags":[
        "farm",
        "soybean"
    ],
    "wof:name":"Doyle Hurst",
    "wof:placetype":"venue"
},
  "geometry": {"coordinates":[-85.66763899999999,39.486026],"type":"Point"}
}