{
  "type": "Feature",
  "properties": {
    "iso:country":"US",
    "sg:address":"203 Elm St",
    "sg:city":"Rockport",
    "sg:classifiers":[
        {
            "category":"Health Services",
            "subcategory":"Health Practitioner",
            "type":"Services"
        }
    ],
    "sg:phone":"+1 812 649 9534",
    "sg:postcode":"47635",
    "sg:province":"IN",
    "wof:name":"Mary E Posner PHD",
    "wof:placetype":"venue"
},
  "geometry": {"coordinates":[-87.04726,37.884307],"type":"Point"}
}