{
  "type": "Feature",
  "properties": {
    "iso:country":"US",
    "sg:address":"819 E Ridge Rd",
    "sg:city":"Griffith",
    "sg:classifiers":[
        {
            "category":"Food & Beverages",
            "subcategory":"Groceries & Convenience Stores",
            "type":"Retail Goods"
        }
    ],
    "sg:phone":"+1 219 923 2037",
    "sg:postcode":"46319",
    "sg:province":"IN",
    "wof:name":"Ridge Food Ctr",
    "wof:placetype":"venue"
},
  "geometry": {"coordinates":[-87.418604,41.55006],"type":"Point"}
}