{
  "type": "Feature",
  "properties": {
    "addr:full":"1711 Clover Rd Mishawaka IN 46545",
    "addr:housenumber":"1711",
    "addr:postcode":"46545",
    "addr:street":"Clover Rd",
    "iso:country":"US",
    "sg:address":"1711 Clover Rd",
    "sg:city":"Mishawaka",
    "sg:classifiers":[
        {
            "category":"Manufacturing",
            "subcategory":"Chemicals & Compounds",
            "type":"Manufacturing & Wholesale Goods"
        }
    ],
    "sg:phone":"+1 574 674 5884",
    "sg:postcode":"46545",
    "sg:province":"IN",
    "sg:tags":[
        "adhesive",
        "sealant"
    ],
    "wof:name":"Colorimetric Division",
    "wof:placetype":"venue"
},
  "geometry": {"coordinates":[-86.153903,41.676789],"type":"Point"}
}