{
  "type": "Feature",
  "properties": {
    "addr:full":"3409 S Western Ave Marion IN 46953",
    "addr:housenumber":"3409",
    "addr:postcode":"46953",
    "addr:street":"S Western Ave",
    "iso:country":"US",
    "sg:address":"3409 S Western Ave",
    "sg:city":"Marion",
    "sg:classifiers":[
        {
            "category":"Manufacturing",
            "subcategory":"Tools & Machinery",
            "type":"Manufacturing & Wholesale Goods"
        }
    ],
    "sg:phone":"+1 765 674 6729",
    "sg:postcode":"46953",
    "sg:province":"IN",
    "sg:tags":[
        "mold",
        "special"
    ],
    "wof:name":"Alliance Tool & Design",
    "wof:placetype":"venue"
},
  "geometry": {"coordinates":[-85.673541,40.527842],"type":"Point"}
}