{
  "type": "Feature",
  "properties": {
    "iso:country":"US",
    "sg:address":"800 E North St",
    "sg:city":"Crown Point",
    "sg:classifiers":[
        {
            "category":"Freight",
            "type":"Transportation"
        }
    ],
    "sg:phone":"+1 219 663 3936",
    "sg:postcode":"46307",
    "sg:province":"IN",
    "sg:tags":[
        "commercial",
        "storage"
    ],
    "wof:name":"Storage Unlimited",
    "wof:placetype":"venue"
},
  "geometry": {"coordinates":[-87.354014,41.420256],"type":"Point"}
}