{
  "type": "Feature",
  "properties": {
    "iso:country":"US",
    "sg:address":"9132 E Doswell Blvd",
    "sg:city":"Cromwell",
    "sg:classifiers":[
        {
            "category":"Building & Trades",
            "subcategory":"Construction",
            "type":"Services"
        }
    ],
    "sg:phone":"+1 260 856 2486",
    "sg:postcode":"46732",
    "sg:province":"IN",
    "sg:tags":[
        "designer",
        "dealer",
        "pool",
        "swimming"
    ],
    "wof:name":"Enchanted Hills Pool",
    "wof:placetype":"venue"
},
  "geometry": {"coordinates":[-85.669652,41.398823],"type":"Point"}
}