{
  "type": "Feature",
  "properties": {
    "addr:full":"555 E County Line Rd Greenwood IN 46143",
    "addr:housenumber":"555",
    "addr:postcode":"46143",
    "addr:street":"E County Line Rd",
    "iso:country":"US",
    "sg:address":"555 E County Line Rd",
    "sg:city":"Greenwood",
    "sg:classifiers":[
        {
            "category":"Building & Trades",
            "subcategory":"Construction",
            "type":"Services"
        }
    ],
    "sg:phone":"+1 317 889 3800",
    "sg:postcode":"46143",
    "sg:province":"IN",
    "sg:tags":[
        "management"
    ],
    "wof:name":"Alderson Commercial Group Inc",
    "wof:placetype":"venue"
},
  "geometry": {"coordinates":[-86.09314000000001,39.63612],"type":"Point"}
}