{
  "type": "Feature",
  "properties": {
    "iso:country":"US",
    "sg:address":"130 W Van Buren St",
    "sg:city":"Columbia City",
    "sg:classifiers":[
        {
            "category":"Utilities",
            "subcategory":"Mobile Phone",
            "type":"Services"
        }
    ],
    "sg:phone":"+1 260 244 4688",
    "sg:postcode":"46725",
    "sg:province":"IN",
    "sg:tags":[
        "telephone",
        "cellular"
    ],
    "wof:name":"Be Prepaid Home & Cellular",
    "wof:placetype":"venue"
},
  "geometry": {"coordinates":[-85.489419,41.157098],"type":"Point"}
}