{
  "type": "Feature",
  "properties": {
    "iso:country":"US",
    "sg:address":"995 N Lake St",
    "sg:city":"Warsaw",
    "sg:classifiers":[
        {
            "category":"Retail",
            "subcategory":"Auto Repair",
            "type":"Services"
        }
    ],
    "sg:phone":"+1 574 269 9250",
    "sg:postcode":"46580",
    "sg:province":"IN",
    "sg:tags":[
        "repairing",
        "automobile",
        "general"
    ],
    "wof:name":"North Lake Auto Inc",
    "wof:placetype":"venue"
},
  "geometry": {"coordinates":[-85.867357,41.247547],"type":"Point"}
}