{
  "type": "Feature",
  "properties": {
    "iso:country":"US",
    "sg:address":"2440 Indianapolis Blvd",
    "sg:city":"Whiting",
    "sg:classifiers":[
        {
            "category":"Food & Beverages",
            "subcategory":"Liquor & Beverages",
            "type":"Retail Goods"
        }
    ],
    "sg:phone":"+1 219 659 4166",
    "sg:postcode":"46394",
    "sg:province":"IN",
    "sg:tags":[
        "beer",
        "spirit",
        "wine"
    ],
    "wof:name":"Happy Jacks Liquors",
    "wof:placetype":"venue"
},
  "geometry": {"coordinates":[-87.48960099999999,41.6702],"type":"Point"}
}