{
  "type": "Feature",
  "properties": {
    "iso:country":"US",
    "sg:address":"5550 S Emerson Ave",
    "sg:city":"Indianapolis",
    "sg:classifiers":[
        {
            "category":"Retail",
            "subcategory":"Veterinary Services",
            "type":"Services"
        }
    ],
    "sg:phone":"+1 317 546 4021",
    "sg:postcode":"46237",
    "sg:province":"IN",
    "sg:tags":[
        "hospital",
        "animal"
    ],
    "wof:name":"Noah's Animal Hospital",
    "wof:placetype":"venue"
},
  "geometry": {"coordinates":[-86.082608,39.683531],"type":"Point"}
}