{
  "type": "Feature",
  "properties": {
    "iso:country":"US",
    "sg:address":"127 S East St",
    "sg:city":"Tipton",
    "sg:classifiers":[
        {
            "category":"Travel",
            "subcategory":"Hotels & Motels",
            "type":"Entertainment"
        }
    ],
    "sg:phone":"+1 765 675 7505",
    "sg:postcode":"46072",
    "sg:province":"IN",
    "wof:name":"East Street Inn",
    "wof:placetype":"venue"
},
  "geometry": {"coordinates":[-86.03774,40.281977],"type":"Point"}
}