{
  "type": "Feature",
  "properties": {
    "iso:country":"US",
    "sg:address":"251 N Illinois St",
    "sg:city":"Indianapolis",
    "sg:classifiers":[
        {
            "category":"Government",
            "subcategory":"Office",
            "type":"Public Place"
        }
    ],
    "sg:phone":"+1 317 232 9860",
    "sg:postcode":"46204",
    "sg:province":"IN",
    "wof:name":"Lobby Registration Commission",
    "wof:placetype":"venue"
},
  "geometry": {"coordinates":[-86.159692,39.770589],"type":"Point"}
}