{
  "type": "Feature",
  "properties": {
    "iso:country":"US",
    "sg:address":"1004 Cass St",
    "sg:city":"Fort Wayne",
    "sg:classifiers":[
        {
            "category":"Shopping",
            "subcategory":"Crafts & Fabrics",
            "type":"Retail Goods"
        }
    ],
    "sg:phone":"+1 260 420 2277",
    "sg:postcode":"46808",
    "sg:province":"IN",
    "sg:tags":[
        "yarn"
    ],
    "sg:website":"www.cassstreetdepot.com",
    "wof:name":"Cass Street Yarn Depot",
    "wof:placetype":"venue"
},
  "geometry": {"coordinates":[-85.145082,41.08371],"type":"Point"}
}