{
  "type": "Feature",
  "properties": {
    "iso:country":"US",
    "sg:address":"927 Wabash Ave",
    "sg:city":"Vincennes",
    "sg:classifiers":[
        {
            "category":"Building & Trades",
            "subcategory":"Plumbing",
            "type":"Services"
        }
    ],
    "sg:phone":"+1 812 882 0452",
    "sg:postcode":"47591",
    "sg:province":"IN",
    "sg:tags":[
        "conditioning",
        "air",
        "system",
        "contractor"
    ],
    "wof:name":"Frizzi's Heating & Air Cond",
    "wof:placetype":"venue"
},
  "geometry": {"coordinates":[-87.516782,38.680306],"type":"Point"}
}