{
  "type": "Feature",
  "properties": {
    "iso:country":"US",
    "sg:address":"1635 Hawthorne Dr",
    "sg:city":"Plainfield",
    "sg:classifiers":[
        {
            "category":"Health Services",
            "subcategory":"Doctor",
            "type":"Services"
        }
    ],
    "sg:phone":"+1 317 839 8191",
    "sg:postcode":"46168",
    "sg:province":"IN",
    "sg:tags":[
        "dentist"
    ],
    "wof:name":"Wines' Family Dentistry",
    "wof:placetype":"venue"
},
  "geometry": {"coordinates":[-86.37944899999999,39.711254],"type":"Point"}
}