{
  "type": "Feature",
  "properties": {
    "iso:country":"US",
    "sg:address":"3300 Bluff Rd",
    "sg:city":"Mt Vernon",
    "sg:classifiers":[
        {
            "category":"Mining & Drilling",
            "type":"Manufacturing & Wholesale Goods"
        }
    ],
    "sg:phone":"+1 812 838 5531",
    "sg:postcode":"47620",
    "sg:province":"IN",
    "sg:tags":[
        "coal",
        "shipping"
    ],
    "wof:name":"Mt Vernon Transfer Terminal",
    "wof:placetype":"venue"
},
  "geometry": {"coordinates":[-87.864781,37.922797],"type":"Point"}
}