{
  "type": "Feature",
  "properties": {
    "iso:country":"US",
    "sg:address":"475 N McCullum St",
    "sg:city":"Knightstown",
    "sg:classifiers":[
        {
            "category":"Banks & Credit Unions",
            "subcategory":"Bank",
            "type":"Services"
        }
    ],
    "sg:phone":"+1 765 345 2183",
    "sg:postcode":"46148",
    "sg:province":"IN",
    "wof:name":"Citizens State Bank",
    "wof:placetype":"venue"
},
  "geometry": {"coordinates":[-85.532144,39.801085],"type":"Point"}
}