{
  "type": "Feature",
  "properties": {
    "iso:country":"US",
    "sg:address":"295 E Lincoln Rd",
    "sg:city":"Kokomo",
    "sg:classifiers":[
        {
            "category":"Restaurant",
            "type":"Food & Drink"
        }
    ],
    "sg:phone":"+1 765 453 4773",
    "sg:postcode":"46902",
    "sg:province":"IN",
    "wof:name":"Damac Inc",
    "wof:placetype":"venue"
},
  "geometry": {"coordinates":[-86.128418,40.455173],"type":"Point"}
}