{
  "type": "Feature",
  "properties": {
    "addr:full":"749 Chase St Gary IN 46404",
    "addr:housenumber":"749",
    "addr:postcode":"46404",
    "addr:street":"Chase St Gary",
    "iso:country":"US",
    "sg:address":"749 Chase St",
    "sg:city":"Gary",
    "sg:classifiers":[
        {
            "category":"Organizations",
            "subcategory":"Religious Organization",
            "type":"Services"
        }
    ],
    "sg:phone":"+1 219 944 8285",
    "sg:postcode":"46404",
    "sg:province":"IN",
    "sg:tags":[
        "church"
    ],
    "wof:name":"St Andrew AME Zion Church",
    "wof:placetype":"venue"
},
  "geometry": {"coordinates":[-87.375612,41.596015],"type":"Point"}
}