{
  "type": "Feature",
  "properties": {
    "iso:country":"US",
    "sg:address":"9961 Allisonville Rd",
    "sg:city":"Fishers",
    "sg:classifiers":[
        {
            "category":"Professional",
            "subcategory":"Management & Consulting",
            "type":"Services"
        }
    ],
    "sg:phone":"+1 317 684 3550",
    "sg:postcode":"46038",
    "sg:province":"IN",
    "sg:tags":[
        "consultant",
        "business"
    ],
    "wof:name":"Planning Plus",
    "wof:placetype":"venue"
},
  "geometry": {"coordinates":[-86.05993599999999,39.931616],"type":"Point"}
}