{
  "type": "Feature",
  "properties": {
    "iso:country":"US",
    "sg:address":"415 N Main St",
    "sg:city":"Hebron",
    "sg:classifiers":[
        {
            "category":"Retail",
            "subcategory":"Auto Rental",
            "type":"Services"
        }
    ],
    "sg:phone":"+1 219 393 1882",
    "sg:postcode":"46341",
    "sg:province":"IN",
    "sg:tags":[
        "renting",
        "truck",
        "leasing"
    ],
    "wof:name":"U-Haul Co",
    "wof:placetype":"venue"
},
  "geometry": {"coordinates":[-87.200048,41.324617],"type":"Point"}
}