{
  "type": "Feature",
  "properties": {
    "iso:country":"US",
    "sg:address":"7868 Allison Ave",
    "sg:city":"Indianapolis",
    "sg:classifiers":[
        {
            "category":"Professional",
            "subcategory":"Management & Consulting",
            "type":"Services"
        }
    ],
    "sg:phone":"+1 317 824 0939",
    "sg:postcode":"46268",
    "sg:province":"IN",
    "sg:tags":[
        "logistics"
    ],
    "wof:name":"Controlled Logisitics",
    "wof:placetype":"venue"
},
  "geometry": {"coordinates":[-86.25013800000001,39.894791],"type":"Point"}
}