{
  "type": "Feature",
  "properties": {
    "iso:country":"US",
    "sg:address":"9007 Indianapolis Blvd",
    "sg:city":"Highland",
    "sg:classifiers":[
        {
            "category":"Health Services",
            "subcategory":"Podiatrist",
            "type":"Services"
        }
    ],
    "sg:phone":"+1 219 923 1254",
    "sg:postcode":"46322",
    "sg:province":"IN",
    "wof:name":"Accredited Foot Surgeons",
    "wof:placetype":"venue"
},
  "geometry": {"coordinates":[-87.471298,41.549],"type":"Point"}
}