{
  "type": "Feature",
  "properties": {
    "iso:country":"US",
    "sg:address":"1520 Broadway",
    "sg:city":"Gary",
    "sg:classifiers":[
        {
            "category":"Shopping",
            "subcategory":"Used Merchandise",
            "type":"Retail Goods"
        }
    ],
    "sg:phone":"+1 219 882 6462",
    "sg:postcode":"46407",
    "sg:province":"IN",
    "sg:tags":[
        "clothing"
    ],
    "wof:name":"Mr Dave",
    "wof:placetype":"venue"
},
  "geometry": {"coordinates":[-87.337101,41.587146],"type":"Point"}
}