{
  "type": "Feature",
  "properties": {
    "iso:country":"US",
    "sg:address":"1314 E 7th St",
    "sg:city":"Auburn",
    "sg:classifiers":[
        {
            "category":"Health Services",
            "subcategory":"Doctor",
            "type":"Services"
        }
    ],
    "sg:phone":"+1 260 927 9514",
    "sg:postcode":"46706",
    "sg:province":"IN",
    "sg:tags":[
        "physician",
        "surgeon"
    ],
    "wof:name":"Shawn E Kidder DO",
    "wof:placetype":"venue"
},
  "geometry": {"coordinates":[-85.03060000000001,41.367852],"type":"Point"}
}