{
  "type": "Feature",
  "properties": {
    "iso:country":"US",
    "sg:address":"6045 W Pendleton Pike",
    "sg:city":"Mc Cordsville",
    "sg:classifiers":[
        {
            "category":"Professional",
            "type":"Services"
        }
    ],
    "sg:phone":"+1 317 335 3263",
    "sg:postcode":"46055",
    "sg:province":"IN",
    "sg:tags":[
        "establishment"
    ],
    "wof:name":"C/Dcap Modem Line",
    "wof:placetype":"venue"
},
  "geometry": {"coordinates":[-85.918393,39.896267],"type":"Point"}
}