{
  "type": "Feature",
  "properties": {
    "iso:country":"US",
    "sg:address":"319 E Main St",
    "sg:city":"Washington",
    "sg:classifiers":[
        {
            "category":"Organizations",
            "subcategory":"Community Association",
            "type":"Services"
        }
    ],
    "sg:phone":"+1 812 254 1275",
    "sg:postcode":"47501",
    "sg:province":"IN",
    "sg:tags":[
        "fraternal"
    ],
    "wof:name":"Knights Of Columbus",
    "wof:placetype":"venue"
},
  "geometry": {"coordinates":[-87.172161,38.656867],"type":"Point"}
}