{
  "type": "Feature",
  "properties": {
    "iso:country":"US",
    "sg:address":"123 W Main St",
    "sg:city":"Vevay",
    "sg:classifiers":[
        {
            "category":"Bars & Pubs",
            "type":"Food & Drink"
        }
    ],
    "sg:phone":"+1 812 427 9131",
    "sg:postcode":"47043",
    "sg:province":"IN",
    "wof:name":"Cuzz's Bar",
    "wof:placetype":"venue"
},
  "geometry": {"coordinates":[-85.067272,38.747462],"type":"Point"}
}