{
  "type": "Feature",
  "properties": {
    "addr:full":"2121 W Washington St Indianapolis IN 46222",
    "addr:housenumber":"2121",
    "addr:postcode":"46222",
    "addr:street":"W Washington St",
    "iso:country":"US",
    "sg:address":"2121 W Washington St",
    "sg:city":"Indianapolis",
    "sg:classifiers":[
        {
            "category":"Retail",
            "subcategory":"Portrait Studio",
            "type":"Services"
        }
    ],
    "sg:phone":"+1 317 917 1151",
    "sg:postcode":"46222",
    "sg:province":"IN",
    "sg:tags":[
        "photo",
        "photographers-portrait"
    ],
    "wof:name":"Photo Studio Fantasia",
    "wof:placetype":"venue"
},
  "geometry": {"coordinates":[-86.197616,39.766173],"type":"Point"}
}