{
  "type": "Feature",
  "properties": {
    "iso:country":"US",
    "sg:address":"1201 N Lincoln St",
    "sg:city":"Greensburg",
    "sg:classifiers":[
        {
            "category":"Retail",
            "subcategory":"Self-service Laundry",
            "type":"Services"
        }
    ],
    "sg:phone":"+1 812 663 4175",
    "sg:postcode":"47240",
    "sg:province":"IN",
    "wof:name":"G's Carwash & Laundromat Plus",
    "wof:placetype":"venue"
},
  "geometry": {"coordinates":[-85.479231,39.348874],"type":"Point"}
}