{
  "type": "Feature",
  "properties": {
    "iso:country":"US",
    "sg:address":"3117 Roselawn Dr",
    "sg:city":"Evansville",
    "sg:classifiers":[
        {
            "category":"Professional",
            "subcategory":"Management & Consulting",
            "type":"Services"
        }
    ],
    "sg:phone":"+1 812 985 3387",
    "sg:postcode":"47711",
    "sg:province":"IN",
    "sg:tags":[
        "consultant",
        "business"
    ],
    "wof:name":"J M Management Inc",
    "wof:placetype":"venue"
},
  "geometry": {"coordinates":[-87.508369,38.006404],"type":"Point"}
}