{
  "type": "Feature",
  "properties": {
    "iso:country":"US",
    "sg:address":"4767 Cleveland St",
    "sg:city":"Gary",
    "sg:classifiers":[
        {
            "category":"Personal",
            "subcategory":"Beauty Salon",
            "type":"Services"
        }
    ],
    "sg:phone":"+1 219 985 2366",
    "sg:postcode":"46408",
    "sg:province":"IN",
    "wof:name":"Advanced Cosmetologists",
    "wof:placetype":"venue"
},
  "geometry": {"coordinates":[-87.360375,41.532704],"type":"Point"}
}