{
  "type": "Feature",
  "properties": {
    "iso:country":"US",
    "sg:address":"3766 N Sherman Dr",
    "sg:city":"Indianapolis",
    "sg:classifiers":[
        {
            "category":"Utilities",
            "subcategory":"Mobile Phone",
            "type":"Services"
        }
    ],
    "sg:phone":"+1 317 377 0788",
    "sg:postcode":"46218",
    "sg:province":"IN",
    "sg:tags":[
        "telephone",
        "cellular"
    ],
    "wof:name":"Pagers Plus",
    "wof:placetype":"venue"
},
  "geometry": {"coordinates":[-86.102782,39.824008],"type":"Point"}
}