{
  "type": "Feature",
  "properties": {
    "iso:country":"US",
    "sg:address":"124 Innisbrooke Ave",
    "sg:city":"Greenwood",
    "sg:classifiers":[
        {
            "category":"Wholesale",
            "subcategory":"Durable Goods & Equipment",
            "type":"Manufacturing & Wholesale Goods"
        },
        {
            "category":"Manufacturing",
            "subcategory":"Building Materials",
            "type":"Manufacturing & Wholesale Goods"
        }
    ],
    "sg:phone":"+1 317 888 4785",
    "sg:postcode":"46142",
    "sg:province":"IN",
    "sg:tags":[
        "filtering",
        "filters-liquid-wholesale",
        "supply"
    ],
    "wof:name":"Gp Services",
    "wof:placetype":"venue"
},
  "geometry": {"coordinates":[-86.201639,39.615754],"type":"Point"}
}