{
  "type": "Feature",
  "properties": {
    "addr:full":"1900 N 3rd St Terre Haute IN 47804",
    "addr:housenumber":"1900",
    "addr:postcode":"47804",
    "addr:street":"N 3Rd St",
    "iso:country":"US",
    "sg:address":"1900 N 3rd St",
    "sg:city":"Terre Haute",
    "sg:classifiers":[
        {
            "category":"Home & Garden",
            "subcategory":"Household Appliances",
            "type":"Retail Goods"
        }
    ],
    "sg:phone":"+1 812 232 5566",
    "sg:postcode":"47804",
    "sg:province":"IN",
    "sg:tags":[
        "cleaners",
        "vacuum"
    ],
    "wof:name":"Terre Haute Vacuum Ctr",
    "wof:placetype":"venue"
},
  "geometry": {"coordinates":[-87.41399699999999,39.489551],"type":"Point"}
}