{
  "type": "Feature",
  "properties": {
    "addr:full":"300 W 900 S Warren IN 46792",
    "addr:housenumber":"300",
    "addr:postcode":"46792",
    "addr:street":"W 900 S Warren",
    "iso:country":"US",
    "sg:address":"300 W 900 S",
    "sg:city":"Warren",
    "sg:classifiers":[
        {
            "category":"Organizations",
            "subcategory":"Religious Organization",
            "type":"Services"
        }
    ],
    "sg:phone":"+1 260 375 2997",
    "sg:postcode":"46792",
    "sg:province":"IN",
    "sg:tags":[
        "church"
    ],
    "wof:name":"United Methodist Church",
    "wof:placetype":"venue"
},
  "geometry": {"coordinates":[-85.454657,40.69768],"type":"Point"}
}