{
  "type": "Feature",
  "properties": {
    "iso:country":"US",
    "sg:address":"6302 Rucker Rd",
    "sg:city":"Indianapolis",
    "sg:classifiers":[
        {
            "category":"Health Services",
            "subcategory":"Nursing And Care Facility",
            "type":"Services"
        },
        {
            "category":"Health Services",
            "subcategory":"Health Practitioner",
            "type":"Services"
        }
    ],
    "sg:phone":"+1 317 282 0945",
    "sg:postcode":"46220",
    "sg:province":"IN",
    "sg:tags":[
        "home",
        "nurse"
    ],
    "sg:website":"http://www.acmehhc.com",
    "wof:name":"Acme Health Services Inc",
    "wof:placetype":"venue"
},
  "geometry": {"coordinates":[-86.07933,39.871044],"type":"Point"}
}