{
  "type": "Feature",
  "properties": {
    "iso:country":"US",
    "sg:address":"103 Industrial Park Dr",
    "sg:city":"Walkerton",
    "sg:classifiers":[
        {
            "category":"Manufacturing",
            "subcategory":"Rubber & Plastics",
            "type":"Manufacturing & Wholesale Goods"
        }
    ],
    "sg:phone":"+1 574 586 3145",
    "sg:postcode":"46574",
    "sg:province":"IN",
    "sg:tags":[
        "product"
    ],
    "sg:website":"www.polygoncompany.com",
    "wof:name":"Polygon Co",
    "wof:placetype":"venue"
},
  "geometry": {"coordinates":[-86.495055,41.469237],"type":"Point"}
}