{
  "type": "Feature",
  "properties": {
    "iso:country":"US",
    "sg:address":"5945 Crawfordsville Rd",
    "sg:city":"Speedway",
    "sg:classifiers":[
        {
            "category":"Personal",
            "subcategory":"Beauty Salon",
            "type":"Services"
        }
    ],
    "sg:phone":"+1 317 244 8519",
    "sg:postcode":"46224",
    "sg:province":"IN",
    "wof:name":"Shear Images",
    "wof:placetype":"venue"
},
  "geometry": {"coordinates":[-86.263019,39.796913],"type":"Point"}
}