{
  "type": "Feature",
  "properties": {
    "addr:full":"1265 N Madison Ave Greenwood IN 46142",
    "addr:housenumber":"1265",
    "addr:postcode":"46142",
    "addr:street":"N Madison Ave",
    "iso:country":"US",
    "sg:address":"1265 N Madison Ave",
    "sg:city":"Greenwood",
    "sg:classifiers":[
        {
            "category":"Shopping",
            "subcategory":"Clothing, Apparel, & Fashions",
            "type":"Retail Goods"
        }
    ],
    "sg:phone":"+1 317 885 8616",
    "sg:postcode":"46142",
    "sg:province":"IN",
    "sg:tags":[
        "uniform"
    ],
    "wof:name":"Uniforms Unique",
    "wof:placetype":"venue"
},
  "geometry": {"coordinates":[-86.11574299999999,39.631924],"type":"Point"}
}