{
  "type": "Feature",
  "properties": {
    "iso:country":"US",
    "sg:address":"124 S Clark Blvd",
    "sg:city":"Clarksville",
    "sg:classifiers":[
        {
            "category":"Retail",
            "subcategory":"Portrait Studio",
            "type":"Services"
        }
    ],
    "sg:phone":"+1 812 944 1549",
    "sg:postcode":"47129",
    "sg:province":"IN",
    "sg:tags":[
        "photographer"
    ],
    "wof:name":"Adams Photography",
    "wof:placetype":"venue"
},
  "geometry": {"coordinates":[-85.762531,38.286114],"type":"Point"}
}