{
  "type": "Feature",
  "properties": {
    "iso:country":"US",
    "sg:address":"3415 Holton Ave",
    "sg:city":"Fort Wayne",
    "sg:classifiers":[
        {
            "category":"Building & Trades",
            "subcategory":"Construction",
            "type":"Services"
        }
    ],
    "sg:phone":"+1 260 458 9403",
    "sg:postcode":"46806",
    "sg:province":"IN",
    "sg:tags":[
        "resurfacing",
        "laying",
        "refinishing",
        "floor"
    ],
    "wof:name":"A 1 Flooring",
    "wof:placetype":"venue"
},
  "geometry": {"coordinates":[-85.118308,41.054368],"type":"Point"}
}