{
  "type": "Feature",
  "properties": {
    "addr:full":"3202 S East St Indianapolis IN 46227",
    "addr:housenumber":"3202",
    "addr:postcode":"46227",
    "addr:street":"S East St",
    "iso:country":"US",
    "sg:address":"3202 S East St",
    "sg:city":"Indianapolis",
    "sg:classifiers":[
        {
            "category":"Autos & Motor Vehicles",
            "subcategory":"Automobile Sales",
            "type":"Retail Goods"
        }
    ],
    "sg:phone":"+1 317 780 0750",
    "sg:postcode":"46227",
    "sg:province":"IN",
    "sg:tags":[
        "car",
        "dealer"
    ],
    "wof:name":"Quick Auto Inc",
    "wof:placetype":"venue"
},
  "geometry": {"coordinates":[-86.14909900000001,39.718558],"type":"Point"}
}