{
  "type": "Feature",
  "properties": {
    "iso:country":"US",
    "sg:address":"8112 Oakwood Ave",
    "sg:city":"Munster",
    "sg:classifiers":[
        {
            "category":"Wholesale",
            "subcategory":"Medical Equipment & Supplies",
            "type":"Manufacturing & Wholesale Goods"
        }
    ],
    "sg:phone":"+1 219 923 4629",
    "sg:postcode":"46321",
    "sg:province":"IN",
    "wof:name":"Spencer Dd Inc",
    "wof:placetype":"venue"
},
  "geometry": {"coordinates":[-87.48751,41.563171],"type":"Point"}
}