{
  "type": "Feature",
  "properties": {
    "addr:full":"7530 US Hwy 31 S Indianapolis IN 46227",
    "addr:housenumber":"7530",
    "addr:postcode":"46227",
    "addr:street":"Us Hwy 31 S",
    "iso:country":"US",
    "sg:address":"7530 US Hwy 31 S",
    "sg:city":"Indianapolis",
    "sg:classifiers":[
        {
            "category":"Professional",
            "subcategory":"Computer Services",
            "type":"Services"
        }
    ],
    "sg:phone":"+1 317 787 6025",
    "sg:postcode":"46227",
    "sg:province":"IN",
    "sg:tags":[
        "internet"
    ],
    "wof:name":"Cleary Computer Co Inc",
    "wof:placetype":"venue"
},
  "geometry": {"coordinates":[-86.142822,39.658098],"type":"Point"}
}