{
  "type": "Feature",
  "properties": {
    "iso:country":"US",
    "sg:address":"1610 N Calhoun St",
    "sg:city":"Fort Wayne",
    "sg:classifiers":[
        {
            "category":"Wholesale",
            "subcategory":"Scrap",
            "type":"Manufacturing & Wholesale Goods"
        }
    ],
    "sg:phone":"+1 260 422 5541",
    "sg:postcode":"46808",
    "sg:province":"IN",
    "sg:tags":[
        "recycling",
        "center"
    ],
    "sg:website":"www.omnisource.com",
    "wof:name":"Omni Source Corp",
    "wof:placetype":"venue"
},
  "geometry": {"coordinates":[-85.142225,41.089547],"type":"Point"}
}