{
  "type": "Feature",
  "properties": {
    "iso:country":"US",
    "sg:address":"1610 Industrial Dr",
    "sg:city":"Greenwood",
    "sg:classifiers":[
        {
            "category":"Manufacturing",
            "subcategory":"Printing",
            "type":"Manufacturing & Wholesale Goods"
        }
    ],
    "sg:phone":"+1 317 865 0007",
    "sg:postcode":"46143",
    "sg:province":"IN",
    "sg:tags":[
        "commercial"
    ],
    "wof:name":"Heron Printing Co",
    "wof:placetype":"venue"
},
  "geometry": {"coordinates":[-86.100837,39.593145],"type":"Point"}
}