{
  "type": "Feature",
  "properties": {
    "iso:country":"US",
    "sg:address":"1423 Aetna St",
    "sg:city":"Gary",
    "sg:classifiers":[
        {
            "category":"Bars & Pubs",
            "type":"Food & Drink"
        }
    ],
    "sg:phone":"+1 219 938 2442",
    "sg:postcode":"46403",
    "sg:province":"IN",
    "sg:tags":[
        "drinking"
    ],
    "wof:name":"Franks Night Out",
    "wof:placetype":"venue"
},
  "geometry": {"coordinates":[-87.287684,41.589017],"type":"Point"}
}