{
  "type": "Feature",
  "properties": {
    "iso:country":"US",
    "sg:address":"935 S Clark Blvd",
    "sg:city":"Clarksville",
    "sg:classifiers":[
        {
            "category":"Restaurant",
            "type":"Food & Drink"
        }
    ],
    "sg:phone":"+1 812 288 7675",
    "sg:postcode":"47129",
    "sg:province":"IN",
    "sg:tags":[
        "eating"
    ],
    "wof:name":"Arbys",
    "wof:placetype":"venue"
},
  "geometry": {"coordinates":[-85.75805,38.278494],"type":"Point"}
}