{
  "type": "Feature",
  "properties": {
    "iso:country":"US",
    "sg:address":"1282 N Sandhill Rd",
    "sg:city":"Covington",
    "sg:classifiers":[
        {
            "category":"Real Estate",
            "subcategory":"Real Estate Operator",
            "type":"Services"
        }
    ],
    "sg:phone":"+1 765 793 4901",
    "sg:postcode":"47932",
    "sg:province":"IN",
    "sg:tags":[
        "property",
        "lessor"
    ],
    "wof:name":"David Shelby",
    "wof:placetype":"venue"
},
  "geometry": {"coordinates":[-87.424081,40.164176],"type":"Point"}
}