{
  "type": "Feature",
  "properties": {
    "iso:country":"US",
    "sg:address":"2620 E Wallen Rd",
    "sg:city":"Fort Wayne",
    "sg:classifiers":[
        {
            "category":"Professional",
            "type":"Services"
        }
    ],
    "sg:phone":"+1 260 425 3880",
    "sg:postcode":"46825",
    "sg:province":"IN",
    "sg:tags":[
        "establishment"
    ],
    "wof:name":"Wallen Place",
    "wof:placetype":"venue"
},
  "geometry": {"coordinates":[-85.109155,41.164247],"type":"Point"}
}