{
  "type": "Feature",
  "properties": {
    "iso:country":"US",
    "sg:address":"1348 Pauls Dr",
    "sg:city":"Greenfield",
    "sg:classifiers":[
        {
            "category":"Banks & Credit Unions",
            "subcategory":"Financial Services",
            "type":"Services"
        }
    ],
    "sg:phone":"+1 317 462 2856",
    "sg:postcode":"46140",
    "sg:province":"IN",
    "sg:tags":[
        "management",
        "open",
        "investment"
    ],
    "wof:name":"Linda Zimmermann Financial",
    "wof:placetype":"venue"
},
  "geometry": {"coordinates":[-85.761242,39.806501],"type":"Point"}
}