{
  "type": "Feature",
  "properties": {
    "addr:full":"2700 S Belmont Ave Indianapolis IN 46221",
    "addr:housenumber":"2700",
    "addr:postcode":"46221",
    "addr:street":"S Belmont Ave",
    "iso:country":"US",
    "sg:address":"2700 S Belmont Ave",
    "sg:city":"Indianapolis",
    "sg:classifiers":[
        {
            "category":"Government",
            "subcategory":"Office",
            "type":"Public Place"
        }
    ],
    "sg:phone":"+1 317 639 7000",
    "sg:postcode":"46221",
    "sg:province":"IN",
    "sg:tags":[
        "village"
    ],
    "sg:website":"www.unitedwater.com",
    "wof:name":"Indianapolis Wastewater Trtmnt",
    "wof:placetype":"venue"
},
  "geometry": {"coordinates":[-86.193201,39.734302],"type":"Point"}
}