{
  "type": "Feature",
  "properties": {
    "addr:full":"2004 S Memorial Dr New Castle IN 47362",
    "addr:housenumber":"2004",
    "addr:postcode":"47362",
    "addr:street":"S Memorial Dr",
    "iso:country":"US",
    "sg:address":"2004 S Memorial Dr",
    "sg:city":"New Castle",
    "sg:classifiers":[
        {
            "category":"Real Estate",
            "subcategory":"Real Estate Services",
            "type":"Services"
        }
    ],
    "sg:phone":"+1 765 593 0142",
    "sg:postcode":"47362",
    "sg:province":"IN",
    "wof:name":"Real Property Research",
    "wof:placetype":"venue"
},
  "geometry": {"coordinates":[-85.384874,39.912851],"type":"Point"}
}