{
  "type": "Feature",
  "properties": {
    "addr:full":"1115 Broad Ripple Ave Indianapolis IN 46220",
    "addr:housenumber":"1115",
    "addr:postcode":"46220",
    "addr:street":"Broad Ripple Ave",
    "iso:country":"US",
    "sg:address":"1115 Broad Ripple Ave",
    "sg:city":"Indianapolis",
    "sg:classifiers":[
        {
            "category":"Education",
            "subcategory":"School",
            "type":"Public Place"
        }
    ],
    "sg:phone":"+1 317 693 5757",
    "sg:postcode":"46220",
    "sg:province":"IN",
    "sg:tags":[
        "high",
        "k-",
        "private"
    ],
    "sg:website":"http://www.ips.k12.in.us",
    "wof:name":"Ips Broad Ripple High School",
    "wof:placetype":"venue"
},
  "geometry": {"coordinates":[-86.138715,39.86966],"type":"Point"}
}