{
  "type": "Feature",
  "properties": {
    "iso:country":"US",
    "sg:address":"3187 N US Hwy 41",
    "sg:city":"Sullivan",
    "sg:classifiers":[
        {
            "category":"Autos & Motor Vehicles",
            "subcategory":"Automobile Sales",
            "type":"Retail Goods"
        }
    ],
    "sg:phone":"+1 812 268 0346",
    "sg:postcode":"47882",
    "sg:province":"IN",
    "sg:tags":[
        "sport",
        "trailer",
        "utility"
    ],
    "wof:name":"Harmon Trailer Sales",
    "wof:placetype":"venue"
},
  "geometry": {"coordinates":[-87.409734,39.132967],"type":"Point"}
}