{
  "type": "Feature",
  "properties": {
    "iso:country":"US",
    "sg:address":"7613 Eider Ave",
    "sg:city":"Hobart",
    "sg:classifiers":[
        {
            "category":"Freight",
            "type":"Transportation"
        }
    ],
    "sg:phone":"+1 219 947 8203",
    "sg:postcode":"46342",
    "sg:province":"IN",
    "sg:tags":[
        "consultant"
    ],
    "wof:name":"Maximum Logistics",
    "wof:placetype":"venue"
},
  "geometry": {"coordinates":[-87.242676,41.505431],"type":"Point"}
}