{
  "type": "Feature",
  "properties": {
    "iso:country":"US",
    "sg:address":"127 W 2nd St",
    "sg:city":"Seymour",
    "sg:classifiers":[
        {
            "category":"Manufacturing",
            "subcategory":"Printing",
            "type":"Manufacturing & Wholesale Goods"
        }
    ],
    "sg:phone":"+1 812 524 7701",
    "sg:postcode":"47274",
    "sg:province":"IN",
    "sg:tags":[
        "printer"
    ],
    "wof:name":"Artistic Impressions",
    "wof:placetype":"venue"
},
  "geometry": {"coordinates":[-85.889428,38.959261],"type":"Point"}
}