{
  "type": "Feature",
  "properties": {
    "addr:full":"3303 Peppermill Dr West Lafayette IN 47906",
    "addr:housenumber":"3303",
    "addr:postcode":"47906",
    "addr:street":"Peppermill Dr",
    "iso:country":"US",
    "sg:address":"3303 Peppermill Dr",
    "sg:city":"West Lafayette",
    "sg:classifiers":[
        {
            "category":"Real Estate",
            "subcategory":"Real Estate Operator",
            "type":"Services"
        }
    ],
    "sg:phone":"+1 765 463 2576",
    "sg:postcode":"47906",
    "sg:province":"IN",
    "sg:tags":[
        "apartment"
    ],
    "wof:name":"Peppermill Village-Oxford",
    "wof:placetype":"venue"
},
  "geometry": {"coordinates":[-86.92542299999999,40.46194],"type":"Point"}
}