{
  "type": "Feature",
  "properties": {
    "iso:country":"US",
    "sg:address":"3801 National Rd E",
    "sg:city":"Richmond",
    "sg:classifiers":[
        {
            "category":"Shopping",
            "subcategory":"Clothing, Apparel, & Fashions",
            "type":"Retail Goods"
        }
    ],
    "sg:phone":"+1 765 962 2738",
    "sg:postcode":"47374",
    "sg:province":"IN",
    "sg:tags":[
        "sportswear"
    ],
    "sg:website":"www.finishline.com",
    "wof:name":"Finish Line",
    "wof:placetype":"venue"
},
  "geometry": {"coordinates":[-84.845767,39.831024],"type":"Point"}
}