{
  "type": "Feature",
  "properties": {
    "iso:country":"US",
    "sg:address":"504 Nowlin Ave",
    "sg:city":"Greendale",
    "sg:classifiers":[
        {
            "category":"Personal",
            "subcategory":"Beauty Salon",
            "type":"Services"
        }
    ],
    "sg:phone":"+1 812 537 9585",
    "sg:postcode":"47025",
    "sg:province":"IN",
    "wof:name":"Wendy's Hair & Nailz",
    "wof:placetype":"venue"
},
  "geometry": {"coordinates":[-84.86730900000001,39.11006],"type":"Point"}
}