{
  "type": "Feature",
  "properties": {
    "iso:country":"US",
    "sg:address":"715 E Ireland Rd",
    "sg:city":"South Bend",
    "sg:classifiers":[
        {
            "category":"Home & Garden",
            "subcategory":"Building Materials",
            "type":"Retail Goods"
        }
    ],
    "sg:phone":"+1 574 291 7100",
    "sg:postcode":"46614",
    "sg:province":"IN",
    "sg:tags":[
        "mixed",
        "concrete"
    ],
    "sg:website":"www.transitmixinc.com",
    "wof:name":"Transit Mix Inc",
    "wof:placetype":"venue"
},
  "geometry": {"coordinates":[-86.242011,41.629259],"type":"Point"}
}