{
  "type": "Feature",
  "properties": {
    "iso:country":"US",
    "sg:address":"225 S Perry St",
    "sg:city":"Attica",
    "sg:classifiers":[
        {
            "category":"Autos & Motor Vehicles",
            "subcategory":"Auto Supplies",
            "type":"Retail Goods"
        }
    ],
    "sg:phone":"+1 765 762 2429",
    "sg:postcode":"47918",
    "sg:province":"IN",
    "sg:tags":[
        "automobile",
        "parts"
    ],
    "wof:name":"NAPA Auto Parts",
    "wof:placetype":"venue"
},
  "geometry": {"coordinates":[-87.24913599999999,40.293481],"type":"Point"}
}