{
  "type": "Feature",
  "properties": {
    "iso:country":"US",
    "sg:address":"482 W 580 N",
    "sg:city":"Crawfordsville",
    "sg:classifiers":[
        {
            "category":"Education",
            "subcategory":"School",
            "type":"Public Place"
        }
    ],
    "sg:phone":"+1 765 364 1071",
    "sg:postcode":"47933",
    "sg:province":"IN",
    "sg:website":"www.nm.k12.in.us",
    "wof:name":"Northridge Middle School",
    "wof:placetype":"venue"
},
  "geometry": {"coordinates":[-86.91211699999999,40.12308],"type":"Point"}
}