{
  "type": "Feature",
  "properties": {
    "iso:country":"US",
    "sg:address":"100 W York St",
    "sg:city":"Rockville",
    "sg:classifiers":[
        {
            "category":"Recreation",
            "type":"Entertainment"
        }
    ],
    "sg:phone":"+1 765 569 5099",
    "sg:postcode":"47872",
    "sg:province":"IN",
    "sg:tags":[
        "attraction",
        "tourist"
    ],
    "wof:name":"Terre Vin Winery",
    "wof:placetype":"venue"
},
  "geometry": {"coordinates":[-87.229132,39.763562],"type":"Point"}
}