{
  "type": "Feature",
  "properties": {
    "iso:country":"US",
    "sg:address":"1911 Clover Rd",
    "sg:city":"Mishawaka",
    "sg:classifiers":[
        {
            "category":"Professional",
            "subcategory":"Computer Services",
            "type":"Services"
        }
    ],
    "sg:phone":"+1 574 257 9215",
    "sg:postcode":"46545",
    "sg:province":"IN",
    "wof:name":"Cso",
    "wof:placetype":"venue"
},
  "geometry": {"coordinates":[-86.153887,41.675524],"type":"Point"}
}