{
  "type": "Feature",
  "properties": {
    "iso:country":"US",
    "sg:address":"1079 N Luther Rd",
    "sg:city":"Georgetown",
    "sg:classifiers":[
        {
            "category":"Travel",
            "subcategory":"Hotels & Motels",
            "type":"Entertainment"
        }
    ],
    "sg:phone":"+1 812 923 0441",
    "sg:postcode":"47122",
    "sg:province":"IN",
    "wof:name":"Motel 6",
    "wof:placetype":"venue"
},
  "geometry": {"coordinates":[-85.91407599999999,38.290879],"type":"Point"}
}