{
  "type": "Feature",
  "properties": {
    "iso:country":"US",
    "sg:address":"554 State Rd 42",
    "sg:city":"Mooresville",
    "sg:classifiers":[
        {
            "category":"Professional",
            "subcategory":"Business Services",
            "type":"Services"
        }
    ],
    "sg:phone":"+1 317 996 2402",
    "sg:postcode":"46158",
    "sg:province":"IN",
    "sg:tags":[
        "auctioneer"
    ],
    "wof:name":"Midway Auction Co",
    "wof:placetype":"venue"
},
  "geometry": {"coordinates":[-86.41692399999999,39.593135],"type":"Point"}
}