{
  "type": "Feature",
  "properties": {
    "iso:country":"US",
    "sg:address":"50 W 64th St",
    "sg:city":"Indianapolis",
    "sg:classifiers":[
        {
            "category":"Health Services",
            "subcategory":"Doctor",
            "type":"Services"
        }
    ],
    "sg:phone":"+1 317 253 1400",
    "sg:postcode":"46260",
    "sg:province":"IN",
    "sg:tags":[
        "medical"
    ],
    "wof:name":"Rodney Mail MD",
    "wof:placetype":"venue"
},
  "geometry": {"coordinates":[-86.158561,39.873611],"type":"Point"}
}