{
  "type": "Feature",
  "properties": {
    "addr:full":"5655 Harrison St Merrillville IN 46410",
    "addr:housenumber":"5655",
    "addr:postcode":"46410",
    "addr:street":"Harrison St",
    "iso:country":"US",
    "sg:address":"5655 Harrison St",
    "sg:city":"Merrillville",
    "sg:classifiers":[
        {
            "category":"Health Services",
            "subcategory":"Doctor",
            "type":"Services"
        }
    ],
    "sg:phone":"+1 219 980 4900",
    "sg:postcode":"46410",
    "sg:province":"IN",
    "sg:tags":[
        "dentist"
    ],
    "wof:name":"United Dental Ctr",
    "wof:placetype":"venue"
},
  "geometry": {"coordinates":[-87.34566700000001,41.515864],"type":"Point"}
}