{
  "type": "Feature",
  "properties": {
    "iso:country":"US",
    "sg:address":"702 Lincolnway W",
    "sg:city":"South Bend",
    "sg:classifiers":[
        {
            "category":"Organizations",
            "subcategory":"Non-profit Organization",
            "type":"Services"
        }
    ],
    "sg:phone":"+1 574 287 4700",
    "sg:postcode":"46616",
    "sg:province":"IN",
    "sg:website":"www.wubs.org",
    "wof:name":"ICU Ministries",
    "wof:placetype":"venue"
},
  "geometry": {"coordinates":[-86.25986899999999,41.681037],"type":"Point"}
}