{
  "type": "Feature",
  "properties": {
    "addr:full":"451 S Park Ridge Rd Bloomington IN 47401",
    "addr:housenumber":"451",
    "addr:postcode":"47401",
    "addr:street":"S Park Ridge Rd",
    "iso:country":"US",
    "sg:address":"451 S Park Ridge Rd",
    "sg:city":"Bloomington",
    "sg:classifiers":[
        {
            "category":"Health Services",
            "subcategory":"Doctor",
            "type":"Services"
        }
    ],
    "sg:phone":"+1 812 331 1601",
    "sg:postcode":"47401",
    "sg:province":"IN",
    "sg:tags":[
        "psychiatrist"
    ],
    "wof:name":"Lybrook Polly MD",
    "wof:placetype":"venue"
},
  "geometry": {"coordinates":[-86.47608700000001,39.163267],"type":"Point"}
}