{
  "type": "Feature",
  "properties": {
    "iso:country":"US",
    "sg:address":"1204 Darlington Ave",
    "sg:city":"Crawfordsville",
    "sg:classifiers":[
        {
            "category":"Manufacturing",
            "subcategory":"Motor Vehicles & Parts",
            "type":"Manufacturing & Wholesale Goods"
        }
    ],
    "sg:phone":"+1 765 362 3500",
    "sg:postcode":"47933",
    "sg:province":"IN",
    "sg:tags":[
        "automobile",
        "supply"
    ],
    "sg:website":"www.raybestos.com",
    "wof:name":"Raybestos Products Co",
    "wof:placetype":"venue"
},
  "geometry": {"coordinates":[-86.885495,40.04463],"type":"Point"}
}