{
  "type": "Feature",
  "properties": {
    "iso:country":"US",
    "sg:address":"4740 Kingsway Dr",
    "sg:city":"Indianapolis",
    "sg:classifiers":[
        {
            "category":"Organizations",
            "subcategory":"Membership Organization",
            "type":"Services"
        }
    ],
    "sg:phone":"+1 317 466 2019",
    "sg:postcode":"46205",
    "sg:province":"IN",
    "wof:name":"Parkinson Outreach Program",
    "wof:placetype":"venue"
},
  "geometry": {"coordinates":[-86.119545,39.84664],"type":"Point"}
}