{
  "type": "Feature",
  "properties": {
    "addr:full":"1218 Sheffield Ave Dyer IN 46311",
    "addr:housenumber":"1218",
    "addr:postcode":"46311",
    "addr:street":"Sheffield Ave",
    "iso:country":"US",
    "sg:address":"1218 Sheffield Ave",
    "sg:city":"Dyer",
    "sg:classifiers":[
        {
            "category":"Food & Beverages",
            "subcategory":"Groceries & Convenience Stores",
            "type":"Retail Goods"
        }
    ],
    "sg:phone":"+1 219 322 6428",
    "sg:postcode":"46311",
    "sg:province":"IN",
    "sg:tags":[
        "grocer"
    ],
    "wof:name":"Walt's Food Ctr",
    "wof:placetype":"venue"
},
  "geometry": {"coordinates":[-87.518849,41.508652],"type":"Point"}
}