{
  "type": "Feature",
  "properties": {
    "iso:country":"US",
    "sg:address":"904 N Jefferson St",
    "sg:city":"Converse",
    "sg:classifiers":[
        {
            "category":"Freight",
            "type":"Transportation"
        }
    ],
    "sg:phone":"+1 765 395 3564",
    "sg:postcode":"46919",
    "sg:province":"IN",
    "sg:tags":[
        "operator",
        "local",
        "trucking"
    ],
    "wof:name":"Green Trucking",
    "wof:placetype":"venue"
},
  "geometry": {"coordinates":[-85.87334,40.586658],"type":"Point"}
}