{
  "type": "Feature",
  "properties": {
    "iso:country":"US",
    "sg:address":"1641 N State Rd 39",
    "sg:city":"Monticello",
    "sg:classifiers":[
        {
            "category":"Building & Trades",
            "subcategory":"Construction",
            "type":"Services"
        }
    ],
    "sg:phone":"+1 574 583 5514",
    "sg:postcode":"47960",
    "sg:province":"IN",
    "sg:tags":[
        "general",
        "contractor"
    ],
    "wof:name":"Tribbett Electric Inc",
    "wof:placetype":"venue"
},
  "geometry": {"coordinates":[-86.745289,40.776868],"type":"Point"}
}