{
  "type": "Feature",
  "properties": {
    "iso:country":"US",
    "sg:address":"58263 Charlotte Ave",
    "sg:city":"Elkhart",
    "sg:classifiers":[
        {
            "category":"Wholesale",
            "subcategory":"Machinery & Supplies",
            "type":"Manufacturing & Wholesale Goods"
        }
    ],
    "sg:phone":"+1 574 522 6249",
    "sg:postcode":"46517",
    "sg:province":"IN",
    "sg:tags":[
        "equipment",
        "safety",
        "clothing"
    ],
    "wof:name":"Nagy Fleetnet Inc",
    "wof:placetype":"venue"
},
  "geometry": {"coordinates":[-86.010325,41.65194],"type":"Point"}
}