{
  "type": "Feature",
  "properties": {
    "iso:country":"US",
    "sg:address":"900 Prospect Ave",
    "sg:city":"New Haven",
    "sg:classifiers":[
        {
            "category":"Education",
            "subcategory":"School",
            "type":"Public Place"
        }
    ],
    "sg:phone":"+1 260 446 0230",
    "sg:postcode":"46774",
    "sg:province":"IN",
    "wof:name":"New Haven Middle School",
    "wof:placetype":"venue"
},
  "geometry": {"coordinates":[-85.01611800000001,41.068162],"type":"Point"}
}