{
  "type": "Feature",
  "properties": {
    "iso:country":"US",
    "sg:address":"2827 State Rd 19",
    "sg:city":"Peru",
    "sg:classifiers":[
        {
            "category":"Farming",
            "subcategory":"Farm",
            "type":"Manufacturing & Wholesale Goods"
        }
    ],
    "sg:phone":"+1 765 473 4283",
    "sg:postcode":"46970",
    "sg:province":"IN",
    "wof:name":"Catey Family Farms",
    "wof:placetype":"venue"
},
  "geometry": {"coordinates":[-86.039451,40.802041],"type":"Point"}
}