{
  "type": "Feature",
  "properties": {
    "iso:country":"US",
    "sg:address":"401 N Weinbach Ave",
    "sg:city":"Evansville",
    "sg:classifiers":[
        {
            "category":"Professional",
            "subcategory":"Accounting & Tax Preparation",
            "type":"Services"
        }
    ],
    "sg:phone":"+1 812 477 2226",
    "sg:postcode":"47711",
    "sg:province":"IN",
    "sg:tags":[
        "accountant"
    ],
    "wof:name":"Reinitz Shade & Co",
    "wof:placetype":"venue"
},
  "geometry": {"coordinates":[-87.529338,37.982116],"type":"Point"}
}