{
  "type": "Feature",
  "properties": {
    "addr:full":"7460 S Burlington Dr Muncie IN 47302",
    "addr:housenumber":"7460",
    "addr:postcode":"47302",
    "addr:street":"S Burlington Dr",
    "iso:country":"US",
    "sg:address":"7460 S Burlington Dr",
    "sg:city":"Muncie",
    "sg:classifiers":[
        {
            "category":"Building & Trades",
            "subcategory":"Construction",
            "type":"Services"
        }
    ],
    "sg:phone":"+1 765 289 0242",
    "sg:postcode":"47302",
    "sg:province":"IN",
    "sg:tags":[
        "house"
    ],
    "wof:name":"Lackey Construction Dl",
    "wof:placetype":"venue"
},
  "geometry": {"coordinates":[-85.299007,40.122125],"type":"Point"}
}