{
  "type": "Feature",
  "properties": {
    "iso:country":"US",
    "sg:address":"3022 E Geyman Hill Rd",
    "sg:city":"Madison",
    "sg:classifiers":[
        {
            "category":"Organizations",
            "subcategory":"Professional Association",
            "type":"Services"
        }
    ],
    "sg:phone":"+1 812 265 2019",
    "sg:postcode":"47250",
    "sg:province":"IN",
    "wof:name":"Girl Scouts Camp Whippoorwill",
    "wof:placetype":"venue"
},
  "geometry": {"coordinates":[-85.33377299999999,38.807356],"type":"Point"}
}