{
  "type": "Feature",
  "properties": {
    "iso:country":"US",
    "sg:address":"7713 S Becks Mill Rd",
    "sg:city":"Salem",
    "sg:classifiers":[
        {
            "category":"Farming",
            "subcategory":"Livestock Farm",
            "type":"Manufacturing & Wholesale Goods"
        }
    ],
    "sg:phone":"+1 812 472 3526",
    "sg:postcode":"47167",
    "sg:province":"IN",
    "sg:tags":[
        "feedlot",
        "field",
        "crop",
        "beef",
        "cattle"
    ],
    "wof:name":"Evaline Farm",
    "wof:placetype":"venue"
},
  "geometry": {"coordinates":[-86.17386399999999,38.494178],"type":"Point"}
}