{
  "type": "Feature",
  "properties": {
    "iso:country":"US",
    "sg:address":"1213 State Rd 25 W",
    "sg:city":"Lafayette",
    "sg:classifiers":[
        {
            "category":"Building & Trades",
            "subcategory":"Construction",
            "type":"Services"
        }
    ],
    "sg:phone":"+1 765 474 3091",
    "sg:postcode":"47909",
    "sg:province":"IN",
    "sg:tags":[
        "general",
        "contractor"
    ],
    "wof:name":"Mowat Construction",
    "wof:placetype":"venue"
},
  "geometry": {"coordinates":[-86.92527200000001,40.384538],"type":"Point"}
}