{
  "type": "Feature",
  "properties": {
    "iso:country":"US",
    "sg:address":"924 N Carver St",
    "sg:city":"Greensburg",
    "sg:classifiers":[
        {
            "category":"Retail",
            "subcategory":"Auto Repair",
            "type":"Services"
        }
    ],
    "sg:phone":"+1 812 663 5854",
    "sg:postcode":"47240",
    "sg:province":"IN",
    "sg:tags":[
        "body",
        "automobile",
        "painting"
    ],
    "wof:name":"Jerry Wright Autobody Rstrtn",
    "wof:placetype":"venue"
},
  "geometry": {"coordinates":[-85.491721,39.345837],"type":"Point"}
}