{
  "type": "Feature",
  "properties": {
    "iso:country":"US",
    "sg:address":"9890 S Voyles Rd",
    "sg:city":"Borden",
    "sg:classifiers":[
        {
            "category":"Building & Trades",
            "subcategory":"Construction",
            "type":"Services"
        }
    ],
    "sg:phone":"+1 812 967 5236",
    "sg:postcode":"47106",
    "sg:province":"IN",
    "sg:tags":[
        "residential"
    ],
    "wof:name":"Stinson & Son Contracting",
    "wof:placetype":"venue"
},
  "geometry": {"coordinates":[-85.99605,38.447649],"type":"Point"}
}