{
  "type": "Feature",
  "properties": {
    "iso:country":"US",
    "sg:address":"6795 W Leiber Ave",
    "sg:city":"West Terre Haute",
    "sg:classifiers":[
        {
            "category":"Building & Trades",
            "subcategory":"Construction",
            "type":"Services"
        }
    ],
    "sg:phone":"+1 812 535 3453",
    "sg:postcode":"47885",
    "sg:province":"IN",
    "sg:tags":[
        "concrete",
        "contractor"
    ],
    "wof:name":"Dick Allen Concrete",
    "wof:placetype":"venue"
},
  "geometry": {"coordinates":[-87.530647,39.534889],"type":"Point"}
}