{
  "type": "Feature",
  "properties": {
    "iso:country":"US",
    "sg:address":"12890 Parkside Dr",
    "sg:city":"Fishers",
    "sg:classifiers":[
        {
            "category":"Social Services",
            "subcategory":"Child Care",
            "type":"Services"
        }
    ],
    "sg:phone":"+1 317 598 0080",
    "sg:postcode":"46038",
    "sg:province":"IN",
    "wof:name":"Kid's World Day Care",
    "wof:placetype":"venue"
},
  "geometry": {"coordinates":[-86.00147200000001,39.975049],"type":"Point"}
}