{
  "type": "Feature",
  "properties": {
    "iso:country":"US",
    "sg:address":"1130 Verdant St",
    "sg:city":"Elkhart",
    "sg:classifiers":[
        {
            "category":"Manufacturing",
            "subcategory":"Metals",
            "type":"Manufacturing & Wholesale Goods"
        }
    ],
    "sg:phone":"+1 574 293 5576",
    "sg:postcode":"46516",
    "sg:province":"IN",
    "sg:tags":[
        "steel"
    ],
    "wof:name":"Helgeson Steel Inc",
    "wof:placetype":"venue"
},
  "geometry": {"coordinates":[-85.894493,41.678058],"type":"Point"}
}