{
  "type": "Feature",
  "properties": {
    "addr:full":"235 W Creighton Ave Fort Wayne IN 46807",
    "addr:housenumber":"235",
    "addr:postcode":"46807",
    "addr:street":"W Creighton Ave",
    "iso:country":"US",
    "sg:address":"235 W Creighton Ave",
    "sg:city":"Fort Wayne",
    "sg:classifiers":[
        {
            "category":"Professional",
            "subcategory":"Business Services",
            "type":"Services"
        }
    ],
    "sg:phone":"+1 260 373 1999",
    "sg:postcode":"46807",
    "sg:province":"IN",
    "sg:tags":[
        "translator",
        "interpreter"
    ],
    "sg:website":"www.northeastin.redcross.org",
    "wof:name":"MIX Program",
    "wof:placetype":"venue"
},
  "geometry": {"coordinates":[-85.14023400000001,41.064181],"type":"Point"}
}