{
  "type": "Feature",
  "properties": {
    "iso:country":"US",
    "sg:address":"975 Hyrock Blvd",
    "sg:city":"Boonville",
    "sg:classifiers":[
        {
            "category":"Autos & Motor Vehicles",
            "subcategory":"Automobile Sales",
            "type":"Retail Goods"
        }
    ],
    "sg:phone":"+1 812 897 3600",
    "sg:postcode":"47601",
    "sg:province":"IN",
    "sg:tags":[
        "performance",
        "race",
        "dealer"
    ],
    "sg:website":"www.dynatechheaders.com",
    "wof:name":"Dynatech Division",
    "wof:placetype":"venue"
},
  "geometry": {"coordinates":[-87.319433,38.045014],"type":"Point"}
}