{
  "type": "Feature",
  "properties": {
    "iso:country":"US",
    "sg:address":"1207 E 7th St",
    "sg:city":"Auburn",
    "sg:classifiers":[
        {
            "category":"Food & Beverages",
            "subcategory":"Groceries & Convenience Stores",
            "type":"Retail Goods"
        }
    ],
    "sg:phone":"+1 260 925 1087",
    "sg:postcode":"46706",
    "sg:province":"IN",
    "wof:name":"Sunshine Market",
    "wof:placetype":"venue"
},
  "geometry": {"coordinates":[-85.039709,41.36756],"type":"Point"}
}