{
  "type": "Feature",
  "properties": {
    "addr:full":"16229 Saint Marys Rd Brookville IN 47012",
    "addr:housenumber":"16229",
    "addr:postcode":"47012",
    "addr:street":"Saint Marys Rd",
    "iso:country":"US",
    "sg:address":"16229 Saint Marys Rd",
    "sg:city":"Brookville",
    "sg:classifiers":[
        {
            "category":"Home & Garden",
            "subcategory":"Hardware",
            "type":"Retail Goods"
        }
    ],
    "sg:phone":"+1 765 647 3679",
    "sg:postcode":"47012",
    "sg:province":"IN",
    "wof:name":"Oak Forest General Store",
    "wof:placetype":"venue"
},
  "geometry": {"coordinates":[-85.08425699999999,39.393643],"type":"Point"}
}