{
  "type": "Feature",
  "properties": {
    "iso:country":"US",
    "sg:address":"58312 Oakwood Ct",
    "sg:city":"Elkhart",
    "sg:classifiers":[
        {
            "category":"Home & Garden",
            "subcategory":"Home Furnishings",
            "type":"Retail Goods"
        }
    ],
    "sg:phone":"+1 574 875 6941",
    "sg:postcode":"46516",
    "sg:province":"IN",
    "sg:tags":[
        "curtain",
        "made",
        "drapery"
    ],
    "wof:name":"Creative Windowear",
    "wof:placetype":"venue"
},
  "geometry": {"coordinates":[-85.92026,41.647666],"type":"Point"}
}