{
  "type": "Feature",
  "properties": {
    "iso:country":"US",
    "sg:address":"422 Park 800 Dr",
    "sg:city":"Greenwood",
    "sg:classifiers":[
        {
            "category":"Wholesale",
            "subcategory":"Medical Equipment & Supplies",
            "type":"Manufacturing & Wholesale Goods"
        }
    ],
    "sg:phone":"+1 317 881 7269",
    "sg:postcode":"46143",
    "sg:province":"IN",
    "sg:tags":[
        "x",
        "apparatus"
    ],
    "wof:name":"Radiation Services",
    "wof:placetype":"venue"
},
  "geometry": {"coordinates":[-86.095721,39.591903],"type":"Point"}
}