{
  "type": "Feature",
  "properties": {
    "iso:country":"US",
    "sg:address":"6814 E 700 S",
    "sg:city":"Star City",
    "sg:classifiers":[
        {
            "category":"Farming",
            "subcategory":"Farm",
            "type":"Manufacturing & Wholesale Goods"
        }
    ],
    "sg:phone":"+1 574 595 7306",
    "sg:postcode":"46985",
    "sg:province":"IN",
    "sg:tags":[
        "crop",
        "general"
    ],
    "wof:name":"Sammy Jones Farms",
    "wof:placetype":"venue"
},
  "geometry": {"coordinates":[-86.473026,40.953442],"type":"Point"}
}