{
  "type": "Feature",
  "properties": {
    "iso:country":"US",
    "sg:address":"999 Eastern Blvd",
    "sg:city":"Clarksville",
    "sg:classifiers":[
        {
            "category":"Banks & Credit Unions",
            "subcategory":"Bank",
            "type":"Services"
        }
    ],
    "sg:phone":"+1 812 288 9131",
    "sg:postcode":"47129",
    "sg:province":"IN",
    "sg:tags":[
        "financing"
    ],
    "wof:name":"Citi Financial",
    "wof:placetype":"venue"
},
  "geometry": {"coordinates":[-85.764747,38.303003],"type":"Point"}
}