{
  "type": "Feature",
  "properties": {
    "iso:country":"US",
    "sg:address":"205 E Main St",
    "sg:city":"Brownsburg",
    "sg:classifiers":[
        {
            "category":"Real Estate",
            "subcategory":"Real Estate Agent",
            "type":"Services"
        }
    ],
    "sg:phone":"+1 317 852 7519",
    "sg:postcode":"46112",
    "sg:province":"IN",
    "wof:name":"Kelly Cook & Assoc Realtors",
    "wof:placetype":"venue"
},
  "geometry": {"coordinates":[-86.394594,39.842312],"type":"Point"}
}