{
  "type": "Feature",
  "properties": {
    "addr:full":"3875 Culligan Ave Indianapolis IN 46218",
    "addr:housenumber":"3875",
    "addr:postcode":"46218",
    "addr:street":"Culligan Ave",
    "iso:country":"US",
    "sg:address":"3875 Culligan Ave",
    "sg:city":"Indianapolis",
    "sg:classifiers":[
        {
            "category":"Manufacturing",
            "subcategory":"Food",
            "type":"Manufacturing & Wholesale Goods"
        }
    ],
    "sg:phone":"+1 317 351 8960",
    "sg:postcode":"46218",
    "sg:province":"IN",
    "sg:tags":[
        "spice"
    ],
    "wof:name":"Food Innovations",
    "wof:placetype":"venue"
},
  "geometry": {"coordinates":[-86.10101,39.790807],"type":"Point"}
}