{
  "type": "Feature",
  "properties": {
    "addr:full":"4801 W 106th St Zionsville IN 46077",
    "addr:housenumber":"4801",
    "addr:postcode":"46077",
    "addr:street":"W 106Th St",
    "iso:country":"US",
    "sg:address":"4801 W 106th St",
    "sg:city":"Zionsville",
    "sg:classifiers":[
        {
            "category":"Building & Trades",
            "subcategory":"Plumbing",
            "type":"Services"
        }
    ],
    "sg:phone":"+1 317 873 4887",
    "sg:postcode":"46077",
    "sg:province":"IN",
    "sg:tags":[
        "plumbing",
        "contractor"
    ],
    "wof:name":"Jerry Jones Plumbing & Well",
    "wof:placetype":"venue"
},
  "geometry": {"coordinates":[-86.24090099999999,39.940753],"type":"Point"}
}