{
  "type": "Feature",
  "properties": {
    "iso:country":"US",
    "sg:address":"4113 Turner Rd",
    "sg:city":"Richmond",
    "sg:classifiers":[
        {
            "category":"Shopping",
            "type":"Retail Goods"
        }
    ],
    "sg:phone":"+1 765 935 3566",
    "sg:postcode":"47374",
    "sg:province":"IN",
    "sg:tags":[
        "merchandise"
    ],
    "wof:name":"Safety Systems",
    "wof:placetype":"venue"
},
  "geometry": {"coordinates":[-84.845516,39.876541],"type":"Point"}
}