{
  "type": "Feature",
  "properties": {
    "addr:full":"6081 E 82nd St Indianapolis IN 46250",
    "addr:housenumber":"6081",
    "addr:postcode":"46250",
    "addr:street":"E 82Nd St",
    "iso:country":"US",
    "sg:address":"6081 E 82nd St",
    "sg:city":"Indianapolis",
    "sg:classifiers":[
        {
            "category":"Wholesale",
            "subcategory":"Motor Vehicles",
            "type":"Manufacturing & Wholesale Goods"
        }
    ],
    "sg:phone":"+1 317 585 1930",
    "sg:postcode":"46250",
    "sg:province":"IN",
    "sg:tags":[
        "bus"
    ],
    "wof:name":"Corbeil",
    "wof:placetype":"venue"
},
  "geometry": {"coordinates":[-86.06455099999999,39.905194],"type":"Point"}
}