{
  "type": "Feature",
  "properties": {
    "iso:country":"US",
    "sg:address":"1528 Lake Point Ln N",
    "sg:city":"Greenwood",
    "sg:classifiers":[
        {
            "category":"Arts & Performance",
            "subcategory":"Theater",
            "type":"Entertainment"
        }
    ],
    "sg:phone":"+1 317 889 8375",
    "sg:postcode":"46142",
    "sg:province":"IN",
    "sg:tags":[
        "group"
    ],
    "wof:name":"Lakin Nicholas Lee Professi On",
    "wof:placetype":"venue"
},
  "geometry": {"coordinates":[-86.149817,39.617372],"type":"Point"}
}