{
  "type": "Feature",
  "properties": {
    "iso:country":"US",
    "sg:address":"6222 Central Ave",
    "sg:city":"Portage",
    "sg:classifiers":[
        {
            "category":"Restaurant",
            "type":"Food & Drink"
        }
    ],
    "sg:phone":"+1 219 762 2388",
    "sg:postcode":"46368",
    "sg:province":"IN",
    "wof:name":"Jade Garden Restaurant",
    "wof:placetype":"venue"
},
  "geometry": {"coordinates":[-87.174554,41.575936],"type":"Point"}
}