{
  "type": "Feature",
  "properties": {
    "iso:country":"US",
    "sg:address":"2610 N Lyn-Mar Dr",
    "sg:city":"Muncie",
    "sg:classifiers":[
        {
            "category":"Building & Trades",
            "subcategory":"Construction",
            "type":"Services"
        }
    ],
    "sg:phone":"+1 765 284 9263",
    "sg:postcode":"47304",
    "sg:province":"IN",
    "sg:tags":[
        "residential"
    ],
    "wof:name":"Paramount Builders",
    "wof:placetype":"venue"
},
  "geometry": {"coordinates":[-85.432007,40.216333],"type":"Point"}
}