{
  "type": "Feature",
  "properties": {
    "iso:country":"US",
    "sg:address":"9071 Technology Dr",
    "sg:city":"Fishers",
    "sg:classifiers":[
        {
            "category":"Wholesale",
            "subcategory":"Machinery & Supplies",
            "type":"Manufacturing & Wholesale Goods"
        }
    ],
    "sg:phone":"+1 317 577 5565",
    "sg:postcode":"46038",
    "sg:province":"IN",
    "sg:tags":[
        "equipment",
        "industrial"
    ],
    "wof:name":"R L Guimont Co",
    "wof:placetype":"venue"
},
  "geometry": {"coordinates":[-86.009629,39.961038],"type":"Point"}
}