{
  "type": "Feature",
  "properties": {
    "iso:country":"US",
    "sg:address":"192 Professional Ct",
    "sg:city":"Hebron",
    "sg:classifiers":[
        {
            "category":"Health Services",
            "subcategory":"Doctor",
            "type":"Services"
        }
    ],
    "sg:phone":"+1 219 996 5606",
    "sg:postcode":"46341",
    "sg:province":"IN",
    "sg:tags":[
        "dentist"
    ],
    "wof:name":"Peter J Blank DDS",
    "wof:placetype":"venue"
},
  "geometry": {"coordinates":[-87.20275,41.334039],"type":"Point"}
}