{
  "type": "Feature",
  "properties": {
    "iso:country":"US",
    "sg:address":"2415 Directors Row",
    "sg:city":"Indianapolis",
    "sg:classifiers":[
        {
            "category":"Wholesale",
            "subcategory":"Machinery & Supplies",
            "type":"Manufacturing & Wholesale Goods"
        }
    ],
    "sg:phone":"+1 317 243 3496",
    "sg:postcode":"46241",
    "sg:province":"IN",
    "sg:tags":[
        "bearing"
    ],
    "wof:name":"THK America Inc",
    "wof:placetype":"venue"
},
  "geometry": {"coordinates":[-86.260496,39.730229],"type":"Point"}
}