{
  "type": "Feature",
  "properties": {
    "addr:full":"917 W Memorial Dr Muncie IN 47302",
    "addr:housenumber":"917",
    "addr:postcode":"47302",
    "addr:street":"W Memorial Dr",
    "iso:country":"US",
    "sg:address":"917 W Memorial Dr",
    "sg:city":"Muncie",
    "sg:classifiers":[
        {
            "category":"Cinema",
            "subcategory":"Movie Rental",
            "type":"Entertainment"
        }
    ],
    "sg:phone":"+1 765 282 0788",
    "sg:postcode":"47302",
    "sg:province":"IN",
    "sg:tags":[
        "leasing",
        "video",
        "disc",
        "tape"
    ],
    "wof:name":"Lee's Video Library",
    "wof:placetype":"venue"
},
  "geometry": {"coordinates":[-85.396523,40.178263],"type":"Point"}
}