{
  "type": "Feature",
  "properties": {
    "iso:country":"US",
    "sg:address":"1204 W 7th Pl",
    "sg:city":"Hobart",
    "sg:classifiers":[
        {
            "category":"Building & Trades",
            "subcategory":"Construction",
            "type":"Services"
        }
    ],
    "sg:phone":"+1 219 947 9299",
    "sg:postcode":"46342",
    "sg:province":"IN",
    "sg:tags":[
        "contractor"
    ],
    "wof:name":"Advantage Tile",
    "wof:placetype":"venue"
},
  "geometry": {"coordinates":[-87.275499,41.526314],"type":"Point"}
}