{
  "type": "Feature",
  "properties": {
    "addr:full":"400 S Huntington St Syracuse IN 46567",
    "addr:housenumber":"400",
    "addr:postcode":"46567",
    "addr:street":"S Huntington St",
    "iso:country":"US",
    "sg:address":"400 S Huntington St",
    "sg:city":"Syracuse",
    "sg:classifiers":[
        {
            "category":"Restaurant",
            "type":"Food & Drink"
        }
    ],
    "sg:menulink":"http://www.allmenus.com/in/turkey-creek/198519-kfc---kentucky-fried-chicken/menu/",
    "sg:phone":"+1 574 457 5199",
    "sg:postcode":"46567",
    "sg:province":"IN",
    "sg:tags":[
        "american",
        "chicken"
    ],
    "wof:name":"KFC - Kentucky Fried Chicken",
    "wof:placetype":"venue"
},
  "geometry": {"coordinates":[-85.747578,41.418858],"type":"Point"}
}