{
  "type": "Feature",
  "properties": {
    "iso:country":"US",
    "sg:address":"2454 S Co Rd 850 E",
    "sg:city":"New Castle",
    "sg:phone":"+1 765 332 2862",
    "sg:postcode":"47362",
    "sg:province":"IN",
    "sg:tags":[
        "farm",
        "corn",
        "soybean"
    ],
    "wof:name":"Fred Lowhorn",
    "wof:placetype":"venue"
},
  "geometry": {"coordinates":[-85.22325499999999,39.895689],"type":"Point"}
}