{
  "type": "Feature",
  "properties": {
    "iso:country":"US",
    "sg:address":"11611 N Meridian St",
    "sg:city":"Carmel",
    "sg:classifiers":[
        {
            "category":"Banks & Credit Unions",
            "subcategory":"Financial Services",
            "type":"Services"
        }
    ],
    "sg:phone":"+1 317 843 8986",
    "sg:postcode":"46032",
    "sg:province":"IN",
    "sg:tags":[
        "company",
        "holding"
    ],
    "wof:name":"Worldwide Associates LLC",
    "wof:placetype":"venue"
},
  "geometry": {"coordinates":[-86.157551,39.956421],"type":"Point"}
}