{
  "type": "Feature",
  "properties": {
    "iso:country":"US",
    "sg:address":"6745 Gray Rd",
    "sg:city":"Indianapolis",
    "sg:classifiers":[
        {
            "category":"Wholesale",
            "subcategory":"Scrap",
            "type":"Manufacturing & Wholesale Goods"
        }
    ],
    "sg:phone":"+1 317 791 1295",
    "sg:postcode":"46237",
    "sg:province":"IN",
    "sg:tags":[
        "recycling",
        "center"
    ],
    "wof:name":"Ocean Group",
    "wof:placetype":"venue"
},
  "geometry": {"coordinates":[-86.096687,39.669345],"type":"Point"}
}