{
  "type": "Feature",
  "properties": {
    "iso:country":"US",
    "sg:address":"860 S Penn Ave",
    "sg:city":"Sellersburg",
    "sg:classifiers":[
        {
            "category":"Wholesale",
            "subcategory":"Construction Materials",
            "type":"Manufacturing & Wholesale Goods"
        }
    ],
    "sg:phone":"+1 812 246 5619",
    "sg:postcode":"47172",
    "sg:province":"IN",
    "sg:tags":[
        "marble"
    ],
    "wof:name":"BSWB-Benita Springs",
    "wof:placetype":"venue"
},
  "geometry": {"coordinates":[-85.749313,38.387708],"type":"Point"}
}