{
  "type": "Feature",
  "properties": {
    "iso:country":"US",
    "sg:address":"14880 Lamar Rd",
    "sg:city":"Hagerstown",
    "sg:classifiers":[
        {
            "category":"Shopping",
            "subcategory":"Computers & Home Electronics",
            "type":"Retail Goods"
        }
    ],
    "sg:phone":"+1 765 489 5450",
    "sg:postcode":"47346",
    "sg:province":"IN",
    "wof:name":"PC Sales & Service",
    "wof:placetype":"venue"
},
  "geometry": {"coordinates":[-85.158829,39.960677],"type":"Point"}
}