{
  "type": "Feature",
  "properties": {
    "addr:full":"4850 S Emerson Ave Indianapolis IN 46203",
    "addr:housenumber":"4850",
    "addr:postcode":"46203",
    "addr:street":"S Emerson Ave",
    "iso:country":"US",
    "sg:address":"4850 S Emerson Ave",
    "sg:city":"Indianapolis",
    "sg:phone":"+1 317 786 6980",
    "sg:postcode":"46203",
    "sg:province":"IN",
    "sg:tags":[
        "oil"
    ],
    "wof:name":"Crystal Flash Petroleum Corp",
    "wof:placetype":"venue"
},
  "geometry": {"coordinates":[-86.08253499999999,39.69811],"type":"Point"}
}