{
  "type": "Feature",
  "properties": {
    "addr:full":"11505 Browning Rd Evansville IN 47725",
    "addr:housenumber":"11505",
    "addr:postcode":"47725",
    "addr:street":"Browning Rd",
    "iso:country":"US",
    "sg:address":"11505 Browning Rd",
    "sg:city":"Evansville",
    "sg:classifiers":[
        {
            "category":"Organizations",
            "subcategory":"Community Association",
            "type":"Services"
        }
    ],
    "sg:phone":"+1 812 867 1900",
    "sg:postcode":"47725",
    "sg:province":"IN",
    "sg:tags":[
        "club"
    ],
    "wof:name":"Oak Meadow Golf Club",
    "wof:placetype":"venue"
},
  "geometry": {"coordinates":[-87.53363899999999,38.082631],"type":"Point"}
}