{
  "type": "Feature",
  "properties": {
    "addr:full":"14678 State Rd 23 Granger IN 46530",
    "addr:housenumber":"14678;23",
    "addr:postcode":"46530",
    "addr:street":"State Rd",
    "iso:country":"US",
    "sg:address":"14678 State Rd 23",
    "sg:city":"Granger",
    "sg:classifiers":[
        {
            "category":"Personal",
            "subcategory":"Beauty Salon",
            "type":"Services"
        }
    ],
    "sg:phone":"+1 574 271 2323",
    "sg:postcode":"46530",
    "sg:province":"IN",
    "wof:name":"Studio 23",
    "wof:placetype":"venue"
},
  "geometry": {"coordinates":[-86.149332,41.738079],"type":"Point"}
}