{
  "type": "Feature",
  "properties": {
    "iso:country":"US",
    "sg:address":"5035 Study Rd",
    "sg:city":"Centerville",
    "sg:classifiers":[
        {
            "category":"Professional",
            "subcategory":"Management & Consulting",
            "type":"Services"
        }
    ],
    "sg:phone":"+1 765 855 1300",
    "sg:postcode":"47330",
    "sg:province":"IN",
    "wof:name":"Myra Baldwin",
    "wof:placetype":"venue"
},
  "geometry": {"coordinates":[-84.97424,39.779844],"type":"Point"}
}