{
  "type": "Feature",
  "properties": {
    "iso:country":"US",
    "sg:address":"6501 N State Rd 39",
    "sg:city":"La Porte",
    "sg:phone":"+1 219 767 2631",
    "sg:postcode":"46350",
    "sg:province":"IN",
    "sg:tags":[
        "farm",
        "corn"
    ],
    "wof:name":"Big Shot Farms",
    "wof:placetype":"venue"
},
  "geometry": {"coordinates":[-86.730097,41.704715],"type":"Point"}
}