{
  "type": "Feature",
  "properties": {
    "iso:country":"US",
    "sg:address":"906 N 800 W",
    "sg:city":"Andrews",
    "sg:phone":"+1 260 786 3283",
    "sg:postcode":"46702",
    "sg:province":"IN",
    "sg:tags":[
        "farm",
        "corn",
        "wheat",
        "soybean"
    ],
    "wof:name":"Rodocker Olan",
    "wof:placetype":"venue"
},
  "geometry": {"coordinates":[-85.603397,40.840413],"type":"Point"}
}