{
  "type": "Feature",
  "properties": {
    "addr:full":"1601 W Gump Rd Huntertown IN 46748",
    "addr:housenumber":"1601",
    "addr:postcode":"46748",
    "addr:street":"W Gump Rd",
    "iso:country":"US",
    "sg:address":"1601 W Gump Rd",
    "sg:city":"Huntertown",
    "sg:classifiers":[
        {
            "category":"Restaurant",
            "type":"Food & Drink"
        }
    ],
    "sg:phone":"+1 260 637 5411",
    "sg:postcode":"46748",
    "sg:province":"IN",
    "wof:name":"Willows",
    "wof:placetype":"venue"
},
  "geometry": {"coordinates":[-85.16577599999999,41.224469],"type":"Point"}
}