{
  "type": "Feature",
  "properties": {
    "addr:full":"846 Main St Lafayette IN 47901",
    "addr:housenumber":"846",
    "addr:postcode":"47901",
    "addr:street":"Main St",
    "iso:country":"US",
    "sg:address":"846 Main St",
    "sg:city":"Lafayette",
    "sg:classifiers":[
        {
            "category":"Shopping",
            "subcategory":"Gifts & Souvenirs",
            "type":"Retail Goods"
        }
    ],
    "sg:phone":"+1 765 420 8990",
    "sg:postcode":"47901",
    "sg:province":"IN",
    "sg:tags":[
        "announcement",
        "invitation"
    ],
    "sg:website":"www.twotulips.com",
    "wof:name":"Two Tulips",
    "wof:placetype":"venue"
},
  "geometry": {"coordinates":[-86.886999,40.419203],"type":"Point"}
}