{
  "type": "Feature",
  "properties": {
    "iso:country":"US",
    "sg:address":"712 Upper 11th St",
    "sg:city":"Vincennes",
    "sg:classifiers":[
        {
            "category":"Manufacturing",
            "subcategory":"Building Materials",
            "type":"Manufacturing & Wholesale Goods"
        }
    ],
    "sg:phone":"+1 812 882 8547",
    "sg:postcode":"47591",
    "sg:province":"IN",
    "sg:tags":[
        "solid",
        "wood",
        "door",
        "mfg"
    ],
    "sg:website":"www.fabco-inc.net",
    "wof:name":"Fabco Inc",
    "wof:placetype":"venue"
},
  "geometry": {"coordinates":[-87.518997,38.676414],"type":"Point"}
}