{
  "type": "Feature",
  "properties": {
    "addr:full":"301 S Walnut St Muncie IN 47305",
    "addr:housenumber":"301",
    "addr:postcode":"47305",
    "addr:street":"S Walnut St",
    "iso:country":"US",
    "sg:address":"301 S Walnut St",
    "sg:city":"Muncie",
    "sg:classifiers":[
        {
            "category":"Shopping",
            "type":"Retail Goods"
        }
    ],
    "sg:phone":"+1 765 288 2221",
    "sg:postcode":"47305",
    "sg:province":"IN",
    "sg:tags":[
        "art",
        "gallery",
        "dealer"
    ],
    "sg:website":"www.artworks.biz",
    "wof:name":"Artworks",
    "wof:placetype":"venue"
},
  "geometry": {"coordinates":[-85.386563,40.191115],"type":"Point"}
}