{
  "type": "Feature",
  "properties": {
    "iso:country":"US",
    "sg:address":"128 E Lake St",
    "sg:city":"Topeka",
    "sg:classifiers":[
        {
            "category":"Wholesale",
            "subcategory":"Construction Materials",
            "type":"Manufacturing & Wholesale Goods"
        }
    ],
    "sg:phone":"+1 260 593 2358",
    "sg:postcode":"46571",
    "sg:province":"IN",
    "sg:tags":[
        "sand",
        "gravel"
    ],
    "wof:name":"Shrock's Gravel",
    "wof:placetype":"venue"
},
  "geometry": {"coordinates":[-85.538769,41.539412],"type":"Point"}
}