{
  "type": "Feature",
  "properties": {
    "iso:country":"US",
    "sg:address":"5128 E 65th St",
    "sg:city":"Indianapolis",
    "sg:classifiers":[
        {
            "category":"Autos & Motor Vehicles",
            "subcategory":"Auto Supplies",
            "type":"Retail Goods"
        }
    ],
    "sg:phone":"+1 317 579 9520",
    "sg:postcode":"46220",
    "sg:province":"IN",
    "sg:tags":[
        "automobile",
        "equipment",
        "car",
        "performance",
        "sport",
        "racing"
    ],
    "sg:website":"http://www.epwerks.com",
    "wof:name":"EP Werks- Authorzied APR Dealer-AUDI-VW-Porsche",
    "wof:placetype":"venue"
},
  "geometry": {"coordinates":[-86.08456700000001,39.875938],"type":"Point"}
}