{
  "type": "Feature",
  "properties": {
    "iso:country":"US",
    "sg:address":"2406 Valley Ct",
    "sg:city":"Shelbyville",
    "sg:classifiers":[
        {
            "category":"Building & Trades",
            "subcategory":"Construction",
            "type":"Services"
        }
    ],
    "sg:phone":"+1 317 398 8918",
    "sg:postcode":"46176",
    "sg:province":"IN",
    "sg:tags":[
        "residential"
    ],
    "wof:name":"Terrells Construction",
    "wof:placetype":"venue"
},
  "geometry": {"coordinates":[-85.77279299999999,39.498324],"type":"Point"}
}