{
  "type": "Feature",
  "properties": {
    "iso:country":"US",
    "sg:address":"330 N 400 E",
    "sg:city":"Valparaiso",
    "sg:classifiers":[
        {
            "category":"Manufacturing",
            "subcategory":"Tools & Machinery",
            "type":"Manufacturing & Wholesale Goods"
        }
    ],
    "sg:phone":"+1 219 464 2027",
    "sg:postcode":"46383",
    "sg:province":"IN",
    "sg:website":"www.ufsc.com",
    "wof:name":"UFS Corp",
    "wof:placetype":"venue"
},
  "geometry": {"coordinates":[-86.988437,41.481244],"type":"Point"}
}