{
  "type": "Feature",
  "properties": {
    "addr:full":"6556 Co Rd 34 Butler IN 46721",
    "addr:housenumber":"6556;34",
    "addr:postcode":"46721",
    "addr:street":"Co Rd",
    "iso:country":"US",
    "sg:address":"6556 Co Rd 34",
    "sg:city":"Butler",
    "sg:classifiers":[
        {
            "category":"Retail",
            "subcategory":"Animal Services",
            "type":"Services"
        }
    ],
    "sg:phone":"+1 260 868 0120",
    "sg:postcode":"46721",
    "sg:province":"IN",
    "sg:tags":[
        "pet",
        "grooming",
        "washing"
    ],
    "wof:name":"Denise's Country Grooming",
    "wof:placetype":"venue"
},
  "geometry": {"coordinates":[-84.88323,41.407455],"type":"Point"}
}