{
  "type": "Feature",
  "properties": {
    "iso:country":"US",
    "sg:address":"5419 Hanna St",
    "sg:city":"Fort Wayne",
    "sg:classifiers":[
        {
            "category":"Autos & Motor Vehicles",
            "subcategory":"Automobile Sales",
            "type":"Retail Goods"
        }
    ],
    "sg:phone":"+1 260 458 9292",
    "sg:postcode":"46806",
    "sg:province":"IN",
    "sg:tags":[
        "car",
        "dealer"
    ],
    "wof:name":"Circle K Used Cars Inc",
    "wof:placetype":"venue"
},
  "geometry": {"coordinates":[-85.12721500000001,41.035182],"type":"Point"}
}