{
  "type": "Feature",
  "properties": {
    "iso:country":"US",
    "sg:address":"1475 Locust St",
    "sg:city":"Terre Haute",
    "sg:classifiers":[
        {
            "category":"Professional",
            "subcategory":"Accounting & Tax Preparation",
            "type":"Services"
        }
    ],
    "sg:phone":"+1 812 232 6864",
    "sg:postcode":"47807",
    "sg:province":"IN",
    "sg:tags":[
        "return",
        "filing"
    ],
    "sg:website":"www.larrisonstax.com",
    "wof:name":"Larrison's Bookkeeping & Tax",
    "wof:placetype":"venue"
},
  "geometry": {"coordinates":[-87.393551,39.477461],"type":"Point"}
}