{
  "type": "Feature",
  "properties": {
    "iso:country":"US",
    "sg:address":"210 5th St",
    "sg:city":"Aurora",
    "sg:classifiers":[
        {
            "category":"Education",
            "subcategory":"Special Training",
            "type":"Public Place"
        }
    ],
    "sg:phone":"+1 812 926 0060",
    "sg:postcode":"47001",
    "sg:province":"IN",
    "sg:tags":[
        "center"
    ],
    "wof:name":"St Mary's Religious Education",
    "wof:placetype":"venue"
},
  "geometry": {"coordinates":[-84.90005,39.053586],"type":"Point"}
}