{
  "type": "Feature",
  "properties": {
    "iso:country":"US",
    "sg:address":"2514 Messick Dr S",
    "sg:city":"Goshen",
    "sg:classifiers":[
        {
            "category":"Education",
            "subcategory":"Special Training",
            "type":"Public Place"
        }
    ],
    "sg:phone":"+1 574 534 2096",
    "sg:postcode":"46526",
    "sg:province":"IN",
    "sg:tags":[
        "educational"
    ],
    "wof:name":"Modern Educational Systems",
    "wof:placetype":"venue"
},
  "geometry": {"coordinates":[-85.812341,41.552214],"type":"Point"}
}