{
  "type": "Feature",
  "properties": {
    "addr:full":"3590 Edwardsville Galena Rd Georgetown IN 47122",
    "addr:housenumber":"3590",
    "addr:postcode":"47122",
    "addr:street":"Edwardsville Galena Rd",
    "iso:country":"US",
    "sg:address":"3590 Edwardsville Galena Rd",
    "sg:city":"Georgetown",
    "sg:classifiers":[
        {
            "category":"Building & Trades",
            "subcategory":"Landscaping Services",
            "type":"Services"
        }
    ],
    "sg:phone":"+1 812 923 5953",
    "sg:postcode":"47122",
    "sg:province":"IN",
    "sg:tags":[
        "landscape",
        "contractor"
    ],
    "wof:name":"Myers & Hofelich Landscaping",
    "wof:placetype":"venue"
},
  "geometry": {"coordinates":[-85.933587,38.325222],"type":"Point"}
}