{
  "type": "Feature",
  "properties": {
    "iso:country":"US",
    "sg:address":"25 Indiana St",
    "sg:city":"Jasper",
    "sg:classifiers":[
        {
            "category":"Restaurant",
            "type":"Food & Drink"
        }
    ],
    "sg:phone":"+1 812 481 1466",
    "sg:postcode":"47546",
    "sg:province":"IN",
    "wof:name":"Shoney's",
    "wof:placetype":"venue"
},
  "geometry": {"coordinates":[-86.94199,38.386217],"type":"Point"}
}