{
  "type": "Feature",
  "properties": {
    "iso:country":"US",
    "sg:address":"4500 Crestview Dr",
    "sg:city":"Evansville",
    "sg:classifiers":[
        {
            "category":"Sports & Exercise",
            "subcategory":"Race Track",
            "type":"Entertainment"
        }
    ],
    "sg:phone":"+1 812 479 8760",
    "sg:postcode":"47711",
    "sg:province":"IN",
    "wof:name":"Ump Motor Sports Inc",
    "wof:placetype":"venue"
},
  "geometry": {"coordinates":[-87.495683,38.022129],"type":"Point"}
}