{
  "type": "Feature",
  "properties": {
    "iso:country":"US",
    "sg:address":"117 E Charles St",
    "sg:city":"Muncie",
    "sg:classifiers":[
        {
            "category":"Banks & Credit Unions",
            "subcategory":"Bank",
            "type":"Services"
        }
    ],
    "sg:phone":"+1 765 741 0560",
    "sg:postcode":"47305",
    "sg:province":"IN",
    "sg:tags":[
        "loan",
        "real estate"
    ],
    "wof:name":"Federal Mortgage Corp",
    "wof:placetype":"venue"
},
  "geometry": {"coordinates":[-85.385613,40.191022],"type":"Point"}
}