{
  "type": "Feature",
  "properties": {
    "iso:country":"US",
    "sg:address":"4977 N 350 E",
    "sg:city":"Anderson",
    "sg:classifiers":[
        {
            "category":"Building & Trades",
            "subcategory":"Construction",
            "type":"Services"
        }
    ],
    "sg:phone":"+1 765 521 4111",
    "sg:postcode":"46012",
    "sg:province":"IN",
    "sg:tags":[
        "water",
        "well",
        "drilling"
    ],
    "wof:name":"Findlay Well & Pump Svc",
    "wof:placetype":"venue"
},
  "geometry": {"coordinates":[-85.61055,40.178272],"type":"Point"}
}