{
  "type": "Feature",
  "properties": {
    "iso:country":"US",
    "sg:address":"8311 W 10th St",
    "sg:city":"Indianapolis",
    "sg:classifiers":[
        {
            "category":"Professional",
            "subcategory":"Accounting & Tax Preparation",
            "type":"Services"
        }
    ],
    "sg:phone":"+1 317 271 1040",
    "sg:postcode":"46234",
    "sg:province":"IN",
    "sg:tags":[
        "accountant"
    ],
    "wof:name":"Mark E Rhodes CPA",
    "wof:placetype":"venue"
},
  "geometry": {"coordinates":[-86.303068,39.779016],"type":"Point"}
}