{
  "type": "Feature",
  "properties": {
    "iso:country":"US",
    "sg:address":"300 W Margaret Ave",
    "sg:city":"Terre Haute",
    "sg:classifiers":[
        {
            "category":"Wholesale",
            "subcategory":"Machinery & Supplies",
            "type":"Manufacturing & Wholesale Goods"
        }
    ],
    "sg:phone":"+1 812 234 2627",
    "sg:postcode":"47802",
    "sg:province":"IN",
    "sg:tags":[
        "farm",
        "equipment"
    ],
    "wof:name":"Minnis International Inc",
    "wof:placetype":"venue"
},
  "geometry": {"coordinates":[-87.42276099999999,39.433771],"type":"Point"}
}