{
  "type": "Feature",
  "properties": {
    "iso:country":"US",
    "sg:address":"2235 Concord Rd",
    "sg:city":"Lafayette",
    "sg:classifiers":[
        {
            "category":"Home & Garden",
            "subcategory":"Carpets & Floor Coverings",
            "type":"Retail Goods"
        }
    ],
    "sg:phone":"+1 765 477 7400",
    "sg:postcode":"47909",
    "sg:province":"IN",
    "sg:tags":[
        "dealer",
        "rug"
    ],
    "wof:name":"Reifers Rugs & Carpets",
    "wof:placetype":"venue"
},
  "geometry": {"coordinates":[-86.857302,40.392764],"type":"Point"}
}