{
  "type": "Feature",
  "properties": {
    "addr:full":"3516 N Clinton St Fort Wayne IN 46805",
    "addr:housenumber":"3516",
    "addr:postcode":"46805",
    "addr:street":"N Clinton St",
    "iso:country":"US",
    "sg:address":"3516 N Clinton St",
    "sg:city":"Fort Wayne",
    "sg:classifiers":[
        {
            "category":"Shopping",
            "subcategory":"Used Merchandise",
            "type":"Retail Goods"
        }
    ],
    "sg:phone":"+1 260 484 6686",
    "sg:postcode":"46805",
    "sg:province":"IN",
    "sg:tags":[
        "shop",
        "consignment"
    ],
    "wof:name":"Consignor Boutique Inc",
    "wof:placetype":"venue"
},
  "geometry": {"coordinates":[-85.13651,41.109075],"type":"Point"}
}