{
  "type": "Feature",
  "properties": {
    "iso:country":"US",
    "sg:address":"2109 W 57th St",
    "sg:city":"Hobart",
    "sg:classifiers":[
        {
            "category":"Education",
            "subcategory":"School",
            "type":"Public Place"
        }
    ],
    "sg:phone":"+1 219 947 7060",
    "sg:postcode":"46342",
    "sg:province":"IN",
    "wof:name":"Head Start Hobart",
    "wof:placetype":"venue"
},
  "geometry": {"coordinates":[-87.313147,41.514481],"type":"Point"}
}