{
  "type": "Feature",
  "properties": {
    "iso:country":"US",
    "sg:address":"2008 Washington Ave",
    "sg:city":"Evansville",
    "sg:classifiers":[
        {
            "category":"Restaurant",
            "type":"Food & Drink"
        }
    ],
    "sg:phone":"+1 812 473 8558",
    "sg:postcode":"47714",
    "sg:province":"IN",
    "wof:name":"Orient Express",
    "wof:placetype":"venue"
},
  "geometry": {"coordinates":[-87.528236,37.962778],"type":"Point"}
}