{
  "type": "Feature",
  "properties": {
    "iso:country":"US",
    "sg:address":"1825 W US Hwy 20",
    "sg:city":"Angola",
    "sg:classifiers":[
        {
            "category":"Shopping",
            "type":"Retail Goods"
        }
    ],
    "sg:phone":"+1 260 665 6663",
    "sg:postcode":"46703",
    "sg:province":"IN",
    "sg:tags":[
        "awning",
        "canopy"
    ],
    "wof:name":"Classic Sign & Awning",
    "wof:placetype":"venue"
},
  "geometry": {"coordinates":[-85.027911,41.634982],"type":"Point"}
}