{
  "type": "Feature",
  "properties": {
    "iso:country":"US",
    "sg:address":"980 Creekview Dr",
    "sg:city":"Columbus",
    "sg:classifiers":[
        {
            "category":"Health Services",
            "subcategory":"Health Practitioner",
            "type":"Services"
        }
    ],
    "sg:phone":"+1 812 372 7023",
    "sg:postcode":"47201",
    "sg:province":"IN",
    "sg:tags":[
        "therapist",
        "physical"
    ],
    "wof:name":"Physiotherapy Associates Inc",
    "wof:placetype":"venue"
},
  "geometry": {"coordinates":[-85.883191,39.208318],"type":"Point"}
}