{
  "type": "Feature",
  "properties": {
    "iso:country":"US",
    "sg:address":"1260 E North St",
    "sg:city":"Crown Point",
    "sg:classifiers":[
        {
            "category":"Restaurant",
            "type":"Food & Drink"
        }
    ],
    "sg:phone":"+1 219 662 3989",
    "sg:postcode":"46307",
    "sg:province":"IN",
    "sg:tags":[
        "caterer"
    ],
    "wof:name":"B J's Catering",
    "wof:placetype":"venue"
},
  "geometry": {"coordinates":[-87.348155,41.420275],"type":"Point"}
}