{
  "type": "Feature",
  "properties": {
    "addr:full":"301 S Beach Dr Monticello IN 47960",
    "addr:housenumber":"301",
    "addr:postcode":"47960",
    "addr:street":"S Beach Dr",
    "iso:country":"US",
    "sg:address":"301 S Beach Dr",
    "sg:city":"Monticello",
    "sg:classifiers":[
        {
            "category":"Organizations",
            "subcategory":"Religious Organization",
            "type":"Services"
        }
    ],
    "sg:phone":"+1 574 583 9004",
    "sg:postcode":"47960",
    "sg:province":"IN",
    "sg:tags":[
        "church"
    ],
    "wof:name":"Grace Community Baptist Church",
    "wof:placetype":"venue"
},
  "geometry": {"coordinates":[-86.76071,40.754039],"type":"Point"}
}