{
  "type": "Feature",
  "properties": {
    "iso:country":"US",
    "sg:address":"1445 Brookville Way Ste I",
    "sg:city":"Indianapolis",
    "sg:classifiers":[
        {
            "category":"Banks & Credit Unions",
            "subcategory":"Financial Services",
            "type":"Services"
        }
    ],
    "sg:phone":"+1 317 806 2166",
    "sg:postcode":"46239",
    "sg:province":"IN",
    "sg:tags":[
        "loan",
        "alternative",
        "financing"
    ],
    "wof:name":"Union Acceptance Company",
    "wof:placetype":"venue"
},
  "geometry": {"coordinates":[-86.044693,39.749843],"type":"Point"}
}