{
  "type": "Feature",
  "properties": {
    "iso:country":"US",
    "sg:address":"6884 W Oler Rd",
    "sg:city":"Williamsburg",
    "sg:classifiers":[
        {
            "category":"Building & Trades",
            "subcategory":"Construction",
            "type":"Services"
        }
    ],
    "sg:phone":"+1 765 489 6289",
    "sg:postcode":"47393",
    "sg:province":"IN",
    "sg:tags":[
        "contractor"
    ],
    "wof:name":"Eric Bales",
    "wof:placetype":"venue"
},
  "geometry": {"coordinates":[-85.005861,39.946963],"type":"Point"}
}