{
  "type": "Feature",
  "properties": {
    "iso:country":"US",
    "sg:address":"509 W Main St",
    "sg:city":"Bloomfield",
    "sg:classifiers":[
        {
            "category":"Food & Beverages",
            "subcategory":"Groceries & Convenience Stores",
            "type":"Retail Goods"
        }
    ],
    "sg:phone":"+1 812 384 4121",
    "sg:postcode":"47424",
    "sg:province":"IN",
    "wof:name":"Huck's & Godfather's Pizza",
    "wof:placetype":"venue"
},
  "geometry": {"coordinates":[-86.946113,39.02688],"type":"Point"}
}