{
  "type": "Feature",
  "properties": {
    "iso:country":"US",
    "sg:address":"3336 N Emerson Ave",
    "sg:city":"Indianapolis",
    "sg:classifiers":[
        {
            "category":"Personal",
            "subcategory":"Beauty Salon",
            "type":"Services"
        }
    ],
    "sg:phone":"+1 317 546 0477",
    "sg:postcode":"46218",
    "sg:province":"IN",
    "sg:tags":[
        "shop"
    ],
    "wof:name":"Alpha & Omega Hair Salon",
    "wof:placetype":"venue"
},
  "geometry": {"coordinates":[-86.083673,39.817701],"type":"Point"}
}