{
  "type": "Feature",
  "properties": {
    "iso:country":"US",
    "sg:address":"4030 Arba Pike",
    "sg:city":"Richmond",
    "sg:classifiers":[
        {
            "category":"Farming",
            "subcategory":"Nursery",
            "type":"Manufacturing & Wholesale Goods"
        }
    ],
    "sg:phone":"+1 765 935 3486",
    "sg:postcode":"47374",
    "sg:province":"IN",
    "sg:tags":[
        "greenhouse"
    ],
    "wof:name":"Jo's Greenhouses",
    "wof:placetype":"venue"
},
  "geometry": {"coordinates":[-84.888229,39.887763],"type":"Point"}
}