{
  "type": "Feature",
  "properties": {
    "iso:country":"US",
    "sg:address":"2301 W Christy Ln",
    "sg:city":"Muncie",
    "sg:classifiers":[
        {
            "category":"Shopping",
            "subcategory":"Clothing, Apparel, & Fashions",
            "type":"Retail Goods"
        }
    ],
    "sg:phone":"+1 765 289 8549",
    "sg:postcode":"47304",
    "sg:province":"IN",
    "wof:name":"Nikki Assmann",
    "wof:placetype":"venue"
},
  "geometry": {"coordinates":[-85.412055,40.22308],"type":"Point"}
}