{
  "type": "Feature",
  "properties": {
    "iso:country":"US",
    "sg:address":"5511 Epworth Rd",
    "sg:city":"Newburgh",
    "sg:classifiers":[
        {
            "category":"Insurance",
            "subcategory":"Insurance Agent",
            "type":"Services"
        }
    ],
    "sg:phone":"+1 812 842 2336",
    "sg:postcode":"47630",
    "sg:province":"IN",
    "wof:name":"Randy Beem Insurance",
    "wof:placetype":"venue"
},
  "geometry": {"coordinates":[-87.44152699999999,37.954296],"type":"Point"}
}