{
  "type": "Feature",
  "properties": {
    "iso:country":"US",
    "sg:address":"208 Wells St",
    "sg:city":"Rockville",
    "sg:classifiers":[
        {
            "category":"Shopping",
            "type":"Retail Goods"
        }
    ],
    "sg:phone":"+1 765 569 5711",
    "sg:postcode":"47872",
    "sg:province":"IN",
    "sg:tags":[
        "monument"
    ],
    "wof:name":"Park County Monuments",
    "wof:placetype":"venue"
},
  "geometry": {"coordinates":[-87.218659,39.760689],"type":"Point"}
}