{
  "type": "Feature",
  "properties": {
    "iso:country":"US",
    "sg:address":"14 David Ln",
    "sg:city":"Indianapolis",
    "sg:classifiers":[
        {
            "category":"Banks & Credit Unions",
            "subcategory":"Investment Brokerage",
            "type":"Services"
        }
    ],
    "sg:phone":"+1 317 887 6660",
    "sg:postcode":"46227",
    "sg:province":"IN",
    "sg:tags":[
        "consultant",
        "planning",
        "financial"
    ],
    "wof:name":"Reainco Development Corp",
    "wof:placetype":"venue"
},
  "geometry": {"coordinates":[-86.14920499999999,39.641212],"type":"Point"}
}