{
  "type": "Feature",
  "properties": {
    "iso:country":"US",
    "sg:address":"6466 E 82nd St",
    "sg:city":"Indianapolis",
    "sg:classifiers":[
        {
            "category":"Bars & Pubs",
            "type":"Food & Drink"
        },
        {
            "category":"Restaurant",
            "type":"Food & Drink"
        }
    ],
    "sg:phone":"+1 317 849 2739",
    "sg:postcode":"46250",
    "sg:province":"IN",
    "sg:tags":[
        "traditional",
        "american"
    ],
    "sg:website":"www.beersellar.net",
    "wof:name":"The Beer Sellar",
    "wof:placetype":"venue"
},
  "geometry": {"coordinates":[-86.055508,39.905382],"type":"Point"}
}