{
  "type": "Feature",
  "properties": {
    "iso:country":"US",
    "sg:address":"300 W Lincoln Hwy",
    "sg:city":"Schererville",
    "sg:classifiers":[
        {
            "category":"Recreation",
            "type":"Entertainment"
        }
    ],
    "sg:phone":"+1 219 865 5444",
    "sg:postcode":"46375",
    "sg:province":"IN",
    "sg:tags":[
        "martial",
        "arts",
        "instruction"
    ],
    "wof:name":"Kwak's TAEKWONDO-Kta",
    "wof:placetype":"venue"
},
  "geometry": {"coordinates":[-87.440436,41.483256],"type":"Point"}
}