{
  "type": "Feature",
  "properties": {
    "iso:country":"US",
    "sg:address":"160 W Carmel Dr",
    "sg:city":"Carmel",
    "sg:classifiers":[
        {
            "category":"Professional",
            "subcategory":"Lawyer & Legal Services",
            "type":"Services"
        }
    ],
    "sg:phone":"+1 317 844 2936",
    "sg:postcode":"46032",
    "sg:province":"IN",
    "wof:name":"Christine Altman",
    "wof:placetype":"venue"
},
  "geometry": {"coordinates":[-86.130302,39.961498],"type":"Point"}
}