{
  "type": "Feature",
  "properties": {
    "iso:country":"US",
    "sg:address":"525 E 7th St",
    "sg:city":"Rushville",
    "sg:classifiers":[
        {
            "category":"Social Services",
            "type":"Services"
        }
    ],
    "sg:phone":"+1 765 932 2863",
    "sg:postcode":"46173",
    "sg:province":"IN",
    "sg:tags":[
        "organization",
        "welfare"
    ],
    "wof:name":"Inter Local Community Action",
    "wof:placetype":"venue"
},
  "geometry": {"coordinates":[-85.437787,39.614294],"type":"Point"}
}