{
  "type": "Feature",
  "properties": {
    "iso:country":"US",
    "sg:address":"515 S 2nd St",
    "sg:city":"Elkhart",
    "sg:classifiers":[
        {
            "category":"Health Services",
            "subcategory":"Doctor",
            "type":"Services"
        }
    ],
    "sg:phone":"+1 574 295 4141",
    "sg:postcode":"46516",
    "sg:province":"IN",
    "sg:tags":[
        "physician",
        "surgeon"
    ],
    "wof:name":"Jeffrey A Mark MD",
    "wof:placetype":"venue"
},
  "geometry": {"coordinates":[-85.97270899999999,41.682304],"type":"Point"}
}