{
  "type": "Feature",
  "properties": {
    "iso:country":"US",
    "sg:address":"8493 W 600 S",
    "sg:city":"Chalmers",
    "sg:classifiers":[
        {
            "category":"Manufacturing",
            "subcategory":"Buildings",
            "type":"Manufacturing & Wholesale Goods"
        }
    ],
    "sg:phone":"+1 219 279 3101",
    "sg:postcode":"47929",
    "sg:province":"IN",
    "sg:tags":[
        "home",
        "log",
        "cabin"
    ],
    "wof:name":"Jim Barna Log Systems Midwest",
    "wof:placetype":"venue"
},
  "geometry": {"coordinates":[-87.023342,40.663127],"type":"Point"}
}