{
  "type": "Feature",
  "properties": {
    "iso:country":"US",
    "sg:address":"12211 State Rd 101",
    "sg:city":"Sunman",
    "sg:classifiers":[
        {
            "category":"Farming",
            "subcategory":"Farm",
            "type":"Manufacturing & Wholesale Goods"
        }
    ],
    "sg:phone":"+1 812 623 5098",
    "sg:postcode":"47041",
    "sg:province":"IN",
    "sg:tags":[
        "crop",
        "general"
    ],
    "wof:name":"Eugene Freyer",
    "wof:placetype":"venue"
},
  "geometry": {"coordinates":[-85.09452899999999,39.255674],"type":"Point"}
}