{
  "type": "Feature",
  "properties": {
    "iso:country":"US",
    "sg:address":"3801 Coldwater Rd",
    "sg:city":"Fort Wayne",
    "sg:classifiers":[
        {
            "category":"Shopping",
            "subcategory":"Department Store",
            "type":"Retail Goods"
        }
    ],
    "sg:phone":"+1 260 484 9591",
    "sg:postcode":"46805",
    "sg:province":"IN",
    "sg:website":"www.target.com",
    "wof:name":"Target",
    "wof:placetype":"venue"
},
  "geometry": {"coordinates":[-85.135092,41.111358],"type":"Point"}
}