{
  "type": "Feature",
  "properties": {
    "iso:country":"US",
    "sg:address":"230 Bellemeade Ave",
    "sg:city":"Evansville",
    "sg:classifiers":[
        {
            "category":"Health Services",
            "subcategory":"Doctor",
            "type":"Services"
        }
    ],
    "sg:phone":"+1 812 425 4111",
    "sg:postcode":"47713",
    "sg:province":"IN",
    "sg:tags":[
        "clinic"
    ],
    "wof:name":"Ohio Valley Dialysis",
    "wof:placetype":"venue"
},
  "geometry": {"coordinates":[-87.561969,37.968563],"type":"Point"}
}