{
  "type": "Feature",
  "properties": {
    "iso:country":"US",
    "sg:address":"44 W 80th Pl",
    "sg:city":"Merrillville",
    "sg:classifiers":[
        {
            "category":"Restaurant",
            "type":"Food & Drink"
        }
    ],
    "sg:phone":"+1 219 736 7784",
    "sg:postcode":"46410",
    "sg:province":"IN",
    "wof:name":"Balkan Restaurant",
    "wof:placetype":"venue"
},
  "geometry": {"coordinates":[-87.33627199999999,41.473368],"type":"Point"}
}