{
  "type": "Feature",
  "properties": {
    "iso:country":"US",
    "sg:address":"650 N 175 W",
    "sg:city":"Valparaiso",
    "sg:classifiers":[
        {
            "category":"Travel",
            "subcategory":"Campground",
            "type":"Entertainment"
        }
    ],
    "sg:phone":"+1 219 462 5736",
    "sg:postcode":"46385",
    "sg:province":"IN",
    "sg:tags":[
        "camp"
    ],
    "wof:name":"Camp Butternut Springs Girl",
    "wof:placetype":"venue"
},
  "geometry": {"coordinates":[-87.099901,41.528894],"type":"Point"}
}