{
  "type": "Feature",
  "properties": {
    "iso:country":"US",
    "sg:address":"1310 W Monon Dr",
    "sg:city":"Bloomington",
    "sg:classifiers":[
        {
            "category":"Wholesale",
            "subcategory":"Groceries",
            "type":"Manufacturing & Wholesale Goods"
        }
    ],
    "sg:phone":"+1 812 336 5192",
    "sg:postcode":"47403",
    "sg:province":"IN",
    "sg:tags":[
        "tea",
        "coffee"
    ],
    "wof:name":"Partridge & Quigley Coffee",
    "wof:placetype":"venue"
},
  "geometry": {"coordinates":[-86.534123,39.152242],"type":"Point"}
}