{
  "type": "Feature",
  "properties": {
    "addr:full":"102 S Main St Advance IN 46102",
    "addr:housenumber":"102",
    "addr:postcode":"46102",
    "addr:street":"S Main St",
    "iso:country":"US",
    "sg:address":"102 S Main St",
    "sg:city":"Advance",
    "sg:classifiers":[
        {
            "category":"Personal",
            "subcategory":"Beauty Salon",
            "type":"Services"
        }
    ],
    "sg:phone":"+1 765 676 6604",
    "sg:postcode":"46102",
    "sg:province":"IN",
    "wof:name":"Kitty's House Of Glamour",
    "wof:placetype":"venue"
},
  "geometry": {"coordinates":[-86.619775,39.995687],"type":"Point"}
}