{
  "type": "Feature",
  "properties": {
    "addr:full":"7254 E 86th St Indianapolis IN 46250",
    "addr:housenumber":"7254",
    "addr:postcode":"46250",
    "addr:street":"E 86Th St",
    "iso:country":"US",
    "sg:address":"7254 E 86th St",
    "sg:city":"Indianapolis",
    "sg:classifiers":[
        {
            "category":"Structure",
            "subcategory":"Warehouse",
            "type":"Public Place"
        },
        {
            "category":"Retail",
            "subcategory":"Storage",
            "type":"Services"
        },
        {
            "category":"Home & Garden",
            "subcategory":"Furniture",
            "type":"Retail Goods"
        }
    ],
    "sg:phone":"+1 317 578 2990",
    "sg:postcode":"46250",
    "sg:province":"IN",
    "sg:tags":[
        "self",
        "warehouses-merchandise",
        "store"
    ],
    "wof:name":"Copper Creek Canyon Warehouse",
    "wof:placetype":"venue"
},
  "geometry": {"coordinates":[-86.041518,39.912629],"type":"Point"}
}