{
  "type": "Feature",
  "properties": {
    "iso:country":"US",
    "sg:address":"120 N Main St",
    "sg:city":"Owensville",
    "sg:classifiers":[
        {
            "category":"Organizations",
            "subcategory":"Religious Organization",
            "type":"Services"
        }
    ],
    "sg:phone":"+1 812 724 4114",
    "sg:postcode":"47665",
    "sg:province":"IN",
    "sg:tags":[
        "church"
    ],
    "wof:name":"Dayspring Community Church",
    "wof:placetype":"venue"
},
  "geometry": {"coordinates":[-87.691462,38.273188],"type":"Point"}
}