{
  "type": "Feature",
  "properties": {
    "iso:country":"US",
    "sg:address":"701 S Main St",
    "sg:city":"Kokomo",
    "sg:classifiers":[
        {
            "category":"Building & Trades",
            "subcategory":"Plumbing",
            "type":"Services"
        }
    ],
    "sg:phone":"+1 765 452 6869",
    "sg:postcode":"46901",
    "sg:province":"IN",
    "sg:tags":[
        "conditioning",
        "air",
        "system",
        "contractor"
    ],
    "wof:name":"Duncan Service Co",
    "wof:placetype":"venue"
},
  "geometry": {"coordinates":[-86.131167,40.479651],"type":"Point"}
}