{
  "type": "Feature",
  "properties": {
    "iso:country":"US",
    "sg:address":"2004 N Apperson Way",
    "sg:city":"Kokomo",
    "sg:classifiers":[
        {
            "category":"Shopping",
            "subcategory":"Department Store",
            "type":"Retail Goods"
        }
    ],
    "sg:phone":"+1 765 457 6056",
    "sg:postcode":"46901",
    "sg:province":"IN",
    "sg:tags":[
        "shop"
    ],
    "wof:name":"Dollar General",
    "wof:placetype":"venue"
},
  "geometry": {"coordinates":[-86.126796,40.504506],"type":"Point"}
}