{
  "type": "Feature",
  "properties": {
    "iso:country":"US",
    "sg:address":"6797 Park Elwood Rd",
    "sg:city":"Richmond",
    "sg:classifiers":[
        {
            "category":"Farming",
            "subcategory":"Dairy Farm",
            "type":"Manufacturing & Wholesale Goods"
        }
    ],
    "sg:phone":"+1 765 847 2667",
    "sg:postcode":"47374",
    "sg:province":"IN",
    "wof:name":"Sarah Beck",
    "wof:placetype":"venue"
},
  "geometry": {"coordinates":[-84.847634,39.926534],"type":"Point"}
}