{
  "type": "Feature",
  "properties": {
    "iso:country":"US",
    "sg:address":"220 N Harrison St",
    "sg:city":"Russellville",
    "sg:classifiers":[
        {
            "category":"Banks & Credit Unions",
            "subcategory":"Bank",
            "type":"Services"
        }
    ],
    "sg:phone":"+1 765 435 2620",
    "sg:postcode":"46175",
    "sg:province":"IN",
    "wof:name":"Tri-County Bank & Trust",
    "wof:placetype":"venue"
},
  "geometry": {"coordinates":[-86.98378200000001,39.858087],"type":"Point"}
}