{
  "type": "Feature",
  "properties": {
    "iso:country":"US",
    "sg:address":"750 S Walker St",
    "sg:city":"Bloomington",
    "sg:classifiers":[
        {
            "category":"Building & Trades",
            "subcategory":"Cleaning & Sanitation",
            "type":"Services"
        }
    ],
    "sg:phone":"+1 812 334 1407",
    "sg:postcode":"47403",
    "sg:province":"IN",
    "sg:tags":[
        "janitor"
    ],
    "wof:name":"Krystalz Cleaning Svc",
    "wof:placetype":"venue"
},
  "geometry": {"coordinates":[-86.546077,39.159119],"type":"Point"}
}