{
  "type": "Feature",
  "properties": {
    "iso:country":"US",
    "sg:address":"212 N Water St",
    "sg:city":"Salem",
    "sg:classifiers":[
        {
            "category":"Professional",
            "subcategory":"Lawyer & Legal Services",
            "type":"Services"
        }
    ],
    "sg:phone":"+1 812 896 0044",
    "sg:postcode":"47167",
    "sg:province":"IN",
    "sg:tags":[
        "attorney"
    ],
    "wof:name":"Houchin Law Office",
    "wof:placetype":"venue"
},
  "geometry": {"coordinates":[-86.102172,38.607625],"type":"Point"}
}