{
  "type": "Feature",
  "properties": {
    "iso:country":"US",
    "sg:address":"15 W North St",
    "sg:city":"Remington",
    "sg:classifiers":[
        {
            "category":"Shopping",
            "subcategory":"Florist",
            "type":"Retail Goods"
        }
    ],
    "sg:phone":"+1 219 261 2561",
    "sg:postcode":"47977",
    "sg:province":"IN",
    "wof:name":"Blossom Boutique",
    "wof:placetype":"venue"
},
  "geometry": {"coordinates":[-87.152204,40.761385],"type":"Point"}
}