{
  "type": "Feature",
  "properties": {
    "iso:country":"US",
    "sg:address":"1902 US Hwy 40 Scn",
    "sg:city":"Clayton",
    "sg:classifiers":[
        {
            "category":"Recreation",
            "type":"Entertainment"
        }
    ],
    "sg:phone":"+1 317 539 4839",
    "sg:postcode":"46118",
    "sg:province":"IN",
    "wof:name":"Plainfield Karate",
    "wof:placetype":"venue"
},
  "geometry": {"coordinates":[-86.485677,39.678127],"type":"Point"}
}