{
  "type": "Feature",
  "properties": {
    "iso:country":"US",
    "sg:address":"109 S Allen Chapel Rd",
    "sg:city":"Kendallville",
    "sg:classifiers":[
        {
            "category":"Wholesale",
            "subcategory":"Electrical",
            "type":"Manufacturing & Wholesale Goods"
        }
    ],
    "sg:phone":"+1 260 347 3190",
    "sg:postcode":"46755",
    "sg:province":"IN",
    "sg:tags":[
        "equipment",
        "electric",
        "supply"
    ],
    "wof:name":"Kendall Electric Inc",
    "wof:placetype":"venue"
},
  "geometry": {"coordinates":[-85.23172700000001,41.444736],"type":"Point"}
}