{
  "type": "Feature",
  "properties": {
    "addr:full":"1106 E Winona Ave Warsaw IN 46580",
    "addr:housenumber":"1106 e",
    "addr:postcode":"46580",
    "addr:street":"Winona Ave",
    "iso:country":"US",
    "sg:address":"1106 E Winona Ave",
    "sg:city":"Warsaw",
    "sg:classifiers":[
        {
            "category":"Restaurant",
            "type":"Food & Drink"
        }
    ],
    "sg:phone":"+1 574 268 5300",
    "sg:postcode":"46580",
    "sg:province":"IN",
    "sg:tags":[
        "eating"
    ],
    "wof:name":"Jr S Sandwiches",
    "wof:placetype":"venue"
},
  "geometry": {"coordinates":[-85.841493,41.235352],"type":"Point"}
}