{
  "type": "Feature",
  "properties": {
    "iso:country":"US",
    "sg:address":"122 N Main St",
    "sg:city":"Tipton",
    "sg:classifiers":[
        {
            "category":"Organizations",
            "subcategory":"Professional Association",
            "type":"Services"
        }
    ],
    "sg:phone":"+1 765 675 2345",
    "sg:postcode":"46072",
    "sg:province":"IN",
    "wof:name":"Masonic Lodge",
    "wof:placetype":"venue"
},
  "geometry": {"coordinates":[-86.041327,40.283257],"type":"Point"}
}