{
  "type": "Feature",
  "properties": {
    "iso:country":"US",
    "sg:address":"3101 New Haven Ave",
    "sg:city":"Fort Wayne",
    "sg:classifiers":[
        {
            "category":"Manufacturing",
            "subcategory":"Tools & Machinery",
            "type":"Manufacturing & Wholesale Goods"
        }
    ],
    "sg:phone":"+1 260 424 0405",
    "sg:postcode":"46803",
    "sg:province":"IN",
    "sg:tags":[
        "contractor"
    ],
    "sg:website":"www.hmc-us.com",
    "wof:name":"Hercules Machinery Corp",
    "wof:placetype":"venue"
},
  "geometry": {"coordinates":[-85.09701,41.068723],"type":"Point"}
}