{
  "type": "Feature",
  "properties": {
    "iso:country":"US",
    "sg:address":"9364 N Hummel Dr",
    "sg:city":"Mooresville",
    "sg:classifiers":[
        {
            "category":"Building & Trades",
            "subcategory":"Construction",
            "type":"Services"
        }
    ],
    "sg:phone":"+1 317 996 6123",
    "sg:postcode":"46158",
    "sg:province":"IN",
    "sg:tags":[
        "excavation",
        "contractor"
    ],
    "wof:name":"Juan B Hummel Excavating",
    "wof:placetype":"venue"
},
  "geometry": {"coordinates":[-86.426051,39.562881],"type":"Point"}
}