{
  "type": "Feature",
  "properties": {
    "iso:country":"US",
    "sg:address":"425 N Main St",
    "sg:city":"Princeton",
    "sg:classifiers":[
        {
            "category":"Government",
            "subcategory":"Office",
            "type":"Public Place"
        }
    ],
    "sg:phone":"+1 812 385 1227",
    "sg:postcode":"47670",
    "sg:province":"IN",
    "wof:name":"Coroner's Office",
    "wof:placetype":"venue"
},
  "geometry": {"coordinates":[-87.567572,38.358382],"type":"Point"}
}