{
  "type": "Feature",
  "properties": {
    "addr:full":"521 Ralston St Gary IN 46406",
    "addr:housenumber":"521",
    "addr:postcode":"46406",
    "addr:street":"Ralston St Gary",
    "iso:country":"US",
    "sg:address":"521 Ralston St",
    "sg:city":"Gary",
    "sg:classifiers":[
        {
            "category":"Organizations",
            "subcategory":"Religious Organization",
            "type":"Services"
        }
    ],
    "sg:phone":"+1 219 949 0877",
    "sg:postcode":"46406",
    "sg:province":"IN",
    "wof:name":"Angel Fith Mssnary Bptst Chrch",
    "wof:placetype":"venue"
},
  "geometry": {"coordinates":[-87.402272,41.601662],"type":"Point"}
}