{
  "type": "Feature",
  "properties": {
    "iso:country":"US",
    "sg:address":"915 E Walnut St",
    "sg:city":"Lebanon",
    "sg:classifiers":[
        {
            "category":"Autos & Motor Vehicles",
            "subcategory":"Automobile Sales",
            "type":"Retail Goods"
        }
    ],
    "sg:phone":"+1 765 482 1846",
    "sg:postcode":"46052",
    "sg:province":"IN",
    "sg:tags":[
        "car",
        "dealer"
    ],
    "wof:name":"Barney's Auto Sales",
    "wof:placetype":"venue"
},
  "geometry": {"coordinates":[-86.458871,40.039918],"type":"Point"}
}