{
  "type": "Feature",
  "properties": {
    "iso:country":"US",
    "sg:address":"1029 Washington St",
    "sg:city":"Columbus",
    "sg:classifiers":[
        {
            "category":"Retail",
            "subcategory":"Funeral Services",
            "type":"Services"
        }
    ],
    "sg:phone":"+1 812 372 2515",
    "sg:postcode":"47201",
    "sg:province":"IN",
    "sg:tags":[
        "director"
    ],
    "wof:name":"Barkes Inlow & Weaver Funeral",
    "wof:placetype":"venue"
},
  "geometry": {"coordinates":[-85.921354,39.209041],"type":"Point"}
}