{
  "type": "Feature",
  "properties": {
    "iso:country":"US",
    "sg:address":"821 S E St",
    "sg:city":"Richmond",
    "sg:classifiers":[
        {
            "category":"Education",
            "subcategory":"School",
            "type":"Public Place"
        }
    ],
    "sg:phone":"+1 765 935 9159",
    "sg:postcode":"47374",
    "sg:province":"IN",
    "sg:tags":[
        "academic",
        "special"
    ],
    "wof:name":"Shooting Stars Lrnng Ctr",
    "wof:placetype":"venue"
},
  "geometry": {"coordinates":[-84.892352,39.821585],"type":"Point"}
}