{
  "type": "Feature",
  "properties": {
    "iso:country":"US",
    "sg:address":"2801 S Madison St",
    "sg:city":"Muncie",
    "sg:classifiers":[
        {
            "category":"Bars & Pubs",
            "type":"Food & Drink"
        },
        {
            "category":"Restaurant",
            "type":"Food & Drink"
        }
    ],
    "sg:phone":"+1 765 284 7730",
    "sg:postcode":"47302",
    "sg:province":"IN",
    "sg:tags":[
        "tavern",
        "grill",
        "brew"
    ],
    "wof:name":"Stag Bar",
    "wof:placetype":"venue"
},
  "geometry": {"coordinates":[-85.381653,40.169312],"type":"Point"}
}