{
  "type": "Feature",
  "properties": {
    "iso:country":"US",
    "sg:address":"63469 Co Rd 33",
    "sg:city":"Goshen",
    "sg:classifiers":[
        {
            "category":"Travel",
            "subcategory":"Hotels & Motels",
            "type":"Entertainment"
        }
    ],
    "sg:phone":"+1 574 642 3222",
    "sg:postcode":"46528",
    "sg:province":"IN",
    "sg:tags":[
        "breakfast",
        "accommodation",
        "bed"
    ],
    "wof:name":"Ol' Barn Bed & Breakfast",
    "wof:placetype":"venue"
},
  "geometry": {"coordinates":[-85.752146,41.576159],"type":"Point"}
}