{
  "type": "Feature",
  "properties": {
    "iso:country":"US",
    "sg:address":"4717 W 30th St",
    "sg:city":"Indianapolis",
    "sg:classifiers":[
        {
            "category":"Autos & Motor Vehicles",
            "subcategory":"Automobile Sales",
            "type":"Retail Goods"
        }
    ],
    "sg:phone":"+1 317 293 3093",
    "sg:postcode":"46222",
    "sg:province":"IN",
    "sg:tags":[
        "car",
        "dealer"
    ],
    "wof:name":"Gutierrez Auto Sales",
    "wof:placetype":"venue"
},
  "geometry": {"coordinates":[-86.238566,39.809307],"type":"Point"}
}