{
  "type": "Feature",
  "properties": {
    "iso:country":"US",
    "sg:address":"209 W Ohio St",
    "sg:city":"Kendallville",
    "sg:classifiers":[
        {
            "category":"Manufacturing",
            "subcategory":"Metals",
            "type":"Manufacturing & Wholesale Goods"
        }
    ],
    "sg:phone":"+1 260 347 1768",
    "sg:postcode":"46755",
    "sg:province":"IN",
    "sg:tags":[
        "brass",
        "foundry",
        "bronze"
    ],
    "sg:website":"www.mahoneyfoundries.com",
    "wof:name":"Mahoney Foundries Inc",
    "wof:placetype":"venue"
},
  "geometry": {"coordinates":[-85.26681,41.43269],"type":"Point"}
}