{
  "type": "Feature",
  "properties": {
    "iso:country":"US",
    "sg:address":"202 S 5th St",
    "sg:city":"Goshen",
    "sg:classifiers":[
        {
            "category":"Government",
            "subcategory":"Office",
            "type":"Public Place"
        }
    ],
    "sg:phone":"+1 574 533 9399",
    "sg:postcode":"46528",
    "sg:province":"IN",
    "sg:tags":[
        "village"
    ],
    "wof:name":"Goshen Sewer Dept",
    "wof:placetype":"venue"
},
  "geometry": {"coordinates":[-85.832892,41.584408],"type":"Point"}
}