{
  "type": "Feature",
  "properties": {
    "iso:country":"US",
    "sg:address":"1118 Eastern Blvd",
    "sg:city":"Clarksville",
    "sg:classifiers":[
        {
            "category":"Health Services",
            "subcategory":"Chiropractor",
            "type":"Services"
        }
    ],
    "sg:phone":"+1 812 280 8188",
    "sg:postcode":"47129",
    "sg:province":"IN",
    "wof:name":"Family Care Chiropractic",
    "wof:placetype":"venue"
},
  "geometry": {"coordinates":[-85.766406,38.305018],"type":"Point"}
}