{
  "type": "Feature",
  "properties": {
    "iso:country":"US",
    "sg:address":"3655 S 50 E",
    "sg:city":"Lebanon",
    "sg:classifiers":[
        {
            "category":"Building & Trades",
            "subcategory":"Construction",
            "type":"Services"
        }
    ],
    "sg:phone":"+1 765 483 1419",
    "sg:postcode":"46052",
    "sg:province":"IN",
    "sg:tags":[
        "wallcoverings-installation",
        "wallpaper",
        "painting",
        "contractor"
    ],
    "wof:name":"Chuck Suttle Painting",
    "wof:placetype":"venue"
},
  "geometry": {"coordinates":[-86.460441,39.987862],"type":"Point"}
}