{
  "type": "Feature",
  "properties": {
    "addr:full":"2452 W Kem Rd Marion IN 46952",
    "addr:housenumber":"2452",
    "addr:postcode":"46952",
    "addr:street":"W Kem Rd",
    "iso:country":"US",
    "sg:address":"2452 W Kem Rd",
    "sg:city":"Marion",
    "sg:classifiers":[
        {
            "category":"Social Services",
            "subcategory":"Adult Care",
            "type":"Services"
        }
    ],
    "sg:phone":"+1 765 384 4500",
    "sg:postcode":"46952",
    "sg:province":"IN",
    "sg:tags":[
        "home",
        "residential"
    ],
    "wof:name":"Alterra Sterling House",
    "wof:placetype":"venue"
},
  "geometry": {"coordinates":[-85.697143,40.574589],"type":"Point"}
}