{
  "type": "Feature",
  "properties": {
    "iso:country":"US",
    "sg:address":"122 E Cherry St",
    "sg:city":"Chandler",
    "sg:classifiers":[
        {
            "category":"Organizations",
            "subcategory":"Religious Organization",
            "type":"Services"
        }
    ],
    "sg:phone":"+1 812 925 6475",
    "sg:postcode":"47610",
    "sg:province":"IN",
    "sg:tags":[
        "clergy"
    ],
    "wof:name":"Dan Gross",
    "wof:placetype":"venue"
},
  "geometry": {"coordinates":[-87.36642999999999,38.039416],"type":"Point"}
}