{
  "type": "Feature",
  "properties": {
    "iso:country":"US",
    "sg:address":"101 W 30th St",
    "sg:city":"Connersville",
    "sg:classifiers":[
        {
            "category":"Retail",
            "subcategory":"Auto Rental",
            "type":"Services"
        }
    ],
    "sg:phone":"+1 765 827 6000",
    "sg:postcode":"47331",
    "sg:province":"IN",
    "sg:tags":[
        "renting",
        "automobile"
    ],
    "wof:name":"Groce Auto Rentals",
    "wof:placetype":"venue"
},
  "geometry": {"coordinates":[-85.129892,39.6716],"type":"Point"}
}