{
  "type": "Feature",
  "properties": {
    "addr:full":"144 Knox Dr West Lafayette IN 47906",
    "addr:housenumber":"144",
    "addr:postcode":"47906",
    "addr:street":"Knox Dr",
    "iso:country":"US",
    "sg:address":"144 Knox Dr",
    "sg:city":"West Lafayette",
    "sg:classifiers":[
        {
            "category":"Farming",
            "subcategory":"Farm",
            "type":"Manufacturing & Wholesale Goods"
        }
    ],
    "sg:phone":"+1 765 463 5014",
    "sg:postcode":"47906",
    "sg:province":"IN",
    "sg:tags":[
        "crop",
        "general"
    ],
    "wof:name":"Norma Scheufler",
    "wof:placetype":"venue"
},
  "geometry": {"coordinates":[-86.903521,40.451274],"type":"Point"}
}