{
  "type": "Feature",
  "properties": {
    "iso:country":"US",
    "sg:address":"728 8th St SE",
    "sg:city":"Demotte",
    "sg:classifiers":[
        {
            "category":"Shopping",
            "type":"Retail Goods"
        }
    ],
    "sg:phone":"+1 219 987 4213",
    "sg:postcode":"46310",
    "sg:province":"IN",
    "sg:tags":[
        "installs",
        "suppl",
        "pool",
        "swimming"
    ],
    "sg:website":"www.bfpools.com",
    "wof:name":"B & F Pools Inc",
    "wof:placetype":"venue"
},
  "geometry": {"coordinates":[-87.189918,41.195482],"type":"Point"}
}