{
  "type": "Feature",
  "properties": {
    "iso:country":"US",
    "sg:address":"3344 Beech Pl",
    "sg:city":"Carmel",
    "sg:classifiers":[
        {
            "category":"Personal",
            "subcategory":"Beauty Salon",
            "type":"Services"
        },
        {
            "category":"Personal",
            "subcategory":"Skin Care",
            "type":"Services"
        }
    ],
    "sg:phone":"+1 317 875 5998",
    "sg:postcode":"46032",
    "sg:province":"IN",
    "sg:tags":[
        "cosmetologist",
        "cosmetic"
    ],
    "wof:name":"Mardredan Design Group",
    "wof:placetype":"venue"
},
  "geometry": {"coordinates":[-86.219447,39.928522],"type":"Point"}
}