{
  "type": "Feature",
  "properties": {
    "iso:country":"US",
    "sg:address":"409 Southway Ct",
    "sg:city":"Bargersville",
    "sg:classifiers":[
        {
            "category":"Freight",
            "type":"Transportation"
        }
    ],
    "sg:phone":"+1 317 422 1336",
    "sg:postcode":"46106",
    "sg:province":"IN",
    "sg:tags":[
        "trucking"
    ],
    "wof:name":"ANE Trucking Inc",
    "wof:placetype":"venue"
},
  "geometry": {"coordinates":[-86.174791,39.520265],"type":"Point"}
}