{
  "type": "Feature",
  "properties": {
    "addr:full":"6481 Moser Knob Rd Floyds Knobs IN 47119",
    "addr:housenumber":"6481",
    "addr:postcode":"47119",
    "addr:street":"Moser Knob Rd",
    "iso:country":"US",
    "sg:address":"6481 Moser Knob Rd",
    "sg:city":"Floyds Knobs",
    "sg:classifiers":[
        {
            "category":"Home & Garden",
            "subcategory":"Carpets & Floor Coverings",
            "type":"Retail Goods"
        }
    ],
    "sg:phone":"+1 812 945 7906",
    "sg:postcode":"47119",
    "sg:province":"IN",
    "sg:tags":[
        "dealer",
        "rug"
    ],
    "wof:name":"Odell Andres & Sons Carpet Inc",
    "wof:placetype":"venue"
},
  "geometry": {"coordinates":[-85.83670499999999,38.356635],"type":"Point"}
}