{
  "type": "Feature",
  "properties": {
    "iso:country":"US",
    "sg:address":"6136 E Co Rd 400 N",
    "sg:city":"Greensburg",
    "sg:classifiers":[
        {
            "category":"Manufacturing",
            "subcategory":"Tools & Machinery",
            "type":"Manufacturing & Wholesale Goods"
        }
    ],
    "sg:phone":"+1 812 663 8737",
    "sg:postcode":"47240",
    "sg:province":"IN",
    "sg:tags":[
        "mfg"
    ],
    "wof:name":"Oasis Tool",
    "wof:placetype":"venue"
},
  "geometry": {"coordinates":[-85.36035,39.396671],"type":"Point"}
}