{
  "type": "Feature",
  "properties": {
    "addr:full":"5982 W Ridge Rd Gary IN 46408",
    "addr:housenumber":"5982",
    "addr:postcode":"46408",
    "addr:street":"W Ridge Rd",
    "iso:country":"US",
    "sg:address":"5982 W Ridge Rd",
    "sg:city":"Gary",
    "sg:classifiers":[
        {
            "category":"Shopping",
            "subcategory":"Discount & Variety Stores",
            "type":"Retail Goods"
        }
    ],
    "sg:phone":"+1 219 923 0821",
    "sg:postcode":"46408",
    "sg:province":"IN",
    "wof:name":"Indiana Dollar Plus Inc",
    "wof:placetype":"venue"
},
  "geometry": {"coordinates":[-87.411203,41.549458],"type":"Point"}
}