{
  "type": "Feature",
  "properties": {
    "iso:country":"US",
    "sg:address":"11333 Co Rd 2",
    "sg:city":"Middlebury",
    "sg:classifiers":[
        {
            "category":"Manufacturing",
            "subcategory":"Buildings",
            "type":"Manufacturing & Wholesale Goods"
        }
    ],
    "sg:phone":"+1 574 825 9999",
    "sg:postcode":"46540",
    "sg:province":"IN",
    "sg:tags":[
        "mobile",
        "home"
    ],
    "sg:website":"www.fourseasonshousing.com",
    "wof:name":"Four Seasons",
    "wof:placetype":"venue"
},
  "geometry": {"coordinates":[-85.688197,41.754931],"type":"Point"}
}