{
  "type": "Feature",
  "properties": {
    "iso:country":"US",
    "sg:address":"13301 State Rd 32",
    "sg:city":"Yorktown",
    "sg:classifiers":[
        {
            "category":"Professional",
            "subcategory":"Accounting & Tax Preparation",
            "type":"Services"
        }
    ],
    "sg:phone":"+1 765 759 5213",
    "sg:postcode":"47396",
    "sg:province":"IN",
    "sg:tags":[
        "bookkeeping",
        "general"
    ],
    "wof:name":"Yorktown Bookkeeping & Tax Svc",
    "wof:placetype":"venue"
},
  "geometry": {"coordinates":[-85.54267299999999,40.142699],"type":"Point"}
}