{
  "type": "Feature",
  "properties": {
    "addr:full":"2717 N 17th St Terre Haute IN 47804",
    "addr:housenumber":"2717",
    "addr:postcode":"47804",
    "addr:street":"N 17Th St",
    "iso:country":"US",
    "sg:address":"2717 N 17th St",
    "sg:city":"Terre Haute",
    "sg:classifiers":[
        {
            "category":"Shopping",
            "subcategory":"Gifts & Souvenirs",
            "type":"Retail Goods"
        }
    ],
    "sg:phone":"+1 812 553 0939",
    "sg:postcode":"47804",
    "sg:province":"IN",
    "sg:tags":[
        "wholesale",
        "catalog",
        "sales"
    ],
    "wof:name":"B&B Gift Solutions",
    "wof:placetype":"venue"
},
  "geometry": {"coordinates":[-87.38960899999999,39.500248],"type":"Point"}
}