{
  "type": "Feature",
  "properties": {
    "iso:country":"US",
    "sg:address":"277 Lansdowne Dr",
    "sg:city":"Noblesville",
    "sg:classifiers":[
        {
            "category":"Professional",
            "subcategory":"Research",
            "type":"Services"
        }
    ],
    "sg:phone":"+1 317 773 0098",
    "sg:postcode":"46060",
    "sg:province":"IN",
    "sg:tags":[
        "nonphysical",
        "commercial"
    ],
    "wof:name":"Sports Marketing Group Inc",
    "wof:placetype":"venue"
},
  "geometry": {"coordinates":[-86.000522,40.022554],"type":"Point"}
}