{
  "type": "Feature",
  "properties": {
    "iso:country":"US",
    "sg:address":"55130 Barksdale St",
    "sg:city":"Osceola",
    "sg:classifiers":[
        {
            "category":"Retail",
            "subcategory":"Portrait Studio",
            "type":"Services"
        }
    ],
    "sg:phone":"+1 574 651 2000",
    "sg:postcode":"46561",
    "sg:province":"IN",
    "sg:tags":[
        "photographer"
    ],
    "wof:name":"First Class Photo",
    "wof:placetype":"venue"
},
  "geometry": {"coordinates":[-86.086755,41.690304],"type":"Point"}
}