{
  "type": "Feature",
  "properties": {
    "iso:country":"US",
    "sg:address":"4225 E Morgan Ave",
    "sg:city":"Evansville",
    "sg:classifiers":[
        {
            "category":"Professional",
            "type":"Services"
        }
    ],
    "sg:phone":"+1 812 477 5354",
    "sg:postcode":"47715",
    "sg:province":"IN",
    "sg:tags":[
        "establishment"
    ],
    "wof:name":"King's Great Buys Plus",
    "wof:placetype":"venue"
},
  "geometry": {"coordinates":[-87.500142,37.991229],"type":"Point"}
}