{
  "type": "Feature",
  "properties": {
    "iso:country":"US",
    "sg:address":"2723 W 800 N",
    "sg:city":"Wawaka",
    "sg:classifiers":[
        {
            "category":"Personal",
            "subcategory":"Beauty Salon",
            "type":"Services"
        }
    ],
    "sg:phone":"+1 260 761 3410",
    "sg:postcode":"46794",
    "sg:province":"IN",
    "sg:tags":[
        "shop"
    ],
    "wof:name":"Artistic Cut Hair Salon",
    "wof:placetype":"venue"
},
  "geometry": {"coordinates":[-85.47561,41.467304],"type":"Point"}
}