{
  "type": "Feature",
  "properties": {
    "iso:country":"US",
    "sg:address":"7469 W Brownstown Rd",
    "sg:city":"Osgood",
    "sg:classifiers":[
        {
            "category":"Home & Garden",
            "subcategory":"Building Materials",
            "type":"Retail Goods"
        }
    ],
    "sg:phone":"+1 812 852 4570",
    "sg:postcode":"47037",
    "sg:province":"IN",
    "sg:tags":[
        "glass",
        "window",
        "plate"
    ],
    "wof:name":"Johnsons Complete Glass Svc",
    "wof:placetype":"venue"
},
  "geometry": {"coordinates":[-85.392994,39.193024],"type":"Point"}
}