{
  "type": "Feature",
  "properties": {
    "iso:country":"US",
    "sg:address":"1102 W 700 S",
    "sg:city":"Pendleton",
    "sg:classifiers":[
        {
            "category":"Organizations",
            "subcategory":"Religious Organization",
            "type":"Services"
        }
    ],
    "sg:phone":"+1 765 778 3166",
    "sg:postcode":"46064",
    "sg:province":"IN",
    "sg:tags":[
        "church"
    ],
    "wof:name":"Fall Creek Christian Church",
    "wof:placetype":"venue"
},
  "geometry": {"coordinates":[-85.693382,40.00387],"type":"Point"}
}