{
  "type": "Feature",
  "properties": {
    "iso:country":"US",
    "sg:address":"1001 Bomar Ln",
    "sg:city":"Greenwood",
    "sg:classifiers":[
        {
            "category":"Building & Trades",
            "subcategory":"Landscaping Services",
            "type":"Services"
        }
    ],
    "sg:phone":"+1 317 889 8625",
    "sg:postcode":"46142",
    "sg:province":"IN",
    "wof:name":"Midwest Tree Experts",
    "wof:placetype":"venue"
},
  "geometry": {"coordinates":[-86.147994,39.631328],"type":"Point"}
}