{
  "type": "Feature",
  "properties": {
    "iso:country":"US",
    "sg:address":"104 E Boehringer St",
    "sg:city":"Batesville",
    "sg:classifiers":[
        {
            "category":"Restaurant",
            "type":"Food & Drink"
        }
    ],
    "sg:phone":"+1 812 934 4004",
    "sg:postcode":"47006",
    "sg:province":"IN",
    "wof:name":"Pizza Haus Inc",
    "wof:placetype":"venue"
},
  "geometry": {"coordinates":[-85.221946,39.299263],"type":"Point"}
}