{
  "type": "Feature",
  "properties": {
    "addr:full":"2160 Arnold St Columbus IN 47203",
    "addr:housenumber":"2160",
    "addr:postcode":"47203",
    "addr:street":"Arnold St",
    "iso:country":"US",
    "sg:address":"2160 Arnold St",
    "sg:city":"Columbus",
    "sg:classifiers":[
        {
            "category":"Government",
            "subcategory":"Office",
            "type":"Public Place"
        }
    ],
    "sg:phone":"+1 812 378 1928",
    "sg:postcode":"47203",
    "sg:province":"IN",
    "sg:tags":[
        "federal",
        "security"
    ],
    "wof:name":"US Army National Guard",
    "wof:placetype":"venue"
},
  "geometry": {"coordinates":[-85.901511,39.253929],"type":"Point"}
}