{
  "type": "Feature",
  "properties": {
    "iso:country":"US",
    "sg:address":"946 Crown Ct",
    "sg:city":"Crown Point",
    "sg:classifiers":[
        {
            "category":"Health Services",
            "subcategory":"Doctor",
            "type":"Services"
        }
    ],
    "sg:phone":"+1 219 365 8533",
    "sg:postcode":"46307",
    "sg:province":"IN",
    "sg:tags":[
        "physician",
        "surgeon"
    ],
    "wof:name":"St John Health Ctr",
    "wof:placetype":"venue"
},
  "geometry": {"coordinates":[-87.353851,41.431279],"type":"Point"}
}