{
  "type": "Feature",
  "properties": {
    "iso:country":"US",
    "sg:address":"115 N Washington St",
    "sg:city":"Flora",
    "sg:classifiers":[
        {
            "category":"Social Services",
            "subcategory":"Child Care",
            "type":"Services"
        }
    ],
    "sg:phone":"+1 574 967 3509",
    "sg:postcode":"46929",
    "sg:province":"IN",
    "sg:tags":[
        "kindergarten",
        "academic",
        "school"
    ],
    "wof:name":"First Step Preschool",
    "wof:placetype":"venue"
},
  "geometry": {"coordinates":[-86.527305,40.549369],"type":"Point"}
}