{
  "type": "Feature",
  "properties": {
    "iso:country":"US",
    "sg:address":"6959 Hillsdale Ct",
    "sg:city":"Indianapolis",
    "sg:classifiers":[
        {
            "category":"Real Estate",
            "subcategory":"Real Estate Agent",
            "type":"Services"
        }
    ],
    "sg:phone":"+1 317 845 9511",
    "sg:postcode":"46250",
    "sg:province":"IN",
    "sg:website":"www.e-indyrealty.com",
    "wof:name":"Ken R Fisher & Assoc Realtors",
    "wof:placetype":"venue"
},
  "geometry": {"coordinates":[-86.04703,39.896089],"type":"Point"}
}