{
  "type": "Feature",
  "properties": {
    "iso:country":"US",
    "sg:address":"7016 Southeastern Ave",
    "sg:city":"Indianapolis",
    "sg:classifiers":[
        {
            "category":"Building & Trades",
            "subcategory":"Construction",
            "type":"Services"
        }
    ],
    "sg:phone":"+1 317 862 4444",
    "sg:postcode":"46239",
    "sg:province":"IN",
    "sg:tags":[
        "excavating",
        "contractor"
    ],
    "wof:name":"Walnut Acres",
    "wof:placetype":"venue"
},
  "geometry": {"coordinates":[-86.041174,39.722553],"type":"Point"}
}