{
  "type": "Feature",
  "properties": {
    "iso:country":"US",
    "sg:address":"1117 Prospect Dr",
    "sg:city":"Mishawaka",
    "sg:classifiers":[
        {
            "category":"Real Estate",
            "subcategory":"Real Estate Agent",
            "type":"Services"
        }
    ],
    "sg:phone":"+1 574 258 0218",
    "sg:postcode":"46544",
    "sg:province":"IN",
    "sg:tags":[
        "appraiser"
    ],
    "wof:name":"D L Carpenter Appraisers",
    "wof:placetype":"venue"
},
  "geometry": {"coordinates":[-86.162614,41.669337],"type":"Point"}
}