{
  "type": "Feature",
  "properties": {
    "iso:country":"US",
    "sg:address":"9665 S State Rd 15",
    "sg:city":"Silver Lake",
    "sg:classifiers":[
        {
            "category":"Restaurant",
            "type":"Food & Drink"
        }
    ],
    "sg:phone":"+1 260 352 2662",
    "sg:postcode":"46982",
    "sg:province":"IN",
    "wof:name":"Manns Kountry Kitchen",
    "wof:placetype":"venue"
},
  "geometry": {"coordinates":[-85.891689,41.091742],"type":"Point"}
}