{
  "type": "Feature",
  "properties": {
    "iso:country":"US",
    "sg:address":"2118 Pinehurst Dr",
    "sg:city":"Carmel",
    "sg:classifiers":[
        {
            "category":"Building & Trades",
            "subcategory":"Construction",
            "type":"Services"
        }
    ],
    "sg:phone":"+1 317 848 8947",
    "sg:postcode":"46032",
    "sg:province":"IN",
    "sg:tags":[
        "house"
    ],
    "wof:name":"Jerry Feldhake Inc",
    "wof:placetype":"venue"
},
  "geometry": {"coordinates":[-86.19953700000001,39.947776],"type":"Point"}
}