{
  "type": "Feature",
  "properties": {
    "addr:full":"5638 S US Hwy 421 Westville IN 46391",
    "addr:housenumber":"5638",
    "addr:postcode":"46391",
    "addr:street":"S Us Hwy 421",
    "iso:country":"US",
    "sg:address":"5638 S US Hwy 421",
    "sg:city":"Westville",
    "sg:classifiers":[
        {
            "category":"Home & Garden",
            "subcategory":"Building Materials",
            "type":"Retail Goods"
        }
    ],
    "sg:phone":"+1 219 785 2508",
    "sg:postcode":"46391",
    "sg:province":"IN",
    "sg:tags":[
        "mixed",
        "concrete"
    ],
    "wof:name":"Zimco Materials Inc",
    "wof:placetype":"venue"
},
  "geometry": {"coordinates":[-86.89563699999999,41.5287],"type":"Point"}
}