{
  "type": "Feature",
  "properties": {
    "iso:country":"US",
    "sg:address":"6021 Cadillac Dr",
    "sg:city":"Indianapolis",
    "sg:classifiers":[
        {
            "category":"Building & Trades",
            "subcategory":"Landscaping Services",
            "type":"Services"
        }
    ],
    "sg:phone":"+1 317 487 6098",
    "sg:postcode":"46224",
    "sg:province":"IN",
    "wof:name":"Max Bigelow Landscape Ser",
    "wof:placetype":"venue"
},
  "geometry": {"coordinates":[-86.26620699999999,39.788271],"type":"Point"}
}