{
  "type": "Feature",
  "properties": {
    "iso:country":"US",
    "sg:address":"137 E Main St",
    "sg:city":"New Albany",
    "sg:classifiers":[
        {
            "category":"Banks & Credit Unions",
            "subcategory":"Bank",
            "type":"Services"
        }
    ],
    "sg:phone":"+1 812 941 7283",
    "sg:postcode":"47150",
    "sg:province":"IN",
    "sg:tags":[
        "loan",
        "real estate"
    ],
    "sg:website":"www.1stcitizensfinancial.com",
    "wof:name":"First Citizens Financial Inc",
    "wof:placetype":"venue"
},
  "geometry": {"coordinates":[-85.82088299999999,38.284174],"type":"Point"}
}