{
  "type": "Feature",
  "properties": {
    "iso:country":"US",
    "sg:address":"2845 Monnier St",
    "sg:city":"Portage",
    "sg:classifiers":[
        {
            "category":"Arts & Performance",
            "subcategory":"Theater",
            "type":"Entertainment"
        }
    ],
    "sg:phone":"+1 219 762 1398",
    "sg:postcode":"46368",
    "sg:province":"IN",
    "sg:tags":[
        "dance",
        "group"
    ],
    "wof:name":"Tonis Dance Academy",
    "wof:placetype":"venue"
},
  "geometry": {"coordinates":[-87.185983,41.569552],"type":"Point"}
}