{
  "type": "Feature",
  "properties": {
    "iso:country":"US",
    "sg:address":"555 Shady Brook Hts",
    "sg:city":"Greenwood",
    "sg:classifiers":[
        {
            "category":"Manufacturing",
            "subcategory":"Retail Goods",
            "type":"Manufacturing & Wholesale Goods"
        }
    ],
    "sg:phone":"+1 317 865 9403",
    "sg:postcode":"46142",
    "sg:province":"IN",
    "sg:tags":[
        "lead",
        "mfg"
    ],
    "wof:name":"Sol Fleitz",
    "wof:placetype":"venue"
},
  "geometry": {"coordinates":[-86.18343900000001,39.63185],"type":"Point"}
}