{
  "type": "Feature",
  "properties": {
    "iso:country":"US",
    "sg:address":"1614 25th St",
    "sg:city":"Bedford",
    "sg:classifiers":[
        {
            "category":"Health Services",
            "subcategory":"Doctor",
            "type":"Services"
        }
    ],
    "sg:phone":"+1 812 277 0118",
    "sg:postcode":"47421",
    "sg:province":"IN",
    "sg:tags":[
        "physician",
        "surgeon"
    ],
    "wof:name":"Southern In Pediatrics",
    "wof:placetype":"venue"
},
  "geometry": {"coordinates":[-86.494131,38.851732],"type":"Point"}
}