{
  "type": "Feature",
  "properties": {
    "iso:country":"US",
    "sg:address":"18 Jefferson St",
    "sg:city":"Valparaiso",
    "sg:classifiers":[
        {
            "category":"Personal",
            "subcategory":"Beauty Salon",
            "type":"Services"
        }
    ],
    "sg:phone":"+1 219 476 9159",
    "sg:postcode":"46383",
    "sg:province":"IN",
    "wof:name":"DRG Design",
    "wof:placetype":"venue"
},
  "geometry": {"coordinates":[-87.061139,41.468719],"type":"Point"}
}