{
  "type": "Feature",
  "properties": {
    "addr:full":"7100 W 9th Ave Gary IN 46406",
    "addr:housenumber":"7100",
    "addr:postcode":"46406",
    "addr:street":"W 9Th Ave",
    "iso:country":"US",
    "sg:address":"7100 W 9th Ave",
    "sg:city":"Gary",
    "sg:classifiers":[
        {
            "category":"Manufacturing",
            "subcategory":"Glass & Minerals",
            "type":"Manufacturing & Wholesale Goods"
        }
    ],
    "sg:phone":"+1 219 944 6250",
    "sg:postcode":"46406",
    "sg:province":"IN",
    "sg:tags":[
        "abrasive",
        "product"
    ],
    "wof:name":"Reed Minerals",
    "wof:placetype":"venue"
},
  "geometry": {"coordinates":[-87.426734,41.595376],"type":"Point"}
}