{
  "type": "Feature",
  "properties": {
    "iso:country":"US",
    "sg:address":"67970 State Rd 15",
    "sg:city":"New Paris",
    "sg:classifiers":[
        {
            "category":"Autos & Motor Vehicles",
            "subcategory":"Automobile Sales",
            "type":"Retail Goods"
        }
    ],
    "sg:phone":"+1 574 831 5620",
    "sg:postcode":"46553",
    "sg:province":"IN",
    "sg:tags":[
        "car",
        "dealer"
    ],
    "wof:name":"New Paris Auto Connection",
    "wof:placetype":"venue"
},
  "geometry": {"coordinates":[-85.834219,41.508927],"type":"Point"}
}