{
  "type": "Feature",
  "properties": {
    "iso:country":"US",
    "sg:address":"1313 N Main St",
    "sg:city":"Evansville",
    "sg:classifiers":[
        {
            "category":"Restaurant",
            "type":"Food & Drink"
        }
    ],
    "sg:phone":"+1 812 422 1150",
    "sg:postcode":"47711",
    "sg:province":"IN",
    "sg:tags":[
        "caterer"
    ],
    "wof:name":"Reis Catering",
    "wof:placetype":"venue"
},
  "geometry": {"coordinates":[-87.563625,37.990176],"type":"Point"}
}