{
  "type": "Feature",
  "properties": {
    "iso:country":"US",
    "sg:address":"1400 Professional Blvd",
    "sg:city":"Evansville",
    "sg:classifiers":[
        {
            "category":"Wholesale",
            "subcategory":"Medical Equipment & Supplies",
            "type":"Manufacturing & Wholesale Goods"
        }
    ],
    "sg:phone":"+1 812 476 4407",
    "sg:postcode":"47714",
    "sg:province":"IN",
    "sg:tags":[
        "electronics"
    ],
    "wof:name":"Meds Inc",
    "wof:placetype":"venue"
},
  "geometry": {"coordinates":[-87.501846,37.956691],"type":"Point"}
}