{
  "type": "Feature",
  "properties": {
    "iso:country":"US",
    "sg:address":"2806 E Michigan St",
    "sg:city":"Indianapolis",
    "sg:classifiers":[
        {
            "category":"Building & Trades",
            "subcategory":"Construction",
            "type":"Services"
        }
    ],
    "sg:phone":"+1 317 632 2302",
    "sg:postcode":"46201",
    "sg:province":"IN",
    "sg:tags":[
        "roofing",
        "contractor"
    ],
    "wof:name":"Majestic Home Improvement Co",
    "wof:placetype":"venue"
},
  "geometry": {"coordinates":[-86.115454,39.774564],"type":"Point"}
}