{
  "type": "Feature",
  "properties": {
    "iso:country":"US",
    "sg:address":"361 W Main St",
    "sg:city":"Westville",
    "sg:classifiers":[
        {
            "category":"Manufacturing",
            "subcategory":"Printing",
            "type":"Manufacturing & Wholesale Goods"
        }
    ],
    "sg:phone":"+1 219 785 2821",
    "sg:postcode":"46391",
    "sg:province":"IN",
    "sg:tags":[
        "commercial"
    ],
    "wof:name":"WAR-LLC Westville Printing",
    "wof:placetype":"venue"
},
  "geometry": {"coordinates":[-86.901135,41.541544],"type":"Point"}
}