{
  "type": "Feature",
  "properties": {
    "addr:full":"5200 Cleveland St Merrillville IN 46410",
    "addr:housenumber":"5200",
    "addr:postcode":"46410",
    "addr:street":"Cleveland St",
    "iso:country":"US",
    "sg:address":"5200 Cleveland St",
    "sg:city":"Merrillville",
    "sg:classifiers":[
        {
            "category":"Building & Trades",
            "subcategory":"Construction",
            "type":"Services"
        }
    ],
    "sg:phone":"+1 219 980 3710",
    "sg:postcode":"46410",
    "sg:province":"IN",
    "sg:tags":[
        "roofing",
        "contractor"
    ],
    "wof:name":"Maris Roofing",
    "wof:placetype":"venue"
},
  "geometry": {"coordinates":[-87.36033399999999,41.523466],"type":"Point"}
}