{
  "type": "Feature",
  "properties": {
    "iso:country":"US",
    "sg:address":"100 Sycamore Estates Dr",
    "sg:city":"Aurora",
    "sg:classifiers":[
        {
            "category":"Personal",
            "subcategory":"Beauty Salon",
            "type":"Services"
        }
    ],
    "sg:phone":"+1 812 926 3132",
    "sg:postcode":"47001",
    "sg:province":"IN",
    "wof:name":"Cost Cutters Family Hair Care",
    "wof:placetype":"venue"
},
  "geometry": {"coordinates":[-84.893462,39.075069],"type":"Point"}
}