{
  "type": "Feature",
  "properties": {
    "iso:country":"US",
    "sg:address":"803 W Pearl St",
    "sg:city":"Lebanon",
    "sg:classifiers":[
        {
            "category":"Government",
            "subcategory":"Office",
            "type":"Public Place"
        }
    ],
    "sg:phone":"+1 765 482 6355",
    "sg:postcode":"46052",
    "sg:province":"IN",
    "sg:tags":[
        "federal"
    ],
    "wof:name":"US Consolidated Farm Svc Agcy",
    "wof:placetype":"venue"
},
  "geometry": {"coordinates":[-86.475295,40.045734],"type":"Point"}
}