{
  "type": "Feature",
  "properties": {
    "iso:country":"US",
    "sg:address":"705 Lincoln Hwy W",
    "sg:city":"New Haven",
    "sg:classifiers":[
        {
            "category":"Shopping",
            "subcategory":"Discount & Variety Stores",
            "type":"Retail Goods"
        }
    ],
    "sg:phone":"+1 260 749 9315",
    "sg:postcode":"46774",
    "sg:province":"IN",
    "wof:name":"Dollar Saver Inc",
    "wof:placetype":"venue"
},
  "geometry": {"coordinates":[-85.036006,41.069855],"type":"Point"}
}