{
  "type": "Feature",
  "properties": {
    "addr:full":"2510 Laporte Ave Valparaiso IN 46383",
    "addr:housenumber":"2510",
    "addr:postcode":"46383",
    "addr:street":"Laporte Ave",
    "iso:country":"US",
    "sg:address":"2510 Laporte Ave",
    "sg:city":"Valparaiso",
    "sg:classifiers":[
        {
            "category":"Restaurant",
            "type":"Food & Drink"
        }
    ],
    "sg:menulink":"http://www.allmenus.com/in/valparaiso/79506-pizza-hut/menu/",
    "sg:phone":"+1 219 465 6500",
    "sg:postcode":"46383",
    "sg:province":"IN",
    "sg:tags":[
        "american",
        "pizza"
    ],
    "wof:name":"Pizza Hut",
    "wof:placetype":"venue"
},
  "geometry": {"coordinates":[-87.03119599999999,41.468203],"type":"Point"}
}