{
  "type": "Feature",
  "properties": {
    "iso:country":"US",
    "sg:address":"1905 Northshore Exd",
    "sg:city":"Anderson",
    "sg:classifiers":[
        {
            "category":"Restaurant",
            "type":"Food & Drink"
        }
    ],
    "sg:phone":"+1 765 642 2725",
    "sg:postcode":"46011",
    "sg:province":"IN",
    "wof:name":"Grandview Grille & Pub",
    "wof:placetype":"venue"
},
  "geometry": {"coordinates":[-85.70507600000001,40.116393],"type":"Point"}
}