{
  "type": "Feature",
  "properties": {
    "iso:country":"US",
    "sg:address":"803 Helen Ave",
    "sg:city":"Auburn",
    "sg:classifiers":[
        {
            "category":"Building & Trades",
            "subcategory":"Construction",
            "type":"Services"
        }
    ],
    "sg:phone":"+1 260 925 1030",
    "sg:postcode":"46706",
    "sg:province":"IN",
    "sg:tags":[
        "concrete",
        "contractor"
    ],
    "wof:name":"Seiss Concrete Construction",
    "wof:placetype":"venue"
},
  "geometry": {"coordinates":[-85.065121,41.354147],"type":"Point"}
}