{
  "type": "Feature",
  "properties": {
    "iso:country":"US",
    "sg:address":"7601 W Co Rd 550 S",
    "sg:city":"Daleville",
    "sg:classifiers":[
        {
            "category":"Building & Trades",
            "subcategory":"Electrical",
            "type":"Services"
        }
    ],
    "sg:phone":"+1 765 759 5932",
    "sg:postcode":"47302",
    "sg:province":"IN",
    "sg:tags":[
        "electric",
        "contractor"
    ],
    "wof:name":"Steve Sult Electric",
    "wof:placetype":"venue"
},
  "geometry": {"coordinates":[-85.480553,40.113312],"type":"Point"}
}