{
  "type": "Feature",
  "properties": {
    "iso:country":"US",
    "sg:address":"2220 Toledo Rd",
    "sg:city":"Elkhart",
    "sg:classifiers":[
        {
            "category":"Retail",
            "subcategory":"Auto Rental",
            "type":"Services"
        }
    ],
    "sg:phone":"+1 574 293 5681",
    "sg:postcode":"46516",
    "sg:province":"IN",
    "sg:tags":[
        "renting",
        "truck",
        "leasing"
    ],
    "wof:name":"Penske Truck Leasing",
    "wof:placetype":"venue"
},
  "geometry": {"coordinates":[-85.92986000000001,41.677695],"type":"Point"}
}