{
  "type": "Feature",
  "properties": {
    "iso:country":"US",
    "sg:address":"406 E 2nd St",
    "sg:city":"Madison",
    "sg:classifiers":[
        {
            "category":"Shopping",
            "subcategory":"Florist",
            "type":"Retail Goods"
        }
    ],
    "sg:phone":"+1 812 265 4127",
    "sg:postcode":"47250",
    "sg:province":"IN",
    "wof:name":"Colonial Flower Shop",
    "wof:placetype":"venue"
},
  "geometry": {"coordinates":[-85.37563299999999,38.735007],"type":"Point"}
}