{
  "type": "Feature",
  "properties": {
    "iso:country":"US",
    "sg:address":"9515 Indianapolis Blvd",
    "sg:city":"Highland",
    "sg:classifiers":[
        {
            "category":"Real Estate",
            "subcategory":"Real Estate Agent",
            "type":"Services"
        }
    ],
    "sg:phone":"+1 219 934 9300",
    "sg:postcode":"46322",
    "sg:province":"IN",
    "sg:tags":[
        "appraiser"
    ],
    "wof:name":"Calumet Commercial Appraisals",
    "wof:placetype":"venue"
},
  "geometry": {"coordinates":[-87.471153,41.540599],"type":"Point"}
}