{
  "type": "Feature",
  "properties": {
    "iso:country":"US",
    "sg:address":"3121 E 10th St",
    "sg:city":"Jeffersonville",
    "sg:classifiers":[
        {
            "category":"Real Estate",
            "subcategory":"Real Estate Services",
            "type":"Services"
        },
        {
            "category":"Real Estate",
            "subcategory":"Real Estate Agent",
            "type":"Services"
        }
    ],
    "sg:phone":"+1 812 284 1532",
    "sg:postcode":"47130",
    "sg:province":"IN",
    "sg:tags":[
        "buyer",
        "management",
        "broker"
    ],
    "wof:name":"Jimmy Guthrie Real Estate",
    "wof:placetype":"venue"
},
  "geometry": {"coordinates":[-85.71234,38.326042],"type":"Point"}
}