{
  "type": "Feature",
  "properties": {
    "iso:country":"US",
    "sg:address":"945 S Indiana Ave",
    "sg:city":"Sellersburg",
    "sg:classifiers":[
        {
            "category":"Personal",
            "subcategory":"Beauty Salon",
            "type":"Services"
        }
    ],
    "sg:phone":"+1 812 246 3903",
    "sg:postcode":"47172",
    "sg:province":"IN",
    "wof:name":"Hair Etc",
    "wof:placetype":"venue"
},
  "geometry": {"coordinates":[-85.751052,38.386988],"type":"Point"}
}