{
  "type": "Feature",
  "properties": {
    "iso:country":"US",
    "sg:address":"1945 S Wabash St",
    "sg:city":"Wabash",
    "sg:classifiers":[
        {
            "category":"Home & Garden",
            "subcategory":"Carpets & Floor Coverings",
            "type":"Retail Goods"
        }
    ],
    "sg:phone":"+1 260 563 7218",
    "sg:postcode":"46992",
    "sg:province":"IN",
    "sg:tags":[
        "dealer",
        "rug"
    ],
    "wof:name":"Quality Discount Carpet",
    "wof:placetype":"venue"
},
  "geometry": {"coordinates":[-85.819557,40.777793],"type":"Point"}
}