{
  "type": "Feature",
  "properties": {
    "addr:full":"206 Cedar St Vevay IN 47043",
    "addr:housenumber":"206",
    "addr:postcode":"47043",
    "addr:street":"Cedar St",
    "iso:country":"US",
    "sg:address":"206 Cedar St",
    "sg:city":"Vevay",
    "sg:classifiers":[
        {
            "category":"Professional",
            "subcategory":"Computer Services",
            "type":"Services"
        }
    ],
    "sg:phone":"+1 812 427 9446",
    "sg:postcode":"47043",
    "sg:province":"IN",
    "sg:tags":[
        "datum"
    ],
    "wof:name":"Hankins Computer Service",
    "wof:placetype":"venue"
},
  "geometry": {"coordinates":[-85.074716,38.742663],"type":"Point"}
}