{
  "type": "Feature",
  "properties": {
    "iso:country":"US",
    "sg:address":"5014 Southeastern Ave",
    "sg:city":"Indianapolis",
    "sg:classifiers":[
        {
            "category":"Travel",
            "subcategory":"Bed & Breakfast",
            "type":"Entertainment"
        }
    ],
    "sg:phone":"+1 317 357 5004",
    "sg:postcode":"46203",
    "sg:province":"IN",
    "sg:tags":[
        "inn"
    ],
    "wof:name":"Choo Choo Inn King Of Clubs",
    "wof:placetype":"venue"
},
  "geometry": {"coordinates":[-86.085155,39.74597],"type":"Point"}
}