{
  "type": "Feature",
  "properties": {
    "iso:country":"US",
    "sg:address":"410 S Cherry St",
    "sg:city":"Martinsville",
    "sg:classifiers":[
        {
            "category":"Manufacturing",
            "subcategory":"Tools & Machinery",
            "type":"Manufacturing & Wholesale Goods"
        }
    ],
    "sg:phone":"+1 765 352 0180",
    "sg:postcode":"46151",
    "sg:province":"IN",
    "sg:tags":[
        "machine",
        "shop"
    ],
    "wof:name":"Lee Engineering",
    "wof:placetype":"venue"
},
  "geometry": {"coordinates":[-86.432227,39.423271],"type":"Point"}
}