{
  "type": "Feature",
  "properties": {
    "iso:country":"US",
    "sg:address":"7036 E 10th St",
    "sg:city":"Indianapolis",
    "sg:classifiers":[
        {
            "category":"Real Estate",
            "subcategory":"Real Estate Operator",
            "type":"Services"
        }
    ],
    "sg:phone":"+1 317 356 9452",
    "sg:postcode":"46219",
    "sg:province":"IN",
    "sg:tags":[
        "apartment"
    ],
    "wof:name":"Eastgate Terrace Apartments",
    "wof:placetype":"venue"
},
  "geometry": {"coordinates":[-86.041313,39.781876],"type":"Point"}
}