{
  "type": "Feature",
  "properties": {
    "iso:country":"US",
    "sg:address":"2609 N Co Rd 825 W",
    "sg:city":"Royal Center",
    "sg:classifiers":[
        {
            "category":"Farming",
            "subcategory":"Livestock Farm",
            "type":"Manufacturing & Wholesale Goods"
        }
    ],
    "sg:phone":"+1 574 722 4059",
    "sg:postcode":"46978",
    "sg:province":"IN",
    "sg:tags":[
        "beef",
        "feedlot",
        "cattle"
    ],
    "wof:name":"Joe Carlson",
    "wof:placetype":"venue"
},
  "geometry": {"coordinates":[-86.528941,40.802317],"type":"Point"}
}