{
  "type": "Feature",
  "properties": {
    "iso:country":"US",
    "sg:address":"6745 N State Rd 9",
    "sg:city":"Hope",
    "sg:phone":"+1 812 546 4324",
    "sg:postcode":"47246",
    "sg:province":"IN",
    "sg:tags":[
        "farm",
        "corn",
        "soybean"
    ],
    "wof:name":"Baute Farms",
    "wof:placetype":"venue"
},
  "geometry": {"coordinates":[-85.771371,39.269159],"type":"Point"}
}