{
  "type": "Feature",
  "properties": {
    "iso:country":"US",
    "sg:address":"3117 N Gale St",
    "sg:city":"Indianapolis",
    "sg:classifiers":[
        {
            "category":"Shopping",
            "subcategory":"Discount & Variety Stores",
            "type":"Retail Goods"
        }
    ],
    "sg:phone":"+1 317 545 4981",
    "sg:postcode":"46218",
    "sg:province":"IN",
    "wof:name":"Davis Variety Store",
    "wof:placetype":"venue"
},
  "geometry": {"coordinates":[-86.10574699999999,39.812277],"type":"Point"}
}