{
  "type": "Feature",
  "properties": {
    "iso:country":"US",
    "sg:address":"8902 Airport Dr",
    "sg:city":"Fort Wayne",
    "sg:classifiers":[
        {
            "category":"Building & Trades",
            "subcategory":"Construction",
            "type":"Services"
        }
    ],
    "sg:phone":"+1 260 469 4060",
    "sg:postcode":"46809",
    "sg:province":"IN",
    "sg:tags":[
        "designer"
    ],
    "sg:website":"www.gotobig.com",
    "wof:name":"Big Design & Advertising",
    "wof:placetype":"venue"
},
  "geometry": {"coordinates":[-85.18335,41.002006],"type":"Point"}
}