{
  "type": "Feature",
  "properties": {
    "iso:country":"US",
    "sg:address":"370 W 12th St",
    "sg:city":"Peru",
    "sg:classifiers":[
        {
            "category":"Building & Trades",
            "subcategory":"Construction",
            "type":"Services"
        }
    ],
    "sg:phone":"+1 765 473 9645",
    "sg:postcode":"46970",
    "sg:province":"IN",
    "sg:tags":[
        "house"
    ],
    "wof:name":"Max Gasaway General Contg",
    "wof:placetype":"venue"
},
  "geometry": {"coordinates":[-86.085471,40.755248],"type":"Point"}
}