{
  "type": "Feature",
  "properties": {
    "iso:country":"US",
    "sg:address":"9222 Garrison Dr",
    "sg:city":"Indianapolis",
    "sg:classifiers":[
        {
            "category":"Real Estate",
            "subcategory":"Real Estate Operator",
            "type":"Services"
        }
    ],
    "sg:phone":"+1 317 844 1382",
    "sg:postcode":"46240",
    "sg:province":"IN",
    "sg:tags":[
        "apartment"
    ],
    "wof:name":"Crestwood Village Apartments",
    "wof:placetype":"venue"
},
  "geometry": {"coordinates":[-86.136746,39.922226],"type":"Point"}
}