{
  "type": "Feature",
  "properties": {
    "addr:full":"3211 Conner St Noblesville IN 46060",
    "addr:housenumber":"3211",
    "addr:postcode":"46060",
    "addr:street":"Conner St",
    "iso:country":"US",
    "sg:address":"3211 Conner St",
    "sg:city":"Noblesville",
    "sg:classifiers":[
        {
            "category":"Manufacturing",
            "subcategory":"Chemicals & Compounds",
            "type":"Manufacturing & Wholesale Goods"
        }
    ],
    "sg:phone":"+1 317 773 3787",
    "sg:postcode":"46060",
    "sg:province":"IN",
    "sg:tags":[
        "rubber"
    ],
    "sg:website":"www.fieldrubber.com",
    "wof:name":"Field Rubber Products Co",
    "wof:placetype":"venue"
},
  "geometry": {"coordinates":[-85.991232,40.045637],"type":"Point"}
}