{
  "type": "Feature",
  "properties": {
    "iso:country":"US",
    "sg:address":"822 S Lafayette Blvd",
    "sg:city":"South Bend",
    "sg:classifiers":[
        {
            "category":"Bars & Pubs",
            "type":"Food & Drink"
        }
    ],
    "sg:phone":"+1 574 289 9829",
    "sg:postcode":"46601",
    "sg:province":"IN",
    "wof:name":"Dew Drop Inn Restaurant",
    "wof:placetype":"venue"
},
  "geometry": {"coordinates":[-86.253264,41.6653],"type":"Point"}
}