{
  "type": "Feature",
  "properties": {
    "iso:country":"US",
    "sg:address":"1101 N Dunn St",
    "sg:city":"Bloomington",
    "sg:classifiers":[
        {
            "category":"Arts & Performance",
            "subcategory":"Arts Center",
            "type":"Entertainment"
        }
    ],
    "sg:phone":"+1 812 334 0506",
    "sg:postcode":"47408",
    "sg:province":"IN",
    "sg:tags":[
        "performing"
    ],
    "wof:name":"Windfall Dancers Inc",
    "wof:placetype":"venue"
},
  "geometry": {"coordinates":[-86.52835899999999,39.176992],"type":"Point"}
}