{
  "type": "Feature",
  "properties": {
    "iso:country":"US",
    "sg:address":"115 E Main St",
    "sg:city":"Syracuse",
    "sg:classifiers":[
        {
            "category":"Education",
            "subcategory":"Library",
            "type":"Public Place"
        }
    ],
    "sg:phone":"+1 574 457 3022",
    "sg:postcode":"46567",
    "sg:province":"IN",
    "sg:website":"www.syracuse.lib.in.us",
    "wof:name":"Syracuse Public Library",
    "wof:placetype":"venue"
},
  "geometry": {"coordinates":[-85.751777,41.428145],"type":"Point"}
}