{
  "type": "Feature",
  "properties": {
    "iso:country":"US",
    "sg:address":"9123 Aboite Center Rd",
    "sg:city":"Fort Wayne",
    "sg:classifiers":[
        {
            "category":"Social Services",
            "subcategory":"Child Care",
            "type":"Services"
        }
    ],
    "sg:phone":"+1 260 436 6821",
    "sg:postcode":"46804",
    "sg:province":"IN",
    "sg:tags":[
        "kindergarten",
        "academic",
        "school"
    ],
    "wof:name":"Peace Children's Nursery Schl",
    "wof:placetype":"venue"
},
  "geometry": {"coordinates":[-85.26261100000001,41.045089],"type":"Point"}
}