{
  "type": "Feature",
  "properties": {
    "iso:country":"US",
    "sg:address":"314 W Franklin St",
    "sg:city":"Winchester",
    "sg:classifiers":[
        {
            "category":"Retail",
            "subcategory":"Auto Repair",
            "type":"Services"
        }
    ],
    "sg:phone":"+1 765 584 7227",
    "sg:postcode":"47394",
    "sg:province":"IN",
    "sg:tags":[
        "repairing",
        "automobile"
    ],
    "wof:name":"Winchester Master Tech",
    "wof:placetype":"venue"
},
  "geometry": {"coordinates":[-84.983981,40.171689],"type":"Point"}
}