{
  "type": "Feature",
  "properties": {
    "iso:country":"US",
    "sg:address":"409 E Cook Rd",
    "sg:city":"Fort Wayne",
    "sg:classifiers":[
        {
            "category":"Banks & Credit Unions",
            "subcategory":"Bank",
            "type":"Services"
        }
    ],
    "sg:phone":"+1 260 471 5252",
    "sg:postcode":"46825",
    "sg:province":"IN",
    "sg:tags":[
        "loan",
        "real estate"
    ],
    "wof:name":"Maximum Mortgage Inc",
    "wof:placetype":"venue"
},
  "geometry": {"coordinates":[-85.136555,41.147453],"type":"Point"}
}