{
  "type": "Feature",
  "properties": {
    "addr:full":"2810 N Wheeling Ave Muncie IN 47303",
    "addr:housenumber":"2810",
    "addr:postcode":"47303",
    "addr:street":"N Wheeling Ave",
    "iso:country":"US",
    "sg:address":"2810 N Wheeling Ave",
    "sg:city":"Muncie",
    "sg:classifiers":[
        {
            "category":"Manufacturing",
            "subcategory":"Tools & Machinery",
            "type":"Manufacturing & Wholesale Goods"
        }
    ],
    "sg:phone":"+1 765 284 3119",
    "sg:postcode":"47303",
    "sg:province":"IN",
    "sg:tags":[
        "equipment",
        "blueprinting",
        "supply"
    ],
    "sg:website":"www.easternengineering.com",
    "wof:name":"Eastern Engineering Supply Inc",
    "wof:placetype":"venue"
},
  "geometry": {"coordinates":[-85.401871,40.217744],"type":"Point"}
}