{
  "type": "Feature",
  "properties": {
    "addr:full":"5009 Lookout Dr West Harrison OH 47060",
    "addr:housenumber":"5009",
    "addr:postcode":"oh 47060",
    "addr:street":"Lookout Dr",
    "iso:country":"US",
    "sg:address":"5009 Lookout Dr",
    "sg:city":"West Harrison",
    "sg:classifiers":[
        {
            "category":"Building & Trades",
            "subcategory":"Plumbing",
            "type":"Services"
        }
    ],
    "sg:phone":"+1 812 637 5625",
    "sg:postcode":"47060",
    "sg:province":"OH",
    "sg:tags":[
        "tank",
        "septic"
    ],
    "wof:name":"Savings Liquid Waste",
    "wof:placetype":"venue"
},
  "geometry": {"coordinates":[-85.012214,39.386677],"type":"Point"}
}