{
  "type": "Feature",
  "properties": {
    "addr:full":"1601 Truckers Blvd Jeffersonville IN 47130",
    "addr:housenumber":"1601",
    "addr:postcode":"47130",
    "addr:street":"Truckers Blvd",
    "iso:country":"US",
    "sg:address":"1601 Truckers Blvd",
    "sg:city":"Jeffersonville",
    "sg:classifiers":[
        {
            "category":"Retail",
            "subcategory":"Auto Repair",
            "type":"Services"
        }
    ],
    "sg:phone":"+1 812 283 7783",
    "sg:postcode":"47130",
    "sg:province":"IN",
    "sg:tags":[
        "truck"
    ],
    "wof:name":"Alignrite Inc",
    "wof:placetype":"venue"
},
  "geometry": {"coordinates":[-85.748175,38.319225],"type":"Point"}
}