{
  "type": "Feature",
  "properties": {
    "iso:country":"US",
    "sg:address":"1821 Southeastern Ave",
    "sg:city":"Indianapolis",
    "sg:classifiers":[
        {
            "category":"Building & Trades",
            "subcategory":"Cleaning & Sanitation",
            "type":"Services"
        }
    ],
    "sg:phone":"+1 317 636 2140",
    "sg:postcode":"46201",
    "sg:province":"IN",
    "sg:tags":[
        "janitor"
    ],
    "wof:name":"Tayne's Cleaning Svc",
    "wof:placetype":"venue"
},
  "geometry": {"coordinates":[-86.128715,39.763266],"type":"Point"}
}