{
  "type": "Feature",
  "properties": {
    "iso:country":"US",
    "sg:address":"2310 Toledo Rd",
    "sg:city":"Elkhart",
    "sg:classifiers":[
        {
            "category":"Building & Trades",
            "subcategory":"Plumbing",
            "type":"Services"
        }
    ],
    "sg:phone":"+1 574 295 2440",
    "sg:postcode":"46516",
    "sg:province":"IN",
    "sg:tags":[
        "plumbing",
        "contractor"
    ],
    "sg:website":"www.griffenph.com",
    "wof:name":"Griffen Plumbing-Htg-Cooling",
    "wof:placetype":"venue"
},
  "geometry": {"coordinates":[-85.927711,41.677684],"type":"Point"}
}