{
  "type": "Feature",
  "properties": {
    "iso:country":"US",
    "sg:address":"6815 W Co Rd 200 N",
    "sg:city":"Frankfort",
    "sg:classifiers":[
        {
            "category":"Travel",
            "subcategory":"Campground",
            "type":"Entertainment"
        }
    ],
    "sg:phone":"+1 765 296 2753",
    "sg:postcode":"46041",
    "sg:province":"IN",
    "sg:tags":[
        "camp"
    ],
    "wof:name":"George C Cullom Camp",
    "wof:placetype":"venue"
},
  "geometry": {"coordinates":[-86.634075,40.315622],"type":"Point"}
}