{
  "type": "Feature",
  "properties": {
    "iso:country":"US",
    "sg:address":"4921 N Kenyon Dr",
    "sg:city":"Indianapolis",
    "sg:classifiers":[
        {
            "category":"Personal",
            "subcategory":"Beauty Salon",
            "type":"Services"
        }
    ],
    "sg:phone":"+1 317 545 4247",
    "sg:postcode":"46226",
    "sg:province":"IN",
    "wof:name":"Change N Attitude Glamour",
    "wof:placetype":"venue"
},
  "geometry": {"coordinates":[-86.05313700000001,39.844249],"type":"Point"}
}