{
  "type": "Feature",
  "properties": {
    "iso:country":"US",
    "sg:address":"5855 Madison Ave",
    "sg:city":"Indianapolis",
    "sg:classifiers":[
        {
            "category":"Health Services",
            "subcategory":"Doctor",
            "type":"Services"
        }
    ],
    "sg:phone":"+1 317 787 6160",
    "sg:postcode":"46227",
    "sg:province":"IN",
    "sg:tags":[
        "dentist"
    ],
    "wof:name":"Edgewood Family Dental Care",
    "wof:placetype":"venue"
},
  "geometry": {"coordinates":[-86.132608,39.681454],"type":"Point"}
}