{
  "type": "Feature",
  "properties": {
    "iso:country":"US",
    "sg:address":"1885 US Hwy 27",
    "sg:city":"Winchester",
    "sg:classifiers":[
        {
            "category":"Recreation",
            "type":"Entertainment"
        }
    ],
    "sg:phone":"+1 765 584 4771",
    "sg:postcode":"47394",
    "sg:province":"IN",
    "sg:tags":[
        "fairground"
    ],
    "wof:name":"Fairgrounds 4-H",
    "wof:placetype":"venue"
},
  "geometry": {"coordinates":[-84.965336,40.137246],"type":"Point"}
}