{
  "type": "Feature",
  "properties": {
    "iso:country":"US",
    "sg:address":"945 9th St",
    "sg:city":"Tell City",
    "sg:classifiers":[
        {
            "category":"Shopping",
            "subcategory":"Used Merchandise",
            "type":"Retail Goods"
        }
    ],
    "sg:phone":"+1 812 547 5143",
    "sg:postcode":"47586",
    "sg:province":"IN",
    "sg:tags":[
        "shop",
        "consignment"
    ],
    "wof:name":"Holly Tree Boutique & Consignm",
    "wof:placetype":"venue"
},
  "geometry": {"coordinates":[-86.768528,37.954637],"type":"Point"}
}