{
  "type": "Feature",
  "properties": {
    "addr:full":"700 State Rd 25 Logansport IN 46947",
    "addr:housenumber":"700;25",
    "addr:postcode":"46947",
    "addr:street":"State Rd",
    "iso:country":"US",
    "sg:address":"700 State Rd 25",
    "sg:city":"Logansport",
    "sg:classifiers":[
        {
            "category":"Retail",
            "subcategory":"Repair Shop",
            "type":"Services"
        }
    ],
    "sg:phone":"+1 574 753 6513",
    "sg:postcode":"46947",
    "sg:province":"IN",
    "sg:tags":[
        "satellite",
        "system"
    ],
    "wof:name":"Walker Wireless Communications",
    "wof:placetype":"venue"
},
  "geometry": {"coordinates":[-86.353527,40.77357],"type":"Point"}
}