{
  "type": "Feature",
  "properties": {
    "iso:country":"US",
    "sg:address":"101 S Washington St",
    "sg:city":"Swayzee",
    "sg:classifiers":[
        {
            "category":"Restaurant",
            "type":"Food & Drink"
        }
    ],
    "sg:phone":"+1 765 922 7041",
    "sg:postcode":"46986",
    "sg:province":"IN",
    "wof:name":"Shipp's Of Swayzee",
    "wof:placetype":"venue"
},
  "geometry": {"coordinates":[-85.855073,40.498984],"type":"Point"}
}