{
  "type": "Feature",
  "properties": {
    "iso:country":"US",
    "sg:address":"8590 NW Winchester Rd",
    "sg:city":"Decatur",
    "sg:classifiers":[
        {
            "category":"Retail",
            "subcategory":"Repair Shop",
            "type":"Services"
        }
    ],
    "sg:phone":"+1 260 724 7295",
    "sg:postcode":"46733",
    "sg:province":"IN",
    "sg:tags":[
        "upholsterer"
    ],
    "wof:name":"Casselman's Upholstery",
    "wof:placetype":"venue"
},
  "geometry": {"coordinates":[-84.974173,40.871977],"type":"Point"}
}