{
  "type": "Feature",
  "properties": {
    "iso:country":"US",
    "sg:address":"2882 W 900 S",
    "sg:city":"Trafalgar",
    "sg:classifiers":[
        {
            "category":"Building & Trades",
            "subcategory":"Construction",
            "type":"Services"
        }
    ],
    "sg:phone":"+1 317 878 5300",
    "sg:postcode":"46181",
    "sg:province":"IN",
    "sg:tags":[
        "fire",
        "restoration",
        "damage"
    ],
    "wof:name":"Service Master By Armstrong",
    "wof:placetype":"venue"
},
  "geometry": {"coordinates":[-86.154967,39.342989],"type":"Point"}
}