{
  "type": "Feature",
  "properties": {
    "addr:full":"2630 Arizona St Lake Station IN 46405",
    "addr:housenumber":"2630",
    "addr:postcode":"46405",
    "addr:street":"Arizona St",
    "iso:country":"US",
    "sg:address":"2630 Arizona St",
    "sg:city":"Lake Station",
    "sg:classifiers":[
        {
            "category":"Professional",
            "type":"Services"
        }
    ],
    "sg:phone":"+1 219 962 6287",
    "sg:postcode":"46405",
    "sg:province":"IN",
    "wof:name":"Munchie Machine Inc",
    "wof:placetype":"venue"
},
  "geometry": {"coordinates":[-87.28827800000001,41.570241],"type":"Point"}
}