{
  "type": "Feature",
  "properties": {
    "iso:country":"US",
    "sg:address":"1001 E Jefferson St",
    "sg:city":"Plymouth",
    "sg:classifiers":[
        {
            "category":"Autos & Motor Vehicles",
            "subcategory":"Automobile Sales",
            "type":"Retail Goods"
        }
    ],
    "sg:phone":"+1 574 935 1001",
    "sg:postcode":"46563",
    "sg:province":"IN",
    "sg:tags":[
        "car",
        "dealer"
    ],
    "sg:website":"www.oliverford.com",
    "wof:name":"Oliver Ford Lincoln-Mercury",
    "wof:placetype":"venue"
},
  "geometry": {"coordinates":[-86.292203,41.34393],"type":"Point"}
}