{
  "type": "Feature",
  "properties": {
    "iso:country":"US",
    "sg:address":"10404 W 700 S",
    "sg:city":"Mentone",
    "sg:classifiers":[
        {
            "category":"Building & Trades",
            "subcategory":"Construction",
            "type":"Services"
        }
    ],
    "sg:phone":"+1 574 353 7391",
    "sg:postcode":"46539",
    "sg:province":"IN",
    "sg:tags":[
        "maintenance",
        "contractor"
    ],
    "wof:name":"Lehigh Maintenance",
    "wof:placetype":"venue"
},
  "geometry": {"coordinates":[-86.025631,41.129452],"type":"Point"}
}