{
  "type": "Feature",
  "properties": {
    "iso:country":"US",
    "sg:address":"2578 S US Hwy 421",
    "sg:city":"Greensburg",
    "sg:classifiers":[
        {
            "category":"Retail",
            "subcategory":"Auto Repair",
            "type":"Services"
        }
    ],
    "sg:phone":"+1 812 663 2575",
    "sg:postcode":"47240",
    "sg:province":"IN",
    "sg:tags":[
        "body",
        "automobile",
        "painting"
    ],
    "wof:name":"Luken & Sons Body Shop",
    "wof:placetype":"venue"
},
  "geometry": {"coordinates":[-85.426821,39.299476],"type":"Point"}
}