{
  "type": "Feature",
  "properties": {
    "iso:country":"US",
    "sg:address":"3619 Ralston Ave",
    "sg:city":"Indianapolis",
    "sg:classifiers":[
        {
            "category":"Building & Trades",
            "subcategory":"Plumbing",
            "type":"Services"
        }
    ],
    "sg:phone":"+1 317 926 3630",
    "sg:postcode":"46218",
    "sg:province":"IN",
    "sg:tags":[
        "plumbing",
        "contractor"
    ],
    "wof:name":"Duke Plumbing Co",
    "wof:placetype":"venue"
},
  "geometry": {"coordinates":[-86.131124,39.822577],"type":"Point"}
}