{
  "type": "Feature",
  "properties": {
    "iso:country":"US",
    "sg:address":"3550 Pennsylvania Ave",
    "sg:city":"East Chicago",
    "sg:classifiers":[
        {
            "category":"Education",
            "subcategory":"Library",
            "type":"Public Place"
        }
    ],
    "sg:phone":"+1 219 397 4014",
    "sg:postcode":"46312",
    "sg:province":"IN",
    "wof:name":"Pennsylvania Center Library",
    "wof:placetype":"venue"
},
  "geometry": {"coordinates":[-87.444199,41.649799],"type":"Point"}
}