{
  "type": "Feature",
  "properties": {
    "addr:full":"9039 Kleinman Rd Highland IN 46322",
    "addr:housenumber":"9039",
    "addr:postcode":"46322",
    "addr:street":"Kleinman Rd",
    "iso:country":"US",
    "sg:address":"9039 Kleinman Rd",
    "sg:city":"Highland",
    "sg:classifiers":[
        {
            "category":"Retail",
            "subcategory":"Funeral Services",
            "type":"Services"
        }
    ],
    "sg:phone":"+1 219 923 7800",
    "sg:postcode":"46322",
    "sg:province":"IN",
    "sg:tags":[
        "cemetery"
    ],
    "wof:name":"Kuiper Funeral Home",
    "wof:placetype":"venue"
},
  "geometry": {"coordinates":[-87.437202,41.548599],"type":"Point"}
}