{
  "type": "Feature",
  "properties": {
    "addr:full":"650 E Southport Rd Indianapolis IN 46227",
    "addr:housenumber":"650",
    "addr:postcode":"46227",
    "addr:street":"E Southport Rd",
    "iso:country":"US",
    "sg:address":"650 E Southport Rd",
    "sg:city":"Indianapolis",
    "sg:classifiers":[
        {
            "category":"Shopping",
            "type":"Retail Goods"
        },
        {
            "category":"Health Services",
            "subcategory":"Hospital",
            "type":"Services"
        }
    ],
    "sg:phone":"+1 317 787 3177",
    "sg:postcode":"46227",
    "sg:province":"IN",
    "sg:tags":[
        "orthopedic",
        "appliance",
        "general"
    ],
    "wof:name":"Action Brace & Prosthetic Inc",
    "wof:placetype":"venue"
},
  "geometry": {"coordinates":[-86.145043,39.66454],"type":"Point"}
}