{
  "type": "Feature",
  "properties": {
    "addr:full":"1424 Swafford Rd Liberty IN 47353",
    "addr:housenumber":"1424",
    "addr:postcode":"47353",
    "addr:street":"Swafford Rd",
    "iso:country":"US",
    "sg:address":"1424 Swafford Rd",
    "sg:city":"Liberty",
    "sg:classifiers":[
        {
            "category":"Farming",
            "subcategory":"Livestock Farm",
            "type":"Manufacturing & Wholesale Goods"
        }
    ],
    "sg:phone":"+1 765 458 5648",
    "sg:postcode":"47353",
    "sg:province":"IN",
    "sg:tags":[
        "feedlot",
        "corn",
        "soybean",
        "beef",
        "cattle"
    ],
    "wof:name":"E B B Farms Inc",
    "wof:placetype":"venue"
},
  "geometry": {"coordinates":[-84.88038299999999,39.652735],"type":"Point"}
}