{
  "type": "Feature",
  "properties": {
    "addr:full":"11600 Buente Rd Evansville IN 47720",
    "addr:housenumber":"11600",
    "addr:postcode":"47720",
    "addr:street":"Buente Rd",
    "iso:country":"US",
    "sg:address":"11600 Buente Rd",
    "sg:city":"Evansville",
    "sg:classifiers":[
        {
            "category":"Building & Trades",
            "subcategory":"Construction",
            "type":"Services"
        }
    ],
    "sg:phone":"+1 812 963 3960",
    "sg:postcode":"47720",
    "sg:province":"IN",
    "sg:tags":[
        "general",
        "contractor"
    ],
    "wof:name":"Kissel Construction",
    "wof:placetype":"venue"
},
  "geometry": {"coordinates":[-87.666737,38.095259],"type":"Point"}
}