{
  "type": "Feature",
  "properties": {
    "iso:country":"US",
    "sg:address":"298 Gasoline Aly",
    "sg:city":"Indianapolis",
    "sg:classifiers":[
        {
            "category":"Autos & Motor Vehicles",
            "subcategory":"Auto Supplies",
            "type":"Retail Goods"
        },
        {
            "category":"Shopping",
            "subcategory":"Clothing, Apparel, & Fashions",
            "type":"Retail Goods"
        }
    ],
    "sg:phone":"+1 317 381 9890",
    "sg:postcode":"46222",
    "sg:province":"IN",
    "sg:tags":[
        "equipment",
        "racing",
        "car",
        "automobile"
    ],
    "wof:name":"Pilot Race Gear",
    "wof:placetype":"venue"
},
  "geometry": {"coordinates":[-86.23535,39.769965],"type":"Point"}
}