{
  "type": "Feature",
  "properties": {
    "addr:full":"401 Harrison St Elkhart IN 46516",
    "addr:housenumber":"401",
    "addr:postcode":"46516",
    "addr:street":"Harrison St",
    "iso:country":"US",
    "sg:address":"401 Harrison St",
    "sg:city":"Elkhart",
    "sg:classifiers":[
        {
            "category":"Organizations",
            "subcategory":"Community Association",
            "type":"Services"
        }
    ],
    "sg:phone":"+1 574 293 6013",
    "sg:postcode":"46516",
    "sg:province":"IN",
    "sg:tags":[
        "social"
    ],
    "wof:name":"Italian-Amer Mult Relief Assoc",
    "wof:placetype":"venue"
},
  "geometry": {"coordinates":[-85.975841,41.680648],"type":"Point"}
}