{
  "type": "Feature",
  "properties": {
    "iso:country":"US",
    "sg:address":"206 Lincoln St",
    "sg:city":"Porter",
    "sg:classifiers":[
        {
            "category":"Bars & Pubs",
            "type":"Food & Drink"
        }
    ],
    "sg:phone":"+1 219 926 8869",
    "sg:postcode":"46304",
    "sg:province":"IN",
    "wof:name":"Arellano Porter Grill",
    "wof:placetype":"venue"
},
  "geometry": {"coordinates":[-87.07214999999999,41.61568],"type":"Point"}
}