{
  "type": "Feature",
  "properties": {
    "iso:country":"US",
    "sg:address":"2 Sherwood Sq",
    "sg:city":"Peru",
    "sg:classifiers":[
        {
            "category":"Restaurant",
            "type":"Food & Drink"
        }
    ],
    "sg:menulink":"http://www.allmenus.com/in/peru/83689-papa-johns-pizza/menu/",
    "sg:phone":"+1 765 473 7200",
    "sg:postcode":"46970",
    "sg:province":"IN",
    "sg:tags":[
        "american",
        "pizza"
    ],
    "wof:name":"Papa John's Pizza",
    "wof:placetype":"venue"
},
  "geometry": {"coordinates":[-86.094262,40.744827],"type":"Point"}
}