{
  "type": "Feature",
  "properties": {
    "iso:country":"US",
    "sg:address":"1000 E 4th St",
    "sg:city":"Mt Vernon",
    "sg:classifiers":[
        {
            "category":"Home & Garden",
            "subcategory":"Building Materials",
            "type":"Retail Goods"
        }
    ],
    "sg:phone":"+1 812 838 2475",
    "sg:postcode":"47620",
    "sg:province":"IN",
    "sg:tags":[
        "glass",
        "window",
        "plate"
    ],
    "wof:name":"Siemers Glass Co Inc",
    "wof:placetype":"venue"
},
  "geometry": {"coordinates":[-87.884001,37.935134],"type":"Point"}
}