{
  "type": "Feature",
  "properties": {
    "iso:country":"US",
    "sg:address":"1543 Dominion Dr",
    "sg:city":"Zionsville",
    "sg:classifiers":[
        {
            "category":"Professional",
            "subcategory":"Computer Services",
            "type":"Services"
        }
    ],
    "sg:phone":"+1 317 873 5156",
    "sg:postcode":"46077",
    "sg:province":"IN",
    "wof:name":"David Winter",
    "wof:placetype":"venue"
},
  "geometry": {"coordinates":[-86.282967,39.949994],"type":"Point"}
}