{
  "type": "Feature",
  "properties": {
    "iso:country":"US",
    "sg:address":"2608 Lower Huntington Rd",
    "sg:city":"Fort Wayne",
    "sg:classifiers":[
        {
            "category":"Shopping",
            "subcategory":"Catalog Store",
            "type":"Retail Goods"
        }
    ],
    "sg:phone":"+1 260 478 7079",
    "sg:postcode":"46809",
    "sg:province":"IN",
    "sg:tags":[
        "e"
    ],
    "wof:name":"Summit Outlet",
    "wof:placetype":"venue"
},
  "geometry": {"coordinates":[-85.173907,41.020354],"type":"Point"}
}