{
  "type": "Feature",
  "properties": {
    "iso:country":"US",
    "sg:address":"766 Bennington Pike",
    "sg:city":"Vevay",
    "sg:classifiers":[
        {
            "category":"Building & Trades",
            "subcategory":"Plumbing",
            "type":"Services"
        }
    ],
    "sg:phone":"+1 812 427 3715",
    "sg:postcode":"47043",
    "sg:province":"IN",
    "sg:tags":[
        "product",
        "management",
        "energy",
        "system"
    ],
    "wof:name":"Hoosier Energy",
    "wof:placetype":"venue"
},
  "geometry": {"coordinates":[-85.140181,38.857063],"type":"Point"}
}