{
  "type": "Feature",
  "properties": {
    "iso:country":"US",
    "sg:address":"905 SW 15th St",
    "sg:city":"Richmond",
    "sg:classifiers":[
        {
            "category":"Shopping",
            "subcategory":"Bicycles & Sporting Goods",
            "type":"Retail Goods"
        }
    ],
    "sg:phone":"+1 765 939 2299",
    "sg:postcode":"47374",
    "sg:province":"IN",
    "wof:name":"Gregg's Recumbent Bikes",
    "wof:placetype":"venue"
},
  "geometry": {"coordinates":[-84.92345,39.81779],"type":"Point"}
}