{
  "type": "Feature",
  "properties": {
    "addr:full":"202 W Pine St Griffith IN 46319",
    "addr:housenumber":"202",
    "addr:postcode":"46319",
    "addr:street":"W Pine St",
    "iso:country":"US",
    "sg:address":"202 W Pine St",
    "sg:city":"Griffith",
    "sg:classifiers":[
        {
            "category":"Social Services",
            "subcategory":"Child Care",
            "type":"Services"
        }
    ],
    "sg:phone":"+1 219 924 6840",
    "sg:postcode":"46319",
    "sg:province":"IN",
    "sg:tags":[
        "kindergarten",
        "academic",
        "school"
    ],
    "sg:website":"www.gfcc.net",
    "wof:name":"First Christian Church",
    "wof:placetype":"venue"
},
  "geometry": {"coordinates":[-87.42901999999999,41.533749],"type":"Point"}
}