{
  "type": "Feature",
  "properties": {
    "iso:country":"US",
    "sg:address":"22815 Greenville Borden Rd",
    "sg:city":"Borden",
    "sg:classifiers":[
        {
            "category":"Organizations",
            "subcategory":"Religious Organization",
            "type":"Services"
        }
    ],
    "sg:phone":"+1 812 923 5377",
    "sg:postcode":"47106",
    "sg:province":"IN",
    "wof:name":"James E Temple",
    "wof:placetype":"venue"
},
  "geometry": {"coordinates":[-85.957835,38.430685],"type":"Point"}
}