{
  "type": "Feature",
  "properties": {
    "addr:full":"5775 N Clinton St Terre Haute IN 47805",
    "addr:housenumber":"5775",
    "addr:postcode":"47805",
    "addr:street":"N Clinton St",
    "iso:country":"US",
    "sg:address":"5775 N Clinton St",
    "sg:city":"Terre Haute",
    "sg:classifiers":[
        {
            "category":"Professional",
            "subcategory":"Management & Consulting",
            "type":"Services"
        }
    ],
    "sg:phone":"+1 812 553 0809",
    "sg:postcode":"47805",
    "sg:province":"IN",
    "sg:tags":[
        "logistics"
    ],
    "wof:name":"Reel Time Logistics",
    "wof:placetype":"venue"
},
  "geometry": {"coordinates":[-87.36981299999999,39.536367],"type":"Point"}
}