{
  "type": "Feature",
  "properties": {
    "iso:country":"US",
    "sg:address":"306 Cypress Dr",
    "sg:city":"Schererville",
    "sg:classifiers":[
        {
            "category":"Shopping",
            "subcategory":"Clothing, Apparel, & Fashions",
            "type":"Retail Goods"
        }
    ],
    "sg:phone":"+1 219 864 9293",
    "sg:postcode":"46375",
    "sg:province":"IN",
    "wof:name":"Style Wise",
    "wof:placetype":"venue"
},
  "geometry": {"coordinates":[-87.48119800000001,41.516778],"type":"Point"}
}