{
  "type": "Feature",
  "properties": {
    "iso:country":"US",
    "sg:address":"1825 Washington Dr",
    "sg:city":"Sellersburg",
    "sg:classifiers":[
        {
            "category":"Shopping",
            "subcategory":"Musical Instruments",
            "type":"Retail Goods"
        },
        {
            "category":"Retail",
            "subcategory":"Repair Shop",
            "type":"Services"
        }
    ],
    "sg:phone":"+1 812 246 3295",
    "sg:postcode":"47172",
    "sg:province":"IN",
    "sg:tags":[
        "piano",
        "organ-tuning",
        "restoration",
        "organ"
    ],
    "wof:name":"Bill Riley Piano Tuning",
    "wof:placetype":"venue"
},
  "geometry": {"coordinates":[-85.758622,38.367119],"type":"Point"}
}