{
  "type": "Feature",
  "properties": {
    "iso:country":"US",
    "sg:address":"9989 Lantern Rd",
    "sg:city":"Fishers",
    "sg:classifiers":[
        {
            "category":"Insurance",
            "subcategory":"Insurance Agent",
            "type":"Services"
        }
    ],
    "sg:phone":"+1 317 577 3635",
    "sg:postcode":"46037",
    "sg:province":"IN",
    "wof:name":"Frankenmuth Mutual Insurance",
    "wof:placetype":"venue"
},
  "geometry": {"coordinates":[-86.013643,39.931497],"type":"Point"}
}