{
  "type": "Feature",
  "properties": {
    "iso:country":"US",
    "sg:address":"110 S Main St",
    "sg:city":"Patoka",
    "sg:classifiers":[
        {
            "category":"Retail",
            "subcategory":"Laundry & Dry Cleaning",
            "type":"Services"
        }
    ],
    "sg:phone":"+1 812 779 5427",
    "sg:postcode":"47666",
    "sg:province":"IN",
    "sg:tags":[
        "cleaners",
        "rug",
        "carpet"
    ],
    "wof:name":"AAAA Carpet Clean USA",
    "wof:placetype":"venue"
},
  "geometry": {"coordinates":[-87.585859,38.405992],"type":"Point"}
}