{
  "type": "Feature",
  "properties": {
    "addr:full":"11350 N Meridian St Ste 130 Carmel IN 46032",
    "addr:housenumber":"11350",
    "addr:postcode":"46032",
    "addr:street":"N Meridian St Ste 130",
    "iso:country":"US",
    "sg:address":"11350 N Meridian St Ste 130",
    "sg:city":"Carmel",
    "sg:classifiers":[
        {
            "category":"Banks & Credit Unions",
            "subcategory":"Financial Services",
            "type":"Services"
        }
    ],
    "sg:phone":"+1 317 843 5055",
    "sg:postcode":"46032",
    "sg:province":"IN",
    "sg:tags":[
        "broker",
        "mortgage"
    ],
    "wof:name":"Prime Mortgage USA Inc",
    "wof:placetype":"venue"
},
  "geometry": {"coordinates":[-86.157898,39.952202],"type":"Point"}
}