{
  "type": "Feature",
  "properties": {
    "iso:country":"US",
    "sg:address":"5958 W Stinemyer Rd",
    "sg:city":"New Palestine",
    "sg:classifiers":[
        {
            "category":"Building & Trades",
            "subcategory":"Construction",
            "type":"Services"
        }
    ],
    "sg:phone":"+1 317 861 9198",
    "sg:postcode":"46163",
    "sg:province":"IN",
    "sg:tags":[
        "house"
    ],
    "wof:name":"Rush Construction",
    "wof:placetype":"venue"
},
  "geometry": {"coordinates":[-85.913062,39.71515],"type":"Point"}
}