{
  "type": "Feature",
  "properties": {
    "addr:full":"4897 Kessler Blvd East Dr Indianapolis IN 46220",
    "addr:housenumber":"4897",
    "addr:postcode":"46220",
    "addr:street":"Kessler Blvd East Dr",
    "iso:country":"US",
    "sg:address":"4897 Kessler Blvd East Dr",
    "sg:city":"Indianapolis",
    "sg:classifiers":[
        {
            "category":"Manufacturing",
            "subcategory":"Retail Goods",
            "type":"Manufacturing & Wholesale Goods"
        },
        {
            "category":"Manufacturing",
            "subcategory":"Chemicals & Compounds",
            "type":"Manufacturing & Wholesale Goods"
        }
    ],
    "sg:phone":"+1 317 253 0454",
    "sg:postcode":"46220",
    "sg:province":"IN",
    "sg:tags":[
        "inorganic",
        "manufacturer",
        "mfg"
    ],
    "wof:name":"Floral Guard",
    "wof:placetype":"venue"
},
  "geometry": {"coordinates":[-86.091008,39.85806],"type":"Point"}
}