{
  "type": "Feature",
  "properties": {
    "iso:country":"US",
    "sg:address":"1730 W Beardsley Ave",
    "sg:city":"Elkhart",
    "sg:classifiers":[
        {
            "category":"Autos & Motor Vehicles",
            "subcategory":"Auto Supplies",
            "type":"Retail Goods"
        }
    ],
    "sg:phone":"+1 574 293 9811",
    "sg:postcode":"46514",
    "sg:province":"IN",
    "sg:tags":[
        "automobile",
        "parts"
    ],
    "wof:name":"Hoffman Brothers Auto Parts",
    "wof:placetype":"venue"
},
  "geometry": {"coordinates":[-86.002777,41.692649],"type":"Point"}
}