{
  "type": "Feature",
  "properties": {
    "iso:country":"US",
    "sg:address":"4713 N Wheeling Ave",
    "sg:city":"Muncie",
    "sg:classifiers":[
        {
            "category":"Organizations",
            "subcategory":"Professional Association",
            "type":"Services"
        }
    ],
    "sg:phone":"+1 765 288 2280",
    "sg:postcode":"47304",
    "sg:province":"IN",
    "wof:name":"Muncie Teachers Assoc",
    "wof:placetype":"venue"
},
  "geometry": {"coordinates":[-85.409682,40.230668],"type":"Point"}
}