{
  "type": "Feature",
  "properties": {
    "iso:country":"US",
    "sg:address":"2304 N 750 E",
    "sg:city":"Monticello",
    "sg:classifiers":[
        {
            "category":"Wholesale",
            "subcategory":"Machinery & Supplies",
            "type":"Manufacturing & Wholesale Goods"
        }
    ],
    "sg:phone":"+1 574 583 3206",
    "sg:postcode":"47960",
    "sg:province":"IN",
    "sg:tags":[
        "burial",
        "vault"
    ],
    "wof:name":"Monticello Vault",
    "wof:placetype":"venue"
},
  "geometry": {"coordinates":[-86.725538,40.78548],"type":"Point"}
}