{
  "type": "Feature",
  "properties": {
    "iso:country":"US",
    "sg:address":"11 W Joliet St",
    "sg:city":"Schererville",
    "sg:classifiers":[
        {
            "category":"Professional",
            "subcategory":"Accounting & Tax Preparation",
            "type":"Services"
        }
    ],
    "sg:phone":"+1 219 322 6811",
    "sg:postcode":"46375",
    "sg:province":"IN",
    "sg:tags":[
        "accountant"
    ],
    "wof:name":"Paul F Hoenstine CPA",
    "wof:placetype":"venue"
},
  "geometry": {"coordinates":[-87.452093,41.49197],"type":"Point"}
}