{
  "type": "Feature",
  "properties": {
    "iso:country":"US",
    "sg:address":"1015 Monticello Dr",
    "sg:city":"Anderson",
    "sg:classifiers":[
        {
            "category":"Social Services",
            "type":"Services"
        }
    ],
    "sg:phone":"+1 765 643 1106",
    "sg:postcode":"46011",
    "sg:province":"IN",
    "sg:tags":[
        "senior",
        "citizen"
    ],
    "wof:name":"Monticello House",
    "wof:placetype":"venue"
},
  "geometry": {"coordinates":[-85.69331,40.12841],"type":"Point"}
}