{
  "type": "Feature",
  "properties": {
    "iso:country":"US",
    "sg:address":"707 E Short St",
    "sg:city":"Columbia City",
    "sg:classifiers":[
        {
            "category":"Wholesale",
            "subcategory":"Machinery & Supplies",
            "type":"Manufacturing & Wholesale Goods"
        }
    ],
    "sg:phone":"+1 260 248 2888",
    "sg:postcode":"46725",
    "sg:province":"IN",
    "sg:tags":[
        "rubber",
        "product"
    ],
    "wof:name":"Robco Engineered Rubber Prods",
    "wof:placetype":"venue"
},
  "geometry": {"coordinates":[-85.44186,41.242251],"type":"Point"}
}