{
  "type": "Feature",
  "properties": {
    "iso:country":"US",
    "sg:address":"4444 National Rd E",
    "sg:city":"Richmond",
    "sg:classifiers":[
        {
            "category":"Social Services",
            "type":"Services"
        }
    ],
    "sg:phone":"+1 765 969 8551",
    "sg:postcode":"47374",
    "sg:province":"IN",
    "wof:name":"Young Life",
    "wof:placetype":"venue"
},
  "geometry": {"coordinates":[-84.830438,39.832094],"type":"Point"}
}