{
  "type": "Feature",
  "properties": {
    "iso:country":"US",
    "sg:address":"311 Main St",
    "sg:city":"Rockport",
    "sg:classifiers":[
        {
            "category":"Bars & Pubs",
            "type":"Food & Drink"
        }
    ],
    "sg:phone":"+1 812 649 9980",
    "sg:postcode":"47635",
    "sg:province":"IN",
    "wof:name":"Kirk's Bar & Grill",
    "wof:placetype":"venue"
},
  "geometry": {"coordinates":[-87.048286,37.883255],"type":"Point"}
}