{
  "type": "Feature",
  "properties": {
    "addr:full":"1611 N 825 E Akron IN 46910",
    "addr:housenumber":"1611",
    "addr:postcode":"46910",
    "addr:street":"N 825 E",
    "iso:country":"US",
    "sg:address":"1611 N 825 E",
    "sg:city":"Akron",
    "sg:classifiers":[
        {
            "category":"Real Estate",
            "subcategory":"Real Estate Operator",
            "type":"Services"
        }
    ],
    "sg:phone":"+1 574 893 4009",
    "sg:postcode":"46910",
    "sg:province":"IN",
    "sg:tags":[
        "property",
        "lessor"
    ],
    "wof:name":"Marion Leininger",
    "wof:placetype":"venue"
},
  "geometry": {"coordinates":[-86.09017799999999,41.080366],"type":"Point"}
}