{
  "type": "Feature",
  "properties": {
    "iso:country":"US",
    "sg:address":"1941 E Spring St",
    "sg:city":"New Albany",
    "sg:classifiers":[
        {
            "category":"Real Estate",
            "subcategory":"Real Estate Services",
            "type":"Services"
        }
    ],
    "sg:phone":"+1 812 981 3027",
    "sg:postcode":"47150",
    "sg:province":"IN",
    "sg:tags":[
        "company",
        "title"
    ],
    "wof:name":"W T & S TITLE LLC",
    "wof:placetype":"venue"
},
  "geometry": {"coordinates":[-85.802157,38.29544],"type":"Point"}
}