{
  "type": "Feature",
  "properties": {
    "addr:full":"254 State Road 130 Valparaiso IN 46385",
    "addr:housenumber":"254",
    "addr:postcode":"46385",
    "addr:street":"State Road 130",
    "iso:country":"US",
    "sg:address":"254 State Road 130",
    "sg:city":"Valparaiso",
    "sg:classifiers":[
        {
            "category":"Restaurant",
            "type":"Food & Drink"
        }
    ],
    "sg:menulink":"http://www.allmenus.com/in/valparaiso/120087-subway/menu/",
    "sg:phone":"+1 219 462 3026",
    "sg:postcode":"46385",
    "sg:province":"IN",
    "sg:tags":[
        "american",
        "sandwich"
    ],
    "wof:name":"Subway",
    "wof:placetype":"venue"
},
  "geometry": {"coordinates":[-87.11524300000001,41.492521],"type":"Point"}
}