{
  "type": "Feature",
  "properties": {
    "iso:country":"US",
    "sg:address":"7732 US Hwy 36",
    "sg:city":"Avon",
    "sg:classifiers":[
        {
            "category":"Professional",
            "subcategory":"Accounting & Tax Preparation",
            "type":"Services"
        }
    ],
    "sg:phone":"+1 317 272 0407",
    "sg:postcode":"46123",
    "sg:province":"IN",
    "sg:tags":[
        "return",
        "filing"
    ],
    "wof:name":"H & R Block Tax Svc",
    "wof:placetype":"venue"
},
  "geometry": {"coordinates":[-86.399554,39.762841],"type":"Point"}
}