{
  "type": "Feature",
  "properties": {
    "iso:country":"US",
    "sg:address":"2620 Beulah Ave",
    "sg:city":"Indianapolis",
    "sg:classifiers":[
        {
            "category":"Building & Trades",
            "subcategory":"Cleaning & Sanitation",
            "type":"Services"
        }
    ],
    "sg:phone":"+1 317 352 9025",
    "sg:postcode":"46241",
    "sg:province":"IN",
    "sg:tags":[
        "window"
    ],
    "wof:name":"A Brighter Window Cleaning Svc",
    "wof:placetype":"venue"
},
  "geometry": {"coordinates":[-86.246604,39.72682],"type":"Point"}
}