{
  "type": "Feature",
  "properties": {
    "iso:country":"US",
    "sg:address":"8394 N Advincula Dr",
    "sg:city":"Brazil",
    "sg:classifiers":[
        {
            "category":"Real Estate",
            "subcategory":"Real Estate Operator",
            "type":"Services"
        }
    ],
    "sg:phone":"+1 812 448 3935",
    "sg:postcode":"47834",
    "sg:province":"IN",
    "sg:tags":[
        "building",
        "apartment"
    ],
    "wof:name":"Parkway Apartments",
    "wof:placetype":"venue"
},
  "geometry": {"coordinates":[-87.12269,39.51003],"type":"Point"}
}