{
  "type": "Feature",
  "properties": {
    "iso:country":"US",
    "sg:address":"735 Meridian St",
    "sg:city":"Anderson",
    "sg:classifiers":[
        {
            "category":"Banks & Credit Unions",
            "subcategory":"Investment Brokerage",
            "type":"Services"
        }
    ],
    "sg:phone":"+1 765 642 2274",
    "sg:postcode":"46016",
    "sg:province":"IN",
    "sg:tags":[
        "stock",
        "bond"
    ],
    "wof:name":"Edward Jones Co",
    "wof:placetype":"venue"
},
  "geometry": {"coordinates":[-85.67930800000001,40.108244],"type":"Point"}
}