{
  "type": "Feature",
  "properties": {
    "iso:country":"US",
    "sg:address":"7134 Blackhawk Ln",
    "sg:city":"Fort Wayne",
    "sg:classifiers":[
        {
            "category":"Professional",
            "subcategory":"Accounting & Tax Preparation",
            "type":"Services"
        }
    ],
    "sg:phone":"+1 260 485 2357",
    "sg:postcode":"46815",
    "sg:province":"IN",
    "sg:tags":[
        "return"
    ],
    "wof:name":"Amstutz Tax Services",
    "wof:placetype":"venue"
},
  "geometry": {"coordinates":[-85.04971,41.110964],"type":"Point"}
}