{
  "type": "Feature",
  "properties": {
    "addr:full":"1296 N Gardner St Scottsburg IN 47170",
    "addr:housenumber":"1296",
    "addr:postcode":"47170",
    "addr:street":"N Gardner St",
    "iso:country":"US",
    "sg:address":"1296 N Gardner St",
    "sg:city":"Scottsburg",
    "sg:classifiers":[
        {
            "category":"Autos & Motor Vehicles",
            "subcategory":"Automobile Sales",
            "type":"Retail Goods"
        }
    ],
    "sg:phone":"+1 812 752 5000",
    "sg:postcode":"47170",
    "sg:province":"IN",
    "sg:tags":[
        "car",
        "dealer"
    ],
    "wof:name":"John Jones GM City",
    "wof:placetype":"venue"
},
  "geometry": {"coordinates":[-85.78500699999999,38.702905],"type":"Point"}
}