{
  "type": "Feature",
  "properties": {
    "iso:country":"US",
    "sg:address":"8449 N Fox Hollow Rd",
    "sg:city":"Bloomington",
    "sg:classifiers":[
        {
            "category":"Organizations",
            "subcategory":"Religious Organization",
            "type":"Services"
        }
    ],
    "sg:phone":"+1 812 876 2896",
    "sg:postcode":"47408",
    "sg:province":"IN",
    "sg:tags":[
        "church"
    ],
    "wof:name":"United Pentecostal Assembly",
    "wof:placetype":"venue"
},
  "geometry": {"coordinates":[-86.517053,39.287693],"type":"Point"}
}