{
  "type": "Feature",
  "properties": {
    "addr:full":"6407 Carrollton Ave Indianapolis IN 46220",
    "addr:housenumber":"6407",
    "addr:postcode":"46220",
    "addr:street":"Carrollton Ave",
    "iso:country":"US",
    "sg:address":"6407 Carrollton Ave",
    "sg:city":"Indianapolis",
    "sg:classifiers":[
        {
            "category":"Personal",
            "subcategory":"Beauty Salon",
            "type":"Services"
        }
    ],
    "sg:phone":"+1 317 466 7999",
    "sg:postcode":"46220",
    "sg:province":"IN",
    "sg:tags":[
        "shop"
    ],
    "wof:name":"Envy Design",
    "wof:placetype":"venue"
},
  "geometry": {"coordinates":[-86.1446,39.873437],"type":"Point"}
}