{
  "type": "Feature",
  "properties": {
    "iso:country":"US",
    "sg:address":"4821 Massachusetts Ave",
    "sg:city":"Indianapolis",
    "sg:classifiers":[
        {
            "category":"Professional",
            "subcategory":"Detective & Security Services",
            "type":"Services"
        }
    ],
    "sg:phone":"+1 317 545 1227",
    "sg:postcode":"46218",
    "sg:province":"IN",
    "sg:tags":[
        "information",
        "bureau"
    ],
    "wof:name":"Alliance Parts And Services",
    "wof:placetype":"venue"
},
  "geometry": {"coordinates":[-86.08455600000001,39.81062],"type":"Point"}
}