{
  "type": "Feature",
  "properties": {
    "addr:full":"4211 Hobson Rd Fort Wayne IN 46805",
    "addr:housenumber":"4211",
    "addr:postcode":"46805",
    "addr:street":"Hobson Rd",
    "iso:country":"US",
    "sg:address":"4211 Hobson Rd",
    "sg:city":"Fort Wayne",
    "sg:classifiers":[
        {
            "category":"Banks & Credit Unions",
            "subcategory":"Investment Brokerage",
            "type":"Services"
        }
    ],
    "sg:phone":"+1 260 492 7570",
    "sg:postcode":"46805",
    "sg:province":"IN",
    "sg:tags":[
        "advisory",
        "financial"
    ],
    "wof:name":"Raymond James Financial Svc",
    "wof:placetype":"venue"
},
  "geometry": {"coordinates":[-85.099844,41.116809],"type":"Point"}
}