{
  "type": "Feature",
  "properties": {
    "iso:country":"US",
    "sg:address":"6502 E 56th St",
    "sg:city":"Indianapolis",
    "sg:classifiers":[
        {
            "category":"Health Services",
            "subcategory":"Chiropractor",
            "type":"Services"
        },
        {
            "category":"Health Services",
            "subcategory":"Health Practitioner",
            "type":"Services"
        }
    ],
    "sg:phone":"+1 317 541 0500",
    "sg:postcode":"46226",
    "sg:province":"IN",
    "wof:name":"Acupuncture & Associates",
    "wof:placetype":"venue"
},
  "geometry": {"coordinates":[-86.056523,39.85513],"type":"Point"}
}