{
  "type": "Feature",
  "properties": {
    "iso:country":"US",
    "sg:address":"327 E Franklin St",
    "sg:city":"Spencer",
    "sg:classifiers":[
        {
            "category":"Organizations",
            "subcategory":"Religious Organization",
            "type":"Services"
        }
    ],
    "sg:phone":"+1 812 882 6709",
    "sg:postcode":"47460",
    "sg:province":"IN",
    "sg:tags":[
        "church"
    ],
    "wof:name":"Seventh Day Adventist Church",
    "wof:placetype":"venue"
},
  "geometry": {"coordinates":[-86.758751,39.286208],"type":"Point"}
}