{
  "type": "Feature",
  "properties": {
    "iso:country":"US",
    "sg:address":"4 N Commercial St",
    "sg:city":"Worthington",
    "sg:classifiers":[
        {
            "category":"Shopping",
            "type":"Retail Goods"
        }
    ],
    "sg:phone":"+1 812 875 8758",
    "sg:postcode":"47471",
    "sg:province":"IN",
    "sg:tags":[
        "cards",
        "sport",
        "baseball",
        "memorabilia"
    ],
    "wof:name":"Big League Cards",
    "wof:placetype":"venue"
},
  "geometry": {"coordinates":[-86.975893,39.119007],"type":"Point"}
}