{
  "type": "Feature",
  "properties": {
    "iso:country":"US",
    "sg:address":"3419 S Rural St",
    "sg:city":"Indianapolis",
    "sg:classifiers":[
        {
            "category":"Building & Trades",
            "subcategory":"Cleaning & Sanitation",
            "type":"Services"
        }
    ],
    "sg:phone":"+1 317 788 2899",
    "sg:postcode":"46237",
    "sg:province":"IN",
    "sg:tags":[
        "janitor"
    ],
    "wof:name":"Angie's Cleaning",
    "wof:placetype":"venue"
},
  "geometry": {"coordinates":[-86.115842,39.716224],"type":"Point"}
}