{
  "type": "Feature",
  "properties": {
    "iso:country":"US",
    "sg:address":"3328 Congressional Pkwy",
    "sg:city":"Fort Wayne",
    "sg:classifiers":[
        {
            "category":"Manufacturing",
            "subcategory":"Metals",
            "type":"Manufacturing & Wholesale Goods"
        }
    ],
    "sg:phone":"+1 260 482 3671",
    "sg:postcode":"46808",
    "sg:province":"IN",
    "sg:tags":[
        "screw",
        "nut",
        "bolt"
    ],
    "wof:name":"Anixter Fasteners",
    "wof:placetype":"venue"
},
  "geometry": {"coordinates":[-85.179359,41.111209],"type":"Point"}
}