{
  "type": "Feature",
  "properties": {
    "iso:country":"US",
    "sg:address":"10700 Prospect Ln",
    "sg:city":"Aurora",
    "sg:classifiers":[
        {
            "category":"Government",
            "subcategory":"Office",
            "type":"Public Place"
        }
    ],
    "sg:phone":"+1 812 926 9963",
    "sg:postcode":"47001",
    "sg:province":"IN",
    "wof:name":"Dearborn Conty Recycling Ctr",
    "wof:placetype":"venue"
},
  "geometry": {"coordinates":[-84.937754,39.031146],"type":"Point"}
}