{
  "type": "Feature",
  "properties": {
    "iso:country":"US",
    "sg:address":"5215 Reed St",
    "sg:city":"Fort Wayne",
    "sg:classifiers":[
        {
            "category":"Social Services",
            "subcategory":"Child Care",
            "type":"Services"
        }
    ],
    "sg:phone":"+1 260 744 2222",
    "sg:postcode":"46806",
    "sg:province":"IN",
    "wof:name":"Greater Spirit Of Love Child",
    "wof:placetype":"venue"
},
  "geometry": {"coordinates":[-85.11654900000001,41.035447],"type":"Point"}
}