{
  "type": "Feature",
  "properties": {
    "iso:country":"US",
    "sg:address":"805 E Main St",
    "sg:city":"Greensburg",
    "sg:classifiers":[
        {
            "category":"Building & Trades",
            "subcategory":"Plumbing",
            "type":"Services"
        }
    ],
    "sg:phone":"+1 812 662 7344",
    "sg:postcode":"47240",
    "sg:province":"IN",
    "sg:tags":[
        "plumbing",
        "contractor"
    ],
    "wof:name":"Ron Bailey",
    "wof:placetype":"venue"
},
  "geometry": {"coordinates":[-85.473383,39.336619],"type":"Point"}
}