{
  "type": "Feature",
  "properties": {
    "iso:country":"US",
    "sg:address":"6464 Merchants Dr",
    "sg:city":"Laotto",
    "sg:classifiers":[
        {
            "category":"Banks & Credit Unions",
            "subcategory":"Bank",
            "type":"Services"
        }
    ],
    "sg:phone":"+1 260 897 2891",
    "sg:postcode":"46763",
    "sg:province":"IN",
    "sg:tags":[
        "state",
        "commercial"
    ],
    "sg:website":"www.fmfbank.com",
    "wof:name":"Farmers & Merchants Bank",
    "wof:placetype":"venue"
},
  "geometry": {"coordinates":[-85.189308,41.294219],"type":"Point"}
}