{
  "type": "Feature",
  "properties": {
    "iso:country":"US",
    "sg:address":"1115 S A St",
    "sg:city":"Richmond",
    "sg:classifiers":[
        {
            "category":"Banks & Credit Unions",
            "subcategory":"Bank",
            "type":"Services"
        }
    ],
    "sg:phone":"+1 765 939 6969",
    "sg:postcode":"47374",
    "sg:province":"IN",
    "sg:tags":[
        "loan",
        "real estate"
    ],
    "wof:name":"Galaxy Mortgage Corp",
    "wof:placetype":"venue"
},
  "geometry": {"coordinates":[-84.887532,39.827171],"type":"Point"}
}