{
  "type": "Feature",
  "properties": {
    "iso:country":"US",
    "sg:address":"5440 W Washington St",
    "sg:city":"Indianapolis",
    "sg:classifiers":[
        {
            "category":"Personal",
            "type":"Services"
        },
        {
            "category":"Personal",
            "subcategory":"Barber",
            "type":"Services"
        }
    ],
    "sg:phone":"+1 317 243 0608",
    "sg:postcode":"46241",
    "sg:province":"IN",
    "sg:tags":[
        "hair",
        "shop",
        "beauty",
        "replacement"
    ],
    "wof:name":"Williams Hair Center",
    "wof:placetype":"venue"
},
  "geometry": {"coordinates":[-86.253365,39.751988],"type":"Point"}
}