{
  "type": "Feature",
  "properties": {
    "iso:country":"US",
    "sg:address":"115 NW 4th St",
    "sg:city":"Evansville",
    "sg:classifiers":[
        {
            "category":"Professional",
            "subcategory":"Lawyer & Legal Services",
            "type":"Services"
        }
    ],
    "sg:phone":"+1 812 464 8800",
    "sg:postcode":"47708",
    "sg:province":"IN",
    "sg:tags":[
        "attorney"
    ],
    "wof:name":"Glenn A Grampp",
    "wof:placetype":"venue"
},
  "geometry": {"coordinates":[-87.572316,37.973169],"type":"Point"}
}