{
  "type": "Feature",
  "properties": {
    "iso:country":"US",
    "sg:address":"54361 N 30th St",
    "sg:city":"South Bend",
    "sg:classifiers":[
        {
            "category":"Banks & Credit Unions",
            "subcategory":"Investment Brokerage",
            "type":"Services"
        }
    ],
    "sg:phone":"+1 574 968 1060",
    "sg:postcode":"46635",
    "sg:province":"IN",
    "sg:tags":[
        "advisory",
        "financial"
    ],
    "wof:name":"Complete Financial Solutions",
    "wof:placetype":"venue"
},
  "geometry": {"coordinates":[-86.206964,41.703328],"type":"Point"}
}