{
  "type": "Feature",
  "properties": {
    "iso:country":"US",
    "sg:address":"5208 Commerce Square Dr",
    "sg:city":"Indianapolis",
    "sg:classifiers":[
        {
            "category":"Wholesale",
            "subcategory":"Groceries",
            "type":"Manufacturing & Wholesale Goods"
        }
    ],
    "sg:phone":"+1 317 882 8872",
    "sg:postcode":"46237",
    "sg:province":"IN",
    "sg:tags":[
        "baker"
    ],
    "wof:name":"French Confection",
    "wof:placetype":"venue"
},
  "geometry": {"coordinates":[-86.077545,39.653694],"type":"Point"}
}