{
  "type": "Feature",
  "properties": {
    "addr:full":"14100 E Orr Rd Parker City IN 47368",
    "addr:housenumber":"14100",
    "addr:postcode":"47368",
    "addr:street":"E Orr Rd",
    "iso:country":"US",
    "sg:address":"14100 E Orr Rd",
    "sg:city":"Parker City",
    "sg:classifiers":[
        {
            "category":"Farming",
            "subcategory":"Farm & Veterinary Services",
            "type":"Manufacturing & Wholesale Goods"
        }
    ],
    "sg:phone":"+1 765 468 8113",
    "sg:postcode":"47368",
    "sg:province":"IN",
    "wof:name":"Whispering Willow Farm",
    "wof:placetype":"venue"
},
  "geometry": {"coordinates":[-85.22166300000001,40.229585],"type":"Point"}
}