{
  "type": "Feature",
  "properties": {
    "iso:country":"US",
    "sg:address":"1717 W 86th St",
    "sg:city":"Indianapolis",
    "sg:classifiers":[
        {
            "category":"Shopping",
            "type":"Retail Goods"
        }
    ],
    "sg:phone":"+1 317 471 8564",
    "sg:postcode":"46260",
    "sg:province":"IN",
    "sg:tags":[
        "cosmetic",
        "perfume"
    ],
    "wof:name":"Victoria's Center",
    "wof:placetype":"venue"
},
  "geometry": {"coordinates":[-86.19367099999999,39.911992],"type":"Point"}
}