{
  "type": "Feature",
  "properties": {
    "iso:country":"US",
    "sg:address":"2537 Millville Oxford Rd",
    "sg:city":"Hamilton",
    "sg:classifiers":[
        {
            "category":"Home & Garden",
            "subcategory":"Carpets & Floor Coverings",
            "type":"Retail Goods"
        }
    ],
    "sg:phone":"+1 513 523 9585",
    "sg:postcode":"45013",
    "sg:province":"IN",
    "sg:tags":[
        "dealer",
        "rug"
    ],
    "wof:name":"Austins Floor Store",
    "wof:placetype":"venue"
},
  "geometry": {"coordinates":[-84.68919699999999,39.453838],"type":"Point"}
}