{
  "type": "Feature",
  "properties": {
    "iso:country":"US",
    "sg:address":"122 W Washington St",
    "sg:city":"Elkhart",
    "sg:classifiers":[
        {
            "category":"Manufacturing",
            "subcategory":"Printing",
            "type":"Manufacturing & Wholesale Goods"
        }
    ],
    "sg:phone":"+1 574 295 7000",
    "sg:postcode":"46516",
    "sg:province":"IN",
    "sg:tags":[
        "newspaper"
    ],
    "wof:name":"Tribune Business Weekly",
    "wof:placetype":"venue"
},
  "geometry": {"coordinates":[-85.975059,41.689461],"type":"Point"}
}