{
  "type": "Feature",
  "properties": {
    "iso:country":"US",
    "sg:address":"7665 N Raider Rd",
    "sg:city":"Middletown",
    "sg:classifiers":[
        {
            "category":"Health Services",
            "subcategory":"Hospital",
            "type":"Services"
        }
    ],
    "sg:phone":"+1 765 354 6000",
    "sg:postcode":"47356",
    "sg:province":"IN",
    "sg:tags":[
        "mental"
    ],
    "wof:name":"Christian Counseling Svc",
    "wof:placetype":"venue"
},
  "geometry": {"coordinates":[-85.529383,40.045694],"type":"Point"}
}