{
  "type": "Feature",
  "properties": {
    "iso:country":"US",
    "sg:address":"1904 Washington Ave",
    "sg:city":"Vincennes",
    "sg:classifiers":[
        {
            "category":"Health Services",
            "subcategory":"Hospital",
            "type":"Services"
        }
    ],
    "sg:phone":"+1 812 886 1955",
    "sg:postcode":"47591",
    "sg:province":"IN",
    "sg:tags":[
        "mental"
    ],
    "wof:name":"Dan Linkenhoker",
    "wof:placetype":"venue"
},
  "geometry": {"coordinates":[-87.506753,38.682766],"type":"Point"}
}