{
  "type": "Feature",
  "properties": {
    "iso:country":"US",
    "sg:address":"1902 E Markland Ave",
    "sg:city":"Kokomo",
    "sg:classifiers":[
        {
            "category":"Food & Beverages",
            "subcategory":"Meat & Fish",
            "type":"Retail Goods"
        }
    ],
    "sg:phone":"+1 765 452 3444",
    "sg:postcode":"46901",
    "sg:province":"IN",
    "wof:name":"Country Choice",
    "wof:placetype":"venue"
},
  "geometry": {"coordinates":[-86.10515,40.476768],"type":"Point"}
}