{
  "type": "Feature",
  "properties": {
    "addr:full":"4501 Viking Trl New Castle IN 47362",
    "addr:housenumber":"4501",
    "addr:postcode":"47362",
    "addr:street":"Viking Trl",
    "iso:country":"US",
    "sg:address":"4501 Viking Trl",
    "sg:city":"New Castle",
    "sg:classifiers":[
        {
            "category":"Health Services",
            "subcategory":"Health Practitioner",
            "type":"Services"
        }
    ],
    "sg:phone":"+1 765 593 0231",
    "sg:postcode":"47362",
    "sg:province":"IN",
    "wof:name":"Thera Speech Inc",
    "wof:placetype":"venue"
},
  "geometry": {"coordinates":[-85.32781300000001,39.987896],"type":"Point"}
}