{
  "type": "Feature",
  "properties": {
    "iso:country":"US",
    "sg:address":"623 S Olive St",
    "sg:city":"South Bend",
    "sg:classifiers":[
        {
            "category":"Restaurant",
            "type":"Food & Drink"
        }
    ],
    "sg:phone":"+1 574 289 3663",
    "sg:postcode":"46619",
    "sg:province":"IN",
    "wof:name":"Papinos Pizza",
    "wof:placetype":"venue"
},
  "geometry": {"coordinates":[-86.28332399999999,41.669286],"type":"Point"}
}