{
  "type": "Feature",
  "properties": {
    "addr:full":"6109 Squire Pl Aurora IN 47001",
    "addr:housenumber":"6109",
    "addr:postcode":"47001",
    "addr:street":"Squire Pl",
    "iso:country":"US",
    "sg:address":"6109 Squire Pl",
    "sg:city":"Aurora",
    "sg:classifiers":[
        {
            "category":"Education",
            "subcategory":"School",
            "type":"Public Place"
        }
    ],
    "sg:phone":"+1 812 926 2090",
    "sg:postcode":"47001",
    "sg:province":"IN",
    "wof:name":"South Dearborn Comm Sch Corp",
    "wof:placetype":"venue"
},
  "geometry": {"coordinates":[-84.922145,39.063138],"type":"Point"}
}