{
  "type": "Feature",
  "properties": {
    "addr:full":"115 W Garro St Plymouth IN 46563",
    "addr:housenumber":"115",
    "addr:postcode":"46563",
    "addr:street":"W Garro St",
    "iso:country":"US",
    "sg:address":"115 W Garro St",
    "sg:city":"Plymouth",
    "sg:classifiers":[
        {
            "category":"Professional",
            "subcategory":"Accounting & Tax Preparation",
            "type":"Services"
        }
    ],
    "sg:phone":"+1 574 936 2128",
    "sg:postcode":"46563",
    "sg:province":"IN",
    "sg:tags":[
        "accountant"
    ],
    "wof:name":"Zehner Maloy & Assoc",
    "wof:placetype":"venue"
},
  "geometry": {"coordinates":[-86.309308,41.34075],"type":"Point"}
}