{
  "type": "Feature",
  "properties": {
    "iso:country":"US",
    "sg:address":"6006 N Fail Rd",
    "sg:city":"Laporte",
    "sg:classifiers":[
        {
            "category":"Social Services",
            "type":"Services"
        }
    ],
    "sg:phone":"+1 219 778 9444",
    "sg:postcode":"46350",
    "sg:province":"IN",
    "sg:tags":[
        "food",
        "banks"
    ],
    "wof:name":"Good Shepard Food Pantry",
    "wof:placetype":"venue"
},
  "geometry": {"coordinates":[-86.679278,41.701793],"type":"Point"}
}