{
  "type": "Feature",
  "properties": {
    "addr:full":"300 E Fall Creek Pkwy N Dr Indianapolis IN 46205",
    "addr:housenumber":"300",
    "addr:postcode":"46205",
    "addr:street":"E Fall Creek Pkwy N Dr",
    "iso:country":"US",
    "sg:address":"300 E Fall Creek Pkwy N Dr",
    "sg:city":"Indianapolis",
    "sg:classifiers":[
        {
            "category":"Government",
            "subcategory":"Office",
            "type":"Public Place"
        }
    ],
    "sg:phone":"+1 317 920 0300",
    "sg:postcode":"46205",
    "sg:province":"IN",
    "sg:tags":[
        "village"
    ],
    "wof:name":"Center Twp Trustee",
    "wof:placetype":"venue"
},
  "geometry": {"coordinates":[-86.150724,39.806045],"type":"Point"}
}