{
  "type": "Feature",
  "properties": {
    "iso:country":"US",
    "sg:address":"1434 Johnson St",
    "sg:city":"Elkhart",
    "sg:classifiers":[
        {
            "category":"Government",
            "subcategory":"Office",
            "type":"Public Place"
        }
    ],
    "sg:phone":"+1 574 266 8176",
    "sg:postcode":"46514",
    "sg:province":"IN",
    "wof:name":"US Xchange",
    "wof:placetype":"venue"
},
  "geometry": {"coordinates":[-85.966026,41.702116],"type":"Point"}
}