{
  "type": "Feature",
  "properties": {
    "addr:full":"3564 State Rd 15 Wabash IN 46992",
    "addr:housenumber":"3564;15",
    "addr:postcode":"46992",
    "addr:street":"State Rd",
    "iso:country":"US",
    "sg:address":"3564 State Rd 15",
    "sg:city":"Wabash",
    "sg:classifiers":[
        {
            "category":"Farming",
            "subcategory":"Nursery",
            "type":"Manufacturing & Wholesale Goods"
        }
    ],
    "sg:phone":"+1 260 563 8297",
    "sg:postcode":"46992",
    "sg:province":"IN",
    "sg:tags":[
        "greenhouse"
    ],
    "wof:name":"Southside Gardens",
    "wof:placetype":"venue"
},
  "geometry": {"coordinates":[-85.819536,40.771393],"type":"Point"}
}