{
  "type": "Feature",
  "properties": {
    "addr:full":"6815 S Emerson Ave Indianapolis IN 46237",
    "addr:housenumber":"6815",
    "addr:postcode":"46237",
    "addr:street":"S Emerson Ave",
    "iso:country":"US",
    "sg:address":"6815 S Emerson Ave",
    "sg:city":"Indianapolis",
    "sg:classifiers":[
        {
            "category":"Personal",
            "subcategory":"Beauty Salon",
            "type":"Services"
        }
    ],
    "sg:phone":"+1 317 788 9362",
    "sg:postcode":"46237",
    "sg:province":"IN",
    "wof:name":"Style Trends",
    "wof:placetype":"venue"
},
  "geometry": {"coordinates":[-86.08243899999999,39.668345],"type":"Point"}
}