{
  "type": "Feature",
  "properties": {
    "addr:full":"1630 Coliseum Blvd E Fort Wayne IN 46805",
    "addr:housenumber":"1630",
    "addr:postcode":"46805",
    "addr:street":"Coliseum Blvd E",
    "iso:country":"US",
    "sg:address":"1630 Coliseum Blvd E",
    "sg:city":"Fort Wayne",
    "sg:classifiers":[
        {
            "category":"Autos & Motor Vehicles",
            "subcategory":"Automobile Sales",
            "type":"Retail Goods"
        }
    ],
    "sg:phone":"+1 260 420 3700",
    "sg:postcode":"46805",
    "sg:province":"IN",
    "sg:tags":[
        "car",
        "dealer"
    ],
    "sg:website":"www.jdbyrider.com",
    "wof:name":"J D Byrider Auto Sales",
    "wof:placetype":"venue"
},
  "geometry": {"coordinates":[-85.12460400000001,41.117003],"type":"Point"}
}