{
  "type": "Feature",
  "properties": {
    "iso:country":"US",
    "sg:address":"2505 Gay St",
    "sg:city":"Fort Wayne",
    "sg:classifiers":[
        {
            "category":"Sports & Exercise",
            "subcategory":"Gym",
            "type":"Entertainment"
        }
    ],
    "sg:phone":"+1 260 456 5124",
    "sg:postcode":"46803",
    "sg:province":"IN",
    "sg:tags":[
        "fitness",
        "physical",
        "facility"
    ],
    "wof:name":"Step Up To Fitness Studio",
    "wof:placetype":"venue"
},
  "geometry": {"coordinates":[-85.124216,41.060701],"type":"Point"}
}