{
  "type": "Feature",
  "properties": {
    "iso:country":"US",
    "sg:address":"1951 N Co Rd 200 W",
    "sg:city":"Connersville",
    "sg:classifiers":[
        {
            "category":"Organizations",
            "subcategory":"Religious Organization",
            "type":"Services"
        }
    ],
    "sg:phone":"+1 765 825 7354",
    "sg:postcode":"47331",
    "sg:province":"IN",
    "sg:tags":[
        "church"
    ],
    "wof:name":"Harrisburg Union Church",
    "wof:placetype":"venue"
},
  "geometry": {"coordinates":[-85.176709,39.669557],"type":"Point"}
}