{
  "type": "Feature",
  "properties": {
    "iso:country":"US",
    "sg:address":"2547 N Co Rd 775 W",
    "sg:city":"Petersburg",
    "sg:classifiers":[
        {
            "category":"Freight",
            "type":"Transportation"
        }
    ],
    "sg:phone":"+1 812 354 3311",
    "sg:postcode":"47567",
    "sg:province":"IN",
    "sg:tags":[
        "local",
        "storage",
        "trucking"
    ],
    "wof:name":"Stephen Sullivan",
    "wof:placetype":"venue"
},
  "geometry": {"coordinates":[-87.421351,38.460272],"type":"Point"}
}