{
  "type": "Feature",
  "properties": {
    "addr:full":"1618 W 3rd St Bloomington IN 47404",
    "addr:housenumber":"1618",
    "addr:postcode":"47404",
    "addr:street":"W 3Rd St",
    "iso:country":"US",
    "sg:address":"1618 W 3rd St",
    "sg:city":"Bloomington",
    "sg:classifiers":[
        {
            "category":"Insurance",
            "subcategory":"Hazard Insurance",
            "type":"Services"
        }
    ],
    "sg:phone":"+1 812 336 0174",
    "sg:postcode":"47404",
    "sg:province":"IN",
    "sg:website":"www.infarmbureau.com",
    "wof:name":"Farm Bureau Insurance",
    "wof:placetype":"venue"
},
  "geometry": {"coordinates":[-86.554497,39.164501],"type":"Point"}
}