{
  "type": "Feature",
  "properties": {
    "iso:country":"US",
    "sg:address":"183 Cheshire Ln",
    "sg:city":"Hardinsburg",
    "sg:classifiers":[
        {
            "category":"Social Services",
            "subcategory":"Adult Care",
            "type":"Services"
        }
    ],
    "sg:phone":"+1 812 472 9059",
    "sg:postcode":"47125",
    "sg:province":"IN",
    "sg:tags":[
        "organization",
        "senior",
        "citizen"
    ],
    "wof:name":"Hardinsburg Senior Citizens",
    "wof:placetype":"venue"
},
  "geometry": {"coordinates":[-86.27704,38.459426],"type":"Point"}
}