{
  "type": "Feature",
  "properties": {
    "iso:country":"US",
    "sg:address":"124 W 11th St",
    "sg:city":"Michigan City",
    "sg:classifiers":[
        {
            "category":"Bus Charters",
            "type":"Transportation"
        }
    ],
    "sg:phone":"+1 219 879 7224",
    "sg:postcode":"46360",
    "sg:province":"IN",
    "sg:tags":[
        "rental"
    ],
    "wof:name":"Always Business Svc",
    "wof:placetype":"venue"
},
  "geometry": {"coordinates":[-86.900014,41.711027],"type":"Point"}
}