{
  "type": "Feature",
  "properties": {
    "iso:country":"US",
    "sg:address":"1001 W Co Rd 900 S",
    "sg:city":"Carlisle",
    "sg:classifiers":[
        {
            "category":"Mining & Drilling",
            "type":"Manufacturing & Wholesale Goods"
        }
    ],
    "sg:phone":"+1 812 659 3392",
    "sg:postcode":"47838",
    "sg:province":"IN",
    "sg:tags":[
        "coal",
        "shipping"
    ],
    "wof:name":"Hawthorn Mine",
    "wof:placetype":"venue"
},
  "geometry": {"coordinates":[-87.430317,38.94607],"type":"Point"}
}