{
  "type": "Feature",
  "properties": {
    "iso:country":"US",
    "sg:address":"10849 US Hwy 36",
    "sg:city":"Avon",
    "sg:classifiers":[
        {
            "category":"Shopping",
            "subcategory":"Clothing, Apparel, & Fashions",
            "type":"Retail Goods"
        }
    ],
    "sg:phone":"+1 317 209 1245",
    "sg:postcode":"46123",
    "sg:province":"IN",
    "sg:tags":[
        "furnishing"
    ],
    "wof:name":"Men's Wearhouse",
    "wof:placetype":"venue"
},
  "geometry": {"coordinates":[-86.327416,39.763541],"type":"Point"}
}