{
  "type": "Feature",
  "properties": {
    "iso:country":"US",
    "sg:address":"26125 Co Rd 54",
    "sg:city":"Nappanee",
    "sg:classifiers":[
        {
            "category":"Farming",
            "subcategory":"Dairy Farm",
            "type":"Manufacturing & Wholesale Goods"
        }
    ],
    "sg:phone":"+1 574 773 3776",
    "sg:postcode":"46550",
    "sg:province":"IN",
    "sg:tags":[
        "corn",
        "soybean"
    ],
    "wof:name":"Lyle Miller",
    "wof:placetype":"venue"
},
  "geometry": {"coordinates":[-85.96361400000001,41.450148],"type":"Point"}
}