{
  "type": "Feature",
  "properties": {
    "iso:country":"US",
    "sg:address":"8487 Union Chapel Rd",
    "sg:city":"Indianapolis",
    "sg:classifiers":[
        {
            "category":"Restaurant",
            "type":"Food & Drink"
        }
    ],
    "sg:phone":"+1 317 259 4000",
    "sg:postcode":"46240",
    "sg:province":"IN",
    "sg:tags":[
        "delicatessen"
    ],
    "wof:name":"Mc Alister's Deli",
    "wof:placetype":"venue"
},
  "geometry": {"coordinates":[-86.10798,39.909583],"type":"Point"}
}