{
  "type": "Feature",
  "properties": {
    "iso:country":"US",
    "sg:address":"366 W Main St",
    "sg:city":"Rossville",
    "sg:classifiers":[
        {
            "category":"Shopping",
            "subcategory":"Pharmacy",
            "type":"Retail Goods"
        }
    ],
    "sg:phone":"+1 765 379 2517",
    "sg:postcode":"46065",
    "sg:province":"IN",
    "wof:name":"CVS Pharmacy",
    "wof:placetype":"venue"
},
  "geometry": {"coordinates":[-86.60050200000001,40.41702],"type":"Point"}
}