{
  "type": "Feature",
  "properties": {
    "iso:country":"US",
    "sg:address":"226 E Hardy Rd",
    "sg:city":"Underwood",
    "sg:classifiers":[
        {
            "category":"Manufacturing",
            "subcategory":"Building Materials",
            "type":"Manufacturing & Wholesale Goods"
        }
    ],
    "sg:phone":"+1 812 752 5800",
    "sg:postcode":"47177",
    "sg:province":"IN",
    "sg:tags":[
        "cabinet"
    ],
    "wof:name":"D & J Custom Cabinets Inc",
    "wof:placetype":"venue"
},
  "geometry": {"coordinates":[-85.772167,38.608935],"type":"Point"}
}