{
  "type": "Feature",
  "properties": {
    "iso:country":"US",
    "sg:address":"2466 E 116th St",
    "sg:city":"Carmel",
    "sg:classifiers":[
        {
            "category":"Shopping",
            "subcategory":"Florist",
            "type":"Retail Goods"
        }
    ],
    "sg:phone":"+1 317 843 9200",
    "sg:postcode":"46032",
    "sg:province":"IN",
    "wof:name":"Rue De Fleurs",
    "wof:placetype":"venue"
},
  "geometry": {"coordinates":[-86.114852,39.956723],"type":"Point"}
}