{
  "type": "Feature",
  "properties": {
    "iso:country":"US",
    "sg:address":"101 Lincoln St",
    "sg:city":"Somerville",
    "sg:classifiers":[
        {
            "category":"Organizations",
            "subcategory":"Religious Organization",
            "type":"Services"
        }
    ],
    "sg:phone":"+1 812 795 2255",
    "sg:postcode":"47683",
    "sg:province":"IN",
    "sg:tags":[
        "church"
    ],
    "wof:name":"Somerville Wesleyan Church",
    "wof:placetype":"venue"
},
  "geometry": {"coordinates":[-87.377589,38.277273],"type":"Point"}
}