{
  "type": "Feature",
  "properties": {
    "addr:full":"370 W Eads Pkwy Lawrenceburg IN 47025",
    "addr:housenumber":"370",
    "addr:postcode":"47025",
    "addr:street":"W Eads Pkwy",
    "iso:country":"US",
    "sg:address":"370 W Eads Pkwy",
    "sg:city":"Lawrenceburg",
    "sg:classifiers":[
        {
            "category":"Utilities",
            "subcategory":"Sewage",
            "type":"Services"
        }
    ],
    "sg:phone":"+1 812 537 0457",
    "sg:postcode":"47025",
    "sg:province":"IN",
    "sg:tags":[
        "system",
        "sewerage"
    ],
    "wof:name":"South Drborn Rgonal Sewer Dist",
    "wof:placetype":"venue"
},
  "geometry": {"coordinates":[-84.85914200000001,39.09584],"type":"Point"}
}