{
  "type": "Feature",
  "properties": {
    "addr:full":"7024 State Rd 311 Sellersburg IN 47172",
    "addr:housenumber":"7024",
    "addr:postcode":"47172",
    "addr:street":"State Rd 311",
    "iso:country":"US",
    "sg:address":"7024 State Rd 311",
    "sg:city":"Sellersburg",
    "sg:classifiers":[
        {
            "category":"Building & Trades",
            "subcategory":"Construction",
            "type":"Services"
        }
    ],
    "sg:phone":"+1 812 246 8865",
    "sg:postcode":"47172",
    "sg:province":"IN",
    "sg:tags":[
        "general",
        "contractor"
    ],
    "wof:name":"Klein Development Co Inc",
    "wof:placetype":"venue"
},
  "geometry": {"coordinates":[-85.77280500000001,38.373724],"type":"Point"}
}