{
  "type": "Feature",
  "properties": {
    "iso:country":"US",
    "sg:address":"151 E Spring St",
    "sg:city":"New Albany",
    "sg:classifiers":[
        {
            "category":"Professional",
            "subcategory":"Business Services",
            "type":"Services"
        }
    ],
    "sg:phone":"+1 812 949 2333",
    "sg:postcode":"47150",
    "sg:province":"IN",
    "sg:tags":[
        "interior",
        "consultant",
        "design",
        "decorator"
    ],
    "wof:name":"Creative Designs",
    "wof:placetype":"venue"
},
  "geometry": {"coordinates":[-85.822372,38.286316],"type":"Point"}
}