{
  "type": "Feature",
  "properties": {
    "addr:full":"3283 Co Rd 45 Waterloo IN 46793",
    "addr:housenumber":"3283;45",
    "addr:postcode":"46793",
    "addr:street":"Co Rd",
    "iso:country":"US",
    "sg:address":"3283 Co Rd 45",
    "sg:city":"Waterloo",
    "sg:classifiers":[
        {
            "category":"Personal",
            "subcategory":"Beauty Salon",
            "type":"Services"
        }
    ],
    "sg:phone":"+1 260 837 2005",
    "sg:postcode":"46793",
    "sg:province":"IN",
    "sg:tags":[
        "shop"
    ],
    "wof:name":"Jans Country Salon",
    "wof:placetype":"venue"
},
  "geometry": {"coordinates":[-84.976409,41.413605],"type":"Point"}
}