{
  "type": "Feature",
  "properties": {
    "addr:full":"1000 W Wilden Ave Goshen IN 46528",
    "addr:housenumber":"1000",
    "addr:postcode":"46528",
    "addr:street":"W Wilden Ave",
    "iso:country":"US",
    "sg:address":"1000 W Wilden Ave",
    "sg:city":"Goshen",
    "sg:classifiers":[
        {
            "category":"Government",
            "subcategory":"Office",
            "type":"Public Place"
        }
    ],
    "sg:phone":"+1 574 534 4102",
    "sg:postcode":"46528",
    "sg:province":"IN",
    "sg:tags":[
        "govt",
        "city"
    ],
    "wof:name":"Goshen Wastewater Treatment",
    "wof:placetype":"venue"
},
  "geometry": {"coordinates":[-85.848787,41.597207],"type":"Point"}
}