{
  "type": "Feature",
  "properties": {
    "iso:country":"US",
    "sg:address":"1009 Broad Ripple Ave",
    "sg:city":"Indianapolis",
    "sg:classifiers":[
        {
            "category":"Recreation",
            "subcategory":"Water Park",
            "type":"Entertainment"
        },
        {
            "category":"Building & Trades",
            "subcategory":"Plumbing",
            "type":"Services"
        },
        {
            "category":"Home & Garden",
            "subcategory":"Hardware",
            "type":"Retail Goods"
        },
        {
            "category":"Food & Beverages",
            "subcategory":"Specialty",
            "type":"Retail Goods"
        },
        {
            "category":"Manufacturing",
            "subcategory":"Chemicals & Compounds",
            "type":"Manufacturing & Wholesale Goods"
        },
        {
            "category":"Food & Beverages",
            "subcategory":"Fruits & Vegetables",
            "type":"Retail Goods"
        },
        {
            "category":"Utilities",
            "subcategory":"Water",
            "type":"Services"
        },
        {
            "category":"Food & Beverages",
            "subcategory":"Groceries & Convenience Stores",
            "type":"Retail Goods"
        }
    ],
    "sg:phone":"+1 317 251 9223",
    "sg:postcode":"46220",
    "sg:province":"IN",
    "sg:tags":[
        "filtration",
        "softening",
        "supply",
        "herb",
        "work",
        "purification",
        "filter",
        "equipment",
        "fountain",
        "conditioning",
        "equipment-service",
        "spice",
        "salt",
        "coolers",
        "treatment"
    ],
    "sg:website":"http://www.elginwater.com",
    "wof:name":"Elgin Watercare",
    "wof:placetype":"venue"
},
  "geometry": {"coordinates":[-86.140968,39.869719],"type":"Point"}
}