{
  "type": "Feature",
  "properties": {
    "addr:full":"5190 S US Hwy 31 Columbus IN 47201",
    "addr:housenumber":"5190",
    "addr:postcode":"47201",
    "addr:street":"S Us Hwy 31",
    "iso:country":"US",
    "sg:address":"5190 S US Hwy 31",
    "sg:city":"Columbus",
    "sg:classifiers":[
        {
            "category":"Farming",
            "subcategory":"Nursery",
            "type":"Manufacturing & Wholesale Goods"
        }
    ],
    "sg:phone":"+1 812 372 4216",
    "sg:postcode":"47201",
    "sg:province":"IN",
    "sg:tags":[
        "greenhouse"
    ],
    "wof:name":"Whipker's Market & Greenhouse",
    "wof:placetype":"venue"
},
  "geometry": {"coordinates":[-85.841696,39.15266],"type":"Point"}
}