{
  "type": "Feature",
  "properties": {
    "iso:country":"US",
    "sg:address":"1325 N Main St",
    "sg:city":"Auburn",
    "sg:classifiers":[
        {
            "category":"Insurance",
            "subcategory":"Insurance Agent",
            "type":"Services"
        }
    ],
    "sg:phone":"+1 260 925 0100",
    "sg:postcode":"46706",
    "sg:province":"IN",
    "wof:name":"Korff Insurance Agency",
    "wof:placetype":"venue"
},
  "geometry": {"coordinates":[-85.054644,41.376975],"type":"Point"}
}