{
  "type": "Feature",
  "properties": {
    "iso:country":"US",
    "sg:address":"408 S 9th St",
    "sg:city":"Noblesville",
    "sg:classifiers":[
        {
            "category":"Organizations",
            "subcategory":"Non-profit Organization",
            "type":"Services"
        }
    ],
    "sg:phone":"+1 317 773 0728",
    "sg:postcode":"46060",
    "sg:province":"IN",
    "sg:tags":[
        "fund",
        "counselor",
        "raising"
    ],
    "wof:name":"Victory Card",
    "wof:placetype":"venue"
},
  "geometry": {"coordinates":[-86.01339400000001,40.042251],"type":"Point"}
}