{
  "type": "Feature",
  "properties": {
    "iso:country":"US",
    "sg:address":"2601 Shelby St",
    "sg:city":"Indianapolis",
    "sg:classifiers":[
        {
            "category":"Real Estate",
            "subcategory":"Real Estate Agent",
            "type":"Services"
        }
    ],
    "sg:phone":"+1 317 783 7368",
    "sg:postcode":"46203",
    "sg:province":"IN",
    "wof:name":"MFC Property Management",
    "wof:placetype":"venue"
},
  "geometry": {"coordinates":[-86.139641,39.729388],"type":"Point"}
}