{
  "type": "Feature",
  "properties": {
    "iso:country":"US",
    "sg:address":"304 N Walnut St",
    "sg:city":"Plymouth",
    "sg:classifiers":[
        {
            "category":"Professional",
            "subcategory":"Advertising",
            "type":"Services"
        }
    ],
    "sg:phone":"+1 574 936 5078",
    "sg:postcode":"46563",
    "sg:province":"IN",
    "sg:tags":[
        "guide"
    ],
    "wof:name":"Coupons & More",
    "wof:placetype":"venue"
},
  "geometry": {"coordinates":[-86.311775,41.342422],"type":"Point"}
}