{
  "type": "Feature",
  "properties": {
    "iso:country":"US",
    "sg:address":"4 N Washington St",
    "sg:city":"Worthington",
    "sg:classifiers":[
        {
            "category":"Education",
            "subcategory":"School",
            "type":"Public Place"
        }
    ],
    "sg:phone":"+1 812 875 2025",
    "sg:postcode":"47471",
    "sg:province":"IN",
    "wof:name":"White River Valley School Dist",
    "wof:placetype":"venue"
},
  "geometry": {"coordinates":[-86.97645900000001,39.119012],"type":"Point"}
}