{
  "type": "Feature",
  "properties": {
    "iso:country":"US",
    "sg:address":"1010 W 21st St",
    "sg:city":"Anderson",
    "sg:classifiers":[
        {
            "category":"Manufacturing",
            "subcategory":"Metals",
            "type":"Manufacturing & Wholesale Goods"
        }
    ],
    "sg:phone":"+1 765 642 3549",
    "sg:postcode":"46016",
    "sg:province":"IN",
    "sg:tags":[
        "brass",
        "foundry",
        "bronze"
    ],
    "wof:name":"Dillon Pattern Works & Foundry",
    "wof:placetype":"venue"
},
  "geometry": {"coordinates":[-85.693047,40.095419],"type":"Point"}
}