{
  "type": "Feature",
  "properties": {
    "iso:country":"US",
    "sg:address":"257 Indiana Ave",
    "sg:city":"Valparaiso",
    "sg:classifiers":[
        {
            "category":"Professional",
            "subcategory":"Accounting & Tax Preparation",
            "type":"Services"
        }
    ],
    "sg:phone":"+1 219 462 1956",
    "sg:postcode":"46383",
    "sg:province":"IN",
    "sg:tags":[
        "accountant"
    ],
    "wof:name":"John H Shroat CPA",
    "wof:placetype":"venue"
},
  "geometry": {"coordinates":[-87.063509,41.466806],"type":"Point"}
}