{
  "type": "Feature",
  "properties": {
    "iso:country":"US",
    "sg:address":"2911 Georgetown Rd",
    "sg:city":"Indianapolis",
    "sg:classifiers":[
        {
            "category":"Retail",
            "subcategory":"Self-service Laundry",
            "type":"Services"
        }
    ],
    "sg:phone":"+1 317 293 2926",
    "sg:postcode":"46224",
    "sg:province":"IN",
    "wof:name":"Speed Queen 500 Laundry & Dry",
    "wof:placetype":"venue"
},
  "geometry": {"coordinates":[-86.239799,39.8093],"type":"Point"}
}