{
  "type": "Feature",
  "properties": {
    "iso:country":"US",
    "sg:address":"4820 Desoto Dr",
    "sg:city":"Fort Wayne",
    "sg:classifiers":[
        {
            "category":"Real Estate",
            "subcategory":"Real Estate Agent",
            "type":"Services"
        }
    ],
    "sg:phone":"+1 260 483 1330",
    "sg:postcode":"46815",
    "sg:province":"IN",
    "sg:website":"www.ftwaynehomes.com",
    "wof:name":"Duesler Realty House",
    "wof:placetype":"venue"
},
  "geometry": {"coordinates":[-85.078875,41.104311],"type":"Point"}
}