{
  "type": "Feature",
  "properties": {
    "iso:country":"US",
    "sg:address":"4678 E 100 S",
    "sg:city":"Laporte",
    "sg:classifiers":[
        {
            "category":"Professional",
            "subcategory":"Business Services",
            "type":"Services"
        }
    ],
    "sg:phone":"+1 219 324 7055",
    "sg:postcode":"46350",
    "sg:province":"IN",
    "sg:tags":[
        "auctioneer"
    ],
    "wof:name":"Lee J Wainscott Auctioneer",
    "wof:placetype":"venue"
},
  "geometry": {"coordinates":[-86.61339,41.591779],"type":"Point"}
}