{
  "type": "Feature",
  "properties": {
    "iso:country":"US",
    "sg:address":"7180 Warrior Trl",
    "sg:city":"Indianapolis",
    "sg:classifiers":[
        {
            "category":"Personal",
            "subcategory":"Beauty Salon",
            "type":"Services"
        }
    ],
    "sg:phone":"+1 317 202 0272",
    "sg:postcode":"46260",
    "sg:province":"IN",
    "wof:name":"El Prestige African Hair Brdng",
    "wof:placetype":"venue"
},
  "geometry": {"coordinates":[-86.194638,39.883817],"type":"Point"}
}