{
  "type": "Feature",
  "properties": {
    "iso:country":"US",
    "sg:address":"513 National Ave",
    "sg:city":"Indianapolis",
    "sg:classifiers":[
        {
            "category":"Professional",
            "type":"Services"
        }
    ],
    "sg:phone":"+1 317 783 0940",
    "sg:postcode":"46227",
    "sg:province":"IN",
    "wof:name":"Hanover Service Ctr",
    "wof:placetype":"venue"
},
  "geometry": {"coordinates":[-86.144819,39.711639],"type":"Point"}
}