{
  "type": "Feature",
  "properties": {
    "addr:full":"10583 W 950 S Covington IN 47932",
    "addr:housenumber":"10583",
    "addr:postcode":"47932",
    "addr:street":"W 950 S",
    "iso:country":"US",
    "sg:address":"10583 W 950 S",
    "sg:city":"Covington",
    "sg:classifiers":[
        {
            "category":"Manufacturing",
            "subcategory":"Food",
            "type":"Manufacturing & Wholesale Goods"
        },
        {
            "category":"Farming",
            "subcategory":"Farm",
            "type":"Manufacturing & Wholesale Goods"
        }
    ],
    "sg:phone":"+1 765 793 2886",
    "sg:postcode":"47932",
    "sg:province":"IN",
    "sg:tags":[
        "corn",
        "product"
    ],
    "wof:name":"Paul Kirkpatrick",
    "wof:placetype":"venue"
},
  "geometry": {"coordinates":[-87.520039,40.177395],"type":"Point"}
}