{
  "type": "Feature",
  "properties": {
    "iso:country":"US",
    "sg:address":"4399 Spruce Dr",
    "sg:city":"Newburgh",
    "sg:classifiers":[
        {
            "category":"Shopping",
            "subcategory":"Computers & Home Electronics",
            "type":"Retail Goods"
        }
    ],
    "sg:phone":"+1 812 853 7487",
    "sg:postcode":"47630",
    "sg:province":"IN",
    "sg:tags":[
        "equipment",
        "dealer"
    ],
    "wof:name":"Midwestern Marketing Co",
    "wof:placetype":"venue"
},
  "geometry": {"coordinates":[-87.404208,37.971386],"type":"Point"}
}