{
  "type": "Feature",
  "properties": {
    "addr:full":"9105 Indianapolis Blvd Highland IN 46322",
    "addr:housenumber":"9105",
    "addr:postcode":"46322",
    "addr:street":"Indianapolis Blvd",
    "iso:country":"US",
    "sg:address":"9105 Indianapolis Blvd",
    "sg:city":"Highland",
    "sg:classifiers":[
        {
            "category":"Professional",
            "subcategory":"Lawyer & Legal Services",
            "type":"Services"
        }
    ],
    "sg:phone":"+1 219 989 7380",
    "sg:postcode":"46322",
    "sg:province":"IN",
    "wof:name":"Irons Jennifer Atty",
    "wof:placetype":"venue"
},
  "geometry": {"coordinates":[-87.471107,41.548335],"type":"Point"}
}