{
  "type": "Feature",
  "properties": {
    "iso:country":"US",
    "sg:address":"212 N Morton Ave",
    "sg:city":"Centerville",
    "sg:classifiers":[
        {
            "category":"Wholesale",
            "subcategory":"Construction Materials",
            "type":"Manufacturing & Wholesale Goods"
        }
    ],
    "sg:phone":"+1 765 855 5500",
    "sg:postcode":"47330",
    "sg:province":"IN",
    "sg:tags":[
        "fence"
    ],
    "wof:name":"J & S Fencing",
    "wof:placetype":"venue"
},
  "geometry": {"coordinates":[-84.996365,39.819069],"type":"Point"}
}