{
  "type": "Feature",
  "properties": {
    "iso:country":"US",
    "sg:address":"400 S Market St",
    "sg:city":"Rockville",
    "sg:classifiers":[
        {
            "category":"Home & Garden",
            "subcategory":"Building Materials",
            "type":"Retail Goods"
        }
    ],
    "sg:phone":"+1 765 569 3113",
    "sg:postcode":"47872",
    "sg:province":"IN",
    "sg:tags":[
        "lumber"
    ],
    "wof:name":"Ferguson Lumber Corp",
    "wof:placetype":"venue"
},
  "geometry": {"coordinates":[-87.229314,39.759032],"type":"Point"}
}