{
  "type": "Feature",
  "properties": {
    "iso:country":"US",
    "sg:address":"1817 I Ave",
    "sg:city":"New Castle",
    "sg:classifiers":[
        {
            "category":"Autos & Motor Vehicles",
            "subcategory":"Automobile Sales",
            "type":"Retail Goods"
        }
    ],
    "sg:phone":"+1 765 747 5096",
    "sg:postcode":"47362",
    "sg:province":"IN",
    "sg:tags":[
        "car",
        "dealer"
    ],
    "wof:name":"Chrysler Corp",
    "wof:placetype":"venue"
},
  "geometry": {"coordinates":[-85.362968,39.916803],"type":"Point"}
}