{
  "type": "Feature",
  "properties": {
    "iso:country":"US",
    "sg:address":"722 W Pearl St",
    "sg:city":"Lebanon",
    "sg:classifiers":[
        {
            "category":"Building & Trades",
            "subcategory":"Construction",
            "type":"Services"
        }
    ],
    "sg:phone":"+1 765 483 1750",
    "sg:postcode":"46052",
    "sg:province":"IN",
    "sg:tags":[
        "ceiling"
    ],
    "wof:name":"Acoustical Ceiling Systems",
    "wof:placetype":"venue"
},
  "geometry": {"coordinates":[-86.474554,40.045874],"type":"Point"}
}