{
  "type": "Feature",
  "properties": {
    "iso:country":"US",
    "sg:address":"1651 Thornapple Cir",
    "sg:city":"Valparaiso",
    "sg:classifiers":[
        {
            "category":"Health Services",
            "subcategory":"Doctor",
            "type":"Services"
        }
    ],
    "sg:phone":"+1 219 462 9937",
    "sg:postcode":"46385",
    "sg:province":"IN",
    "sg:tags":[
        "physician",
        "surgeon"
    ],
    "wof:name":"Heritage Ear Nose & Throat",
    "wof:placetype":"venue"
},
  "geometry": {"coordinates":[-87.081497,41.45914],"type":"Point"}
}