{
  "type": "Feature",
  "properties": {
    "iso:country":"US",
    "sg:address":"384 Co Rd 11",
    "sg:city":"Hudson",
    "sg:classifiers":[
        {
            "category":"Real Estate",
            "subcategory":"Real Estate Operator",
            "type":"Services"
        }
    ],
    "sg:phone":"+1 260 587 9488",
    "sg:postcode":"46747",
    "sg:province":"IN",
    "sg:tags":[
        "mobile",
        "home",
        "site"
    ],
    "wof:name":"Paradise Park Inc",
    "wof:placetype":"venue"
},
  "geometry": {"coordinates":[-85.134548,41.516583],"type":"Point"}
}