{
  "type": "Feature",
  "properties": {
    "iso:country":"US",
    "sg:address":"406 16th St",
    "sg:city":"Bedford",
    "sg:classifiers":[
        {
            "category":"Restaurant",
            "type":"Food & Drink"
        }
    ],
    "sg:phone":"+1 812 277 8888",
    "sg:postcode":"47421",
    "sg:province":"IN",
    "wof:name":"Pizza King",
    "wof:placetype":"venue"
},
  "geometry": {"coordinates":[-86.475521,38.861132],"type":"Point"}
}