{
  "type": "Feature",
  "properties": {
    "addr:full":"8701 Parkway Dr Highland IN 46322",
    "addr:housenumber":"8701",
    "addr:postcode":"46322",
    "addr:street":"Parkway Dr",
    "iso:country":"US",
    "sg:address":"8701 Parkway Dr",
    "sg:city":"Highland",
    "sg:classifiers":[
        {
            "category":"Professional",
            "subcategory":"Engineering",
            "type":"Services"
        }
    ],
    "sg:phone":"+1 219 838 9580",
    "sg:postcode":"46322",
    "sg:province":"IN",
    "sg:tags":[
        "engineer"
    ],
    "wof:name":"Comsub Design & Engineering",
    "wof:placetype":"venue"
},
  "geometry": {"coordinates":[-87.48004299999999,41.553477],"type":"Point"}
}