{
  "type": "Feature",
  "properties": {
    "iso:country":"US",
    "sg:address":"180 S Windy Shore Dr",
    "sg:city":"Lexington",
    "sg:classifiers":[
        {
            "category":"Real Estate",
            "subcategory":"Real Estate Operator",
            "type":"Services"
        }
    ],
    "sg:phone":"+1 812 889 3113",
    "sg:postcode":"47138",
    "sg:province":"IN",
    "sg:tags":[
        "property",
        "lessor"
    ],
    "wof:name":"Donald L Jones Inc",
    "wof:placetype":"venue"
},
  "geometry": {"coordinates":[-85.665692,38.691859],"type":"Point"}
}