{
  "type": "Feature",
  "properties": {
    "iso:country":"US",
    "sg:address":"5251 W 1500 N",
    "sg:city":"Silver Lake",
    "sg:classifiers":[
        {
            "category":"Professional",
            "subcategory":"Management & Consulting",
            "type":"Services"
        }
    ],
    "sg:phone":"+1 260 352 0009",
    "sg:postcode":"46982",
    "sg:province":"IN",
    "sg:tags":[
        "marketing",
        "program"
    ],
    "wof:name":"Woodside Marketing",
    "wof:placetype":"venue"
},
  "geometry": {"coordinates":[-85.929631,41.04273],"type":"Point"}
}