{
  "type": "Feature",
  "properties": {
    "iso:country":"US",
    "sg:address":"300 N High St",
    "sg:city":"Muncie",
    "sg:classifiers":[
        {
            "category":"Government",
            "subcategory":"Office",
            "type":"Public Place"
        }
    ],
    "sg:phone":"+1 765 747 4862",
    "sg:postcode":"47305",
    "sg:province":"IN",
    "sg:tags":[
        "village"
    ],
    "sg:website":"www.cityofmuncie.com",
    "wof:name":"Muncie Building Commissioner",
    "wof:placetype":"venue"
},
  "geometry": {"coordinates":[-85.388441,40.196638],"type":"Point"}
}