{
  "type": "Feature",
  "properties": {
    "iso:country":"US",
    "sg:address":"5901 Waite St",
    "sg:city":"Merrillville",
    "sg:classifiers":[
        {
            "category":"Education",
            "subcategory":"School",
            "type":"Public Place"
        }
    ],
    "sg:phone":"+1 219 650 5303",
    "sg:postcode":"46410",
    "sg:province":"IN",
    "wof:name":"Miller Elementary School",
    "wof:placetype":"venue"
},
  "geometry": {"coordinates":[-87.375938,41.510082],"type":"Point"}
}