{
  "type": "Feature",
  "properties": {
    "iso:country":"US",
    "sg:address":"7001 N State Rd 39",
    "sg:city":"Laporte",
    "sg:classifiers":[
        {
            "category":"Retail",
            "subcategory":"Repair Shop",
            "type":"Services"
        }
    ],
    "sg:phone":"+1 219 325 0414",
    "sg:postcode":"46350",
    "sg:province":"IN",
    "sg:tags":[
        "refrigerating"
    ],
    "sg:website":"www.midstatesrefrig.com",
    "wof:name":"Mid-States Refrigeration Supl",
    "wof:placetype":"venue"
},
  "geometry": {"coordinates":[-86.732619,41.716779],"type":"Point"}
}