{
  "type": "Feature",
  "properties": {
    "addr:full":"312 E Broadway St Logansport IN 46947",
    "addr:housenumber":"312",
    "addr:postcode":"46947",
    "addr:street":"E Broadway St",
    "iso:country":"US",
    "sg:address":"312 E Broadway St",
    "sg:city":"Logansport",
    "sg:classifiers":[
        {
            "category":"Government",
            "subcategory":"Office",
            "type":"Public Place"
        }
    ],
    "sg:phone":"+1 574 735 3615",
    "sg:postcode":"46947",
    "sg:province":"IN",
    "sg:tags":[
        "armed",
        "force",
        "recruiting"
    ],
    "wof:name":"US Army Recruiting",
    "wof:placetype":"venue"
},
  "geometry": {"coordinates":[-86.365264,40.754197],"type":"Point"}
}