{
  "type": "Feature",
  "properties": {
    "iso:country":"US",
    "sg:address":"6430 Adams Center Rd",
    "sg:city":"Fort Wayne",
    "sg:classifiers":[
        {
            "category":"Building & Trades",
            "subcategory":"Construction",
            "type":"Services"
        }
    ],
    "sg:phone":"+1 260 441 0425",
    "sg:postcode":"46816",
    "sg:province":"IN",
    "sg:tags":[
        "home",
        "improvement"
    ],
    "wof:name":"Mike Dye Maintenance Inc",
    "wof:placetype":"venue"
},
  "geometry": {"coordinates":[-85.05777999999999,41.024367],"type":"Point"}
}