{
  "type": "Feature",
  "properties": {
    "iso:country":"US",
    "sg:address":"701 Superior Ave",
    "sg:city":"Munster",
    "sg:classifiers":[
        {
            "category":"Health Services",
            "subcategory":"Doctor",
            "type":"Services"
        }
    ],
    "sg:phone":"+1 219 922 3040",
    "sg:postcode":"46321",
    "sg:province":"IN",
    "sg:tags":[
        "physician",
        "surgeon"
    ],
    "wof:name":"Consultants Gastroenterology",
    "wof:placetype":"venue"
},
  "geometry": {"coordinates":[-87.5112,41.537272],"type":"Point"}
}