{
  "type": "Feature",
  "properties": {
    "iso:country":"US",
    "sg:address":"3010 Trier Rd",
    "sg:city":"Fort Wayne",
    "sg:classifiers":[
        {
            "category":"Restaurant",
            "type":"Food & Drink"
        }
    ],
    "sg:phone":"+1 260 482 4342",
    "sg:postcode":"46815",
    "sg:province":"IN",
    "wof:name":"Triangle Park",
    "wof:placetype":"venue"
},
  "geometry": {"coordinates":[-85.104316,41.11168],"type":"Point"}
}