{
  "type": "Feature",
  "properties": {
    "iso:country":"US",
    "sg:address":"2908 State Rd 47 S",
    "sg:city":"Crawfordsville",
    "sg:classifiers":[
        {
            "category":"Building & Trades",
            "subcategory":"Construction",
            "type":"Services"
        }
    ],
    "sg:phone":"+1 765 362 8343",
    "sg:postcode":"47933",
    "sg:province":"IN",
    "sg:tags":[
        "concrete",
        "contractor"
    ],
    "wof:name":"Kincaid Concrete Co",
    "wof:placetype":"venue"
},
  "geometry": {"coordinates":[-86.923284,39.997782],"type":"Point"}
}