{
  "type": "Feature",
  "properties": {
    "iso:country":"US",
    "sg:address":"1247 169th St",
    "sg:city":"Hammond",
    "sg:classifiers":[
        {
            "category":"Social Services",
            "type":"Services"
        }
    ],
    "sg:phone":"+1 219 989 2027",
    "sg:postcode":"46324",
    "sg:province":"IN",
    "sg:tags":[
        "counselor"
    ],
    "wof:name":"Marriage & Family Therapy Ctr",
    "wof:placetype":"venue"
},
  "geometry": {"coordinates":[-87.496409,41.588453],"type":"Point"}
}