{
  "type": "Feature",
  "properties": {
    "iso:country":"US",
    "sg:address":"1900 W 50th St",
    "sg:city":"Marion",
    "sg:classifiers":[
        {
            "category":"Professional",
            "type":"Services"
        }
    ],
    "sg:phone":"+1 765 674 5482",
    "sg:postcode":"46953",
    "sg:province":"IN",
    "sg:tags":[
        "establishment"
    ],
    "wof:name":"Institute For Professional Dev",
    "wof:placetype":"venue"
},
  "geometry": {"coordinates":[-85.687435,40.509483],"type":"Point"}
}