{
  "type": "Feature",
  "properties": {
    "iso:country":"US",
    "sg:address":"111 E Columbia St",
    "sg:city":"Evansville",
    "sg:classifiers":[
        {
            "category":"Professional",
            "subcategory":"Detective & Security Services",
            "type":"Services"
        }
    ],
    "sg:phone":"+1 812 422 8515",
    "sg:postcode":"47711",
    "sg:province":"IN",
    "sg:tags":[
        "guard",
        "patrol"
    ],
    "wof:name":"Comaier Services Inc",
    "wof:placetype":"venue"
},
  "geometry": {"coordinates":[-87.561246,37.98465],"type":"Point"}
}