{
  "type": "Feature",
  "properties": {
    "addr:full":"7999 Silverleaf Dr Indianapolis IN 46260",
    "addr:housenumber":"7999",
    "addr:postcode":"46260",
    "addr:street":"Silverleaf Dr",
    "iso:country":"US",
    "sg:address":"7999 Silverleaf Dr",
    "sg:city":"Indianapolis",
    "sg:classifiers":[
        {
            "category":"Real Estate",
            "subcategory":"Real Estate Operator",
            "type":"Services"
        }
    ],
    "sg:phone":"+1 317 875 5900",
    "sg:postcode":"46260",
    "sg:province":"IN",
    "sg:tags":[
        "apartment"
    ],
    "wof:name":"Reflections Apartments",
    "wof:placetype":"venue"
},
  "geometry": {"coordinates":[-86.19149299999999,39.900138],"type":"Point"}
}