{
  "type": "Feature",
  "properties": {
    "addr:full":"227 N Main St New Castle IN 47362",
    "addr:housenumber":"227",
    "addr:postcode":"47362",
    "addr:street":"N Main St",
    "iso:country":"US",
    "sg:address":"227 N Main St",
    "sg:city":"New Castle",
    "sg:classifiers":[
        {
            "category":"Government",
            "subcategory":"Office",
            "type":"Public Place"
        }
    ],
    "sg:phone":"+1 765 521 6820",
    "sg:postcode":"47362",
    "sg:province":"IN",
    "sg:tags":[
        "govt",
        "city"
    ],
    "wof:name":"Utility Dept",
    "wof:placetype":"venue"
},
  "geometry": {"coordinates":[-85.370322,39.932977],"type":"Point"}
}