{
  "type": "Feature",
  "properties": {
    "iso:country":"US",
    "sg:address":"331 US Hwy 30 W",
    "sg:city":"New Haven",
    "sg:classifiers":[
        {
            "category":"Autos & Motor Vehicles",
            "subcategory":"Auto Supplies",
            "type":"Retail Goods"
        }
    ],
    "sg:phone":"+1 260 749 4711",
    "sg:postcode":"46774",
    "sg:province":"IN",
    "sg:tags":[
        "automobile",
        "parts"
    ],
    "wof:name":"Autozone",
    "wof:placetype":"venue"
},
  "geometry": {"coordinates":[-85.033579,41.068752],"type":"Point"}
}