{
  "type": "Feature",
  "properties": {
    "iso:country":"US",
    "sg:address":"54300 Walnut Rd",
    "sg:city":"New Carlisle",
    "sg:classifiers":[
        {
            "category":"Freight",
            "type":"Transportation"
        }
    ],
    "sg:phone":"+1 574 654 3116",
    "sg:postcode":"46552",
    "sg:province":"IN",
    "sg:tags":[
        "grain",
        "elevator"
    ],
    "wof:name":"Lake's Farm Svc Inc",
    "wof:placetype":"venue"
},
  "geometry": {"coordinates":[-86.476833,41.707339],"type":"Point"}
}