{
  "type": "Feature",
  "properties": {
    "iso:country":"US",
    "sg:address":"1201 E Jackson St",
    "sg:city":"Muncie",
    "sg:classifiers":[
        {
            "category":"Organizations",
            "subcategory":"Religious Organization",
            "type":"Services"
        }
    ],
    "sg:phone":"+1 765 282 1034",
    "sg:postcode":"47305",
    "sg:province":"IN",
    "sg:tags":[
        "church"
    ],
    "wof:name":"Spiritual Missionary Baptist",
    "wof:placetype":"venue"
},
  "geometry": {"coordinates":[-85.372413,40.192577],"type":"Point"}
}