{
  "type": "Feature",
  "properties": {
    "addr:full":"151 Della Rd Columbus IN 47203",
    "addr:housenumber":"151",
    "addr:postcode":"47203",
    "addr:street":"Della Rd",
    "iso:country":"US",
    "sg:address":"151 Della Rd",
    "sg:city":"Columbus",
    "sg:classifiers":[
        {
            "category":"Government",
            "subcategory":"Fire Station",
            "type":"Public Place"
        }
    ],
    "sg:phone":"+1 812 376 7150",
    "sg:postcode":"47203",
    "sg:province":"IN",
    "sg:tags":[
        "department"
    ],
    "wof:name":"Clay Township Fire Dept",
    "wof:placetype":"venue"
},
  "geometry": {"coordinates":[-85.851061,39.201811],"type":"Point"}
}