{
  "type": "Feature",
  "properties": {
    "iso:country":"US",
    "sg:address":"325 W Broadway St",
    "sg:city":"Fortville",
    "sg:classifiers":[
        {
            "category":"Wholesale",
            "subcategory":"Poultry",
            "type":"Manufacturing & Wholesale Goods"
        }
    ],
    "sg:phone":"+1 317 485 5332",
    "sg:postcode":"46040",
    "sg:province":"IN",
    "sg:tags":[
        "eggs"
    ],
    "wof:name":"Fortville Poultry & Egg",
    "wof:placetype":"venue"
},
  "geometry": {"coordinates":[-85.850098,39.930352],"type":"Point"}
}