{
  "type": "Feature",
  "properties": {
    "addr:full":"901 N Indiana Ave Bloomington IN 47408",
    "addr:housenumber":"901",
    "addr:postcode":"47408",
    "addr:street":"N Indiana Ave",
    "iso:country":"US",
    "sg:address":"901 N Indiana Ave",
    "sg:city":"Bloomington",
    "sg:classifiers":[
        {
            "category":"Food & Beverages",
            "subcategory":"Groceries & Convenience Stores",
            "type":"Retail Goods"
        }
    ],
    "sg:phone":"+1 812 336 5207",
    "sg:postcode":"47408",
    "sg:province":"IN",
    "wof:name":"Marsh",
    "wof:placetype":"venue"
},
  "geometry": {"coordinates":[-86.52699699999999,39.175078],"type":"Point"}
}