{
  "type": "Feature",
  "properties": {
    "iso:country":"US",
    "sg:address":"1035 Wall St",
    "sg:city":"Jeffersonville",
    "sg:classifiers":[
        {
            "category":"Health Services",
            "subcategory":"Doctor",
            "type":"Services"
        }
    ],
    "sg:phone":"+1 812 284 4771",
    "sg:postcode":"47130",
    "sg:province":"IN",
    "sg:tags":[
        "physician",
        "surgeon"
    ],
    "wof:name":"Morkas, Muffaddal S",
    "wof:placetype":"venue"
},
  "geometry": {"coordinates":[-85.745053,38.280098],"type":"Point"}
}