{
  "type": "Feature",
  "properties": {
    "iso:country":"US",
    "sg:address":"107 W Mill St",
    "sg:city":"Attica",
    "sg:classifiers":[
        {
            "category":"Cinema",
            "subcategory":"Movie Theater",
            "type":"Entertainment"
        }
    ],
    "sg:phone":"+1 765 762 3403",
    "sg:postcode":"47918",
    "sg:province":"IN",
    "wof:name":"Devon Theatre",
    "wof:placetype":"venue"
},
  "geometry": {"coordinates":[-87.25022,40.293969],"type":"Point"}
}