{
  "type": "Feature",
  "properties": {
    "iso:country":"US",
    "sg:address":"205 Mc Cray Ct",
    "sg:city":"Kendallville",
    "sg:classifiers":[
        {
            "category":"Building & Trades",
            "subcategory":"Landscaping Services",
            "type":"Services"
        }
    ],
    "sg:phone":"+1 260 349 0724",
    "sg:postcode":"46755",
    "sg:province":"IN",
    "sg:tags":[
        "landscape",
        "contractor"
    ],
    "wof:name":"Green Side Up",
    "wof:placetype":"venue"
},
  "geometry": {"coordinates":[-85.267023,41.445728],"type":"Point"}
}