{
  "type": "Feature",
  "properties": {
    "iso:country":"US",
    "sg:address":"3216 W Co Rd 850 N",
    "sg:city":"Lizton",
    "sg:classifiers":[
        {
            "category":"Building & Trades",
            "subcategory":"Landscaping Services",
            "type":"Services"
        }
    ],
    "sg:phone":"+1 317 994 5487",
    "sg:postcode":"46149",
    "sg:province":"IN",
    "sg:tags":[
        "landscape",
        "contractor"
    ],
    "wof:name":"Arbor Terra Consulting Inc",
    "wof:placetype":"venue"
},
  "geometry": {"coordinates":[-86.599691,39.886463],"type":"Point"}
}