{
  "type": "Feature",
  "properties": {
    "iso:country":"US",
    "sg:address":"9182 Wellston Dr",
    "sg:city":"Indianapolis",
    "sg:classifiers":[
        {
            "category":"Retail",
            "subcategory":"Repair Shop",
            "type":"Services"
        }
    ],
    "sg:phone":"+1 317 271 0353",
    "sg:postcode":"46234",
    "sg:province":"IN",
    "sg:tags":[
        "equipment",
        "commercial"
    ],
    "wof:name":"Quality Scale Service Co Inc",
    "wof:placetype":"venue"
},
  "geometry": {"coordinates":[-86.322802,39.771436],"type":"Point"}
}