{
  "type": "Feature",
  "properties": {
    "iso:country":"US",
    "sg:address":"151 W Main St",
    "sg:city":"New Albany",
    "sg:classifiers":[
        {
            "category":"Professional",
            "subcategory":"Computer Services",
            "type":"Services"
        }
    ],
    "sg:phone":"+1 812 948 1618",
    "sg:postcode":"47150",
    "sg:province":"IN",
    "sg:tags":[
        "internet"
    ],
    "wof:name":"Data Network Technology LLC",
    "wof:placetype":"venue"
},
  "geometry": {"coordinates":[-85.824655,38.282783],"type":"Point"}
}