{
  "type": "Feature",
  "properties": {
    "iso:country":"US",
    "sg:address":"1260 N Malibu St",
    "sg:city":"Knox",
    "sg:classifiers":[
        {
            "category":"Personal",
            "type":"Services"
        }
    ],
    "sg:phone":"+1 574 772 4307",
    "sg:postcode":"46534",
    "sg:province":"IN",
    "wof:name":"Keeping In Touch Massage &",
    "wof:placetype":"venue"
},
  "geometry": {"coordinates":[-86.59887,41.323691],"type":"Point"}
}