{
  "type": "Feature",
  "properties": {
    "iso:country":"US",
    "sg:address":"5404 W 25th Ave",
    "sg:city":"Gary",
    "sg:classifiers":[
        {
            "category":"Professional",
            "subcategory":"Business Services",
            "type":"Services"
        }
    ],
    "sg:phone":"+1 219 989 8158",
    "sg:postcode":"46406",
    "sg:province":"IN",
    "sg:tags":[
        "recording",
        "studio"
    ],
    "wof:name":"Quickdraw Productions Digital",
    "wof:placetype":"venue"
},
  "geometry": {"coordinates":[-87.405794,41.57359],"type":"Point"}
}