{
  "type": "Feature",
  "properties": {
    "addr:full":"115 S State Road 446 Bloomington IN 47401",
    "addr:housenumber":"115",
    "addr:postcode":"47401",
    "addr:street":"S State Road 446",
    "iso:country":"US",
    "sg:address":"115 S State Road 446",
    "sg:city":"Bloomington",
    "sg:classifiers":[
        {
            "category":"Ice Cream",
            "type":"Food & Drink"
        }
    ],
    "sg:menulink":"http://www.allmenus.com/in/broadview/184788-cold-stone-creamery/menu/",
    "sg:phone":"+1 812 334 8250",
    "sg:postcode":"47401",
    "sg:province":"IN",
    "sg:tags":[
        "smoothy",
        "juice",
        "american"
    ],
    "wof:name":"Cold Stone Creamery",
    "wof:placetype":"venue"
},
  "geometry": {"coordinates":[-86.471794,39.163636],"type":"Point"}
}