{
  "type": "Feature",
  "properties": {
    "iso:country":"US",
    "sg:address":"633 Jackson St",
    "sg:city":"Anderson",
    "sg:classifiers":[
        {
            "category":"Autos & Motor Vehicles",
            "subcategory":"Auto Supplies",
            "type":"Retail Goods"
        }
    ],
    "sg:phone":"+1 765 642 0281",
    "sg:postcode":"46016",
    "sg:province":"IN",
    "sg:tags":[
        "automobile",
        "parts"
    ],
    "wof:name":"Carquest Auto Parts",
    "wof:placetype":"venue"
},
  "geometry": {"coordinates":[-85.680622,40.109201],"type":"Point"}
}