{
  "type": "Feature",
  "properties": {
    "iso:country":"US",
    "sg:address":"706 W 3rd St",
    "sg:city":"Madison",
    "sg:classifiers":[
        {
            "category":"Organizations",
            "subcategory":"Religious Organization",
            "type":"Services"
        }
    ],
    "sg:phone":"+1 812 265 0909",
    "sg:postcode":"47250",
    "sg:province":"IN",
    "sg:tags":[
        "church"
    ],
    "wof:name":"Rev Michael Dearing Ddiv",
    "wof:placetype":"venue"
},
  "geometry": {"coordinates":[-85.389357,38.739306],"type":"Point"}
}