{
  "type": "Feature",
  "properties": {
    "iso:country":"US",
    "sg:address":"3664 Valley Branch Rd",
    "sg:city":"Nashville",
    "sg:classifiers":[
        {
            "category":"Building & Trades",
            "subcategory":"Construction",
            "type":"Services"
        }
    ],
    "sg:phone":"+1 812 988 7843",
    "sg:postcode":"47448",
    "sg:province":"IN",
    "sg:tags":[
        "carpentry",
        "contractor"
    ],
    "wof:name":"Indiana Seamless Guttering",
    "wof:placetype":"venue"
},
  "geometry": {"coordinates":[-86.157005,39.144262],"type":"Point"}
}