{
  "type": "Feature",
  "properties": {
    "iso:country":"US",
    "sg:address":"11711 N College Ave Ste 195",
    "sg:city":"Carmel",
    "sg:classifiers":[
        {
            "category":"Building & Trades",
            "subcategory":"Construction",
            "type":"Services"
        }
    ],
    "sg:phone":"+1 317 706 0772",
    "sg:postcode":"46032",
    "sg:province":"IN",
    "sg:tags":[
        "interior",
        "design"
    ],
    "sg:website":"www.julieobriendesign.com",
    "wof:name":"O'brien Julie Design Group",
    "wof:placetype":"venue"
},
  "geometry": {"coordinates":[-86.145774,39.959079],"type":"Point"}
}