{
  "type": "Feature",
  "properties": {
    "iso:country":"US",
    "sg:address":"15232 Stoney Creek Way",
    "sg:city":"Noblesville",
    "sg:classifiers":[
        {
            "category":"Freight",
            "type":"Transportation"
        }
    ],
    "sg:phone":"+1 317 773 3717",
    "sg:postcode":"46060",
    "sg:province":"IN",
    "sg:tags":[
        "broker",
        "trucking"
    ],
    "wof:name":"Knight Transportation Inc",
    "wof:placetype":"venue"
},
  "geometry": {"coordinates":[-86.007606,40.007914],"type":"Point"}
}