{
  "type": "Feature",
  "properties": {
    "iso:country":"US",
    "sg:address":"5874 N Co Rd 1380 E",
    "sg:city":"Russiaville",
    "sg:classifiers":[
        {
            "category":"Building & Trades",
            "subcategory":"Cleaning & Sanitation",
            "type":"Services"
        }
    ],
    "sg:phone":"+1 765 883 8439",
    "sg:postcode":"46979",
    "sg:province":"IN",
    "sg:tags":[
        "maintenance"
    ],
    "wof:name":"Saumarkco",
    "wof:placetype":"venue"
},
  "geometry": {"coordinates":[-86.247704,40.368125],"type":"Point"}
}