{
  "type": "Feature",
  "properties": {
    "iso:country":"US",
    "sg:address":"1241 Cumberland Ave",
    "sg:city":"West Lafayette",
    "sg:classifiers":[
        {
            "category":"Banks & Credit Unions",
            "subcategory":"Investment Brokerage",
            "type":"Services"
        }
    ],
    "sg:phone":"+1 765 497 0197",
    "sg:postcode":"47906",
    "sg:province":"IN",
    "sg:tags":[
        "advisory",
        "financial"
    ],
    "wof:name":"Banker Investment Group",
    "wof:placetype":"venue"
},
  "geometry": {"coordinates":[-86.92587,40.460636],"type":"Point"}
}