{
  "type": "Feature",
  "properties": {
    "iso:country":"US",
    "sg:address":"76 E US Hwy 6",
    "sg:city":"Valparaiso",
    "sg:classifiers":[
        {
            "category":"Building & Trades",
            "subcategory":"Construction",
            "type":"Services"
        }
    ],
    "sg:phone":"+1 219 921 4646",
    "sg:postcode":"46383",
    "sg:province":"IN",
    "sg:tags":[
        "contractor"
    ],
    "wof:name":"Burts Drywall",
    "wof:placetype":"venue"
},
  "geometry": {"coordinates":[-87.050994,41.549966],"type":"Point"}
}