{
  "type": "Feature",
  "properties": {
    "iso:country":"US",
    "sg:address":"111 S Downey Ave",
    "sg:city":"Indianapolis",
    "sg:classifiers":[
        {
            "category":"Wholesale",
            "subcategory":"Books, Periodicals, & Newspapers",
            "type":"Manufacturing & Wholesale Goods"
        },
        {
            "category":"Professional",
            "subcategory":"Management & Consulting",
            "type":"Services"
        }
    ],
    "sg:phone":"+1 317 375 8846",
    "sg:postcode":"46219",
    "sg:province":"IN",
    "sg:tags":[
        "magazine",
        "agent"
    ],
    "wof:name":"Disciplesworld Inc",
    "wof:placetype":"venue"
},
  "geometry": {"coordinates":[-86.076644,39.768527],"type":"Point"}
}