{
  "type": "Feature",
  "properties": {
    "iso:country":"US",
    "sg:address":"111 N Front St",
    "sg:city":"Rising Sun",
    "sg:classifiers":[
        {
            "category":"Shopping",
            "subcategory":"Gifts & Souvenirs",
            "type":"Retail Goods"
        }
    ],
    "sg:phone":"+1 812 438 2503",
    "sg:postcode":"47040",
    "sg:province":"IN",
    "wof:name":"Riverfront Gift Shop",
    "wof:placetype":"venue"
},
  "geometry": {"coordinates":[-84.850364,38.948573],"type":"Point"}
}