{
  "type": "Feature",
  "properties": {
    "iso:country":"US",
    "sg:address":"11911 N Executive Dr",
    "sg:city":"Edinburgh",
    "sg:classifiers":[
        {
            "category":"Shopping",
            "type":"Retail Goods"
        }
    ],
    "sg:phone":"+1 812 526 4069",
    "sg:postcode":"46124",
    "sg:province":"IN",
    "sg:tags":[
        "factory",
        "outlet"
    ],
    "wof:name":"Edinburgh Outlet Ctr",
    "wof:placetype":"venue"
},
  "geometry": {"coordinates":[-85.96459,39.311261],"type":"Point"}
}