{
  "type": "Feature",
  "properties": {
    "addr:full":"25 E 40th St Indianapolis IN 46205",
    "addr:housenumber":"25",
    "addr:postcode":"46205",
    "addr:street":"E 40Th St",
    "iso:country":"US",
    "sg:address":"25 E 40th St",
    "sg:city":"Indianapolis",
    "sg:classifiers":[
        {
            "category":"Real Estate",
            "subcategory":"Real Estate Services",
            "type":"Services"
        }
    ],
    "sg:phone":"+1 866 374 3024",
    "sg:postcode":"46205",
    "sg:province":"IN",
    "sg:tags":[
        "management",
        "condominium"
    ],
    "wof:name":"40 North On Meridian",
    "wof:placetype":"venue"
},
  "geometry": {"coordinates":[-86.15632100000001,39.828476],"type":"Point"}
}