{
  "type": "Feature",
  "properties": {
    "iso:country":"US",
    "sg:address":"924 E Clark St",
    "sg:city":"Warsaw",
    "sg:classifiers":[
        {
            "category":"Real Estate",
            "subcategory":"Real Estate Agent",
            "type":"Services"
        }
    ],
    "sg:phone":"+1 574 267 0077",
    "sg:postcode":"46580",
    "sg:province":"IN",
    "wof:name":"Universal Property Svc",
    "wof:placetype":"venue"
},
  "geometry": {"coordinates":[-85.844325,41.24088],"type":"Point"}
}