{
  "type": "Feature",
  "properties": {
    "addr:full":"5222 Kenwood Dr Newburgh IN 47630",
    "addr:housenumber":"5222",
    "addr:postcode":"47630",
    "addr:street":"Kenwood Dr",
    "iso:country":"US",
    "sg:address":"5222 Kenwood Dr",
    "sg:city":"Newburgh",
    "sg:classifiers":[
        {
            "category":"Communications",
            "subcategory":"Film & Video Production",
            "type":"Services"
        }
    ],
    "sg:phone":"+1 812 490 9974",
    "sg:postcode":"47630",
    "sg:province":"IN",
    "sg:tags":[
        "motion"
    ],
    "wof:name":"Black Tie Video Productions",
    "wof:placetype":"venue"
},
  "geometry": {"coordinates":[-87.395239,37.954434],"type":"Point"}
}