{
  "type": "Feature",
  "properties": {
    "iso:country":"US",
    "sg:address":"5838 Maplecrest Rd",
    "sg:city":"Fort Wayne",
    "sg:classifiers":[
        {
            "category":"Personal",
            "subcategory":"Beauty Salon",
            "type":"Services"
        }
    ],
    "sg:phone":"+1 260 485 4247",
    "sg:postcode":"46835",
    "sg:province":"IN",
    "wof:name":"Innovations Hair Design",
    "wof:placetype":"venue"
},
  "geometry": {"coordinates":[-85.062111,41.134061],"type":"Point"}
}