{
  "type": "Feature",
  "properties": {
    "iso:country":"US",
    "sg:address":"4444 Broadway St",
    "sg:city":"Indianapolis",
    "sg:classifiers":[
        {
            "category":"Professional",
            "subcategory":"Art Services",
            "type":"Services"
        }
    ],
    "sg:phone":"+1 317 926 5796",
    "sg:postcode":"46205",
    "sg:province":"IN",
    "sg:tags":[
        "commercial",
        "graphic",
        "design"
    ],
    "wof:name":"Rsa Graphics Corporation",
    "wof:placetype":"venue"
},
  "geometry": {"coordinates":[-86.14700999999999,39.838798],"type":"Point"}
}