{
  "type": "Feature",
  "properties": {
    "addr:full":"1405 S Smith Rd Bloomington IN 47401",
    "addr:housenumber":"1405",
    "addr:postcode":"47401",
    "addr:street":"S Smith Rd",
    "iso:country":"US",
    "sg:address":"1405 S Smith Rd",
    "sg:city":"Bloomington",
    "sg:classifiers":[
        {
            "category":"Autos & Motor Vehicles",
            "subcategory":"Automobile Sales",
            "type":"Retail Goods"
        }
    ],
    "sg:phone":"+1 812 332 6299",
    "sg:postcode":"47401",
    "sg:province":"IN",
    "sg:tags":[
        "car",
        "dealer"
    ],
    "wof:name":"Ted's Auto Sales",
    "wof:placetype":"venue"
},
  "geometry": {"coordinates":[-86.48034800000001,39.147431],"type":"Point"}
}