{
  "type": "Feature",
  "properties": {
    "iso:country":"US",
    "sg:address":"10 Orchard Ln",
    "sg:city":"Huntington",
    "sg:classifiers":[
        {
            "category":"Government",
            "subcategory":"Police Station",
            "type":"Public Place"
        }
    ],
    "sg:phone":"+1 260 359 0842",
    "sg:postcode":"46750",
    "sg:province":"IN",
    "sg:tags":[
        "protection",
        "electrical",
        "contractor"
    ],
    "wof:name":"Holdencom",
    "wof:placetype":"venue"
},
  "geometry": {"coordinates":[-85.50997,40.885452],"type":"Point"}
}