{
  "type": "Feature",
  "properties": {
    "iso:country":"US",
    "sg:address":"3678 N Wells St",
    "sg:city":"Fort Wayne",
    "sg:classifiers":[
        {
            "category":"Shopping",
            "subcategory":"Musical Instruments",
            "type":"Retail Goods"
        }
    ],
    "sg:phone":"+1 260 482 9669",
    "sg:postcode":"46808",
    "sg:province":"IN",
    "wof:name":"Blessing Music",
    "wof:placetype":"venue"
},
  "geometry": {"coordinates":[-85.147511,41.106701],"type":"Point"}
}