{
  "type": "Feature",
  "properties": {
    "iso:country":"US",
    "sg:address":"1123 N Edmondson Ave",
    "sg:city":"Indianapolis",
    "sg:classifiers":[
        {
            "category":"Social Services",
            "subcategory":"Adult Care",
            "type":"Services"
        }
    ],
    "sg:phone":"+1 317 356 4173",
    "sg:postcode":"46219",
    "sg:province":"IN",
    "sg:tags":[
        "home",
        "apartment",
        "residential"
    ],
    "sg:website":"http://www.crestwood-living.com",
    "wof:name":"Crestwood Village - East",
    "wof:placetype":"venue"
},
  "geometry": {"coordinates":[-86.05006,39.783746],"type":"Point"}
}