{
  "type": "Feature",
  "properties": {
    "iso:country":"US",
    "sg:address":"8033 Euclid Ave",
    "sg:city":"Munster",
    "sg:classifiers":[
        {
            "category":"Personal",
            "subcategory":"Beauty Salon",
            "type":"Services"
        }
    ],
    "sg:phone":"+1 219 836 1096",
    "sg:postcode":"46321",
    "sg:province":"IN",
    "wof:name":"New Waves",
    "wof:placetype":"venue"
},
  "geometry": {"coordinates":[-87.50594,41.56857],"type":"Point"}
}