{
  "type": "Feature",
  "properties": {
    "iso:country":"US",
    "sg:address":"207 Broadway",
    "sg:city":"Chesterton",
    "sg:classifiers":[
        {
            "category":"Retail",
            "subcategory":"Animal Services",
            "type":"Services"
        }
    ],
    "sg:phone":"+1 219 921 0600",
    "sg:postcode":"46304",
    "sg:province":"IN",
    "wof:name":"Barkleys Inc",
    "wof:placetype":"venue"
},
  "geometry": {"coordinates":[-87.054498,41.610844],"type":"Point"}
}