{
  "type": "Feature",
  "properties": {
    "iso:country":"US",
    "sg:address":"6308 W Co Rd 600 S",
    "sg:city":"Greensburg",
    "sg:classifiers":[
        {
            "category":"Wholesale",
            "subcategory":"Machinery & Supplies",
            "type":"Manufacturing & Wholesale Goods"
        }
    ],
    "sg:phone":"+1 812 591 4150",
    "sg:postcode":"47240",
    "sg:province":"IN",
    "sg:tags":[
        "burial",
        "vault"
    ],
    "wof:name":"Stone Family Vault Works",
    "wof:placetype":"venue"
},
  "geometry": {"coordinates":[-85.599911,39.248705],"type":"Point"}
}