{
  "type": "Feature",
  "properties": {
    "iso:country":"US",
    "sg:address":"573 N Green River Rd",
    "sg:city":"Evansville",
    "sg:classifiers":[
        {
            "category":"Restaurant",
            "type":"Food & Drink"
        }
    ],
    "sg:phone":"+1 812 479 7430",
    "sg:postcode":"47715",
    "sg:province":"IN",
    "sg:tags":[
        "parlor",
        "ice",
        "cream"
    ],
    "wof:name":"TCBY",
    "wof:placetype":"venue"
},
  "geometry": {"coordinates":[-87.492616,37.983174],"type":"Point"}
}