{
  "type": "Feature",
  "properties": {
    "addr:full":"15 E Maryland St Indianapolis IN 46204",
    "addr:housenumber":"15",
    "addr:postcode":"46204",
    "addr:street":"E Maryland St",
    "iso:country":"US",
    "sg:address":"15 E Maryland St",
    "sg:city":"Indianapolis",
    "sg:classifiers":[
        {
            "category":"Communications",
            "subcategory":"Radio Station",
            "type":"Services"
        }
    ],
    "sg:phone":"+1 317 635 9318",
    "sg:postcode":"46204",
    "sg:province":"IN",
    "sg:tags":[
        "company",
        "broadcasting"
    ],
    "wof:name":"WIBC Radio Emmis Comm",
    "wof:placetype":"venue"
},
  "geometry": {"coordinates":[-86.15742899999999,39.765701],"type":"Point"}
}