{
  "type": "Feature",
  "properties": {
    "iso:country":"US",
    "sg:address":"8901 Rawles Ave",
    "sg:city":"Indianapolis",
    "sg:classifiers":[
        {
            "category":"Building & Trades",
            "subcategory":"Construction",
            "type":"Services"
        }
    ],
    "sg:phone":"+1 317 890 9078",
    "sg:postcode":"46219",
    "sg:province":"IN",
    "sg:tags":[
        "masonry",
        "contractor"
    ],
    "wof:name":"Batts Construction Inc",
    "wof:placetype":"venue"
},
  "geometry": {"coordinates":[-86.00898,39.762147],"type":"Point"}
}