{
  "type": "Feature",
  "properties": {
    "iso:country":"US",
    "sg:address":"723 W Frank St",
    "sg:city":"Mitchell",
    "sg:classifiers":[
        {
            "category":"Organizations",
            "subcategory":"Religious Organization",
            "type":"Services"
        }
    ],
    "sg:phone":"+1 812 849 4764",
    "sg:postcode":"47446",
    "sg:province":"IN",
    "sg:tags":[
        "church"
    ],
    "wof:name":"First Baptist Church",
    "wof:placetype":"venue"
},
  "geometry": {"coordinates":[-86.47297399999999,38.730818],"type":"Point"}
}