{
  "type": "Feature",
  "properties": {
    "addr:full":"2162 Cessna Rd Warsaw IN 46582",
    "addr:housenumber":"2162",
    "addr:postcode":"46582",
    "addr:street":"Cessna Rd",
    "iso:country":"US",
    "sg:address":"2162 Cessna Rd",
    "sg:city":"Warsaw",
    "sg:classifiers":[
        {
            "category":"Wholesale",
            "subcategory":"Fruits & Vegetables",
            "type":"Manufacturing & Wholesale Goods"
        }
    ],
    "sg:phone":"+1 574 267 5439",
    "sg:postcode":"46582",
    "sg:province":"IN",
    "wof:name":"Pizza Supply Of Indiana Inc",
    "wof:placetype":"venue"
},
  "geometry": {"coordinates":[-85.829865,41.263295],"type":"Point"}
}