{
  "type": "Feature",
  "properties": {
    "iso:country":"US",
    "sg:address":"1803 Charles St",
    "sg:city":"Anderson",
    "sg:classifiers":[
        {
            "category":"Organizations",
            "subcategory":"Religious Organization",
            "type":"Services"
        }
    ],
    "sg:phone":"+1 765 642 3672",
    "sg:postcode":"46013",
    "sg:province":"IN",
    "sg:tags":[
        "church"
    ],
    "wof:name":"Abundant Life Church Of God",
    "wof:placetype":"venue"
},
  "geometry": {"coordinates":[-85.654516,40.066009],"type":"Point"}
}