{
  "type": "Feature",
  "properties": {
    "addr:full":"117 S Washington St Crawfordsville IN 47933",
    "addr:housenumber":"117",
    "addr:postcode":"47933",
    "addr:street":"S Washington St",
    "iso:country":"US",
    "sg:address":"117 S Washington St",
    "sg:city":"Crawfordsville",
    "sg:classifiers":[
        {
            "category":"Banks & Credit Unions",
            "subcategory":"Bank",
            "type":"Services"
        }
    ],
    "sg:phone":"+1 765 362 1458",
    "sg:postcode":"47933",
    "sg:province":"IN",
    "sg:tags":[
        "loan",
        "real estate"
    ],
    "wof:name":"GMAC Mortgage",
    "wof:placetype":"venue"
},
  "geometry": {"coordinates":[-86.901481,40.041538],"type":"Point"}
}