{
  "type": "Feature",
  "properties": {
    "iso:country":"US",
    "sg:address":"3136 Clifty Dr",
    "sg:city":"Madison",
    "sg:classifiers":[
        {
            "category":"Building & Trades",
            "subcategory":"Construction",
            "type":"Services"
        }
    ],
    "sg:phone":"+1 812 265 6046",
    "sg:postcode":"47250",
    "sg:province":"IN",
    "sg:tags":[
        "home",
        "builder"
    ],
    "wof:name":"Quality Homes Of Madison",
    "wof:placetype":"venue"
},
  "geometry": {"coordinates":[-85.450014,38.752359],"type":"Point"}
}