{
  "type": "Feature",
  "properties": {
    "iso:country":"US",
    "sg:address":"8008 Kennedy Ave",
    "sg:city":"Highland",
    "sg:classifiers":[
        {
            "category":"Autos & Motor Vehicles",
            "subcategory":"Automobile Sales",
            "type":"Retail Goods"
        }
    ],
    "sg:phone":"+1 219 923 1356",
    "sg:postcode":"46322",
    "sg:province":"IN",
    "sg:tags":[
        "car",
        "dealer"
    ],
    "wof:name":"All Star Auto Sales",
    "wof:placetype":"venue"
},
  "geometry": {"coordinates":[-87.46172,41.56783],"type":"Point"}
}