{
  "type": "Feature",
  "properties": {
    "iso:country":"US",
    "sg:address":"1004 Eliza St",
    "sg:city":"Fort Wayne",
    "sg:classifiers":[
        {
            "category":"Professional",
            "type":"Services"
        }
    ],
    "sg:phone":"+1 260 422 2902",
    "sg:postcode":"46803",
    "sg:province":"IN",
    "sg:tags":[
        "establishment"
    ],
    "wof:name":"Mccoun Eligha",
    "wof:placetype":"venue"
},
  "geometry": {"coordinates":[-85.124015,41.073064],"type":"Point"}
}