{
  "type": "Feature",
  "properties": {
    "iso:country":"US",
    "sg:address":"1308 Meadowbrook Dr",
    "sg:city":"Kokomo",
    "sg:classifiers":[
        {
            "category":"Retail",
            "subcategory":"Auto Repair",
            "type":"Services"
        }
    ],
    "sg:phone":"+1 765 457 7779",
    "sg:postcode":"46902",
    "sg:province":"IN",
    "sg:tags":[
        "automobile",
        "customizing"
    ],
    "wof:name":"Auto Trim Design",
    "wof:placetype":"venue"
},
  "geometry": {"coordinates":[-86.105261,40.471919],"type":"Point"}
}