{
  "type": "Feature",
  "properties": {
    "iso:country":"US",
    "sg:address":"828 S Bend Ave",
    "sg:city":"South Bend",
    "sg:classifiers":[
        {
            "category":"Health Services",
            "subcategory":"Doctor",
            "type":"Services"
        }
    ],
    "sg:phone":"+1 574 233 5858",
    "sg:postcode":"46617",
    "sg:province":"IN",
    "sg:tags":[
        "physician",
        "surgeon"
    ],
    "wof:name":"Rickey L Wilson MD",
    "wof:placetype":"venue"
},
  "geometry": {"coordinates":[-86.237962,41.685756],"type":"Point"}
}