{
  "type": "Feature",
  "properties": {
    "addr:full":"5454 S East St Indianapolis IN 46227",
    "addr:housenumber":"5454",
    "addr:postcode":"46227",
    "addr:street":"S East St",
    "iso:country":"US",
    "sg:address":"5454 S East St",
    "sg:city":"Indianapolis",
    "sg:classifiers":[
        {
            "category":"Shopping",
            "subcategory":"Used Merchandise",
            "type":"Retail Goods"
        }
    ],
    "sg:phone":"+1 317 782 1358",
    "sg:postcode":"46227",
    "sg:province":"IN",
    "sg:tags":[
        "antique"
    ],
    "wof:name":"Manor House Antique Mall",
    "wof:placetype":"venue"
},
  "geometry": {"coordinates":[-86.1489,39.68801],"type":"Point"}
}