{
  "type": "Feature",
  "properties": {
    "addr:full":"3505 Brooklyn Ave Fort Wayne IN 46809",
    "addr:housenumber":"3505",
    "addr:postcode":"46809",
    "addr:street":"Brooklyn Ave",
    "iso:country":"US",
    "sg:address":"3505 Brooklyn Ave",
    "sg:city":"Fort Wayne",
    "sg:classifiers":[
        {
            "category":"Manufacturing",
            "subcategory":"Signs",
            "type":"Manufacturing & Wholesale Goods"
        }
    ],
    "sg:phone":"+1 260 747 0872",
    "sg:postcode":"46809",
    "sg:province":"IN",
    "sg:tags":[
        "advertising",
        "specialty"
    ],
    "wof:name":"Signs Unlimited",
    "wof:placetype":"venue"
},
  "geometry": {"coordinates":[-85.164439,41.051488],"type":"Point"}
}