{
  "type": "Feature",
  "properties": {
    "iso:country":"US",
    "sg:address":"11110 Pear Rd",
    "sg:city":"Plymouth",
    "sg:classifiers":[
        {
            "category":"Shopping",
            "subcategory":"Bicycles & Sporting Goods",
            "type":"Retail Goods"
        }
    ],
    "sg:phone":"+1 574 936 2003",
    "sg:postcode":"46563",
    "sg:province":"IN",
    "wof:name":"Other Place",
    "wof:placetype":"venue"
},
  "geometry": {"coordinates":[-86.357219,41.316033],"type":"Point"}
}