{
  "type": "Feature",
  "properties": {
    "iso:country":"US",
    "sg:address":"28 Sagamore Pkwy N",
    "sg:city":"Lafayette",
    "sg:classifiers":[
        {
            "category":"Autos & Motor Vehicles",
            "subcategory":"Auto Supplies",
            "type":"Retail Goods"
        }
    ],
    "sg:phone":"+1 765 446 2671",
    "sg:postcode":"47904",
    "sg:province":"IN",
    "sg:tags":[
        "tire"
    ],
    "wof:name":"A To Z Muffler & Brake Auto",
    "wof:placetype":"venue"
},
  "geometry": {"coordinates":[-86.858287,40.420225],"type":"Point"}
}