{
  "type": "Feature",
  "properties": {
    "iso:country":"US",
    "sg:address":"936 N Gospel St",
    "sg:city":"Paoli",
    "sg:classifiers":[
        {
            "category":"Autos & Motor Vehicles",
            "subcategory":"Auto Supplies",
            "type":"Retail Goods"
        }
    ],
    "sg:phone":"+1 812 723 0090",
    "sg:postcode":"47454",
    "sg:province":"IN",
    "sg:tags":[
        "automobile",
        "parts"
    ],
    "wof:name":"Advance Auto Parts Inc",
    "wof:placetype":"venue"
},
  "geometry": {"coordinates":[-86.464303,38.56752],"type":"Point"}
}