{
  "type": "Feature",
  "properties": {
    "iso:country":"US",
    "sg:address":"1010 S Walnut St",
    "sg:city":"Bloomington",
    "sg:classifiers":[
        {
            "category":"Building & Trades",
            "subcategory":"Construction",
            "type":"Services"
        }
    ],
    "sg:phone":"+1 812 336 2597",
    "sg:postcode":"47401",
    "sg:province":"IN",
    "sg:tags":[
        "shelter"
    ],
    "wof:name":"Martha's House",
    "wof:placetype":"venue"
},
  "geometry": {"coordinates":[-86.533783,39.154367],"type":"Point"}
}