{
  "type": "Feature",
  "properties": {
    "iso:country":"US",
    "sg:address":"226 W Barker Ave",
    "sg:city":"Michigan City",
    "sg:classifiers":[
        {
            "category":"Shopping",
            "subcategory":"Gifts & Souvenirs",
            "type":"Retail Goods"
        }
    ],
    "sg:phone":"+1 219 877 3223",
    "sg:postcode":"46360",
    "sg:province":"IN",
    "sg:tags":[
        "shop"
    ],
    "wof:name":"Summer Solstice",
    "wof:placetype":"venue"
},
  "geometry": {"coordinates":[-86.898517,41.704807],"type":"Point"}
}