{
  "type": "Feature",
  "properties": {
    "iso:country":"US",
    "sg:address":"535 W Main St",
    "sg:city":"Peru",
    "sg:classifiers":[
        {
            "category":"Autos & Motor Vehicles",
            "subcategory":"Automobile Sales",
            "type":"Retail Goods"
        }
    ],
    "sg:phone":"+1 765 472 2405",
    "sg:postcode":"46970",
    "sg:province":"IN",
    "sg:tags":[
        "car",
        "dealer"
    ],
    "wof:name":"Jett's Auto Sales",
    "wof:placetype":"venue"
},
  "geometry": {"coordinates":[-86.08462400000001,40.747157],"type":"Point"}
}