{
  "type": "Feature",
  "properties": {
    "iso:country":"US",
    "sg:address":"309 S Shirley Rd",
    "sg:city":"Shirley",
    "sg:classifiers":[
        {
            "category":"Organizations",
            "subcategory":"Religious Organization",
            "type":"Services"
        }
    ],
    "sg:phone":"+1 765 738 6710",
    "sg:postcode":"47384",
    "sg:province":"IN",
    "sg:tags":[
        "church"
    ],
    "wof:name":"Shirley Wilkinson Community",
    "wof:placetype":"venue"
},
  "geometry": {"coordinates":[-85.57619800000001,39.925884],"type":"Point"}
}