{
  "type": "Feature",
  "properties": {
    "addr:full":"2301 E 44th St Indianapolis IN 46205",
    "addr:housenumber":"2301",
    "addr:postcode":"46205",
    "addr:street":"E 44Th St",
    "iso:country":"US",
    "sg:address":"2301 E 44th St",
    "sg:city":"Indianapolis",
    "sg:classifiers":[
        {
            "category":"Manufacturing",
            "subcategory":"Motor Vehicles & Parts",
            "type":"Manufacturing & Wholesale Goods"
        },
        {
            "category":"Autos & Motor Vehicles",
            "subcategory":"Auto Supplies",
            "type":"Retail Goods"
        }
    ],
    "sg:phone":"+1 317 546 1140",
    "sg:postcode":"46205",
    "sg:province":"IN",
    "sg:tags":[
        "automobile",
        "rebuilt",
        "supplies-used",
        "driveshaft"
    ],
    "sg:website":"http://www.indianapolisrackandaxle.com",
    "wof:name":"Indianapolis Rack & Axle",
    "wof:placetype":"venue"
},
  "geometry": {"coordinates":[-86.12205400000001,39.836525],"type":"Point"}
}