{
  "type": "Feature",
  "properties": {
    "iso:country":"US",
    "sg:address":"52549 Gumwood Rd",
    "sg:city":"Granger",
    "sg:classifiers":[
        {
            "category":"Education",
            "subcategory":"Special Training",
            "type":"Public Place"
        }
    ],
    "sg:phone":"+1 574 271 0334",
    "sg:postcode":"46530",
    "sg:province":"IN",
    "sg:tags":[
        "instruction",
        "music"
    ],
    "sg:website":"www.suzukied.org",
    "wof:name":"Suzuki Music School",
    "wof:placetype":"venue"
},
  "geometry": {"coordinates":[-86.178122,41.72763],"type":"Point"}
}