{
  "type": "Feature",
  "properties": {
    "iso:country":"US",
    "sg:address":"1220 I St",
    "sg:city":"Bedford",
    "sg:classifiers":[
        {
            "category":"Organizations",
            "subcategory":"Labor Organization",
            "type":"Services"
        }
    ],
    "sg:phone":"+1 812 275 8516",
    "sg:postcode":"47421",
    "sg:province":"IN",
    "wof:name":"IBEW",
    "wof:placetype":"venue"
},
  "geometry": {"coordinates":[-86.48262800000001,38.864842],"type":"Point"}
}