{
  "type": "Feature",
  "properties": {
    "iso:country":"US",
    "sg:address":"418 Blackport Dr",
    "sg:city":"Goshen",
    "sg:classifiers":[
        {
            "category":"Home & Garden",
            "subcategory":"Building Materials",
            "type":"Retail Goods"
        }
    ],
    "sg:phone":"+1 260 484 0490",
    "sg:postcode":"46528",
    "sg:province":"IN",
    "wof:name":"Sliding World",
    "wof:placetype":"venue"
},
  "geometry": {"coordinates":[-85.809631,41.58457],"type":"Point"}
}