{
  "type": "Feature",
  "properties": {
    "addr:full":"2600 S Harding St Indianapolis IN 46217",
    "addr:housenumber":"2600",
    "addr:postcode":"46217",
    "addr:street":"S Harding St",
    "iso:country":"US",
    "sg:address":"2600 S Harding St",
    "sg:city":"Indianapolis",
    "sg:classifiers":[
        {
            "category":"Government",
            "subcategory":"Office",
            "type":"Public Place"
        }
    ],
    "sg:phone":"+1 317 327 1380",
    "sg:postcode":"46217",
    "sg:province":"IN",
    "sg:tags":[
        "animal"
    ],
    "wof:name":"Public Safety Dept",
    "wof:placetype":"venue"
},
  "geometry": {"coordinates":[-86.187116,39.731324],"type":"Point"}
}