{
  "type": "Feature",
  "properties": {
    "iso:country":"US",
    "sg:address":"520 S West Blvd",
    "sg:city":"Elkhart",
    "sg:classifiers":[
        {
            "category":"Real Estate",
            "subcategory":"Real Estate Operator",
            "type":"Services"
        }
    ],
    "sg:phone":"+1 574 293 7486",
    "sg:postcode":"46514",
    "sg:province":"IN",
    "sg:tags":[
        "renting",
        "property"
    ],
    "wof:name":"Michael D Church",
    "wof:placetype":"venue"
},
  "geometry": {"coordinates":[-85.996536,41.679556],"type":"Point"}
}