{
  "type": "Feature",
  "properties": {
    "iso:country":"US",
    "sg:address":"1404 E Lincolnway",
    "sg:city":"Valparaiso",
    "sg:classifiers":[
        {
            "category":"Banks & Credit Unions",
            "subcategory":"Bank",
            "type":"Services"
        }
    ],
    "sg:phone":"+1 219 465 0650",
    "sg:postcode":"46383",
    "sg:province":"IN",
    "sg:tags":[
        "loan",
        "real estate"
    ],
    "wof:name":"Irwin Mortgage",
    "wof:placetype":"venue"
},
  "geometry": {"coordinates":[-87.041532,41.467699],"type":"Point"}
}