{
  "type": "Feature",
  "properties": {
    "iso:country":"US",
    "sg:address":"5943 Tanana Dr",
    "sg:city":"Carmel",
    "sg:classifiers":[
        {
            "category":"Professional",
            "subcategory":"Business Services",
            "type":"Services"
        }
    ],
    "sg:phone":"+1 317 574 1636",
    "sg:postcode":"46033",
    "sg:province":"IN",
    "sg:tags":[
        "interior",
        "consultant",
        "design",
        "decorator"
    ],
    "wof:name":"Interiors By Decorating Den",
    "wof:placetype":"venue"
},
  "geometry": {"coordinates":[-86.067545,39.989589],"type":"Point"}
}