{
  "type": "Feature",
  "properties": {
    "iso:country":"US",
    "sg:address":"3575 Inverness Blvd",
    "sg:city":"Carmel",
    "sg:classifiers":[
        {
            "category":"Professional",
            "subcategory":"Business Services",
            "type":"Services"
        }
    ],
    "sg:phone":"+1 317 802 9377",
    "sg:postcode":"46032",
    "sg:province":"IN",
    "wof:name":"Posada & Associates Inc",
    "wof:placetype":"venue"
},
  "geometry": {"coordinates":[-86.2221,39.935166],"type":"Point"}
}