{
  "type": "Feature",
  "properties": {
    "iso:country":"US",
    "sg:address":"215 W State St",
    "sg:city":"Princeton",
    "sg:classifiers":[
        {
            "category":"Professional",
            "subcategory":"Lawyer & Legal Services",
            "type":"Services"
        }
    ],
    "sg:phone":"+1 812 385 1218",
    "sg:postcode":"47670",
    "sg:province":"IN",
    "sg:tags":[
        "attorney"
    ],
    "wof:name":"Lisa A Moody Law Office",
    "wof:placetype":"venue"
},
  "geometry": {"coordinates":[-87.569866,38.356168],"type":"Point"}
}