{
  "type": "Feature",
  "properties": {
    "iso:country":"US",
    "sg:address":"2045 Davis Ave",
    "sg:city":"Whiting",
    "sg:classifiers":[
        {
            "category":"Building & Trades",
            "subcategory":"Construction",
            "type":"Services"
        }
    ],
    "sg:phone":"+1 219 659 0450",
    "sg:postcode":"46394",
    "sg:province":"IN",
    "sg:tags":[
        "air",
        "heating",
        "conditioning/hvac"
    ],
    "wof:name":"Dr Climate",
    "wof:placetype":"venue"
},
  "geometry": {"coordinates":[-87.507349,41.67656],"type":"Point"}
}