{
  "type": "Feature",
  "properties": {
    "addr:full":"10150 Lenover St Dillsboro IN 47018",
    "addr:housenumber":"10150",
    "addr:postcode":"47018",
    "addr:street":"Lenover St",
    "iso:country":"US",
    "sg:address":"10150 Lenover St",
    "sg:city":"Dillsboro",
    "sg:classifiers":[
        {
            "category":"Manufacturing",
            "subcategory":"Tools & Machinery",
            "type":"Manufacturing & Wholesale Goods"
        }
    ],
    "sg:phone":"+1 812 432 5946",
    "sg:postcode":"47018",
    "sg:province":"IN",
    "sg:tags":[
        "machine",
        "shop"
    ],
    "wof:name":"Multiple Machining",
    "wof:placetype":"venue"
},
  "geometry": {"coordinates":[-85.05170200000001,39.01866],"type":"Point"}
}