{
  "type": "Feature",
  "properties": {
    "addr:full":"98 E Canal St Wabash IN 46992",
    "addr:housenumber":"98",
    "addr:postcode":"46992",
    "addr:street":"E Canal St",
    "iso:country":"US",
    "sg:address":"98 E Canal St",
    "sg:city":"Wabash",
    "sg:classifiers":[
        {
            "category":"Manufacturing",
            "subcategory":"Rubber & Plastics",
            "type":"Manufacturing & Wholesale Goods"
        }
    ],
    "sg:phone":"+1 260 569 9088",
    "sg:postcode":"46992",
    "sg:province":"IN",
    "sg:website":"www.bulldog-battery.com",
    "wof:name":"Poly Plastics LTD",
    "wof:placetype":"venue"
},
  "geometry": {"coordinates":[-85.819464,40.796054],"type":"Point"}
}