{
  "type": "Feature",
  "properties": {
    "iso:country":"US",
    "sg:address":"1947 S 700 W",
    "sg:city":"New Palestine",
    "sg:classifiers":[
        {
            "category":"Autos & Motor Vehicles",
            "subcategory":"Automobile Sales",
            "type":"Retail Goods"
        }
    ],
    "sg:phone":"+1 317 861 1018",
    "sg:postcode":"46163",
    "sg:province":"IN",
    "sg:tags":[
        "car",
        "dealer"
    ],
    "wof:name":"Bob Sullivan Motors",
    "wof:placetype":"venue"
},
  "geometry": {"coordinates":[-85.933065,39.761689],"type":"Point"}
}