{
  "type": "Feature",
  "properties": {
    "iso:country":"US",
    "sg:address":"12615 W 93rd Ave",
    "sg:city":"Saint John",
    "sg:classifiers":[
        {
            "category":"Professional",
            "subcategory":"Business Services",
            "type":"Services"
        }
    ],
    "sg:phone":"+1 219 365 7075",
    "sg:postcode":"46373",
    "sg:province":"IN",
    "wof:name":"Filkor Enterprises LLC",
    "wof:placetype":"venue"
},
  "geometry": {"coordinates":[-87.48478299999999,41.449891],"type":"Point"}
}