{
  "type": "Feature",
  "properties": {
    "iso:country":"US",
    "sg:address":"1901 S Heaton St",
    "sg:city":"Knox",
    "sg:classifiers":[
        {
            "category":"Health Services",
            "subcategory":"Doctor",
            "type":"Services"
        }
    ],
    "sg:phone":"+1 574 772 6363",
    "sg:postcode":"46534",
    "sg:province":"IN",
    "sg:tags":[
        "physician",
        "surgeon"
    ],
    "wof:name":"Cardiovascular Clinic",
    "wof:placetype":"venue"
},
  "geometry": {"coordinates":[-86.620723,41.276918],"type":"Point"}
}