{
  "type": "Feature",
  "properties": {
    "addr:full":"1828 Westfield Ct Griffith IN 46319",
    "addr:housenumber":"1828",
    "addr:postcode":"46319",
    "addr:street":"Westfield Ct",
    "iso:country":"US",
    "sg:address":"1828 Westfield Ct",
    "sg:city":"Griffith",
    "sg:classifiers":[
        {
            "category":"Building & Trades",
            "subcategory":"Plumbing",
            "type":"Services"
        }
    ],
    "sg:phone":"+1 219 923 3617",
    "sg:postcode":"46319",
    "sg:province":"IN",
    "sg:tags":[
        "plumbing",
        "contractor"
    ],
    "wof:name":"Gary Downing Plumbing",
    "wof:placetype":"venue"
},
  "geometry": {"coordinates":[-87.422042,41.554615],"type":"Point"}
}