{
  "type": "Feature",
  "properties": {
    "iso:country":"US",
    "sg:address":"2520 Walton Blvd",
    "sg:city":"Warsaw",
    "sg:classifiers":[
        {
            "category":"Shopping",
            "subcategory":"Clothing, Apparel, & Fashions",
            "type":"Retail Goods"
        }
    ],
    "sg:phone":"+1 574 267 7199",
    "sg:postcode":"46582",
    "sg:province":"IN",
    "wof:name":"Fashion Bug",
    "wof:placetype":"venue"
},
  "geometry": {"coordinates":[-85.856576,41.271],"type":"Point"}
}