{
  "type": "Feature",
  "properties": {
    "iso:country":"US",
    "sg:address":"9021 W Lewisville Rd",
    "sg:city":"Paragon",
    "sg:classifiers":[
        {
            "category":"Building & Trades",
            "subcategory":"Construction",
            "type":"Services"
        }
    ],
    "sg:phone":"+1 765 537 2032",
    "sg:postcode":"46166",
    "sg:province":"IN",
    "sg:tags":[
        "house"
    ],
    "wof:name":"Samson Construction",
    "wof:placetype":"venue"
},
  "geometry": {"coordinates":[-86.59730999999999,39.469914],"type":"Point"}
}