{
  "type": "Feature",
  "properties": {
    "iso:country":"US",
    "sg:address":"2450 N Meridian St",
    "sg:city":"Indianapolis",
    "sg:classifiers":[
        {
            "category":"Education",
            "subcategory":"Library",
            "type":"Public Place"
        }
    ],
    "sg:phone":"+1 317 269 5388",
    "sg:postcode":"46208",
    "sg:province":"IN",
    "wof:name":"Library Service Ctr",
    "wof:placetype":"venue"
},
  "geometry": {"coordinates":[-86.156825,39.801383],"type":"Point"}
}