{
  "type": "Feature",
  "properties": {
    "iso:country":"US",
    "sg:address":"7125 Georgetown Rd",
    "sg:city":"Indianapolis",
    "sg:classifiers":[
        {
            "category":"Personal",
            "subcategory":"Beauty Salon",
            "type":"Services"
        }
    ],
    "sg:phone":"+1 317 290 6001",
    "sg:postcode":"46254",
    "sg:province":"IN",
    "wof:name":"Fantastic Sam's",
    "wof:placetype":"venue"
},
  "geometry": {"coordinates":[-86.241529,39.89324],"type":"Point"}
}