{
  "type": "Feature",
  "properties": {
    "iso:country":"US",
    "sg:address":"116 N Jefferson St",
    "sg:city":"Hartford City",
    "sg:classifiers":[
        {
            "category":"Professional",
            "subcategory":"Business Services",
            "type":"Services"
        }
    ],
    "sg:phone":"+1 765 348 3048",
    "sg:postcode":"47348",
    "sg:province":"IN",
    "sg:tags":[
        "license"
    ],
    "wof:name":"License Branch-Auto",
    "wof:placetype":"venue"
},
  "geometry": {"coordinates":[-85.36733,40.451991],"type":"Point"}
}