{
  "type": "Feature",
  "properties": {
    "addr:full":"1400 E Hanna Ave Indianapolis IN 46227",
    "addr:housenumber":"1400",
    "addr:postcode":"46227",
    "addr:street":"E Hanna Ave",
    "iso:country":"US",
    "sg:address":"1400 E Hanna Ave",
    "sg:city":"Indianapolis",
    "sg:classifiers":[
        {
            "category":"Communications",
            "subcategory":"Radio Station",
            "type":"Services"
        }
    ],
    "sg:phone":"+1 317 788 3280",
    "sg:postcode":"46227",
    "sg:province":"IN",
    "sg:tags":[
        "company",
        "broadcasting"
    ],
    "wof:name":"WICR Comm",
    "wof:placetype":"venue"
},
  "geometry": {"coordinates":[-86.139314,39.708401],"type":"Point"}
}