{
  "type": "Feature",
  "properties": {
    "addr:full":"3585 W 500 N Decatur IN 46733",
    "addr:housenumber":"3585",
    "addr:postcode":"46733",
    "addr:street":"W 500 N",
    "iso:country":"US",
    "sg:address":"3585 W 500 N",
    "sg:city":"Decatur",
    "sg:classifiers":[
        {
            "category":"Building & Trades",
            "subcategory":"Construction",
            "type":"Services"
        }
    ],
    "sg:phone":"+1 260 547 4626",
    "sg:postcode":"46733",
    "sg:province":"IN",
    "sg:tags":[
        "insulation",
        "heat",
        "contractor"
    ],
    "wof:name":"Hamilton Insulation Inc",
    "wof:placetype":"venue"
},
  "geometry": {"coordinates":[-85.006788,40.816642],"type":"Point"}
}