{
  "type": "Feature",
  "properties": {
    "addr:full":"1730 State Rd 37 Paoli IN 47454",
    "addr:housenumber":"1730;37",
    "addr:postcode":"47454",
    "addr:street":"State Rd",
    "iso:country":"US",
    "sg:address":"1730 State Rd 37",
    "sg:city":"Paoli",
    "sg:classifiers":[
        {
            "category":"Personal",
            "subcategory":"Beauty Salon",
            "type":"Services"
        }
    ],
    "sg:phone":"+1 812 723 5258",
    "sg:postcode":"47454",
    "sg:province":"IN",
    "sg:tags":[
        "shop"
    ],
    "wof:name":"Debbie's Hair Care",
    "wof:placetype":"venue"
},
  "geometry": {"coordinates":[-86.460526,38.536098],"type":"Point"}
}