{
  "type": "Feature",
  "properties": {
    "iso:country":"US",
    "sg:address":"1916 Manhattan St",
    "sg:city":"Michigan City",
    "sg:classifiers":[
        {
            "category":"Building & Trades",
            "subcategory":"Construction",
            "type":"Services"
        }
    ],
    "sg:phone":"+1 219 871 0203",
    "sg:postcode":"46360",
    "sg:province":"IN",
    "sg:tags":[
        "lettering",
        "painting",
        "boat"
    ],
    "wof:name":"Michigan City Signs",
    "wof:placetype":"venue"
},
  "geometry": {"coordinates":[-86.901709,41.702735],"type":"Point"}
}