{
  "type": "Feature",
  "properties": {
    "addr:full":"3816 E Rachels Glen Rd Bloomington IN 47408",
    "addr:housenumber":"3816",
    "addr:postcode":"47408",
    "addr:street":"E Rachels Glen Rd",
    "iso:country":"US",
    "sg:address":"3816 E Rachels Glen Rd",
    "sg:city":"Bloomington",
    "sg:classifiers":[
        {
            "category":"Shopping",
            "type":"Retail Goods"
        }
    ],
    "sg:phone":"+1 812 339 3014",
    "sg:postcode":"47408",
    "sg:province":"IN",
    "sg:tags":[
        "merchandise"
    ],
    "wof:name":"Harrison Fine Art",
    "wof:placetype":"venue"
},
  "geometry": {"coordinates":[-86.484814,39.177059],"type":"Point"}
}