{
  "type": "Feature",
  "properties": {
    "iso:country":"US",
    "sg:address":"5147 S US Hwy 41",
    "sg:city":"Terre Haute",
    "sg:classifiers":[
        {
            "category":"Restaurant",
            "type":"Food & Drink"
        }
    ],
    "sg:phone":"+1 812 298 0643",
    "sg:postcode":"47802",
    "sg:province":"IN",
    "wof:name":"Los Tres Caminos",
    "wof:placetype":"venue"
},
  "geometry": {"coordinates":[-87.406919,39.405164],"type":"Point"}
}