{
  "type": "Feature",
  "properties": {
    "iso:country":"US",
    "sg:address":"4207 N Clinton St",
    "sg:city":"Fort Wayne",
    "sg:classifiers":[
        {
            "category":"Professional",
            "subcategory":"Business Services",
            "type":"Services"
        }
    ],
    "sg:phone":"+1 260 482 3448",
    "sg:postcode":"46805",
    "sg:province":"IN",
    "sg:tags":[
        "trade",
        "fair",
        "show"
    ],
    "sg:website":"www.cpishows.com",
    "wof:name":"CPI",
    "wof:placetype":"venue"
},
  "geometry": {"coordinates":[-85.13036099999999,41.115972],"type":"Point"}
}