{
  "type": "Feature",
  "properties": {
    "iso:country":"US",
    "sg:address":"30338 Co Rd 12",
    "sg:city":"Elkhart",
    "sg:classifiers":[
        {
            "category":"Autos & Motor Vehicles",
            "subcategory":"Auto Supplies",
            "type":"Retail Goods"
        }
    ],
    "sg:phone":"+1 574 264 5963",
    "sg:postcode":"46514",
    "sg:province":"IN",
    "sg:tags":[
        "automobile",
        "parts"
    ],
    "wof:name":"Auto 1 Motors Inc",
    "wof:placetype":"venue"
},
  "geometry": {"coordinates":[-86.050459,41.69532],"type":"Point"}
}