{
  "type": "Feature",
  "properties": {
    "iso:country":"US",
    "sg:address":"429 E Vermont St",
    "sg:city":"Indianapolis",
    "sg:classifiers":[
        {
            "category":"Building & Trades",
            "subcategory":"Landscaping Services",
            "type":"Services"
        }
    ],
    "sg:phone":"+1 317 263 0127",
    "sg:postcode":"46202",
    "sg:province":"IN",
    "sg:tags":[
        "designer",
        "landscape"
    ],
    "wof:name":"Rundell Ernstberger Assocs",
    "wof:placetype":"venue"
},
  "geometry": {"coordinates":[-86.148839,39.772427],"type":"Point"}
}