{
  "type": "Feature",
  "properties": {
    "iso:country":"US",
    "sg:address":"1610 S Weinbach Ave",
    "sg:city":"Evansville",
    "sg:classifiers":[
        {
            "category":"Building & Trades",
            "subcategory":"Construction",
            "type":"Services"
        }
    ],
    "sg:phone":"+1 812 471 1727",
    "sg:postcode":"47714",
    "sg:province":"IN",
    "sg:tags":[
        "resurfacing",
        "laying",
        "refinishing",
        "floor"
    ],
    "wof:name":"Randy Rasure Floors",
    "wof:placetype":"venue"
},
  "geometry": {"coordinates":[-87.529684,37.954633],"type":"Point"}
}