{
  "type": "Feature",
  "properties": {
    "iso:country":"US",
    "sg:address":"1349 Graham Rd",
    "sg:city":"Franklin",
    "sg:classifiers":[
        {
            "category":"Organizations",
            "subcategory":"Religious Organization",
            "type":"Services"
        }
    ],
    "sg:phone":"+1 317 736 9276",
    "sg:postcode":"46131",
    "sg:province":"IN",
    "sg:tags":[
        "church"
    ],
    "wof:name":"Faith Missionary Baptist Chr",
    "wof:placetype":"venue"
},
  "geometry": {"coordinates":[-86.055115,39.492799],"type":"Point"}
}