{
  "type": "Feature",
  "properties": {
    "addr:full":"219 N Perkins St Rushville IN 46173",
    "addr:housenumber":"219",
    "addr:postcode":"46173",
    "addr:street":"N Perkins St",
    "iso:country":"US",
    "sg:address":"219 N Perkins St",
    "sg:city":"Rushville",
    "sg:classifiers":[
        {
            "category":"Professional",
            "type":"Services"
        }
    ],
    "sg:phone":"+1 765 932 3111",
    "sg:postcode":"46173",
    "sg:province":"IN",
    "sg:tags":[
        "establishment"
    ],
    "wof:name":"Rushville Telegram",
    "wof:placetype":"venue"
},
  "geometry": {"coordinates":[-85.44340699999999,39.609135],"type":"Point"}
}