{
  "type": "Feature",
  "properties": {
    "iso:country":"US",
    "sg:address":"973 W Monoquet Rd",
    "sg:city":"Warsaw",
    "sg:classifiers":[
        {
            "category":"Retail",
            "subcategory":"Repair Shop",
            "type":"Services"
        }
    ],
    "sg:phone":"+1 574 269 4505",
    "sg:postcode":"46582",
    "sg:province":"IN",
    "sg:tags":[
        "electrical"
    ],
    "wof:name":"Dons Appliance Repair",
    "wof:placetype":"venue"
},
  "geometry": {"coordinates":[-85.86207,41.289349],"type":"Point"}
}