{
  "type": "Feature",
  "properties": {
    "iso:country":"US",
    "sg:address":"5701 Grape Rd",
    "sg:city":"Mishawaka",
    "sg:classifiers":[
        {
            "category":"Home & Garden",
            "subcategory":"Furniture",
            "type":"Retail Goods"
        }
    ],
    "sg:phone":"+1 574 255 9989",
    "sg:postcode":"46545",
    "sg:province":"IN",
    "sg:tags":[
        "mattress"
    ],
    "wof:name":"Mattress Warehouse Inc",
    "wof:placetype":"venue"
},
  "geometry": {"coordinates":[-86.1877,41.711987],"type":"Point"}
}