{
  "type": "Feature",
  "properties": {
    "iso:country":"US",
    "sg:address":"831 Kreckler St",
    "sg:city":"Clinton",
    "sg:classifiers":[
        {
            "category":"Autos & Motor Vehicles",
            "subcategory":"Automobile Sales",
            "type":"Retail Goods"
        }
    ],
    "sg:phone":"+1 765 832 9470",
    "sg:postcode":"47842",
    "sg:province":"IN",
    "sg:tags":[
        "used"
    ],
    "wof:name":"Golden Years Auto Mart",
    "wof:placetype":"venue"
},
  "geometry": {"coordinates":[-87.40822799999999,39.674371],"type":"Point"}
}