{
  "type": "Feature",
  "properties": {
    "iso:country":"US",
    "sg:address":"1720 S 10th St",
    "sg:city":"Noblesville",
    "sg:classifiers":[
        {
            "category":"Manufacturing",
            "subcategory":"Signs",
            "type":"Manufacturing & Wholesale Goods"
        }
    ],
    "sg:phone":"+1 317 773 7200",
    "sg:postcode":"46060",
    "sg:province":"IN",
    "wof:name":"Logan St Signs & Banners",
    "wof:placetype":"venue"
},
  "geometry": {"coordinates":[-86.01195,40.028704],"type":"Point"}
}