{
  "type": "Feature",
  "properties": {
    "iso:country":"US",
    "sg:address":"1101 E 500 N",
    "sg:city":"West Lafayette",
    "sg:classifiers":[
        {
            "category":"Building & Trades",
            "subcategory":"Construction",
            "type":"Services"
        }
    ],
    "sg:phone":"+1 765 463 0111",
    "sg:postcode":"47906",
    "sg:province":"IN",
    "sg:tags":[
        "home",
        "improvement"
    ],
    "wof:name":"River City Builders",
    "wof:placetype":"venue"
},
  "geometry": {"coordinates":[-86.889892,40.489344],"type":"Point"}
}