{
  "type": "Feature",
  "properties": {
    "addr:full":"10721 W Lakeshore Dr Carmel IN 46033",
    "addr:housenumber":"10721",
    "addr:postcode":"46033",
    "addr:street":"W Lakeshore Dr",
    "iso:country":"US",
    "sg:address":"10721 W Lakeshore Dr",
    "sg:city":"Carmel",
    "sg:classifiers":[
        {
            "category":"Education",
            "subcategory":"School",
            "type":"Public Place"
        }
    ],
    "sg:phone":"+1 317 844 4948",
    "sg:postcode":"46033",
    "sg:province":"IN",
    "sg:tags":[
        "high",
        "middle",
        "elementary"
    ],
    "wof:name":"Public Schools",
    "wof:placetype":"venue"
},
  "geometry": {"coordinates":[-86.111265,39.943783],"type":"Point"}
}