{
  "type": "Feature",
  "properties": {
    "addr:full":"WE COME TO U Indianapolis IN 46214",
    "addr:postcode":"46214",
    "iso:country":"US",
    "sg:address":"WE COME TO U",
    "sg:city":"Indianapolis",
    "sg:phone":"+1 317 717 1153",
    "sg:postcode":"46214",
    "sg:province":"IN",
    "wof:name":"MOBILE NAILS",
    "wof:placetype":"venue"
},
  "geometry": {"coordinates":[-86.268158,39.765629],"type":"Point"}
}