{
  "type": "Feature",
  "properties": {
    "iso:country":"US",
    "sg:address":"2901 Parnell Ave",
    "sg:city":"Fort Wayne",
    "sg:classifiers":[
        {
            "category":"Health Services",
            "subcategory":"Medical Lab",
            "type":"Services"
        }
    ],
    "sg:phone":"+1 260 427 9170",
    "sg:postcode":"46805",
    "sg:province":"IN",
    "sg:tags":[
        "x"
    ],
    "wof:name":"Mobilex",
    "wof:placetype":"venue"
},
  "geometry": {"coordinates":[-85.130215,41.102886],"type":"Point"}
}