{
  "type": "Feature",
  "properties": {
    "addr:full":"3119 W Sample St South Bend IN 46619",
    "addr:housenumber":"3119",
    "addr:postcode":"46619",
    "addr:street":"W Sample St",
    "iso:country":"US",
    "sg:address":"3119 W Sample St",
    "sg:city":"South Bend",
    "sg:classifiers":[
        {
            "category":"Professional",
            "type":"Services"
        }
    ],
    "sg:phone":"+1 574 232 3179",
    "sg:postcode":"46619",
    "sg:province":"IN",
    "sg:tags":[
        "establishment"
    ],
    "wof:name":"Preferred Finishing",
    "wof:placetype":"venue"
},
  "geometry": {"coordinates":[-86.293374,41.664796],"type":"Point"}
}