{
  "type": "Feature",
  "properties": {
    "iso:country":"US",
    "sg:address":"1670 W McClain St",
    "sg:city":"Scottsburg",
    "sg:classifiers":[
        {
            "category":"Banks & Credit Unions",
            "subcategory":"Bank",
            "type":"Services"
        }
    ],
    "sg:phone":"+1 812 752 9229",
    "sg:postcode":"47170",
    "sg:province":"IN",
    "sg:tags":[
        "loan"
    ],
    "wof:name":"Cash 2 Go",
    "wof:placetype":"venue"
},
  "geometry": {"coordinates":[-85.787629,38.685597],"type":"Point"}
}