{
  "type": "Feature",
  "properties": {
    "iso:country":"US",
    "sg:address":"9014 Kirkham Ct",
    "sg:city":"Indianapolis",
    "sg:classifiers":[
        {
            "category":"Professional",
            "subcategory":"Lawyer & Legal Services",
            "type":"Services"
        }
    ],
    "sg:phone":"+1 317 844 1308",
    "sg:postcode":"46260",
    "sg:province":"IN",
    "wof:name":"Young John A Atty",
    "wof:placetype":"venue"
},
  "geometry": {"coordinates":[-86.183296,39.9184],"type":"Point"}
}