{
  "type": "Feature",
  "properties": {
    "iso:country":"US",
    "sg:address":"1702 W 51st St",
    "sg:city":"Indianapolis",
    "sg:classifiers":[
        {
            "category":"Professional",
            "subcategory":"Business Services",
            "type":"Services"
        }
    ],
    "sg:phone":"+1 317 475 1906",
    "sg:postcode":"46228",
    "sg:province":"IN",
    "sg:tags":[
        "interior",
        "consultant",
        "design",
        "decorator"
    ],
    "sg:website":"www.popeinteriors.com",
    "wof:name":"Pope Interior Design",
    "wof:placetype":"venue"
},
  "geometry": {"coordinates":[-86.192336,39.844524],"type":"Point"}
}