{
  "type": "Feature",
  "properties": {
    "iso:country":"US",
    "sg:address":"30 State Rd 129",
    "sg:city":"Batesville",
    "sg:classifiers":[
        {
            "category":"Social Services",
            "type":"Services"
        }
    ],
    "sg:phone":"+1 812 934 6006",
    "sg:postcode":"47006",
    "sg:province":"IN",
    "sg:tags":[
        "organization",
        "welfare"
    ],
    "wof:name":"YMCA",
    "wof:placetype":"venue"
},
  "geometry": {"coordinates":[-85.202528,39.288747],"type":"Point"}
}