{
  "type": "Feature",
  "properties": {
    "iso:country":"US",
    "sg:address":"2611 E Michigan St",
    "sg:city":"Indianapolis",
    "sg:classifiers":[
        {
            "category":"Real Estate",
            "subcategory":"Real Estate Operator",
            "type":"Services"
        }
    ],
    "sg:phone":"+1 317 636 1156",
    "sg:postcode":"46201",
    "sg:province":"IN",
    "sg:tags":[
        "apartment"
    ],
    "wof:name":"Agee & Co",
    "wof:placetype":"venue"
},
  "geometry": {"coordinates":[-86.117927,39.774373],"type":"Point"}
}