{
  "type": "Feature",
  "properties": {
    "iso:country":"US",
    "sg:address":"1920 Parkvalley Dr",
    "sg:city":"Columbus",
    "sg:classifiers":[
        {
            "category":"Retail",
            "subcategory":"Laundry & Dry Cleaning",
            "type":"Services"
        }
    ],
    "sg:phone":"+1 812 372 3960",
    "sg:postcode":"47203",
    "sg:province":"IN",
    "wof:name":"Specialists In Deep Clean",
    "wof:placetype":"venue"
},
  "geometry": {"coordinates":[-85.880569,39.219475],"type":"Point"}
}