{
  "type": "Feature",
  "properties": {
    "iso:country":"US",
    "sg:address":"8330 Castleton Corner Dr",
    "sg:city":"Indianapolis",
    "sg:classifiers":[
        {
            "category":"Real Estate",
            "subcategory":"Real Estate Agent",
            "type":"Services"
        }
    ],
    "sg:phone":"+1 317 595 8904",
    "sg:postcode":"46250",
    "sg:province":"IN",
    "wof:name":"Mc Kinley",
    "wof:placetype":"venue"
},
  "geometry": {"coordinates":[-86.071202,39.908631],"type":"Point"}
}