{
  "type": "Feature",
  "properties": {
    "iso:country":"US",
    "sg:address":"400 S West St",
    "sg:city":"Mishawaka",
    "sg:classifiers":[
        {
            "category":"Manufacturing",
            "subcategory":"Metals",
            "type":"Manufacturing & Wholesale Goods"
        }
    ],
    "sg:phone":"+1 574 674 8009",
    "sg:postcode":"46544",
    "sg:province":"IN",
    "sg:tags":[
        "stamping"
    ],
    "wof:name":"Budget Advertising Inc",
    "wof:placetype":"venue"
},
  "geometry": {"coordinates":[-86.185943,41.657396],"type":"Point"}
}