{
  "type": "Feature",
  "properties": {
    "iso:country":"US",
    "sg:address":"1358 Knighthood Dr",
    "sg:city":"Dyer",
    "sg:classifiers":[
        {
            "category":"Professional",
            "subcategory":"Management & Consulting",
            "type":"Services"
        }
    ],
    "sg:phone":"+1 219 322 5385",
    "sg:postcode":"46311",
    "sg:province":"IN",
    "sg:tags":[
        "consultant",
        "business"
    ],
    "wof:name":"Angel Venture Enterprises",
    "wof:placetype":"venue"
},
  "geometry": {"coordinates":[-87.498635,41.481497],"type":"Point"}
}