{
  "type": "Feature",
  "properties": {
    "iso:country":"US",
    "sg:address":"619 Lincoln Ave",
    "sg:city":"Bedford",
    "sg:classifiers":[
        {
            "category":"Retail",
            "subcategory":"Animal Services",
            "type":"Services"
        }
    ],
    "sg:phone":"+1 812 278 9880",
    "sg:postcode":"47421",
    "sg:province":"IN",
    "sg:tags":[
        "pet",
        "grooming",
        "washing"
    ],
    "wof:name":"Wags & Whiskers Pet Grooming",
    "wof:placetype":"venue"
},
  "geometry": {"coordinates":[-86.490576,38.872916],"type":"Point"}
}