{
  "type": "Feature",
  "properties": {
    "iso:country":"US",
    "sg:address":"650 Sycamore St",
    "sg:city":"Terre Haute",
    "sg:classifiers":[
        {
            "category":"Education",
            "subcategory":"Library",
            "type":"Public Place"
        }
    ],
    "sg:phone":"+1 812 237 3700",
    "sg:postcode":"47438",
    "sg:province":"IN",
    "wof:name":"Cunningham Memorial Library",
    "wof:placetype":"venue"
},
  "geometry": {"coordinates":[-87.191584,39.162167],"type":"Point"}
}