{
  "type": "Feature",
  "properties": {
    "iso:country":"US",
    "sg:address":"5239 Mann Rd",
    "sg:city":"Indianapolis",
    "sg:classifiers":[
        {
            "category":"Manufacturing",
            "subcategory":"Printing",
            "type":"Manufacturing & Wholesale Goods"
        }
    ],
    "sg:phone":"+1 317 856 5915",
    "sg:postcode":"46221",
    "sg:province":"IN",
    "sg:tags":[
        "screen"
    ],
    "wof:name":"Sassi Enterprises",
    "wof:placetype":"venue"
},
  "geometry": {"coordinates":[-86.244336,39.687102],"type":"Point"}
}