{
  "type": "Feature",
  "properties": {
    "iso:country":"US",
    "sg:address":"3905 Vincennes Rd",
    "sg:city":"Indianapolis",
    "sg:classifiers":[
        {
            "category":"Banks & Credit Unions",
            "subcategory":"Bank",
            "type":"Services"
        }
    ],
    "sg:phone":"+1 317 871 8300",
    "sg:postcode":"46268",
    "sg:province":"IN",
    "sg:tags":[
        "loan",
        "real estate"
    ],
    "wof:name":"KBM Mortgage Corp",
    "wof:placetype":"venue"
},
  "geometry": {"coordinates":[-86.227923,39.91514],"type":"Point"}
}