{
  "type": "Feature",
  "properties": {
    "iso:country":"US",
    "sg:address":"635 S State Rd 213",
    "sg:city":"Tipton",
    "sg:phone":"+1 765 675 2164",
    "sg:postcode":"46072",
    "sg:province":"IN",
    "sg:tags":[
        "farm",
        "corn",
        "soybean"
    ],
    "wof:name":"Larry Griffin",
    "wof:placetype":"venue"
},
  "geometry": {"coordinates":[-85.956881,40.296555],"type":"Point"}
}