{
  "type": "Feature",
  "properties": {
    "iso:country":"US",
    "sg:address":"4201 W Tanglewood Dr",
    "sg:city":"Bloomington",
    "sg:classifiers":[
        {
            "category":"Arts & Performance",
            "subcategory":"Theater",
            "type":"Entertainment"
        }
    ],
    "sg:phone":"+1 812 876 9249",
    "sg:postcode":"47404",
    "sg:province":"IN",
    "sg:tags":[
        "magician"
    ],
    "wof:name":"Magic By Greg",
    "wof:placetype":"venue"
},
  "geometry": {"coordinates":[-86.58559700000001,39.234981],"type":"Point"}
}