{
  "type": "Feature",
  "properties": {
    "addr:full":"11602 E 500 S Greentown IN 46936",
    "addr:housenumber":"11602",
    "addr:postcode":"46936",
    "addr:street":"E 500 S Greentown",
    "iso:country":"US",
    "sg:address":"11602 E 500 S",
    "sg:city":"Greentown",
    "sg:classifiers":[
        {
            "category":"Farming",
            "subcategory":"Farm",
            "type":"Manufacturing & Wholesale Goods"
        }
    ],
    "sg:phone":"+1 765 945 7380",
    "sg:postcode":"46936",
    "sg:province":"IN",
    "sg:tags":[
        "crop",
        "general"
    ],
    "wof:name":"Smith Farm Inc",
    "wof:placetype":"venue"
},
  "geometry": {"coordinates":[-85.90131599999999,40.406702],"type":"Point"}
}