{
  "type": "Feature",
  "properties": {
    "iso:country":"US",
    "sg:address":"705 W Coolidge Dr",
    "sg:city":"Bloomington",
    "sg:classifiers":[
        {
            "category":"Education",
            "subcategory":"School",
            "type":"Public Place"
        }
    ],
    "sg:phone":"+1 812 330 7739",
    "sg:postcode":"47403",
    "sg:province":"IN",
    "wof:name":"Broadview Elementary School",
    "wof:placetype":"venue"
},
  "geometry": {"coordinates":[-86.542151,39.141241],"type":"Point"}
}