{
  "type": "Feature",
  "properties": {
    "iso:country":"US",
    "sg:address":"132 Berens St",
    "sg:city":"Dyer",
    "sg:classifiers":[
        {
            "category":"Social Services",
            "type":"Services"
        },
        {
            "category":"Building & Trades",
            "subcategory":"Landscaping Services",
            "type":"Services"
        }
    ],
    "sg:phone":"+1 219 865 0253",
    "sg:postcode":"46311",
    "sg:province":"IN",
    "sg:tags":[
        "aged",
        "homes-institutional"
    ],
    "sg:website":"http://www.in-pact.org",
    "wof:name":"In-Pact, Inc.",
    "wof:placetype":"venue"
},
  "geometry": {"coordinates":[-87.52253899999999,41.487291],"type":"Point"}
}