{
  "type": "Feature",
  "properties": {
    "iso:country":"US",
    "sg:address":"1403 S Harkless Dr",
    "sg:city":"Syracuse",
    "sg:classifiers":[
        {
            "category":"Building & Trades",
            "subcategory":"Construction",
            "type":"Services"
        }
    ],
    "sg:phone":"+1 574 457 3034",
    "sg:postcode":"46567",
    "sg:province":"IN",
    "sg:tags":[
        "painter"
    ],
    "wof:name":"Handyman Home Improvement Svc",
    "wof:placetype":"venue"
},
  "geometry": {"coordinates":[-85.743964,41.406129],"type":"Point"}
}