{
  "type": "Feature",
  "properties": {
    "iso:country":"US",
    "sg:address":"13923 Selvin Rd",
    "sg:city":"Holland",
    "sg:classifiers":[
        {
            "category":"Professional",
            "subcategory":"Management & Consulting",
            "type":"Services"
        }
    ],
    "sg:phone":"+1 812 536 2404",
    "sg:postcode":"47541",
    "sg:province":"IN",
    "wof:name":"Conflict Consulting Inc",
    "wof:placetype":"venue"
},
  "geometry": {"coordinates":[-87.07388899999999,38.232205],"type":"Point"}
}