{
  "type": "Feature",
  "properties": {
    "addr:full":"5767 Thunderbird Rd Indianapolis IN 46236",
    "addr:housenumber":"5767",
    "addr:postcode":"46236",
    "addr:street":"Thunderbird Rd",
    "iso:country":"US",
    "sg:address":"5767 Thunderbird Rd",
    "sg:city":"Indianapolis",
    "sg:classifiers":[
        {
            "category":"Manufacturing",
            "subcategory":"Chemicals & Compounds",
            "type":"Manufacturing & Wholesale Goods"
        },
        {
            "category":"Wholesale",
            "subcategory":"Medical Equipment & Supplies",
            "type":"Manufacturing & Wholesale Goods"
        },
        {
            "category":"Shopping",
            "subcategory":"Pharmacy",
            "type":"Retail Goods"
        }
    ],
    "sg:phone":"+1 317 895 9000",
    "sg:postcode":"46236",
    "sg:province":"IN",
    "sg:tags":[
        "pharmaceutical",
        "product",
        "proprietary",
        "products-wholesale",
        "medicines-patent",
        "manufacturer"
    ],
    "sg:website":"http://www.vestapharm.com",
    "wof:name":"Vesta Pharmaceuticals, Inc",
    "wof:placetype":"venue"
},
  "geometry": {"coordinates":[-85.981082,39.860115],"type":"Point"}
}