{
  "type": "Feature",
  "properties": {
    "iso:country":"US",
    "sg:address":"830 E Markland Ave",
    "sg:city":"Kokomo",
    "sg:classifiers":[
        {
            "category":"Manufacturing",
            "subcategory":"Food",
            "type":"Manufacturing & Wholesale Goods"
        }
    ],
    "sg:phone":"+1 765 452 5516",
    "sg:postcode":"46901",
    "sg:province":"IN",
    "sg:tags":[
        "frozen",
        "dessert",
        "ice",
        "cream"
    ],
    "wof:name":"Passion For Cheesecake",
    "wof:placetype":"venue"
},
  "geometry": {"coordinates":[-86.122292,40.47662],"type":"Point"}
}