{
  "type": "Feature",
  "properties": {
    "iso:country":"US",
    "sg:address":"403 W Co Rd 700 N",
    "sg:city":"Orleans",
    "sg:classifiers":[
        {
            "category":"Autos & Motor Vehicles",
            "subcategory":"Auto Supplies",
            "type":"Retail Goods"
        }
    ],
    "sg:phone":"+1 812 865 3919",
    "sg:postcode":"47452",
    "sg:province":"IN",
    "wof:name":"Hagers Tire Shop",
    "wof:placetype":"venue"
},
  "geometry": {"coordinates":[-86.467549,38.659275],"type":"Point"}
}