{
  "type": "Feature",
  "properties": {
    "iso:country":"US",
    "sg:address":"625 3rd Ave SW",
    "sg:city":"Carmel",
    "sg:classifiers":[
        {
            "category":"Autos & Motor Vehicles",
            "subcategory":"Motorcycle Sales",
            "type":"Retail Goods"
        }
    ],
    "sg:phone":"+1 317 569 0879",
    "sg:postcode":"46032",
    "sg:province":"IN",
    "sg:tags":[
        "scooter"
    ],
    "wof:name":"Segway Of Indiana LLC",
    "wof:placetype":"venue"
},
  "geometry": {"coordinates":[-86.13122,39.968424],"type":"Point"}
}