{
  "type": "Feature",
  "properties": {
    "iso:country":"US",
    "sg:address":"5921 N 350 E",
    "sg:city":"Columbia City",
    "sg:classifiers":[
        {
            "category":"Real Estate",
            "subcategory":"Real Estate Agent",
            "type":"Services"
        }
    ],
    "sg:phone":"+1 260 691 2115",
    "sg:postcode":"46725",
    "sg:province":"IN",
    "wof:name":"Miller-Howe Raydeen",
    "wof:placetype":"venue"
},
  "geometry": {"coordinates":[-85.423958,41.252111],"type":"Point"}
}