{
  "type": "Feature",
  "properties": {
    "iso:country":"US",
    "sg:address":"1523 E Broadway",
    "sg:city":"Logansport",
    "sg:classifiers":[
        {
            "category":"Building & Trades",
            "subcategory":"Construction",
            "type":"Services"
        }
    ],
    "sg:phone":"+1 574 739 1776",
    "sg:postcode":"46947",
    "sg:province":"IN",
    "sg:tags":[
        "house"
    ],
    "wof:name":"Nelson Remodeling",
    "wof:placetype":"venue"
},
  "geometry": {"coordinates":[-86.349518,40.756728],"type":"Point"}
}