{
  "type": "Feature",
  "properties": {
    "addr:full":"6214 Northwood Dr Carmel IN 46033",
    "addr:housenumber":"6214",
    "addr:postcode":"46033",
    "addr:street":"Northwood Dr",
    "iso:country":"US",
    "sg:address":"6214 Northwood Dr",
    "sg:city":"Carmel",
    "sg:classifiers":[
        {
            "category":"Building & Trades",
            "subcategory":"Construction",
            "type":"Services"
        }
    ],
    "sg:phone":"+1 317 846 5800",
    "sg:postcode":"46033",
    "sg:province":"IN",
    "sg:tags":[
        "contractor"
    ],
    "sg:website":"www.fccdevelopment.com",
    "wof:name":"Fcc Development Corp",
    "wof:placetype":"venue"
},
  "geometry": {"coordinates":[-86.06300400000001,39.9641],"type":"Point"}
}