{
  "type": "Feature",
  "properties": {
    "iso:country":"US",
    "sg:address":"624 W 3rd St",
    "sg:city":"Hobart",
    "sg:classifiers":[
        {
            "category":"Home & Garden",
            "subcategory":"Home Furnishings",
            "type":"Retail Goods"
        }
    ],
    "sg:phone":"+1 219 942 6000",
    "sg:postcode":"46342",
    "sg:province":"IN",
    "sg:tags":[
        "venetian",
        "blind"
    ],
    "wof:name":"Eddie Z's Express Blinds",
    "wof:placetype":"venue"
},
  "geometry": {"coordinates":[-87.267791,41.532668],"type":"Point"}
}