{
  "type": "Feature",
  "properties": {
    "iso:country":"US",
    "sg:address":"307 E Main St",
    "sg:city":"Bloomfield",
    "sg:classifiers":[
        {
            "category":"Food & Beverages",
            "subcategory":"Liquor & Beverages",
            "type":"Retail Goods"
        }
    ],
    "sg:phone":"+1 812 384 4362",
    "sg:postcode":"47424",
    "sg:province":"IN",
    "wof:name":"Bloomfield Liquors",
    "wof:placetype":"venue"
},
  "geometry": {"coordinates":[-86.934636,39.026704],"type":"Point"}
}