{
  "type": "Feature",
  "properties": {
    "iso:country":"US",
    "sg:address":"226 Cherry St",
    "sg:city":"Greenfield",
    "sg:classifiers":[
        {
            "category":"Organizations",
            "subcategory":"Community Association",
            "type":"Services"
        }
    ],
    "sg:phone":"+1 317 467 4100",
    "sg:postcode":"46140",
    "sg:province":"IN",
    "sg:tags":[
        "fraternal"
    ],
    "wof:name":"Fraternal Order Of Eagles",
    "wof:placetype":"venue"
},
  "geometry": {"coordinates":[-85.752279,39.788077],"type":"Point"}
}