{
  "type": "Feature",
  "properties": {
    "addr:full":"511 Green Blvd Aurora IN 47001",
    "addr:housenumber":"511",
    "addr:postcode":"47001",
    "addr:street":"Green Blvd",
    "iso:country":"US",
    "sg:address":"511 Green Blvd",
    "sg:city":"Aurora",
    "sg:classifiers":[
        {
            "category":"Shopping",
            "subcategory":"Department Store",
            "type":"Retail Goods"
        }
    ],
    "sg:phone":"+1 812 926 8100",
    "sg:postcode":"47001",
    "sg:province":"IN",
    "sg:tags":[
        "shop"
    ],
    "wof:name":"Family Dollar Store",
    "wof:placetype":"venue"
},
  "geometry": {"coordinates":[-84.89702200000001,39.063043],"type":"Point"}
}