{
  "type": "Feature",
  "properties": {
    "iso:country":"US",
    "sg:address":"203 W Roselawn Dr",
    "sg:city":"Logansport",
    "sg:classifiers":[
        {
            "category":"Recreation",
            "type":"Entertainment"
        }
    ],
    "sg:phone":"+1 574 722 6505",
    "sg:postcode":"46947",
    "sg:province":"IN",
    "sg:tags":[
        "amusement"
    ],
    "wof:name":"Go Vertical Inc",
    "wof:placetype":"venue"
},
  "geometry": {"coordinates":[-86.330494,40.761414],"type":"Point"}
}