{
  "type": "Feature",
  "properties": {
    "addr:full":"833 W Lincoln Hwy Schererville IN 46375",
    "addr:housenumber":"833",
    "addr:postcode":"46375",
    "addr:street":"W Lincoln Hwy",
    "iso:country":"US",
    "sg:address":"833 W Lincoln Hwy",
    "sg:city":"Schererville",
    "sg:classifiers":[
        {
            "category":"Professional",
            "type":"Services"
        }
    ],
    "sg:phone":"+1 219 322 2723",
    "sg:postcode":"46375",
    "sg:province":"IN",
    "wof:name":"Karen Briggs Do",
    "wof:placetype":"venue"
},
  "geometry": {"coordinates":[-87.433457,41.4819],"type":"Point"}
}