{
  "type": "Feature",
  "properties": {
    "iso:country":"US",
    "sg:address":"404 E Vine St",
    "sg:city":"Liberty",
    "sg:classifiers":[
        {
            "category":"Organizations",
            "subcategory":"Religious Organization",
            "type":"Services"
        }
    ],
    "sg:phone":"+1 765 458 5412",
    "sg:postcode":"47353",
    "sg:province":"IN",
    "wof:name":"St Bridget Catholic Church",
    "wof:placetype":"venue"
},
  "geometry": {"coordinates":[-84.92484,39.633497],"type":"Point"}
}