{
  "type": "Feature",
  "properties": {
    "addr:full":"4485 E 1700 S Goodland IN 47948",
    "addr:housenumber":"4485",
    "addr:postcode":"47948",
    "addr:street":"E 1700 S",
    "iso:country":"US",
    "sg:address":"4485 E 1700 S",
    "sg:city":"Goodland",
    "sg:classifiers":[
        {
            "category":"Farming",
            "subcategory":"Farm",
            "type":"Manufacturing & Wholesale Goods"
        }
    ],
    "sg:phone":"+1 219 297 4455",
    "sg:postcode":"47948",
    "sg:province":"IN",
    "wof:name":"Ronald L Royer Farms & Excavtn",
    "wof:placetype":"venue"
},
  "geometry": {"coordinates":[-87.322124,40.751103],"type":"Point"}
}