{
  "type": "Feature",
  "properties": {
    "iso:country":"US",
    "sg:address":"1236 N Cherry St",
    "sg:city":"Rushville",
    "sg:classifiers":[
        {
            "category":"Professional",
            "subcategory":"Business Services",
            "type":"Services"
        }
    ],
    "sg:phone":"+1 765 938 2200",
    "sg:postcode":"46173",
    "sg:province":"IN",
    "wof:name":"Calvin Crawley Auctioneer",
    "wof:placetype":"venue"
},
  "geometry": {"coordinates":[-85.441073,39.620752],"type":"Point"}
}