{
  "type": "Feature",
  "properties": {
    "iso:country":"US",
    "sg:address":"105 E Jackson St",
    "sg:city":"Gaston",
    "sg:classifiers":[
        {
            "category":"Retail",
            "subcategory":"Auto Repair",
            "type":"Services"
        }
    ],
    "sg:phone":"+1 765 358 3676",
    "sg:postcode":"47342",
    "sg:province":"IN",
    "sg:tags":[
        "repairing",
        "automobile"
    ],
    "wof:name":"Ramsey Auto Repair",
    "wof:placetype":"venue"
},
  "geometry": {"coordinates":[-85.496138,40.314415],"type":"Point"}
}