{
  "type": "Feature",
  "properties": {
    "iso:country":"US",
    "sg:address":"4291 W 96th St",
    "sg:city":"Indianapolis",
    "sg:classifiers":[
        {
            "category":"Professional",
            "type":"Services"
        }
    ],
    "sg:phone":"+1 317 872 1924",
    "sg:postcode":"46268",
    "sg:province":"IN",
    "sg:tags":[
        "establishment"
    ],
    "wof:name":"Premier Productions",
    "wof:placetype":"venue"
},
  "geometry": {"coordinates":[-86.232468,39.926071],"type":"Point"}
}