{
  "type": "Feature",
  "properties": {
    "addr:full":"20 E 1100 N North Manchester IN 46962",
    "addr:housenumber":"20;n",
    "addr:postcode":"46962",
    "addr:street":"E 1100;North",
    "iso:country":"US",
    "sg:address":"20 E 1100 N",
    "sg:city":"North Manchester",
    "sg:classifiers":[
        {
            "category":"Home & Garden",
            "subcategory":"Garden Supply",
            "type":"Retail Goods"
        }
    ],
    "sg:phone":"+1 260 982 2338",
    "sg:postcode":"46962",
    "sg:province":"IN",
    "sg:tags":[
        "lawn",
        "mower"
    ],
    "wof:name":"Slater's Lawn & Garden",
    "wof:placetype":"venue"
},
  "geometry": {"coordinates":[-85.79360800000001,40.986045],"type":"Point"}
}