{
  "type": "Feature",
  "properties": {
    "iso:country":"US",
    "sg:address":"3200 E Main St",
    "sg:city":"Richmond",
    "sg:classifiers":[
        {
            "category":"Autos & Motor Vehicles",
            "subcategory":"Automobile Sales",
            "type":"Retail Goods"
        }
    ],
    "sg:phone":"+1 765 962 0505",
    "sg:postcode":"47374",
    "sg:province":"IN",
    "sg:tags":[
        "car",
        "dealer"
    ],
    "sg:website":"www.studebakerautos.com",
    "wof:name":"Studebaker Buick GMC Trucks",
    "wof:placetype":"venue"
},
  "geometry": {"coordinates":[-84.859972,39.830874],"type":"Point"}
}