{
  "type": "Feature",
  "properties": {
    "addr:full":"125 W Washington St Morgantown IN 46160",
    "addr:housenumber":"125",
    "addr:postcode":"46160",
    "addr:street":"W Washington St",
    "iso:country":"US",
    "sg:address":"125 W Washington St",
    "sg:city":"Morgantown",
    "sg:classifiers":[
        {
            "category":"Shopping",
            "subcategory":"Used Merchandise",
            "type":"Retail Goods"
        }
    ],
    "sg:phone":"+1 812 597 2687",
    "sg:postcode":"46160",
    "sg:province":"IN",
    "sg:tags":[
        "antique"
    ],
    "wof:name":"Sister's Country Junction",
    "wof:placetype":"venue"
},
  "geometry": {"coordinates":[-86.26311800000001,39.371355],"type":"Point"}
}