{
  "type": "Feature",
  "properties": {
    "iso:country":"US",
    "sg:address":"200 Triton Dr",
    "sg:city":"Bourbon",
    "sg:classifiers":[
        {
            "category":"Education",
            "subcategory":"School",
            "type":"Public Place"
        }
    ],
    "sg:phone":"+1 574 342 2355",
    "sg:postcode":"46504",
    "sg:province":"IN",
    "sg:website":"www.triton.k12.in.us",
    "wof:name":"Triton Elementary School",
    "wof:placetype":"venue"
},
  "geometry": {"coordinates":[-86.110007,41.302836],"type":"Point"}
}