{
  "type": "Feature",
  "properties": {
    "iso:country":"US",
    "sg:address":"1232 W 600 S",
    "sg:city":"Fountaintown",
    "sg:classifiers":[
        {
            "category":"Wholesale",
            "subcategory":"Machinery & Supplies",
            "type":"Manufacturing & Wholesale Goods"
        }
    ],
    "sg:phone":"+1 317 861 4600",
    "sg:postcode":"46130",
    "sg:province":"IN",
    "sg:tags":[
        "equipment",
        "irrigation",
        "system"
    ],
    "wof:name":"Outdoor Management Svc Inc",
    "wof:placetype":"venue"
},
  "geometry": {"coordinates":[-85.823987,39.69862],"type":"Point"}
}