{
  "type": "Feature",
  "properties": {
    "iso:country":"US",
    "sg:address":"36 E Main St",
    "sg:city":"Brownsburg",
    "sg:classifiers":[
        {
            "category":"Professional",
            "subcategory":"Management & Consulting",
            "type":"Services"
        }
    ],
    "sg:phone":"+1 317 852 6471",
    "sg:postcode":"46112",
    "sg:province":"IN",
    "sg:tags":[
        "consultant",
        "business"
    ],
    "sg:website":"www.competitivebusiness.com",
    "wof:name":"Competitive Business Assoc",
    "wof:placetype":"venue"
},
  "geometry": {"coordinates":[-86.397499,39.84327],"type":"Point"}
}