{
  "type": "Feature",
  "properties": {
    "iso:country":"US",
    "sg:address":"3611 N Briarwood Ln",
    "sg:city":"Muncie",
    "sg:classifiers":[
        {
            "category":"Education",
            "subcategory":"Dance Studio",
            "type":"Public Place"
        }
    ],
    "sg:phone":"+1 765 286 5099",
    "sg:postcode":"47304",
    "sg:province":"IN",
    "sg:tags":[
        "instruction",
        "dancing"
    ],
    "wof:name":"Dazzle Dance Academy Inc",
    "wof:placetype":"venue"
},
  "geometry": {"coordinates":[-85.428381,40.220961],"type":"Point"}
}