{
  "type": "Feature",
  "properties": {
    "addr:full":"11583 N Bob Wolfe Rd Oaktown IN 47561",
    "addr:housenumber":"11583",
    "addr:postcode":"47561",
    "addr:street":"N Bob Wolfe Rd",
    "iso:country":"US",
    "sg:address":"11583 N Bob Wolfe Rd",
    "sg:city":"Oaktown",
    "sg:classifiers":[
        {
            "category":"Farming",
            "subcategory":"Farm",
            "type":"Manufacturing & Wholesale Goods"
        }
    ],
    "sg:phone":"+1 812 745 2583",
    "sg:postcode":"47561",
    "sg:province":"IN",
    "sg:tags":[
        "crop",
        "general"
    ],
    "wof:name":"Ed Jackson",
    "wof:placetype":"venue"
},
  "geometry": {"coordinates":[-87.479646,38.833976],"type":"Point"}
}