{
  "type": "Feature",
  "properties": {
    "iso:country":"US",
    "sg:address":"1834 Golfview Ct",
    "sg:city":"Franklin",
    "sg:classifiers":[
        {
            "category":"Professional",
            "subcategory":"Management & Consulting",
            "type":"Services"
        }
    ],
    "sg:phone":"+1 317 738 2505",
    "sg:postcode":"46131",
    "sg:province":"IN",
    "sg:tags":[
        "se"
    ],
    "wof:name":"Betty Dluzyn",
    "wof:placetype":"venue"
},
  "geometry": {"coordinates":[-86.024153,39.484076],"type":"Point"}
}