{
  "type": "Feature",
  "properties": {
    "iso:country":"US",
    "sg:address":"411 E 114th St",
    "sg:city":"Carmel",
    "sg:classifiers":[
        {
            "category":"Professional",
            "subcategory":"Management & Consulting",
            "type":"Services"
        }
    ],
    "sg:phone":"+1 317 575 9892",
    "sg:postcode":"46032",
    "sg:province":"IN",
    "sg:tags":[
        "consultant",
        "training"
    ],
    "wof:name":"Williams & Assoc",
    "wof:placetype":"venue"
},
  "geometry": {"coordinates":[-86.151882,39.953159],"type":"Point"}
}