{
  "type": "Feature",
  "properties": {
    "iso:country":"US",
    "sg:address":"5500 Vann Rd",
    "sg:city":"Newburgh",
    "sg:classifiers":[
        {
            "category":"Building & Trades",
            "subcategory":"Construction",
            "type":"Services"
        }
    ],
    "sg:phone":"+1 812 853 2414",
    "sg:postcode":"47630",
    "sg:province":"IN",
    "sg:tags":[
        "excavating",
        "contractor"
    ],
    "wof:name":"Burgess Construction Inc",
    "wof:placetype":"venue"
},
  "geometry": {"coordinates":[-87.341306,37.984],"type":"Point"}
}