{
  "type": "Feature",
  "properties": {
    "iso:country":"US",
    "sg:address":"10124 Bitterroot Dr",
    "sg:city":"Fort Wayne",
    "sg:classifiers":[
        {
            "category":"Communications",
            "type":"Services"
        }
    ],
    "sg:phone":"+1 260 432 6189",
    "sg:postcode":"46804",
    "sg:province":"IN",
    "sg:tags":[
        "carrier"
    ],
    "wof:name":"Nations Bell Inc",
    "wof:placetype":"venue"
},
  "geometry": {"coordinates":[-85.275713,41.050866],"type":"Point"}
}