{
  "type": "Feature",
  "properties": {
    "iso:country":"US",
    "sg:address":"1404 N Wheeling Ave",
    "sg:city":"Muncie",
    "sg:classifiers":[
        {
            "category":"Home & Garden",
            "subcategory":"Household Appliances",
            "type":"Retail Goods"
        }
    ],
    "sg:phone":"+1 765 284 8085",
    "sg:postcode":"47303",
    "sg:province":"IN",
    "wof:name":"Factory Sew Mch & Sweeper Co",
    "wof:placetype":"venue"
},
  "geometry": {"coordinates":[-85.39509099999999,40.205926],"type":"Point"}
}