{
  "type": "Feature",
  "properties": {
    "iso:country":"US",
    "sg:address":"606 N Central Ave",
    "sg:city":"Connersville",
    "sg:classifiers":[
        {
            "category":"Professional",
            "subcategory":"Accounting & Tax Preparation",
            "type":"Services"
        }
    ],
    "sg:phone":"+1 765 827 0032",
    "sg:postcode":"47331",
    "sg:province":"IN",
    "sg:tags":[
        "accountant"
    ],
    "wof:name":"Diana Weiler Income Tax Acct",
    "wof:placetype":"venue"
},
  "geometry": {"coordinates":[-85.138197,39.64274],"type":"Point"}
}