{
  "type": "Feature",
  "properties": {
    "iso:country":"US",
    "sg:address":"247 S Main St",
    "sg:city":"Clinton",
    "sg:classifiers":[
        {
            "category":"Shopping",
            "subcategory":"Gifts & Souvenirs",
            "type":"Retail Goods"
        }
    ],
    "sg:phone":"+1 765 832 6000",
    "sg:postcode":"47842",
    "sg:province":"IN",
    "sg:tags":[
        "shop"
    ],
    "wof:name":"Jan's Hallmark",
    "wof:placetype":"venue"
},
  "geometry": {"coordinates":[-87.398369,39.658843],"type":"Point"}
}