{
  "type": "Feature",
  "properties": {
    "iso:country":"US",
    "sg:address":"1926 Mounds Rd",
    "sg:city":"Anderson",
    "sg:classifiers":[
        {
            "category":"Retail",
            "subcategory":"Car Wash",
            "type":"Services"
        }
    ],
    "sg:phone":"+1 765 640 9274",
    "sg:postcode":"46016",
    "sg:province":"IN",
    "sg:tags":[
        "automobile",
        "detail",
        "clean"
    ],
    "wof:name":"Triple Crown Car Wash",
    "wof:placetype":"venue"
},
  "geometry": {"coordinates":[-85.652701,40.092237],"type":"Point"}
}