{
  "type": "Feature",
  "properties": {
    "iso:country":"US",
    "sg:address":"8844 Indianapolis Blvd",
    "sg:city":"Highland",
    "sg:classifiers":[
        {
            "category":"Autos & Motor Vehicles",
            "subcategory":"Automobile Sales",
            "type":"Retail Goods"
        }
    ],
    "sg:phone":"+1 219 923 4711",
    "sg:postcode":"46373",
    "sg:province":"IN",
    "sg:tags":[
        "car",
        "dealer"
    ],
    "wof:name":"Reliable Motors",
    "wof:placetype":"venue"
},
  "geometry": {"coordinates":[-87.470406,41.460522],"type":"Point"}
}