{
  "type": "Feature",
  "properties": {
    "addr:full":"601 W Market St Vevay IN 47043",
    "addr:housenumber":"601",
    "addr:postcode":"47043",
    "addr:street":"W Market St",
    "iso:country":"US",
    "sg:address":"601 W Market St",
    "sg:city":"Vevay",
    "sg:classifiers":[
        {
            "category":"Organizations",
            "subcategory":"Community Association",
            "type":"Services"
        }
    ],
    "sg:phone":"+1 812 427 2588",
    "sg:postcode":"47043",
    "sg:province":"IN",
    "wof:name":"Kiwanis Club of Vevay Inc",
    "wof:placetype":"venue"
},
  "geometry": {"coordinates":[-85.072633,38.742584],"type":"Point"}
}