{
  "type": "Feature",
  "properties": {
    "iso:country":"US",
    "sg:address":"140 E Main St",
    "sg:city":"Camden",
    "sg:classifiers":[
        {
            "category":"Professional",
            "type":"Services"
        }
    ],
    "sg:phone":"+1 574 686 2865",
    "sg:postcode":"46917",
    "sg:province":"IN",
    "sg:tags":[
        "establishment"
    ],
    "wof:name":"Camden Pub",
    "wof:placetype":"venue"
},
  "geometry": {"coordinates":[-86.53843999999999,40.608619],"type":"Point"}
}