{
  "type": "Feature",
  "properties": {
    "addr:full":"234 E 9th St Indianapolis IN 46204",
    "addr:housenumber":"234",
    "addr:postcode":"46204",
    "addr:street":"E 9Th St",
    "iso:country":"US",
    "sg:address":"234 E 9th St",
    "sg:city":"Indianapolis",
    "sg:classifiers":[
        {
            "category":"Real Estate",
            "subcategory":"Real Estate Agent",
            "type":"Services"
        }
    ],
    "sg:phone":"+1 317 955 0987",
    "sg:postcode":"46204",
    "sg:province":"IN",
    "wof:name":"Downtown Alternative",
    "wof:placetype":"venue"
},
  "geometry": {"coordinates":[-86.152188,39.779035],"type":"Point"}
}