{
  "type": "Feature",
  "properties": {
    "iso:country":"US",
    "sg:address":"2271 W 48th Pl",
    "sg:city":"Gary",
    "sg:classifiers":[
        {
            "category":"Building & Trades",
            "subcategory":"Landscaping Services",
            "type":"Services"
        }
    ],
    "sg:phone":"+1 219 981 2178",
    "sg:postcode":"46408",
    "sg:province":"IN",
    "sg:tags":[
        "tree"
    ],
    "wof:name":"Quality Tree Svc",
    "wof:placetype":"venue"
},
  "geometry": {"coordinates":[-87.3633,41.530534],"type":"Point"}
}