{
  "type": "Feature",
  "properties": {
    "iso:country":"US",
    "sg:address":"814 Sherman St",
    "sg:city":"Logansport",
    "sg:classifiers":[
        {
            "category":"Arts & Performance",
            "subcategory":"Theater",
            "type":"Entertainment"
        }
    ],
    "sg:phone":"+1 574 737 8413",
    "sg:postcode":"46947",
    "sg:province":"IN",
    "sg:tags":[
        "live",
        "music"
    ],
    "wof:name":"Reel'In & Rock'In DJ",
    "wof:placetype":"venue"
},
  "geometry": {"coordinates":[-86.378822,40.741291],"type":"Point"}
}