{
  "type": "Feature",
  "properties": {
    "iso:country":"US",
    "sg:address":"189 3rd St SE",
    "sg:city":"Linton",
    "sg:classifiers":[
        {
            "category":"Autos & Motor Vehicles",
            "subcategory":"Auto Supplies",
            "type":"Retail Goods"
        }
    ],
    "sg:phone":"+1 812 847 4469",
    "sg:postcode":"47441",
    "sg:province":"IN",
    "sg:tags":[
        "tire"
    ],
    "wof:name":"Petro's Tire Sales & Svc",
    "wof:placetype":"venue"
},
  "geometry": {"coordinates":[-87.1631,39.031292],"type":"Point"}
}