{
  "type": "Feature",
  "properties": {
    "iso:country":"US",
    "sg:address":"905 N Raceway Rd",
    "sg:city":"Indianapolis",
    "sg:classifiers":[
        {
            "category":"Personal",
            "type":"Services"
        },
        {
            "category":"Sports & Exercise",
            "subcategory":"Gym",
            "type":"Entertainment"
        }
    ],
    "sg:phone":"+1 317 491 5205",
    "sg:postcode":"46234",
    "sg:province":"IN",
    "sg:tags":[
        "trainer",
        "consultant",
        "program",
        "physical",
        "fitness"
    ],
    "wof:name":"Fittech Incorporated",
    "wof:placetype":"venue"
},
  "geometry": {"coordinates":[-86.326914,39.776373],"type":"Point"}
}