{
  "type": "Feature",
  "properties": {
    "iso:country":"US",
    "sg:address":"7432 Lions Head Dr",
    "sg:city":"Indianapolis",
    "sg:classifiers":[
        {
            "category":"Home & Garden",
            "subcategory":"Furniture",
            "type":"Retail Goods"
        }
    ],
    "sg:phone":"+1 317 257 5584",
    "sg:postcode":"46260",
    "sg:province":"IN",
    "wof:name":"Now & Then Shop",
    "wof:placetype":"venue"
},
  "geometry": {"coordinates":[-86.168925,39.888751],"type":"Point"}
}