{
  "type": "Feature",
  "properties": {
    "iso:country":"US",
    "sg:address":"42 E 8th St",
    "sg:city":"Peru",
    "sg:classifiers":[
        {
            "category":"Building & Trades",
            "subcategory":"Plumbing",
            "type":"Services"
        }
    ],
    "sg:phone":"+1 765 472 4918",
    "sg:postcode":"46970",
    "sg:province":"IN",
    "sg:tags":[
        "conditioning",
        "air",
        "system",
        "contractor"
    ],
    "wof:name":"Air-Master",
    "wof:placetype":"venue"
},
  "geometry": {"coordinates":[-86.0711,40.757285],"type":"Point"}
}