{
  "type": "Feature",
  "properties": {
    "iso:country":"US",
    "sg:address":"702 W Spring St",
    "sg:city":"Brownstown",
    "sg:classifiers":[
        {
            "category":"Social Services",
            "subcategory":"Child Care",
            "type":"Services"
        }
    ],
    "sg:phone":"+1 812 358 1702",
    "sg:postcode":"47220",
    "sg:province":"IN",
    "sg:tags":[
        "kindergarten",
        "academic",
        "school"
    ],
    "wof:name":"Brownstone Christian Daycare",
    "wof:placetype":"venue"
},
  "geometry": {"coordinates":[-86.049695,38.882941],"type":"Point"}
}