{
  "type": "Feature",
  "properties": {
    "iso:country":"US",
    "sg:address":"1302 E Creighton Ave",
    "sg:city":"Fort Wayne",
    "sg:classifiers":[
        {
            "category":"Real Estate",
            "subcategory":"Real Estate Agent",
            "type":"Services"
        }
    ],
    "sg:phone":"+1 260 744 2188",
    "sg:postcode":"46803",
    "sg:province":"IN",
    "wof:name":"Growth Industries",
    "wof:placetype":"venue"
},
  "geometry": {"coordinates":[-85.11903100000001,41.064841],"type":"Point"}
}