{
  "type": "Feature",
  "properties": {
    "iso:country":"US",
    "sg:address":"3400 Jefferson St",
    "sg:city":"Gary",
    "sg:classifiers":[
        {
            "category":"Restaurant",
            "type":"Food & Drink"
        }
    ],
    "sg:phone":"+1 219 884 1280",
    "sg:postcode":"46408",
    "sg:province":"IN",
    "wof:name":"Garden Cafe",
    "wof:placetype":"venue"
},
  "geometry": {"coordinates":[-87.340113,41.555946],"type":"Point"}
}