{
  "type": "Feature",
  "properties": {
    "iso:country":"US",
    "sg:address":"9351 N Delaware St",
    "sg:city":"Indianapolis",
    "sg:classifiers":[
        {
            "category":"Arts & Performance",
            "subcategory":"Theater",
            "type":"Entertainment"
        }
    ],
    "sg:phone":"+1 317 846 9334",
    "sg:postcode":"46240",
    "sg:province":"IN",
    "sg:tags":[
        "chamber",
        "music",
        "group"
    ],
    "wof:name":"Ronen Chamber Ensemble  Inc",
    "wof:placetype":"venue"
},
  "geometry": {"coordinates":[-86.153756,39.919944],"type":"Point"}
}