{
  "type": "Feature",
  "properties": {
    "addr:full":"980 N Morton St Franklin IN 46131",
    "addr:housenumber":"980",
    "addr:postcode":"46131",
    "addr:street":"N Morton St",
    "iso:country":"US",
    "sg:address":"980 N Morton St",
    "sg:city":"Franklin",
    "sg:classifiers":[
        {
            "category":"Restaurant",
            "type":"Food & Drink"
        }
    ],
    "sg:menulink":"http://www.allmenus.com/in/franklin/69630-donatos-pizza/menu/",
    "sg:phone":"+1 317 738 9715",
    "sg:postcode":"46131",
    "sg:province":"IN",
    "sg:tags":[
        "sandwich",
        "salad",
        "soup",
        "american",
        "wrap",
        "pizza"
    ],
    "wof:name":"Donatos Pizza",
    "wof:placetype":"venue"
},
  "geometry": {"coordinates":[-86.064211,39.49011],"type":"Point"}
}