{
  "type": "Feature",
  "properties": {
    "iso:country":"US",
    "sg:address":"180 Deborah Ln",
    "sg:city":"Whiteland",
    "sg:classifiers":[
        {
            "category":"Professional",
            "type":"Services"
        }
    ],
    "sg:phone":"+1 317 535 0742",
    "sg:postcode":"46184",
    "sg:province":"IN",
    "wof:name":"Decks Etc",
    "wof:placetype":"venue"
},
  "geometry": {"coordinates":[-86.095761,39.540636],"type":"Point"}
}