{
  "type": "Feature",
  "properties": {
    "iso:country":"US",
    "sg:address":"6980 Corporate Dr",
    "sg:city":"Indianapolis",
    "sg:classifiers":[
        {
            "category":"Autos & Motor Vehicles",
            "subcategory":"Automobile Sales",
            "type":"Retail Goods"
        }
    ],
    "sg:phone":"+1 317 254 3162",
    "sg:postcode":"46278",
    "sg:province":"IN",
    "sg:tags":[
        "performance",
        "race",
        "dealer"
    ],
    "wof:name":"Gearheads Automobilia Shop",
    "wof:placetype":"venue"
},
  "geometry": {"coordinates":[-86.26556100000001,39.88008],"type":"Point"}
}