{
  "type": "Feature",
  "properties": {
    "addr:full":"111 E Broadway St Princeton IN 47670",
    "addr:housenumber":"111",
    "addr:postcode":"47670",
    "addr:street":"E Broadway St",
    "iso:country":"US",
    "sg:address":"111 E Broadway St",
    "sg:city":"Princeton",
    "sg:classifiers":[
        {
            "category":"Restaurant",
            "type":"Food & Drink"
        }
    ],
    "sg:menulink":"http://www.allmenus.com/in/patoka/76454-dominos-pizza/menu/",
    "sg:phone":"+1 812 386 3030",
    "sg:postcode":"47670",
    "sg:province":"IN",
    "sg:tags":[
        "american",
        "wing",
        "pizza"
    ],
    "wof:name":"Domino's Pizza",
    "wof:placetype":"venue"
},
  "geometry": {"coordinates":[-87.567418,38.355224],"type":"Point"}
}