{
  "type": "Feature",
  "properties": {
    "iso:country":"US",
    "sg:address":"742 Co Rd 3 N",
    "sg:city":"Elkhart",
    "sg:classifiers":[
        {
            "category":"Autos & Motor Vehicles",
            "subcategory":"Recreational Vehicle Sales",
            "type":"Retail Goods"
        }
    ],
    "sg:phone":"+1 574 295 5600",
    "sg:postcode":"46514",
    "sg:province":"IN",
    "wof:name":"Westover",
    "wof:placetype":"venue"
},
  "geometry": {"coordinates":[-86.01803,41.697241],"type":"Point"}
}