{
  "type": "Feature",
  "properties": {
    "iso:country":"US",
    "sg:address":"13545 E 296th St",
    "sg:city":"Atlanta",
    "sg:classifiers":[
        {
            "category":"Government",
            "subcategory":"Office",
            "type":"Public Place"
        }
    ],
    "sg:phone":"+1 765 552 5142",
    "sg:postcode":"46031",
    "sg:province":"IN",
    "sg:tags":[
        "executive"
    ],
    "wof:name":"White Rver Township Volunteers",
    "wof:placetype":"venue"
},
  "geometry": {"coordinates":[-85.920358,40.218486],"type":"Point"}
}