{
  "type": "Feature",
  "properties": {
    "iso:country":"US",
    "sg:address":"2110 N 3rd St",
    "sg:city":"Logansport",
    "sg:classifiers":[
        {
            "category":"Organizations",
            "subcategory":"Religious Organization",
            "type":"Services"
        }
    ],
    "sg:phone":"+1 574 753 7345",
    "sg:postcode":"46947",
    "sg:province":"IN",
    "sg:tags":[
        "church"
    ],
    "wof:name":"Hillcrest Baptist Church",
    "wof:placetype":"venue"
},
  "geometry": {"coordinates":[-86.373839,40.768264],"type":"Point"}
}