{
  "type": "Feature",
  "properties": {
    "addr:full":"404 S Meridian St Holland IN 47541",
    "addr:housenumber":"404",
    "addr:postcode":"47541",
    "addr:street":"S Meridian St",
    "iso:country":"US",
    "sg:address":"404 S Meridian St",
    "sg:city":"Holland",
    "sg:classifiers":[
        {
            "category":"Education",
            "subcategory":"School",
            "type":"Public Place"
        }
    ],
    "sg:phone":"+1 812 536 2441",
    "sg:postcode":"47541",
    "sg:province":"IN",
    "wof:name":"Holland Elementary School",
    "wof:placetype":"venue"
},
  "geometry": {"coordinates":[-87.03591299999999,38.247834],"type":"Point"}
}