{
  "type": "Feature",
  "properties": {
    "iso:country":"US",
    "sg:address":"1202 Lincoln Way E",
    "sg:city":"Mishawaka",
    "sg:classifiers":[
        {
            "category":"Education",
            "subcategory":"School",
            "type":"Public Place"
        }
    ],
    "sg:phone":"+1 574 254 7300",
    "sg:postcode":"46544",
    "sg:province":"IN",
    "sg:website":"www.mishawaka.k12.in.us",
    "wof:name":"Mishawaka High School",
    "wof:placetype":"venue"
},
  "geometry": {"coordinates":[-86.16101999999999,41.661964],"type":"Point"}
}