{
  "type": "Feature",
  "properties": {
    "iso:country":"US",
    "sg:address":"8669 Admirals Woods Dr",
    "sg:city":"Indianapolis",
    "sg:classifiers":[
        {
            "category":"Professional",
            "subcategory":"Management & Consulting",
            "type":"Services"
        }
    ],
    "sg:phone":"+1 317 826 1597",
    "sg:postcode":"46236",
    "sg:province":"IN",
    "sg:website":"www.shamrockrun.com",
    "wof:name":"Austin Integrated Marketing",
    "wof:placetype":"venue"
},
  "geometry": {"coordinates":[-85.954641,39.913923],"type":"Point"}
}