{
  "type": "Feature",
  "properties": {
    "iso:country":"US",
    "sg:address":"40 Lukes Ct",
    "sg:city":"Hobart",
    "sg:classifiers":[
        {
            "category":"Building & Trades",
            "subcategory":"Cleaning & Sanitation",
            "type":"Services"
        }
    ],
    "sg:phone":"+1 219 947 0885",
    "sg:postcode":"46342",
    "sg:province":"IN",
    "sg:tags":[
        "maintenance"
    ],
    "wof:name":"S Camisa",
    "wof:placetype":"venue"
},
  "geometry": {"coordinates":[-87.260985,41.541218],"type":"Point"}
}