{
  "type": "Feature",
  "properties": {
    "iso:country":"US",
    "sg:address":"146 E Elm St",
    "sg:city":"New Albany",
    "sg:classifiers":[
        {
            "category":"Banks & Credit Unions",
            "subcategory":"Investment Brokerage",
            "type":"Services"
        }
    ],
    "sg:phone":"+1 812 944 5100",
    "sg:postcode":"47150",
    "sg:province":"IN",
    "sg:tags":[
        "security"
    ],
    "wof:name":"Edward Jones Co",
    "wof:placetype":"venue"
},
  "geometry": {"coordinates":[-85.822823,38.287273],"type":"Point"}
}