{
  "type": "Feature",
  "properties": {
    "iso:country":"US",
    "sg:address":"11405 Regency Ln",
    "sg:city":"Carmel",
    "sg:classifiers":[
        {
            "category":"Retail",
            "subcategory":"Animal Services",
            "type":"Services"
        }
    ],
    "sg:phone":"+1 317 844 3072",
    "sg:postcode":"46033",
    "sg:province":"IN",
    "wof:name":"Pooch Parlour LLC",
    "wof:placetype":"venue"
},
  "geometry": {"coordinates":[-86.085234,39.954641],"type":"Point"}
}