{
  "type": "Feature",
  "properties": {
    "iso:country":"US",
    "sg:address":"1612 S 3rd St",
    "sg:city":"Terre Haute",
    "sg:classifiers":[
        {
            "category":"Shopping",
            "subcategory":"Used Merchandise",
            "type":"Retail Goods"
        }
    ],
    "sg:phone":"+1 812 232 2991",
    "sg:postcode":"47802",
    "sg:province":"IN",
    "wof:name":"Trends and Golden Treausers",
    "wof:placetype":"venue"
},
  "geometry": {"coordinates":[-87.413677,39.449688],"type":"Point"}
}