{
  "type": "Feature",
  "properties": {
    "iso:country":"US",
    "sg:address":"3779 State Rd 9",
    "sg:city":"Anderson",
    "sg:classifiers":[
        {
            "category":"Autos & Motor Vehicles",
            "subcategory":"Boat Sales",
            "type":"Retail Goods"
        }
    ],
    "sg:phone":"+1 765 649 2833",
    "sg:postcode":"46012",
    "sg:province":"IN",
    "sg:tags":[
        "dealer",
        "sales"
    ],
    "sg:website":"www.killbuckvalleysports.com",
    "wof:name":"Killbuck Valley Sports",
    "wof:placetype":"venue"
},
  "geometry": {"coordinates":[-85.671823,40.164735],"type":"Point"}
}