{
  "type": "Feature",
  "properties": {
    "iso:country":"US",
    "sg:address":"18913 Fairfield Blvd",
    "sg:city":"Noblesville",
    "sg:classifiers":[
        {
            "category":"Insurance",
            "subcategory":"Insurance Agent",
            "type":"Services"
        }
    ],
    "sg:phone":"+1 317 774 1153",
    "sg:postcode":"46060",
    "sg:province":"IN",
    "sg:tags":[
        "consultant"
    ],
    "wof:name":"Caronia Corp",
    "wof:placetype":"venue"
},
  "geometry": {"coordinates":[-86.000227,40.06307],"type":"Point"}
}