{
  "type": "Feature",
  "properties": {
    "iso:country":"US",
    "sg:address":"6081 E 82nd St",
    "sg:city":"Indianapolis",
    "sg:classifiers":[
        {
            "category":"Insurance",
            "subcategory":"Health Insurance",
            "type":"Services"
        }
    ],
    "sg:phone":"+1 317 578 7960",
    "sg:postcode":"46250",
    "sg:province":"IN",
    "sg:tags":[
        "dental"
    ],
    "wof:name":"Health Resources Inc.",
    "wof:placetype":"venue"
},
  "geometry": {"coordinates":[-86.06124800000001,39.905247],"type":"Point"}
}