{
  "type": "Feature",
  "properties": {
    "iso:country":"US",
    "sg:address":"209 E 250 S",
    "sg:city":"Rochester",
    "sg:classifiers":[
        {
            "category":"Personal",
            "subcategory":"Beauty Salon",
            "type":"Services"
        }
    ],
    "sg:phone":"+1 574 223 7971",
    "sg:postcode":"46975",
    "sg:province":"IN",
    "wof:name":"Ginger Snips",
    "wof:placetype":"venue"
},
  "geometry": {"coordinates":[-86.187694,41.016503],"type":"Point"}
}