{
  "type": "Feature",
  "properties": {
    "iso:country":"US",
    "sg:address":"1000 Grove St",
    "sg:city":"Evansville",
    "sg:classifiers":[
        {
            "category":"Manufacturing",
            "subcategory":"Rubber & Plastics",
            "type":"Manufacturing & Wholesale Goods"
        }
    ],
    "sg:phone":"+1 812 423 7300",
    "sg:postcode":"47710",
    "sg:province":"IN",
    "sg:website":"www.cytexplastics.com",
    "wof:name":"Cytex",
    "wof:placetype":"venue"
},
  "geometry": {"coordinates":[-87.588239,37.986203],"type":"Point"}
}