{
  "type": "Feature",
  "properties": {
    "addr:full":"30753 US Hwy 20 Elkhart IN 46514",
    "addr:postcode":"30753;46514",
    "addr:street":"Us Hwy 20",
    "iso:country":"US",
    "sg:address":"30753 US Hwy 20",
    "sg:city":"Elkhart",
    "sg:classifiers":[
        {
            "category":"Manufacturing",
            "subcategory":"Signs",
            "type":"Manufacturing & Wholesale Goods"
        }
    ],
    "sg:phone":"+1 574 675 9111",
    "sg:postcode":"46514",
    "sg:province":"IN",
    "wof:name":"Art Works",
    "wof:placetype":"venue"
},
  "geometry": {"coordinates":[-86.05869199999999,41.688557],"type":"Point"}
}