{
  "type": "Feature",
  "properties": {
    "addr:full":"302 S Council St Attica IN 47918",
    "addr:housenumber":"302",
    "addr:postcode":"47918",
    "addr:street":"S Council St",
    "iso:country":"US",
    "sg:address":"302 S Council St",
    "sg:city":"Attica",
    "sg:classifiers":[
        {
            "category":"Insurance",
            "subcategory":"Insurance Agent",
            "type":"Services"
        }
    ],
    "sg:phone":"+1 765 762 3619",
    "sg:postcode":"47918",
    "sg:province":"IN",
    "wof:name":"Valley Insurance",
    "wof:placetype":"venue"
},
  "geometry": {"coordinates":[-87.24624,40.290579],"type":"Point"}
}