{
  "type": "Feature",
  "properties": {
    "iso:country":"US",
    "sg:address":"812 Elston St",
    "sg:city":"Michigan City",
    "sg:classifiers":[
        {
            "category":"Organizations",
            "subcategory":"Religious Organization",
            "type":"Services"
        }
    ],
    "sg:phone":"+1 219 879 9908",
    "sg:postcode":"46360",
    "sg:province":"IN",
    "sg:tags":[
        "church"
    ],
    "wof:name":"Lindsey Chapel",
    "wof:placetype":"venue"
},
  "geometry": {"coordinates":[-86.90631399999999,41.712213],"type":"Point"}
}