{
  "type": "Feature",
  "properties": {
    "iso:country":"US",
    "sg:address":"4928 Old State Rd 46",
    "sg:city":"Nashville",
    "sg:classifiers":[
        {
            "category":"Organizations",
            "subcategory":"Religious Organization",
            "type":"Services"
        }
    ],
    "sg:phone":"+1 812 988 2387",
    "sg:postcode":"47448",
    "sg:province":"IN",
    "sg:tags":[
        "church"
    ],
    "wof:name":"Gnaw Bone Wesleyan Church",
    "wof:placetype":"venue"
},
  "geometry": {"coordinates":[-86.155523,39.189926],"type":"Point"}
}