{
  "type": "Feature",
  "properties": {
    "iso:country":"US",
    "sg:address":"515 E Dupont Rd",
    "sg:city":"Fort Wayne",
    "sg:classifiers":[
        {
            "category":"Wholesale",
            "subcategory":"Machinery & Supplies",
            "type":"Manufacturing & Wholesale Goods"
        }
    ],
    "sg:phone":"+1 260 637 4103",
    "sg:postcode":"46825",
    "sg:province":"IN",
    "sg:tags":[
        "truck"
    ],
    "wof:name":"Penske Truck Rental",
    "wof:placetype":"venue"
},
  "geometry": {"coordinates":[-85.13275899999999,41.178268],"type":"Point"}
}