{
  "type": "Feature",
  "properties": {
    "iso:country":"US",
    "sg:address":"8016 W 82nd St",
    "sg:city":"Indianapolis",
    "sg:classifiers":[
        {
            "category":"Health Services",
            "subcategory":"Doctor",
            "type":"Services"
        }
    ],
    "sg:phone":"+1 317 297 7850",
    "sg:postcode":"46278",
    "sg:province":"IN",
    "sg:tags":[
        "physician",
        "family",
        "practice",
        "surgeons",
        "medicine"
    ],
    "wof:name":"Canal Family Ltd Partners",
    "wof:placetype":"venue"
},
  "geometry": {"coordinates":[-86.30477,39.903296],"type":"Point"}
}