{
  "type": "Feature",
  "properties": {
    "iso:country":"US",
    "sg:address":"6700 S State Rd 9",
    "sg:city":"Wolcottville",
    "sg:classifiers":[
        {
            "category":"Autos & Motor Vehicles",
            "subcategory":"Automobile Sales",
            "type":"Retail Goods"
        }
    ],
    "sg:phone":"+1 260 854 3457",
    "sg:postcode":"46795",
    "sg:province":"IN",
    "sg:tags":[
        "car",
        "dealer"
    ],
    "wof:name":"D & K Auto Sales & Svc",
    "wof:placetype":"venue"
},
  "geometry": {"coordinates":[-85.366643,41.544789],"type":"Point"}
}