{
  "type": "Feature",
  "properties": {
    "iso:country":"US",
    "sg:address":"7535 W Jefferson Blvd",
    "sg:city":"Fort Wayne",
    "sg:classifiers":[
        {
            "category":"Professional",
            "type":"Services"
        }
    ],
    "sg:phone":"+1 260 432 6382",
    "sg:postcode":"46804",
    "sg:province":"IN",
    "sg:tags":[
        "establishment"
    ],
    "wof:name":"C & J",
    "wof:placetype":"venue"
},
  "geometry": {"coordinates":[-85.241422,41.04143],"type":"Point"}
}