{
  "type": "Feature",
  "properties": {
    "iso:country":"US",
    "sg:address":"4211 E Jackson St",
    "sg:city":"Muncie",
    "sg:classifiers":[
        {
            "category":"Manufacturing",
            "subcategory":"Metals",
            "type":"Manufacturing & Wholesale Goods"
        }
    ],
    "sg:phone":"+1 765 289 3355",
    "sg:postcode":"47303",
    "sg:province":"IN",
    "sg:tags":[
        "product",
        "wire",
        "fabricated"
    ],
    "wof:name":"Mid-West Metal Products Co",
    "wof:placetype":"venue"
},
  "geometry": {"coordinates":[-85.340025,40.192859],"type":"Point"}
}