{
  "type": "Feature",
  "properties": {
    "iso:country":"US",
    "sg:address":"12302 Hancock St",
    "sg:city":"Carmel",
    "sg:classifiers":[
        {
            "category":"Professional",
            "type":"Services"
        }
    ],
    "sg:phone":"+1 317 573 8018",
    "sg:postcode":"46032",
    "sg:province":"IN",
    "wof:name":"Ilion Machine Products Inc",
    "wof:placetype":"venue"
},
  "geometry": {"coordinates":[-86.14837199999999,39.969677],"type":"Point"}
}