{
  "type": "Feature",
  "properties": {
    "iso:country":"US",
    "sg:address":"10662 N Co Rd 1025 E",
    "sg:city":"Brownsburg",
    "sg:classifiers":[
        {
            "category":"Professional",
            "subcategory":"Management & Consulting",
            "type":"Services"
        }
    ],
    "sg:phone":"+1 317 769 7600",
    "sg:postcode":"46112",
    "sg:province":"IN",
    "sg:tags":[
        "counselor",
        "public",
        "relations"
    ],
    "wof:name":"Marlene Rose & Associates",
    "wof:placetype":"venue"
},
  "geometry": {"coordinates":[-86.340273,39.919808],"type":"Point"}
}