{
  "type": "Feature",
  "properties": {
    "addr:full":"1626 N Carver St Greensburg IN 47240",
    "addr:housenumber":"1626",
    "addr:postcode":"47240",
    "addr:street":"N Carver St",
    "iso:country":"US",
    "sg:address":"1626 N Carver St",
    "sg:city":"Greensburg",
    "sg:classifiers":[
        {
            "category":"Autos & Motor Vehicles",
            "subcategory":"Fuel & Gas Station",
            "type":"Retail Goods"
        }
    ],
    "sg:phone":"+1 812 663 6533",
    "sg:postcode":"47240",
    "sg:province":"IN",
    "sg:tags":[
        "cb",
        "chainsaw",
        "station",
        "saw",
        "radio"
    ],
    "wof:name":"Carls CB & Saw",
    "wof:placetype":"venue"
},
  "geometry": {"coordinates":[-85.491692,39.353298],"type":"Point"}
}