{
  "type": "Feature",
  "properties": {
    "iso:country":"US",
    "sg:address":"530 E 300 N",
    "sg:city":"Portland",
    "sg:classifiers":[
        {
            "category":"Manufacturing",
            "subcategory":"Metals",
            "type":"Manufacturing & Wholesale Goods"
        }
    ],
    "sg:phone":"+1 260 726 9670",
    "sg:postcode":"47371",
    "sg:province":"IN",
    "sg:tags":[
        "machine",
        "parts",
        "mfg"
    ],
    "wof:name":"Kable Tool & Engineering",
    "wof:placetype":"venue"
},
  "geometry": {"coordinates":[-84.969634,40.482947],"type":"Point"}
}