{
  "type": "Feature",
  "properties": {
    "iso:country":"US",
    "sg:address":"494 N Van Rensselaer St",
    "sg:city":"Rensselaer",
    "sg:classifiers":[
        {
            "category":"Restaurant",
            "type":"Food & Drink"
        }
    ],
    "sg:phone":"+1 219 866 7466",
    "sg:postcode":"47978",
    "sg:province":"IN",
    "sg:tags":[
        "eating"
    ],
    "wof:name":"Rick's Pizza",
    "wof:placetype":"venue"
},
  "geometry": {"coordinates":[-87.15464,40.938559],"type":"Point"}
}