{
  "type": "Feature",
  "properties": {
    "iso:country":"US",
    "sg:address":"11291 E Co Rd 50 N",
    "sg:city":"Seymour",
    "sg:classifiers":[
        {
            "category":"Autos & Motor Vehicles",
            "subcategory":"Automobile Sales",
            "type":"Retail Goods"
        }
    ],
    "sg:phone":"+1 812 523 8029",
    "sg:postcode":"47274",
    "sg:province":"IN",
    "sg:tags":[
        "car",
        "only",
        "used"
    ],
    "wof:name":"Stewarts Specialty Cars",
    "wof:placetype":"venue"
},
  "geometry": {"coordinates":[-85.827206,38.888998],"type":"Point"}
}