{
  "type": "Feature",
  "properties": {
    "addr:full":"608 Main St New Harmony IN 47631",
    "addr:housenumber":"608",
    "addr:postcode":"47631",
    "addr:street":"Main St",
    "iso:country":"US",
    "sg:address":"608 Main St",
    "sg:city":"New Harmony",
    "sg:classifiers":[
        {
            "category":"Shopping",
            "subcategory":"Used Merchandise",
            "type":"Retail Goods"
        }
    ],
    "sg:phone":"+1 812 682 4811",
    "sg:postcode":"47631",
    "sg:province":"IN",
    "sg:tags":[
        "antique"
    ],
    "wof:name":"Firehouse Antiques",
    "wof:placetype":"venue"
},
  "geometry": {"coordinates":[-87.934918,38.128653],"type":"Point"}
}