{
  "type": "Feature",
  "properties": {
    "addr:full":"480 New Albany Plz New Albany IN 47150",
    "addr:housenumber":"480",
    "addr:postcode":"47150",
    "addr:street":"New;Plz",
    "iso:country":"US",
    "sg:address":"480 New Albany Plz",
    "sg:city":"New Albany",
    "sg:classifiers":[
        {
            "category":"Banks & Credit Unions",
            "subcategory":"Bank",
            "type":"Services"
        }
    ],
    "sg:phone":"+1 812 949 6852",
    "sg:postcode":"47150",
    "sg:province":"IN",
    "wof:name":"Community Bank",
    "wof:placetype":"venue"
},
  "geometry": {"coordinates":[-85.84165900000001,38.306991],"type":"Point"}
}