{
  "type": "Feature",
  "properties": {
    "iso:country":"US",
    "sg:address":"4210 N Old State Road 37",
    "sg:city":"Bloomington",
    "sg:classifiers":[
        {
            "category":"Professional",
            "type":"Services"
        }
    ],
    "sg:phone":"+1 812 332 4210",
    "sg:postcode":"47408",
    "sg:province":"IN",
    "sg:tags":[
        "establishment"
    ],
    "wof:name":"Share Web Inc",
    "wof:placetype":"venue"
},
  "geometry": {"coordinates":[-86.52584,39.208222],"type":"Point"}
}