{
  "type": "Feature",
  "properties": {
    "iso:country":"US",
    "sg:address":"1182 N Concord St",
    "sg:city":"Indianapolis",
    "sg:classifiers":[
        {
            "category":"Personal",
            "subcategory":"Barber",
            "type":"Services"
        }
    ],
    "sg:phone":"+1 317 917 8490",
    "sg:postcode":"46222",
    "sg:province":"IN",
    "wof:name":"Right Cut",
    "wof:placetype":"venue"
},
  "geometry": {"coordinates":[-86.21073,39.782395],"type":"Point"}
}