{
  "type": "Feature",
  "properties": {
    "iso:country":"US",
    "sg:address":"1305 N Jordan Ave",
    "sg:city":"Bloomington",
    "sg:classifiers":[
        {
            "category":"Organizations",
            "subcategory":"Community Association",
            "type":"Services"
        }
    ],
    "sg:phone":"+1 812 332 1488",
    "sg:postcode":"47406",
    "sg:province":"IN",
    "sg:tags":[
        "sorority",
        "fraternity"
    ],
    "wof:name":"Gamma Phi Beta",
    "wof:placetype":"venue"
},
  "geometry": {"coordinates":[-86.512527,39.177958],"type":"Point"}
}