{
  "type": "Feature",
  "properties": {
    "iso:country":"US",
    "sg:address":"6005 Bluffton Rd",
    "sg:city":"Fort Wayne",
    "sg:classifiers":[
        {
            "category":"Health Services",
            "subcategory":"Doctor",
            "type":"Services"
        }
    ],
    "sg:phone":"+1 260 478 9960",
    "sg:postcode":"46809",
    "sg:province":"IN",
    "sg:tags":[
        "physician",
        "surgeon"
    ],
    "wof:name":"M A Karim Moshref MD",
    "wof:placetype":"venue"
},
  "geometry": {"coordinates":[-85.167244,41.027813],"type":"Point"}
}