{
  "type": "Feature",
  "properties": {
    "addr:full":"3901 N Broadway Ave Muncie IN 47303",
    "addr:housenumber":"3901",
    "addr:postcode":"47303",
    "addr:street":"N Broadway Ave",
    "iso:country":"US",
    "sg:address":"3901 N Broadway Ave",
    "sg:city":"Muncie",
    "sg:classifiers":[
        {
            "category":"Organizations",
            "subcategory":"Community Association",
            "type":"Services"
        }
    ],
    "sg:phone":"+1 765 747 7158",
    "sg:postcode":"47303",
    "sg:province":"IN",
    "wof:name":"Teamwork For Quality Living",
    "wof:placetype":"venue"
},
  "geometry": {"coordinates":[-85.367936,40.226189],"type":"Point"}
}