{
  "type": "Feature",
  "properties": {
    "iso:country":"US",
    "sg:address":"119 Short St",
    "sg:city":"Lawrenceburg",
    "sg:classifiers":[
        {
            "category":"Organizations",
            "subcategory":"Labor Organization",
            "type":"Services"
        }
    ],
    "sg:phone":"+1 812 537 1062",
    "sg:postcode":"47025",
    "sg:province":"IN",
    "wof:name":"Carpenters Union",
    "wof:placetype":"venue"
},
  "geometry": {"coordinates":[-84.846889,39.093364],"type":"Point"}
}