{
  "type": "Feature",
  "properties": {
    "addr:full":"227 W McCarty St Indianapolis IN 46225",
    "addr:housenumber":"227",
    "addr:postcode":"46225",
    "addr:street":"W Mccarty St",
    "iso:country":"US",
    "sg:address":"227 W McCarty St",
    "sg:city":"Indianapolis",
    "sg:classifiers":[
        {
            "category":"Retail",
            "subcategory":"Repair Shop",
            "type":"Services"
        }
    ],
    "sg:phone":"+1 317 637 2912",
    "sg:postcode":"46225",
    "sg:province":"IN",
    "sg:tags":[
        "welding"
    ],
    "wof:name":"Certified Welding Co",
    "wof:placetype":"venue"
},
  "geometry": {"coordinates":[-86.162476,39.756538],"type":"Point"}
}