{
  "type": "Feature",
  "properties": {
    "iso:country":"US",
    "sg:address":"4300 N Janney Ave",
    "sg:city":"Muncie",
    "sg:classifiers":[
        {
            "category":"Building & Trades",
            "subcategory":"Cleaning & Sanitation",
            "type":"Services"
        }
    ],
    "sg:phone":"+1 765 282 1529",
    "sg:postcode":"47304",
    "sg:province":"IN",
    "sg:tags":[
        "maintenance"
    ],
    "wof:name":"Custom Cleaning",
    "wof:placetype":"venue"
},
  "geometry": {"coordinates":[-85.402636,40.231497],"type":"Point"}
}