{
  "type": "Feature",
  "properties": {
    "iso:country":"US",
    "sg:address":"1916 W Wylie St",
    "sg:city":"Bloomington",
    "sg:classifiers":[
        {
            "category":"Building & Trades",
            "subcategory":"Construction",
            "type":"Services"
        }
    ],
    "sg:phone":"+1 812 336 2600",
    "sg:postcode":"47403",
    "sg:province":"IN",
    "sg:tags":[
        "contractor"
    ],
    "wof:name":"Foster James Construction",
    "wof:placetype":"venue"
},
  "geometry": {"coordinates":[-86.55819700000001,39.159302],"type":"Point"}
}