{
  "type": "Feature",
  "properties": {
    "iso:country":"US",
    "sg:address":"7793 State Rd 8",
    "sg:city":"St Joe",
    "sg:classifiers":[
        {
            "category":"Building & Trades",
            "subcategory":"Plumbing",
            "type":"Services"
        }
    ],
    "sg:phone":"+1 260 337 5280",
    "sg:postcode":"46785",
    "sg:province":"IN",
    "sg:tags":[
        "plumbing",
        "contractor"
    ],
    "wof:name":"Yoder Plumbing",
    "wof:placetype":"venue"
},
  "geometry": {"coordinates":[-84.819562,41.336103],"type":"Point"}
}