{
  "type": "Feature",
  "properties": {
    "iso:country":"US",
    "sg:address":"319 Cottage Ave",
    "sg:city":"Anderson",
    "sg:classifiers":[
        {
            "category":"Education",
            "subcategory":"College",
            "type":"Public Place"
        }
    ],
    "sg:phone":"+1 765 641 4551",
    "sg:postcode":"46012",
    "sg:province":"IN",
    "sg:tags":[
        "academic",
        "school"
    ],
    "wof:name":"Purdue University",
    "wof:placetype":"venue"
},
  "geometry": {"coordinates":[-85.668654,40.110931],"type":"Point"}
}