{
  "type": "Feature",
  "properties": {
    "iso:country":"US",
    "sg:address":"4950 US Hwy 231 S",
    "sg:city":"Crawfordsville",
    "sg:classifiers":[
        {
            "category":"Utilities",
            "subcategory":"Natural Gas",
            "type":"Services"
        }
    ],
    "sg:phone":"+1 765 866 0210",
    "sg:postcode":"47933",
    "sg:province":"IN",
    "sg:tags":[
        "transmission",
        "distribution"
    ],
    "wof:name":"Ameri Gas Inc",
    "wof:placetype":"venue"
},
  "geometry": {"coordinates":[-86.903375,39.966138],"type":"Point"}
}