{
  "type": "Feature",
  "properties": {
    "iso:country":"US",
    "sg:address":"10333 N Meridian St",
    "sg:city":"Indianapolis",
    "sg:classifiers":[
        {
            "category":"Professional",
            "subcategory":"Lawyer & Legal Services",
            "type":"Services"
        }
    ],
    "sg:phone":"+1 317 464 5188",
    "sg:postcode":"46290",
    "sg:province":"IN",
    "sg:tags":[
        "attorney"
    ],
    "wof:name":"Baker & Gilchrist",
    "wof:placetype":"venue"
},
  "geometry": {"coordinates":[-86.157481,39.941036],"type":"Point"}
}