{
  "type": "Feature",
  "properties": {
    "addr:full":"359 N Oneil St Frankfort IN 46041",
    "addr:housenumber":"359",
    "addr:postcode":"46041",
    "addr:street":"N Oneil St",
    "iso:country":"US",
    "sg:address":"359 N Oneil St",
    "sg:city":"Frankfort",
    "sg:classifiers":[
        {
            "category":"Building & Trades",
            "subcategory":"Construction",
            "type":"Services"
        }
    ],
    "sg:phone":"+1 765 659 2385",
    "sg:postcode":"46041",
    "sg:province":"IN",
    "sg:tags":[
        "general",
        "carpentry"
    ],
    "wof:name":"Whit-Co Construction",
    "wof:placetype":"venue"
},
  "geometry": {"coordinates":[-86.50246300000001,40.283279],"type":"Point"}
}