{
  "type": "Feature",
  "properties": {
    "addr:full":"5512 Council Ring Blvd Kokomo IN 46902",
    "addr:housenumber":"5512",
    "addr:postcode":"46902",
    "addr:street":"Council Ring Blvd",
    "iso:country":"US",
    "sg:address":"5512 Council Ring Blvd",
    "sg:city":"Kokomo",
    "sg:classifiers":[
        {
            "category":"Building & Trades",
            "subcategory":"Landscaping Services",
            "type":"Services"
        }
    ],
    "sg:phone":"+1 765 453 5764",
    "sg:postcode":"46902",
    "sg:province":"IN",
    "sg:tags":[
        "landscape",
        "contractor"
    ],
    "wof:name":"Pondscapes",
    "wof:placetype":"venue"
},
  "geometry": {"coordinates":[-86.113372,40.425902],"type":"Point"}
}