{
  "type": "Feature",
  "properties": {
    "iso:country":"US",
    "sg:address":"3750 Kentucky Ave",
    "sg:city":"Indianapolis",
    "sg:classifiers":[
        {
            "category":"Professional",
            "subcategory":"Lawyer & Legal Services",
            "type":"Services"
        }
    ],
    "sg:phone":"+1 317 821 1976",
    "sg:postcode":"46221",
    "sg:province":"IN",
    "sg:tags":[
        "attorney"
    ],
    "wof:name":"Richard A Mann",
    "wof:placetype":"venue"
},
  "geometry": {"coordinates":[-86.248661,39.709844],"type":"Point"}
}