{
  "type": "Feature",
  "properties": {
    "iso:country":"US",
    "sg:address":"115 S US Hwy 231",
    "sg:city":"Jasper",
    "sg:classifiers":[
        {
            "category":"Shopping",
            "subcategory":"Bicycles & Sporting Goods",
            "type":"Retail Goods"
        }
    ],
    "sg:phone":"+1 812 482 2421",
    "sg:postcode":"47546",
    "sg:province":"IN",
    "wof:name":"Sports Garden",
    "wof:placetype":"venue"
},
  "geometry": {"coordinates":[-86.94252400000001,38.38501],"type":"Point"}
}