{
  "type": "Feature",
  "properties": {
    "iso:country":"US",
    "sg:address":"1115 Broadway",
    "sg:city":"Fort Wayne",
    "sg:classifiers":[
        {
            "category":"Shopping",
            "subcategory":"Used Merchandise",
            "type":"Retail Goods"
        }
    ],
    "sg:phone":"+1 260 422 6505",
    "sg:postcode":"46802",
    "sg:province":"IN",
    "wof:name":"Baxters On Broadway Antiq Mall",
    "wof:placetype":"venue"
},
  "geometry": {"coordinates":[-85.147767,41.074581],"type":"Point"}
}