{
  "type": "Feature",
  "properties": {
    "iso:country":"US",
    "sg:address":"2025 English Ave",
    "sg:city":"Indianapolis",
    "sg:classifiers":[
        {
            "category":"Shopping",
            "subcategory":"Used Merchandise",
            "type":"Retail Goods"
        }
    ],
    "sg:phone":"+1 317 951 1234",
    "sg:postcode":"46201",
    "sg:province":"IN",
    "sg:tags":[
        "appliance"
    ],
    "wof:name":"Appliance Outlet",
    "wof:placetype":"venue"
},
  "geometry": {"coordinates":[-86.126665,39.75966],"type":"Point"}
}