{
  "type": "Feature",
  "properties": {
    "iso:country":"US",
    "sg:address":"7451 W Johnson Rd",
    "sg:city":"Michigan City",
    "sg:classifiers":[
        {
            "category":"Social Services",
            "type":"Services"
        }
    ],
    "sg:phone":"+1 219 874 0007",
    "sg:postcode":"46360",
    "sg:province":"IN",
    "sg:tags":[
        "development",
        "education",
        "child"
    ],
    "sg:website":"www.dunebrook.org",
    "wof:name":"Dunebrook Parent Information",
    "wof:placetype":"venue"
},
  "geometry": {"coordinates":[-86.843677,41.670998],"type":"Point"}
}