{
  "type": "Feature",
  "properties": {
    "iso:country":"US",
    "sg:address":"1809 W University Ave",
    "sg:city":"Muncie",
    "sg:classifiers":[
        {
            "category":"Professional",
            "subcategory":"Computer Services",
            "type":"Services"
        }
    ],
    "sg:phone":"+1 765 284 0910",
    "sg:postcode":"47303",
    "sg:province":"IN",
    "sg:tags":[
        "website",
        "design"
    ],
    "wof:name":"Spin Web Net Designs Inc",
    "wof:placetype":"venue"
},
  "geometry": {"coordinates":[-85.407716,40.197581],"type":"Point"}
}