{
  "type": "Feature",
  "properties": {
    "iso:country":"US",
    "sg:address":"3816 Cranbrook Dr",
    "sg:city":"Indianapolis",
    "sg:classifiers":[
        {
            "category":"Manufacturing",
            "subcategory":"Chemicals & Compounds",
            "type":"Manufacturing & Wholesale Goods"
        }
    ],
    "sg:phone":"+1 317 849 1345",
    "sg:postcode":"46240",
    "sg:province":"IN",
    "sg:tags":[
        "preparation",
        "pharmaceutical"
    ],
    "wof:name":"M Burk Designs",
    "wof:placetype":"venue"
},
  "geometry": {"coordinates":[-86.101572,39.884271],"type":"Point"}
}