{
  "type": "Feature",
  "properties": {
    "iso:country":"US",
    "sg:address":"960 Harlash St",
    "sg:city":"Kendallville",
    "sg:classifiers":[
        {
            "category":"Autos & Motor Vehicles",
            "subcategory":"Auto Supplies",
            "type":"Retail Goods"
        }
    ],
    "sg:phone":"+1 260 347 2211",
    "sg:postcode":"46755",
    "sg:province":"IN",
    "sg:tags":[
        "automobile",
        "parts"
    ],
    "wof:name":"NAPA Auto Parts",
    "wof:placetype":"venue"
},
  "geometry": {"coordinates":[-85.279079,41.453288],"type":"Point"}
}