{
  "type": "Feature",
  "properties": {
    "iso:country":"US",
    "sg:address":"10 45th Ave",
    "sg:city":"Munster",
    "sg:classifiers":[
        {
            "category":"Autos & Motor Vehicles",
            "subcategory":"Fuel & Gas Station",
            "type":"Retail Goods"
        }
    ],
    "sg:phone":"+1 219 924 9030",
    "sg:postcode":"46321",
    "sg:province":"IN",
    "wof:name":"Exxon",
    "wof:placetype":"venue"
},
  "geometry": {"coordinates":[-87.524879,41.542902],"type":"Point"}
}