{
  "type": "Feature",
  "properties": {
    "iso:country":"US",
    "sg:address":"801 National Rd W",
    "sg:city":"Richmond",
    "sg:classifiers":[
        {
            "category":"Restaurant",
            "type":"Food & Drink"
        }
    ],
    "sg:menulink":"http://www.allmenus.com/in/richmond/120285-subway/menu/",
    "sg:phone":"+1 765 983 1379",
    "sg:postcode":"47374",
    "sg:province":"IN",
    "sg:tags":[
        "american",
        "sandwich"
    ],
    "wof:name":"Subway",
    "wof:placetype":"venue"
},
  "geometry": {"coordinates":[-84.91284,39.826401],"type":"Point"}
}