{
  "type": "Feature",
  "properties": {
    "addr:full":"8225 Franke Rd Fort Wayne IN 46816",
    "addr:postcode":"8225;46816",
    "addr:street":"Franke Rd",
    "iso:country":"US",
    "sg:address":"8225 Franke Rd",
    "sg:city":"Fort Wayne",
    "sg:classifiers":[
        {
            "category":"Bars & Pubs",
            "type":"Food & Drink"
        }
    ],
    "sg:phone":"+1 260 623 6396",
    "sg:postcode":"46816",
    "sg:province":"IN",
    "wof:name":"Maples Inn Inc",
    "wof:placetype":"venue"
},
  "geometry": {"coordinates":[-84.96938,41.012301],"type":"Point"}
}