{
  "type": "Feature",
  "properties": {
    "addr:full":"11095 N 500 W Milford IN 46542",
    "addr:housenumber":"11095",
    "addr:postcode":"46542",
    "addr:street":"N 500 W",
    "iso:country":"US",
    "sg:address":"11095 N 500 W",
    "sg:city":"Milford",
    "sg:classifiers":[
        {
            "category":"Building & Trades",
            "subcategory":"Construction",
            "type":"Services"
        }
    ],
    "sg:phone":"+1 574 773 7115",
    "sg:postcode":"46542",
    "sg:province":"IN",
    "sg:tags":[
        "dry wall",
        "contractor"
    ],
    "wof:name":"J & J Drywall",
    "wof:placetype":"venue"
},
  "geometry": {"coordinates":[-85.943681,41.396728],"type":"Point"}
}