{
  "type": "Feature",
  "properties": {
    "iso:country":"US",
    "sg:address":"118 S Mulberry St",
    "sg:city":"Rising Sun",
    "sg:classifiers":[
        {
            "category":"Travel",
            "subcategory":"Hotels & Motels",
            "type":"Entertainment"
        }
    ],
    "sg:phone":"+1 812 438 2206",
    "sg:postcode":"47040",
    "sg:province":"IN",
    "sg:tags":[
        "operation"
    ],
    "wof:name":"Mulberry Inn Grdns Bed Brkfast",
    "wof:placetype":"venue"
},
  "geometry": {"coordinates":[-84.856816,38.950454],"type":"Point"}
}