{
  "type": "Feature",
  "properties": {
    "iso:country":"US",
    "sg:address":"2917 Calumet Ave",
    "sg:city":"Valparaiso",
    "sg:classifiers":[
        {
            "category":"Food & Beverages",
            "subcategory":"Specialty",
            "type":"Retail Goods"
        }
    ],
    "sg:phone":"+1 219 464 7818",
    "sg:postcode":"46383",
    "sg:province":"IN",
    "sg:tags":[
        "health",
        "diet"
    ],
    "wof:name":"Hilke's Nutrition Ctr",
    "wof:placetype":"venue"
},
  "geometry": {"coordinates":[-87.044661,41.495931],"type":"Point"}
}