{
  "type": "Feature",
  "properties": {
    "addr:full":"4445 Linden Rd South Bend IN 46614",
    "addr:housenumber":"4445",
    "addr:postcode":"46614",
    "addr:street":"Linden Rd",
    "iso:country":"US",
    "sg:address":"4445 Linden Rd",
    "sg:city":"South Bend",
    "sg:classifiers":[
        {
            "category":"Social Services",
            "subcategory":"Child Care",
            "type":"Services"
        }
    ],
    "sg:phone":"+1 574 291 3333",
    "sg:postcode":"46614",
    "sg:province":"IN",
    "wof:name":"Apple Tree Learning Ctr",
    "wof:placetype":"venue"
},
  "geometry": {"coordinates":[-86.27282099999999,41.627243],"type":"Point"}
}