{
  "type": "Feature",
  "properties": {
    "iso:country":"US",
    "sg:address":"428 N Co Rd 950 E",
    "sg:city":"Logansport",
    "sg:classifiers":[
        {
            "category":"Building & Trades",
            "subcategory":"Construction",
            "type":"Services"
        }
    ],
    "sg:phone":"+1 574 753 9676",
    "sg:postcode":"46947",
    "sg:province":"IN",
    "sg:tags":[
        "concrete",
        "contractor"
    ],
    "wof:name":"BF Concrete",
    "wof:placetype":"venue"
},
  "geometry": {"coordinates":[-86.197519,40.76939],"type":"Point"}
}