{
  "type": "Feature",
  "properties": {
    "addr:full":"720 W Bristol St Elkhart IN 46514",
    "addr:housenumber":"720",
    "addr:postcode":"46514",
    "addr:street":"W Bristol St",
    "iso:country":"US",
    "sg:address":"720 W Bristol St",
    "sg:city":"Elkhart",
    "sg:classifiers":[
        {
            "category":"Autos & Motor Vehicles",
            "subcategory":"Motorcycle Sales",
            "type":"Retail Goods"
        }
    ],
    "sg:phone":"+1 574 262 2735",
    "sg:postcode":"46514",
    "sg:province":"IN",
    "sg:tags":[
        "scooter"
    ],
    "sg:website":"www.gerencers.com",
    "wof:name":"Gerencer's Harley-Davidson",
    "wof:placetype":"venue"
},
  "geometry": {"coordinates":[-85.987116,41.702694],"type":"Point"}
}