{
  "type": "Feature",
  "properties": {
    "addr:full":"11321 Village Square Ln Fishers IN 46038",
    "addr:housenumber":"11321",
    "addr:postcode":"46038",
    "addr:street":"Village Square Ln",
    "iso:country":"US",
    "sg:address":"11321 Village Square Ln",
    "sg:city":"Fishers",
    "sg:classifiers":[
        {
            "category":"Shopping",
            "type":"Retail Goods"
        }
    ],
    "sg:phone":"+1 317 849 8640",
    "sg:postcode":"46038",
    "sg:province":"IN",
    "sg:tags":[
        "merchandise"
    ],
    "wof:name":"Namaste Plaza Inc",
    "wof:placetype":"venue"
},
  "geometry": {"coordinates":[-86.041484,39.951387],"type":"Point"}
}