{
  "type": "Feature",
  "properties": {
    "iso:country":"US",
    "sg:address":"1742 E 400 N",
    "sg:city":"Fowler",
    "sg:classifiers":[
        {
            "category":"Autos & Motor Vehicles",
            "subcategory":"Auto Supplies",
            "type":"Retail Goods"
        }
    ],
    "sg:phone":"+1 765 884 0648",
    "sg:postcode":"47944",
    "sg:province":"IN",
    "sg:tags":[
        "battery"
    ],
    "wof:name":"Interstate Battery System",
    "wof:placetype":"venue"
},
  "geometry": {"coordinates":[-87.286017,40.664152],"type":"Point"}
}