{
  "type": "Feature",
  "properties": {
    "iso:country":"US",
    "sg:address":"1121 W Grant St",
    "sg:city":"Bremen",
    "sg:classifiers":[
        {
            "category":"Real Estate",
            "subcategory":"Real Estate Agent",
            "type":"Services"
        }
    ],
    "sg:phone":"+1 574 546 3641",
    "sg:postcode":"46506",
    "sg:province":"IN",
    "sg:tags":[
        "appraiser"
    ],
    "wof:name":"A M Appraisals",
    "wof:placetype":"venue"
},
  "geometry": {"coordinates":[-86.160689,41.442909],"type":"Point"}
}