{
  "type": "Feature",
  "properties": {
    "iso:country":"US",
    "sg:address":"4004 Campbell St",
    "sg:city":"Valparaiso",
    "sg:classifiers":[
        {
            "category":"Health Services",
            "subcategory":"Chiropractor",
            "type":"Services"
        }
    ],
    "sg:phone":"+1 219 548 0555",
    "sg:postcode":"46385",
    "sg:province":"IN",
    "wof:name":"A Body For Life",
    "wof:placetype":"venue"
},
  "geometry": {"coordinates":[-87.065945,41.504817],"type":"Point"}
}