{
  "type": "Feature",
  "properties": {
    "iso:country":"US",
    "sg:address":"114 Jack Imel Ave",
    "sg:city":"Portland",
    "sg:classifiers":[
        {
            "category":"Building & Trades",
            "subcategory":"Construction",
            "type":"Services"
        }
    ],
    "sg:phone":"+1 260 726 3731",
    "sg:postcode":"47371",
    "sg:province":"IN",
    "wof:name":"T-N-T Construction",
    "wof:placetype":"venue"
},
  "geometry": {"coordinates":[-84.995393,40.434527],"type":"Point"}
}