{
  "type": "Feature",
  "properties": {
    "iso:country":"US",
    "sg:address":"3829 Egbert Rd",
    "sg:city":"Martinsville",
    "sg:classifiers":[
        {
            "category":"Building & Trades",
            "subcategory":"Construction",
            "type":"Services"
        }
    ],
    "sg:phone":"+1 765 352 1956",
    "sg:postcode":"46151",
    "sg:province":"IN",
    "sg:tags":[
        "fire",
        "house",
        "restoration",
        "damage"
    ],
    "sg:website":"www.clowrestoration.com",
    "wof:name":"Clow Construction Inc",
    "wof:placetype":"venue"
},
  "geometry": {"coordinates":[-86.354582,39.479316],"type":"Point"}
}