{
  "type": "Feature",
  "properties": {
    "iso:country":"US",
    "sg:address":"8564 E Main St",
    "sg:city":"Dugger",
    "sg:classifiers":[
        {
            "category":"Government",
            "subcategory":"Office",
            "type":"Public Place"
        }
    ],
    "sg:phone":"+1 812 648 2196",
    "sg:postcode":"47848",
    "sg:province":"IN",
    "sg:tags":[
        "space",
        "technology",
        "research"
    ],
    "wof:name":"Possum Holler Inc",
    "wof:placetype":"venue"
},
  "geometry": {"coordinates":[-87.252743,39.067223],"type":"Point"}
}