{
  "type": "Feature",
  "properties": {
    "iso:country":"US",
    "sg:address":"321 N Range Line Rd",
    "sg:city":"Carmel",
    "sg:classifiers":[
        {
            "category":"Professional",
            "subcategory":"Business Services",
            "type":"Services"
        }
    ],
    "sg:phone":"+1 317 844 0845",
    "sg:postcode":"46032",
    "sg:province":"IN",
    "wof:name":"Forbush Design Inc",
    "wof:placetype":"venue"
},
  "geometry": {"coordinates":[-86.126993,39.981107],"type":"Point"}
}