{
  "type": "Feature",
  "properties": {
    "iso:country":"US",
    "sg:address":"514 N Halleck St",
    "sg:city":"Demotte",
    "sg:classifiers":[
        {
            "category":"Restaurant",
            "type":"Food & Drink"
        }
    ],
    "sg:phone":"+1 219 987 5757",
    "sg:postcode":"46310",
    "sg:province":"IN",
    "wof:name":"Boundary Waters Lodge",
    "wof:placetype":"venue"
},
  "geometry": {"coordinates":[-87.19893,41.207947],"type":"Point"}
}