{
  "type": "Feature",
  "properties": {
    "iso:country":"US",
    "sg:address":"112 N Division St",
    "sg:city":"Cayuga",
    "sg:classifiers":[
        {
            "category":"Personal",
            "subcategory":"Tanning Parlor",
            "type":"Services"
        }
    ],
    "sg:phone":"+1 765 492 9885",
    "sg:postcode":"47928",
    "sg:province":"IN",
    "sg:tags":[
        "salon"
    ],
    "wof:name":"Sensational Spray Tan",
    "wof:placetype":"venue"
},
  "geometry": {"coordinates":[-87.461192,39.950318],"type":"Point"}
}