{
  "type": "Feature",
  "properties": {
    "addr:full":"1110 5th St NW Linton IN 47441",
    "addr:housenumber":"1110",
    "addr:postcode":"47441",
    "addr:street":"5Th St Nw",
    "iso:country":"US",
    "sg:address":"1110 5th St NW",
    "sg:city":"Linton",
    "sg:classifiers":[
        {
            "category":"Shopping",
            "subcategory":"Florist",
            "type":"Retail Goods"
        }
    ],
    "sg:phone":"+1 812 847 0947",
    "sg:postcode":"47441",
    "sg:province":"IN",
    "wof:name":"Vine & Branches",
    "wof:placetype":"venue"
},
  "geometry": {"coordinates":[-87.171154,39.043063],"type":"Point"}
}