{
  "type": "Feature",
  "properties": {
    "iso:country":"US",
    "sg:address":"800 Fairview Ave",
    "sg:city":"Crawfordsville",
    "sg:classifiers":[
        {
            "category":"Education",
            "subcategory":"School",
            "type":"Public Place"
        }
    ],
    "sg:phone":"+1 765 362 2886",
    "sg:postcode":"47933",
    "sg:province":"IN",
    "wof:name":"Hose School",
    "wof:placetype":"venue"
},
  "geometry": {"coordinates":[-86.89108899999999,40.045359],"type":"Point"}
}