{
  "type": "Feature",
  "properties": {
    "iso:country":"US",
    "sg:address":"7606 Meriwood Dr",
    "sg:city":"Fort Wayne",
    "sg:classifiers":[
        {
            "category":"Building & Trades",
            "subcategory":"Construction",
            "type":"Services"
        }
    ],
    "sg:phone":"+1 260 486 5834",
    "sg:postcode":"46835",
    "sg:province":"IN",
    "sg:tags":[
        "house"
    ],
    "wof:name":"Kester Construction Inc",
    "wof:placetype":"venue"
},
  "geometry": {"coordinates":[-85.062122,41.151725],"type":"Point"}
}