{
  "type": "Feature",
  "properties": {
    "addr:full":"1114 Broad St New Castle IN 47362",
    "addr:housenumber":"1114",
    "addr:postcode":"47362",
    "addr:street":"Broad St",
    "iso:country":"US",
    "sg:address":"1114 Broad St",
    "sg:city":"New Castle",
    "sg:classifiers":[
        {
            "category":"Shopping",
            "subcategory":"Computers & Home Electronics",
            "type":"Retail Goods"
        }
    ],
    "sg:phone":"+1 765 593 9076",
    "sg:postcode":"47362",
    "sg:province":"IN",
    "sg:tags":[
        "equipment",
        "dealer"
    ],
    "sg:website":"www.sui.net",
    "wof:name":"Solutions Unlimited",
    "wof:placetype":"venue"
},
  "geometry": {"coordinates":[-85.37284,39.931288],"type":"Point"}
}