{
  "type": "Feature",
  "properties": {
    "iso:country":"US",
    "sg:address":"4140 W 206th St",
    "sg:city":"Sheridan",
    "sg:classifiers":[
        {
            "category":"Building & Trades",
            "subcategory":"Construction",
            "type":"Services"
        }
    ],
    "sg:phone":"+1 317 867 3199",
    "sg:postcode":"46069",
    "sg:province":"IN",
    "sg:tags":[
        "house"
    ],
    "wof:name":"Mike Kistler Builders Inc",
    "wof:placetype":"venue"
},
  "geometry": {"coordinates":[-86.23257700000001,40.085448],"type":"Point"}
}