{
  "type": "Feature",
  "properties": {
    "iso:country":"US",
    "sg:address":"13510 Saint Wendel Rd",
    "sg:city":"Evansville",
    "sg:classifiers":[
        {
            "category":"Restaurant",
            "type":"Food & Drink"
        }
    ],
    "sg:phone":"+1 812 963 0944",
    "sg:postcode":"47720",
    "sg:province":"IN",
    "wof:name":"Silver Bell Restaurant",
    "wof:placetype":"venue"
},
  "geometry": {"coordinates":[-87.694321,38.096455],"type":"Point"}
}