{
  "type": "Feature",
  "properties": {
    "iso:country":"US",
    "sg:address":"1402 S Main St",
    "sg:city":"Kouts",
    "sg:classifiers":[
        {
            "category":"Freight",
            "type":"Transportation"
        }
    ],
    "sg:phone":"+1 219 766 3322",
    "sg:postcode":"46347",
    "sg:province":"IN",
    "sg:tags":[
        "livestock",
        "hauling"
    ],
    "wof:name":"Richard Gingerich Livestock Co",
    "wof:placetype":"venue"
},
  "geometry": {"coordinates":[-87.025862,41.308627],"type":"Point"}
}