{
  "type": "Feature",
  "properties": {
    "addr:full":"619 E Dupont Rd Fort Wayne IN 46825",
    "addr:housenumber":"619",
    "addr:postcode":"46825",
    "addr:street":"E Dupont Rd",
    "iso:country":"US",
    "sg:address":"619 E Dupont Rd",
    "sg:city":"Fort Wayne",
    "sg:classifiers":[
        {
            "category":"Professional",
            "subcategory":"Business Services",
            "type":"Services"
        }
    ],
    "sg:phone":"+1 260 637 4809",
    "sg:postcode":"46825",
    "sg:province":"IN",
    "sg:tags":[
        "packaging"
    ],
    "wof:name":"Pak Mail Ctr",
    "wof:placetype":"venue"
},
  "geometry": {"coordinates":[-85.134321,41.178232],"type":"Point"}
}