{
  "type": "Feature",
  "properties": {
    "iso:country":"US",
    "sg:address":"1200 Leesburg Rd",
    "sg:city":"Fort Wayne",
    "sg:classifiers":[
        {
            "category":"Building & Trades",
            "subcategory":"Plumbing",
            "type":"Services"
        }
    ],
    "sg:phone":"+1 260 432 3205",
    "sg:postcode":"46808",
    "sg:province":"IN",
    "sg:tags":[
        "conditioning",
        "air",
        "system",
        "contractor"
    ],
    "wof:name":"Sheets Air Conditioning Htg",
    "wof:placetype":"venue"
},
  "geometry": {"coordinates":[-85.17006600000001,41.085077],"type":"Point"}
}