{
  "type": "Feature",
  "properties": {
    "iso:country":"US",
    "sg:address":"5260 Old US Hwy 30",
    "sg:city":"Hamlet",
    "sg:classifiers":[
        {
            "category":"Building & Trades",
            "subcategory":"Construction",
            "type":"Services"
        }
    ],
    "sg:phone":"+1 574 586 2617",
    "sg:postcode":"46532",
    "sg:province":"IN",
    "sg:tags":[
        "water",
        "well",
        "drilling"
    ],
    "wof:name":"James Harness Well Drilli",
    "wof:placetype":"venue"
},
  "geometry": {"coordinates":[-86.597367,41.384412],"type":"Point"}
}