{
  "type": "Feature",
  "properties": {
    "iso:country":"US",
    "sg:address":"812 Indianapolis Rd",
    "sg:city":"Greencastle",
    "sg:classifiers":[
        {
            "category":"Professional",
            "subcategory":"Accounting & Tax Preparation",
            "type":"Services"
        }
    ],
    "sg:phone":"+1 765 653 8822",
    "sg:postcode":"46135",
    "sg:province":"IN",
    "sg:tags":[
        "return",
        "filing"
    ],
    "wof:name":"Triple C Tax Svc",
    "wof:placetype":"venue"
},
  "geometry": {"coordinates":[-86.843269,39.645567],"type":"Point"}
}