{
  "type": "Feature",
  "properties": {
    "iso:country":"US",
    "sg:address":"140 Polk Ave",
    "sg:city":"Greenfield",
    "sg:classifiers":[
        {
            "category":"Education",
            "subcategory":"School",
            "type":"Public Place"
        }
    ],
    "sg:phone":"+1 317 462 1492",
    "sg:postcode":"46140",
    "sg:province":"IN",
    "wof:name":"Weston Elementary School",
    "wof:placetype":"venue"
},
  "geometry": {"coordinates":[-85.787095,39.787237],"type":"Point"}
}