{
  "type": "Feature",
  "properties": {
    "iso:country":"US",
    "sg:address":"1432 W McGalliard Rd",
    "sg:city":"Muncie",
    "sg:classifiers":[
        {
            "category":"Personal",
            "type":"Services"
        }
    ],
    "sg:phone":"+1 765 282 7502",
    "sg:postcode":"47304",
    "sg:province":"IN",
    "sg:tags":[
        "control",
        "weight"
    ],
    "wof:name":"LA Weight Loss Ctr Inc",
    "wof:placetype":"venue"
},
  "geometry": {"coordinates":[-85.40195300000001,40.218996],"type":"Point"}
}