{
  "type": "Feature",
  "properties": {
    "addr:full":"9519 Cedar Rd Bourbon IN 46504",
    "addr:housenumber":"9519",
    "addr:postcode":"46504",
    "addr:street":"Cedar Rd",
    "iso:country":"US",
    "sg:address":"9519 Cedar Rd",
    "sg:city":"Bourbon",
    "sg:classifiers":[
        {
            "category":"Organizations",
            "subcategory":"Religious Organization",
            "type":"Services"
        }
    ],
    "sg:phone":"+1 574 342 0006",
    "sg:postcode":"46504",
    "sg:province":"IN",
    "wof:name":"New Wine Church",
    "wof:placetype":"venue"
},
  "geometry": {"coordinates":[-86.096614,41.339018],"type":"Point"}
}