{
  "type": "Feature",
  "properties": {
    "iso:country":"US",
    "sg:address":"906 W 4th St",
    "sg:city":"Greensburg",
    "sg:classifiers":[
        {
            "category":"Health Services",
            "subcategory":"Doctor",
            "type":"Services"
        }
    ],
    "sg:phone":"+1 812 663 8088",
    "sg:postcode":"47240",
    "sg:province":"IN",
    "sg:tags":[
        "dentist"
    ],
    "wof:name":"Robert Eversole DDS",
    "wof:placetype":"venue"
},
  "geometry": {"coordinates":[-85.494104,39.347263],"type":"Point"}
}