{
  "type": "Feature",
  "properties": {
    "iso:country":"US",
    "sg:address":"117 N Huntington St",
    "sg:city":"Syracuse",
    "sg:classifiers":[
        {
            "category":"Personal",
            "subcategory":"Beauty Salon",
            "type":"Services"
        }
    ],
    "sg:phone":"+1 574 528 6111",
    "sg:postcode":"46567",
    "sg:province":"IN",
    "wof:name":"True Colors",
    "wof:placetype":"venue"
},
  "geometry": {"coordinates":[-85.7486,41.42299],"type":"Point"}
}