{
  "type": "Feature",
  "properties": {
    "iso:country":"US",
    "sg:address":"1138 E 900 N",
    "sg:city":"Milford",
    "sg:classifiers":[
        {
            "category":"Health Services",
            "subcategory":"Doctor",
            "type":"Services"
        }
    ],
    "sg:phone":"+1 574 658 9631",
    "sg:postcode":"46542",
    "sg:province":"IN",
    "sg:tags":[
        "anesthetist"
    ],
    "wof:name":"M Beardslee Anesthesia Svc",
    "wof:placetype":"venue"
},
  "geometry": {"coordinates":[-85.808302,41.363519],"type":"Point"}
}