{
  "type": "Feature",
  "properties": {
    "iso:country":"US",
    "sg:address":"2311 S 7th St",
    "sg:city":"Terre Haute",
    "sg:classifiers":[
        {
            "category":"Social Services",
            "subcategory":"Child Care",
            "type":"Services"
        }
    ],
    "sg:phone":"+1 812 235 0052",
    "sg:postcode":"47802",
    "sg:province":"IN",
    "wof:name":"Town South Daycare",
    "wof:placetype":"venue"
},
  "geometry": {"coordinates":[-87.406938,39.441159],"type":"Point"}
}