{
  "type": "Feature",
  "properties": {
    "iso:country":"US",
    "sg:address":"2801 S Eaton Ave",
    "sg:city":"Muncie",
    "sg:classifiers":[
        {
            "category":"Government",
            "subcategory":"Office",
            "type":"Public Place"
        }
    ],
    "sg:phone":"+1 765 286 7441",
    "sg:postcode":"47302",
    "sg:province":"IN",
    "sg:tags":[
        "village"
    ],
    "wof:name":"Center Township Trustee Pole",
    "wof:placetype":"venue"
},
  "geometry": {"coordinates":[-85.34851999999999,40.169971],"type":"Point"}
}