{
  "type": "Feature",
  "properties": {
    "iso:country":"US",
    "sg:address":"8816 Bono Rd",
    "sg:city":"Terre Haute",
    "sg:classifiers":[
        {
            "category":"Personal",
            "subcategory":"Beauty Salon",
            "type":"Services"
        }
    ],
    "sg:phone":"+1 812 298 8806",
    "sg:postcode":"47802",
    "sg:province":"IN",
    "sg:tags":[
        "shop"
    ],
    "wof:name":"Hair At Home",
    "wof:placetype":"venue"
},
  "geometry": {"coordinates":[-87.378933,39.35316],"type":"Point"}
}