{
  "type": "Feature",
  "properties": {
    "iso:country":"US",
    "sg:address":"22676 US Hwy 33",
    "sg:city":"Elkhart",
    "sg:classifiers":[
        {
            "category":"Shopping",
            "subcategory":"Clothing, Apparel, & Fashions",
            "type":"Retail Goods"
        }
    ],
    "sg:phone":"+1 574 875 1625",
    "sg:postcode":"46517",
    "sg:province":"IN",
    "wof:name":"Dots Inc",
    "wof:placetype":"venue"
},
  "geometry": {"coordinates":[-85.910197,41.628806],"type":"Point"}
}