{
  "type": "Feature",
  "properties": {
    "iso:country":"US",
    "sg:address":"505 E Central Ave",
    "sg:city":"Greensburg",
    "sg:classifiers":[
        {
            "category":"Education",
            "subcategory":"School",
            "type":"Public Place"
        }
    ],
    "sg:phone":"+1 812 663 7523",
    "sg:postcode":"47240",
    "sg:province":"IN",
    "sg:website":"www.greensburg.k12.in.us",
    "wof:name":"Greensburg Community Jr High",
    "wof:placetype":"venue"
},
  "geometry": {"coordinates":[-85.47622200000001,39.339863],"type":"Point"}
}