{
  "type": "Feature",
  "properties": {
    "iso:country":"US",
    "sg:address":"3100 N National Rd",
    "sg:city":"Columbus",
    "sg:classifiers":[
        {
            "category":"Shopping",
            "subcategory":"Department Store",
            "type":"Retail Goods"
        }
    ],
    "sg:phone":"+1 812 372 1817",
    "sg:postcode":"47201",
    "sg:province":"IN",
    "wof:name":"Target",
    "wof:placetype":"venue"
},
  "geometry": {"coordinates":[-85.905644,39.230153],"type":"Point"}
}