{
  "type": "Feature",
  "properties": {
    "addr:full":"6424 E State Blvd Fort Wayne IN 46815",
    "addr:housenumber":"6424",
    "addr:postcode":"46815",
    "addr:street":"E State Blvd",
    "iso:country":"US",
    "sg:address":"6424 E State Blvd",
    "sg:city":"Fort Wayne",
    "sg:classifiers":[
        {
            "category":"Professional",
            "subcategory":"Accounting & Tax Preparation",
            "type":"Services"
        }
    ],
    "sg:phone":"+1 260 749 6040",
    "sg:postcode":"46815",
    "sg:province":"IN",
    "sg:tags":[
        "return",
        "filing"
    ],
    "wof:name":"Expertax",
    "wof:placetype":"venue"
},
  "geometry": {"coordinates":[-85.059129,41.101126],"type":"Point"}
}