{
  "type": "Feature",
  "properties": {
    "iso:country":"US",
    "sg:address":"6026 W 700 S",
    "sg:city":"Morgantown",
    "sg:classifiers":[
        {
            "category":"Home & Garden",
            "subcategory":"Building Materials",
            "type":"Retail Goods"
        }
    ],
    "sg:phone":"+1 812 597 2008",
    "sg:postcode":"46160",
    "sg:province":"IN",
    "sg:tags":[
        "carpentry",
        "contractor"
    ],
    "wof:name":"Bryant Window & Door Inc",
    "wof:placetype":"venue"
},
  "geometry": {"coordinates":[-86.218549,39.371565],"type":"Point"}
}