{
  "type": "Feature",
  "properties": {
    "addr:full":"1049 US Hwy 41 Schererville IN 46375",
    "addr:housenumber":"1049",
    "addr:postcode":"46375",
    "addr:street":"Us Hwy 41",
    "iso:country":"US",
    "sg:address":"1049 US Hwy 41",
    "sg:city":"Schererville",
    "sg:classifiers":[
        {
            "category":"Manufacturing",
            "subcategory":"Metals",
            "type":"Manufacturing & Wholesale Goods"
        }
    ],
    "sg:phone":"+1 219 865 8040",
    "sg:postcode":"46375",
    "sg:province":"IN",
    "sg:tags":[
        "product",
        "primary"
    ],
    "wof:name":"Mason Corp",
    "wof:placetype":"venue"
},
  "geometry": {"coordinates":[-87.47110000000001,41.50687],"type":"Point"}
}