{
  "type": "Feature",
  "properties": {
    "addr:full":"10433 Indianapolis Blvd Highland IN 46322",
    "addr:housenumber":"10433",
    "addr:postcode":"46322",
    "addr:street":"Indianapolis Blvd",
    "iso:country":"US",
    "sg:address":"10433 Indianapolis Blvd",
    "sg:city":"Highland",
    "sg:classifiers":[
        {
            "category":"Personal",
            "type":"Services"
        }
    ],
    "sg:phone":"+1 219 922 6197",
    "sg:postcode":"46322",
    "sg:province":"IN",
    "sg:tags":[
        "control",
        "weight"
    ],
    "wof:name":"Jenny Craig Weight Loss Ctr",
    "wof:placetype":"venue"
},
  "geometry": {"coordinates":[-87.471158,41.525528],"type":"Point"}
}