{
  "type": "Feature",
  "properties": {
    "iso:country":"US",
    "sg:address":"7552 N 750 W",
    "sg:city":"Roann",
    "sg:classifiers":[
        {
            "category":"Farming",
            "subcategory":"Farm",
            "type":"Manufacturing & Wholesale Goods"
        }
    ],
    "sg:phone":"+1 765 833 5523",
    "sg:postcode":"46974",
    "sg:province":"IN",
    "sg:tags":[
        "crop",
        "general"
    ],
    "wof:name":"Donald Slee",
    "wof:placetype":"venue"
},
  "geometry": {"coordinates":[-85.934935,40.933625],"type":"Point"}
}