{
  "type": "Feature",
  "properties": {
    "iso:country":"US",
    "sg:address":"323 S Monfort St",
    "sg:city":"Greensburg",
    "sg:classifiers":[
        {
            "category":"Wholesale",
            "subcategory":"Auto Parts",
            "type":"Manufacturing & Wholesale Goods"
        }
    ],
    "sg:phone":"+1 812 663 5587",
    "sg:postcode":"47240",
    "sg:province":"IN",
    "sg:tags":[
        "automobile",
        "rebuilt"
    ],
    "wof:name":"Decatur Wrecking",
    "wof:placetype":"venue"
},
  "geometry": {"coordinates":[-85.48715,39.334079],"type":"Point"}
}