{
  "type": "Feature",
  "properties": {
    "iso:country":"US",
    "sg:address":"324 N 4th St",
    "sg:city":"Richmond",
    "sg:classifiers":[
        {
            "category":"Retail",
            "subcategory":"Repair Shop",
            "type":"Services"
        }
    ],
    "sg:phone":"+1 765 966 1215",
    "sg:postcode":"47374",
    "sg:province":"IN",
    "sg:tags":[
        "welding"
    ],
    "wof:name":"Mikes Welding Shop",
    "wof:placetype":"venue"
},
  "geometry": {"coordinates":[-84.896379,39.832538],"type":"Point"}
}