{
  "type": "Feature",
  "properties": {
    "addr:full":"8847 Commerce Park Pl Indianapolis IN 46268",
    "addr:housenumber":"8847",
    "addr:postcode":"46268",
    "addr:street":"Commerce Park Pl",
    "iso:country":"US",
    "sg:address":"8847 Commerce Park Pl",
    "sg:city":"Indianapolis",
    "sg:classifiers":[
        {
            "category":"Wholesale",
            "subcategory":"Non-durable Goods",
            "type":"Manufacturing & Wholesale Goods"
        }
    ],
    "sg:phone":"+1 317 228 1903",
    "sg:postcode":"46268",
    "sg:province":"IN",
    "sg:tags":[
        "advertising"
    ],
    "wof:name":"Custom Creations By Victoria",
    "wof:placetype":"venue"
},
  "geometry": {"coordinates":[-86.23316,39.912173],"type":"Point"}
}