{
  "type": "Feature",
  "properties": {
    "iso:country":"US",
    "sg:address":"8117 Groton Ln",
    "sg:city":"Indianapolis",
    "sg:classifiers":[
        {
            "category":"Manufacturing",
            "subcategory":"Tools & Machinery",
            "type":"Manufacturing & Wholesale Goods"
        }
    ],
    "sg:phone":"+1 317 257 1655",
    "sg:postcode":"46260",
    "sg:province":"IN",
    "sg:tags":[
        "equipment",
        "system",
        "automation"
    ],
    "wof:name":"Servo To Go Inc",
    "wof:placetype":"venue"
},
  "geometry": {"coordinates":[-86.176732,39.905489],"type":"Point"}
}