{
  "type": "Feature",
  "properties": {
    "iso:country":"US",
    "sg:address":"390 S Main St",
    "sg:city":"Zionsville",
    "sg:classifiers":[
        {
            "category":"Banks & Credit Unions",
            "subcategory":"Bank",
            "type":"Services"
        }
    ],
    "sg:phone":"+1 317 873 4455",
    "sg:postcode":"46077",
    "sg:province":"IN",
    "wof:name":"National City Bank",
    "wof:placetype":"venue"
},
  "geometry": {"coordinates":[-86.261121,39.948554],"type":"Point"}
}