{
  "type": "Feature",
  "properties": {
    "iso:country":"US",
    "sg:address":"6081 W 800 N",
    "sg:city":"Fountaintown",
    "sg:classifiers":[
        {
            "category":"Building & Trades",
            "subcategory":"Construction",
            "type":"Services"
        }
    ],
    "sg:phone":"+1 317 626 6301",
    "sg:postcode":"46130",
    "sg:province":"IN",
    "sg:tags":[
        "residential"
    ],
    "wof:name":"Arlis E Thompson",
    "wof:placetype":"venue"
},
  "geometry": {"coordinates":[-85.89775,39.639066],"type":"Point"}
}