{
  "type": "Feature",
  "properties": {
    "addr:full":"523 E National Ave Brazil IN 47834",
    "addr:housenumber":"523",
    "addr:postcode":"47834",
    "addr:street":"E National Ave",
    "iso:country":"US",
    "sg:address":"523 E National Ave",
    "sg:city":"Brazil",
    "sg:classifiers":[
        {
            "category":"Social Services",
            "type":"Services"
        }
    ],
    "sg:phone":"+1 812 446 2262",
    "sg:postcode":"47834",
    "sg:province":"IN",
    "sg:tags":[
        "organization",
        "welfare"
    ],
    "wof:name":"United Way",
    "wof:placetype":"venue"
},
  "geometry": {"coordinates":[-87.119579,39.524899],"type":"Point"}
}