{
  "type": "Feature",
  "properties": {
    "iso:country":"US",
    "sg:address":"2010 N Wayne St",
    "sg:city":"Angola",
    "sg:classifiers":[
        {
            "category":"Restaurant",
            "type":"Food & Drink"
        }
    ],
    "sg:menulink":"http://www.allmenus.com/in/angola/235932-mancinos-pizzas-and-grinders/menu/",
    "sg:phone":"+1 260 624 3399",
    "sg:postcode":"46703",
    "sg:province":"IN",
    "sg:tags":[
        "wrap",
        "american",
        "sandwich",
        "pizza"
    ],
    "wof:name":"Mancinos Pizzas and Grinders",
    "wof:placetype":"venue"
},
  "geometry": {"coordinates":[-84.999572,41.659729],"type":"Point"}
}