{
  "type": "Feature",
  "properties": {
    "addr:full":"1990 Hwy 337 NW Corydon IN 47112",
    "addr:housenumber":"1990",
    "addr:postcode":"47112",
    "addr:street":"Hwy 337 Nw",
    "iso:country":"US",
    "sg:address":"1990 Hwy 337 NW",
    "sg:city":"Corydon",
    "sg:classifiers":[
        {
            "category":"Health Services",
            "subcategory":"Chiropractor",
            "type":"Services"
        }
    ],
    "sg:phone":"+1 812 738 6003",
    "sg:postcode":"47112",
    "sg:province":"IN",
    "wof:name":"York Chiropractic Ctr",
    "wof:placetype":"venue"
},
  "geometry": {"coordinates":[-86.14069499999999,38.23184],"type":"Point"}
}