{
  "type": "Feature",
  "properties": {
    "iso:country":"US",
    "sg:address":"6557 W Sweet Creek Dr",
    "sg:city":"New Palestine",
    "sg:classifiers":[
        {
            "category":"Autos & Motor Vehicles",
            "subcategory":"Motorcycle Sales",
            "type":"Retail Goods"
        }
    ],
    "sg:phone":"+1 317 861 8478",
    "sg:postcode":"46163",
    "sg:province":"IN",
    "wof:name":"Sly Fox Mx Closeouts",
    "wof:placetype":"venue"
},
  "geometry": {"coordinates":[-85.92440499999999,39.720318],"type":"Point"}
}