{
  "type": "Feature",
  "properties": {
    "iso:country":"US",
    "sg:address":"12843 N Co Rd 50 W",
    "sg:city":"Batesville",
    "sg:classifiers":[
        {
            "category":"Building & Trades",
            "subcategory":"Construction",
            "type":"Services"
        }
    ],
    "sg:phone":"+1 812 934 2325",
    "sg:postcode":"47006",
    "sg:province":"IN",
    "sg:tags":[
        "general",
        "contractor"
    ],
    "wof:name":"Koehne Construction Inc",
    "wof:placetype":"venue"
},
  "geometry": {"coordinates":[-85.267846,39.250025],"type":"Point"}
}