{
  "type": "Feature",
  "properties": {
    "iso:country":"US",
    "sg:address":"972 S Prairiewood Dr",
    "sg:city":"Rochester",
    "sg:classifiers":[
        {
            "category":"Professional",
            "type":"Services"
        }
    ],
    "sg:phone":"+1 574 224 7852",
    "sg:postcode":"46975",
    "sg:province":"IN",
    "sg:tags":[
        "establishment"
    ],
    "wof:name":"RSC",
    "wof:placetype":"venue"
},
  "geometry": {"coordinates":[-86.255685,41.0687],"type":"Point"}
}