{
  "type": "Feature",
  "properties": {
    "iso:country":"US",
    "sg:address":"2650 Chaseway Ct",
    "sg:city":"Indianapolis",
    "sg:classifiers":[
        {
            "category":"Professional",
            "subcategory":"Business Services",
            "type":"Services"
        }
    ],
    "sg:phone":"+1 317 875 3821",
    "sg:postcode":"46268",
    "sg:province":"IN",
    "sg:tags":[
        "development",
        "plan"
    ],
    "wof:name":"Marketing Resource Partners Inc",
    "wof:placetype":"venue"
},
  "geometry": {"coordinates":[-86.207325,39.925864],"type":"Point"}
}