{
  "type": "Feature",
  "properties": {
    "iso:country":"US",
    "sg:address":"833 Main St",
    "sg:city":"Tell City",
    "sg:classifiers":[
        {
            "category":"Retail",
            "subcategory":"Portrait Studio",
            "type":"Services"
        }
    ],
    "sg:phone":"+1 812 547 6540",
    "sg:postcode":"47586",
    "sg:province":"IN",
    "sg:tags":[
        "photographer"
    ],
    "wof:name":"Debra's Studio-Photography",
    "wof:placetype":"venue"
},
  "geometry": {"coordinates":[-86.769853,37.953318],"type":"Point"}
}