{
  "type": "Feature",
  "properties": {
    "addr:full":"4325 Engle Rd Fort Wayne IN 46804",
    "addr:housenumber":"4325",
    "addr:postcode":"46804",
    "addr:street":"Engle Rd",
    "iso:country":"US",
    "sg:address":"4325 Engle Rd",
    "sg:city":"Fort Wayne",
    "sg:classifiers":[
        {
            "category":"Wholesale",
            "subcategory":"Groceries",
            "type":"Manufacturing & Wholesale Goods"
        }
    ],
    "sg:phone":"+1 260 459 6206",
    "sg:postcode":"46804",
    "sg:province":"IN",
    "sg:tags":[
        "pasta"
    ],
    "wof:name":"JND Co Inc",
    "wof:placetype":"venue"
},
  "geometry": {"coordinates":[-85.196516,41.045543],"type":"Point"}
}