{
  "type": "Feature",
  "properties": {
    "addr:full":"425 Lincoln Way E Mishawaka IN 46544",
    "addr:housenumber":"425",
    "addr:postcode":"46544",
    "addr:street":"Lincoln Way E",
    "iso:country":"US",
    "sg:address":"425 Lincoln Way E",
    "sg:city":"Mishawaka",
    "sg:classifiers":[
        {
            "category":"Insurance",
            "subcategory":"Insurance Agent",
            "type":"Services"
        }
    ],
    "sg:phone":"+1 574 256 6070",
    "sg:postcode":"46544",
    "sg:province":"IN",
    "sg:website":"www.tcuinsurance.com",
    "wof:name":"TCU Insurance",
    "wof:placetype":"venue"
},
  "geometry": {"coordinates":[-86.175481,41.661055],"type":"Point"}
}