{
  "type": "Feature",
  "properties": {
    "iso:country":"US",
    "sg:address":"610 Jay Dee St",
    "sg:city":"Elkhart",
    "sg:classifiers":[
        {
            "category":"Wholesale",
            "subcategory":"Hardware",
            "type":"Manufacturing & Wholesale Goods"
        }
    ],
    "sg:phone":"+1 574 294 7113",
    "sg:postcode":"46514",
    "sg:province":"IN",
    "sg:tags":[
        "builder"
    ],
    "wof:name":"Builders Enterprise Corp",
    "wof:placetype":"venue"
},
  "geometry": {"coordinates":[-86.019581,41.686752],"type":"Point"}
}