{
  "type": "Feature",
  "properties": {
    "iso:country":"US",
    "sg:address":"1703 Miller Ave",
    "sg:city":"Shelbyville",
    "sg:classifiers":[
        {
            "category":"Organizations",
            "subcategory":"Religious Organization",
            "type":"Services"
        }
    ],
    "sg:phone":"+1 317 392 1181",
    "sg:postcode":"46176",
    "sg:province":"IN",
    "sg:tags":[
        "church"
    ],
    "wof:name":"Shelbyville Baptist Temple",
    "wof:placetype":"venue"
},
  "geometry": {"coordinates":[-85.795608,39.510302],"type":"Point"}
}