{
  "type": "Feature",
  "properties": {
    "addr:full":"820 Joliet St Dyer IN 46311",
    "addr:housenumber":"820",
    "addr:postcode":"46311",
    "addr:street":"Joliet St",
    "iso:country":"US",
    "sg:address":"820 Joliet St",
    "sg:city":"Dyer",
    "sg:classifiers":[
        {
            "category":"Banks & Credit Unions",
            "subcategory":"Bank",
            "type":"Services"
        }
    ],
    "sg:phone":"+1 219 865 1001",
    "sg:postcode":"46311",
    "sg:province":"IN",
    "wof:name":"Bank Calumet",
    "wof:placetype":"venue"
},
  "geometry": {"coordinates":[-87.50778099999999,41.492749],"type":"Point"}
}