{
  "type": "Feature",
  "properties": {
    "addr:full":"396 S Indiana St Mooresville IN 46158",
    "addr:housenumber":"396",
    "addr:postcode":"46158",
    "addr:street":"S Indiana St",
    "iso:country":"US",
    "sg:address":"396 S Indiana St",
    "sg:city":"Mooresville",
    "sg:classifiers":[
        {
            "category":"Shopping",
            "subcategory":"Florist",
            "type":"Retail Goods"
        }
    ],
    "sg:phone":"+1 317 831 3333",
    "sg:postcode":"46158",
    "sg:province":"IN",
    "wof:name":"Bud & Bloom Florist",
    "wof:placetype":"venue"
},
  "geometry": {"coordinates":[-86.374967,39.608571],"type":"Point"}
}