{
  "type": "Feature",
  "properties": {
    "iso:country":"US",
    "sg:address":"4243 Endsley Rd",
    "sg:city":"Richmond",
    "sg:classifiers":[
        {
            "category":"Recreation",
            "type":"Entertainment"
        }
    ],
    "sg:phone":"+1 765 962 8926",
    "sg:postcode":"47374",
    "sg:province":"IN",
    "sg:tags":[
        "pond",
        "fishing",
        "lake"
    ],
    "wof:name":"Elkhorn Lakes",
    "wof:placetype":"venue"
},
  "geometry": {"coordinates":[-84.957731,39.751204],"type":"Point"}
}