{
  "type": "Feature",
  "properties": {
    "iso:country":"US",
    "sg:address":"6458 Inke Rd",
    "sg:city":"Richmond",
    "sg:classifiers":[
        {
            "category":"Building & Trades",
            "subcategory":"Construction",
            "type":"Services"
        }
    ],
    "sg:phone":"+1 765 847 5007",
    "sg:postcode":"47374",
    "sg:province":"IN",
    "sg:tags":[
        "general",
        "contractor"
    ],
    "wof:name":"B & B Construction Of Richmond",
    "wof:placetype":"venue"
},
  "geometry": {"coordinates":[-84.813225,39.909243],"type":"Point"}
}