{
  "type": "Feature",
  "properties": {
    "iso:country":"US",
    "sg:address":"2520 Lanier Dr",
    "sg:city":"Madison",
    "sg:classifiers":[
        {
            "category":"Manufacturing",
            "subcategory":"Metals",
            "type":"Manufacturing & Wholesale Goods"
        }
    ],
    "sg:phone":"+1 812 273 2211",
    "sg:postcode":"47250",
    "sg:province":"IN",
    "sg:tags":[
        "plating"
    ],
    "wof:name":"Madison Plating Inc",
    "wof:placetype":"venue"
},
  "geometry": {"coordinates":[-85.416233,38.773063],"type":"Point"}
}