{
  "type": "Feature",
  "properties": {
    "iso:country":"US",
    "sg:address":"1008 N Wells St",
    "sg:city":"Fort Wayne",
    "sg:classifiers":[
        {
            "category":"Bars & Pubs",
            "type":"Food & Drink"
        }
    ],
    "sg:phone":"+1 260 423 2202",
    "sg:postcode":"46808",
    "sg:province":"IN",
    "wof:name":"Hide N Seek's Pub & Eatery",
    "wof:placetype":"venue"
},
  "geometry": {"coordinates":[-85.144408,41.083314],"type":"Point"}
}