{
  "type": "Feature",
  "properties": {
    "iso:country":"US",
    "sg:address":"5088 E Indiana Beach Rd",
    "sg:city":"Monticello",
    "sg:classifiers":[
        {
            "category":"Travel",
            "subcategory":"Hotels & Motels",
            "type":"Entertainment"
        }
    ],
    "sg:phone":"+1 574 583 3511",
    "sg:postcode":"47960",
    "sg:province":"IN",
    "sg:tags":[
        "operation"
    ],
    "wof:name":"Kearneys Bay Side Resort",
    "wof:placetype":"venue"
},
  "geometry": {"coordinates":[-86.77032,40.79136],"type":"Point"}
}