{
  "type": "Feature",
  "properties": {
    "iso:country":"US",
    "sg:address":"4449 E 225 S",
    "sg:city":"Winamac",
    "sg:classifiers":[
        {
            "category":"Farming",
            "subcategory":"Farm",
            "type":"Manufacturing & Wholesale Goods"
        }
    ],
    "sg:phone":"+1 574 946 6980",
    "sg:postcode":"46996",
    "sg:province":"IN",
    "sg:tags":[
        "crop",
        "general"
    ],
    "wof:name":"Tony Kasten",
    "wof:placetype":"venue"
},
  "geometry": {"coordinates":[-86.518982,41.022452],"type":"Point"}
}