{
  "type": "Feature",
  "properties": {
    "iso:country":"US",
    "sg:address":"8511 Oak Ave",
    "sg:city":"Gary",
    "sg:classifiers":[
        {
            "category":"Shopping",
            "type":"Retail Goods"
        }
    ],
    "sg:phone":"+1 219 938 8784",
    "sg:postcode":"46403",
    "sg:province":"IN",
    "sg:tags":[
        "art",
        "gallery",
        "dealer"
    ],
    "wof:name":"Studio UK USA",
    "wof:placetype":"venue"
},
  "geometry": {"coordinates":[-87.23469,41.620486],"type":"Point"}
}