{
  "type": "Feature",
  "properties": {
    "iso:country":"US",
    "sg:address":"252 E Park St",
    "sg:city":"Williams",
    "sg:classifiers":[
        {
            "category":"Building & Trades",
            "subcategory":"Landscaping Services",
            "type":"Services"
        }
    ],
    "sg:phone":"+1 812 388 6599",
    "sg:postcode":"47452",
    "sg:province":"IN",
    "sg:tags":[
        "tree"
    ],
    "wof:name":"Heartland Forestery LLC",
    "wof:placetype":"venue"
},
  "geometry": {"coordinates":[-86.450326,38.654867],"type":"Point"}
}