{
  "type": "Feature",
  "properties": {
    "iso:country":"US",
    "sg:address":"759 N 400 E",
    "sg:city":"Valparaiso",
    "sg:classifiers":[
        {
            "category":"Professional",
            "subcategory":"Business Services",
            "type":"Services"
        }
    ],
    "sg:phone":"+1 219 464 9214",
    "sg:postcode":"46383",
    "sg:province":"IN",
    "wof:name":"Analyze Service & Performance",
    "wof:placetype":"venue"
},
  "geometry": {"coordinates":[-86.985582,41.5404],"type":"Point"}
}