{
  "type": "Feature",
  "properties": {
    "iso:country":"US",
    "sg:address":"118 E Wiley Ave",
    "sg:city":"Bluffton",
    "sg:classifiers":[
        {
            "category":"Building & Trades",
            "subcategory":"Construction",
            "type":"Services"
        }
    ],
    "sg:phone":"+1 260 824 1244",
    "sg:postcode":"46714",
    "sg:province":"IN",
    "sg:tags":[
        "repairing",
        "remodeling",
        "contractor"
    ],
    "wof:name":"Sands Construction Co",
    "wof:placetype":"venue"
},
  "geometry": {"coordinates":[-85.171262,40.734289],"type":"Point"}
}