{
  "type": "Feature",
  "properties": {
    "iso:country":"US",
    "sg:address":"8215 S Fairfax Rd",
    "sg:city":"Bloomington",
    "sg:classifiers":[
        {
            "category":"Building & Trades",
            "subcategory":"Cleaning & Sanitation",
            "type":"Services"
        }
    ],
    "sg:phone":"+1 812 824 7550",
    "sg:postcode":"47401",
    "sg:province":"IN",
    "sg:tags":[
        "janitor"
    ],
    "wof:name":"Dust Busters Inc",
    "wof:placetype":"venue"
},
  "geometry": {"coordinates":[-86.49195,39.048648],"type":"Point"}
}