{
  "type": "Feature",
  "properties": {
    "iso:country":"US",
    "sg:address":"14100 Old State Rd 37",
    "sg:city":"Tell City",
    "sg:classifiers":[
        {
            "category":"Organizations",
            "subcategory":"Non-profit Organization",
            "type":"Services"
        }
    ],
    "sg:phone":"+1 812 836 2020",
    "sg:postcode":"47586",
    "sg:province":"IN",
    "wof:name":"And-Tro Inc",
    "wof:placetype":"venue"
},
  "geometry": {"coordinates":[-86.649051,38.048098],"type":"Point"}
}