{
  "type": "Feature",
  "properties": {
    "addr:full":"7168 E 86th St Indianapolis IN 46250",
    "addr:housenumber":"7168",
    "addr:postcode":"46250",
    "addr:street":"E 86Th St",
    "iso:country":"US",
    "sg:address":"7168 E 86th St",
    "sg:city":"Indianapolis",
    "sg:classifiers":[
        {
            "category":"Social Services",
            "subcategory":"Job Training",
            "type":"Services"
        }
    ],
    "sg:phone":"+1 317 578 0556",
    "sg:postcode":"46250",
    "sg:province":"IN",
    "sg:tags":[
        "rehabilitation"
    ],
    "wof:name":"Rehab Associates",
    "wof:placetype":"venue"
},
  "geometry": {"coordinates":[-86.040905,39.912588],"type":"Point"}
}