{
  "type": "Feature",
  "properties": {
    "iso:country":"US",
    "sg:address":"250 Gostlin St",
    "sg:city":"Hammond",
    "sg:classifiers":[
        {
            "category":"Bars & Pubs",
            "type":"Food & Drink"
        }
    ],
    "sg:phone":"+1 219 933 9418",
    "sg:postcode":"46327",
    "sg:province":"IN",
    "wof:name":"Don's Pub",
    "wof:placetype":"venue"
},
  "geometry": {"coordinates":[-87.518464,41.632135],"type":"Point"}
}