{
  "type": "Feature",
  "properties": {
    "addr:full":"1314 W Mishawaka Ave South Bend IN 46615",
    "addr:housenumber":"1314",
    "addr:postcode":"46615",
    "addr:street":"W Mishawaka Ave",
    "iso:country":"US",
    "sg:address":"1314 W Mishawaka Ave",
    "sg:city":"South Bend",
    "sg:classifiers":[
        {
            "category":"Manufacturing",
            "subcategory":"Tools & Machinery",
            "type":"Manufacturing & Wholesale Goods"
        }
    ],
    "sg:phone":"+1 574 234 1497",
    "sg:postcode":"46615",
    "sg:province":"IN",
    "sg:tags":[
        "equipment",
        "dental",
        "supply"
    ],
    "wof:name":"Crown Art Dental Lab Inc",
    "wof:placetype":"venue"
},
  "geometry": {"coordinates":[-86.230158,41.665773],"type":"Point"}
}