{
  "type": "Feature",
  "properties": {
    "iso:country":"US",
    "sg:address":"14439 N 100 W",
    "sg:city":"Macy",
    "sg:classifiers":[
        {
            "category":"Farming",
            "subcategory":"Farm",
            "type":"Manufacturing & Wholesale Goods"
        }
    ],
    "sg:phone":"+1 574 382 3018",
    "sg:postcode":"46951",
    "sg:province":"IN",
    "wof:name":"Eckrote Farms Inc",
    "wof:placetype":"venue"
},
  "geometry": {"coordinates":[-86.096013,40.983037],"type":"Point"}
}