{
  "type": "Feature",
  "properties": {
    "addr:full":"740 Memory Ln Hobart IN 46342",
    "addr:housenumber":"740",
    "addr:postcode":"46342",
    "addr:street":"Memory Ln",
    "iso:country":"US",
    "sg:address":"740 Memory Ln",
    "sg:city":"Hobart",
    "sg:classifiers":[
        {
            "category":"Organizations",
            "subcategory":"Religious Organization",
            "type":"Services"
        }
    ],
    "sg:phone":"+1 219 942 2227",
    "sg:postcode":"46342",
    "sg:province":"IN",
    "wof:name":"Community Christian Church",
    "wof:placetype":"venue"
},
  "geometry": {"coordinates":[-87.248319,41.525646],"type":"Point"}
}