{
  "type": "Feature",
  "properties": {
    "iso:country":"US",
    "sg:address":"1333 W Lusher Ave",
    "sg:city":"Elkhart",
    "sg:classifiers":[
        {
            "category":"Social Services",
            "subcategory":"Job Training",
            "type":"Services"
        }
    ],
    "sg:phone":"+1 574 293 1818",
    "sg:postcode":"46517",
    "sg:province":"IN",
    "sg:tags":[
        "employment"
    ],
    "sg:website":"www.goodwill-ni.org",
    "wof:name":"Goodwill Industries",
    "wof:placetype":"venue"
},
  "geometry": {"coordinates":[-85.987407,41.66685],"type":"Point"}
}