{
  "type": "Feature",
  "properties": {
    "addr:full":"5773 Hornbill Pl Carmel IN 46033",
    "addr:housenumber":"5773",
    "addr:postcode":"46033",
    "addr:street":"Hornbill Pl",
    "iso:country":"US",
    "sg:address":"5773 Hornbill Pl",
    "sg:city":"Carmel",
    "sg:classifiers":[
        {
            "category":"Taxi",
            "type":"Transportation"
        }
    ],
    "sg:phone":"+1 317 227 9000",
    "sg:postcode":"46033",
    "sg:province":"IN",
    "wof:name":"Indy Food Taxi",
    "wof:placetype":"venue"
},
  "geometry": {"coordinates":[-86.08032900000001,39.985062],"type":"Point"}
}