{
  "type": "Feature",
  "properties": {
    "iso:country":"US",
    "sg:address":"6909 Grape Rd",
    "sg:city":"Mishawaka",
    "sg:classifiers":[
        {
            "category":"Insurance",
            "subcategory":"Insurance Agent",
            "type":"Services"
        }
    ],
    "sg:phone":"+1 574 271 5200",
    "sg:postcode":"46545",
    "sg:province":"IN",
    "wof:name":"1ST Source Insurance",
    "wof:placetype":"venue"
},
  "geometry": {"coordinates":[-86.187862,41.721482],"type":"Point"}
}