{
  "type": "Feature",
  "properties": {
    "iso:country":"US",
    "sg:address":"125 E North St",
    "sg:city":"Kendallville",
    "sg:classifiers":[
        {
            "category":"Real Estate",
            "subcategory":"Real Estate Agent",
            "type":"Services"
        }
    ],
    "sg:phone":"+1 260 347 4206",
    "sg:postcode":"46755",
    "sg:province":"IN",
    "sg:website":"www.orizonrealestate.com",
    "wof:name":"Orizon Real Estate Inc",
    "wof:placetype":"venue"
},
  "geometry": {"coordinates":[-85.267208,41.452385],"type":"Point"}
}