{
  "type": "Feature",
  "properties": {
    "iso:country":"US",
    "sg:address":"1631 W McClain St",
    "sg:city":"Scottsburg",
    "sg:classifiers":[
        {
            "category":"Freight",
            "type":"Transportation"
        }
    ],
    "sg:phone":"+1 812 752 9879",
    "sg:postcode":"47170",
    "sg:province":"IN",
    "sg:tags":[
        "commercial",
        "storage",
        "special"
    ],
    "wof:name":"Roseland Storage",
    "wof:placetype":"venue"
},
  "geometry": {"coordinates":[-85.787372,38.685435],"type":"Point"}
}