{
  "type": "Feature",
  "properties": {
    "iso:country":"US",
    "sg:address":"706 E Lake St",
    "sg:city":"Knox",
    "sg:classifiers":[
        {
            "category":"Retail",
            "subcategory":"Laundry & Dry Cleaning",
            "type":"Services"
        }
    ],
    "sg:phone":"+1 574 772 5095",
    "sg:postcode":"46534",
    "sg:province":"IN",
    "sg:tags":[
        "cleaners",
        "rug",
        "carpet"
    ],
    "wof:name":"Kevin's Carpet Cleaning",
    "wof:placetype":"venue"
},
  "geometry": {"coordinates":[-86.61367,41.297374],"type":"Point"}
}