{
  "type": "Feature",
  "properties": {
    "iso:country":"US",
    "sg:address":"100 E National Ave",
    "sg:city":"Brazil",
    "sg:classifiers":[
        {
            "category":"Museum",
            "type":"Entertainment"
        }
    ],
    "sg:phone":"+1 812 446 4036",
    "sg:postcode":"47834",
    "sg:province":"IN",
    "wof:name":"Clay County Historical Society",
    "wof:placetype":"venue"
},
  "geometry": {"coordinates":[-87.126077,39.523438],"type":"Point"}
}