{
  "type": "Feature",
  "properties": {
    "iso:country":"US",
    "sg:address":"3270 State Rd 9",
    "sg:city":"Howe",
    "sg:classifiers":[
        {
            "category":"Autos & Motor Vehicles",
            "subcategory":"Automobile Sales",
            "type":"Retail Goods"
        }
    ],
    "sg:phone":"+1 260 463 5266",
    "sg:postcode":"46746",
    "sg:province":"IN",
    "sg:tags":[
        "car",
        "dealer"
    ],
    "wof:name":"WANA Auto Sales",
    "wof:placetype":"venue"
},
  "geometry": {"coordinates":[-85.425659,41.686894],"type":"Point"}
}