{
  "type": "Feature",
  "properties": {
    "iso:country":"US",
    "sg:address":"20847 Summit Rd",
    "sg:city":"Noblesville",
    "sg:classifiers":[
        {
            "category":"Wholesale",
            "subcategory":"Machinery & Supplies",
            "type":"Manufacturing & Wholesale Goods"
        }
    ],
    "sg:phone":"+1 317 546 7406",
    "sg:postcode":"46062",
    "sg:province":"IN",
    "sg:tags":[
        "industrial"
    ],
    "wof:name":"Hy-Tech Fastening",
    "wof:placetype":"venue"
},
  "geometry": {"coordinates":[-86.08320500000001,40.089933],"type":"Point"}
}