{
  "type": "Feature",
  "properties": {
    "iso:country":"US",
    "sg:address":"52 E Main St",
    "sg:city":"Rossville",
    "sg:classifiers":[
        {
            "category":"Retail",
            "subcategory":"Veterinary Services",
            "type":"Services"
        }
    ],
    "sg:phone":"+1 765 379 2226",
    "sg:postcode":"46065",
    "sg:province":"IN",
    "sg:tags":[
        "hospital",
        "animal"
    ],
    "wof:name":"Wayside Veterinary Clinic",
    "wof:placetype":"venue"
},
  "geometry": {"coordinates":[-86.593364,40.417019],"type":"Point"}
}