{
  "type": "Feature",
  "properties": {
    "iso:country":"US",
    "sg:address":"5373 E Fairbanks Ct",
    "sg:city":"Monticello",
    "sg:classifiers":[
        {
            "category":"Professional",
            "subcategory":"Management & Consulting",
            "type":"Services"
        }
    ],
    "sg:phone":"+1 574 583 4335",
    "sg:postcode":"47960",
    "sg:province":"IN",
    "sg:tags":[
        "business"
    ],
    "wof:name":"Randall R Mitchell Consultin",
    "wof:placetype":"venue"
},
  "geometry": {"coordinates":[-86.769945,40.782862],"type":"Point"}
}