{
  "type": "Feature",
  "properties": {
    "addr:full":"9783 N Co Rd 100 E Springport IN 47386",
    "addr:housenumber":"9783",
    "addr:postcode":"47386",
    "addr:street":"N Co Rd 100 E",
    "iso:country":"US",
    "sg:address":"9783 N Co Rd 100 E",
    "sg:city":"Springport",
    "sg:classifiers":[
        {
            "category":"Retail",
            "subcategory":"Auto Repair",
            "type":"Services"
        }
    ],
    "sg:phone":"+1 765 755 3336",
    "sg:postcode":"47386",
    "sg:province":"IN",
    "sg:tags":[
        "body"
    ],
    "wof:name":"Jims Mobile Home Service",
    "wof:placetype":"venue"
},
  "geometry": {"coordinates":[-85.36649,40.073289],"type":"Point"}
}