{
  "type": "Feature",
  "properties": {
    "iso:country":"US",
    "sg:address":"305 N 5th St",
    "sg:city":"Chandler",
    "sg:classifiers":[
        {
            "category":"Organizations",
            "subcategory":"Religious Organization",
            "type":"Services"
        }
    ],
    "sg:phone":"+1 812 925 6236",
    "sg:postcode":"47610",
    "sg:province":"IN",
    "sg:tags":[
        "clergy"
    ],
    "wof:name":"Robert Helms",
    "wof:placetype":"venue"
},
  "geometry": {"coordinates":[-87.360996,38.045139],"type":"Point"}
}