{
  "type": "Feature",
  "properties": {
    "iso:country":"US",
    "sg:address":"4502 E Michigan St",
    "sg:city":"Indianapolis",
    "sg:classifiers":[
        {
            "category":"Retail",
            "subcategory":"Auto Repair",
            "type":"Services"
        }
    ],
    "sg:phone":"+1 317 351 0571",
    "sg:postcode":"46201",
    "sg:province":"IN",
    "sg:tags":[
        "repairing",
        "automobile"
    ],
    "wof:name":"Buck's Automotive",
    "wof:placetype":"venue"
},
  "geometry": {"coordinates":[-86.091533,39.774884],"type":"Point"}
}