{
  "type": "Feature",
  "properties": {
    "iso:country":"US",
    "sg:address":"810 Coliseum Blvd E",
    "sg:city":"Fort Wayne",
    "sg:classifiers":[
        {
            "category":"Banks & Credit Unions",
            "subcategory":"Investment Brokerage",
            "type":"Services"
        }
    ],
    "sg:phone":"+1 260 481 5896",
    "sg:postcode":"46805",
    "sg:province":"IN",
    "sg:tags":[
        "advisory",
        "financial"
    ],
    "wof:name":"Diem Thomas Financial Svc",
    "wof:placetype":"venue"
},
  "geometry": {"coordinates":[-85.13525199999999,41.118252],"type":"Point"}
}