{
  "type": "Feature",
  "properties": {
    "iso:country":"US",
    "sg:address":"3905 Williamsburg Way",
    "sg:city":"Columbus",
    "sg:classifiers":[
        {
            "category":"Insurance",
            "subcategory":"Insurance Agent",
            "type":"Services"
        }
    ],
    "sg:phone":"+1 812 379 4924",
    "sg:postcode":"47203",
    "sg:province":"IN",
    "wof:name":"Jackson Insurance Svc",
    "wof:placetype":"venue"
},
  "geometry": {"coordinates":[-85.87695600000001,39.225343],"type":"Point"}
}