{
  "type": "Feature",
  "properties": {
    "addr:full":"5355 Boy Scout Rd Indianapolis IN 46226",
    "addr:housenumber":"5355",
    "addr:postcode":"46226",
    "addr:street":"Boy Scout Rd",
    "iso:country":"US",
    "sg:address":"5355 Boy Scout Rd",
    "sg:city":"Indianapolis",
    "sg:classifiers":[
        {
            "category":"Building & Trades",
            "subcategory":"Construction",
            "type":"Services"
        }
    ],
    "sg:phone":"+1 317 542 7777",
    "sg:postcode":"46226",
    "sg:province":"IN",
    "sg:tags":[
        "excavating",
        "contractor"
    ],
    "wof:name":"A Plus Excavating LLC",
    "wof:placetype":"venue"
},
  "geometry": {"coordinates":[-86.031997,39.852072],"type":"Point"}
}