{
  "type": "Feature",
  "properties": {
    "iso:country":"US",
    "sg:address":"6125 Rosslyn Ave",
    "sg:city":"Indianapolis",
    "sg:classifiers":[
        {
            "category":"Communications",
            "subcategory":"Film & Video Production",
            "type":"Services"
        }
    ],
    "sg:phone":"+1 317 251 3308",
    "sg:postcode":"46220",
    "sg:province":"IN",
    "sg:tags":[
        "motion"
    ],
    "wof:name":"John Pinella Production",
    "wof:placetype":"venue"
},
  "geometry": {"coordinates":[-86.13402000000001,39.866823],"type":"Point"}
}