{
  "type": "Feature",
  "properties": {
    "addr:full":"6222 E State Blvd Fort Wayne IN 46815",
    "addr:housenumber":"6222",
    "addr:postcode":"46815",
    "addr:street":"E State Blvd",
    "iso:country":"US",
    "sg:address":"6222 E State Blvd",
    "sg:city":"Fort Wayne",
    "sg:classifiers":[
        {
            "category":"Professional",
            "subcategory":"Accounting & Tax Preparation",
            "type":"Services"
        }
    ],
    "sg:phone":"+1 260 493 0410",
    "sg:postcode":"46815",
    "sg:province":"IN",
    "sg:tags":[
        "return",
        "filing"
    ],
    "wof:name":"H & R Block Tax Svc",
    "wof:placetype":"venue"
},
  "geometry": {"coordinates":[-85.06471500000001,41.098939],"type":"Point"}
}