{
  "type": "Feature",
  "properties": {
    "iso:country":"US",
    "sg:address":"4165 N Emerson Ave",
    "sg:city":"Indianapolis",
    "sg:classifiers":[
        {
            "category":"Organizations",
            "subcategory":"Religious Organization",
            "type":"Services"
        }
    ],
    "sg:phone":"+1 317 541 9072",
    "sg:postcode":"46226",
    "sg:province":"IN",
    "sg:tags":[
        "church"
    ],
    "wof:name":"Zion Baptist Church",
    "wof:placetype":"venue"
},
  "geometry": {"coordinates":[-86.083704,39.832563],"type":"Point"}
}