{
  "type": "Feature",
  "properties": {
    "iso:country":"US",
    "sg:address":"7121 Tulip Tree Trl",
    "sg:city":"Indianapolis",
    "sg:classifiers":[
        {
            "category":"Building & Trades",
            "subcategory":"Equipment Rental",
            "type":"Services"
        }
    ],
    "sg:phone":"+1 317 849 1961",
    "sg:postcode":"46256",
    "sg:province":"IN",
    "wof:name":"Up & Down Inc",
    "wof:placetype":"venue"
},
  "geometry": {"coordinates":[-86.024006,39.883739],"type":"Point"}
}