{
  "type": "Feature",
  "properties": {
    "iso:country":"US",
    "sg:address":"2040 Cornwall Ct",
    "sg:city":"South Bend",
    "sg:classifiers":[
        {
            "category":"Organizations",
            "subcategory":"Professional Association",
            "type":"Services"
        }
    ],
    "sg:phone":"+1 574 299 1181",
    "sg:postcode":"46614",
    "sg:province":"IN",
    "wof:name":"Somers Square East Home Owners",
    "wof:placetype":"venue"
},
  "geometry": {"coordinates":[-86.215993,41.610499],"type":"Point"}
}