{
  "type": "Feature",
  "properties": {
    "iso:country":"US",
    "sg:address":"104 W 3rd St",
    "sg:city":"Sheridan",
    "sg:classifiers":[
        {
            "category":"Retail",
            "subcategory":"Laundry & Dry Cleaning",
            "type":"Services"
        }
    ],
    "sg:phone":"+1 317 758 5810",
    "sg:postcode":"46069",
    "sg:province":"IN",
    "sg:tags":[
        "cleaners"
    ],
    "wof:name":"Steam Express",
    "wof:placetype":"venue"
},
  "geometry": {"coordinates":[-86.221766,40.136085],"type":"Point"}
}