{
  "type": "Feature",
  "properties": {
    "addr:full":"7032 Olcott Ave Hammond IN 46323",
    "addr:postcode":"7032;46323",
    "addr:street":"Olcott Ave",
    "iso:country":"US",
    "sg:address":"7032 Olcott Ave",
    "sg:city":"Hammond",
    "sg:classifiers":[
        {
            "category":"Professional",
            "subcategory":"Management & Consulting",
            "type":"Services"
        }
    ],
    "sg:phone":"+1 219 845 8053",
    "sg:postcode":"46323",
    "sg:province":"IN",
    "sg:tags":[
        "business"
    ],
    "wof:name":"Coxhead Consulting LLC",
    "wof:placetype":"venue"
},
  "geometry": {"coordinates":[-87.479741,41.585294],"type":"Point"}
}