{
  "type": "Feature",
  "properties": {
    "iso:country":"US",
    "sg:address":"210 E Water St",
    "sg:city":"Pendleton",
    "sg:classifiers":[
        {
            "category":"Health Services",
            "subcategory":"Optometrist",
            "type":"Services"
        }
    ],
    "sg:phone":"+1 765 778 7524",
    "sg:postcode":"46064",
    "sg:province":"IN",
    "wof:name":"Catheran A Crafton OD",
    "wof:placetype":"venue"
},
  "geometry": {"coordinates":[-85.744315,40.00375],"type":"Point"}
}