{
  "type": "Feature",
  "properties": {
    "iso:country":"US",
    "sg:address":"220 W Wayne St",
    "sg:city":"Kendallville",
    "sg:classifiers":[
        {
            "category":"Building & Trades",
            "subcategory":"Landscaping Services",
            "type":"Services"
        }
    ],
    "sg:phone":"+1 260 343 0054",
    "sg:postcode":"46755",
    "sg:province":"IN",
    "sg:tags":[
        "landscape"
    ],
    "wof:name":"Duke Landscaping & Beddings",
    "wof:placetype":"venue"
},
  "geometry": {"coordinates":[-85.268179,41.447194],"type":"Point"}
}