{
  "type": "Feature",
  "properties": {
    "iso:country":"US",
    "sg:address":"124 S Tuxedo Dr",
    "sg:city":"South Bend",
    "sg:classifiers":[
        {
            "category":"Wholesale",
            "subcategory":"Machinery & Supplies",
            "type":"Manufacturing & Wholesale Goods"
        }
    ],
    "sg:phone":"+1 574 287 8287",
    "sg:postcode":"46615",
    "sg:province":"IN",
    "sg:tags":[
        "cargo",
        "container",
        "freight"
    ],
    "wof:name":"System's Resource Group",
    "wof:placetype":"venue"
},
  "geometry": {"coordinates":[-86.21351,41.675741],"type":"Point"}
}