{
  "type": "Feature",
  "properties": {
    "iso:country":"US",
    "sg:address":"11262 S 100 E",
    "sg:city":"Battle Ground",
    "sg:classifiers":[
        {
            "category":"Retail",
            "subcategory":"Auto Repair",
            "type":"Services"
        }
    ],
    "sg:phone":"+1 765 563 3463",
    "sg:postcode":"47920",
    "sg:province":"IN",
    "sg:tags":[
        "wrecker"
    ],
    "wof:name":"Garry's Towing",
    "wof:placetype":"venue"
},
  "geometry": {"coordinates":[-86.849924,40.58413],"type":"Point"}
}