{
  "type": "Feature",
  "properties": {
    "iso:country":"US",
    "sg:address":"613 W Main St",
    "sg:city":"Greentown",
    "sg:classifiers":[
        {
            "category":"Autos & Motor Vehicles",
            "subcategory":"Automobile Sales",
            "type":"Retail Goods"
        }
    ],
    "sg:phone":"+1 765 628 3321",
    "sg:postcode":"46936",
    "sg:province":"IN",
    "sg:tags":[
        "car",
        "dealer"
    ],
    "sg:website":"www.bhiford.com",
    "wof:name":"Brad Howell Ford",
    "wof:placetype":"venue"
},
  "geometry": {"coordinates":[-85.973195,40.477851],"type":"Point"}
}