{
  "type": "Feature",
  "properties": {
    "iso:country":"US",
    "sg:address":"111 N 1st St",
    "sg:city":"Pierceton",
    "sg:classifiers":[
        {
            "category":"Banks & Credit Unions",
            "subcategory":"Bank",
            "type":"Services"
        }
    ],
    "sg:phone":"+1 574 594 2122",
    "sg:postcode":"46562",
    "sg:province":"IN",
    "wof:name":"National City Bank",
    "wof:placetype":"venue"
},
  "geometry": {"coordinates":[-85.705326,41.199946],"type":"Point"}
}