{
  "type": "Feature",
  "properties": {
    "iso:country":"US",
    "sg:address":"210 Main St",
    "sg:city":"Colfax",
    "sg:classifiers":[
        {
            "category":"Government",
            "subcategory":"Office",
            "type":"Public Place"
        }
    ],
    "sg:phone":"+1 765 324 2777",
    "sg:postcode":"46035",
    "sg:province":"IN",
    "sg:tags":[
        "village"
    ],
    "wof:name":"Colfax Town Marshall",
    "wof:placetype":"venue"
},
  "geometry": {"coordinates":[-86.668376,40.193083],"type":"Point"}
}