{
  "type": "Feature",
  "properties": {
    "iso:country":"US",
    "sg:address":"3127 W Washington St",
    "sg:city":"Indianapolis",
    "sg:classifiers":[
        {
            "category":"Restaurant",
            "type":"Food & Drink"
        }
    ],
    "sg:phone":"+1 317 631 7796",
    "sg:postcode":"46222",
    "sg:province":"IN",
    "wof:name":"Hardee's",
    "wof:placetype":"venue"
},
  "geometry": {"coordinates":[-86.21211099999999,39.764627],"type":"Point"}
}