{
  "type": "Feature",
  "properties": {
    "iso:country":"US",
    "sg:address":"512 Hornung Hills Dr",
    "sg:city":"New Albany",
    "sg:classifiers":[
        {
            "category":"Professional",
            "subcategory":"Business Services",
            "type":"Services"
        }
    ],
    "sg:phone":"+1 502 319 0709",
    "sg:postcode":"47150",
    "sg:province":"IN",
    "wof:name":"Barnes Computer Solutions",
    "wof:placetype":"venue"
},
  "geometry": {"coordinates":[-85.826347,38.303093],"type":"Point"}
}