{
  "type": "Feature",
  "properties": {
    "addr:full":"1251 W Kem Rd Marion IN 46952",
    "addr:housenumber":"1251",
    "addr:postcode":"46952",
    "addr:street":"W Kem Rd",
    "iso:country":"US",
    "sg:address":"1251 W Kem Rd",
    "sg:city":"Marion",
    "sg:classifiers":[
        {
            "category":"Health Services",
            "subcategory":"Doctor",
            "type":"Services"
        }
    ],
    "sg:phone":"+1 765 662 7906",
    "sg:postcode":"46952",
    "sg:province":"IN",
    "sg:tags":[
        "dentist"
    ],
    "wof:name":"Endodontic Associates Inc",
    "wof:placetype":"venue"
},
  "geometry": {"coordinates":[-85.67421899999999,40.574425],"type":"Point"}
}