{
  "type": "Feature",
  "properties": {
    "addr:full":"3801 N 1st Ave Evansville IN 47710",
    "addr:housenumber":"3801",
    "addr:postcode":"47710",
    "addr:street":"N 1St Ave",
    "iso:country":"US",
    "sg:address":"3801 N 1st Ave",
    "sg:city":"Evansville",
    "sg:classifiers":[
        {
            "category":"Real Estate",
            "subcategory":"Real Estate Agent",
            "type":"Services"
        }
    ],
    "sg:phone":"+1 812 428 2323",
    "sg:postcode":"47710",
    "sg:province":"IN",
    "sg:tags":[
        "appraiser"
    ],
    "wof:name":"Riddle & Co",
    "wof:placetype":"venue"
},
  "geometry": {"coordinates":[-87.57414199999999,38.014185],"type":"Point"}
}