{
  "type": "Feature",
  "properties": {
    "addr:full":"5696 E 100 N Portland IN 47371",
    "addr:housenumber":"5696",
    "addr:postcode":"47371",
    "addr:street":"E 100 N",
    "iso:country":"US",
    "sg:address":"5696 E 100 N",
    "sg:city":"Portland",
    "sg:classifiers":[
        {
            "category":"Real Estate",
            "subcategory":"Real Estate Operator",
            "type":"Services"
        }
    ],
    "sg:phone":"+1 260 726 4176",
    "sg:postcode":"47371",
    "sg:province":"IN",
    "sg:tags":[
        "property",
        "lessor"
    ],
    "wof:name":"Earl Shauver",
    "wof:placetype":"venue"
},
  "geometry": {"coordinates":[-84.869719,40.455177],"type":"Point"}
}