{
  "type": "Feature",
  "properties": {
    "iso:country":"US",
    "sg:address":"5810 Lee Rd",
    "sg:city":"Indianapolis",
    "sg:classifiers":[
        {
            "category":"Professional",
            "type":"Services"
        }
    ],
    "sg:phone":"+1 317 549 3708",
    "sg:postcode":"46216",
    "sg:province":"IN",
    "sg:tags":[
        "establishment"
    ],
    "wof:name":"Sheehan",
    "wof:placetype":"venue"
},
  "geometry": {"coordinates":[-86.000936,39.860482],"type":"Point"}
}