{
  "type": "Feature",
  "properties": {
    "addr:full":"616 Station Dr Carmel IN 46032",
    "addr:housenumber":"616",
    "addr:postcode":"46032",
    "addr:street":"Station Dr",
    "iso:country":"US",
    "sg:address":"616 Station Dr",
    "sg:city":"Carmel",
    "sg:classifiers":[
        {
            "category":"Manufacturing",
            "subcategory":"Signs",
            "type":"Manufacturing & Wholesale Goods"
        }
    ],
    "sg:phone":"+1 317 575 1805",
    "sg:postcode":"46032",
    "sg:province":"IN",
    "wof:name":"Ad-Point",
    "wof:placetype":"venue"
},
  "geometry": {"coordinates":[-86.11763999999999,39.960697],"type":"Point"}
}