{
  "type": "Feature",
  "properties": {
    "iso:country":"US",
    "sg:address":"10570 N Michigan Rd",
    "sg:city":"Carmel",
    "sg:classifiers":[
        {
            "category":"Banks & Credit Unions",
            "subcategory":"Bank",
            "type":"Services"
        }
    ],
    "sg:phone":"+1 317 876 0570",
    "sg:postcode":"46032",
    "sg:province":"IN",
    "wof:name":"National City Bank",
    "wof:placetype":"venue"
},
  "geometry": {"coordinates":[-86.236575,39.94014],"type":"Point"}
}