{
  "type": "Feature",
  "properties": {
    "iso:country":"US",
    "sg:address":"115 E Michigan St",
    "sg:city":"Indianapolis",
    "sg:classifiers":[
        {
            "category":"Wholesale",
            "subcategory":"Computers",
            "type":"Manufacturing & Wholesale Goods"
        },
        {
            "category":"Professional",
            "subcategory":"Computer Services",
            "type":"Services"
        }
    ],
    "sg:phone":"+1 317 974 3000",
    "sg:postcode":"46204",
    "sg:province":"IN",
    "sg:tags":[
        "repair",
        "internet",
        "cd-rom",
        "isp",
        "provider",
        "equipment",
        "equipment-service",
        "software"
    ],
    "wof:name":"Association Computer Services Inc.",
    "wof:placetype":"venue"
},
  "geometry": {"coordinates":[-86.155286,39.774047],"type":"Point"}
}