{
  "type": "Feature",
  "properties": {
    "iso:country":"US",
    "sg:address":"7473 N 600 W",
    "sg:city":"Huntington",
    "sg:classifiers":[
        {
            "category":"Building & Trades",
            "subcategory":"Landscaping Services",
            "type":"Services"
        }
    ],
    "sg:phone":"+1 260 344 3043",
    "sg:postcode":"46750",
    "sg:province":"IN",
    "wof:name":"Brodbecks Lawn Care",
    "wof:placetype":"venue"
},
  "geometry": {"coordinates":[-85.565635,40.93805],"type":"Point"}
}