{
  "type": "Feature",
  "properties": {
    "iso:country":"US",
    "sg:address":"27706 Legion Rd",
    "sg:city":"Sunman",
    "sg:classifiers":[
        {
            "category":"Farming",
            "subcategory":"Livestock Farm",
            "type":"Manufacturing & Wholesale Goods"
        }
    ],
    "sg:phone":"+1 812 623 2175",
    "sg:postcode":"47041",
    "sg:province":"IN",
    "sg:tags":[
        "specialty",
        "animal"
    ],
    "wof:name":"Werner Lonnie & Shirley",
    "wof:placetype":"venue"
},
  "geometry": {"coordinates":[-85.011907,39.273111],"type":"Point"}
}