{
  "type": "Feature",
  "properties": {
    "iso:country":"US",
    "sg:address":"8128 Oakwood Ave",
    "sg:city":"Munster",
    "sg:classifiers":[
        {
            "category":"Health Services",
            "subcategory":"Clinic",
            "type":"Services"
        }
    ],
    "sg:phone":"+1 219 838 2651",
    "sg:postcode":"46321",
    "sg:province":"IN",
    "wof:name":"Alternative Wellness",
    "wof:placetype":"venue"
},
  "geometry": {"coordinates":[-87.487654,41.563405],"type":"Point"}
}