{
  "type": "Feature",
  "properties": {
    "iso:country":"US",
    "sg:address":"1131 E Maryland St",
    "sg:city":"Evansville",
    "sg:classifiers":[
        {
            "category":"Manufacturing",
            "subcategory":"Tools & Machinery",
            "type":"Manufacturing & Wholesale Goods"
        }
    ],
    "sg:phone":"+1 812 423 6866",
    "sg:postcode":"47711",
    "sg:province":"IN",
    "sg:tags":[
        "die",
        "cutting"
    ],
    "wof:name":"Exacta Cut",
    "wof:placetype":"venue"
},
  "geometry": {"coordinates":[-87.54453,37.985557],"type":"Point"}
}