{
  "type": "Feature",
  "properties": {
    "addr:full":"3847 W Washington St Indianapolis IN 46241",
    "addr:housenumber":"3847",
    "addr:postcode":"46241",
    "addr:street":"W Washington St",
    "iso:country":"US",
    "sg:address":"3847 W Washington St",
    "sg:city":"Indianapolis",
    "sg:classifiers":[
        {
            "category":"Restaurant",
            "type":"Food & Drink"
        }
    ],
    "sg:menulink":"http://www.allmenus.com/in/speedway/200333-long-john-silvers/menu/",
    "sg:phone":"+1 317 248 9000",
    "sg:postcode":"46241",
    "sg:province":"IN",
    "sg:tags":[
        "seafood",
        "american"
    ],
    "wof:name":"Long John Silver's",
    "wof:placetype":"venue"
},
  "geometry": {"coordinates":[-86.22727500000001,39.75944],"type":"Point"}
}