{
  "type": "Feature",
  "properties": {
    "iso:country":"US",
    "sg:address":"9245 N Meridian St",
    "sg:city":"Indianapolis",
    "sg:classifiers":[
        {
            "category":"Insurance",
            "subcategory":"Hazard Insurance",
            "type":"Services"
        },
        {
            "category":"Insurance",
            "subcategory":"Insurance Agent",
            "type":"Services"
        },
        {
            "category":"Insurance",
            "subcategory":"Life Insurance",
            "type":"Services"
        },
        {
            "category":"Insurance",
            "subcategory":"Title Insurance",
            "type":"Services"
        }
    ],
    "sg:phone":"+1 317 708 6171",
    "sg:postcode":"46260",
    "sg:province":"IN",
    "sg:tags":[
        "auto",
        "homeowner"
    ],
    "sg:website":"http://statefarm.mqgroup.com/url.asp?usr=143738",
    "wof:name":"David B Gilmore Ins Agcy Inc - State Farm Insurance Agent",
    "wof:placetype":"venue"
},
  "geometry": {"coordinates":[-86.15763099999999,39.921249],"type":"Point"}
}