{
  "type": "Feature",
  "properties": {
    "iso:country":"US",
    "sg:address":"5038 Saint Charles Pl",
    "sg:city":"Carmel",
    "sg:classifiers":[
        {
            "category":"Professional",
            "subcategory":"Management & Consulting",
            "type":"Services"
        }
    ],
    "sg:phone":"+1 317 575 8728",
    "sg:postcode":"46033",
    "sg:province":"IN",
    "sg:tags":[
        "consultant",
        "business"
    ],
    "wof:name":"Tamcor International",
    "wof:placetype":"venue"
},
  "geometry": {"coordinates":[-86.08410000000001,39.945528],"type":"Point"}
}