{
  "type": "Feature",
  "properties": {
    "iso:country":"US",
    "sg:address":"2705 S State Rd 1",
    "sg:city":"Bluffton",
    "sg:classifiers":[
        {
            "category":"Retail",
            "subcategory":"Auto Repair",
            "type":"Services"
        }
    ],
    "sg:phone":"+1 260 824 9815",
    "sg:postcode":"46714",
    "sg:province":"IN",
    "sg:tags":[
        "truck"
    ],
    "wof:name":"KIRK National Lease",
    "wof:placetype":"venue"
},
  "geometry": {"coordinates":[-85.16668,40.703416],"type":"Point"}
}