{
  "type": "Feature",
  "properties": {
    "iso:country":"US",
    "sg:address":"316 S Range Line Rd",
    "sg:city":"Carmel",
    "sg:classifiers":[
        {
            "category":"Banks & Credit Unions",
            "subcategory":"Bank",
            "type":"Services"
        }
    ],
    "sg:phone":"+1 317 575 8550",
    "sg:postcode":"46032",
    "sg:province":"IN",
    "sg:tags":[
        "loan",
        "real estate"
    ],
    "wof:name":"Prime Equity Mortgage Corp",
    "wof:placetype":"venue"
},
  "geometry": {"coordinates":[-86.127138,39.975445],"type":"Point"}
}