{
  "type": "Feature",
  "properties": {
    "addr:full":"1125 Country Place Dr Boonville IN 47601",
    "addr:housenumber":"1125",
    "addr:postcode":"47601",
    "addr:street":"Country Place Dr",
    "iso:country":"US",
    "sg:address":"1125 Country Place Dr",
    "sg:city":"Boonville",
    "sg:classifiers":[
        {
            "category":"Professional",
            "type":"Services"
        }
    ],
    "sg:phone":"+1 812 897 3987",
    "sg:postcode":"47601",
    "sg:province":"IN",
    "wof:name":"John Katter Asst Truck",
    "wof:placetype":"venue"
},
  "geometry": {"coordinates":[-87.26339299999999,38.037577],"type":"Point"}
}