{
  "type": "Feature",
  "properties": {
    "addr:full":"210 S Halleck St Demotte IN 46310",
    "addr:housenumber":"210",
    "addr:postcode":"46310",
    "addr:street":"S Halleck St",
    "iso:country":"US",
    "sg:address":"210 S Halleck St",
    "sg:city":"Demotte",
    "sg:classifiers":[
        {
            "category":"Banks & Credit Unions",
            "subcategory":"Financial Services",
            "type":"Services"
        }
    ],
    "sg:phone":"+1 219 987 4141",
    "sg:postcode":"46310",
    "sg:province":"IN",
    "sg:tags":[
        "company",
        "holding"
    ],
    "wof:name":"Demotte Bancorp",
    "wof:placetype":"venue"
},
  "geometry": {"coordinates":[-87.198819,41.201336],"type":"Point"}
}