{
  "type": "Feature",
  "properties": {
    "iso:country":"US",
    "sg:address":"5655 W State Rd 234",
    "sg:city":"Mc Cordsville",
    "sg:classifiers":[
        {
            "category":"Manufacturing",
            "subcategory":"Printing",
            "type":"Manufacturing & Wholesale Goods"
        }
    ],
    "sg:phone":"+1 317 466 1075",
    "sg:postcode":"46055",
    "sg:province":"IN",
    "sg:tags":[
        "commercial"
    ],
    "wof:name":"Bach Graphics Inc",
    "wof:placetype":"venue"
},
  "geometry": {"coordinates":[-85.91141,39.899032],"type":"Point"}
}