{
  "type": "Feature",
  "properties": {
    "addr:full":"3513 Shelby St Indianapolis IN 46227",
    "addr:housenumber":"3513",
    "addr:postcode":"46227",
    "addr:street":"Shelby St",
    "iso:country":"US",
    "sg:address":"3513 Shelby St",
    "sg:city":"Indianapolis",
    "sg:classifiers":[
        {
            "category":"Banks & Credit Unions",
            "subcategory":"Bureau De Change",
            "type":"Services"
        }
    ],
    "sg:phone":"+1 317 396 2674",
    "sg:postcode":"46227",
    "sg:province":"IN",
    "sg:tags":[
        "equipment",
        "imaging",
        "supply"
    ],
    "wof:name":"Tr Imaging Solutions",
    "wof:placetype":"venue"
},
  "geometry": {"coordinates":[-86.139448,39.71522],"type":"Point"}
}