{
  "type": "Feature",
  "properties": {
    "iso:country":"US",
    "sg:address":"407 W State Rd 47",
    "sg:city":"Lebanon",
    "sg:classifiers":[
        {
            "category":"Home & Garden",
            "subcategory":"Garden Supply",
            "type":"Retail Goods"
        }
    ],
    "sg:phone":"+1 765 485 3336",
    "sg:postcode":"46052",
    "sg:province":"IN",
    "sg:tags":[
        "center"
    ],
    "wof:name":"Corner Of Eden Garden Ctr",
    "wof:placetype":"venue"
},
  "geometry": {"coordinates":[-86.48133199999999,40.126215],"type":"Point"}
}