{
  "type": "Feature",
  "properties": {
    "iso:country":"US",
    "sg:address":"120 W Washington St",
    "sg:city":"Plymouth",
    "sg:classifiers":[
        {
            "category":"Health Services",
            "subcategory":"Doctor",
            "type":"Services"
        }
    ],
    "sg:phone":"+1 574 936 4557",
    "sg:postcode":"46563",
    "sg:province":"IN",
    "sg:tags":[
        "dentist"
    ],
    "wof:name":"Jeff Badell DDS",
    "wof:placetype":"venue"
},
  "geometry": {"coordinates":[-86.309496,41.3418],"type":"Point"}
}