{
  "type": "Feature",
  "properties": {
    "iso:country":"US",
    "sg:address":"1959 N Carver St",
    "sg:city":"Greensburg",
    "sg:classifiers":[
        {
            "category":"Shopping",
            "subcategory":"Gifts & Souvenirs",
            "type":"Retail Goods"
        }
    ],
    "sg:phone":"+1 812 663 9592",
    "sg:postcode":"47240",
    "sg:province":"IN",
    "wof:name":"Jackie Madden",
    "wof:placetype":"venue"
},
  "geometry": {"coordinates":[-85.49164399999999,39.355294],"type":"Point"}
}