{
  "type": "Feature",
  "properties": {
    "iso:country":"US",
    "sg:address":"7089 W 400 N",
    "sg:city":"Michigan City",
    "sg:classifiers":[
        {
            "category":"Education",
            "subcategory":"Library",
            "type":"Public Place"
        }
    ],
    "sg:phone":"+1 219 879 3272",
    "sg:postcode":"46360",
    "sg:province":"IN",
    "wof:name":"LA Porte County Public Library",
    "wof:placetype":"venue"
},
  "geometry": {"coordinates":[-86.843157,41.665753],"type":"Point"}
}