{
  "type": "Feature",
  "properties": {
    "iso:country":"US",
    "sg:address":"142 E US Hwy 52",
    "sg:city":"Rushville",
    "sg:classifiers":[
        {
            "category":"Organizations",
            "subcategory":"Religious Organization",
            "type":"Services"
        }
    ],
    "sg:phone":"+1 765 938 1556",
    "sg:postcode":"46173",
    "sg:province":"IN",
    "sg:tags":[
        "church"
    ],
    "wof:name":"United Methodist Dist Office",
    "wof:placetype":"venue"
},
  "geometry": {"coordinates":[-85.443708,39.602752],"type":"Point"}
}