{
  "type": "Feature",
  "properties": {
    "iso:country":"US",
    "sg:address":"211 State Hwy 212",
    "sg:city":"Michigan City",
    "sg:classifiers":[
        {
            "category":"Manufacturing",
            "subcategory":"Signs",
            "type":"Manufacturing & Wholesale Goods"
        }
    ],
    "sg:phone":"+1 219 874 2903",
    "sg:postcode":"46360",
    "sg:province":"IN",
    "wof:name":"Jerome Wozniak's City Signs",
    "wof:placetype":"venue"
},
  "geometry": {"coordinates":[-86.826234,41.740708],"type":"Point"}
}