{
  "type": "Feature",
  "properties": {
    "iso:country":"US",
    "sg:address":"7244 Josiah Ct",
    "sg:city":"Acton",
    "sg:classifiers":[
        {
            "category":"Professional",
            "subcategory":"Management & Consulting",
            "type":"Services"
        }
    ],
    "sg:phone":"+1 317 862 6100",
    "sg:postcode":"46259",
    "sg:province":"IN",
    "sg:tags":[
        "construction"
    ],
    "wof:name":"EKW Group Inc",
    "wof:placetype":"venue"
},
  "geometry": {"coordinates":[-86.039114,39.663338],"type":"Point"}
}