{
  "type": "Feature",
  "properties": {
    "addr:full":"2741 N Salisbury St West Lafayette IN 47906",
    "addr:housenumber":"2741",
    "addr:postcode":"47906",
    "addr:street":"N Salisbury St",
    "iso:country":"US",
    "sg:address":"2741 N Salisbury St",
    "sg:city":"West Lafayette",
    "sg:classifiers":[
        {
            "category":"Banks & Credit Unions",
            "subcategory":"Bank",
            "type":"Services"
        }
    ],
    "sg:phone":"+1 765 476 8239",
    "sg:postcode":"47906",
    "sg:province":"IN",
    "wof:name":"Regions",
    "wof:placetype":"venue"
},
  "geometry": {"coordinates":[-86.915721,40.457794],"type":"Point"}
}