{
  "type": "Feature",
  "properties": {
    "iso:country":"US",
    "sg:address":"632 S Lake St",
    "sg:city":"Gary",
    "sg:classifiers":[
        {
            "category":"Professional",
            "subcategory":"Research",
            "type":"Services"
        }
    ],
    "sg:phone":"+1 219 939 1240",
    "sg:postcode":"46403",
    "sg:province":"IN",
    "sg:tags":[
        "environmental",
        "ecological"
    ],
    "wof:name":"CHC Technologies Inc",
    "wof:placetype":"venue"
},
  "geometry": {"coordinates":[-87.267031,41.599306],"type":"Point"}
}