{
  "type": "Feature",
  "properties": {
    "iso:country":"US",
    "sg:address":"1109 N Gibson Ave",
    "sg:city":"Indianapolis",
    "sg:classifiers":[
        {
            "category":"Professional",
            "subcategory":"Business Services",
            "type":"Services"
        }
    ],
    "sg:phone":"+1 317 897 0050",
    "sg:postcode":"46219",
    "sg:province":"IN",
    "sg:tags":[
        "interior",
        "consultant",
        "design",
        "decorator"
    ],
    "wof:name":"Design East Inc",
    "wof:placetype":"venue"
},
  "geometry": {"coordinates":[-86.01637599999999,39.781963],"type":"Point"}
}