{
  "type": "Feature",
  "properties": {
    "addr:full":"4478 Pennsylvania St Gary IN 46409",
    "addr:housenumber":"4478",
    "addr:postcode":"46409",
    "addr:street":"Pennsylvania St Gary",
    "iso:country":"US",
    "sg:address":"4478 Pennsylvania St",
    "sg:city":"Gary",
    "sg:classifiers":[
        {
            "category":"Personal",
            "subcategory":"Beauty Salon",
            "type":"Services"
        }
    ],
    "sg:phone":"+1 219 980 0626",
    "sg:postcode":"46409",
    "sg:province":"IN",
    "wof:name":"Dee Cuttery",
    "wof:placetype":"venue"
},
  "geometry": {"coordinates":[-87.33259,41.537079],"type":"Point"}
}