{
  "type": "Feature",
  "properties": {
    "iso:country":"US",
    "sg:address":"5201 N Keystone Ave",
    "sg:city":"Indianapolis",
    "sg:classifiers":[
        {
            "category":"Autos & Motor Vehicles",
            "subcategory":"Fuel & Gas Station",
            "type":"Retail Goods"
        }
    ],
    "sg:phone":"+1 317 257 4269",
    "sg:postcode":"46220",
    "sg:province":"IN",
    "sg:tags":[
        "oil"
    ],
    "wof:name":"BP",
    "wof:placetype":"venue"
},
  "geometry": {"coordinates":[-86.12205299999999,39.849016],"type":"Point"}
}