{
  "type": "Feature",
  "properties": {
    "iso:country":"US",
    "sg:address":"4414 Smith St",
    "sg:city":"Fort Wayne",
    "sg:classifiers":[
        {
            "category":"Recreation",
            "type":"Entertainment"
        }
    ],
    "sg:phone":"+1 260 744 6174",
    "sg:postcode":"46806",
    "sg:province":"IN",
    "sg:tags":[
        "center"
    ],
    "wof:name":"Summit City Sports & Rec",
    "wof:placetype":"venue"
},
  "geometry": {"coordinates":[-85.121493,41.041936],"type":"Point"}
}