{
  "type": "Feature",
  "properties": {
    "iso:country":"US",
    "sg:address":"5909 S Jay St",
    "sg:city":"Marion",
    "sg:classifiers":[
        {
            "category":"Organizations",
            "subcategory":"Religious Organization",
            "type":"Services"
        }
    ],
    "sg:phone":"+1 765 674 1860",
    "sg:postcode":"46953",
    "sg:province":"IN",
    "sg:tags":[
        "church"
    ],
    "wof:name":"Lighthouse Assembly Of God",
    "wof:placetype":"venue"
},
  "geometry": {"coordinates":[-85.628691,40.495348],"type":"Point"}
}