{
  "type": "Feature",
  "properties": {
    "iso:country":"US",
    "sg:address":"222 N Co Rd 900 E",
    "sg:city":"Coatesville",
    "sg:classifiers":[
        {
            "category":"Retail",
            "subcategory":"Auto Repair",
            "type":"Services"
        }
    ],
    "sg:phone":"+1 765 386 2264",
    "sg:postcode":"46121",
    "sg:province":"IN",
    "sg:tags":[
        "muffler",
        "exhaust",
        "system"
    ],
    "wof:name":"Warren's Exhaust Svc",
    "wof:placetype":"venue"
},
  "geometry": {"coordinates":[-86.687364,39.665337],"type":"Point"}
}