{
  "type": "Feature",
  "properties": {
    "iso:country":"US",
    "sg:address":"20 N Meridian St",
    "sg:city":"Indianapolis",
    "sg:classifiers":[
        {
            "category":"Professional",
            "subcategory":"Lawyer & Legal Services",
            "type":"Services"
        }
    ],
    "sg:phone":"+1 317 636 7460",
    "sg:postcode":"46204",
    "sg:province":"IN",
    "sg:tags":[
        "attorney"
    ],
    "wof:name":"Lewis & Wilkins PC",
    "wof:placetype":"venue"
},
  "geometry": {"coordinates":[-86.158062,39.767955],"type":"Point"}
}