{
  "type": "Feature",
  "properties": {
    "iso:country":"US",
    "sg:address":"3641 N Briarwood Ln",
    "sg:city":"Muncie",
    "sg:classifiers":[
        {
            "category":"Banks & Credit Unions",
            "subcategory":"Investment Brokerage",
            "type":"Services"
        }
    ],
    "sg:phone":"+1 765 281 9444",
    "sg:postcode":"47304",
    "sg:province":"IN",
    "sg:tags":[
        "advisory",
        "financial"
    ],
    "wof:name":"Capital Select Invstmnt Corp",
    "wof:placetype":"venue"
},
  "geometry": {"coordinates":[-85.428383,40.220698],"type":"Point"}
}