{
  "type": "Feature",
  "properties": {
    "iso:country":"US",
    "sg:address":"114 W 30th St",
    "sg:city":"Connersville",
    "sg:classifiers":[
        {
            "category":"Home & Garden",
            "subcategory":"Building Materials",
            "type":"Retail Goods"
        }
    ],
    "sg:phone":"+1 765 825 4813",
    "sg:postcode":"47331",
    "sg:province":"IN",
    "sg:tags":[
        "paint"
    ],
    "wof:name":"Sherwin-Williams Paints",
    "wof:placetype":"venue"
},
  "geometry": {"coordinates":[-85.129552,39.671675],"type":"Point"}
}