{
  "type": "Feature",
  "properties": {
    "iso:country":"US",
    "sg:address":"2235 E Base Rd",
    "sg:city":"Greensburg",
    "sg:phone":"+1 812 663 6073",
    "sg:postcode":"47240",
    "sg:province":"IN",
    "sg:tags":[
        "real",
        "lessor",
        "farm",
        "corn",
        "soybean",
        "property"
    ],
    "wof:name":"Krieger John",
    "wof:placetype":"venue"
},
  "geometry": {"coordinates":[-85.439149,39.337283],"type":"Point"}
}