{
  "type": "Feature",
  "properties": {
    "addr:full":"208 W 18th St Rochester IN 46975",
    "addr:housenumber":"208",
    "addr:postcode":"46975",
    "addr:street":"W 18Th St",
    "iso:country":"US",
    "sg:address":"208 W 18th St",
    "sg:city":"Rochester",
    "sg:classifiers":[
        {
            "category":"Sports & Exercise",
            "subcategory":"Gym",
            "type":"Entertainment"
        }
    ],
    "sg:phone":"+1 574 223 8286",
    "sg:postcode":"46975",
    "sg:province":"IN",
    "sg:tags":[
        "club",
        "health",
        "studio",
        "gymnasium"
    ],
    "wof:name":"Curves For Women",
    "wof:placetype":"venue"
},
  "geometry": {"coordinates":[-86.218214,41.055133],"type":"Point"}
}