{
  "type": "Feature",
  "properties": {
    "iso:country":"US",
    "sg:address":"9683 N Co Rd 600 W",
    "sg:city":"Rossville",
    "sg:classifiers":[
        {
            "category":"Retail",
            "subcategory":"Auto Repair",
            "type":"Services"
        }
    ],
    "sg:phone":"+1 765 379 2387",
    "sg:postcode":"46065",
    "sg:province":"IN",
    "sg:tags":[
        "repairing",
        "automobile"
    ],
    "wof:name":"Car Tech",
    "wof:placetype":"venue"
},
  "geometry": {"coordinates":[-86.618347,40.428885],"type":"Point"}
}