{
  "type": "Feature",
  "properties": {
    "addr:full":"208 S Spring St Odon IN 47562",
    "addr:housenumber":"208",
    "addr:postcode":"47562",
    "addr:street":"S Spring St",
    "iso:country":"US",
    "sg:address":"208 S Spring St",
    "sg:city":"Odon",
    "sg:classifiers":[
        {
            "category":"Organizations",
            "subcategory":"Religious Organization",
            "type":"Services"
        }
    ],
    "sg:phone":"+1 812 636 7330",
    "sg:postcode":"47562",
    "sg:province":"IN",
    "sg:tags":[
        "church"
    ],
    "wof:name":"Christian Church",
    "wof:placetype":"venue"
},
  "geometry": {"coordinates":[-86.99133999999999,38.841889],"type":"Point"}
}