{
  "type": "Feature",
  "properties": {
    "iso:country":"US",
    "sg:address":"304 N Waldemere Ave",
    "sg:city":"Muncie",
    "sg:classifiers":[
        {
            "category":"Social Services",
            "type":"Services"
        }
    ],
    "sg:phone":"+1 765 282 3473",
    "sg:postcode":"47303",
    "sg:province":"IN",
    "sg:tags":[
        "youth",
        "organization",
        "center"
    ],
    "wof:name":"Fuegos Youth Ctr",
    "wof:placetype":"venue"
},
  "geometry": {"coordinates":[-85.349785,40.195727],"type":"Point"}
}