{
  "type": "Feature",
  "properties": {
    "iso:country":"US",
    "sg:address":"276 Main Cross St",
    "sg:city":"Charlestown",
    "sg:classifiers":[
        {
            "category":"Shopping",
            "subcategory":"Musical Instruments",
            "type":"Retail Goods"
        }
    ],
    "sg:phone":"+1 812 256 4257",
    "sg:postcode":"47111",
    "sg:province":"IN",
    "wof:name":"Copper Kettle",
    "wof:placetype":"venue"
},
  "geometry": {"coordinates":[-85.660916,38.44342],"type":"Point"}
}