{
  "type": "Feature",
  "properties": {
    "iso:country":"US",
    "sg:address":"4350 E Co Rd 700 N",
    "sg:city":"Frankfort",
    "sg:classifiers":[
        {
            "category":"Real Estate",
            "subcategory":"Real Estate Operator",
            "type":"Services"
        }
    ],
    "sg:phone":"+1 765 258 3263",
    "sg:postcode":"46041",
    "sg:province":"IN",
    "sg:tags":[
        "property",
        "lessor"
    ],
    "wof:name":"Max Crum",
    "wof:placetype":"venue"
},
  "geometry": {"coordinates":[-86.418548,40.387878],"type":"Point"}
}