{
  "type": "Feature",
  "properties": {
    "iso:country":"US",
    "sg:address":"500 S Main St",
    "sg:city":"Elkhart",
    "sg:classifiers":[
        {
            "category":"Organizations",
            "subcategory":"Non-profit Organization",
            "type":"Services"
        }
    ],
    "sg:phone":"+1 574 294 7531",
    "sg:postcode":"46516",
    "sg:province":"IN",
    "wof:name":"Mennonite Board Of Education",
    "wof:placetype":"venue"
},
  "geometry": {"coordinates":[-85.971401,41.683116],"type":"Point"}
}