{
  "type": "Feature",
  "properties": {
    "iso:country":"US",
    "sg:address":"236 Main St",
    "sg:city":"Hobart",
    "sg:classifiers":[
        {
            "category":"Bars & Pubs",
            "type":"Food & Drink"
        }
    ],
    "sg:phone":"+1 219 942 1396",
    "sg:postcode":"46342",
    "sg:province":"IN",
    "wof:name":"Rosie O Grady's Lounge",
    "wof:placetype":"venue"
},
  "geometry": {"coordinates":[-87.255126,41.532353],"type":"Point"}
}