{
  "type": "Feature",
  "properties": {
    "iso:country":"US",
    "sg:address":"100 E Main St",
    "sg:city":"Washington",
    "sg:classifiers":[
        {
            "category":"Bars & Pubs",
            "type":"Food & Drink"
        }
    ],
    "sg:phone":"+1 812 254 9987",
    "sg:postcode":"47501",
    "sg:province":"IN",
    "wof:name":"Antique Bar",
    "wof:placetype":"venue"
},
  "geometry": {"coordinates":[-87.174447,38.656929],"type":"Point"}
}