{
  "type": "Feature",
  "properties": {
    "iso:country":"US",
    "sg:address":"414 E Jefferson St",
    "sg:city":"Tipton",
    "sg:classifiers":[
        {
            "category":"Retail",
            "subcategory":"Car Wash",
            "type":"Services"
        }
    ],
    "sg:phone":"+1 765 675 8076",
    "sg:postcode":"46072",
    "sg:province":"IN",
    "sg:tags":[
        "polishing",
        "washing"
    ],
    "wof:name":"Diamond Car Wash Partners",
    "wof:placetype":"venue"
},
  "geometry": {"coordinates":[-86.03532300000001,40.282481],"type":"Point"}
}