{
  "type": "Feature",
  "properties": {
    "addr:full":"8198 US Hwy 40 Centerville IN 47330",
    "addr:housenumber":"8198",
    "addr:postcode":"47330",
    "addr:street":"Us Hwy 40",
    "iso:country":"US",
    "sg:address":"8198 US Hwy 40",
    "sg:city":"Centerville",
    "sg:classifiers":[
        {
            "category":"Building & Trades",
            "subcategory":"Construction",
            "type":"Services"
        }
    ],
    "sg:phone":"+1 765 855 3323",
    "sg:postcode":"47330",
    "sg:province":"IN",
    "sg:tags":[
        "grading",
        "contractor"
    ],
    "wof:name":"Wayne Cnty Highway Dept Garage",
    "wof:placetype":"venue"
},
  "geometry": {"coordinates":[-85.030964,39.816409],"type":"Point"}
}