{
  "type": "Feature",
  "properties": {
    "addr:full":"202 S Michigan St South Bend IN 46601",
    "addr:housenumber":"202",
    "addr:postcode":"46601",
    "addr:street":"S Michigan St",
    "iso:country":"US",
    "sg:address":"202 S Michigan St",
    "sg:city":"South Bend",
    "sg:classifiers":[
        {
            "category":"Professional",
            "type":"Services"
        }
    ],
    "sg:phone":"+1 574 289 4365",
    "sg:postcode":"46601",
    "sg:province":"IN",
    "sg:tags":[
        "establishment"
    ],
    "wof:name":"Robert Bradley Assoc LLC",
    "wof:placetype":"venue"
},
  "geometry": {"coordinates":[-86.250243,41.674387],"type":"Point"}
}