{
  "type": "Feature",
  "properties": {
    "iso:country":"US",
    "sg:address":"705 W Clinton St",
    "sg:city":"Frankfort",
    "sg:classifiers":[
        {
            "category":"Manufacturing",
            "subcategory":"Food",
            "type":"Manufacturing & Wholesale Goods"
        }
    ],
    "sg:phone":"+1 765 654 6712",
    "sg:postcode":"46041",
    "sg:province":"IN",
    "sg:tags":[
        "frozen",
        "dessert",
        "ice",
        "cream"
    ],
    "wof:name":"Glover's Ice Cream Inc",
    "wof:placetype":"venue"
},
  "geometry": {"coordinates":[-86.519782,40.28064],"type":"Point"}
}