{
  "type": "Feature",
  "properties": {
    "addr:full":"4820 E State Rd 64 Saint Anthony IN 47575",
    "addr:housenumber":"4820;64",
    "addr:postcode":"47575",
    "addr:street":"E State Rd",
    "iso:country":"US",
    "sg:address":"4820 E State Rd 64",
    "sg:city":"Saint Anthony",
    "sg:classifiers":[
        {
            "category":"Building & Trades",
            "subcategory":"Construction",
            "type":"Services"
        }
    ],
    "sg:phone":"+1 812 326 2984",
    "sg:postcode":"47575",
    "sg:province":"IN",
    "sg:tags":[
        "floor",
        "laying",
        "contractor"
    ],
    "wof:name":"Brian Blessinger",
    "wof:placetype":"venue"
},
  "geometry": {"coordinates":[-86.817213,38.303753],"type":"Point"}
}