{
  "type": "Feature",
  "properties": {
    "addr:full":"2807 Daniel Ct Bloomington IN 47401",
    "addr:housenumber":"2807",
    "addr:postcode":"47401",
    "addr:street":"Daniel Ct",
    "iso:country":"US",
    "sg:address":"2807 Daniel Ct",
    "sg:city":"Bloomington",
    "sg:classifiers":[
        {
            "category":"Health Services",
            "subcategory":"Health Practitioner",
            "type":"Services"
        }
    ],
    "sg:phone":"+1 812 336 3781",
    "sg:postcode":"47401",
    "sg:province":"IN",
    "wof:name":"Speech Works Inc",
    "wof:placetype":"venue"
},
  "geometry": {"coordinates":[-86.495895,39.136915],"type":"Point"}
}