{
  "type": "Feature",
  "properties": {
    "addr:full":"4969 Roxbury Ct Pittsboro IN 46167",
    "addr:housenumber":"4969",
    "addr:postcode":"46167",
    "addr:street":"Roxbury Ct",
    "iso:country":"US",
    "sg:address":"4969 Roxbury Ct",
    "sg:city":"Pittsboro",
    "sg:classifiers":[
        {
            "category":"Professional",
            "subcategory":"Computer Services",
            "type":"Services"
        }
    ],
    "sg:phone":"+1 317 892 4503",
    "sg:postcode":"46167",
    "sg:province":"IN",
    "sg:tags":[
        "datum"
    ],
    "wof:name":"Icecubetray",
    "wof:placetype":"venue"
},
  "geometry": {"coordinates":[-86.440825,39.84916],"type":"Point"}
}