{
  "type": "Feature",
  "properties": {
    "iso:country":"US",
    "sg:address":"238 S Meridian St",
    "sg:city":"Indianapolis",
    "sg:classifiers":[
        {
            "category":"Real Estate",
            "subcategory":"Developer",
            "type":"Services"
        }
    ],
    "sg:phone":"+1 317 635 8318",
    "sg:postcode":"46225",
    "sg:province":"IN",
    "sg:tags":[
        "vacancy",
        "rental",
        "listing"
    ],
    "wof:name":"Norle Investments Inc",
    "wof:placetype":"venue"
},
  "geometry": {"coordinates":[-86.158221,39.763362],"type":"Point"}
}