{
  "type": "Feature",
  "properties": {
    "iso:country":"US",
    "sg:address":"1402 W 32nd St",
    "sg:city":"Indianapolis",
    "sg:classifiers":[
        {
            "category":"Personal",
            "subcategory":"Beauty Salon",
            "type":"Services"
        }
    ],
    "sg:phone":"+1 317 920 9151",
    "sg:postcode":"46208",
    "sg:province":"IN",
    "wof:name":"Gina's Hair & Nails",
    "wof:placetype":"venue"
},
  "geometry": {"coordinates":[-86.189708,39.813013],"type":"Point"}
}