{
  "type": "Feature",
  "properties": {
    "iso:country":"US",
    "sg:address":"67 E Main St",
    "sg:city":"Mooresville",
    "sg:classifiers":[
        {
            "category":"Shopping",
            "type":"Retail Goods"
        }
    ],
    "sg:phone":"+1 317 831 8314",
    "sg:postcode":"46158",
    "sg:province":"IN",
    "sg:tags":[
        "merchandise"
    ],
    "wof:name":"Color Works",
    "wof:placetype":"venue"
},
  "geometry": {"coordinates":[-86.373674,39.612708],"type":"Point"}
}