{
  "type": "Feature",
  "properties": {
    "iso:country":"US",
    "sg:address":"2703 S Main St",
    "sg:city":"Elkhart",
    "sg:classifiers":[
        {
            "category":"Restaurant",
            "type":"Food & Drink"
        }
    ],
    "sg:phone":"+1 574 293 2117",
    "sg:postcode":"46517",
    "sg:province":"IN",
    "wof:name":"Hunter's Place",
    "wof:placetype":"venue"
},
  "geometry": {"coordinates":[-85.94708900000001,41.658556],"type":"Point"}
}