{
  "type": "Feature",
  "properties": {
    "iso:country":"US",
    "sg:address":"4407 N Fail Rd",
    "sg:city":"Laporte",
    "sg:classifiers":[
        {
            "category":"Wholesale",
            "subcategory":"Petroleum",
            "type":"Manufacturing & Wholesale Goods"
        }
    ],
    "sg:phone":"+1 219 778 8116",
    "sg:postcode":"46350",
    "sg:province":"IN",
    "sg:tags":[
        "pipe",
        "line",
        "company"
    ],
    "wof:name":"Vector Pipeline",
    "wof:placetype":"venue"
},
  "geometry": {"coordinates":[-86.680218,41.670227],"type":"Point"}
}