{
  "type": "Feature",
  "properties": {
    "iso:country":"US",
    "sg:address":"7636 S Mooresville Rd",
    "sg:city":"Indianapolis",
    "sg:classifiers":[
        {
            "category":"Government",
            "subcategory":"Post Office",
            "type":"Public Place"
        }
    ],
    "sg:phone":"+1 317 856 7036",
    "sg:postcode":"46113",
    "sg:province":"IN",
    "wof:name":"US Post Office",
    "wof:placetype":"venue"
},
  "geometry": {"coordinates":[-86.279397,39.65369],"type":"Point"}
}