{
  "type": "Feature",
  "properties": {
    "iso:country":"US",
    "sg:address":"122 N Franklin St",
    "sg:city":"Greensburg",
    "sg:classifiers":[
        {
            "category":"Insurance",
            "subcategory":"Insurance Agent",
            "type":"Services"
        }
    ],
    "sg:phone":"+1 812 663 4850",
    "sg:postcode":"47240",
    "sg:province":"IN",
    "wof:name":"Moeller Insurance Inc",
    "wof:placetype":"venue"
},
  "geometry": {"coordinates":[-85.482747,39.337449],"type":"Point"}
}