{
  "type": "Feature",
  "properties": {
    "iso:country":"US",
    "sg:address":"214 E Elm St",
    "sg:city":"New Albany",
    "sg:classifiers":[
        {
            "category":"Real Estate",
            "subcategory":"Real Estate Agent",
            "type":"Services"
        }
    ],
    "sg:phone":"+1 812 944 1500",
    "sg:postcode":"47150",
    "sg:province":"IN",
    "wof:name":"Elite Realty Group",
    "wof:placetype":"venue"
},
  "geometry": {"coordinates":[-85.821588,38.287668],"type":"Point"}
}