{
  "type": "Feature",
  "properties": {
    "iso:country":"US",
    "sg:address":"12737 Tealwood Dr",
    "sg:city":"Indianapolis",
    "sg:classifiers":[
        {
            "category":"Wholesale",
            "subcategory":"Office Equipment",
            "type":"Manufacturing & Wholesale Goods"
        }
    ],
    "sg:phone":"+1 317 826 7804",
    "sg:postcode":"46236",
    "sg:province":"IN",
    "sg:tags":[
        "dictating",
        "machine",
        "supply"
    ],
    "sg:website":"www.dictaphone.com",
    "wof:name":"Dictaphone Corp",
    "wof:placetype":"venue"
},
  "geometry": {"coordinates":[-85.943088,39.908624],"type":"Point"}
}