{
  "type": "Feature",
  "properties": {
    "iso:country":"US",
    "sg:address":"7410 N Co Rd 700 E",
    "sg:city":"Michigantown",
    "sg:classifiers":[
        {
            "category":"Professional",
            "subcategory":"Business Services",
            "type":"Services"
        }
    ],
    "sg:phone":"+1 765 249 2290",
    "sg:postcode":"46057",
    "sg:province":"IN",
    "wof:name":"Ogle Corp",
    "wof:placetype":"venue"
},
  "geometry": {"coordinates":[-86.375556,40.39677],"type":"Point"}
}