{
  "type": "Feature",
  "properties": {
    "iso:country":"US",
    "sg:address":"1120 M St",
    "sg:city":"Bedford",
    "sg:classifiers":[
        {
            "category":"Retail",
            "subcategory":"Animal Services",
            "type":"Services"
        }
    ],
    "sg:phone":"+1 812 275 3455",
    "sg:postcode":"47421",
    "sg:province":"IN",
    "sg:tags":[
        "pet",
        "grooming",
        "washing"
    ],
    "wof:name":"Johnson's Paws & Pals",
    "wof:placetype":"venue"
},
  "geometry": {"coordinates":[-86.488637,38.866938],"type":"Point"}
}