{
  "type": "Feature",
  "properties": {
    "addr:full":"856 Woodruff Pl Indianapolis IN 46201",
    "addr:housenumber":"856",
    "addr:postcode":"46201",
    "addr:street":"Woodruff Pl",
    "iso:country":"US",
    "sg:address":"856 Woodruff Pl",
    "sg:city":"Indianapolis",
    "sg:classifiers":[
        {
            "category":"Building & Trades",
            "subcategory":"Construction",
            "type":"Services"
        }
    ],
    "sg:phone":"+1 317 636 1495",
    "sg:postcode":"46201",
    "sg:province":"IN",
    "sg:tags":[
        "carpentry",
        "contractor"
    ],
    "wof:name":"Woodruff Carpentry Co",
    "wof:placetype":"venue"
},
  "geometry": {"coordinates":[-86.130787,39.779762],"type":"Point"}
}