{
  "type": "Feature",
  "properties": {
    "iso:country":"US",
    "sg:address":"9895 Deer Trl",
    "sg:city":"Plymouth",
    "sg:classifiers":[
        {
            "category":"Building & Trades",
            "subcategory":"Landscaping Services",
            "type":"Services"
        }
    ],
    "sg:phone":"+1 574 936 5905",
    "sg:postcode":"46563",
    "sg:province":"IN",
    "wof:name":"Tree Mgmt Inc",
    "wof:placetype":"venue"
},
  "geometry": {"coordinates":[-86.343996,41.332729],"type":"Point"}
}