{
  "type": "Feature",
  "properties": {
    "addr:full":"203 E Berry St Fort Wayne IN 46802",
    "addr:housenumber":"203",
    "addr:postcode":"46802",
    "addr:street":"E Berry St",
    "iso:country":"US",
    "sg:address":"203 E Berry St",
    "sg:city":"Fort Wayne",
    "sg:classifiers":[
        {
            "category":"Professional",
            "subcategory":"Lawyer & Legal Services",
            "type":"Services"
        }
    ],
    "sg:phone":"+1 260 426 0545",
    "sg:postcode":"46802",
    "sg:province":"IN",
    "sg:tags":[
        "attorney"
    ],
    "sg:website":"www.tcrjlaw.com",
    "wof:name":"Tourkow Crell Rosenblatt",
    "wof:placetype":"venue"
},
  "geometry": {"coordinates":[-85.136611,41.079827],"type":"Point"}
}