{
  "type": "Feature",
  "properties": {
    "iso:country":"US",
    "sg:address":"116 E 1st St",
    "sg:city":"Greensburg",
    "sg:classifiers":[
        {
            "category":"Building & Trades",
            "subcategory":"Construction",
            "type":"Services"
        }
    ],
    "sg:phone":"+1 812 662 3025",
    "sg:postcode":"47240",
    "sg:province":"IN",
    "sg:tags":[
        "hanging",
        "contractor"
    ],
    "wof:name":"Woodard Decorative Paintings",
    "wof:placetype":"venue"
},
  "geometry": {"coordinates":[-85.484077,39.344094],"type":"Point"}
}