{
  "type": "Feature",
  "properties": {
    "addr:full":"1226 E Tremont Way Bloomington IN 47401",
    "addr:housenumber":"1226",
    "addr:postcode":"47401",
    "addr:street":"E Tremont Way",
    "iso:country":"US",
    "sg:address":"1226 E Tremont Way",
    "sg:city":"Bloomington",
    "sg:classifiers":[
        {
            "category":"Building & Trades",
            "subcategory":"Construction",
            "type":"Services"
        }
    ],
    "sg:phone":"+1 812 339 9257",
    "sg:postcode":"47401",
    "sg:province":"IN",
    "sg:tags":[
        "general",
        "contractor"
    ],
    "wof:name":"Coppercorn Inc",
    "wof:placetype":"venue"
},
  "geometry": {"coordinates":[-86.518918,39.131718],"type":"Point"}
}