{
  "type": "Feature",
  "properties": {
    "iso:country":"US",
    "sg:address":"6117 N College Ave",
    "sg:city":"Indianapolis",
    "sg:classifiers":[
        {
            "category":"Real Estate",
            "subcategory":"Real Estate Agent",
            "type":"Services"
        }
    ],
    "sg:phone":"+1 317 257 9016",
    "sg:postcode":"46220",
    "sg:province":"IN",
    "wof:name":"Realty Comp Inc",
    "wof:placetype":"venue"
},
  "geometry": {"coordinates":[-86.14599800000001,39.866465],"type":"Point"}
}