{
  "type": "Feature",
  "properties": {
    "iso:country":"US",
    "sg:address":"826 Sunset Ave",
    "sg:city":"Rising Sun",
    "sg:classifiers":[
        {
            "category":"Building & Trades",
            "subcategory":"Construction",
            "type":"Services"
        }
    ],
    "sg:phone":"+1 812 438 3009",
    "sg:postcode":"47040",
    "sg:province":"IN",
    "sg:tags":[
        "masonry",
        "contractor"
    ],
    "wof:name":"H & S Brickwork",
    "wof:placetype":"venue"
},
  "geometry": {"coordinates":[-84.858234,38.958269],"type":"Point"}
}