{
  "type": "Feature",
  "properties": {
    "iso:country":"US",
    "sg:address":"815 Main St",
    "sg:city":"Rochester",
    "sg:classifiers":[
        {
            "category":"Government",
            "subcategory":"Court House",
            "type":"Public Place"
        }
    ],
    "sg:phone":"+1 574 223 7716",
    "sg:postcode":"46975",
    "sg:province":"IN",
    "sg:tags":[
        "county"
    ],
    "wof:name":"Circuit Court Jury Vrfctn",
    "wof:placetype":"venue"
},
  "geometry": {"coordinates":[-86.215881,41.065897],"type":"Point"}
}