{
  "type": "Feature",
  "properties": {
    "addr:full":"201 N Harrison St Alexandria IN 46001",
    "addr:housenumber":"201",
    "addr:postcode":"46001",
    "addr:street":"N Harrison St",
    "iso:country":"US",
    "sg:address":"201 N Harrison St",
    "sg:city":"Alexandria",
    "sg:classifiers":[
        {
            "category":"Professional",
            "subcategory":"Accounting & Tax Preparation",
            "type":"Services"
        }
    ],
    "sg:phone":"+1 765 724 9457",
    "sg:postcode":"46001",
    "sg:province":"IN",
    "sg:tags":[
        "return",
        "filing"
    ],
    "wof:name":"H & R Block Tax Svc",
    "wof:placetype":"venue"
},
  "geometry": {"coordinates":[-85.67447799999999,40.264472],"type":"Point"}
}