{
  "type": "Feature",
  "properties": {
    "iso:country":"US",
    "sg:address":"3085 E Lincolnway",
    "sg:city":"Columbia City",
    "sg:classifiers":[
        {
            "category":"Organizations",
            "subcategory":"Religious Organization",
            "type":"Services"
        }
    ],
    "sg:phone":"+1 260 248 4844",
    "sg:postcode":"46725",
    "sg:province":"IN",
    "sg:tags":[
        "church"
    ],
    "wof:name":"Church Of Jesus Christ Of Lds",
    "wof:placetype":"venue"
},
  "geometry": {"coordinates":[-85.432986,41.141118],"type":"Point"}
}