{
  "type": "Feature",
  "properties": {
    "iso:country":"US",
    "sg:address":"2095 Fremont Dr",
    "sg:city":"Columbus",
    "sg:classifiers":[
        {
            "category":"Building & Trades",
            "subcategory":"Electrical",
            "type":"Services"
        }
    ],
    "sg:phone":"+1 812 526 5241",
    "sg:postcode":"47201",
    "sg:province":"IN",
    "sg:tags":[
        "electric",
        "contractor"
    ],
    "wof:name":"Mac's Electric",
    "wof:placetype":"venue"
},
  "geometry": {"coordinates":[-85.953516,39.285111],"type":"Point"}
}