{
  "type": "Feature",
  "properties": {
    "addr:full":"404 W Superior St Kokomo IN 46901",
    "addr:housenumber":"404",
    "addr:postcode":"46901",
    "addr:street":"W Superior St",
    "iso:country":"US",
    "sg:address":"404 W Superior St",
    "sg:city":"Kokomo",
    "sg:classifiers":[
        {
            "category":"Professional",
            "subcategory":"Computer Services",
            "type":"Services"
        }
    ],
    "sg:phone":"+1 765 452 2337",
    "sg:postcode":"46901",
    "sg:province":"IN",
    "sg:tags":[
        "repair"
    ],
    "sg:website":"www.klings.com",
    "wof:name":"Kling's Computers",
    "wof:placetype":"venue"
},
  "geometry": {"coordinates":[-86.13857899999999,40.485475],"type":"Point"}
}