{
  "type": "Feature",
  "properties": {
    "addr:full":"610 S Harrison St Shelbyville IN 46176",
    "addr:housenumber":"610",
    "addr:postcode":"46176",
    "addr:street":"S Harrison St",
    "iso:country":"US",
    "sg:address":"610 S Harrison St",
    "sg:city":"Shelbyville",
    "sg:classifiers":[
        {
            "category":"Shopping",
            "subcategory":"Gifts & Souvenirs",
            "type":"Retail Goods"
        }
    ],
    "sg:phone":"+1 317 398 2444",
    "sg:postcode":"46176",
    "sg:province":"IN",
    "wof:name":"Angels Etc",
    "wof:placetype":"venue"
},
  "geometry": {"coordinates":[-85.776951,39.519952],"type":"Point"}
}