{
  "type": "Feature",
  "properties": {
    "addr:full":"4000 W 106th St Carmel IN 46032",
    "addr:housenumber":"4000",
    "addr:postcode":"46032",
    "addr:street":"W 106Th St",
    "iso:country":"US",
    "sg:address":"4000 W 106th St",
    "sg:city":"Carmel",
    "sg:classifiers":[
        {
            "category":"Professional",
            "subcategory":"Business Services",
            "type":"Services"
        }
    ],
    "sg:phone":"+1 317 733 4011",
    "sg:postcode":"46032",
    "sg:province":"IN",
    "sg:tags":[
        "packaging"
    ],
    "wof:name":"UPS Store",
    "wof:placetype":"venue"
},
  "geometry": {"coordinates":[-86.229691,39.940951],"type":"Point"}
}