{
  "type": "Feature",
  "properties": {
    "iso:country":"US",
    "sg:address":"106 S Broad St",
    "sg:city":"Griffith",
    "sg:classifiers":[
        {
            "category":"Restaurant",
            "type":"Food & Drink"
        }
    ],
    "sg:phone":"+1 219 924 6000",
    "sg:postcode":"46319",
    "sg:province":"IN",
    "sg:tags":[
        "pizza"
    ],
    "wof:name":"Squigi's Pizza",
    "wof:placetype":"venue"
},
  "geometry": {"coordinates":[-87.42776000000001,41.521769],"type":"Point"}
}