{
  "type": "Feature",
  "properties": {
    "iso:country":"US",
    "sg:address":"315 Walnut St",
    "sg:city":"Lawrenceburg",
    "sg:classifiers":[
        {
            "category":"Professional",
            "subcategory":"Engineering",
            "type":"Services"
        }
    ],
    "sg:phone":"+1 812 539 2455",
    "sg:postcode":"47025",
    "sg:province":"IN",
    "sg:tags":[
        "engineer"
    ],
    "wof:name":"ATC Assoc Inc",
    "wof:placetype":"venue"
},
  "geometry": {"coordinates":[-84.850949,39.095054],"type":"Point"}
}