{
  "type": "Feature",
  "properties": {
    "iso:country":"US",
    "sg:address":"605 Water St",
    "sg:city":"Union Mills",
    "sg:classifiers":[
        {
            "category":"Health Services",
            "subcategory":"Medical Lab",
            "type":"Services"
        }
    ],
    "sg:phone":"+1 219 767 2282",
    "sg:postcode":"46382",
    "sg:province":"IN",
    "sg:tags":[
        "laboratory"
    ],
    "wof:name":"Twin Lakes Lab Inc",
    "wof:placetype":"venue"
},
  "geometry": {"coordinates":[-86.777343,41.49299],"type":"Point"}
}