{
  "type": "Feature",
  "properties": {
    "iso:country":"US",
    "sg:address":"3810 N Kercheval Dr",
    "sg:city":"Indianapolis",
    "sg:classifiers":[
        {
            "category":"Building & Trades",
            "subcategory":"Construction",
            "type":"Services"
        }
    ],
    "sg:phone":"+1 317 545 4210",
    "sg:postcode":"46226",
    "sg:province":"IN",
    "sg:tags":[
        "builder",
        "stair"
    ],
    "wof:name":"Straight Flight Stair Systems",
    "wof:placetype":"venue"
},
  "geometry": {"coordinates":[-86.040276,39.827891],"type":"Point"}
}