{
  "type": "Feature",
  "properties": {
    "iso:country":"US",
    "sg:address":"6509 S Co Rd 800 W",
    "sg:city":"Daleville",
    "sg:classifiers":[
        {
            "category":"Manufacturing",
            "subcategory":"Metals",
            "type":"Manufacturing & Wholesale Goods"
        }
    ],
    "sg:phone":"+1 765 378 1292",
    "sg:postcode":"47334",
    "sg:province":"IN",
    "sg:tags":[
        "engraver"
    ],
    "wof:name":"Morrow Device Marking",
    "wof:placetype":"venue"
},
  "geometry": {"coordinates":[-85.537547,40.134532],"type":"Point"}
}