{
  "type": "Feature",
  "properties": {
    "iso:country":"US",
    "sg:address":"1600 Pennsylvania St",
    "sg:city":"Gary",
    "sg:classifiers":[
        {
            "category":"Organizations",
            "subcategory":"Community Association",
            "type":"Services"
        }
    ],
    "sg:phone":"+1 219 885 9447",
    "sg:postcode":"46407",
    "sg:province":"IN",
    "wof:name":"Most Wrshipful King Solom Mwks",
    "wof:placetype":"venue"
},
  "geometry": {"coordinates":[-87.333181,41.585871],"type":"Point"}
}