{
  "type": "Feature",
  "properties": {
    "iso:country":"US",
    "sg:address":"4301 S Co Rd 388 E",
    "sg:city":"Muncie",
    "sg:classifiers":[
        {
            "category":"Airport",
            "type":"Transportation"
        }
    ],
    "sg:phone":"+1 765 284 9611",
    "sg:postcode":"47302",
    "sg:province":"IN",
    "wof:name":"Reese Flying Svc",
    "wof:placetype":"venue"
},
  "geometry": {"coordinates":[-85.313237,40.156998],"type":"Point"}
}