{
  "type": "Feature",
  "properties": {
    "iso:country":"US",
    "sg:address":"5121 N 1000 E",
    "sg:city":"Pierceton",
    "sg:classifiers":[
        {
            "category":"Travel",
            "subcategory":"Campground",
            "type":"Entertainment"
        }
    ],
    "sg:phone":"+1 574 834 1300",
    "sg:postcode":"46562",
    "sg:province":"IN",
    "sg:tags":[
        "camp"
    ],
    "wof:name":"Camp Adventure Lookout Lodge",
    "wof:placetype":"venue"
},
  "geometry": {"coordinates":[-85.652394,41.311279],"type":"Point"}
}