{
  "type": "Feature",
  "properties": {
    "iso:country":"US",
    "sg:address":"6027 S Co Rd 250 E",
    "sg:city":"Greencastle",
    "sg:classifiers":[
        {
            "category":"Farming",
            "subcategory":"Livestock Farm",
            "type":"Manufacturing & Wholesale Goods"
        }
    ],
    "sg:phone":"+1 765 795 4609",
    "sg:postcode":"46135",
    "sg:province":"IN",
    "sg:tags":[
        "animal",
        "general"
    ],
    "wof:name":"Noble A Costin",
    "wof:placetype":"venue"
},
  "geometry": {"coordinates":[-86.80405399999999,39.57289],"type":"Point"}
}