{
  "type": "Feature",
  "properties": {
    "addr:full":"3035 S Keystone Ave Indianapolis IN 46237",
    "addr:housenumber":"3035",
    "addr:postcode":"46237",
    "addr:street":"S Keystone Ave",
    "iso:country":"US",
    "sg:address":"3035 S Keystone Ave",
    "sg:city":"Indianapolis",
    "sg:classifiers":[
        {
            "category":"Building & Trades",
            "subcategory":"Construction",
            "type":"Services"
        }
    ],
    "sg:phone":"+1 317 786 5303",
    "sg:postcode":"46237",
    "sg:province":"IN",
    "sg:tags":[
        "painter"
    ],
    "wof:name":"Standard Coating Svc Inc",
    "wof:placetype":"venue"
},
  "geometry": {"coordinates":[-86.120683,39.721951],"type":"Point"}
}