{
  "type": "Feature",
  "properties": {
    "iso:country":"US",
    "sg:address":"101 Place Rd",
    "sg:city":"Jasper",
    "sg:classifiers":[
        {
            "category":"Restaurant",
            "type":"Food & Drink"
        }
    ],
    "sg:phone":"+1 812 482 7564",
    "sg:postcode":"47546",
    "sg:province":"IN",
    "sg:tags":[
        "eating"
    ],
    "wof:name":"Los Bravos Mexican Restaurant",
    "wof:placetype":"venue"
},
  "geometry": {"coordinates":[-86.943635,38.383551],"type":"Point"}
}