{
  "type": "Feature",
  "properties": {
    "iso:country":"US",
    "sg:address":"5803 W Co Rd 275 S",
    "sg:city":"Coatesville",
    "sg:classifiers":[
        {
            "category":"Building & Trades",
            "subcategory":"Plumbing",
            "type":"Services"
        }
    ],
    "sg:phone":"+1 317 539 4916",
    "sg:postcode":"46121",
    "sg:province":"IN",
    "sg:tags":[
        "conditioning",
        "air",
        "system",
        "contractor"
    ],
    "wof:name":"Bill Clontz Heating & Cooling",
    "wof:placetype":"venue"
},
  "geometry": {"coordinates":[-86.62756899999999,39.720395],"type":"Point"}
}