{
  "type": "Feature",
  "properties": {
    "iso:country":"US",
    "sg:address":"502 E Culver Rd",
    "sg:city":"Knox",
    "sg:classifiers":[
        {
            "category":"Health Services",
            "subcategory":"Podiatrist",
            "type":"Services"
        }
    ],
    "sg:phone":"+1 574 772 3780",
    "sg:postcode":"46534",
    "sg:province":"IN",
    "wof:name":"Affiliated Ankle & Foot Clinic",
    "wof:placetype":"venue"
},
  "geometry": {"coordinates":[-86.615944,41.287981],"type":"Point"}
}