{
  "type": "Feature",
  "properties": {
    "iso:country":"US",
    "sg:address":"1013 N Huntington St",
    "sg:city":"Syracuse",
    "sg:classifiers":[
        {
            "category":"Building & Trades",
            "subcategory":"Construction",
            "type":"Services"
        }
    ],
    "sg:phone":"+1 574 457 8751",
    "sg:postcode":"46567",
    "sg:province":"IN",
    "sg:tags":[
        "general",
        "contractor"
    ],
    "wof:name":"Complete Cottage Care",
    "wof:placetype":"venue"
},
  "geometry": {"coordinates":[-85.754562,41.429617],"type":"Point"}
}