{
  "type": "Feature",
  "properties": {
    "iso:country":"US",
    "sg:address":"1188 E 400 S",
    "sg:city":"Oakford",
    "sg:classifiers":[
        {
            "category":"Building & Trades",
            "subcategory":"Construction",
            "type":"Services"
        }
    ],
    "sg:phone":"+1 765 453 1133",
    "sg:postcode":"46992",
    "sg:province":"IN",
    "sg:tags":[
        "insulation",
        "heat",
        "contractor"
    ],
    "wof:name":"Wolff Insulation Svc",
    "wof:placetype":"venue"
},
  "geometry": {"coordinates":[-85.769926,40.768256],"type":"Point"}
}