{
  "type": "Feature",
  "properties": {
    "iso:country":"US",
    "sg:address":"4321 Skylark Dr",
    "sg:city":"Indianapolis",
    "sg:classifiers":[
        {
            "category":"Building & Trades",
            "subcategory":"Construction",
            "type":"Services"
        }
    ],
    "sg:phone":"+1 317 850 3580",
    "sg:postcode":"46239",
    "sg:province":"IN",
    "sg:tags":[
        "coping",
        "plastering",
        "tiling",
        "pool",
        "swimming"
    ],
    "wof:name":"Aquadoc Poolcare",
    "wof:placetype":"venue"
},
  "geometry": {"coordinates":[-86.005286,39.70426],"type":"Point"}
}