{
  "type": "Feature",
  "properties": {
    "addr:full":"115 N College Ave Bloomington IN 47404",
    "addr:housenumber":"115",
    "addr:postcode":"47404",
    "addr:street":"N College Ave",
    "iso:country":"US",
    "sg:address":"115 N College Ave",
    "sg:city":"Bloomington",
    "sg:classifiers":[
        {
            "category":"Insurance",
            "subcategory":"Insurance Agent",
            "type":"Services"
        }
    ],
    "sg:phone":"+1 812 334 9956",
    "sg:postcode":"47404",
    "sg:province":"IN",
    "wof:name":"Federated Insurance",
    "wof:placetype":"venue"
},
  "geometry": {"coordinates":[-86.534941,39.167418],"type":"Point"}
}