{
  "type": "Feature",
  "properties": {
    "iso:country":"US",
    "sg:address":"329 W Main St",
    "sg:city":"Madison",
    "sg:phone":"+1 812 265 3313",
    "sg:postcode":"47250",
    "sg:province":"IN",
    "sg:tags":[
        "gas"
    ],
    "wof:name":"Blue Flame Gas",
    "wof:placetype":"venue"
},
  "geometry": {"coordinates":[-85.382942,38.736707],"type":"Point"}
}