{
  "type": "Feature",
  "properties": {
    "iso:country":"US",
    "sg:address":"3315 Mc Carty Ln",
    "sg:city":"Lafayette",
    "sg:classifiers":[
        {
            "category":"Organizations",
            "subcategory":"Labor Organization",
            "type":"Services"
        }
    ],
    "sg:phone":"+1 765 447 2438",
    "sg:postcode":"47905",
    "sg:province":"IN",
    "wof:name":"USWA",
    "wof:placetype":"venue"
},
  "geometry": {"coordinates":[-86.850087,40.40282],"type":"Point"}
}