{
  "type": "Feature",
  "properties": {
    "addr:full":"58 Napoleon St Valparaiso IN 46383",
    "addr:housenumber":"58",
    "addr:postcode":"46383",
    "addr:street":"Napoleon St",
    "iso:country":"US",
    "sg:address":"58 Napoleon St",
    "sg:city":"Valparaiso",
    "sg:classifiers":[
        {
            "category":"Insurance",
            "subcategory":"Insurance Agent",
            "type":"Services"
        }
    ],
    "sg:phone":"+1 219 462 0558",
    "sg:postcode":"46383",
    "sg:province":"IN",
    "wof:name":"Bartholomew & Son Insurance",
    "wof:placetype":"venue"
},
  "geometry": {"coordinates":[-87.063402,41.46594],"type":"Point"}
}