{
  "type": "Feature",
  "properties": {
    "addr:full":"6416 Timber Walk Dr Indianapolis IN 46236",
    "addr:housenumber":"6416",
    "addr:postcode":"46236",
    "addr:street":"Timber Walk Dr",
    "iso:country":"US",
    "sg:address":"6416 Timber Walk Dr",
    "sg:city":"Indianapolis",
    "sg:classifiers":[
        {
            "category":"Building & Trades",
            "subcategory":"Construction",
            "type":"Services"
        }
    ],
    "sg:phone":"+1 317 826 4043",
    "sg:postcode":"46236",
    "sg:province":"IN",
    "sg:tags":[
        "home",
        "builder"
    ],
    "wof:name":"Centex Homes",
    "wof:placetype":"venue"
},
  "geometry": {"coordinates":[-85.983062,39.874215],"type":"Point"}
}