{
  "type": "Feature",
  "properties": {
    "addr:full":"328 S 5th St Terre Haute IN 47807",
    "addr:housenumber":"328",
    "addr:postcode":"47807",
    "addr:street":"S 5Th St",
    "iso:country":"US",
    "sg:address":"328 S 5th St",
    "sg:city":"Terre Haute",
    "sg:classifiers":[
        {
            "category":"Professional",
            "subcategory":"Management & Consulting",
            "type":"Services"
        }
    ],
    "sg:phone":"+1 812 232 2875",
    "sg:postcode":"47807",
    "sg:province":"IN",
    "sg:tags":[
        "marketing",
        "program"
    ],
    "sg:website":"www.millerwhite.com",
    "wof:name":"Miller White LLC",
    "wof:placetype":"venue"
},
  "geometry": {"coordinates":[-87.41120600000001,39.462695],"type":"Point"}
}