{
  "type": "Feature",
  "properties": {
    "iso:country":"US",
    "sg:address":"1602 E 8th St",
    "sg:city":"Jeffersonville",
    "sg:classifiers":[
        {
            "category":"Banks & Credit Unions",
            "subcategory":"Investment Brokerage",
            "type":"Services"
        }
    ],
    "sg:phone":"+1 812 288 4110",
    "sg:postcode":"47130",
    "sg:province":"IN",
    "sg:tags":[
        "consultant",
        "planning",
        "financial"
    ],
    "wof:name":"Garrett Davis Financial Svc",
    "wof:placetype":"venue"
},
  "geometry": {"coordinates":[-85.72151700000001,38.288806],"type":"Point"}
}