{
  "type": "Feature",
  "properties": {
    "iso:country":"US",
    "sg:address":"159 Westridge Pl",
    "sg:city":"Greenwood",
    "sg:classifiers":[
        {
            "category":"Shopping",
            "subcategory":"Hobbies, Toys, & Games",
            "type":"Retail Goods"
        }
    ],
    "sg:phone":"+1 317 859 0420",
    "sg:postcode":"46142",
    "sg:province":"IN",
    "wof:name":"Triviahost",
    "wof:placetype":"venue"
},
  "geometry": {"coordinates":[-86.145073,39.613855],"type":"Point"}
}