{
  "type": "Feature",
  "properties": {
    "addr:full":"1192 W 3rd St Rochester IN 46975",
    "addr:housenumber":"1192",
    "addr:postcode":"46975",
    "addr:street":"W 3Rd St",
    "iso:country":"US",
    "sg:address":"1192 W 3rd St",
    "sg:city":"Rochester",
    "sg:classifiers":[
        {
            "category":"Retail",
            "subcategory":"Animal Services",
            "type":"Services"
        }
    ],
    "sg:phone":"+1 574 223 5977",
    "sg:postcode":"46975",
    "sg:province":"IN",
    "sg:tags":[
        "pet",
        "grooming",
        "washing"
    ],
    "wof:name":"Fluff n Puff Poodle Salon",
    "wof:placetype":"venue"
},
  "geometry": {"coordinates":[-86.227683,41.071909],"type":"Point"}
}