{
  "type": "Feature",
  "properties": {
    "iso:country":"US",
    "sg:address":"1 Bulldog Blvd W",
    "sg:city":"Batesville",
    "sg:classifiers":[
        {
            "category":"Education",
            "subcategory":"School",
            "type":"Public Place"
        }
    ],
    "sg:phone":"+1 812 934 4384",
    "sg:postcode":"47006",
    "sg:province":"IN",
    "sg:website":"www.batesville.k12.in.us",
    "wof:name":"Batesville High School",
    "wof:placetype":"venue"
},
  "geometry": {"coordinates":[-85.23570599999999,39.309878],"type":"Point"}
}