{
  "type": "Feature",
  "properties": {
    "iso:country":"US",
    "sg:address":"2095 W 400 S",
    "sg:city":"Albion",
    "sg:phone":"+1 260 636 2749",
    "sg:postcode":"46701",
    "sg:province":"IN",
    "sg:tags":[
        "farm",
        "corn",
        "wheat",
        "soybean"
    ],
    "wof:name":"Rex Stangland",
    "wof:placetype":"venue"
},
  "geometry": {"coordinates":[-85.462991,41.294431],"type":"Point"}
}