{
  "type": "Feature",
  "properties": {
    "iso:country":"US",
    "sg:address":"2553 Dickey Rd",
    "sg:city":"East Chicago",
    "sg:classifiers":[
        {
            "category":"Wholesale",
            "subcategory":"Chemicals & Plastics",
            "type":"Manufacturing & Wholesale Goods"
        }
    ],
    "sg:phone":"+1 219 398 3400",
    "sg:postcode":"46312",
    "sg:province":"IN",
    "sg:tags":[
        "handling"
    ],
    "wof:name":"Superior Carriers Inc",
    "wof:placetype":"venue"
},
  "geometry": {"coordinates":[-87.471699,41.664301],"type":"Point"}
}