{
  "type": "Feature",
  "properties": {
    "iso:country":"US",
    "sg:address":"10082 E 10th St",
    "sg:city":"Indianapolis",
    "sg:classifiers":[
        {
            "category":"Personal",
            "subcategory":"Beauty Salon",
            "type":"Services"
        }
    ],
    "sg:phone":"+1 317 897 2957",
    "sg:postcode":"46229",
    "sg:province":"IN",
    "wof:name":"Aboubacar Toure",
    "wof:placetype":"venue"
},
  "geometry": {"coordinates":[-85.9835,39.782415],"type":"Point"}
}