{
  "type": "Feature",
  "properties": {
    "iso:country":"US",
    "sg:address":"4901 W 106th St",
    "sg:city":"Zionsville",
    "sg:classifiers":[
        {
            "category":"Retail",
            "subcategory":"Auto Repair",
            "type":"Services"
        }
    ],
    "sg:phone":"+1 317 873 4550",
    "sg:postcode":"46077",
    "sg:province":"IN",
    "sg:tags":[
        "wrecker"
    ],
    "wof:name":"Zionsville Towing Inc",
    "wof:placetype":"venue"
},
  "geometry": {"coordinates":[-86.241409,39.940634],"type":"Point"}
}