{
  "type": "Feature",
  "properties": {
    "addr:full":"151 Vernon St North Vernon IN 47265",
    "addr:housenumber":"151",
    "addr:postcode":"47265",
    "addr:street":"Vernon St",
    "iso:country":"US",
    "sg:address":"151 Vernon St",
    "sg:city":"North Vernon",
    "sg:classifiers":[
        {
            "category":"Personal",
            "subcategory":"Beauty Salon",
            "type":"Services"
        }
    ],
    "sg:phone":"+1 812 352 1234",
    "sg:postcode":"47265",
    "sg:province":"IN",
    "wof:name":"Rumors",
    "wof:placetype":"venue"
},
  "geometry": {"coordinates":[-85.62321,39.002603],"type":"Point"}
}