{
  "type": "Feature",
  "properties": {
    "iso:country":"US",
    "sg:address":"6028 Manchester Dr",
    "sg:city":"Fort Wayne",
    "sg:classifiers":[
        {
            "category":"Professional",
            "subcategory":"Business Services",
            "type":"Services"
        }
    ],
    "sg:phone":"+1 260 969 0358",
    "sg:postcode":"46835",
    "sg:province":"IN",
    "wof:name":"Summit Capital Solutions",
    "wof:placetype":"venue"
},
  "geometry": {"coordinates":[-85.062952,41.125087],"type":"Point"}
}