{
  "type": "Feature",
  "properties": {
    "iso:country":"US",
    "sg:address":"11082 N Co Rd 300 W",
    "sg:city":"Brazil",
    "sg:classifiers":[
        {
            "category":"Shopping",
            "subcategory":"Gifts & Souvenirs",
            "type":"Retail Goods"
        }
    ],
    "sg:phone":"+1 812 448 1600",
    "sg:postcode":"47834",
    "sg:province":"IN",
    "sg:tags":[
        "shop"
    ],
    "wof:name":"Mee & Ewe Shoppe",
    "wof:placetype":"venue"
},
  "geometry": {"coordinates":[-87.162204,39.548751],"type":"Point"}
}