{
  "type": "Feature",
  "properties": {
    "iso:country":"US",
    "sg:address":"121 W Center St",
    "sg:city":"Warsaw",
    "sg:classifiers":[
        {
            "category":"Shopping",
            "type":"Retail Goods"
        }
    ],
    "sg:phone":"+1 574 269 7006",
    "sg:postcode":"46580",
    "sg:province":"IN",
    "sg:tags":[
        "orthopedic",
        "appliance"
    ],
    "wof:name":"F J Rowland & Assoc",
    "wof:placetype":"venue"
},
  "geometry": {"coordinates":[-85.857759,41.238022],"type":"Point"}
}