{
  "type": "Feature",
  "properties": {
    "iso:country":"US",
    "sg:address":"3729 Elm St",
    "sg:city":"East Chicago",
    "sg:classifiers":[
        {
            "category":"Social Services",
            "subcategory":"Child Care",
            "type":"Services"
        }
    ],
    "sg:phone":"+1 219 397 0853",
    "sg:postcode":"46312",
    "sg:province":"IN",
    "wof:name":"Darias Daycare",
    "wof:placetype":"venue"
},
  "geometry": {"coordinates":[-87.447302,41.644972],"type":"Point"}
}