{
  "type": "Feature",
  "properties": {
    "iso:country":"US",
    "sg:address":"1040 E 86th St",
    "sg:city":"Indianapolis",
    "sg:classifiers":[
        {
            "category":"Travel",
            "subcategory":"Travel Agent",
            "type":"Entertainment"
        }
    ],
    "sg:phone":"+1 317 573 4919",
    "sg:postcode":"46240",
    "sg:province":"IN",
    "sg:tags":[
        "agency",
        "bureau"
    ],
    "sg:website":"www.travelboutique.com",
    "wof:name":"Uniworld Travel",
    "wof:placetype":"venue"
},
  "geometry": {"coordinates":[-86.14023,39.91261],"type":"Point"}
}