{
  "type": "Feature",
  "properties": {
    "addr:full":"2301 Lexington Rd Evansville IN 47720",
    "addr:housenumber":"2301",
    "addr:postcode":"47720",
    "addr:street":"Lexington Rd",
    "iso:country":"US",
    "sg:address":"2301 Lexington Rd",
    "sg:city":"Evansville",
    "sg:classifiers":[
        {
            "category":"Manufacturing",
            "subcategory":"Tools & Machinery",
            "type":"Manufacturing & Wholesale Goods"
        }
    ],
    "sg:phone":"+1 812 402 9522",
    "sg:postcode":"47720",
    "sg:province":"IN",
    "sg:tags":[
        "die",
        "cutting"
    ],
    "wof:name":"Mico Industries",
    "wof:placetype":"venue"
},
  "geometry": {"coordinates":[-87.597662,38.016124],"type":"Point"}
}