{
  "type": "Feature",
  "properties": {
    "iso:country":"US",
    "sg:address":"3725 N Post Rd",
    "sg:city":"Indianapolis",
    "sg:classifiers":[
        {
            "category":"Organizations",
            "subcategory":"Religious Organization",
            "type":"Services"
        }
    ],
    "sg:phone":"+1 317 895 0525",
    "sg:postcode":"46226",
    "sg:province":"IN",
    "sg:tags":[
        "denomination",
        "churches-various",
        "church"
    ],
    "wof:name":"Living Word Fellowship",
    "wof:placetype":"venue"
},
  "geometry": {"coordinates":[-86.009835,39.824522],"type":"Point"}
}