{
  "type": "Feature",
  "properties": {
    "iso:country":"US",
    "sg:address":"10060 E 63rd St",
    "sg:city":"Indianapolis",
    "sg:classifiers":[
        {
            "category":"Health Services",
            "subcategory":"Chiropractor",
            "type":"Services"
        }
    ],
    "sg:phone":"+1 317 823 8678",
    "sg:postcode":"46236",
    "sg:province":"IN",
    "wof:name":"Rempel Chiropractic",
    "wof:placetype":"venue"
},
  "geometry": {"coordinates":[-85.986842,39.87399],"type":"Point"}
}