{
  "type": "Feature",
  "properties": {
    "iso:country":"US",
    "sg:address":"8844 Nineveh Rd",
    "sg:city":"Nineveh",
    "sg:classifiers":[
        {
            "category":"Organizations",
            "subcategory":"Religious Organization",
            "type":"Services"
        }
    ],
    "sg:phone":"+1 317 933 2595",
    "sg:postcode":"46164",
    "sg:province":"IN",
    "sg:tags":[
        "church"
    ],
    "sg:website":"www.churchofthelakes.worthyofpraise.org",
    "wof:name":"Church Of The Lakes",
    "wof:placetype":"venue"
},
  "geometry": {"coordinates":[-86.10681700000001,39.322947],"type":"Point"}
}