{
  "type": "Feature",
  "properties": {
    "iso:country":"US",
    "sg:address":"4009 N High School Rd",
    "sg:city":"Indianapolis",
    "sg:classifiers":[
        {
            "category":"Social Services",
            "subcategory":"Child Care",
            "type":"Services"
        }
    ],
    "sg:phone":"+1 317 293 2199",
    "sg:postcode":"46254",
    "sg:province":"IN",
    "wof:name":"Learning Universe",
    "wof:placetype":"venue"
},
  "geometry": {"coordinates":[-86.270416,39.832219],"type":"Point"}
}