{
  "type": "Feature",
  "properties": {
    "iso:country":"US",
    "sg:address":"1006 Elmore St",
    "sg:city":"Crawfordsville",
    "sg:classifiers":[
        {
            "category":"Building & Trades",
            "subcategory":"Construction",
            "type":"Services"
        }
    ],
    "sg:phone":"+1 765 364 8115",
    "sg:postcode":"47933",
    "sg:province":"IN",
    "sg:tags":[
        "house"
    ],
    "wof:name":"McCollum Remodeling",
    "wof:placetype":"venue"
},
  "geometry": {"coordinates":[-86.88881499999999,40.032381],"type":"Point"}
}