{
  "type": "Feature",
  "properties": {
    "iso:country":"US",
    "sg:address":"3429 Madison Ave",
    "sg:city":"Anderson",
    "sg:classifiers":[
        {
            "category":"Sports & Exercise",
            "subcategory":"Golf",
            "type":"Entertainment"
        }
    ],
    "sg:phone":"+1 765 644 9754",
    "sg:postcode":"46013",
    "sg:province":"IN",
    "sg:tags":[
        "course"
    ],
    "wof:name":"Meadowbrook Golf Course LLC",
    "wof:placetype":"venue"
},
  "geometry": {"coordinates":[-85.692019,40.083437],"type":"Point"}
}