{
  "type": "Feature",
  "properties": {
    "iso:country":"US",
    "sg:address":"58172 Charlotte Ave",
    "sg:city":"Elkhart",
    "sg:classifiers":[
        {
            "category":"Wholesale",
            "subcategory":"Chemicals & Plastics",
            "type":"Manufacturing & Wholesale Goods"
        }
    ],
    "sg:phone":"+1 574 293 0502",
    "sg:postcode":"46517",
    "sg:province":"IN",
    "sg:tags":[
        "adhesive",
        "glue"
    ],
    "sg:website":"www.hahnsystems.com",
    "wof:name":"Hahn Systems",
    "wof:placetype":"venue"
},
  "geometry": {"coordinates":[-86.01012799999999,41.649402],"type":"Point"}
}