{
  "type": "Feature",
  "properties": {
    "iso:country":"US",
    "sg:address":"3173 E Main St",
    "sg:city":"Danville",
    "sg:classifiers":[
        {
            "category":"Wholesale",
            "subcategory":"Machinery & Supplies",
            "type":"Manufacturing & Wholesale Goods"
        }
    ],
    "sg:phone":"+1 317 745 6929",
    "sg:postcode":"46122",
    "sg:province":"IN",
    "sg:tags":[
        "equipment",
        "excavating"
    ],
    "sg:website":"www.ditchwitchmidwest.com",
    "wof:name":"Ditch Witch Midwest",
    "wof:placetype":"venue"
},
  "geometry": {"coordinates":[-86.465817,39.761832],"type":"Point"}
}