{
  "type": "Feature",
  "properties": {
    "iso:country":"US",
    "sg:address":"9151 N 1200 W",
    "sg:city":"Demotte",
    "sg:classifiers":[
        {
            "category":"Professional",
            "subcategory":"Lawyer & Legal Services",
            "type":"Services"
        }
    ],
    "sg:phone":"+1 219 345 3114",
    "sg:postcode":"46310",
    "sg:province":"IN",
    "sg:tags":[
        "attorney"
    ],
    "wof:name":"Charles P Dargo Atty At Law",
    "wof:placetype":"venue"
},
  "geometry": {"coordinates":[-87.275757,41.136594],"type":"Point"}
}