{
  "type": "Feature",
  "properties": {
    "iso:country":"US",
    "sg:address":"1420 Corporate Way",
    "sg:city":"Seymour",
    "sg:classifiers":[
        {
            "category":"Government",
            "subcategory":"Office",
            "type":"Public Place"
        }
    ],
    "sg:phone":"+1 812 523 8630",
    "sg:postcode":"47274",
    "sg:province":"IN",
    "wof:name":"Alcohol & Drug Abuse Program",
    "wof:placetype":"venue"
},
  "geometry": {"coordinates":[-85.90852,38.948579],"type":"Point"}
}