{
  "type": "Feature",
  "properties": {
    "iso:country":"US",
    "sg:address":"110 N Baldwin Ave",
    "sg:city":"Marion",
    "sg:classifiers":[
        {
            "category":"Health Services",
            "subcategory":"Doctor",
            "type":"Services"
        }
    ],
    "sg:phone":"+1 765 668 8780",
    "sg:postcode":"46952",
    "sg:province":"IN",
    "sg:tags":[
        "physician",
        "surgeon"
    ],
    "wof:name":"Thomas Haney & Assoc",
    "wof:placetype":"venue"
},
  "geometry": {"coordinates":[-85.67571599999999,40.561722],"type":"Point"}
}