{
  "type": "Feature",
  "properties": {
    "iso:country":"US",
    "sg:address":"12124 Lima Rd",
    "sg:city":"Fort Wayne",
    "sg:classifiers":[
        {
            "category":"Recreation",
            "type":"Entertainment"
        }
    ],
    "sg:phone":"+1 260 637 1551",
    "sg:postcode":"46818",
    "sg:province":"IN",
    "sg:tags":[
        "tennis",
        "court"
    ],
    "wof:name":"Pine Ridge Racquet Club",
    "wof:placetype":"venue"
},
  "geometry": {"coordinates":[-85.168161,41.19416],"type":"Point"}
}