{
  "type": "Feature",
  "properties": {
    "iso:country":"US",
    "sg:address":"2646 Highway Ave",
    "sg:city":"Highland",
    "sg:classifiers":[
        {
            "category":"Organizations",
            "subcategory":"Religious Organization",
            "type":"Services"
        }
    ],
    "sg:phone":"+1 219 838 1093",
    "sg:postcode":"46322",
    "sg:province":"IN",
    "sg:tags":[
        "church"
    ],
    "wof:name":"New Hope Women's Outreach",
    "wof:placetype":"venue"
},
  "geometry": {"coordinates":[-87.464949,41.555444],"type":"Point"}
}