{
  "type": "Feature",
  "properties": {
    "iso:country":"US",
    "sg:address":"2976 Dillard Rd",
    "sg:city":"Birdseye",
    "sg:classifiers":[
        {
            "category":"Restaurant",
            "type":"Food & Drink"
        }
    ],
    "sg:phone":"+1 812 685 2769",
    "sg:postcode":"47513",
    "sg:province":"IN",
    "wof:name":"Patoka Station Grill",
    "wof:placetype":"venue"
},
  "geometry": {"coordinates":[-86.644021,38.374141],"type":"Point"}
}