{
  "type": "Feature",
  "properties": {
    "iso:country":"US",
    "sg:address":"4541 Illinois Rd",
    "sg:city":"Fort Wayne",
    "sg:classifiers":[
        {
            "category":"Restaurant",
            "type":"Food & Drink"
        }
    ],
    "sg:phone":"+1 260 459 9090",
    "sg:postcode":"46804",
    "sg:province":"IN",
    "sg:tags":[
        "eating"
    ],
    "wof:name":"Hacienda Mexican Restaurant",
    "wof:placetype":"venue"
},
  "geometry": {"coordinates":[-85.198831,41.074429],"type":"Point"}
}