{
  "type": "Feature",
  "properties": {
    "iso:country":"US",
    "sg:address":"1910 Lafayette Ave",
    "sg:city":"Crawfordsville",
    "sg:classifiers":[
        {
            "category":"Autos & Motor Vehicles",
            "subcategory":"Automobile Sales",
            "type":"Retail Goods"
        }
    ],
    "sg:phone":"+1 765 362 6607",
    "sg:postcode":"47933",
    "sg:province":"IN",
    "sg:tags":[
        "car",
        "dealer"
    ],
    "wof:name":"Horner's Bargain Lot",
    "wof:placetype":"venue"
},
  "geometry": {"coordinates":[-86.907504,40.068057],"type":"Point"}
}