{
  "type": "Feature",
  "properties": {
    "iso:country":"US",
    "sg:address":"622 W Lake St",
    "sg:city":"Griffith",
    "sg:classifiers":[
        {
            "category":"Professional",
            "subcategory":"Lawyer & Legal Services",
            "type":"Services"
        }
    ],
    "sg:phone":"+1 219 924 7004",
    "sg:postcode":"46319",
    "sg:province":"IN",
    "sg:tags":[
        "attorney"
    ],
    "wof:name":"Gerald P Kray",
    "wof:placetype":"venue"
},
  "geometry": {"coordinates":[-87.434791,41.526521],"type":"Point"}
}