{
  "type": "Feature",
  "properties": {
    "iso:country":"US",
    "sg:address":"501 N 13th St",
    "sg:city":"Terre Haute",
    "sg:classifiers":[
        {
            "category":"Retail",
            "subcategory":"Auto Repair",
            "type":"Services"
        }
    ],
    "sg:phone":"+1 812 232 9337",
    "sg:postcode":"47807",
    "sg:province":"IN",
    "sg:tags":[
        "body",
        "automobile",
        "painting"
    ],
    "wof:name":"Martin Collision Repair Ctr",
    "wof:placetype":"venue"
},
  "geometry": {"coordinates":[-87.39773599999999,39.473454],"type":"Point"}
}