{
  "type": "Feature",
  "properties": {
    "iso:country":"US",
    "sg:address":"386 S Main St",
    "sg:city":"Franklin",
    "sg:classifiers":[
        {
            "category":"Freight",
            "type":"Transportation"
        }
    ],
    "sg:phone":"+1 317 738 4783",
    "sg:postcode":"46131",
    "sg:province":"IN",
    "sg:tags":[
        "commercial",
        "storage"
    ],
    "wof:name":"Heartland Storage",
    "wof:placetype":"venue"
},
  "geometry": {"coordinates":[-86.055204,39.475982],"type":"Point"}
}