{
  "type": "Feature",
  "properties": {
    "iso:country":"US",
    "sg:address":"1240 Meridian St",
    "sg:city":"Anderson",
    "sg:classifiers":[
        {
            "category":"Real Estate",
            "subcategory":"Real Estate Services",
            "type":"Services"
        }
    ],
    "sg:phone":"+1 765 640 9999",
    "sg:postcode":"46016",
    "sg:province":"IN",
    "sg:tags":[
        "company",
        "title"
    ],
    "wof:name":"Guarantee Title & Trust Co",
    "wof:placetype":"venue"
},
  "geometry": {"coordinates":[-85.679129,40.103536],"type":"Point"}
}