{
  "type": "Feature",
  "properties": {
    "iso:country":"US",
    "sg:address":"1100 College Ave",
    "sg:city":"Terre Haute",
    "sg:classifiers":[
        {
            "category":"Building & Trades",
            "subcategory":"Construction",
            "type":"Services"
        }
    ],
    "sg:phone":"+1 812 232 9904",
    "sg:postcode":"47802",
    "sg:province":"IN",
    "sg:tags":[
        "fence",
        "contractor"
    ],
    "wof:name":"Quality Fence Co",
    "wof:placetype":"venue"
},
  "geometry": {"coordinates":[-87.40105800000001,39.455611],"type":"Point"}
}