{
  "type": "Feature",
  "properties": {
    "iso:country":"US",
    "sg:address":"5019 Fieldstone Trce",
    "sg:city":"Indianapolis",
    "sg:classifiers":[
        {
            "category":"Banks & Credit Unions",
            "subcategory":"Financial Services",
            "type":"Services"
        }
    ],
    "sg:phone":"+1 317 387 0543",
    "sg:postcode":"46254",
    "sg:province":"IN",
    "sg:tags":[
        "company",
        "holding"
    ],
    "wof:name":"Hudson Holdings Ltd",
    "wof:placetype":"venue"
},
  "geometry": {"coordinates":[-86.29293,39.842826],"type":"Point"}
}