{
  "type": "Feature",
  "properties": {
    "iso:country":"US",
    "sg:address":"717 E Chicago Ave",
    "sg:city":"East Chicago",
    "sg:classifiers":[
        {
            "category":"Professional",
            "subcategory":"Business Services",
            "type":"Services"
        }
    ],
    "sg:phone":"+1 219 972 4584",
    "sg:postcode":"46312",
    "sg:province":"IN",
    "wof:name":"Ameritech",
    "wof:placetype":"venue"
},
  "geometry": {"coordinates":[-87.463222,41.629175],"type":"Point"}
}