{
  "type": "Feature",
  "properties": {
    "iso:country":"US",
    "sg:address":"3391 W State Rd 28",
    "sg:city":"West Lebanon",
    "sg:classifiers":[
        {
            "category":"Home & Garden",
            "subcategory":"Hardware",
            "type":"Retail Goods"
        }
    ],
    "sg:phone":"+1 765 893 8888",
    "sg:postcode":"47991",
    "sg:province":"IN",
    "wof:name":"Powell Ace Home Ctr",
    "wof:placetype":"venue"
},
  "geometry": {"coordinates":[-87.383624,40.280013],"type":"Point"}
}