{
  "type": "Feature",
  "properties": {
    "iso:country":"US",
    "sg:address":"1418 Camellia Dr",
    "sg:city":"Munster",
    "sg:classifiers":[
        {
            "category":"Professional",
            "subcategory":"Computer Services",
            "type":"Services"
        }
    ],
    "sg:phone":"+1 219 934 9202",
    "sg:postcode":"46321",
    "sg:province":"IN",
    "wof:name":"Doss Networking",
    "wof:placetype":"venue"
},
  "geometry": {"coordinates":[-87.492465,41.538391],"type":"Point"}
}