{
  "type": "Feature",
  "properties": {
    "iso:country":"US",
    "sg:address":"104 N Main St",
    "sg:city":"Farmland",
    "sg:classifiers":[
        {
            "category":"Personal",
            "subcategory":"Beauty Salon",
            "type":"Services"
        }
    ],
    "sg:phone":"+1 765 468 6417",
    "sg:postcode":"47340",
    "sg:province":"IN",
    "sg:tags":[
        "shop"
    ],
    "wof:name":"Cathys Cuts & Curls",
    "wof:placetype":"venue"
},
  "geometry": {"coordinates":[-85.127667,40.189711],"type":"Point"}
}