{
  "type": "Feature",
  "properties": {
    "iso:country":"US",
    "sg:address":"55 Burlington Beach Rd",
    "sg:city":"Valparaiso",
    "sg:classifiers":[
        {
            "category":"Manufacturing",
            "subcategory":"Printing",
            "type":"Manufacturing & Wholesale Goods"
        }
    ],
    "sg:phone":"+1 219 477 1800",
    "sg:postcode":"46383",
    "sg:province":"IN",
    "sg:tags":[
        "publisher"
    ],
    "wof:name":"Onelight Productions",
    "wof:placetype":"venue"
},
  "geometry": {"coordinates":[-87.065699,41.507177],"type":"Point"}
}