{
  "type": "Feature",
  "properties": {
    "addr:full":"9750 Indiana Pkwy Munster IN 46321",
    "addr:housenumber":"9750",
    "addr:postcode":"46321",
    "addr:street":"Indiana Pkwy",
    "iso:country":"US",
    "sg:address":"9750 Indiana Pkwy",
    "sg:city":"Munster",
    "sg:classifiers":[
        {
            "category":"Food & Beverages",
            "subcategory":"Groceries & Convenience Stores",
            "type":"Retail Goods"
        }
    ],
    "sg:phone":"+1 219 924 7810",
    "sg:postcode":"46321",
    "sg:province":"IN",
    "sg:tags":[
        "product"
    ],
    "wof:name":"L J Foods Inc",
    "wof:placetype":"venue"
},
  "geometry": {"coordinates":[-87.515739,41.537265],"type":"Point"}
}