{
  "type": "Feature",
  "properties": {
    "addr:full":"9002 N State Rd 9 Morristown IN 46161",
    "addr:housenumber":"9002",
    "addr:postcode":"46161",
    "addr:street":"N State Rd 9",
    "iso:country":"US",
    "sg:address":"9002 N State Rd 9",
    "sg:city":"Morristown",
    "sg:classifiers":[
        {
            "category":"Real Estate",
            "subcategory":"Real Estate Operator",
            "type":"Services"
        }
    ],
    "sg:phone":"+1 765 763 6062",
    "sg:postcode":"46161",
    "sg:province":"IN",
    "sg:tags":[
        "property",
        "lessor"
    ],
    "wof:name":"Aaron Hatton",
    "wof:placetype":"venue"
},
  "geometry": {"coordinates":[-85.77270799999999,39.65198],"type":"Point"}
}