{
  "type": "Feature",
  "properties": {
    "iso:country":"US",
    "sg:address":"2618 E 57th St",
    "sg:city":"Indianapolis",
    "sg:classifiers":[
        {
            "category":"Professional",
            "type":"Services"
        }
    ],
    "sg:phone":"+1 317 251 6259",
    "sg:postcode":"46220",
    "sg:province":"IN",
    "wof:name":"Robert E Hartsock Studio",
    "wof:placetype":"venue"
},
  "geometry": {"coordinates":[-86.118336,39.856717],"type":"Point"}
}