{
  "type": "Feature",
  "properties": {
    "iso:country":"US",
    "sg:address":"410 E 6th St",
    "sg:city":"Huntingburg",
    "sg:classifiers":[
        {
            "category":"Wholesale",
            "subcategory":"Farm Supplies",
            "type":"Manufacturing & Wholesale Goods"
        }
    ],
    "sg:phone":"+1 812 683 2119",
    "sg:postcode":"47542",
    "sg:province":"IN",
    "wof:name":"Veterinary & Poultry Supply",
    "wof:placetype":"venue"
},
  "geometry": {"coordinates":[-86.95531200000001,38.298949],"type":"Point"}
}