{
  "type": "Feature",
  "properties": {
    "iso:country":"US",
    "sg:address":"581 Cheyenne Ct",
    "sg:city":"Westville",
    "sg:classifiers":[
        {
            "category":"Professional",
            "subcategory":"Management & Consulting",
            "type":"Services"
        }
    ],
    "sg:phone":"+1 219 926 4860",
    "sg:postcode":"46391",
    "sg:province":"IN",
    "wof:name":"Stevens Enterprises",
    "wof:placetype":"venue"
},
  "geometry": {"coordinates":[-86.95156,41.545032],"type":"Point"}
}