{
  "type": "Feature",
  "properties": {
    "addr:full":"886 Hummingbird Ln Columbus IN 47203",
    "addr:housenumber":"886",
    "addr:postcode":"47203",
    "addr:street":"Hummingbird Ln",
    "iso:country":"US",
    "sg:address":"886 Hummingbird Ln",
    "sg:city":"Columbus",
    "sg:classifiers":[
        {
            "category":"Professional",
            "type":"Services"
        }
    ],
    "sg:phone":"+1 812 378 5363",
    "sg:postcode":"47203",
    "sg:province":"IN",
    "sg:tags":[
        "establishment"
    ],
    "wof:name":"Chang Group Corp",
    "wof:placetype":"venue"
},
  "geometry": {"coordinates":[-85.915707,39.242477],"type":"Point"}
}