{
  "type": "Feature",
  "properties": {
    "iso:country":"US",
    "sg:address":"51425 State Rd 19",
    "sg:city":"Elkhart",
    "sg:classifiers":[
        {
            "category":"Bars & Pubs",
            "type":"Food & Drink"
        }
    ],
    "sg:phone":"+1 574 262 2237",
    "sg:postcode":"46514",
    "sg:province":"IN",
    "wof:name":"Jimmy's",
    "wof:placetype":"venue"
},
  "geometry": {"coordinates":[-85.975131,41.747601],"type":"Point"}
}