{
  "type": "Feature",
  "properties": {
    "iso:country":"US",
    "sg:address":"2444 Getz Rd",
    "sg:city":"Fort Wayne",
    "sg:classifiers":[
        {
            "category":"Personal",
            "subcategory":"Beauty Salon",
            "type":"Services"
        }
    ],
    "sg:phone":"+1 260 435 1460",
    "sg:postcode":"46804",
    "sg:province":"IN",
    "wof:name":"Covington Hair Designers",
    "wof:placetype":"venue"
},
  "geometry": {"coordinates":[-85.219431,41.061048],"type":"Point"}
}