{
  "type": "Feature",
  "properties": {
    "addr:full":"1712 W Washington St Indianapolis IN 46222",
    "addr:housenumber":"1712",
    "addr:postcode":"46222",
    "addr:street":"W Washington St",
    "iso:country":"US",
    "sg:address":"1712 W Washington St",
    "sg:city":"Indianapolis",
    "sg:classifiers":[
        {
            "category":"Bars & Pubs",
            "type":"Food & Drink"
        }
    ],
    "sg:phone":"+1 317 632 0522",
    "sg:postcode":"46222",
    "sg:province":"IN",
    "wof:name":"Tom Inkoff Tavern",
    "wof:placetype":"venue"
},
  "geometry": {"coordinates":[-86.1918,39.766843],"type":"Point"}
}