{
  "type": "Feature",
  "properties": {
    "iso:country":"US",
    "sg:address":"1356 E Altgeld St",
    "sg:city":"South Bend",
    "sg:classifiers":[
        {
            "category":"Building & Trades",
            "subcategory":"Cleaning & Sanitation",
            "type":"Services"
        }
    ],
    "sg:phone":"+1 574 288 4378",
    "sg:postcode":"46614",
    "sg:province":"IN",
    "sg:tags":[
        "maintenance"
    ],
    "wof:name":"R W Foster Floor Service",
    "wof:placetype":"venue"
},
  "geometry": {"coordinates":[-86.226191,41.650122],"type":"Point"}
}