{
  "type": "Feature",
  "properties": {
    "iso:country":"US",
    "sg:address":"1232 Meridian St",
    "sg:city":"Anderson",
    "sg:classifiers":[
        {
            "category":"Professional",
            "subcategory":"Management & Consulting",
            "type":"Services"
        }
    ],
    "sg:phone":"+1 765 644 7177",
    "sg:postcode":"46016",
    "sg:province":"IN",
    "sg:tags":[
        "marketing",
        "consultant"
    ],
    "wof:name":"Baylor & Assoc",
    "wof:placetype":"venue"
},
  "geometry": {"coordinates":[-85.679128,40.103455],"type":"Point"}
}