{
  "type": "Feature",
  "properties": {
    "iso:country":"US",
    "sg:address":"3012 N Granville Ave",
    "sg:city":"Muncie",
    "sg:classifiers":[
        {
            "category":"Personal",
            "subcategory":"Beauty Salon",
            "type":"Services"
        }
    ],
    "sg:phone":"+1 765 282 4797",
    "sg:postcode":"47303",
    "sg:province":"IN",
    "sg:tags":[
        "shop"
    ],
    "wof:name":"G G & M Hair & Beauty Spa",
    "wof:placetype":"venue"
},
  "geometry": {"coordinates":[-85.374828,40.218326],"type":"Point"}
}