{
  "type": "Feature",
  "properties": {
    "iso:country":"US",
    "sg:address":"1480 Winchester Rd",
    "sg:city":"Decatur",
    "sg:classifiers":[
        {
            "category":"Restaurant",
            "type":"Food & Drink"
        }
    ],
    "sg:phone":"+1 260 728 4008",
    "sg:postcode":"46733",
    "sg:province":"IN",
    "wof:name":"El Camino Real Iv",
    "wof:placetype":"venue"
},
  "geometry": {"coordinates":[-84.937903,40.845416],"type":"Point"}
}