{
  "type": "Feature",
  "properties": {
    "iso:country":"US",
    "sg:address":"19 W Main St",
    "sg:city":"Plainville",
    "sg:classifiers":[
        {
            "category":"Manufacturing",
            "subcategory":"Tools & Machinery",
            "type":"Manufacturing & Wholesale Goods"
        }
    ],
    "sg:phone":"+1 812 687 7203",
    "sg:postcode":"47501",
    "sg:province":"IN",
    "sg:tags":[
        "machine",
        "shop"
    ],
    "wof:name":"C & S Machine Inc",
    "wof:placetype":"venue"
},
  "geometry": {"coordinates":[-87.176395,38.656842],"type":"Point"}
}