{
  "type": "Feature",
  "properties": {
    "iso:country":"US",
    "sg:address":"11594 Newbridge Ct",
    "sg:city":"Carmel",
    "sg:classifiers":[
        {
            "category":"Airline",
            "type":"Transportation"
        }
    ],
    "sg:phone":"+1 317 569 9359",
    "sg:postcode":"46032",
    "sg:province":"IN",
    "sg:tags":[
        "aircraft-charter",
        "leasing",
        "rental"
    ],
    "wof:name":"Skycorp Inc",
    "wof:placetype":"venue"
},
  "geometry": {"coordinates":[-86.198594,39.955058],"type":"Point"}
}