{
  "type": "Feature",
  "properties": {
    "addr:full":"307 Sycamore St Newburgh IN 47630",
    "addr:housenumber":"307",
    "addr:postcode":"47630",
    "addr:street":"Sycamore St",
    "iso:country":"US",
    "sg:address":"307 Sycamore St",
    "sg:city":"Newburgh",
    "sg:classifiers":[
        {
            "category":"Arts & Performance",
            "subcategory":"Theater",
            "type":"Entertainment"
        }
    ],
    "sg:phone":"+1 812 490 3658",
    "sg:postcode":"47630",
    "sg:province":"IN",
    "sg:tags":[
        "group"
    ],
    "wof:name":"Evansville Haunted House Inc",
    "wof:placetype":"venue"
},
  "geometry": {"coordinates":[-87.40311800000001,37.946321],"type":"Point"}
}