{
  "type": "Feature",
  "properties": {
    "addr:full":"504 E Thompson St Edinburgh IN 46124",
    "addr:housenumber":"504",
    "addr:postcode":"46124",
    "addr:street":"E Thompson St",
    "iso:country":"US",
    "sg:address":"504 E Thompson St",
    "sg:city":"Edinburgh",
    "sg:classifiers":[
        {
            "category":"Real Estate",
            "subcategory":"Real Estate Operator",
            "type":"Services"
        }
    ],
    "sg:phone":"+1 812 526 5167",
    "sg:postcode":"46124",
    "sg:province":"IN",
    "sg:tags":[
        "building",
        "apartment"
    ],
    "wof:name":"Decoursey Realty",
    "wof:placetype":"venue"
},
  "geometry": {"coordinates":[-85.959056,39.353533],"type":"Point"}
}