{
  "type": "Feature",
  "properties": {
    "addr:full":"1501 E Market St Nappanee IN 46550",
    "addr:housenumber":"1501",
    "addr:postcode":"46550",
    "addr:street":"E Market St",
    "iso:country":"US",
    "sg:address":"1501 E Market St",
    "sg:city":"Nappanee",
    "sg:classifiers":[
        {
            "category":"Travel",
            "subcategory":"Hotels & Motels",
            "type":"Entertainment"
        }
    ],
    "sg:phone":"+1 574 773 3193",
    "sg:postcode":"46550",
    "sg:province":"IN",
    "sg:tags":[
        "operation"
    ],
    "wof:name":"Shamrock Motel",
    "wof:placetype":"venue"
},
  "geometry": {"coordinates":[-85.984371,41.442598],"type":"Point"}
}