{
  "type": "Feature",
  "properties": {
    "addr:full":"1037 S Main St Elkhart IN 46516",
    "addr:housenumber":"1037",
    "addr:postcode":"46516",
    "addr:street":"S Main St",
    "iso:country":"US",
    "sg:address":"1037 S Main St",
    "sg:city":"Elkhart",
    "sg:classifiers":[
        {
            "category":"Shopping",
            "subcategory":"Computers & Home Electronics",
            "type":"Retail Goods"
        }
    ],
    "sg:phone":"+1 574 293 2842",
    "sg:postcode":"46516",
    "sg:province":"IN",
    "sg:tags":[
        "high",
        "fidelity",
        "stereophonic"
    ],
    "wof:name":"El Cart Stero",
    "wof:placetype":"venue"
},
  "geometry": {"coordinates":[-85.965806,41.677971],"type":"Point"}
}