{
  "type": "Feature",
  "properties": {
    "iso:country":"US",
    "sg:address":"1158 S 17th St",
    "sg:city":"Kokomo",
    "sg:classifiers":[
        {
            "category":"Shopping",
            "subcategory":"Clothing, Apparel, & Fashions",
            "type":"Retail Goods"
        }
    ],
    "sg:phone":"+1 765 459 5992",
    "sg:postcode":"46902",
    "sg:province":"IN",
    "sg:tags":[
        "item",
        "boutique"
    ],
    "sg:website":"www.claires.com",
    "wof:name":"Claire's Boutique",
    "wof:placetype":"venue"
},
  "geometry": {"coordinates":[-86.110781,40.474525],"type":"Point"}
}