{
  "type": "Feature",
  "properties": {
    "iso:country":"US",
    "sg:address":"2516 E Pulaski St",
    "sg:city":"Star City",
    "sg:classifiers":[
        {
            "category":"Building & Trades",
            "subcategory":"Cleaning & Sanitation",
            "type":"Services"
        }
    ],
    "sg:phone":"+1 574 595 7640",
    "sg:postcode":"46985",
    "sg:province":"IN",
    "sg:tags":[
        "snow",
        "removal"
    ],
    "wof:name":"Gunter's Lawn & Asphalt Mntnc",
    "wof:placetype":"venue"
},
  "geometry": {"coordinates":[-86.554883,40.970465],"type":"Point"}
}