{
  "type": "Feature",
  "properties": {
    "iso:country":"US",
    "sg:address":"6421 Cathedral Oaks Pl",
    "sg:city":"Fort Wayne",
    "sg:classifiers":[
        {
            "category":"Food & Beverages",
            "subcategory":"Candy",
            "type":"Retail Goods"
        }
    ],
    "sg:phone":"+1 260 485 1113",
    "sg:postcode":"46835",
    "sg:province":"IN",
    "sg:tags":[
        "confectionery"
    ],
    "wof:name":"Candy Bouquet",
    "wof:placetype":"venue"
},
  "geometry": {"coordinates":[-85.03947599999999,41.141447],"type":"Point"}
}