{
  "type": "Feature",
  "properties": {
    "iso:country":"US",
    "sg:address":"41 N Post Rd",
    "sg:city":"Indianapolis",
    "sg:classifiers":[
        {
            "category":"Personal",
            "subcategory":"Tattoo Parlor",
            "type":"Services"
        }
    ],
    "sg:phone":"+1 317 890 8282",
    "sg:postcode":"46219",
    "sg:province":"IN",
    "sg:tags":[
        "tattooing"
    ],
    "wof:name":"Monster Ink",
    "wof:placetype":"venue"
},
  "geometry": {"coordinates":[-86.009176,39.77624],"type":"Point"}
}