{
  "type": "Feature",
  "properties": {
    "addr:full":"360 N State St Harrison IN 47060",
    "addr:housenumber":"360",
    "addr:postcode":"47060",
    "addr:street":"N State St",
    "iso:country":"US",
    "sg:address":"360 N State St",
    "sg:city":"Harrison",
    "sg:classifiers":[
        {
            "category":"Organizations",
            "subcategory":"Religious Organization",
            "type":"Services"
        }
    ],
    "sg:phone":"+1 513 367 4225",
    "sg:postcode":"47060",
    "sg:province":"IN",
    "sg:tags":[
        "church"
    ],
    "wof:name":"Bible Baptist Fellowship",
    "wof:placetype":"venue"
},
  "geometry": {"coordinates":[-84.81979200000001,39.268457],"type":"Point"}
}