{
  "type": "Feature",
  "properties": {
    "iso:country":"US",
    "sg:address":"122 W Main St",
    "sg:city":"Warsaw",
    "sg:classifiers":[
        {
            "category":"Real Estate",
            "subcategory":"Real Estate Services",
            "type":"Services"
        }
    ],
    "sg:phone":"+1 574 267 5138",
    "sg:postcode":"46580",
    "sg:province":"IN",
    "wof:name":"Warsaw Abstract & Title Corp",
    "wof:placetype":"venue"
},
  "geometry": {"coordinates":[-85.857731,41.239168],"type":"Point"}
}