{
  "type": "Feature",
  "properties": {
    "addr:full":"2730 Maplecrest Rd Fort Wayne IN 46815",
    "addr:housenumber":"2730",
    "addr:postcode":"46815",
    "addr:street":"Maplecrest Rd",
    "iso:country":"US",
    "sg:address":"2730 Maplecrest Rd",
    "sg:city":"Fort Wayne",
    "sg:classifiers":[
        {
            "category":"Shopping",
            "subcategory":"Department Store",
            "type":"Retail Goods"
        }
    ],
    "sg:phone":"+1 260 485 4799",
    "sg:postcode":"46815",
    "sg:province":"IN",
    "sg:tags":[
        "shop"
    ],
    "wof:name":"Dollar General",
    "wof:placetype":"venue"
},
  "geometry": {"coordinates":[-85.06031299999999,41.103048],"type":"Point"}
}