{
  "type": "Feature",
  "properties": {
    "iso:country":"US",
    "sg:address":"13150 W Co Rd 300 N",
    "sg:city":"Yorktown",
    "sg:classifiers":[
        {
            "category":"Professional",
            "subcategory":"Management & Consulting",
            "type":"Services"
        }
    ],
    "sg:phone":"+1 765 759 9719",
    "sg:postcode":"47396",
    "sg:province":"IN",
    "sg:tags":[
        "business"
    ],
    "wof:name":"Richard W Howe",
    "wof:placetype":"venue"
},
  "geometry": {"coordinates":[-85.541141,40.233419],"type":"Point"}
}