{
  "type": "Feature",
  "properties": {
    "iso:country":"US",
    "sg:address":"218 S Meridian St",
    "sg:city":"Portland",
    "sg:classifiers":[
        {
            "category":"Personal",
            "subcategory":"Barber",
            "type":"Services"
        }
    ],
    "sg:phone":"+1 260 726 2483",
    "sg:postcode":"47371",
    "sg:province":"IN",
    "sg:tags":[
        "shop"
    ],
    "wof:name":"Linus Mescher",
    "wof:placetype":"venue"
},
  "geometry": {"coordinates":[-84.977909,40.431694],"type":"Point"}
}