{
  "type": "Feature",
  "properties": {
    "iso:country":"US",
    "sg:address":"2401 N Walnut St",
    "sg:city":"Muncie",
    "sg:classifiers":[
        {
            "category":"Real Estate",
            "subcategory":"Real Estate Operator",
            "type":"Services"
        }
    ],
    "sg:phone":"+1 765 288 6100",
    "sg:postcode":"47303",
    "sg:province":"IN",
    "sg:tags":[
        "development",
        "apartment"
    ],
    "wof:name":"Chateau Apartments",
    "wof:placetype":"venue"
},
  "geometry": {"coordinates":[-85.386997,40.214939],"type":"Point"}
}