{
  "type": "Feature",
  "properties": {
    "iso:country":"US",
    "sg:address":"1212 Garden St",
    "sg:city":"Kendallville",
    "sg:classifiers":[
        {
            "category":"Building & Trades",
            "subcategory":"Pest Control",
            "type":"Services"
        }
    ],
    "sg:phone":"+1 260 347 9672",
    "sg:postcode":"46755",
    "sg:province":"IN",
    "wof:name":"Accurate Pest Control Svc",
    "wof:placetype":"venue"
},
  "geometry": {"coordinates":[-85.258441,41.432745],"type":"Point"}
}