{
  "type": "Feature",
  "properties": {
    "iso:country":"US",
    "sg:address":"11771 Technology Dr",
    "sg:city":"Fishers",
    "sg:classifiers":[
        {
            "category":"Autos & Motor Vehicles",
            "subcategory":"Auto Supplies",
            "type":"Retail Goods"
        }
    ],
    "sg:phone":"+1 317 915 8588",
    "sg:postcode":"46038",
    "sg:province":"IN",
    "sg:tags":[
        "stereo",
        "automobile",
        "coating",
        "system",
        "tinting",
        "glass",
        "window",
        "part",
        "radio"
    ],
    "wof:name":"American Customs Inc",
    "wof:placetype":"venue"
},
  "geometry": {"coordinates":[-86.00715599999999,39.961182],"type":"Point"}
}