{
  "type": "Feature",
  "properties": {
    "iso:country":"US",
    "sg:address":"10305 N Alford Rd",
    "sg:city":"Fortville",
    "sg:classifiers":[
        {
            "category":"Building & Trades",
            "subcategory":"Construction",
            "type":"Services"
        }
    ],
    "sg:phone":"+1 765 778 8195",
    "sg:postcode":"46040",
    "sg:province":"IN",
    "sg:tags":[
        "roofing",
        "contractor"
    ],
    "wof:name":"G G Roofing & Exteriors",
    "wof:placetype":"venue"
},
  "geometry": {"coordinates":[-85.78195100000001,39.934218],"type":"Point"}
}