{
  "type": "Feature",
  "properties": {
    "iso:country":"US",
    "sg:address":"13540 N US Hwy 31",
    "sg:city":"Edinburgh",
    "sg:classifiers":[
        {
            "category":"Real Estate",
            "subcategory":"Real Estate Operator",
            "type":"Services"
        }
    ],
    "sg:phone":"+1 812 526 6891",
    "sg:postcode":"46124",
    "sg:province":"IN",
    "sg:tags":[
        "mobile",
        "home",
        "community"
    ],
    "wof:name":"Driftside Mobile Home Cmnty",
    "wof:placetype":"venue"
},
  "geometry": {"coordinates":[-85.971611,39.325738],"type":"Point"}
}