{
  "type": "Feature",
  "properties": {
    "addr:full":"2360 Grant St Gary IN 46404",
    "addr:housenumber":"2360",
    "addr:postcode":"46404",
    "addr:street":"Grant St Gary",
    "iso:country":"US",
    "sg:address":"2360 Grant St",
    "sg:city":"Gary",
    "sg:classifiers":[
        {
            "category":"Wholesale",
            "subcategory":"Machinery & Supplies",
            "type":"Manufacturing & Wholesale Goods"
        }
    ],
    "sg:phone":"+1 219 944 9224",
    "sg:postcode":"46404",
    "sg:province":"IN",
    "sg:tags":[
        "washing",
        "mach"
    ],
    "wof:name":"Barnes Washer Repair & Parts",
    "wof:placetype":"venue"
},
  "geometry": {"coordinates":[-87.35623099999999,41.576247],"type":"Point"}
}