{
  "type": "Feature",
  "properties": {
    "iso:country":"US",
    "sg:address":"8721 Droege Rd",
    "sg:city":"Decatur",
    "sg:classifiers":[
        {
            "category":"Building & Trades",
            "subcategory":"Landscaping Services",
            "type":"Services"
        }
    ],
    "sg:phone":"+1 260 639 6389",
    "sg:postcode":"46733",
    "sg:province":"IN",
    "sg:tags":[
        "lawn",
        "maintenance",
        "grounds"
    ],
    "wof:name":"Don's Lawn Svc & Landscpg Inc",
    "wof:placetype":"venue"
},
  "geometry": {"coordinates":[-85.02697499999999,40.925632],"type":"Point"}
}