{
  "type": "Feature",
  "properties": {
    "iso:country":"US",
    "sg:address":"600 N Cook Rd",
    "sg:city":"Muncie",
    "sg:classifiers":[
        {
            "category":"Real Estate",
            "subcategory":"Real Estate Agent",
            "type":"Services"
        }
    ],
    "sg:phone":"+1 765 284 5884",
    "sg:postcode":"47303",
    "sg:province":"IN",
    "wof:name":"J V R Enterprises",
    "wof:placetype":"venue"
},
  "geometry": {"coordinates":[-85.304943,40.197767],"type":"Point"}
}