{
  "type": "Feature",
  "properties": {
    "iso:country":"US",
    "sg:address":"8501 Neu Rd",
    "sg:city":"Evansville",
    "sg:classifiers":[
        {
            "category":"Manufacturing",
            "subcategory":"Tools & Machinery",
            "type":"Manufacturing & Wholesale Goods"
        }
    ],
    "sg:phone":"+1 812 963 6677",
    "sg:postcode":"47720",
    "sg:province":"IN",
    "sg:tags":[
        "mold"
    ],
    "wof:name":"Accurate Tool & Engineering",
    "wof:placetype":"venue"
},
  "geometry": {"coordinates":[-87.653154,38.058926],"type":"Point"}
}