{
  "type": "Feature",
  "properties": {
    "iso:country":"US",
    "sg:address":"1752 W Barner St",
    "sg:city":"Frankfort",
    "sg:classifiers":[
        {
            "category":"Organizations",
            "subcategory":"Religious Organization",
            "type":"Services"
        }
    ],
    "sg:phone":"+1 765 654 5118",
    "sg:postcode":"46041",
    "sg:province":"IN",
    "wof:name":"Dale Downes Rev",
    "wof:placetype":"venue"
},
  "geometry": {"coordinates":[-86.534896,40.286394],"type":"Point"}
}