{
  "type": "Feature",
  "properties": {
    "iso:country":"US",
    "sg:address":"8440 Northcrest Cir",
    "sg:city":"Indianapolis",
    "sg:classifiers":[
        {
            "category":"Building & Trades",
            "subcategory":"Locksmith",
            "type":"Services"
        }
    ],
    "sg:phone":"+1 317 682 9126",
    "sg:postcode":"46256",
    "sg:province":"IN",
    "sg:tags":[
        "key"
    ],
    "wof:name":"24 Hour Locksmith",
    "wof:placetype":"venue"
},
  "geometry": {"coordinates":[-86.03385,39.909741],"type":"Point"}
}