{
  "type": "Feature",
  "properties": {
    "iso:country":"US",
    "sg:address":"5130 N Mechanicsburg Rd",
    "sg:city":"Middletown",
    "sg:classifiers":[
        {
            "category":"Organizations",
            "subcategory":"Religious Organization",
            "type":"Services"
        }
    ],
    "sg:phone":"+1 765 779 4796",
    "sg:postcode":"47356",
    "sg:province":"IN",
    "sg:tags":[
        "church"
    ],
    "wof:name":"Mechanicsburg Methodist Church",
    "wof:placetype":"venue"
},
  "geometry": {"coordinates":[-85.55704,40.006631],"type":"Point"}
}