{
  "type": "Feature",
  "properties": {
    "addr:full":"475 11th Ave Jasper IN 47546",
    "addr:housenumber":"475",
    "addr:postcode":"47546",
    "addr:street":"11Th Ave",
    "iso:country":"US",
    "sg:address":"475 11th Ave",
    "sg:city":"Jasper",
    "sg:classifiers":[
        {
            "category":"Retail",
            "subcategory":"Auto Repair",
            "type":"Services"
        }
    ],
    "sg:phone":"+1 812 482 3122",
    "sg:postcode":"47546",
    "sg:province":"IN",
    "sg:tags":[
        "repairing",
        "tire"
    ],
    "wof:name":"Master Tire Of Jasper",
    "wof:placetype":"venue"
},
  "geometry": {"coordinates":[-86.94049200000001,38.373687],"type":"Point"}
}