{
  "type": "Feature",
  "properties": {
    "iso:country":"US",
    "sg:address":"1815 D St",
    "sg:city":"Anderson",
    "sg:classifiers":[
        {
            "category":"Insurance",
            "subcategory":"Insurance Agent",
            "type":"Services"
        }
    ],
    "sg:phone":"+1 765 649 4240",
    "sg:postcode":"46016",
    "sg:province":"IN",
    "wof:name":"Alexander Insurance",
    "wof:placetype":"venue"
},
  "geometry": {"coordinates":[-85.655187,40.097748],"type":"Point"}
}