{
  "type": "Feature",
  "properties": {
    "iso:country":"US",
    "sg:address":"820 Lincolnway",
    "sg:city":"Laporte",
    "sg:classifiers":[
        {
            "category":"Shopping",
            "subcategory":"Used Merchandise",
            "type":"Retail Goods"
        }
    ],
    "sg:phone":"+1 219 326 7296",
    "sg:postcode":"46350",
    "sg:province":"IN",
    "sg:tags":[
        "pawnbroker"
    ],
    "wof:name":"Ameripawn",
    "wof:placetype":"venue"
},
  "geometry": {"coordinates":[-86.721335,41.611098],"type":"Point"}
}