{
  "type": "Feature",
  "properties": {
    "addr:full":"107 S 14th St Vincennes IN 47591",
    "addr:housenumber":"107",
    "addr:postcode":"47591",
    "addr:street":"S 14Th St",
    "iso:country":"US",
    "sg:address":"107 S 14th St",
    "sg:city":"Vincennes",
    "sg:phone":"+1 812 886 5482",
    "sg:postcode":"47591",
    "sg:province":"IN",
    "wof:name":"A1 Auto And Collission Rep",
    "wof:placetype":"venue"
},
  "geometry": {"coordinates":[-87.52338399999999,38.669277],"type":"Point"}
}