{
  "type": "Feature",
  "properties": {
    "iso:country":"US",
    "sg:address":"11024 Bluffton Rd",
    "sg:city":"Fort Wayne",
    "sg:classifiers":[
        {
            "category":"Autos & Motor Vehicles",
            "subcategory":"Automobile Sales",
            "type":"Retail Goods"
        }
    ],
    "sg:phone":"+1 260 478 6418",
    "sg:postcode":"46809",
    "sg:province":"IN",
    "sg:tags":[
        "truck"
    ],
    "sg:website":"www.tandrtrucksales.com",
    "wof:name":"T & R Truck Sales",
    "wof:placetype":"venue"
},
  "geometry": {"coordinates":[-85.168441,40.984729],"type":"Point"}
}