{
  "type": "Feature",
  "properties": {
    "addr:full":"2206 Lafayette Ave Crawfordsville IN 47933",
    "addr:housenumber":"2206",
    "addr:postcode":"47933",
    "addr:street":"Lafayette Ave",
    "iso:country":"US",
    "sg:address":"2206 Lafayette Ave",
    "sg:city":"Crawfordsville",
    "sg:classifiers":[
        {
            "category":"Health Services",
            "subcategory":"Chiropractor",
            "type":"Services"
        }
    ],
    "sg:phone":"+1 765 362 0123",
    "sg:postcode":"47933",
    "sg:province":"IN",
    "wof:name":"Northridge Chiropractic Clinic",
    "wof:placetype":"venue"
},
  "geometry": {"coordinates":[-86.907021,40.069441],"type":"Point"}
}