{
  "type": "Feature",
  "properties": {
    "iso:country":"US",
    "sg:address":"1601 E Main St",
    "sg:city":"Danville",
    "sg:classifiers":[
        {
            "category":"Home & Garden",
            "subcategory":"Household Appliances",
            "type":"Retail Goods"
        }
    ],
    "sg:phone":"+1 317 745 0719",
    "sg:postcode":"46122",
    "sg:province":"IN",
    "wof:name":"Ribble's Maytag Home Appliance",
    "wof:placetype":"venue"
},
  "geometry": {"coordinates":[-86.49204400000001,39.761568],"type":"Point"}
}