{
  "type": "Feature",
  "properties": {
    "iso:country":"US",
    "sg:address":"2903 Westbrook Dr",
    "sg:city":"Fort Wayne",
    "sg:classifiers":[
        {
            "category":"Real Estate",
            "subcategory":"Real Estate Operator",
            "type":"Services"
        }
    ],
    "sg:phone":"+1 260 483 2738",
    "sg:postcode":"46805",
    "sg:province":"IN",
    "sg:tags":[
        "apartment"
    ],
    "wof:name":"Centlivre Village Apartments",
    "wof:placetype":"venue"
},
  "geometry": {"coordinates":[-85.140161,41.102754],"type":"Point"}
}