{
  "type": "Feature",
  "properties": {
    "iso:country":"US",
    "sg:address":"218 W Market St",
    "sg:city":"Jeffersonville",
    "sg:classifiers":[
        {
            "category":"Building & Trades",
            "subcategory":"Construction",
            "type":"Services"
        }
    ],
    "sg:phone":"+1 502 494 8160",
    "sg:postcode":"47130",
    "sg:province":"IN",
    "sg:tags":[
        "finishing",
        "wood"
    ],
    "wof:name":"Circle M",
    "wof:placetype":"venue"
},
  "geometry": {"coordinates":[-85.74114,38.269904],"type":"Point"}
}