{
  "type": "Feature",
  "properties": {
    "addr:full":"9401 Melton Rd Gary IN 46403",
    "addr:housenumber":"9401",
    "addr:postcode":"46403",
    "addr:street":"Melton Rd",
    "iso:country":"US",
    "sg:address":"9401 Melton Rd",
    "sg:city":"Gary",
    "sg:classifiers":[
        {
            "category":"Wholesale",
            "subcategory":"Toys & Hobbies",
            "type":"Manufacturing & Wholesale Goods"
        }
    ],
    "sg:phone":"+1 219 938 5559",
    "sg:postcode":"46403",
    "sg:province":"IN",
    "sg:tags":[
        "firework"
    ],
    "wof:name":"Lightning Fireworks",
    "wof:placetype":"venue"
},
  "geometry": {"coordinates":[-87.23711900000001,41.594913],"type":"Point"}
}