{
  "type": "Feature",
  "properties": {
    "iso:country":"US",
    "sg:address":"701 US Hwy 31",
    "sg:city":"Lapaz",
    "sg:classifiers":[
        {
            "category":"Autos & Motor Vehicles",
            "subcategory":"Automobile Sales",
            "type":"Retail Goods"
        }
    ],
    "sg:phone":"+1 574 784 2994",
    "sg:postcode":"46563",
    "sg:province":"IN",
    "sg:tags":[
        "car",
        "dealer"
    ],
    "wof:name":"Gold Coast Motors",
    "wof:placetype":"venue"
},
  "geometry": {"coordinates":[-86.30946900000001,41.453326],"type":"Point"}
}