{
  "type": "Feature",
  "properties": {
    "iso:country":"US",
    "sg:address":"1224 N Salisbury St",
    "sg:city":"West Lafayette",
    "sg:classifiers":[
        {
            "category":"Professional",
            "type":"Services"
        }
    ],
    "sg:phone":"+1 765 743 0400",
    "sg:postcode":"47906",
    "sg:province":"IN",
    "sg:tags":[
        "consulting",
        "scientific"
    ],
    "wof:name":"Gabriele Ogg",
    "wof:placetype":"venue"
},
  "geometry": {"coordinates":[-86.906032,40.436818],"type":"Point"}
}