{
  "type": "Feature",
  "properties": {
    "iso:country":"US",
    "sg:address":"55 S State Ave",
    "sg:city":"Indianapolis",
    "sg:classifiers":[
        {
            "category":"Professional",
            "type":"Services"
        }
    ],
    "sg:phone":"+1 317 262 5014",
    "sg:postcode":"46201",
    "sg:province":"IN",
    "sg:tags":[
        "consulting",
        "chemist"
    ],
    "wof:name":"Support Technology Corp",
    "wof:placetype":"venue"
},
  "geometry": {"coordinates":[-86.13053600000001,39.765141],"type":"Point"}
}