{
  "type": "Feature",
  "properties": {
    "iso:country":"US",
    "sg:address":"9 W Main St",
    "sg:city":"Mooresville",
    "sg:classifiers":[
        {
            "category":"Professional",
            "subcategory":"Lawyer & Legal Services",
            "type":"Services"
        }
    ],
    "sg:phone":"+1 317 831 4466",
    "sg:postcode":"46158",
    "sg:province":"IN",
    "sg:tags":[
        "attorney",
        "business",
        "real estate",
        "planning",
        "family",
        "law"
    ],
    "wof:name":"Harris & Currens",
    "wof:placetype":"venue"
},
  "geometry": {"coordinates":[-86.375125,39.612782],"type":"Point"}
}