{
  "type": "Feature",
  "properties": {
    "addr:full":"705 W Lake Rd W Scottsburg IN 47170",
    "addr:housenumber":"705",
    "addr:postcode":"47170",
    "addr:street":"W Lake Rd W",
    "iso:country":"US",
    "sg:address":"705 W Lake Rd W",
    "sg:city":"Scottsburg",
    "sg:classifiers":[
        {
            "category":"Restaurant",
            "type":"Food & Drink"
        }
    ],
    "sg:phone":"+1 812 754 0411",
    "sg:postcode":"47170",
    "sg:province":"IN",
    "sg:tags":[
        "pizza"
    ],
    "sg:website":"www.caseys.com",
    "wof:name":"Casey's Carry Out Pizza",
    "wof:placetype":"venue"
},
  "geometry": {"coordinates":[-85.791065,38.67077],"type":"Point"}
}