{
  "type": "Feature",
  "properties": {
    "addr:full":"5958 Co Rd 56 Saint Joe IN 46785",
    "addr:housenumber":"5958;56",
    "addr:postcode":"46785",
    "addr:street":"Co Rd",
    "iso:country":"US",
    "sg:address":"5958 Co Rd 56",
    "sg:city":"Saint Joe",
    "sg:phone":"+1 260 337 5515",
    "sg:postcode":"46785",
    "sg:province":"IN",
    "sg:tags":[
        "real",
        "lessor",
        "farm",
        "corn",
        "soybean",
        "property"
    ],
    "wof:name":"Richard Crow",
    "wof:placetype":"venue"
},
  "geometry": {"coordinates":[-84.914349,41.326724],"type":"Point"}
}