{
  "type": "Feature",
  "properties": {
    "iso:country":"US",
    "sg:address":"5747 N Post Rd",
    "sg:city":"Indianapolis",
    "sg:classifiers":[
        {
            "category":"Building & Trades",
            "subcategory":"Pest Control",
            "type":"Services"
        }
    ],
    "sg:phone":"+1 317 547 1308",
    "sg:postcode":"46216",
    "sg:province":"IN",
    "sg:website":"http://www.circlecitypestcontrol.com",
    "wof:name":"Circle City Pest Control Co",
    "wof:placetype":"venue"
},
  "geometry": {"coordinates":[-86.01038,39.856293],"type":"Point"}
}