{
  "type": "Feature",
  "properties": {
    "addr:full":"16460 Lincoln Hwy Plymouth IN 46563",
    "addr:housenumber":"16460",
    "addr:postcode":"46563",
    "addr:street":"Lincoln Hwy",
    "iso:country":"US",
    "sg:address":"16460 Lincoln Hwy",
    "sg:city":"Plymouth",
    "sg:classifiers":[
        {
            "category":"Autos & Motor Vehicles",
            "subcategory":"Fuel & Gas Station",
            "type":"Retail Goods"
        }
    ],
    "sg:phone":"+1 574 936 8843",
    "sg:postcode":"46563",
    "sg:province":"IN",
    "sg:tags":[
        "oil"
    ],
    "wof:name":"Plymouth Shell Hot Stuff Pizza",
    "wof:placetype":"venue"
},
  "geometry": {"coordinates":[-86.367226,41.357571],"type":"Point"}
}