{
  "type": "Feature",
  "properties": {
    "addr:full":"6855 N Starnes Rd Gosport IN 47433",
    "addr:housenumber":"6855",
    "addr:postcode":"47433",
    "addr:street":"N Starnes Rd",
    "iso:country":"US",
    "sg:address":"6855 N Starnes Rd",
    "sg:city":"Gosport",
    "sg:classifiers":[
        {
            "category":"Mining & Drilling",
            "type":"Manufacturing & Wholesale Goods"
        }
    ],
    "sg:phone":"+1 812 876 6759",
    "sg:postcode":"47433",
    "sg:province":"IN",
    "sg:tags":[
        "stone"
    ],
    "wof:name":"Flatwoods Stone Co",
    "wof:placetype":"venue"
},
  "geometry": {"coordinates":[-86.659167,39.25239],"type":"Point"}
}