{
  "type": "Feature",
  "properties": {
    "iso:country":"US",
    "sg:address":"1100 N Clark Blvd",
    "sg:city":"Clarksville",
    "sg:classifiers":[
        {
            "category":"Building & Trades",
            "subcategory":"Construction",
            "type":"Services"
        }
    ],
    "sg:phone":"+1 812 284 4392",
    "sg:postcode":"47129",
    "sg:province":"IN",
    "sg:tags":[
        "utility",
        "contractor"
    ],
    "wof:name":"Standafer & Son",
    "wof:placetype":"venue"
},
  "geometry": {"coordinates":[-85.774735,38.299783],"type":"Point"}
}