{
  "type": "Feature",
  "properties": {
    "iso:country":"US",
    "sg:address":"7138 Broadway",
    "sg:city":"Merrillville",
    "sg:classifiers":[
        {
            "category":"Shopping",
            "subcategory":"Clothing, Apparel, & Fashions",
            "type":"Retail Goods"
        }
    ],
    "sg:phone":"+1 219 680 4696",
    "sg:postcode":"46410",
    "sg:province":"IN",
    "sg:tags":[
        "shop",
        "bridal"
    ],
    "wof:name":"Gowns For Less",
    "wof:placetype":"venue"
},
  "geometry": {"coordinates":[-87.3361,41.488021],"type":"Point"}
}