{
  "type": "Feature",
  "properties": {
    "addr:full":"18800 Old Hwy 57 Evansville IN 47725",
    "addr:housenumber":"18800",
    "addr:postcode":"47725",
    "addr:street":"Old Hwy 57",
    "iso:country":"US",
    "sg:address":"18800 Old Hwy 57",
    "sg:city":"Evansville",
    "sg:classifiers":[
        {
            "category":"Building & Trades",
            "subcategory":"Construction",
            "type":"Services"
        }
    ],
    "sg:phone":"+1 812 983 2553",
    "sg:postcode":"47725",
    "sg:province":"IN",
    "sg:tags":[
        "house"
    ],
    "wof:name":"Declues Home Improvements",
    "wof:placetype":"venue"
},
  "geometry": {"coordinates":[-87.47700399999999,38.146053],"type":"Point"}
}