{
  "type": "Feature",
  "properties": {
    "addr:full":"43 E Judson St Bloomfield IN 47424",
    "addr:housenumber":"43",
    "addr:postcode":"47424",
    "addr:street":"E Judson St",
    "iso:country":"US",
    "sg:address":"43 E Judson St",
    "sg:city":"Bloomfield",
    "sg:classifiers":[
        {
            "category":"Government",
            "subcategory":"Office",
            "type":"Public Place"
        }
    ],
    "sg:phone":"+1 812 384 4830",
    "sg:postcode":"47424",
    "sg:province":"IN",
    "sg:tags":[
        "state",
        "program"
    ],
    "wof:name":"Transportation Dept",
    "wof:placetype":"venue"
},
  "geometry": {"coordinates":[-86.936204,39.018688],"type":"Point"}
}