{
  "type": "Feature",
  "properties": {
    "addr:full":"154 S Wabash St Peru IN 46970",
    "addr:housenumber":"154",
    "addr:postcode":"46970",
    "addr:street":"S Wabash St",
    "iso:country":"US",
    "sg:address":"154 S Wabash St",
    "sg:city":"Peru",
    "sg:classifiers":[
        {
            "category":"Organizations",
            "subcategory":"Non-profit Organization",
            "type":"Services"
        }
    ],
    "sg:phone":"+1 765 473 3193",
    "sg:postcode":"46970",
    "sg:province":"IN",
    "wof:name":"Peru Maennerchor",
    "wof:placetype":"venue"
},
  "geometry": {"coordinates":[-86.065586,40.751488],"type":"Point"}
}