{
  "type": "Feature",
  "properties": {
    "iso:country":"US",
    "sg:address":"905 W Lake Rd W",
    "sg:city":"Scottsburg",
    "sg:classifiers":[
        {
            "category":"Professional",
            "subcategory":"Computer Services",
            "type":"Services"
        }
    ],
    "sg:phone":"+1 812 752 7776",
    "sg:postcode":"47170",
    "sg:province":"IN",
    "sg:tags":[
        "programming"
    ],
    "wof:name":"Integral Solutions Inc",
    "wof:placetype":"venue"
},
  "geometry": {"coordinates":[-85.793043,38.670738],"type":"Point"}
}