{
  "type": "Feature",
  "properties": {
    "iso:country":"US",
    "sg:address":"315 Farabee Dr",
    "sg:city":"Lafayette",
    "sg:classifiers":[
        {
            "category":"Building & Trades",
            "subcategory":"Electrical",
            "type":"Services"
        }
    ],
    "sg:phone":"+1 765 447 4658",
    "sg:postcode":"47905",
    "sg:province":"IN",
    "sg:tags":[
        "electric",
        "contractor"
    ],
    "sg:website":"www.mpbaker.com",
    "wof:name":"M P Baker Electric Inc",
    "wof:placetype":"venue"
},
  "geometry": {"coordinates":[-86.851939,40.413542],"type":"Point"}
}