{
  "type": "Feature",
  "properties": {
    "iso:country":"US",
    "sg:address":"605 W Main St",
    "sg:city":"Madison",
    "sg:classifiers":[
        {
            "category":"Restaurant",
            "type":"Food & Drink"
        }
    ],
    "sg:phone":"+1 812 265 9963",
    "sg:postcode":"47250",
    "sg:province":"IN",
    "wof:name":"Mc Quiston's Malt House",
    "wof:placetype":"venue"
},
  "geometry": {"coordinates":[-85.387363,38.737569],"type":"Point"}
}