{
  "type": "Feature",
  "properties": {
    "iso:country":"US",
    "sg:address":"3888 State Rd 261",
    "sg:city":"Newburgh",
    "sg:classifiers":[
        {
            "category":"Shopping",
            "subcategory":"Florist",
            "type":"Retail Goods"
        }
    ],
    "sg:phone":"+1 812 858 3205",
    "sg:postcode":"47630",
    "sg:province":"IN",
    "wof:name":"Buehler's Flowers Plus",
    "wof:placetype":"venue"
},
  "geometry": {"coordinates":[-87.390688,37.977624],"type":"Point"}
}