{
  "type": "Feature",
  "properties": {
    "iso:country":"US",
    "sg:address":"1821 Century Dr",
    "sg:city":"Goshen",
    "sg:classifiers":[
        {
            "category":"Banks & Credit Unions",
            "subcategory":"Financial Services",
            "type":"Services"
        }
    ],
    "sg:phone":"+1 574 533 1389",
    "sg:postcode":"46528",
    "sg:province":"IN",
    "sg:tags":[
        "company",
        "holding"
    ],
    "wof:name":"Gilbar Corps",
    "wof:placetype":"venue"
},
  "geometry": {"coordinates":[-85.788951,41.565856],"type":"Point"}
}