{
  "type": "Feature",
  "properties": {
    "iso:country":"US",
    "sg:address":"6267 E Trusdell Ave",
    "sg:city":"Syracuse",
    "sg:classifiers":[
        {
            "category":"Professional",
            "subcategory":"Management & Consulting",
            "type":"Services"
        }
    ],
    "sg:phone":"+1 574 457 4933",
    "sg:postcode":"46567",
    "sg:province":"IN",
    "sg:tags":[
        "construction"
    ],
    "wof:name":"Eldridge Construction Co",
    "wof:placetype":"venue"
},
  "geometry": {"coordinates":[-85.725983,41.403754],"type":"Point"}
}