{
  "type": "Feature",
  "properties": {
    "iso:country":"US",
    "sg:address":"302 S Range St",
    "sg:city":"Wolcott",
    "sg:classifiers":[
        {
            "category":"Food & Beverages",
            "subcategory":"Groceries & Convenience Stores",
            "type":"Retail Goods"
        }
    ],
    "sg:phone":"+1 219 279 2834",
    "sg:postcode":"47995",
    "sg:province":"IN",
    "sg:tags":[
        "grocer"
    ],
    "wof:name":"Wolcott Grocery",
    "wof:placetype":"venue"
},
  "geometry": {"coordinates":[-87.041634,40.756461],"type":"Point"}
}