{
  "type": "Feature",
  "properties": {
    "iso:country":"US",
    "sg:address":"3606 State Rte 59",
    "sg:city":"Brazil",
    "sg:classifiers":[
        {
            "category":"Utilities",
            "subcategory":"Refuse",
            "type":"Services"
        }
    ],
    "sg:phone":"+1 812 835 2088",
    "sg:postcode":"47834",
    "sg:province":"IN",
    "sg:tags":[
        "garbage",
        "collection"
    ],
    "wof:name":"Best Way Disposal",
    "wof:placetype":"venue"
},
  "geometry": {"coordinates":[-87.126301,39.442222],"type":"Point"}
}