{
  "type": "Feature",
  "properties": {
    "iso:country":"US",
    "sg:address":"11480 Main St",
    "sg:city":"Laconia",
    "sg:classifiers":[
        {
            "category":"Farming",
            "subcategory":"Nursery",
            "type":"Manufacturing & Wholesale Goods"
        }
    ],
    "sg:phone":"+1 812 737 2480",
    "sg:postcode":"47135",
    "sg:province":"IN",
    "sg:tags":[
        "greenhouse"
    ],
    "wof:name":"Laconia Greenery",
    "wof:placetype":"venue"
},
  "geometry": {"coordinates":[-86.085454,38.031978],"type":"Point"}
}