{
  "type": "Feature",
  "properties": {
    "iso:country":"US",
    "sg:address":"775 W Johnson Dr",
    "sg:city":"Terre Haute",
    "sg:classifiers":[
        {
            "category":"Building & Trades",
            "subcategory":"Plumbing",
            "type":"Services"
        }
    ],
    "sg:phone":"+1 812 234 1152",
    "sg:postcode":"47802",
    "sg:province":"IN",
    "sg:tags":[
        "plumbing",
        "contractor"
    ],
    "wof:name":"B & S Plumbing & Heating",
    "wof:placetype":"venue"
},
  "geometry": {"coordinates":[-87.427702,39.423626],"type":"Point"}
}