{
  "type": "Feature",
  "properties": {
    "iso:country":"US",
    "sg:address":"3095 N Washington St",
    "sg:city":"Kokomo",
    "sg:classifiers":[
        {
            "category":"Sports & Exercise",
            "subcategory":"Race Track",
            "type":"Entertainment"
        }
    ],
    "sg:phone":"+1 765 452 9202",
    "sg:postcode":"46901",
    "sg:province":"IN",
    "sg:tags":[
        "equipment",
        "supply"
    ],
    "wof:name":"Chalk Racing Products",
    "wof:placetype":"venue"
},
  "geometry": {"coordinates":[-86.128358,40.519562],"type":"Point"}
}