{
  "type": "Feature",
  "properties": {
    "iso:country":"US",
    "sg:address":"421 Westfield Ave",
    "sg:city":"Goshen",
    "sg:classifiers":[
        {
            "category":"Retail",
            "subcategory":"Animal Services",
            "type":"Services"
        }
    ],
    "sg:phone":"+1 574 534 7009",
    "sg:postcode":"46528",
    "sg:province":"IN",
    "sg:tags":[
        "pet"
    ],
    "wof:name":"On The Go Pet Svc Inc",
    "wof:placetype":"venue"
},
  "geometry": {"coordinates":[-85.847734,41.592],"type":"Point"}
}