{
  "type": "Feature",
  "properties": {
    "iso:country":"US",
    "sg:address":"9275 Water Tank Rd",
    "sg:city":"Poseyville",
    "sg:classifiers":[
        {
            "category":"Building & Trades",
            "subcategory":"Construction",
            "type":"Services"
        }
    ],
    "sg:phone":"+1 812 845 2796",
    "sg:postcode":"47633",
    "sg:province":"IN",
    "sg:tags":[
        "drainage",
        "contractor"
    ],
    "wof:name":"Martin Farm Drainage Inc",
    "wof:placetype":"venue"
},
  "geometry": {"coordinates":[-87.738796,38.161506],"type":"Point"}
}