{
  "type": "Feature",
  "properties": {
    "iso:country":"US",
    "sg:address":"620 Rivers Edge Ct",
    "sg:city":"Mishawaka",
    "sg:classifiers":[
        {
            "category":"Building & Trades",
            "subcategory":"Construction",
            "type":"Services"
        }
    ],
    "sg:phone":"+1 574 256 1833",
    "sg:postcode":"46544",
    "sg:province":"IN",
    "sg:tags":[
        "home",
        "builder"
    ],
    "wof:name":"Mitchell Builders Inc",
    "wof:placetype":"venue"
},
  "geometry": {"coordinates":[-86.10844400000001,41.67235],"type":"Point"}
}