{
  "type": "Feature",
  "properties": {
    "iso:country":"US",
    "sg:address":"1606 Chestnut St",
    "sg:city":"Mishawaka",
    "sg:classifiers":[
        {
            "category":"Building & Trades",
            "subcategory":"Plumbing",
            "type":"Services"
        }
    ],
    "sg:phone":"+1 574 257 0156",
    "sg:postcode":"46545",
    "sg:province":"IN",
    "sg:tags":[
        "mechanical",
        "contractor"
    ],
    "wof:name":"Dynamic Mechanical Svc Inc",
    "wof:placetype":"venue"
},
  "geometry": {"coordinates":[-86.174439,41.673215],"type":"Point"}
}