{
  "type": "Feature",
  "properties": {
    "iso:country":"US",
    "sg:address":"320 Georgetown Rd",
    "sg:city":"Greenwood",
    "sg:classifiers":[
        {
            "category":"Wholesale",
            "subcategory":"Machinery & Supplies",
            "type":"Manufacturing & Wholesale Goods"
        }
    ],
    "sg:phone":"+1 317 679 6633",
    "sg:postcode":"46142",
    "sg:province":"IN",
    "wof:name":"Hoosier Machine Svc Inc",
    "wof:placetype":"venue"
},
  "geometry": {"coordinates":[-86.135436,39.612273],"type":"Point"}
}