{
  "type": "Feature",
  "properties": {
    "iso:country":"US",
    "sg:address":"1629 Ironwood St SW",
    "sg:city":"Demotte",
    "sg:classifiers":[
        {
            "category":"Organizations",
            "subcategory":"Non-profit Organization",
            "type":"Services"
        }
    ],
    "sg:phone":"+1 219 766 3436",
    "sg:postcode":"46310",
    "sg:province":"IN",
    "wof:name":"Sandpebbles Inc",
    "wof:placetype":"venue"
},
  "geometry": {"coordinates":[-87.20981,41.18655],"type":"Point"}
}