{
  "type": "Feature",
  "properties": {
    "addr:full":"306 S 10th St Richmond IN 47374",
    "addr:housenumber":"306",
    "addr:postcode":"47374",
    "addr:street":"S 10Th St",
    "iso:country":"US",
    "sg:address":"306 S 10th St",
    "sg:city":"Richmond",
    "sg:classifiers":[
        {
            "category":"Organizations",
            "subcategory":"Non-profit Organization",
            "type":"Services"
        }
    ],
    "sg:phone":"+1 765 935 7779",
    "sg:postcode":"47374",
    "sg:province":"IN",
    "sg:tags":[
        "action",
        "agency",
        "community"
    ],
    "wof:name":"Hope Ministries Church Inc",
    "wof:placetype":"venue"
},
  "geometry": {"coordinates":[-84.889177,39.824481],"type":"Point"}
}