{
  "type": "Feature",
  "properties": {
    "iso:country":"US",
    "sg:address":"2725 W 250 S",
    "sg:city":"North Judson",
    "sg:classifiers":[
        {
            "category":"Wholesale",
            "subcategory":"Construction Materials",
            "type":"Manufacturing & Wholesale Goods"
        }
    ],
    "sg:phone":"+1 574 896 5314",
    "sg:postcode":"46366",
    "sg:province":"IN",
    "sg:tags":[
        "pallet",
        "skid"
    ],
    "wof:name":"Standard Pallet Co",
    "wof:placetype":"venue"
},
  "geometry": {"coordinates":[-86.750613,41.26626],"type":"Point"}
}