{
  "type": "Feature",
  "properties": {
    "iso:country":"US",
    "sg:address":"150 N 36th St",
    "sg:city":"Lafayette",
    "sg:classifiers":[
        {
            "category":"Building & Trades",
            "subcategory":"Construction",
            "type":"Services"
        }
    ],
    "sg:phone":"+1 765 447 1191",
    "sg:postcode":"47905",
    "sg:province":"IN",
    "sg:tags":[
        "downspouts",
        "gutter"
    ],
    "wof:name":"Gale Insulation",
    "wof:placetype":"venue"
},
  "geometry": {"coordinates":[-86.85004000000001,40.419058],"type":"Point"}
}