{
  "type": "Feature",
  "properties": {
    "iso:country":"US",
    "sg:address":"6111 N College Ave",
    "sg:city":"Indianapolis",
    "sg:classifiers":[
        {
            "category":"Personal",
            "subcategory":"Beauty Salon",
            "type":"Services"
        }
    ],
    "sg:phone":"+1 317 253 6300",
    "sg:postcode":"46220",
    "sg:province":"IN",
    "wof:name":"Nedal's Hair Design",
    "wof:placetype":"venue"
},
  "geometry": {"coordinates":[-86.146,39.866632],"type":"Point"}
}