{
  "type": "Feature",
  "properties": {
    "iso:country":"US",
    "sg:address":"5040 Trump Dr",
    "sg:city":"Indianapolis",
    "sg:classifiers":[
        {
            "category":"Home & Garden",
            "subcategory":"Household Appliances",
            "type":"Retail Goods"
        }
    ],
    "sg:phone":"+1 317 849 6499",
    "sg:postcode":"46235",
    "sg:province":"IN",
    "sg:tags":[
        "repair",
        "electrical"
    ],
    "wof:name":"Acme Appliance Service",
    "wof:placetype":"venue"
},
  "geometry": {"coordinates":[-85.99324,39.847772],"type":"Point"}
}