{
  "type": "Feature",
  "properties": {
    "iso:country":"US",
    "sg:address":"4207 Lake Ave",
    "sg:city":"Fort Wayne",
    "sg:classifiers":[
        {
            "category":"Health Services",
            "subcategory":"Doctor",
            "type":"Services"
        }
    ],
    "sg:phone":"+1 260 426 3401",
    "sg:postcode":"46815",
    "sg:province":"IN",
    "sg:tags":[
        "dentist"
    ],
    "wof:name":"Leo W Rumbaugh DDS",
    "wof:placetype":"venue"
},
  "geometry": {"coordinates":[-85.087293,41.090589],"type":"Point"}
}