{
  "type": "Feature",
  "properties": {
    "addr:full":"1975 W 100 N Angola IN 46703",
    "addr:housenumber":"1975",
    "addr:postcode":"46703",
    "addr:street":"W 100 N",
    "iso:country":"US",
    "sg:address":"1975 W 100 N",
    "sg:city":"Angola",
    "sg:classifiers":[
        {
            "category":"Banks & Credit Unions",
            "subcategory":"Bank",
            "type":"Services"
        }
    ],
    "sg:phone":"+1 260 624 2490",
    "sg:postcode":"46703",
    "sg:province":"IN",
    "sg:tags":[
        "loan",
        "real estate"
    ],
    "wof:name":"GMAC Mortgage",
    "wof:placetype":"venue"
},
  "geometry": {"coordinates":[-85.027846,41.656854],"type":"Point"}
}