{
  "type": "Feature",
  "properties": {
    "addr:full":"935 State Rd 131 Clarksville IN 47129",
    "addr:housenumber":"935;131",
    "addr:postcode":"47129",
    "addr:street":"State Rd",
    "iso:country":"US",
    "sg:address":"935 State Rd 131",
    "sg:city":"Clarksville",
    "sg:classifiers":[
        {
            "category":"Restaurant",
            "type":"Food & Drink"
        }
    ],
    "sg:phone":"+1 812 288 7675",
    "sg:postcode":"47129",
    "sg:province":"IN",
    "wof:name":"Arby's",
    "wof:placetype":"venue"
},
  "geometry": {"coordinates":[-85.758951,38.315859],"type":"Point"}
}