{
  "type": "Feature",
  "properties": {
    "addr:full":"230 W 9th St Anderson IN 46016",
    "addr:housenumber":"230",
    "addr:postcode":"46016",
    "addr:street":"W 9Th St",
    "iso:country":"US",
    "sg:address":"230 W 9th St",
    "sg:city":"Anderson",
    "sg:classifiers":[
        {
            "category":"Organizations",
            "subcategory":"Religious Organization",
            "type":"Services"
        }
    ],
    "sg:phone":"+1 765 642 0219",
    "sg:postcode":"46016",
    "sg:province":"IN",
    "sg:tags":[
        "church"
    ],
    "sg:website":"www.anderson.presbychurch.org",
    "wof:name":"First Presbyterian Church",
    "wof:placetype":"venue"
},
  "geometry": {"coordinates":[-85.68301200000001,40.107167],"type":"Point"}
}