{
  "type": "Feature",
  "properties": {
    "iso:country":"US",
    "sg:address":"1157 Troy Ridge Rd",
    "sg:city":"Tell City",
    "sg:classifiers":[
        {
            "category":"Real Estate",
            "subcategory":"Real Estate Agent",
            "type":"Services"
        }
    ],
    "sg:phone":"+1 812 547 6124",
    "sg:postcode":"47586",
    "sg:province":"IN",
    "wof:name":"Owen Propertie Inc",
    "wof:placetype":"venue"
},
  "geometry": {"coordinates":[-86.773975,37.992739],"type":"Point"}
}