{
  "type": "Feature",
  "properties": {
    "iso:country":"US",
    "sg:address":"6941 Ironwood Ave",
    "sg:city":"Gary",
    "sg:classifiers":[
        {
            "category":"Professional",
            "subcategory":"Lawyer & Legal Services",
            "type":"Services"
        }
    ],
    "sg:phone":"+1 219 939 9511",
    "sg:postcode":"46403",
    "sg:province":"IN",
    "sg:tags":[
        "attorney"
    ],
    "wof:name":"Douglas M Grimes PC",
    "wof:placetype":"venue"
},
  "geometry": {"coordinates":[-87.253371,41.615487],"type":"Point"}
}