{
  "type": "Feature",
  "properties": {
    "iso:country":"US",
    "sg:address":"2354 N US Hwy 35",
    "sg:city":"Laporte",
    "sg:classifiers":[
        {
            "category":"Banks & Credit Unions",
            "subcategory":"Bank",
            "type":"Services"
        }
    ],
    "sg:phone":"+1 219 324 4081",
    "sg:postcode":"46350",
    "sg:province":"IN",
    "sg:tags":[
        "loan",
        "real estate"
    ],
    "wof:name":"Advantage Mortgage Corp",
    "wof:placetype":"venue"
},
  "geometry": {"coordinates":[-86.763384,41.654653],"type":"Point"}
}