{
  "type": "Feature",
  "properties": {
    "iso:country":"US",
    "sg:address":"320 N Washington St",
    "sg:city":"Flora",
    "sg:classifiers":[
        {
            "category":"Wholesale",
            "subcategory":"Non-durable Goods",
            "type":"Manufacturing & Wholesale Goods"
        }
    ],
    "sg:phone":"+1 574 967 0032",
    "sg:postcode":"46929",
    "sg:province":"IN",
    "wof:name":"Central Trading Co",
    "wof:placetype":"venue"
},
  "geometry": {"coordinates":[-86.527435,40.551209],"type":"Point"}
}