{
  "type": "Feature",
  "properties": {
    "iso:country":"US",
    "sg:address":"333 Pasadena Dr",
    "sg:city":"Fort Wayne",
    "sg:classifiers":[
        {
            "category":"Retail",
            "subcategory":"Repair Shop",
            "type":"Services"
        }
    ],
    "sg:phone":"+1 260 456 6930",
    "sg:postcode":"46807",
    "sg:province":"IN",
    "wof:name":"AAA Sewer Service",
    "wof:placetype":"venue"
},
  "geometry": {"coordinates":[-85.14137100000001,41.043122],"type":"Point"}
}