{
  "type": "Feature",
  "properties": {
    "iso:country":"US",
    "sg:address":"5090 W 106th St",
    "sg:city":"Zionsville",
    "sg:classifiers":[
        {
            "category":"Building & Trades",
            "subcategory":"Construction",
            "type":"Services"
        }
    ],
    "sg:phone":"+1 317 873 9560",
    "sg:postcode":"46077",
    "sg:province":"IN",
    "sg:tags":[
        "repairing",
        "remodeling",
        "contractor"
    ],
    "wof:name":"Mikhov Construction Co",
    "wof:placetype":"venue"
},
  "geometry": {"coordinates":[-86.242303,39.94074],"type":"Point"}
}