{
  "type": "Feature",
  "properties": {
    "iso:country":"US",
    "sg:address":"403 W Broadway St",
    "sg:city":"Monon",
    "sg:classifiers":[
        {
            "category":"Personal",
            "subcategory":"Beauty Salon",
            "type":"Services"
        }
    ],
    "sg:phone":"+1 219 253 6477",
    "sg:postcode":"47959",
    "sg:province":"IN",
    "wof:name":"Guys & Dolls Hair Styling",
    "wof:placetype":"venue"
},
  "geometry": {"coordinates":[-86.882656,40.868154],"type":"Point"}
}