{
  "type": "Feature",
  "properties": {
    "iso:country":"US",
    "sg:address":"3968 N Xavier Rd",
    "sg:city":"Attica",
    "sg:classifiers":[
        {
            "category":"Autos & Motor Vehicles",
            "subcategory":"Motorcycle Sales",
            "type":"Retail Goods"
        }
    ],
    "sg:phone":"+1 765 762 2981",
    "sg:postcode":"47918",
    "sg:province":"IN",
    "sg:tags":[
        "scooter"
    ],
    "sg:website":"www.badlandsoffroad.com",
    "wof:name":"Badlands Off Road Park",
    "wof:placetype":"venue"
},
  "geometry": {"coordinates":[-87.257749,40.274589],"type":"Point"}
}