{
  "type": "Feature",
  "properties": {
    "iso:country":"US",
    "sg:address":"3701 Main St",
    "sg:city":"East Chicago",
    "sg:classifiers":[
        {
            "category":"Banks & Credit Unions",
            "subcategory":"Bank",
            "type":"Services"
        }
    ],
    "sg:phone":"+1 219 398 9900",
    "sg:postcode":"46312",
    "sg:province":"IN",
    "sg:website":"www.nationalcity.com",
    "wof:name":"National City Bank",
    "wof:placetype":"venue"
},
  "geometry": {"coordinates":[-87.444827,41.646182],"type":"Point"}
}