{
  "type": "Feature",
  "properties": {
    "iso:country":"US",
    "sg:address":"104 W Marks St",
    "sg:city":"Swayzee",
    "sg:classifiers":[
        {
            "category":"Professional",
            "subcategory":"Business Services",
            "type":"Services"
        }
    ],
    "sg:phone":"+1 765 922 7996",
    "sg:postcode":"46986",
    "sg:province":"IN",
    "sg:tags":[
        "auctioneer"
    ],
    "wof:name":"Trusty Auction Svc",
    "wof:placetype":"venue"
},
  "geometry": {"coordinates":[-85.825644,40.506727],"type":"Point"}
}