{
  "type": "Feature",
  "properties": {
    "addr:full":"1223 State Rd 131 Clarksville IN 47129",
    "addr:housenumber":"1223;131",
    "addr:postcode":"47129",
    "addr:street":"State Rd",
    "iso:country":"US",
    "sg:address":"1223 State Rd 131",
    "sg:city":"Clarksville",
    "sg:classifiers":[
        {
            "category":"Shopping",
            "type":"Retail Goods"
        }
    ],
    "sg:phone":"+1 812 944 5608",
    "sg:postcode":"47129",
    "sg:province":"IN",
    "sg:tags":[
        "trophy",
        "medal",
        "award"
    ],
    "wof:name":"Autograph Gallery",
    "wof:placetype":"venue"
},
  "geometry": {"coordinates":[-85.754914,38.31804],"type":"Point"}
}