{
  "type": "Feature",
  "properties": {
    "iso:country":"US",
    "sg:address":"6250 W Kilgore Ave",
    "sg:city":"Muncie",
    "sg:classifiers":[
        {
            "category":"Shopping",
            "subcategory":"Florist",
            "type":"Retail Goods"
        }
    ],
    "sg:phone":"+1 765 282 7061",
    "sg:postcode":"47304",
    "sg:province":"IN",
    "wof:name":"Foister's House Of Flowers",
    "wof:placetype":"venue"
},
  "geometry": {"coordinates":[-85.461284,40.181219],"type":"Point"}
}