{
  "type": "Feature",
  "properties": {
    "iso:country":"US",
    "sg:address":"9880 E 625 S",
    "sg:city":"Monterey",
    "sg:classifiers":[
        {
            "category":"Freight",
            "type":"Transportation"
        }
    ],
    "sg:phone":"+1 574 542 2593",
    "sg:postcode":"46960",
    "sg:province":"IN",
    "sg:tags":[
        "operator",
        "local",
        "trucking"
    ],
    "wof:name":"Roger Williams",
    "wof:placetype":"venue"
},
  "geometry": {"coordinates":[-86.50713,41.211669],"type":"Point"}
}