{
  "type": "Feature",
  "properties": {
    "iso:country":"US",
    "sg:address":"13435 S 350 W",
    "sg:city":"Columbus",
    "sg:phone":"+1 812 342 6020",
    "sg:postcode":"47201",
    "sg:province":"IN",
    "sg:tags":[
        "farm",
        "corn",
        "soybean"
    ],
    "wof:name":"Dennis Meyer",
    "wof:placetype":"venue"
},
  "geometry": {"coordinates":[-85.975385,39.082292],"type":"Point"}
}