{
  "type": "Feature",
  "properties": {
    "iso:country":"US",
    "sg:address":"7504 S Anthony Blvd",
    "sg:city":"Fort Wayne",
    "sg:classifiers":[
        {
            "category":"Shopping",
            "subcategory":"Music",
            "type":"Retail Goods"
        }
    ],
    "sg:phone":"+1 260 447 3857",
    "sg:postcode":"46816",
    "sg:province":"IN",
    "sg:tags":[
        "video",
        "disc",
        "tape",
        "cassette"
    ],
    "wof:name":"VIP Video",
    "wof:placetype":"venue"
},
  "geometry": {"coordinates":[-85.112204,41.013632],"type":"Point"}
}