{
  "type": "Feature",
  "properties": {
    "iso:country":"US",
    "sg:address":"6550 O'Hare St",
    "sg:city":"Portage",
    "sg:classifiers":[
        {
            "category":"Building & Trades",
            "subcategory":"Construction",
            "type":"Services"
        },
        {
            "category":"Professional",
            "subcategory":"Management & Consulting",
            "type":"Services"
        }
    ],
    "sg:phone":"+1 219 762 4092",
    "sg:postcode":"46368",
    "sg:province":"IN",
    "sg:tags":[
        "house"
    ],
    "wof:name":"Planning & Construction Servic",
    "wof:placetype":"venue"
},
  "geometry": {"coordinates":[-87.159201,41.61976],"type":"Point"}
}