{
  "type": "Feature",
  "properties": {
    "iso:country":"US",
    "sg:address":"5611 W 74th St",
    "sg:city":"Indianapolis",
    "sg:classifiers":[
        {
            "category":"Manufacturing",
            "subcategory":"Food",
            "type":"Manufacturing & Wholesale Goods"
        }
    ],
    "sg:phone":"+1 317 328 8050",
    "sg:postcode":"46278",
    "sg:province":"IN",
    "sg:tags":[
        "product",
        "manufacturer"
    ],
    "wof:name":"Savory Creations Intl",
    "wof:placetype":"venue"
},
  "geometry": {"coordinates":[-86.25994799999999,39.887335],"type":"Point"}
}