{
  "type": "Feature",
  "properties": {
    "iso:country":"US",
    "sg:address":"8100 Rose Hill Rd",
    "sg:city":"Newburgh",
    "sg:classifiers":[
        {
            "category":"Health Services",
            "subcategory":"Chiropractor",
            "type":"Services"
        }
    ],
    "sg:phone":"+1 812 858 1234",
    "sg:postcode":"47630",
    "sg:province":"IN",
    "wof:name":"Chiropractic Health Svc",
    "wof:placetype":"venue"
},
  "geometry": {"coordinates":[-87.396548,37.962075],"type":"Point"}
}