{
  "type": "Feature",
  "properties": {
    "iso:country":"US",
    "sg:address":"4327 E 3rd St",
    "sg:city":"Bloomington",
    "sg:classifiers":[
        {
            "category":"Professional",
            "subcategory":"Accounting & Tax Preparation",
            "type":"Services"
        }
    ],
    "sg:phone":"+1 812 339 9330",
    "sg:postcode":"47401",
    "sg:province":"IN",
    "sg:tags":[
        "accountant"
    ],
    "wof:name":"Sare David Neal CPA",
    "wof:placetype":"venue"
},
  "geometry": {"coordinates":[-86.476799,39.164299],"type":"Point"}
}