{
  "type": "Feature",
  "properties": {
    "addr:full":"408 E Southway Blvd Kokomo IN 46902",
    "addr:housenumber":"408",
    "addr:postcode":"46902",
    "addr:street":"E Southway Blvd",
    "iso:country":"US",
    "sg:address":"408 E Southway Blvd",
    "sg:city":"Kokomo",
    "sg:classifiers":[
        {
            "category":"Health Services",
            "subcategory":"Hospital",
            "type":"Services"
        }
    ],
    "sg:phone":"+1 765 865 3300",
    "sg:postcode":"46902",
    "sg:province":"IN",
    "wof:name":"Howard Regional Health System",
    "wof:placetype":"venue"
},
  "geometry": {"coordinates":[-86.124149,40.444331],"type":"Point"}
}