{
  "type": "Feature",
  "properties": {
    "iso:country":"US",
    "sg:address":"1847 Garden St",
    "sg:city":"Elkhart",
    "sg:classifiers":[
        {
            "category":"Real Estate",
            "subcategory":"Developer",
            "type":"Services"
        }
    ],
    "sg:phone":"+1 574 264 3988",
    "sg:postcode":"46514",
    "sg:province":"IN",
    "sg:tags":[
        "mobile",
        "home"
    ],
    "wof:name":"Wise Estates & Wise Manor Home",
    "wof:placetype":"venue"
},
  "geometry": {"coordinates":[-85.96991300000001,41.709022],"type":"Point"}
}