{
  "type": "Feature",
  "properties": {
    "iso:country":"US",
    "sg:address":"7250 S 185 E",
    "sg:city":"Wolcottville",
    "sg:classifiers":[
        {
            "category":"Building & Trades",
            "subcategory":"Electrical",
            "type":"Services"
        }
    ],
    "sg:phone":"+1 260 854 9181",
    "sg:postcode":"46795",
    "sg:province":"IN",
    "sg:tags":[
        "electrical",
        "electric",
        "contractor"
    ],
    "wof:name":"Billingsley Electric Corp",
    "wof:placetype":"venue"
},
  "geometry": {"coordinates":[-85.388866,41.536959],"type":"Point"}
}