{
  "type": "Feature",
  "properties": {
    "iso:country":"US",
    "sg:address":"625 N Co Rd 650 W",
    "sg:city":"Yorktown",
    "sg:classifiers":[
        {
            "category":"Professional",
            "subcategory":"Management & Consulting",
            "type":"Services"
        }
    ],
    "sg:phone":"+1 765 759 6732",
    "sg:postcode":"47396",
    "sg:province":"IN",
    "sg:tags":[
        "business"
    ],
    "wof:name":"Abel Consulting",
    "wof:placetype":"venue"
},
  "geometry": {"coordinates":[-85.509523,40.197388],"type":"Point"}
}