{
  "type": "Feature",
  "properties": {
    "iso:country":"US",
    "sg:address":"645 Harding St",
    "sg:city":"Plainfield",
    "sg:classifiers":[
        {
            "category":"Real Estate",
            "subcategory":"Developer",
            "type":"Services"
        }
    ],
    "sg:phone":"+1 317 839 6770",
    "sg:postcode":"46168",
    "sg:province":"IN",
    "sg:tags":[
        "cemetery"
    ],
    "wof:name":"Maple Hill Cemetery",
    "wof:placetype":"venue"
},
  "geometry": {"coordinates":[-86.396878,39.697611],"type":"Point"}
}