{
  "type": "Feature",
  "properties": {
    "addr:full":"800 Boyd Blvd Laporte IN 46350",
    "addr:housenumber":"800",
    "addr:postcode":"46350",
    "addr:street":"Boyd Blvd",
    "iso:country":"US",
    "sg:address":"800 Boyd Blvd",
    "sg:city":"Laporte",
    "sg:classifiers":[
        {
            "category":"Manufacturing",
            "subcategory":"Food",
            "type":"Manufacturing & Wholesale Goods"
        }
    ],
    "sg:phone":"+1 219 362 4561",
    "sg:postcode":"46350",
    "sg:province":"IN",
    "sg:tags":[
        "bakery",
        "prod",
        "cookie"
    ],
    "wof:name":"Lewis Bakeries Inc",
    "wof:placetype":"venue"
},
  "geometry": {"coordinates":[-86.686818,41.612061],"type":"Point"}
}