{
  "type": "Feature",
  "properties": {
    "iso:country":"US",
    "sg:address":"4139 Sheffield Ave",
    "sg:city":"Hammond",
    "sg:classifiers":[
        {
            "category":"Banks & Credit Unions",
            "subcategory":"Financial Services",
            "type":"Services"
        }
    ],
    "sg:phone":"+1 219 933 1040",
    "sg:postcode":"46327",
    "sg:province":"IN",
    "sg:tags":[
        "trust",
        "nonprofit",
        "management"
    ],
    "wof:name":"College Fund Div",
    "wof:placetype":"venue"
},
  "geometry": {"coordinates":[-87.518351,41.638207],"type":"Point"}
}