{
  "type": "Feature",
  "properties": {
    "iso:country":"US",
    "sg:address":"5525 Broadway",
    "sg:city":"Merrillville",
    "sg:classifiers":[
        {
            "category":"Social Services",
            "type":"Services"
        }
    ],
    "sg:phone":"+1 219 980 4330",
    "sg:postcode":"46410",
    "sg:province":"IN",
    "sg:tags":[
        "counselor",
        "marriage",
        "family"
    ],
    "wof:name":"Family Matters Institute Inc",
    "wof:placetype":"venue"
},
  "geometry": {"coordinates":[-87.336026,41.516734],"type":"Point"}
}