{
  "type": "Feature",
  "properties": {
    "iso:country":"US",
    "sg:address":"5402 Moeller Rd",
    "sg:city":"Fort Wayne",
    "sg:classifiers":[
        {
            "category":"Real Estate",
            "subcategory":"Real Estate Agent",
            "type":"Services"
        }
    ],
    "sg:phone":"+1 260 424 5441",
    "sg:postcode":"46806",
    "sg:province":"IN",
    "wof:name":"Fillers Realty",
    "wof:placetype":"venue"
},
  "geometry": {"coordinates":[-85.07616299999999,41.054405],"type":"Point"}
}