{
  "type": "Feature",
  "properties": {
    "addr:full":"10501 10th St Fort Wayne IN 46809",
    "addr:housenumber":"10501",
    "addr:postcode":"46809",
    "addr:street":"10Th St",
    "iso:country":"US",
    "sg:address":"10501 10th St",
    "sg:city":"Fort Wayne",
    "sg:classifiers":[
        {
            "category":"Government",
            "subcategory":"Office",
            "type":"Public Place"
        }
    ],
    "sg:phone":"+1 260 747 7276",
    "sg:postcode":"46809",
    "sg:province":"IN",
    "sg:tags":[
        "federal",
        "taxation"
    ],
    "wof:name":"US Treasury Dept",
    "wof:placetype":"venue"
},
  "geometry": {"coordinates":[-85.18489099999999,40.987545],"type":"Point"}
}