{
  "type": "Feature",
  "properties": {
    "iso:country":"US",
    "sg:address":"7499 Big Bend Rd",
    "sg:city":"Martinsville",
    "sg:classifiers":[
        {
            "category":"Home & Garden",
            "subcategory":"Furniture",
            "type":"Retail Goods"
        }
    ],
    "sg:phone":"+1 317 834 6150",
    "sg:postcode":"46151",
    "sg:province":"IN",
    "sg:website":"www.milesfurniture.net",
    "wof:name":"Miles Furniture",
    "wof:placetype":"venue"
},
  "geometry": {"coordinates":[-86.29201500000001,39.530739],"type":"Point"}
}