{
  "type": "Feature",
  "properties": {
    "iso:country":"US",
    "sg:address":"1671 W Franklin St",
    "sg:city":"Elkhart",
    "sg:classifiers":[
        {
            "category":"Manufacturing",
            "subcategory":"Tools & Machinery",
            "type":"Manufacturing & Wholesale Goods"
        }
    ],
    "sg:phone":"+1 574 293 2846",
    "sg:postcode":"46516",
    "sg:province":"IN",
    "sg:tags":[
        "mold"
    ],
    "wof:name":"Premier Mold",
    "wof:placetype":"venue"
},
  "geometry": {"coordinates":[-85.992398,41.673716],"type":"Point"}
}