{
  "type": "Feature",
  "properties": {
    "addr:full":"222 E Main St Atwood IN 46502",
    "addr:housenumber":"222",
    "addr:postcode":"46502",
    "addr:street":"E Main St",
    "iso:country":"US",
    "sg:address":"222 E Main St",
    "sg:city":"Atwood",
    "sg:classifiers":[
        {
            "category":"Insurance",
            "subcategory":"Insurance Agent",
            "type":"Services"
        }
    ],
    "sg:phone":"+1 574 858 2531",
    "sg:postcode":"46502",
    "sg:province":"IN",
    "wof:name":"Jennings Insurance",
    "wof:placetype":"venue"
},
  "geometry": {"coordinates":[-85.976567,41.260734],"type":"Point"}
}