{
  "type": "Feature",
  "properties": {
    "addr:full":"6510 N Oxford St Indianapolis IN 46220",
    "addr:housenumber":"6510",
    "addr:postcode":"46220",
    "addr:street":"N Oxford St",
    "iso:country":"US",
    "sg:address":"6510 N Oxford St",
    "sg:city":"Indianapolis",
    "sg:classifiers":[
        {
            "category":"Professional",
            "type":"Services"
        }
    ],
    "sg:phone":"+1 317 255 4621",
    "sg:postcode":"46220",
    "sg:province":"IN",
    "wof:name":"Outdoor Creations",
    "wof:placetype":"venue"
},
  "geometry": {"coordinates":[-86.115841,39.877048],"type":"Point"}
}