{
  "type": "Feature",
  "properties": {
    "iso:country":"US",
    "sg:address":"1088 N 350 E",
    "sg:city":"Chesterton",
    "sg:classifiers":[
        {
            "category":"Professional",
            "subcategory":"Management & Consulting",
            "type":"Services"
        }
    ],
    "sg:phone":"+1 219 926 8699",
    "sg:postcode":"46304",
    "sg:province":"IN",
    "sg:tags":[
        "business"
    ],
    "wof:name":"Glea",
    "wof:placetype":"venue"
},
  "geometry": {"coordinates":[-86.999493,41.588883],"type":"Point"}
}