{
  "type": "Feature",
  "properties": {
    "iso:country":"US",
    "sg:address":"1602 N Walnut St",
    "sg:city":"Hartford City",
    "sg:classifiers":[
        {
            "category":"Food & Beverages",
            "subcategory":"Liquor & Beverages",
            "type":"Retail Goods"
        }
    ],
    "sg:phone":"+1 765 348 2506",
    "sg:postcode":"47348",
    "sg:province":"IN",
    "wof:name":"Hughes Pic-A-Pac",
    "wof:placetype":"venue"
},
  "geometry": {"coordinates":[-85.369997,40.464853],"type":"Point"}
}