{
  "type": "Feature",
  "properties": {
    "iso:country":"US",
    "sg:address":"241 Atwood St",
    "sg:city":"Corydon",
    "sg:classifiers":[
        {
            "category":"Health Services",
            "subcategory":"Doctor",
            "type":"Services"
        }
    ],
    "sg:phone":"+1 812 738 1686",
    "sg:postcode":"47112",
    "sg:province":"IN",
    "sg:tags":[
        "physician",
        "surgeon"
    ],
    "wof:name":"Orthopedic Surgeons",
    "wof:placetype":"venue"
},
  "geometry": {"coordinates":[-86.12217699999999,38.207437],"type":"Point"}
}