{
  "type": "Feature",
  "properties": {
    "iso:country":"US",
    "sg:address":"1014 E Pond Rd",
    "sg:city":"Greencastle",
    "sg:classifiers":[
        {
            "category":"Health Services",
            "subcategory":"Clinic",
            "type":"Services"
        }
    ],
    "sg:phone":"+1 765 653 9070",
    "sg:postcode":"46160",
    "sg:province":"IN",
    "wof:name":"Mill Pond Health Campus",
    "wof:placetype":"venue"
},
  "geometry": {"coordinates":[-86.272184,39.366442],"type":"Point"}
}