{
  "type": "Feature",
  "properties": {
    "iso:country":"US",
    "sg:address":"2340 E 10th St",
    "sg:city":"Indianapolis",
    "sg:classifiers":[
        {
            "category":"Government",
            "subcategory":"Office",
            "type":"Public Place"
        }
    ],
    "sg:phone":"+1 317 637 3935",
    "sg:postcode":"46201",
    "sg:province":"IN",
    "sg:tags":[
        "county",
        "resource"
    ],
    "wof:name":"Marion County Wic Clinics",
    "wof:placetype":"venue"
},
  "geometry": {"coordinates":[-86.121809,39.781406],"type":"Point"}
}