{
  "type": "Feature",
  "properties": {
    "addr:full":"5202 W Linden Ave South Bend IN 46619",
    "addr:housenumber":"5202",
    "addr:postcode":"46619",
    "addr:street":"W Linden Ave",
    "iso:country":"US",
    "sg:address":"5202 W Linden Ave",
    "sg:city":"South Bend",
    "sg:classifiers":[
        {
            "category":"Recreation",
            "type":"Entertainment"
        }
    ],
    "sg:phone":"+1 574 233 9717",
    "sg:postcode":"46619",
    "sg:province":"IN",
    "sg:tags":[
        "club",
        "membership"
    ],
    "wof:name":"Knights Of Columbus",
    "wof:placetype":"venue"
},
  "geometry": {"coordinates":[-86.31882299999999,41.678979],"type":"Point"}
}