{
  "type": "Feature",
  "properties": {
    "addr:full":"34 N Depot St New Palestine IN 46163",
    "addr:housenumber":"34",
    "addr:postcode":"46163",
    "addr:street":"N Depot St",
    "iso:country":"US",
    "sg:address":"34 N Depot St",
    "sg:city":"New Palestine",
    "sg:classifiers":[
        {
            "category":"Autos & Motor Vehicles",
            "subcategory":"Motorcycle Sales",
            "type":"Retail Goods"
        }
    ],
    "sg:phone":"+1 317 861 6317",
    "sg:postcode":"46163",
    "sg:province":"IN",
    "sg:tags":[
        "repair"
    ],
    "wof:name":"ATV Connection",
    "wof:placetype":"venue"
},
  "geometry": {"coordinates":[-85.88873100000001,39.723532],"type":"Point"}
}