{
  "type": "Feature",
  "properties": {
    "iso:country":"US",
    "sg:address":"1615 E Poplar St",
    "sg:city":"Terre Haute",
    "sg:classifiers":[
        {
            "category":"Professional",
            "subcategory":"Accounting & Tax Preparation",
            "type":"Services"
        }
    ],
    "sg:phone":"+1 812 232 8684",
    "sg:postcode":"47807",
    "sg:province":"IN",
    "sg:tags":[
        "firm",
        "return",
        "filing"
    ],
    "wof:name":"Shaker & Shaker Lpas",
    "wof:placetype":"venue"
},
  "geometry": {"coordinates":[-87.390772,39.462808],"type":"Point"}
}