{
  "type": "Feature",
  "properties": {
    "iso:country":"US",
    "sg:address":"927 N California St",
    "sg:city":"Indianapolis",
    "sg:classifiers":[
        {
            "category":"Building & Trades",
            "subcategory":"Construction",
            "type":"Services"
        }
    ],
    "sg:phone":"+1 317 955 8984",
    "sg:postcode":"46202",
    "sg:province":"IN",
    "sg:tags":[
        "home",
        "improvement"
    ],
    "wof:name":"T Morgan Construction Inc",
    "wof:placetype":"venue"
},
  "geometry": {"coordinates":[-86.169457,39.780557],"type":"Point"}
}