{
  "type": "Feature",
  "properties": {
    "addr:full":"1225 Sheffield Ave Dyer IN 46311",
    "addr:housenumber":"1225",
    "addr:postcode":"46311",
    "addr:street":"Sheffield Ave",
    "iso:country":"US",
    "sg:address":"1225 Sheffield Ave",
    "sg:city":"Dyer",
    "sg:classifiers":[
        {
            "category":"Retail",
            "subcategory":"Auto Repair",
            "type":"Services"
        }
    ],
    "sg:phone":"+1 219 322 6719",
    "sg:postcode":"46311",
    "sg:province":"IN",
    "sg:tags":[
        "repairing",
        "automobile"
    ],
    "wof:name":"Metcalf Foreign Car Repair",
    "wof:placetype":"venue"
},
  "geometry": {"coordinates":[-87.518699,41.50882],"type":"Point"}
}