{
  "type": "Feature",
  "properties": {
    "iso:country":"US",
    "sg:address":"19816 State Rd 120",
    "sg:city":"Bristol",
    "sg:classifiers":[
        {
            "category":"Professional",
            "type":"Services"
        }
    ],
    "sg:phone":"+1 574 848 7451",
    "sg:postcode":"46507",
    "sg:province":"IN",
    "wof:name":"Niils-Visual Impairment Svc",
    "wof:placetype":"venue"
},
  "geometry": {"coordinates":[-85.847767,41.714321],"type":"Point"}
}