{
  "type": "Feature",
  "properties": {
    "addr:full":"2324 N A St Elwood IN 46036",
    "addr:housenumber":"2324",
    "addr:postcode":"46036",
    "addr:street":"N A St",
    "iso:country":"US",
    "sg:address":"2324 N A St",
    "sg:city":"Elwood",
    "sg:classifiers":[
        {
            "category":"Shopping",
            "subcategory":"Discount & Variety Stores",
            "type":"Retail Goods"
        }
    ],
    "sg:phone":"+1 765 552 3807",
    "sg:postcode":"46036",
    "sg:province":"IN",
    "wof:name":"Tinks Trading Post",
    "wof:placetype":"venue"
},
  "geometry": {"coordinates":[-85.831255,40.278044],"type":"Point"}
}