{
  "type": "Feature",
  "properties": {
    "iso:country":"US",
    "sg:address":"5354 Old Boonville Hwy",
    "sg:city":"Evansville",
    "sg:classifiers":[
        {
            "category":"Retail",
            "subcategory":"Repair Shop",
            "type":"Services"
        }
    ],
    "sg:phone":"+1 812 477 7727",
    "sg:postcode":"47715",
    "sg:province":"IN",
    "sg:tags":[
        "spa",
        "hot",
        "tub"
    ],
    "wof:name":"Spa & Hot Tub Svc Ctr",
    "wof:placetype":"venue"
},
  "geometry": {"coordinates":[-87.483541,37.996844],"type":"Point"}
}