{
  "type": "Feature",
  "properties": {
    "addr:full":"8005 N Clinton St Fort Wayne IN 46825",
    "addr:housenumber":"8005",
    "addr:postcode":"46825",
    "addr:street":"N Clinton St",
    "iso:country":"US",
    "sg:address":"8005 N Clinton St",
    "sg:city":"Fort Wayne",
    "sg:classifiers":[
        {
            "category":"Manufacturing",
            "subcategory":"Chemicals & Compounds",
            "type":"Manufacturing & Wholesale Goods"
        }
    ],
    "sg:phone":"+1 260 484 2000",
    "sg:postcode":"46825",
    "sg:province":"IN",
    "sg:tags":[
        "paint",
        "remover"
    ],
    "wof:name":"Chemicals Solvents & Lubricant",
    "wof:placetype":"venue"
},
  "geometry": {"coordinates":[-85.10847699999999,41.155674],"type":"Point"}
}