{
  "type": "Feature",
  "properties": {
    "iso:country":"US",
    "sg:address":"1500 Corydon Ramsey Rd NW",
    "sg:city":"Corydon",
    "sg:classifiers":[
        {
            "category":"Organizations",
            "subcategory":"Religious Organization",
            "type":"Services"
        }
    ],
    "sg:phone":"+1 812 738 4108",
    "sg:postcode":"47112",
    "sg:province":"IN",
    "wof:name":"Church of Nazarene",
    "wof:placetype":"venue"
},
  "geometry": {"coordinates":[-86.14539499999999,38.224637],"type":"Point"}
}