{
  "type": "Feature",
  "properties": {
    "iso:country":"US",
    "sg:address":"4712 Patricia St",
    "sg:city":"Indianapolis",
    "sg:classifiers":[
        {
            "category":"Social Services",
            "subcategory":"Child Care",
            "type":"Services"
        }
    ],
    "sg:phone":"+1 317 298 8963",
    "sg:postcode":"46222",
    "sg:province":"IN",
    "wof:name":"Kribbs Childcare",
    "wof:placetype":"venue"
},
  "geometry": {"coordinates":[-86.23979,39.811133],"type":"Point"}
}