{
  "type": "Feature",
  "properties": {
    "addr:full":"3501 N Granville Ave Muncie IN 47303",
    "addr:housenumber":"3501",
    "addr:postcode":"47303",
    "addr:street":"N Granville Ave",
    "iso:country":"US",
    "sg:address":"3501 N Granville Ave",
    "sg:city":"Muncie",
    "sg:classifiers":[
        {
            "category":"Shopping",
            "subcategory":"Clothing, Apparel, & Fashions",
            "type":"Retail Goods"
        }
    ],
    "sg:phone":"+1 765 289 4229",
    "sg:postcode":"47303",
    "sg:province":"IN",
    "sg:tags":[
        "item",
        "boutique"
    ],
    "wof:name":"Claire's Boutique",
    "wof:placetype":"venue"
},
  "geometry": {"coordinates":[-85.37379199999999,40.219741],"type":"Point"}
}