{
  "type": "Feature",
  "properties": {
    "iso:country":"US",
    "sg:address":"101 W Washington St",
    "sg:city":"Millersburg",
    "sg:classifiers":[
        {
            "category":"Home & Garden",
            "subcategory":"Building Materials",
            "type":"Retail Goods"
        }
    ],
    "sg:phone":"+1 574 642 4975",
    "sg:postcode":"46543",
    "sg:province":"IN",
    "sg:tags":[
        "glass",
        "leaded"
    ],
    "wof:name":"Gierek's Stained Glass",
    "wof:placetype":"venue"
},
  "geometry": {"coordinates":[-85.699722,41.524257],"type":"Point"}
}