{
  "type": "Feature",
  "properties": {
    "addr:full":"2700 E 55th Pl Indianapolis IN 46220",
    "addr:housenumber":"2700",
    "addr:postcode":"46220",
    "addr:street":"E 55Th Pl",
    "iso:country":"US",
    "sg:address":"2700 E 55th Pl",
    "sg:city":"Indianapolis",
    "sg:classifiers":[
        {
            "category":"Organizations",
            "subcategory":"Religious Organization",
            "type":"Services"
        }
    ],
    "sg:phone":"+1 317 257 5150",
    "sg:postcode":"46220",
    "sg:province":"IN",
    "wof:name":"Urban Harvest Ministries",
    "wof:placetype":"venue"
},
  "geometry": {"coordinates":[-86.11752199999999,39.85382],"type":"Point"}
}