{
  "type": "Feature",
  "properties": {
    "iso:country":"US",
    "sg:address":"1122 5th St",
    "sg:city":"Bedford",
    "sg:classifiers":[
        {
            "category":"Shopping",
            "subcategory":"Used Merchandise",
            "type":"Retail Goods"
        }
    ],
    "sg:phone":"+1 812 279 5751",
    "sg:postcode":"47421",
    "sg:province":"IN",
    "sg:tags":[
        "pawnshop"
    ],
    "wof:name":"Midwest Pawnbrokers",
    "wof:placetype":"venue"
},
  "geometry": {"coordinates":[-86.486767,38.874303],"type":"Point"}
}