{
  "type": "Feature",
  "properties": {
    "iso:country":"US",
    "sg:address":"1125 Broadway St",
    "sg:city":"Anderson",
    "sg:classifiers":[
        {
            "category":"Insurance",
            "subcategory":"Insurance Agent",
            "type":"Services"
        }
    ],
    "sg:phone":"+1 765 642 9903",
    "sg:postcode":"46012",
    "sg:province":"IN",
    "wof:name":"State Farm Insurance",
    "wof:placetype":"venue"
},
  "geometry": {"coordinates":[-85.678231,40.126106],"type":"Point"}
}