{
  "type": "Feature",
  "properties": {
    "addr:full":"1501 W Washington St Indianapolis IN 46222",
    "addr:housenumber":"1501",
    "addr:postcode":"46222",
    "addr:street":"W Washington St",
    "iso:country":"US",
    "sg:address":"1501 W Washington St",
    "sg:city":"Indianapolis",
    "sg:classifiers":[
        {
            "category":"Organizations",
            "subcategory":"Labor Organization",
            "type":"Services"
        }
    ],
    "sg:phone":"+1 317 632 8262",
    "sg:postcode":"46222",
    "sg:province":"IN",
    "wof:name":"Amalgamated Transit",
    "wof:placetype":"venue"
},
  "geometry": {"coordinates":[-86.18826300000001,39.76712],"type":"Point"}
}