{
  "type": "Feature",
  "properties": {
    "iso:country":"US",
    "sg:address":"124 E Staat St",
    "sg:city":"Fortville",
    "sg:classifiers":[
        {
            "category":"Retail",
            "subcategory":"Funeral Services",
            "type":"Services"
        }
    ],
    "sg:phone":"+1 317 485 5138",
    "sg:postcode":"46040",
    "sg:province":"IN",
    "sg:tags":[
        "director"
    ],
    "wof:name":"Erlewein Mortuary",
    "wof:placetype":"venue"
},
  "geometry": {"coordinates":[-85.848904,39.934379],"type":"Point"}
}