{
  "type": "Feature",
  "properties": {
    "iso:country":"US",
    "sg:address":"9292 Broadway",
    "sg:city":"Merrillville",
    "sg:classifiers":[
        {
            "category":"Organizations",
            "subcategory":"Religious Organization",
            "type":"Services"
        }
    ],
    "sg:phone":"+1 219 769 9292",
    "sg:postcode":"46410",
    "sg:province":"IN",
    "sg:tags":[
        "church"
    ],
    "sg:website":"www.dcgary.org",
    "wof:name":"Catholic Diocese Of Gary",
    "wof:placetype":"venue"
},
  "geometry": {"coordinates":[-87.335856,41.4494],"type":"Point"}
}