{
  "type": "Feature",
  "properties": {
    "iso:country":"US",
    "sg:address":"11542 Woodview E Dr",
    "sg:city":"Carmel",
    "sg:classifiers":[
        {
            "category":"Professional",
            "subcategory":"Business Services",
            "type":"Services"
        }
    ],
    "sg:phone":"+1 317 843 9840",
    "sg:postcode":"46032",
    "sg:province":"IN",
    "wof:name":"Plotners Enterprise",
    "wof:placetype":"venue"
},
  "geometry": {"coordinates":[-86.141858,39.953758],"type":"Point"}
}