{
  "type": "Feature",
  "properties": {
    "iso:country":"US",
    "sg:address":"109 NW I St",
    "sg:city":"Linton",
    "sg:classifiers":[
        {
            "category":"Education",
            "subcategory":"Special Training",
            "type":"Public Place"
        }
    ],
    "sg:phone":"+1 812 847 8651",
    "sg:postcode":"47441",
    "sg:province":"IN",
    "sg:tags":[
        "guidance",
        "vocational"
    ],
    "wof:name":"Twin Rivers Vocational Area",
    "wof:placetype":"venue"
},
  "geometry": {"coordinates":[-87.16945200000001,39.042131],"type":"Point"}
}