{
  "type": "Feature",
  "properties": {
    "iso:country":"US",
    "sg:address":"6284 Rucker Rd Ste N",
    "sg:city":"Indianapolis",
    "sg:classifiers":[
        {
            "category":"Social Services",
            "type":"Services"
        },
        {
            "category":"Personal",
            "type":"Services"
        }
    ],
    "sg:phone":"+1 317 475 1389",
    "sg:postcode":"46220",
    "sg:province":"IN",
    "sg:tags":[
        "family",
        "counselors-licensed",
        "individual",
        "marriage",
        "child",
        "professional",
        "counselor"
    ],
    "wof:name":"Living Well Inc",
    "wof:placetype":"venue"
},
  "geometry": {"coordinates":[-86.07933,39.870195],"type":"Point"}
}