{
  "type": "Feature",
  "properties": {
    "iso:country":"US",
    "sg:address":"64921 Miami Rd",
    "sg:city":"Bremen",
    "sg:classifiers":[
        {
            "category":"Building & Trades",
            "subcategory":"Construction",
            "type":"Services"
        }
    ],
    "sg:phone":"+1 574 291 7693",
    "sg:postcode":"46506",
    "sg:province":"IN",
    "sg:tags":[
        "resurfacing",
        "laying",
        "refinishing",
        "floor"
    ],
    "wof:name":"4d Custom Woodworking Inc",
    "wof:placetype":"venue"
},
  "geometry": {"coordinates":[-86.22815900000001,41.563166],"type":"Point"}
}