{
  "type": "Feature",
  "properties": {
    "addr:full":"2675 Hwy 62 NE Corydon IN 47112",
    "addr:housenumber":"2675",
    "addr:postcode":"47112",
    "addr:street":"Hwy 62 Ne",
    "iso:country":"US",
    "sg:address":"2675 Hwy 62 NE",
    "sg:city":"Corydon",
    "sg:classifiers":[
        {
            "category":"Insurance",
            "subcategory":"Insurance Agent",
            "type":"Services"
        }
    ],
    "sg:phone":"+1 812 968 0769",
    "sg:postcode":"47112",
    "sg:province":"IN",
    "wof:name":"Ordner Insurance Services LLC",
    "wof:placetype":"venue"
},
  "geometry": {"coordinates":[-86.08279899999999,38.201879],"type":"Point"}
}