{
  "type": "Feature",
  "properties": {
    "iso:country":"US",
    "sg:address":"2277 N Madison Ave",
    "sg:city":"Anderson",
    "sg:classifiers":[
        {
            "category":"Organizations",
            "subcategory":"Religious Organization",
            "type":"Services"
        }
    ],
    "sg:phone":"+1 765 649 5153",
    "sg:postcode":"46011",
    "sg:province":"IN",
    "sg:tags":[
        "church"
    ],
    "wof:name":"New Hope Christian Church",
    "wof:placetype":"venue"
},
  "geometry": {"coordinates":[-85.691028,40.141307],"type":"Point"}
}