{
  "type": "Feature",
  "properties": {
    "iso:country":"US",
    "sg:address":"490 45th St",
    "sg:city":"Munster",
    "sg:classifiers":[
        {
            "category":"Retail",
            "subcategory":"Auto Repair",
            "type":"Services"
        }
    ],
    "sg:phone":"+1 219 924 4722",
    "sg:postcode":"46321",
    "sg:province":"IN",
    "sg:tags":[
        "body",
        "automobile",
        "painting"
    ],
    "wof:name":"Collision Revision",
    "wof:placetype":"venue"
},
  "geometry": {"coordinates":[-87.517838,41.542873],"type":"Point"}
}