{
  "type": "Feature",
  "properties": {
    "iso:country":"US",
    "sg:address":"148 W Jefferson St",
    "sg:city":"Spencer",
    "sg:classifiers":[
        {
            "category":"Autos & Motor Vehicles",
            "subcategory":"Auto Supplies",
            "type":"Retail Goods"
        }
    ],
    "sg:phone":"+1 812 829 2376",
    "sg:postcode":"47460",
    "sg:province":"IN",
    "sg:tags":[
        "automobile",
        "parts"
    ],
    "wof:name":"Anderson Auto Supply",
    "wof:placetype":"venue"
},
  "geometry": {"coordinates":[-86.763786,39.284204],"type":"Point"}
}