{
  "type": "Feature",
  "properties": {
    "iso:country":"US",
    "sg:address":"1087 E Co Rd 550 S",
    "sg:city":"Clay City",
    "sg:classifiers":[
        {
            "category":"Farming",
            "subcategory":"Dairy Farm",
            "type":"Manufacturing & Wholesale Goods"
        }
    ],
    "sg:phone":"+1 812 939 2813",
    "sg:postcode":"47841",
    "sg:province":"IN",
    "wof:name":"Alan Yegerlehner",
    "wof:placetype":"venue"
},
  "geometry": {"coordinates":[-87.08925000000001,39.306483],"type":"Point"}
}