{
  "type": "Feature",
  "properties": {
    "iso:country":"US",
    "sg:address":"11711 N Meridian St",
    "sg:city":"Carmel",
    "sg:classifiers":[
        {
            "category":"Professional",
            "subcategory":"Accounting & Tax Preparation",
            "type":"Services"
        }
    ],
    "sg:phone":"+1 317 580 2162",
    "sg:postcode":"46032",
    "sg:province":"IN",
    "sg:tags":[
        "accountant"
    ],
    "wof:name":"Leslie Mimms",
    "wof:placetype":"venue"
},
  "geometry": {"coordinates":[-86.15755299999999,39.958139],"type":"Point"}
}