{
  "type": "Feature",
  "properties": {
    "iso:country":"US",
    "sg:address":"2352 Miracle Ln",
    "sg:city":"Mishawaka",
    "sg:classifiers":[
        {
            "category":"Shopping",
            "subcategory":"Department Store",
            "type":"Retail Goods"
        }
    ],
    "sg:phone":"+1 574 254 0015",
    "sg:postcode":"46545",
    "sg:province":"IN",
    "sg:tags":[
        "shop"
    ],
    "wof:name":"Dollar Bills",
    "wof:placetype":"venue"
},
  "geometry": {"coordinates":[-86.194293,41.683111],"type":"Point"}
}