{
  "type": "Feature",
  "properties": {
    "iso:country":"US",
    "sg:address":"14510 Shady Valley Dr",
    "sg:city":"Evansville",
    "sg:classifiers":[
        {
            "category":"Professional",
            "type":"Services"
        }
    ],
    "sg:phone":"+1 812 867 0656",
    "sg:postcode":"47725",
    "sg:province":"IN",
    "wof:name":"Geo Serve",
    "wof:placetype":"venue"
},
  "geometry": {"coordinates":[-87.527812,38.108322],"type":"Point"}
}