{
  "type": "Feature",
  "properties": {
    "iso:country":"US",
    "sg:address":"19 N Walnut St",
    "sg:city":"Brazil",
    "sg:classifiers":[
        {
            "category":"Banks & Credit Unions",
            "subcategory":"Bank",
            "type":"Services"
        }
    ],
    "sg:phone":"+1 812 446 4663",
    "sg:postcode":"47834",
    "sg:province":"IN",
    "sg:tags":[
        "loan",
        "real estate"
    ],
    "wof:name":"Century Home Mortgage Svc",
    "wof:placetype":"venue"
},
  "geometry": {"coordinates":[-87.128171,39.523683],"type":"Point"}
}