{
  "type": "Feature",
  "properties": {
    "addr:full":"2106 Franklin St South Bend IN 46613",
    "addr:housenumber":"2106",
    "addr:postcode":"46613",
    "addr:street":"Franklin St",
    "iso:country":"US",
    "sg:address":"2106 Franklin St",
    "sg:city":"South Bend",
    "sg:classifiers":[
        {
            "category":"Building & Trades",
            "subcategory":"Cleaning & Sanitation",
            "type":"Services"
        }
    ],
    "sg:phone":"+1 574 234 1151",
    "sg:postcode":"46613",
    "sg:province":"IN",
    "sg:tags":[
        "janitor"
    ],
    "wof:name":"Performance Plus",
    "wof:placetype":"venue"
},
  "geometry": {"coordinates":[-86.254448,41.651806],"type":"Point"}
}