{
  "type": "Feature",
  "properties": {
    "iso:country":"US",
    "sg:address":"2940 N Bay View Rd",
    "sg:city":"Angola",
    "sg:classifiers":[
        {
            "category":"Building & Trades",
            "subcategory":"Construction",
            "type":"Services"
        }
    ],
    "sg:phone":"+1 260 833 0200",
    "sg:postcode":"46703",
    "sg:province":"IN",
    "sg:tags":[
        "hanging",
        "painter",
        "contractor"
    ],
    "wof:name":"Hoosier Painting Company",
    "wof:placetype":"venue"
},
  "geometry": {"coordinates":[-85.029318,41.683843],"type":"Point"}
}