{
  "type": "Feature",
  "properties": {
    "iso:country":"US",
    "sg:address":"17 E Main St",
    "sg:city":"Peru",
    "sg:classifiers":[
        {
            "category":"Banks & Credit Unions",
            "subcategory":"Investment Brokerage",
            "type":"Services"
        }
    ],
    "sg:phone":"+1 765 472 7089",
    "sg:postcode":"46970",
    "sg:province":"IN",
    "sg:tags":[
        "security"
    ],
    "wof:name":"Edward Jones Co",
    "wof:placetype":"venue"
},
  "geometry": {"coordinates":[-86.06908199999999,40.753734],"type":"Point"}
}