{
  "type": "Feature",
  "properties": {
    "iso:country":"US",
    "sg:address":"1 E 81st Ave",
    "sg:city":"Merrillville",
    "sg:classifiers":[
        {
            "category":"Restaurant",
            "type":"Food & Drink"
        }
    ],
    "sg:phone":"+1 219 769 9649",
    "sg:postcode":"46410",
    "sg:province":"IN",
    "sg:website":"www.whatyoucrave.com",
    "wof:name":"White Castle",
    "wof:placetype":"venue"
},
  "geometry": {"coordinates":[-87.335794,41.471085],"type":"Point"}
}