{
  "type": "Feature",
  "properties": {
    "addr:full":"3162 W Graceland Ave West Terre Haute IN 47885",
    "addr:housenumber":"3162",
    "addr:postcode":"47885",
    "addr:street":"W Graceland Ave",
    "iso:country":"US",
    "sg:address":"3162 W Graceland Ave",
    "sg:city":"West Terre Haute",
    "sg:classifiers":[
        {
            "category":"Building & Trades",
            "subcategory":"Landscaping Services",
            "type":"Services"
        }
    ],
    "sg:phone":"+1 812 533 2364",
    "sg:postcode":"47885",
    "sg:province":"IN",
    "sg:tags":[
        "landscape",
        "contractor"
    ],
    "wof:name":"Cut & Trim Lawn & Landscape",
    "wof:placetype":"venue"
},
  "geometry": {"coordinates":[-87.466734,39.466467],"type":"Point"}
}