{
  "type": "Feature",
  "properties": {
    "iso:country":"US",
    "sg:address":"2209 Conner St",
    "sg:city":"Noblesville",
    "sg:classifiers":[
        {
            "category":"Personal",
            "subcategory":"Beauty Salon",
            "type":"Services"
        }
    ],
    "sg:phone":"+1 317 776 0191",
    "sg:postcode":"46060",
    "sg:province":"IN",
    "wof:name":"Rejuvenations Salon & Day Spa",
    "wof:placetype":"venue"
},
  "geometry": {"coordinates":[-85.998358,40.045537],"type":"Point"}
}