{
  "type": "Feature",
  "properties": {
    "iso:country":"US",
    "sg:address":"110 W High St",
    "sg:city":"Wingate",
    "sg:classifiers":[
        {
            "category":"Government",
            "subcategory":"Post Office",
            "type":"Public Place"
        }
    ],
    "sg:phone":"+1 765 275 2480",
    "sg:postcode":"47994",
    "sg:province":"IN",
    "wof:name":"US Post Office",
    "wof:placetype":"venue"
},
  "geometry": {"coordinates":[-87.072831,40.172244],"type":"Point"}
}