{
  "type": "Feature",
  "properties": {
    "iso:country":"US",
    "sg:address":"2701 S 7th St",
    "sg:city":"Terre Haute",
    "sg:classifiers":[
        {
            "category":"Retail",
            "subcategory":"Veterinary Services",
            "type":"Services"
        }
    ],
    "sg:phone":"+1 812 235 1111",
    "sg:postcode":"47802",
    "sg:province":"IN",
    "sg:tags":[
        "veterinarian"
    ],
    "wof:name":"Petcare Animal Hospital",
    "wof:placetype":"venue"
},
  "geometry": {"coordinates":[-87.40684299999999,39.437667],"type":"Point"}
}