{
  "type": "Feature",
  "properties": {
    "iso:country":"US",
    "sg:address":"2250 E Pointe Rd",
    "sg:city":"Bloomington",
    "sg:classifiers":[
        {
            "category":"Real Estate",
            "subcategory":"Real Estate Agent",
            "type":"Services"
        }
    ],
    "sg:phone":"+1 812 824 4700",
    "sg:postcode":"47401",
    "sg:province":"IN",
    "sg:website":"www.eaglepointerealty.com",
    "wof:name":"Eagle Pointe Realty",
    "wof:placetype":"venue"
},
  "geometry": {"coordinates":[-86.514266,39.032604],"type":"Point"}
}