{
  "type": "Feature",
  "properties": {
    "addr:full":"5435 N 600 W Fairland IN 46126",
    "addr:housenumber":"5435",
    "addr:postcode":"46126",
    "addr:street":"N 600 W Fairland",
    "iso:country":"US",
    "sg:address":"5435 N 600 W",
    "sg:city":"Fairland",
    "sg:classifiers":[
        {
            "category":"Professional",
            "subcategory":"Business Services",
            "type":"Services"
        }
    ],
    "sg:phone":"+1 317 835 7847",
    "sg:postcode":"46126",
    "sg:province":"IN",
    "sg:tags":[
        "auction"
    ],
    "wof:name":"East Side Auction Co",
    "wof:placetype":"venue"
},
  "geometry": {"coordinates":[-85.896278,39.602362],"type":"Point"}
}