{
  "type": "Feature",
  "properties": {
    "addr:full":"14300 Clay Terrace Boulevard Carmel IN 46032",
    "addr:housenumber":"14300",
    "addr:postcode":"46032",
    "addr:street":"Clay Terrace Boulevard",
    "iso:country":"US",
    "sg:address":"14300 Clay Terrace Boulevard",
    "sg:city":"Carmel",
    "sg:classifiers":[
        {
            "category":"Shopping Center",
            "type":"Public Place"
        }
    ],
    "sg:phone":"+1 317 566 0011",
    "sg:postcode":"46032",
    "sg:province":"IN",
    "sg:website":"www.clayterrace.com",
    "wof:name":"Clay Terrace",
    "wof:placetype":"venue"
},
  "geometry": {"coordinates":[-86.12960099999999,39.996201],"type":"Point"}
}