{
  "type": "Feature",
  "properties": {
    "addr:full":"15147 Lincoln Hwy Plymouth IN 46563",
    "addr:housenumber":"15147",
    "addr:postcode":"46563",
    "addr:street":"Lincoln Hwy",
    "iso:country":"US",
    "sg:address":"15147 Lincoln Hwy",
    "sg:city":"Plymouth",
    "sg:classifiers":[
        {
            "category":"Building & Trades",
            "subcategory":"Construction",
            "type":"Services"
        }
    ],
    "sg:phone":"+1 574 936 9938",
    "sg:postcode":"46563",
    "sg:province":"IN",
    "sg:tags":[
        "fire",
        "restoration",
        "damage"
    ],
    "wof:name":"Servpro",
    "wof:placetype":"venue"
},
  "geometry": {"coordinates":[-86.349346,41.347922],"type":"Point"}
}