{
  "type": "Feature",
  "properties": {
    "iso:country":"US",
    "sg:address":"136 W Church St",
    "sg:city":"Cambridge City",
    "sg:classifiers":[
        {
            "category":"Social Services",
            "type":"Services"
        }
    ],
    "sg:phone":"+1 765 478 5417",
    "sg:postcode":"47327",
    "sg:province":"IN",
    "sg:tags":[
        "organization",
        "welfare"
    ],
    "wof:name":"United States Government",
    "wof:placetype":"venue"
},
  "geometry": {"coordinates":[-85.172134,39.811494],"type":"Point"}
}