{
  "type": "Feature",
  "properties": {
    "iso:country":"US",
    "sg:address":"220 E Vistula St",
    "sg:city":"Bristol",
    "sg:classifiers":[
        {
            "category":"Retail",
            "subcategory":"Repair Shop",
            "type":"Services"
        }
    ],
    "sg:phone":"+1 574 848 7815",
    "sg:postcode":"46507",
    "sg:province":"IN",
    "sg:tags":[
        "tool",
        "parts"
    ],
    "wof:name":"Tool Shed",
    "wof:placetype":"venue"
},
  "geometry": {"coordinates":[-85.815043,41.72152],"type":"Point"}
}