{
  "type": "Feature",
  "properties": {
    "iso:country":"US",
    "sg:address":"6880 W Rd 375 N",
    "sg:city":"Bargersville",
    "sg:classifiers":[
        {
            "category":"Professional",
            "subcategory":"Management & Consulting",
            "type":"Services"
        }
    ],
    "sg:phone":"+1 317 422 9438",
    "sg:postcode":"46106",
    "sg:province":"IN",
    "sg:tags":[
        "business"
    ],
    "wof:name":"GL Amick Co",
    "wof:placetype":"venue"
},
  "geometry": {"coordinates":[-86.236393,39.528945],"type":"Point"}
}