{
  "type": "Feature",
  "properties": {
    "addr:full":"1126 N I St Richmond IN 47374",
    "addr:housenumber":"1126",
    "addr:postcode":"47374",
    "addr:street":"N I St",
    "iso:country":"US",
    "sg:address":"1126 N I St",
    "sg:city":"Richmond",
    "sg:classifiers":[
        {
            "category":"Professional",
            "type":"Services"
        }
    ],
    "sg:phone":"+1 765 962 5494",
    "sg:postcode":"47374",
    "sg:province":"IN",
    "sg:tags":[
        "establishment"
    ],
    "wof:name":"Cosby Terrace",
    "wof:placetype":"venue"
},
  "geometry": {"coordinates":[-84.886584,39.839523],"type":"Point"}
}