{
  "type": "Feature",
  "properties": {
    "iso:country":"US",
    "sg:address":"212 N Washington St",
    "sg:city":"Crawfordsville",
    "sg:classifiers":[
        {
            "category":"Autos & Motor Vehicles",
            "subcategory":"Auto Supplies",
            "type":"Retail Goods"
        }
    ],
    "sg:phone":"+1 765 362 2010",
    "sg:postcode":"47933",
    "sg:province":"IN",
    "wof:name":"Dyno Automotive",
    "wof:placetype":"venue"
},
  "geometry": {"coordinates":[-86.901321,40.043345],"type":"Point"}
}