{
  "type": "Feature",
  "properties": {
    "addr:full":"6714 State Rd 227 Richmond IN 47374",
    "addr:housenumber":"6714;227",
    "addr:postcode":"47374",
    "addr:street":"State Rd",
    "iso:country":"US",
    "sg:address":"6714 State Rd 227",
    "sg:city":"Richmond",
    "sg:classifiers":[
        {
            "category":"Building & Trades",
            "subcategory":"Construction",
            "type":"Services"
        }
    ],
    "sg:phone":"+1 765 847 5143",
    "sg:postcode":"47374",
    "sg:province":"IN",
    "sg:tags":[
        "contractor"
    ],
    "wof:name":"Seals Caulking",
    "wof:placetype":"venue"
},
  "geometry": {"coordinates":[-84.83151700000001,39.923472],"type":"Point"}
}