{
  "type": "Feature",
  "properties": {
    "iso:country":"US",
    "sg:address":"207 W Co Rd 200 S",
    "sg:city":"Danville",
    "sg:classifiers":[
        {
            "category":"Building & Trades",
            "subcategory":"Landscaping Services",
            "type":"Services"
        }
    ],
    "sg:phone":"+1 317 745 6606",
    "sg:postcode":"46122",
    "sg:province":"IN",
    "wof:name":"Brian Rutlegdge Enterprises",
    "wof:placetype":"venue"
},
  "geometry": {"coordinates":[-86.53037,39.731183],"type":"Point"}
}