{
  "type": "Feature",
  "properties": {
    "iso:country":"US",
    "sg:address":"720 E Elm St",
    "sg:city":"New Albany",
    "sg:classifiers":[
        {
            "category":"Professional",
            "subcategory":"Lawyer & Legal Services",
            "type":"Services"
        }
    ],
    "sg:phone":"+1 812 944 1292",
    "sg:postcode":"47150",
    "sg:province":"IN",
    "sg:tags":[
        "naturalization",
        "immigration"
    ],
    "wof:name":"Hispanic Connection",
    "wof:placetype":"venue"
},
  "geometry": {"coordinates":[-85.816485,38.289285],"type":"Point"}
}