{
  "type": "Feature",
  "properties": {
    "iso:country":"US",
    "sg:address":"6287 E 600 S",
    "sg:city":"Cutler",
    "sg:classifiers":[
        {
            "category":"Wholesale",
            "subcategory":"Farm Supplies",
            "type":"Manufacturing & Wholesale Goods"
        }
    ],
    "sg:phone":"+1 765 566 2184",
    "sg:postcode":"46920",
    "sg:province":"IN",
    "sg:tags":[
        "bulb",
        "seed"
    ],
    "wof:name":"Cornerstone Seeds",
    "wof:placetype":"venue"
},
  "geometry": {"coordinates":[-86.407336,40.46063],"type":"Point"}
}