{
  "type": "Feature",
  "properties": {
    "iso:country":"US",
    "sg:address":"8934 Shetland Ln",
    "sg:city":"Indianapolis",
    "sg:classifiers":[
        {
            "category":"Shopping",
            "subcategory":"Computers & Home Electronics",
            "type":"Retail Goods"
        }
    ],
    "sg:phone":"+1 317 297 1044",
    "sg:postcode":"46278",
    "sg:province":"IN",
    "sg:tags":[
        "high",
        "fidelity",
        "stereophonic"
    ],
    "wof:name":"Tone Studio High-End Audio",
    "wof:placetype":"venue"
},
  "geometry": {"coordinates":[-86.322892,39.913874],"type":"Point"}
}