{
  "type": "Feature",
  "properties": {
    "iso:country":"US",
    "sg:address":"2676 S Main St",
    "sg:city":"Elkhart",
    "sg:classifiers":[
        {
            "category":"Autos & Motor Vehicles",
            "subcategory":"Auto Supplies",
            "type":"Retail Goods"
        }
    ],
    "sg:phone":"+1 574 293 2200",
    "sg:postcode":"46517",
    "sg:province":"IN",
    "sg:tags":[
        "wheel",
        "cover"
    ],
    "wof:name":"Eulloqui's Kustom Wheels",
    "wof:placetype":"venue"
},
  "geometry": {"coordinates":[-85.948425,41.660306],"type":"Point"}
}