{
  "type": "Feature",
  "properties": {
    "iso:country":"US",
    "sg:address":"3300 US Hwy 52 S",
    "sg:city":"Lafayette",
    "sg:classifiers":[
        {
            "category":"Building & Trades",
            "subcategory":"Plumbing",
            "type":"Services"
        }
    ],
    "sg:phone":"+1 765 477 0488",
    "sg:postcode":"47905",
    "sg:province":"IN",
    "sg:tags":[
        "mechanical",
        "contractor"
    ],
    "wof:name":"B & H Inc Of Indiana",
    "wof:placetype":"venue"
},
  "geometry": {"coordinates":[-86.841625,40.381115],"type":"Point"}
}