{
  "type": "Feature",
  "properties": {
    "iso:country":"US",
    "sg:address":"2429 Luigs Rd",
    "sg:city":"Wadesville",
    "sg:classifiers":[
        {
            "category":"Organizations",
            "subcategory":"Community Association",
            "type":"Services"
        }
    ],
    "sg:phone":"+1 812 985 3149",
    "sg:postcode":"47638",
    "sg:province":"IN",
    "wof:name":"Order of Eastern Star of",
    "wof:placetype":"venue"
},
  "geometry": {"coordinates":[-87.724972,38.073117],"type":"Point"}
}