{
  "type": "Feature",
  "properties": {
    "iso:country":"US",
    "sg:address":"8315 US Hwy 36",
    "sg:city":"Avon",
    "sg:classifiers":[
        {
            "category":"Autos & Motor Vehicles",
            "subcategory":"Automobile Sales",
            "type":"Retail Goods"
        }
    ],
    "sg:phone":"+1 317 272 1348",
    "sg:postcode":"46123",
    "sg:province":"IN",
    "sg:tags":[
        "car",
        "dealer"
    ],
    "wof:name":"Bart's Car Store",
    "wof:placetype":"venue"
},
  "geometry": {"coordinates":[-86.385296,39.762819],"type":"Point"}
}