{
  "type": "Feature",
  "properties": {
    "iso:country":"US",
    "sg:address":"57 Franklin St",
    "sg:city":"Valparaiso",
    "sg:classifiers":[
        {
            "category":"Insurance",
            "subcategory":"Insurance Agent",
            "type":"Services"
        }
    ],
    "sg:phone":"+1 219 464 2069",
    "sg:postcode":"46383",
    "sg:province":"IN",
    "wof:name":"TPA One",
    "wof:placetype":"venue"
},
  "geometry": {"coordinates":[-87.05982899999999,41.466922],"type":"Point"}
}