{
  "type": "Feature",
  "properties": {
    "iso:country":"US",
    "sg:address":"11170 S 200 W",
    "sg:city":"Flat Rock",
    "sg:classifiers":[
        {
            "category":"Mining & Drilling",
            "type":"Manufacturing & Wholesale Goods"
        }
    ],
    "sg:phone":"+1 812 587 0272",
    "sg:postcode":"47234",
    "sg:province":"IN",
    "sg:tags":[
        "stone"
    ],
    "wof:name":"Ward Stone LLC",
    "wof:placetype":"venue"
},
  "geometry": {"coordinates":[-85.818,39.361958],"type":"Point"}
}