{
  "type": "Feature",
  "properties": {
    "iso:country":"US",
    "sg:address":"2812 Willow Dr",
    "sg:city":"Richmond",
    "sg:classifiers":[
        {
            "category":"Professional",
            "subcategory":"Management & Consulting",
            "type":"Services"
        }
    ],
    "sg:phone":"+1 765 935 3143",
    "sg:postcode":"47374",
    "sg:province":"IN",
    "sg:tags":[
        "business"
    ],
    "wof:name":"Tek Industrial Consultants",
    "wof:placetype":"venue"
},
  "geometry": {"coordinates":[-84.941,39.82818],"type":"Point"}
}