{
  "type": "Feature",
  "properties": {
    "iso:country":"US",
    "sg:address":"5525 Georgetown Rd",
    "sg:city":"Indianapolis",
    "sg:classifiers":[
        {
            "category":"Social Services",
            "type":"Services"
        }
    ],
    "sg:phone":"+1 317 328 5800",
    "sg:postcode":"46254",
    "sg:province":"IN",
    "sg:tags":[
        "counselor",
        "marriage",
        "family"
    ],
    "wof:name":"Behavior Corp",
    "wof:placetype":"venue"
},
  "geometry": {"coordinates":[-86.23998,39.85291],"type":"Point"}
}