{
  "type": "Feature",
  "properties": {
    "iso:country":"US",
    "sg:address":"1609 N 500 W",
    "sg:city":"Tipton",
    "sg:classifiers":[
        {
            "category":"Professional",
            "type":"Services"
        }
    ],
    "sg:phone":"+1 765 675 6520",
    "sg:postcode":"46072",
    "sg:province":"IN",
    "wof:name":"Glen & Lucille Lightfoot Farms",
    "wof:placetype":"venue"
},
  "geometry": {"coordinates":[-86.107964,40.331052],"type":"Point"}
}