{
  "type": "Feature",
  "properties": {
    "iso:country":"US",
    "sg:address":"1800 Dutch Ln",
    "sg:city":"Jeffersonville",
    "sg:classifiers":[
        {
            "category":"Professional",
            "subcategory":"Art Services",
            "type":"Services"
        }
    ],
    "sg:phone":"+1 812 282 8488",
    "sg:postcode":"47130",
    "sg:province":"IN",
    "sg:tags":[
        "photographer"
    ],
    "wof:name":"Kentuckiana Aerial Photography",
    "wof:placetype":"venue"
},
  "geometry": {"coordinates":[-85.74036099999999,38.288276],"type":"Point"}
}