{
  "type": "Feature",
  "properties": {
    "iso:country":"US",
    "sg:address":"11995 N US Hwy 31",
    "sg:city":"Edinburgh",
    "sg:classifiers":[
        {
            "category":"Restaurant",
            "type":"Food & Drink"
        }
    ],
    "sg:phone":"+1 812 526 8458",
    "sg:postcode":"46124",
    "sg:province":"IN",
    "wof:name":"Mc Donald's",
    "wof:placetype":"venue"
},
  "geometry": {"coordinates":[-85.966138,39.312385],"type":"Point"}
}