{
  "type": "Feature",
  "properties": {
    "addr:full":"4402 New Haven Ave Fort Wayne IN 46803",
    "addr:housenumber":"4402",
    "addr:postcode":"46803",
    "addr:street":"New Haven Ave",
    "iso:country":"US",
    "sg:address":"4402 New Haven Ave",
    "sg:city":"Fort Wayne",
    "sg:classifiers":[
        {
            "category":"Manufacturing",
            "subcategory":"Metals",
            "type":"Manufacturing & Wholesale Goods"
        }
    ],
    "sg:phone":"+1 260 704 0506",
    "sg:postcode":"46803",
    "sg:province":"IN",
    "sg:tags":[
        "fabrication",
        "structural"
    ],
    "wof:name":"Renegade Portable Welding Inc",
    "wof:placetype":"venue"
},
  "geometry": {"coordinates":[-85.08031800000001,41.068831],"type":"Point"}
}