{
  "type": "Feature",
  "properties": {
    "iso:country":"US",
    "sg:address":"1116 W 900 S",
    "sg:city":"Bunker Hill",
    "sg:classifiers":[
        {
            "category":"Manufacturing",
            "subcategory":"Signs",
            "type":"Manufacturing & Wholesale Goods"
        }
    ],
    "sg:phone":"+1 765 689 8889",
    "sg:postcode":"46914",
    "sg:province":"IN",
    "wof:name":"A Good Sign",
    "wof:placetype":"venue"
},
  "geometry": {"coordinates":[-86.091818,40.635822],"type":"Point"}
}