{
  "type": "Feature",
  "properties": {
    "addr:full":"313 W Jefferson St Decatur IN 46733",
    "addr:housenumber":"313",
    "addr:postcode":"46733",
    "addr:street":"W Jefferson St",
    "iso:country":"US",
    "sg:address":"313 W Jefferson St",
    "sg:city":"Decatur",
    "sg:classifiers":[
        {
            "category":"Social Services",
            "subcategory":"Child Care",
            "type":"Services"
        }
    ],
    "sg:phone":"+1 260 724 8809",
    "sg:postcode":"46733",
    "sg:province":"IN",
    "wof:name":"Child Care Resource & Referral",
    "wof:placetype":"venue"
},
  "geometry": {"coordinates":[-84.925022,40.828516],"type":"Point"}
}