{
  "type": "Feature",
  "properties": {
    "addr:full":"109 N Washington St North Manchester IN 46962",
    "addr:housenumber":"109",
    "addr:postcode":"46962",
    "addr:street":"N Washington St",
    "iso:country":"US",
    "sg:address":"109 N Washington St",
    "sg:city":"North Manchester",
    "sg:classifiers":[
        {
            "category":"Home & Garden",
            "subcategory":"Building Materials",
            "type":"Retail Goods"
        }
    ],
    "sg:phone":"+1 260 982 7521",
    "sg:postcode":"46962",
    "sg:province":"IN",
    "wof:name":"Frantz Lumber True Value",
    "wof:placetype":"venue"
},
  "geometry": {"coordinates":[-85.7779,40.99996],"type":"Point"}
}