{
  "type": "Feature",
  "properties": {
    "iso:country":"US",
    "sg:address":"9487 US Hwy 231",
    "sg:city":"Demotte",
    "sg:classifiers":[
        {
            "category":"Farming",
            "subcategory":"Farm",
            "type":"Manufacturing & Wholesale Goods"
        }
    ],
    "sg:phone":"+1 219 987 2019",
    "sg:postcode":"46310",
    "sg:province":"IN",
    "wof:name":"Vanderwall Farms Inc",
    "wof:placetype":"venue"
},
  "geometry": {"coordinates":[-87.151134,41.156375],"type":"Point"}
}