{
  "type": "Feature",
  "properties": {
    "iso:country":"US",
    "sg:address":"125 Walnut St",
    "sg:city":"Lawrenceburg",
    "sg:classifiers":[
        {
            "category":"Home & Garden",
            "subcategory":"Home Furnishings",
            "type":"Retail Goods"
        }
    ],
    "sg:phone":"+1 812 926 4939",
    "sg:postcode":"47025",
    "sg:province":"IN",
    "sg:tags":[
        "quilting"
    ],
    "wof:name":"Quilt Bug",
    "wof:placetype":"venue"
},
  "geometry": {"coordinates":[-84.84839100000001,39.093108],"type":"Point"}
}