{
  "type": "Feature",
  "properties": {
    "addr:full":"117 W Cherry St Scottsburg IN 47170",
    "addr:housenumber":"117",
    "addr:postcode":"47170",
    "addr:street":"W Cherry St",
    "iso:country":"US",
    "sg:address":"117 W Cherry St",
    "sg:city":"Scottsburg",
    "sg:classifiers":[
        {
            "category":"Local Transit",
            "type":"Transportation"
        }
    ],
    "sg:phone":"+1 812 752 7771",
    "sg:postcode":"47170",
    "sg:province":"IN",
    "sg:tags":[
        "airport"
    ],
    "wof:name":"Reliable Delivery Courier",
    "wof:placetype":"venue"
},
  "geometry": {"coordinates":[-85.772604,38.683909],"type":"Point"}
}