{
  "type": "Feature",
  "properties": {
    "addr:full":"3753 S Taylor Rd Scottsburg IN 47170",
    "addr:housenumber":"3753",
    "addr:postcode":"47170",
    "addr:street":"S Taylor Rd",
    "iso:country":"US",
    "sg:address":"3753 S Taylor Rd",
    "sg:city":"Scottsburg",
    "sg:classifiers":[
        {
            "category":"Farming",
            "subcategory":"Farm",
            "type":"Manufacturing & Wholesale Goods"
        }
    ],
    "sg:phone":"+1 812 752 2698",
    "sg:postcode":"47170",
    "sg:province":"IN",
    "sg:tags":[
        "crop",
        "general"
    ],
    "wof:name":"Cass Donald Farm Inc",
    "wof:placetype":"venue"
},
  "geometry": {"coordinates":[-85.849205,38.637858],"type":"Point"}
}