{
  "type": "Feature",
  "properties": {
    "iso:country":"US",
    "sg:address":"7010 W 25th Ave",
    "sg:city":"Gary",
    "sg:classifiers":[
        {
            "category":"Autos & Motor Vehicles",
            "subcategory":"Automobile Sales",
            "type":"Retail Goods"
        }
    ],
    "sg:phone":"+1 219 844 3452",
    "sg:postcode":"46406",
    "sg:province":"IN",
    "sg:tags":[
        "car",
        "dealer"
    ],
    "wof:name":"Best Choice Auto Sales",
    "wof:placetype":"venue"
},
  "geometry": {"coordinates":[-87.427406,41.573654],"type":"Point"}
}