{
  "type": "Feature",
  "properties": {
    "addr:full":"12 Murphy St Brookville IN 47012",
    "addr:housenumber":"12",
    "addr:postcode":"47012",
    "addr:street":"Murphy St",
    "iso:country":"US",
    "sg:address":"12 Murphy St",
    "sg:city":"Brookville",
    "sg:classifiers":[
        {
            "category":"Autos & Motor Vehicles",
            "subcategory":"Auto Supplies",
            "type":"Retail Goods"
        }
    ],
    "sg:phone":"+1 765 647 3541",
    "sg:postcode":"47012",
    "sg:province":"IN",
    "sg:tags":[
        "automobile",
        "parts"
    ],
    "wof:name":"NAPA Auto Parts",
    "wof:placetype":"venue"
},
  "geometry": {"coordinates":[-85.011191,39.416685],"type":"Point"}
}