{
  "type": "Feature",
  "properties": {
    "iso:country":"US",
    "sg:address":"1325 E 111th St",
    "sg:city":"Indianapolis",
    "sg:classifiers":[
        {
            "category":"Education",
            "subcategory":"School",
            "type":"Public Place"
        }
    ],
    "sg:phone":"+1 317 571 0258",
    "sg:postcode":"46280",
    "sg:province":"IN",
    "sg:tags":[
        "academic",
        "special"
    ],
    "wof:name":"Broad Horizons Montessori Schl",
    "wof:placetype":"venue"
},
  "geometry": {"coordinates":[-86.133254,39.949049],"type":"Point"}
}