{
  "type": "Feature",
  "properties": {
    "addr:full":"7402 E 90 ST Fishers IN 46038",
    "addr:housenumber":"7402;90",
    "addr:postcode":"46038",
    "addr:street":"E;St",
    "iso:country":"US",
    "sg:address":"7402 E 90 ST",
    "sg:city":"Fishers",
    "sg:classifiers":[
        {
            "category":"Manufacturing",
            "subcategory":"Tools & Machinery",
            "type":"Manufacturing & Wholesale Goods"
        },
        {
            "category":"Building & Trades",
            "subcategory":"Equipment Rental",
            "type":"Services"
        }
    ],
    "sg:phone":"+1 317 849 7007",
    "sg:postcode":"46038",
    "sg:province":"IN",
    "sg:tags":[
        "pumps-wholesale",
        "manufacturer",
        "hydraulic",
        "supply"
    ],
    "wof:name":"Morrell Incorporated",
    "wof:placetype":"venue"
},
  "geometry": {"coordinates":[-86.065128,39.932034],"type":"Point"}
}