{
  "type": "Feature",
  "properties": {
    "addr:full":"603 Elmer Ave Fort Wayne IN 46808",
    "addr:housenumber":"603",
    "addr:postcode":"46808",
    "addr:street":"Elmer Ave",
    "iso:country":"US",
    "sg:address":"603 Elmer Ave",
    "sg:city":"Fort Wayne",
    "sg:classifiers":[
        {
            "category":"Building & Trades",
            "subcategory":"Construction",
            "type":"Services"
        }
    ],
    "sg:phone":"+1 260 484 6525",
    "sg:postcode":"46808",
    "sg:province":"IN",
    "sg:tags":[
        "concrete",
        "contractor"
    ],
    "wof:name":"Shannon Concrete",
    "wof:placetype":"venue"
},
  "geometry": {"coordinates":[-85.151276,41.101152],"type":"Point"}
}