{
  "type": "Feature",
  "properties": {
    "addr:full":"3110 Pine Ridge Dr Kokomo IN 46902",
    "addr:housenumber":"3110",
    "addr:postcode":"46902",
    "addr:street":"Pine Ridge Dr",
    "iso:country":"US",
    "sg:address":"3110 Pine Ridge Dr",
    "sg:city":"Kokomo",
    "sg:classifiers":[
        {
            "category":"Building & Trades",
            "subcategory":"Construction",
            "type":"Services"
        }
    ],
    "sg:phone":"+1 765 453 2544",
    "sg:postcode":"46902",
    "sg:province":"IN",
    "sg:tags":[
        "general",
        "contractor"
    ],
    "wof:name":"D R Colter Construction",
    "wof:placetype":"venue"
},
  "geometry": {"coordinates":[-86.105125,40.431402],"type":"Point"}
}