{
  "type": "Feature",
  "properties": {
    "addr:full":"7235 N Oakland Ave Indianapolis IN 46240",
    "addr:housenumber":"7235",
    "addr:postcode":"46240",
    "addr:street":"N Oakland Ave",
    "iso:country":"US",
    "sg:address":"7235 N Oakland Ave",
    "sg:city":"Indianapolis",
    "sg:classifiers":[
        {
            "category":"Building & Trades",
            "subcategory":"Construction",
            "type":"Services"
        }
    ],
    "sg:phone":"+1 317 466 9800",
    "sg:postcode":"46240",
    "sg:province":"IN",
    "sg:tags":[
        "home",
        "improvement"
    ],
    "wof:name":"Sunrise Construction Co",
    "wof:placetype":"venue"
},
  "geometry": {"coordinates":[-86.111814,39.887141],"type":"Point"}
}