{
  "type": "Feature",
  "properties": {
    "iso:country":"US",
    "sg:address":"1025 E 54th St",
    "sg:city":"Indianapolis",
    "sg:classifiers":[
        {
            "category":"Home & Garden",
            "subcategory":"Carpets & Floor Coverings",
            "type":"Retail Goods"
        }
    ],
    "sg:phone":"+1 317 251 0350",
    "sg:postcode":"46220",
    "sg:province":"IN",
    "sg:tags":[
        "dealer",
        "rug"
    ],
    "wof:name":"Brothers Floor Covering Inc",
    "wof:placetype":"venue"
},
  "geometry": {"coordinates":[-86.141637,39.851036],"type":"Point"}
}