{
  "type": "Feature",
  "properties": {
    "iso:country":"US",
    "sg:address":"3781 S Co Rd 175 E",
    "sg:city":"Paoli",
    "sg:classifiers":[
        {
            "category":"Building & Trades",
            "subcategory":"Construction",
            "type":"Services"
        }
    ],
    "sg:phone":"+1 812 723 2585",
    "sg:postcode":"47454",
    "sg:province":"IN",
    "sg:tags":[
        "masonry",
        "contractor"
    ],
    "wof:name":"Hickman Construction",
    "wof:placetype":"venue"
},
  "geometry": {"coordinates":[-86.421332,38.501625],"type":"Point"}
}