{
  "type": "Feature",
  "properties": {
    "iso:country":"US",
    "sg:address":"505 Silhavy Rd",
    "sg:city":"Valparaiso",
    "sg:classifiers":[
        {
            "category":"Health Services",
            "subcategory":"Chiropractor",
            "type":"Services"
        }
    ],
    "sg:phone":"+1 219 464 3038",
    "sg:postcode":"46383",
    "sg:province":"IN",
    "wof:name":"Valparaiso Chiropractic Ctr",
    "wof:placetype":"venue"
},
  "geometry": {"coordinates":[-87.02719,41.473839],"type":"Point"}
}