{
  "type": "Feature",
  "properties": {
    "iso:country":"US",
    "sg:address":"1428 N Wells St",
    "sg:city":"Fort Wayne",
    "sg:classifiers":[
        {
            "category":"Shopping",
            "subcategory":"Used Merchandise",
            "type":"Retail Goods"
        }
    ],
    "sg:phone":"+1 260 424 0197",
    "sg:postcode":"46808",
    "sg:province":"IN",
    "sg:tags":[
        "book",
        "rare",
        "dealer"
    ],
    "sg:website":"www.hydebros.com",
    "wof:name":"Hyde Brothers Booksellers",
    "wof:placetype":"venue"
},
  "geometry": {"coordinates":[-85.145549,41.08742],"type":"Point"}
}