{
  "type": "Feature",
  "properties": {
    "iso:country":"US",
    "sg:address":"1878 Blackiston Mill Rd",
    "sg:city":"Clarksville",
    "sg:classifiers":[
        {
            "category":"Retail",
            "subcategory":"Laundry & Dry Cleaning",
            "type":"Services"
        }
    ],
    "sg:phone":"+1 812 948 9494",
    "sg:postcode":"47129",
    "sg:province":"IN",
    "sg:tags":[
        "cleaners"
    ],
    "wof:name":"Blackiston Mill Cleaners",
    "wof:placetype":"venue"
},
  "geometry": {"coordinates":[-85.777943,38.317361],"type":"Point"}
}