{
  "type": "Feature",
  "properties": {
    "addr:full":"2215 E 34th St Indianapolis IN 46218",
    "addr:housenumber":"2215",
    "addr:postcode":"46218",
    "addr:street":"E 34Th St",
    "iso:country":"US",
    "sg:address":"2215 E 34th St",
    "sg:city":"Indianapolis",
    "sg:classifiers":[
        {
            "category":"Personal",
            "subcategory":"Beauty Salon",
            "type":"Services"
        }
    ],
    "sg:phone":"+1 317 920 1610",
    "sg:postcode":"46218",
    "sg:province":"IN",
    "wof:name":"Gifted Hands Beauty Salon",
    "wof:placetype":"venue"
},
  "geometry": {"coordinates":[-86.12299400000001,39.818024],"type":"Point"}
}