{
  "type": "Feature",
  "properties": {
    "iso:country":"US",
    "sg:address":"7938 Island Club Dr",
    "sg:city":"Indianapolis",
    "sg:classifiers":[
        {
            "category":"Real Estate",
            "subcategory":"Real Estate Operator",
            "type":"Services"
        }
    ],
    "sg:phone":"+1 317 293 2582",
    "sg:postcode":"46214",
    "sg:province":"IN",
    "sg:tags":[
        "apartment"
    ],
    "wof:name":"Island Club Apartments",
    "wof:placetype":"venue"
},
  "geometry": {"coordinates":[-86.30178100000001,39.814665],"type":"Point"}
}