{
  "type": "Feature",
  "properties": {
    "iso:country":"US",
    "sg:address":"610 Massachusetts Ave",
    "sg:city":"Indianapolis",
    "sg:classifiers":[
        {
            "category":"Personal",
            "subcategory":"Beauty Salon",
            "type":"Services"
        }
    ],
    "sg:phone":"+1 317 266 8787",
    "sg:postcode":"46204",
    "sg:province":"IN",
    "wof:name":"A New Order Total Salon",
    "wof:placetype":"venue"
},
  "geometry": {"coordinates":[-86.148234,39.775654],"type":"Point"}
}