{
  "type": "Feature",
  "properties": {
    "iso:country":"US",
    "sg:address":"1405 N Rangeline Rd",
    "sg:city":"Anderson",
    "sg:classifiers":[
        {
            "category":"Social Services",
            "subcategory":"Adult Care",
            "type":"Services"
        }
    ],
    "sg:phone":"+1 765 643 1169",
    "sg:postcode":"46012",
    "sg:province":"IN",
    "sg:tags":[
        "organization",
        "senior",
        "citizen"
    ],
    "wof:name":"Rangeline Community Ctr Inc",
    "wof:placetype":"venue"
},
  "geometry": {"coordinates":[-85.63368,40.121009],"type":"Point"}
}