{
  "type": "Feature",
  "properties": {
    "iso:country":"US",
    "sg:address":"2828 E 55th Pl",
    "sg:city":"Indianapolis",
    "sg:classifiers":[
        {
            "category":"Professional",
            "type":"Services"
        }
    ],
    "sg:phone":"+1 317 479 3285",
    "sg:postcode":"46220",
    "sg:province":"IN",
    "sg:tags":[
        "establishment"
    ],
    "wof:name":"Prohome",
    "wof:placetype":"venue"
},
  "geometry": {"coordinates":[-86.116224,39.853899],"type":"Point"}
}