{
  "type": "Feature",
  "properties": {
    "iso:country":"US",
    "sg:address":"911 N Cullen St",
    "sg:city":"Rensselaer",
    "sg:classifiers":[
        {
            "category":"Wholesale",
            "subcategory":"Farm Supplies",
            "type":"Manufacturing & Wholesale Goods"
        }
    ],
    "sg:phone":"+1 219 866 2718",
    "sg:postcode":"47978",
    "sg:province":"IN",
    "sg:tags":[
        "fertilizer"
    ],
    "wof:name":"Vision Ag",
    "wof:placetype":"venue"
},
  "geometry": {"coordinates":[-87.154216,40.943906],"type":"Point"}
}