{
  "type": "Feature",
  "properties": {
    "iso:country":"US",
    "sg:address":"3860 E 500 S",
    "sg:city":"Lafayette",
    "sg:classifiers":[
        {
            "category":"Social Services",
            "subcategory":"Child Care",
            "type":"Services"
        }
    ],
    "sg:phone":"+1 765 474 5088",
    "sg:postcode":"47909",
    "sg:province":"IN",
    "wof:name":"Country Lane Daycare Inc",
    "wof:placetype":"venue"
},
  "geometry": {"coordinates":[-86.85146899999999,40.34531],"type":"Point"}
}