{
  "type": "Feature",
  "properties": {
    "iso:country":"US",
    "sg:address":"3402 S 300 W",
    "sg:city":"Greenfield",
    "sg:classifiers":[
        {
            "category":"Professional",
            "subcategory":"Employment Agencies",
            "type":"Services"
        }
    ],
    "sg:phone":"+1 317 861 5945",
    "sg:postcode":"46140",
    "sg:province":"IN",
    "sg:tags":[
        "help",
        "supply"
    ],
    "wof:name":"Don Wheeler Trucking Co",
    "wof:placetype":"venue"
},
  "geometry": {"coordinates":[-85.857586,39.736469],"type":"Point"}
}