{
  "type": "Feature",
  "properties": {
    "iso:country":"US",
    "sg:address":"1035 N Olney St",
    "sg:city":"Indianapolis",
    "sg:classifiers":[
        {
            "category":"Organizations",
            "subcategory":"Religious Organization",
            "type":"Services"
        }
    ],
    "sg:phone":"+1 317 636 8883",
    "sg:postcode":"46201",
    "sg:province":"IN",
    "sg:tags":[
        "church"
    ],
    "wof:name":"Brookside United Methodist Chr",
    "wof:placetype":"venue"
},
  "geometry": {"coordinates":[-86.106916,39.782146],"type":"Point"}
}