{
  "type": "Feature",
  "properties": {
    "addr:full":"2102 Home Ave Columbus IN 47201",
    "addr:housenumber":"2102",
    "addr:postcode":"47201",
    "addr:street":"Home Ave",
    "iso:country":"US",
    "sg:address":"2102 Home Ave",
    "sg:city":"Columbus",
    "sg:classifiers":[
        {
            "category":"Banks & Credit Unions",
            "subcategory":"Investment Brokerage",
            "type":"Services"
        }
    ],
    "sg:phone":"+1 812 379 4194",
    "sg:postcode":"47201",
    "sg:province":"IN",
    "sg:tags":[
        "advisory",
        "financial"
    ],
    "wof:name":"Crown Financial Svc Inc",
    "wof:placetype":"venue"
},
  "geometry": {"coordinates":[-85.91216799999999,39.219351],"type":"Point"}
}