{
  "type": "Feature",
  "properties": {
    "iso:country":"US",
    "sg:address":"421 S 2nd St",
    "sg:city":"Elkhart",
    "sg:classifiers":[
        {
            "category":"Professional",
            "type":"Services"
        }
    ],
    "sg:phone":"+1 574 522 5453",
    "sg:postcode":"46516",
    "sg:province":"IN",
    "sg:tags":[
        "establishment"
    ],
    "wof:name":"Tiedemann Co",
    "wof:placetype":"venue"
},
  "geometry": {"coordinates":[-85.973027,41.682903],"type":"Point"}
}