{
  "type": "Feature",
  "properties": {
    "iso:country":"US",
    "sg:address":"1235 Runnion Ave",
    "sg:city":"Fort Wayne",
    "sg:classifiers":[
        {
            "category":"Restaurant",
            "type":"Food & Drink"
        }
    ],
    "sg:phone":"+1 260 424 1103",
    "sg:postcode":"46808",
    "sg:province":"IN",
    "wof:name":"Saylor's Hometown Diner & Pzz",
    "wof:placetype":"venue"
},
  "geometry": {"coordinates":[-85.16602399999999,41.085538],"type":"Point"}
}