{
  "type": "Feature",
  "properties": {
    "iso:country":"US",
    "sg:address":"6433 Highcroft Dr",
    "sg:city":"Evansville",
    "sg:classifiers":[
        {
            "category":"Wholesale",
            "subcategory":"Construction Materials",
            "type":"Manufacturing & Wholesale Goods"
        }
    ],
    "sg:phone":"+1 812 471 1171",
    "sg:postcode":"47715",
    "sg:province":"IN",
    "sg:tags":[
        "fence"
    ],
    "wof:name":"Coach House Garages",
    "wof:placetype":"venue"
},
  "geometry": {"coordinates":[-87.474116,37.971015],"type":"Point"}
}