{
  "type": "Feature",
  "properties": {
    "iso:country":"US",
    "sg:address":"1474 State Rd 3",
    "sg:city":"Hartford City",
    "sg:classifiers":[
        {
            "category":"Manufacturing",
            "subcategory":"Printing",
            "type":"Manufacturing & Wholesale Goods"
        }
    ],
    "sg:phone":"+1 765 348 3120",
    "sg:postcode":"47348",
    "sg:province":"IN",
    "sg:tags":[
        "menu"
    ],
    "wof:name":"Oswalt Menu Co Inc",
    "wof:placetype":"venue"
},
  "geometry": {"coordinates":[-85.37001100000001,40.462405],"type":"Point"}
}