{
  "type": "Feature",
  "properties": {
    "iso:country":"US",
    "sg:address":"101 NW 1st St",
    "sg:city":"Evansville",
    "sg:classifiers":[
        {
            "category":"Professional",
            "subcategory":"Engineering",
            "type":"Services"
        }
    ],
    "sg:phone":"+1 812 423 3264",
    "sg:postcode":"47708",
    "sg:province":"IN",
    "sg:tags":[
        "engineer"
    ],
    "wof:name":"Tenex Inc",
    "wof:placetype":"venue"
},
  "geometry": {"coordinates":[-87.575715,37.971584],"type":"Point"}
}