{
  "type": "Feature",
  "properties": {
    "iso:country":"US",
    "sg:address":"4645 W State Rd 45",
    "sg:city":"Bloomington",
    "sg:classifiers":[
        {
            "category":"Social Services",
            "subcategory":"Child Care",
            "type":"Services"
        }
    ],
    "sg:phone":"+1 812 825 7260",
    "sg:postcode":"47403",
    "sg:province":"IN",
    "wof:name":"Calvary Christian Daycare",
    "wof:placetype":"venue"
},
  "geometry": {"coordinates":[-86.595899,39.135276],"type":"Point"}
}