{
  "type": "Feature",
  "properties": {
    "addr:full":"1970 Hwy 337 NW Corydon IN 47112",
    "addr:housenumber":"1970",
    "addr:postcode":"47112",
    "addr:street":"Hwy 337 Nw",
    "iso:country":"US",
    "sg:address":"1970 Hwy 337 NW",
    "sg:city":"Corydon",
    "sg:classifiers":[
        {
            "category":"Personal",
            "subcategory":"Beauty Salon",
            "type":"Services"
        }
    ],
    "sg:phone":"+1 812 738 7903",
    "sg:postcode":"47112",
    "sg:province":"IN",
    "sg:tags":[
        "manicuring"
    ],
    "wof:name":"Lee Nails",
    "wof:placetype":"venue"
},
  "geometry": {"coordinates":[-86.139967,38.231626],"type":"Point"}
}