{
  "type": "Feature",
  "properties": {
    "addr:full":"318 W Tipton St Seymour IN 47274",
    "addr:housenumber":"318",
    "addr:postcode":"47274",
    "addr:street":"W Tipton St",
    "iso:country":"US",
    "sg:address":"318 W Tipton St",
    "sg:city":"Seymour",
    "sg:classifiers":[
        {
            "category":"Home & Garden",
            "subcategory":"Building Materials",
            "type":"Retail Goods"
        }
    ],
    "sg:phone":"+1 812 523 1300",
    "sg:postcode":"47274",
    "sg:province":"IN",
    "sg:tags":[
        "wallpaper"
    ],
    "wof:name":"Paper Place",
    "wof:placetype":"venue"
},
  "geometry": {"coordinates":[-85.889869,38.957118],"type":"Point"}
}