{
  "type": "Feature",
  "properties": {
    "iso:country":"US",
    "sg:address":"201 S 7th St",
    "sg:city":"Petersburg",
    "sg:classifiers":[
        {
            "category":"Shopping",
            "subcategory":"Florist",
            "type":"Retail Goods"
        }
    ],
    "sg:phone":"+1 812 354 8793",
    "sg:postcode":"47567",
    "sg:province":"IN",
    "wof:name":"Ole Flower Shoppe",
    "wof:placetype":"venue"
},
  "geometry": {"coordinates":[-87.279569,38.490469],"type":"Point"}
}