{
  "type": "Feature",
  "properties": {
    "iso:country":"US",
    "sg:address":"1618 S 6th St",
    "sg:city":"Elkhart",
    "sg:classifiers":[
        {
            "category":"Organizations",
            "subcategory":"Religious Organization",
            "type":"Services"
        }
    ],
    "sg:phone":"+1 574 294 1416",
    "sg:postcode":"46516",
    "sg:province":"IN",
    "sg:tags":[
        "church"
    ],
    "wof:name":"Fellowship Of Hope",
    "wof:placetype":"venue"
},
  "geometry": {"coordinates":[-85.97510200000001,41.672583],"type":"Point"}
}