{
  "type": "Feature",
  "properties": {
    "iso:country":"US",
    "sg:address":"2230 E Washington St",
    "sg:city":"Indianapolis",
    "sg:classifiers":[
        {
            "category":"Autos & Motor Vehicles",
            "subcategory":"Automobile Sales",
            "type":"Retail Goods"
        }
    ],
    "sg:phone":"+1 317 632 4547",
    "sg:postcode":"46201",
    "sg:province":"IN",
    "sg:tags":[
        "dealers-used",
        "car",
        "used",
        "cars-wholesale"
    ],
    "sg:website":"http://www.samwolfusedcars.com",
    "wof:name":"Wolf, Sam Auto Sales",
    "wof:placetype":"venue"
},
  "geometry": {"coordinates":[-86.123441,39.767853],"type":"Point"}
}