{
  "type": "Feature",
  "properties": {
    "iso:country":"US",
    "sg:address":"3647 S 390 E",
    "sg:city":"Wabash",
    "sg:classifiers":[
        {
            "category":"Building & Trades",
            "subcategory":"Construction",
            "type":"Services"
        }
    ],
    "sg:phone":"+1 260 563 1471",
    "sg:postcode":"46992",
    "sg:province":"IN",
    "sg:tags":[
        "carpenter"
    ],
    "wof:name":"Speicher Construction Inc",
    "wof:placetype":"venue"
},
  "geometry": {"coordinates":[-85.717689,40.773619],"type":"Point"}
}