{
  "type": "Feature",
  "properties": {
    "iso:country":"US",
    "sg:address":"1835 Main St",
    "sg:city":"Ferdinand",
    "sg:classifiers":[
        {
            "category":"Health Services",
            "subcategory":"Doctor",
            "type":"Services"
        }
    ],
    "sg:phone":"+1 812 367 0702",
    "sg:postcode":"47532",
    "sg:province":"IN",
    "sg:tags":[
        "clinic"
    ],
    "wof:name":"Ferdinand Clinic",
    "wof:placetype":"venue"
},
  "geometry": {"coordinates":[-86.862145,38.233315],"type":"Point"}
}