{
  "type": "Feature",
  "properties": {
    "iso:country":"US",
    "sg:address":"10234 Arbor Trl",
    "sg:city":"Fort Wayne",
    "sg:classifiers":[
        {
            "category":"Professional",
            "subcategory":"Business Services",
            "type":"Services"
        }
    ],
    "sg:phone":"+1 260 436 6762",
    "sg:postcode":"46804",
    "sg:province":"IN",
    "wof:name":"F&F Business Systems Inc",
    "wof:placetype":"venue"
},
  "geometry": {"coordinates":[-85.275155,41.020219],"type":"Point"}
}