{
  "type": "Feature",
  "properties": {
    "iso:country":"US",
    "sg:address":"401 E Southern Ave",
    "sg:city":"Indianapolis",
    "sg:classifiers":[
        {
            "category":"Organizations",
            "subcategory":"Religious Organization",
            "type":"Services"
        }
    ],
    "sg:phone":"+1 317 786 0426",
    "sg:postcode":"46225",
    "sg:province":"IN",
    "wof:name":"Garfield Park Church Of God",
    "wof:placetype":"venue"
},
  "geometry": {"coordinates":[-86.14971799999999,39.729824],"type":"Point"}
}