{
  "type": "Feature",
  "properties": {
    "iso:country":"US",
    "sg:address":"1617 E Michigan Rd",
    "sg:city":"Shelbyville",
    "sg:classifiers":[
        {
            "category":"Sports & Exercise",
            "subcategory":"Gym",
            "type":"Entertainment"
        }
    ],
    "sg:phone":"+1 317 392 3001",
    "sg:postcode":"46176",
    "sg:province":"IN",
    "sg:tags":[
        "club",
        "health",
        "studio",
        "gymnasium"
    ],
    "wof:name":"Curves For Women",
    "wof:placetype":"venue"
},
  "geometry": {"coordinates":[-85.751823,39.5186],"type":"Point"}
}