{
  "type": "Feature",
  "properties": {
    "iso:country":"US",
    "sg:address":"1253 W Broadway St",
    "sg:city":"Monticello",
    "sg:classifiers":[
        {
            "category":"Health Services",
            "subcategory":"Doctor",
            "type":"Services"
        }
    ],
    "sg:phone":"+1 574 583 8255",
    "sg:postcode":"47960",
    "sg:province":"IN",
    "sg:tags":[
        "physician",
        "surgeon"
    ],
    "wof:name":"Max L Fields Inc",
    "wof:placetype":"venue"
},
  "geometry": {"coordinates":[-86.777719,40.744943],"type":"Point"}
}