{
  "type": "Feature",
  "properties": {
    "iso:country":"US",
    "sg:address":"1015 S Michigan St",
    "sg:city":"South Bend",
    "sg:classifiers":[
        {
            "category":"Wholesale",
            "subcategory":"Hardware",
            "type":"Manufacturing & Wholesale Goods"
        }
    ],
    "sg:phone":"+1 574 234 7767",
    "sg:postcode":"46601",
    "sg:province":"IN",
    "sg:tags":[
        "used",
        "boiler"
    ],
    "wof:name":"Repairs Inc",
    "wof:placetype":"venue"
},
  "geometry": {"coordinates":[-86.25014899999999,41.663823],"type":"Point"}
}