{
  "type": "Feature",
  "properties": {
    "iso:country":"US",
    "sg:address":"714 W 13th St",
    "sg:city":"Bloomington",
    "sg:classifiers":[
        {
            "category":"Shopping",
            "subcategory":"Clothing, Apparel, & Fashions",
            "type":"Retail Goods"
        }
    ],
    "sg:phone":"+1 812 339 3362",
    "sg:postcode":"47404",
    "sg:province":"IN",
    "wof:name":"Bloomington Cstm Screen Prtrs",
    "wof:placetype":"venue"
},
  "geometry": {"coordinates":[-86.54198700000001,39.175141],"type":"Point"}
}