{
  "type": "Feature",
  "properties": {
    "iso:country":"US",
    "sg:address":"1027 Main St",
    "sg:city":"Tell City",
    "sg:classifiers":[
        {
            "category":"Personal",
            "subcategory":"Beauty Salon",
            "type":"Services"
        }
    ],
    "sg:phone":"+1 812 547 2801",
    "sg:postcode":"47586",
    "sg:province":"IN",
    "wof:name":"Lena's Beauty Shop",
    "wof:placetype":"venue"
},
  "geometry": {"coordinates":[-86.76985999999999,37.956423],"type":"Point"}
}