{
  "type": "Feature",
  "properties": {
    "iso:country":"US",
    "sg:address":"749 S Bluff St",
    "sg:city":"Monticello",
    "sg:classifiers":[
        {
            "category":"Retail",
            "subcategory":"Repair Shop",
            "type":"Services"
        }
    ],
    "sg:phone":"+1 574 583 5375",
    "sg:postcode":"47960",
    "sg:province":"IN",
    "sg:tags":[
        "repairing",
        "lawn",
        "mower"
    ],
    "wof:name":"Miller's Lawn Mower Shop",
    "wof:placetype":"venue"
},
  "geometry": {"coordinates":[-86.760234,40.734388],"type":"Point"}
}