{
  "type": "Feature",
  "properties": {
    "iso:country":"US",
    "sg:address":"12511 Reynolds Dr",
    "sg:city":"Fishers",
    "sg:classifiers":[
        {
            "category":"Autos & Motor Vehicles",
            "subcategory":"Auto Supplies",
            "type":"Retail Goods"
        }
    ],
    "sg:phone":"+1 317 842 0544",
    "sg:postcode":"46038",
    "sg:province":"IN",
    "sg:tags":[
        "tire"
    ],
    "wof:name":"Clark Tire Fishers Inc",
    "wof:placetype":"venue"
},
  "geometry": {"coordinates":[-86.002377,39.969094],"type":"Point"}
}