{
  "type": "Feature",
  "properties": {
    "iso:country":"US",
    "sg:address":"3501 Mesker Park Dr",
    "sg:city":"Evansville",
    "sg:classifiers":[
        {
            "category":"Organizations",
            "subcategory":"Community Association",
            "type":"Services"
        }
    ],
    "sg:phone":"+1 812 422 0808",
    "sg:postcode":"47720",
    "sg:province":"IN",
    "sg:tags":[
        "club"
    ],
    "wof:name":"Twin Tower Inc",
    "wof:placetype":"venue"
},
  "geometry": {"coordinates":[-87.612719,38.012721],"type":"Point"}
}