{
  "type": "Feature",
  "properties": {
    "iso:country":"US",
    "sg:address":"111 E Wayne St",
    "sg:city":"Fort Wayne",
    "sg:classifiers":[
        {
            "category":"Professional",
            "subcategory":"Lawyer & Legal Services",
            "type":"Services"
        }
    ],
    "sg:phone":"+1 260 424 8000",
    "sg:postcode":"46802",
    "sg:province":"IN",
    "sg:tags":[
        "attorney"
    ],
    "sg:website":"www.bakerdaniels.com",
    "wof:name":"Baker & Daniels",
    "wof:placetype":"venue"
},
  "geometry": {"coordinates":[-85.137899,41.078556],"type":"Point"}
}