{
  "type": "Feature",
  "properties": {
    "addr:full":"1252 E 100 S Rochester IN 46975",
    "addr:housenumber":"1252",
    "addr:postcode":"46975",
    "addr:street":"E 100 S Rochester",
    "iso:country":"US",
    "sg:address":"1252 E 100 S",
    "sg:city":"Rochester",
    "sg:classifiers":[
        {
            "category":"Government",
            "subcategory":"Office",
            "type":"Public Place"
        }
    ],
    "sg:phone":"+1 574 223 4241",
    "sg:postcode":"46975",
    "sg:province":"IN",
    "sg:tags":[
        "state"
    ],
    "wof:name":"State Of In Natural Resources",
    "wof:placetype":"venue"
},
  "geometry": {"coordinates":[-86.224227,41.040649],"type":"Point"}
}