{
  "type": "Feature",
  "properties": {
    "iso:country":"US",
    "sg:address":"1911 Sheridan Rd",
    "sg:city":"Fort Wayne",
    "sg:classifiers":[
        {
            "category":"Manufacturing",
            "subcategory":"Rubber & Plastics",
            "type":"Manufacturing & Wholesale Goods"
        }
    ],
    "sg:phone":"+1 260 749 0280",
    "sg:postcode":"46803",
    "sg:province":"IN",
    "sg:tags":[
        "product",
        "mfg"
    ],
    "wof:name":"Wayne Haven Tool",
    "wof:placetype":"venue"
},
  "geometry": {"coordinates":[-85.071781,41.063891],"type":"Point"}
}