{
  "type": "Feature",
  "properties": {
    "iso:country":"US",
    "sg:address":"474 Emerson Rd",
    "sg:city":"Carmel",
    "sg:classifiers":[
        {
            "category":"Building & Trades",
            "subcategory":"Construction",
            "type":"Services"
        }
    ],
    "sg:phone":"+1 317 848 3570",
    "sg:postcode":"46032",
    "sg:province":"IN",
    "sg:tags":[
        "carpentry",
        "contractor"
    ],
    "wof:name":"B & B Construction Inc",
    "wof:placetype":"venue"
},
  "geometry": {"coordinates":[-86.132983,39.976146],"type":"Point"}
}