{
  "type": "Feature",
  "properties": {
    "iso:country":"US",
    "sg:address":"1000 Randolph St",
    "sg:city":"Elkhart",
    "sg:classifiers":[
        {
            "category":"Professional",
            "subcategory":"Management & Consulting",
            "type":"Services"
        }
    ],
    "sg:phone":"+1 574 206 8616",
    "sg:postcode":"46514",
    "sg:province":"IN",
    "wof:name":"Spark Management",
    "wof:placetype":"venue"
},
  "geometry": {"coordinates":[-85.98674099999999,41.69698],"type":"Point"}
}