{
  "type": "Feature",
  "properties": {
    "iso:country":"US",
    "sg:address":"220 Ironwood Cir",
    "sg:city":"Noblesville",
    "sg:classifiers":[
        {
            "category":"Professional",
            "subcategory":"Management & Consulting",
            "type":"Services"
        }
    ],
    "sg:phone":"+1 317 770 9098",
    "sg:postcode":"46062",
    "sg:province":"IN",
    "sg:tags":[
        "consultant",
        "resource",
        "human"
    ],
    "wof:name":"Human Capital Solutions Inc",
    "wof:placetype":"venue"
},
  "geometry": {"coordinates":[-86.066181,40.080619],"type":"Point"}
}