{
  "type": "Feature",
  "properties": {
    "iso:country":"US",
    "sg:address":"1500 W Market St",
    "sg:city":"Salem",
    "sg:classifiers":[
        {
            "category":"Wholesale",
            "subcategory":"Auto Parts",
            "type":"Manufacturing & Wholesale Goods"
        }
    ],
    "sg:phone":"+1 812 883 8839",
    "sg:postcode":"47167",
    "sg:province":"IN",
    "sg:tags":[
        "body",
        "automobile",
        "shop"
    ],
    "wof:name":"P & P Supplies",
    "wof:placetype":"venue"
},
  "geometry": {"coordinates":[-86.119893,38.602545],"type":"Point"}
}