{
  "type": "Feature",
  "properties": {
    "iso:country":"US",
    "sg:address":"4350 Carrollton Ave",
    "sg:city":"Indianapolis",
    "sg:classifiers":[
        {
            "category":"Building & Trades",
            "subcategory":"Construction",
            "type":"Services"
        }
    ],
    "sg:phone":"+1 317 283 5356",
    "sg:postcode":"46205",
    "sg:province":"IN",
    "sg:tags":[
        "general",
        "contractor"
    ],
    "wof:name":"Homefax Construction",
    "wof:placetype":"venue"
},
  "geometry": {"coordinates":[-86.143775,39.833231],"type":"Point"}
}