{
  "type": "Feature",
  "properties": {
    "iso:country":"US",
    "sg:address":"2901 Warsaw St",
    "sg:city":"Fort Wayne",
    "sg:classifiers":[
        {
            "category":"Organizations",
            "subcategory":"Religious Organization",
            "type":"Services"
        }
    ],
    "sg:phone":"+1 260 744 1804",
    "sg:postcode":"46806",
    "sg:province":"IN",
    "wof:name":"Warsaw Street Baptist Church",
    "wof:placetype":"venue"
},
  "geometry": {"coordinates":[-85.130515,41.057873],"type":"Point"}
}