{
  "type": "Feature",
  "properties": {
    "iso:country":"US",
    "sg:address":"1627 S 600 W",
    "sg:city":"Anderson",
    "sg:classifiers":[
        {
            "category":"Building & Trades",
            "subcategory":"Construction",
            "type":"Services"
        }
    ],
    "sg:phone":"+1 765 620 6224",
    "sg:postcode":"46011",
    "sg:province":"IN",
    "sg:tags":[
        "trim",
        "finish",
        "carpentry"
    ],
    "wof:name":"Keb Construction Inc",
    "wof:placetype":"venue"
},
  "geometry": {"coordinates":[-85.786795,40.089326],"type":"Point"}
}