{
  "type": "Feature",
  "properties": {
    "addr:full":"130 Demaree Dr Madison IN 47250",
    "addr:housenumber":"130",
    "addr:postcode":"47250",
    "addr:street":"Demaree Dr",
    "iso:country":"US",
    "sg:address":"130 Demaree Dr",
    "sg:city":"Madison",
    "sg:classifiers":[
        {
            "category":"Professional",
            "subcategory":"Employment Agencies",
            "type":"Services"
        }
    ],
    "sg:phone":"+1 812 265 5772",
    "sg:postcode":"47250",
    "sg:province":"IN",
    "sg:tags":[
        "help",
        "contractor"
    ],
    "wof:name":"Personnel Management Inc",
    "wof:placetype":"venue"
},
  "geometry": {"coordinates":[-85.385695,38.778458],"type":"Point"}
}