{
  "type": "Feature",
  "properties": {
    "iso:country":"US",
    "sg:address":"104 E Main St",
    "sg:city":"Saratoga",
    "sg:classifiers":[
        {
            "category":"Organizations",
            "subcategory":"Religious Organization",
            "type":"Services"
        }
    ],
    "sg:phone":"+1 765 584 0116",
    "sg:postcode":"47382",
    "sg:province":"IN",
    "sg:tags":[
        "church"
    ],
    "wof:name":"Saratoga United Methodist Chr",
    "wof:placetype":"venue"
},
  "geometry": {"coordinates":[-84.919304,40.236831],"type":"Point"}
}