{
  "type": "Feature",
  "properties": {
    "iso:country":"US",
    "sg:address":"6330 E 75th St",
    "sg:city":"Indianapolis",
    "sg:classifiers":[
        {
            "category":"Professional",
            "subcategory":"Business Services",
            "type":"Services"
        }
    ],
    "sg:phone":"+1 317 578 1968",
    "sg:postcode":"46250",
    "sg:province":"IN",
    "wof:name":"Advantage Document Solutions",
    "wof:placetype":"venue"
},
  "geometry": {"coordinates":[-86.058998,39.890746],"type":"Point"}
}