{
  "type": "Feature",
  "properties": {
    "iso:country":"US",
    "sg:address":"1728 N Ironwood Dr",
    "sg:city":"South Bend",
    "sg:classifiers":[
        {
            "category":"Home & Garden",
            "subcategory":"Building Materials",
            "type":"Retail Goods"
        }
    ],
    "sg:phone":"+1 574 272 6888",
    "sg:postcode":"46635",
    "sg:province":"IN",
    "sg:tags":[
        "paint"
    ],
    "wof:name":"C E Lee Co",
    "wof:placetype":"venue"
},
  "geometry": {"coordinates":[-86.216437,41.698799],"type":"Point"}
}