{
  "type": "Feature",
  "properties": {
    "iso:country":"US",
    "sg:address":"602 Cherokee Dr",
    "sg:city":"New Albany",
    "sg:classifiers":[
        {
            "category":"Real Estate",
            "subcategory":"Real Estate Services",
            "type":"Services"
        }
    ],
    "sg:phone":"+1 502 876 7254",
    "sg:postcode":"47150",
    "sg:province":"IN",
    "sg:tags":[
        "abstract",
        "title"
    ],
    "wof:name":"Access Title & Processing LLC",
    "wof:placetype":"venue"
},
  "geometry": {"coordinates":[-85.823503,38.317167],"type":"Point"}
}