{
  "type": "Feature",
  "properties": {
    "iso:country":"US",
    "sg:address":"2003 Lincoln Ave",
    "sg:city":"Evansville",
    "sg:classifiers":[
        {
            "category":"Shopping",
            "subcategory":"Computers & Home Electronics",
            "type":"Retail Goods"
        }
    ],
    "sg:phone":"+1 812 473 2660",
    "sg:postcode":"47714",
    "sg:province":"IN",
    "sg:tags":[
        "equipment",
        "dealer"
    ],
    "wof:name":"Laboratory Computers",
    "wof:placetype":"venue"
},
  "geometry": {"coordinates":[-87.539329,37.969983],"type":"Point"}
}