{
  "type": "Feature",
  "properties": {
    "addr:full":"1341 E State Rd 2 Laporte IN 46350",
    "addr:housenumber":"1341",
    "addr:postcode":"46350",
    "addr:street":"E State Rd 2",
    "iso:country":"US",
    "sg:address":"1341 E State Rd 2",
    "sg:city":"Laporte",
    "sg:classifiers":[
        {
            "category":"Autos & Motor Vehicles",
            "subcategory":"Auto Supplies",
            "type":"Retail Goods"
        }
    ],
    "sg:phone":"+1 219 326 5901",
    "sg:postcode":"46350",
    "sg:province":"IN",
    "sg:tags":[
        "automobile",
        "parts"
    ],
    "wof:name":"Dealer Distributing",
    "wof:placetype":"venue"
},
  "geometry": {"coordinates":[-86.69387,41.623573],"type":"Point"}
}