{
  "type": "Feature",
  "properties": {
    "iso:country":"US",
    "sg:address":"1415 N 2nd St",
    "sg:city":"Vincennes",
    "sg:classifiers":[
        {
            "category":"Personal",
            "subcategory":"Beauty Salon",
            "type":"Services"
        }
    ],
    "sg:phone":"+1 812 886 6464",
    "sg:postcode":"47591",
    "sg:province":"IN",
    "sg:tags":[
        "tanning"
    ],
    "wof:name":"Tanfastic Hair Connections",
    "wof:placetype":"venue"
},
  "geometry": {"coordinates":[-87.518277,38.686506],"type":"Point"}
}