{
  "type": "Feature",
  "properties": {
    "iso:country":"US",
    "sg:address":"125 S Washington St",
    "sg:city":"Crawfordsville",
    "sg:classifiers":[
        {
            "category":"Insurance",
            "subcategory":"Insurance Agent",
            "type":"Services"
        }
    ],
    "sg:phone":"+1 765 361 1399",
    "sg:postcode":"47933",
    "sg:province":"IN",
    "wof:name":"All American Insurance Inc",
    "wof:placetype":"venue"
},
  "geometry": {"coordinates":[-86.901481,40.041446],"type":"Point"}
}