{
  "type": "Feature",
  "properties": {
    "iso:country":"US",
    "sg:address":"3452 Stellhorn Rd",
    "sg:city":"Fort Wayne",
    "sg:classifiers":[
        {
            "category":"Communications",
            "subcategory":"Film & Video Production",
            "type":"Services"
        }
    ],
    "sg:phone":"+1 260 486 5428",
    "sg:postcode":"46815",
    "sg:province":"IN",
    "sg:tags":[
        "taping"
    ],
    "wof:name":"Schweickart & Assocites",
    "wof:placetype":"venue"
},
  "geometry": {"coordinates":[-85.09782199999999,41.119187],"type":"Point"}
}