{
  "type": "Feature",
  "properties": {
    "iso:country":"US",
    "sg:address":"1009 S Division St",
    "sg:city":"Bristol",
    "sg:classifiers":[
        {
            "category":"Manufacturing",
            "subcategory":"Wood Products",
            "type":"Manufacturing & Wholesale Goods"
        }
    ],
    "sg:phone":"+1 574 848 1164",
    "sg:postcode":"46507",
    "sg:province":"IN",
    "sg:tags":[
        "lumber"
    ],
    "wof:name":"Wood Recycling",
    "wof:placetype":"venue"
},
  "geometry": {"coordinates":[-85.817326,41.711794],"type":"Point"}
}