{
  "type": "Feature",
  "properties": {
    "iso:country":"US",
    "sg:address":"1500 Polco St",
    "sg:city":"Indianapolis",
    "sg:classifiers":[
        {
            "category":"Education",
            "subcategory":"Library",
            "type":"Public Place"
        }
    ],
    "sg:phone":"+1 317 240 2520",
    "sg:postcode":"46222",
    "sg:province":"IN",
    "sg:tags":[
        "special",
        "interest"
    ],
    "wof:name":"Praxair Surface Tech Libr",
    "wof:placetype":"venue"
},
  "geometry": {"coordinates":[-86.234916,39.786832],"type":"Point"}
}