{
  "type": "Feature",
  "properties": {
    "iso:country":"US",
    "sg:address":"2140 N 700 W",
    "sg:city":"Shipshewana",
    "sg:classifiers":[
        {
            "category":"Shopping",
            "subcategory":"Bicycles & Sporting Goods",
            "type":"Retail Goods"
        }
    ],
    "sg:phone":"+1 260 768 7025",
    "sg:postcode":"46565",
    "sg:province":"IN",
    "wof:name":"Miller's Bicycle Shop",
    "wof:placetype":"venue"
},
  "geometry": {"coordinates":[-85.561238,41.670858],"type":"Point"}
}