{
  "type": "Feature",
  "properties": {
    "addr:full":"1120 Vine St Noblesville IN 46060",
    "addr:housenumber":"1120",
    "addr:postcode":"46060",
    "addr:street":"Vine St",
    "iso:country":"US",
    "sg:address":"1120 Vine St",
    "sg:city":"Noblesville",
    "sg:classifiers":[
        {
            "category":"Health Services",
            "subcategory":"Doctor",
            "type":"Services"
        }
    ],
    "sg:phone":"+1 317 770 1057",
    "sg:postcode":"46060",
    "sg:province":"IN",
    "sg:tags":[
        "physician",
        "surgeon"
    ],
    "wof:name":"Jeffery E Boone Family Prctc",
    "wof:placetype":"venue"
},
  "geometry": {"coordinates":[-86.01084299999999,40.040995],"type":"Point"}
}