{
  "type": "Feature",
  "properties": {
    "iso:country":"US",
    "sg:address":"7767 Tufton St",
    "sg:city":"Fishers",
    "sg:classifiers":[
        {
            "category":"Professional",
            "subcategory":"Computer Services",
            "type":"Services"
        }
    ],
    "sg:phone":"+1 317 578 4355",
    "sg:postcode":"46038",
    "sg:province":"IN",
    "sg:tags":[
        "design",
        "integrated",
        "system"
    ],
    "wof:name":"Supercomputing Unlimited (su)",
    "wof:placetype":"venue"
},
  "geometry": {"coordinates":[-86.02684499999999,39.949441],"type":"Point"}
}