{
  "type": "Feature",
  "properties": {
    "iso:country":"US",
    "sg:address":"401 N Warpath Dr",
    "sg:city":"Milan",
    "sg:classifiers":[
        {
            "category":"Autos & Motor Vehicles",
            "subcategory":"Automobile Sales",
            "type":"Retail Goods"
        }
    ],
    "sg:phone":"+1 812 654 3636",
    "sg:postcode":"47031",
    "sg:province":"IN",
    "sg:tags":[
        "car",
        "dealer"
    ],
    "wof:name":"Doug's Cars",
    "wof:placetype":"venue"
},
  "geometry": {"coordinates":[-85.129939,39.126321],"type":"Point"}
}