{
  "type": "Feature",
  "properties": {
    "addr:full":"4215 W 86th St Indianapolis IN 46268",
    "addr:housenumber":"4215",
    "addr:postcode":"46268",
    "addr:street":"W 86Th St",
    "iso:country":"US",
    "sg:address":"4215 W 86th St",
    "sg:city":"Indianapolis",
    "sg:classifiers":[
        {
            "category":"Personal",
            "subcategory":"Beauty Salon",
            "type":"Services"
        }
    ],
    "sg:phone":"+1 317 871 0817",
    "sg:postcode":"46268",
    "sg:province":"IN",
    "wof:name":"Hair Design Studio",
    "wof:placetype":"venue"
},
  "geometry": {"coordinates":[-86.236664,39.911425],"type":"Point"}
}