{
  "type": "Feature",
  "properties": {
    "iso:country":"US",
    "sg:address":"4700 Central Ave",
    "sg:city":"Lake Station",
    "sg:classifiers":[
        {
            "category":"Social Services",
            "type":"Services"
        }
    ],
    "sg:phone":"+1 219 963 9200",
    "sg:postcode":"46405",
    "sg:province":"IN",
    "sg:tags":[
        "youth",
        "organization",
        "center"
    ],
    "wof:name":"Boys & Girls Clubs Of Nw In",
    "wof:placetype":"venue"
},
  "geometry": {"coordinates":[-87.225574,41.574328],"type":"Point"}
}