{
  "type": "Feature",
  "properties": {
    "iso:country":"US",
    "sg:address":"921 18th St",
    "sg:city":"Tell City",
    "sg:classifiers":[
        {
            "category":"Building & Trades",
            "subcategory":"Electrical",
            "type":"Services"
        }
    ],
    "sg:phone":"+1 812 547 4251",
    "sg:postcode":"47586",
    "sg:province":"IN",
    "sg:tags":[
        "electric",
        "contractor"
    ],
    "wof:name":"Terry Electrical Svc",
    "wof:placetype":"venue"
},
  "geometry": {"coordinates":[-86.756685,37.954619],"type":"Point"}
}