{
  "type": "Feature",
  "properties": {
    "addr:full":"4801 Southeastern Ave Indianapolis IN 46203",
    "addr:housenumber":"4801",
    "addr:postcode":"46203",
    "addr:street":"Southeastern Ave",
    "iso:country":"US",
    "sg:address":"4801 Southeastern Ave",
    "sg:city":"Indianapolis",
    "sg:classifiers":[
        {
            "category":"Retail",
            "subcategory":"Repair Shop",
            "type":"Services"
        }
    ],
    "sg:phone":"+1 317 955 1249",
    "sg:postcode":"46203",
    "sg:province":"IN",
    "sg:tags":[
        "upholsterer"
    ],
    "wof:name":"D J Upholstery",
    "wof:placetype":"venue"
},
  "geometry": {"coordinates":[-86.085821,39.746303],"type":"Point"}
}