{
  "type": "Feature",
  "properties": {
    "iso:country":"US",
    "sg:address":"1301 W Miller St",
    "sg:city":"Clinton",
    "sg:classifiers":[
        {
            "category":"Real Estate",
            "subcategory":"Real Estate Operator",
            "type":"Services"
        }
    ],
    "sg:phone":"+1 765 832 8546",
    "sg:postcode":"47842",
    "sg:province":"IN",
    "sg:tags":[
        "property",
        "lessor"
    ],
    "wof:name":"Bill Knoblett",
    "wof:placetype":"venue"
},
  "geometry": {"coordinates":[-87.413845,39.672194],"type":"Point"}
}