{
  "type": "Feature",
  "properties": {
    "iso:country":"US",
    "sg:address":"7510 W Stinemyer Rd",
    "sg:city":"New Palestine",
    "sg:classifiers":[
        {
            "category":"Communications",
            "subcategory":"News Services",
            "type":"Services"
        }
    ],
    "sg:phone":"+1 317 861 0548",
    "sg:postcode":"46163",
    "sg:province":"IN",
    "wof:name":"Ans Core Systems Inc",
    "wof:placetype":"venue"
},
  "geometry": {"coordinates":[-85.941943,39.715891],"type":"Point"}
}