{
  "type": "Feature",
  "properties": {
    "iso:country":"US",
    "sg:address":"2435 Monroe St",
    "sg:city":"La Porte",
    "sg:classifiers":[
        {
            "category":"Autos & Motor Vehicles",
            "subcategory":"Motorcycle Sales",
            "type":"Retail Goods"
        }
    ],
    "sg:phone":"+1 219 324 2178",
    "sg:postcode":"46350",
    "sg:province":"IN",
    "sg:tags":[
        "watercraft"
    ],
    "wof:name":"Serious Fun Inc",
    "wof:placetype":"venue"
},
  "geometry": {"coordinates":[-86.694838,41.601261],"type":"Point"}
}