{
  "type": "Feature",
  "properties": {
    "iso:country":"US",
    "sg:address":"341 Copeland Dr",
    "sg:city":"Carmel",
    "sg:classifiers":[
        {
            "category":"Wholesale",
            "subcategory":"Machinery & Supplies",
            "type":"Manufacturing & Wholesale Goods"
        }
    ],
    "sg:phone":"+1 317 580 4460",
    "sg:postcode":"46032",
    "sg:province":"IN",
    "sg:tags":[
        "bearing"
    ],
    "wof:name":"Fagbearings Corp",
    "wof:placetype":"venue"
},
  "geometry": {"coordinates":[-86.164127,40.000506],"type":"Point"}
}