{
  "type": "Feature",
  "properties": {
    "iso:country":"US",
    "sg:address":"119 W Mitchell St",
    "sg:city":"Kendallville",
    "sg:classifiers":[
        {
            "category":"Real Estate",
            "subcategory":"Real Estate Agent",
            "type":"Services"
        }
    ],
    "sg:phone":"+1 260 347 9633",
    "sg:postcode":"46755",
    "sg:province":"IN",
    "sg:tags":[
        "appraiser"
    ],
    "wof:name":"Hosler Appraisal",
    "wof:placetype":"venue"
},
  "geometry": {"coordinates":[-85.265929,41.443807],"type":"Point"}
}