{
  "type": "Feature",
  "properties": {
    "addr:full":"2721 E 3rd St Bloomington IN 47401",
    "addr:housenumber":"2721",
    "addr:postcode":"47401",
    "addr:street":"E 3Rd St",
    "iso:country":"US",
    "sg:address":"2721 E 3rd St",
    "sg:city":"Bloomington",
    "sg:classifiers":[
        {
            "category":"Shopping",
            "subcategory":"Computers & Home Electronics",
            "type":"Retail Goods"
        }
    ],
    "sg:phone":"+1 812 336 7921",
    "sg:postcode":"47401",
    "sg:province":"IN",
    "sg:tags":[
        "equipment",
        "electronic",
        "supply"
    ],
    "wof:name":"Best Buy",
    "wof:placetype":"venue"
},
  "geometry": {"coordinates":[-86.496949,39.164293],"type":"Point"}
}