{
  "type": "Feature",
  "properties": {
    "iso:country":"US",
    "sg:address":"2550 Waterbridge Way",
    "sg:city":"Evansville",
    "sg:classifiers":[
        {
            "category":"Banks & Credit Unions",
            "subcategory":"Bank",
            "type":"Services"
        }
    ],
    "sg:phone":"+1 812 424 5626",
    "sg:postcode":"47710",
    "sg:province":"IN",
    "sg:tags":[
        "loan",
        "real estate"
    ],
    "wof:name":"Novastar Home Mortgage",
    "wof:placetype":"venue"
},
  "geometry": {"coordinates":[-87.571934,38.001995],"type":"Point"}
}