{
  "type": "Feature",
  "properties": {
    "iso:country":"US",
    "sg:address":"811 Joliet St",
    "sg:city":"Dyer",
    "sg:classifiers":[
        {
            "category":"Retail",
            "subcategory":"Laundry & Dry Cleaning",
            "type":"Services"
        }
    ],
    "sg:phone":"+1 219 322 4266",
    "sg:postcode":"46311",
    "sg:province":"IN",
    "sg:tags":[
        "cleaners"
    ],
    "wof:name":"Dyer Dry Cleaners",
    "wof:placetype":"venue"
},
  "geometry": {"coordinates":[-87.507484,41.492873],"type":"Point"}
}