{
  "type": "Feature",
  "properties": {
    "iso:country":"US",
    "sg:address":"1509 Dubois St",
    "sg:city":"Fort Wayne",
    "sg:classifiers":[
        {
            "category":"Manufacturing",
            "subcategory":"Furniture",
            "type":"Manufacturing & Wholesale Goods"
        }
    ],
    "sg:phone":"+1 260 424 5524",
    "sg:postcode":"46803",
    "sg:province":"IN",
    "wof:name":"Koskee Co",
    "wof:placetype":"venue"
},
  "geometry": {"coordinates":[-85.109438,41.072069],"type":"Point"}
}