{
  "type": "Feature",
  "properties": {
    "iso:country":"US",
    "sg:address":"2525 Palisade Dr",
    "sg:city":"Fort Wayne",
    "sg:classifiers":[
        {
            "category":"Education",
            "subcategory":"School",
            "type":"Public Place"
        }
    ],
    "sg:phone":"+1 260 447 5060",
    "sg:postcode":"46806",
    "sg:province":"IN",
    "wof:name":"Urban Brightest Community Acad",
    "wof:placetype":"venue"
},
  "geometry": {"coordinates":[-85.103876,41.035405],"type":"Point"}
}