{
  "type": "Feature",
  "properties": {
    "iso:country":"US",
    "sg:address":"1908 E US Hwy 20",
    "sg:city":"Michigan City",
    "sg:classifiers":[
        {
            "category":"Banks & Credit Unions",
            "subcategory":"Bank",
            "type":"Services"
        }
    ],
    "sg:phone":"+1 219 879 0691",
    "sg:postcode":"46360",
    "sg:province":"IN",
    "sg:tags":[
        "financing"
    ],
    "wof:name":"Personal Finance Co",
    "wof:placetype":"venue"
},
  "geometry": {"coordinates":[-86.849786,41.687454],"type":"Point"}
}