{
  "type": "Feature",
  "properties": {
    "iso:country":"US",
    "sg:address":"502 W Randolph St",
    "sg:city":"Nappanee",
    "sg:classifiers":[
        {
            "category":"Autos & Motor Vehicles",
            "subcategory":"Automobile Sales",
            "type":"Retail Goods"
        }
    ],
    "sg:phone":"+1 574 773 2440",
    "sg:postcode":"46550",
    "sg:province":"IN",
    "sg:tags":[
        "sport",
        "trailer",
        "utility"
    ],
    "wof:name":"Aluminum Trailer Co",
    "wof:placetype":"venue"
},
  "geometry": {"coordinates":[-86.006183,41.43991],"type":"Point"}
}