{
  "type": "Feature",
  "properties": {
    "iso:country":"US",
    "sg:address":"838 Lafountaine Ave",
    "sg:city":"Wabash",
    "sg:classifiers":[
        {
            "category":"Manufacturing",
            "subcategory":"Tools & Machinery",
            "type":"Manufacturing & Wholesale Goods"
        }
    ],
    "sg:phone":"+1 260 563 3143",
    "sg:postcode":"46992",
    "sg:province":"IN",
    "wof:name":"United Tool Inc",
    "wof:placetype":"venue"
},
  "geometry": {"coordinates":[-85.813767,40.790617],"type":"Point"}
}