{
  "type": "Feature",
  "properties": {
    "iso:country":"US",
    "sg:address":"1180 E Main St",
    "sg:city":"Berne",
    "sg:classifiers":[
        {
            "category":"Food & Beverages",
            "subcategory":"Groceries & Convenience Stores",
            "type":"Retail Goods"
        }
    ],
    "sg:phone":"+1 260 589 3444",
    "sg:postcode":"46711",
    "sg:province":"IN",
    "wof:name":"Swiss Deli Express",
    "wof:placetype":"venue"
},
  "geometry": {"coordinates":[-84.938011,40.658035],"type":"Point"}
}