{
  "type": "Feature",
  "properties": {
    "iso:country":"US",
    "sg:address":"339 N 450 W",
    "sg:city":"Jasper",
    "sg:classifiers":[
        {
            "category":"Freight",
            "type":"Transportation"
        }
    ],
    "sg:phone":"+1 812 634 9500",
    "sg:postcode":"47546",
    "sg:province":"IN",
    "sg:tags":[
        "consultant"
    ],
    "wof:name":"C & H Logistics",
    "wof:placetype":"venue"
},
  "geometry": {"coordinates":[-86.991024,38.384928],"type":"Point"}
}