{
  "type": "Feature",
  "properties": {
    "addr:full":"9741 E Washington St Indianapolis IN 46229",
    "addr:housenumber":"9741",
    "addr:postcode":"46229",
    "addr:street":"E Washington St",
    "iso:country":"US",
    "sg:address":"9741 E Washington St",
    "sg:city":"Indianapolis",
    "sg:classifiers":[
        {
            "category":"Shopping",
            "subcategory":"Optical Goods",
            "type":"Retail Goods"
        }
    ],
    "sg:phone":"+1 317 869 0308",
    "sg:postcode":"46229",
    "sg:province":"IN",
    "wof:name":"America's Best Contact",
    "wof:placetype":"venue"
},
  "geometry": {"coordinates":[-85.993364,39.774614],"type":"Point"}
}