{
  "type": "Feature",
  "properties": {
    "iso:country":"US",
    "sg:address":"3035 English Ave",
    "sg:city":"Indianapolis",
    "sg:classifiers":[
        {
            "category":"Insurance",
            "subcategory":"Insurance Agent",
            "type":"Services"
        }
    ],
    "sg:phone":"+1 317 217 1666",
    "sg:postcode":"46201",
    "sg:province":"IN",
    "wof:name":"Chappell Insurance",
    "wof:placetype":"venue"
},
  "geometry": {"coordinates":[-86.111781,39.759824],"type":"Point"}
}