{
  "type": "Feature",
  "properties": {
    "iso:country":"US",
    "sg:address":"10326 Missaukee Trl",
    "sg:city":"Fort Wayne",
    "sg:classifiers":[
        {
            "category":"Professional",
            "subcategory":"Management & Consulting",
            "type":"Services"
        }
    ],
    "sg:phone":"+1 260 435 1300",
    "sg:postcode":"46804",
    "sg:province":"IN",
    "sg:tags":[
        "coffee",
        "brewing",
        "devices"
    ],
    "wof:name":"Cappuccino Co",
    "wof:placetype":"venue"
},
  "geometry": {"coordinates":[-85.274803,41.030961],"type":"Point"}
}