{
  "type": "Feature",
  "properties": {
    "iso:country":"US",
    "sg:address":"8748 Surrey Dr",
    "sg:city":"Pendleton",
    "sg:classifiers":[
        {
            "category":"Professional",
            "subcategory":"Art Services",
            "type":"Services"
        }
    ],
    "sg:phone":"+1 765 778 4577",
    "sg:postcode":"46064",
    "sg:province":"IN",
    "sg:tags":[
        "commercial",
        "design"
    ],
    "wof:name":"Miller Graphics",
    "wof:placetype":"venue"
},
  "geometry": {"coordinates":[-85.689026,40.008024],"type":"Point"}
}