{
  "type": "Feature",
  "properties": {
    "iso:country":"US",
    "sg:address":"9511 Poplar Creek Pl",
    "sg:city":"Leo",
    "sg:classifiers":[
        {
            "category":"Building & Trades",
            "subcategory":"Construction",
            "type":"Services"
        }
    ],
    "sg:phone":"+1 260 627 3663",
    "sg:postcode":"46765",
    "sg:province":"IN",
    "sg:tags":[
        "house"
    ],
    "wof:name":"Fordale Construction",
    "wof:placetype":"venue"
},
  "geometry": {"coordinates":[-85.025854,41.227768],"type":"Point"}
}