{
  "type": "Feature",
  "properties": {
    "iso:country":"US",
    "sg:address":"1305 W Mulberry St",
    "sg:city":"Salem",
    "sg:classifiers":[
        {
            "category":"Personal",
            "subcategory":"Beauty Salon",
            "type":"Services"
        }
    ],
    "sg:phone":"+1 812 883 6888",
    "sg:postcode":"47167",
    "sg:province":"IN",
    "wof:name":"Jan's Place",
    "wof:placetype":"venue"
},
  "geometry": {"coordinates":[-86.121624,38.608307],"type":"Point"}
}