{
  "type": "Feature",
  "properties": {
    "iso:country":"US",
    "sg:address":"9485 S 300 W",
    "sg:city":"Silver Lake",
    "sg:classifiers":[
        {
            "category":"Organizations",
            "subcategory":"Religious Organization",
            "type":"Services"
        }
    ],
    "sg:phone":"+1 260 352 2188",
    "sg:postcode":"46982",
    "sg:province":"IN",
    "sg:tags":[
        "church"
    ],
    "wof:name":"Center United Methodist Church",
    "wof:placetype":"venue"
},
  "geometry": {"coordinates":[-85.892786,41.094769],"type":"Point"}
}