{
  "type": "Feature",
  "properties": {
    "iso:country":"US",
    "sg:address":"4245 W Co Rd 250 S",
    "sg:city":"Sullivan",
    "sg:classifiers":[
        {
            "category":"Organizations",
            "subcategory":"Religious Organization",
            "type":"Services"
        }
    ],
    "sg:phone":"+1 812 356 4772",
    "sg:postcode":"47882",
    "sg:province":"IN",
    "wof:name":"New Lebanon United Method",
    "wof:placetype":"venue"
},
  "geometry": {"coordinates":[-87.480554,39.048209],"type":"Point"}
}