{
  "type": "Feature",
  "properties": {
    "iso:country":"US",
    "sg:address":"408 US Hwy 50",
    "sg:city":"Versailles",
    "sg:classifiers":[
        {
            "category":"Real Estate",
            "subcategory":"Real Estate Agent",
            "type":"Services"
        }
    ],
    "sg:phone":"+1 812 689 7110",
    "sg:postcode":"47042",
    "sg:province":"IN",
    "wof:name":"Realty Exchange",
    "wof:placetype":"venue"
},
  "geometry": {"coordinates":[-85.247458,39.066613],"type":"Point"}
}