{
  "type": "Feature",
  "properties": {
    "iso:country":"US",
    "sg:address":"754 Marana Dr",
    "sg:city":"Carmel",
    "sg:classifiers":[
        {
            "category":"Health Services",
            "subcategory":"Podiatrist",
            "type":"Services"
        }
    ],
    "sg:phone":"+1 317 581 8862",
    "sg:postcode":"46032",
    "sg:province":"IN",
    "sg:tags":[
        "equipment",
        "supply"
    ],
    "wof:name":"Shera Medical",
    "wof:placetype":"venue"
},
  "geometry": {"coordinates":[-86.14216,39.989545],"type":"Point"}
}