{
  "type": "Feature",
  "properties": {
    "iso:country":"US",
    "sg:address":"236 N 400 W",
    "sg:city":"Peru",
    "sg:classifiers":[
        {
            "category":"Building & Trades",
            "subcategory":"Construction",
            "type":"Services"
        }
    ],
    "sg:phone":"+1 765 473 5557",
    "sg:postcode":"46970",
    "sg:province":"IN",
    "sg:tags":[
        "consulting",
        "management",
        "nonresidential"
    ],
    "wof:name":"Boardwalk Constructors",
    "wof:placetype":"venue"
},
  "geometry": {"coordinates":[-86.149109,40.766436],"type":"Point"}
}