{
  "type": "Feature",
  "properties": {
    "iso:country":"US",
    "sg:address":"3309 Richmond Ave",
    "sg:city":"Connersville",
    "sg:classifiers":[
        {
            "category":"Organizations",
            "subcategory":"Religious Organization",
            "type":"Services"
        }
    ],
    "sg:phone":"+1 765 825 0885",
    "sg:postcode":"47331",
    "sg:province":"IN",
    "wof:name":"Dexter Worrell",
    "wof:placetype":"venue"
},
  "geometry": {"coordinates":[-85.125688,39.677492],"type":"Point"}
}