{
  "type": "Feature",
  "properties": {
    "iso:country":"US",
    "sg:address":"7625 Briarstone Dr",
    "sg:city":"Indianapolis",
    "sg:classifiers":[
        {
            "category":"Organizations",
            "subcategory":"Religious Organization",
            "type":"Services"
        }
    ],
    "sg:phone":"+1 317 884 1814",
    "sg:postcode":"46227",
    "sg:province":"IN",
    "sg:tags":[
        "monastery",
        "convent"
    ],
    "wof:name":"Sisters Of Providence",
    "wof:placetype":"venue"
},
  "geometry": {"coordinates":[-86.13041,39.655828],"type":"Point"}
}