{
  "type": "Feature",
  "properties": {
    "iso:country":"US",
    "sg:address":"767 N 900 E",
    "sg:city":"Pierceton",
    "sg:classifiers":[
        {
            "category":"Building & Trades",
            "subcategory":"Construction",
            "type":"Services"
        }
    ],
    "sg:phone":"+1 574 594 5950",
    "sg:postcode":"46562",
    "sg:province":"IN",
    "sg:tags":[
        "home",
        "improvement"
    ],
    "wof:name":"Mosher Maintenance Free",
    "wof:placetype":"venue"
},
  "geometry": {"coordinates":[-85.67064,41.238215],"type":"Point"}
}