{
  "type": "Feature",
  "properties": {
    "iso:country":"US",
    "sg:address":"3800 E State Rd 28",
    "sg:city":"Frankfort",
    "sg:classifiers":[
        {
            "category":"Building & Trades",
            "subcategory":"Construction",
            "type":"Services"
        }
    ],
    "sg:phone":"+1 765 656 0234",
    "sg:postcode":"46041",
    "sg:province":"IN",
    "sg:tags":[
        "tile",
        "dealer"
    ],
    "wof:name":"Custom Building Products",
    "wof:placetype":"venue"
},
  "geometry": {"coordinates":[-86.432203,40.278957],"type":"Point"}
}