{
  "type": "Feature",
  "properties": {
    "iso:country":"US",
    "sg:address":"200 E Michigan Blvd",
    "sg:city":"Michigan City",
    "sg:classifiers":[
        {
            "category":"Organizations",
            "subcategory":"Professional Association",
            "type":"Services"
        }
    ],
    "sg:phone":"+1 219 874 6221",
    "sg:postcode":"46360",
    "sg:province":"IN",
    "sg:tags":[
        "chambers",
        "commerce"
    ],
    "sg:website":"www.michigancitychamber.com",
    "wof:name":"Michigan Area Chamber-Commerce",
    "wof:placetype":"venue"
},
  "geometry": {"coordinates":[-86.900104,41.720321],"type":"Point"}
}