{
  "type": "Feature",
  "properties": {
    "iso:country":"US",
    "sg:address":"318 E Culver Rd",
    "sg:city":"Knox",
    "sg:classifiers":[
        {
            "category":"Government",
            "subcategory":"Office",
            "type":"Public Place"
        }
    ],
    "sg:phone":"+1 574 772 3411",
    "sg:postcode":"46534",
    "sg:province":"IN",
    "wof:name":"Starke County Ofc-Family & Chl",
    "wof:placetype":"venue"
},
  "geometry": {"coordinates":[-86.619266,41.287985],"type":"Point"}
}