{
  "type": "Feature",
  "properties": {
    "iso:country":"US",
    "sg:address":"1521 S Old US Hwy 27",
    "sg:city":"Angola",
    "sg:classifiers":[
        {
            "category":"Retail",
            "subcategory":"Repair Shop",
            "type":"Services"
        }
    ],
    "sg:phone":"+1 260 665 2611",
    "sg:postcode":"46703",
    "sg:province":"IN",
    "sg:tags":[
        "related"
    ],
    "wof:name":"Sarver's LLC",
    "wof:placetype":"venue"
},
  "geometry": {"coordinates":[-85.001222,41.618465],"type":"Point"}
}