{
  "type": "Feature",
  "properties": {
    "addr:full":"1814 Frisse Ave Evansville IN 47714",
    "addr:housenumber":"1814",
    "addr:postcode":"47714",
    "addr:street":"Frisse Ave",
    "iso:country":"US",
    "sg:address":"1814 Frisse Ave",
    "sg:city":"Evansville",
    "sg:classifiers":[
        {
            "category":"Building & Trades",
            "subcategory":"Construction",
            "type":"Services"
        }
    ],
    "sg:phone":"+1 812 477 2155",
    "sg:postcode":"47714",
    "sg:province":"IN",
    "sg:tags":[
        "siding",
        "contractor"
    ],
    "wof:name":"Landco Exteriors",
    "wof:placetype":"venue"
},
  "geometry": {"coordinates":[-87.52987400000001,37.945474],"type":"Point"}
}