{
  "type": "Feature",
  "properties": {
    "addr:full":"1108 Essex Dr Auburn IN 46706",
    "addr:housenumber":"1108",
    "addr:postcode":"46706",
    "addr:street":"Essex Dr",
    "iso:country":"US",
    "sg:address":"1108 Essex Dr",
    "sg:city":"Auburn",
    "sg:classifiers":[
        {
            "category":"Professional",
            "subcategory":"Management & Consulting",
            "type":"Services"
        }
    ],
    "sg:phone":"+1 260 925 6987",
    "sg:postcode":"46706",
    "sg:province":"IN",
    "sg:tags":[
        "consultant"
    ],
    "wof:name":"Molding Consulting Inc",
    "wof:placetype":"venue"
},
  "geometry": {"coordinates":[-85.04350100000001,41.376164],"type":"Point"}
}