{
  "type": "Feature",
  "properties": {
    "iso:country":"US",
    "sg:address":"4810 N Audubon Rd",
    "sg:city":"Indianapolis",
    "sg:classifiers":[
        {
            "category":"Personal",
            "subcategory":"Beauty Salon",
            "type":"Services"
        }
    ],
    "sg:phone":"+1 317 545 9513",
    "sg:postcode":"46226",
    "sg:province":"IN",
    "sg:tags":[
        "cosmetologist"
    ],
    "wof:name":"Carter Virginia",
    "wof:placetype":"venue"
},
  "geometry": {"coordinates":[-86.070635,39.843831],"type":"Point"}
}