{
  "type": "Feature",
  "properties": {
    "iso:country":"US",
    "sg:address":"4469 Arthur St",
    "sg:city":"Gary",
    "sg:classifiers":[
        {
            "category":"Professional",
            "subcategory":"Management & Consulting",
            "type":"Services"
        }
    ],
    "sg:phone":"+1 219 980 1110",
    "sg:postcode":"46408",
    "sg:province":"IN",
    "sg:tags":[
        "break",
        "coffee",
        "supply"
    ],
    "wof:name":"Quality Coffee Svc",
    "wof:placetype":"venue"
},
  "geometry": {"coordinates":[-87.35922,41.537649],"type":"Point"}
}