{
  "type": "Feature",
  "properties": {
    "iso:country":"US",
    "sg:address":"10804 W 117th Ave",
    "sg:city":"Cedar Lake",
    "sg:classifiers":[
        {
            "category":"Retail",
            "subcategory":"Portrait Studio",
            "type":"Services"
        }
    ],
    "sg:phone":"+1 219 374 6474",
    "sg:postcode":"46303",
    "sg:province":"IN",
    "sg:tags":[
        "photographer"
    ],
    "wof:name":"A R Richard's Photography",
    "wof:placetype":"venue"
},
  "geometry": {"coordinates":[-87.465485,41.406596],"type":"Point"}
}