{
  "type": "Feature",
  "properties": {
    "addr:full":"3020 Frontage Rd Warsaw IN 46580",
    "addr:housenumber":"3020",
    "addr:postcode":"46580",
    "addr:street":"Frontage Rd",
    "iso:country":"US",
    "sg:address":"3020 Frontage Rd",
    "sg:city":"Warsaw",
    "sg:classifiers":[
        {
            "category":"Home & Garden",
            "subcategory":"Mobile Homes",
            "type":"Retail Goods"
        }
    ],
    "sg:phone":"+1 574 268 1400",
    "sg:postcode":"46580",
    "sg:province":"IN",
    "wof:name":"Gallery Homes",
    "wof:placetype":"venue"
},
  "geometry": {"coordinates":[-85.81374599999999,41.236879],"type":"Point"}
}