{
  "type": "Feature",
  "properties": {
    "iso:country":"US",
    "sg:address":"1236 Belleview Dr",
    "sg:city":"Greendale",
    "sg:classifiers":[
        {
            "category":"Autos & Motor Vehicles",
            "subcategory":"Auto Supplies",
            "type":"Retail Goods"
        }
    ],
    "sg:phone":"+1 812 537 9252",
    "sg:postcode":"47025",
    "sg:province":"IN",
    "sg:tags":[
        "tire"
    ],
    "wof:name":"Dearborn Tire Mart",
    "wof:placetype":"venue"
},
  "geometry": {"coordinates":[-84.848373,39.12423],"type":"Point"}
}