{
  "type": "Feature",
  "properties": {
    "iso:country":"US",
    "sg:address":"762 Lakeshore Dr",
    "sg:city":"Scottsburg",
    "sg:classifiers":[
        {
            "category":"Education",
            "subcategory":"School",
            "type":"Public Place"
        }
    ],
    "sg:phone":"+1 812 752 7409",
    "sg:postcode":"47170",
    "sg:province":"IN",
    "wof:name":"OVO Headstart",
    "wof:placetype":"venue"
},
  "geometry": {"coordinates":[-85.7794,38.693132],"type":"Point"}
}