{
  "type": "Feature",
  "properties": {
    "iso:country":"US",
    "sg:address":"8315 E 56th St",
    "sg:city":"Indianapolis",
    "sg:classifiers":[
        {
            "category":"Health Services",
            "subcategory":"Doctor",
            "type":"Services"
        }
    ],
    "sg:phone":"+1 317 621 2232",
    "sg:postcode":"46216",
    "sg:province":"IN",
    "sg:tags":[
        "physician",
        "stomach",
        "intestines",
        "gastroenterology",
        "surgeons"
    ],
    "wof:name":"Indianapolis Endoscopy Center",
    "wof:placetype":"venue"
},
  "geometry": {"coordinates":[-86.02175,39.855],"type":"Point"}
}