{
  "type": "Feature",
  "properties": {
    "iso:country":"US",
    "sg:address":"1635 Elmore St",
    "sg:city":"Crawfordsville",
    "sg:classifiers":[
        {
            "category":"Manufacturing",
            "subcategory":"Motor Vehicles & Parts",
            "type":"Manufacturing & Wholesale Goods"
        }
    ],
    "sg:phone":"+1 765 362 5120",
    "sg:postcode":"47933",
    "sg:province":"IN",
    "sg:tags":[
        "trailer"
    ],
    "wof:name":"Fleetwood Travel Trailers Inc",
    "wof:placetype":"venue"
},
  "geometry": {"coordinates":[-86.879942,40.032201],"type":"Point"}
}