{
  "type": "Feature",
  "properties": {
    "addr:full":"8979 Broadway Merrillville IN 46410",
    "addr:housenumber":"8979",
    "addr:postcode":"46410",
    "addr:street":"Broadway",
    "iso:country":"US",
    "sg:address":"8979 Broadway",
    "sg:city":"Merrillville",
    "sg:classifiers":[
        {
            "category":"Insurance",
            "subcategory":"Hazard Insurance",
            "type":"Services"
        }
    ],
    "sg:phone":"+1 219 769 4012",
    "sg:postcode":"46410",
    "sg:province":"IN",
    "sg:tags":[
        "employee",
        "benefit",
        "compensation",
        "plan"
    ],
    "wof:name":"Shaner Insurance",
    "wof:placetype":"venue"
},
  "geometry": {"coordinates":[-87.33575999999999,41.455641],"type":"Point"}
}