{
  "type": "Feature",
  "properties": {
    "iso:country":"US",
    "sg:address":"229 Boulder Ct",
    "sg:city":"Carmel",
    "sg:classifiers":[
        {
            "category":"Building & Trades",
            "subcategory":"Landscaping Services",
            "type":"Services"
        }
    ],
    "sg:phone":"+1 317 573 9572",
    "sg:postcode":"46032",
    "sg:province":"IN",
    "sg:tags":[
        "landscape",
        "contractor"
    ],
    "wof:name":"Spaulding & Assoc Inc",
    "wof:placetype":"venue"
},
  "geometry": {"coordinates":[-86.132509,39.993127],"type":"Point"}
}