{
  "type": "Feature",
  "properties": {
    "addr:full":"18526 Lima Rd Huntertown IN 46748",
    "addr:housenumber":"18526",
    "addr:postcode":"46748",
    "addr:street":"Lima Rd",
    "iso:country":"US",
    "sg:address":"18526 Lima Rd",
    "sg:city":"Huntertown",
    "sg:classifiers":[
        {
            "category":"Building & Trades",
            "subcategory":"Construction",
            "type":"Services"
        }
    ],
    "sg:phone":"+1 260 436 2792",
    "sg:postcode":"46748",
    "sg:province":"IN",
    "sg:tags":[
        "builder",
        "repairer",
        "chimney"
    ],
    "wof:name":"Naylor & Sons Inc",
    "wof:placetype":"venue"
},
  "geometry": {"coordinates":[-85.18136699999999,41.256877],"type":"Point"}
}