{
  "type": "Feature",
  "properties": {
    "addr:full":"6012 Industrial Hwy Gary IN 46406",
    "addr:housenumber":"6012",
    "addr:postcode":"46406",
    "addr:street":"Industrial Hwy Gary",
    "iso:country":"US",
    "sg:address":"6012 Industrial Hwy",
    "sg:city":"Gary",
    "sg:classifiers":[
        {
            "category":"Recreation",
            "subcategory":"Arcade",
            "type":"Entertainment"
        }
    ],
    "sg:phone":"+1 219 977 7000",
    "sg:postcode":"46406",
    "sg:province":"IN",
    "sg:tags":[
        "casino"
    ],
    "wof:name":"Trump Casino",
    "wof:placetype":"venue"
},
  "geometry": {"coordinates":[-87.39980300000001,41.614203],"type":"Point"}
}