{
  "type": "Feature",
  "properties": {
    "iso:country":"US",
    "sg:address":"1001 Evans Ave",
    "sg:city":"Valparaiso",
    "sg:classifiers":[
        {
            "category":"Personal",
            "subcategory":"Beauty Salon",
            "type":"Services"
        }
    ],
    "sg:phone":"+1 219 548 8383",
    "sg:postcode":"46383",
    "sg:province":"IN",
    "wof:name":"Cinnamon Tree",
    "wof:placetype":"venue"
},
  "geometry": {"coordinates":[-87.046527,41.478162],"type":"Point"}
}