{
  "type": "Feature",
  "properties": {
    "iso:country":"US",
    "sg:address":"800 W 7th St",
    "sg:city":"Muncie",
    "sg:classifiers":[
        {
            "category":"Organizations",
            "subcategory":"Labor Organization",
            "type":"Services"
        }
    ],
    "sg:phone":"+1 765 288 0994",
    "sg:postcode":"47302",
    "sg:province":"IN",
    "wof:name":"Graphic Communications Intl Un",
    "wof:placetype":"venue"
},
  "geometry": {"coordinates":[-85.39591799999999,40.183245],"type":"Point"}
}