{
  "type": "Feature",
  "properties": {
    "iso:country":"US",
    "sg:address":"8320 N Michigan Rd",
    "sg:city":"Indianapolis",
    "sg:classifiers":[
        {
            "category":"Organizations",
            "subcategory":"Non-profit Organization",
            "type":"Services"
        }
    ],
    "sg:phone":"+1 317 471 1316",
    "sg:postcode":"46268",
    "sg:province":"IN",
    "sg:tags":[
        "information",
        "alcoholism",
        "treatment"
    ],
    "wof:name":"Guardian Interlock",
    "wof:placetype":"venue"
},
  "geometry": {"coordinates":[-86.222257,39.910384],"type":"Point"}
}