{
  "type": "Feature",
  "properties": {
    "iso:country":"US",
    "sg:address":"1282 Washington St",
    "sg:city":"Columbus",
    "sg:classifiers":[
        {
            "category":"Personal",
            "type":"Services"
        }
    ],
    "sg:phone":"+1 812 375 9631",
    "sg:postcode":"47201",
    "sg:province":"IN",
    "sg:tags":[
        "therapist",
        "massage"
    ],
    "wof:name":"Progressive Health",
    "wof:placetype":"venue"
},
  "geometry": {"coordinates":[-85.921542,39.211946],"type":"Point"}
}