{
  "type": "Feature",
  "properties": {
    "iso:country":"US",
    "sg:address":"27031 Pocket Rd",
    "sg:city":"Batesville",
    "sg:classifiers":[
        {
            "category":"Farming",
            "subcategory":"Dairy Farm",
            "type":"Manufacturing & Wholesale Goods"
        }
    ],
    "sg:phone":"+1 812 934 3574",
    "sg:postcode":"47006",
    "sg:province":"IN",
    "wof:name":"Alvin Kessens",
    "wof:placetype":"venue"
},
  "geometry": {"coordinates":[-85.277569,39.322172],"type":"Point"}
}