{
  "type": "Feature",
  "properties": {
    "iso:country":"US",
    "sg:address":"429 Dream Way",
    "sg:city":"Cloverdale",
    "sg:classifiers":[
        {
            "category":"Organizations",
            "subcategory":"Professional Association",
            "type":"Services"
        }
    ],
    "sg:phone":"+1 765 795 5238",
    "sg:postcode":"46120",
    "sg:province":"IN",
    "wof:name":"Wabash Valley Chapter MADD",
    "wof:placetype":"venue"
},
  "geometry": {"coordinates":[-86.810001,39.521668],"type":"Point"}
}