{
  "type": "Feature",
  "properties": {
    "addr:full":"412 E Main St New Albany IN 47150",
    "addr:housenumber":"412",
    "addr:postcode":"47150",
    "addr:street":"E Main St",
    "iso:country":"US",
    "sg:address":"412 E Main St",
    "sg:city":"New Albany",
    "sg:classifiers":[
        {
            "category":"Professional",
            "subcategory":"Lawyer & Legal Services",
            "type":"Services"
        }
    ],
    "sg:phone":"+1 812 542 0048",
    "sg:postcode":"47150",
    "sg:province":"IN",
    "sg:tags":[
        "attorney"
    ],
    "wof:name":"Stanley O Faith",
    "wof:placetype":"venue"
},
  "geometry": {"coordinates":[-85.81778,38.28516],"type":"Point"}
}