{
  "type": "Feature",
  "properties": {
    "iso:country":"US",
    "sg:address":"816 E Auto Mall Rd",
    "sg:city":"Bloomington",
    "sg:classifiers":[
        {
            "category":"Recreation",
            "type":"Entertainment"
        }
    ],
    "sg:phone":"+1 812 333 0159",
    "sg:postcode":"47401",
    "sg:province":"IN",
    "wof:name":"Harrison Renny",
    "wof:placetype":"venue"
},
  "geometry": {"coordinates":[-86.49616,39.155571],"type":"Point"}
}