{
  "type": "Feature",
  "properties": {
    "addr:full":"2917 Michigan Rd Madison IN 47250",
    "addr:housenumber":"2917",
    "addr:postcode":"47250",
    "addr:street":"Michigan Rd",
    "iso:country":"US",
    "sg:address":"2917 Michigan Rd",
    "sg:city":"Madison",
    "sg:classifiers":[
        {
            "category":"Manufacturing",
            "subcategory":"Metals",
            "type":"Manufacturing & Wholesale Goods"
        }
    ],
    "sg:phone":"+1 812 265 1553",
    "sg:postcode":"47250",
    "sg:province":"IN",
    "sg:tags":[
        "tubing"
    ],
    "wof:name":"Midwest Tube Mills Inc",
    "wof:placetype":"venue"
},
  "geometry": {"coordinates":[-85.38738600000001,38.780692],"type":"Point"}
}