{
  "type": "Feature",
  "properties": {
    "iso:country":"US",
    "sg:address":"301 E 13th St",
    "sg:city":"Huntingburg",
    "sg:classifiers":[
        {
            "category":"Health Services",
            "subcategory":"Optometrist",
            "type":"Services"
        }
    ],
    "sg:phone":"+1 812 683 4443",
    "sg:postcode":"47542",
    "sg:province":"IN",
    "wof:name":"Professional Eyecare Assoc",
    "wof:placetype":"venue"
},
  "geometry": {"coordinates":[-86.95867,38.307144],"type":"Point"}
}