{
  "type": "Feature",
  "properties": {
    "iso:country":"US",
    "sg:address":"325 Boulevard",
    "sg:city":"Kokomo",
    "sg:classifiers":[
        {
            "category":"Building & Trades",
            "subcategory":"Cleaning & Sanitation",
            "type":"Services"
        }
    ],
    "sg:phone":"+1 765 455 5899",
    "sg:postcode":"46970",
    "sg:province":"IN",
    "sg:tags":[
        "janitor"
    ],
    "wof:name":"Preferred Touch Cleaning Svc",
    "wof:placetype":"venue"
},
  "geometry": {"coordinates":[-86.083234,40.755075],"type":"Point"}
}