{
  "type": "Feature",
  "properties": {
    "addr:full":"1309 N Fruitridge Ave Terre Haute IN 47804",
    "addr:housenumber":"1309",
    "addr:postcode":"47804",
    "addr:street":"N Fruitridge Ave",
    "iso:country":"US",
    "sg:address":"1309 N Fruitridge Ave",
    "sg:city":"Terre Haute",
    "sg:classifiers":[
        {
            "category":"Farming",
            "subcategory":"Nursery",
            "type":"Manufacturing & Wholesale Goods"
        }
    ],
    "sg:phone":"+1 812 466 5104",
    "sg:postcode":"47804",
    "sg:province":"IN",
    "sg:tags":[
        "greenhouse"
    ],
    "wof:name":"Fruitridge Gardens",
    "wof:placetype":"venue"
},
  "geometry": {"coordinates":[-87.360108,39.498703],"type":"Point"}
}