{
  "type": "Feature",
  "properties": {
    "iso:country":"US",
    "sg:address":"5730 Broadway",
    "sg:city":"Merrillville",
    "sg:classifiers":[
        {
            "category":"Retail",
            "subcategory":"Auto Repair",
            "type":"Services"
        }
    ],
    "sg:phone":"+1 219 884 9263",
    "sg:postcode":"46410",
    "sg:province":"IN",
    "sg:tags":[
        "transmission"
    ],
    "wof:name":"Mr Transmission",
    "wof:placetype":"venue"
},
  "geometry": {"coordinates":[-87.33618300000001,41.513705],"type":"Point"}
}