{
  "type": "Feature",
  "properties": {
    "addr:full":"103 W Franklin St Delphi IN 46923",
    "addr:housenumber":"103",
    "addr:postcode":"46923",
    "addr:street":"W Franklin St",
    "iso:country":"US",
    "sg:address":"103 W Franklin St",
    "sg:city":"Delphi",
    "sg:classifiers":[
        {
            "category":"Restaurant",
            "type":"Food & Drink"
        }
    ],
    "sg:phone":"+1 765 564 3202",
    "sg:postcode":"46923",
    "sg:province":"IN",
    "wof:name":"Mc Greevey's Pizza King",
    "wof:placetype":"venue"
},
  "geometry": {"coordinates":[-86.674599,40.58705],"type":"Point"}
}