{
  "type": "Feature",
  "properties": {
    "iso:country":"US",
    "sg:address":"1950 Indianapolis Blvd",
    "sg:city":"Whiting",
    "sg:classifiers":[
        {
            "category":"Restaurant",
            "type":"Food & Drink"
        }
    ],
    "sg:phone":"+1 219 473 7985",
    "sg:postcode":"46394",
    "sg:province":"IN",
    "sg:tags":[
        "eating"
    ],
    "wof:name":"2 Friends Cafe",
    "wof:placetype":"venue"
},
  "geometry": {"coordinates":[-87.497639,41.6778],"type":"Point"}
}