{
  "type": "Feature",
  "properties": {
    "iso:country":"US",
    "sg:address":"11741 N 100 E",
    "sg:city":"Decatur",
    "sg:classifiers":[
        {
            "category":"Shopping",
            "subcategory":"Clothing, Apparel, & Fashions",
            "type":"Retail Goods"
        }
    ],
    "sg:phone":"+1 260 724 8742",
    "sg:postcode":"46733",
    "sg:province":"IN",
    "wof:name":"Mr Screenprinting Ltd",
    "wof:placetype":"venue"
},
  "geometry": {"coordinates":[-84.91905,40.916482],"type":"Point"}
}