{
  "type": "Feature",
  "properties": {
    "iso:country":"US",
    "sg:address":"460 N Oak St Exd",
    "sg:city":"Bluffton",
    "sg:classifiers":[
        {
            "category":"Building & Trades",
            "subcategory":"Construction",
            "type":"Services"
        }
    ],
    "sg:phone":"+1 260 824 5429",
    "sg:postcode":"46714",
    "sg:province":"IN",
    "sg:tags":[
        "residential",
        "contractor"
    ],
    "wof:name":"Taylor Construction",
    "wof:placetype":"venue"
},
  "geometry": {"coordinates":[-85.182117,40.751835],"type":"Point"}
}