{
  "type": "Feature",
  "properties": {
    "addr:full":"717 W Jefferson Blvd Fort Wayne IN 46802",
    "addr:housenumber":"717",
    "addr:postcode":"46802",
    "addr:street":"W Jefferson Blvd",
    "iso:country":"US",
    "sg:address":"717 W Jefferson Blvd",
    "sg:city":"Fort Wayne",
    "sg:classifiers":[
        {
            "category":"Health Services",
            "subcategory":"Doctor",
            "type":"Services"
        }
    ],
    "sg:phone":"+1 260 426 3494",
    "sg:postcode":"46802",
    "sg:province":"IN",
    "sg:tags":[
        "physician",
        "surgeon"
    ],
    "wof:name":"Earl A Braunlin MD",
    "wof:placetype":"venue"
},
  "geometry": {"coordinates":[-85.148915,41.074567],"type":"Point"}
}