{
  "type": "Feature",
  "properties": {
    "iso:country":"US",
    "sg:address":"7416 Sargent Rd",
    "sg:city":"Indianapolis",
    "sg:classifiers":[
        {
            "category":"Professional",
            "subcategory":"Management & Consulting",
            "type":"Services"
        }
    ],
    "sg:phone":"+1 317 722 0500",
    "sg:postcode":"46256",
    "sg:province":"IN",
    "sg:tags":[
        "consultant",
        "search",
        "executive"
    ],
    "wof:name":"Johnson Brown Associates Inc",
    "wof:placetype":"venue"
},
  "geometry": {"coordinates":[-86.01966,39.888013],"type":"Point"}
}