{
  "type": "Feature",
  "properties": {
    "addr:full":"616 E Main St Muncie IN 47305",
    "addr:housenumber":"616",
    "addr:postcode":"47305",
    "addr:street":"E Main St",
    "iso:country":"US",
    "sg:address":"616 E Main St",
    "sg:city":"Muncie",
    "sg:classifiers":[
        {
            "category":"Organizations",
            "subcategory":"Non-profit Organization",
            "type":"Services"
        }
    ],
    "sg:phone":"+1 765 284 3556",
    "sg:postcode":"47305",
    "sg:province":"IN",
    "wof:name":"East Central Reinvestment Corp",
    "wof:placetype":"venue"
},
  "geometry": {"coordinates":[-85.379666,40.193633],"type":"Point"}
}