{
  "type": "Feature",
  "properties": {
    "iso:country":"US",
    "sg:address":"921 E 86th St",
    "sg:city":"Indianapolis",
    "sg:classifiers":[
        {
            "category":"Real Estate",
            "subcategory":"Real Estate Services",
            "type":"Services"
        }
    ],
    "sg:phone":"+1 317 726 1443",
    "sg:postcode":"46240",
    "sg:province":"IN",
    "sg:tags":[
        "company",
        "title"
    ],
    "sg:website":"www.titlefirst.com",
    "wof:name":"Title First Agency",
    "wof:placetype":"venue"
},
  "geometry": {"coordinates":[-86.141279,39.912464],"type":"Point"}
}