{
  "type": "Feature",
  "properties": {
    "addr:full":"1326 N Weinbach Ave Evansville IN 47711",
    "addr:housenumber":"1326",
    "addr:postcode":"47711",
    "addr:street":"N Weinbach Ave",
    "iso:country":"US",
    "sg:address":"1326 N Weinbach Ave",
    "sg:city":"Evansville",
    "sg:classifiers":[
        {
            "category":"Recreation",
            "type":"Entertainment"
        }
    ],
    "sg:phone":"+1 812 491 9642",
    "sg:postcode":"47711",
    "sg:province":"IN",
    "sg:tags":[
        "instruction",
        "yoga"
    ],
    "wof:name":"Sundance Yoga Studio",
    "wof:placetype":"venue"
},
  "geometry": {"coordinates":[-87.529246,37.991437],"type":"Point"}
}