{
  "type": "Feature",
  "properties": {
    "iso:country":"US",
    "sg:address":"702 Barnhill Dr",
    "sg:city":"Indianapolis",
    "sg:classifiers":[
        {
            "category":"Health Services",
            "subcategory":"Doctor",
            "type":"Services"
        }
    ],
    "sg:phone":"+1 317 274 8571",
    "sg:postcode":"46202",
    "sg:province":"IN",
    "sg:tags":[
        "medical"
    ],
    "wof:name":"Michael H Fritsch MD Inc",
    "wof:placetype":"venue"
},
  "geometry": {"coordinates":[-86.178686,39.775943],"type":"Point"}
}