{
  "type": "Feature",
  "properties": {
    "iso:country":"US",
    "sg:address":"520 Mary St",
    "sg:city":"Evansville",
    "sg:classifiers":[
        {
            "category":"Health Services",
            "subcategory":"Doctor",
            "type":"Services"
        }
    ],
    "sg:phone":"+1 812 424 2800",
    "sg:postcode":"47710",
    "sg:province":"IN",
    "sg:tags":[
        "physician",
        "surgeon"
    ],
    "wof:name":"Neurocare Diagnostics",
    "wof:placetype":"venue"
},
  "geometry": {"coordinates":[-87.570778,37.982769],"type":"Point"}
}