{
  "type": "Feature",
  "properties": {
    "iso:country":"US",
    "sg:address":"2612 N 6th St",
    "sg:city":"Vincennes",
    "sg:classifiers":[
        {
            "category":"Banks & Credit Unions",
            "subcategory":"Bank",
            "type":"Services"
        }
    ],
    "sg:phone":"+1 812 882 2919",
    "sg:postcode":"47591",
    "sg:province":"IN",
    "wof:name":"Old National Bank",
    "wof:placetype":"venue"
},
  "geometry": {"coordinates":[-87.50576,38.688893],"type":"Point"}
}