{
  "type": "Feature",
  "properties": {
    "iso:country":"US",
    "sg:address":"2405 Raible Ave",
    "sg:city":"Carmel",
    "sg:classifiers":[
        {
            "category":"Building & Trades",
            "subcategory":"Cleaning & Sanitation",
            "type":"Services"
        }
    ],
    "sg:phone":"+1 317 815 5700",
    "sg:postcode":"46032",
    "sg:province":"IN",
    "sg:tags":[
        "carpet"
    ],
    "wof:name":"Edmonson Carpet & Upholstery Cleaning",
    "wof:placetype":"venue"
},
  "geometry": {"coordinates":[-86.161102,39.971401],"type":"Point"}
}