{
  "type": "Feature",
  "properties": {
    "iso:country":"US",
    "sg:address":"605 N Dixon Rd",
    "sg:city":"Kokomo",
    "sg:classifiers":[
        {
            "category":"Banks & Credit Unions",
            "subcategory":"Bank",
            "type":"Services"
        }
    ],
    "sg:phone":"+1 765 452 1545",
    "sg:postcode":"46901",
    "sg:province":"IN",
    "wof:name":"Salin Bank & Trust Co",
    "wof:placetype":"venue"
},
  "geometry": {"coordinates":[-86.165014,40.494375],"type":"Point"}
}