{
  "type": "Feature",
  "properties": {
    "addr:full":"4931 Robison Rd Indianapolis IN 46268",
    "addr:housenumber":"4931",
    "addr:postcode":"46268",
    "addr:street":"Robison Rd",
    "iso:country":"US",
    "sg:address":"4931 Robison Rd",
    "sg:city":"Indianapolis",
    "sg:classifiers":[
        {
            "category":"Home & Garden",
            "subcategory":"Garden Supply",
            "type":"Retail Goods"
        }
    ],
    "sg:phone":"+1 317 228 4900",
    "sg:postcode":"46268",
    "sg:province":"IN",
    "sg:tags":[
        "mulch"
    ],
    "sg:website":"www.tiffanylawnandgarden.com",
    "wof:name":"Tiffany Lawn & Garden Supl Inc",
    "wof:placetype":"venue"
},
  "geometry": {"coordinates":[-86.25091399999999,39.924807],"type":"Point"}
}