{
  "type": "Feature",
  "properties": {
    "addr:full":"51637 Ash Rd Granger IN 46530",
    "addr:housenumber":"51637",
    "addr:postcode":"46530",
    "addr:street":"Ash Rd",
    "iso:country":"US",
    "sg:address":"51637 Ash Rd",
    "sg:city":"Granger",
    "sg:classifiers":[
        {
            "category":"Organizations",
            "subcategory":"Religious Organization",
            "type":"Services"
        }
    ],
    "sg:phone":"+1 574 679 9464",
    "sg:postcode":"46530",
    "sg:province":"IN",
    "sg:tags":[
        "church"
    ],
    "wof:name":"Michiana Church Of God",
    "wof:placetype":"venue"
},
  "geometry": {"coordinates":[-86.062286,41.745101],"type":"Point"}
}