{
  "type": "Feature",
  "properties": {
    "iso:country":"US",
    "sg:address":"4155 N Co Rd 1000 E",
    "sg:city":"Brownsburg",
    "sg:classifiers":[
        {
            "category":"Autos & Motor Vehicles",
            "subcategory":"Motorcycle Sales",
            "type":"Retail Goods"
        }
    ],
    "sg:phone":"+1 317 858 1830",
    "sg:postcode":"46112",
    "sg:province":"IN",
    "sg:tags":[
        "car",
        "golf",
        "cart"
    ],
    "wof:name":"Pit Pro Custom Carts",
    "wof:placetype":"venue"
},
  "geometry": {"coordinates":[-86.346171,39.824576],"type":"Point"}
}