{
  "type": "Feature",
  "properties": {
    "iso:country":"US",
    "sg:address":"6304 Guilford Ave",
    "sg:city":"Indianapolis",
    "sg:classifiers":[
        {
            "category":"Professional",
            "subcategory":"Management & Consulting",
            "type":"Services"
        }
    ],
    "sg:phone":"+1 317 252 5630",
    "sg:postcode":"46220",
    "sg:province":"IN",
    "sg:tags":[
        "consultant",
        "business"
    ],
    "sg:website":"www.insg.net",
    "wof:name":"INSGLLC",
    "wof:placetype":"venue"
},
  "geometry": {"coordinates":[-86.14296,39.870552],"type":"Point"}
}