{
  "type": "Feature",
  "properties": {
    "iso:country":"US",
    "sg:address":"2517 Dieffenbach Rd",
    "sg:city":"Evansville",
    "sg:classifiers":[
        {
            "category":"Building & Trades",
            "subcategory":"Construction",
            "type":"Services"
        }
    ],
    "sg:phone":"+1 812 424 3198",
    "sg:postcode":"47720",
    "sg:province":"IN",
    "sg:tags":[
        "house"
    ],
    "wof:name":"Fred Rutledge Construction",
    "wof:placetype":"venue"
},
  "geometry": {"coordinates":[-87.650173,38.001421],"type":"Point"}
}