{
  "type": "Feature",
  "properties": {
    "iso:country":"US",
    "sg:address":"2230 Fairfield Ave",
    "sg:city":"Fort Wayne",
    "sg:classifiers":[
        {
            "category":"Autos & Motor Vehicles",
            "subcategory":"Automobile Sales",
            "type":"Retail Goods"
        }
    ],
    "sg:phone":"+1 260 744 6244",
    "sg:postcode":"46802",
    "sg:province":"IN",
    "sg:tags":[
        "car",
        "dealer"
    ],
    "wof:name":"Marquez Auto Sales",
    "wof:placetype":"venue"
},
  "geometry": {"coordinates":[-85.145257,41.064415],"type":"Point"}
}