{
  "type": "Feature",
  "properties": {
    "iso:country":"US",
    "sg:address":"9600 N 125 W",
    "sg:city":"Fortville",
    "sg:classifiers":[
        {
            "category":"Real Estate",
            "subcategory":"Real Estate Agent",
            "type":"Services"
        }
    ],
    "sg:phone":"+1 317 485 5252",
    "sg:postcode":"46040",
    "sg:province":"IN",
    "wof:name":"Location Realty",
    "wof:placetype":"venue"
},
  "geometry": {"coordinates":[-85.829301,39.923839],"type":"Point"}
}