{
  "type": "Feature",
  "properties": {
    "iso:country":"US",
    "sg:address":"314 4th St",
    "sg:city":"Logansport",
    "sg:classifiers":[
        {
            "category":"Banks & Credit Unions",
            "subcategory":"Bank",
            "type":"Services"
        }
    ],
    "sg:phone":"+1 574 722 6261",
    "sg:postcode":"46947",
    "sg:province":"IN",
    "wof:name":"Security Federal Savings Bank",
    "wof:placetype":"venue"
},
  "geometry": {"coordinates":[-86.365731,40.75354],"type":"Point"}
}