{
  "type": "Feature",
  "properties": {
    "addr:full":"1600 119th St Whiting IN 46394",
    "addr:housenumber":"1600",
    "addr:postcode":"46394",
    "addr:street":"119Th St",
    "iso:country":"US",
    "sg:address":"1600 119th St",
    "sg:city":"Whiting",
    "sg:classifiers":[
        {
            "category":"Shopping",
            "subcategory":"Used Merchandise",
            "type":"Retail Goods"
        }
    ],
    "sg:phone":"+1 219 659 3438",
    "sg:postcode":"46394",
    "sg:province":"IN",
    "wof:name":"Antiques-Just Little Things",
    "wof:placetype":"venue"
},
  "geometry": {"coordinates":[-87.489869,41.679342],"type":"Point"}
}