{
  "type": "Feature",
  "properties": {
    "addr:full":"11534 N Co Rd 200 E Brazil IN 47834",
    "addr:housenumber":"11534",
    "addr:postcode":"47834",
    "addr:street":"N Co Rd 200 E",
    "iso:country":"US",
    "sg:address":"11534 N Co Rd 200 E",
    "sg:city":"Brazil",
    "sg:phone":"+1 812 448 3632",
    "sg:postcode":"47834",
    "sg:province":"IN",
    "sg:tags":[
        "farm",
        "corn",
        "soybean"
    ],
    "wof:name":"Mace John",
    "wof:placetype":"venue"
},
  "geometry": {"coordinates":[-87.070008,39.556535],"type":"Point"}
}