{
  "type": "Feature",
  "properties": {
    "iso:country":"US",
    "sg:address":"714 E 65th St",
    "sg:city":"Indianapolis",
    "sg:classifiers":[
        {
            "category":"Organizations",
            "subcategory":"Non-profit Organization",
            "type":"Services"
        }
    ],
    "sg:phone":"+1 317 253 5340",
    "sg:postcode":"46220",
    "sg:province":"IN",
    "wof:name":"Hoosier Salon Patrons Assn",
    "wof:placetype":"venue"
},
  "geometry": {"coordinates":[-86.144845,39.873573],"type":"Point"}
}