{
  "type": "Feature",
  "properties": {
    "addr:city":"Indianapolis",
    "addr:full":"714 E 65Th St Indianapolis, In 46220-1610",
    "addr:house_number":"714",
    "addr:housenumber":"714",
    "addr:phone":"+1 317-253-5340",
    "addr:postcode":"46220-1610",
    "addr:road":"E 65Th St",
    "addr:state":"IN",
    "addr:street":"E 65Th St",
    "iso:country":"US",
    "sg:address":"714 E 65th St",
    "sg:city":"Indianapolis",
    "sg:classifiers":[
        {
            "category":"Organizations",
            "subcategory":"Non-profit Organization",
            "type":"Services"
        }
    ],
    "sg:phone":"+1 317 253 5340",
    "sg:postcode":"46220",
    "sg:province":"IN",
    "wof:airports":[
        102534155
    ],
    "wof:name":"Hoosier Salon Patrons Association",
    "wof:placetype":"venue"
},
  "geometry": {"coordinates":[-86.14606999999999,39.87342],"type":"Point"}
}