{
  "type": "Feature",
  "properties": {
    "iso:country":"US",
    "sg:address":"12475 Springbrooke Run",
    "sg:city":"Carmel",
    "sg:classifiers":[
        {
            "category":"Professional",
            "subcategory":"Business Services",
            "type":"Services"
        }
    ],
    "sg:phone":"+1 317 815 4801",
    "sg:postcode":"46033",
    "sg:province":"IN",
    "wof:name":"Jamie Gauker Interior Dctg",
    "wof:placetype":"venue"
},
  "geometry": {"coordinates":[-86.079051,39.964405],"type":"Point"}
}