{
  "type": "Feature",
  "properties": {
    "iso:country":"US",
    "sg:address":"1142 Sugar Maple Dr",
    "sg:city":"Greenwood",
    "sg:classifiers":[
        {
            "category":"Place Of Worship",
            "subcategory":"Church",
            "type":"Public Place"
        },
        {
            "category":"Place Of Worship",
            "type":"Public Place"
        }
    ],
    "sg:phone":"+1 317 859 0832",
    "sg:postcode":"46143",
    "sg:province":"IN",
    "sg:tags":[
        "churches-pentecostal-independent",
        "churches-pentecostal"
    ],
    "wof:name":"Pentecost & Assoc Inc",
    "wof:placetype":"venue"
},
  "geometry": {"coordinates":[-86.079982,39.596075],"type":"Point"}
}