{
  "type": "Feature",
  "properties": {
    "iso:country":"US",
    "sg:address":"8364 State Rd 39",
    "sg:city":"Clayton",
    "sg:classifiers":[
        {
            "category":"Farming",
            "subcategory":"Farm & Veterinary Services",
            "type":"Manufacturing & Wholesale Goods"
        }
    ],
    "sg:phone":"+1 317 539 2753",
    "sg:postcode":"46118",
    "sg:province":"IN",
    "sg:tags":[
        "crop",
        "general"
    ],
    "wof:name":"Centered Valley Organic Farm",
    "wof:placetype":"venue"
},
  "geometry": {"coordinates":[-86.481679,39.639183],"type":"Point"}
}