{
  "type": "Feature",
  "properties": {
    "iso:country":"US",
    "sg:address":"11 E Village Dr",
    "sg:city":"Madison",
    "sg:classifiers":[
        {
            "category":"Real Estate",
            "subcategory":"Real Estate Operator",
            "type":"Services"
        }
    ],
    "sg:phone":"+1 812 273 3717",
    "sg:postcode":"47250",
    "sg:province":"IN",
    "sg:tags":[
        "mobile",
        "home",
        "community"
    ],
    "wof:name":"Madison Village Manufactured",
    "wof:placetype":"venue"
},
  "geometry": {"coordinates":[-85.386219,38.792024],"type":"Point"}
}