{
  "type": "Feature",
  "properties": {
    "iso:country":"US",
    "sg:address":"3242 E State Rd 14",
    "sg:city":"Fair Oaks",
    "sg:classifiers":[
        {
            "category":"Recreation",
            "type":"Entertainment"
        }
    ],
    "sg:phone":"+1 219 394 2363",
    "sg:postcode":"47963",
    "sg:province":"IN",
    "sg:tags":[
        "club",
        "membership"
    ],
    "wof:name":"New Horizons Hunt Club",
    "wof:placetype":"venue"
},
  "geometry": {"coordinates":[-87.332792,41.013422],"type":"Point"}
}