{
  "type": "Feature",
  "properties": {
    "iso:country":"US",
    "sg:address":"3236 Industrial Pkwy",
    "sg:city":"Jeffersonville",
    "sg:classifiers":[
        {
            "category":"Freight",
            "type":"Transportation"
        }
    ],
    "sg:phone":"+1 812 284 3263",
    "sg:postcode":"47130",
    "sg:province":"IN",
    "sg:tags":[
        "trucking"
    ],
    "wof:name":"Bennett Frozen Freight",
    "wof:placetype":"venue"
},
  "geometry": {"coordinates":[-85.749917,38.31244],"type":"Point"}
}