{
  "type": "Feature",
  "properties": {
    "iso:country":"US",
    "sg:address":"515 S Maple St",
    "sg:city":"Galveston",
    "sg:classifiers":[
        {
            "category":"Organizations",
            "subcategory":"Religious Organization",
            "type":"Services"
        }
    ],
    "sg:phone":"+1 574 699 7642",
    "sg:postcode":"46932",
    "sg:province":"IN",
    "sg:tags":[
        "church"
    ],
    "sg:website":"www.galvestonumchurch.org",
    "wof:name":"Galveston United Methodist Chr",
    "wof:placetype":"venue"
},
  "geometry": {"coordinates":[-86.193559,40.573422],"type":"Point"}
}