{
  "type": "Feature",
  "properties": {
    "addr:full":"2992 W 11th Ave Gary IN 46404",
    "addr:housenumber":"2992",
    "addr:postcode":"46404",
    "addr:street":"W 11Th Ave",
    "iso:country":"US",
    "sg:address":"2992 W 11th Ave",
    "sg:city":"Gary",
    "sg:classifiers":[
        {
            "category":"Personal",
            "subcategory":"Shoe Repair & Shine",
            "type":"Services"
        }
    ],
    "sg:phone":"+1 219 949 0557",
    "sg:postcode":"46404",
    "sg:province":"IN",
    "sg:tags":[
        "repairing",
        "boot"
    ],
    "wof:name":"Al's Shoe Repair",
    "wof:placetype":"venue"
},
  "geometry": {"coordinates":[-87.374661,41.591602],"type":"Point"}
}