{
  "type": "Feature",
  "properties": {
    "iso:country":"US",
    "sg:address":"3803 Murvihill Rd",
    "sg:city":"Valparaiso",
    "sg:classifiers":[
        {
            "category":"Autos & Motor Vehicles",
            "subcategory":"Automobile Sales",
            "type":"Retail Goods"
        }
    ],
    "sg:phone":"+1 219 462 7826",
    "sg:postcode":"46383",
    "sg:province":"IN",
    "sg:tags":[
        "aircraft"
    ],
    "wof:name":"Hall Aircraft",
    "wof:placetype":"venue"
},
  "geometry": {"coordinates":[-87.01213,41.44907],"type":"Point"}
}