{
  "type": "Feature",
  "properties": {
    "iso:country":"US",
    "sg:address":"3900 S Old State Road 37",
    "sg:city":"Bloomington",
    "sg:classifiers":[
        {
            "category":"Professional",
            "subcategory":"Accounting & Tax Preparation",
            "type":"Services"
        }
    ],
    "sg:phone":"+1 812 330 0154",
    "sg:postcode":"47401",
    "sg:province":"IN",
    "sg:tags":[
        "bookkeeping",
        "general"
    ],
    "wof:name":"Advantage Accounting Svc Inc",
    "wof:placetype":"venue"
},
  "geometry": {"coordinates":[-86.531345,39.121449],"type":"Point"}
}