{
  "type": "Feature",
  "properties": {
    "iso:country":"US",
    "sg:address":"700 W 50 N",
    "sg:city":"Wabash",
    "sg:classifiers":[
        {
            "category":"Building & Trades",
            "subcategory":"Construction",
            "type":"Services"
        }
    ],
    "sg:phone":"+1 260 563 8350",
    "sg:postcode":"46992",
    "sg:province":"IN",
    "sg:tags":[
        "contractor"
    ],
    "sg:website":"www.kellaminc.com",
    "wof:name":"Kellam Inc",
    "wof:placetype":"venue"
},
  "geometry": {"coordinates":[-85.803647,40.832417],"type":"Point"}
}