{
  "type": "Feature",
  "properties": {
    "iso:country":"US",
    "sg:address":"115 N Girls School Rd",
    "sg:city":"Indianapolis",
    "sg:classifiers":[
        {
            "category":"Professional",
            "subcategory":"Lawyer & Legal Services",
            "type":"Services"
        }
    ],
    "sg:phone":"+1 317 484 8115",
    "sg:postcode":"46214",
    "sg:province":"IN",
    "sg:tags":[
        "attorney"
    ],
    "wof:name":"Claire E Lewis Law Ofc",
    "wof:placetype":"venue"
},
  "geometry": {"coordinates":[-86.289121,39.766705],"type":"Point"}
}