{
  "type": "Feature",
  "properties": {
    "addr:full":"1440 Locust St Terre Haute IN 47807",
    "addr:housenumber":"1440",
    "addr:postcode":"47807",
    "addr:street":"Locust St",
    "iso:country":"US",
    "sg:address":"1440 Locust St",
    "sg:city":"Terre Haute",
    "sg:classifiers":[
        {
            "category":"Organizations",
            "subcategory":"Religious Organization",
            "type":"Services"
        }
    ],
    "sg:phone":"+1 812 232 6832",
    "sg:postcode":"47807",
    "sg:province":"IN",
    "sg:tags":[
        "church"
    ],
    "wof:name":"St Ann Church",
    "wof:placetype":"venue"
},
  "geometry": {"coordinates":[-87.392923,39.477608],"type":"Point"}
}