{
  "type": "Feature",
  "properties": {
    "iso:country":"US",
    "sg:address":"104 S Jefferson St",
    "sg:city":"Ossian",
    "sg:classifiers":[
        {
            "category":"Home & Garden",
            "subcategory":"Carpets & Floor Coverings",
            "type":"Retail Goods"
        }
    ],
    "sg:phone":"+1 260 622 7465",
    "sg:postcode":"46777",
    "sg:province":"IN",
    "sg:tags":[
        "dealer",
        "rug"
    ],
    "wof:name":"Main Street Flooring",
    "wof:placetype":"venue"
},
  "geometry": {"coordinates":[-85.166607,40.879184],"type":"Point"}
}