{
  "type": "Feature",
  "properties": {
    "iso:country":"US",
    "sg:address":"2200 E Shockley Rd",
    "sg:city":"Muncie",
    "sg:classifiers":[
        {
            "category":"Farming",
            "subcategory":"Farm",
            "type":"Manufacturing & Wholesale Goods"
        }
    ],
    "sg:phone":"+1 765 288 1726",
    "sg:postcode":"47302",
    "sg:province":"IN",
    "sg:tags":[
        "crop",
        "general"
    ],
    "wof:name":"James Shockley",
    "wof:placetype":"venue"
},
  "geometry": {"coordinates":[-85.359167,40.106475],"type":"Point"}
}