{
  "type": "Feature",
  "properties": {
    "addr:full":"1211 E Maryland St Evansville IN 47711",
    "addr:housenumber":"1211",
    "addr:postcode":"47711",
    "addr:street":"E Maryland St",
    "iso:country":"US",
    "sg:address":"1211 E Maryland St",
    "sg:city":"Evansville",
    "sg:classifiers":[
        {
            "category":"Retail",
            "subcategory":"Auto Repair",
            "type":"Services"
        }
    ],
    "sg:phone":"+1 812 422 3931",
    "sg:postcode":"47711",
    "sg:province":"IN",
    "sg:tags":[
        "repairing",
        "automobile"
    ],
    "wof:name":"B & B Auto Svc",
    "wof:placetype":"venue"
},
  "geometry": {"coordinates":[-87.54254,37.985496],"type":"Point"}
}