{
  "type": "Feature",
  "properties": {
    "iso:country":"US",
    "sg:address":"5546 Elmwood Ct",
    "sg:city":"Indianapolis",
    "sg:classifiers":[
        {
            "category":"Manufacturing",
            "subcategory":"Tools & Machinery",
            "type":"Manufacturing & Wholesale Goods"
        }
    ],
    "sg:phone":"+1 317 787 9000",
    "sg:postcode":"46203",
    "sg:province":"IN",
    "sg:tags":[
        "cam"
    ],
    "sg:website":"www.camsinc.thomasregister.com",
    "wof:name":"CAMS-Inc",
    "wof:placetype":"venue"
},
  "geometry": {"coordinates":[-86.07140800000001,39.70839],"type":"Point"}
}