{
  "type": "Feature",
  "properties": {
    "iso:country":"US",
    "sg:address":"1015 E Waterford St",
    "sg:city":"Wakarusa",
    "sg:classifiers":[
        {
            "category":"Manufacturing",
            "subcategory":"Tools & Machinery",
            "type":"Manufacturing & Wholesale Goods"
        }
    ],
    "sg:phone":"+1 574 862 1966",
    "sg:postcode":"46573",
    "sg:province":"IN",
    "sg:tags":[
        "product",
        "mfg",
        "plastic"
    ],
    "wof:name":"Eagle Mold & Tool",
    "wof:placetype":"venue"
},
  "geometry": {"coordinates":[-85.999144,41.536064],"type":"Point"}
}