{
  "type": "Feature",
  "properties": {
    "iso:country":"US",
    "sg:address":"757 State Rd 131",
    "sg:city":"Clarksville",
    "sg:classifiers":[
        {
            "category":"Shopping",
            "type":"Retail Goods"
        }
    ],
    "sg:phone":"+1 812 284 1950",
    "sg:postcode":"47129",
    "sg:province":"IN",
    "sg:tags":[
        "telephone",
        "cellular"
    ],
    "wof:name":"Cellular Sales",
    "wof:placetype":"venue"
},
  "geometry": {"coordinates":[-85.76385000000001,38.313212],"type":"Point"}
}