{
  "type": "Feature",
  "properties": {
    "iso:country":"US",
    "sg:address":"2810 S Main St",
    "sg:city":"South Bend",
    "sg:classifiers":[
        {
            "category":"Retail",
            "subcategory":"Repair Shop",
            "type":"Services"
        }
    ],
    "sg:phone":"+1 574 291 4294",
    "sg:postcode":"46614",
    "sg:province":"IN",
    "sg:tags":[
        "equipment",
        "hydraulic"
    ],
    "wof:name":"Miller Hydraulic Svc",
    "wof:placetype":"venue"
},
  "geometry": {"coordinates":[-86.25115599999999,41.644913],"type":"Point"}
}