{
  "type": "Feature",
  "properties": {
    "addr:full":"375 W Vaughn Dr Madison IN 47250",
    "addr:housenumber":"375",
    "addr:postcode":"47250",
    "addr:street":"W Vaughn Dr",
    "iso:country":"US",
    "sg:address":"375 W Vaughn Dr",
    "sg:city":"Madison",
    "sg:classifiers":[
        {
            "category":"Restaurant",
            "type":"Food & Drink"
        }
    ],
    "sg:phone":"+1 812 265 4888",
    "sg:postcode":"47250",
    "sg:province":"IN",
    "wof:name":"Wharf Restaurant & Lounge",
    "wof:placetype":"venue"
},
  "geometry": {"coordinates":[-85.38352,38.733296],"type":"Point"}
}