{
  "type": "Feature",
  "properties": {
    "iso:country":"US",
    "sg:address":"155 W 86th Ave",
    "sg:city":"Merrillville",
    "sg:classifiers":[
        {
            "category":"Health Services",
            "subcategory":"Doctor",
            "type":"Services"
        }
    ],
    "sg:phone":"+1 219 756 6605",
    "sg:postcode":"46410",
    "sg:province":"IN",
    "sg:tags":[
        "physician",
        "surgeon"
    ],
    "wof:name":"Advanced Medical Ctr",
    "wof:placetype":"venue"
},
  "geometry": {"coordinates":[-87.337035,41.461925],"type":"Point"}
}