{
  "type": "Feature",
  "properties": {
    "addr:full":"59132 Elm Rd Mishawaka IN 46544",
    "addr:housenumber":"59132",
    "addr:postcode":"46544",
    "addr:street":"Elm Rd",
    "iso:country":"US",
    "sg:address":"59132 Elm Rd",
    "sg:city":"Mishawaka",
    "sg:classifiers":[
        {
            "category":"Organizations",
            "subcategory":"Religious Organization",
            "type":"Services"
        }
    ],
    "sg:phone":"+1 574 255 7853",
    "sg:postcode":"46544",
    "sg:province":"IN",
    "sg:tags":[
        "church"
    ],
    "wof:name":"Apostolic Faith Temple",
    "wof:placetype":"venue"
},
  "geometry": {"coordinates":[-86.138311,41.643247],"type":"Point"}
}