{
  "type": "Feature",
  "properties": {
    "addr:full":"1929 Grant Line Rd New Albany IN 47150",
    "addr:housenumber":"1929",
    "addr:postcode":"47150",
    "addr:street":"Grant Line Rd",
    "iso:country":"US",
    "sg:address":"1929 Grant Line Rd",
    "sg:city":"New Albany",
    "sg:classifiers":[
        {
            "category":"Cinema",
            "subcategory":"Movie Rental",
            "type":"Entertainment"
        }
    ],
    "sg:phone":"+1 812 948 0909",
    "sg:postcode":"47150",
    "sg:province":"IN",
    "sg:tags":[
        "leasing",
        "video",
        "disc",
        "tape"
    ],
    "wof:name":"Movie Gallery",
    "wof:placetype":"venue"
},
  "geometry": {"coordinates":[-85.81874500000001,38.30275],"type":"Point"}
}