{
  "type": "Feature",
  "properties": {
    "iso:country":"US",
    "sg:address":"6510 Bluffton Rd",
    "sg:city":"Fort Wayne",
    "sg:classifiers":[
        {
            "category":"Personal",
            "subcategory":"Barber",
            "type":"Services"
        }
    ],
    "sg:phone":"+1 260 747 2579",
    "sg:postcode":"46809",
    "sg:province":"IN",
    "wof:name":"Hair Barn Classics",
    "wof:placetype":"venue"
},
  "geometry": {"coordinates":[-85.16919,41.022456],"type":"Point"}
}