{
  "type": "Feature",
  "properties": {
    "iso:country":"US",
    "sg:address":"2024 Inwood Dr",
    "sg:city":"Fort Wayne",
    "sg:classifiers":[
        {
            "category":"Health Services",
            "subcategory":"Medical Lab",
            "type":"Services"
        }
    ],
    "sg:phone":"+1 260 420 5277",
    "sg:postcode":"46815",
    "sg:province":"IN",
    "sg:tags":[
        "laboratory"
    ],
    "wof:name":"Fort Wayne Dental Laboratory",
    "wof:placetype":"venue"
},
  "geometry": {"coordinates":[-85.08663199999999,41.098965],"type":"Point"}
}