{
  "type": "Feature",
  "properties": {
    "iso:country":"US",
    "sg:address":"611 E Tippecanoe Springs Ct",
    "sg:city":"Monticello",
    "sg:classifiers":[
        {
            "category":"Health Services",
            "subcategory":"Medical Lab",
            "type":"Services"
        }
    ],
    "sg:phone":"+1 574 583 5999",
    "sg:postcode":"47960",
    "sg:province":"IN",
    "sg:tags":[
        "detection",
        "equipment",
        "drug"
    ],
    "wof:name":"Jabeco Inc",
    "wof:placetype":"venue"
},
  "geometry": {"coordinates":[-86.752646,40.717272],"type":"Point"}
}