{
  "type": "Feature",
  "properties": {
    "iso:country":"US",
    "sg:address":"5934 W Jefferson Blvd",
    "sg:city":"Fort Wayne",
    "sg:classifiers":[
        {
            "category":"Personal",
            "subcategory":"Shoe Repair & Shine",
            "type":"Services"
        }
    ],
    "sg:phone":"+1 260 436 7297",
    "sg:postcode":"46804",
    "sg:province":"IN",
    "sg:tags":[
        "repairing",
        "boot"
    ],
    "wof:name":"Shoe Cobbler",
    "wof:placetype":"venue"
},
  "geometry": {"coordinates":[-85.219113,41.059123],"type":"Point"}
}