{
  "type": "Feature",
  "properties": {
    "iso:country":"US",
    "sg:address":"400 E Church St",
    "sg:city":"Brazil",
    "sg:classifiers":[
        {
            "category":"Organizations",
            "subcategory":"Religious Organization",
            "type":"Services"
        }
    ],
    "sg:phone":"+1 812 448 1500",
    "sg:postcode":"47834",
    "sg:province":"IN",
    "wof:name":"Eastside Christian Church",
    "wof:placetype":"venue"
},
  "geometry": {"coordinates":[-87.121947,39.525368],"type":"Point"}
}