{
  "type": "Feature",
  "properties": {
    "addr:full":"10635 Hwy 135 NE New Salisbury IN 47161",
    "addr:housenumber":"10635",
    "addr:postcode":"47161",
    "addr:street":"Hwy 135 Ne New",
    "iso:country":"US",
    "sg:address":"10635 Hwy 135 NE",
    "sg:city":"New Salisbury",
    "sg:phone":"+1 812 364 6335",
    "sg:postcode":"47161",
    "sg:province":"IN",
    "sg:tags":[
        "farm",
        "field",
        "crop"
    ],
    "wof:name":"Leland Krush",
    "wof:placetype":"venue"
},
  "geometry": {"coordinates":[-86.10048500000001,38.351544],"type":"Point"}
}