{
  "type": "Feature",
  "properties": {
    "iso:country":"US",
    "sg:address":"7300 W Isanogel Rd",
    "sg:city":"Muncie",
    "sg:classifiers":[
        {
            "category":"Real Estate",
            "subcategory":"Architect",
            "type":"Services"
        }
    ],
    "sg:phone":"+1 765 289 5559",
    "sg:postcode":"47304",
    "sg:province":"IN",
    "wof:name":"Underwood Architecture",
    "wof:placetype":"venue"
},
  "geometry": {"coordinates":[-85.47108799999999,40.200202],"type":"Point"}
}