{
  "type": "Feature",
  "properties": {
    "addr:full":"506 E South St South Bend IN 46601",
    "addr:housenumber":"506 e",
    "addr:postcode":"46601",
    "addr:street":"South St",
    "iso:country":"US",
    "sg:address":"506 E South St",
    "sg:city":"South Bend",
    "sg:classifiers":[
        {
            "category":"Utilities",
            "subcategory":"Mobile Phone",
            "type":"Services"
        }
    ],
    "sg:phone":"+1 574 287 8412",
    "sg:postcode":"46601",
    "sg:province":"IN",
    "sg:tags":[
        "telephone",
        "cellular"
    ],
    "wof:name":"Century Tel",
    "wof:placetype":"venue"
},
  "geometry": {"coordinates":[-86.24387299999999,41.669393],"type":"Point"}
}