{
  "type": "Feature",
  "properties": {
    "iso:country":"US",
    "sg:address":"405 S Western Ave",
    "sg:city":"Kokomo",
    "sg:classifiers":[
        {
            "category":"Professional",
            "subcategory":"Business Services",
            "type":"Services"
        }
    ],
    "sg:phone":"+1 765 459 0115",
    "sg:postcode":"46901",
    "sg:province":"IN",
    "sg:tags":[
        "jewelry"
    ],
    "wof:name":"Designs By Judy",
    "wof:placetype":"venue"
},
  "geometry": {"coordinates":[-86.148445,40.482462],"type":"Point"}
}