{
  "type": "Feature",
  "properties": {
    "iso:country":"US",
    "sg:address":"610 W Washington St",
    "sg:city":"Bluffton",
    "sg:classifiers":[
        {
            "category":"Building & Trades",
            "subcategory":"Plumbing",
            "type":"Services"
        }
    ],
    "sg:phone":"+1 260 824 8369",
    "sg:postcode":"46714",
    "sg:province":"IN",
    "sg:tags":[
        "sheet",
        "work",
        "metal",
        "contractor"
    ],
    "wof:name":"Exterior 2000 Inc",
    "wof:placetype":"venue"
},
  "geometry": {"coordinates":[-85.178844,40.738678],"type":"Point"}
}