{
  "type": "Feature",
  "properties": {
    "iso:country":"US",
    "sg:address":"155 E Elizabeth Dr",
    "sg:city":"Schererville",
    "sg:classifiers":[
        {
            "category":"Personal",
            "subcategory":"Beauty Salon",
            "type":"Services"
        }
    ],
    "sg:phone":"+1 219 865 3700",
    "sg:postcode":"46375",
    "sg:province":"IN",
    "wof:name":"You Got The Look Full Salon",
    "wof:placetype":"venue"
},
  "geometry": {"coordinates":[-87.448504,41.483658],"type":"Point"}
}