{
  "type": "Feature",
  "properties": {
    "iso:country":"US",
    "sg:address":"951 N Clark Blvd",
    "sg:city":"Clarksville",
    "sg:classifiers":[
        {
            "category":"Building & Trades",
            "subcategory":"Plumbing",
            "type":"Services"
        }
    ],
    "sg:phone":"+1 812 288 8304",
    "sg:postcode":"47129",
    "sg:province":"IN",
    "sg:tags":[
        "mechanical",
        "contractor"
    ],
    "wof:name":"Stewart Mechanical Enterprises",
    "wof:placetype":"venue"
},
  "geometry": {"coordinates":[-85.773536,38.298256],"type":"Point"}
}