{
  "type": "Feature",
  "properties": {
    "addr:full":"1526 E Mills Ave Indianapolis IN 46227",
    "addr:housenumber":"1526",
    "addr:postcode":"46227",
    "addr:street":"E Mills Ave",
    "iso:country":"US",
    "sg:address":"1526 E Mills Ave",
    "sg:city":"Indianapolis",
    "sg:classifiers":[
        {
            "category":"Social Services",
            "type":"Services"
        }
    ],
    "sg:phone":"+1 317 788 0539",
    "sg:postcode":"46227",
    "sg:province":"IN",
    "sg:tags":[
        "organization",
        "welfare"
    ],
    "wof:name":"Joy's Center-Creative Living",
    "wof:placetype":"venue"
},
  "geometry": {"coordinates":[-86.13314699999999,39.704708],"type":"Point"}
}