{
  "type": "Feature",
  "properties": {
    "iso:country":"US",
    "sg:address":"1101 E Lewis and Clark Pkwy",
    "sg:city":"Clarksville",
    "sg:classifiers":[
        {
            "category":"Restaurant",
            "type":"Food & Drink"
        }
    ],
    "sg:menulink":"http://www.allmenus.com/in/jeffersonville/41759-bob-evans/menu/",
    "sg:phone":"+1 812 282 8299",
    "sg:postcode":"47129",
    "sg:province":"IN",
    "sg:tags":[
        "american"
    ],
    "wof:name":"Bob Evans",
    "wof:placetype":"venue"
},
  "geometry": {"coordinates":[-85.75774699999999,38.316531],"type":"Point"}
}