{
  "type": "Feature",
  "properties": {
    "iso:country":"US",
    "sg:address":"2715 S Main St",
    "sg:city":"South Bend",
    "sg:classifiers":[
        {
            "category":"Shopping",
            "type":"Retail Goods"
        }
    ],
    "sg:phone":"+1 574 291 2682",
    "sg:postcode":"46614",
    "sg:province":"IN",
    "sg:tags":[
        "miscellaneous",
        "store"
    ],
    "wof:name":"Goalie Entertaiment",
    "wof:placetype":"venue"
},
  "geometry": {"coordinates":[-86.251327,41.646129],"type":"Point"}
}