{
  "type": "Feature",
  "properties": {
    "iso:country":"US",
    "sg:address":"770 Joliet St",
    "sg:city":"Dyer",
    "sg:classifiers":[
        {
            "category":"Shopping",
            "subcategory":"Pharmacy",
            "type":"Retail Goods"
        }
    ],
    "sg:phone":"+1 219 322 4331",
    "sg:postcode":"46311",
    "sg:province":"IN",
    "wof:name":"Walgreens",
    "wof:placetype":"venue"
},
  "geometry": {"coordinates":[-87.51116,41.493025],"type":"Point"}
}