{
  "type": "Feature",
  "properties": {
    "iso:country":"US",
    "sg:address":"719 Rockhill St",
    "sg:city":"Fort Wayne",
    "sg:classifiers":[
        {
            "category":"Restaurant",
            "type":"Food & Drink"
        }
    ],
    "sg:phone":"+1 260 493 1384",
    "sg:postcode":"46802",
    "sg:province":"IN",
    "sg:tags":[
        "eating"
    ],
    "wof:name":"Arena Dinner Theatre Inc",
    "wof:placetype":"venue"
},
  "geometry": {"coordinates":[-85.153372,41.077335],"type":"Point"}
}