{
  "type": "Feature",
  "properties": {
    "iso:country":"US",
    "sg:address":"30 W Shaws Rd",
    "sg:city":"English",
    "sg:classifiers":[
        {
            "category":"Insurance",
            "subcategory":"Hazard Insurance",
            "type":"Services"
        }
    ],
    "sg:phone":"+1 812 338 4254",
    "sg:postcode":"47118",
    "sg:province":"IN",
    "sg:tags":[
        "bond"
    ],
    "wof:name":"Gail Cox's Bail Bonds",
    "wof:placetype":"venue"
},
  "geometry": {"coordinates":[-86.48295,38.260757],"type":"Point"}
}