{
  "type": "Feature",
  "properties": {
    "iso:country":"US",
    "sg:address":"1193 Driftwood Dr",
    "sg:city":"Carmel",
    "sg:classifiers":[
        {
            "category":"Professional",
            "subcategory":"Management & Consulting",
            "type":"Services"
        }
    ],
    "sg:phone":"+1 317 575 6287",
    "sg:postcode":"46033",
    "sg:province":"IN",
    "sg:tags":[
        "consultant",
        "business"
    ],
    "wof:name":"Alpha Financial Consulting Inc",
    "wof:placetype":"venue"
},
  "geometry": {"coordinates":[-86.105561,39.989762],"type":"Point"}
}