{
  "type": "Feature",
  "properties": {
    "addr:full":"390 W US Hwy 6 Valparaiso IN 46385",
    "addr:housenumber":"390",
    "addr:postcode":"46385",
    "addr:street":"W Us Hwy 6",
    "iso:country":"US",
    "sg:address":"390 W US Hwy 6",
    "sg:city":"Valparaiso",
    "sg:classifiers":[
        {
            "category":"Personal",
            "subcategory":"Beauty Salon",
            "type":"Services"
        }
    ],
    "sg:phone":"+1 219 762 2522",
    "sg:postcode":"46385",
    "sg:province":"IN",
    "wof:name":"Primary Color Hair Salon",
    "wof:placetype":"venue"
},
  "geometry": {"coordinates":[-87.14202299999999,41.550239],"type":"Point"}
}