{
  "type": "Feature",
  "properties": {
    "iso:country":"US",
    "sg:address":"2120 S State Rd 39",
    "sg:city":"Frankfort",
    "sg:classifiers":[
        {
            "category":"Organizations",
            "subcategory":"Community Association",
            "type":"Services"
        }
    ],
    "sg:phone":"+1 765 654 4441",
    "sg:postcode":"46041",
    "sg:province":"IN",
    "sg:tags":[
        "fraternal"
    ],
    "wof:name":"Elks Lodge",
    "wof:placetype":"venue"
},
  "geometry": {"coordinates":[-86.51038800000001,40.254557],"type":"Point"}
}