{
  "type": "Feature",
  "properties": {
    "iso:country":"US",
    "sg:address":"486 E 600 N",
    "sg:city":"Fortville",
    "sg:classifiers":[
        {
            "category":"Professional",
            "subcategory":"Management & Consulting",
            "type":"Services"
        }
    ],
    "sg:phone":"+1 317 326 8345",
    "sg:postcode":"46040",
    "sg:province":"IN",
    "wof:name":"Bml Management Consulting",
    "wof:placetype":"venue"
},
  "geometry": {"coordinates":[-85.790908,39.871739],"type":"Point"}
}