{
  "type": "Feature",
  "properties": {
    "iso:country":"US",
    "sg:address":"7311 Preamble Ct",
    "sg:city":"Indianapolis",
    "sg:classifiers":[
        {
            "category":"Building & Trades",
            "subcategory":"Construction",
            "type":"Services"
        }
    ],
    "sg:phone":"+1 317 862 7996",
    "sg:postcode":"46259",
    "sg:province":"IN",
    "sg:tags":[
        "general",
        "contractor"
    ],
    "wof:name":"Sublette Brothers Construction",
    "wof:placetype":"venue"
},
  "geometry": {"coordinates":[-86.03765,39.662805],"type":"Point"}
}