{
  "type": "Feature",
  "properties": {
    "iso:country":"US",
    "sg:address":"16 W Jennings St",
    "sg:city":"Newburgh",
    "sg:classifiers":[
        {
            "category":"Shopping",
            "subcategory":"Clothing, Apparel, & Fashions",
            "type":"Retail Goods"
        }
    ],
    "sg:phone":"+1 812 490 5835",
    "sg:postcode":"47630",
    "sg:province":"IN",
    "wof:name":"Mulberry Jeans Accents",
    "wof:placetype":"venue"
},
  "geometry": {"coordinates":[-87.405288,37.944659],"type":"Point"}
}