{
  "type": "Feature",
  "properties": {
    "iso:country":"US",
    "sg:address":"506 N Main St",
    "sg:city":"Walton",
    "sg:classifiers":[
        {
            "category":"Personal",
            "subcategory":"Tanning Parlor",
            "type":"Services"
        }
    ],
    "sg:phone":"+1 574 626 2826",
    "sg:postcode":"46994",
    "sg:province":"IN",
    "sg:tags":[
        "salon"
    ],
    "wof:name":"Outback Tanning",
    "wof:placetype":"venue"
},
  "geometry": {"coordinates":[-86.245978,40.665369],"type":"Point"}
}