{
  "type": "Feature",
  "properties": {
    "iso:country":"US",
    "sg:address":"510 W Merrill St",
    "sg:city":"Indianapolis",
    "sg:classifiers":[
        {
            "category":"Wholesale",
            "subcategory":"Tobacco Products",
            "type":"Manufacturing & Wholesale Goods"
        }
    ],
    "sg:phone":"+1 317 639 2591",
    "sg:postcode":"46225",
    "sg:province":"IN",
    "sg:tags":[
        "cigarette",
        "confectionery",
        "candy",
        "cigar"
    ],
    "sg:website":"http://www.buyerswholesale.com",
    "wof:name":"Buyers Wholesale Distributors Inc",
    "wof:placetype":"venue"
},
  "geometry": {"coordinates":[-86.168228,39.759178],"type":"Point"}
}