{
  "type": "Feature",
  "properties": {
    "iso:country":"US",
    "sg:address":"112 E Ridge Rd",
    "sg:city":"Griffith",
    "sg:classifiers":[
        {
            "category":"Sports & Exercise",
            "subcategory":"Gym",
            "type":"Entertainment"
        }
    ],
    "sg:phone":"+1 219 838 2222",
    "sg:postcode":"46319",
    "sg:province":"IN",
    "sg:tags":[
        "club",
        "health",
        "studio",
        "gymnasium"
    ],
    "wof:name":"Curves For Women",
    "wof:placetype":"venue"
},
  "geometry": {"coordinates":[-87.425251,41.550811],"type":"Point"}
}