{
  "type": "Feature",
  "properties": {
    "iso:country":"US",
    "sg:address":"2777 Sherman Blvd",
    "sg:city":"Fort Wayne",
    "sg:classifiers":[
        {
            "category":"Retail",
            "subcategory":"Repair Shop",
            "type":"Services"
        }
    ],
    "sg:phone":"+1 260 482 3100",
    "sg:postcode":"46808",
    "sg:province":"IN",
    "sg:tags":[
        "refinishing",
        "furniture"
    ],
    "wof:name":"Souder's Furniture Repair",
    "wof:placetype":"venue"
},
  "geometry": {"coordinates":[-85.153966,41.100425],"type":"Point"}
}