{
  "type": "Feature",
  "properties": {
    "iso:country":"US",
    "sg:address":"2309 Graves Light Dr",
    "sg:city":"Indianapolis",
    "sg:classifiers":[
        {
            "category":"Shopping",
            "subcategory":"Music",
            "type":"Retail Goods"
        }
    ],
    "sg:phone":"+1 317 780 1757",
    "sg:postcode":"46217",
    "sg:province":"IN",
    "wof:name":"Abyss Records",
    "wof:placetype":"venue"
},
  "geometry": {"coordinates":[-86.200876,39.668049],"type":"Point"}
}