{
  "type": "Feature",
  "properties": {
    "iso:country":"US",
    "sg:address":"1156 Keystone Way",
    "sg:city":"Carmel",
    "sg:classifiers":[
        {
            "category":"Personal",
            "subcategory":"Nail Salon",
            "type":"Services"
        }
    ],
    "sg:phone":"+1 317 566 9558",
    "sg:postcode":"46032",
    "sg:province":"IN",
    "wof:name":"Excellent Nails",
    "wof:placetype":"venue"
},
  "geometry": {"coordinates":[-86.115303,39.9599],"type":"Point"}
}