{
  "type": "Feature",
  "properties": {
    "addr:full":"441 Prescott Rd Valparaiso IN 46385",
    "addr:housenumber":"441",
    "addr:postcode":"46385",
    "addr:street":"Prescott Rd",
    "iso:country":"US",
    "sg:address":"441 Prescott Rd",
    "sg:city":"Valparaiso",
    "sg:classifiers":[
        {
            "category":"Freight",
            "type":"Transportation"
        }
    ],
    "sg:phone":"+1 219 759 5821",
    "sg:postcode":"46385",
    "sg:province":"IN",
    "sg:tags":[
        "operator",
        "local",
        "trucking"
    ],
    "wof:name":"F & D Trucking Inc",
    "wof:placetype":"venue"
},
  "geometry": {"coordinates":[-87.148501,41.531069],"type":"Point"}
}