{
  "type": "Feature",
  "properties": {
    "iso:country":"US",
    "sg:address":"103 W Harris St",
    "sg:city":"Eaton",
    "sg:classifiers":[
        {
            "category":"Cinema",
            "subcategory":"Movie Rental",
            "type":"Entertainment"
        }
    ],
    "sg:phone":"+1 765 396 3969",
    "sg:postcode":"47338",
    "sg:province":"IN",
    "sg:tags":[
        "leasing",
        "video",
        "disc",
        "tape"
    ],
    "wof:name":"Eaton Video",
    "wof:placetype":"venue"
},
  "geometry": {"coordinates":[-85.355459,40.341809],"type":"Point"}
}