{
  "type": "Feature",
  "properties": {
    "addr:full":"2070 E Morgan Ave Evansville IN 47711",
    "addr:housenumber":"2070",
    "addr:postcode":"47711",
    "addr:street":"E Morgan Ave",
    "iso:country":"US",
    "sg:address":"2070 E Morgan Ave",
    "sg:city":"Evansville",
    "sg:classifiers":[
        {
            "category":"Restaurant",
            "type":"Food & Drink"
        }
    ],
    "sg:phone":"+1 812 476 0189",
    "sg:postcode":"47711",
    "sg:province":"IN",
    "wof:name":"Royal Palace Chinese Rstrnt",
    "wof:placetype":"venue"
},
  "geometry": {"coordinates":[-87.526732,37.991736],"type":"Point"}
}