{
  "type": "Feature",
  "properties": {
    "iso:country":"US",
    "sg:address":"45 S Franklin Rd",
    "sg:city":"Indianapolis",
    "sg:classifiers":[
        {
            "category":"Shopping",
            "subcategory":"Computers & Home Electronics",
            "type":"Retail Goods"
        }
    ],
    "sg:phone":"+1 317 916 1630",
    "sg:postcode":"46219",
    "sg:province":"IN",
    "sg:tags":[
        "equipment",
        "dealer"
    ],
    "sg:website":"www.themacexperience.com",
    "wof:name":"Mac Experience Inc",
    "wof:placetype":"venue"
},
  "geometry": {"coordinates":[-86.026162,39.769578],"type":"Point"}
}