{
  "type": "Feature",
  "properties": {
    "iso:country":"US",
    "sg:address":"1203 Lake Forest Dr",
    "sg:city":"Fort Wayne",
    "sg:classifiers":[
        {
            "category":"Shopping",
            "subcategory":"Bicycles & Sporting Goods",
            "type":"Retail Goods"
        }
    ],
    "sg:phone":"+1 260 493 1012",
    "sg:postcode":"46815",
    "sg:province":"IN",
    "sg:tags":[
        "equipment",
        "tennis",
        "supply"
    ],
    "wof:name":"Lake Forest Swim & Tennis",
    "wof:placetype":"venue"
},
  "geometry": {"coordinates":[-85.05193,41.090715],"type":"Point"}
}