{
  "type": "Feature",
  "properties": {
    "iso:country":"US",
    "sg:address":"13980 W Commerce Rd",
    "sg:city":"Daleville",
    "sg:classifiers":[
        {
            "category":"Home & Garden",
            "subcategory":"Furniture",
            "type":"Retail Goods"
        }
    ],
    "sg:phone":"+1 765 378 0260",
    "sg:postcode":"47334",
    "sg:province":"IN",
    "wof:name":"Daleville Furniture Outlet",
    "wof:placetype":"venue"
},
  "geometry": {"coordinates":[-85.550993,40.113515],"type":"Point"}
}