{
  "type": "Feature",
  "properties": {
    "iso:country":"US",
    "sg:address":"105 E Harrison St",
    "sg:city":"Attica",
    "sg:classifiers":[
        {
            "category":"Freight",
            "type":"Transportation"
        }
    ],
    "sg:phone":"+1 765 762 6763",
    "sg:postcode":"47918",
    "sg:province":"IN",
    "sg:tags":[
        "grain",
        "elevator"
    ],
    "wof:name":"Adm Grain",
    "wof:placetype":"venue"
},
  "geometry": {"coordinates":[-87.257385,40.276456],"type":"Point"}
}