{
  "type": "Feature",
  "properties": {
    "iso:country":"US",
    "sg:address":"7477 E State Rd 114-92",
    "sg:city":"Roanoke",
    "sg:classifiers":[
        {
            "category":"Home & Garden",
            "subcategory":"Furniture",
            "type":"Retail Goods"
        }
    ],
    "sg:phone":"+1 260 672 8462",
    "sg:postcode":"46783",
    "sg:province":"IN",
    "sg:tags":[
        "equipment",
        "kitchen",
        "cabinet"
    ],
    "wof:name":"Roanoke Woodworking Inc",
    "wof:placetype":"venue"
},
  "geometry": {"coordinates":[-85.346522,41.005266],"type":"Point"}
}