{
  "type": "Feature",
  "properties": {
    "iso:country":"US",
    "sg:address":"12670 State Rd 23",
    "sg:city":"Granger",
    "sg:classifiers":[
        {
            "category":"Real Estate",
            "subcategory":"Real Estate Agent",
            "type":"Services"
        }
    ],
    "sg:phone":"+1 574 272 2121",
    "sg:postcode":"46530",
    "sg:province":"IN",
    "wof:name":"Centry Twenty One Goldstar",
    "wof:placetype":"venue"
},
  "geometry": {"coordinates":[-86.11659,41.753538],"type":"Point"}
}