{
  "type": "Feature",
  "properties": {
    "addr:full":"1501 Allens Ln Evansville IN 47710",
    "addr:housenumber":"1501",
    "addr:postcode":"47710",
    "addr:street":"Allens Ln",
    "iso:country":"US",
    "sg:address":"1501 Allens Ln",
    "sg:city":"Evansville",
    "sg:classifiers":[
        {
            "category":"Wholesale",
            "subcategory":"Office Equipment",
            "type":"Manufacturing & Wholesale Goods"
        }
    ],
    "sg:phone":"+1 812 426 1496",
    "sg:postcode":"47710",
    "sg:province":"IN",
    "sg:tags":[
        "machine",
        "duplicating",
        "copying"
    ],
    "sg:website":"www.langcompany.com",
    "wof:name":"Lang Co",
    "wof:placetype":"venue"
},
  "geometry": {"coordinates":[-87.586465,38.007702],"type":"Point"}
}