{
  "type": "Feature",
  "properties": {
    "iso:country":"US",
    "sg:address":"503 E Van Cleve St",
    "sg:city":"Hartford City",
    "sg:classifiers":[
        {
            "category":"Health Services",
            "subcategory":"Hospital",
            "type":"Services"
        }
    ],
    "sg:phone":"+1 765 348 0300",
    "sg:postcode":"47348",
    "sg:province":"IN",
    "wof:name":"Blackford Community Hospital",
    "wof:placetype":"venue"
},
  "geometry": {"coordinates":[-85.36290099999999,40.456391],"type":"Point"}
}