{
  "type": "Feature",
  "properties": {
    "iso:country":"US",
    "sg:address":"3725 E Southport Rd",
    "sg:city":"Indianapolis",
    "sg:classifiers":[
        {
            "category":"Banks & Credit Unions",
            "subcategory":"Bank",
            "type":"Services"
        }
    ],
    "sg:phone":"+1 317 885 0100",
    "sg:postcode":"46227",
    "sg:province":"IN",
    "sg:tags":[
        "loan",
        "real estate"
    ],
    "wof:name":"Lock Financial",
    "wof:placetype":"venue"
},
  "geometry": {"coordinates":[-86.101418,39.665244],"type":"Point"}
}