{
  "type": "Feature",
  "properties": {
    "iso:country":"US",
    "sg:address":"2905 Newton St",
    "sg:city":"Jasper",
    "sg:classifiers":[
        {
            "category":"Restaurant",
            "type":"Food & Drink"
        }
    ],
    "sg:phone":"+1 812 482 6020",
    "sg:postcode":"47546",
    "sg:province":"IN",
    "sg:tags":[
        "parlor",
        "ice",
        "cream"
    ],
    "wof:name":"Helen Hutchley",
    "wof:placetype":"venue"
},
  "geometry": {"coordinates":[-86.937948,38.414288],"type":"Point"}
}