{
  "type": "Feature",
  "properties": {
    "iso:country":"US",
    "sg:address":"7880 Broadway",
    "sg:city":"Merrillville",
    "sg:classifiers":[
        {
            "category":"Health Services",
            "subcategory":"Doctor",
            "type":"Services"
        }
    ],
    "sg:phone":"+1 219 795 9999",
    "sg:postcode":"46410",
    "sg:province":"IN",
    "sg:tags":[
        "dentist"
    ],
    "wof:name":"A & A Dental Ctr",
    "wof:placetype":"venue"
},
  "geometry": {"coordinates":[-87.33607000000001,41.479262],"type":"Point"}
}