{
  "type": "Feature",
  "properties": {
    "iso:country":"US",
    "sg:address":"535 Ridgelawn Dr",
    "sg:city":"Hobart",
    "sg:classifiers":[
        {
            "category":"Building & Trades",
            "subcategory":"Construction",
            "type":"Services"
        }
    ],
    "sg:phone":"+1 219 947 4174",
    "sg:postcode":"46342",
    "sg:province":"IN",
    "sg:tags":[
        "general",
        "contractor"
    ],
    "wof:name":"Larson's Carpenters",
    "wof:placetype":"venue"
},
  "geometry": {"coordinates":[-87.292758,41.548331],"type":"Point"}
}