{
  "type": "Feature",
  "properties": {
    "iso:country":"US",
    "sg:address":"1511 S Hunter Rd",
    "sg:city":"Indianapolis",
    "sg:classifiers":[
        {
            "category":"Retail",
            "subcategory":"Repair Shop",
            "type":"Services"
        }
    ],
    "sg:phone":"+1 317 359 8992",
    "sg:postcode":"46239",
    "sg:province":"IN",
    "sg:tags":[
        "plumbing",
        "drain",
        "cleaning",
        "sewer"
    ],
    "wof:name":"A Action Rooter Smithes",
    "wof:placetype":"venue"
},
  "geometry": {"coordinates":[-86.04965300000001,39.750812],"type":"Point"}
}