{
  "type": "Feature",
  "properties": {
    "addr:full":"1313 Flat Wood Court Brownsburg IN 46112",
    "addr:housenumber":"1313 flat",
    "addr:postcode":"46112",
    "addr:street":"Wood Court",
    "iso:country":"US",
    "sg:address":"1313 Flat Wood Court",
    "sg:city":"Brownsburg",
    "sg:classifiers":[
        {
            "category":"Shopping",
            "subcategory":"Clothing, Apparel, & Fashions",
            "type":"Retail Goods"
        },
        {
            "category":"Recreation",
            "subcategory":"Dog Park",
            "type":"Entertainment"
        },
        {
            "category":"Shopping",
            "subcategory":"Gifts & Souvenirs",
            "type":"Retail Goods"
        },
        {
            "category":"Shopping",
            "subcategory":"Pets & Pet Supplies",
            "type":"Retail Goods"
        },
        {
            "category":"Retail",
            "subcategory":"Animal Services",
            "type":"Services"
        }
    ],
    "sg:phone":"+1 317 456 4183",
    "sg:postcode":"46112",
    "sg:province":"IN",
    "sg:tags":[
        "t-shirt",
        "basket",
        "care",
        "specialty",
        "day"
    ],
    "sg:website":"http://www.adogspot.net",
    "wof:name":"A Dog Spot LLC",
    "wof:placetype":"venue"
},
  "geometry": {"coordinates":[-86.369776,39.857113],"type":"Point"}
}