{
  "type": "Feature",
  "properties": {
    "iso:country":"US",
    "sg:address":"1182 W 500 S",
    "sg:city":"Crawfordsville",
    "sg:classifiers":[
        {
            "category":"Retail",
            "subcategory":"Auto Repair",
            "type":"Services"
        }
    ],
    "sg:phone":"+1 765 866 7103",
    "sg:postcode":"47933",
    "sg:province":"IN",
    "sg:tags":[
        "repairing",
        "automobile"
    ],
    "wof:name":"Automotive Technical Svc",
    "wof:placetype":"venue"
},
  "geometry": {"coordinates":[-86.923041,39.966908],"type":"Point"}
}