{
  "type": "Feature",
  "properties": {
    "iso:country":"US",
    "sg:address":"342 Lincolnway E",
    "sg:city":"South Bend",
    "sg:classifiers":[
        {
            "category":"Taxi",
            "type":"Transportation"
        }
    ],
    "sg:phone":"+1 574 288 7777",
    "sg:postcode":"46601",
    "sg:province":"IN",
    "sg:tags":[
        "taxicab"
    ],
    "wof:name":"Checker Cab Northern Indiana",
    "wof:placetype":"venue"
},
  "geometry": {"coordinates":[-86.246236,41.670936],"type":"Point"}
}