{
  "type": "Feature",
  "properties": {
    "iso:country":"US",
    "sg:address":"2975 N 275 W",
    "sg:city":"Crawfordsville",
    "sg:classifiers":[
        {
            "category":"Recreation",
            "type":"Entertainment"
        }
    ],
    "sg:phone":"+1 765 362 7650",
    "sg:postcode":"47933",
    "sg:province":"IN",
    "sg:tags":[
        "textile",
        "pr",
        "fabricated",
        "mfg"
    ],
    "wof:name":"B & M Powered Chutes Inc",
    "wof:placetype":"venue"
},
  "geometry": {"coordinates":[-86.95556500000001,40.07998],"type":"Point"}
}