{
  "type": "Feature",
  "properties": {
    "iso:country":"US",
    "sg:address":"124 W Pine St",
    "sg:city":"Topeka",
    "sg:classifiers":[
        {
            "category":"Organizations",
            "subcategory":"Religious Organization",
            "type":"Services"
        }
    ],
    "sg:phone":"+1 260 593 2941",
    "sg:postcode":"46571",
    "sg:province":"IN",
    "sg:tags":[
        "church"
    ],
    "wof:name":"Topeka United Methodist Church",
    "wof:placetype":"venue"
},
  "geometry": {"coordinates":[-85.540274,41.536972],"type":"Point"}
}