{
  "type": "Feature",
  "properties": {
    "addr:full":"2000 Evangel Way Nappanee IN 46550",
    "addr:housenumber":"2000",
    "addr:postcode":"46550",
    "addr:street":"Evangel Way",
    "iso:country":"US",
    "sg:address":"2000 Evangel Way",
    "sg:city":"Nappanee",
    "sg:classifiers":[
        {
            "category":"Manufacturing",
            "subcategory":"Printing",
            "type":"Manufacturing & Wholesale Goods"
        }
    ],
    "sg:phone":"+1 574 773 3164",
    "sg:postcode":"46550",
    "sg:province":"IN",
    "sg:tags":[
        "printer"
    ],
    "sg:website":"www.prayercard.com",
    "wof:name":"Evangel Press",
    "wof:placetype":"venue"
},
  "geometry": {"coordinates":[-85.97704899999999,41.444635],"type":"Point"}
}