{
  "type": "Feature",
  "properties": {
    "iso:country":"US",
    "sg:address":"2300 25th St",
    "sg:city":"Columbus",
    "sg:classifiers":[
        {
            "category":"Shopping",
            "subcategory":"Department Store",
            "type":"Retail Goods"
        }
    ],
    "sg:phone":"+1 812 372 9083",
    "sg:postcode":"47201",
    "sg:province":"IN",
    "wof:name":"Goody's Family Clothing",
    "wof:placetype":"venue"
},
  "geometry": {"coordinates":[-85.89723600000001,39.223041],"type":"Point"}
}