{
  "type": "Feature",
  "properties": {
    "iso:country":"US",
    "sg:address":"200 Ct Park",
    "sg:city":"Logansport",
    "sg:classifiers":[
        {
            "category":"Government",
            "subcategory":"Office",
            "type":"Public Place"
        }
    ],
    "sg:phone":"+1 574 753 7870",
    "sg:postcode":"46947",
    "sg:province":"IN",
    "wof:name":"Cass County Voter Registration",
    "wof:placetype":"venue"
},
  "geometry": {"coordinates":[-86.367526,40.754337],"type":"Point"}
}