{
  "type": "Feature",
  "properties": {
    "iso:country":"US",
    "sg:address":"7361 N Shadeland Ave",
    "sg:city":"Indianapolis",
    "sg:classifiers":[
        {
            "category":"Personal",
            "subcategory":"Tanning Parlor",
            "type":"Services"
        }
    ],
    "sg:phone":"+1 317 842 3224",
    "sg:postcode":"46250",
    "sg:province":"IN",
    "sg:tags":[
        "salon"
    ],
    "wof:name":"Indoor Beach",
    "wof:placetype":"venue"
},
  "geometry": {"coordinates":[-86.046036,39.890117],"type":"Point"}
}