{
  "type": "Feature",
  "properties": {
    "iso:country":"US",
    "sg:address":"3960 E Bellefontaine Rd",
    "sg:city":"Hamilton",
    "sg:classifiers":[
        {
            "category":"Real Estate",
            "subcategory":"Real Estate Agent",
            "type":"Services"
        }
    ],
    "sg:phone":"+1 260 488 4321",
    "sg:postcode":"46742",
    "sg:province":"IN",
    "wof:name":"Lakefront Real Estate",
    "wof:placetype":"venue"
},
  "geometry": {"coordinates":[-84.913737,41.533644],"type":"Point"}
}