{
  "type": "Feature",
  "properties": {
    "addr:full":"10412 Breckenridge Dr Carmel IN 46033",
    "addr:housenumber":"10412",
    "addr:postcode":"46033",
    "addr:street":"Breckenridge Dr",
    "iso:country":"US",
    "sg:address":"10412 Breckenridge Dr",
    "sg:city":"Carmel",
    "sg:classifiers":[
        {
            "category":"Building & Trades",
            "subcategory":"Locksmith",
            "type":"Services"
        }
    ],
    "sg:phone":"+1 317 682 9092",
    "sg:postcode":"46033",
    "sg:province":"IN",
    "sg:tags":[
        "key"
    ],
    "wof:name":"24 Hour Locksmith",
    "wof:placetype":"venue"
},
  "geometry": {"coordinates":[-86.09742300000001,39.936769],"type":"Point"}
}