{
  "type": "Feature",
  "properties": {
    "addr:full":"66252 Ash Rd Wakarusa IN 46573",
    "addr:housenumber":"66252",
    "addr:postcode":"46573",
    "addr:street":"Ash Rd",
    "iso:country":"US",
    "sg:address":"66252 Ash Rd",
    "sg:city":"Wakarusa",
    "sg:classifiers":[
        {
            "category":"Real Estate",
            "subcategory":"Real Estate Agent",
            "type":"Services"
        }
    ],
    "sg:phone":"+1 574 862 2588",
    "sg:postcode":"46573",
    "sg:province":"IN",
    "sg:tags":[
        "consulting",
        "management"
    ],
    "wof:name":"Hahn's Realty",
    "wof:placetype":"venue"
},
  "geometry": {"coordinates":[-86.059867,41.535897],"type":"Point"}
}