{
  "type": "Feature",
  "properties": {
    "iso:country":"US",
    "sg:address":"334 US Hwy 30",
    "sg:city":"Valparaiso",
    "sg:classifiers":[
        {
            "category":"Professional",
            "type":"Services"
        }
    ],
    "sg:phone":"+1 219 548 3388",
    "sg:postcode":"46383",
    "sg:province":"IN",
    "sg:tags":[
        "establishment"
    ],
    "wof:name":"Vdi Coil Systems Inc",
    "wof:placetype":"venue"
},
  "geometry": {"coordinates":[-87.00201199999999,41.446005],"type":"Point"}
}