{
  "type": "Feature",
  "properties": {
    "iso:country":"US",
    "sg:address":"510 W 9th St",
    "sg:city":"Marion",
    "sg:classifiers":[
        {
            "category":"Retail",
            "subcategory":"Auto Repair",
            "type":"Services"
        }
    ],
    "sg:phone":"+1 765 662 3839",
    "sg:postcode":"46953",
    "sg:province":"IN",
    "sg:tags":[
        "truck"
    ],
    "wof:name":"Truckmasters Inc",
    "wof:placetype":"venue"
},
  "geometry": {"coordinates":[-85.664004,40.55289],"type":"Point"}
}