{
  "type": "Feature",
  "properties": {
    "addr:full":"6702 New Jersey Ave Hammond IN 46323",
    "addr:housenumber":"6702",
    "addr:postcode":"46323",
    "addr:street":"New Jersey Ave",
    "iso:country":"US",
    "sg:address":"6702 New Jersey Ave",
    "sg:city":"Hammond",
    "sg:classifiers":[
        {
            "category":"Freight",
            "type":"Transportation"
        }
    ],
    "sg:phone":"+1 219 844 1527",
    "sg:postcode":"46323",
    "sg:province":"IN",
    "sg:tags":[
        "operator",
        "local",
        "trucking"
    ],
    "wof:name":"Cheyenne Trucking Inc",
    "wof:placetype":"venue"
},
  "geometry": {"coordinates":[-87.438658,41.588171],"type":"Point"}
}