{
  "type": "Feature",
  "properties": {
    "iso:country":"US",
    "sg:address":"969 W McClain St",
    "sg:city":"Scottsburg",
    "sg:classifiers":[
        {
            "category":"Professional",
            "subcategory":"Employment Agencies",
            "type":"Services"
        }
    ],
    "sg:phone":"+1 812 754 1401",
    "sg:postcode":"47170",
    "sg:province":"IN",
    "sg:tags":[
        "opportunity"
    ],
    "wof:name":"Rauch Employment Svc",
    "wof:placetype":"venue"
},
  "geometry": {"coordinates":[-85.781299,38.685529],"type":"Point"}
}