{
  "type": "Feature",
  "properties": {
    "iso:country":"US",
    "sg:address":"1310 N College Ave",
    "sg:city":"Bloomington",
    "sg:classifiers":[
        {
            "category":"Restaurant",
            "type":"Food & Drink"
        }
    ],
    "sg:phone":"+1 812 336 4848",
    "sg:postcode":"47404",
    "sg:province":"IN",
    "wof:name":"Austin Riley's Royal Pizza",
    "wof:placetype":"venue"
},
  "geometry": {"coordinates":[-86.534651,39.177486],"type":"Point"}
}