{
  "type": "Feature",
  "properties": {
    "addr:full":"2034 Milburn Rd Brownsburg IN 46112",
    "addr:housenumber":"2034",
    "addr:postcode":"46112",
    "addr:street":"Milburn Rd",
    "iso:country":"US",
    "sg:address":"2034 Milburn Rd",
    "sg:city":"Brownsburg",
    "sg:classifiers":[
        {
            "category":"Building & Trades",
            "subcategory":"Landscaping Services",
            "type":"Services"
        }
    ],
    "sg:phone":"+1 317 852 2647",
    "sg:postcode":"46112",
    "sg:province":"IN",
    "sg:tags":[
        "landscape",
        "contractor"
    ],
    "wof:name":"Nature's Choice Landscaping",
    "wof:placetype":"venue"
},
  "geometry": {"coordinates":[-86.387106,39.812991],"type":"Point"}
}