{
  "type": "Feature",
  "properties": {
    "iso:country":"US",
    "sg:address":"350 N Van Buren St",
    "sg:city":"Shipshewana",
    "sg:classifiers":[
        {
            "category":"Shopping",
            "subcategory":"Musical Instruments",
            "type":"Retail Goods"
        }
    ],
    "sg:phone":"+1 260 768 7675",
    "sg:postcode":"46565",
    "sg:province":"IN",
    "sg:tags":[
        "piano"
    ],
    "wof:name":"Best Grand Pianos",
    "wof:placetype":"venue"
},
  "geometry": {"coordinates":[-85.580585,41.670091],"type":"Point"}
}