{
  "type": "Feature",
  "properties": {
    "iso:country":"US",
    "sg:address":"1030 N 3rd St",
    "sg:city":"Logansport",
    "sg:classifiers":[
        {
            "category":"Professional",
            "subcategory":"Accounting & Tax Preparation",
            "type":"Services"
        }
    ],
    "sg:phone":"+1 574 732 1456",
    "sg:postcode":"46947",
    "sg:province":"IN",
    "sg:tags":[
        "accountant"
    ],
    "wof:name":"KNOX Accounting & Tax Svc",
    "wof:placetype":"venue"
},
  "geometry": {"coordinates":[-86.37052300000001,40.759465],"type":"Point"}
}