{
  "type": "Feature",
  "properties": {
    "iso:country":"US",
    "sg:address":"355 Westfield Rd Ste 120",
    "sg:city":"Noblesville",
    "sg:classifiers":[
        {
            "category":"Health Services",
            "subcategory":"Doctor",
            "type":"Services"
        }
    ],
    "sg:phone":"+1 317 776 0140",
    "sg:postcode":"46060",
    "sg:province":"IN",
    "sg:tags":[
        "orthopedist"
    ],
    "wof:name":"Hamilton Orthopaedics & Sports Medicine",
    "wof:placetype":"venue"
},
  "geometry": {"coordinates":[-86.023003,40.047001],"type":"Point"}
}