{
  "type": "Feature",
  "properties": {
    "iso:country":"US",
    "sg:address":"2601 Brookway St",
    "sg:city":"Indianapolis",
    "sg:classifiers":[
        {
            "category":"Restaurant",
            "type":"Food & Drink"
        }
    ],
    "sg:phone":"+1 317 423 8708",
    "sg:postcode":"46218",
    "sg:province":"IN",
    "sg:tags":[
        "caterer"
    ],
    "wof:name":"Occassions Catering",
    "wof:placetype":"venue"
},
  "geometry": {"coordinates":[-86.117327,39.790375],"type":"Point"}
}