{
  "type": "Feature",
  "properties": {
    "addr:full":"271 S Mitthoeffer Rd Indianapolis IN 46229",
    "addr:housenumber":"271",
    "addr:postcode":"46229",
    "addr:street":"S Mitthoeffer Rd",
    "iso:country":"US",
    "sg:address":"271 S Mitthoeffer Rd",
    "sg:city":"Indianapolis",
    "sg:classifiers":[
        {
            "category":"Sports & Exercise",
            "subcategory":"Golf",
            "type":"Entertainment"
        }
    ],
    "sg:phone":"+1 317 899 4653",
    "sg:postcode":"46229",
    "sg:province":"IN",
    "sg:tags":[
        "course"
    ],
    "wof:name":"Morningstar Golf Club",
    "wof:placetype":"venue"
},
  "geometry": {"coordinates":[-85.990084,39.763723],"type":"Point"}
}