{
  "type": "Feature",
  "properties": {
    "iso:country":"US",
    "sg:address":"108 Indianapolis Ave",
    "sg:city":"Seymour",
    "sg:classifiers":[
        {
            "category":"Personal",
            "subcategory":"Beauty Salon",
            "type":"Services"
        }
    ],
    "sg:phone":"+1 812 522 7373",
    "sg:postcode":"47274",
    "sg:province":"IN",
    "wof:name":"Carousel Beauty Salon",
    "wof:placetype":"venue"
},
  "geometry": {"coordinates":[-85.888689,38.958753],"type":"Point"}
}