{
  "type": "Feature",
  "properties": {
    "iso:country":"US",
    "sg:address":"11261 State Rd 335",
    "sg:city":"Pekin",
    "sg:classifiers":[
        {
            "category":"Home & Garden",
            "subcategory":"Garden Supply",
            "type":"Retail Goods"
        }
    ],
    "sg:phone":"+1 812 967 3573",
    "sg:postcode":"47165",
    "sg:province":"IN",
    "sg:tags":[
        "nurseryman"
    ],
    "wof:name":"Hein Tree Farm & Gift Shop",
    "wof:placetype":"venue"
},
  "geometry": {"coordinates":[-86.03262100000001,38.428155],"type":"Point"}
}