{
  "type": "Feature",
  "properties": {
    "iso:country":"US",
    "sg:address":"2710 American Way",
    "sg:city":"Fort Wayne",
    "sg:classifiers":[
        {
            "category":"Manufacturing",
            "subcategory":"Chemicals & Compounds",
            "type":"Manufacturing & Wholesale Goods"
        }
    ],
    "sg:phone":"+1 260 479 4100",
    "sg:postcode":"46809",
    "sg:province":"IN",
    "sg:tags":[
        "plastic"
    ],
    "sg:website":"www.polyhisolidur.com",
    "wof:name":"Poly Hi Solidur",
    "wof:placetype":"venue"
},
  "geometry": {"coordinates":[-85.171945,41.001404],"type":"Point"}
}