{
  "type": "Feature",
  "properties": {
    "iso:country":"US",
    "sg:address":"1813 State St",
    "sg:city":"New Albany",
    "sg:classifiers":[
        {
            "category":"Health Services",
            "subcategory":"Doctor",
            "type":"Services"
        }
    ],
    "sg:phone":"+1 812 944 6759",
    "sg:postcode":"47150",
    "sg:province":"IN",
    "sg:tags":[
        "dentist"
    ],
    "wof:name":"Denzinger Family Orthodontics",
    "wof:placetype":"venue"
},
  "geometry": {"coordinates":[-85.834255,38.299718],"type":"Point"}
}