{
  "type": "Feature",
  "properties": {
    "iso:country":"US",
    "sg:address":"1545 US Hwy 41",
    "sg:city":"Schererville",
    "sg:classifiers":[
        {
            "category":"Restaurant",
            "type":"Food & Drink"
        }
    ],
    "sg:phone":"+1 219 864 7810",
    "sg:postcode":"46375",
    "sg:province":"IN",
    "sg:website":"www.fazolis.com",
    "wof:name":"Fazoli's",
    "wof:placetype":"venue"
},
  "geometry": {"coordinates":[-87.470823,41.492263],"type":"Point"}
}