{
  "type": "Feature",
  "properties": {
    "iso:country":"US",
    "sg:address":"412 North St",
    "sg:city":"Logansport",
    "sg:classifiers":[
        {
            "category":"Health Services",
            "subcategory":"Optometrist",
            "type":"Services"
        }
    ],
    "sg:phone":"+1 574 722 6600",
    "sg:postcode":"46947",
    "sg:province":"IN",
    "wof:name":"Dianne J Brown OD",
    "wof:placetype":"venue"
},
  "geometry": {"coordinates":[-86.364943,40.755408],"type":"Point"}
}