{
  "type": "Feature",
  "properties": {
    "addr:full":"2405 S Earl Ave Lafayette IN 47905",
    "addr:housenumber":"2405",
    "addr:postcode":"47905",
    "addr:street":"S Earl Ave",
    "iso:country":"US",
    "sg:address":"2405 S Earl Ave",
    "sg:city":"Lafayette",
    "sg:classifiers":[
        {
            "category":"Shopping",
            "type":"Retail Goods"
        }
    ],
    "sg:phone":"+1 765 448 1821",
    "sg:postcode":"47905",
    "sg:province":"IN",
    "sg:tags":[
        "art",
        "gallery",
        "dealer"
    ],
    "wof:name":"Kelly's Custom Frames Inc",
    "wof:placetype":"venue"
},
  "geometry": {"coordinates":[-86.868043,40.402504],"type":"Point"}
}