{
  "type": "Feature",
  "properties": {
    "iso:country":"US",
    "sg:address":"4400 Spring Valley Rd",
    "sg:city":"Evansville",
    "sg:classifiers":[
        {
            "category":"Real Estate",
            "subcategory":"Real Estate Operator",
            "type":"Services"
        }
    ],
    "sg:phone":"+1 812 477 7464",
    "sg:postcode":"47715",
    "sg:province":"IN",
    "sg:tags":[
        "apartment"
    ],
    "wof:name":"Spring Valley Apartments",
    "wof:placetype":"venue"
},
  "geometry": {"coordinates":[-87.495505,38.008072],"type":"Point"}
}