{
  "type": "Feature",
  "properties": {
    "addr:full":"204 S John F Kennedy Ave Loogootee IN 47553",
    "addr:housenumber":"204",
    "addr:postcode":"47553",
    "addr:street":"S John F Kennedy Ave",
    "iso:country":"US",
    "sg:address":"204 S John F Kennedy Ave",
    "sg:city":"Loogootee",
    "sg:classifiers":[
        {
            "category":"Government",
            "subcategory":"Office",
            "type":"Public Place"
        }
    ],
    "sg:phone":"+1 812 295 4044",
    "sg:postcode":"47553",
    "sg:province":"IN",
    "sg:tags":[
        "village"
    ],
    "wof:name":"Perry Twp Trustee",
    "wof:placetype":"venue"
},
  "geometry": {"coordinates":[-86.913369,38.675665],"type":"Point"}
}