{
  "type": "Feature",
  "properties": {
    "iso:country":"US",
    "sg:address":"5465 Kessner Bridge Rd",
    "sg:city":"Huntingburg",
    "sg:classifiers":[
        {
            "category":"Professional",
            "type":"Services"
        }
    ],
    "sg:phone":"+1 812 683 8366",
    "sg:postcode":"47542",
    "sg:province":"IN",
    "wof:name":"Truesdale Specialty Svc Inc",
    "wof:placetype":"venue"
},
  "geometry": {"coordinates":[-87.00586,38.347808],"type":"Point"}
}