{
  "type": "Feature",
  "properties": {
    "addr:full":"2364 E 200 N Rochester IN 46975",
    "addr:housenumber":"2364",
    "addr:postcode":"46975",
    "addr:street":"E 200 N",
    "iso:country":"US",
    "sg:address":"2364 E 200 N",
    "sg:city":"Rochester",
    "sg:classifiers":[
        {
            "category":"Personal",
            "subcategory":"Beauty Salon",
            "type":"Services"
        }
    ],
    "sg:phone":"+1 574 223 4405",
    "sg:postcode":"46975",
    "sg:province":"IN",
    "sg:tags":[
        "shop"
    ],
    "wof:name":"Nu Look Hair Styling Salon",
    "wof:placetype":"venue"
},
  "geometry": {"coordinates":[-86.18766599999999,41.083852],"type":"Point"}
}