{
  "type": "Feature",
  "properties": {
    "iso:country":"US",
    "sg:address":"920 State Rd 930 E",
    "sg:city":"New Haven",
    "sg:classifiers":[
        {
            "category":"Personal",
            "subcategory":"Beauty Salon",
            "type":"Services"
        }
    ],
    "sg:phone":"+1 260 749 0017",
    "sg:postcode":"46774",
    "sg:province":"IN",
    "wof:name":"Duce Hair Designing Team",
    "wof:placetype":"venue"
},
  "geometry": {"coordinates":[-85.016072,41.067028],"type":"Point"}
}