{
  "type": "Feature",
  "properties": {
    "addr:full":"1516 Riley Rd Lebanon IN 46052",
    "addr:housenumber":"1516",
    "addr:postcode":"46052",
    "addr:street":"Riley Rd",
    "iso:country":"US",
    "sg:address":"1516 Riley Rd",
    "sg:city":"Lebanon",
    "sg:classifiers":[
        {
            "category":"Building & Trades",
            "subcategory":"Landscaping Services",
            "type":"Services"
        }
    ],
    "sg:phone":"+1 765 482 5176",
    "sg:postcode":"46052",
    "sg:province":"IN",
    "sg:tags":[
        "lawn",
        "maintenance",
        "grounds"
    ],
    "wof:name":"J & S Lawn Care",
    "wof:placetype":"venue"
},
  "geometry": {"coordinates":[-86.485675,40.058648],"type":"Point"}
}