{
  "type": "Feature",
  "properties": {
    "addr:full":"6745 Middle Jamestown Rd Jamestown IN 46147",
    "addr:housenumber":"6745",
    "addr:postcode":"46147",
    "addr:street":"Middle Jamestown Rd",
    "iso:country":"US",
    "sg:address":"6745 Middle Jamestown Rd",
    "sg:city":"Jamestown",
    "sg:classifiers":[
        {
            "category":"Manufacturing",
            "subcategory":"Tools & Machinery",
            "type":"Manufacturing & Wholesale Goods"
        }
    ],
    "sg:phone":"+1 765 676 6323",
    "sg:postcode":"46147",
    "sg:province":"IN",
    "sg:tags":[
        "mold",
        "special"
    ],
    "wof:name":"P & H Engineering",
    "wof:placetype":"venue"
},
  "geometry": {"coordinates":[-86.595843,39.937343],"type":"Point"}
}