{
  "type": "Feature",
  "properties": {
    "addr:full":"1215 N 10th St Noblesville IN 46060",
    "addr:housenumber":"1215",
    "addr:postcode":"46060",
    "addr:street":"N 10Th St",
    "iso:country":"US",
    "sg:address":"1215 N 10th St",
    "sg:city":"Noblesville",
    "sg:classifiers":[
        {
            "category":"Organizations",
            "subcategory":"Community Association",
            "type":"Services"
        }
    ],
    "sg:phone":"+1 317 773 0356",
    "sg:postcode":"46060",
    "sg:province":"IN",
    "sg:tags":[
        "fraternal"
    ],
    "wof:name":"Loyal Order Of Moose 540",
    "wof:placetype":"venue"
},
  "geometry": {"coordinates":[-86.010234,40.057842],"type":"Point"}
}