{
  "type": "Feature",
  "properties": {
    "iso:country":"US",
    "sg:address":"4015 W 3rd St",
    "sg:city":"Bloomington",
    "sg:classifiers":[
        {
            "category":"Shopping",
            "subcategory":"Florist",
            "type":"Retail Goods"
        }
    ],
    "sg:phone":"+1 812 339 7673",
    "sg:postcode":"47404",
    "sg:province":"IN",
    "wof:name":"Judy's Flowers & Gifts",
    "wof:placetype":"venue"
},
  "geometry": {"coordinates":[-86.583099,39.164501],"type":"Point"}
}