{
  "type": "Feature",
  "properties": {
    "iso:country":"US",
    "sg:address":"4200 Illinois Rd",
    "sg:city":"Fort Wayne",
    "sg:classifiers":[
        {
            "category":"Autos & Motor Vehicles",
            "subcategory":"Automobile Sales",
            "type":"Retail Goods"
        }
    ],
    "sg:phone":"+1 260 434 4200",
    "sg:postcode":"46804",
    "sg:province":"IN",
    "wof:name":"Odaniel Oldsmobile Inc",
    "wof:placetype":"venue"
},
  "geometry": {"coordinates":[-85.195558,41.074712],"type":"Point"}
}