{
  "type": "Feature",
  "properties": {
    "iso:country":"US",
    "sg:address":"302 Chestnut St",
    "sg:city":"Bristol",
    "sg:classifiers":[
        {
            "category":"Retail",
            "subcategory":"Auto Repair",
            "type":"Services"
        }
    ],
    "sg:phone":"+1 574 848 1064",
    "sg:postcode":"46507",
    "sg:province":"IN",
    "sg:tags":[
        "repairing",
        "automobile"
    ],
    "wof:name":"Rodgers Automotive",
    "wof:placetype":"venue"
},
  "geometry": {"coordinates":[-85.820955,41.719561],"type":"Point"}
}