{
  "type": "Feature",
  "properties": {
    "iso:country":"US",
    "sg:address":"1201 Main St",
    "sg:city":"Rochester",
    "sg:classifiers":[
        {
            "category":"Insurance",
            "subcategory":"Insurance Agent",
            "type":"Services"
        }
    ],
    "sg:phone":"+1 574 223 3017",
    "sg:postcode":"46975",
    "sg:province":"IN",
    "wof:name":"State Farm Insurance",
    "wof:placetype":"venue"
},
  "geometry": {"coordinates":[-86.21642,41.061661],"type":"Point"}
}