{
  "type": "Feature",
  "properties": {
    "iso:country":"US",
    "sg:address":"1500 Main St",
    "sg:city":"Indianapolis",
    "sg:classifiers":[
        {
            "category":"Restaurant",
            "type":"Food & Drink"
        }
    ],
    "sg:phone":"+1 317 243 0500",
    "sg:postcode":"46224",
    "sg:province":"IN",
    "wof:name":"Bob's TU Your Door Pizza",
    "wof:placetype":"venue"
},
  "geometry": {"coordinates":[-86.24107,39.787408],"type":"Point"}
}