{
  "type": "Feature",
  "properties": {
    "addr:full":"1500 Main St Indianapolis IN 46224",
    "addr:housenumber":"1500",
    "addr:postcode":"46224",
    "addr:street":"Main St",
    "iso:country":"US",
    "sg:address":"1500 Main St",
    "sg:city":"Indianapolis",
    "sg:classifiers":[
        {
            "category":"Restaurant",
            "type":"Food & Drink"
        }
    ],
    "sg:phone":"+1 317 243 0500",
    "sg:postcode":"46224",
    "sg:province":"IN",
    "wof:name":"Bob's TU Your Door Pizza",
    "wof:placetype":"venue"
},
  "geometry": {"coordinates":[-86.24106999999999,39.787408],"type":"Point"}
}