{
  "type": "Feature",
  "properties": {
    "iso:country":"US",
    "sg:address":"2613 W Washington St",
    "sg:city":"Indianapolis",
    "sg:classifiers":[
        {
            "category":"Food & Beverages",
            "subcategory":"Bakery",
            "type":"Retail Goods"
        }
    ],
    "sg:phone":"+1 317 951 0011",
    "sg:postcode":"46222",
    "sg:province":"IN",
    "sg:tags":[
        "baker"
    ],
    "wof:name":"LA Explosiva",
    "wof:placetype":"venue"
},
  "geometry": {"coordinates":[-86.205186,39.76534],"type":"Point"}
}