{
  "type": "Feature",
  "properties": {
    "iso:country":"US",
    "sg:address":"919 E Waterford St",
    "sg:city":"Wakarusa",
    "sg:classifiers":[
        {
            "category":"Building & Trades",
            "subcategory":"Plumbing",
            "type":"Services"
        }
    ],
    "sg:phone":"+1 574 862 2605",
    "sg:postcode":"46573",
    "sg:province":"IN",
    "sg:tags":[
        "heating",
        "contractor"
    ],
    "wof:name":"Lechlitner Plumbing & Heating",
    "wof:placetype":"venue"
},
  "geometry": {"coordinates":[-86.004226,41.536167],"type":"Point"}
}