{
  "type": "Feature",
  "properties": {
    "iso:country":"US",
    "sg:address":"515 E Tipton St",
    "sg:city":"Seymour",
    "sg:classifiers":[
        {
            "category":"Retail",
            "subcategory":"Auto Repair",
            "type":"Services"
        }
    ],
    "sg:phone":"+1 812 523 6403",
    "sg:postcode":"47274",
    "sg:province":"IN",
    "sg:tags":[
        "body"
    ],
    "wof:name":"Custom Auto Body",
    "wof:placetype":"venue"
},
  "geometry": {"coordinates":[-85.88129600000001,38.958096],"type":"Point"}
}