{
  "type": "Feature",
  "properties": {
    "iso:country":"US",
    "sg:address":"2359 State Rd 46 E",
    "sg:city":"Nashville",
    "sg:classifiers":[
        {
            "category":"Travel",
            "subcategory":"Hotels & Motels",
            "type":"Entertainment"
        }
    ],
    "sg:phone":"+1 812 988 7888",
    "sg:postcode":"47448",
    "sg:province":"IN",
    "sg:website":"www.saltcreekgolf.com",
    "wof:name":"Salt Creek Golf Retreat",
    "wof:placetype":"venue"
},
  "geometry": {"coordinates":[-86.173347,39.189385],"type":"Point"}
}