{
  "type": "Feature",
  "properties": {
    "iso:country":"US",
    "sg:address":"2501 N Indianapolis Rd",
    "sg:city":"Columbus",
    "sg:classifiers":[
        {
            "category":"Retail",
            "subcategory":"Auto Repair",
            "type":"Services"
        }
    ],
    "sg:phone":"+1 812 372 1779",
    "sg:postcode":"47201",
    "sg:province":"IN",
    "sg:tags":[
        "transmission"
    ],
    "wof:name":"Bud's Transmission",
    "wof:placetype":"venue"
},
  "geometry": {"coordinates":[-85.933284,39.222512],"type":"Point"}
}