{
  "type": "Feature",
  "properties": {
    "addr:full":"3251 Interchange Dr Elkhart IN 46514",
    "addr:housenumber":"3251",
    "addr:postcode":"46514",
    "addr:street":"Interchange Dr",
    "iso:country":"US",
    "sg:address":"3251 Interchange Dr",
    "sg:city":"Elkhart",
    "sg:classifiers":[
        {
            "category":"Restaurant",
            "type":"Food & Drink"
        }
    ],
    "sg:phone":"+1 574 264 2541",
    "sg:postcode":"46514",
    "sg:province":"IN",
    "wof:name":"Perkins Family Restaurant",
    "wof:placetype":"venue"
},
  "geometry": {"coordinates":[-85.974256,41.734654],"type":"Point"}
}