{
  "type": "Feature",
  "properties": {
    "iso:country":"US",
    "sg:address":"801 W Tipton St",
    "sg:city":"Seymour",
    "sg:classifiers":[
        {
            "category":"Home & Garden",
            "subcategory":"Garden Supply",
            "type":"Retail Goods"
        }
    ],
    "sg:phone":"+1 812 522 3705",
    "sg:postcode":"47274",
    "sg:province":"IN",
    "sg:tags":[
        "lawn",
        "mower"
    ],
    "wof:name":"Fisher's Power Equipment",
    "wof:placetype":"venue"
},
  "geometry": {"coordinates":[-85.896146,38.955593],"type":"Point"}
}