{
  "type": "Feature",
  "properties": {
    "iso:country":"US",
    "sg:address":"5998 S 500 W",
    "sg:city":"Jamestown",
    "sg:classifiers":[
        {
            "category":"Manufacturing",
            "subcategory":"Metals",
            "type":"Manufacturing & Wholesale Goods"
        }
    ],
    "sg:phone":"+1 765 676 4170",
    "sg:postcode":"46147",
    "sg:province":"IN",
    "sg:tags":[
        "metalwork",
        "sheet",
        "mfg"
    ],
    "wof:name":"JRS Custom Fabrication",
    "wof:placetype":"venue"
},
  "geometry": {"coordinates":[-86.563092,39.951938],"type":"Point"}
}