{
  "type": "Feature",
  "properties": {
    "iso:country":"US",
    "sg:address":"8988 Ruffian Ln",
    "sg:city":"Newburgh",
    "sg:classifiers":[
        {
            "category":"Professional",
            "type":"Services"
        }
    ],
    "sg:phone":"+1 812 490 6181",
    "sg:postcode":"47630",
    "sg:province":"IN",
    "sg:tags":[
        "establishment"
    ],
    "wof:name":"Newburgh Theological Seminary",
    "wof:placetype":"venue"
},
  "geometry": {"coordinates":[-87.413736,37.9757],"type":"Point"}
}