{
  "type": "Feature",
  "properties": {
    "iso:country":"US",
    "sg:address":"756 S Walnut St",
    "sg:city":"Bloomington",
    "sg:classifiers":[
        {
            "category":"Shopping",
            "subcategory":"Adult",
            "type":"Retail Goods"
        },
        {
            "category":"Cinema",
            "subcategory":"Movie Rental",
            "type":"Entertainment"
        }
    ],
    "sg:phone":"+1 812 331 1732",
    "sg:postcode":"47401",
    "sg:province":"IN",
    "sg:tags":[
        "game",
        "video"
    ],
    "wof:name":"Garden of Eden",
    "wof:placetype":"venue"
},
  "geometry": {"coordinates":[-86.533827,39.157816],"type":"Point"}
}