{
  "type": "Feature",
  "properties": {
    "addr:full":"705 W State Rd 2 Hebron IN 46341",
    "addr:housenumber":"705",
    "addr:postcode":"46341",
    "addr:street":"W State Rd 2",
    "iso:country":"US",
    "sg:address":"705 W State Rd 2",
    "sg:city":"Hebron",
    "sg:classifiers":[
        {
            "category":"Retail",
            "subcategory":"Auto Repair",
            "type":"Services"
        }
    ],
    "sg:phone":"+1 219 996 2225",
    "sg:postcode":"46341",
    "sg:province":"IN",
    "sg:tags":[
        "body",
        "automobile",
        "painting"
    ],
    "wof:name":"Body Art Collision & Color",
    "wof:placetype":"venue"
},
  "geometry": {"coordinates":[-87.200811,41.289365],"type":"Point"}
}