{
  "type": "Feature",
  "properties": {
    "iso:country":"US",
    "sg:address":"1222 N Vigo St",
    "sg:city":"Gary",
    "sg:classifiers":[
        {
            "category":"Arts & Performance",
            "subcategory":"Theater",
            "type":"Entertainment"
        }
    ],
    "sg:phone":"+1 219 938 9001",
    "sg:postcode":"46403",
    "sg:province":"IN",
    "sg:tags":[
        "group"
    ],
    "wof:name":"Omar Presents",
    "wof:placetype":"venue"
},
  "geometry": {"coordinates":[-87.22871,41.622349],"type":"Point"}
}