{
  "type": "Feature",
  "properties": {
    "addr:full":"108 E Montgomery St Owensville IN 47665",
    "addr:housenumber":"108",
    "addr:postcode":"47665",
    "addr:street":"E Montgomery St",
    "iso:country":"US",
    "sg:address":"108 E Montgomery St",
    "sg:city":"Owensville",
    "sg:classifiers":[
        {
            "category":"Shopping",
            "subcategory":"Department Store",
            "type":"Retail Goods"
        }
    ],
    "sg:phone":"+1 812 724 3131",
    "sg:postcode":"47665",
    "sg:province":"IN",
    "sg:tags":[
        "shop"
    ],
    "wof:name":"Dollar General",
    "wof:placetype":"venue"
},
  "geometry": {"coordinates":[-87.691349,38.271492],"type":"Point"}
}