{
  "type": "Feature",
  "properties": {
    "iso:country":"US",
    "sg:address":"918 Sandpiper Dr",
    "sg:city":"Chesterton",
    "sg:classifiers":[
        {
            "category":"Professional",
            "subcategory":"Lawyer & Legal Services",
            "type":"Services"
        }
    ],
    "sg:phone":"+1 219 926 6405",
    "sg:postcode":"46304",
    "sg:province":"IN",
    "wof:name":"Law Office of James D Socha",
    "wof:placetype":"venue"
},
  "geometry": {"coordinates":[-87.033759,41.61439],"type":"Point"}
}