{
  "type": "Feature",
  "properties": {
    "iso:country":"US",
    "sg:address":"3125 Calumet Ave",
    "sg:city":"Valparaiso",
    "sg:classifiers":[
        {
            "category":"Banks & Credit Unions",
            "subcategory":"Bank",
            "type":"Services"
        }
    ],
    "sg:phone":"+1 219 464 1667",
    "sg:postcode":"46383",
    "sg:province":"IN",
    "sg:tags":[
        "financing"
    ],
    "wof:name":"Beneficial Finance",
    "wof:placetype":"venue"
},
  "geometry": {"coordinates":[-87.045716,41.494088],"type":"Point"}
}