{
  "type": "Feature",
  "properties": {
    "iso:country":"US",
    "sg:address":"1800 E 19th St",
    "sg:city":"Anderson",
    "sg:classifiers":[
        {
            "category":"Insurance",
            "subcategory":"Insurance Agent",
            "type":"Services"
        }
    ],
    "sg:phone":"+1 765 646 6800",
    "sg:postcode":"46016",
    "sg:province":"IN",
    "wof:name":"Citizens Lutz & Cooper Ins",
    "wof:placetype":"venue"
},
  "geometry": {"coordinates":[-85.65269499999999,40.09767],"type":"Point"}
}