{
  "type": "Feature",
  "properties": {
    "iso:country":"US",
    "sg:address":"1235 Canal St",
    "sg:city":"Evansville",
    "sg:classifiers":[
        {
            "category":"Retail",
            "subcategory":"Auto Repair",
            "type":"Services"
        }
    ],
    "sg:phone":"+1 812 455 5281",
    "sg:postcode":"47711",
    "sg:province":"IN",
    "sg:tags":[
        "body",
        "automobile",
        "painting"
    ],
    "wof:name":"Got Dents-Wolf's Paintless",
    "wof:placetype":"venue"
},
  "geometry": {"coordinates":[-87.544387,37.979124],"type":"Point"}
}