{
  "type": "Feature",
  "properties": {
    "addr:full":"5510 Franklin St Michigan City IN 46360",
    "addr:housenumber":"5510",
    "addr:postcode":"46360",
    "addr:street":"Franklin St",
    "iso:country":"US",
    "sg:address":"5510 Franklin St",
    "sg:city":"Michigan City",
    "sg:classifiers":[
        {
            "category":"Home & Garden",
            "subcategory":"Furniture",
            "type":"Retail Goods"
        }
    ],
    "sg:phone":"+1 219 879 8250",
    "sg:postcode":"46360",
    "sg:province":"IN",
    "sg:tags":[
        "mattress"
    ],
    "wof:name":"Bedding Experts Inc",
    "wof:placetype":"venue"
},
  "geometry": {"coordinates":[-86.894018,41.668855],"type":"Point"}
}