{
  "type": "Feature",
  "properties": {
    "iso:country":"US",
    "sg:address":"1020 E Wheeler Ave",
    "sg:city":"Terre Haute",
    "sg:classifiers":[
        {
            "category":"Social Services",
            "subcategory":"Child Care",
            "type":"Services"
        }
    ],
    "sg:phone":"+1 812 232 6363",
    "sg:postcode":"47802",
    "sg:province":"IN",
    "wof:name":"Teri's Daycare",
    "wof:placetype":"venue"
},
  "geometry": {"coordinates":[-87.40177199999999,39.435762],"type":"Point"}
}