{
  "type": "Feature",
  "properties": {
    "iso:country":"US",
    "sg:address":"10608 State Rd 250",
    "sg:city":"Deputy",
    "sg:classifiers":[
        {
            "category":"Farming",
            "subcategory":"Livestock Farm",
            "type":"Manufacturing & Wholesale Goods"
        }
    ],
    "sg:phone":"+1 812 873 6432",
    "sg:postcode":"47230",
    "sg:province":"IN",
    "sg:tags":[
        "feedlot",
        "hog",
        "or",
        "beef",
        "cattle"
    ],
    "wof:name":"Riley John",
    "wof:placetype":"venue"
},
  "geometry": {"coordinates":[-85.584723,38.833155],"type":"Point"}
}