{
  "type": "Feature",
  "properties": {
    "iso:country":"US",
    "sg:address":"115 Freyer Rd",
    "sg:city":"Michigan City",
    "sg:classifiers":[
        {
            "category":"Building & Trades",
            "subcategory":"Construction",
            "type":"Services"
        }
    ],
    "sg:phone":"+1 219 878 0752",
    "sg:postcode":"46360",
    "sg:province":"IN",
    "sg:tags":[
        "sandblasting"
    ],
    "wof:name":"Schultz's Sandblasting & Paint",
    "wof:placetype":"venue"
},
  "geometry": {"coordinates":[-86.841568,41.738549],"type":"Point"}
}