{
  "type": "Feature",
  "properties": {
    "addr:full":"6079 E 300 S Franklin IN 46131",
    "addr:housenumber":"6079",
    "addr:postcode":"46131",
    "addr:street":"E 300 S Franklin",
    "iso:country":"US",
    "sg:address":"6079 E 300 S",
    "sg:city":"Franklin",
    "sg:classifiers":[
        {
            "category":"Building & Trades",
            "subcategory":"Equipment Rental",
            "type":"Services"
        }
    ],
    "sg:phone":"+1 317 736 9216",
    "sg:postcode":"46131",
    "sg:province":"IN",
    "wof:name":"Rafferty Rentals",
    "wof:placetype":"venue"
},
  "geometry": {"coordinates":[-85.990227,39.434952],"type":"Point"}
}