{
  "type": "Feature",
  "properties": {
    "iso:country":"US",
    "sg:address":"8602 S State Rd 61",
    "sg:city":"Monroe City",
    "sg:classifiers":[
        {
            "category":"Building & Trades",
            "subcategory":"Construction",
            "type":"Services"
        }
    ],
    "sg:phone":"+1 812 743 2329",
    "sg:postcode":"47557",
    "sg:province":"IN",
    "sg:tags":[
        "excavation",
        "contractor"
    ],
    "wof:name":"Shepard Construction",
    "wof:placetype":"venue"
},
  "geometry": {"coordinates":[-87.309345,38.560878],"type":"Point"}
}