{
  "type": "Feature",
  "properties": {
    "iso:country":"US",
    "sg:address":"3535 W 300 S",
    "sg:city":"Columbia City",
    "sg:classifiers":[
        {
            "category":"Building & Trades",
            "subcategory":"Landscaping Services",
            "type":"Services"
        }
    ],
    "sg:phone":"+1 260 609 7265",
    "sg:postcode":"46725",
    "sg:province":"IN",
    "sg:tags":[
        "landscape",
        "contractor"
    ],
    "wof:name":"Fahl Colors",
    "wof:placetype":"venue"
},
  "geometry": {"coordinates":[-85.55879400000001,41.118379],"type":"Point"}
}