{
  "type": "Feature",
  "properties": {
    "iso:country":"US",
    "sg:address":"815 Pennsylvania Ave",
    "sg:city":"South Bend",
    "sg:classifiers":[
        {
            "category":"Building & Trades",
            "subcategory":"Construction",
            "type":"Services"
        }
    ],
    "sg:phone":"+1 574 289 9898",
    "sg:postcode":"46601",
    "sg:province":"IN",
    "sg:tags":[
        "home",
        "improvement"
    ],
    "wof:name":"E J Barany Wholesale",
    "wof:placetype":"venue"
},
  "geometry": {"coordinates":[-86.235231,41.660926],"type":"Point"}
}