{
  "type": "Feature",
  "properties": {
    "addr:full":"202 S Main St Bicknell IN 47512",
    "addr:housenumber":"202",
    "addr:postcode":"47512",
    "addr:street":"S Main St",
    "iso:country":"US",
    "sg:address":"202 S Main St",
    "sg:city":"Bicknell",
    "sg:classifiers":[
        {
            "category":"Retail",
            "subcategory":"Auto Repair",
            "type":"Services"
        }
    ],
    "sg:phone":"+1 812 735 4401",
    "sg:postcode":"47512",
    "sg:province":"IN",
    "sg:tags":[
        "automobile",
        "diagnostic"
    ],
    "wof:name":"Tim's Auto Tech",
    "wof:placetype":"venue"
},
  "geometry": {"coordinates":[-87.30603499999999,38.771862],"type":"Point"}
}