{
  "type": "Feature",
  "properties": {
    "iso:country":"US",
    "sg:address":"59865 Market St",
    "sg:city":"South Bend",
    "sg:classifiers":[
        {
            "category":"Wholesale",
            "subcategory":"Chemicals & Plastics",
            "type":"Manufacturing & Wholesale Goods"
        }
    ],
    "sg:phone":"+1 574 289 0321",
    "sg:postcode":"46614",
    "sg:province":"IN",
    "sg:website":"www.univarusa.com",
    "wof:name":"Univar USA",
    "wof:placetype":"venue"
},
  "geometry": {"coordinates":[-86.31514,41.626499],"type":"Point"}
}