{
  "type": "Feature",
  "properties": {
    "iso:country":"US",
    "sg:address":"576 Valley View Rd SW",
    "sg:city":"Corydon",
    "sg:classifiers":[
        {
            "category":"Building & Trades",
            "subcategory":"Plumbing",
            "type":"Services"
        }
    ],
    "sg:phone":"+1 812 738 2045",
    "sg:postcode":"47112",
    "sg:province":"IN",
    "sg:tags":[
        "plumbing",
        "contractor"
    ],
    "wof:name":"Sigh Of Relief Plbg Repairs",
    "wof:placetype":"venue"
},
  "geometry": {"coordinates":[-86.201922,38.192104],"type":"Point"}
}