{
  "type": "Feature",
  "properties": {
    "iso:country":"US",
    "sg:address":"3504 W Alto Rd",
    "sg:city":"Kokomo",
    "sg:classifiers":[
        {
            "category":"Real Estate",
            "subcategory":"Real Estate Agent",
            "type":"Services"
        }
    ],
    "sg:phone":"+1 765 453 0480",
    "sg:postcode":"46902",
    "sg:province":"IN",
    "wof:name":"Mark A Kirkendall PHD",
    "wof:placetype":"venue"
},
  "geometry": {"coordinates":[-86.184214,40.439803],"type":"Point"}
}