{
  "type": "Feature",
  "properties": {
    "addr:full":"6560 Mallard Lndg Fishers IN 46038",
    "addr:housenumber":"6560",
    "addr:postcode":"46038",
    "addr:street":"Mallard Lndg",
    "iso:country":"US",
    "sg:address":"6560 Mallard Lndg",
    "sg:city":"Fishers",
    "sg:classifiers":[
        {
            "category":"Professional",
            "subcategory":"Business Services",
            "type":"Services"
        }
    ],
    "sg:phone":"+1 317 579 9782",
    "sg:postcode":"46038",
    "sg:province":"IN",
    "wof:name":"Midwest Property Solutions LLC",
    "wof:placetype":"venue"
},
  "geometry": {"coordinates":[-86.05193300000001,39.950187],"type":"Point"}
}