{
  "type": "Feature",
  "properties": {
    "iso:country":"US",
    "sg:address":"1430 Main St",
    "sg:city":"Indianapolis",
    "sg:classifiers":[
        {
            "category":"Shopping",
            "subcategory":"Tobacco",
            "type":"Retail Goods"
        }
    ],
    "sg:phone":"+1 317 246 3651",
    "sg:postcode":"46224",
    "sg:province":"IN",
    "sg:tags":[
        "cigarette",
        "cigar"
    ],
    "wof:name":"Main Stream Tobacco",
    "wof:placetype":"venue"
},
  "geometry": {"coordinates":[-86.241023,39.785546],"type":"Point"}
}