{
  "type": "Feature",
  "properties": {
    "addr:full":"200 N Union St Kokomo IN 46901",
    "addr:housenumber":"200",
    "addr:postcode":"46901",
    "addr:street":"N Union St",
    "iso:country":"US",
    "sg:address":"200 N Union St",
    "sg:city":"Kokomo",
    "sg:classifiers":[
        {
            "category":"Social Services",
            "type":"Services"
        }
    ],
    "sg:phone":"+1 765 457 4447",
    "sg:postcode":"46901",
    "sg:province":"IN",
    "sg:tags":[
        "organization",
        "welfare"
    ],
    "sg:website":"www.kokomoymca.org",
    "wof:name":"YMCA",
    "wof:placetype":"venue"
},
  "geometry": {"coordinates":[-86.130014,40.48836],"type":"Point"}
}