{
  "type": "Feature",
  "properties": {
    "iso:country":"US",
    "sg:address":"1604 Calumet Ave",
    "sg:city":"Valparaiso",
    "sg:classifiers":[
        {
            "category":"Retail",
            "subcategory":"Car Wash",
            "type":"Services"
        }
    ],
    "sg:phone":"+1 219 464 2388",
    "sg:postcode":"46383",
    "sg:province":"IN",
    "sg:tags":[
        "polishing",
        "washing"
    ],
    "wof:name":"Zoom Clean",
    "wof:placetype":"venue"
},
  "geometry": {"coordinates":[-87.05230899999999,41.48305],"type":"Point"}
}