{
  "type": "Feature",
  "properties": {
    "iso:country":"US",
    "sg:address":"2602 Ruth Dr",
    "sg:city":"Indianapolis",
    "sg:classifiers":[
        {
            "category":"Restaurant",
            "type":"Food & Drink"
        }
    ],
    "sg:phone":"+1 317 259 4122",
    "sg:postcode":"46240",
    "sg:province":"IN",
    "wof:name":"Capri Restaurant",
    "wof:placetype":"venue"
},
  "geometry": {"coordinates":[-86.12019,39.889046],"type":"Point"}
}