{
  "type": "Feature",
  "properties": {
    "iso:country":"US",
    "sg:address":"6611 Owls Head Dr",
    "sg:city":"Indianapolis",
    "sg:classifiers":[
        {
            "category":"Building & Trades",
            "subcategory":"Landscaping Services",
            "type":"Services"
        }
    ],
    "sg:phone":"+1 317 241 0460",
    "sg:postcode":"46217",
    "sg:province":"IN",
    "sg:tags":[
        "lawn",
        "maintenance",
        "grounds"
    ],
    "wof:name":"Diamond Cut Lawn & Landscape",
    "wof:placetype":"venue"
},
  "geometry": {"coordinates":[-86.201172,39.669404],"type":"Point"}
}