{
  "type": "Feature",
  "properties": {
    "iso:country":"US",
    "sg:address":"546 N Front St",
    "sg:city":"Whiteland",
    "sg:classifiers":[
        {
            "category":"Organizations",
            "subcategory":"Community Association",
            "type":"Services"
        }
    ],
    "sg:phone":"+1 317 535 1613",
    "sg:postcode":"46184",
    "sg:province":"IN",
    "sg:tags":[
        "fraternal"
    ],
    "wof:name":"Johnson County Eagles",
    "wof:placetype":"venue"
},
  "geometry": {"coordinates":[-86.078238,39.554055],"type":"Point"}
}