{
  "type": "Feature",
  "properties": {
    "iso:country":"US",
    "sg:address":"113 E Laporte St",
    "sg:city":"Plymouth",
    "sg:classifiers":[
        {
            "category":"Manufacturing",
            "subcategory":"Metals",
            "type":"Manufacturing & Wholesale Goods"
        }
    ],
    "sg:phone":"+1 574 936 3234",
    "sg:postcode":"46563",
    "sg:province":"IN",
    "sg:tags":[
        "equipment",
        "heating"
    ],
    "wof:name":"Bowman's Tin Shop",
    "wof:placetype":"venue"
},
  "geometry": {"coordinates":[-86.30793,41.340089],"type":"Point"}
}