{
  "type": "Feature",
  "properties": {
    "iso:country":"US",
    "sg:address":"8649 E Old State Road 38",
    "sg:city":"New Castle",
    "sg:classifiers":[
        {
            "category":"Professional",
            "subcategory":"Accounting & Tax Preparation",
            "type":"Services"
        }
    ],
    "sg:phone":"+1 765 332 2133",
    "sg:postcode":"47362",
    "sg:province":"IN",
    "sg:tags":[
        "return",
        "filing"
    ],
    "wof:name":"Scalf Tax & Accounting",
    "wof:placetype":"venue"
},
  "geometry": {"coordinates":[-85.21969300000001,39.917422],"type":"Point"}
}