{
  "type": "Feature",
  "properties": {
    "iso:country":"US",
    "sg:address":"299 S Willow Dr",
    "sg:city":"Union City",
    "sg:classifiers":[
        {
            "category":"Real Estate",
            "subcategory":"Real Estate Operator",
            "type":"Services"
        }
    ],
    "sg:phone":"+1 765 964 4948",
    "sg:postcode":"47390",
    "sg:province":"OH",
    "sg:tags":[
        "mobile",
        "home",
        "community"
    ],
    "wof:name":"AFE Management",
    "wof:placetype":"venue"
},
  "geometry": {"coordinates":[-84.818954,40.194266],"type":"Point"}
}