{
  "type": "Feature",
  "properties": {
    "iso:country":"US",
    "sg:address":"2354 N US Hwy 35",
    "sg:city":"Laporte",
    "sg:classifiers":[
        {
            "category":"Real Estate",
            "subcategory":"Real Estate Agent",
            "type":"Services"
        }
    ],
    "sg:phone":"+1 219 873 0021",
    "sg:postcode":"46350",
    "sg:province":"IN",
    "sg:website":"www.c21firstteam.com",
    "wof:name":"Century 21",
    "wof:placetype":"venue"
},
  "geometry": {"coordinates":[-86.763384,41.654653],"type":"Point"}
}