{
  "type": "Feature",
  "properties": {
    "iso:country":"US",
    "sg:address":"20 E US Hwy 30",
    "sg:city":"Schererville",
    "sg:classifiers":[
        {
            "category":"Real Estate",
            "subcategory":"Real Estate Agent",
            "type":"Services"
        }
    ],
    "sg:phone":"+1 219 865 9911",
    "sg:postcode":"46375",
    "sg:province":"IN",
    "sg:website":"www.coldwellbankeronline.com",
    "wof:name":"Coldwell Banker Residential",
    "wof:placetype":"venue"
},
  "geometry": {"coordinates":[-87.448582,41.485321],"type":"Point"}
}