{
  "type": "Feature",
  "properties": {
    "iso:country":"US",
    "sg:address":"960 S Hebron Ave",
    "sg:city":"Evansville",
    "sg:classifiers":[
        {
            "category":"Health Services",
            "subcategory":"Doctor",
            "type":"Services"
        }
    ],
    "sg:phone":"+1 812 473 1900",
    "sg:postcode":"47714",
    "sg:province":"IN",
    "sg:tags":[
        "dentist"
    ],
    "sg:website":"www.catertocowards.net",
    "wof:name":"Tri State Family Dental Ctr",
    "wof:placetype":"venue"
},
  "geometry": {"coordinates":[-87.49630999999999,37.963183],"type":"Point"}
}