{
  "type": "Feature",
  "properties": {
    "iso:country":"US",
    "sg:address":"5734 W Schultz Rd",
    "sg:city":"Laporte",
    "sg:classifiers":[
        {
            "category":"Wholesale",
            "subcategory":"Machinery & Supplies",
            "type":"Manufacturing & Wholesale Goods"
        }
    ],
    "sg:phone":"+1 219 362 3818",
    "sg:postcode":"46350",
    "sg:province":"IN",
    "sg:tags":[
        "equipment",
        "safety",
        "clothing"
    ],
    "sg:website":"www.esp4safety.com",
    "wof:name":"Environmental Safety Products",
    "wof:placetype":"venue"
},
  "geometry": {"coordinates":[-86.811986,41.6635],"type":"Point"}
}