{
  "type": "Feature",
  "properties": {
    "iso:country":"US",
    "sg:address":"4864 Filbert Trl",
    "sg:city":"Bremen",
    "sg:classifiers":[
        {
            "category":"Freight",
            "type":"Transportation"
        }
    ],
    "sg:phone":"+1 574 546 5403",
    "sg:postcode":"46506",
    "sg:province":"IN",
    "sg:tags":[
        "operator",
        "local",
        "trucking"
    ],
    "wof:name":"Heydes Family Trucking LLC",
    "wof:placetype":"venue"
},
  "geometry": {"coordinates":[-86.174076,41.405886],"type":"Point"}
}