{
  "type": "Feature",
  "properties": {
    "iso:country":"US",
    "sg:address":"426 E Main St",
    "sg:city":"Madison",
    "sg:classifiers":[
        {
            "category":"Professional",
            "subcategory":"Lawyer & Legal Services",
            "type":"Services"
        }
    ],
    "sg:phone":"+1 812 265 3617",
    "sg:postcode":"47250",
    "sg:province":"IN",
    "sg:tags":[
        "attorney"
    ],
    "wof:name":"Michael J Walro",
    "wof:placetype":"venue"
},
  "geometry": {"coordinates":[-85.374597,38.736195],"type":"Point"}
}