{
  "type": "Feature",
  "properties": {
    "iso:country":"US",
    "sg:address":"22 College St",
    "sg:city":"Chrisney",
    "sg:classifiers":[
        {
            "category":"Organizations",
            "subcategory":"Religious Organization",
            "type":"Services"
        }
    ],
    "sg:phone":"+1 812 362 7310",
    "sg:postcode":"47611",
    "sg:province":"IN",
    "sg:tags":[
        "church"
    ],
    "wof:name":"Zion United Church Of Christ",
    "wof:placetype":"venue"
},
  "geometry": {"coordinates":[-87.034588,38.014585],"type":"Point"}
}