{
  "type": "Feature",
  "properties": {
    "iso:country":"US",
    "sg:address":"8128 Castle Cove Rd",
    "sg:city":"Indianapolis",
    "sg:classifiers":[
        {
            "category":"Personal",
            "subcategory":"Beauty Salon",
            "type":"Services"
        }
    ],
    "sg:phone":"+1 317 849 6272",
    "sg:postcode":"46256",
    "sg:province":"IN",
    "sg:tags":[
        "cosmetologist"
    ],
    "wof:name":"Sandra Benton",
    "wof:placetype":"venue"
},
  "geometry": {"coordinates":[-86.025248,39.903554],"type":"Point"}
}