{
  "type": "Feature",
  "properties": {
    "iso:country":"US",
    "sg:address":"3242 Sutherland Ave",
    "sg:city":"Indianapolis",
    "sg:classifiers":[
        {
            "category":"Professional",
            "subcategory":"Business Services",
            "type":"Services"
        }
    ],
    "sg:phone":"+1 317 632 8040",
    "sg:postcode":"46205",
    "sg:province":"IN",
    "sg:tags":[
        "auctioneer"
    ],
    "wof:name":"Commercial Liquidators",
    "wof:placetype":"venue"
},
  "geometry": {"coordinates":[-86.136296,39.816326],"type":"Point"}
}