{
  "type": "Feature",
  "properties": {
    "addr:full":"301 S Main St South Bend IN 46601",
    "addr:housenumber":"301",
    "addr:postcode":"46601",
    "addr:street":"S Main St",
    "iso:country":"US",
    "sg:address":"301 S Main St",
    "sg:city":"South Bend",
    "sg:classifiers":[
        {
            "category":"Banks & Credit Unions",
            "subcategory":"Bank",
            "type":"Services"
        }
    ],
    "sg:phone":"+1 574 245 5000",
    "sg:postcode":"46601",
    "sg:province":"IN",
    "sg:website":"www.53.com",
    "wof:name":"Fifth Third Bank",
    "wof:placetype":"venue"
},
  "geometry": {"coordinates":[-86.251915,41.672981],"type":"Point"}
}