{
  "type": "Feature",
  "properties": {
    "iso:country":"US",
    "sg:address":"2236 E 10th St",
    "sg:city":"Indianapolis",
    "sg:classifiers":[
        {
            "category":"Social Services",
            "type":"Services"
        }
    ],
    "sg:phone":"+1 317 633 3104",
    "sg:postcode":"46201",
    "sg:province":"IN",
    "sg:tags":[
        "care",
        "center",
        "day"
    ],
    "wof:name":"Elder Alternative & Adult Care",
    "wof:placetype":"venue"
},
  "geometry": {"coordinates":[-86.122884,39.781401],"type":"Point"}
}