{
  "type": "Feature",
  "properties": {
    "addr:full":"1790 W 81st Ave Merrillville IN 46410",
    "addr:housenumber":"1790",
    "addr:postcode":"46410",
    "addr:street":"W 81St Ave",
    "iso:country":"US",
    "sg:address":"1790 W 81st Ave",
    "sg:city":"Merrillville",
    "sg:classifiers":[
        {
            "category":"Home & Garden",
            "subcategory":"Building Materials",
            "type":"Retail Goods"
        }
    ],
    "sg:phone":"+1 219 769 1606",
    "sg:postcode":"46410",
    "sg:province":"IN",
    "sg:tags":[
        "glass",
        "window",
        "plate"
    ],
    "wof:name":"Safelite Auto Glass",
    "wof:placetype":"venue"
},
  "geometry": {"coordinates":[-87.35882599999999,41.471185],"type":"Point"}
}