{
  "type": "Feature",
  "properties": {
    "iso:country":"US",
    "sg:address":"902 S Division St",
    "sg:city":"Bristol",
    "sg:classifiers":[
        {
            "category":"Manufacturing",
            "subcategory":"Tools & Machinery",
            "type":"Manufacturing & Wholesale Goods"
        }
    ],
    "sg:phone":"+1 574 848 4491",
    "sg:postcode":"46507",
    "sg:province":"IN",
    "sg:tags":[
        "fan"
    ],
    "sg:website":"www.ventline.com",
    "wof:name":"Ventline /LVS",
    "wof:placetype":"venue"
},
  "geometry": {"coordinates":[-85.817202,41.713005],"type":"Point"}
}