{
  "type": "Feature",
  "properties": {
    "iso:country":"US",
    "sg:address":"4921 E State Rd 252",
    "sg:city":"Franklin",
    "sg:classifiers":[
        {
            "category":"Professional",
            "subcategory":"Lawyer & Legal Services",
            "type":"Services"
        }
    ],
    "sg:phone":"+1 317 738 2655",
    "sg:postcode":"46131",
    "sg:province":"IN",
    "sg:tags":[
        "medical",
        "witness"
    ],
    "wof:name":"Robyn Goshorn",
    "wof:placetype":"venue"
},
  "geometry": {"coordinates":[-86.011988,39.411451],"type":"Point"}
}