{
  "type": "Feature",
  "properties": {
    "iso:country":"US",
    "sg:address":"35 N Co Rd 900 E",
    "sg:city":"Avon",
    "sg:classifiers":[
        {
            "category":"Manufacturing",
            "subcategory":"Printing",
            "type":"Manufacturing & Wholesale Goods"
        }
    ],
    "sg:phone":"+1 317 271 1442",
    "sg:postcode":"46123",
    "sg:province":"IN",
    "sg:tags":[
        "commercial"
    ],
    "wof:name":"Superior Printing Co",
    "wof:placetype":"venue"
},
  "geometry": {"coordinates":[-86.361778,39.763555],"type":"Point"}
}