{
  "type": "Feature",
  "properties": {
    "iso:country":"US",
    "sg:address":"9240 E 350 S",
    "sg:city":"Zionsville",
    "sg:classifiers":[
        {
            "category":"Government",
            "subcategory":"Office",
            "type":"Public Place"
        }
    ],
    "sg:phone":"+1 317 769 8801",
    "sg:postcode":"46077",
    "sg:province":"IN",
    "sg:tags":[
        "county"
    ],
    "wof:name":"Boone County Commissioner Dist",
    "wof:placetype":"venue"
},
  "geometry": {"coordinates":[-86.29813900000001,39.990723],"type":"Point"}
}