{
  "type": "Feature",
  "properties": {
    "iso:country":"US",
    "sg:address":"1200 Berkey Ave",
    "sg:city":"Goshen",
    "sg:classifiers":[
        {
            "category":"Organizations",
            "subcategory":"Religious Organization",
            "type":"Services"
        }
    ],
    "sg:phone":"+1 574 533 6360",
    "sg:postcode":"46526",
    "sg:province":"IN",
    "sg:tags":[
        "church"
    ],
    "wof:name":"West Goshen Church-Brethren",
    "wof:placetype":"venue"
},
  "geometry": {"coordinates":[-85.851906,41.580583],"type":"Point"}
}