{
  "type": "Feature",
  "properties": {
    "iso:country":"US",
    "sg:address":"2047 W Glen Park Ave",
    "sg:city":"Griffith",
    "sg:classifiers":[
        {
            "category":"Professional",
            "subcategory":"Computer Services",
            "type":"Services"
        },
        {
            "category":"Wholesale",
            "subcategory":"Computers",
            "type":"Manufacturing & Wholesale Goods"
        }
    ],
    "sg:phone":"+1 219 934 9565",
    "sg:postcode":"46319",
    "sg:province":"IN",
    "sg:tags":[
        "equipment",
        "cd-rom",
        "manufacturer",
        "computer-wholesale",
        "software"
    ],
    "wof:name":"PC Pounders",
    "wof:placetype":"venue"
},
  "geometry": {"coordinates":[-87.44573200000001,41.537319],"type":"Point"}
}