{
  "type": "Feature",
  "properties": {
    "addr:full":"401 E Main St Richmond IN 47374",
    "addr:housenumber":"401",
    "addr:postcode":"47374",
    "addr:street":"E Main St",
    "iso:country":"US",
    "sg:address":"401 E Main St",
    "sg:city":"Richmond",
    "sg:classifiers":[
        {
            "category":"Government",
            "subcategory":"Office",
            "type":"Public Place"
        }
    ],
    "sg:phone":"+1 765 973 9238",
    "sg:postcode":"47374",
    "sg:province":"IN",
    "sg:tags":[
        "county",
        "taxation"
    ],
    "wof:name":"Wayne County Treasurer",
    "wof:placetype":"venue"
},
  "geometry": {"coordinates":[-84.896401,39.82906],"type":"Point"}
}