{
  "type": "Feature",
  "properties": {
    "iso:country":"US",
    "sg:address":"13109 Thomas Morris Trce",
    "sg:city":"Carmel",
    "sg:classifiers":[
        {
            "category":"Real Estate",
            "subcategory":"Real Estate Agent",
            "type":"Services"
        }
    ],
    "sg:phone":"+1 317 844 1959",
    "sg:postcode":"46033",
    "sg:province":"IN",
    "wof:name":"Enterprise Associates",
    "wof:placetype":"venue"
},
  "geometry": {"coordinates":[-86.046845,39.97893],"type":"Point"}
}