{
  "type": "Feature",
  "properties": {
    "iso:country":"US",
    "sg:address":"1083 Spade Dr",
    "sg:city":"Rochester",
    "sg:classifiers":[
        {
            "category":"Building & Trades",
            "subcategory":"Construction",
            "type":"Services"
        }
    ],
    "sg:phone":"+1 574 223 5269",
    "sg:postcode":"46975",
    "sg:province":"IN",
    "sg:tags":[
        "house"
    ],
    "wof:name":"Kinsel Const",
    "wof:placetype":"venue"
},
  "geometry": {"coordinates":[-86.205296,41.044067],"type":"Point"}
}