{
  "type": "Feature",
  "properties": {
    "iso:country":"US",
    "sg:address":"29918 Riley Rd",
    "sg:city":"North Liberty",
    "sg:phone":"+1 574 656 8965",
    "sg:postcode":"46554",
    "sg:province":"IN",
    "sg:tags":[
        "farm",
        "field",
        "crop"
    ],
    "wof:name":"Terry Borton",
    "wof:placetype":"venue"
},
  "geometry": {"coordinates":[-86.428467,41.505683],"type":"Point"}
}