{
  "type": "Feature",
  "properties": {
    "iso:country":"US",
    "sg:address":"5353 Millersville Rd",
    "sg:city":"Indianapolis",
    "sg:classifiers":[
        {
            "category":"Organizations",
            "subcategory":"Religious Organization",
            "type":"Services"
        }
    ],
    "sg:phone":"+1 317 545 4260",
    "sg:postcode":"46226",
    "sg:province":"IN",
    "sg:tags":[
        "church"
    ],
    "wof:name":"Victory Temple",
    "wof:placetype":"venue"
},
  "geometry": {"coordinates":[-86.090637,39.849244],"type":"Point"}
}