{
  "type": "Feature",
  "properties": {
    "iso:country":"US",
    "sg:address":"1308 W Vernal Pike",
    "sg:city":"Bloomington",
    "sg:classifiers":[
        {
            "category":"Retail",
            "subcategory":"Repair Shop",
            "type":"Services"
        }
    ],
    "sg:phone":"+1 812 339 7698",
    "sg:postcode":"47404",
    "sg:province":"IN",
    "sg:tags":[
        "welding"
    ],
    "wof:name":"Bruce's Welding & Fabrication",
    "wof:placetype":"venue"
},
  "geometry": {"coordinates":[-86.550992,39.170518],"type":"Point"}
}