{
  "type": "Feature",
  "properties": {
    "iso:country":"US",
    "sg:address":"3963 W Dunes Hwy",
    "sg:city":"Michigan City",
    "sg:classifiers":[
        {
            "category":"Home & Garden",
            "subcategory":"Carpets & Floor Coverings",
            "type":"Retail Goods"
        }
    ],
    "sg:phone":"+1 219 872 9950",
    "sg:postcode":"46360",
    "sg:province":"IN",
    "sg:tags":[
        "dealer",
        "rug"
    ],
    "wof:name":"Carpet Cuts",
    "wof:placetype":"venue"
},
  "geometry": {"coordinates":[-86.956851,41.684487],"type":"Point"}
}