{
  "type": "Feature",
  "properties": {
    "addr:full":"777 N Meridian St Ste 204 Indianapolis IN 46204",
    "addr:housenumber":"777",
    "addr:postcode":"46204",
    "addr:street":"N Meridian St Ste 204",
    "iso:country":"US",
    "sg:address":"777 N Meridian St Ste 204",
    "sg:city":"Indianapolis",
    "sg:classifiers":[
        {
            "category":"Organizations",
            "subcategory":"Membership Organization",
            "type":"Services"
        }
    ],
    "sg:phone":"+1 317 634 1804",
    "sg:postcode":"46204",
    "sg:province":"IN",
    "sg:tags":[
        "fraternal"
    ],
    "wof:name":"Des Qrante Hommes Et 8 Chevaux",
    "wof:placetype":"venue"
},
  "geometry": {"coordinates":[-86.157645,39.777686],"type":"Point"}
}