{
  "type": "Feature",
  "properties": {
    "addr:full":"261 W 25th St Indianapolis IN 46208",
    "addr:housenumber":"261",
    "addr:postcode":"46208",
    "addr:street":"W 25Th St",
    "iso:country":"US",
    "sg:address":"261 W 25th St",
    "sg:city":"Indianapolis",
    "sg:classifiers":[
        {
            "category":"Place Of Worship",
            "subcategory":"Church",
            "type":"Public Place"
        },
        {
            "category":"Place Of Worship",
            "type":"Public Place"
        }
    ],
    "sg:phone":"+1 317 925 3737",
    "sg:postcode":"46208",
    "sg:province":"IN",
    "sg:tags":[
        "lutheran",
        "america",
        "churches-lutheran",
        "churches-lutheran-evangelical"
    ],
    "wof:name":"Our Savior Evangelical Lu",
    "wof:placetype":"venue"
},
  "geometry": {"coordinates":[-86.16256,39.802866],"type":"Point"}
}