{
  "type": "Feature",
  "properties": {
    "iso:country":"US",
    "sg:address":"222 N Main St",
    "sg:city":"Goshen",
    "sg:classifiers":[
        {
            "category":"Professional",
            "subcategory":"Accounting & Tax Preparation",
            "type":"Services"
        }
    ],
    "sg:phone":"+1 574 534 8293",
    "sg:postcode":"46526",
    "sg:province":"IN",
    "sg:tags":[
        "return",
        "filing"
    ],
    "wof:name":"Global Tax & Accounting",
    "wof:placetype":"venue"
},
  "geometry": {"coordinates":[-85.834468,41.588197],"type":"Point"}
}