{
  "type": "Feature",
  "properties": {
    "iso:country":"US",
    "sg:address":"9014 N 200 E",
    "sg:city":"Lake Village",
    "sg:classifiers":[
        {
            "category":"Restaurant",
            "type":"Food & Drink"
        }
    ],
    "sg:phone":"+1 219 345 2378",
    "sg:postcode":"46349",
    "sg:province":"IN",
    "wof:name":"TGI",
    "wof:placetype":"venue"
},
  "geometry": {"coordinates":[-87.353112,41.133283],"type":"Point"}
}