{
  "type": "Feature",
  "properties": {
    "iso:country":"US",
    "sg:address":"297 Hillendale Dr",
    "sg:city":"Greenwood",
    "sg:classifiers":[
        {
            "category":"Retail",
            "subcategory":"Animal Services",
            "type":"Services"
        }
    ],
    "sg:phone":"+1 317 882 8018",
    "sg:postcode":"46142",
    "sg:province":"IN",
    "sg:tags":[
        "pet",
        "training"
    ],
    "wof:name":"Blackburn Canine Training",
    "wof:placetype":"venue"
},
  "geometry": {"coordinates":[-86.180777,39.615351],"type":"Point"}
}