{
  "type": "Feature",
  "properties": {
    "iso:country":"US",
    "sg:address":"3321 Morgan St",
    "sg:city":"West Lafayette",
    "sg:classifiers":[
        {
            "category":"Professional",
            "subcategory":"Business Services",
            "type":"Services"
        }
    ],
    "sg:phone":"+1 765 463 7177",
    "sg:postcode":"47906",
    "sg:province":"IN",
    "wof:name":"Ls Technology Inc",
    "wof:placetype":"venue"
},
  "geometry": {"coordinates":[-86.90929,40.467902],"type":"Point"}
}