{
  "type": "Feature",
  "properties": {
    "addr:full":"11202 Fall Creek Rd Indianapolis IN 46256",
    "addr:housenumber":"11202",
    "addr:postcode":"46256",
    "addr:street":"Fall Creek Rd",
    "iso:country":"US",
    "sg:address":"11202 Fall Creek Rd",
    "sg:city":"Indianapolis",
    "sg:classifiers":[
        {
            "category":"Retail",
            "subcategory":"Laundry & Dry Cleaning",
            "type":"Services"
        }
    ],
    "sg:phone":"+1 317 842 5244",
    "sg:postcode":"46256",
    "sg:province":"IN",
    "sg:tags":[
        "cleaners"
    ],
    "wof:name":"Classic Cleaners",
    "wof:placetype":"venue"
},
  "geometry": {"coordinates":[-85.96812300000001,39.931651],"type":"Point"}
}