{
  "type": "Feature",
  "properties": {
    "iso:country":"US",
    "sg:address":"9332 E 10th St",
    "sg:city":"Indianapolis",
    "sg:classifiers":[
        {
            "category":"Professional",
            "subcategory":"Business Services",
            "type":"Services"
        }
    ],
    "sg:phone":"+1 317 899 2337",
    "sg:postcode":"46229",
    "sg:province":"IN",
    "wof:name":"Indianapolis Grain Inspection",
    "wof:placetype":"venue"
},
  "geometry": {"coordinates":[-85.999355,39.782211],"type":"Point"}
}