{
  "type": "Feature",
  "properties": {
    "iso:country":"US",
    "sg:address":"1215 E McGalliard Rd",
    "sg:city":"Muncie",
    "sg:classifiers":[
        {
            "category":"Shopping",
            "subcategory":"Used Merchandise",
            "type":"Retail Goods"
        }
    ],
    "sg:phone":"+1 765 281 8960",
    "sg:postcode":"47303",
    "sg:province":"IN",
    "sg:tags":[
        "pawnbroker"
    ],
    "wof:name":"EZ Pawn Inc",
    "wof:placetype":"venue"
},
  "geometry": {"coordinates":[-85.369878,40.218943],"type":"Point"}
}