{
  "type": "Feature",
  "properties": {
    "iso:country":"US",
    "sg:address":"1270 Manchester Ave",
    "sg:city":"Wabash",
    "sg:classifiers":[
        {
            "category":"Retail",
            "subcategory":"Veterinary Services",
            "type":"Services"
        }
    ],
    "sg:phone":"+1 260 563 5058",
    "sg:postcode":"46992",
    "sg:province":"IN",
    "sg:tags":[
        "clinic",
        "hospital"
    ],
    "wof:name":"Countryside Veterinary Hospital",
    "wof:placetype":"venue"
},
  "geometry": {"coordinates":[-85.801405,40.825994],"type":"Point"}
}