{
  "type": "Feature",
  "properties": {
    "iso:country":"US",
    "sg:address":"503 Wall St",
    "sg:city":"Valparaiso",
    "sg:classifiers":[
        {
            "category":"Manufacturing",
            "subcategory":"Tools & Machinery",
            "type":"Manufacturing & Wholesale Goods"
        }
    ],
    "sg:phone":"+1 219 477 4488",
    "sg:postcode":"46383",
    "sg:province":"IN",
    "sg:tags":[
        "physician",
        "surgeon"
    ],
    "wof:name":"Okaya Electric America",
    "wof:placetype":"venue"
},
  "geometry": {"coordinates":[-87.053963,41.488835],"type":"Point"}
}