{
  "type": "Feature",
  "properties": {
    "addr:full":"947 N Alabama St Indianapolis IN 46202",
    "addr:housenumber":"947",
    "addr:postcode":"46202",
    "addr:street":"N Alabama St",
    "iso:country":"US",
    "sg:address":"947 N Alabama St",
    "sg:city":"Indianapolis",
    "sg:classifiers":[
        {
            "category":"Food & Beverages",
            "subcategory":"Liquor & Beverages",
            "type":"Retail Goods"
        }
    ],
    "sg:phone":"+1 317 634 8792",
    "sg:postcode":"46202",
    "sg:province":"IN",
    "wof:name":"Alabama Liquor Store",
    "wof:placetype":"venue"
},
  "geometry": {"coordinates":[-86.152069,39.780329],"type":"Point"}
}