{
  "type": "Feature",
  "properties": {
    "iso:country":"US",
    "sg:address":"515 W Main St",
    "sg:city":"Thorntown",
    "sg:classifiers":[
        {
            "category":"Retail",
            "subcategory":"Laundry & Dry Cleaning",
            "type":"Services"
        }
    ],
    "sg:phone":"+1 765 436 7055",
    "sg:postcode":"46071",
    "sg:province":"IN",
    "sg:tags":[
        "cleaners",
        "rug",
        "carpet"
    ],
    "wof:name":"Ameri-Serve Inc",
    "wof:placetype":"venue"
},
  "geometry": {"coordinates":[-86.611665,40.129372],"type":"Point"}
}