{
  "type": "Feature",
  "properties": {
    "iso:country":"US",
    "sg:address":"2502 Middlebury St",
    "sg:city":"Elkhart",
    "sg:classifiers":[
        {
            "category":"Manufacturing",
            "subcategory":"Rubber & Plastics",
            "type":"Manufacturing & Wholesale Goods"
        }
    ],
    "sg:phone":"+1 574 295 0184",
    "sg:postcode":"46516",
    "sg:province":"IN",
    "wof:name":"Louroth Industries Inc",
    "wof:placetype":"venue"
},
  "geometry": {"coordinates":[-85.923789,41.68142],"type":"Point"}
}