{
  "type": "Feature",
  "properties": {
    "iso:country":"US",
    "sg:address":"420 S Asher St",
    "sg:city":"Brownstown",
    "sg:classifiers":[
        {
            "category":"Real Estate",
            "subcategory":"Real Estate Operator",
            "type":"Services"
        }
    ],
    "sg:phone":"+1 812 358 3425",
    "sg:postcode":"47220",
    "sg:province":"IN",
    "sg:tags":[
        "mobile",
        "home",
        "site"
    ],
    "wof:name":"Bane & Warren Rentals",
    "wof:placetype":"venue"
},
  "geometry": {"coordinates":[-86.04611,38.876377],"type":"Point"}
}