{
  "type": "Feature",
  "properties": {
    "iso:country":"US",
    "sg:address":"8230 US Hwy 31 S",
    "sg:city":"Indianapolis",
    "sg:classifiers":[
        {
            "category":"Retail",
            "subcategory":"Car Wash",
            "type":"Services"
        }
    ],
    "sg:phone":"+1 317 881 6299",
    "sg:postcode":"46227",
    "sg:province":"IN",
    "sg:tags":[
        "polishing",
        "washing"
    ],
    "wof:name":"Mike's Express Carwash",
    "wof:placetype":"venue"
},
  "geometry": {"coordinates":[-86.13258999999999,39.64375],"type":"Point"}
}