{
  "type": "Feature",
  "properties": {
    "addr:full":"4142 Ansar Ct Indianapolis IN 46254",
    "addr:postcode":"4142;46254",
    "addr:street":"Ansar Ct",
    "iso:country":"US",
    "sg:address":"4142 Ansar Ct",
    "sg:city":"Indianapolis",
    "sg:classifiers":[
        {
            "category":"Shopping",
            "subcategory":"Florist",
            "type":"Retail Goods"
        }
    ],
    "sg:phone":"+1 317 280 9175",
    "sg:postcode":"46254",
    "sg:province":"IN",
    "wof:name":"Indy Flowers",
    "wof:placetype":"venue"
},
  "geometry": {"coordinates":[-86.232698,39.838319],"type":"Point"}
}