{
  "type": "Feature",
  "properties": {
    "iso:country":"US",
    "sg:address":"1400 E State Rd 44",
    "sg:city":"Shelbyville",
    "sg:classifiers":[
        {
            "category":"Retail",
            "subcategory":"Car Wash",
            "type":"Services"
        }
    ],
    "sg:phone":"+1 317 392 4308",
    "sg:postcode":"46176",
    "sg:province":"IN",
    "sg:tags":[
        "polishing",
        "washing"
    ],
    "wof:name":"Eastside Express Wash",
    "wof:placetype":"venue"
},
  "geometry": {"coordinates":[-85.756578,39.520086],"type":"Point"}
}