{
  "type": "Feature",
  "properties": {
    "iso:country":"US",
    "sg:address":"8807 N State Rd 109",
    "sg:city":"Wilkinson",
    "sg:classifiers":[
        {
            "category":"Recreation",
            "type":"Entertainment"
        }
    ],
    "sg:phone":"+1 765 785 2588",
    "sg:postcode":"46186",
    "sg:province":"IN",
    "sg:tags":[
        "parks"
    ],
    "wof:name":"Indiana Field Guide Park",
    "wof:placetype":"venue"
},
  "geometry": {"coordinates":[-85.63418799999999,39.914288],"type":"Point"}
}