{
  "type": "Feature",
  "properties": {
    "iso:country":"US",
    "sg:address":"3950 Priority Way South Dr",
    "sg:city":"Indianapolis",
    "sg:classifiers":[
        {
            "category":"Professional",
            "subcategory":"Management & Consulting",
            "type":"Services"
        },
        {
            "category":"Professional",
            "subcategory":"Advertising",
            "type":"Services"
        }
    ],
    "sg:phone":"+1 317 571 0051",
    "sg:postcode":"46240",
    "sg:province":"IN",
    "sg:tags":[
        "marketing",
        "agency",
        "specialty",
        "program",
        "relation",
        "consultant",
        "counselor",
        "public"
    ],
    "sg:website":"http://www.colespr.com",
    "wof:name":"Coles Marketing Communications Inc",
    "wof:placetype":"venue"
},
  "geometry": {"coordinates":[-86.099405,39.919075],"type":"Point"}
}