{
  "type": "Feature",
  "properties": {
    "iso:country":"US",
    "sg:address":"115 Camden St",
    "sg:city":"Ridgeville",
    "sg:classifiers":[
        {
            "category":"Organizations",
            "subcategory":"Community Association",
            "type":"Services"
        }
    ],
    "sg:phone":"+1 765 857 2515",
    "sg:postcode":"47380",
    "sg:province":"IN",
    "sg:tags":[
        "military"
    ],
    "wof:name":"American Legion",
    "wof:placetype":"venue"
},
  "geometry": {"coordinates":[-85.029704,40.290904],"type":"Point"}
}