{
  "type": "Feature",
  "properties": {
    "iso:country":"US",
    "sg:address":"5811 Massachusetts Ave",
    "sg:city":"Indianapolis",
    "sg:classifiers":[
        {
            "category":"Autos & Motor Vehicles",
            "subcategory":"Automobile Sales",
            "type":"Retail Goods"
        }
    ],
    "sg:phone":"+1 317 547 4064",
    "sg:postcode":"46218",
    "sg:province":"IN",
    "sg:tags":[
        "car",
        "dealer"
    ],
    "wof:name":"Nealy's Body Shop",
    "wof:placetype":"venue"
},
  "geometry": {"coordinates":[-86.069802,39.816458],"type":"Point"}
}