{
  "type": "Feature",
  "properties": {
    "iso:country":"US",
    "sg:address":"126 S Main St",
    "sg:city":"Rushville",
    "sg:classifiers":[
        {
            "category":"Utilities",
            "subcategory":"Electric",
            "type":"Services"
        }
    ],
    "sg:phone":"+1 765 932 4121",
    "sg:postcode":"46173",
    "sg:province":"IN",
    "sg:tags":[
        "company"
    ],
    "sg:website":"www.rse.coop",
    "wof:name":"Rush Shelby Energy",
    "wof:placetype":"venue"
},
  "geometry": {"coordinates":[-85.444699,39.606823],"type":"Point"}
}