{
  "type": "Feature",
  "properties": {
    "iso:country":"US",
    "sg:address":"6123 N 750 W",
    "sg:city":"Jasper",
    "sg:phone":"+1 812 482 7340",
    "sg:postcode":"47546",
    "sg:province":"IN",
    "sg:tags":[
        "farm",
        "grain",
        "cash"
    ],
    "wof:name":"Edward Harker",
    "wof:placetype":"venue"
},
  "geometry": {"coordinates":[-87.044499,38.480925],"type":"Point"}
}