{
  "type": "Feature",
  "properties": {
    "iso:country":"US",
    "sg:address":"2446 E Business 30",
    "sg:city":"Columbia City",
    "sg:classifiers":[
        {
            "category":"Professional",
            "subcategory":"Management & Consulting",
            "type":"Services"
        }
    ],
    "sg:phone":"+1 260 244 9680",
    "sg:postcode":"46725",
    "sg:province":"IN",
    "sg:tags":[
        "consultant"
    ],
    "wof:name":"Daniel Menu & Party Consulting",
    "wof:placetype":"venue"
},
  "geometry": {"coordinates":[-85.43940600000001,41.139985],"type":"Point"}
}