{
  "type": "Feature",
  "properties": {
    "iso:country":"US",
    "sg:address":"507 Michigan Ave",
    "sg:city":"Auburn",
    "sg:classifiers":[
        {
            "category":"Government",
            "subcategory":"Office",
            "type":"Public Place"
        }
    ],
    "sg:phone":"+1 260 482 3047",
    "sg:postcode":"46706",
    "sg:province":"IN",
    "sg:tags":[
        "state"
    ],
    "wof:name":"Natural Resources Div",
    "wof:placetype":"venue"
},
  "geometry": {"coordinates":[-85.061172,41.370577],"type":"Point"}
}