{
  "type": "Feature",
  "properties": {
    "addr:full":"701 S Maple St Fortville IN 46040",
    "addr:housenumber":"701",
    "addr:postcode":"46040",
    "addr:street":"S Maple St",
    "iso:country":"US",
    "sg:address":"701 S Maple St",
    "sg:city":"Fortville",
    "sg:classifiers":[
        {
            "category":"Organizations",
            "subcategory":"Religious Organization",
            "type":"Services"
        }
    ],
    "sg:phone":"+1 317 485 6443",
    "sg:postcode":"46040",
    "sg:province":"IN",
    "sg:tags":[
        "church"
    ],
    "wof:name":"Fortville Church-The Nazarene",
    "wof:placetype":"venue"
},
  "geometry": {"coordinates":[-85.846626,39.929264],"type":"Point"}
}