{
  "type": "Feature",
  "properties": {
    "iso:country":"US",
    "sg:address":"800 E Jefferson St",
    "sg:city":"Tipton",
    "sg:classifiers":[
        {
            "category":"Ice Cream",
            "type":"Food & Drink"
        }
    ],
    "sg:menulink":"http://www.allmenus.com/in/cicero/161724-dairy-queen/menu/",
    "sg:phone":"+1 765 675 4095",
    "sg:postcode":"46072",
    "sg:province":"IN",
    "sg:tags":[
        "burger",
        "american"
    ],
    "wof:name":"Dairy Queen",
    "wof:placetype":"venue"
},
  "geometry": {"coordinates":[-86.03148899999999,40.282604],"type":"Point"}
}