{
  "type": "Feature",
  "properties": {
    "iso:country":"US",
    "sg:address":"7029 W 25th Ave",
    "sg:city":"Gary",
    "sg:classifiers":[
        {
            "category":"Manufacturing",
            "subcategory":"Building Materials",
            "type":"Manufacturing & Wholesale Goods"
        }
    ],
    "sg:phone":"+1 219 844 1233",
    "sg:postcode":"46406",
    "sg:province":"IN",
    "sg:tags":[
        "door"
    ],
    "wof:name":"Nu-Tec Industries Inc",
    "wof:placetype":"venue"
},
  "geometry": {"coordinates":[-87.427125,41.573503],"type":"Point"}
}