{
  "type": "Feature",
  "properties": {
    "iso:country":"US",
    "sg:address":"1011 S State Rd 135",
    "sg:city":"Greenwood",
    "sg:classifiers":[
        {
            "category":"Utilities",
            "subcategory":"Mobile Phone",
            "type":"Services"
        }
    ],
    "sg:phone":"+1 317 859 1169",
    "sg:postcode":"46143",
    "sg:province":"IN",
    "sg:tags":[
        "telephone",
        "cellular"
    ],
    "wof:name":"Jim Stewart Mobile Phones Inc",
    "wof:placetype":"venue"
},
  "geometry": {"coordinates":[-86.15902699999999,39.595943],"type":"Point"}
}