{
  "type": "Feature",
  "properties": {
    "iso:country":"US",
    "sg:address":"318 Campbell Ave",
    "sg:city":"Indianapolis",
    "sg:classifiers":[
        {
            "category":"Health Services",
            "subcategory":"Health Practitioner",
            "type":"Services"
        }
    ],
    "sg:phone":"+1 317 352 9820",
    "sg:postcode":"46219",
    "sg:province":"IN",
    "sg:tags":[
        "breastfeeding",
        "c",
        "supply",
        "lactation",
        "retail",
        "rental"
    ],
    "wof:name":"Baby Dance",
    "wof:placetype":"venue"
},
  "geometry": {"coordinates":[-86.065496,39.772207],"type":"Point"}
}