{
  "type": "Feature",
  "properties": {
    "iso:country":"US",
    "sg:address":"5720 W State Rd 46",
    "sg:city":"Bloomington",
    "sg:classifiers":[
        {
            "category":"Manufacturing",
            "subcategory":"Signs",
            "type":"Manufacturing & Wholesale Goods"
        }
    ],
    "sg:phone":"+1 812 876 6696",
    "sg:postcode":"47404",
    "sg:province":"IN",
    "sg:tags":[
        "specialty",
        "mfg"
    ],
    "wof:name":"Xtreme Signs & Graphics",
    "wof:placetype":"venue"
},
  "geometry": {"coordinates":[-86.613566,39.225797],"type":"Point"}
}