{
  "type": "Feature",
  "properties": {
    "iso:country":"US",
    "sg:address":"6550 E 30th St",
    "sg:city":"Indianapolis",
    "sg:classifiers":[
        {
            "category":"Professional",
            "type":"Services"
        }
    ],
    "sg:phone":"+1 317 630 0186",
    "sg:postcode":"46219",
    "sg:province":"IN",
    "sg:tags":[
        "establishment"
    ],
    "wof:name":"Sound & Spirit",
    "wof:placetype":"venue"
},
  "geometry": {"coordinates":[-86.04571199999999,39.811071],"type":"Point"}
}