{
  "type": "Feature",
  "properties": {
    "iso:country":"US",
    "sg:address":"760 N Union St",
    "sg:city":"Hobart",
    "sg:classifiers":[
        {
            "category":"Social Services",
            "subcategory":"Job Training",
            "type":"Services"
        }
    ],
    "sg:phone":"+1 219 947 3348",
    "sg:postcode":"46342",
    "sg:province":"IN",
    "sg:tags":[
        "apprenticeship",
        "program"
    ],
    "wof:name":"Carpenters Apprentice Program",
    "wof:placetype":"venue"
},
  "geometry": {"coordinates":[-87.231099,41.549209],"type":"Point"}
}