{
  "type": "Feature",
  "properties": {
    "iso:country":"US",
    "sg:address":"133 S Taylor St",
    "sg:city":"South Bend",
    "sg:classifiers":[
        {
            "category":"Professional",
            "subcategory":"Lawyer & Legal Services",
            "type":"Services"
        }
    ],
    "sg:phone":"+1 574 288 9447",
    "sg:postcode":"46601",
    "sg:province":"IN",
    "sg:tags":[
        "attorney"
    ],
    "wof:name":"William P Stanley & Assoc",
    "wof:placetype":"venue"
},
  "geometry": {"coordinates":[-86.257288,41.676077],"type":"Point"}
}