{
  "type": "Feature",
  "properties": {
    "iso:country":"US",
    "sg:address":"514 E Merrill St",
    "sg:city":"Indianapolis",
    "sg:classifiers":[
        {
            "category":"Place Of Worship",
            "subcategory":"Monastery",
            "type":"Public Place"
        }
    ],
    "sg:phone":"+1 317 917 0306",
    "sg:postcode":"46203",
    "sg:province":"IN",
    "sg:tags":[
        "convent"
    ],
    "wof:name":"Franciscan Sist",
    "wof:placetype":"venue"
},
  "geometry": {"coordinates":[-86.149128,39.758744],"type":"Point"}
}