{
  "type": "Feature",
  "properties": {
    "addr:full":"408 E Center Rd Kokomo IN 46902",
    "addr:housenumber":"408",
    "addr:postcode":"46902",
    "addr:street":"E Center Rd",
    "iso:country":"US",
    "sg:address":"408 E Center Rd",
    "sg:city":"Kokomo",
    "sg:classifiers":[
        {
            "category":"Restaurant",
            "type":"Food & Drink"
        }
    ],
    "sg:menulink":"http://www.allmenus.com/in/taylor/79421-pizza-hut/menu/",
    "sg:phone":"+1 765 453 1511",
    "sg:postcode":"46902",
    "sg:province":"IN",
    "sg:tags":[
        "american",
        "pizza"
    ],
    "wof:name":"Pizza Hut",
    "wof:placetype":"venue"
},
  "geometry": {"coordinates":[-86.123789,40.433461],"type":"Point"}
}