{
  "type": "Feature",
  "properties": {
    "iso:country":"US",
    "sg:address":"200 Sandpiper Dr",
    "sg:city":"Chesterton",
    "sg:classifiers":[
        {
            "category":"Professional",
            "subcategory":"Management & Consulting",
            "type":"Services"
        }
    ],
    "sg:phone":"+1 219 921 1589",
    "sg:postcode":"46304",
    "sg:province":"IN",
    "sg:tags":[
        "consultant",
        "business"
    ],
    "wof:name":"Strategic Learning Partners",
    "wof:placetype":"venue"
},
  "geometry": {"coordinates":[-87.02932699999999,41.610082],"type":"Point"}
}