{
  "type": "Feature",
  "properties": {
    "iso:country":"US",
    "sg:address":"121 N Main St",
    "sg:city":"Tipton",
    "sg:classifiers":[
        {
            "category":"Professional",
            "subcategory":"Accounting & Tax Preparation",
            "type":"Services"
        }
    ],
    "sg:phone":"+1 765 675 7021",
    "sg:postcode":"46072",
    "sg:province":"IN",
    "sg:tags":[
        "accountant"
    ],
    "wof:name":"Patrick N Logan CPA",
    "wof:placetype":"venue"
},
  "geometry": {"coordinates":[-86.041178,40.283288],"type":"Point"}
}