{
  "type": "Feature",
  "properties": {
    "iso:country":"US",
    "sg:address":"2649 Highway Ave",
    "sg:city":"Highland",
    "sg:classifiers":[
        {
            "category":"Building & Trades",
            "subcategory":"Plumbing",
            "type":"Services"
        }
    ],
    "sg:phone":"+1 219 838 2302",
    "sg:postcode":"46322",
    "sg:province":"IN",
    "sg:tags":[
        "plumbing",
        "contractor"
    ],
    "wof:name":"Leathers Plumbers Inc",
    "wof:placetype":"venue"
},
  "geometry": {"coordinates":[-87.464984,41.555594],"type":"Point"}
}