{
  "type": "Feature",
  "properties": {
    "addr:full":"228 Holton Rd Laporte IN 46350",
    "addr:housenumber":"228",
    "addr:postcode":"46350",
    "addr:street":"Holton Rd",
    "iso:country":"US",
    "sg:address":"228 Holton Rd",
    "sg:city":"Laporte",
    "sg:classifiers":[
        {
            "category":"Utilities",
            "subcategory":"Sewage",
            "type":"Services"
        }
    ],
    "sg:phone":"+1 219 325 3281",
    "sg:postcode":"46350",
    "sg:province":"IN",
    "sg:tags":[
        "company",
        "sewer"
    ],
    "wof:name":"Pine Lake Conservancy District",
    "wof:placetype":"venue"
},
  "geometry": {"coordinates":[-86.760255,41.626459],"type":"Point"}
}