{
  "type": "Feature",
  "properties": {
    "addr:full":"1011 Heath St Lafayette IN 47904",
    "addr:housenumber":"1011",
    "addr:postcode":"47904",
    "addr:street":"Heath St",
    "iso:country":"US",
    "sg:address":"1011 Heath St",
    "sg:city":"Lafayette",
    "sg:classifiers":[
        {
            "category":"Organizations",
            "subcategory":"Religious Organization",
            "type":"Services"
        }
    ],
    "sg:phone":"+1 765 742 2191",
    "sg:postcode":"47904",
    "sg:province":"IN",
    "sg:tags":[
        "church"
    ],
    "wof:name":"Harvest Chapel",
    "wof:placetype":"venue"
},
  "geometry": {"coordinates":[-86.88430099999999,40.428774],"type":"Point"}
}