{
  "type": "Feature",
  "properties": {
    "iso:country":"US",
    "sg:address":"8014 Mc Farland Ct",
    "sg:city":"Indianapolis",
    "sg:classifiers":[
        {
            "category":"Building & Trades",
            "subcategory":"Construction",
            "type":"Services"
        }
    ],
    "sg:phone":"+1 317 887 6035",
    "sg:postcode":"46227",
    "sg:province":"IN",
    "sg:tags":[
        "house"
    ],
    "wof:name":"DLS Home Improvement",
    "wof:placetype":"venue"
},
  "geometry": {"coordinates":[-86.110544,39.649706],"type":"Point"}
}