{
  "type": "Feature",
  "properties": {
    "iso:country":"US",
    "sg:address":"4506 Haffner Dr",
    "sg:city":"Fort Wayne",
    "sg:classifiers":[
        {
            "category":"Home & Garden",
            "subcategory":"Furniture",
            "type":"Retail Goods"
        }
    ],
    "sg:phone":"+1 260 456 4145",
    "sg:postcode":"46835",
    "sg:province":"IN",
    "wof:name":"J D Treasures",
    "wof:placetype":"venue"
},
  "geometry": {"coordinates":[-85.078605,41.124239],"type":"Point"}
}