{
  "type": "Feature",
  "properties": {
    "iso:country":"US",
    "sg:address":"300 W US Hwy 6",
    "sg:city":"Ligonier",
    "sg:classifiers":[
        {
            "category":"Sports & Exercise",
            "subcategory":"Bowling",
            "type":"Entertainment"
        }
    ],
    "sg:phone":"+1 260 894 3732",
    "sg:postcode":"46767",
    "sg:province":"IN",
    "sg:tags":[
        "center"
    ],
    "wof:name":"Bowlway Lanes",
    "wof:placetype":"venue"
},
  "geometry": {"coordinates":[-85.590415,41.452075],"type":"Point"}
}