{
  "type": "Feature",
  "properties": {
    "iso:country":"US",
    "sg:address":"2361 N New Jersey St",
    "sg:city":"Indianapolis",
    "sg:classifiers":[
        {
            "category":"Social Services",
            "subcategory":"Child Care",
            "type":"Services"
        }
    ],
    "sg:phone":"+1 317 920 9086",
    "sg:postcode":"46205",
    "sg:province":"IN",
    "wof:name":"Chanteria's Day Care",
    "wof:placetype":"venue"
},
  "geometry": {"coordinates":[-86.15066400000001,39.800032],"type":"Point"}
}