{
  "type": "Feature",
  "properties": {
    "iso:country":"US",
    "sg:address":"1075 Hilltop Dr",
    "sg:city":"Rome City",
    "sg:classifiers":[
        {
            "category":"Building & Trades",
            "subcategory":"Construction",
            "type":"Services"
        }
    ],
    "sg:phone":"+1 260 854 4741",
    "sg:postcode":"46784",
    "sg:province":"IN",
    "sg:tags":[
        "general",
        "contractor"
    ],
    "wof:name":"Thompson Construction",
    "wof:placetype":"venue"
},
  "geometry": {"coordinates":[-85.358649,41.483876],"type":"Point"}
}