{
  "type": "Feature",
  "properties": {
    "iso:country":"US",
    "sg:address":"216 S Lake St",
    "sg:city":"Warsaw",
    "sg:classifiers":[
        {
            "category":"Retail",
            "subcategory":"Laundry & Dry Cleaning",
            "type":"Services"
        }
    ],
    "sg:phone":"+1 574 267 5885",
    "sg:postcode":"46580",
    "sg:province":"IN",
    "sg:tags":[
        "cleaners"
    ],
    "wof:name":"Wolford Dry Cleaners",
    "wof:placetype":"venue"
},
  "geometry": {"coordinates":[-85.858043,41.236939],"type":"Point"}
}