{
  "type": "Feature",
  "properties": {
    "iso:country":"US",
    "sg:address":"1701 Library Blvd",
    "sg:city":"Greenwood",
    "sg:classifiers":[
        {
            "category":"Professional",
            "subcategory":"Lawyer & Legal Services",
            "type":"Services"
        }
    ],
    "sg:phone":"+1 317 882 9839",
    "sg:postcode":"46142",
    "sg:province":"IN",
    "sg:tags":[
        "attorney",
        "law",
        "business",
        "litigation",
        "civil",
        "corporation",
        "partnership",
        "trial",
        "personal",
        "real estate",
        "injury"
    ],
    "sg:website":"http://www.reameslaw.com",
    "wof:name":"Reames, John M PC",
    "wof:placetype":"venue"
},
  "geometry": {"coordinates":[-86.157349,39.60775],"type":"Point"}
}