{
  "type": "Feature",
  "properties": {
    "iso:country":"US",
    "sg:address":"5260 Egbert Rd",
    "sg:city":"Martinsville",
    "sg:classifiers":[
        {
            "category":"Building & Trades",
            "subcategory":"Construction",
            "type":"Services"
        }
    ],
    "sg:phone":"+1 765 342 7444",
    "sg:postcode":"46151",
    "sg:province":"IN",
    "sg:tags":[
        "general",
        "contractor"
    ],
    "wof:name":"Pipelink Maintenance Inc",
    "wof:placetype":"venue"
},
  "geometry": {"coordinates":[-86.327759,39.479789],"type":"Point"}
}