{
  "type": "Feature",
  "properties": {
    "iso:country":"US",
    "sg:address":"415 E Hendricks St",
    "sg:city":"Shelbyville",
    "sg:classifiers":[
        {
            "category":"Restaurant",
            "type":"Food & Drink"
        }
    ],
    "sg:phone":"+1 317 421 0820",
    "sg:postcode":"46176",
    "sg:province":"IN",
    "sg:tags":[
        "banquet",
        "rooms"
    ],
    "wof:name":"Occasions",
    "wof:placetype":"venue"
},
  "geometry": {"coordinates":[-85.773373,39.521939],"type":"Point"}
}