{
  "type": "Feature",
  "properties": {
    "iso:country":"US",
    "sg:address":"1778 Bridgewater Dr",
    "sg:city":"Avon",
    "sg:classifiers":[
        {
            "category":"Retail",
            "subcategory":"Repair Shop",
            "type":"Services"
        }
    ],
    "sg:phone":"+1 317 839 2077",
    "sg:postcode":"46123",
    "sg:province":"IN",
    "sg:tags":[
        "welding"
    ],
    "wof:name":"Bales Mobile Welding Co",
    "wof:placetype":"venue"
},
  "geometry": {"coordinates":[-86.409277,39.736631],"type":"Point"}
}