{
  "type": "Feature",
  "properties": {
    "iso:country":"US",
    "sg:address":"874 Massachusetts Ave",
    "sg:city":"Indianapolis",
    "sg:classifiers":[
        {
            "category":"Professional",
            "subcategory":"Art Services",
            "type":"Services"
        }
    ],
    "sg:phone":"+1 317 822 5922",
    "sg:postcode":"46204",
    "sg:province":"IN",
    "sg:tags":[
        "commercial",
        "design"
    ],
    "wof:name":"McFee Gallery",
    "wof:placetype":"venue"
},
  "geometry": {"coordinates":[-86.14241699999999,39.779615],"type":"Point"}
}