{
  "type": "Feature",
  "properties": {
    "iso:country":"US",
    "sg:address":"8725 E Washington St",
    "sg:city":"Indianapolis",
    "sg:classifiers":[
        {
            "category":"Sports & Exercise",
            "subcategory":"Gym",
            "type":"Entertainment"
        }
    ],
    "sg:phone":"+1 317 898 8988",
    "sg:postcode":"46219",
    "sg:province":"IN",
    "sg:tags":[
        "club",
        "health",
        "studio",
        "gymnasium"
    ],
    "wof:name":"Ladies Only",
    "wof:placetype":"venue"
},
  "geometry": {"coordinates":[-86.013474,39.773639],"type":"Point"}
}