{
  "type": "Feature",
  "properties": {
    "iso:country":"US",
    "sg:address":"2202 S State Rd 57",
    "sg:city":"Washington",
    "sg:classifiers":[
        {
            "category":"Recreation",
            "subcategory":"Marina",
            "type":"Entertainment"
        }
    ],
    "sg:phone":"+1 812 254 9350",
    "sg:postcode":"47501",
    "sg:province":"IN",
    "wof:name":"Outdoor World",
    "wof:placetype":"venue"
},
  "geometry": {"coordinates":[-87.17826100000001,38.635853],"type":"Point"}
}