{
  "type": "Feature",
  "properties": {
    "iso:country":"US",
    "sg:address":"10991 Mallard Way",
    "sg:city":"Indianapolis",
    "sg:classifiers":[
        {
            "category":"Retail",
            "subcategory":"Repair Shop",
            "type":"Services"
        }
    ],
    "sg:phone":"+1 317 858 0408",
    "sg:postcode":"46278",
    "sg:province":"IN",
    "sg:tags":[
        "hospital",
        "refinishing"
    ],
    "wof:name":"Star Medical",
    "wof:placetype":"venue"
},
  "geometry": {"coordinates":[-86.329804,39.879075],"type":"Point"}
}