{
  "type": "Feature",
  "properties": {
    "iso:country":"US",
    "sg:address":"4060 State Rd 32 W",
    "sg:city":"Crawfordsville",
    "sg:classifiers":[
        {
            "category":"Retail",
            "subcategory":"Repair Shop",
            "type":"Services"
        }
    ],
    "sg:phone":"+1 765 362 2221",
    "sg:postcode":"47933",
    "sg:province":"IN",
    "sg:tags":[
        "upholsterer"
    ],
    "wof:name":"Pat's Upholstery",
    "wof:placetype":"venue"
},
  "geometry": {"coordinates":[-86.97882300000001,40.024789],"type":"Point"}
}