{
  "type": "Feature",
  "properties": {
    "addr:full":"8060 Knue Rd Indianapolis IN 46250",
    "addr:housenumber":"8060",
    "addr:postcode":"46250",
    "addr:street":"Knue Rd",
    "iso:country":"US",
    "sg:address":"8060 Knue Rd",
    "sg:city":"Indianapolis",
    "sg:classifiers":[
        {
            "category":"Organizations",
            "subcategory":"Membership Organization",
            "type":"Services"
        }
    ],
    "sg:phone":"+1 317 578 0857",
    "sg:postcode":"46250",
    "sg:province":"IN",
    "wof:name":"Kiwanis Indiana District",
    "wof:placetype":"venue"
},
  "geometry": {"coordinates":[-86.06025200000001,39.900554],"type":"Point"}
}