{
  "type": "Feature",
  "properties": {
    "iso:country":"US",
    "sg:address":"6321 University Cmns",
    "sg:city":"South Bend",
    "sg:classifiers":[
        {
            "category":"Professional",
            "subcategory":"Lawyer & Legal Services",
            "type":"Services"
        }
    ],
    "sg:phone":"+1 574 247 0862",
    "sg:postcode":"46635",
    "sg:province":"IN",
    "sg:tags":[
        "attorney"
    ],
    "wof:name":"Robert A Schlifke",
    "wof:placetype":"venue"
},
  "geometry": {"coordinates":[-86.196207,41.717066],"type":"Point"}
}