{
  "type": "Feature",
  "properties": {
    "addr:full":"319 E South St Lebanon IN 46052",
    "addr:housenumber":"319 e",
    "addr:postcode":"46052",
    "addr:street":"South St",
    "iso:country":"US",
    "sg:address":"319 E South St",
    "sg:city":"Lebanon",
    "sg:classifiers":[
        {
            "category":"Organizations",
            "subcategory":"Religious Organization",
            "type":"Services"
        }
    ],
    "sg:phone":"+1 765 482 5558",
    "sg:postcode":"46052",
    "sg:province":"IN",
    "sg:tags":[
        "church"
    ],
    "sg:website":"www.stjoeleb.org",
    "wof:name":"St Joseph Catholic Church",
    "wof:placetype":"venue"
},
  "geometry": {"coordinates":[-86.46626999999999,40.04667],"type":"Point"}
}