{
  "type": "Feature",
  "properties": {
    "iso:country":"US",
    "sg:address":"5340 S 400 W",
    "sg:city":"Berne",
    "sg:classifiers":[
        {
            "category":"Personal",
            "subcategory":"Beauty Salon",
            "type":"Services"
        }
    ],
    "sg:phone":"+1 260 334 5561",
    "sg:postcode":"46711",
    "sg:province":"IN",
    "wof:name":"Jenny's Beauty Salon",
    "wof:placetype":"venue"
},
  "geometry": {"coordinates":[-85.013489,40.66586],"type":"Point"}
}