{
  "type": "Feature",
  "properties": {
    "addr:full":"9533 Corporation Dr Indianapolis IN 46256",
    "addr:housenumber":"9533",
    "addr:postcode":"46256",
    "addr:street":"Corporation Dr",
    "iso:country":"US",
    "sg:address":"9533 Corporation Dr",
    "sg:city":"Indianapolis",
    "sg:classifiers":[
        {
            "category":"Fast Food",
            "type":"Food & Drink"
        },
        {
            "category":"Food & Beverages",
            "subcategory":"Meat & Fish",
            "type":"Retail Goods"
        }
    ],
    "sg:phone":"+1 317 578 2484",
    "sg:postcode":"46256",
    "sg:province":"IN",
    "sg:tags":[
        "burger",
        "hot",
        "dog"
    ],
    "sg:website":"www.burgerking.com",
    "wof:name":"Burger King",
    "wof:placetype":"venue"
},
  "geometry": {"coordinates":[-86.032791,39.925746],"type":"Point"}
}