{
  "type": "Feature",
  "properties": {
    "iso:country":"US",
    "sg:address":"1356 Lane St",
    "sg:city":"Gary",
    "sg:classifiers":[
        {
            "category":"Retail",
            "subcategory":"Auto Repair",
            "type":"Services"
        }
    ],
    "sg:phone":"+1 219 977 8586",
    "sg:postcode":"46404",
    "sg:province":"IN",
    "sg:tags":[
        "body",
        "automobile",
        "painting",
        "repairing"
    ],
    "wof:name":"Southside Fleet",
    "wof:placetype":"venue"
},
  "geometry": {"coordinates":[-87.388931,41.589206],"type":"Point"}
}