{
  "type": "Feature",
  "properties": {
    "iso:country":"US",
    "sg:address":"100 N Harrison St",
    "sg:city":"Salem",
    "sg:classifiers":[
        {
            "category":"Health Services",
            "subcategory":"Doctor",
            "type":"Services"
        }
    ],
    "sg:phone":"+1 812 883 5804",
    "sg:postcode":"47167",
    "sg:province":"IN",
    "sg:tags":[
        "dentist"
    ],
    "wof:name":"Gene F Hedrick DDS",
    "wof:placetype":"venue"
},
  "geometry": {"coordinates":[-86.10600100000001,38.606739],"type":"Point"}
}