{
  "type": "Feature",
  "properties": {
    "iso:country":"US",
    "sg:address":"212 W US Hwy 136",
    "sg:city":"Veedersburg",
    "sg:classifiers":[
        {
            "category":"Retail",
            "subcategory":"Veterinary Services",
            "type":"Services"
        }
    ],
    "sg:phone":"+1 765 294 2203",
    "sg:postcode":"47987",
    "sg:province":"IN",
    "sg:tags":[
        "veterinarian"
    ],
    "wof:name":"West Central Veterinary Svc",
    "wof:placetype":"venue"
},
  "geometry": {"coordinates":[-87.288742,40.118411],"type":"Point"}
}