{
  "type": "Feature",
  "properties": {
    "iso:country":"US",
    "sg:address":"6321 S East St",
    "sg:city":"Indianapolis",
    "sg:classifiers":[
        {
            "category":"Professional",
            "subcategory":"Engineering",
            "type":"Services"
        }
    ],
    "sg:phone":"+1 317 791 1120",
    "sg:postcode":"46227",
    "sg:province":"IN",
    "sg:tags":[
        "engineer"
    ],
    "wof:name":"Kenna Consulting",
    "wof:placetype":"venue"
},
  "geometry": {"coordinates":[-86.149168,39.672019],"type":"Point"}
}