{
  "type": "Feature",
  "properties": {
    "addr:full":"122 N Main St Kokomo IN 46901",
    "addr:housenumber":"122",
    "addr:postcode":"46901",
    "addr:street":"N Main St",
    "iso:country":"US",
    "sg:address":"122 N Main St",
    "sg:city":"Kokomo",
    "sg:classifiers":[
        {
            "category":"Professional",
            "subcategory":"Lawyer & Legal Services",
            "type":"Services"
        }
    ],
    "sg:phone":"+1 765 459 0751",
    "sg:postcode":"46901",
    "sg:province":"IN",
    "sg:tags":[
        "attorney"
    ],
    "sg:website":"www.kms-law.com",
    "wof:name":"King Mc Cann & Scott",
    "wof:placetype":"venue"
},
  "geometry": {"coordinates":[-86.131164,40.487194],"type":"Point"}
}