{
  "type": "Feature",
  "properties": {
    "addr:full":"8440 Woodfield Crossing Blvd Indianapolis IN 46240",
    "addr:housenumber":"8440",
    "addr:postcode":"46240",
    "addr:street":"Woodfield Crossing Blvd",
    "iso:country":"US",
    "sg:address":"8440 Woodfield Crossing Blvd",
    "sg:city":"Indianapolis",
    "sg:classifiers":[
        {
            "category":"Professional",
            "type":"Services"
        }
    ],
    "sg:phone":"+1 317 639 7513",
    "sg:postcode":"46240",
    "sg:province":"IN",
    "sg:tags":[
        "establishment"
    ],
    "wof:name":"Intus Technologies",
    "wof:placetype":"venue"
},
  "geometry": {"coordinates":[-86.120324,39.910172],"type":"Point"}
}