{
  "type": "Feature",
  "properties": {
    "iso:country":"US",
    "sg:address":"202 S Warman Ave",
    "sg:city":"Indianapolis",
    "sg:classifiers":[
        {
            "category":"Building & Trades",
            "subcategory":"Construction",
            "type":"Services"
        }
    ],
    "sg:phone":"+1 317 637 6969",
    "sg:postcode":"46222",
    "sg:province":"IN",
    "sg:tags":[
        "marking",
        "maintenance",
        "parking"
    ],
    "wof:name":"Accu Seal & Supply",
    "wof:placetype":"venue"
},
  "geometry": {"coordinates":[-86.20654500000001,39.761953],"type":"Point"}
}