{
  "type": "Feature",
  "properties": {
    "iso:country":"US",
    "sg:address":"5088 W 17th Ave",
    "sg:city":"Gary",
    "sg:classifiers":[
        {
            "category":"Shopping",
            "subcategory":"Music",
            "type":"Retail Goods"
        }
    ],
    "sg:phone":"+1 219 944 1491",
    "sg:postcode":"46406",
    "sg:province":"IN",
    "wof:name":"Lion Heart Records Inc",
    "wof:placetype":"venue"
},
  "geometry": {"coordinates":[-87.400134,41.586212],"type":"Point"}
}