{
  "type": "Feature",
  "properties": {
    "iso:country":"US",
    "sg:address":"711 N Clark Blvd",
    "sg:city":"Clarksville",
    "sg:classifiers":[
        {
            "category":"Insurance",
            "subcategory":"Insurance Agent",
            "type":"Services"
        }
    ],
    "sg:phone":"+1 812 282 1475",
    "sg:postcode":"47129",
    "sg:province":"IN",
    "wof:name":"Allstate Insurance",
    "wof:placetype":"venue"
},
  "geometry": {"coordinates":[-85.771192,38.295779],"type":"Point"}
}