{
  "type": "Feature",
  "properties": {
    "addr:full":"11360 Old Stone Dr Indianapolis IN 46236",
    "addr:housenumber":"11360",
    "addr:postcode":"46236",
    "addr:street":"Old Stone Dr",
    "iso:country":"US",
    "sg:address":"11360 Old Stone Dr",
    "sg:city":"Indianapolis",
    "sg:classifiers":[
        {
            "category":"Personal",
            "subcategory":"Barber",
            "type":"Services"
        }
    ],
    "sg:phone":"+1 317 823 8732",
    "sg:postcode":"46236",
    "sg:province":"IN",
    "wof:name":"Barber Shops Inc",
    "wof:placetype":"venue"
},
  "geometry": {"coordinates":[-85.965322,39.917148],"type":"Point"}
}