{
  "type": "Feature",
  "properties": {
    "iso:country":"US",
    "sg:address":"7605 W Co Rd 1000 N",
    "sg:city":"Gaston",
    "sg:classifiers":[
        {
            "category":"Farming",
            "subcategory":"Farm",
            "type":"Manufacturing & Wholesale Goods"
        }
    ],
    "sg:phone":"+1 765 358 4087",
    "sg:postcode":"47342",
    "sg:province":"IN",
    "sg:tags":[
        "crop",
        "general"
    ],
    "wof:name":"Dunroven Farm",
    "wof:placetype":"venue"
},
  "geometry": {"coordinates":[-85.473565,40.335615],"type":"Point"}
}