{
  "type": "Feature",
  "properties": {
    "iso:country":"US",
    "sg:address":"311 2nd St",
    "sg:city":"Aurora",
    "sg:classifiers":[
        {
            "category":"Shopping",
            "subcategory":"Used Merchandise",
            "type":"Retail Goods"
        }
    ],
    "sg:phone":"+1 812 926 1333",
    "sg:postcode":"47001",
    "sg:province":"IN",
    "sg:tags":[
        "shop",
        "consignment"
    ],
    "wof:name":"Once Again",
    "wof:placetype":"venue"
},
  "geometry": {"coordinates":[-84.900023,39.05631],"type":"Point"}
}