{
  "type": "Feature",
  "properties": {
    "iso:country":"US",
    "sg:address":"435 W State St",
    "sg:city":"Huntington",
    "sg:classifiers":[
        {
            "category":"Farming",
            "subcategory":"Dairy Farm",
            "type":"Manufacturing & Wholesale Goods"
        }
    ],
    "sg:phone":"+1 260 356 9530",
    "sg:postcode":"46750",
    "sg:province":"IN",
    "wof:name":"National Dairy Products Corp",
    "wof:placetype":"venue"
},
  "geometry": {"coordinates":[-85.497491,40.880232],"type":"Point"}
}