{
  "type": "Feature",
  "properties": {
    "iso:country":"US",
    "sg:address":"777 Cor-Dale Rd",
    "sg:city":"Lafayette",
    "sg:classifiers":[
        {
            "category":"Building & Trades",
            "subcategory":"Construction",
            "type":"Services"
        }
    ],
    "sg:phone":"+1 765 742 4822",
    "sg:postcode":"47904",
    "sg:province":"IN",
    "sg:tags":[
        "fence",
        "contractor"
    ],
    "wof:name":"Mr Fence-It",
    "wof:placetype":"venue"
},
  "geometry": {"coordinates":[-86.88208,40.447291],"type":"Point"}
}