{
  "type": "Feature",
  "properties": {
    "addr:full":"118 W Edison Rd Mishawaka IN 46545",
    "addr:housenumber":"118",
    "addr:postcode":"46545",
    "addr:street":"W Edison Rd",
    "iso:country":"US",
    "sg:address":"118 W Edison Rd",
    "sg:city":"Mishawaka",
    "sg:classifiers":[
        {
            "category":"Insurance",
            "subcategory":"Insurance Agent",
            "type":"Services"
        }
    ],
    "sg:phone":"+1 574 258 6200",
    "sg:postcode":"46545",
    "sg:province":"IN",
    "wof:name":"State Farm Insurance",
    "wof:placetype":"venue"
},
  "geometry": {"coordinates":[-86.18705799999999,41.694909],"type":"Point"}
}