{
  "type": "Feature",
  "properties": {
    "iso:country":"US",
    "sg:address":"400 E Jefferson St",
    "sg:city":"Plymouth",
    "sg:classifiers":[
        {
            "category":"Autos & Motor Vehicles",
            "subcategory":"Fuel & Gas Station",
            "type":"Retail Goods"
        }
    ],
    "sg:phone":"+1 574 936 1721",
    "sg:postcode":"46563",
    "sg:province":"IN",
    "sg:tags":[
        "oil"
    ],
    "wof:name":"Plymouth Clark",
    "wof:placetype":"venue"
},
  "geometry": {"coordinates":[-86.305016,41.343688],"type":"Point"}
}