{
  "type": "Feature",
  "properties": {
    "iso:country":"US",
    "sg:address":"16505 Houk Rd",
    "sg:city":"Hoagland",
    "sg:classifiers":[
        {
            "category":"Farming",
            "subcategory":"Dairy Farm",
            "type":"Manufacturing & Wholesale Goods"
        }
    ],
    "sg:phone":"+1 260 639 6918",
    "sg:postcode":"46745",
    "sg:province":"IN",
    "sg:tags":[
        "hog",
        "or",
        "feedlot"
    ],
    "wof:name":"Terry Scott",
    "wof:placetype":"venue"
},
  "geometry": {"coordinates":[-84.958826,40.933408],"type":"Point"}
}