{
  "type": "Feature",
  "properties": {
    "iso:country":"US",
    "sg:address":"29700 Riley Rd",
    "sg:city":"North Liberty",
    "sg:phone":"+1 574 656 4663",
    "sg:postcode":"46554",
    "sg:province":"IN",
    "sg:tags":[
        "grain",
        "cash"
    ],
    "wof:name":"Millar Farms",
    "wof:placetype":"venue"
},
  "geometry": {"coordinates":[-86.43312400000001,41.505655],"type":"Point"}
}