{
  "type": "Feature",
  "properties": {
    "iso:country":"US",
    "sg:address":"1550 Stadium Dr",
    "sg:city":"Indianapolis",
    "sg:classifiers":[
        {
            "category":"Wholesale",
            "subcategory":"Machinery & Supplies",
            "type":"Manufacturing & Wholesale Goods"
        }
    ],
    "sg:phone":"+1 317 264 2131",
    "sg:postcode":"46202",
    "sg:province":"IN",
    "sg:tags":[
        "abrasive"
    ],
    "wof:name":"Tooling Technology & Supply",
    "wof:placetype":"venue"
},
  "geometry": {"coordinates":[-86.183879,39.787751],"type":"Point"}
}