{
  "type": "Feature",
  "properties": {
    "iso:country":"US",
    "sg:address":"800 N Detroit St",
    "sg:city":"Lagrange",
    "sg:classifiers":[
        {
            "category":"Professional",
            "subcategory":"Accounting & Tax Preparation",
            "type":"Services"
        }
    ],
    "sg:phone":"+1 260 463 2390",
    "sg:postcode":"46761",
    "sg:province":"IN",
    "sg:tags":[
        "accountant"
    ],
    "wof:name":"Randy D Fry CPA",
    "wof:placetype":"venue"
},
  "geometry": {"coordinates":[-85.418417,41.650789],"type":"Point"}
}