{
  "type": "Feature",
  "properties": {
    "iso:country":"US",
    "sg:address":"4794 E Harbor Ct",
    "sg:city":"Monticello",
    "sg:classifiers":[
        {
            "category":"Travel",
            "subcategory":"Hotels & Motels",
            "type":"Entertainment"
        }
    ],
    "sg:phone":"+1 574 583 6023",
    "sg:postcode":"47960",
    "sg:province":"IN",
    "sg:tags":[
        "operation"
    ],
    "wof:name":"Quiet Water Bed & Breakfast",
    "wof:placetype":"venue"
},
  "geometry": {"coordinates":[-86.778006,40.78925],"type":"Point"}
}