{
  "type": "Feature",
  "properties": {
    "addr:full":"6700 N 800 E Lafayette IN 47905",
    "addr:housenumber":"6700",
    "addr:postcode":"47905",
    "addr:street":"N 800 E",
    "iso:country":"US",
    "sg:address":"6700 N 800 E",
    "sg:city":"Lafayette",
    "sg:classifiers":[
        {
            "category":"Recreation",
            "type":"Entertainment"
        }
    ],
    "sg:phone":"+1 765 589 1775",
    "sg:postcode":"47905",
    "sg:province":"IN",
    "sg:tags":[
        "stable"
    ],
    "wof:name":"Dream Acres Farm",
    "wof:placetype":"venue"
},
  "geometry": {"coordinates":[-86.74979500000001,40.514143],"type":"Point"}
}