{
  "type": "Feature",
  "properties": {
    "iso:country":"US",
    "sg:address":"4029 E 13th Ave",
    "sg:city":"Gary",
    "sg:classifiers":[
        {
            "category":"Coffee & Tea",
            "type":"Food & Drink"
        },
        {
            "category":"Restaurant",
            "type":"Food & Drink"
        }
    ],
    "sg:phone":"+1 219 938 2659",
    "sg:postcode":"46403",
    "sg:province":"IN",
    "sg:tags":[
        "espresso"
    ],
    "wof:name":"The Soul Cafe With Valarie Renee",
    "wof:placetype":"venue"
},
  "geometry": {"coordinates":[-87.28762399999999,41.590092],"type":"Point"}
}