{
  "type": "Feature",
  "properties": {
    "iso:country":"US",
    "sg:address":"1659 Eastway Dr",
    "sg:city":"Crawfordsville",
    "sg:classifiers":[
        {
            "category":"Wholesale",
            "subcategory":"Farm Supplies",
            "type":"Manufacturing & Wholesale Goods"
        }
    ],
    "sg:phone":"+1 765 362 6047",
    "sg:postcode":"47933",
    "sg:province":"IN",
    "wof:name":"Thrifty Supply Inc",
    "wof:placetype":"venue"
},
  "geometry": {"coordinates":[-86.899722,40.024252],"type":"Point"}
}