{
  "type": "Feature",
  "properties": {
    "iso:country":"US",
    "sg:address":"8472 E 100 N",
    "sg:city":"Angola",
    "sg:classifiers":[
        {
            "category":"Building & Trades",
            "subcategory":"Construction",
            "type":"Services"
        }
    ],
    "sg:phone":"+1 260 495 3008",
    "sg:postcode":"46703",
    "sg:province":"IN",
    "sg:tags":[
        "contractor"
    ],
    "wof:name":"D L Hammond Masonry Inc",
    "wof:placetype":"venue"
},
  "geometry": {"coordinates":[-84.82378799999999,41.659691],"type":"Point"}
}