{
  "type": "Feature",
  "properties": {
    "addr:full":"7420 Stonehurst Ct Indianapolis IN 46256",
    "addr:housenumber":"7420",
    "addr:postcode":"46256",
    "addr:street":"Stonehurst Ct",
    "iso:country":"US",
    "sg:address":"7420 Stonehurst Ct",
    "sg:city":"Indianapolis",
    "sg:classifiers":[
        {
            "category":"Building & Trades",
            "subcategory":"Construction",
            "type":"Services"
        }
    ],
    "sg:phone":"+1 317 594 8879",
    "sg:postcode":"46256",
    "sg:province":"IN",
    "sg:tags":[
        "house"
    ],
    "wof:name":"Medallion Homes Inc",
    "wof:placetype":"venue"
},
  "geometry": {"coordinates":[-86.028645,39.889869],"type":"Point"}
}