{
  "type": "Feature",
  "properties": {
    "iso:country":"US",
    "sg:address":"7000 W Co Rd 700 S",
    "sg:city":"Coatesville",
    "sg:classifiers":[
        {
            "category":"Real Estate",
            "subcategory":"Surveying",
            "type":"Services"
        }
    ],
    "sg:phone":"+1 765 386 6200",
    "sg:postcode":"46121",
    "sg:province":"IN",
    "sg:tags":[
        "surveyor"
    ],
    "wof:name":"Gaston Engineering & Land Srvy",
    "wof:placetype":"venue"
},
  "geometry": {"coordinates":[-86.648872,39.659219],"type":"Point"}
}