{
  "type": "Feature",
  "properties": {
    "addr:full":"2096 S 400 W Warsaw IN 46580",
    "addr:housenumber":"2096;400",
    "addr:postcode":"46580",
    "addr:street":"S;W Warsaw",
    "iso:country":"US",
    "sg:address":"2096 S 400 W",
    "sg:city":"Warsaw",
    "sg:classifiers":[
        {
            "category":"Building & Trades",
            "subcategory":"Construction",
            "type":"Services"
        }
    ],
    "sg:phone":"+1 574 267 4998",
    "sg:postcode":"46580",
    "sg:province":"IN",
    "sg:tags":[
        "floor",
        "laying",
        "contractor"
    ],
    "wof:name":"Custom Carpet",
    "wof:placetype":"venue"
},
  "geometry": {"coordinates":[-85.918768,41.201548],"type":"Point"}
}