{
  "type": "Feature",
  "properties": {
    "addr:full":"4222 Bell Rd Newburgh IN 47630",
    "addr:housenumber":"4222",
    "addr:postcode":"47630",
    "addr:street":"Bell Rd",
    "iso:country":"US",
    "sg:address":"4222 Bell Rd",
    "sg:city":"Newburgh",
    "sg:classifiers":[
        {
            "category":"Restaurant",
            "type":"Food & Drink"
        }
    ],
    "sg:menulink":"http://www.allmenus.com/in/ohio/124463-quiznos-sub/menu/",
    "sg:phone":"+1 812 490 1144",
    "sg:postcode":"47630",
    "sg:province":"IN",
    "sg:tags":[
        "wrap",
        "american",
        "sandwich"
    ],
    "wof:name":"Quiznos Sub",
    "wof:placetype":"venue"
},
  "geometry": {"coordinates":[-87.404855,37.973719],"type":"Point"}
}