{
  "type": "Feature",
  "properties": {
    "addr:full":"9043 Crawfordsville Rd Indianapolis IN 46234",
    "addr:postcode":"9043;46234",
    "addr:street":"Crawfordsville Rd",
    "iso:country":"US",
    "sg:address":"9043 Crawfordsville Rd",
    "sg:city":"Indianapolis",
    "sg:classifiers":[
        {
            "category":"Building & Trades",
            "subcategory":"Construction",
            "type":"Services"
        }
    ],
    "sg:phone":"+1 317 291 8733",
    "sg:postcode":"46234",
    "sg:province":"IN",
    "sg:tags":[
        "tile",
        "dealer"
    ],
    "wof:name":"Jeff Tarry's Residential Tile",
    "wof:placetype":"venue"
},
  "geometry": {"coordinates":[-86.32409199999999,39.816496],"type":"Point"}
}