{
  "type": "Feature",
  "properties": {
    "iso:country":"US",
    "sg:address":"542 N Memorial Dr",
    "sg:city":"New Castle",
    "sg:classifiers":[
        {
            "category":"Banks & Credit Unions",
            "subcategory":"Bank",
            "type":"Services"
        }
    ],
    "sg:phone":"+1 765 529 7802",
    "sg:postcode":"47362",
    "sg:province":"IN",
    "sg:tags":[
        "financing"
    ],
    "wof:name":"Personal Finance Co LLC",
    "wof:placetype":"venue"
},
  "geometry": {"coordinates":[-85.383541,39.936822],"type":"Point"}
}