{
  "type": "Feature",
  "properties": {
    "addr:full":"127 N 4th St Decatur IN 46733",
    "addr:housenumber":"127",
    "addr:postcode":"46733",
    "addr:street":"N 4Th St",
    "iso:country":"US",
    "sg:address":"127 N 4th St",
    "sg:city":"Decatur",
    "sg:classifiers":[
        {
            "category":"Social Services",
            "subcategory":"Child Care",
            "type":"Services"
        }
    ],
    "sg:phone":"+1 260 724 2737",
    "sg:postcode":"46733",
    "sg:province":"IN",
    "wof:name":"Saint Joseph's Daycare",
    "wof:placetype":"venue"
},
  "geometry": {"coordinates":[-84.92682000000001,40.830781],"type":"Point"}
}