{
  "type": "Feature",
  "properties": {
    "iso:country":"US",
    "sg:address":"500 W Madison St",
    "sg:city":"Plymouth",
    "sg:classifiers":[
        {
            "category":"Recreation",
            "type":"Entertainment"
        }
    ],
    "sg:phone":"+1 574 936 4685",
    "sg:postcode":"46563",
    "sg:province":"IN",
    "sg:tags":[
        "skating",
        "rink"
    ],
    "wof:name":"Plymouth Skating Palace",
    "wof:placetype":"venue"
},
  "geometry": {"coordinates":[-86.315894,41.344135],"type":"Point"}
}