{
  "type": "Feature",
  "properties": {
    "iso:country":"US",
    "sg:address":"126 S 3rd St",
    "sg:city":"Lafayette",
    "sg:classifiers":[
        {
            "category":"Professional",
            "subcategory":"Management & Consulting",
            "type":"Services"
        }
    ],
    "sg:phone":"+1 765 423 4400",
    "sg:postcode":"47901",
    "sg:province":"IN",
    "sg:tags":[
        "construction"
    ],
    "wof:name":"A & K Commercial Development",
    "wof:placetype":"venue"
},
  "geometry": {"coordinates":[-86.894244,40.416422],"type":"Point"}
}