{
  "type": "Feature",
  "properties": {
    "iso:country":"US",
    "sg:address":"1315 N Fares Ave",
    "sg:city":"Evansville",
    "sg:classifiers":[
        {
            "category":"Wholesale",
            "subcategory":"Machinery & Supplies",
            "type":"Manufacturing & Wholesale Goods"
        }
    ],
    "sg:phone":"+1 812 425 8426",
    "sg:postcode":"47711",
    "sg:province":"IN",
    "sg:tags":[
        "equipment",
        "labeling"
    ],
    "wof:name":"Tri-State Addressing Machine",
    "wof:placetype":"venue"
},
  "geometry": {"coordinates":[-87.54286,37.989083],"type":"Point"}
}