{
  "type": "Feature",
  "properties": {
    "iso:country":"US",
    "sg:address":"5552 E 400 N",
    "sg:city":"Portland",
    "sg:classifiers":[
        {
            "category":"Farming",
            "subcategory":"Farm",
            "type":"Manufacturing & Wholesale Goods"
        }
    ],
    "sg:phone":"+1 260 726 6679",
    "sg:postcode":"47371",
    "sg:province":"IN",
    "wof:name":"D & M Farms",
    "wof:placetype":"venue"
},
  "geometry": {"coordinates":[-84.86596,40.498947],"type":"Point"}
}