{
  "type": "Feature",
  "properties": {
    "iso:country":"US",
    "sg:address":"1149 N National Rd",
    "sg:city":"Columbus",
    "sg:classifiers":[
        {
            "category":"Shopping",
            "subcategory":"Hobbies, Toys, & Games",
            "type":"Retail Goods"
        }
    ],
    "sg:phone":"+1 812 379 4972",
    "sg:postcode":"47201",
    "sg:province":"IN",
    "sg:tags":[
        "craft",
        "supply"
    ],
    "sg:website":"www.hobbylobby.com",
    "wof:name":"Hobby Lobby Creative Ctr",
    "wof:placetype":"venue"
},
  "geometry": {"coordinates":[-85.877967,39.211079],"type":"Point"}
}