{
  "type": "Feature",
  "properties": {
    "iso:country":"US",
    "sg:address":"209 E Michigan Blvd",
    "sg:city":"Michigan City",
    "sg:classifiers":[
        {
            "category":"Museum",
            "type":"Entertainment"
        }
    ],
    "sg:phone":"+1 219 878 1514",
    "sg:postcode":"46360",
    "sg:province":"IN",
    "wof:name":"Ragtops Automobile Museumof",
    "wof:placetype":"venue"
},
  "geometry": {"coordinates":[-86.900215,41.720363],"type":"Point"}
}