{
  "type": "Feature",
  "properties": {
    "iso:country":"US",
    "sg:address":"450 E 96th St",
    "sg:city":"Indianapolis",
    "sg:classifiers":[
        {
            "category":"Health Services",
            "subcategory":"Health Practitioner",
            "type":"Services"
        }
    ],
    "sg:phone":"+1 317 581 6263",
    "sg:postcode":"46240",
    "sg:province":"IN",
    "sg:tags":[
        "nurse",
        "registry"
    ],
    "wof:name":"On Assignment",
    "wof:placetype":"venue"
},
  "geometry": {"coordinates":[-86.148657,39.927206],"type":"Point"}
}