{
  "type": "Feature",
  "properties": {
    "iso:country":"US",
    "sg:address":"165 W Muskegon Dr",
    "sg:city":"Greenfield",
    "sg:classifiers":[
        {
            "category":"Retail",
            "subcategory":"Auto Rental",
            "type":"Services"
        }
    ],
    "sg:phone":"+1 317 467 1903",
    "sg:postcode":"46140",
    "sg:province":"IN",
    "sg:tags":[
        "renting",
        "automobile"
    ],
    "wof:name":"Enterprise Rent-A-Car",
    "wof:placetype":"venue"
},
  "geometry": {"coordinates":[-85.771183,39.810308],"type":"Point"}
}