{
  "type": "Feature",
  "properties": {
    "addr:full":"4755 N Post Rd Indianapolis IN 46226",
    "addr:housenumber":"4755",
    "addr:postcode":"46226",
    "addr:street":"N Post Rd",
    "iso:country":"US",
    "sg:address":"4755 N Post Rd",
    "sg:city":"Indianapolis",
    "sg:classifiers":[
        {
            "category":"Professional",
            "subcategory":"Accounting & Tax Preparation",
            "type":"Services"
        }
    ],
    "sg:phone":"+1 317 897 9406",
    "sg:postcode":"46226",
    "sg:province":"IN",
    "sg:tags":[
        "return"
    ],
    "wof:name":"H & R Block",
    "wof:placetype":"venue"
},
  "geometry": {"coordinates":[-86.01016,39.843764],"type":"Point"}
}