{
  "type": "Feature",
  "properties": {
    "iso:country":"US",
    "sg:address":"1213 W Miller St",
    "sg:city":"Clinton",
    "sg:classifiers":[
        {
            "category":"Professional",
            "subcategory":"Business Services",
            "type":"Services"
        },
        {
            "category":"Education",
            "subcategory":"School",
            "type":"Public Place"
        }
    ],
    "sg:phone":"+1 765 832 3541",
    "sg:postcode":"47842",
    "sg:province":"IN",
    "sg:tags":[
        "lecture",
        "bureau",
        "seminar"
    ],
    "wof:name":"Professional Seminars Med",
    "wof:placetype":"venue"
},
  "geometry": {"coordinates":[-87.413715,39.672269],"type":"Point"}
}