{
  "type": "Feature",
  "properties": {
    "addr:full":"1106 Meridian St Anderson IN 46016",
    "addr:housenumber":"1106",
    "addr:postcode":"46016",
    "addr:street":"Meridian St",
    "iso:country":"US",
    "sg:address":"1106 Meridian St",
    "sg:city":"Anderson",
    "sg:classifiers":[
        {
            "category":"Professional",
            "subcategory":"Lawyer & Legal Services",
            "type":"Services"
        }
    ],
    "sg:phone":"+1 765 646 6076",
    "sg:postcode":"46016",
    "sg:province":"IN",
    "sg:tags":[
        "attorney"
    ],
    "wof:name":"UAW-Gm Legal Svc Plan",
    "wof:placetype":"venue"
},
  "geometry": {"coordinates":[-85.67913799999999,40.10418],"type":"Point"}
}