{
  "type": "Feature",
  "properties": {
    "iso:country":"US",
    "sg:address":"3731 Guion Rd",
    "sg:city":"Indianapolis",
    "sg:classifiers":[
        {
            "category":"Health Services",
            "subcategory":"Doctor",
            "type":"Services"
        }
    ],
    "sg:phone":"+1 317 925 6553",
    "sg:postcode":"46222",
    "sg:province":"IN",
    "sg:tags":[
        "physician",
        "surgeon"
    ],
    "wof:name":"Guion Family Practice",
    "wof:placetype":"venue"
},
  "geometry": {"coordinates":[-86.22105999999999,39.82232],"type":"Point"}
}