{
  "type": "Feature",
  "properties": {
    "iso:country":"US",
    "sg:address":"715 E Maumee St",
    "sg:city":"Angola",
    "sg:classifiers":[
        {
            "category":"Autos & Motor Vehicles",
            "subcategory":"Automobile Sales",
            "type":"Retail Goods"
        }
    ],
    "sg:phone":"+1 260 665 1000",
    "sg:postcode":"46703",
    "sg:province":"IN",
    "sg:tags":[
        "car",
        "dealer"
    ],
    "wof:name":"Corkle Auto Sales Inc",
    "wof:placetype":"venue"
},
  "geometry": {"coordinates":[-84.99103700000001,41.63504],"type":"Point"}
}