{
  "type": "Feature",
  "properties": {
    "iso:country":"US",
    "sg:address":"303 S Nappanee St",
    "sg:city":"Elkhart",
    "sg:classifiers":[
        {
            "category":"Health Services",
            "subcategory":"Health Practitioner",
            "type":"Services"
        }
    ],
    "sg:phone":"+1 574 206 8800",
    "sg:postcode":"46514",
    "sg:province":"IN",
    "wof:name":"Karyn Macneil",
    "wof:placetype":"venue"
},
  "geometry": {"coordinates":[-86.003393,41.681609],"type":"Point"}
}