{
  "type": "Feature",
  "properties": {
    "iso:country":"US",
    "sg:address":"3025 N Saint Joseph Ave",
    "sg:city":"Evansville",
    "sg:classifiers":[
        {
            "category":"Food & Beverages",
            "subcategory":"Groceries & Convenience Stores",
            "type":"Retail Goods"
        }
    ],
    "sg:phone":"+1 812 425 3786",
    "sg:postcode":"47720",
    "sg:province":"IN",
    "wof:name":"Always Open Gas Marts",
    "wof:placetype":"venue"
},
  "geometry": {"coordinates":[-87.599836,38.007274],"type":"Point"}
}