{
  "type": "Feature",
  "properties": {
    "iso:country":"US",
    "sg:address":"1282 W Indiana St",
    "sg:city":"Kouts",
    "sg:classifiers":[
        {
            "category":"Shopping",
            "subcategory":"Florist",
            "type":"Retail Goods"
        }
    ],
    "sg:phone":"+1 219 766 3601",
    "sg:postcode":"46347",
    "sg:province":"IN",
    "sg:tags":[
        "farm",
        "supply"
    ],
    "wof:name":"Heinigers Seed Flral Grnhouses",
    "wof:placetype":"venue"
},
  "geometry": {"coordinates":[-87.03736499999999,41.3184],"type":"Point"}
}