{
  "type": "Feature",
  "properties": {
    "iso:country":"US",
    "sg:address":"4754 N Co Rd 200 E",
    "sg:city":"Orleans",
    "sg:classifiers":[
        {
            "category":"Professional",
            "subcategory":"Business Services",
            "type":"Services"
        }
    ],
    "sg:phone":"+1 812 865 2364",
    "sg:postcode":"47452",
    "sg:province":"IN",
    "sg:tags":[
        "auctioneer"
    ],
    "wof:name":"Robinson Auction Svc",
    "wof:placetype":"venue"
},
  "geometry": {"coordinates":[-86.420608,38.626015],"type":"Point"}
}