{
  "type": "Feature",
  "properties": {
    "addr:full":"2205 N Jefferson St Huntington IN 46750",
    "addr:housenumber":"2205",
    "addr:postcode":"46750",
    "addr:street":"N Jefferson",
    "iso:country":"US",
    "sg:address":"2205 N Jefferson St",
    "sg:city":"Huntington",
    "sg:classifiers":[
        {
            "category":"Travel",
            "subcategory":"Hotels & Motels",
            "type":"Entertainment"
        }
    ],
    "sg:phone":"+1 260 359 0583",
    "sg:postcode":"46750",
    "sg:province":"IN",
    "wof:name":"Comfort Inn",
    "wof:placetype":"venue"
},
  "geometry": {"coordinates":[-85.507119,40.894707],"type":"Point"}
}