{
  "type": "Feature",
  "properties": {
    "iso:country":"US",
    "sg:address":"359 E Main St",
    "sg:city":"Mooresville",
    "sg:classifiers":[
        {
            "category":"Building & Trades",
            "subcategory":"Equipment Rental",
            "type":"Services"
        }
    ],
    "sg:phone":"+1 317 834 0524",
    "sg:postcode":"46158",
    "sg:province":"IN",
    "sg:tags":[
        "party",
        "supply"
    ],
    "wof:name":"Great Day Party Rental",
    "wof:placetype":"venue"
},
  "geometry": {"coordinates":[-86.36576,39.612779],"type":"Point"}
}