{
  "type": "Feature",
  "properties": {
    "iso:country":"US",
    "sg:address":"504 Rainbow Dr",
    "sg:city":"Kokomo",
    "sg:classifiers":[
        {
            "category":"Building & Trades",
            "subcategory":"Landscaping Services",
            "type":"Services"
        }
    ],
    "sg:phone":"+1 765 864 0065",
    "sg:postcode":"46902",
    "sg:province":"IN",
    "sg:tags":[
        "lawn",
        "maintenance",
        "grounds"
    ],
    "wof:name":"Mitchell Lawn & Landscape Inc",
    "wof:placetype":"venue"
},
  "geometry": {"coordinates":[-86.126891,40.449804],"type":"Point"}
}