{
  "type": "Feature",
  "properties": {
    "iso:country":"US",
    "sg:address":"453 Bell Flower Rd",
    "sg:city":"Valparaiso",
    "sg:classifiers":[
        {
            "category":"Professional",
            "type":"Services"
        }
    ],
    "sg:phone":"+1 219 464 0990",
    "sg:postcode":"46383",
    "sg:province":"IN",
    "wof:name":"Hart Transfer Inc",
    "wof:placetype":"venue"
},
  "geometry": {"coordinates":[-86.973706,41.542583],"type":"Point"}
}