{
  "type": "Feature",
  "properties": {
    "iso:country":"US",
    "sg:address":"3418 Gander Dr",
    "sg:city":"Jeffersonville",
    "sg:classifiers":[
        {
            "category":"Professional",
            "subcategory":"Business Services",
            "type":"Services"
        }
    ],
    "sg:phone":"+1 812 284 5913",
    "sg:postcode":"47130",
    "sg:province":"IN",
    "wof:name":"Wlg Sales",
    "wof:placetype":"venue"
},
  "geometry": {"coordinates":[-85.726247,38.327753],"type":"Point"}
}