{
  "type": "Feature",
  "properties": {
    "iso:country":"US",
    "sg:address":"584 Roosevelt St",
    "sg:city":"Gary",
    "sg:classifiers":[
        {
            "category":"Arts & Performance",
            "subcategory":"Theater",
            "type":"Entertainment"
        }
    ],
    "sg:phone":"+1 219 883 0663",
    "sg:postcode":"46404",
    "sg:province":"IN",
    "sg:tags":[
        "bureau"
    ],
    "wof:name":"Play Time Entertainment",
    "wof:placetype":"venue"
},
  "geometry": {"coordinates":[-87.364265,41.601117],"type":"Point"}
}