{
  "type": "Feature",
  "properties": {
    "addr:full":"106 W Pike St Vevay IN 47043",
    "addr:housenumber":"106",
    "addr:postcode":"47043",
    "addr:street":"W Pike St",
    "iso:country":"US",
    "sg:address":"106 W Pike St",
    "sg:city":"Vevay",
    "sg:classifiers":[
        {
            "category":"Personal",
            "subcategory":"Beauty Salon",
            "type":"Services"
        }
    ],
    "sg:phone":"+1 812 427 2177",
    "sg:postcode":"47043",
    "sg:province":"IN",
    "sg:tags":[
        "shop"
    ],
    "wof:name":"Nail Salon",
    "wof:placetype":"venue"
},
  "geometry": {"coordinates":[-85.068067,38.748506],"type":"Point"}
}