{
  "type": "Feature",
  "properties": {
    "addr:full":"8949 US Hwy 421 Napoleon IN 47037",
    "addr:housenumber":"8949",
    "addr:postcode":"47037",
    "addr:street":"Us Hwy 421 Napoleon",
    "iso:country":"US",
    "sg:address":"8949 US Hwy 421",
    "sg:city":"Napoleon",
    "sg:classifiers":[
        {
            "category":"Government",
            "subcategory":"Post Office",
            "type":"Public Place"
        }
    ],
    "sg:phone":"+1 812 000 1111",
    "sg:postcode":"47037",
    "sg:province":"IN",
    "wof:name":"US Post Office",
    "wof:placetype":"venue"
},
  "geometry": {"coordinates":[-85.330708,39.205245],"type":"Point"}
}