{
  "type": "Feature",
  "properties": {
    "iso:country":"US",
    "sg:address":"2735 E Buttonwood Ln",
    "sg:city":"Bloomington",
    "sg:classifiers":[
        {
            "category":"Building & Trades",
            "subcategory":"Construction",
            "type":"Services"
        }
    ],
    "sg:phone":"+1 812 336 2617",
    "sg:postcode":"47401",
    "sg:province":"IN",
    "sg:tags":[
        "nonresidential"
    ],
    "wof:name":"Al Vlasman Construction Inc",
    "wof:placetype":"venue"
},
  "geometry": {"coordinates":[-86.497085,39.139299],"type":"Point"}
}