{
  "type": "Feature",
  "properties": {
    "iso:country":"US",
    "sg:address":"5240 State Rd 28 E",
    "sg:city":"Lafayette",
    "sg:classifiers":[
        {
            "category":"Wholesale",
            "subcategory":"Hardware",
            "type":"Manufacturing & Wholesale Goods"
        }
    ],
    "sg:phone":"+1 765 523 2226",
    "sg:postcode":"47909",
    "sg:province":"IN",
    "sg:tags":[
        "refrigerating"
    ],
    "wof:name":"RMC Inc",
    "wof:placetype":"venue"
},
  "geometry": {"coordinates":[-86.804893,40.258432],"type":"Point"}
}