{
  "type": "Feature",
  "properties": {
    "iso:country":"US",
    "sg:address":"235 S Michigan St",
    "sg:city":"South Bend",
    "sg:classifiers":[
        {
            "category":"Restaurant",
            "type":"Food & Drink"
        }
    ],
    "sg:phone":"+1 574 289 3333",
    "sg:postcode":"46601",
    "sg:province":"IN",
    "wof:name":"O'Sullivans Crossing",
    "wof:placetype":"venue"
},
  "geometry": {"coordinates":[-86.250399,41.674835],"type":"Point"}
}