{
  "type": "Feature",
  "properties": {
    "iso:country":"US",
    "sg:address":"2302 W 86th St",
    "sg:city":"Indianapolis",
    "sg:classifiers":[
        {
            "category":"Food & Beverages",
            "subcategory":"Supermarket",
            "type":"Retail Goods"
        }
    ],
    "sg:phone":"+1 317 875 8468",
    "sg:postcode":"46260",
    "sg:province":"IN",
    "sg:tags":[
        "super",
        "store"
    ],
    "wof:name":"New Albertson's, Inc.",
    "wof:placetype":"venue"
},
  "geometry": {"coordinates":[-86.201684,39.912026],"type":"Point"}
}