{
  "type": "Feature",
  "properties": {
    "iso:country":"US",
    "sg:address":"980 W US Hwy 30",
    "sg:city":"Schererville",
    "sg:classifiers":[
        {
            "category":"Restaurant",
            "type":"Food & Drink"
        }
    ],
    "sg:phone":"+1 219 322 2266",
    "sg:postcode":"46375",
    "sg:province":"IN",
    "wof:name":"Culver's Of Schererville",
    "wof:placetype":"venue"
},
  "geometry": {"coordinates":[-87.477468,41.490902],"type":"Point"}
}