{
  "type": "Feature",
  "properties": {
    "iso:country":"US",
    "sg:address":"9745 Randall Dr",
    "sg:city":"Indianapolis",
    "sg:classifiers":[
        {
            "category":"Retail",
            "subcategory":"Veterinary Services",
            "type":"Services"
        }
    ],
    "sg:phone":"+1 317 324 1116",
    "sg:postcode":"46280",
    "sg:province":"IN",
    "sg:tags":[
        "specialty"
    ],
    "sg:website":"http://www.vcahospitals.com",
    "wof:name":"Vca Specialty Animal Hospitals",
    "wof:placetype":"venue"
},
  "geometry": {"coordinates":[-86.095793,39.927036],"type":"Point"}
}