{
  "type": "Feature",
  "properties": {
    "iso:country":"US",
    "sg:address":"107 N Washington Ave",
    "sg:city":"Fowler",
    "sg:classifiers":[
        {
            "category":"Government",
            "subcategory":"Fire Station",
            "type":"Public Place"
        }
    ],
    "sg:phone":"+1 765 884 8011",
    "sg:postcode":"47944",
    "sg:province":"IN",
    "sg:tags":[
        "department"
    ],
    "wof:name":"Fowler Fire Dept",
    "wof:placetype":"venue"
},
  "geometry": {"coordinates":[-87.323392,40.61858],"type":"Point"}
}