{
  "type": "Feature",
  "properties": {
    "iso:country":"US",
    "sg:address":"15 S Main St",
    "sg:city":"Sullivan",
    "sg:classifiers":[
        {
            "category":"Banks & Credit Unions",
            "subcategory":"Bank",
            "type":"Services"
        }
    ],
    "sg:phone":"+1 812 268 3331",
    "sg:postcode":"47882",
    "sg:province":"IN",
    "sg:tags":[
        "saving",
        "commercial"
    ],
    "sg:website":"http://www.first-online.com",
    "wof:name":"Farmers State Bank Of Sul",
    "wof:placetype":"venue"
},
  "geometry": {"coordinates":[-87.40704700000001,39.095258],"type":"Point"}
}