{
  "type": "Feature",
  "properties": {
    "iso:country":"US",
    "sg:address":"14108 State Rd 101",
    "sg:city":"Brookville",
    "sg:classifiers":[
        {
            "category":"Government",
            "subcategory":"Office",
            "type":"Public Place"
        }
    ],
    "sg:phone":"+1 765 647 5755",
    "sg:postcode":"47012",
    "sg:province":"IN",
    "sg:tags":[
        "state"
    ],
    "wof:name":"Natural Resources-Svc Building",
    "wof:placetype":"venue"
},
  "geometry": {"coordinates":[-84.948787,39.487224],"type":"Point"}
}