{
  "type": "Feature",
  "properties": {
    "iso:country":"US",
    "sg:address":"1500 Ann St",
    "sg:city":"Kokomo",
    "sg:classifiers":[
        {
            "category":"Manufacturing",
            "subcategory":"Metals",
            "type":"Manufacturing & Wholesale Goods"
        }
    ],
    "sg:phone":"+1 765 457 0223",
    "sg:postcode":"46901",
    "sg:province":"IN",
    "sg:website":"www.mierproducts.com",
    "wof:name":"Mier Products Inc",
    "wof:placetype":"venue"
},
  "geometry": {"coordinates":[-86.13149799999999,40.500356],"type":"Point"}
}