{
  "type": "Feature",
  "properties": {
    "iso:country":"US",
    "sg:address":"110 N 15th St",
    "sg:city":"Vincennes",
    "sg:classifiers":[
        {
            "category":"Health Services",
            "subcategory":"Clinic",
            "type":"Services"
        }
    ],
    "sg:phone":"+1 812 886 0188",
    "sg:postcode":"47591",
    "sg:province":"IN",
    "sg:tags":[
        "home"
    ],
    "wof:name":"Friends Home Health Care",
    "wof:placetype":"venue"
},
  "geometry": {"coordinates":[-87.519654,38.669969],"type":"Point"}
}