{
  "type": "Feature",
  "properties": {
    "iso:country":"US",
    "sg:address":"120 W 3rd St",
    "sg:city":"Madison",
    "sg:classifiers":[
        {
            "category":"Organizations",
            "subcategory":"Non-profit Organization",
            "type":"Services"
        }
    ],
    "sg:phone":"+1 812 265 2412",
    "sg:postcode":"47250",
    "sg:province":"IN",
    "wof:name":"Hutchings Office",
    "wof:placetype":"venue"
},
  "geometry": {"coordinates":[-85.381348,38.737725],"type":"Point"}
}