{
  "type": "Feature",
  "properties": {
    "iso:country":"US",
    "sg:address":"4986 E White Point Dr",
    "sg:city":"Monticello",
    "sg:classifiers":[
        {
            "category":"Bars & Pubs",
            "type":"Food & Drink"
        }
    ],
    "sg:phone":"+1 574 583 8200",
    "sg:postcode":"47960",
    "sg:province":"IN",
    "wof:name":"Sayler's Bar & Grill",
    "wof:placetype":"venue"
},
  "geometry": {"coordinates":[-86.77802800000001,40.789484],"type":"Point"}
}