{
  "type": "Feature",
  "properties": {
    "iso:country":"US",
    "sg:address":"8620 Driftwood Dr",
    "sg:city":"Indianapolis",
    "sg:classifiers":[
        {
            "category":"Personal",
            "subcategory":"Beauty Salon",
            "type":"Services"
        }
    ],
    "sg:phone":"+1 317 581 9388",
    "sg:postcode":"46240",
    "sg:province":"IN",
    "sg:tags":[
        "cosmetologist"
    ],
    "wof:name":"Tammy L Fife",
    "wof:placetype":"venue"
},
  "geometry": {"coordinates":[-86.118909,39.915211],"type":"Point"}
}