{
  "type": "Feature",
  "properties": {
    "iso:country":"US",
    "sg:address":"4101 Edison Lakes Pkwy",
    "sg:city":"Mishawaka",
    "sg:classifiers":[
        {
            "category":"Professional",
            "subcategory":"Accounting & Tax Preparation",
            "type":"Services"
        }
    ],
    "sg:phone":"+1 574 272 7700",
    "sg:postcode":"46545",
    "sg:province":"IN",
    "wof:name":"Pricewaterhousecoopers LLP",
    "wof:placetype":"venue"
},
  "geometry": {"coordinates":[-86.176457,41.696506],"type":"Point"}
}