{
  "type": "Feature",
  "properties": {
    "iso:country":"US",
    "sg:address":"6013 Andy Way",
    "sg:city":"Bloomington",
    "sg:classifiers":[
        {
            "category":"Organizations",
            "subcategory":"Non-profit Organization",
            "type":"Services"
        }
    ],
    "sg:phone":"+1 812 876 3742",
    "sg:postcode":"47404",
    "sg:province":"IN",
    "sg:tags":[
        "medical",
        "management"
    ],
    "wof:name":"Yellowwood Medical Claims Inc",
    "wof:placetype":"venue"
},
  "geometry": {"coordinates":[-86.587411,39.201429],"type":"Point"}
}