{
  "type": "Feature",
  "properties": {
    "iso:country":"US",
    "sg:address":"40 Valdez Ct",
    "sg:city":"Lafayette",
    "sg:classifiers":[
        {
            "category":"Food & Beverages",
            "subcategory":"Specialty",
            "type":"Retail Goods"
        }
    ],
    "sg:phone":"+1 765 448 9712",
    "sg:postcode":"47905",
    "sg:province":"IN",
    "wof:name":"Shaklee Authorized Distrs",
    "wof:placetype":"venue"
},
  "geometry": {"coordinates":[-86.845328,40.437864],"type":"Point"}
}