{
  "type": "Feature",
  "properties": {
    "addr:full":"6919 E 10th St Indianapolis IN 46219",
    "addr:housenumber":"6919",
    "addr:postcode":"46219",
    "addr:street":"E 10Th St",
    "iso:country":"US",
    "sg:address":"6919 E 10th St",
    "sg:city":"Indianapolis",
    "sg:classifiers":[
        {
            "category":"Professional",
            "subcategory":"Accounting & Tax Preparation",
            "type":"Services"
        }
    ],
    "sg:phone":"+1 317 356 6348",
    "sg:postcode":"46219",
    "sg:province":"IN",
    "sg:tags":[
        "bookkeeping",
        "general"
    ],
    "sg:website":"www.matrixaccounting.com",
    "wof:name":"Matrix Accounting & Business",
    "wof:placetype":"venue"
},
  "geometry": {"coordinates":[-86.04570200000001,39.781678],"type":"Point"}
}