{
  "type": "Feature",
  "properties": {
    "addr:full":"5467 US Hwy 6 Portage IN 46368",
    "addr:housenumber":"5467",
    "addr:postcode":"46368",
    "addr:street":"Us Hwy 6",
    "iso:country":"US",
    "sg:address":"5467 US Hwy 6",
    "sg:city":"Portage",
    "sg:classifiers":[
        {
            "category":"Autos & Motor Vehicles",
            "subcategory":"Auto Supplies",
            "type":"Retail Goods"
        }
    ],
    "sg:phone":"+1 219 763 9600",
    "sg:postcode":"46368",
    "sg:province":"IN",
    "sg:tags":[
        "wheel",
        "cover"
    ],
    "wof:name":"Karmic Wheels Inc",
    "wof:placetype":"venue"
},
  "geometry": {"coordinates":[-87.20271700000001,41.550526],"type":"Point"}
}