{
  "type": "Feature",
  "properties": {
    "iso:country":"US",
    "sg:address":"1205 W 11th St",
    "sg:city":"Connersville",
    "sg:classifiers":[
        {
            "category":"Social Services",
            "subcategory":"Child Care",
            "type":"Services"
        }
    ],
    "sg:phone":"+1 765 827 4591",
    "sg:postcode":"47331",
    "sg:province":"IN",
    "wof:name":"Sherry's Sunshine Child Care",
    "wof:placetype":"venue"
},
  "geometry": {"coordinates":[-85.152296,39.649004],"type":"Point"}
}