{
  "type": "Feature",
  "properties": {
    "iso:country":"US",
    "sg:address":"1014 State Rd 1",
    "sg:city":"Butler",
    "sg:classifiers":[
        {
            "category":"Farming",
            "subcategory":"Farm",
            "type":"Manufacturing & Wholesale Goods"
        }
    ],
    "sg:phone":"+1 260 868 5211",
    "sg:postcode":"46721",
    "sg:province":"IN",
    "sg:tags":[
        "crop",
        "general"
    ],
    "wof:name":"Noah Graber Farm",
    "wof:placetype":"venue"
},
  "geometry": {"coordinates":[-84.872818,41.497561],"type":"Point"}
}