{
  "type": "Feature",
  "properties": {
    "addr:full":"15009 N Gray Rd Noblesville IN 46062",
    "addr:housenumber":"15009",
    "addr:postcode":"46062",
    "addr:street":"N Gray Rd",
    "iso:country":"US",
    "sg:address":"15009 N Gray Rd",
    "sg:city":"Noblesville",
    "sg:classifiers":[
        {
            "category":"Wholesale",
            "subcategory":"Fruits & Vegetables",
            "type":"Manufacturing & Wholesale Goods"
        }
    ],
    "sg:phone":"+1 317 580 1517",
    "sg:postcode":"46062",
    "sg:province":"IN",
    "sg:tags":[
        "veggie"
    ],
    "wof:name":"Broccoli Bill's",
    "wof:placetype":"venue"
},
  "geometry": {"coordinates":[-86.08967699999999,40.006377],"type":"Point"}
}