{
  "type": "Feature",
  "properties": {
    "iso:country":"US",
    "sg:address":"301 S High St",
    "sg:city":"West Lebanon",
    "sg:classifiers":[
        {
            "category":"Wholesale",
            "subcategory":"Farm Supplies",
            "type":"Manufacturing & Wholesale Goods"
        }
    ],
    "sg:phone":"+1 765 893 4700",
    "sg:postcode":"47991",
    "sg:province":"IN",
    "sg:tags":[
        "fertilizer"
    ],
    "wof:name":"UAP Richter",
    "wof:placetype":"venue"
},
  "geometry": {"coordinates":[-87.386698,40.269463],"type":"Point"}
}