{
  "type": "Feature",
  "properties": {
    "iso:country":"US",
    "sg:address":"2045 S Wabash St",
    "sg:city":"Wabash",
    "sg:classifiers":[
        {
            "category":"Wholesale",
            "subcategory":"Machinery & Supplies",
            "type":"Manufacturing & Wholesale Goods"
        }
    ],
    "sg:phone":"+1 260 563 0672",
    "sg:postcode":"46992",
    "sg:province":"IN",
    "sg:tags":[
        "farm",
        "equipment"
    ],
    "sg:website":"www.agrochem.com",
    "wof:name":"Agro-Chem",
    "wof:placetype":"venue"
},
  "geometry": {"coordinates":[-85.819523,40.777015],"type":"Point"}
}