{
  "type": "Feature",
  "properties": {
    "iso:country":"US",
    "sg:address":"5201 Madison Ave",
    "sg:city":"Indianapolis",
    "sg:classifiers":[
        {
            "category":"Wholesale",
            "subcategory":"Auto Parts",
            "type":"Manufacturing & Wholesale Goods"
        }
    ],
    "sg:phone":"+1 317 783 3434",
    "sg:postcode":"46227",
    "sg:province":"IN",
    "sg:tags":[
        "truck",
        "accessory"
    ],
    "sg:website":"www.trucknvan.com",
    "wof:name":"Truck'n Van",
    "wof:placetype":"venue"
},
  "geometry": {"coordinates":[-86.135548,39.689961],"type":"Point"}
}