{
  "type": "Feature",
  "properties": {
    "addr:full":"2812 E Jefferson Blvd South Bend IN 46615",
    "addr:housenumber":"2812",
    "addr:postcode":"46615",
    "addr:street":"E Jefferson Blvd",
    "iso:country":"US",
    "sg:address":"2812 E Jefferson Blvd",
    "sg:city":"South Bend",
    "sg:classifiers":[
        {
            "category":"Insurance",
            "subcategory":"Insurance Agent",
            "type":"Services"
        }
    ],
    "sg:phone":"+1 574 289 5178",
    "sg:postcode":"46615",
    "sg:province":"IN",
    "wof:name":"Dodd Insurance",
    "wof:placetype":"venue"
},
  "geometry": {"coordinates":[-86.206992,41.672852],"type":"Point"}
}