{
  "type": "Feature",
  "properties": {
    "iso:country":"US",
    "sg:address":"203 S Tekoppel Ave",
    "sg:city":"Evansville",
    "sg:classifiers":[
        {
            "category":"Building & Trades",
            "subcategory":"Construction",
            "type":"Services"
        }
    ],
    "sg:phone":"+1 812 423 4556",
    "sg:postcode":"47712",
    "sg:province":"IN",
    "sg:tags":[
        "equipment",
        "installation"
    ],
    "wof:name":"Berrys Automatic Door Service",
    "wof:placetype":"venue"
},
  "geometry": {"coordinates":[-87.619086,37.97416],"type":"Point"}
}