{
  "type": "Feature",
  "properties": {
    "iso:country":"US",
    "sg:address":"4878 E 450N",
    "sg:city":"Dubois",
    "sg:classifiers":[
        {
            "category":"Professional",
            "type":"Services"
        }
    ],
    "sg:phone":"+1 812 678 3471",
    "sg:postcode":"47527",
    "sg:province":"IN",
    "sg:tags":[
        "establishment"
    ],
    "wof:name":"Wabash Breaking Div",
    "wof:placetype":"venue"
},
  "geometry": {"coordinates":[-86.816553,38.445709],"type":"Point"}
}