{
  "type": "Feature",
  "properties": {
    "iso:country":"US",
    "sg:address":"1223 N 11th St",
    "sg:city":"Vincennes",
    "sg:classifiers":[
        {
            "category":"Professional",
            "subcategory":"Business Services",
            "type":"Services"
        }
    ],
    "sg:phone":"+1 812 886 5399",
    "sg:postcode":"47591",
    "sg:province":"IN",
    "wof:name":"International Assoc of FI",
    "wof:placetype":"venue"
},
  "geometry": {"coordinates":[-87.514512,38.67952],"type":"Point"}
}