{
  "type": "Feature",
  "properties": {
    "addr:full":"25248 Aqua Dr Elkhart IN 46514",
    "addr:postcode":"25248;46514",
    "addr:street":"Aqua Dr",
    "iso:country":"US",
    "sg:address":"25248 Aqua Dr",
    "sg:city":"Elkhart",
    "sg:classifiers":[
        {
            "category":"Building & Trades",
            "subcategory":"Plumbing",
            "type":"Services"
        }
    ],
    "sg:phone":"+1 574 206 8967",
    "sg:postcode":"46514",
    "sg:province":"IN",
    "sg:tags":[
        "contractor"
    ],
    "wof:name":"Advanced Energy Services Inc",
    "wof:placetype":"venue"
},
  "geometry": {"coordinates":[-85.94364899999999,41.748476],"type":"Point"}
}