{
  "type": "Feature",
  "properties": {
    "iso:country":"US",
    "sg:address":"6554 Fountain Springs Blvd",
    "sg:city":"Indianapolis",
    "sg:classifiers":[
        {
            "category":"Real Estate",
            "subcategory":"Real Estate Agent",
            "type":"Services"
        }
    ],
    "sg:phone":"+1 317 823 0242",
    "sg:postcode":"46236",
    "sg:province":"IN",
    "wof:name":"Latonia Smith Realty",
    "wof:placetype":"venue"
},
  "geometry": {"coordinates":[-85.991568,39.873938],"type":"Point"}
}