{
  "type": "Feature",
  "properties": {
    "addr:full":"10260 E State Rd 46 Columbus IN 47203",
    "addr:housenumber":"10260;46",
    "addr:postcode":"47203",
    "addr:street":"E State Rd",
    "iso:country":"US",
    "sg:address":"10260 E State Rd 46",
    "sg:city":"Columbus",
    "sg:classifiers":[
        {
            "category":"Building & Trades",
            "subcategory":"Landscaping Services",
            "type":"Services"
        }
    ],
    "sg:phone":"+1 812 579 5702",
    "sg:postcode":"47203",
    "sg:province":"IN",
    "sg:tags":[
        "tree"
    ],
    "wof:name":"Frank's Tree Svc",
    "wof:placetype":"venue"
},
  "geometry": {"coordinates":[-85.80663800000001,39.224766],"type":"Point"}
}