{
  "type": "Feature",
  "properties": {
    "addr:full":"3904 S Hoyt Ave Muncie IN 47302",
    "addr:housenumber":"3904",
    "addr:postcode":"47302",
    "addr:street":"S Hoyt Ave",
    "iso:country":"US",
    "sg:address":"3904 S Hoyt Ave",
    "sg:city":"Muncie",
    "sg:classifiers":[
        {
            "category":"Manufacturing",
            "subcategory":"Tools & Machinery",
            "type":"Manufacturing & Wholesale Goods"
        }
    ],
    "sg:phone":"+1 765 282 1515",
    "sg:postcode":"47302",
    "sg:province":"IN",
    "sg:tags":[
        "machine",
        "shop"
    ],
    "wof:name":"Kendon Corp",
    "wof:placetype":"venue"
},
  "geometry": {"coordinates":[-85.427251,40.156667],"type":"Point"}
}