{
  "type": "Feature",
  "properties": {
    "iso:country":"US",
    "sg:address":"5750 E 30th St",
    "sg:city":"Indianapolis",
    "sg:classifiers":[
        {
            "category":"Social Services",
            "subcategory":"Child Care",
            "type":"Services"
        }
    ],
    "sg:phone":"+1 317 591 5050",
    "sg:postcode":"46218",
    "sg:province":"IN",
    "wof:name":"Jewel Child Care Preschool",
    "wof:placetype":"venue"
},
  "geometry": {"coordinates":[-86.06907699999999,39.811031],"type":"Point"}
}