{
  "type": "Feature",
  "properties": {
    "iso:country":"US",
    "sg:address":"5906 Tulip Dr",
    "sg:city":"Brownsburg",
    "sg:classifiers":[
        {
            "category":"Building & Trades",
            "subcategory":"Construction",
            "type":"Services"
        }
    ],
    "sg:phone":"+1 317 852 2108",
    "sg:postcode":"46112",
    "sg:province":"IN",
    "sg:tags":[
        "house"
    ],
    "wof:name":"Puricha Service",
    "wof:placetype":"venue"
},
  "geometry": {"coordinates":[-86.421195,39.829433],"type":"Point"}
}