{
  "type": "Feature",
  "properties": {
    "iso:country":"US",
    "sg:address":"5420 N College Ave",
    "sg:city":"Indianapolis",
    "sg:classifiers":[
        {
            "category":"Manufacturing",
            "subcategory":"Signs",
            "type":"Manufacturing & Wholesale Goods"
        }
    ],
    "sg:phone":"+1 317 396 0908",
    "sg:postcode":"46220",
    "sg:province":"IN",
    "wof:name":"Digital Creations LLC",
    "wof:placetype":"venue"
},
  "geometry": {"coordinates":[-86.145912,39.851699],"type":"Point"}
}