{
  "type": "Feature",
  "properties": {
    "addr:full":"7453 N Piqua Rd Decatur IN 46733",
    "addr:housenumber":"7453",
    "addr:postcode":"46733",
    "addr:street":"N Piqua Rd",
    "iso:country":"US",
    "sg:address":"7453 N Piqua Rd",
    "sg:city":"Decatur",
    "sg:classifiers":[
        {
            "category":"Professional",
            "subcategory":"Research",
            "type":"Services"
        }
    ],
    "sg:phone":"+1 260 728 8000",
    "sg:postcode":"46733",
    "sg:province":"IN",
    "sg:tags":[
        "development",
        "laboratory"
    ],
    "wof:name":"Adm Alliance Nutrition",
    "wof:placetype":"venue"
},
  "geometry": {"coordinates":[-84.92363400000001,40.849016],"type":"Point"}
}