{
  "type": "Feature",
  "properties": {
    "iso:country":"US",
    "sg:address":"625 E Michigan Blvd",
    "sg:city":"Michigan City",
    "sg:classifiers":[
        {
            "category":"Real Estate",
            "subcategory":"Real Estate Agent",
            "type":"Services"
        }
    ],
    "sg:phone":"+1 219 873 7702",
    "sg:postcode":"46360",
    "sg:province":"IN",
    "sg:tags":[
        "authorities",
        "housing"
    ],
    "wof:name":"Housing Authority-Planning",
    "wof:placetype":"venue"
},
  "geometry": {"coordinates":[-86.894617,41.717048],"type":"Point"}
}