{
  "type": "Feature",
  "properties": {
    "iso:country":"US",
    "sg:address":"405 W Dorsey St",
    "sg:city":"St Paul",
    "sg:classifiers":[
        {
            "category":"Wholesale",
            "subcategory":"Meat",
            "type":"Manufacturing & Wholesale Goods"
        }
    ],
    "sg:phone":"+1 765 525 6304",
    "sg:postcode":"47272",
    "sg:province":"IN",
    "sg:tags":[
        "packer"
    ],
    "wof:name":"Myers Frozen Food Provisions",
    "wof:placetype":"venue"
},
  "geometry": {"coordinates":[-85.633598,39.430944],"type":"Point"}
}