{
  "type": "Feature",
  "properties": {
    "iso:country":"US",
    "sg:address":"205 N College Ave Ste 100",
    "sg:city":"Bloomington",
    "sg:classifiers":[
        {
            "category":"Shopping",
            "subcategory":"Jewelry",
            "type":"Retail Goods"
        }
    ],
    "sg:phone":"+1 812 336 3100",
    "sg:postcode":"47404",
    "sg:province":"IN",
    "sg:website":"www.argentum-jewelry.com",
    "wof:name":"Argentum Jewelry",
    "wof:placetype":"venue"
},
  "geometry": {"coordinates":[-86.534897,39.167599],"type":"Point"}
}