{
  "type": "Feature",
  "properties": {
    "addr:full":"6110 Madison Ave Indianapolis IN 46227",
    "addr:housenumber":"6110",
    "addr:postcode":"46227",
    "addr:street":"Madison Ave",
    "iso:country":"US",
    "sg:address":"6110 Madison Ave",
    "sg:city":"Indianapolis",
    "sg:classifiers":[
        {
            "category":"Real Estate",
            "subcategory":"Real Estate Agent",
            "type":"Services"
        }
    ],
    "sg:phone":"+1 317 784 6673",
    "sg:postcode":"46227",
    "sg:province":"IN",
    "wof:name":"YNM Group",
    "wof:placetype":"venue"
},
  "geometry": {"coordinates":[-86.13121599999999,39.676211],"type":"Point"}
}