{
  "type": "Feature",
  "properties": {
    "addr:full":"5902 N College Ave Indianapolis IN 46220",
    "addr:housenumber":"5902",
    "addr:postcode":"46220",
    "addr:street":"N College Ave",
    "iso:country":"US",
    "sg:address":"5902 N College Ave",
    "sg:city":"Indianapolis",
    "sg:classifiers":[
        {
            "category":"Bars & Pubs",
            "type":"Food & Drink"
        }
    ],
    "sg:menulink":"http://www.allmenus.com/in/meridian-hills/268682-binkleys-kitchen--bar/menu/",
    "sg:phone":"+1 317 722 8888",
    "sg:postcode":"46220",
    "sg:province":"IN",
    "sg:tags":[
        "american"
    ],
    "wof:name":"Binkley's Kitchen & Bar",
    "wof:placetype":"venue"
},
  "geometry": {"coordinates":[-86.146418,39.862439],"type":"Point"}
}