{
  "type": "Feature",
  "properties": {
    "iso:country":"US",
    "sg:address":"215 S 8th St",
    "sg:city":"Mitchell",
    "sg:classifiers":[
        {
            "category":"Manufacturing",
            "subcategory":"Tools & Machinery",
            "type":"Manufacturing & Wholesale Goods"
        }
    ],
    "sg:phone":"+1 812 849 9701",
    "sg:postcode":"47446",
    "sg:province":"IN",
    "sg:tags":[
        "mfg"
    ],
    "wof:name":"Deb Cory",
    "wof:placetype":"venue"
},
  "geometry": {"coordinates":[-86.474254,38.731219],"type":"Point"}
}