{
  "type": "Feature",
  "properties": {
    "iso:country":"US",
    "sg:address":"918 W Cook Rd",
    "sg:city":"Fort Wayne",
    "sg:classifiers":[
        {
            "category":"Wholesale",
            "subcategory":"Groceries",
            "type":"Manufacturing & Wholesale Goods"
        }
    ],
    "sg:phone":"+1 260 489 1535",
    "sg:postcode":"46825",
    "sg:province":"IN",
    "sg:tags":[
        "chips",
        "potato"
    ],
    "wof:name":"Olde York Potato Chips",
    "wof:placetype":"venue"
},
  "geometry": {"coordinates":[-85.148636,41.14709],"type":"Point"}
}