{
  "type": "Feature",
  "properties": {
    "iso:country":"US",
    "sg:address":"1316 Broadway St",
    "sg:city":"East Chicago",
    "sg:classifiers":[
        {
            "category":"Personal",
            "type":"Services"
        },
        {
            "category":"Retail",
            "subcategory":"Auto Repair",
            "type":"Services"
        }
    ],
    "sg:phone":"+1 219 398 1254",
    "sg:postcode":"46312",
    "sg:province":"IN",
    "sg:tags":[
        "towing"
    ],
    "wof:name":"Bill's Auto Service",
    "wof:placetype":"venue"
},
  "geometry": {"coordinates":[-87.455704,41.646301],"type":"Point"}
}