{
  "type": "Feature",
  "properties": {
    "iso:country":"US",
    "sg:address":"112 S Main St",
    "sg:city":"Kokomo",
    "sg:classifiers":[
        {
            "category":"Shopping",
            "subcategory":"Computers & Home Electronics",
            "type":"Retail Goods"
        }
    ],
    "sg:phone":"+1 765 459 5146",
    "sg:postcode":"46901",
    "sg:province":"IN",
    "sg:tags":[
        "equipment",
        "dealer"
    ],
    "sg:website":"www.beckleys.com",
    "wof:name":"Beckley Office Supply",
    "wof:placetype":"venue"
},
  "geometry": {"coordinates":[-86.131126,40.485657],"type":"Point"}
}