{
  "type": "Feature",
  "properties": {
    "iso:country":"US",
    "sg:address":"1720 W 38th St",
    "sg:city":"Marion",
    "sg:classifiers":[
        {
            "category":"Organizations",
            "subcategory":"Religious Organization",
            "type":"Services"
        }
    ],
    "sg:phone":"+1 765 677 1065",
    "sg:postcode":"46953",
    "sg:province":"IN",
    "sg:tags":[
        "church"
    ],
    "wof:name":"Heritage Bible Fellowship",
    "wof:placetype":"venue"
},
  "geometry": {"coordinates":[-85.682194,40.523924],"type":"Point"}
}