{
  "type": "Feature",
  "properties": {
    "iso:country":"US",
    "sg:address":"28717 Holiday Pl",
    "sg:city":"Elkhart",
    "sg:classifiers":[
        {
            "category":"Professional",
            "type":"Services"
        }
    ],
    "sg:phone":"+1 574 522 6224",
    "sg:postcode":"46517",
    "sg:province":"IN",
    "sg:tags":[
        "establishment"
    ],
    "wof:name":"Master Tech Rv Svc",
    "wof:placetype":"venue"
},
  "geometry": {"coordinates":[-86.014411,41.654934],"type":"Point"}
}