{
  "type": "Feature",
  "properties": {
    "addr:full":"6850 Equestrian Ln Indianapolis IN 46260",
    "addr:housenumber":"6850",
    "addr:postcode":"46260",
    "addr:street":"Equestrian Ln",
    "iso:country":"US",
    "sg:address":"6850 Equestrian Ln",
    "sg:city":"Indianapolis",
    "sg:classifiers":[
        {
            "category":"Professional",
            "subcategory":"Art Services",
            "type":"Services"
        }
    ],
    "sg:phone":"+1 317 726 0643",
    "sg:postcode":"46260",
    "sg:province":"IN",
    "sg:tags":[
        "commercial",
        "design"
    ],
    "wof:name":"Audball Graphics",
    "wof:placetype":"venue"
},
  "geometry": {"coordinates":[-86.196752,39.879822],"type":"Point"}
}