{
  "type": "Feature",
  "properties": {
    "iso:country":"US",
    "sg:address":"2446 N Rainbow Dr",
    "sg:city":"Warsaw",
    "sg:classifiers":[
        {
            "category":"Retail",
            "subcategory":"Auto Rental",
            "type":"Services"
        }
    ],
    "sg:phone":"+1 574 267 5105",
    "sg:postcode":"46582",
    "sg:province":"IN",
    "sg:tags":[
        "renting",
        "truck",
        "leasing"
    ],
    "wof:name":"U-Haul Co",
    "wof:placetype":"venue"
},
  "geometry": {"coordinates":[-85.84895400000001,41.267382],"type":"Point"}
}