{
  "type": "Feature",
  "properties": {
    "iso:country":"US",
    "sg:address":"888 S Center Rd",
    "sg:city":"Boonville",
    "sg:classifiers":[
        {
            "category":"Building & Trades",
            "subcategory":"Construction",
            "type":"Services"
        }
    ],
    "sg:phone":"+1 812 925 8887",
    "sg:postcode":"47601",
    "sg:province":"IN",
    "sg:tags":[
        "house"
    ],
    "wof:name":"Paradise Villa Homes LLC",
    "wof:placetype":"venue"
},
  "geometry": {"coordinates":[-87.33917599999999,38.021067],"type":"Point"}
}