{
  "type": "Feature",
  "properties": {
    "iso:country":"US",
    "sg:address":"505 el Portal Dr",
    "sg:city":"Michiana Shores",
    "sg:classifiers":[
        {
            "category":"Government",
            "subcategory":"Fire Station",
            "type":"Public Place"
        }
    ],
    "sg:phone":"+1 219 872 1788",
    "sg:postcode":"46360",
    "sg:province":"IN",
    "sg:tags":[
        "department"
    ],
    "wof:name":"Michiana Shores Fire Dept",
    "wof:placetype":"venue"
},
  "geometry": {"coordinates":[-86.816011,41.752699],"type":"Point"}
}