{
  "type": "Feature",
  "properties": {
    "addr:full":"1131 N Burke St Kokomo IN 46901",
    "addr:housenumber":"1131",
    "addr:postcode":"46901",
    "addr:street":"N Burke St",
    "iso:country":"US",
    "sg:address":"1131 N Burke St",
    "sg:city":"Kokomo",
    "sg:classifiers":[
        {
            "category":"Organizations",
            "subcategory":"Religious Organization",
            "type":"Services"
        }
    ],
    "sg:phone":"+1 765 452 0512",
    "sg:postcode":"46901",
    "sg:province":"IN",
    "sg:tags":[
        "church"
    ],
    "wof:name":"New Hope Missionary Baptist",
    "wof:placetype":"venue"
},
  "geometry": {"coordinates":[-86.146631,40.496643],"type":"Point"}
}