{
  "type": "Feature",
  "properties": {
    "iso:country":"US",
    "sg:address":"10277 E State Rd 68",
    "sg:city":"Dale",
    "sg:classifiers":[
        {
            "category":"Shopping",
            "subcategory":"Computers & Home Electronics",
            "type":"Retail Goods"
        }
    ],
    "sg:phone":"+1 812 536 3707",
    "sg:postcode":"47523",
    "sg:province":"IN",
    "sg:tags":[
        "equipment",
        "dealer"
    ],
    "wof:name":"Micro Farm Systems",
    "wof:placetype":"venue"
},
  "geometry": {"coordinates":[-87.035149,38.186838],"type":"Point"}
}