{
  "type": "Feature",
  "properties": {
    "iso:country":"US",
    "sg:address":"6555 Carrollton Ave",
    "sg:city":"Indianapolis",
    "sg:classifiers":[
        {
            "category":"Health Services",
            "subcategory":"Health Practitioner",
            "type":"Services"
        }
    ],
    "sg:phone":"+1 317 257 9672",
    "sg:postcode":"46220",
    "sg:province":"IN",
    "sg:tags":[
        "psychologist"
    ],
    "wof:name":"Neuroscience Center Of Indpls",
    "wof:placetype":"venue"
},
  "geometry": {"coordinates":[-86.144615,39.875327],"type":"Point"}
}