{
  "type": "Feature",
  "properties": {
    "addr:full":"25969 Dole Rd West Harrison IN 47060",
    "addr:postcode":"25969;47060",
    "addr:street":"Dole Rd",
    "iso:country":"US",
    "sg:address":"25969 Dole Rd",
    "sg:city":"West Harrison",
    "sg:classifiers":[
        {
            "category":"Education",
            "subcategory":"Library",
            "type":"Public Place"
        }
    ],
    "sg:phone":"+1 812 637 0777",
    "sg:postcode":"47060",
    "sg:province":"IN",
    "wof:name":"North Dearborn Branch Library",
    "wof:placetype":"venue"
},
  "geometry": {"coordinates":[-84.88538200000001,39.246993],"type":"Point"}
}