{
  "type": "Feature",
  "properties": {
    "iso:country":"US",
    "sg:address":"2960 N Meridian St",
    "sg:city":"Indianapolis",
    "sg:classifiers":[
        {
            "category":"Recreation",
            "type":"Entertainment"
        }
    ],
    "sg:phone":"+1 317 283 2725",
    "sg:postcode":"46208",
    "sg:province":"IN",
    "sg:tags":[
        "carnival"
    ],
    "wof:name":"500 Festival",
    "wof:placetype":"venue"
},
  "geometry": {"coordinates":[-86.156774,39.809042],"type":"Point"}
}