{
  "type": "Feature",
  "properties": {
    "iso:country":"US",
    "sg:address":"2163 Central Ave",
    "sg:city":"Indianapolis",
    "sg:classifiers":[
        {
            "category":"Food & Beverages",
            "subcategory":"Liquor & Beverages",
            "type":"Retail Goods"
        }
    ],
    "sg:phone":"+1 317 923 7144",
    "sg:postcode":"46202",
    "sg:province":"IN",
    "wof:name":"B & B Liquors",
    "wof:placetype":"venue"
},
  "geometry": {"coordinates":[-86.149427,39.796314],"type":"Point"}
}