{
  "type": "Feature",
  "properties": {
    "iso:country":"US",
    "sg:address":"1159 W 10th St",
    "sg:city":"Hobart",
    "sg:classifiers":[
        {
            "category":"Building & Trades",
            "subcategory":"Electrical",
            "type":"Services"
        }
    ],
    "sg:phone":"+1 219 942 8405",
    "sg:postcode":"46342",
    "sg:province":"IN",
    "sg:tags":[
        "electrical",
        "contractor"
    ],
    "wof:name":"Gary Electric",
    "wof:placetype":"venue"
},
  "geometry": {"coordinates":[-87.273744,41.521787],"type":"Point"}
}