{
  "type": "Feature",
  "properties": {
    "iso:country":"US",
    "sg:address":"114 Park Ave",
    "sg:city":"Chesterton",
    "sg:classifiers":[
        {
            "category":"Manufacturing",
            "subcategory":"Tools & Machinery",
            "type":"Manufacturing & Wholesale Goods"
        }
    ],
    "sg:phone":"+1 219 926 8555",
    "sg:postcode":"46304",
    "sg:province":"IN",
    "sg:tags":[
        "machine",
        "shop"
    ],
    "wof:name":"Excel Machine Technologies Inc",
    "wof:placetype":"venue"
},
  "geometry": {"coordinates":[-87.051682,41.604944],"type":"Point"}
}