{
  "type": "Feature",
  "properties": {
    "iso:country":"US",
    "sg:address":"3816 Grant St",
    "sg:city":"Gary",
    "sg:classifiers":[
        {
            "category":"Social Services",
            "subcategory":"Job Training",
            "type":"Services"
        }
    ],
    "sg:phone":"+1 219 981 8109",
    "sg:postcode":"46408",
    "sg:province":"IN",
    "sg:tags":[
        "rehabilitation"
    ],
    "wof:name":"Sport Orthopedic Rehab",
    "wof:placetype":"venue"
},
  "geometry": {"coordinates":[-87.355896,41.548823],"type":"Point"}
}