{
  "type": "Feature",
  "properties": {
    "iso:country":"US",
    "sg:address":"12 William O Vance Ct",
    "sg:city":"New Albany",
    "sg:classifiers":[
        {
            "category":"Health Services",
            "subcategory":"Clinic",
            "type":"Services"
        }
    ],
    "sg:phone":"+1 812 945 3338",
    "sg:postcode":"47150",
    "sg:province":"IN",
    "sg:tags":[
        "home",
        "care"
    ],
    "wof:name":"Tina L Corn Nurse",
    "wof:placetype":"venue"
},
  "geometry": {"coordinates":[-85.834078,38.294337],"type":"Point"}
}