{
  "type": "Feature",
  "properties": {
    "iso:country":"US",
    "sg:address":"208 N Main St",
    "sg:city":"Bicknell",
    "sg:classifiers":[
        {
            "category":"Professional",
            "type":"Services"
        }
    ],
    "sg:phone":"+1 812 735 2360",
    "sg:postcode":"47512",
    "sg:province":"IN",
    "sg:tags":[
        "establishment"
    ],
    "wof:name":"A Harris",
    "wof:placetype":"venue"
},
  "geometry": {"coordinates":[-87.307775,38.774083],"type":"Point"}
}