{
  "type": "Feature",
  "properties": {
    "addr:full":"1907 W Sycamore St Kokomo IN 46901",
    "addr:housenumber":"1907",
    "addr:postcode":"46901",
    "addr:street":"W Sycamore St",
    "iso:country":"US",
    "sg:address":"1907 W Sycamore St",
    "sg:city":"Kokomo",
    "sg:classifiers":[
        {
            "category":"Health Services",
            "subcategory":"Doctor",
            "type":"Services"
        }
    ],
    "sg:phone":"+1 765 456 5100",
    "sg:postcode":"46901",
    "sg:province":"IN",
    "sg:website":"www.stjhhc.org",
    "wof:name":"Higgins Center For Women's",
    "wof:placetype":"venue"
},
  "geometry": {"coordinates":[-86.15821200000001,40.487329],"type":"Point"}
}