{
  "type": "Feature",
  "properties": {
    "iso:country":"US",
    "sg:address":"9900 W Jackson St",
    "sg:city":"Yorktown",
    "sg:classifiers":[
        {
            "category":"Wholesale",
            "subcategory":"Machinery & Supplies",
            "type":"Manufacturing & Wholesale Goods"
        }
    ],
    "sg:phone":"+1 765 759 5584",
    "sg:postcode":"47396",
    "sg:province":"IN",
    "sg:tags":[
        "equipment",
        "industrial"
    ],
    "wof:name":"Doughty Well Drilling",
    "wof:placetype":"venue"
},
  "geometry": {"coordinates":[-85.50211299999999,40.214661],"type":"Point"}
}