{
  "type": "Feature",
  "properties": {
    "iso:country":"US",
    "sg:address":"416 N Main St",
    "sg:city":"Middlebury",
    "sg:classifiers":[
        {
            "category":"Restaurant",
            "type":"Food & Drink"
        }
    ],
    "sg:phone":"+1 574 825 5222",
    "sg:postcode":"46540",
    "sg:province":"IN",
    "sg:tags":[
        "parlor",
        "ice",
        "cream"
    ],
    "wof:name":"Dairy Queen",
    "wof:placetype":"venue"
},
  "geometry": {"coordinates":[-85.702983,41.681981],"type":"Point"}
}