{
  "type": "Feature",
  "properties": {
    "addr:full":"11223 N Old State Rd 15 Milford IN 46542",
    "addr:housenumber":"11223;15",
    "addr:postcode":"46542",
    "addr:street":"N Old State Rd",
    "iso:country":"US",
    "sg:address":"11223 N Old State Rd 15",
    "sg:city":"Milford",
    "sg:classifiers":[
        {
            "category":"Personal",
            "subcategory":"Beauty Salon",
            "type":"Services"
        }
    ],
    "sg:phone":"+1 574 658 4545",
    "sg:postcode":"46542",
    "sg:province":"IN",
    "sg:tags":[
        "shop"
    ],
    "wof:name":"K S Hair Express",
    "wof:placetype":"venue"
},
  "geometry": {"coordinates":[-85.845366,41.397972],"type":"Point"}
}