{
  "type": "Feature",
  "properties": {
    "addr:full":"61577 Miami Meadows Ct South Bend IN 46614",
    "addr:housenumber":"61577",
    "addr:postcode":"46614",
    "addr:street":"Miami Meadows Ct",
    "iso:country":"US",
    "sg:address":"61577 Miami Meadows Ct",
    "sg:city":"South Bend",
    "sg:classifiers":[
        {
            "category":"Building & Trades",
            "subcategory":"Electrical",
            "type":"Services"
        }
    ],
    "sg:phone":"+1 574 299 9658",
    "sg:postcode":"46614",
    "sg:province":"IN",
    "sg:tags":[
        "electric",
        "contractor"
    ],
    "wof:name":"JKM Wiring Inc",
    "wof:placetype":"venue"
},
  "geometry": {"coordinates":[-86.245616,41.598158],"type":"Point"}
}