{
  "type": "Feature",
  "properties": {
    "iso:country":"US",
    "sg:address":"135 S Chauncey Ave",
    "sg:city":"West Lafayette",
    "sg:classifiers":[
        {
            "category":"Personal",
            "subcategory":"Beauty Salon",
            "type":"Services"
        }
    ],
    "sg:phone":"+1 765 743 4280",
    "sg:postcode":"47906",
    "sg:province":"IN",
    "sg:tags":[
        "manicuring"
    ],
    "wof:name":"Happy Nails",
    "wof:placetype":"venue"
},
  "geometry": {"coordinates":[-86.907524,40.422227],"type":"Point"}
}