{
  "type": "Feature",
  "properties": {
    "addr:full":"1022 Broadway St Anderson IN 46012",
    "addr:housenumber":"1022",
    "addr:postcode":"46012",
    "addr:street":"Broadway St",
    "iso:country":"US",
    "sg:address":"1022 Broadway St",
    "sg:city":"Anderson",
    "sg:classifiers":[
        {
            "category":"Organizations",
            "subcategory":"Community Association",
            "type":"Services"
        }
    ],
    "sg:phone":"+1 765 644 8317",
    "sg:postcode":"46012",
    "sg:province":"IN",
    "sg:tags":[
        "fraternal"
    ],
    "wof:name":"Masonic Lodge",
    "wof:placetype":"venue"
},
  "geometry": {"coordinates":[-85.67816500000001,40.127682],"type":"Point"}
}