{
  "type": "Feature",
  "properties": {
    "iso:country":"US",
    "sg:address":"4741 Winterberry Pl",
    "sg:city":"Columbus",
    "sg:classifiers":[
        {
            "category":"Professional",
            "type":"Services"
        }
    ],
    "sg:phone":"+1 812 342 6115",
    "sg:postcode":"47201",
    "sg:province":"IN",
    "sg:tags":[
        "establishment"
    ],
    "wof:name":"Chicago Tokyo Group",
    "wof:placetype":"venue"
},
  "geometry": {"coordinates":[-85.976736,39.191247],"type":"Point"}
}