{
  "type": "Feature",
  "properties": {
    "iso:country":"US",
    "sg:address":"2443 S Walnut Street Pike",
    "sg:city":"Bloomington",
    "sg:classifiers":[
        {
            "category":"Restaurant",
            "type":"Food & Drink"
        }
    ],
    "sg:phone":"+1 812 332 8500",
    "sg:postcode":"47401",
    "sg:province":"IN",
    "sg:tags":[
        "pizza"
    ],
    "wof:name":"Pizza Express",
    "wof:placetype":"venue"
},
  "geometry": {"coordinates":[-86.52919799999999,39.1367],"type":"Point"}
}