{
  "type": "Feature",
  "properties": {
    "iso:country":"US",
    "sg:address":"2792 N State Rd 29",
    "sg:city":"Camden",
    "sg:classifiers":[
        {
            "category":"Personal",
            "subcategory":"Beauty Salon",
            "type":"Services"
        }
    ],
    "sg:phone":"+1 260 564 2364",
    "sg:postcode":"46917",
    "sg:province":"IN",
    "sg:tags":[
        "shop"
    ],
    "wof:name":"Iris White",
    "wof:placetype":"venue"
},
  "geometry": {"coordinates":[-86.391671,40.590124],"type":"Point"}
}