{
  "type": "Feature",
  "properties": {
    "iso:country":"US",
    "sg:address":"17825 Wentworth Ave",
    "sg:city":"Lansing",
    "sg:classifiers":[
        {
            "category":"Health Services",
            "subcategory":"Nursing And Care Facility",
            "type":"Services"
        }
    ],
    "sg:phone":"+1 708 889 1019",
    "sg:postcode":"60438",
    "sg:province":"IL",
    "sg:tags":[
        "hospice"
    ],
    "wof:name":"Blue Skies Hospice",
    "wof:placetype":"venue"
},
  "geometry": {"coordinates":[-87.529692,41.572057],"type":"Point"}
}