{
  "type": "Feature",
  "properties": {
    "iso:country":"US",
    "sg:address":"2419 Hialeah Dr",
    "sg:city":"Evansville",
    "sg:classifiers":[
        {
            "category":"Home & Garden",
            "subcategory":"Home Furnishings",
            "type":"Retail Goods"
        }
    ],
    "sg:phone":"+1 812 471 1100",
    "sg:postcode":"47715",
    "sg:province":"IN",
    "sg:tags":[
        "venetian",
        "blind"
    ],
    "wof:name":"Hunter Venetian Blind Co",
    "wof:placetype":"venue"
},
  "geometry": {"coordinates":[-87.498718,37.997894],"type":"Point"}
}