{
  "type": "Feature",
  "properties": {
    "iso:country":"US",
    "sg:address":"102 E Franklin St",
    "sg:city":"Greencastle",
    "sg:classifiers":[
        {
            "category":"Autos & Motor Vehicles",
            "subcategory":"Auto Supplies",
            "type":"Retail Goods"
        }
    ],
    "sg:phone":"+1 765 653 3157",
    "sg:postcode":"46135",
    "sg:province":"IN",
    "sg:tags":[
        "automobile",
        "parts"
    ],
    "wof:name":"NAPA Auto Parts",
    "wof:placetype":"venue"
},
  "geometry": {"coordinates":[-86.862793,39.644684],"type":"Point"}
}