{
  "type": "Feature",
  "properties": {
    "iso:country":"US",
    "sg:address":"1210 Burberry Ct",
    "sg:city":"Lafayette",
    "sg:classifiers":[
        {
            "category":"Wholesale",
            "subcategory":"Auto Parts",
            "type":"Manufacturing & Wholesale Goods"
        }
    ],
    "sg:phone":"+1 765 448 4817",
    "sg:postcode":"47905",
    "sg:province":"IN",
    "sg:tags":[
        "automobile"
    ],
    "wof:name":"Sian Inc",
    "wof:placetype":"venue"
},
  "geometry": {"coordinates":[-86.835745,40.400598],"type":"Point"}
}