{
  "type": "Feature",
  "properties": {
    "addr:full":"309 Baker St Plymouth IN 46563",
    "addr:housenumber":"309",
    "addr:postcode":"46563",
    "addr:street":"Baker St",
    "iso:country":"US",
    "sg:address":"309 Baker St",
    "sg:city":"Plymouth",
    "sg:classifiers":[
        {
            "category":"Building & Trades",
            "subcategory":"Plumbing",
            "type":"Services"
        }
    ],
    "sg:phone":"+1 574 936 3540",
    "sg:postcode":"46563",
    "sg:province":"IN",
    "sg:tags":[
        "heating",
        "contractor"
    ],
    "wof:name":"Robert Geist Sr",
    "wof:placetype":"venue"
},
  "geometry": {"coordinates":[-86.30754899999999,41.349832],"type":"Point"}
}