{
  "type": "Feature",
  "properties": {
    "iso:country":"US",
    "sg:address":"212 S Babcock Ave",
    "sg:city":"Topeka",
    "sg:classifiers":[
        {
            "category":"Retail",
            "subcategory":"Repair Shop",
            "type":"Services"
        }
    ],
    "sg:phone":"+1 260 593 3777",
    "sg:postcode":"46571",
    "sg:province":"IN",
    "sg:tags":[
        "instrument",
        "musical"
    ],
    "wof:name":"SRP Harmonicas",
    "wof:placetype":"venue"
},
  "geometry": {"coordinates":[-85.540594,41.537939],"type":"Point"}
}