{
  "type": "Feature",
  "properties": {
    "addr:full":"10204 Carriage Dr Plymouth IN 46563",
    "addr:housenumber":"10204",
    "addr:postcode":"46563",
    "addr:street":"Carriage Dr",
    "iso:country":"US",
    "sg:address":"10204 Carriage Dr",
    "sg:city":"Plymouth",
    "sg:classifiers":[
        {
            "category":"Education",
            "subcategory":"Dance Studio",
            "type":"Public Place"
        }
    ],
    "sg:phone":"+1 574 936 8279",
    "sg:postcode":"46563",
    "sg:province":"IN",
    "wof:name":"Best Foot Forward School Dance",
    "wof:placetype":"venue"
},
  "geometry": {"coordinates":[-86.35659099999999,41.32842],"type":"Point"}
}