{
  "type": "Feature",
  "properties": {
    "iso:country":"US",
    "sg:address":"2450 Inishmore Ct",
    "sg:city":"Indianapolis",
    "sg:classifiers":[
        {
            "category":"Home & Garden",
            "subcategory":"Building Materials",
            "type":"Retail Goods"
        }
    ],
    "sg:phone":"+1 317 271 3199",
    "sg:postcode":"46214",
    "sg:province":"IN",
    "sg:tags":[
        "plumbing",
        "fixture",
        "supply"
    ],
    "wof:name":"Majestic Supply Co Inc",
    "wof:placetype":"venue"
},
  "geometry": {"coordinates":[-86.298931,39.799866],"type":"Point"}
}