{
  "type": "Feature",
  "properties": {
    "iso:country":"US",
    "sg:address":"1005 N Western Ave",
    "sg:city":"Marion",
    "sg:classifiers":[
        {
            "category":"Professional",
            "subcategory":"Lawyer & Legal Services",
            "type":"Services"
        }
    ],
    "sg:phone":"+1 765 662 2576",
    "sg:postcode":"46952",
    "sg:province":"IN",
    "sg:tags":[
        "attorney"
    ],
    "wof:name":"Fishburne & Lewis",
    "wof:placetype":"venue"
},
  "geometry": {"coordinates":[-85.67427600000001,40.572385],"type":"Point"}
}