{
  "type": "Feature",
  "properties": {
    "iso:country":"US",
    "sg:address":"117 W Thornton St",
    "sg:city":"Paoli",
    "sg:classifiers":[
        {
            "category":"Retail",
            "subcategory":"Car Wash",
            "type":"Services"
        }
    ],
    "sg:phone":"+1 812 723 4659",
    "sg:postcode":"47454",
    "sg:province":"IN",
    "sg:tags":[
        "polishing",
        "washing"
    ],
    "wof:name":"Randy's Car Wash",
    "wof:placetype":"venue"
},
  "geometry": {"coordinates":[-86.469602,38.55815],"type":"Point"}
}