{
  "type": "Feature",
  "properties": {
    "iso:country":"US",
    "sg:address":"9840 Westpoint Dr Ste 500",
    "sg:city":"Indianapolis",
    "sg:classifiers":[
        {
            "category":"Health Services",
            "subcategory":"Dentist",
            "type":"Services"
        }
    ],
    "sg:phone":"+1 317 579 1875",
    "sg:postcode":"46256",
    "sg:province":"IN",
    "wof:name":"Stante Julie L PC",
    "wof:placetype":"venue"
},
  "geometry": {"coordinates":[-86.030998,39.932701],"type":"Point"}
}