{
  "type": "Feature",
  "properties": {
    "iso:country":"US",
    "sg:address":"6007 Woodsview Ct",
    "sg:city":"Floyds Knobs",
    "sg:classifiers":[
        {
            "category":"Manufacturing",
            "subcategory":"Printing",
            "type":"Manufacturing & Wholesale Goods"
        }
    ],
    "sg:phone":"+1 812 923 0671",
    "sg:postcode":"47119",
    "sg:province":"IN",
    "sg:tags":[
        "publisher"
    ],
    "sg:website":"www.mediak.com",
    "wof:name":"Mediak",
    "wof:placetype":"venue"
},
  "geometry": {"coordinates":[-85.849948,38.363178],"type":"Point"}
}