{
  "type": "Feature",
  "properties": {
    "iso:country":"US",
    "sg:address":"113 E Main St",
    "sg:city":"North Manchester",
    "sg:classifiers":[
        {
            "category":"Personal",
            "subcategory":"Tanning Parlor",
            "type":"Services"
        }
    ],
    "sg:phone":"+1 260 982 1338",
    "sg:postcode":"46962",
    "sg:province":"IN",
    "sg:tags":[
        "salon"
    ],
    "wof:name":"Twin Tanning",
    "wof:placetype":"venue"
},
  "geometry": {"coordinates":[-85.8178,40.798042],"type":"Point"}
}