{
  "type": "Feature",
  "properties": {
    "iso:country":"US",
    "sg:address":"441 W North St",
    "sg:city":"Kendallville",
    "sg:classifiers":[
        {
            "category":"Professional",
            "subcategory":"Employment Agencies",
            "type":"Services"
        }
    ],
    "sg:phone":"+1 260 347 9761",
    "sg:postcode":"46755",
    "sg:province":"IN",
    "sg:tags":[
        "help",
        "contractor"
    ],
    "wof:name":"Pro Resources Inc",
    "wof:placetype":"venue"
},
  "geometry": {"coordinates":[-85.272758,41.452269],"type":"Point"}
}