{
  "type": "Feature",
  "properties": {
    "iso:country":"US",
    "sg:address":"105 N Wabash Ave",
    "sg:city":"La Fontaine",
    "sg:classifiers":[
        {
            "category":"Personal",
            "subcategory":"Beauty Salon",
            "type":"Services"
        }
    ],
    "sg:phone":"+1 765 981 4414",
    "sg:postcode":"46940",
    "sg:province":"IN",
    "wof:name":"Classic Hair & Tanning Salon",
    "wof:placetype":"venue"
},
  "geometry": {"coordinates":[-85.722278,40.675881],"type":"Point"}
}