{
  "type": "Feature",
  "properties": {
    "iso:country":"US",
    "sg:address":"5467 N Co Rd 420 W",
    "sg:city":"Greensburg",
    "sg:classifiers":[
        {
            "category":"Real Estate",
            "subcategory":"Real Estate Operator",
            "type":"Services"
        }
    ],
    "sg:phone":"+1 812 663 2035",
    "sg:postcode":"47240",
    "sg:province":"IN",
    "sg:tags":[
        "property",
        "lessor"
    ],
    "wof:name":"George Saylor",
    "wof:placetype":"venue"
},
  "geometry": {"coordinates":[-85.559251,39.41735],"type":"Point"}
}