{
  "type": "Feature",
  "properties": {
    "iso:country":"US",
    "sg:address":"14550 US Hwy 6",
    "sg:city":"Plymouth",
    "sg:classifiers":[
        {
            "category":"Building & Trades",
            "subcategory":"Landscaping Services",
            "type":"Services"
        }
    ],
    "sg:phone":"+1 574 784 2123",
    "sg:postcode":"46563",
    "sg:province":"IN",
    "sg:tags":[
        "landscape",
        "contractor"
    ],
    "wof:name":"Don Creed Commercial & Rsdntl",
    "wof:placetype":"venue"
},
  "geometry": {"coordinates":[-86.339764,41.449034],"type":"Point"}
}