{
  "type": "Feature",
  "properties": {
    "iso:country":"US",
    "sg:address":"305 N 6th Ave",
    "sg:city":"Princeton",
    "sg:classifiers":[
        {
            "category":"Health Services",
            "subcategory":"Health Practitioner",
            "type":"Services"
        }
    ],
    "sg:phone":"+1 812 385 2287",
    "sg:postcode":"47670",
    "sg:province":"IN",
    "sg:tags":[
        "therapy"
    ],
    "wof:name":"Sunbelt Therapy Management",
    "wof:placetype":"venue"
},
  "geometry": {"coordinates":[-87.592651,38.360207],"type":"Point"}
}