{
  "type": "Feature",
  "properties": {
    "addr:full":"119 E Goldsboro St Crown Point IN 46307",
    "addr:housenumber":"119",
    "addr:postcode":"46307",
    "addr:street":"E Goldsboro St",
    "iso:country":"US",
    "sg:address":"119 E Goldsboro St",
    "sg:city":"Crown Point",
    "sg:classifiers":[
        {
            "category":"Personal",
            "subcategory":"Tanning Parlor",
            "type":"Services"
        }
    ],
    "sg:phone":"+1 219 663 3962",
    "sg:postcode":"46307",
    "sg:province":"IN",
    "wof:name":"We Got the Look Inc",
    "wof:placetype":"venue"
},
  "geometry": {"coordinates":[-87.362396,41.4231],"type":"Point"}
}