{
  "type": "Feature",
  "properties": {
    "iso:country":"US",
    "sg:address":"62646 Miami Rd",
    "sg:city":"South Bend",
    "sg:classifiers":[
        {
            "category":"Wholesale",
            "subcategory":"Machinery & Supplies",
            "type":"Manufacturing & Wholesale Goods"
        }
    ],
    "sg:phone":"+1 574 291 7809",
    "sg:postcode":"46614",
    "sg:province":"IN",
    "wof:name":"Evergreen Irrigation Systems",
    "wof:placetype":"venue"
},
  "geometry": {"coordinates":[-86.234512,41.585444],"type":"Point"}
}