{
  "type": "Feature",
  "properties": {
    "addr:full":"7201 W 25th Ave Gary IN 46406",
    "addr:housenumber":"7201",
    "addr:postcode":"46406",
    "addr:street":"W 25Th Ave",
    "iso:country":"US",
    "sg:address":"7201 W 25th Ave",
    "sg:city":"Gary",
    "sg:classifiers":[
        {
            "category":"Education",
            "subcategory":"School",
            "type":"Public Place"
        }
    ],
    "sg:phone":"+1 219 844 2255",
    "sg:postcode":"46406",
    "sg:province":"IN",
    "wof:name":"Grissom Elementary School",
    "wof:placetype":"venue"
},
  "geometry": {"coordinates":[-87.429298,41.573502],"type":"Point"}
}