{
  "type": "Feature",
  "properties": {
    "iso:country":"US",
    "sg:address":"7030 Madison Ave",
    "sg:city":"Indianapolis",
    "sg:classifiers":[
        {
            "category":"Banks & Credit Unions",
            "subcategory":"Bank",
            "type":"Services"
        }
    ],
    "sg:phone":"+1 317 472 7143",
    "sg:postcode":"46227",
    "sg:province":"IN",
    "sg:tags":[
        "cashing",
        "check"
    ],
    "wof:name":"Cashland Financial Svc",
    "wof:placetype":"venue"
},
  "geometry": {"coordinates":[-86.12676399999999,39.66404],"type":"Point"}
}