{
  "type": "Feature",
  "properties": {
    "iso:country":"US",
    "sg:address":"7387 5c Rd",
    "sg:city":"Bremen",
    "sg:classifiers":[
        {
            "category":"Retail",
            "subcategory":"Car Wash",
            "type":"Services"
        }
    ],
    "sg:phone":"+1 574 546 5426",
    "sg:postcode":"46506",
    "sg:province":"IN",
    "sg:tags":[
        "automobile",
        "detail",
        "clean"
    ],
    "wof:name":"C & M Distributors",
    "wof:placetype":"venue"
},
  "geometry": {"coordinates":[-86.058739,41.397278],"type":"Point"}
}