{
  "type": "Feature",
  "properties": {
    "iso:country":"US",
    "sg:address":"1904 Worthington Dr",
    "sg:city":"Valparaiso",
    "sg:classifiers":[
        {
            "category":"Social Services",
            "type":"Services"
        }
    ],
    "sg:phone":"+1 219 464 9530",
    "sg:postcode":"46383",
    "sg:province":"IN",
    "sg:tags":[
        "counseling"
    ],
    "wof:name":"Center For Life Change",
    "wof:placetype":"venue"
},
  "geometry": {"coordinates":[-87.032526,41.486263],"type":"Point"}
}