{
  "type": "Feature",
  "properties": {
    "iso:country":"US",
    "sg:address":"131 Creekside Dr",
    "sg:city":"Kokomo",
    "sg:classifiers":[
        {
            "category":"Freight",
            "type":"Transportation"
        }
    ],
    "sg:phone":"+1 765 452 0499",
    "sg:postcode":"46901",
    "sg:province":"IN",
    "sg:tags":[
        "delivery"
    ],
    "wof:name":"A-Tran's Delivery Svc",
    "wof:placetype":"venue"
},
  "geometry": {"coordinates":[-86.108645,40.487487],"type":"Point"}
}