{
  "type": "Feature",
  "properties": {
    "iso:country":"US",
    "sg:address":"1842 W Jefferson St",
    "sg:city":"Plymouth",
    "sg:classifiers":[
        {
            "category":"Shopping",
            "type":"Retail Goods"
        }
    ],
    "sg:phone":"+1 574 935 4677",
    "sg:postcode":"46563",
    "sg:province":"IN",
    "sg:tags":[
        "equipment",
        "care",
        "health",
        "home"
    ],
    "wof:name":"Memorial Home Care",
    "wof:placetype":"venue"
},
  "geometry": {"coordinates":[-86.331385,41.343031],"type":"Point"}
}