{
  "type": "Feature",
  "properties": {
    "addr:full":"7636 Co Rd W 300 N Kokomo IN 46901",
    "addr:housenumber":"7636;300",
    "addr:postcode":"46901",
    "addr:street":"Co Rd W;N",
    "iso:country":"US",
    "sg:address":"7636 Co Rd W 300 N",
    "sg:city":"Kokomo",
    "sg:classifiers":[
        {
            "category":"Farming",
            "subcategory":"Livestock Farm",
            "type":"Manufacturing & Wholesale Goods"
        }
    ],
    "sg:phone":"+1 765 628 3236",
    "sg:postcode":"46901",
    "sg:province":"IN",
    "sg:tags":[
        "corn",
        "wheat",
        "feedlot",
        "beef",
        "cattle"
    ],
    "wof:name":"William Donson",
    "wof:placetype":"venue"
},
  "geometry": {"coordinates":[-86.27365399999999,40.518549],"type":"Point"}
}