{
  "type": "Feature",
  "properties": {
    "iso:country":"US",
    "sg:address":"271 State Rd 129",
    "sg:city":"Batesville",
    "sg:classifiers":[
        {
            "category":"Home & Garden",
            "subcategory":"Building Materials",
            "type":"Retail Goods"
        }
    ],
    "sg:phone":"+1 812 934 4140",
    "sg:postcode":"47006",
    "sg:province":"IN",
    "wof:name":"Gillman Construction Co",
    "wof:placetype":"venue"
},
  "geometry": {"coordinates":[-85.203338,39.285098],"type":"Point"}
}