{
  "type": "Feature",
  "properties": {
    "iso:country":"US",
    "sg:address":"7890 E State Rd 44",
    "sg:city":"Shelbyville",
    "sg:classifiers":[
        {
            "category":"Manufacturing",
            "subcategory":"Metals",
            "type":"Manufacturing & Wholesale Goods"
        }
    ],
    "sg:phone":"+1 765 544 9152",
    "sg:postcode":"46176",
    "sg:province":"IN",
    "sg:tags":[
        "steel"
    ],
    "wof:name":"Triple J Ironworks Inc",
    "wof:placetype":"venue"
},
  "geometry": {"coordinates":[-85.635251,39.568895],"type":"Point"}
}