{
  "type": "Feature",
  "properties": {
    "iso:country":"US",
    "sg:address":"2416 N State Rd 75",
    "sg:city":"Thorntown",
    "sg:classifiers":[
        {
            "category":"Manufacturing",
            "subcategory":"Furniture",
            "type":"Manufacturing & Wholesale Goods"
        }
    ],
    "sg:phone":"+1 765 436 2466",
    "sg:postcode":"46071",
    "sg:province":"IN",
    "wof:name":"J & J Wood Crafters",
    "wof:placetype":"venue"
},
  "geometry": {"coordinates":[-86.619808,40.072891],"type":"Point"}
}