{
  "type": "Feature",
  "properties": {
    "addr:full":"5939 Castle Creek Parkway North Dr Nort Indianapolis IN 46250",
    "addr:housenumber":"5939",
    "addr:postcode":"46250",
    "addr:street":"Castle Creek Parkway North Dr",
    "iso:country":"US",
    "sg:address":"5939 Castle Creek Parkway North Dr Nort",
    "sg:city":"Indianapolis",
    "sg:classifiers":[
        {
            "category":"Organizations",
            "subcategory":"Membership Organization",
            "type":"Services"
        }
    ],
    "sg:phone":"+1 317 579 5050",
    "sg:postcode":"46250",
    "sg:province":"IN",
    "sg:tags":[
        "sorority",
        "fraternal",
        "fraternity"
    ],
    "sg:website":"http://www.alphachiomega.org",
    "wof:name":"Alpha Chi Omega National Hdqrs",
    "wof:placetype":"venue"
},
  "geometry": {"coordinates":[-86.065229,39.916804],"type":"Point"}
}