{
  "type": "Feature",
  "properties": {
    "iso:country":"US",
    "sg:address":"9502 State Rd 144",
    "sg:city":"Martinsville",
    "sg:classifiers":[
        {
            "category":"Restaurant",
            "type":"Food & Drink"
        }
    ],
    "sg:phone":"+1 317 422 1601",
    "sg:postcode":"46151",
    "sg:province":"IN",
    "wof:name":"Pancho's Lefty's",
    "wof:placetype":"venue"
},
  "geometry": {"coordinates":[-86.251041,39.566345],"type":"Point"}
}