{
  "type": "Feature",
  "properties": {
    "iso:country":"US",
    "sg:address":"651 Armory Rd",
    "sg:city":"Delphi",
    "sg:classifiers":[
        {
            "category":"Health Services",
            "subcategory":"Doctor",
            "type":"Services"
        }
    ],
    "sg:phone":"+1 765 564 2777",
    "sg:postcode":"46923",
    "sg:province":"IN",
    "sg:tags":[
        "physician",
        "surgeon"
    ],
    "sg:website":"www.arnettclinic.com",
    "wof:name":"Arnett Clinic Delphi",
    "wof:placetype":"venue"
},
  "geometry": {"coordinates":[-86.668768,40.576527],"type":"Point"}
}