{
  "type": "Feature",
  "properties": {
    "iso:country":"US",
    "sg:address":"1176 W Eads Pkwy",
    "sg:city":"Lawrenceburg",
    "sg:classifiers":[
        {
            "category":"Autos & Motor Vehicles",
            "subcategory":"Automobile Sales",
            "type":"Retail Goods"
        }
    ],
    "sg:phone":"+1 812 539 2214",
    "sg:postcode":"47025",
    "sg:province":"IN",
    "sg:tags":[
        "car",
        "dealer"
    ],
    "wof:name":"ABC Auto Sales",
    "wof:placetype":"venue"
},
  "geometry": {"coordinates":[-84.882076,39.082573],"type":"Point"}
}