{
  "type": "Feature",
  "properties": {
    "iso:country":"US",
    "sg:address":"5720 Columbia Ave",
    "sg:city":"Hammond",
    "sg:classifiers":[
        {
            "category":"Wholesale",
            "subcategory":"Construction Materials",
            "type":"Manufacturing & Wholesale Goods"
        }
    ],
    "sg:phone":"+1 219 933 4686",
    "sg:postcode":"46320",
    "sg:province":"IN",
    "sg:tags":[
        "fence"
    ],
    "wof:name":"Hammond Fence Co",
    "wof:placetype":"venue"
},
  "geometry": {"coordinates":[-87.49995800000001,41.609584],"type":"Point"}
}