{
  "type": "Feature",
  "properties": {
    "iso:country":"US",
    "sg:address":"51092 Streamwood Dr",
    "sg:city":"Granger",
    "sg:classifiers":[
        {
            "category":"Real Estate",
            "subcategory":"Real Estate Agent",
            "type":"Services"
        }
    ],
    "sg:phone":"+1 574 272 5455",
    "sg:postcode":"46530",
    "sg:province":"IN",
    "wof:name":"Jill Robinson LLC",
    "wof:placetype":"venue"
},
  "geometry": {"coordinates":[-86.099384,41.752183],"type":"Point"}
}