{
  "type": "Feature",
  "properties": {
    "addr:full":"205 S Walnut St Bloomington IN 47404",
    "addr:housenumber":"205",
    "addr:postcode":"47404",
    "addr:street":"S Walnut St",
    "iso:country":"US",
    "sg:address":"205 S Walnut St",
    "sg:city":"Bloomington",
    "sg:classifiers":[
        {
            "category":"Professional",
            "subcategory":"Lawyer & Legal Services",
            "type":"Services"
        }
    ],
    "sg:phone":"+1 812 331 3000",
    "sg:postcode":"47404",
    "sg:province":"IN",
    "sg:tags":[
        "attorney"
    ],
    "wof:name":"Gerard W Pauwels",
    "wof:placetype":"venue"
},
  "geometry": {"coordinates":[-86.533552,39.164638],"type":"Point"}
}