{
  "type": "Feature",
  "properties": {
    "addr:full":"127 N Capitol Ave Indianapolis IN 46204",
    "addr:housenumber":"127",
    "addr:postcode":"46204",
    "addr:street":"N Capitol Ave",
    "iso:country":"US",
    "sg:address":"127 N Capitol Ave",
    "sg:city":"Indianapolis",
    "sg:classifiers":[
        {
            "category":"Parking",
            "type":"Transportation"
        }
    ],
    "sg:phone":"+1 317 634 9090",
    "sg:postcode":"46204",
    "sg:province":"IN",
    "sg:tags":[
        "garage"
    ],
    "sg:website":"www.abm.com",
    "wof:name":"AMPCO System Parking",
    "wof:placetype":"venue"
},
  "geometry": {"coordinates":[-86.16153199999999,39.769943],"type":"Point"}
}