{
  "type": "Feature",
  "properties": {
    "addr:full":"201 Main St Hobart IN 46342",
    "addr:housenumber":"201",
    "addr:postcode":"46342",
    "addr:street":"Main St",
    "iso:country":"US",
    "sg:address":"201 Main St",
    "sg:city":"Hobart",
    "sg:classifiers":[
        {
            "category":"Shopping",
            "subcategory":"Shoes",
            "type":"Retail Goods"
        }
    ],
    "sg:phone":"+1 219 942 5544",
    "sg:postcode":"46342",
    "sg:province":"IN",
    "wof:name":"Greener's Men's & Women's",
    "wof:placetype":"venue"
},
  "geometry": {"coordinates":[-87.254863,41.532025],"type":"Point"}
}