{
  "type": "Feature",
  "properties": {
    "iso:country":"US",
    "sg:address":"8255 Wicker Ave",
    "sg:city":"St John",
    "sg:classifiers":[
        {
            "category":"Shopping",
            "subcategory":"Gifts & Souvenirs",
            "type":"Retail Goods"
        }
    ],
    "sg:phone":"+1 219 365 8844",
    "sg:postcode":"46373",
    "sg:province":"IN",
    "sg:tags":[
        "shop"
    ],
    "wof:name":"Off The Vine",
    "wof:placetype":"venue"
},
  "geometry": {"coordinates":[-87.470315,41.467757],"type":"Point"}
}