{
  "type": "Feature",
  "properties": {
    "iso:country":"US",
    "sg:address":"1400 S Lake Park Ave",
    "sg:city":"Hobart",
    "sg:classifiers":[
        {
            "category":"Health Services",
            "subcategory":"Doctor",
            "type":"Services"
        }
    ],
    "sg:phone":"+1 219 947 4410",
    "sg:postcode":"46342",
    "sg:province":"IN",
    "sg:tags":[
        "physician",
        "surgeon"
    ],
    "wof:name":"Deen-Gross Eye Ctr",
    "wof:placetype":"venue"
},
  "geometry": {"coordinates":[-87.258989,41.512783],"type":"Point"}
}