{
  "type": "Feature",
  "properties": {
    "iso:country":"US",
    "sg:address":"3602 Grape Rd",
    "sg:city":"Mishawaka",
    "sg:classifiers":[
        {
            "category":"Restaurant",
            "type":"Food & Drink"
        }
    ],
    "sg:phone":"+1 574 256 5277",
    "sg:postcode":"46545",
    "sg:province":"IN",
    "sg:tags":[
        "delicatessen"
    ],
    "wof:name":"Grapevine Deli",
    "wof:placetype":"venue"
},
  "geometry": {"coordinates":[-86.18721600000001,41.692991],"type":"Point"}
}