{
  "type": "Feature",
  "properties": {
    "iso:country":"US",
    "sg:address":"342 Massachusetts Ave Ste 500",
    "sg:city":"Indianapolis",
    "sg:classifiers":[
        {
            "category":"Farming",
            "subcategory":"Fish & Marine Products",
            "type":"Manufacturing & Wholesale Goods"
        }
    ],
    "sg:phone":"+1 317 860 2890",
    "sg:postcode":"46204",
    "sg:province":"IN",
    "wof:name":"Rubin Levin",
    "wof:placetype":"venue"
},
  "geometry": {"coordinates":[-86.15378699999999,39.771614],"type":"Point"}
}