{
  "type": "Feature",
  "properties": {
    "iso:country":"US",
    "sg:address":"1015 E National Ave",
    "sg:city":"Brazil",
    "sg:classifiers":[
        {
            "category":"Government",
            "subcategory":"Office",
            "type":"Public Place"
        }
    ],
    "sg:phone":"+1 812 448 1011",
    "sg:postcode":"47834",
    "sg:province":"IN",
    "sg:tags":[
        "state",
        "resource"
    ],
    "wof:name":"Child Protective Svc",
    "wof:placetype":"venue"
},
  "geometry": {"coordinates":[-87.112949,39.526479],"type":"Point"}
}