{
  "type": "Feature",
  "properties": {
    "iso:country":"US",
    "sg:address":"2164 W 1200 N",
    "sg:city":"Burnettsville",
    "sg:classifiers":[
        {
            "category":"Retail",
            "subcategory":"Repair Shop",
            "type":"Services"
        }
    ],
    "sg:phone":"+1 574 826 4415",
    "sg:postcode":"47926",
    "sg:province":"IN",
    "wof:name":"Oliver Taxidermy",
    "wof:placetype":"venue"
},
  "geometry": {"coordinates":[-86.565293,40.721713],"type":"Point"}
}