{
  "type": "Feature",
  "properties": {
    "iso:country":"US",
    "sg:address":"1700 W Smith Valley Rd",
    "sg:city":"Greenwood",
    "sg:classifiers":[
        {
            "category":"Insurance",
            "subcategory":"Insurance Agent",
            "type":"Services"
        }
    ],
    "sg:phone":"+1 317 882 0069",
    "sg:postcode":"46142",
    "sg:province":"IN",
    "wof:name":"Bagby & Assoc",
    "wof:placetype":"venue"
},
  "geometry": {"coordinates":[-86.157924,39.605973],"type":"Point"}
}