{
  "type": "Feature",
  "properties": {
    "addr:full":"3099 Central Ave Lake Station IN 46405",
    "addr:housenumber":"3099",
    "addr:postcode":"46405",
    "addr:street":"Central Ave Lake",
    "iso:country":"US",
    "sg:address":"3099 Central Ave",
    "sg:city":"Lake Station",
    "sg:classifiers":[
        {
            "category":"Health Services",
            "subcategory":"Doctor",
            "type":"Services"
        }
    ],
    "sg:phone":"+1 219 962 1418",
    "sg:postcode":"46405",
    "sg:province":"IN",
    "sg:tags":[
        "physician",
        "surgeon"
    ],
    "wof:name":"Fernando H Rivera Inc",
    "wof:placetype":"venue"
},
  "geometry": {"coordinates":[-87.24872000000001,41.573081],"type":"Point"}
}