{
  "type": "Feature",
  "properties": {
    "iso:country":"US",
    "sg:address":"512 N Meridian St",
    "sg:city":"Greenwood",
    "sg:classifiers":[
        {
            "category":"Real Estate",
            "subcategory":"Real Estate Services",
            "type":"Services"
        }
    ],
    "sg:phone":"+1 317 882 4332",
    "sg:postcode":"46143",
    "sg:province":"IN",
    "sg:tags":[
        "company",
        "title"
    ],
    "wof:name":"Carpenter Title Agency Inc",
    "wof:placetype":"venue"
},
  "geometry": {"coordinates":[-86.10638,39.624286],"type":"Point"}
}