{
  "type": "Feature",
  "properties": {
    "iso:country":"US",
    "sg:address":"551 Hospital Rd",
    "sg:city":"Franklin",
    "sg:classifiers":[
        {
            "category":"Building & Trades",
            "subcategory":"Construction",
            "type":"Services"
        }
    ],
    "sg:phone":"+1 317 736 0837",
    "sg:postcode":"46131",
    "sg:province":"IN",
    "sg:tags":[
        "contractor"
    ],
    "wof:name":"Ford Masonry",
    "wof:placetype":"venue"
},
  "geometry": {"coordinates":[-86.092668,39.476252],"type":"Point"}
}