{
  "type": "Feature",
  "properties": {
    "iso:country":"US",
    "sg:address":"545 Barnhill Dr Ste Em435",
    "sg:city":"Indianapolis",
    "sg:classifiers":[
        {
            "category":"Health Services",
            "subcategory":"Doctor",
            "type":"Services"
        }
    ],
    "sg:phone":"+1 317 274 4806",
    "sg:postcode":"46202",
    "sg:province":"IN",
    "sg:tags":[
        "physician",
        "surgeon",
        "surgeons",
        "pathology"
    ],
    "wof:name":"Indiana University",
    "wof:placetype":"venue"
},
  "geometry": {"coordinates":[-86.17859199999999,39.775154],"type":"Point"}
}