{
  "type": "Feature",
  "properties": {
    "iso:country":"US",
    "sg:address":"6520 Belle Isle Pl",
    "sg:city":"Fort Wayne",
    "sg:classifiers":[
        {
            "category":"Professional",
            "subcategory":"Management & Consulting",
            "type":"Services"
        }
    ],
    "sg:phone":"+1 260 485 2902",
    "sg:postcode":"46835",
    "sg:province":"IN",
    "sg:tags":[
        "retail",
        "direct",
        "sales"
    ],
    "wof:name":"Either Ores",
    "wof:placetype":"venue"
},
  "geometry": {"coordinates":[-85.059573,41.156306],"type":"Point"}
}