{
  "type": "Feature",
  "properties": {
    "addr:full":"310 S Clinton St Boswell IN 47921",
    "addr:housenumber":"310",
    "addr:postcode":"47921",
    "addr:street":"S Clinton St",
    "iso:country":"US",
    "sg:address":"310 S Clinton St",
    "sg:city":"Boswell",
    "sg:classifiers":[
        {
            "category":"Organizations",
            "subcategory":"Religious Organization",
            "type":"Services"
        }
    ],
    "sg:phone":"+1 765 869 5744",
    "sg:postcode":"47921",
    "sg:province":"IN",
    "sg:tags":[
        "church"
    ],
    "wof:name":"Boswell Church Of Christ",
    "wof:placetype":"venue"
},
  "geometry": {"coordinates":[-87.38175699999999,40.516373],"type":"Point"}
}