{
  "type": "Feature",
  "properties": {
    "iso:country":"US",
    "sg:address":"804 W Main St",
    "sg:city":"Mitchell",
    "sg:classifiers":[
        {
            "category":"Education",
            "subcategory":"Library",
            "type":"Public Place"
        }
    ],
    "sg:phone":"+1 812 849 2412",
    "sg:postcode":"47446",
    "sg:province":"IN",
    "sg:website":"www.mitlib.org",
    "wof:name":"Mitchell Community Public Libr",
    "wof:placetype":"venue"
},
  "geometry": {"coordinates":[-86.474674,38.732412],"type":"Point"}
}