{
  "type": "Feature",
  "properties": {
    "iso:country":"US",
    "sg:address":"3950 E 10th St",
    "sg:city":"Bloomington",
    "sg:classifiers":[
        {
            "category":"Building & Trades",
            "subcategory":"Construction",
            "type":"Services"
        }
    ],
    "sg:phone":"+1 812 336 2118",
    "sg:postcode":"47408",
    "sg:province":"IN",
    "sg:tags":[
        "general",
        "contractor"
    ],
    "wof:name":"Derk Brewer Construction",
    "wof:placetype":"venue"
},
  "geometry": {"coordinates":[-86.48321,39.172287],"type":"Point"}
}