{
  "type": "Feature",
  "properties": {
    "iso:country":"US",
    "sg:address":"404 E 38th St",
    "sg:city":"Indianapolis",
    "sg:classifiers":[
        {
            "category":"Organizations",
            "subcategory":"Religious Organization",
            "type":"Services"
        }
    ],
    "sg:phone":"+1 317 283 1358",
    "sg:postcode":"46205",
    "sg:province":"IN",
    "wof:name":"Unification Church",
    "wof:placetype":"venue"
},
  "geometry": {"coordinates":[-86.14981,39.825078],"type":"Point"}
}