{
  "type": "Feature",
  "properties": {
    "iso:country":"US",
    "sg:address":"6860 W 650 N",
    "sg:city":"Bryant",
    "sg:classifiers":[
        {
            "category":"Farming",
            "subcategory":"Farm",
            "type":"Manufacturing & Wholesale Goods"
        }
    ],
    "sg:phone":"+1 260 731 5063",
    "sg:postcode":"47326",
    "sg:province":"IN",
    "wof:name":"Point Of View Farms Inc",
    "wof:placetype":"venue"
},
  "geometry": {"coordinates":[-85.11304800000001,40.531631],"type":"Point"}
}