{
  "type": "Feature",
  "properties": {
    "iso:country":"US",
    "sg:address":"7060 W Key St",
    "sg:city":"West Baden Spgs",
    "sg:classifiers":[
        {
            "category":"Organizations",
            "subcategory":"Religious Organization",
            "type":"Services"
        }
    ],
    "sg:phone":"+1 812 936 2027",
    "sg:postcode":"47469",
    "sg:province":"IN",
    "sg:tags":[
        "clergy"
    ],
    "wof:name":"Walt Kirkam",
    "wof:placetype":"venue"
},
  "geometry": {"coordinates":[-86.607291,38.570001],"type":"Point"}
}