{
  "type": "Feature",
  "properties": {
    "iso:country":"US",
    "sg:address":"22810 Mule Barn Rd",
    "sg:city":"Sheridan",
    "sg:classifiers":[
        {
            "category":"Recreation",
            "type":"Entertainment"
        }
    ],
    "sg:phone":"+1 317 758 5850",
    "sg:postcode":"46069",
    "sg:province":"IN",
    "sg:tags":[
        "stable"
    ],
    "wof:name":"Laurelwood Stables",
    "wof:placetype":"venue"
},
  "geometry": {"coordinates":[-86.222695,40.114454],"type":"Point"}
}