{
  "type": "Feature",
  "properties": {
    "addr:full":"6425 W Old Road 64 Huntingburg IN 47542",
    "addr:housenumber":"6425",
    "addr:postcode":"47542",
    "addr:street":"W Old Road 64 Huntingburg",
    "iso:country":"US",
    "sg:address":"6425 W Old Road 64",
    "sg:city":"Huntingburg",
    "sg:classifiers":[
        {
            "category":"Building & Trades",
            "subcategory":"Plumbing",
            "type":"Services"
        }
    ],
    "sg:phone":"+1 812 683 0997",
    "sg:postcode":"47542",
    "sg:province":"IN",
    "sg:tags":[
        "conditioning",
        "air",
        "system",
        "contractor"
    ],
    "wof:name":"Barkley's Heating Air Cond",
    "wof:placetype":"venue"
},
  "geometry": {"coordinates":[-87.023871,38.269157],"type":"Point"}
}