{
  "type": "Feature",
  "properties": {
    "iso:country":"US",
    "sg:address":"24 Marble St",
    "sg:city":"Hammond",
    "sg:classifiers":[
        {
            "category":"Wholesale",
            "subcategory":"Construction Materials",
            "type":"Manufacturing & Wholesale Goods"
        }
    ],
    "sg:phone":"+1 219 932 3340",
    "sg:postcode":"46327",
    "sg:province":"IN",
    "sg:tags":[
        "concrete",
        "product"
    ],
    "wof:name":"Calumet Flexicore Corp",
    "wof:placetype":"venue"
},
  "geometry": {"coordinates":[-87.51864999999999,41.629164],"type":"Point"}
}