{
  "type": "Feature",
  "properties": {
    "iso:country":"US",
    "sg:address":"4008 N Rosewood Dr",
    "sg:city":"Bloomington",
    "sg:classifiers":[
        {
            "category":"Professional",
            "subcategory":"Business Services",
            "type":"Services"
        }
    ],
    "sg:phone":"+1 812 339 4446",
    "sg:postcode":"47404",
    "sg:province":"IN",
    "wof:name":"Audio Recording Service",
    "wof:placetype":"venue"
},
  "geometry": {"coordinates":[-86.54869600000001,39.205731],"type":"Point"}
}