{
  "type": "Feature",
  "properties": {
    "iso:country":"US",
    "sg:address":"2817 Westbrook Dr",
    "sg:city":"Fort Wayne",
    "sg:classifiers":[
        {
            "category":"Professional",
            "subcategory":"Management & Consulting",
            "type":"Services"
        }
    ],
    "sg:phone":"+1 260 482 2063",
    "sg:postcode":"46805",
    "sg:province":"IN",
    "sg:tags":[
        "business"
    ],
    "wof:name":"Pharos Consulting & Publ",
    "wof:placetype":"venue"
},
  "geometry": {"coordinates":[-85.143198,41.098112],"type":"Point"}
}