{
  "type": "Feature",
  "properties": {
    "addr:full":"15 Williamsburg Ct Zionsville IN 46077",
    "addr:housenumber":"15",
    "addr:postcode":"46077",
    "addr:street":"Williamsburg Ct",
    "iso:country":"US",
    "sg:address":"15 Williamsburg Ct",
    "sg:city":"Zionsville",
    "sg:classifiers":[
        {
            "category":"Organizations",
            "subcategory":"Community Association",
            "type":"Services"
        }
    ],
    "sg:phone":"+1 317 873 2134",
    "sg:postcode":"46077",
    "sg:province":"IN",
    "wof:name":"Advion Council of Zionville",
    "wof:placetype":"venue"
},
  "geometry": {"coordinates":[-86.27127900000001,39.962073],"type":"Point"}
}