{
  "type": "Feature",
  "properties": {
    "iso:country":"US",
    "sg:address":"3507 Brookside Pkwy N Dr",
    "sg:city":"Indianapolis",
    "sg:classifiers":[
        {
            "category":"Personal",
            "subcategory":"Barber",
            "type":"Services"
        }
    ],
    "sg:phone":"+1 317 637 5701",
    "sg:postcode":"46201",
    "sg:province":"IN",
    "wof:name":"Jack's Barber Shop",
    "wof:placetype":"venue"
},
  "geometry": {"coordinates":[-86.105806,39.792259],"type":"Point"}
}