{
  "type": "Feature",
  "properties": {
    "iso:country":"US",
    "sg:address":"3699 Oregon St",
    "sg:city":"Lake Station",
    "sg:classifiers":[
        {
            "category":"Professional",
            "type":"Services"
        }
    ],
    "sg:phone":"+1 219 962 9900",
    "sg:postcode":"46405",
    "sg:province":"IN",
    "sg:tags":[
        "establishment"
    ],
    "wof:name":"T J Auto",
    "wof:placetype":"venue"
},
  "geometry": {"coordinates":[-87.302567,41.551331],"type":"Point"}
}