{
  "type": "Feature",
  "properties": {
    "addr:full":"2415 Sagamore Pkwy S Lafayette IN 47905",
    "addr:housenumber":"2415",
    "addr:postcode":"47905",
    "addr:street":"Sagamore Pkwy S",
    "iso:country":"US",
    "sg:address":"2415 Sagamore Pkwy S",
    "sg:city":"Lafayette",
    "sg:classifiers":[
        {
            "category":"Shopping",
            "subcategory":"Shoes",
            "type":"Retail Goods"
        }
    ],
    "sg:phone":"+1 765 448 9438",
    "sg:postcode":"47905",
    "sg:province":"IN",
    "wof:name":"Foot Locker",
    "wof:placetype":"venue"
},
  "geometry": {"coordinates":[-86.855665,40.394737],"type":"Point"}
}