{
  "type": "Feature",
  "properties": {
    "iso:country":"US",
    "sg:address":"412 N Central Ave",
    "sg:city":"Connersville",
    "sg:classifiers":[
        {
            "category":"Social Services",
            "type":"Services"
        }
    ],
    "sg:phone":"+1 765 825 2813",
    "sg:postcode":"47331",
    "sg:province":"IN",
    "sg:tags":[
        "probation"
    ],
    "wof:name":"Fayette Probation Officer",
    "wof:placetype":"venue"
},
  "geometry": {"coordinates":[-85.139866,39.640595],"type":"Point"}
}