{
  "type": "Feature",
  "properties": {
    "iso:country":"US",
    "sg:address":"1308 E Broadway",
    "sg:city":"Logansport",
    "sg:classifiers":[
        {
            "category":"Personal",
            "subcategory":"Beauty Salon",
            "type":"Services"
        }
    ],
    "sg:phone":"+1 574 753 3503",
    "sg:postcode":"46947",
    "sg:province":"IN",
    "wof:name":"Style's On Broadway",
    "wof:placetype":"venue"
},
  "geometry": {"coordinates":[-86.352276,40.75642],"type":"Point"}
}