{
  "type": "Feature",
  "properties": {
    "iso:country":"US",
    "sg:address":"2535 E 10th St",
    "sg:city":"Anderson",
    "sg:classifiers":[
        {
            "category":"Health Services",
            "subcategory":"Optometrist",
            "type":"Services"
        }
    ],
    "sg:phone":"+1 765 643 5329",
    "sg:postcode":"46012",
    "sg:province":"IN",
    "wof:name":"Anderson Eye Care",
    "wof:placetype":"venue"
},
  "geometry": {"coordinates":[-85.64670099999999,40.105785],"type":"Point"}
}