{
  "type": "Feature",
  "properties": {
    "addr:full":"113 W 10th St Burlington IN 46938",
    "addr:housenumber":"113",
    "addr:postcode":"46938",
    "addr:street":"W 10Th St",
    "iso:country":"US",
    "sg:address":"113 W 10th St",
    "sg:city":"Burlington",
    "sg:classifiers":[
        {
            "category":"Organizations",
            "subcategory":"Religious Organization",
            "type":"Services"
        }
    ],
    "sg:phone":"+1 765 566 3729",
    "sg:postcode":"46938",
    "sg:province":"IN",
    "wof:name":"Burlington Untd Methdst Church",
    "wof:placetype":"venue"
},
  "geometry": {"coordinates":[-85.62836299999999,40.476043],"type":"Point"}
}