{
  "type": "Feature",
  "properties": {
    "iso:country":"US",
    "sg:address":"159 Holiday Pl",
    "sg:city":"Franklin",
    "sg:classifiers":[
        {
            "category":"Organizations",
            "subcategory":"Community Association",
            "type":"Services"
        }
    ],
    "sg:phone":"+1 317 738 5269",
    "sg:postcode":"46131",
    "sg:province":"IN",
    "sg:tags":[
        "club"
    ],
    "wof:name":"Millennium Night Club",
    "wof:placetype":"venue"
},
  "geometry": {"coordinates":[-86.016537,39.482156],"type":"Point"}
}