{
  "type": "Feature",
  "properties": {
    "addr:full":"8888 Keystone Xing Indianapolis IN 46240",
    "addr:housenumber":"8888",
    "addr:postcode":"46240",
    "addr:street":"Keystone Xing",
    "iso:country":"US",
    "sg:address":"8888 Keystone Xing",
    "sg:city":"Indianapolis",
    "sg:classifiers":[
        {
            "category":"Professional",
            "subcategory":"Lawyer & Legal Services",
            "type":"Services"
        }
    ],
    "sg:phone":"+1 317 573 8888",
    "sg:postcode":"46240",
    "sg:province":"IN",
    "sg:tags":[
        "living",
        "attorney",
        "law",
        "business",
        "estate",
        "wills",
        "contract",
        "planning",
        "trust",
        "probate"
    ],
    "sg:website":"http://www.cgglawfirm.com/Bio/BradleyCohen",
    "wof:name":"Cohen, Bradley H",
    "wof:placetype":"venue"
},
  "geometry": {"coordinates":[-86.109421,39.917511],"type":"Point"}
}