{
  "type": "Feature",
  "properties": {
    "iso:country":"US",
    "sg:address":"330 Lakeview Dr",
    "sg:city":"Goshen",
    "sg:classifiers":[
        {
            "category":"Health Services",
            "subcategory":"Hospital",
            "type":"Services"
        }
    ],
    "sg:phone":"+1 574 533 1234",
    "sg:postcode":"46528",
    "sg:province":"IN",
    "sg:tags":[
        "mental"
    ],
    "wof:name":"Oaklawn",
    "wof:placetype":"venue"
},
  "geometry": {"coordinates":[-85.835673,41.603502],"type":"Point"}
}