{
  "type": "Feature",
  "properties": {
    "iso:country":"US",
    "sg:address":"3055 S 200 E",
    "sg:city":"Kingman",
    "sg:phone":"+1 765 397 3059",
    "sg:postcode":"47952",
    "sg:province":"IN",
    "sg:tags":[
        "farm",
        "corn",
        "soybean"
    ],
    "wof:name":"James Graham",
    "wof:placetype":"venue"
},
  "geometry": {"coordinates":[-87.224328,40.013142],"type":"Point"}
}