{
  "type": "Feature",
  "properties": {
    "iso:country":"US",
    "sg:address":"1050 S Arlington Ave",
    "sg:city":"Indianapolis",
    "sg:classifiers":[
        {
            "category":"Building & Trades",
            "subcategory":"Construction",
            "type":"Services"
        }
    ],
    "sg:phone":"+1 317 356 2101",
    "sg:postcode":"46203",
    "sg:province":"IN",
    "sg:tags":[
        "excavating",
        "contractor"
    ],
    "wof:name":"G & W Excavators Inc",
    "wof:placetype":"venue"
},
  "geometry": {"coordinates":[-86.06398900000001,39.754214],"type":"Point"}
}