{
  "type": "Feature",
  "properties": {
    "iso:country":"US",
    "sg:address":"3489 W 86th St",
    "sg:city":"Indianapolis",
    "sg:classifiers":[
        {
            "category":"Shopping",
            "subcategory":"Department Store",
            "type":"Retail Goods"
        }
    ],
    "sg:phone":"+1 317 876 0335",
    "sg:postcode":"46268",
    "sg:province":"IN",
    "sg:tags":[
        "shop"
    ],
    "sg:website":"www.dollartree.com",
    "wof:name":"Dollar Tree",
    "wof:placetype":"venue"
},
  "geometry": {"coordinates":[-86.221248,39.911607],"type":"Point"}
}