{
  "type": "Feature",
  "properties": {
    "iso:country":"US",
    "sg:address":"106 Rolling Hills Ave",
    "sg:city":"Columbia City",
    "sg:classifiers":[
        {
            "category":"Professional",
            "type":"Services"
        }
    ],
    "sg:phone":"+1 260 244 7513",
    "sg:postcode":"46725",
    "sg:province":"IN",
    "wof:name":"Eja Inc",
    "wof:placetype":"venue"
},
  "geometry": {"coordinates":[-85.474618,41.159404],"type":"Point"}
}