{
  "type": "Feature",
  "properties": {
    "addr:full":"1948 Lanier Dr Madison IN 47250",
    "addr:housenumber":"1948",
    "addr:postcode":"47250",
    "addr:street":"Lanier Dr",
    "iso:country":"US",
    "sg:address":"1948 Lanier Dr",
    "sg:city":"Madison",
    "sg:classifiers":[
        {
            "category":"Personal",
            "subcategory":"Beauty Salon",
            "type":"Services"
        }
    ],
    "sg:phone":"+1 812 273 3761",
    "sg:postcode":"47250",
    "sg:province":"IN",
    "wof:name":"Fashion N Flair",
    "wof:placetype":"venue"
},
  "geometry": {"coordinates":[-85.40812,38.763466],"type":"Point"}
}