{
  "type": "Feature",
  "properties": {
    "iso:country":"US",
    "sg:address":"6923 Calumet Ave",
    "sg:city":"Hammond",
    "sg:classifiers":[
        {
            "category":"Retail",
            "subcategory":"Auto Repair",
            "type":"Services"
        }
    ],
    "sg:phone":"+1 219 932 1522",
    "sg:postcode":"46324",
    "sg:province":"IN",
    "sg:tags":[
        "body",
        "shop",
        "painting",
        "automobile"
    ],
    "wof:name":"Dick's Body Shop",
    "wof:placetype":"venue"
},
  "geometry": {"coordinates":[-87.508797,41.588001],"type":"Point"}
}