{
  "type": "Feature",
  "properties": {
    "addr:full":"6800 Pendleton Pike Ste A Indianapolis IN 46226",
    "addr:housenumber":"6800",
    "addr:postcode":"46226",
    "addr:street":"Pendleton Pike Ste A",
    "iso:country":"US",
    "sg:address":"6800 Pendleton Pike Ste A",
    "sg:city":"Indianapolis",
    "sg:classifiers":[
        {
            "category":"Home & Garden",
            "subcategory":"Building Materials",
            "type":"Retail Goods"
        }
    ],
    "sg:phone":"+1 317 549 2696",
    "sg:postcode":"46226",
    "sg:province":"IN",
    "sg:website":"http://www.menards.com",
    "wof:name":"Menard, Inc.",
    "wof:placetype":"venue"
},
  "geometry": {"coordinates":[-86.049217,39.825729],"type":"Point"}
}