{
  "type": "Feature",
  "properties": {
    "iso:country":"US",
    "sg:address":"9148 Louisiana St",
    "sg:city":"Merrillville",
    "sg:classifiers":[
        {
            "category":"Wholesale",
            "subcategory":"Machinery & Supplies",
            "type":"Manufacturing & Wholesale Goods"
        }
    ],
    "sg:phone":"+1 219 757 8000",
    "sg:postcode":"46410",
    "sg:province":"IN",
    "sg:tags":[
        "truck"
    ],
    "wof:name":"Powerequip Inc",
    "wof:placetype":"venue"
},
  "geometry": {"coordinates":[-87.319351,41.452045],"type":"Point"}
}