{
  "type": "Feature",
  "properties": {
    "iso:country":"US",
    "sg:address":"1740 W Sandford Ave",
    "sg:city":"West Terre Haute",
    "sg:classifiers":[
        {
            "category":"Manufacturing",
            "subcategory":"Metals",
            "type":"Manufacturing & Wholesale Goods"
        }
    ],
    "sg:phone":"+1 812 533 5501",
    "sg:postcode":"47885",
    "sg:province":"IN",
    "sg:tags":[
        "stampings",
        "mfg"
    ],
    "wof:name":"Jag Metal Spinning Inc",
    "wof:placetype":"venue"
},
  "geometry": {"coordinates":[-87.440936,39.541062],"type":"Point"}
}