{
  "type": "Feature",
  "properties": {
    "iso:country":"US",
    "sg:address":"532 Runnymede Ave",
    "sg:city":"Evansville",
    "sg:classifiers":[
        {
            "category":"Real Estate",
            "subcategory":"Real Estate Operator",
            "type":"Services"
        }
    ],
    "sg:phone":"+1 812 824 4807",
    "sg:postcode":"47714",
    "sg:province":"IN",
    "sg:tags":[
        "property",
        "lessor"
    ],
    "wof:name":"River Bend 8 Partnership LLP",
    "wof:placetype":"venue"
},
  "geometry": {"coordinates":[-87.53517100000001,37.972315],"type":"Point"}
}