{
  "type": "Feature",
  "properties": {
    "iso:country":"US",
    "sg:address":"521 Devon Dr",
    "sg:city":"Dyer",
    "sg:classifiers":[
        {
            "category":"Building & Trades",
            "subcategory":"Construction",
            "type":"Services"
        }
    ],
    "sg:phone":"+1 219 322 7747",
    "sg:postcode":"46311",
    "sg:province":"IN",
    "sg:tags":[
        "downspouts",
        "gutter"
    ],
    "wof:name":"Joy's Gutter Co",
    "wof:placetype":"venue"
},
  "geometry": {"coordinates":[-87.51648,41.500768],"type":"Point"}
}