{
  "type": "Feature",
  "properties": {
    "iso:country":"US",
    "sg:address":"507 3rd Ave",
    "sg:city":"Jasper",
    "sg:classifiers":[
        {
            "category":"Shopping",
            "subcategory":"Clothing, Apparel, & Fashions",
            "type":"Retail Goods"
        }
    ],
    "sg:phone":"+1 812 634 2797",
    "sg:postcode":"47546",
    "sg:province":"IN",
    "wof:name":"Looking Glass",
    "wof:placetype":"venue"
},
  "geometry": {"coordinates":[-86.919815,38.381277],"type":"Point"}
}