{
  "type": "Feature",
  "properties": {
    "iso:country":"US",
    "sg:address":"9121 Behner Brook Ct",
    "sg:city":"Indianapolis",
    "sg:classifiers":[
        {
            "category":"Professional",
            "type":"Services"
        }
    ],
    "sg:phone":"+1 317 842 7335",
    "sg:postcode":"46250",
    "sg:province":"IN",
    "wof:name":"D&D Hilgendorf Family Ltd",
    "wof:placetype":"venue"
},
  "geometry": {"coordinates":[-86.057447,39.920579],"type":"Point"}
}