{
  "type": "Feature",
  "properties": {
    "addr:full":"6423 Georgetown North Blvd Fort Wayne IN 46815",
    "addr:housenumber":"6423",
    "addr:postcode":"46815",
    "addr:street":"Georgetown North Blvd",
    "iso:country":"US",
    "sg:address":"6423 Georgetown North Blvd",
    "sg:city":"Fort Wayne",
    "sg:classifiers":[
        {
            "category":"Banks & Credit Unions",
            "subcategory":"Bank",
            "type":"Services"
        }
    ],
    "sg:phone":"+1 260 969 8550",
    "sg:postcode":"46815",
    "sg:province":"IN",
    "sg:tags":[
        "loan",
        "real estate"
    ],
    "wof:name":"Allied Home Mortgage Capital",
    "wof:placetype":"venue"
},
  "geometry": {"coordinates":[-85.059485,41.103636],"type":"Point"}
}