{
  "type": "Feature",
  "properties": {
    "iso:country":"US",
    "sg:address":"420 Terrel St",
    "sg:city":"Andrews",
    "sg:classifiers":[
        {
            "category":"Social Services",
            "subcategory":"Child Care",
            "type":"Services"
        }
    ],
    "sg:phone":"+1 260 786 1780",
    "sg:postcode":"46702",
    "sg:province":"IN",
    "wof:name":"Andrew's Daycare",
    "wof:placetype":"venue"
},
  "geometry": {"coordinates":[-85.606903,40.860708],"type":"Point"}
}