{
  "type": "Feature",
  "properties": {
    "iso:country":"US",
    "sg:address":"810 Lincolnwood Ln",
    "sg:city":"Indianapolis",
    "sg:classifiers":[
        {
            "category":"Wholesale",
            "subcategory":"Furniture",
            "type":"Manufacturing & Wholesale Goods"
        }
    ],
    "sg:phone":"+1 317 465 0878",
    "sg:postcode":"46260",
    "sg:province":"IN",
    "wof:name":"Wright Line",
    "wof:placetype":"venue"
},
  "geometry": {"coordinates":[-86.17352,39.874947],"type":"Point"}
}