{
  "type": "Feature",
  "properties": {
    "iso:country":"US",
    "sg:address":"1280 W Main St",
    "sg:city":"Greenfield",
    "sg:classifiers":[
        {
            "category":"Shopping",
            "subcategory":"Discount & Variety Stores",
            "type":"Retail Goods"
        }
    ],
    "sg:phone":"+1 317 462 4591",
    "sg:postcode":"46140",
    "sg:province":"IN",
    "sg:tags":[
        "merchandise",
        "general"
    ],
    "wof:name":"Hancock Developing & Supply",
    "wof:placetype":"venue"
},
  "geometry": {"coordinates":[-85.787856,39.784395],"type":"Point"}
}