{
  "type": "Feature",
  "properties": {
    "iso:country":"US",
    "sg:address":"62 S Park Blvd",
    "sg:city":"Greenwood",
    "sg:classifiers":[
        {
            "category":"Wholesale",
            "subcategory":"Electrical",
            "type":"Manufacturing & Wholesale Goods"
        }
    ],
    "sg:phone":"+1 317 264 1815",
    "sg:postcode":"46143",
    "sg:province":"IN",
    "sg:tags":[
        "alarm",
        "burglar",
        "system"
    ],
    "sg:website":"www.protectionone.com",
    "wof:name":"Protection One Inc",
    "wof:placetype":"venue"
},
  "geometry": {"coordinates":[-86.07759299999999,39.617535],"type":"Point"}
}