{
  "type": "Feature",
  "properties": {
    "iso:country":"US",
    "sg:address":"2305 N Kentucky Ave",
    "sg:city":"Evansville",
    "sg:classifiers":[
        {
            "category":"Manufacturing",
            "subcategory":"Tools & Machinery",
            "type":"Manufacturing & Wholesale Goods"
        }
    ],
    "sg:phone":"+1 812 422 9627",
    "sg:postcode":"47711",
    "sg:province":"IN",
    "sg:tags":[
        "mold"
    ],
    "wof:name":"Focus Mold & Machine",
    "wof:placetype":"venue"
},
  "geometry": {"coordinates":[-87.547243,37.996704],"type":"Point"}
}