{
  "type": "Feature",
  "properties": {
    "iso:country":"US",
    "sg:address":"3771 S A St",
    "sg:city":"Richmond",
    "sg:classifiers":[
        {
            "category":"Government",
            "subcategory":"Office",
            "type":"Public Place"
        }
    ],
    "sg:phone":"+1 765 966 4218",
    "sg:postcode":"47374",
    "sg:province":"IN",
    "wof:name":"Indiana Appellate Section",
    "wof:placetype":"venue"
},
  "geometry": {"coordinates":[-84.848124,39.826482],"type":"Point"}
}