{
  "type": "Feature",
  "properties": {
    "iso:country":"US",
    "sg:address":"118 W Main St",
    "sg:city":"Crawfordsville",
    "sg:classifiers":[
        {
            "category":"Organizations",
            "subcategory":"Non-profit Organization",
            "type":"Services"
        }
    ],
    "sg:phone":"+1 765 362 1267",
    "sg:postcode":"47933",
    "sg:province":"IN",
    "sg:website":"www.mc-cf.org",
    "wof:name":"Montgomery County Comm Fndtn",
    "wof:placetype":"venue"
},
  "geometry": {"coordinates":[-86.90140599999999,40.041722],"type":"Point"}
}