{
  "type": "Feature",
  "properties": {
    "iso:country":"US",
    "sg:address":"411 W Main St",
    "sg:city":"Fort Wayne",
    "sg:classifiers":[
        {
            "category":"Organizations",
            "subcategory":"Community Association",
            "type":"Services"
        }
    ],
    "sg:phone":"+1 260 422 7122",
    "sg:postcode":"46802",
    "sg:province":"IN",
    "wof:name":"Mizpah Shrine Circus",
    "wof:placetype":"venue"
},
  "geometry": {"coordinates":[-85.146143,41.079259],"type":"Point"}
}