{
  "type": "Feature",
  "properties": {
    "addr:full":"2707 W Broadway St Princeton IN 47670",
    "addr:housenumber":"2707",
    "addr:postcode":"47670",
    "addr:street":"W Broadway St",
    "iso:country":"US",
    "sg:address":"2707 W Broadway St",
    "sg:city":"Princeton",
    "sg:classifiers":[
        {
            "category":"Shopping",
            "subcategory":"Department Store",
            "type":"Retail Goods"
        },
        {
            "category":"Shopping",
            "type":"Retail Goods"
        },
        {
            "category":"Shopping",
            "subcategory":"Discount & Variety Stores",
            "type":"Retail Goods"
        }
    ],
    "sg:phone":"+1 812 385 2635",
    "sg:postcode":"47670",
    "sg:province":"IN",
    "sg:tags":[
        "merchandise"
    ],
    "sg:website":"http://www.dollartree.com/",
    "wof:name":"Dollar Tree",
    "wof:placetype":"venue"
},
  "geometry": {"coordinates":[-87.56075300000001,38.354626],"type":"Point"}
}