{
  "type": "Feature",
  "properties": {
    "iso:country":"US",
    "sg:address":"7450 N 1175 E",
    "sg:city":"Hartsville",
    "sg:classifiers":[
        {
            "category":"Farming",
            "subcategory":"Livestock Farm",
            "type":"Manufacturing & Wholesale Goods"
        }
    ],
    "sg:phone":"+1 812 546 4246",
    "sg:postcode":"47244",
    "sg:province":"IN",
    "sg:tags":[
        "wheat",
        "beef",
        "corn",
        "soybean",
        "cattle",
        "feedlot"
    ],
    "wof:name":"Roberts Farms",
    "wof:placetype":"venue"
},
  "geometry": {"coordinates":[-85.69144,39.269278],"type":"Point"}
}