{
  "type": "Feature",
  "properties": {
    "iso:country":"US",
    "sg:address":"6165 Central Ave",
    "sg:city":"Portage",
    "sg:classifiers":[
        {
            "category":"Professional",
            "subcategory":"Lawyer & Legal Services",
            "type":"Services"
        }
    ],
    "sg:phone":"+1 219 762 7718",
    "sg:postcode":"46368",
    "sg:province":"IN",
    "sg:tags":[
        "attorney"
    ],
    "wof:name":"Sarkisian & Fleming",
    "wof:placetype":"venue"
},
  "geometry": {"coordinates":[-87.17701099999999,41.575758],"type":"Point"}
}