{
  "type": "Feature",
  "properties": {
    "iso:country":"US",
    "sg:address":"2533 W 16th St",
    "sg:city":"Indianapolis",
    "sg:classifiers":[
        {
            "category":"Autos & Motor Vehicles",
            "subcategory":"Automobile Sales",
            "type":"Retail Goods"
        }
    ],
    "sg:phone":"+1 317 631 4737",
    "sg:postcode":"46222",
    "sg:province":"IN",
    "sg:tags":[
        "car",
        "dealer"
    ],
    "wof:name":"Curtis Auto Sales Inc",
    "wof:placetype":"venue"
},
  "geometry": {"coordinates":[-86.203825,39.787887],"type":"Point"}
}