{
  "type": "Feature",
  "properties": {
    "iso:country":"US",
    "sg:address":"250 W Main St",
    "sg:city":"Mt Summit",
    "sg:classifiers":[
        {
            "category":"Banks & Credit Unions",
            "subcategory":"Bank",
            "type":"Services"
        }
    ],
    "sg:phone":"+1 765 836 4231",
    "sg:postcode":"47361",
    "sg:province":"IN",
    "wof:name":"Citizens State Bank",
    "wof:placetype":"venue"
},
  "geometry": {"coordinates":[-85.387643,40.004587],"type":"Point"}
}