{
  "type": "Feature",
  "properties": {
    "iso:country":"US",
    "sg:address":"8847 Commerce Park Pl",
    "sg:city":"Indianapolis",
    "sg:classifiers":[
        {
            "category":"Personal",
            "type":"Services"
        },
        {
            "category":"Arena",
            "subcategory":"Sports Club",
            "type":"Entertainment"
        }
    ],
    "sg:phone":"+1 317 876 3657",
    "sg:postcode":"46268",
    "sg:province":"IN",
    "sg:tags":[
        "image",
        "health",
        "consultants-personal"
    ],
    "wof:name":"Indiana Premier",
    "wof:placetype":"venue"
},
  "geometry": {"coordinates":[-86.23294300000001,39.913165],"type":"Point"}
}