{
  "type": "Feature",
  "properties": {
    "iso:country":"US",
    "sg:address":"816 W 30th St",
    "sg:city":"Indianapolis",
    "sg:classifiers":[
        {
            "category":"Organizations",
            "subcategory":"Community Association",
            "type":"Services"
        }
    ],
    "sg:phone":"+1 317 283 1607",
    "sg:postcode":"46208",
    "sg:province":"IN",
    "sg:tags":[
        "club"
    ],
    "wof:name":"Fountain Lounge",
    "wof:placetype":"venue"
},
  "geometry": {"coordinates":[-86.175522,39.810175],"type":"Point"}
}