{
  "type": "Feature",
  "properties": {
    "iso:country":"US",
    "sg:address":"1700 5th St",
    "sg:city":"Laporte",
    "sg:classifiers":[
        {
            "category":"Building & Trades",
            "subcategory":"Construction",
            "type":"Services"
        }
    ],
    "sg:phone":"+1 219 362 3880",
    "sg:postcode":"46350",
    "sg:province":"IN",
    "sg:tags":[
        "home",
        "improvement"
    ],
    "wof:name":"Pioneer Construction",
    "wof:placetype":"venue"
},
  "geometry": {"coordinates":[-86.742962,41.603216],"type":"Point"}
}