{
  "type": "Feature",
  "properties": {
    "iso:country":"US",
    "sg:address":"5106 N Michigan Rd",
    "sg:city":"Indianapolis",
    "sg:classifiers":[
        {
            "category":"Shopping",
            "subcategory":"Used Merchandise",
            "type":"Retail Goods"
        }
    ],
    "sg:phone":"+1 317 254 0957",
    "sg:postcode":"46228",
    "sg:province":"IN",
    "sg:tags":[
        "antique"
    ],
    "wof:name":"Catalpa Inc",
    "wof:placetype":"venue"
},
  "geometry": {"coordinates":[-86.191047,39.845825],"type":"Point"}
}