{
  "type": "Feature",
  "properties": {
    "addr:full":"1002 S Meridian St Portland IN 47371",
    "addr:housenumber":"1002",
    "addr:postcode":"47371",
    "addr:street":"S Meridian St",
    "iso:country":"US",
    "sg:address":"1002 S Meridian St",
    "sg:city":"Portland",
    "sg:classifiers":[
        {
            "category":"Farming",
            "subcategory":"Farm",
            "type":"Manufacturing & Wholesale Goods"
        }
    ],
    "sg:phone":"+1 260 726 3946",
    "sg:postcode":"47371",
    "sg:province":"IN",
    "sg:tags":[
        "crop",
        "general"
    ],
    "wof:name":"Jackie Nelson",
    "wof:placetype":"venue"
},
  "geometry": {"coordinates":[-84.97764100000001,40.421344],"type":"Point"}
}