{
  "type": "Feature",
  "properties": {
    "iso:country":"US",
    "sg:address":"4035 Millersville Rd",
    "sg:city":"Indianapolis",
    "sg:classifiers":[
        {
            "category":"Animal Shelter",
            "type":"Public Place"
        },
        {
            "category":"Building & Trades",
            "subcategory":"Pest Control",
            "type":"Services"
        }
    ],
    "sg:phone":"+1 317 545 1275",
    "sg:postcode":"46205",
    "sg:province":"IN",
    "sg:tags":[
        "removal",
        "termite",
        "bee"
    ],
    "sg:website":"http://www.seeabug.net",
    "wof:name":"Arab Termite & Pest Control",
    "wof:placetype":"venue"
},
  "geometry": {"coordinates":[-86.12397799999999,39.829281],"type":"Point"}
}