{
  "type": "Feature",
  "properties": {
    "iso:country":"US",
    "sg:address":"17163 N 200 W",
    "sg:city":"Summitville",
    "sg:classifiers":[
        {
            "category":"Farming",
            "subcategory":"Farm",
            "type":"Manufacturing & Wholesale Goods"
        }
    ],
    "sg:phone":"+1 765 536 2784",
    "sg:postcode":"46070",
    "sg:province":"IN",
    "sg:tags":[
        "crop",
        "general"
    ],
    "wof:name":"Barbara E Hunter",
    "wof:placetype":"venue"
},
  "geometry": {"coordinates":[-85.709022,40.360708],"type":"Point"}
}