{
  "type": "Feature",
  "properties": {
    "iso:country":"US",
    "sg:address":"722 W Main St",
    "sg:city":"Madison",
    "sg:classifiers":[
        {
            "category":"Professional",
            "type":"Services"
        }
    ],
    "sg:phone":"+1 812 273 8726",
    "sg:postcode":"47250",
    "sg:province":"IN",
    "sg:tags":[
        "establishment"
    ],
    "wof:name":"SBP",
    "wof:placetype":"venue"
},
  "geometry": {"coordinates":[-85.387922,38.737805],"type":"Point"}
}