{
  "type": "Feature",
  "properties": {
    "addr:full":"11123 S 400 E Warren IN 46792",
    "addr:housenumber":"11123;400 e",
    "addr:postcode":"in 46792",
    "addr:street":"S",
    "iso:country":"US",
    "sg:address":"11123 S 400 E",
    "sg:city":"Warren",
    "sg:classifiers":[
        {
            "category":"Wholesale",
            "subcategory":"Machinery & Supplies",
            "type":"Manufacturing & Wholesale Goods"
        }
    ],
    "sg:phone":"+1 260 375 4144",
    "sg:postcode":"46792",
    "sg:province":"IN",
    "sg:tags":[
        "compressor",
        "gas"
    ],
    "wof:name":"Brooks Air Compressor Svc",
    "wof:placetype":"venue"
},
  "geometry": {"coordinates":[-85.372829,40.667146],"type":"Point"}
}