{
  "type": "Feature",
  "properties": {
    "iso:country":"US",
    "sg:address":"307 Wallace Ave",
    "sg:city":"Indianapolis",
    "sg:classifiers":[
        {
            "category":"Retail",
            "subcategory":"Repair Shop",
            "type":"Services"
        }
    ],
    "sg:phone":"+1 317 357 7306",
    "sg:postcode":"46201",
    "sg:province":"IN",
    "wof:name":"Cornwell Trmdle Cab Rfinishing",
    "wof:placetype":"venue"
},
  "geometry": {"coordinates":[-86.088751,39.77476],"type":"Point"}
}