{
  "type": "Feature",
  "properties": {
    "addr:full":"7631 Reynolds Rd Camby IN 46113",
    "addr:housenumber":"7631",
    "addr:postcode":"46113",
    "addr:street":"Reynolds Rd",
    "iso:country":"US",
    "sg:address":"7631 Reynolds Rd",
    "sg:city":"Camby",
    "sg:classifiers":[
        {
            "category":"Wholesale",
            "subcategory":"Toys & Hobbies",
            "type":"Manufacturing & Wholesale Goods"
        }
    ],
    "sg:phone":"+1 317 821 0805",
    "sg:postcode":"46113",
    "sg:province":"IN",
    "sg:tags":[
        "instrument",
        "scientific",
        "apparatus"
    ],
    "sg:website":"www.eurekascience.com",
    "wof:name":"Eureka Science Corp",
    "wof:placetype":"venue"
},
  "geometry": {"coordinates":[-86.29474,39.659157],"type":"Point"}
}