{
  "type": "Feature",
  "properties": {
    "addr:full":"5555 W State Rte 62 Boonville IN 47601",
    "addr:housenumber":"5555",
    "addr:postcode":"47601",
    "addr:street":"W State Rte 62",
    "iso:country":"US",
    "sg:address":"5555 W State Rte 62",
    "sg:city":"Boonville",
    "sg:classifiers":[
        {
            "category":"Autos & Motor Vehicles",
            "subcategory":"Automobile Sales",
            "type":"Retail Goods"
        }
    ],
    "sg:phone":"+1 812 925 6410",
    "sg:postcode":"47601",
    "sg:province":"IN",
    "sg:tags":[
        "car",
        "dealer"
    ],
    "wof:name":"Southern Indiana Auto Sales",
    "wof:placetype":"venue"
},
  "geometry": {"coordinates":[-87.348996,38.04529],"type":"Point"}
}