{
  "type": "Feature",
  "properties": {
    "addr:full":"46 Sunset Trl Portage IN 46368",
    "addr:housenumber":"46",
    "addr:postcode":"46368",
    "addr:street":"Sunset Trl",
    "iso:country":"US",
    "sg:address":"46 Sunset Trl",
    "sg:city":"Portage",
    "sg:classifiers":[
        {
            "category":"Wholesale",
            "subcategory":"Machinery & Supplies",
            "type":"Manufacturing & Wholesale Goods"
        }
    ],
    "sg:phone":"+1 219 762 1077",
    "sg:postcode":"46368",
    "sg:province":"IN",
    "sg:tags":[
        "contractor"
    ],
    "wof:name":"Green Pipe & Supply",
    "wof:placetype":"venue"
},
  "geometry": {"coordinates":[-87.199045,41.624289],"type":"Point"}
}