{
  "type": "Feature",
  "properties": {
    "iso:country":"US",
    "sg:address":"501 John St",
    "sg:city":"Evansville",
    "sg:classifiers":[
        {
            "category":"Social Services",
            "subcategory":"Job Training",
            "type":"Services"
        }
    ],
    "sg:phone":"+1 812 423 4914",
    "sg:postcode":"47713",
    "sg:province":"IN",
    "sg:tags":[
        "employment"
    ],
    "wof:name":"ACS State & Local Solutions",
    "wof:placetype":"venue"
},
  "geometry": {"coordinates":[-87.55669399999999,37.976369],"type":"Point"}
}