{
  "type": "Feature",
  "properties": {
    "iso:country":"US",
    "sg:address":"5980 W 71st St",
    "sg:city":"Indianapolis",
    "sg:classifiers":[
        {
            "category":"Professional",
            "subcategory":"Computer Services",
            "type":"Services"
        }
    ],
    "sg:phone":"+1 317 329 2722",
    "sg:postcode":"46278",
    "sg:province":"IN",
    "sg:tags":[
        "consultant",
        "designer"
    ],
    "wof:name":"Advanced Science & Automation",
    "wof:placetype":"venue"
},
  "geometry": {"coordinates":[-86.26766000000001,39.881664],"type":"Point"}
}