{
  "type": "Feature",
  "properties": {
    "iso:country":"US",
    "sg:address":"113 W Franklin St",
    "sg:city":"Delphi",
    "sg:classifiers":[
        {
            "category":"Professional",
            "subcategory":"Lawyer & Legal Services",
            "type":"Services"
        }
    ],
    "sg:phone":"+1 765 564 2078",
    "sg:postcode":"46923",
    "sg:province":"IN",
    "sg:tags":[
        "attorney"
    ],
    "wof:name":"Ives & Ives",
    "wof:placetype":"venue"
},
  "geometry": {"coordinates":[-86.67468599999999,40.587008],"type":"Point"}
}