{
  "type": "Feature",
  "properties": {
    "iso:country":"US",
    "sg:address":"310 East St",
    "sg:city":"Madison",
    "sg:classifiers":[
        {
            "category":"Real Estate",
            "subcategory":"Real Estate Operator",
            "type":"Services"
        }
    ],
    "sg:phone":"+1 812 265 1586",
    "sg:postcode":"47250",
    "sg:province":"IN",
    "sg:tags":[
        "apartment"
    ],
    "wof:name":"Valley Manor Apartments",
    "wof:placetype":"venue"
},
  "geometry": {"coordinates":[-85.374225,38.736149],"type":"Point"}
}