{
  "type": "Feature",
  "properties": {
    "iso:country":"US",
    "sg:address":"319 E 13th St",
    "sg:city":"Indianapolis",
    "sg:classifiers":[
        {
            "category":"Shopping",
            "subcategory":"Used Merchandise",
            "type":"Retail Goods"
        }
    ],
    "sg:phone":"+1 317 637 7350",
    "sg:postcode":"46202",
    "sg:province":"IN",
    "wof:name":"Mobile Merchant The",
    "wof:placetype":"venue"
},
  "geometry": {"coordinates":[-86.15164799999999,39.784409],"type":"Point"}
}