{
  "type": "Feature",
  "properties": {
    "addr:full":"421 S Range Line Rd Carmel IN 46032",
    "addr:housenumber":"421",
    "addr:postcode":"46032",
    "addr:street":"S Range Line Rd",
    "iso:country":"US",
    "sg:address":"421 S Range Line Rd",
    "sg:city":"Carmel",
    "sg:classifiers":[
        {
            "category":"Building & Trades",
            "subcategory":"Landscaping Services",
            "type":"Services"
        }
    ],
    "sg:phone":"+1 317 575 0482",
    "sg:postcode":"46032",
    "sg:province":"IN",
    "sg:tags":[
        "landscape",
        "contractor"
    ],
    "wof:name":"Natureworks Inc",
    "wof:placetype":"venue"
},
  "geometry": {"coordinates":[-86.12697799999999,39.974564],"type":"Point"}
}