{
  "type": "Feature",
  "properties": {
    "iso:country":"US",
    "sg:address":"2320 E Stop 11 Rd",
    "sg:city":"Indianapolis",
    "sg:classifiers":[
        {
            "category":"Food & Beverages",
            "subcategory":"Groceries & Convenience Stores",
            "type":"Retail Goods"
        }
    ],
    "sg:phone":"+1 317 885 7170",
    "sg:postcode":"46227",
    "sg:province":"IN",
    "sg:tags":[
        "grocer"
    ],
    "wof:name":"Nest Indian Grocery",
    "wof:placetype":"venue"
},
  "geometry": {"coordinates":[-86.118529,39.650345],"type":"Point"}
}