{
  "type": "Feature",
  "properties": {
    "iso:country":"US",
    "sg:address":"6701 Rocklane Rd",
    "sg:city":"Greenwood",
    "sg:classifiers":[
        {
            "category":"Personal",
            "subcategory":"Shoe Repair & Shine",
            "type":"Services"
        }
    ],
    "sg:phone":"+1 317 862 9936",
    "sg:postcode":"46143",
    "sg:province":"IN",
    "sg:tags":[
        "parlor"
    ],
    "wof:name":"Dominics of Indiana Inc",
    "wof:placetype":"venue"
},
  "geometry": {"coordinates":[-85.977293,39.60195],"type":"Point"}
}