{
  "type": "Feature",
  "properties": {
    "iso:country":"US",
    "sg:address":"10722 E Washington St",
    "sg:city":"Indianapolis",
    "sg:classifiers":[
        {
            "category":"Retail",
            "subcategory":"Funeral Services",
            "type":"Services"
        }
    ],
    "sg:phone":"+1 317 899 7115",
    "sg:postcode":"46229",
    "sg:province":"IN",
    "sg:tags":[
        "director"
    ],
    "wof:name":"Flanner & Buchanan Mortuaries",
    "wof:placetype":"venue"
},
  "geometry": {"coordinates":[-85.974358,39.775675],"type":"Point"}
}