{
  "type": "Feature",
  "properties": {
    "iso:country":"US",
    "sg:address":"1330 Sheffield Ave",
    "sg:city":"Dyer",
    "sg:classifiers":[
        {
            "category":"Shopping",
            "subcategory":"Bicycles & Sporting Goods",
            "type":"Retail Goods"
        }
    ],
    "sg:phone":"+1 219 864 8678",
    "sg:postcode":"46311",
    "sg:province":"IN",
    "sg:tags":[
        "apparel",
        "bowling",
        "accessory"
    ],
    "wof:name":"Kofoid's Pro Shop",
    "wof:placetype":"venue"
},
  "geometry": {"coordinates":[-87.518848,41.507106],"type":"Point"}
}