{
  "type": "Feature",
  "properties": {
    "addr:full":"7699 N Pennsylvania St Indianapolis IN 46240",
    "addr:housenumber":"7699",
    "addr:postcode":"46240",
    "addr:street":"N Pennsylvania St",
    "iso:country":"US",
    "sg:address":"7699 N Pennsylvania St",
    "sg:city":"Indianapolis",
    "sg:classifiers":[
        {
            "category":"Wholesale",
            "subcategory":"Durable Goods & Equipment",
            "type":"Manufacturing & Wholesale Goods"
        }
    ],
    "sg:phone":"+1 317 251 4300",
    "sg:postcode":"46240",
    "sg:province":"IN",
    "sg:tags":[
        "representative",
        "manufacturer"
    ],
    "wof:name":"Marr & Assoc Inc",
    "wof:placetype":"venue"
},
  "geometry": {"coordinates":[-86.155396,39.897186],"type":"Point"}
}