{
  "type": "Feature",
  "properties": {
    "iso:country":"US",
    "sg:address":"2704 N Gale St",
    "sg:city":"Indianapolis",
    "sg:classifiers":[
        {
            "category":"Home & Garden",
            "subcategory":"Hardware",
            "type":"Retail Goods"
        }
    ],
    "sg:phone":"+1 317 546 3530",
    "sg:postcode":"46218",
    "sg:province":"IN",
    "wof:name":"Smith Brothers Tool",
    "wof:placetype":"venue"
},
  "geometry": {"coordinates":[-86.105796,39.804471],"type":"Point"}
}