{
  "type": "Feature",
  "properties": {
    "iso:country":"US",
    "sg:address":"8236 N 225 W",
    "sg:city":"Delphi",
    "sg:classifiers":[
        {
            "category":"Real Estate",
            "subcategory":"Real Estate Agent",
            "type":"Services"
        }
    ],
    "sg:phone":"+1 574 686 2667",
    "sg:postcode":"46923",
    "sg:province":"IN",
    "wof:name":"G & K Real Estate Inc",
    "wof:placetype":"venue"
},
  "geometry": {"coordinates":[-86.567927,40.663932],"type":"Point"}
}