{
  "type": "Feature",
  "properties": {
    "iso:country":"US",
    "sg:address":"6406 Green Leaves Rd",
    "sg:city":"Indianapolis",
    "sg:classifiers":[
        {
            "category":"Wholesale",
            "subcategory":"Durable Goods & Equipment",
            "type":"Manufacturing & Wholesale Goods"
        }
    ],
    "sg:phone":"+1 317 465 9950",
    "sg:postcode":"46220",
    "sg:province":"IN",
    "sg:tags":[
        "representative",
        "manufacturer"
    ],
    "wof:name":"Tanksley & Assoc",
    "wof:placetype":"venue"
},
  "geometry": {"coordinates":[-86.074969,39.87217],"type":"Point"}
}