{
  "type": "Feature",
  "properties": {
    "iso:country":"US",
    "sg:address":"8215 Schoen Dr",
    "sg:city":"Indianapolis",
    "sg:classifiers":[
        {
            "category":"Building & Trades",
            "subcategory":"Construction",
            "type":"Services"
        }
    ],
    "sg:phone":"+1 317 545 9321",
    "sg:postcode":"46226",
    "sg:province":"IN",
    "sg:tags":[
        "house"
    ],
    "wof:name":"REO Service Inc",
    "wof:placetype":"venue"
},
  "geometry": {"coordinates":[-86.021615,39.845894],"type":"Point"}
}