{
  "type": "Feature",
  "properties": {
    "addr:full":"115 N Weinbach Ave Evansville IN 47711",
    "addr:housenumber":"115",
    "addr:postcode":"47711",
    "addr:street":"N Weinbach Ave",
    "iso:country":"US",
    "sg:address":"115 N Weinbach Ave",
    "sg:city":"Evansville",
    "sg:classifiers":[
        {
            "category":"Professional",
            "subcategory":"Computer Services",
            "type":"Services"
        }
    ],
    "sg:phone":"+1 812 424 4357",
    "sg:postcode":"47711",
    "sg:province":"IN",
    "sg:tags":[
        "repair"
    ],
    "wof:name":"On-Site Computer Solutions",
    "wof:placetype":"venue"
},
  "geometry": {"coordinates":[-87.529253,37.977277],"type":"Point"}
}