{
  "type": "Feature",
  "properties": {
    "iso:country":"US",
    "sg:address":"2540 W 200 N",
    "sg:city":"Greenfield",
    "sg:classifiers":[
        {
            "category":"Farming",
            "subcategory":"Farm",
            "type":"Manufacturing & Wholesale Goods"
        }
    ],
    "sg:phone":"+1 317 326 4592",
    "sg:postcode":"46140",
    "sg:province":"IN",
    "sg:tags":[
        "crop",
        "general"
    ],
    "wof:name":"Jeff Bricker",
    "wof:placetype":"venue"
},
  "geometry": {"coordinates":[-85.848454,39.813095],"type":"Point"}
}