{
  "type": "Feature",
  "properties": {
    "iso:country":"US",
    "sg:address":"1352 Lincolnway S",
    "sg:city":"Ligonier",
    "sg:classifiers":[
        {
            "category":"Home & Garden",
            "subcategory":"Hardware",
            "type":"Retail Goods"
        }
    ],
    "sg:phone":"+1 260 894 3404",
    "sg:postcode":"46767",
    "sg:province":"IN",
    "wof:name":"Ace Hardware",
    "wof:placetype":"venue"
},
  "geometry": {"coordinates":[-85.500058,41.337933],"type":"Point"}
}