{
  "type": "Feature",
  "properties": {
    "iso:country":"US",
    "sg:address":"304 E Co Rd 650 S",
    "sg:city":"Clay City",
    "sg:classifiers":[
        {
            "category":"Travel",
            "subcategory":"Campground",
            "type":"Entertainment"
        }
    ],
    "sg:phone":"+1 812 939 2896",
    "sg:postcode":"47841",
    "sg:province":"IN",
    "wof:name":"Free Methodist Camp Grnd",
    "wof:placetype":"venue"
},
  "geometry": {"coordinates":[-87.104767,39.292117],"type":"Point"}
}