{
  "type": "Feature",
  "properties": {
    "addr:full":"6 Commercial Rd Huntington IN 46750",
    "addr:housenumber":"6",
    "addr:postcode":"46750",
    "addr:street":"Commercial Rd",
    "iso:country":"US",
    "sg:address":"6 Commercial Rd",
    "sg:city":"Huntington",
    "sg:classifiers":[
        {
            "category":"Wholesale",
            "subcategory":"Electrical",
            "type":"Manufacturing & Wholesale Goods"
        }
    ],
    "sg:phone":"+1 260 356 2060",
    "sg:postcode":"46750",
    "sg:province":"IN",
    "sg:tags":[
        "equipment",
        "transformer",
        "mfg"
    ],
    "wof:name":"Schneider Electric",
    "wof:placetype":"venue"
},
  "geometry": {"coordinates":[-85.525441,40.892041],"type":"Point"}
}