{
  "type": "Feature",
  "properties": {
    "iso:country":"US",
    "sg:address":"4413 E 925 N",
    "sg:city":"Madison",
    "sg:classifiers":[
        {
            "category":"Organizations",
            "subcategory":"Religious Organization",
            "type":"Services"
        }
    ],
    "sg:phone":"+1 812 839 3005",
    "sg:postcode":"47250",
    "sg:province":"IN",
    "sg:tags":[
        "church"
    ],
    "wof:name":"Indian Kentucky Baptist Church",
    "wof:placetype":"venue"
},
  "geometry": {"coordinates":[-85.307677,38.872851],"type":"Point"}
}