{
  "type": "Feature",
  "properties": {
    "iso:country":"US",
    "sg:address":"3325 Industrial Pkwy",
    "sg:city":"Jeffersonville",
    "sg:classifiers":[
        {
            "category":"Professional",
            "subcategory":"Business Services",
            "type":"Services"
        }
    ],
    "sg:phone":"+1 812 282 3773",
    "sg:postcode":"47130",
    "sg:province":"IN",
    "sg:tags":[
        "tank",
        "testing",
        "inspection"
    ],
    "wof:name":"C T Svc",
    "wof:placetype":"venue"
},
  "geometry": {"coordinates":[-85.750003,38.314084],"type":"Point"}
}