{
  "type": "Feature",
  "properties": {
    "addr:full":"870 Lennox St Zionsville IN 46012",
    "addr:housenumber":"870",
    "addr:postcode":"46012",
    "addr:street":"Lennox St",
    "iso:country":"US",
    "sg:address":"870 Lennox St",
    "sg:city":"Zionsville",
    "sg:classifiers":[
        {
            "category":"Wholesale",
            "subcategory":"Durable Goods & Equipment",
            "type":"Manufacturing & Wholesale Goods"
        }
    ],
    "sg:phone":"+1 317 873 4400",
    "sg:postcode":"46012",
    "sg:province":"IN",
    "sg:tags":[
        "laboratory",
        "supply"
    ],
    "sg:website":"www.infolabinc.com",
    "wof:name":"Infolab Inc",
    "wof:placetype":"venue"
},
  "geometry": {"coordinates":[-85.64786599999999,40.107658],"type":"Point"}
}