{
  "type": "Feature",
  "properties": {
    "iso:country":"US",
    "sg:address":"812 E Vine St",
    "sg:city":"Rensselaer",
    "sg:classifiers":[
        {
            "category":"Government",
            "subcategory":"Office",
            "type":"Public Place"
        }
    ],
    "sg:phone":"+1 219 866 8371",
    "sg:postcode":"47978",
    "sg:province":"IN",
    "sg:tags":[
        "village"
    ],
    "wof:name":"Rensselaer Line Dept",
    "wof:placetype":"venue"
},
  "geometry": {"coordinates":[-87.14187,40.942703],"type":"Point"}
}