{
  "type": "Feature",
  "properties": {
    "iso:country":"US",
    "sg:address":"1920 Hart St",
    "sg:city":"Dyer",
    "sg:classifiers":[
        {
            "category":"Retail",
            "subcategory":"Funeral Services",
            "type":"Services"
        }
    ],
    "sg:phone":"+1 219 865 2881",
    "sg:postcode":"46311",
    "sg:province":"IN",
    "sg:tags":[
        "director"
    ],
    "wof:name":"Fagen-Miller Funeral Homes Inc",
    "wof:placetype":"venue"
},
  "geometry": {"coordinates":[-87.52128999999999,41.497338],"type":"Point"}
}