{
  "type": "Feature",
  "properties": {
    "iso:country":"US",
    "sg:address":"2301 S Keystone Ave",
    "sg:city":"Indianapolis",
    "sg:classifiers":[
        {
            "category":"Building & Trades",
            "subcategory":"Construction",
            "type":"Services"
        }
    ],
    "sg:phone":"+1 317 784 5386",
    "sg:postcode":"46203",
    "sg:province":"IN",
    "sg:tags":[
        "roofing",
        "contractor"
    ],
    "wof:name":"Breeden Roofing Inc",
    "wof:placetype":"venue"
},
  "geometry": {"coordinates":[-86.120853,39.735239],"type":"Point"}
}