{
  "type": "Feature",
  "properties": {
    "iso:country":"US",
    "sg:address":"1609 E Coolspring Ave",
    "sg:city":"Michigan City",
    "sg:classifiers":[
        {
            "category":"Home & Garden",
            "subcategory":"Household Appliances",
            "type":"Retail Goods"
        }
    ],
    "sg:phone":"+1 219 872 9696",
    "sg:postcode":"46360",
    "sg:province":"IN",
    "wof:name":"Tylisz Appliance Inc",
    "wof:placetype":"venue"
},
  "geometry": {"coordinates":[-86.87244,41.694648],"type":"Point"}
}