{
  "type": "Feature",
  "properties": {
    "iso:country":"US",
    "sg:address":"2597 S Co Rd 830 E",
    "sg:city":"Frankfort",
    "sg:classifiers":[
        {
            "category":"Building & Trades",
            "subcategory":"Construction",
            "type":"Services"
        }
    ],
    "sg:phone":"+1 317 752 1003",
    "sg:postcode":"46041",
    "sg:province":"IN",
    "sg:tags":[
        "house"
    ],
    "wof:name":"McCarty Bryan Contg & Rmdlg",
    "wof:placetype":"venue"
},
  "geometry": {"coordinates":[-86.351477,40.249415],"type":"Point"}
}