{
  "type": "Feature",
  "properties": {
    "iso:country":"US",
    "sg:address":"1806 E State Rd 44",
    "sg:city":"Shelbyville",
    "sg:classifiers":[
        {
            "category":"Shopping",
            "subcategory":"Shoes",
            "type":"Retail Goods"
        }
    ],
    "sg:phone":"+1 317 398 0536",
    "sg:postcode":"46176",
    "sg:province":"IN",
    "wof:name":"Shoe Show",
    "wof:placetype":"venue"
},
  "geometry": {"coordinates":[-85.750034,39.520498],"type":"Point"}
}