{
  "type": "Feature",
  "properties": {
    "iso:country":"US",
    "sg:address":"302 N Karwick Rd",
    "sg:city":"Michigan City",
    "sg:classifiers":[
        {
            "category":"Personal",
            "subcategory":"Beauty Salon",
            "type":"Services"
        }
    ],
    "sg:phone":"+1 219 879 7088",
    "sg:postcode":"46360",
    "sg:province":"IN",
    "sg:tags":[
        "cosmetologist"
    ],
    "wof:name":"Fisk Valencia",
    "wof:placetype":"venue"
},
  "geometry": {"coordinates":[-86.85558,41.727691],"type":"Point"}
}