{
  "type": "Feature",
  "properties": {
    "iso:country":"US",
    "sg:address":"600 Vale Park Rd",
    "sg:city":"Valparaiso",
    "sg:classifiers":[
        {
            "category":"Real Estate",
            "subcategory":"Real Estate Agent",
            "type":"Services"
        }
    ],
    "sg:phone":"+1 219 464 3800",
    "sg:postcode":"46383",
    "sg:province":"IN",
    "sg:website":"www.tuckernw.com",
    "wof:name":"Fc Tucker Nw Indiana Realtors",
    "wof:placetype":"venue"
},
  "geometry": {"coordinates":[-87.055063,41.49335],"type":"Point"}
}