{
  "type": "Feature",
  "properties": {
    "iso:country":"US",
    "sg:address":"703 S Harrison St",
    "sg:city":"Shelbyville",
    "sg:classifiers":[
        {
            "category":"Retail",
            "subcategory":"Funeral Services",
            "type":"Services"
        }
    ],
    "sg:phone":"+1 317 398 6697",
    "sg:postcode":"46176",
    "sg:province":"IN",
    "sg:tags":[
        "director"
    ],
    "wof:name":"Murphy/Parks Funeral Svc",
    "wof:placetype":"venue"
},
  "geometry": {"coordinates":[-85.777122,39.51889],"type":"Point"}
}