{
  "type": "Feature",
  "properties": {
    "iso:country":"US",
    "sg:address":"1934 E Commercial Ave",
    "sg:city":"Lowell",
    "sg:classifiers":[
        {
            "category":"Real Estate",
            "subcategory":"Real Estate Agent",
            "type":"Services"
        }
    ],
    "sg:phone":"+1 219 696 9022",
    "sg:postcode":"46356",
    "sg:province":"IN",
    "sg:tags":[
        "inspection"
    ],
    "wof:name":"Ameri Spec Home Inspection Svc",
    "wof:placetype":"venue"
},
  "geometry": {"coordinates":[-87.395243,41.289776],"type":"Point"}
}