{
  "type": "Feature",
  "properties": {
    "iso:country":"US",
    "sg:address":"22425 Co Rd 42",
    "sg:city":"Goshen",
    "sg:classifiers":[
        {
            "category":"Farming",
            "subcategory":"Farm",
            "type":"Manufacturing & Wholesale Goods"
        }
    ],
    "sg:phone":"+1 574 831 2794",
    "sg:postcode":"46526",
    "sg:province":"IN",
    "wof:name":"Ruebury Farms",
    "wof:placetype":"venue"
},
  "geometry": {"coordinates":[-85.886236,41.522431],"type":"Point"}
}