{
  "type": "Feature",
  "properties": {
    "iso:country":"US",
    "sg:address":"2702 Willow Oaks Dr",
    "sg:city":"Fort Wayne",
    "sg:classifiers":[
        {
            "category":"Retail",
            "subcategory":"Repair Shop",
            "type":"Services"
        }
    ],
    "sg:phone":"+1 260 747 6589",
    "sg:postcode":"46809",
    "sg:province":"IN",
    "wof:name":"Transmitter Repair Serv",
    "wof:placetype":"venue"
},
  "geometry": {"coordinates":[-85.174995,41.036508],"type":"Point"}
}