{
  "type": "Feature",
  "properties": {
    "iso:country":"US",
    "sg:address":"1086 N State Rd 149",
    "sg:city":"Chesterton",
    "sg:classifiers":[
        {
            "category":"Shopping",
            "type":"Retail Goods"
        }
    ],
    "sg:phone":"+1 219 764 8282",
    "sg:postcode":"46304",
    "sg:province":"IN",
    "sg:tags":[
        "pet",
        "shop"
    ],
    "wof:name":"Dog Land Kennels",
    "wof:placetype":"venue"
},
  "geometry": {"coordinates":[-87.12490200000001,41.600396],"type":"Point"}
}