{
  "type": "Feature",
  "properties": {
    "iso:country":"US",
    "sg:address":"122 W State St",
    "sg:city":"Pendleton",
    "sg:classifiers":[
        {
            "category":"Personal",
            "subcategory":"Beauty Salon",
            "type":"Services"
        }
    ],
    "sg:phone":"+1 765 778 0100",
    "sg:postcode":"46064",
    "sg:province":"IN",
    "sg:tags":[
        "spa",
        "day"
    ],
    "wof:name":"Sophie's Spa-Lon",
    "wof:placetype":"venue"
},
  "geometry": {"coordinates":[-85.746505,40.002547],"type":"Point"}
}