{
  "type": "Feature",
  "properties": {
    "iso:country":"US",
    "sg:address":"9450 E 59th St",
    "sg:city":"Indianapolis",
    "sg:classifiers":[
        {
            "category":"Organizations",
            "subcategory":"Membership Organization",
            "type":"Services"
        }
    ],
    "sg:phone":"+1 317 377 1770",
    "sg:postcode":"46216",
    "sg:province":"IN",
    "sg:tags":[
        "military",
        "veteran",
        "fraternal"
    ],
    "wof:name":"Indiana State Counsel Vva",
    "wof:placetype":"venue"
},
  "geometry": {"coordinates":[-86.00190499999999,39.86283],"type":"Point"}
}