{
  "type": "Feature",
  "properties": {
    "iso:country":"US",
    "sg:address":"215 Dewey Ave",
    "sg:city":"Goshen",
    "sg:classifiers":[
        {
            "category":"Education",
            "subcategory":"School",
            "type":"Public Place"
        }
    ],
    "sg:phone":"+1 574 533 7855",
    "sg:postcode":"46526",
    "sg:province":"IN",
    "sg:website":"www.goshenschools.org",
    "wof:name":"West Goshen Elementary School",
    "wof:placetype":"venue"
},
  "geometry": {"coordinates":[-85.849103,41.584796],"type":"Point"}
}