{
  "type": "Feature",
  "properties": {
    "iso:country":"US",
    "sg:address":"6910 N Main St",
    "sg:city":"Granger",
    "sg:classifiers":[
        {
            "category":"Banks & Credit Unions",
            "subcategory":"Investment Brokerage",
            "type":"Services"
        }
    ],
    "sg:phone":"+1 574 271 0635",
    "sg:postcode":"46530",
    "sg:province":"IN",
    "sg:tags":[
        "security"
    ],
    "wof:name":"Securities America Inc",
    "wof:placetype":"venue"
},
  "geometry": {"coordinates":[-86.17803,41.722915],"type":"Point"}
}