{
  "type": "Feature",
  "properties": {
    "iso:country":"US",
    "sg:address":"60 Valparaiso St",
    "sg:city":"Valparaiso",
    "sg:classifiers":[
        {
            "category":"Building & Trades",
            "subcategory":"Construction",
            "type":"Services"
        }
    ],
    "sg:phone":"+1 219 465 4266",
    "sg:postcode":"46383",
    "sg:province":"IN",
    "sg:tags":[
        "floor"
    ],
    "wof:name":"Nu-Chem Solutions",
    "wof:placetype":"venue"
},
  "geometry": {"coordinates":[-87.056304,41.467006],"type":"Point"}
}