{
  "type": "Feature",
  "properties": {
    "iso:country":"US",
    "sg:address":"1416 Miller Ave",
    "sg:city":"Shelbyville",
    "sg:classifiers":[
        {
            "category":"Sports & Exercise",
            "subcategory":"Bowling",
            "type":"Entertainment"
        }
    ],
    "sg:phone":"+1 317 398 8481",
    "sg:postcode":"46176",
    "sg:province":"IN",
    "sg:tags":[
        "center"
    ],
    "wof:name":"44 Bowl Inc",
    "wof:placetype":"venue"
},
  "geometry": {"coordinates":[-85.79857199999999,39.507205],"type":"Point"}
}