{
  "type": "Feature",
  "properties": {
    "iso:country":"US",
    "sg:address":"102 S Wabash St",
    "sg:city":"Wabash",
    "sg:classifiers":[
        {
            "category":"Professional",
            "subcategory":"Lawyer & Legal Services",
            "type":"Services"
        }
    ],
    "sg:phone":"+1 260 563 8020",
    "sg:postcode":"46992",
    "sg:province":"IN",
    "sg:tags":[
        "attorney"
    ],
    "wof:name":"Lynn & Stein Attorneys At Law",
    "wof:placetype":"venue"
},
  "geometry": {"coordinates":[-85.820914,40.797825],"type":"Point"}
}