{
  "type": "Feature",
  "properties": {
    "iso:country":"US",
    "sg:address":"8541 Bash St",
    "sg:city":"Indianapolis",
    "sg:classifiers":[
        {
            "category":"Manufacturing",
            "subcategory":"Retail Goods",
            "type":"Manufacturing & Wholesale Goods"
        },
        {
            "category":"Wholesale",
            "subcategory":"Durable Goods & Equipment",
            "type":"Manufacturing & Wholesale Goods"
        }
    ],
    "sg:phone":"+1 317 585 0184",
    "sg:postcode":"46250",
    "sg:province":"IN",
    "sg:tags":[
        "product",
        "mfg",
        "representative",
        "manufacturer"
    ],
    "wof:name":"Schueths & Assoc",
    "wof:placetype":"venue"
},
  "geometry": {"coordinates":[-86.047078,39.911107],"type":"Point"}
}