{
  "type": "Feature",
  "properties": {
    "iso:country":"US",
    "sg:address":"403 N Main St",
    "sg:city":"Linden",
    "sg:classifiers":[
        {
            "category":"Utilities",
            "subcategory":"Electric",
            "type":"Services"
        }
    ],
    "sg:phone":"+1 765 339 7211",
    "sg:postcode":"47955",
    "sg:province":"IN",
    "sg:tags":[
        "company"
    ],
    "sg:website":"www.tipmont.org",
    "wof:name":"Tipmont Remc",
    "wof:placetype":"venue"
},
  "geometry": {"coordinates":[-86.903848,40.191385],"type":"Point"}
}