{
  "type": "Feature",
  "properties": {
    "iso:country":"US",
    "sg:address":"451 N Van Buren St",
    "sg:city":"Shipshewana",
    "sg:classifiers":[
        {
            "category":"Home & Garden",
            "subcategory":"Furniture",
            "type":"Retail Goods"
        }
    ],
    "sg:phone":"+1 260 768 4995",
    "sg:postcode":"46565",
    "sg:province":"IN",
    "sg:website":"www.shipshelogfurniture.com",
    "wof:name":"Shipshe Log Furniture & Crafts",
    "wof:placetype":"venue"
},
  "geometry": {"coordinates":[-85.580432,41.669943],"type":"Point"}
}