{
  "type": "Feature",
  "properties": {
    "addr:full":"1803 E 350 S Lafayette IN 47909",
    "addr:housenumber":"1803",
    "addr:postcode":"47909",
    "addr:street":"E 350 S",
    "iso:country":"US",
    "sg:address":"1803 E 350 S",
    "sg:city":"Lafayette",
    "sg:classifiers":[
        {
            "category":"Food & Beverages",
            "subcategory":"Groceries & Convenience Stores",
            "type":"Retail Goods"
        }
    ],
    "sg:phone":"+1 765 474 5012",
    "sg:postcode":"47909",
    "sg:province":"IN",
    "wof:name":"Supertest Mini-Mart",
    "wof:placetype":"venue"
},
  "geometry": {"coordinates":[-86.87366,40.367036],"type":"Point"}
}