{
  "type": "Feature",
  "properties": {
    "iso:country":"US",
    "sg:address":"14522 Bamboo Ct",
    "sg:city":"Mishawaka",
    "sg:classifiers":[
        {
            "category":"Building & Trades",
            "subcategory":"Cleaning & Sanitation",
            "type":"Services"
        }
    ],
    "sg:phone":"+1 574 257 8074",
    "sg:postcode":"46545",
    "sg:province":"IN",
    "sg:tags":[
        "janitorial"
    ],
    "wof:name":"Christopher Rucker",
    "wof:placetype":"venue"
},
  "geometry": {"coordinates":[-86.14895,41.704423],"type":"Point"}
}