{
  "type": "Feature",
  "properties": {
    "addr:full":"655 N Shadeland Ave Indianapolis IN 46219",
    "addr:housenumber":"655",
    "addr:postcode":"46219",
    "addr:street":"N Shadeland Ave",
    "iso:country":"US",
    "sg:address":"655 N Shadeland Ave",
    "sg:city":"Indianapolis",
    "sg:classifiers":[
        {
            "category":"Restaurant",
            "type":"Food & Drink"
        }
    ],
    "sg:menulink":"http://www.allmenus.com/in/warren/105207-ryans/menu/",
    "sg:phone":"+1 317 359 7747",
    "sg:postcode":"46219",
    "sg:province":"IN",
    "sg:tags":[
        "american"
    ],
    "wof:name":"Ryan's",
    "wof:placetype":"venue"
},
  "geometry": {"coordinates":[-86.04412000000001,39.778711],"type":"Point"}
}