{
  "type": "Feature",
  "properties": {
    "iso:country":"US",
    "sg:address":"1283 Main St",
    "sg:city":"Wolflake",
    "sg:classifiers":[
        {
            "category":"Education",
            "subcategory":"School",
            "type":"Public Place"
        }
    ],
    "sg:phone":"+1 260 635 2432",
    "sg:postcode":"46796",
    "sg:province":"IN",
    "wof:name":"Wolf Lake Elementary School",
    "wof:placetype":"venue"
},
  "geometry": {"coordinates":[-85.494376,41.335226],"type":"Point"}
}