{
  "type": "Feature",
  "properties": {
    "iso:country":"US",
    "sg:address":"3715 S Madison St",
    "sg:city":"Muncie",
    "sg:classifiers":[
        {
            "category":"Health Services",
            "subcategory":"Clinic",
            "type":"Services"
        }
    ],
    "sg:phone":"+1 765 287 9880",
    "sg:postcode":"47302",
    "sg:province":"IN",
    "sg:tags":[
        "home"
    ],
    "wof:name":"CHS Home Infusion",
    "wof:placetype":"venue"
},
  "geometry": {"coordinates":[-85.382417,40.157406],"type":"Point"}
}