{
  "type": "Feature",
  "properties": {
    "iso:country":"US",
    "sg:address":"531 S Meridian St",
    "sg:city":"Sunman",
    "sg:classifiers":[
        {
            "category":"Food & Beverages",
            "subcategory":"Liquor & Beverages",
            "type":"Retail Goods"
        }
    ],
    "sg:phone":"+1 812 623 2491",
    "sg:postcode":"47041",
    "sg:province":"IN",
    "wof:name":"Sunman Package Store",
    "wof:placetype":"venue"
},
  "geometry": {"coordinates":[-85.094525,39.230658],"type":"Point"}
}