{
  "type": "Feature",
  "properties": {
    "iso:country":"US",
    "sg:address":"921 W National Ave",
    "sg:city":"Brazil",
    "sg:classifiers":[
        {
            "category":"Autos & Motor Vehicles",
            "subcategory":"Automobile Sales",
            "type":"Retail Goods"
        }
    ],
    "sg:phone":"+1 812 448 1071",
    "sg:postcode":"47834",
    "sg:province":"IN",
    "sg:tags":[
        "car",
        "used",
        "dealer"
    ],
    "wof:name":"Stu Bauer's Auto Exchange",
    "wof:placetype":"venue"
},
  "geometry": {"coordinates":[-87.13803900000001,39.520532],"type":"Point"}
}