{
  "type": "Feature",
  "properties": {
    "iso:country":"US",
    "sg:address":"4316 Champlain Dr",
    "sg:city":"Fort Wayne",
    "sg:classifiers":[
        {
            "category":"Retail",
            "subcategory":"Repair Shop",
            "type":"Services"
        }
    ],
    "sg:phone":"+1 260 745 9292",
    "sg:postcode":"46806",
    "sg:province":"IN",
    "sg:tags":[
        "taxidermist"
    ],
    "wof:name":"AAA Thom's Quality Taxidermy",
    "wof:placetype":"venue"
},
  "geometry": {"coordinates":[-85.133295,41.045492],"type":"Point"}
}