{
  "type": "Feature",
  "properties": {
    "iso:country":"US",
    "sg:address":"5700 W Kilgore Ave",
    "sg:city":"Muncie",
    "sg:classifiers":[
        {
            "category":"Retail",
            "subcategory":"Animal Services",
            "type":"Services"
        }
    ],
    "sg:phone":"+1 765 288 8186",
    "sg:postcode":"47304",
    "sg:province":"IN",
    "sg:tags":[
        "cat",
        "dog",
        "kennel"
    ],
    "sg:website":"www.happycleanandsmart.com",
    "wof:name":"Happy Clean & Smart",
    "wof:placetype":"venue"
},
  "geometry": {"coordinates":[-85.453307,40.181056],"type":"Point"}
}