{
  "type": "Feature",
  "properties": {
    "iso:country":"US",
    "sg:address":"1625 N 100 W",
    "sg:city":"Greenfield",
    "sg:classifiers":[
        {
            "category":"Farming",
            "subcategory":"Livestock Farm",
            "type":"Manufacturing & Wholesale Goods"
        }
    ],
    "sg:phone":"+1 317 326 2438",
    "sg:postcode":"46140",
    "sg:province":"IN",
    "sg:tags":[
        "corn",
        "beef",
        "feedlot",
        "cattle"
    ],
    "wof:name":"Douglas Donley",
    "wof:placetype":"venue"
},
  "geometry": {"coordinates":[-85.821093,39.80298],"type":"Point"}
}