{
  "type": "Feature",
  "properties": {
    "addr:full":"3702 W Minnesota St Indianapolis IN 46241",
    "addr:housenumber":"3702",
    "addr:postcode":"46241",
    "addr:street":"W Minnesota St",
    "iso:country":"US",
    "sg:address":"3702 W Minnesota St",
    "sg:city":"Indianapolis",
    "sg:classifiers":[
        {
            "category":"Freight",
            "type":"Transportation"
        }
    ],
    "sg:phone":"+1 317 486 1770",
    "sg:postcode":"46241",
    "sg:province":"IN",
    "sg:tags":[
        "hauling",
        "trucking"
    ],
    "wof:name":"Knight Transportation",
    "wof:placetype":"venue"
},
  "geometry": {"coordinates":[-86.223071,39.742624],"type":"Point"}
}