{
  "type": "Feature",
  "properties": {
    "iso:country":"US",
    "sg:address":"3644 N Meridian Rd",
    "sg:city":"Peru",
    "sg:phone":"+1 765 985 3466",
    "sg:postcode":"46970",
    "sg:province":"IN",
    "sg:tags":[
        "farm",
        "corn",
        "soybean"
    ],
    "wof:name":"Donaldson John",
    "wof:placetype":"venue"
},
  "geometry": {"coordinates":[-86.074258,40.822069],"type":"Point"}
}