{
  "type": "Feature",
  "properties": {
    "iso:country":"US",
    "sg:address":"2980 State Rd 62",
    "sg:city":"Jeffersonville",
    "sg:classifiers":[
        {
            "category":"Food & Beverages",
            "subcategory":"Groceries & Convenience Stores",
            "type":"Retail Goods"
        }
    ],
    "sg:phone":"+1 812 284 0795",
    "sg:postcode":"47130",
    "sg:province":"IN",
    "wof:name":"Thornton Oil",
    "wof:placetype":"venue"
},
  "geometry": {"coordinates":[-85.713453,38.321074],"type":"Point"}
}