{
  "type": "Feature",
  "properties": {
    "iso:country":"US",
    "sg:address":"15015 State Rd 23",
    "sg:city":"Granger",
    "sg:classifiers":[
        {
            "category":"Restaurant",
            "type":"Food & Drink"
        }
    ],
    "sg:phone":"+1 574 273 8770",
    "sg:postcode":"46530",
    "sg:province":"IN",
    "sg:tags":[
        "shop",
        "coffee"
    ],
    "wof:name":"Java Road",
    "wof:placetype":"venue"
},
  "geometry": {"coordinates":[-86.16078,41.732286],"type":"Point"}
}