{
  "type": "Feature",
  "properties": {
    "addr:full":"1914 N Park Ave Indianapolis IN 46202",
    "addr:housenumber":"1914",
    "addr:postcode":"46202",
    "addr:street":"N Park",
    "iso:country":"US",
    "sg:address":"1914 N Park Ave",
    "sg:city":"Indianapolis",
    "sg:classifiers":[
        {
            "category":"Social Services",
            "subcategory":"Child Care",
            "type":"Services"
        }
    ],
    "sg:phone":"+1 317 924 9046",
    "sg:postcode":"46202",
    "sg:province":"IN",
    "wof:name":"Kristy's Child Care Svc",
    "wof:placetype":"venue"
},
  "geometry": {"coordinates":[-86.147189,39.793675],"type":"Point"}
}