{
  "type": "Feature",
  "properties": {
    "addr:full":"826 E Stewart Dr Rensselaer IN 47978",
    "addr:housenumber":"826",
    "addr:postcode":"47978",
    "addr:street":"E Stewart Dr",
    "iso:country":"US",
    "sg:address":"826 E Stewart Dr",
    "sg:city":"Rensselaer",
    "sg:phone":"+1 219 866 8172",
    "sg:postcode":"47978",
    "sg:province":"IN",
    "sg:tags":[
        "farm",
        "corn"
    ],
    "wof:name":"James Hopkins",
    "wof:placetype":"venue"
},
  "geometry": {"coordinates":[-87.142584,40.931723],"type":"Point"}
}