{
  "type": "Feature",
  "properties": {
    "iso:country":"US",
    "sg:address":"330 S Mapleton St",
    "sg:city":"Columbus",
    "sg:classifiers":[
        {
            "category":"Manufacturing",
            "subcategory":"Tools & Machinery",
            "type":"Manufacturing & Wholesale Goods"
        }
    ],
    "sg:phone":"+1 812 379 9221",
    "sg:postcode":"47201",
    "sg:province":"IN",
    "sg:tags":[
        "machine",
        "shop"
    ],
    "wof:name":"Southern Machine Co",
    "wof:placetype":"venue"
},
  "geometry": {"coordinates":[-85.900797,39.19422],"type":"Point"}
}