{
  "type": "Feature",
  "properties": {
    "iso:country":"US",
    "sg:address":"1300 E 86th St Ste 36A",
    "sg:city":"Indianapolis",
    "sg:classifiers":[
        {
            "category":"Government",
            "subcategory":"Post Office",
            "type":"Public Place"
        }
    ],
    "sg:phone":"+1 317 464 6840",
    "sg:postcode":"46240",
    "sg:province":"IN",
    "sg:website":"http://www.usps.com",
    "wof:name":"USPS - United States Post Office",
    "wof:placetype":"venue"
},
  "geometry": {"coordinates":[-86.138443,39.912579],"type":"Point"}
}