{
  "type": "Feature",
  "properties": {
    "iso:country":"US",
    "sg:address":"303 W Broadway St",
    "sg:city":"Rosedale",
    "sg:classifiers":[
        {
            "category":"Shopping",
            "type":"Retail Goods"
        }
    ],
    "sg:phone":"+1 765 548 4242",
    "sg:postcode":"47879",
    "sg:province":"IN",
    "sg:tags":[
        "hearing",
        "equipment",
        "supply",
        "impaired"
    ],
    "wof:name":"Beltone Hearing & Audiology",
    "wof:placetype":"venue"
},
  "geometry": {"coordinates":[-87.398697,39.181772],"type":"Point"}
}