{
  "type": "Feature",
  "properties": {
    "addr:full":"840 W 17th St Ste 6 Bloomington IN 47404",
    "addr:housenumber":"840",
    "addr:postcode":"47404",
    "addr:street":"W 17Th St Ste 6",
    "iso:country":"US",
    "sg:address":"840 W 17th St Ste 6",
    "sg:city":"Bloomington",
    "sg:classifiers":[
        {
            "category":"Professional",
            "subcategory":"Computer Services",
            "type":"Services"
        }
    ],
    "sg:phone":"+1 812 331 7160",
    "sg:postcode":"47404",
    "sg:province":"IN",
    "sg:tags":[
        "repair"
    ],
    "wof:name":"Indiana Voice and Data",
    "wof:placetype":"venue"
},
  "geometry": {"coordinates":[-86.542503,39.179001],"type":"Point"}
}