{
  "type": "Feature",
  "properties": {
    "iso:country":"US",
    "sg:address":"215 E 9th St",
    "sg:city":"Rushville",
    "sg:classifiers":[
        {
            "category":"Manufacturing",
            "subcategory":"Printing",
            "type":"Manufacturing & Wholesale Goods"
        }
    ],
    "sg:phone":"+1 765 938 1149",
    "sg:postcode":"46173",
    "sg:province":"IN",
    "sg:tags":[
        "screen"
    ],
    "wof:name":"TEE-Riffic Graphics",
    "wof:placetype":"venue"
},
  "geometry": {"coordinates":[-85.442108,39.616172],"type":"Point"}
}