{
  "type": "Feature",
  "properties": {
    "iso:country":"US",
    "sg:address":"106 N 9th St",
    "sg:city":"Lafayette",
    "sg:classifiers":[
        {
            "category":"Professional",
            "subcategory":"Lawyer & Legal Services",
            "type":"Services"
        }
    ],
    "sg:phone":"+1 765 742 4529",
    "sg:postcode":"47901",
    "sg:province":"IN",
    "sg:tags":[
        "attorney"
    ],
    "wof:name":"Seeger Hodson & Forbes",
    "wof:placetype":"venue"
},
  "geometry": {"coordinates":[-86.886861,40.419075],"type":"Point"}
}