{
  "type": "Feature",
  "properties": {
    "iso:country":"US",
    "sg:address":"908 N Independence St",
    "sg:city":"Windfall",
    "sg:classifiers":[
        {
            "category":"Home & Garden",
            "subcategory":"Garden Supply",
            "type":"Retail Goods"
        }
    ],
    "sg:phone":"+1 765 945 7121",
    "sg:postcode":"46076",
    "sg:province":"IN",
    "sg:tags":[
        "bulb",
        "seed"
    ],
    "wof:name":"De Kalb Genetics Corp",
    "wof:placetype":"venue"
},
  "geometry": {"coordinates":[-85.956336,40.368722],"type":"Point"}
}