{
  "type": "Feature",
  "properties": {
    "iso:country":"US",
    "sg:address":"13518 Myrtle Ln",
    "sg:city":"Fishers",
    "sg:classifiers":[
        {
            "category":"Building & Trades",
            "subcategory":"Construction",
            "type":"Services"
        }
    ],
    "sg:phone":"+1 317 773 3590",
    "sg:postcode":"46038",
    "sg:province":"IN",
    "sg:tags":[
        "contractor"
    ],
    "sg:website":"http://www.myersconstructionmgmt.com",
    "wof:name":"Myers Construction Management Inc",
    "wof:placetype":"venue"
},
  "geometry": {"coordinates":[-85.96110400000001,39.985245],"type":"Point"}
}