{
  "type": "Feature",
  "properties": {
    "addr:full":"251 E Ohio St Indianapolis IN 46204",
    "addr:housenumber":"251",
    "addr:postcode":"46204",
    "addr:street":"E Ohio St",
    "iso:country":"US",
    "sg:address":"251 E Ohio St",
    "sg:city":"Indianapolis",
    "sg:classifiers":[
        {
            "category":"Real Estate",
            "subcategory":"Real Estate Operator",
            "type":"Services"
        }
    ],
    "sg:phone":"+1 317 635 1111",
    "sg:postcode":"46204",
    "sg:province":"IN",
    "sg:tags":[
        "condominium"
    ],
    "wof:name":"Residences At Market Square",
    "wof:placetype":"venue"
},
  "geometry": {"coordinates":[-86.153204,39.769807],"type":"Point"}
}