{
  "type": "Feature",
  "properties": {
    "iso:country":"US",
    "sg:address":"9025 Coldwater Rd",
    "sg:city":"Fort Wayne",
    "sg:classifiers":[
        {
            "category":"Communications",
            "type":"Services"
        }
    ],
    "sg:phone":"+1 260 487 3500",
    "sg:postcode":"46825",
    "sg:province":"IN",
    "wof:name":"Thales Communication",
    "wof:placetype":"venue"
},
  "geometry": {"coordinates":[-85.13347400000001,41.163609],"type":"Point"}
}