{
  "type": "Feature",
  "properties": {
    "addr:full":"56 E Main St Wabash IN 46992",
    "addr:housenumber":"56",
    "addr:postcode":"46992",
    "addr:street":"E Main St",
    "iso:country":"US",
    "sg:address":"56 E Main St",
    "sg:city":"Wabash",
    "sg:classifiers":[
        {
            "category":"Real Estate",
            "subcategory":"Real Estate Services",
            "type":"Services"
        }
    ],
    "sg:phone":"+1 260 563 5028",
    "sg:postcode":"46992",
    "sg:province":"IN",
    "wof:name":"Wabash Valley Abstract",
    "wof:placetype":"venue"
},
  "geometry": {"coordinates":[-85.819847,40.797997],"type":"Point"}
}