{
  "type": "Feature",
  "properties": {
    "iso:country":"US",
    "sg:address":"119 W Division Rd",
    "sg:city":"Valparaiso",
    "sg:classifiers":[
        {
            "category":"Building & Trades",
            "subcategory":"Construction",
            "type":"Services"
        }
    ],
    "sg:phone":"+1 219 464 1739",
    "sg:postcode":"46385",
    "sg:province":"IN",
    "sg:tags":[
        "general",
        "contractor"
    ],
    "wof:name":"Total Development Construction",
    "wof:placetype":"venue"
},
  "geometry": {"coordinates":[-87.087363,41.434656],"type":"Point"}
}