{
  "type": "Feature",
  "properties": {
    "iso:country":"US",
    "sg:address":"6845 S Co Rd 475 E",
    "sg:city":"Selma",
    "sg:classifiers":[
        {
            "category":"Shopping",
            "type":"Retail Goods"
        }
    ],
    "sg:phone":"+1 765 281 0662",
    "sg:postcode":"47383",
    "sg:province":"IN",
    "sg:tags":[
        "religious"
    ],
    "wof:name":"Cir Of Friends Youth Ministry",
    "wof:placetype":"venue"
},
  "geometry": {"coordinates":[-85.296586,40.147369],"type":"Point"}
}