{
  "type": "Feature",
  "properties": {
    "addr:full":"646 Franklin St Columbus IN 47201",
    "addr:housenumber":"646",
    "addr:postcode":"47201",
    "addr:street":"Franklin St",
    "iso:country":"US",
    "sg:address":"646 Franklin St",
    "sg:city":"Columbus",
    "sg:classifiers":[
        {
            "category":"Real Estate",
            "subcategory":"Real Estate Operator",
            "type":"Services"
        }
    ],
    "sg:phone":"+1 812 378 3827",
    "sg:postcode":"47201",
    "sg:province":"IN",
    "sg:tags":[
        "apartment"
    ],
    "wof:name":"Armory",
    "wof:placetype":"venue"
},
  "geometry": {"coordinates":[-85.919957,39.20507],"type":"Point"}
}