{
  "type": "Feature",
  "properties": {
    "addr:full":"7001 West 108th Ave. Crown Point IN 46307",
    "addr:housenumber":"7001",
    "addr:postcode":"46307",
    "addr:street":"West 108Th Ave.",
    "iso:country":"US",
    "sg:address":"7001 West 108th Ave.",
    "sg:city":"Crown Point",
    "sg:classifiers":[
        {
            "category":"Building & Trades",
            "subcategory":"Landscaping Services",
            "type":"Services"
        },
        {
            "category":"Building & Trades",
            "subcategory":"Construction",
            "type":"Services"
        }
    ],
    "sg:phone":"+1 219 322 6477",
    "sg:postcode":"46307",
    "sg:province":"IN",
    "sg:tags":[
        "contractor"
    ],
    "sg:website":"www.adamslandscape.com#cid=yelp",
    "wof:name":"Adam's Crown Point Landscape And Demolition Inc.",
    "wof:placetype":"venue"
},
  "geometry": {"coordinates":[-87.41968799999999,41.422601],"type":"Point"}
}