{
  "type": "Feature",
  "properties": {
    "iso:country":"US",
    "sg:address":"1618 11th St",
    "sg:city":"Bedford",
    "sg:classifiers":[
        {
            "category":"Professional",
            "type":"Services"
        }
    ],
    "sg:phone":"+1 812 277 9778",
    "sg:postcode":"47421",
    "sg:province":"IN",
    "sg:tags":[
        "establishment"
    ],
    "wof:name":"Weatherfone",
    "wof:placetype":"venue"
},
  "geometry": {"coordinates":[-86.493933,38.8665],"type":"Point"}
}