{
  "type": "Feature",
  "properties": {
    "addr:full":"625 Thayer St Plymouth IN 46563",
    "addr:housenumber":"625",
    "addr:postcode":"46563",
    "addr:street":"Thayer St",
    "iso:country":"US",
    "sg:address":"625 Thayer St",
    "sg:city":"Plymouth",
    "sg:classifiers":[
        {
            "category":"Personal",
            "subcategory":"Beauty Salon",
            "type":"Services"
        }
    ],
    "sg:phone":"+1 574 936 4353",
    "sg:postcode":"46563",
    "sg:province":"IN",
    "wof:name":"Cyndi's Hare Designs",
    "wof:placetype":"venue"
},
  "geometry": {"coordinates":[-86.308257,41.335206],"type":"Point"}
}