{
  "type": "Feature",
  "properties": {
    "iso:country":"US",
    "sg:address":"5635 Progress Rd",
    "sg:city":"Indianapolis",
    "sg:classifiers":[
        {
            "category":"Building & Trades",
            "subcategory":"Landscaping Services",
            "type":"Services"
        }
    ],
    "sg:phone":"+1 317 381 9575",
    "sg:postcode":"46241",
    "sg:province":"IN",
    "sg:tags":[
        "lawn",
        "landscape",
        "maintenance",
        "grounds"
    ],
    "sg:website":"www.brickmangroup.com",
    "wof:name":"Brickman Group Ltd",
    "wof:placetype":"venue"
},
  "geometry": {"coordinates":[-86.257617,39.741131],"type":"Point"}
}