{
  "type": "Feature",
  "properties": {
    "iso:country":"US",
    "sg:address":"4638 Farrington Ave",
    "sg:city":"Indianapolis",
    "sg:classifiers":[
        {
            "category":"Home & Garden",
            "subcategory":"Building Materials",
            "type":"Retail Goods"
        }
    ],
    "sg:phone":"+1 317 352 9520",
    "sg:postcode":"46201",
    "sg:province":"IN",
    "sg:tags":[
        "glass",
        "stained",
        "leaded-commercial"
    ],
    "sg:website":"http://www.jviciandesigns.com",
    "wof:name":"J Vician Designs",
    "wof:placetype":"venue"
},
  "geometry": {"coordinates":[-86.090341,39.76564],"type":"Point"}
}