{
  "type": "Feature",
  "properties": {
    "iso:country":"US",
    "sg:address":"707 Boyd Blvd",
    "sg:city":"Laporte",
    "sg:classifiers":[
        {
            "category":"Manufacturing",
            "subcategory":"Chemicals & Compounds",
            "type":"Manufacturing & Wholesale Goods"
        }
    ],
    "sg:phone":"+1 219 324 4411",
    "sg:postcode":"46350",
    "sg:province":"IN",
    "sg:tags":[
        "rubber"
    ],
    "wof:name":"Sil Co Tec",
    "wof:placetype":"venue"
},
  "geometry": {"coordinates":[-86.688188,41.613482],"type":"Point"}
}