{
  "type": "Feature",
  "properties": {
    "iso:country":"US",
    "sg:address":"2754 W Franklin St",
    "sg:city":"Evansville",
    "sg:classifiers":[
        {
            "category":"Real Estate",
            "subcategory":"Real Estate Operator",
            "type":"Services"
        }
    ],
    "sg:phone":"+1 812 303 2764",
    "sg:postcode":"47712",
    "sg:province":"IN",
    "sg:tags":[
        "property",
        "leasing"
    ],
    "wof:name":"Franklin Illinois Leasing",
    "wof:placetype":"venue"
},
  "geometry": {"coordinates":[-87.608439,37.980903],"type":"Point"}
}