{
  "type": "Feature",
  "properties": {
    "iso:country":"US",
    "sg:address":"1140 Edgewood Dr",
    "sg:city":"Indianapolis",
    "sg:classifiers":[
        {
            "category":"Home & Garden",
            "subcategory":"Building Materials",
            "type":"Retail Goods"
        },
        {
            "category":"Building & Trades",
            "subcategory":"Construction",
            "type":"Services"
        }
    ],
    "sg:phone":"+1 317 281 7280",
    "sg:postcode":"46219",
    "sg:province":"IN",
    "sg:tags":[
        "builder",
        "gazebo",
        "patio"
    ],
    "wof:name":"Jackson Deck & Design, Inc.",
    "wof:placetype":"venue"
},
  "geometry": {"coordinates":[-86.043864,39.783351],"type":"Point"}
}