{
  "type": "Feature",
  "properties": {
    "iso:country":"US",
    "sg:address":"15131 Thatcher Ln",
    "sg:city":"Carmel",
    "sg:classifiers":[
        {
            "category":"Travel",
            "subcategory":"Hotels & Motels",
            "type":"Entertainment"
        }
    ],
    "sg:phone":"+1 317 575 0000",
    "sg:postcode":"46033",
    "sg:province":"IN",
    "wof:name":"Comfort Suites",
    "wof:placetype":"venue"
},
  "geometry": {"coordinates":[-86.125675,40.007817],"type":"Point"}
}