{
  "type": "Feature",
  "properties": {
    "iso:country":"US",
    "sg:address":"4955 W Washington St",
    "sg:city":"Indianapolis",
    "sg:classifiers":[
        {
            "category":"Restaurant",
            "type":"Food & Drink"
        }
    ],
    "sg:phone":"+1 317 248 1495",
    "sg:postcode":"46241",
    "sg:province":"IN",
    "wof:name":"Rolyno's Pizza",
    "wof:placetype":"venue"
},
  "geometry": {"coordinates":[-86.24385100000001,39.754701],"type":"Point"}
}