{
  "type": "Feature",
  "properties": {
    "iso:country":"US",
    "sg:address":"430 E North St",
    "sg:city":"Bremen",
    "sg:classifiers":[
        {
            "category":"Building & Trades",
            "subcategory":"Plumbing",
            "type":"Services"
        }
    ],
    "sg:phone":"+1 574 546 4841",
    "sg:postcode":"46506",
    "sg:province":"IN",
    "sg:tags":[
        "heating",
        "specialty",
        "contractor"
    ],
    "wof:name":"Manges Dennis Heating",
    "wof:placetype":"venue"
},
  "geometry": {"coordinates":[-86.141974,41.447403],"type":"Point"}
}