{
  "type": "Feature",
  "properties": {
    "iso:country":"US",
    "sg:address":"3510 N Mill Creek Dr",
    "sg:city":"Indianapolis",
    "sg:classifiers":[
        {
            "category":"Building & Trades",
            "subcategory":"Construction",
            "type":"Services"
        }
    ],
    "sg:phone":"+1 317 298 9070",
    "sg:postcode":"46214",
    "sg:province":"IN",
    "sg:tags":[
        "contractor"
    ],
    "wof:name":"Server Tile Inc",
    "wof:placetype":"venue"
},
  "geometry": {"coordinates":[-86.276272,39.818534],"type":"Point"}
}