{
  "type": "Feature",
  "properties": {
    "iso:country":"US",
    "sg:address":"2172 W Chapel Pike",
    "sg:city":"Marion",
    "sg:classifiers":[
        {
            "category":"Organizations",
            "subcategory":"Religious Organization",
            "type":"Services"
        }
    ],
    "sg:phone":"+1 765 664 3047",
    "sg:postcode":"46952",
    "sg:province":"IN",
    "sg:tags":[
        "church"
    ],
    "sg:website":"www.sunnycrestbaptist.org",
    "wof:name":"Sunnycrest Baptist Church",
    "wof:placetype":"venue"
},
  "geometry": {"coordinates":[-85.692151,40.58176],"type":"Point"}
}