{
  "type": "Feature",
  "properties": {
    "addr:full":"1327 E 53rd St Anderson IN 46013",
    "addr:housenumber":"1327",
    "addr:postcode":"46013",
    "addr:street":"E 53Rd St",
    "iso:country":"US",
    "sg:address":"1327 E 53rd St",
    "sg:city":"Anderson",
    "sg:classifiers":[
        {
            "category":"Travel",
            "subcategory":"Hotels & Motels",
            "type":"Entertainment"
        }
    ],
    "sg:phone":"+1 765 644 7766",
    "sg:postcode":"46013",
    "sg:province":"IN",
    "wof:name":"Mar-Jon Motel",
    "wof:placetype":"venue"
},
  "geometry": {"coordinates":[-85.662994,40.061784],"type":"Point"}
}