{
  "type": "Feature",
  "properties": {
    "iso:country":"US",
    "sg:address":"5235 Rockville Rd",
    "sg:city":"Indianapolis",
    "sg:classifiers":[
        {
            "category":"Personal",
            "subcategory":"Barber",
            "type":"Services"
        }
    ],
    "sg:phone":"+1 317 381 9769",
    "sg:postcode":"46224",
    "sg:province":"IN",
    "wof:name":"Worlds Cut Barber Shop Unisex",
    "wof:placetype":"venue"
},
  "geometry": {"coordinates":[-86.24989,39.765084],"type":"Point"}
}