{
  "type": "Feature",
  "properties": {
    "iso:country":"US",
    "sg:address":"601 E Vistula St",
    "sg:city":"Bristol",
    "sg:classifiers":[
        {
            "category":"Organizations",
            "subcategory":"Religious Organization",
            "type":"Services"
        }
    ],
    "sg:phone":"+1 574 848 7114",
    "sg:postcode":"46507",
    "sg:province":"IN",
    "sg:tags":[
        "church"
    ],
    "wof:name":"St John Of The Cross",
    "wof:placetype":"venue"
},
  "geometry": {"coordinates":[-85.812065,41.721478],"type":"Point"}
}