{
  "type": "Feature",
  "properties": {
    "iso:country":"US",
    "sg:address":"1446 N Gardner St",
    "sg:city":"Scottsburg",
    "sg:classifiers":[
        {
            "category":"Shopping",
            "type":"Retail Goods"
        }
    ],
    "sg:phone":"+1 812 754 0120",
    "sg:postcode":"47170",
    "sg:province":"IN",
    "sg:tags":[
        "chemical"
    ],
    "wof:name":"Cherokee Chemical Inc CCI",
    "wof:placetype":"venue"
},
  "geometry": {"coordinates":[-85.785034,38.703443],"type":"Point"}
}