{
  "type": "Feature",
  "properties": {
    "addr:full":"105 S Broadway St Albany IN 47320",
    "addr:housenumber":"105",
    "addr:postcode":"47320",
    "addr:street":"S Broadway St",
    "iso:country":"US",
    "sg:address":"105 S Broadway St",
    "sg:city":"Albany",
    "sg:classifiers":[
        {
            "category":"Education",
            "subcategory":"Library",
            "type":"Public Place"
        }
    ],
    "sg:phone":"+1 765 789 8189",
    "sg:postcode":"47320",
    "sg:province":"IN",
    "wof:name":"Albany Community Library",
    "wof:placetype":"venue"
},
  "geometry": {"coordinates":[-85.239627,40.299708],"type":"Point"}
}