{
  "type": "Feature",
  "properties": {
    "iso:country":"US",
    "sg:address":"205 N East St",
    "sg:city":"Carthage",
    "sg:classifiers":[
        {
            "category":"Organizations",
            "subcategory":"Religious Organization",
            "type":"Services"
        }
    ],
    "sg:phone":"+1 765 565 7296",
    "sg:postcode":"46115",
    "sg:province":"IN",
    "sg:tags":[
        "church"
    ],
    "wof:name":"Carthage United Methodist Chr",
    "wof:placetype":"venue"
},
  "geometry": {"coordinates":[-85.569727,39.740138],"type":"Point"}
}