{
  "type": "Feature",
  "properties": {
    "iso:country":"US",
    "sg:address":"2000 N Harding St",
    "sg:city":"Indianapolis",
    "sg:classifiers":[
        {
            "category":"Personal",
            "subcategory":"Beauty Salon",
            "type":"Services"
        }
    ],
    "sg:phone":"+1 317 423 8626",
    "sg:postcode":"46202",
    "sg:province":"IN",
    "sg:tags":[
        "manicuring"
    ],
    "wof:name":"Kia's Nails",
    "wof:placetype":"venue"
},
  "geometry": {"coordinates":[-86.187452,39.7931],"type":"Point"}
}