{
  "type": "Feature",
  "properties": {
    "addr:full":"4801 Van Cleave St Indianapolis IN 46226",
    "addr:housenumber":"4801",
    "addr:postcode":"46226",
    "addr:street":"Van Cleave St",
    "iso:country":"US",
    "sg:address":"4801 Van Cleave St",
    "sg:city":"Indianapolis",
    "sg:classifiers":[
        {
            "category":"Retail",
            "subcategory":"Repair Shop",
            "type":"Services"
        },
        {
            "category":"Building & Trades",
            "subcategory":"Construction",
            "type":"Services"
        },
        {
            "category":"Building & Trades",
            "subcategory":"Equipment Rental",
            "type":"Services"
        },
        {
            "category":"Wholesale",
            "subcategory":"Machinery & Supplies",
            "type":"Manufacturing & Wholesale Goods"
        },
        {
            "category":"Professional",
            "subcategory":"Engineering",
            "type":"Services"
        },
        {
            "category":"Restaurant",
            "type":"Food & Drink"
        }
    ],
    "sg:phone":"+1 317 545 0968",
    "sg:postcode":"46226",
    "sg:province":"IN",
    "sg:tags":[
        "heating",
        "industrial",
        "system",
        "specialty",
        "supplies-refrigeration",
        "equipment-repair",
        "equipment-commercial",
        "refrigeration",
        "air conditioning",
        "mechanical",
        "ventilating",
        "contractor",
        "freezers-repair",
        "refrigerator",
        "engineer"
    ],
    "sg:website":"http://www.samsunmechanical.com",
    "wof:name":"Samsun Mechanical Inc Refrigeration Heating & Air Conditioning",
    "wof:placetype":"venue"
},
  "geometry": {"coordinates":[-86.02188099999999,39.842892],"type":"Point"}
}