{
  "type": "Feature",
  "properties": {
    "iso:country":"US",
    "sg:address":"825 N Center St",
    "sg:city":"Plymouth",
    "sg:classifiers":[
        {
            "category":"Building & Trades",
            "subcategory":"Construction",
            "type":"Services"
        }
    ],
    "sg:phone":"+1 574 936 5922",
    "sg:postcode":"46563",
    "sg:province":"IN",
    "wof:name":"Alternate Building Systems Inc",
    "wof:placetype":"venue"
},
  "geometry": {"coordinates":[-86.311322,41.347009],"type":"Point"}
}