{
  "type": "Feature",
  "properties": {
    "iso:country":"US",
    "sg:address":"20340 Weller Ave",
    "sg:city":"South Bend",
    "sg:classifiers":[
        {
            "category":"Building & Trades",
            "subcategory":"Plumbing",
            "type":"Services"
        }
    ],
    "sg:phone":"+1 574 299 0381",
    "sg:postcode":"46614",
    "sg:province":"IN",
    "sg:tags":[
        "plumbing",
        "contractor"
    ],
    "wof:name":"Dave Motts Plumbing",
    "wof:placetype":"venue"
},
  "geometry": {"coordinates":[-86.262862,41.595311],"type":"Point"}
}