{
  "type": "Feature",
  "properties": {
    "iso:country":"US",
    "sg:address":"5820 Challenger Pkwy",
    "sg:city":"Fort Wayne",
    "sg:classifiers":[
        {
            "category":"Restaurant",
            "type":"Food & Drink"
        }
    ],
    "sg:phone":"+1 260 490 6622",
    "sg:postcode":"46818",
    "sg:province":"IN",
    "sg:tags":[
        "out"
    ],
    "wof:name":"Pauly's Wings & Grinders",
    "wof:placetype":"venue"
},
  "geometry": {"coordinates":[-85.161984,41.131009],"type":"Point"}
}