{
  "type": "Feature",
  "properties": {
    "iso:country":"US",
    "sg:address":"3330 Stocker Dr",
    "sg:city":"Evansville",
    "sg:classifiers":[
        {
            "category":"Building & Trades",
            "subcategory":"Landscaping Services",
            "type":"Services"
        }
    ],
    "sg:phone":"+1 812 422 6656",
    "sg:postcode":"47720",
    "sg:province":"IN",
    "sg:tags":[
        "landscape",
        "contractor"
    ],
    "wof:name":"Stocker's Landscaping",
    "wof:placetype":"venue"
},
  "geometry": {"coordinates":[-87.61694799999999,37.991023],"type":"Point"}
}