{
  "type": "Feature",
  "properties": {
    "addr:full":"2633 Calvin Ct West Lafayette IN 47906",
    "addr:housenumber":"2633",
    "addr:postcode":"47906",
    "addr:street":"Calvin Ct",
    "iso:country":"US",
    "sg:address":"2633 Calvin Ct",
    "sg:city":"West Lafayette",
    "sg:phone":"+1 765 463 3403",
    "sg:postcode":"47906",
    "sg:province":"IN",
    "sg:tags":[
        "farm",
        "corn",
        "soybean"
    ],
    "wof:name":"Sanbloom Farms Inc",
    "wof:placetype":"venue"
},
  "geometry": {"coordinates":[-86.916662,40.45627],"type":"Point"}
}