{
  "type": "Feature",
  "properties": {
    "iso:country":"US",
    "sg:address":"5149 N Keystone Ave",
    "sg:city":"Indianapolis",
    "sg:classifiers":[
        {
            "category":"Building & Trades",
            "subcategory":"Construction",
            "type":"Services"
        }
    ],
    "sg:phone":"+1 317 259 0392",
    "sg:postcode":"46205",
    "sg:province":"IN",
    "sg:tags":[
        "handyman"
    ],
    "sg:website":"www.ardsleygroup.com",
    "wof:name":"Ardsley Maintenance Svc",
    "wof:placetype":"venue"
},
  "geometry": {"coordinates":[-86.121925,39.845918],"type":"Point"}
}