{
  "type": "Feature",
  "properties": {
    "addr:full":"305 Montefiore St Lafayette IN 47905",
    "addr:housenumber":"305",
    "addr:postcode":"47905",
    "addr:street":"Montefiore St",
    "iso:country":"US",
    "sg:address":"305 Montefiore St",
    "sg:city":"Lafayette",
    "sg:classifiers":[
        {
            "category":"Real Estate",
            "subcategory":"Real Estate Operator",
            "type":"Services"
        }
    ],
    "sg:phone":"+1 765 477 6407",
    "sg:postcode":"47905",
    "sg:province":"IN",
    "sg:tags":[
        "apartment"
    ],
    "wof:name":"Bluffs",
    "wof:placetype":"venue"
},
  "geometry": {"coordinates":[-86.89335,40.401629],"type":"Point"}
}