{
  "type": "Feature",
  "properties": {
    "iso:country":"US",
    "sg:address":"5601 N 600 W",
    "sg:city":"Michigan City",
    "sg:classifiers":[
        {
            "category":"Building & Trades",
            "subcategory":"Plumbing",
            "type":"Services"
        }
    ],
    "sg:phone":"+1 219 873 9171",
    "sg:postcode":"46360",
    "sg:province":"IN",
    "sg:tags":[
        "contractor"
    ],
    "wof:name":"Steeles Plumbing & Mechanical",
    "wof:placetype":"venue"
},
  "geometry": {"coordinates":[-86.816273,41.689319],"type":"Point"}
}