{
  "type": "Feature",
  "properties": {
    "iso:country":"US",
    "sg:address":"116 E State St",
    "sg:city":"Pendleton",
    "sg:classifiers":[
        {
            "category":"Retail",
            "subcategory":"Self-service Laundry",
            "type":"Services"
        }
    ],
    "sg:phone":"+1 765 778 3514",
    "sg:postcode":"46064",
    "sg:province":"IN",
    "wof:name":"Oliver's Launderama",
    "wof:placetype":"venue"
},
  "geometry": {"coordinates":[-85.745382,40.002406],"type":"Point"}
}