{
  "type": "Feature",
  "properties": {
    "iso:country":"US",
    "sg:address":"2505 W 700 N",
    "sg:city":"Mc Cordsville",
    "sg:phone":"+1 317 485 4153",
    "sg:postcode":"46055",
    "sg:province":"IN",
    "sg:tags":[
        "farm",
        "corn",
        "wheat",
        "soybean"
    ],
    "wof:name":"Rush Farms",
    "wof:placetype":"venue"
},
  "geometry": {"coordinates":[-85.85255600000001,39.885266],"type":"Point"}
}