{
  "type": "Feature",
  "properties": {
    "iso:country":"US",
    "sg:address":"5264 State Rd 13",
    "sg:city":"Lapel",
    "sg:classifiers":[
        {
            "category":"Building & Trades",
            "subcategory":"Construction",
            "type":"Services"
        }
    ],
    "sg:phone":"+1 765 534 4573",
    "sg:postcode":"46051",
    "sg:province":"IN",
    "sg:tags":[
        "general",
        "contractor"
    ],
    "wof:name":"TAW Enterprises Inc",
    "wof:placetype":"venue"
},
  "geometry": {"coordinates":[-85.843233,40.030996],"type":"Point"}
}