{
  "type": "Feature",
  "properties": {
    "iso:country":"US",
    "sg:address":"101 W Ohio St",
    "sg:city":"Indianapolis",
    "sg:classifiers":[
        {
            "category":"Government",
            "subcategory":"Office",
            "type":"Public Place"
        }
    ],
    "sg:phone":"+1 317 226 7212",
    "sg:postcode":"46204",
    "sg:province":"IN",
    "sg:tags":[
        "federal",
        "human"
    ],
    "wof:name":"US Equal Employment Opportunty",
    "wof:placetype":"venue"
},
  "geometry": {"coordinates":[-86.16160499999999,39.769999],"type":"Point"}
}