{
  "type": "Feature",
  "properties": {
    "iso:country":"US",
    "sg:address":"6883 Fir Rd",
    "sg:city":"Bremen",
    "sg:classifiers":[
        {
            "category":"Retail",
            "subcategory":"Repair Shop",
            "type":"Services"
        }
    ],
    "sg:phone":"+1 574 342 5628",
    "sg:postcode":"46506",
    "sg:province":"IN",
    "wof:name":"Weiss Upholstery",
    "wof:placetype":"venue"
},
  "geometry": {"coordinates":[-86.155231,41.378122],"type":"Point"}
}