{
  "type": "Feature",
  "properties": {
    "iso:country":"US",
    "sg:address":"8720 US Hwy 24",
    "sg:city":"Logansport",
    "sg:classifiers":[
        {
            "category":"Bars & Pubs",
            "type":"Food & Drink"
        }
    ],
    "sg:phone":"+1 574 753 9625",
    "sg:postcode":"46947",
    "sg:province":"IN",
    "wof:name":"Lake View Tavern",
    "wof:placetype":"venue"
},
  "geometry": {"coordinates":[-86.537961,40.764492],"type":"Point"}
}