{
  "type": "Feature",
  "properties": {
    "iso:country":"US",
    "sg:address":"931 Meridian St",
    "sg:city":"Anderson",
    "sg:classifiers":[
        {
            "category":"Banks & Credit Unions",
            "subcategory":"Bank",
            "type":"Services"
        }
    ],
    "sg:phone":"+1 765 646 5400",
    "sg:postcode":"46016",
    "sg:province":"IN",
    "sg:website":"www.nationalcity.com",
    "wof:name":"National City Bank",
    "wof:placetype":"venue"
},
  "geometry": {"coordinates":[-85.679286,40.106392],"type":"Point"}
}