{
  "type": "Feature",
  "properties": {
    "iso:country":"US",
    "sg:address":"5410 S Meridian St",
    "sg:city":"Indianapolis",
    "sg:classifiers":[
        {
            "category":"Building & Trades",
            "subcategory":"Construction",
            "type":"Services"
        },
        {
            "category":"Insurance",
            "subcategory":"Insurance Agent",
            "type":"Services"
        }
    ],
    "sg:phone":"+1 317 786 4363",
    "sg:postcode":"46217",
    "sg:province":"IN",
    "sg:tags":[
        "fire",
        "agency",
        "damage",
        "restoration"
    ],
    "wof:name":"Warren R Gregory & Sons Inc",
    "wof:placetype":"venue"
},
  "geometry": {"coordinates":[-86.1587,39.690193],"type":"Point"}
}