{
  "type": "Feature",
  "properties": {
    "iso:country":"US",
    "sg:address":"6726 Columbia Ave",
    "sg:city":"Hammond",
    "sg:classifiers":[
        {
            "category":"Wholesale",
            "subcategory":"Machinery & Supplies",
            "type":"Manufacturing & Wholesale Goods"
        }
    ],
    "sg:phone":"+1 219 937 3453",
    "sg:postcode":"46324",
    "sg:province":"IN",
    "sg:tags":[
        "equipment",
        "tool",
        "industrial",
        "rent"
    ],
    "wof:name":"Phocus Industrial Tools & Supl",
    "wof:placetype":"venue"
},
  "geometry": {"coordinates":[-87.50026800000001,41.591899],"type":"Point"}
}