{
  "type": "Feature",
  "properties": {
    "iso:country":"US",
    "sg:address":"2019 Washington Ave",
    "sg:city":"Vincennes",
    "sg:classifiers":[
        {
            "category":"Shopping",
            "subcategory":"Hobbies, Toys, & Games",
            "type":"Retail Goods"
        }
    ],
    "sg:phone":"+1 812 882 1716",
    "sg:postcode":"47591",
    "sg:province":"IN",
    "wof:name":"Raspberry Cottage",
    "wof:placetype":"venue"
},
  "geometry": {"coordinates":[-87.505782,38.682725],"type":"Point"}
}