{
  "type": "Feature",
  "properties": {
    "iso:country":"US",
    "sg:address":"1311 Darlington Ave",
    "sg:city":"Crawfordsville",
    "sg:classifiers":[
        {
            "category":"Freight",
            "type":"Transportation"
        }
    ],
    "sg:phone":"+1 765 359 0379",
    "sg:postcode":"47933",
    "sg:province":"IN",
    "sg:tags":[
        "consultant"
    ],
    "wof:name":"Packaging Technology Of In",
    "wof:placetype":"venue"
},
  "geometry": {"coordinates":[-86.88377699999999,40.045297],"type":"Point"}
}