{
  "type": "Feature",
  "properties": {
    "addr:full":"3630 Willowcreek Rd Portage IN 46368",
    "addr:housenumber":"3630",
    "addr:postcode":"46368",
    "addr:street":"Willowcreek Rd",
    "iso:country":"US",
    "sg:address":"3630 Willowcreek Rd",
    "sg:city":"Portage",
    "sg:classifiers":[
        {
            "category":"Health Services",
            "subcategory":"Doctor",
            "type":"Services"
        }
    ],
    "sg:phone":"+1 219 477 5178",
    "sg:postcode":"46368",
    "sg:province":"IN",
    "sg:tags":[
        "physician",
        "surgeon"
    ],
    "wof:name":"Dhindsa Urology",
    "wof:placetype":"venue"
},
  "geometry": {"coordinates":[-87.18261,41.552817],"type":"Point"}
}