{
  "type": "Feature",
  "properties": {
    "iso:country":"US",
    "sg:address":"54867 Currant Rd",
    "sg:city":"Mishawaka",
    "sg:classifiers":[
        {
            "category":"Shopping",
            "subcategory":"Crafts & Fabrics",
            "type":"Retail Goods"
        }
    ],
    "sg:phone":"+1 574 255 2034",
    "sg:postcode":"46545",
    "sg:province":"IN",
    "sg:tags":[
        "sewing"
    ],
    "wof:name":"Stiches & More Inc",
    "wof:placetype":"venue"
},
  "geometry": {"coordinates":[-86.129217,41.695342],"type":"Point"}
}