{
  "type": "Feature",
  "properties": {
    "iso:country":"US",
    "sg:address":"102 E Carr St",
    "sg:city":"Milan",
    "sg:classifiers":[
        {
            "category":"Shopping",
            "subcategory":"Computers & Home Electronics",
            "type":"Retail Goods"
        }
    ],
    "sg:phone":"+1 812 654 3000",
    "sg:postcode":"47031",
    "sg:province":"IN",
    "sg:tags":[
        "equipment",
        "dealer"
    ],
    "sg:website":"www.milanpc.com",
    "wof:name":"MILANPC.COM",
    "wof:placetype":"venue"
},
  "geometry": {"coordinates":[-85.131324,39.122992],"type":"Point"}
}