{
  "type": "Feature",
  "properties": {
    "iso:country":"US",
    "sg:address":"607 Massachusetts Ave",
    "sg:city":"Indianapolis",
    "sg:classifiers":[
        {
            "category":"Professional",
            "type":"Services"
        }
    ],
    "sg:phone":"+1 317 262 9650",
    "sg:postcode":"46204",
    "sg:province":"IN",
    "sg:tags":[
        "establishment"
    ],
    "wof:name":"Sirens",
    "wof:placetype":"venue"
},
  "geometry": {"coordinates":[-86.148059,39.775608],"type":"Point"}
}