{
  "type": "Feature",
  "properties": {
    "iso:country":"US",
    "sg:address":"2905 E Bucher Dr",
    "sg:city":"Syracuse",
    "sg:phone":"+1 574 658 9305",
    "sg:postcode":"46567",
    "sg:province":"IN",
    "sg:tags":[
        "farm",
        "corn",
        "soybean"
    ],
    "wof:name":"Don Bucher",
    "wof:placetype":"venue"
},
  "geometry": {"coordinates":[-85.793667,41.366765],"type":"Point"}
}