{
  "type": "Feature",
  "properties": {
    "addr:full":"2800 E Dunes Hwy Gary IN 46402",
    "addr:housenumber":"2800",
    "addr:postcode":"46402",
    "addr:street":"E Dunes Hwy Gary",
    "iso:country":"US",
    "sg:address":"2800 E Dunes Hwy",
    "sg:city":"Gary",
    "sg:classifiers":[
        {
            "category":"Manufacturing",
            "subcategory":"Metals",
            "type":"Manufacturing & Wholesale Goods"
        }
    ],
    "sg:phone":"+1 219 886 8135",
    "sg:postcode":"46402",
    "sg:province":"IN",
    "sg:tags":[
        "steel",
        "mfg",
        "foundry",
        "shape",
        "cold",
        "blast"
    ],
    "wof:name":"Gary Cold Finished Plant",
    "wof:placetype":"venue"
},
  "geometry": {"coordinates":[-87.304552,41.597301],"type":"Point"}
}