{
  "type": "Feature",
  "properties": {
    "iso:country":"US",
    "sg:address":"2102 W Western Ave",
    "sg:city":"South Bend",
    "sg:classifiers":[
        {
            "category":"Cinema",
            "subcategory":"Movie Rental",
            "type":"Entertainment"
        }
    ],
    "sg:phone":"+1 574 289 8820",
    "sg:postcode":"46619",
    "sg:province":"IN",
    "sg:tags":[
        "leasing",
        "video",
        "disc",
        "tape"
    ],
    "wof:name":"Video Nueva Imgen",
    "wof:placetype":"venue"
},
  "geometry": {"coordinates":[-86.281126,41.672036],"type":"Point"}
}