{
  "type": "Feature",
  "properties": {
    "iso:country":"US",
    "sg:address":"15509 S Crown Hill Ave",
    "sg:city":"Clinton",
    "sg:classifiers":[
        {
            "category":"Government",
            "subcategory":"Office",
            "type":"Public Place"
        }
    ],
    "sg:phone":"+1 765 832 6258",
    "sg:postcode":"47842",
    "sg:province":"IN",
    "sg:tags":[
        "village"
    ],
    "wof:name":"Clinton Twp Trustee",
    "wof:placetype":"venue"
},
  "geometry": {"coordinates":[-87.473329,39.657821],"type":"Point"}
}