{
  "type": "Feature",
  "properties": {
    "iso:country":"US",
    "sg:address":"12425 Old Meridian St",
    "sg:city":"Carmel",
    "sg:classifiers":[
        {
            "category":"Health Services",
            "subcategory":"Doctor",
            "type":"Services"
        }
    ],
    "sg:phone":"+1 317 706 9600",
    "sg:postcode":"46032",
    "sg:province":"IN",
    "sg:tags":[
        "physician",
        "surgeon"
    ],
    "wof:name":"Jerrold Laskin Plastic Surgery",
    "wof:placetype":"venue"
},
  "geometry": {"coordinates":[-86.152181,39.971032],"type":"Point"}
}