{
  "type": "Feature",
  "properties": {
    "iso:country":"US",
    "sg:address":"1782 S Co Rd 500 E",
    "sg:city":"Greencastle",
    "sg:classifiers":[
        {
            "category":"Government",
            "subcategory":"Office",
            "type":"Public Place"
        }
    ],
    "sg:phone":"+1 765 653 9528",
    "sg:postcode":"46135",
    "sg:province":"IN",
    "wof:name":"Putnam County Home",
    "wof:placetype":"venue"
},
  "geometry": {"coordinates":[-86.762823,39.63471],"type":"Point"}
}