{
  "type": "Feature",
  "properties": {
    "iso:country":"US",
    "sg:address":"9549 N Village Way",
    "sg:city":"Indianapolis",
    "sg:classifiers":[
        {
            "category":"Professional",
            "type":"Services"
        }
    ],
    "sg:phone":"+1 317 578 8420",
    "sg:postcode":"46256",
    "sg:province":"IN",
    "sg:tags":[
        "establishment"
    ],
    "wof:name":"Pro Closing",
    "wof:placetype":"venue"
},
  "geometry": {"coordinates":[-86.01919100000001,39.925835],"type":"Point"}
}