{
  "type": "Feature",
  "properties": {
    "iso:country":"US",
    "sg:address":"300 Crestwood Dr",
    "sg:city":"Hobart",
    "sg:classifiers":[
        {
            "category":"Building & Trades",
            "subcategory":"Construction",
            "type":"Services"
        }
    ],
    "sg:phone":"+1 219 942 6219",
    "sg:postcode":"46342",
    "sg:province":"IN",
    "sg:tags":[
        "house"
    ],
    "wof:name":"K&K Builders Daniel Kidwe",
    "wof:placetype":"venue"
},
  "geometry": {"coordinates":[-87.287249,41.531362],"type":"Point"}
}