{
  "type": "Feature",
  "properties": {
    "iso:country":"US",
    "sg:address":"3087 N Co Rd 925 E",
    "sg:city":"Logansport",
    "sg:phone":"+1 574 664 4201",
    "sg:postcode":"46947",
    "sg:province":"IN",
    "sg:tags":[
        "beef",
        "farm",
        "corn",
        "cash",
        "grain",
        "cattle",
        "feedlot"
    ],
    "wof:name":"Walnut Lawn Farm",
    "wof:placetype":"venue"
},
  "geometry": {"coordinates":[-86.20057300000001,40.81],"type":"Point"}
}