{
  "type": "Feature",
  "properties": {
    "addr:full":"175 Fort Wayne Ave Richmond IN 47374",
    "addr:housenumber":"175",
    "addr:postcode":"47374",
    "addr:street":"Fort Wayne Ave",
    "iso:country":"US",
    "sg:address":"175 Fort Wayne Ave",
    "sg:city":"Richmond",
    "sg:classifiers":[
        {
            "category":"Restaurant",
            "type":"Food & Drink"
        }
    ],
    "sg:phone":"+1 765 962 2999",
    "sg:postcode":"47374",
    "sg:province":"IN",
    "wof:name":"Little Sheba's",
    "wof:placetype":"venue"
},
  "geometry": {"coordinates":[-84.893445,39.832698],"type":"Point"}
}