{
  "type": "Feature",
  "properties": {
    "iso:country":"US",
    "sg:address":"418 Old State Rd 28",
    "sg:city":"Williamsport",
    "sg:classifiers":[
        {
            "category":"Manufacturing",
            "subcategory":"Printing",
            "type":"Manufacturing & Wholesale Goods"
        }
    ],
    "sg:phone":"+1 765 762 6600",
    "sg:postcode":"47993",
    "sg:province":"IN",
    "sg:tags":[
        "commercial"
    ],
    "wof:name":"Warren Graphics",
    "wof:placetype":"venue"
},
  "geometry": {"coordinates":[-87.290084,40.294403],"type":"Point"}
}