{
  "type": "Feature",
  "properties": {
    "iso:country":"US",
    "sg:address":"33 W Jackson St",
    "sg:city":"Sullivan",
    "sg:classifiers":[
        {
            "category":"Shopping",
            "subcategory":"Discount & Variety Stores",
            "type":"Retail Goods"
        }
    ],
    "sg:phone":"+1 812 268 4327",
    "sg:postcode":"47882",
    "sg:province":"IN",
    "wof:name":"Tindall's",
    "wof:placetype":"venue"
},
  "geometry": {"coordinates":[-87.408022,39.094301],"type":"Point"}
}