{
  "type": "Feature",
  "properties": {
    "iso:country":"US",
    "sg:address":"300 E Boyd Ave",
    "sg:city":"Greenfield",
    "sg:classifiers":[
        {
            "category":"Health Services",
            "subcategory":"Doctor",
            "type":"Services"
        }
    ],
    "sg:phone":"+1 317 467 9989",
    "sg:postcode":"46140",
    "sg:province":"IN",
    "sg:tags":[
        "dentist"
    ],
    "wof:name":"Werner Orthodontics",
    "wof:placetype":"venue"
},
  "geometry": {"coordinates":[-85.76655700000001,39.793732],"type":"Point"}
}