{
  "type": "Feature",
  "properties": {
    "iso:country":"US",
    "sg:address":"2007 Willow St",
    "sg:city":"Vincennes",
    "sg:classifiers":[
        {
            "category":"Home & Garden",
            "subcategory":"Furniture",
            "type":"Retail Goods"
        }
    ],
    "sg:phone":"+1 812 886 6995",
    "sg:postcode":"47591",
    "sg:province":"IN",
    "wof:name":"Best-Buy Home Furnishings",
    "wof:placetype":"venue"
},
  "geometry": {"coordinates":[-87.530013,38.655903],"type":"Point"}
}