{
  "type": "Feature",
  "properties": {
    "iso:country":"US",
    "sg:address":"905 Givens Rd",
    "sg:city":"Mt Vernon",
    "sg:classifiers":[
        {
            "category":"Freight",
            "type":"Transportation"
        }
    ],
    "sg:phone":"+1 812 838 5541",
    "sg:postcode":"47620",
    "sg:province":"IN",
    "sg:tags":[
        "trucking"
    ],
    "wof:name":"Wabash Valley Transportation",
    "wof:placetype":"venue"
},
  "geometry": {"coordinates":[-87.901973,37.943532],"type":"Point"}
}