{
  "type": "Feature",
  "properties": {
    "iso:country":"US",
    "sg:address":"1575 E 85th Ave",
    "sg:city":"Merrillville",
    "sg:classifiers":[
        {
            "category":"Health Services",
            "subcategory":"Clinic",
            "type":"Services"
        }
    ],
    "sg:phone":"+1 219 736 1135",
    "sg:postcode":"46410",
    "sg:province":"IN",
    "sg:tags":[
        "home"
    ],
    "sg:website":"www.interimhealthcare.com",
    "wof:name":"Interim Healthcare Svc Inc",
    "wof:placetype":"venue"
},
  "geometry": {"coordinates":[-87.317268,41.463208],"type":"Point"}
}