{
  "type": "Feature",
  "properties": {
    "iso:country":"US",
    "sg:address":"912 Allen St",
    "sg:city":"Scottsburg",
    "sg:classifiers":[
        {
            "category":"Retail",
            "subcategory":"Self-service Laundry",
            "type":"Services"
        }
    ],
    "sg:phone":"+1 812 752 9112",
    "sg:postcode":"47170",
    "sg:province":"IN",
    "wof:name":"Amick's Laundromat",
    "wof:placetype":"venue"
},
  "geometry": {"coordinates":[-85.784271,38.683495],"type":"Point"}
}