{
  "type": "Feature",
  "properties": {
    "iso:country":"US",
    "sg:address":"113 E 4th St",
    "sg:city":"Michigan City",
    "sg:classifiers":[
        {
            "category":"Health Services",
            "subcategory":"Doctor",
            "type":"Services"
        }
    ],
    "sg:phone":"+1 219 873 3130",
    "sg:postcode":"46360",
    "sg:province":"IN",
    "sg:tags":[
        "physician",
        "surgeon"
    ],
    "wof:name":"Pathology Consultants Inc",
    "wof:placetype":"venue"
},
  "geometry": {"coordinates":[-86.90173799999999,41.718459],"type":"Point"}
}