{
  "type": "Feature",
  "properties": {
    "iso:country":"US",
    "sg:address":"218 E Washington St",
    "sg:city":"Winamac",
    "sg:classifiers":[
        {
            "category":"Personal",
            "subcategory":"Beauty Salon",
            "type":"Services"
        }
    ],
    "sg:phone":"+1 574 946 7828",
    "sg:postcode":"46996",
    "sg:province":"IN",
    "wof:name":"Studio 218",
    "wof:placetype":"venue"
},
  "geometry": {"coordinates":[-86.600361,41.049173],"type":"Point"}
}