{
  "type": "Feature",
  "properties": {
    "addr:full":"1921 Elmore St Crawfordsville IN 47933",
    "addr:housenumber":"1921",
    "addr:postcode":"47933",
    "addr:street":"Elmore St",
    "iso:country":"US",
    "sg:address":"1921 Elmore St",
    "sg:city":"Crawfordsville",
    "sg:classifiers":[
        {
            "category":"Freight",
            "type":"Transportation"
        }
    ],
    "sg:phone":"+1 765 361 1833",
    "sg:postcode":"47933",
    "sg:province":"IN",
    "sg:tags":[
        "broker",
        "trucking"
    ],
    "wof:name":"Barrett Transport Inc",
    "wof:placetype":"venue"
},
  "geometry": {"coordinates":[-86.866344,40.032222],"type":"Point"}
}