{
  "type": "Feature",
  "properties": {
    "iso:country":"US",
    "sg:address":"3903 W Washington St",
    "sg:city":"Indianapolis",
    "sg:classifiers":[
        {
            "category":"Shopping",
            "subcategory":"Florist",
            "type":"Retail Goods"
        }
    ],
    "sg:phone":"+1 317 244 2071",
    "sg:postcode":"46241",
    "sg:province":"IN",
    "wof:name":"Cook's Flowers & Gifts",
    "wof:placetype":"venue"
},
  "geometry": {"coordinates":[-86.22914900000001,39.759276],"type":"Point"}
}