{
  "type": "Feature",
  "properties": {
    "iso:country":"US",
    "sg:address":"206 S Butler Ave",
    "sg:city":"Marion",
    "sg:classifiers":[
        {
            "category":"Professional",
            "type":"Services"
        }
    ],
    "sg:phone":"+1 765 673 0442",
    "sg:postcode":"46952",
    "sg:province":"IN",
    "sg:tags":[
        "establishment"
    ],
    "wof:name":"Blessed Creations",
    "wof:placetype":"venue"
},
  "geometry": {"coordinates":[-85.67917199999999,40.558796],"type":"Point"}
}