{
  "type": "Feature",
  "properties": {
    "iso:country":"US",
    "sg:address":"610 Columbia St",
    "sg:city":"Lafayette",
    "sg:classifiers":[
        {
            "category":"Shopping",
            "type":"Retail Goods"
        }
    ],
    "sg:phone":"+1 765 420 8082",
    "sg:postcode":"47901",
    "sg:province":"IN",
    "sg:tags":[
        "religious"
    ],
    "wof:name":"Castle-Brook Spiritual Supply",
    "wof:placetype":"venue"
},
  "geometry": {"coordinates":[-86.88881000000001,40.418303],"type":"Point"}
}