{
  "type": "Feature",
  "properties": {
    "iso:country":"US",
    "sg:address":"1520 N A St",
    "sg:city":"Richmond",
    "sg:classifiers":[
        {
            "category":"Local Transit",
            "type":"Transportation"
        }
    ],
    "sg:phone":"+1 765 965 5751",
    "sg:postcode":"47374",
    "sg:province":"IN",
    "sg:tags":[
        "limousine"
    ],
    "wof:name":"Richmond Executive Trnsprtn",
    "wof:placetype":"venue"
},
  "geometry": {"coordinates":[-84.881414,39.830597],"type":"Point"}
}