{
  "type": "Feature",
  "properties": {
    "iso:country":"US",
    "sg:address":"50763 Co Rd 25",
    "sg:city":"Bristol",
    "sg:classifiers":[
        {
            "category":"Home & Garden",
            "subcategory":"Garden Supply",
            "type":"Retail Goods"
        }
    ],
    "sg:phone":"+1 574 848 4147",
    "sg:postcode":"46507",
    "sg:province":"IN",
    "sg:tags":[
        "nurseryman"
    ],
    "wof:name":"Hilbish Nursery",
    "wof:placetype":"venue"
},
  "geometry": {"coordinates":[-85.797571,41.757734],"type":"Point"}
}