{
  "type": "Feature",
  "properties": {
    "addr:full":"110 Emerald Ln Noblesville IN 46060",
    "addr:housenumber":"110",
    "addr:postcode":"46060",
    "addr:street":"Emerald Ln",
    "iso:country":"US",
    "sg:address":"110 Emerald Ln",
    "sg:city":"Noblesville",
    "sg:classifiers":[
        {
            "category":"Building & Trades",
            "subcategory":"Electrical",
            "type":"Services"
        }
    ],
    "sg:phone":"+1 317 773 6007",
    "sg:postcode":"46060",
    "sg:province":"IN",
    "sg:tags":[
        "lighting",
        "landscape"
    ],
    "wof:name":"Warren Landscape Lighting",
    "wof:placetype":"venue"
},
  "geometry": {"coordinates":[-85.96395099999999,40.074815],"type":"Point"}
}