{
  "type": "Feature",
  "properties": {
    "iso:country":"US",
    "sg:address":"55460 Fresno St",
    "sg:city":"South Bend",
    "sg:classifiers":[
        {
            "category":"Building & Trades",
            "subcategory":"Construction",
            "type":"Services"
        }
    ],
    "sg:phone":"+1 574 232 5200",
    "sg:postcode":"46619",
    "sg:province":"IN",
    "sg:tags":[
        "general",
        "contractor"
    ],
    "wof:name":"Central Builders",
    "wof:placetype":"venue"
},
  "geometry": {"coordinates":[-86.37535699999999,41.691445],"type":"Point"}
}