{
  "type": "Feature",
  "properties": {
    "iso:country":"US",
    "sg:address":"4822 Mann Rd",
    "sg:city":"Indianapolis",
    "sg:classifiers":[
        {
            "category":"Freight",
            "type":"Transportation"
        }
    ],
    "sg:phone":"+1 317 856 7001",
    "sg:postcode":"46221",
    "sg:province":"IN",
    "sg:tags":[
        "commercial",
        "storage"
    ],
    "wof:name":"Store-N-Lock",
    "wof:placetype":"venue"
},
  "geometry": {"coordinates":[-86.242436,39.69561],"type":"Point"}
}