{
  "type": "Feature",
  "properties": {
    "iso:country":"US",
    "sg:address":"1426 W 29th St",
    "sg:city":"Indianapolis",
    "sg:classifiers":[
        {
            "category":"Retail",
            "subcategory":"Repair Shop",
            "type":"Services"
        }
    ],
    "sg:phone":"+1 317 925 4881",
    "sg:postcode":"46208",
    "sg:province":"IN",
    "sg:tags":[
        "upholsterer"
    ],
    "wof:name":"Pat Thomas",
    "wof:placetype":"venue"
},
  "geometry": {"coordinates":[-86.190851,39.808236],"type":"Point"}
}