{
  "type": "Feature",
  "properties": {
    "iso:country":"US",
    "sg:address":"932 Robinson St",
    "sg:city":"West Lafayette",
    "sg:classifiers":[
        {
            "category":"Farming",
            "subcategory":"Farm & Veterinary Services",
            "type":"Manufacturing & Wholesale Goods"
        }
    ],
    "sg:phone":"+1 765 743 1877",
    "sg:postcode":"47906",
    "sg:province":"IN",
    "sg:tags":[
        "management"
    ],
    "wof:name":"Farm Clinic",
    "wof:placetype":"venue"
},
  "geometry": {"coordinates":[-86.905656,40.435098],"type":"Point"}
}