{
  "type": "Feature",
  "properties": {
    "iso:country":"US",
    "sg:address":"4209 E 62nd St",
    "sg:city":"Indianapolis",
    "sg:classifiers":[
        {
            "category":"Retail",
            "subcategory":"Repair Shop",
            "type":"Services"
        },
        {
            "category":"Shopping",
            "type":"Retail Goods"
        }
    ],
    "sg:phone":"+1 317 255 8282",
    "sg:postcode":"46220",
    "sg:province":"IN",
    "sg:tags":[
        "picture",
        "frame"
    ],
    "wof:name":"The Great Frame Up",
    "wof:placetype":"venue"
},
  "geometry": {"coordinates":[-86.094953,39.868557],"type":"Point"}
}