{
  "type": "Feature",
  "properties": {
    "iso:country":"US",
    "sg:address":"5335 E 62nd St",
    "sg:city":"Indianapolis",
    "sg:classifiers":[
        {
            "category":"Bus Charters",
            "type":"Transportation"
        }
    ],
    "sg:phone":"+1 317 255 4297",
    "sg:postcode":"46220",
    "sg:province":"IN",
    "sg:tags":[
        "rental"
    ],
    "wof:name":"Travels-N-All Inc",
    "wof:placetype":"venue"
},
  "geometry": {"coordinates":[-86.07557,39.868769],"type":"Point"}
}