{
  "type": "Feature",
  "properties": {
    "iso:country":"US",
    "sg:address":"4111 Wythe Ln",
    "sg:city":"Indianapolis",
    "sg:classifiers":[
        {
            "category":"Professional",
            "subcategory":"Management & Consulting",
            "type":"Services"
        }
    ],
    "sg:phone":"+1 317 577 2311",
    "sg:postcode":"46250",
    "sg:province":"IN",
    "sg:tags":[
        "consultant",
        "training"
    ],
    "wof:name":"Glick Training Assocs",
    "wof:placetype":"venue"
},
  "geometry": {"coordinates":[-86.09650000000001,39.899638],"type":"Point"}
}