{
  "type": "Feature",
  "properties": {
    "iso:country":"US",
    "sg:address":"900 18th St",
    "sg:city":"Logansport",
    "sg:classifiers":[
        {
            "category":"Insurance",
            "subcategory":"Insurance Agent",
            "type":"Services"
        }
    ],
    "sg:phone":"+1 574 753 4420",
    "sg:postcode":"46947",
    "sg:province":"IN",
    "wof:name":"State Farm Insurance",
    "wof:placetype":"venue"
},
  "geometry": {"coordinates":[-86.344471,40.750661],"type":"Point"}
}