{
  "type": "Feature",
  "properties": {
    "iso:country":"US",
    "sg:address":"1300 Fairfield Dr",
    "sg:city":"Evansville",
    "sg:classifiers":[
        {
            "category":"Recreation",
            "type":"Entertainment"
        }
    ],
    "sg:phone":"+1 812 476 0586",
    "sg:postcode":"47715",
    "sg:province":"IN",
    "sg:tags":[
        "skating",
        "rink"
    ],
    "wof:name":"Skate World Inc",
    "wof:placetype":"venue"
},
  "geometry": {"coordinates":[-87.478939,37.988416],"type":"Point"}
}