{
  "type": "Feature",
  "properties": {
    "iso:country":"US",
    "sg:address":"520 S Washington St",
    "sg:city":"Bloomfield",
    "sg:classifiers":[
        {
            "category":"Organizations",
            "subcategory":"Religious Organization",
            "type":"Services"
        }
    ],
    "sg:phone":"+1 812 384 8984",
    "sg:postcode":"47424",
    "sg:province":"IN",
    "sg:tags":[
        "church"
    ],
    "wof:name":"Seven Day Adventist",
    "wof:placetype":"venue"
},
  "geometry": {"coordinates":[-86.93743499999999,39.022071],"type":"Point"}
}