{
  "type": "Feature",
  "properties": {
    "iso:country":"US",
    "sg:address":"8984 State Rd 236",
    "sg:city":"Middletown",
    "sg:classifiers":[
        {
            "category":"Manufacturing",
            "subcategory":"Apparel",
            "type":"Manufacturing & Wholesale Goods"
        }
    ],
    "sg:phone":"+1 765 354 3000",
    "sg:postcode":"47356",
    "sg:province":"IN",
    "sg:tags":[
        "pillow"
    ],
    "sg:website":"www.lmiforcomfort.com",
    "wof:name":"West Point Stevens",
    "wof:placetype":"venue"
},
  "geometry": {"coordinates":[-85.557117,40.062253],"type":"Point"}
}