{
  "type": "Feature",
  "properties": {
    "iso:country":"US",
    "sg:address":"851 E Market St",
    "sg:city":"Huntington",
    "sg:classifiers":[
        {
            "category":"Bars & Pubs",
            "type":"Food & Drink"
        }
    ],
    "sg:phone":"+1 260 356 4381",
    "sg:postcode":"46750",
    "sg:province":"IN",
    "wof:name":"Sahara",
    "wof:placetype":"venue"
},
  "geometry": {"coordinates":[-85.486483,40.884443],"type":"Point"}
}