{
  "type": "Feature",
  "properties": {
    "iso:country":"US",
    "sg:address":"385 W US Hwy 6",
    "sg:city":"Valparaiso",
    "sg:classifiers":[
        {
            "category":"Restaurant",
            "type":"Food & Drink"
        }
    ],
    "sg:phone":"+1 219 763 4100",
    "sg:postcode":"46385",
    "sg:province":"IN",
    "wof:name":"Petey's Gyros",
    "wof:placetype":"venue"
},
  "geometry": {"coordinates":[-87.143445,41.550326],"type":"Point"}
}