{
  "type": "Feature",
  "properties": {
    "iso:country":"US",
    "sg:address":"12301 Bonebank Rd",
    "sg:city":"Mount Vernon",
    "sg:classifiers":[
        {
            "category":"Farming",
            "subcategory":"Farm",
            "type":"Manufacturing & Wholesale Goods"
        }
    ],
    "sg:phone":"+1 812 838 6758",
    "sg:postcode":"47620",
    "sg:province":"IN",
    "sg:tags":[
        "crop",
        "general"
    ],
    "wof:name":"Bernard J Muller",
    "wof:placetype":"venue"
},
  "geometry": {"coordinates":[-87.986195,37.859278],"type":"Point"}
}