{
  "type": "Feature",
  "properties": {
    "addr:full":"1640 E Washington St Indianapolis IN 46201",
    "addr:housenumber":"1640",
    "addr:postcode":"46201",
    "addr:street":"E Washington St",
    "iso:country":"US",
    "sg:address":"1640 E Washington St",
    "sg:city":"Indianapolis",
    "sg:classifiers":[
        {
            "category":"Autos & Motor Vehicles",
            "subcategory":"Fuel & Gas Station",
            "type":"Retail Goods"
        },
        {
            "category":"Food & Beverages",
            "subcategory":"Groceries & Convenience Stores",
            "type":"Retail Goods"
        }
    ],
    "sg:phone":"+1 317 638 6546",
    "sg:postcode":"46201",
    "sg:province":"IN",
    "sg:website":"http://www.speedway.com",
    "wof:name":"Speedway 6116",
    "wof:placetype":"venue"
},
  "geometry": {"coordinates":[-86.13151499999999,39.76726],"type":"Point"}
}