{
  "type": "Feature",
  "properties": {
    "iso:country":"US",
    "sg:address":"25470 Gwinn Rd",
    "sg:city":"Arcadia",
    "sg:classifiers":[
        {
            "category":"Freight",
            "type":"Transportation"
        }
    ],
    "sg:phone":"+1 317 984 3559",
    "sg:postcode":"46030",
    "sg:province":"IN",
    "sg:tags":[
        "broker",
        "trucking"
    ],
    "wof:name":"Reed Trucking",
    "wof:placetype":"venue"
},
  "geometry": {"coordinates":[-86.04159,40.152289],"type":"Point"}
}