{
  "type": "Feature",
  "properties": {
    "iso:country":"US",
    "sg:address":"1222 McCullough Pike",
    "sg:city":"Clarksville",
    "sg:classifiers":[
        {
            "category":"Wholesale",
            "subcategory":"Auto Parts",
            "type":"Manufacturing & Wholesale Goods"
        }
    ],
    "sg:phone":"+1 812 949 2880",
    "sg:postcode":"47129",
    "sg:province":"IN",
    "sg:tags":[
        "automobile",
        "rebuilt"
    ],
    "wof:name":"Kenny's Auto Parts",
    "wof:placetype":"venue"
},
  "geometry": {"coordinates":[-85.789879,38.298436],"type":"Point"}
}