{
  "type": "Feature",
  "properties": {
    "iso:country":"US",
    "sg:address":"6535 E 82nd St",
    "sg:city":"Indianapolis",
    "sg:classifiers":[
        {
            "category":"Wholesale",
            "subcategory":"Metals & Minerals",
            "type":"Manufacturing & Wholesale Goods"
        }
    ],
    "sg:phone":"+1 317 841 3999",
    "sg:postcode":"46250",
    "sg:province":"IN",
    "sg:tags":[
        "tubing"
    ],
    "wof:name":"Tubes Inc",
    "wof:placetype":"venue"
},
  "geometry": {"coordinates":[-86.05326,39.905186],"type":"Point"}
}