{
  "type": "Feature",
  "properties": {
    "iso:country":"US",
    "sg:address":"11021 State Rd 142",
    "sg:city":"Quincy",
    "sg:classifiers":[
        {
            "category":"Shopping",
            "type":"Retail Goods"
        }
    ],
    "sg:phone":"+1 765 528 2050",
    "sg:postcode":"47456",
    "sg:province":"IN",
    "sg:tags":[
        "merchandise"
    ],
    "wof:name":"Mary Kay Independent Rep",
    "wof:placetype":"venue"
},
  "geometry": {"coordinates":[-86.63257299999999,39.521221],"type":"Point"}
}