{
  "type": "Feature",
  "properties": {
    "addr:full":"2225 Production Rd Kendallville IN 46755",
    "addr:housenumber":"2225",
    "addr:postcode":"46755",
    "addr:street":"Production Rd",
    "iso:country":"US",
    "sg:address":"2225 Production Rd",
    "sg:city":"Kendallville",
    "sg:classifiers":[
        {
            "category":"Manufacturing",
            "subcategory":"Metals",
            "type":"Manufacturing & Wholesale Goods"
        }
    ],
    "sg:phone":"+1 260 347 2600",
    "sg:postcode":"46755",
    "sg:province":"IN",
    "sg:tags":[
        "spring"
    ],
    "wof:name":"No-Sag Spring",
    "wof:placetype":"venue"
},
  "geometry": {"coordinates":[-85.228655,41.443062],"type":"Point"}
}