{
  "type": "Feature",
  "properties": {
    "iso:country":"US",
    "sg:address":"102 Indiana Ave",
    "sg:city":"Russellville",
    "sg:classifiers":[
        {
            "category":"Professional",
            "type":"Services"
        }
    ],
    "sg:phone":"+1 765 435 2813",
    "sg:postcode":"46175",
    "sg:province":"IN",
    "wof:name":"Friends of Park",
    "wof:placetype":"venue"
},
  "geometry": {"coordinates":[-86.983301,39.853382],"type":"Point"}
}