{
  "type": "Feature",
  "properties": {
    "iso:country":"US",
    "sg:address":"5140 Charlestown Rd",
    "sg:city":"New Albany",
    "sg:classifiers":[
        {
            "category":"Banks & Credit Unions",
            "subcategory":"Investment Brokerage",
            "type":"Services"
        }
    ],
    "sg:phone":"+1 812 945 4544",
    "sg:postcode":"47150",
    "sg:province":"IN",
    "sg:tags":[
        "consultant",
        "planning",
        "financial"
    ],
    "wof:name":"Hardin Financial Group",
    "wof:placetype":"venue"
},
  "geometry": {"coordinates":[-85.778062,38.366593],"type":"Point"}
}