{
  "type": "Feature",
  "properties": {
    "iso:country":"US",
    "sg:address":"1772 S 75 E",
    "sg:city":"Wabash",
    "sg:classifiers":[
        {
            "category":"Building & Trades",
            "subcategory":"Construction",
            "type":"Services"
        }
    ],
    "sg:phone":"+1 260 563 3721",
    "sg:postcode":"46992",
    "sg:province":"IN",
    "sg:tags":[
        "house"
    ],
    "wof:name":"American Eagle Home Inspection",
    "wof:placetype":"venue"
},
  "geometry": {"coordinates":[-85.779405,40.799309],"type":"Point"}
}