{
  "type": "Feature",
  "properties": {
    "iso:country":"US",
    "sg:address":"9660 E 520 S",
    "sg:city":"Wolcottville",
    "sg:classifiers":[
        {
            "category":"Organizations",
            "subcategory":"Religious Organization",
            "type":"Services"
        }
    ],
    "sg:phone":"+1 260 351 4602",
    "sg:postcode":"46795",
    "sg:province":"IN",
    "sg:tags":[
        "clergy"
    ],
    "wof:name":"Dean Bearman",
    "wof:placetype":"venue"
},
  "geometry": {"coordinates":[-85.239906,41.566726],"type":"Point"}
}