{
  "type": "Feature",
  "properties": {
    "addr:full":"2745 Old Morgantown Rd Martinsville IN 46151",
    "addr:housenumber":"2745",
    "addr:postcode":"46151",
    "addr:street":"Old Morgantown Rd",
    "iso:country":"US",
    "sg:address":"2745 Old Morgantown Rd",
    "sg:city":"Martinsville",
    "sg:classifiers":[
        {
            "category":"Organizations",
            "subcategory":"Religious Organization",
            "type":"Services"
        }
    ],
    "sg:phone":"+1 765 342 4483",
    "sg:postcode":"46151",
    "sg:province":"IN",
    "sg:tags":[
        "church"
    ],
    "sg:website":"www.eastviewchurch.org",
    "wof:name":"Eastview Christian Church",
    "wof:placetype":"venue"
},
  "geometry": {"coordinates":[-86.364136,39.419573],"type":"Point"}
}