{
  "type": "Feature",
  "properties": {
    "iso:country":"US",
    "sg:address":"108 N Main St",
    "sg:city":"Auburn",
    "sg:classifiers":[
        {
            "category":"Shopping",
            "subcategory":"Computers & Home Electronics",
            "type":"Retail Goods"
        }
    ],
    "sg:phone":"+1 260 925 6578",
    "sg:postcode":"46706",
    "sg:province":"IN",
    "sg:tags":[
        "software"
    ],
    "wof:name":"Tempus Technologies",
    "wof:placetype":"venue"
},
  "geometry": {"coordinates":[-85.055802,41.367421],"type":"Point"}
}