{
  "type": "Feature",
  "properties": {
    "iso:country":"US",
    "sg:address":"511 W Lincoln Rd",
    "sg:city":"Kokomo",
    "sg:classifiers":[
        {
            "category":"Health Services",
            "subcategory":"Optometrist",
            "type":"Services"
        }
    ],
    "sg:phone":"+1 765 453 2907",
    "sg:postcode":"46902",
    "sg:province":"IN",
    "wof:name":"Burkhart Calvin & Burkhart",
    "wof:placetype":"venue"
},
  "geometry": {"coordinates":[-86.13861,40.454853],"type":"Point"}
}