{
  "type": "Feature",
  "properties": {
    "iso:country":"US",
    "sg:address":"4701 Meijer Ct",
    "sg:city":"Lafayette",
    "sg:classifiers":[
        {
            "category":"Travel",
            "subcategory":"Hotels & Motels",
            "type":"Entertainment"
        }
    ],
    "sg:phone":"+1 765 447 3434",
    "sg:postcode":"47905",
    "sg:province":"IN",
    "wof:name":"Lees Inn & Suites Lafayette",
    "wof:placetype":"venue"
},
  "geometry": {"coordinates":[-86.817825,40.416171],"type":"Point"}
}