{
  "type": "Feature",
  "properties": {
    "addr:full":"204 N Broad St Mooreland IN 47360",
    "addr:housenumber":"204",
    "addr:postcode":"47360",
    "addr:street":"N Broad St",
    "iso:country":"US",
    "sg:address":"204 N Broad St",
    "sg:city":"Mooreland",
    "sg:classifiers":[
        {
            "category":"Organizations",
            "subcategory":"Religious Organization",
            "type":"Services"
        }
    ],
    "sg:phone":"+1 765 766 5391",
    "sg:postcode":"47360",
    "sg:province":"IN",
    "sg:tags":[
        "church"
    ],
    "wof:name":"First Christian Church",
    "wof:placetype":"venue"
},
  "geometry": {"coordinates":[-85.251276,39.99948],"type":"Point"}
}