{
  "type": "Feature",
  "properties": {
    "iso:country":"US",
    "sg:address":"2125 E 1050 S",
    "sg:city":"Lynn",
    "sg:classifiers":[
        {
            "category":"Manufacturing",
            "subcategory":"Retail Goods",
            "type":"Manufacturing & Wholesale Goods"
        }
    ],
    "sg:phone":"+1 765 874 2515",
    "sg:postcode":"47355",
    "sg:province":"IN",
    "sg:tags":[
        "burial",
        "casket"
    ],
    "sg:website":"www.matthewsinternational.com",
    "wof:name":"York Casket Co",
    "wof:placetype":"venue"
},
  "geometry": {"coordinates":[-84.937348,40.012514],"type":"Point"}
}