{
  "type": "Feature",
  "properties": {
    "iso:country":"US",
    "sg:address":"1910 Miniature Rose Ln",
    "sg:city":"Mishawaka",
    "sg:classifiers":[
        {
            "category":"Professional",
            "subcategory":"Business Services",
            "type":"Services"
        }
    ],
    "sg:phone":"+1 574 257 1518",
    "sg:postcode":"46544",
    "sg:province":"IN",
    "wof:name":"Ambit Design",
    "wof:placetype":"venue"
},
  "geometry": {"coordinates":[-86.158117,41.642608],"type":"Point"}
}