{
  "type": "Feature",
  "properties": {
    "iso:country":"US",
    "sg:address":"555 Polk St",
    "sg:city":"Gary",
    "sg:classifiers":[
        {
            "category":"Government",
            "subcategory":"Police Station",
            "type":"Public Place"
        }
    ],
    "sg:phone":"+1 219 881 1217",
    "sg:postcode":"46402",
    "sg:province":"IN",
    "sg:tags":[
        "department"
    ],
    "wof:name":"Police Dept-Hit & Run Div",
    "wof:placetype":"venue"
},
  "geometry": {"coordinates":[-87.34986499999999,41.601178],"type":"Point"}
}