{
  "type": "Feature",
  "properties": {
    "addr:full":"9 W Union St Liberty IN 47353",
    "addr:housenumber":"9",
    "addr:postcode":"47353",
    "addr:street":"W Union St",
    "iso:country":"US",
    "sg:address":"9 W Union St",
    "sg:city":"Liberty",
    "sg:classifiers":[
        {
            "category":"Shopping",
            "subcategory":"Used Merchandise",
            "type":"Retail Goods"
        }
    ],
    "sg:phone":"+1 765 458 6925",
    "sg:postcode":"47353",
    "sg:province":"IN",
    "sg:tags":[
        "antique"
    ],
    "wof:name":"Hoosier Antiques & Cllctbls",
    "wof:placetype":"venue"
},
  "geometry": {"coordinates":[-84.930818,39.635504],"type":"Point"}
}