{
  "type": "Feature",
  "properties": {
    "iso:country":"US",
    "sg:address":"916 W 8th St",
    "sg:city":"Rochester",
    "sg:classifiers":[
        {
            "category":"Organizations",
            "subcategory":"Religious Organization",
            "type":"Services"
        }
    ],
    "sg:phone":"+1 574 223 6419",
    "sg:postcode":"46975",
    "sg:province":"IN",
    "wof:name":"Fellowship Christian Athletes",
    "wof:placetype":"venue"
},
  "geometry": {"coordinates":[-86.229942,41.06638],"type":"Point"}
}