{
  "type": "Feature",
  "properties": {
    "iso:country":"US",
    "sg:address":"3101 Fairfield Ave",
    "sg:city":"Fort Wayne",
    "sg:classifiers":[
        {
            "category":"Autos & Motor Vehicles",
            "subcategory":"Automobile Sales",
            "type":"Retail Goods"
        }
    ],
    "sg:phone":"+1 260 456 8731",
    "sg:postcode":"46807",
    "sg:province":"IN",
    "sg:tags":[
        "car",
        "dealer"
    ],
    "wof:name":"Bolyard's Auto Svc",
    "wof:placetype":"venue"
},
  "geometry": {"coordinates":[-85.144857,41.055986],"type":"Point"}
}