{
  "type": "Feature",
  "properties": {
    "iso:country":"US",
    "sg:address":"3005 N Oakwood Ave",
    "sg:city":"Muncie",
    "sg:classifiers":[
        {
            "category":"Food & Beverages",
            "subcategory":"Liquor & Beverages",
            "type":"Retail Goods"
        }
    ],
    "sg:phone":"+1 765 282 2312",
    "sg:postcode":"47304",
    "sg:province":"IN",
    "wof:name":"Muncie Liquor Store Inc",
    "wof:placetype":"venue"
},
  "geometry": {"coordinates":[-85.409677,40.217743],"type":"Point"}
}