{
  "type": "Feature",
  "properties": {
    "iso:country":"US",
    "sg:address":"111 Earl St",
    "sg:city":"Wanatah",
    "sg:classifiers":[
        {
            "category":"Building & Trades",
            "subcategory":"Construction",
            "type":"Services"
        }
    ],
    "sg:phone":"+1 219 733 0412",
    "sg:postcode":"46390",
    "sg:province":"IN",
    "sg:tags":[
        "floor",
        "laying",
        "contractor"
    ],
    "wof:name":"Creative Flooring Inc",
    "wof:placetype":"venue"
},
  "geometry": {"coordinates":[-86.897204,41.438762],"type":"Point"}
}