{
  "type": "Feature",
  "properties": {
    "iso:country":"US",
    "sg:address":"10333 N Meridian St",
    "sg:city":"Indianapolis",
    "sg:classifiers":[
        {
            "category":"Professional",
            "subcategory":"Accounting & Tax Preparation",
            "type":"Services"
        }
    ],
    "sg:phone":"+1 317 844 6458",
    "sg:postcode":"46290",
    "sg:province":"IN",
    "sg:tags":[
        "engineering",
        "management"
    ],
    "wof:name":"Richard Sexson CPA",
    "wof:placetype":"venue"
},
  "geometry": {"coordinates":[-86.157481,39.941036],"type":"Point"}
}