{
  "type": "Feature",
  "properties": {
    "iso:country":"US",
    "sg:address":"14320 Smith Rd",
    "sg:city":"Yoder",
    "sg:classifiers":[
        {
            "category":"Building & Trades",
            "subcategory":"Plumbing",
            "type":"Services"
        }
    ],
    "sg:phone":"+1 260 456 3933",
    "sg:postcode":"46798",
    "sg:province":"IN",
    "sg:tags":[
        "conditioning",
        "air",
        "system",
        "contractor"
    ],
    "sg:website":"www.genesisheating.com",
    "wof:name":"Genesis Heating & Cooling",
    "wof:placetype":"venue"
},
  "geometry": {"coordinates":[-85.206237,40.948578],"type":"Point"}
}