{
  "type": "Feature",
  "properties": {
    "iso:country":"US",
    "sg:address":"6437 Rucker Rd",
    "sg:city":"Indianapolis",
    "sg:classifiers":[
        {
            "category":"Real Estate",
            "subcategory":"Real Estate Agent",
            "type":"Services"
        }
    ],
    "sg:phone":"+1 317 251 3364",
    "sg:postcode":"46220",
    "sg:province":"IN",
    "wof:name":"CMS Real Estate",
    "wof:placetype":"venue"
},
  "geometry": {"coordinates":[-86.07924199999999,39.873686],"type":"Point"}
}