{
  "type": "Feature",
  "properties": {
    "iso:country":"US",
    "sg:address":"6676 Cornell Ave",
    "sg:city":"Indianapolis",
    "sg:classifiers":[
        {
            "category":"Real Estate",
            "subcategory":"Real Estate Operator",
            "type":"Services"
        }
    ],
    "sg:phone":"+1 317 722 9999",
    "sg:postcode":"46220",
    "sg:province":"IN",
    "sg:tags":[
        "condominium"
    ],
    "wof:name":"Monon Row Condominiums",
    "wof:placetype":"venue"
},
  "geometry": {"coordinates":[-86.141317,39.878702],"type":"Point"}
}