{
  "type": "Feature",
  "properties": {
    "iso:country":"US",
    "sg:address":"8 Maple St",
    "sg:city":"Sellersburg",
    "sg:classifiers":[
        {
            "category":"Building & Trades",
            "subcategory":"Plumbing",
            "type":"Services"
        }
    ],
    "sg:phone":"+1 812 738 5131",
    "sg:postcode":"47172",
    "sg:province":"IN",
    "sg:tags":[
        "conditioning",
        "air",
        "system",
        "contractor"
    ],
    "wof:name":"Corydon Heating & Cooling",
    "wof:placetype":"venue"
},
  "geometry": {"coordinates":[-85.744567,38.406899],"type":"Point"}
}