{
  "type": "Feature",
  "properties": {
    "addr:full":"3606 Sheffield Ave Hammond IN 46327",
    "addr:housenumber":"3606",
    "addr:postcode":"46327",
    "addr:street":"Sheffield Ave",
    "iso:country":"US",
    "sg:address":"3606 Sheffield Ave",
    "sg:city":"Hammond",
    "sg:classifiers":[
        {
            "category":"Freight",
            "type":"Transportation"
        }
    ],
    "sg:phone":"+1 219 933 3001",
    "sg:postcode":"46327",
    "sg:province":"IN",
    "sg:tags":[
        "commercial",
        "storage"
    ],
    "wof:name":"Sheffield Storage",
    "wof:placetype":"venue"
},
  "geometry": {"coordinates":[-87.516987,41.647212],"type":"Point"}
}