{
  "type": "Feature",
  "properties": {
    "iso:country":"US",
    "sg:address":"818 N College Ave",
    "sg:city":"Indianapolis",
    "sg:classifiers":[
        {
            "category":"Professional",
            "subcategory":"Lawyer & Legal Services",
            "type":"Services"
        }
    ],
    "sg:phone":"+1 317 630 4287",
    "sg:postcode":"46202",
    "sg:province":"IN",
    "sg:tags":[
        "law"
    ],
    "wof:name":"Thomsen D J Law Office",
    "wof:placetype":"venue"
},
  "geometry": {"coordinates":[-86.145179,39.779631],"type":"Point"}
}