{
  "type": "Feature",
  "properties": {
    "iso:country":"US",
    "sg:address":"7695 S 1150 E",
    "sg:city":"Otterbein",
    "sg:classifiers":[
        {
            "category":"Autos & Motor Vehicles",
            "subcategory":"Auto Supplies",
            "type":"Retail Goods"
        }
    ],
    "sg:phone":"+1 765 583 3323",
    "sg:postcode":"47970",
    "sg:province":"IN",
    "sg:tags":[
        "tire"
    ],
    "wof:name":"Coogle Tire Svc",
    "wof:placetype":"venue"
},
  "geometry": {"coordinates":[-87.103403,40.499655],"type":"Point"}
}