{
  "type": "Feature",
  "properties": {
    "addr:full":"7719 Loma Ct Fishers IN 46038",
    "addr:housenumber":"7719",
    "addr:postcode":"46038",
    "addr:street":"Loma Ct",
    "iso:country":"US",
    "sg:address":"7719 Loma Ct",
    "sg:city":"Fishers",
    "sg:classifiers":[
        {
            "category":"Wholesale",
            "subcategory":"Office Equipment",
            "type":"Manufacturing & Wholesale Goods"
        }
    ],
    "sg:phone":"+1 800 944 2674",
    "sg:postcode":"46038",
    "sg:province":"IN",
    "sg:tags":[
        "machine",
        "mailing"
    ],
    "sg:website":"www.ame-mail.com",
    "wof:name":"Automated Mailing Equip.",
    "wof:placetype":"venue"
},
  "geometry": {"coordinates":[-86.031721,39.937932],"type":"Point"}
}