{
  "type": "Feature",
  "properties": {
    "addr:full":"825 Ridge Rd Munster IN 46321",
    "addr:housenumber":"825",
    "addr:postcode":"46321",
    "addr:street":"Ridge Rd",
    "iso:country":"US",
    "sg:address":"825 Ridge Rd",
    "sg:city":"Munster",
    "sg:classifiers":[
        {
            "category":"Restaurant",
            "type":"Food & Drink"
        }
    ],
    "sg:menulink":"http://www.allmenus.com/in/north/200352-long-john-silvers/menu/",
    "sg:phone":"+1 219 836 1115",
    "sg:postcode":"46321",
    "sg:province":"IN",
    "sg:tags":[
        "seafood",
        "american"
    ],
    "wof:name":"Long John Silver's",
    "wof:placetype":"venue"
},
  "geometry": {"coordinates":[-87.508053,41.561162],"type":"Point"}
}