{
  "type": "Feature",
  "properties": {
    "addr:full":"8082 Woodglen Pl Indianapolis IN 46260",
    "addr:housenumber":"8082",
    "addr:postcode":"46260",
    "addr:street":"Woodglen Pl",
    "iso:country":"US",
    "sg:address":"8082 Woodglen Pl",
    "sg:city":"Indianapolis",
    "sg:classifiers":[
        {
            "category":"Banks & Credit Unions",
            "subcategory":"Investment Brokerage",
            "type":"Services"
        }
    ],
    "sg:phone":"+1 317 334 0665",
    "sg:postcode":"46260",
    "sg:province":"IN",
    "sg:tags":[
        "consultant",
        "financing"
    ],
    "wof:name":"Grant Specialists",
    "wof:placetype":"venue"
},
  "geometry": {"coordinates":[-86.201008,39.901764],"type":"Point"}
}