{
  "type": "Feature",
  "properties": {
    "iso:country":"US",
    "sg:address":"3654 S East St",
    "sg:city":"Indianapolis",
    "sg:classifiers":[
        {
            "category":"Personal",
            "subcategory":"Beauty Salon",
            "type":"Services"
        }
    ],
    "sg:phone":"+1 317 781 1225",
    "sg:postcode":"46227",
    "sg:province":"IN",
    "sg:tags":[
        "manicuring"
    ],
    "wof:name":"Ten Nail",
    "wof:placetype":"venue"
},
  "geometry": {"coordinates":[-86.14902600000001,39.714445],"type":"Point"}
}