{
  "type": "Feature",
  "properties": {
    "iso:country":"US",
    "sg:address":"44 Knoll Ct",
    "sg:city":"Carmel",
    "sg:classifiers":[
        {
            "category":"Insurance",
            "subcategory":"Insurance Agent",
            "type":"Services"
        }
    ],
    "sg:phone":"+1 317 569 0117",
    "sg:postcode":"46032",
    "sg:province":"IN",
    "wof:name":"Anthem Blue Cross Blue Shield",
    "wof:placetype":"venue"
},
  "geometry": {"coordinates":[-86.133444,39.97873],"type":"Point"}
}