{
  "type": "Feature",
  "properties": {
    "iso:country":"US",
    "sg:address":"5123 S State Rd 159",
    "sg:city":"Dugger",
    "sg:classifiers":[
        {
            "category":"Organizations",
            "subcategory":"Religious Organization",
            "type":"Services"
        }
    ],
    "sg:phone":"+1 812 659 2024",
    "sg:postcode":"47848",
    "sg:province":"IN",
    "sg:tags":[
        "church"
    ],
    "wof:name":"Faith Community Church",
    "wof:placetype":"venue"
},
  "geometry": {"coordinates":[-87.259367,39.007208],"type":"Point"}
}