{
  "type": "Feature",
  "properties": {
    "iso:country":"US",
    "sg:address":"10010 N Co Rd 600 E",
    "sg:city":"Hope",
    "sg:classifiers":[
        {
            "category":"Farming",
            "subcategory":"Farm",
            "type":"Manufacturing & Wholesale Goods"
        }
    ],
    "sg:phone":"+1 812 546 5697",
    "sg:postcode":"47246",
    "sg:province":"IN",
    "sg:tags":[
        "crop",
        "general"
    ],
    "wof:name":"Pence John",
    "wof:placetype":"venue"
},
  "geometry": {"coordinates":[-85.799582,39.297396],"type":"Point"}
}