{
  "type": "Feature",
  "properties": {
    "addr:full":"416 E 4th St Bloomington IN 47408",
    "addr:housenumber":"416",
    "addr:postcode":"47408",
    "addr:street":"E 4Th St",
    "iso:country":"US",
    "sg:address":"416 E 4th St",
    "sg:city":"Bloomington",
    "sg:classifiers":[
        {
            "category":"Restaurant",
            "type":"Food & Drink"
        }
    ],
    "sg:phone":"+1 812 331 8844",
    "sg:postcode":"47408",
    "sg:province":"IN",
    "sg:tags":[
        "indian"
    ],
    "sg:website":"amolindia.net",
    "wof:name":"Amol India",
    "wof:placetype":"venue"
},
  "geometry": {"coordinates":[-86.529523,39.16555],"type":"Point"}
}