{
  "type": "Feature",
  "properties": {
    "iso:country":"US",
    "sg:address":"1237 W Main St",
    "sg:city":"Danville",
    "sg:classifiers":[
        {
            "category":"Autos & Motor Vehicles",
            "subcategory":"Automobile Sales",
            "type":"Retail Goods"
        }
    ],
    "sg:phone":"+1 317 718 1963",
    "sg:postcode":"46122",
    "sg:province":"IN",
    "sg:tags":[
        "car",
        "dealer"
    ],
    "wof:name":"J & M Motors",
    "wof:placetype":"venue"
},
  "geometry": {"coordinates":[-86.537539,39.7604],"type":"Point"}
}