{
  "type": "Feature",
  "properties": {
    "iso:country":"US",
    "sg:address":"1007 Shields Ave",
    "sg:city":"Seymour",
    "sg:classifiers":[
        {
            "category":"Shopping",
            "subcategory":"Bicycles & Sporting Goods",
            "type":"Retail Goods"
        }
    ],
    "sg:phone":"+1 812 523 1335",
    "sg:postcode":"47274",
    "sg:province":"IN",
    "sg:website":"www.jetcuts.com",
    "wof:name":"Waterjet Technical Svc",
    "wof:placetype":"venue"
},
  "geometry": {"coordinates":[-85.892579,38.969037],"type":"Point"}
}