{
  "type": "Feature",
  "properties": {
    "iso:country":"US",
    "sg:address":"345 W 26th St",
    "sg:city":"Indianapolis",
    "sg:classifiers":[
        {
            "category":"Social Services",
            "subcategory":"Child Care",
            "type":"Services"
        }
    ],
    "sg:phone":"+1 317 926 1017",
    "sg:postcode":"46208",
    "sg:province":"IN",
    "wof:name":"Chrissy's Daycare",
    "wof:placetype":"venue"
},
  "geometry": {"coordinates":[-86.165456,39.804214],"type":"Point"}
}