{
  "type": "Feature",
  "properties": {
    "iso:country":"US",
    "sg:address":"2727 164th Pl",
    "sg:city":"Hammond",
    "sg:classifiers":[
        {
            "category":"Arts & Performance",
            "subcategory":"Theater",
            "type":"Entertainment"
        }
    ],
    "sg:phone":"+1 219 845 9318",
    "sg:postcode":"46323",
    "sg:province":"IN",
    "sg:tags":[
        "group"
    ],
    "wof:name":"Magnum Music",
    "wof:placetype":"venue"
},
  "geometry": {"coordinates":[-87.46221,41.596598],"type":"Point"}
}