{
  "type": "Feature",
  "properties": {
    "iso:country":"US",
    "sg:address":"3456 Prospect St",
    "sg:city":"Indianapolis",
    "sg:classifiers":[
        {
            "category":"Retail",
            "subcategory":"Car Wash",
            "type":"Services"
        }
    ],
    "sg:phone":"+1 317 506 7641",
    "sg:postcode":"46203",
    "sg:province":"IN",
    "wof:name":"J & J Auto Detailing",
    "wof:placetype":"venue"
},
  "geometry": {"coordinates":[-86.06316700000001,39.753021],"type":"Point"}
}