{
  "type": "Feature",
  "properties": {
    "iso:country":"US",
    "sg:address":"6235 Carrollton Ave",
    "sg:city":"Indianapolis",
    "sg:classifiers":[
        {
            "category":"Real Estate",
            "subcategory":"Real Estate Services",
            "type":"Services"
        }
    ],
    "sg:phone":"+1 317 202 9630",
    "sg:postcode":"46220",
    "sg:province":"IN",
    "sg:tags":[
        "company",
        "title"
    ],
    "wof:name":"Title Place",
    "wof:placetype":"venue"
},
  "geometry": {"coordinates":[-86.14468599999999,39.869072],"type":"Point"}
}