{
  "type": "Feature",
  "properties": {
    "iso:country":"US",
    "sg:address":"326 E Beecher St",
    "sg:city":"Indianapolis",
    "sg:classifiers":[
        {
            "category":"Building & Trades",
            "subcategory":"Construction",
            "type":"Services"
        }
    ],
    "sg:phone":"+1 317 684 9904",
    "sg:postcode":"46225",
    "sg:province":"IN",
    "sg:tags":[
        "contractor"
    ],
    "wof:name":"Wendells Construction Company",
    "wof:placetype":"venue"
},
  "geometry": {"coordinates":[-86.150416,39.741838],"type":"Point"}
}