{
  "type": "Feature",
  "properties": {
    "iso:country":"US",
    "sg:address":"15 N Ritter Ave",
    "sg:city":"Indianapolis",
    "sg:classifiers":[
        {
            "category":"Health Services",
            "subcategory":"Doctor",
            "type":"Services"
        }
    ],
    "sg:phone":"+1 812 355 2555",
    "sg:postcode":"46219",
    "sg:province":"IN",
    "sg:tags":[
        "physician",
        "surgeon"
    ],
    "wof:name":"Cancer Care Group",
    "wof:placetype":"venue"
},
  "geometry": {"coordinates":[-86.07353500000001,39.773101],"type":"Point"}
}