{
  "type": "Feature",
  "properties": {
    "iso:country":"US",
    "sg:address":"1260 20th Rd",
    "sg:city":"Tippecanoe",
    "sg:classifiers":[
        {
            "category":"Freight",
            "type":"Transportation"
        }
    ],
    "sg:phone":"+1 574 353 7376",
    "sg:postcode":"46570",
    "sg:province":"IN",
    "sg:tags":[
        "hauling",
        "trucking"
    ],
    "wof:name":"Triple S Transportation LLC",
    "wof:placetype":"venue"
},
  "geometry": {"coordinates":[-86.078352,41.187471],"type":"Point"}
}