{
  "type": "Feature",
  "properties": {
    "iso:country":"US",
    "sg:address":"1350 E County Line Rd",
    "sg:city":"Indianapolis",
    "sg:classifiers":[
        {
            "category":"Health Services",
            "subcategory":"Doctor",
            "type":"Services"
        }
    ],
    "sg:phone":"+1 317 887 7790",
    "sg:postcode":"46142",
    "sg:province":"IN",
    "sg:tags":[
        "physician",
        "surgeon"
    ],
    "wof:name":"Indiana Surgery Ctr",
    "wof:placetype":"venue"
},
  "geometry": {"coordinates":[-86.14046500000001,39.635245],"type":"Point"}
}