{
  "type": "Feature",
  "properties": {
    "iso:country":"US",
    "sg:address":"8519 E 46th St",
    "sg:city":"Indianapolis",
    "sg:classifiers":[
        {
            "category":"Food & Beverages",
            "subcategory":"Fruits & Vegetables",
            "type":"Retail Goods"
        }
    ],
    "sg:phone":"+1 317 897 8452",
    "sg:postcode":"46226",
    "sg:province":"IN",
    "sg:tags":[
        "produce"
    ],
    "wof:name":"Karman's Produce",
    "wof:placetype":"venue"
},
  "geometry": {"coordinates":[-86.017535,39.840545],"type":"Point"}
}