{
  "type": "Feature",
  "properties": {
    "addr:full":"8449 Bell Oaks Dr Newburgh IN 47630",
    "addr:housenumber":"8449",
    "addr:postcode":"47630",
    "addr:street":"Bell Oaks Dr",
    "iso:country":"US",
    "sg:address":"8449 Bell Oaks Dr",
    "sg:city":"Newburgh",
    "sg:classifiers":[
        {
            "category":"Shopping",
            "subcategory":"Gifts & Souvenirs",
            "type":"Retail Goods"
        }
    ],
    "sg:phone":"+1 812 853 6822",
    "sg:postcode":"47630",
    "sg:province":"IN",
    "sg:tags":[
        "shop"
    ],
    "wof:name":"Wooden Key Gift & Card Shop",
    "wof:placetype":"venue"
},
  "geometry": {"coordinates":[-87.40364099999999,37.975888],"type":"Point"}
}