{
  "type": "Feature",
  "properties": {
    "iso:country":"US",
    "sg:address":"4071 E Co Rd 75 N",
    "sg:city":"Logansport",
    "sg:classifiers":[
        {
            "category":"Building & Trades",
            "subcategory":"Plumbing",
            "type":"Services"
        }
    ],
    "sg:phone":"+1 574 722 7278",
    "sg:postcode":"46947",
    "sg:province":"IN",
    "sg:tags":[
        "plumbing",
        "contractor"
    ],
    "wof:name":"Mordenti Building Svc",
    "wof:placetype":"venue"
},
  "geometry": {"coordinates":[-86.298712,40.775641],"type":"Point"}
}