{
  "type": "Feature",
  "properties": {
    "addr:full":"1211 N Madison Ave Greenwood IN 46142",
    "addr:housenumber":"1211",
    "addr:postcode":"46142",
    "addr:street":"N Madison Ave",
    "iso:country":"US",
    "sg:address":"1211 N Madison Ave",
    "sg:city":"Greenwood",
    "sg:classifiers":[
        {
            "category":"Shopping",
            "subcategory":"Stationery & Office Supplies",
            "type":"Retail Goods"
        }
    ],
    "sg:phone":"+1 317 889 0148",
    "sg:postcode":"46142",
    "sg:province":"IN",
    "sg:tags":[
        "album",
        "scrapbook"
    ],
    "sg:website":"www.forgetmenotscrapbooks.com",
    "wof:name":"Forget-Me-Not Scrapbook Co",
    "wof:placetype":"venue"
},
  "geometry": {"coordinates":[-86.115515,39.631291],"type":"Point"}
}