{
  "type": "Feature",
  "properties": {
    "iso:country":"US",
    "sg:address":"2040 Indiana Ave",
    "sg:city":"New Albany",
    "sg:classifiers":[
        {
            "category":"Retail",
            "subcategory":"Animal Services",
            "type":"Services"
        }
    ],
    "sg:phone":"+1 812 941 8889",
    "sg:postcode":"47150",
    "sg:province":"IN",
    "sg:tags":[
        "pet",
        "grooming",
        "washing"
    ],
    "wof:name":"Teresa's Classy Critters",
    "wof:placetype":"venue"
},
  "geometry": {"coordinates":[-85.813729,38.309871],"type":"Point"}
}