{
  "type": "Feature",
  "properties": {
    "addr:full":"1919 Co Rd 8 Ashley IN 46705",
    "addr:housenumber":"1919;8",
    "addr:postcode":"46705",
    "addr:street":"Co Rd",
    "iso:country":"US",
    "sg:address":"1919 Co Rd 8",
    "sg:city":"Ashley",
    "sg:classifiers":[
        {
            "category":"Wholesale",
            "subcategory":"Farm Supplies",
            "type":"Manufacturing & Wholesale Goods"
        }
    ],
    "sg:phone":"+1 260 587 3363",
    "sg:postcode":"46705",
    "sg:province":"IN",
    "sg:tags":[
        "grain"
    ],
    "wof:name":"Ackman Sales & Svc",
    "wof:placetype":"venue"
},
  "geometry": {"coordinates":[-85.103595,41.497152],"type":"Point"}
}