{
  "type": "Feature",
  "properties": {
    "addr:full":"1520 Washington St New Castle IN 47362",
    "addr:housenumber":"1520",
    "addr:postcode":"47362",
    "addr:street":"Washington St",
    "iso:country":"US",
    "sg:address":"1520 Washington St",
    "sg:city":"New Castle",
    "sg:classifiers":[
        {
            "category":"Health Services",
            "subcategory":"Doctor",
            "type":"Services"
        }
    ],
    "sg:phone":"+1 765 521 0390",
    "sg:postcode":"47362",
    "sg:province":"IN",
    "sg:tags":[
        "dentist"
    ],
    "wof:name":"Russell P Beckett Inc",
    "wof:placetype":"venue"
},
  "geometry": {"coordinates":[-85.366426,39.939188],"type":"Point"}
}