{
  "type": "Feature",
  "properties": {
    "iso:country":"US",
    "sg:address":"8991 W 900 S",
    "sg:city":"Holland",
    "sg:classifiers":[
        {
            "category":"Government",
            "subcategory":"Office",
            "type":"Public Place"
        }
    ],
    "sg:phone":"+1 812 536 5291",
    "sg:postcode":"47541",
    "sg:province":"IN",
    "sg:tags":[
        "village"
    ],
    "wof:name":"Cass Township Trustee",
    "wof:placetype":"venue"
},
  "geometry": {"coordinates":[-87.060588,38.247166],"type":"Point"}
}