{
  "type": "Feature",
  "properties": {
    "iso:country":"US",
    "sg:address":"10850 N 350 E",
    "sg:city":"Columbus",
    "sg:classifiers":[
        {
            "category":"Real Estate",
            "subcategory":"Real Estate Operator",
            "type":"Services"
        }
    ],
    "sg:phone":"+1 812 376 3543",
    "sg:postcode":"47203",
    "sg:province":"IN",
    "sg:tags":[
        "property",
        "lessor"
    ],
    "wof:name":"Steven Robertson",
    "wof:placetype":"venue"
},
  "geometry": {"coordinates":[-85.847144,39.303313],"type":"Point"}
}