{
  "type": "Feature",
  "properties": {
    "iso:country":"US",
    "sg:address":"1000 Spartan Dr",
    "sg:city":"Columbia City",
    "sg:classifiers":[
        {
            "category":"Food & Beverages",
            "subcategory":"Liquor & Beverages",
            "type":"Retail Goods"
        }
    ],
    "sg:phone":"+1 260 248 2455",
    "sg:postcode":"46725",
    "sg:province":"IN",
    "wof:name":"Dock",
    "wof:placetype":"venue"
},
  "geometry": {"coordinates":[-85.484312,41.171473],"type":"Point"}
}