{
  "type": "Feature",
  "properties": {
    "iso:country":"US",
    "sg:address":"4229 Stellhorn Rd",
    "sg:city":"Fort Wayne",
    "sg:classifiers":[
        {
            "category":"Arts & Performance",
            "subcategory":"Theater",
            "type":"Entertainment"
        }
    ],
    "sg:phone":"+1 260 478 4567",
    "sg:postcode":"46815",
    "sg:province":"IN",
    "sg:tags":[
        "live",
        "music"
    ],
    "wof:name":"Noise Pollution Disc Jockey",
    "wof:placetype":"venue"
},
  "geometry": {"coordinates":[-85.084021,41.119717],"type":"Point"}
}