{
  "type": "Feature",
  "properties": {
    "addr:full":"560 Bond Ave Valparaiso IN 46385",
    "addr:housenumber":"560",
    "addr:postcode":"46385",
    "addr:street":"Bond Ave",
    "iso:country":"US",
    "sg:address":"560 Bond Ave",
    "sg:city":"Valparaiso",
    "sg:classifiers":[
        {
            "category":"Manufacturing",
            "subcategory":"Retail Goods",
            "type":"Manufacturing & Wholesale Goods"
        }
    ],
    "sg:phone":"+1 219 462 5000",
    "sg:postcode":"46385",
    "sg:province":"IN",
    "sg:tags":[
        "manufacturer"
    ],
    "wof:name":"Millennium Manufacturing",
    "wof:placetype":"venue"
},
  "geometry": {"coordinates":[-87.067657,41.477021],"type":"Point"}
}