{
  "type": "Feature",
  "properties": {
    "iso:country":"US",
    "sg:address":"317 Creekside Dr",
    "sg:city":"Franklin",
    "sg:classifiers":[
        {
            "category":"Professional",
            "type":"Services"
        }
    ],
    "sg:phone":"+1 317 738 4338",
    "sg:postcode":"46131",
    "sg:province":"IN",
    "sg:tags":[
        "establishment"
    ],
    "wof:name":"Jarvis Enterprises",
    "wof:placetype":"venue"
},
  "geometry": {"coordinates":[-86.095271,39.48382],"type":"Point"}
}