{
  "type": "Feature",
  "properties": {
    "iso:country":"US",
    "sg:address":"1374 N Union Rd",
    "sg:city":"Frankfort",
    "sg:classifiers":[
        {
            "category":"Utilities",
            "subcategory":"Telephone",
            "type":"Services"
        }
    ],
    "sg:phone":"+1 765 654 4327",
    "sg:postcode":"46041",
    "sg:province":"IN",
    "sg:tags":[
        "telecommunication"
    ],
    "wof:name":"American Tower Corp",
    "wof:placetype":"venue"
},
  "geometry": {"coordinates":[-86.52310799999999,40.301638],"type":"Point"}
}