{
  "type": "Feature",
  "properties": {
    "iso:country":"US",
    "sg:address":"3801 S Western Ave",
    "sg:city":"Marion",
    "sg:classifiers":[
        {
            "category":"Food & Beverages",
            "subcategory":"Groceries & Convenience Stores",
            "type":"Retail Goods"
        }
    ],
    "sg:phone":"+1 765 674 7699",
    "sg:postcode":"46953",
    "sg:province":"IN",
    "wof:name":"Citgo",
    "wof:placetype":"venue"
},
  "geometry": {"coordinates":[-85.67343700000001,40.522224],"type":"Point"}
}