{
  "type": "Feature",
  "properties": {
    "iso:country":"US",
    "sg:address":"2215 S Main St",
    "sg:city":"South Bend",
    "sg:classifiers":[
        {
            "category":"Professional",
            "subcategory":"Business Services",
            "type":"Services"
        }
    ],
    "sg:phone":"+1 574 287 3397",
    "sg:postcode":"46613",
    "sg:province":"IN",
    "sg:tags":[
        "water",
        "treatment"
    ],
    "sg:website":"www.watcon-inc.com",
    "wof:name":"Watcon Inc",
    "wof:placetype":"venue"
},
  "geometry": {"coordinates":[-86.251426,41.650862],"type":"Point"}
}