{
  "type": "Feature",
  "properties": {
    "iso:country":"US",
    "sg:address":"5508 E 16th St",
    "sg:city":"Indianapolis",
    "sg:classifiers":[
        {
            "category":"Health Services",
            "subcategory":"Doctor",
            "type":"Services"
        }
    ],
    "sg:phone":"+1 317 355 2700",
    "sg:postcode":"46218",
    "sg:province":"IN",
    "sg:tags":[
        "physician",
        "surgeon"
    ],
    "wof:name":"Adult Primary Care Medicine",
    "wof:placetype":"venue"
},
  "geometry": {"coordinates":[-86.072675,39.788971],"type":"Point"}
}