{
  "type": "Feature",
  "properties": {
    "iso:country":"US",
    "sg:address":"58 W 5th St",
    "sg:city":"Peru",
    "sg:classifiers":[
        {
            "category":"Organizations",
            "subcategory":"Religious Organization",
            "type":"Services"
        }
    ],
    "sg:phone":"+1 765 473 5543",
    "sg:postcode":"46970",
    "sg:province":"IN",
    "sg:tags":[
        "church"
    ],
    "wof:name":"St Charles Catholic Church",
    "wof:placetype":"venue"
},
  "geometry": {"coordinates":[-86.071511,40.753855],"type":"Point"}
}