{
  "type": "Feature",
  "properties": {
    "iso:country":"US",
    "sg:address":"1226 Mulberry St",
    "sg:city":"Mount Vernon",
    "sg:classifiers":[
        {
            "category":"Real Estate",
            "subcategory":"Real Estate Operator",
            "type":"Services"
        }
    ],
    "sg:phone":"+1 812 838 3656",
    "sg:postcode":"47620",
    "sg:province":"IN",
    "sg:tags":[
        "property",
        "lessor"
    ],
    "wof:name":"Frances Shephard",
    "wof:placetype":"venue"
},
  "geometry": {"coordinates":[-87.896041,37.941519],"type":"Point"}
}