{
  "type": "Feature",
  "properties": {
    "iso:country":"US",
    "sg:address":"715 McClure Rd",
    "sg:city":"Columbus",
    "sg:classifiers":[
        {
            "category":"Social Services",
            "subcategory":"Child Care",
            "type":"Services"
        }
    ],
    "sg:phone":"+1 812 379 2448",
    "sg:postcode":"47201",
    "sg:province":"IN",
    "wof:name":"Head Start",
    "wof:placetype":"venue"
},
  "geometry": {"coordinates":[-85.889776,39.205592],"type":"Point"}
}