{
  "type": "Feature",
  "properties": {
    "iso:country":"US",
    "sg:address":"573 Glenwood Dr",
    "sg:city":"Valparaiso",
    "sg:classifiers":[
        {
            "category":"Building & Trades",
            "subcategory":"Construction",
            "type":"Services"
        }
    ],
    "sg:phone":"+1 219 759 1565",
    "sg:postcode":"46385",
    "sg:province":"IN",
    "sg:tags":[
        "contractor"
    ],
    "wof:name":"Dennis Alderson",
    "wof:placetype":"venue"
},
  "geometry": {"coordinates":[-87.118881,41.518397],"type":"Point"}
}