{
  "type": "Feature",
  "properties": {
    "iso:country":"US",
    "sg:address":"14547 Lima Rd",
    "sg:city":"Fort Wayne",
    "sg:classifiers":[
        {
            "category":"Professional",
            "subcategory":"Business Services",
            "type":"Services"
        },
        {
            "category":"Home & Garden",
            "subcategory":"Carpets & Floor Coverings",
            "type":"Retail Goods"
        }
    ],
    "sg:phone":"+1 260 637 9899",
    "sg:postcode":"46818",
    "sg:province":"IN",
    "sg:tags":[
        "dealer",
        "rug"
    ],
    "wof:name":"Interior Images Inc",
    "wof:placetype":"venue"
},
  "geometry": {"coordinates":[-85.171791,41.217861],"type":"Point"}
}