{
  "type": "Feature",
  "properties": {
    "iso:country":"US",
    "sg:address":"5310 E Morgan Ave",
    "sg:city":"Evansville",
    "sg:classifiers":[
        {
            "category":"Autos & Motor Vehicles",
            "subcategory":"Automobile Sales",
            "type":"Retail Goods"
        }
    ],
    "sg:phone":"+1 812 421 0085",
    "sg:postcode":"47715",
    "sg:province":"IN",
    "sg:tags":[
        "car",
        "dealer"
    ],
    "wof:name":"Kids Cars Inc",
    "wof:placetype":"venue"
},
  "geometry": {"coordinates":[-87.482936,37.993176],"type":"Point"}
}