{
  "type": "Feature",
  "properties": {
    "iso:country":"US",
    "sg:address":"459 Painted Hill",
    "sg:city":"Martinsville",
    "sg:classifiers":[
        {
            "category":"Professional",
            "type":"Services"
        }
    ],
    "sg:phone":"+1 317 490 6926",
    "sg:postcode":"46151",
    "sg:province":"IN",
    "sg:tags":[
        "editorial"
    ],
    "sg:website":"www.funwithjunk.com",
    "wof:name":"All The Write Stuff",
    "wof:placetype":"venue"
},
  "geometry": {"coordinates":[-86.350445,39.407501],"type":"Point"}
}