{
  "type": "Feature",
  "properties": {
    "iso:country":"US",
    "sg:address":"3925 Hagan St Ste 201",
    "sg:city":"Bloomington",
    "sg:classifiers":[
        {
            "category":"Health Services",
            "subcategory":"Doctor",
            "type":"Services"
        }
    ],
    "sg:phone":"+1 812 332 0052",
    "sg:postcode":"47401",
    "sg:province":"IN",
    "sg:tags":[
        "surgeon",
        "oral"
    ],
    "wof:name":"Whitlock Todd DDS",
    "wof:placetype":"venue"
},
  "geometry": {"coordinates":[-86.480598,39.162998],"type":"Point"}
}