{
  "type": "Feature",
  "properties": {
    "addr:full":"2858 E 300 N Portland IN 47371",
    "addr:housenumber":"2858",
    "addr:postcode":"47371",
    "addr:street":"E 300 N",
    "iso:country":"US",
    "sg:address":"2858 E 300 N",
    "sg:city":"Portland",
    "sg:classifiers":[
        {
            "category":"Building & Trades",
            "subcategory":"Electrical",
            "type":"Services"
        }
    ],
    "sg:phone":"+1 260 726 6868",
    "sg:postcode":"47371",
    "sg:province":"IN",
    "sg:tags":[
        "electric",
        "contractor"
    ],
    "wof:name":"Sibery Electric Inc",
    "wof:placetype":"venue"
},
  "geometry": {"coordinates":[-84.935464,40.483254],"type":"Point"}
}