{
  "type": "Feature",
  "properties": {
    "iso:country":"US",
    "sg:address":"3050 E Davis Dr",
    "sg:city":"Terre Haute",
    "sg:classifiers":[
        {
            "category":"Organizations",
            "subcategory":"Religious Organization",
            "type":"Services"
        }
    ],
    "sg:phone":"+1 812 232 4808",
    "sg:postcode":"47802",
    "sg:province":"IN",
    "sg:tags":[
        "church"
    ],
    "wof:name":"Mt Pleasant United Methodist",
    "wof:placetype":"venue"
},
  "geometry": {"coordinates":[-87.37069,39.427054],"type":"Point"}
}