{
  "type": "Feature",
  "properties": {
    "iso:country":"US",
    "sg:address":"5511 Quail Canyon Dr",
    "sg:city":"Fort Wayne",
    "sg:classifiers":[
        {
            "category":"Professional",
            "type":"Services"
        }
    ],
    "sg:phone":"+1 260 485 0979",
    "sg:postcode":"46835",
    "sg:province":"IN",
    "wof:name":"Rodara Inc",
    "wof:placetype":"venue"
},
  "geometry": {"coordinates":[-85.024671,41.134689],"type":"Point"}
}