{
  "type": "Feature",
  "properties": {
    "iso:country":"US",
    "sg:address":"713 E Lincolnway",
    "sg:city":"Laporte",
    "sg:classifiers":[
        {
            "category":"Restaurant",
            "type":"Food & Drink"
        }
    ],
    "sg:phone":"+1 219 324 9272",
    "sg:postcode":"46350",
    "sg:province":"IN",
    "wof:name":"San Julian Restaurant",
    "wof:placetype":"venue"
},
  "geometry": {"coordinates":[-86.704278,41.619015],"type":"Point"}
}