{
  "type": "Feature",
  "properties": {
    "addr:full":"5625 Glenn Rd Indianapolis IN 46216",
    "addr:housenumber":"5625",
    "addr:postcode":"46216",
    "addr:street":"Glenn Rd",
    "iso:country":"US",
    "sg:address":"5625 Glenn Rd",
    "sg:city":"Indianapolis",
    "sg:classifiers":[
        {
            "category":"Professional",
            "subcategory":"Detective & Security Services",
            "type":"Services"
        }
    ],
    "sg:phone":"+1 317 217 1543",
    "sg:postcode":"46216",
    "sg:province":"IN",
    "sg:tags":[
        "information",
        "bureau"
    ],
    "sg:website":"http://www.theincentivemall.com",
    "wof:name":"The Incentive Mall",
    "wof:placetype":"venue"
},
  "geometry": {"coordinates":[-86.021732,39.855877],"type":"Point"}
}