{
  "type": "Feature",
  "properties": {
    "iso:country":"US",
    "sg:address":"836 Jordan Cir",
    "sg:city":"Schererville",
    "sg:classifiers":[
        {
            "category":"Insurance",
            "subcategory":"Insurance Agent",
            "type":"Services"
        }
    ],
    "sg:phone":"+1 219 865 5452",
    "sg:postcode":"46375",
    "sg:province":"IN",
    "wof:name":"Vicki Burton",
    "wof:placetype":"venue"
},
  "geometry": {"coordinates":[-87.431681,41.493142],"type":"Point"}
}