{
  "type": "Feature",
  "properties": {
    "iso:country":"US",
    "sg:address":"7002 Ardmore Ave",
    "sg:city":"Fort Wayne",
    "sg:classifiers":[
        {
            "category":"Freight",
            "type":"Transportation"
        }
    ],
    "sg:phone":"+1 260 747 5625",
    "sg:postcode":"46809",
    "sg:province":"IN",
    "sg:tags":[
        "mover"
    ],
    "sg:website":"www.colenmoving.com",
    "wof:name":"Colen Moving & Storage Inc",
    "wof:placetype":"venue"
},
  "geometry": {"coordinates":[-85.188713,41.019243],"type":"Point"}
}