{
  "type": "Feature",
  "properties": {
    "iso:country":"US",
    "sg:address":"239 Indianapolis Rd",
    "sg:city":"Mooresville",
    "sg:classifiers":[
        {
            "category":"Food & Beverages",
            "subcategory":"Groceries & Convenience Stores",
            "type":"Retail Goods"
        }
    ],
    "sg:phone":"+1 317 831 2848",
    "sg:postcode":"46158",
    "sg:province":"IN",
    "sg:website":"www.caseys.com",
    "wof:name":"Casey's Carry Out Pizza",
    "wof:placetype":"venue"
},
  "geometry": {"coordinates":[-86.365379,39.614604],"type":"Point"}
}