{
  "type": "Feature",
  "properties": {
    "iso:country":"US",
    "sg:address":"108 W Albion St",
    "sg:city":"Avilla",
    "sg:classifiers":[
        {
            "category":"Restaurant",
            "type":"Food & Drink"
        }
    ],
    "sg:phone":"+1 260 897 2612",
    "sg:postcode":"46710",
    "sg:province":"IN",
    "wof:name":"Country Kitchen",
    "wof:placetype":"venue"
},
  "geometry": {"coordinates":[-85.238847,41.365816],"type":"Point"}
}