{
  "type": "Feature",
  "properties": {
    "iso:country":"US",
    "sg:address":"707 N Wildwood Ave",
    "sg:city":"Elkhart",
    "sg:classifiers":[
        {
            "category":"Utilities",
            "subcategory":"Refuse",
            "type":"Services"
        }
    ],
    "sg:phone":"+1 574 295 4611",
    "sg:postcode":"46514",
    "sg:province":"IN",
    "sg:tags":[
        "waste",
        "removal"
    ],
    "wof:name":"Kimedic Technologies Inc",
    "wof:placetype":"venue"
},
  "geometry": {"coordinates":[-86.000984,41.690846],"type":"Point"}
}