{
  "type": "Feature",
  "properties": {
    "addr:full":"7752 Broadway Merrillville IN 46410",
    "addr:housenumber":"7752",
    "addr:postcode":"46410",
    "addr:street":"Broadway",
    "iso:country":"US",
    "sg:address":"7752 Broadway",
    "sg:city":"Merrillville",
    "sg:classifiers":[
        {
            "category":"Home & Garden",
            "subcategory":"Household Appliances",
            "type":"Retail Goods"
        }
    ],
    "sg:phone":"+1 219 472 1124",
    "sg:postcode":"46410",
    "sg:province":"IN",
    "sg:tags":[
        "machine",
        "sewing",
        "machines-household"
    ],
    "sg:website":"http://www.indianasews.com",
    "wof:name":"Northwest Indiana Sewing Centers",
    "wof:placetype":"venue"
},
  "geometry": {"coordinates":[-87.335932,41.477487],"type":"Point"}
}