{
  "type": "Feature",
  "properties": {
    "iso:country":"US",
    "sg:address":"3420 Hickory Rd",
    "sg:city":"Mishawaka",
    "sg:classifiers":[
        {
            "category":"Health Services",
            "subcategory":"Doctor",
            "type":"Services"
        }
    ],
    "sg:phone":"+1 574 256 1579",
    "sg:postcode":"46545",
    "sg:province":"IN",
    "sg:tags":[
        "dentist"
    ],
    "wof:name":"George Mighion DDS",
    "wof:placetype":"venue"
},
  "geometry": {"coordinates":[-86.196518,41.691349],"type":"Point"}
}