{
  "type": "Feature",
  "properties": {
    "iso:country":"US",
    "sg:address":"7422 Brackenwood Cir N",
    "sg:city":"Indianapolis",
    "sg:classifiers":[
        {
            "category":"Professional",
            "subcategory":"Business Services",
            "type":"Services"
        }
    ],
    "sg:phone":"+1 317 899 8994",
    "sg:postcode":"46260",
    "sg:province":"IN",
    "wof:name":"Design Options Inc",
    "wof:placetype":"venue"
},
  "geometry": {"coordinates":[-86.173368,39.888634],"type":"Point"}
}