{
  "type": "Feature",
  "properties": {
    "addr:full":"6988 Bayhill Ct Newburgh IN 47630",
    "addr:housenumber":"6988",
    "addr:postcode":"47630",
    "addr:street":"Bayhill Ct",
    "iso:country":"US",
    "sg:address":"6988 Bayhill Ct",
    "sg:city":"Newburgh",
    "sg:classifiers":[
        {
            "category":"Professional",
            "subcategory":"Business Services",
            "type":"Services"
        }
    ],
    "sg:phone":"+1 812 842 2257",
    "sg:postcode":"47630",
    "sg:province":"IN",
    "wof:name":"Vectren Ventures Inc",
    "wof:placetype":"venue"
},
  "geometry": {"coordinates":[-87.37318,37.941993],"type":"Point"}
}