{
  "type": "Feature",
  "properties": {
    "addr:full":"5801 N Olney St Indianapolis IN 46220",
    "addr:housenumber":"5801",
    "addr:postcode":"46220",
    "addr:street":"N Olney St",
    "iso:country":"US",
    "sg:address":"5801 N Olney St",
    "sg:city":"Indianapolis",
    "sg:classifiers":[
        {
            "category":"Shopping",
            "subcategory":"Used Merchandise",
            "type":"Retail Goods"
        }
    ],
    "sg:phone":"+1 317 356 0463",
    "sg:postcode":"46220",
    "sg:province":"IN",
    "wof:name":"Attic Antiques",
    "wof:placetype":"venue"
},
  "geometry": {"coordinates":[-86.108086,39.860167],"type":"Point"}
}