{
  "type": "Feature",
  "properties": {
    "iso:country":"US",
    "sg:address":"1208 April Dr",
    "sg:city":"Evansville",
    "sg:classifiers":[
        {
            "category":"Shopping",
            "subcategory":"Used Merchandise",
            "type":"Retail Goods"
        }
    ],
    "sg:phone":"+1 812 402 7500",
    "sg:postcode":"47710",
    "sg:province":"IN",
    "sg:tags":[
        "shop",
        "consignment"
    ],
    "wof:name":"Disc",
    "wof:placetype":"venue"
},
  "geometry": {"coordinates":[-87.57978,38.047464],"type":"Point"}
}