{
  "type": "Feature",
  "properties": {
    "iso:country":"US",
    "sg:address":"1341 Kappes St",
    "sg:city":"Indianapolis",
    "sg:classifiers":[
        {
            "category":"Building & Trades",
            "subcategory":"Cleaning & Sanitation",
            "type":"Services"
        }
    ],
    "sg:phone":"+1 317 638 4756",
    "sg:postcode":"46221",
    "sg:province":"IN",
    "sg:tags":[
        "janitor"
    ],
    "wof:name":"Jordon Cleaning Svc",
    "wof:placetype":"venue"
},
  "geometry": {"coordinates":[-86.19427,39.748176],"type":"Point"}
}