{
  "type": "Feature",
  "properties": {
    "addr:full":"1520 N Senate Ave Indianapolis IN 46202",
    "addr:housenumber":"1520",
    "addr:postcode":"46202",
    "addr:street":"N Senate Ave",
    "iso:country":"US",
    "sg:address":"1520 N Senate Ave",
    "sg:city":"Indianapolis",
    "sg:classifiers":[
        {
            "category":"Health Services",
            "subcategory":"Doctor",
            "type":"Services"
        }
    ],
    "sg:phone":"+1 317 962 8893",
    "sg:postcode":"46202",
    "sg:province":"IN",
    "sg:tags":[
        "physician",
        "family",
        "practice",
        "surgeons",
        "medicine"
    ],
    "wof:name":"Iu Methodist Family Pract",
    "wof:placetype":"venue"
},
  "geometry": {"coordinates":[-86.16301799999999,39.787169],"type":"Point"}
}