{
  "type": "Feature",
  "properties": {
    "addr:full":"627 W 7th St Bloomington IN 47404",
    "addr:housenumber":"627",
    "addr:postcode":"47404",
    "addr:street":"W 7Th St",
    "iso:country":"US",
    "sg:address":"627 W 7th St",
    "sg:city":"Bloomington",
    "sg:classifiers":[
        {
            "category":"Health Services",
            "subcategory":"Doctor",
            "type":"Services"
        }
    ],
    "sg:phone":"+1 812 334 1542",
    "sg:postcode":"47404",
    "sg:province":"IN",
    "wof:name":"Arnold Stephen PHD",
    "wof:placetype":"venue"
},
  "geometry": {"coordinates":[-86.540497,39.168499],"type":"Point"}
}