{
  "type": "Feature",
  "properties": {
    "addr:full":"2515 W Washington St Indianapolis IN 46222",
    "addr:housenumber":"2515",
    "addr:postcode":"46222",
    "addr:street":"W Washington St",
    "iso:country":"US",
    "sg:address":"2515 W Washington St",
    "sg:city":"Indianapolis",
    "sg:classifiers":[
        {
            "category":"Professional",
            "subcategory":"Lawyer & Legal Services",
            "type":"Services"
        }
    ],
    "sg:phone":"+1 317 822 3847",
    "sg:postcode":"46222",
    "sg:province":"IN",
    "sg:tags":[
        "attorney"
    ],
    "wof:name":"Maldonado Law Office",
    "wof:placetype":"venue"
},
  "geometry": {"coordinates":[-86.203968,39.765461],"type":"Point"}
}