{
  "type": "Feature",
  "properties": {
    "iso:country":"US",
    "sg:address":"5004 S Plaza Dr",
    "sg:city":"Newburgh",
    "sg:classifiers":[
        {
            "category":"Home & Garden",
            "subcategory":"Home Furnishings",
            "type":"Retail Goods"
        }
    ],
    "sg:phone":"+1 812 853 2859",
    "sg:postcode":"47630",
    "sg:province":"IN",
    "sg:tags":[
        "curtain",
        "made",
        "drapery"
    ],
    "wof:name":"All Sewn Up",
    "wof:placetype":"venue"
},
  "geometry": {"coordinates":[-87.396478,37.961746],"type":"Point"}
}