{
  "type": "Feature",
  "properties": {
    "iso:country":"US",
    "sg:address":"826 Mill Lake Rd",
    "sg:city":"Fort Wayne",
    "sg:classifiers":[
        {
            "category":"Personal",
            "subcategory":"Beauty Salon",
            "type":"Services"
        }
    ],
    "sg:phone":"+1 260 637 1331",
    "sg:postcode":"46845",
    "sg:province":"IN",
    "wof:name":"Classic Image Salon",
    "wof:placetype":"venue"
},
  "geometry": {"coordinates":[-85.131747,41.180986],"type":"Point"}
}