{
  "type": "Feature",
  "properties": {
    "iso:country":"US",
    "sg:address":"8936 Southpointe Dr",
    "sg:city":"Indianapolis",
    "sg:classifiers":[
        {
            "category":"Health Services",
            "subcategory":"Clinic",
            "type":"Services"
        },
        {
            "category":"Government",
            "subcategory":"Office",
            "type":"Public Place"
        }
    ],
    "sg:phone":"+1 317 884 1894",
    "sg:postcode":"46227",
    "sg:province":"IN",
    "sg:tags":[
        "parish",
        "medical",
        "government-county"
    ],
    "wof:name":"County Line Road PSC",
    "wof:placetype":"venue"
},
  "geometry": {"coordinates":[-86.13829,39.637741],"type":"Point"}
}