{
  "type": "Feature",
  "properties": {
    "iso:country":"US",
    "sg:address":"5329 Rothermere Dr",
    "sg:city":"Fort Wayne",
    "sg:classifiers":[
        {
            "category":"Building & Trades",
            "subcategory":"Construction",
            "type":"Services"
        }
    ],
    "sg:phone":"+1 260 486 4876",
    "sg:postcode":"46835",
    "sg:province":"IN",
    "sg:tags":[
        "residential"
    ],
    "wof:name":"G T Houck Constr",
    "wof:placetype":"venue"
},
  "geometry": {"coordinates":[-85.07120399999999,41.157623],"type":"Point"}
}