{
  "type": "Feature",
  "properties": {
    "addr:full":"Clay Terrace 14299 Clay Terrace Blvd 14299 Clay Terrace Blvd. Carmel IN 46032",
    "addr:postcode":"14299;14299;46032",
    "addr:street":"Clay Terrace;Clay Terrace Blvd;Clay Terrace Blvd.",
    "iso:country":"US",
    "sg:address":"Clay Terrace 14299 Clay Terrace Blvd 14299 Clay Terrace Blvd.",
    "sg:city":"Carmel",
    "sg:classifiers":[
        {
            "category":"Food & Beverages",
            "subcategory":"Bakery",
            "type":"Retail Goods"
        }
    ],
    "sg:phone":"+1 317 571 1800",
    "sg:postcode":"46032",
    "sg:province":"IN",
    "sg:tags":[
        "sandwich"
    ],
    "sg:website":"www.jimmyjohns.com",
    "wof:name":"Jimmy John's",
    "wof:placetype":"venue"
},
  "geometry": {"coordinates":[-86.128726,39.995513],"type":"Point"}
}