{
  "type": "Feature",
  "properties": {
    "iso:country":"US",
    "sg:address":"10293 N Meridian St",
    "sg:city":"Indianapolis",
    "sg:classifiers":[
        {
            "category":"Health Services",
            "subcategory":"Optometrist",
            "type":"Services"
        }
    ],
    "sg:phone":"+1 317 846 7600",
    "sg:postcode":"46290",
    "sg:province":"IN",
    "wof:name":"Lynn Burford OD",
    "wof:placetype":"venue"
},
  "geometry": {"coordinates":[-86.157736,39.933953],"type":"Point"}
}