{
  "type": "Feature",
  "properties": {
    "iso:country":"US",
    "sg:address":"10870 12B Rd",
    "sg:city":"Plymouth",
    "sg:classifiers":[
        {
            "category":"Real Estate",
            "subcategory":"Real Estate Operator",
            "type":"Services"
        }
    ],
    "sg:phone":"+1 574 936 6668",
    "sg:postcode":"46563",
    "sg:province":"IN",
    "sg:tags":[
        "property",
        "lessor"
    ],
    "wof:name":"Julia Stockman",
    "wof:placetype":"venue"
},
  "geometry": {"coordinates":[-86.262649,41.296095],"type":"Point"}
}