{
  "type": "Feature",
  "properties": {
    "iso:country":"US",
    "sg:address":"208 N Commerce St",
    "sg:city":"Portland",
    "sg:classifiers":[
        {
            "category":"Retail",
            "subcategory":"Funeral Services",
            "type":"Services"
        }
    ],
    "sg:phone":"+1 260 726 7111",
    "sg:postcode":"47371",
    "sg:province":"IN",
    "sg:tags":[
        "director"
    ],
    "wof:name":"Williamson & Spencer Funeral",
    "wof:placetype":"venue"
},
  "geometry": {"coordinates":[-84.979322,40.435232],"type":"Point"}
}