{
  "type": "Feature",
  "properties": {
    "iso:country":"US",
    "sg:address":"5808 Melton Rd",
    "sg:city":"Gary",
    "sg:classifiers":[
        {
            "category":"Restaurant",
            "type":"Food & Drink"
        }
    ],
    "sg:menulink":"http://www.allmenus.com/in/calumet/120227-subway/menu/",
    "sg:phone":"+1 219 938 9665",
    "sg:postcode":"46403",
    "sg:province":"IN",
    "sg:tags":[
        "american",
        "sandwich"
    ],
    "wof:name":"Subway",
    "wof:placetype":"venue"
},
  "geometry": {"coordinates":[-87.2676,41.596682],"type":"Point"}
}