{
  "type": "Feature",
  "properties": {
    "addr:full":"5142 N Clinton St Terre Haute IN 47805",
    "addr:housenumber":"5142",
    "addr:postcode":"47805",
    "addr:street":"N Clinton St",
    "iso:country":"US",
    "sg:address":"5142 N Clinton St",
    "sg:city":"Terre Haute",
    "sg:classifiers":[
        {
            "category":"Bars & Pubs",
            "type":"Food & Drink"
        }
    ],
    "sg:phone":"+1 812 466 4572",
    "sg:postcode":"47805",
    "sg:province":"IN",
    "wof:name":"Elm Grove Tavern",
    "wof:placetype":"venue"
},
  "geometry": {"coordinates":[-87.36999400000001,39.528623],"type":"Point"}
}