{
  "type": "Feature",
  "properties": {
    "iso:country":"US",
    "sg:address":"8960 Crawfordsville Rd",
    "sg:city":"Indianapolis",
    "sg:classifiers":[
        {
            "category":"Personal",
            "subcategory":"Beauty Salon",
            "type":"Services"
        }
    ],
    "sg:phone":"+1 317 299 9693",
    "sg:postcode":"46234",
    "sg:province":"IN",
    "wof:name":"Changes Styling Salon",
    "wof:placetype":"venue"
},
  "geometry": {"coordinates":[-86.32212,39.815794],"type":"Point"}
}