{
  "type": "Feature",
  "properties": {
    "iso:country":"US",
    "sg:address":"302 W Jackson St",
    "sg:city":"Hebron",
    "sg:classifiers":[
        {
            "category":"Shopping",
            "subcategory":"Computers & Home Electronics",
            "type":"Retail Goods"
        }
    ],
    "sg:phone":"+1 219 996 7121",
    "sg:postcode":"46341",
    "sg:province":"IN",
    "sg:tags":[
        "television",
        "radio"
    ],
    "wof:name":"Arkay TV",
    "wof:placetype":"venue"
},
  "geometry": {"coordinates":[-87.201975,41.315718],"type":"Point"}
}