{
  "type": "Feature",
  "properties": {
    "iso:country":"US",
    "sg:address":"5127 S Fairfax Rd",
    "sg:city":"Bloomington",
    "sg:classifiers":[
        {
            "category":"Wholesale",
            "subcategory":"Chemicals & Plastics",
            "type":"Manufacturing & Wholesale Goods"
        }
    ],
    "sg:phone":"+1 812 824 7720",
    "sg:postcode":"47401",
    "sg:province":"IN",
    "sg:tags":[
        "cleaning",
        "compound"
    ],
    "wof:name":"Product Services",
    "wof:placetype":"venue"
},
  "geometry": {"coordinates":[-86.527242,39.10726],"type":"Point"}
}