{
  "type": "Feature",
  "properties": {
    "iso:country":"US",
    "sg:address":"202 W Berry St",
    "sg:city":"Fort Wayne",
    "sg:classifiers":[
        {
            "category":"Real Estate",
            "subcategory":"Real Estate Agent",
            "type":"Services"
        }
    ],
    "sg:phone":"+1 260 422 0894",
    "sg:postcode":"46802",
    "sg:province":"IN",
    "sg:tags":[
        "appraiser"
    ],
    "wof:name":"Griffin Real Estate Svc Inc",
    "wof:placetype":"venue"
},
  "geometry": {"coordinates":[-85.142168,41.078954],"type":"Point"}
}