{
  "type": "Feature",
  "properties": {
    "addr:full":"1324 Roosevelt Ave New Albany IN 47150",
    "addr:housenumber":"1324",
    "addr:postcode":"47150",
    "addr:street":"Roosevelt Ave",
    "iso:country":"US",
    "sg:address":"1324 Roosevelt Ave",
    "sg:city":"New Albany",
    "sg:classifiers":[
        {
            "category":"Social Services",
            "subcategory":"Adult Care",
            "type":"Services"
        }
    ],
    "sg:phone":"+1 812 948 0353",
    "sg:postcode":"47150",
    "sg:province":"IN",
    "sg:tags":[
        "home",
        "group"
    ],
    "wof:name":"Res-Care Group Home",
    "wof:placetype":"venue"
},
  "geometry": {"coordinates":[-85.81306600000001,38.306277],"type":"Point"}
}