{
  "type": "Feature",
  "properties": {
    "addr:full":"100 N Center St Mishawaka IN 46544",
    "addr:housenumber":"100",
    "addr:postcode":"46544",
    "addr:street":"N Center St",
    "iso:country":"US",
    "sg:address":"100 N Center St",
    "sg:city":"Mishawaka",
    "sg:classifiers":[
        {
            "category":"Shopping",
            "subcategory":"Books",
            "type":"Retail Goods"
        }
    ],
    "sg:phone":"+1 574 254 1411",
    "sg:postcode":"46544",
    "sg:province":"IN",
    "sg:tags":[
        "dealer"
    ],
    "wof:name":"Another Book Store",
    "wof:placetype":"venue"
},
  "geometry": {"coordinates":[-86.18937699999999,41.661591],"type":"Point"}
}