{
  "type": "Feature",
  "properties": {
    "iso:country":"US",
    "sg:address":"7920 N 600 W",
    "sg:city":"Leesburg",
    "sg:classifiers":[
        {
            "category":"Building & Trades",
            "subcategory":"Construction",
            "type":"Services"
        }
    ],
    "sg:phone":"+1 574 453 3838",
    "sg:postcode":"46538",
    "sg:province":"IN",
    "sg:tags":[
        "downspouts",
        "gutter"
    ],
    "wof:name":"Mullet's Seamless Guttering",
    "wof:placetype":"venue"
},
  "geometry": {"coordinates":[-85.961921,41.347062],"type":"Point"}
}