{
  "type": "Feature",
  "properties": {
    "iso:country":"US",
    "sg:address":"8976 Classic View Dr",
    "sg:city":"Indianapolis",
    "sg:classifiers":[
        {
            "category":"Building & Trades",
            "subcategory":"Construction",
            "type":"Services"
        }
    ],
    "sg:phone":"+1 317 590 4510",
    "sg:postcode":"46217",
    "sg:province":"IN",
    "sg:tags":[
        "house"
    ],
    "wof:name":"Payne Construction & Conslt",
    "wof:placetype":"venue"
},
  "geometry": {"coordinates":[-86.162662,39.635659],"type":"Point"}
}