{
  "type": "Feature",
  "properties": {
    "addr:full":"1604 W 250 N Morocco IN 47963",
    "addr:housenumber":"1604",
    "addr:postcode":"47963",
    "addr:street":"W 250 N",
    "iso:country":"US",
    "sg:address":"1604 W 250 N",
    "sg:city":"Morocco",
    "sg:classifiers":[
        {
            "category":"Real Estate",
            "subcategory":"Real Estate Agent",
            "type":"Services"
        }
    ],
    "sg:phone":"+1 219 285 2756",
    "sg:postcode":"47963",
    "sg:province":"IN",
    "wof:name":"Mahan Manor",
    "wof:placetype":"venue"
},
  "geometry": {"coordinates":[-87.42447900000001,41.03579],"type":"Point"}
}