{
  "type": "Feature",
  "properties": {
    "iso:country":"US",
    "sg:address":"30 Gasoline Aly",
    "sg:city":"Indianapolis",
    "sg:classifiers":[
        {
            "category":"Autos & Motor Vehicles",
            "subcategory":"Auto Supplies",
            "type":"Retail Goods"
        }
    ],
    "sg:phone":"+1 317 484 1451",
    "sg:postcode":"46222",
    "sg:province":"IN",
    "sg:tags":[
        "equipment",
        "racing",
        "car",
        "automobile"
    ],
    "sg:website":"www.promaxcarbs.com",
    "wof:name":"Promax Performance",
    "wof:placetype":"venue"
},
  "geometry": {"coordinates":[-86.234428,39.764792],"type":"Point"}
}