{
  "type": "Feature",
  "properties": {
    "addr:full":"7320 Six School Rd Evansville IN 47720",
    "addr:housenumber":"7320",
    "addr:postcode":"47720",
    "addr:street":"Six School Rd",
    "iso:country":"US",
    "sg:address":"7320 Six School Rd",
    "sg:city":"Evansville",
    "sg:phone":"+1 812 963 6067",
    "sg:postcode":"47720",
    "sg:province":"IN",
    "sg:tags":[
        "farm",
        "corn"
    ],
    "wof:name":"Thomas Strupp",
    "wof:placetype":"venue"
},
  "geometry": {"coordinates":[-87.66160000000001,38.051487],"type":"Point"}
}