{
  "type": "Feature",
  "properties": {
    "addr:full":"914 Chase St Anderson IN 46016",
    "addr:housenumber":"914",
    "addr:postcode":"46016",
    "addr:street":"Chase St",
    "iso:country":"US",
    "sg:address":"914 Chase St",
    "sg:city":"Anderson",
    "sg:classifiers":[
        {
            "category":"Social Services",
            "type":"Services"
        }
    ],
    "sg:phone":"+1 765 643 6621",
    "sg:postcode":"46016",
    "sg:province":"IN",
    "sg:tags":[
        "organization",
        "welfare"
    ],
    "sg:website":"www.madisoncounty-redcross.org",
    "wof:name":"American Red Cross",
    "wof:placetype":"venue"
},
  "geometry": {"coordinates":[-85.683015,40.106229],"type":"Point"}
}