{
  "type": "Feature",
  "properties": {
    "addr:full":"222 N Thomas Rd Fort Wayne IN 46808",
    "addr:housenumber":"222",
    "addr:postcode":"46808",
    "addr:street":"N Thomas Rd",
    "iso:country":"US",
    "sg:address":"222 N Thomas Rd",
    "sg:city":"Fort Wayne",
    "sg:classifiers":[
        {
            "category":"Manufacturing",
            "subcategory":"Glass & Minerals",
            "type":"Manufacturing & Wholesale Goods"
        }
    ],
    "sg:phone":"+1 260 432 5031",
    "sg:postcode":"46808",
    "sg:province":"IN",
    "sg:tags":[
        "concrete",
        "brick",
        "prod",
        "block"
    ],
    "sg:website":"www.curbs.com",
    "wof:name":"Minnick Concrete Products Inc",
    "wof:placetype":"venue"
},
  "geometry": {"coordinates":[-85.201571,41.081257],"type":"Point"}
}