{
  "type": "Feature",
  "properties": {
    "iso:country":"US",
    "sg:address":"1152 N Co Rd 650 E",
    "sg:city":"Greensburg",
    "sg:classifiers":[
        {
            "category":"Freight",
            "type":"Transportation"
        }
    ],
    "sg:phone":"+1 812 663 3996",
    "sg:postcode":"47240",
    "sg:province":"IN",
    "sg:tags":[
        "operator",
        "local",
        "trucking"
    ],
    "wof:name":"Riedeman Olmer",
    "wof:placetype":"venue"
},
  "geometry": {"coordinates":[-85.357181,39.360114],"type":"Point"}
}