{
  "type": "Feature",
  "properties": {
    "iso:country":"US",
    "sg:address":"9710 Smith Diamond Rd",
    "sg:city":"Mount Vernon",
    "sg:classifiers":[
        {
            "category":"Real Estate",
            "subcategory":"Real Estate Operator",
            "type":"Services"
        }
    ],
    "sg:phone":"+1 812 985 9839",
    "sg:postcode":"47620",
    "sg:province":"IN",
    "sg:tags":[
        "building",
        "apartment"
    ],
    "wof:name":"Ken Mac Inc",
    "wof:placetype":"venue"
},
  "geometry": {"coordinates":[-87.71266,37.89583],"type":"Point"}
}