{
  "type": "Feature",
  "properties": {
    "iso:country":"US",
    "sg:address":"216 NW 4th St",
    "sg:city":"Evansville",
    "sg:classifiers":[
        {
            "category":"Restaurant",
            "type":"Food & Drink"
        }
    ],
    "sg:phone":"+1 812 423 5113",
    "sg:postcode":"47708",
    "sg:province":"IN",
    "sg:tags":[
        "delicatessen"
    ],
    "wof:name":"Bits & Bytes",
    "wof:placetype":"venue"
},
  "geometry": {"coordinates":[-87.573084,37.9739],"type":"Point"}
}