{
  "type": "Feature",
  "properties": {
    "addr:full":"1209 E 14th St Fowler IN 47944",
    "addr:housenumber":"1209",
    "addr:postcode":"47944",
    "addr:street":"E 14Th St",
    "iso:country":"US",
    "sg:address":"1209 E 14th St",
    "sg:city":"Fowler",
    "sg:classifiers":[
        {
            "category":"Real Estate",
            "subcategory":"Real Estate Operator",
            "type":"Services"
        }
    ],
    "sg:phone":"+1 765 884 1617",
    "sg:postcode":"47944",
    "sg:province":"IN",
    "sg:tags":[
        "farm",
        "corn",
        "property",
        "soybean",
        "lessor"
    ],
    "wof:name":"Donald Victor",
    "wof:placetype":"venue"
},
  "geometry": {"coordinates":[-87.308665,40.609041],"type":"Point"}
}