{
  "type": "Feature",
  "properties": {
    "addr:full":"1715 E Market St New Albany IN 47150",
    "addr:housenumber":"1715",
    "addr:postcode":"47150",
    "addr:street":"E Market St",
    "iso:country":"US",
    "sg:address":"1715 E Market St",
    "sg:city":"New Albany",
    "sg:classifiers":[
        {
            "category":"Organizations",
            "subcategory":"Religious Organization",
            "type":"Services"
        }
    ],
    "sg:phone":"+1 812 944 6382",
    "sg:postcode":"47150",
    "sg:province":"IN",
    "sg:tags":[
        "church"
    ],
    "wof:name":"Howard Chapel Baptist Church",
    "wof:placetype":"venue"
},
  "geometry": {"coordinates":[-85.805308,38.291439],"type":"Point"}
}