{
  "type": "Feature",
  "properties": {
    "iso:country":"US",
    "sg:address":"5824 W US Hwy 40",
    "sg:city":"Greenfield",
    "sg:classifiers":[
        {
            "category":"Building & Trades",
            "subcategory":"Construction",
            "type":"Services"
        }
    ],
    "sg:phone":"+1 317 891 7090",
    "sg:postcode":"46140",
    "sg:province":"IN",
    "sg:tags":[
        "contractor"
    ],
    "wof:name":"Skytech",
    "wof:placetype":"venue"
},
  "geometry": {"coordinates":[-85.910844,39.778817],"type":"Point"}
}