{
  "type": "Feature",
  "properties": {
    "iso:country":"US",
    "sg:address":"823 Lakeview Dr",
    "sg:city":"Scottsburg",
    "sg:classifiers":[
        {
            "category":"Personal",
            "subcategory":"Beauty Salon",
            "type":"Services"
        }
    ],
    "sg:phone":"+1 812 752 4320",
    "sg:postcode":"47170",
    "sg:province":"IN",
    "wof:name":"Scissor Talk",
    "wof:placetype":"venue"
},
  "geometry": {"coordinates":[-85.780318,38.692493],"type":"Point"}
}