{
  "type": "Feature",
  "properties": {
    "iso:country":"US",
    "sg:address":"843 Joliet St",
    "sg:city":"Dyer",
    "sg:classifiers":[
        {
            "category":"Restaurant",
            "type":"Food & Drink"
        }
    ],
    "sg:menulink":"http://www.allmenus.com/in/st-john/136610-smoothie-king/menu/",
    "sg:phone":"+1 219 864 3077",
    "sg:postcode":"46311",
    "sg:province":"IN",
    "sg:tags":[
        "smoothy",
        "juice",
        "american"
    ],
    "wof:name":"Smoothie King",
    "wof:placetype":"venue"
},
  "geometry": {"coordinates":[-87.50652599999999,41.492674],"type":"Point"}
}