{
  "type": "Feature",
  "properties": {
    "iso:country":"US",
    "sg:address":"1 Chisholm Trl",
    "sg:city":"Mooresville",
    "sg:classifiers":[
        {
            "category":"Real Estate",
            "subcategory":"Real Estate Operator",
            "type":"Services"
        }
    ],
    "sg:phone":"+1 317 831 6440",
    "sg:postcode":"46158",
    "sg:province":"IN",
    "sg:tags":[
        "mobile",
        "home",
        "community"
    ],
    "wof:name":"Country Manor Estates",
    "wof:placetype":"venue"
},
  "geometry": {"coordinates":[-86.378805,39.553034],"type":"Point"}
}