{
  "type": "Feature",
  "properties": {
    "iso:country":"US",
    "sg:address":"1555 Howe St",
    "sg:city":"Valparaiso",
    "sg:classifiers":[
        {
            "category":"Utilities",
            "subcategory":"Refuse",
            "type":"Services"
        }
    ],
    "sg:phone":"+1 219 464 3419",
    "sg:postcode":"46385",
    "sg:province":"IN",
    "sg:tags":[
        "garbage",
        "collection"
    ],
    "wof:name":"Alien Waste Haulers",
    "wof:placetype":"venue"
},
  "geometry": {"coordinates":[-87.079583,41.476384],"type":"Point"}
}