{
  "type": "Feature",
  "properties": {
    "iso:country":"US",
    "sg:address":"421 N Main St",
    "sg:city":"Monticello",
    "sg:classifiers":[
        {
            "category":"Organizations",
            "subcategory":"Membership Organization",
            "type":"Services"
        }
    ],
    "sg:phone":"+1 574 583 6465",
    "sg:postcode":"47960",
    "sg:province":"IN",
    "sg:tags":[
        "stone",
        "dimension",
        "quarry"
    ],
    "wof:name":"Autonomy House Publications",
    "wof:placetype":"venue"
},
  "geometry": {"coordinates":[-86.761995,40.751106],"type":"Point"}
}