{
  "type": "Feature",
  "properties": {
    "iso:country":"US",
    "sg:address":"3991 State Rd 46 W",
    "sg:city":"Nashville",
    "sg:classifiers":[
        {
            "category":"Manufacturing",
            "subcategory":"Wood Products",
            "type":"Manufacturing & Wholesale Goods"
        }
    ],
    "sg:phone":"+1 812 988 4055",
    "sg:postcode":"47448",
    "sg:province":"IN",
    "sg:tags":[
        "box"
    ],
    "wof:name":"Knight Woodworking",
    "wof:placetype":"venue"
},
  "geometry": {"coordinates":[-86.304061,39.156021],"type":"Point"}
}