{
  "type": "Feature",
  "properties": {
    "iso:country":"US",
    "sg:address":"4328 E State Rd 55",
    "sg:city":"Morocco",
    "sg:phone":"+1 219 394 2145",
    "sg:postcode":"47963",
    "sg:province":"IN",
    "sg:tags":[
        "farm",
        "grain",
        "cash"
    ],
    "wof:name":"Dave Armold",
    "wof:placetype":"venue"
},
  "geometry": {"coordinates":[-87.295699,40.940392],"type":"Point"}
}