{
  "type": "Feature",
  "properties": {
    "iso:country":"US",
    "sg:address":"5066 S 450 E",
    "sg:city":"Rushville",
    "sg:classifiers":[
        {
            "category":"Freight",
            "type":"Transportation"
        }
    ],
    "sg:phone":"+1 765 932 5304",
    "sg:postcode":"46173",
    "sg:province":"IN",
    "sg:tags":[
        "grain",
        "elevator"
    ],
    "wof:name":"Lowe's Pellets & Grain Inc",
    "wof:placetype":"venue"
},
  "geometry": {"coordinates":[-85.35801499999999,39.536103],"type":"Point"}
}