{
  "type": "Feature",
  "properties": {
    "iso:country":"US",
    "sg:address":"2724 S Carey St",
    "sg:city":"Marion",
    "sg:classifiers":[
        {
            "category":"Social Services",
            "subcategory":"Job Training",
            "type":"Services"
        }
    ],
    "sg:phone":"+1 765 668 4990",
    "sg:postcode":"46953",
    "sg:province":"IN",
    "sg:tags":[
        "rehabilitation"
    ],
    "wof:name":"Capabilities",
    "wof:placetype":"venue"
},
  "geometry": {"coordinates":[-85.67081,40.535851],"type":"Point"}
}