{
  "type": "Feature",
  "properties": {
    "iso:country":"US",
    "sg:address":"2521 N Alabama St",
    "sg:city":"Indianapolis",
    "sg:classifiers":[
        {
            "category":"Professional",
            "subcategory":"Employment Agencies",
            "type":"Services"
        }
    ],
    "sg:phone":"+1 317 253 3910",
    "sg:postcode":"46205",
    "sg:province":"IN",
    "sg:tags":[
        "employer"
    ],
    "wof:name":"Bridal Blessing Ministries Inc",
    "wof:placetype":"venue"
},
  "geometry": {"coordinates":[-86.151901,39.803495],"type":"Point"}
}