{
  "type": "Feature",
  "properties": {
    "addr:full":"979 N Shadeland Ave Indianapolis IN 46219",
    "addr:housenumber":"979",
    "addr:postcode":"46219",
    "addr:street":"N Shadeland Ave",
    "iso:country":"US",
    "sg:address":"979 N Shadeland Ave",
    "sg:city":"Indianapolis",
    "sg:classifiers":[
        {
            "category":"Personal",
            "subcategory":"Beauty Salon",
            "type":"Services"
        },
        {
            "category":"Personal",
            "subcategory":"Barber",
            "type":"Services"
        }
    ],
    "sg:phone":"+1 317 375 1242",
    "sg:postcode":"46219",
    "sg:province":"IN",
    "sg:tags":[
        "hair",
        "accessory",
        "stylist",
        "supply"
    ],
    "sg:website":"http://www.greatclips.com/",
    "wof:name":"Great Clips",
    "wof:placetype":"venue"
},
  "geometry": {"coordinates":[-86.045404,39.781531],"type":"Point"}
}