{
  "type": "Feature",
  "properties": {
    "iso:country":"US",
    "sg:address":"1452 3rd St",
    "sg:city":"Osceola",
    "sg:classifiers":[
        {
            "category":"Professional",
            "subcategory":"Management & Consulting",
            "type":"Services"
        }
    ],
    "sg:phone":"+1 574 651 3666",
    "sg:postcode":"46561",
    "sg:province":"IN",
    "sg:tags":[
        "consultant"
    ],
    "wof:name":"American Consulting Environ",
    "wof:placetype":"venue"
},
  "geometry": {"coordinates":[-86.083336,41.66103],"type":"Point"}
}