{
  "type": "Feature",
  "properties": {
    "iso:country":"US",
    "sg:address":"3474 E 500 N",
    "sg:city":"Whiteland",
    "sg:classifiers":[
        {
            "category":"Autos & Motor Vehicles",
            "subcategory":"Auto Supplies",
            "type":"Retail Goods"
        }
    ],
    "sg:phone":"+1 317 535 5510",
    "sg:postcode":"46184",
    "sg:province":"IN",
    "sg:tags":[
        "tire"
    ],
    "wof:name":"Whiteland Tire & Fleet Svc",
    "wof:placetype":"venue"
},
  "geometry": {"coordinates":[-86.03569,39.55067],"type":"Point"}
}