{
  "type": "Feature",
  "properties": {
    "iso:country":"US",
    "sg:address":"5900 Illinois Rd",
    "sg:city":"Fort Wayne",
    "sg:classifiers":[
        {
            "category":"Autos & Motor Vehicles",
            "subcategory":"Automobile Sales",
            "type":"Retail Goods"
        },
        {
            "category":"Retail",
            "subcategory":"Auto Rental",
            "type":"Services"
        }
    ],
    "sg:phone":"+1 260 969 0015",
    "sg:postcode":"46804",
    "sg:province":"IN",
    "sg:tags":[
        "car",
        "leasing",
        "dealer"
    ],
    "sg:website":"www.rohrman.com",
    "wof:name":"Fort Wayne Lexus & Toyota",
    "wof:placetype":"venue"
},
  "geometry": {"coordinates":[-85.218579,41.074512],"type":"Point"}
}