{
  "type": "Feature",
  "properties": {
    "iso:country":"US",
    "sg:address":"3501 S Anthony Blvd",
    "sg:city":"Fort Wayne",
    "sg:classifiers":[
        {
            "category":"Education",
            "subcategory":"School",
            "type":"Public Place"
        }
    ],
    "sg:phone":"+1 260 425 7371",
    "sg:postcode":"46806",
    "sg:province":"IN",
    "wof:name":"John S Irwin School",
    "wof:placetype":"venue"
},
  "geometry": {"coordinates":[-85.113551,41.051642],"type":"Point"}
}