{
  "type": "Feature",
  "properties": {
    "iso:country":"US",
    "sg:address":"7861 Taft St",
    "sg:city":"Merrillville",
    "sg:classifiers":[
        {
            "category":"Retail",
            "subcategory":"Animal Services",
            "type":"Services"
        }
    ],
    "sg:phone":"+1 219 793 9486",
    "sg:postcode":"46410",
    "sg:province":"IN",
    "sg:tags":[
        "pet",
        "grooming",
        "washing"
    ],
    "wof:name":"Just 4 Dogs",
    "wof:placetype":"venue"
},
  "geometry": {"coordinates":[-87.364907,41.472147],"type":"Point"}
}