{
  "type": "Feature",
  "properties": {
    "iso:country":"US",
    "sg:address":"416 E 9th St",
    "sg:city":"Rochester",
    "sg:classifiers":[
        {
            "category":"Building & Trades",
            "subcategory":"Construction",
            "type":"Services"
        }
    ],
    "sg:phone":"+1 574 223 3123",
    "sg:postcode":"46975",
    "sg:province":"IN",
    "sg:tags":[
        "general",
        "contractor"
    ],
    "wof:name":"Rochester Building Svc Inc",
    "wof:placetype":"venue"
},
  "geometry": {"coordinates":[-86.210416,41.064737],"type":"Point"}
}