{
  "type": "Feature",
  "properties": {
    "iso:country":"US",
    "sg:address":"126 E Dustman Rd",
    "sg:city":"Bluffton",
    "sg:classifiers":[
        {
            "category":"Retail",
            "subcategory":"Repair Shop",
            "type":"Services"
        }
    ],
    "sg:phone":"+1 260 824 4897",
    "sg:postcode":"46714",
    "sg:province":"IN",
    "sg:tags":[
        "upholsterer"
    ],
    "wof:name":"Seams Sew Easy",
    "wof:placetype":"venue"
},
  "geometry": {"coordinates":[-85.164041,40.756904],"type":"Point"}
}