{
  "type": "Feature",
  "properties": {
    "iso:country":"US",
    "sg:address":"141 1st St SW",
    "sg:city":"Carmel",
    "sg:classifiers":[
        {
            "category":"Building & Trades",
            "subcategory":"Cleaning & Sanitation",
            "type":"Services"
        }
    ],
    "sg:phone":"+1 317 774 8278",
    "sg:postcode":"46032",
    "sg:province":"IN",
    "sg:tags":[
        "janitor"
    ],
    "wof:name":"Office Pride",
    "wof:placetype":"venue"
},
  "geometry": {"coordinates":[-86.128602,39.97741],"type":"Point"}
}