{
  "type": "Feature",
  "properties": {
    "iso:country":"US",
    "sg:address":"6900 E 30th St",
    "sg:city":"Indianapolis",
    "sg:classifiers":[
        {
            "category":"Home & Garden",
            "subcategory":"Building Materials",
            "type":"Retail Goods"
        }
    ],
    "sg:phone":"+1 317 898 3510",
    "sg:postcode":"46219",
    "sg:province":"IN",
    "sg:website":"www.inmatesintouch.com",
    "wof:name":"G M Supply Co Inc",
    "wof:placetype":"venue"
},
  "geometry": {"coordinates":[-86.057622,39.811021],"type":"Point"}
}