{
  "type": "Feature",
  "properties": {
    "iso:country":"US",
    "sg:address":"1140 N Phillips St",
    "sg:city":"Kokomo",
    "sg:classifiers":[
        {
            "category":"Building & Trades",
            "subcategory":"Construction",
            "type":"Services"
        }
    ],
    "sg:phone":"+1 765 457 3940",
    "sg:postcode":"46901",
    "sg:province":"IN",
    "sg:tags":[
        "concrete",
        "contractor"
    ],
    "wof:name":"Jansens Asphalt Sealing",
    "wof:placetype":"venue"
},
  "geometry": {"coordinates":[-86.145602,40.496394],"type":"Point"}
}