{
  "type": "Feature",
  "properties": {
    "addr:full":"1376 N Range Line Rd Carmel IN 46032",
    "addr:housenumber":"1376",
    "addr:postcode":"46032",
    "addr:street":"N Range Line Rd",
    "iso:country":"US",
    "sg:address":"1376 N Range Line Rd",
    "sg:city":"Carmel",
    "sg:classifiers":[
        {
            "category":"Personal",
            "subcategory":"Beauty Salon",
            "type":"Services"
        }
    ],
    "sg:phone":"+1 317 844 0808",
    "sg:postcode":"46032",
    "sg:province":"IN",
    "sg:tags":[
        "spa",
        "day"
    ],
    "wof:name":"Spa Cleopatra",
    "wof:placetype":"venue"
},
  "geometry": {"coordinates":[-86.12795199999999,39.992527],"type":"Point"}
}