{
  "type": "Feature",
  "properties": {
    "iso:country":"US",
    "sg:address":"110 E Jackson St",
    "sg:city":"Veedersburg",
    "sg:classifiers":[
        {
            "category":"Manufacturing",
            "subcategory":"Metals",
            "type":"Manufacturing & Wholesale Goods"
        }
    ],
    "sg:phone":"+1 765 294 2841",
    "sg:postcode":"47987",
    "sg:province":"IN",
    "sg:tags":[
        "fabricated",
        "structural"
    ],
    "sg:website":"www.wribmfg.com",
    "wof:name":"WRIB Manufacturing Co Inc",
    "wof:placetype":"venue"
},
  "geometry": {"coordinates":[-87.261403,40.110383],"type":"Point"}
}