{
  "type": "Feature",
  "properties": {
    "iso:country":"US",
    "sg:address":"7007 Indianapolis Blvd",
    "sg:city":"Hammond",
    "sg:classifiers":[
        {
            "category":"Real Estate",
            "subcategory":"Real Estate Services",
            "type":"Services"
        },
        {
            "category":"Real Estate",
            "subcategory":"Real Estate Agent",
            "type":"Services"
        }
    ],
    "sg:phone":"+1 219 844 7007",
    "sg:postcode":"46324",
    "sg:province":"IN",
    "sg:tags":[
        "management",
        "rental"
    ],
    "sg:website":"http://activerain.com/nar",
    "wof:name":"Reeder Companies LLC, Realtors",
    "wof:placetype":"venue"
},
  "geometry": {"coordinates":[-87.480953,41.586466],"type":"Point"}
}