{
  "type": "Feature",
  "properties": {
    "iso:country":"US",
    "sg:address":"4030 Piper Dr",
    "sg:city":"Fort Wayne",
    "sg:classifiers":[
        {
            "category":"Professional",
            "subcategory":"Computer Services",
            "type":"Services"
        }
    ],
    "sg:phone":"+1 260 478 1752",
    "sg:postcode":"46809",
    "sg:province":"IN",
    "sg:tags":[
        "scanning"
    ],
    "wof:name":"Porteum",
    "wof:placetype":"venue"
},
  "geometry": {"coordinates":[-85.188587,40.990992],"type":"Point"}
}