{
  "type": "Feature",
  "properties": {
    "iso:country":"US",
    "sg:address":"421 University Dr",
    "sg:city":"Granger",
    "sg:classifiers":[
        {
            "category":"Wholesale",
            "subcategory":"Sporting Goods",
            "type":"Manufacturing & Wholesale Goods"
        }
    ],
    "sg:phone":"+1 574 243 4513",
    "sg:postcode":"46530",
    "sg:province":"IN",
    "sg:tags":[
        "equipment",
        "pool",
        "swimming"
    ],
    "wof:name":"Leslies Poolmart",
    "wof:placetype":"venue"
},
  "geometry": {"coordinates":[-86.187671,41.719316],"type":"Point"}
}