{
  "type": "Feature",
  "properties": {
    "iso:country":"US",
    "sg:address":"2612 N Home St",
    "sg:city":"Mishawaka",
    "sg:classifiers":[
        {
            "category":"Freight",
            "type":"Transportation"
        }
    ],
    "sg:phone":"+1 574 259 8554",
    "sg:postcode":"46545",
    "sg:province":"IN",
    "sg:tags":[
        "mover"
    ],
    "wof:name":"Wiltfong Moving & Storage Inc",
    "wof:placetype":"venue"
},
  "geometry": {"coordinates":[-86.148196,41.685506],"type":"Point"}
}