{
  "type": "Feature",
  "properties": {
    "iso:country":"US",
    "sg:address":"6147 Hythe Rd",
    "sg:city":"Indianapolis",
    "sg:classifiers":[
        {
            "category":"Organizations",
            "subcategory":"Religious Organization",
            "type":"Services"
        }
    ],
    "sg:phone":"+1 317 849 2166",
    "sg:postcode":"46220",
    "sg:province":"IN",
    "wof:name":"Whitcomb Ministries Inc",
    "wof:placetype":"venue"
},
  "geometry": {"coordinates":[-86.062834,39.881684],"type":"Point"}
}