{
  "type": "Feature",
  "properties": {
    "addr:full":"2448 Lake Circle Dr Indianapolis IN 46268",
    "addr:housenumber":"2448",
    "addr:postcode":"46268",
    "addr:street":"Lake Circle Dr",
    "iso:country":"US",
    "sg:address":"2448 Lake Circle Dr",
    "sg:city":"Indianapolis",
    "sg:classifiers":[
        {
            "category":"Professional",
            "subcategory":"Accounting & Tax Preparation",
            "type":"Services"
        }
    ],
    "sg:phone":"+1 317 879 0843",
    "sg:postcode":"46268",
    "sg:province":"IN",
    "sg:tags":[
        "return",
        "filing"
    ],
    "wof:name":"H & R Block Tax Svc",
    "wof:placetype":"venue"
},
  "geometry": {"coordinates":[-86.20679199999999,39.912791],"type":"Point"}
}