{
  "type": "Feature",
  "properties": {
    "iso:country":"US",
    "sg:address":"2685 Elizaville Rd",
    "sg:city":"Lebanon",
    "sg:classifiers":[
        {
            "category":"Restaurant",
            "type":"Food & Drink"
        }
    ],
    "sg:phone":"+1 765 482 3061",
    "sg:postcode":"46052",
    "sg:province":"IN",
    "sg:tags":[
        "caterer"
    ],
    "sg:website":"www.flowerbarn.net",
    "wof:name":"Flower Barn",
    "wof:placetype":"venue"
},
  "geometry": {"coordinates":[-86.41694699999999,40.093645],"type":"Point"}
}