{
  "type": "Feature",
  "properties": {
    "addr:full":"16150 S 300 W Columbus IN 47201",
    "addr:housenumber":"16150;300",
    "addr:postcode":"47201",
    "addr:street":"S;W Columbus",
    "iso:country":"US",
    "sg:address":"16150 S 300 W",
    "sg:city":"Columbus",
    "sg:classifiers":[
        {
            "category":"Organizations",
            "subcategory":"Religious Organization",
            "type":"Services"
        }
    ],
    "sg:phone":"+1 812 342 3516",
    "sg:postcode":"47201",
    "sg:province":"IN",
    "sg:tags":[
        "church"
    ],
    "wof:name":"St John's Lutheran Church",
    "wof:placetype":"venue"
},
  "geometry": {"coordinates":[-85.960825,39.060217],"type":"Point"}
}