{
  "type": "Feature",
  "properties": {
    "iso:country":"US",
    "sg:address":"236 Waterfall Dr",
    "sg:city":"Elkhart",
    "sg:classifiers":[
        {
            "category":"Real Estate",
            "subcategory":"Real Estate Agent",
            "type":"Services"
        }
    ],
    "sg:phone":"+1 574 294 6249",
    "sg:postcode":"46516",
    "sg:province":"IN",
    "sg:tags":[
        "business"
    ],
    "wof:name":"M L P & Associates",
    "wof:placetype":"venue"
},
  "geometry": {"coordinates":[-85.967566,41.684723],"type":"Point"}
}