{
  "type": "Feature",
  "properties": {
    "iso:country":"US",
    "sg:address":"12045 N Executive Dr",
    "sg:city":"Edinburgh",
    "sg:classifiers":[
        {
            "category":"Shopping",
            "subcategory":"Luggage & Leather Goods",
            "type":"Retail Goods"
        }
    ],
    "sg:phone":"+1 812 526 9474",
    "sg:postcode":"46124",
    "sg:province":"IN",
    "wof:name":"Coach Factory Store",
    "wof:placetype":"venue"
},
  "geometry": {"coordinates":[-85.964374,39.311696],"type":"Point"}
}