{
  "type": "Feature",
  "properties": {
    "addr:full":"2948 N Park Ave Indianapolis IN 46205",
    "addr:housenumber":"2948",
    "addr:postcode":"46205",
    "addr:street":"N Park",
    "iso:country":"US",
    "sg:address":"2948 N Park Ave",
    "sg:city":"Indianapolis",
    "sg:classifiers":[
        {
            "category":"Shopping",
            "subcategory":"Discount & Variety Stores",
            "type":"Retail Goods"
        }
    ],
    "sg:phone":"+1 317 924 6672",
    "sg:postcode":"46205",
    "sg:province":"IN",
    "wof:name":"Martins Variety Store",
    "wof:placetype":"venue"
},
  "geometry": {"coordinates":[-86.147329,39.809426],"type":"Point"}
}