{
  "type": "Feature",
  "properties": {
    "iso:country":"US",
    "sg:address":"905 Woodmere Dr",
    "sg:city":"Lafayette",
    "sg:classifiers":[
        {
            "category":"Building & Trades",
            "subcategory":"Construction",
            "type":"Services"
        }
    ],
    "sg:phone":"+1 765 447 8766",
    "sg:postcode":"47905",
    "sg:province":"IN",
    "sg:tags":[
        "house"
    ],
    "wof:name":"Justice Erich & Melissa",
    "wof:placetype":"venue"
},
  "geometry": {"coordinates":[-86.83691399999999,40.426416],"type":"Point"}
}