{
  "type": "Feature",
  "properties": {
    "iso:country":"US",
    "sg:address":"12262 Hancock St",
    "sg:city":"Carmel",
    "sg:classifiers":[
        {
            "category":"Manufacturing",
            "subcategory":"Printing",
            "type":"Manufacturing & Wholesale Goods"
        }
    ],
    "sg:phone":"+1 317 571 9800",
    "sg:postcode":"46032",
    "sg:province":"IN",
    "sg:tags":[
        "printer"
    ],
    "wof:name":"Moore Services Inc",
    "wof:placetype":"venue"
},
  "geometry": {"coordinates":[-86.148372,39.969677],"type":"Point"}
}