{
  "type": "Feature",
  "properties": {
    "addr:full":"528 Belvedere Dr Kokomo IN 46901",
    "addr:housenumber":"528",
    "addr:postcode":"46901",
    "addr:street":"Belvedere Dr",
    "iso:country":"US",
    "sg:address":"528 Belvedere Dr",
    "sg:city":"Kokomo",
    "sg:classifiers":[
        {
            "category":"Professional",
            "type":"Services"
        }
    ],
    "sg:phone":"+1 765 452 9640",
    "sg:postcode":"46901",
    "sg:province":"IN",
    "sg:tags":[
        "establishment"
    ],
    "wof:name":"Ramey Enterprises",
    "wof:placetype":"venue"
},
  "geometry": {"coordinates":[-86.10639,40.482587],"type":"Point"}
}