{
  "type": "Feature",
  "properties": {
    "iso:country":"US",
    "sg:address":"7624 E 300 S",
    "sg:city":"Glenwood",
    "sg:classifiers":[
        {
            "category":"Retail",
            "subcategory":"Animal Services",
            "type":"Services"
        }
    ],
    "sg:phone":"+1 765 679 5560",
    "sg:postcode":"46133",
    "sg:province":"IN",
    "sg:tags":[
        "cat",
        "dog",
        "kennel"
    ],
    "wof:name":"Pawprint Inn",
    "wof:placetype":"venue"
},
  "geometry": {"coordinates":[-85.30774099999999,39.565808],"type":"Point"}
}