{
  "type": "Feature",
  "properties": {
    "iso:country":"US",
    "sg:address":"10231 Nottawa Trl",
    "sg:city":"Fort Wayne",
    "sg:classifiers":[
        {
            "category":"Professional",
            "type":"Services"
        }
    ],
    "sg:phone":"+1 260 489 6849",
    "sg:postcode":"46825",
    "sg:province":"IN",
    "wof:name":"Szuhaj & Associates LLC",
    "wof:placetype":"venue"
},
  "geometry": {"coordinates":[-85.141801,41.178058],"type":"Point"}
}