{
  "type": "Feature",
  "properties": {
    "iso:country":"US",
    "sg:address":"6335 Intech Commons Dr",
    "sg:city":"Indianapolis",
    "sg:classifiers":[
        {
            "category":"Banks & Credit Unions",
            "subcategory":"Bank",
            "type":"Services"
        }
    ],
    "sg:phone":"+1 317 275 2832",
    "sg:postcode":"46278",
    "sg:province":"IN",
    "sg:tags":[
        "loan",
        "real estate"
    ],
    "wof:name":"Landmark Mortgage",
    "wof:placetype":"venue"
},
  "geometry": {"coordinates":[-86.273102,39.880142],"type":"Point"}
}