{
  "type": "Feature",
  "properties": {
    "iso:country":"US",
    "sg:address":"332 S Ironwood Dr",
    "sg:city":"South Bend",
    "sg:classifiers":[
        {
            "category":"Banks & Credit Unions",
            "subcategory":"Bank",
            "type":"Services"
        }
    ],
    "sg:phone":"+1 574 232 0275",
    "sg:postcode":"46615",
    "sg:province":"IN",
    "sg:tags":[
        "mortgage"
    ],
    "wof:name":"Shelter Mortgage Corporation",
    "wof:placetype":"venue"
},
  "geometry": {"coordinates":[-86.21592,41.674595],"type":"Point"}
}