{
  "type": "Feature",
  "properties": {
    "addr:full":"307 S Grant Ave Fowler IN 47944",
    "addr:housenumber":"307",
    "addr:postcode":"47944",
    "addr:street":"S Grant Ave",
    "iso:country":"US",
    "sg:address":"307 S Grant Ave",
    "sg:city":"Fowler",
    "sg:classifiers":[
        {
            "category":"Banks & Credit Unions",
            "subcategory":"Bank",
            "type":"Services"
        }
    ],
    "sg:phone":"+1 765 884 1230",
    "sg:postcode":"47944",
    "sg:province":"IN",
    "wof:name":"Fifth Third Bank",
    "wof:placetype":"venue"
},
  "geometry": {"coordinates":[-87.314787,40.615754],"type":"Point"}
}