{
  "type": "Feature",
  "properties": {
    "addr:full":"4350 Airport Expy Indianapolis IN 46241",
    "addr:housenumber":"4350",
    "addr:postcode":"46241",
    "addr:street":"Airport Expy",
    "iso:country":"US",
    "sg:address":"4350 Airport Expy",
    "sg:city":"Indianapolis",
    "sg:classifiers":[
        {
            "category":"Real Estate",
            "subcategory":"Real Estate Agent",
            "type":"Services"
        }
    ],
    "sg:phone":"+1 317 481 8069",
    "sg:postcode":"46241",
    "sg:province":"IN",
    "wof:name":"Charterhouse Realty",
    "wof:placetype":"venue"
},
  "geometry": {"coordinates":[-86.237264,39.732179],"type":"Point"}
}