{
  "type": "Feature",
  "properties": {
    "iso:country":"US",
    "sg:address":"9700 Lake Shore Dr E",
    "sg:city":"Indianapolis",
    "sg:classifiers":[
        {
            "category":"Shopping",
            "subcategory":"Crafts & Fabrics",
            "type":"Retail Goods"
        },
        {
            "category":"Shopping",
            "subcategory":"Bridal",
            "type":"Retail Goods"
        }
    ],
    "sg:phone":"+1 317 848 6992",
    "sg:postcode":"46280",
    "sg:province":"IN",
    "sg:tags":[
        "store"
    ],
    "wof:name":"Something Wonderful",
    "wof:placetype":"venue"
},
  "geometry": {"coordinates":[-86.103104,39.929199],"type":"Point"}
}