{
  "type": "Feature",
  "properties": {
    "iso:country":"US",
    "sg:address":"2536 E 1100 S",
    "sg:city":"Brookston",
    "sg:classifiers":[
        {
            "category":"Farming",
            "subcategory":"Farm",
            "type":"Manufacturing & Wholesale Goods"
        }
    ],
    "sg:phone":"+1 765 563 3605",
    "sg:postcode":"47923",
    "sg:province":"IN",
    "wof:name":"Lehe Farms",
    "wof:placetype":"venue"
},
  "geometry": {"coordinates":[-86.824353,40.591186],"type":"Point"}
}