{
  "type": "Feature",
  "properties": {
    "iso:country":"US",
    "sg:address":"6406 Rockville Rd",
    "sg:city":"Indianapolis",
    "sg:classifiers":[
        {
            "category":"Shopping",
            "subcategory":"Florist",
            "type":"Retail Goods"
        }
    ],
    "sg:phone":"+1 317 241 7173",
    "sg:postcode":"46214",
    "sg:province":"IN",
    "wof:name":"Watson's Garden Gate Florist",
    "wof:placetype":"venue"
},
  "geometry": {"coordinates":[-86.274011,39.764703],"type":"Point"}
}