{
  "type": "Feature",
  "properties": {
    "iso:country":"US",
    "sg:address":"4711 Pollack Ave",
    "sg:city":"Evansville",
    "sg:classifiers":[
        {
            "category":"Restaurant",
            "type":"Food & Drink"
        }
    ],
    "sg:phone":"+1 812 402 4022",
    "sg:postcode":"47714",
    "sg:province":"IN",
    "wof:name":"Jimmy's UNA Pizza",
    "wof:placetype":"venue"
},
  "geometry": {"coordinates":[-87.492947,37.947812],"type":"Point"}
}