{
  "type": "Feature",
  "properties": {
    "iso:country":"US",
    "sg:address":"1254 Washington St",
    "sg:city":"Columbus",
    "sg:classifiers":[
        {
            "category":"Wholesale",
            "subcategory":"Machinery & Supplies",
            "type":"Manufacturing & Wholesale Goods"
        }
    ],
    "sg:phone":"+1 812 372 5900",
    "sg:postcode":"47201",
    "sg:province":"IN",
    "sg:tags":[
        "equipment",
        "plastic"
    ],
    "sg:website":"www.premierplastic.com",
    "wof:name":"Premier Plastics Group",
    "wof:placetype":"venue"
},
  "geometry": {"coordinates":[-85.92154,39.212284],"type":"Point"}
}