{
  "type": "Feature",
  "properties": {
    "addr:full":"506 Broadway Chesterton IN 46304",
    "addr:housenumber":"506",
    "addr:postcode":"46304",
    "addr:street":"Broadway",
    "iso:country":"US",
    "sg:address":"506 Broadway",
    "sg:city":"Chesterton",
    "sg:classifiers":[
        {
            "category":"Manufacturing",
            "subcategory":"Metals",
            "type":"Manufacturing & Wholesale Goods"
        }
    ],
    "sg:phone":"+1 219 926 4528",
    "sg:postcode":"46304",
    "sg:province":"IN",
    "sg:tags":[
        "tower"
    ],
    "wof:name":"JRG Communications Inc",
    "wof:placetype":"venue"
},
  "geometry": {"coordinates":[-87.05898500000001,41.611423],"type":"Point"}
}