{
  "type": "Feature",
  "properties": {
    "iso:country":"US",
    "sg:address":"2 N Slonneger St",
    "sg:city":"Liberty",
    "sg:classifiers":[
        {
            "category":"Farming",
            "subcategory":"Nursery",
            "type":"Manufacturing & Wholesale Goods"
        }
    ],
    "sg:phone":"+1 765 458 6889",
    "sg:postcode":"47353",
    "sg:province":"IN",
    "sg:tags":[
        "greenhouse"
    ],
    "wof:name":"Liberty Greenhouse",
    "wof:placetype":"venue"
},
  "geometry": {"coordinates":[-84.938492,39.636398],"type":"Point"}
}