{
  "type": "Feature",
  "properties": {
    "iso:country":"US",
    "sg:address":"564 N Union St",
    "sg:city":"Pennville",
    "sg:classifiers":[
        {
            "category":"Professional",
            "type":"Services"
        }
    ],
    "sg:phone":"+1 260 731 2335",
    "sg:postcode":"47369",
    "sg:province":"IN",
    "wof:name":"Shack Lo",
    "wof:placetype":"venue"
},
  "geometry": {"coordinates":[-85.148382,40.496362],"type":"Point"}
}