{
  "type": "Feature",
  "properties": {
    "iso:country":"US",
    "sg:address":"303 N 12th St",
    "sg:city":"Petersburg",
    "sg:classifiers":[
        {
            "category":"Professional",
            "subcategory":"Accounting & Tax Preparation",
            "type":"Services"
        }
    ],
    "sg:phone":"+1 812 354 9673",
    "sg:postcode":"47567",
    "sg:province":"IN",
    "sg:tags":[
        "return"
    ],
    "wof:name":"Robling Tax Service",
    "wof:placetype":"venue"
},
  "geometry": {"coordinates":[-87.278813,38.495121],"type":"Point"}
}