{
  "type": "Feature",
  "properties": {
    "iso:country":"US",
    "sg:address":"9355 E US Hwy 40",
    "sg:city":"Terre Haute",
    "sg:classifiers":[
        {
            "category":"Food & Beverages",
            "subcategory":"Liquor & Beverages",
            "type":"Retail Goods"
        }
    ],
    "sg:phone":"+1 812 877 3388",
    "sg:postcode":"47803",
    "sg:province":"IN",
    "wof:name":"Seelyville Liquor Store",
    "wof:placetype":"venue"
},
  "geometry": {"coordinates":[-87.271192,39.49332],"type":"Point"}
}