{
  "type": "Feature",
  "properties": {
    "iso:country":"US",
    "sg:address":"100 S Union St",
    "sg:city":"Kokomo",
    "sg:classifiers":[
        {
            "category":"Government",
            "subcategory":"Police Station",
            "type":"Public Place"
        }
    ],
    "sg:phone":"+1 765 456 7100",
    "sg:postcode":"46901",
    "sg:province":"IN",
    "sg:tags":[
        "department"
    ],
    "wof:name":"Kokomo Police Dept",
    "wof:placetype":"venue"
},
  "geometry": {"coordinates":[-86.12997,40.485547],"type":"Point"}
}