{
  "type": "Feature",
  "properties": {
    "iso:country":"US",
    "sg:address":"607 Beechwood Ave",
    "sg:city":"Middletown",
    "sg:classifiers":[
        {
            "category":"Building & Trades",
            "subcategory":"Construction",
            "type":"Services"
        }
    ],
    "sg:phone":"+1 765 354 2741",
    "sg:postcode":"47356",
    "sg:province":"IN",
    "sg:tags":[
        "light",
        "remodeling",
        "commercial"
    ],
    "wof:name":"Jon E Thomas",
    "wof:placetype":"venue"
},
  "geometry": {"coordinates":[-85.541003,40.060612],"type":"Point"}
}