{
  "type": "Feature",
  "properties": {
    "addr:full":"145 E Elm St New Albany IN 47150",
    "addr:housenumber":"145",
    "addr:postcode":"47150",
    "addr:street":"E Elm St",
    "iso:country":"US",
    "sg:address":"145 E Elm St",
    "sg:city":"New Albany",
    "sg:classifiers":[
        {
            "category":"Government",
            "subcategory":"Post Office",
            "type":"Public Place"
        }
    ],
    "sg:phone":"+1 812 948 0649",
    "sg:postcode":"47150",
    "sg:province":"IN",
    "wof:name":"US Post Office",
    "wof:placetype":"venue"
},
  "geometry": {"coordinates":[-85.822856,38.287421],"type":"Point"}
}