{
  "type": "Feature",
  "properties": {
    "addr:full":"123 S Kingston Dr Bloomington IN 47408",
    "addr:housenumber":"123",
    "addr:postcode":"47408",
    "addr:street":"S Kingston Dr",
    "iso:country":"US",
    "sg:address":"123 S Kingston Dr",
    "sg:city":"Bloomington",
    "sg:classifiers":[
        {
            "category":"Food & Beverages",
            "subcategory":"Groceries & Convenience Stores",
            "type":"Retail Goods"
        }
    ],
    "sg:phone":"+1 812 355 8700",
    "sg:postcode":"47408",
    "sg:province":"IN",
    "sg:website":"www.marsh.net",
    "wof:name":"Marsh Supermarkets",
    "wof:placetype":"venue"
},
  "geometry": {"coordinates":[-86.49276999999999,39.166571],"type":"Point"}
}