{
  "type": "Feature",
  "properties": {
    "iso:country":"US",
    "sg:address":"716 W Co Rd 950 N",
    "sg:city":"Chrisney",
    "sg:classifiers":[
        {
            "category":"Farming",
            "subcategory":"Farm",
            "type":"Manufacturing & Wholesale Goods"
        }
    ],
    "sg:phone":"+1 812 362 8332",
    "sg:postcode":"47611",
    "sg:province":"IN",
    "sg:tags":[
        "crop",
        "general"
    ],
    "wof:name":"Doug Smith",
    "wof:placetype":"venue"
},
  "geometry": {"coordinates":[-87.06414100000001,38.024633],"type":"Point"}
}