{
  "type": "Feature",
  "properties": {
    "iso:country":"US",
    "sg:address":"2847 S 250 E",
    "sg:city":"Shelbyville",
    "sg:classifiers":[
        {
            "category":"Building & Trades",
            "subcategory":"Construction",
            "type":"Services"
        }
    ],
    "sg:phone":"+1 317 392 4127",
    "sg:postcode":"46176",
    "sg:province":"IN",
    "sg:tags":[
        "dry wall",
        "contractor"
    ],
    "wof:name":"Gary Perry Drywall",
    "wof:placetype":"venue"
},
  "geometry": {"coordinates":[-85.732619,39.485359],"type":"Point"}
}