{
  "type": "Feature",
  "properties": {
    "iso:country":"US",
    "sg:address":"10365 State Rd 3",
    "sg:city":"Deputy",
    "sg:classifiers":[
        {
            "category":"Building & Trades",
            "subcategory":"Construction",
            "type":"Services"
        }
    ],
    "sg:phone":"+1 812 346 7432",
    "sg:postcode":"47230",
    "sg:province":"IN",
    "sg:tags":[
        "excavating",
        "contractor"
    ],
    "wof:name":"J L Browning",
    "wof:placetype":"venue"
},
  "geometry": {"coordinates":[-85.643827,38.833422],"type":"Point"}
}