{
  "type": "Feature",
  "properties": {
    "iso:country":"US",
    "sg:address":"5210 Commerce Cir",
    "sg:city":"Indianapolis",
    "sg:classifiers":[
        {
            "category":"Wholesale",
            "subcategory":"Construction Materials",
            "type":"Manufacturing & Wholesale Goods"
        },
        {
            "category":"Building & Trades",
            "subcategory":"Construction",
            "type":"Services"
        },
        {
            "category":"Home & Garden",
            "subcategory":"Carpets & Floor Coverings",
            "type":"Retail Goods"
        }
    ],
    "sg:phone":"+1 317 426 1398",
    "sg:postcode":"46237",
    "sg:province":"IN",
    "sg:tags":[
        "layer",
        "installation",
        "flooring",
        "contractor",
        "tile-contractors",
        "linoleum"
    ],
    "sg:website":"http://www.yext.com/p/superpages/mc-cammack-tile-indianapolis-indiana.html",
    "wof:name":"McCammack Tile",
    "wof:placetype":"venue"
},
  "geometry": {"coordinates":[-86.08043499999999,39.655463],"type":"Point"}
}