{
  "type": "Feature",
  "properties": {
    "iso:country":"US",
    "sg:address":"4218 Hobson Rd",
    "sg:city":"Fort Wayne",
    "sg:classifiers":[
        {
            "category":"Banks & Credit Unions",
            "subcategory":"Bank",
            "type":"Services"
        }
    ],
    "sg:phone":"+1 260 485 8151",
    "sg:postcode":"46815",
    "sg:province":"IN",
    "sg:tags":[
        "loan",
        "real estate"
    ],
    "wof:name":"Maximum Mortgage Inc",
    "wof:placetype":"venue"
},
  "geometry": {"coordinates":[-85.099689,41.116695],"type":"Point"}
}