{
  "type": "Feature",
  "properties": {
    "iso:country":"US",
    "sg:address":"2336 N A St",
    "sg:city":"Elwood",
    "sg:classifiers":[
        {
            "category":"Shopping",
            "subcategory":"Used Merchandise",
            "type":"Retail Goods"
        }
    ],
    "sg:phone":"+1 765 552 0828",
    "sg:postcode":"46036",
    "sg:province":"IN",
    "sg:tags":[
        "antique"
    ],
    "wof:name":"Homeheartland",
    "wof:placetype":"venue"
},
  "geometry": {"coordinates":[-85.83109399999999,40.278044],"type":"Point"}
}