{
  "type": "Feature",
  "properties": {
    "iso:country":"US",
    "sg:address":"9071 W 1100 S",
    "sg:city":"Covington",
    "sg:phone":"+1 765 793 2913",
    "sg:postcode":"47932",
    "sg:province":"IN",
    "sg:tags":[
        "farm",
        "grain",
        "cash"
    ],
    "wof:name":"Lewsader Farms",
    "wof:placetype":"venue"
},
  "geometry": {"coordinates":[-87.490651,40.155739],"type":"Point"}
}