{
  "type": "Feature",
  "properties": {
    "addr:full":"312 N 8th St Lafayette IN 47901",
    "addr:housenumber":"312",
    "addr:postcode":"47901",
    "addr:street":"N 8Th St",
    "iso:country":"US",
    "sg:address":"312 N 8th St",
    "sg:city":"Lafayette",
    "sg:classifiers":[
        {
            "category":"Social Services",
            "type":"Services"
        }
    ],
    "sg:phone":"+1 765 423 4880",
    "sg:postcode":"47901",
    "sg:province":"IN",
    "sg:tags":[
        "organization",
        "welfare"
    ],
    "wof:name":"Lafayette Transitional Housing",
    "wof:placetype":"venue"
},
  "geometry": {"coordinates":[-86.888366,40.420829],"type":"Point"}
}