{
  "type": "Feature",
  "properties": {
    "iso:country":"US",
    "sg:address":"7258 S Co Rd 600 W",
    "sg:city":"Greensburg",
    "sg:classifiers":[
        {
            "category":"Professional",
            "subcategory":"Business Services",
            "type":"Services"
        }
    ],
    "sg:phone":"+1 812 591 2893",
    "sg:postcode":"47240",
    "sg:province":"IN",
    "wof:name":"Kenneth Owens",
    "wof:placetype":"venue"
},
  "geometry": {"coordinates":[-85.594408,39.230219],"type":"Point"}
}