{
  "type": "Feature",
  "properties": {
    "iso:country":"US",
    "sg:address":"685 Patrick Pl",
    "sg:city":"Brownsburg",
    "sg:classifiers":[
        {
            "category":"Social Services",
            "subcategory":"Child Care",
            "type":"Services"
        }
    ],
    "sg:phone":"+1 317 858 8033",
    "sg:postcode":"46112",
    "sg:province":"IN",
    "wof:name":"Brownsburg Community Child",
    "wof:placetype":"venue"
},
  "geometry": {"coordinates":[-86.384012,39.853636],"type":"Point"}
}