{
  "type": "Feature",
  "properties": {
    "iso:country":"US",
    "sg:address":"599 W 79th St",
    "sg:city":"Indianapolis",
    "sg:classifiers":[
        {
            "category":"Wholesale",
            "subcategory":"Office Equipment",
            "type":"Manufacturing & Wholesale Goods"
        }
    ],
    "sg:phone":"+1 317 475 9806",
    "sg:postcode":"46260",
    "sg:province":"IN",
    "sg:tags":[
        "equipment-wholesale",
        "manufacturer",
        "furniture"
    ],
    "wof:name":"Ikon Intelligence Corporation",
    "wof:placetype":"venue"
},
  "geometry": {"coordinates":[-86.17037500000001,39.897621],"type":"Point"}
}