{
  "type": "Feature",
  "properties": {
    "iso:country":"US",
    "sg:address":"315 S Ferris St",
    "sg:city":"Sullivan",
    "sg:classifiers":[
        {
            "category":"Organizations",
            "subcategory":"Religious Organization",
            "type":"Services"
        }
    ],
    "sg:phone":"+1 812 268 5709",
    "sg:postcode":"47882",
    "sg:province":"IN",
    "sg:tags":[
        "church"
    ],
    "wof:name":"Bible View Baptist Church Inc",
    "wof:placetype":"venue"
},
  "geometry": {"coordinates":[-87.394494,39.091764],"type":"Point"}
}