{
  "type": "Feature",
  "properties": {
    "iso:country":"US",
    "sg:address":"430 N Jefferson St",
    "sg:city":"Huntington",
    "sg:classifiers":[
        {
            "category":"Professional",
            "subcategory":"Accounting & Tax Preparation",
            "type":"Services"
        }
    ],
    "sg:phone":"+1 260 356 8888",
    "sg:postcode":"46750",
    "sg:province":"IN",
    "sg:tags":[
        "accountant"
    ],
    "wof:name":"Carnes Co",
    "wof:placetype":"venue"
},
  "geometry": {"coordinates":[-85.495159,40.882065],"type":"Point"}
}