{
  "type": "Feature",
  "properties": {
    "addr:full":"1063 N Pershing Ave Indianapolis IN 46222",
    "addr:housenumber":"1063",
    "addr:postcode":"46222",
    "addr:street":"N Pershing Ave",
    "iso:country":"US",
    "sg:address":"1063 N Pershing Ave",
    "sg:city":"Indianapolis",
    "sg:classifiers":[
        {
            "category":"Organizations",
            "subcategory":"Religious Organization",
            "type":"Services"
        }
    ],
    "sg:phone":"+1 317 636 6459",
    "sg:postcode":"46222",
    "sg:province":"IN",
    "sg:tags":[
        "church"
    ],
    "wof:name":"Eternal Life Apostolic Church",
    "wof:placetype":"venue"
},
  "geometry": {"coordinates":[-86.199382,39.781369],"type":"Point"}
}