{
  "type": "Feature",
  "properties": {
    "addr:full":"8702 E Washington St Indianapolis IN 46219",
    "addr:housenumber":"8702",
    "addr:postcode":"46219",
    "addr:street":"E Washington St",
    "iso:country":"US",
    "sg:address":"8702 E Washington St",
    "sg:city":"Indianapolis",
    "sg:classifiers":[
        {
            "category":"Autos & Motor Vehicles",
            "subcategory":"Auto Supplies",
            "type":"Retail Goods"
        }
    ],
    "sg:phone":"+1 317 895 0011",
    "sg:postcode":"46219",
    "sg:province":"IN",
    "sg:tags":[
        "automobile",
        "parts"
    ],
    "wof:name":"Autozone",
    "wof:placetype":"venue"
},
  "geometry": {"coordinates":[-86.013229,39.773806],"type":"Point"}
}