{
  "type": "Feature",
  "properties": {
    "addr:full":"7936 S State Rd 3 Milroy IN 46156",
    "addr:housenumber":"7936",
    "addr:postcode":"46156",
    "addr:street":"S State Rd 3",
    "iso:country":"US",
    "sg:address":"7936 S State Rd 3",
    "sg:city":"Milroy",
    "sg:classifiers":[
        {
            "category":"Personal",
            "subcategory":"Beauty Salon",
            "type":"Services"
        }
    ],
    "sg:phone":"+1 765 629 1230",
    "sg:postcode":"46156",
    "sg:province":"IN",
    "sg:tags":[
        "manicuring"
    ],
    "wof:name":"Nails & More",
    "wof:placetype":"venue"
},
  "geometry": {"coordinates":[-85.47572599999999,39.497941],"type":"Point"}
}