{
  "type": "Feature",
  "properties": {
    "addr:full":"6980 W Washington St Indianapolis IN 46241",
    "addr:housenumber":"6980",
    "addr:postcode":"46241",
    "addr:street":"W Washington St",
    "iso:country":"US",
    "sg:address":"6980 W Washington St",
    "sg:city":"Indianapolis",
    "sg:classifiers":[
        {
            "category":"Autos & Motor Vehicles",
            "subcategory":"Automobile Sales",
            "type":"Retail Goods"
        }
    ],
    "sg:phone":"+1 317 486 3915",
    "sg:postcode":"46241",
    "sg:province":"IN",
    "sg:tags":[
        "car",
        "dealer"
    ],
    "wof:name":"Enterprise Car Sales",
    "wof:placetype":"venue"
},
  "geometry": {"coordinates":[-86.282432,39.743042],"type":"Point"}
}