{
  "type": "Feature",
  "properties": {
    "iso:country":"US",
    "sg:address":"4000 E 96th St",
    "sg:city":"Indianapolis",
    "sg:classifiers":[
        {
            "category":"Wholesale",
            "subcategory":"Durable Goods & Equipment",
            "type":"Manufacturing & Wholesale Goods"
        }
    ],
    "sg:phone":"+1 317 575 4600",
    "sg:postcode":"46240",
    "sg:province":"IN",
    "sg:tags":[
        "representative",
        "manufacturer"
    ],
    "wof:name":"Alliance Electronics Marketing",
    "wof:placetype":"venue"
},
  "geometry": {"coordinates":[-86.100506,39.926884],"type":"Point"}
}