{
  "type": "Feature",
  "properties": {
    "iso:country":"US",
    "sg:address":"315 E Havens St",
    "sg:city":"Kokomo",
    "sg:classifiers":[
        {
            "category":"Organizations",
            "subcategory":"Community Association",
            "type":"Services"
        }
    ],
    "sg:phone":"+1 765 452 5800",
    "sg:postcode":"46901",
    "sg:province":"IN",
    "sg:tags":[
        "fraternal"
    ],
    "wof:name":"Elks Lodge",
    "wof:placetype":"venue"
},
  "geometry": {"coordinates":[-86.129012,40.494226],"type":"Point"}
}