{
  "type": "Feature",
  "properties": {
    "iso:country":"US",
    "sg:address":"5319 Cardiff Ct",
    "sg:city":"Fort Wayne",
    "sg:classifiers":[
        {
            "category":"Building & Trades",
            "subcategory":"Landscaping Services",
            "type":"Services"
        }
    ],
    "sg:phone":"+1 260 485 6080",
    "sg:postcode":"46835",
    "sg:province":"IN",
    "wof:name":"Durham Tree & Shrub",
    "wof:placetype":"venue"
},
  "geometry": {"coordinates":[-85.046301,41.131143],"type":"Point"}
}