{
  "type": "Feature",
  "properties": {
    "iso:country":"US",
    "sg:address":"70 Brown St",
    "sg:city":"Vernon",
    "sg:classifiers":[
        {
            "category":"Restaurant",
            "type":"Food & Drink"
        }
    ],
    "sg:phone":"+1 812 346 7177",
    "sg:postcode":"47282",
    "sg:province":"IN",
    "wof:name":"Laural House LLC",
    "wof:placetype":"venue"
},
  "geometry": {"coordinates":[-85.610434,38.985661],"type":"Point"}
}