{
  "type": "Feature",
  "properties": {
    "iso:country":"US",
    "sg:address":"8 S 8th St",
    "sg:city":"Richmond",
    "sg:classifiers":[
        {
            "category":"Organizations",
            "subcategory":"Community Association",
            "type":"Services"
        }
    ],
    "sg:phone":"+1 765 966 0950",
    "sg:postcode":"47374",
    "sg:province":"IN",
    "sg:tags":[
        "fraternal"
    ],
    "wof:name":"IOOF",
    "wof:placetype":"venue"
},
  "geometry": {"coordinates":[-84.891626,39.828936],"type":"Point"}
}