{
  "type": "Feature",
  "properties": {
    "addr:full":"2795 E Main St Plainfield IN 46168",
    "addr:housenumber":"2795",
    "addr:postcode":"46168",
    "addr:street":"E Main St",
    "iso:country":"US",
    "sg:address":"2795 E Main St",
    "sg:city":"Plainfield",
    "sg:classifiers":[
        {
            "category":"Autos & Motor Vehicles",
            "subcategory":"Automobile Sales",
            "type":"Retail Goods"
        }
    ],
    "sg:phone":"+1 317 838 0800",
    "sg:postcode":"46168",
    "sg:province":"IN",
    "sg:tags":[
        "car",
        "dealer"
    ],
    "wof:name":"American Auto Team",
    "wof:placetype":"venue"
},
  "geometry": {"coordinates":[-86.34835099999999,39.721292],"type":"Point"}
}