{
  "type": "Feature",
  "properties": {
    "iso:country":"US",
    "sg:address":"639 Windy Cove Ct",
    "sg:city":"Mishawaka",
    "sg:classifiers":[
        {
            "category":"Personal",
            "type":"Services"
        }
    ],
    "sg:phone":"+1 574 257 0309",
    "sg:postcode":"46544",
    "sg:province":"IN",
    "sg:tags":[
        "cosmetic"
    ],
    "wof:name":"Permanent Cosmetics",
    "wof:placetype":"venue"
},
  "geometry": {"coordinates":[-86.100789,41.671658],"type":"Point"}
}