{
  "type": "Feature",
  "properties": {
    "iso:country":"US",
    "sg:address":"5649 N 800 W",
    "sg:city":"Mc Cordsville",
    "sg:classifiers":[
        {
            "category":"Personal",
            "subcategory":"Beauty Salon",
            "type":"Services"
        }
    ],
    "sg:phone":"+1 317 823 6004",
    "sg:postcode":"46055",
    "sg:province":"IN",
    "sg:tags":[
        "shop"
    ],
    "wof:name":"Sues Beauty Salon",
    "wof:placetype":"venue"
},
  "geometry": {"coordinates":[-85.953926,39.869068],"type":"Point"}
}