{
  "type": "Feature",
  "properties": {
    "iso:country":"US",
    "sg:address":"29 Tulip St",
    "sg:city":"Martinsville",
    "sg:classifiers":[
        {
            "category":"Cinema",
            "subcategory":"Movie Rental",
            "type":"Entertainment"
        }
    ],
    "sg:phone":"+1 765 342 0699",
    "sg:postcode":"46151",
    "sg:province":"IN",
    "sg:tags":[
        "leasing",
        "video",
        "disc",
        "tape"
    ],
    "wof:name":"Video One",
    "wof:placetype":"venue"
},
  "geometry": {"coordinates":[-86.428107,39.408454],"type":"Point"}
}