{
  "type": "Feature",
  "properties": {
    "iso:country":"US",
    "sg:address":"2001 Hunter Valley Rd",
    "sg:city":"Bloomington",
    "sg:classifiers":[
        {
            "category":"Building & Trades",
            "subcategory":"Electrical",
            "type":"Services"
        }
    ],
    "sg:phone":"+1 812 323 8530",
    "sg:postcode":"47404",
    "sg:province":"IN",
    "sg:tags":[
        "electric",
        "contractor"
    ],
    "wof:name":"Genesis Co LLC",
    "wof:placetype":"venue"
},
  "geometry": {"coordinates":[-86.55891,39.193719],"type":"Point"}
}