{
  "type": "Feature",
  "properties": {
    "addr:full":"221 Market St Charlestown IN 47111",
    "addr:housenumber":"221",
    "addr:postcode":"47111",
    "addr:street":"Market St",
    "iso:country":"US",
    "sg:address":"221 Market St",
    "sg:city":"Charlestown",
    "sg:classifiers":[
        {
            "category":"Food & Beverages",
            "subcategory":"Groceries & Convenience Stores",
            "type":"Retail Goods"
        }
    ],
    "sg:phone":"+1 812 256 5595",
    "sg:postcode":"47111",
    "sg:province":"IN",
    "wof:name":"Mikes Food Mart",
    "wof:placetype":"venue"
},
  "geometry": {"coordinates":[-85.661355,38.441953],"type":"Point"}
}