{
  "type": "Feature",
  "properties": {
    "addr:full":"4301 W 200 S Winchester IN 47394",
    "addr:housenumber":"4301",
    "addr:postcode":"winchester in 47394",
    "addr:street":"W 200 S",
    "iso:country":"US",
    "sg:address":"4301 W 200 S",
    "sg:city":"Winchester",
    "sg:classifiers":[
        {
            "category":"Professional",
            "subcategory":"Advertising",
            "type":"Services"
        }
    ],
    "sg:phone":"+1 765 584 1290",
    "sg:postcode":"47394",
    "sg:province":"IN",
    "sg:tags":[
        "counselor",
        "agency"
    ],
    "wof:name":"Lovell's Advertising Plus",
    "wof:placetype":"venue"
},
  "geometry": {"coordinates":[-85.05978500000001,40.134965],"type":"Point"}
}