{
  "type": "Feature",
  "properties": {
    "iso:country":"US",
    "sg:address":"231 Pearl St",
    "sg:city":"Jeffersonville",
    "sg:classifiers":[
        {
            "category":"Organizations",
            "subcategory":"Membership Organization",
            "type":"Services"
        }
    ],
    "sg:phone":"+1 812 283 0808",
    "sg:postcode":"47130",
    "sg:province":"IN",
    "wof:name":"Jeffersonville Jaycees",
    "wof:placetype":"venue"
},
  "geometry": {"coordinates":[-85.741458,38.270878],"type":"Point"}
}