{
  "type": "Feature",
  "properties": {
    "iso:country":"US",
    "sg:address":"9206 W 190th Ave",
    "sg:city":"Lowell",
    "sg:classifiers":[
        {
            "category":"Building & Trades",
            "subcategory":"Landscaping Services",
            "type":"Services"
        }
    ],
    "sg:phone":"+1 219 696 6770",
    "sg:postcode":"46356",
    "sg:province":"IN",
    "sg:tags":[
        "landscape",
        "contractor"
    ],
    "wof:name":"Bills Landscaping",
    "wof:placetype":"venue"
},
  "geometry": {"coordinates":[-87.447616,41.273226],"type":"Point"}
}