{
  "type": "Feature",
  "properties": {
    "iso:country":"US",
    "sg:address":"104 N Walnut St",
    "sg:city":"Shelbyville",
    "sg:classifiers":[
        {
            "category":"Building & Trades",
            "subcategory":"Landscaping Services",
            "type":"Services"
        }
    ],
    "sg:phone":"+1 317 835 4420",
    "sg:postcode":"46176",
    "sg:province":"IN",
    "sg:tags":[
        "lawn",
        "maintenance",
        "grounds"
    ],
    "wof:name":"Shelby Lawn Care Inc",
    "wof:placetype":"venue"
},
  "geometry": {"coordinates":[-85.76839,39.526048],"type":"Point"}
}