{
  "type": "Feature",
  "properties": {
    "iso:country":"US",
    "sg:address":"7857 Beanblossom Cir",
    "sg:city":"Indianapolis",
    "sg:classifiers":[
        {
            "category":"Professional",
            "type":"Services"
        }
    ],
    "sg:phone":"+1 317 585 1834",
    "sg:postcode":"46256",
    "sg:province":"IN",
    "sg:tags":[
        "establishment"
    ],
    "wof:name":"Marcon Enterprises",
    "wof:placetype":"venue"
},
  "geometry": {"coordinates":[-86.030378,39.90313],"type":"Point"}
}