{
  "type": "Feature",
  "properties": {
    "iso:country":"US",
    "sg:address":"609 E National Ave",
    "sg:city":"Brazil",
    "sg:classifiers":[
        {
            "category":"Government",
            "subcategory":"Court House",
            "type":"Public Place"
        }
    ],
    "sg:phone":"+1 812 448 9032",
    "sg:postcode":"47834",
    "sg:province":"IN",
    "sg:tags":[
        "county"
    ],
    "wof:name":"Clay Cnty Superior Court Clerk",
    "wof:placetype":"venue"
},
  "geometry": {"coordinates":[-87.118292,39.525281],"type":"Point"}
}