{
  "type": "Feature",
  "properties": {
    "iso:country":"US",
    "sg:address":"412 Sawyer Rd",
    "sg:city":"Kendallville",
    "sg:classifiers":[
        {
            "category":"Health Services",
            "subcategory":"Doctor",
            "type":"Services"
        }
    ],
    "sg:phone":"+1 260 343 0574",
    "sg:postcode":"46755",
    "sg:province":"IN",
    "sg:tags":[
        "clinic"
    ],
    "wof:name":"Medical Informatics Engnrng",
    "wof:placetype":"venue"
},
  "geometry": {"coordinates":[-85.293499,41.451303],"type":"Point"}
}