{
  "type": "Feature",
  "properties": {
    "iso:country":"US",
    "sg:address":"1832 E Main St",
    "sg:city":"Greenfield",
    "sg:classifiers":[
        {
            "category":"Professional",
            "subcategory":"Management & Consulting",
            "type":"Services"
        }
    ],
    "sg:phone":"+1 317 467 1701",
    "sg:postcode":"46140",
    "sg:province":"IN",
    "sg:tags":[
        "consultant",
        "automation"
    ],
    "wof:name":"Pro-Tect Fabrications",
    "wof:placetype":"venue"
},
  "geometry": {"coordinates":[-85.74800500000001,39.786312],"type":"Point"}
}