{
  "type": "Feature",
  "properties": {
    "addr:full":"108 E Kirkwood Ave Bloomington IN 47408",
    "addr:housenumber":"108",
    "addr:postcode":"47408",
    "addr:street":"E Kirkwood Ave",
    "iso:country":"US",
    "sg:address":"108 E Kirkwood Ave",
    "sg:city":"Bloomington",
    "sg:classifiers":[
        {
            "category":"Shopping",
            "subcategory":"Gifts & Souvenirs",
            "type":"Retail Goods"
        }
    ],
    "sg:phone":"+1 812 339 0734",
    "sg:postcode":"47408",
    "sg:province":"IN",
    "sg:tags":[
        "shop"
    ],
    "wof:name":"Athena",
    "wof:placetype":"venue"
},
  "geometry": {"coordinates":[-86.532428,39.166497],"type":"Point"}
}