{
  "type": "Feature",
  "properties": {
    "iso:country":"US",
    "sg:address":"1431 Production Rd",
    "sg:city":"Fort Wayne",
    "sg:classifiers":[
        {
            "category":"Manufacturing",
            "subcategory":"Tools & Machinery",
            "type":"Manufacturing & Wholesale Goods"
        }
    ],
    "sg:phone":"+1 260 484 0187",
    "sg:postcode":"46808",
    "sg:province":"IN",
    "sg:tags":[
        "die",
        "maker"
    ],
    "wof:name":"Quality Tool Co",
    "wof:placetype":"venue"
},
  "geometry": {"coordinates":[-85.16446000000001,41.120281],"type":"Point"}
}