{
  "type": "Feature",
  "properties": {
    "iso:country":"US",
    "sg:address":"1560 Lake St",
    "sg:city":"Laporte",
    "sg:classifiers":[
        {
            "category":"Manufacturing",
            "subcategory":"Tools & Machinery",
            "type":"Manufacturing & Wholesale Goods"
        }
    ],
    "sg:phone":"+1 219 324 4176",
    "sg:postcode":"46350",
    "sg:province":"IN",
    "sg:tags":[
        "machine",
        "shop"
    ],
    "sg:website":"www.rbmoldanddie.com",
    "wof:name":"R & B Mold & Die",
    "wof:placetype":"venue"
},
  "geometry": {"coordinates":[-86.736566,41.60858],"type":"Point"}
}