{
  "type": "Feature",
  "properties": {
    "iso:country":"US",
    "sg:address":"8602 W US Hwy 24",
    "sg:city":"Wolcott",
    "sg:classifiers":[
        {
            "category":"Freight",
            "type":"Transportation"
        }
    ],
    "sg:phone":"+1 219 279 2860",
    "sg:postcode":"47995",
    "sg:province":"IN",
    "sg:tags":[
        "operator",
        "trucking"
    ],
    "wof:name":"John Yerk",
    "wof:placetype":"venue"
},
  "geometry": {"coordinates":[-87.032155,40.750385],"type":"Point"}
}