{
  "type": "Feature",
  "properties": {
    "iso:country":"US",
    "sg:address":"4260 S 430 W",
    "sg:city":"Kingman",
    "sg:classifiers":[
        {
            "category":"Building & Trades",
            "subcategory":"Construction",
            "type":"Services"
        }
    ],
    "sg:phone":"+1 765 866 9969",
    "sg:postcode":"47952",
    "sg:province":"IN",
    "sg:tags":[
        "water",
        "well",
        "drilling"
    ],
    "wof:name":"Copenhaver Water Well Drilling",
    "wof:placetype":"venue"
},
  "geometry": {"coordinates":[-87.341981,39.97087],"type":"Point"}
}