{
  "type": "Feature",
  "properties": {
    "addr:full":"601 E Dupont Rd Fort Wayne IN 46825",
    "addr:housenumber":"601",
    "addr:postcode":"46825",
    "addr:street":"E Dupont Rd",
    "iso:country":"US",
    "sg:address":"601 E Dupont Rd",
    "sg:city":"Fort Wayne",
    "sg:classifiers":[
        {
            "category":"Food & Beverages",
            "subcategory":"Groceries & Convenience Stores",
            "type":"Retail Goods"
        }
    ],
    "sg:phone":"+1 260 637 4504",
    "sg:postcode":"46825",
    "sg:province":"IN",
    "sg:tags":[
        "grocer"
    ],
    "wof:name":"Kroger",
    "wof:placetype":"venue"
},
  "geometry": {"coordinates":[-85.13381,41.178237],"type":"Point"}
}