{
  "type": "Feature",
  "properties": {
    "iso:country":"US",
    "sg:address":"208 W State St",
    "sg:city":"Huntington",
    "sg:classifiers":[
        {
            "category":"Organizations",
            "subcategory":"Non-profit Organization",
            "type":"Services"
        }
    ],
    "sg:phone":"+1 260 356 9099",
    "sg:postcode":"46750",
    "sg:province":"IN",
    "wof:name":"LA Fontaine Ctr",
    "wof:placetype":"venue"
},
  "geometry": {"coordinates":[-85.495045,40.880789],"type":"Point"}
}