{
  "type": "Feature",
  "properties": {
    "iso:country":"US",
    "sg:address":"9208 E 600 N",
    "sg:city":"Van Buren",
    "sg:classifiers":[
        {
            "category":"Building & Trades",
            "subcategory":"Construction",
            "type":"Services"
        }
    ],
    "sg:phone":"+1 765 934 2787",
    "sg:postcode":"46991",
    "sg:province":"IN",
    "sg:tags":[
        "residential"
    ],
    "wof:name":"Shinholt Construction",
    "wof:placetype":"venue"
},
  "geometry": {"coordinates":[-85.490361,40.639226],"type":"Point"}
}