{
  "type": "Feature",
  "properties": {
    "iso:country":"US",
    "sg:address":"430 W Votaw St",
    "sg:city":"Portland",
    "sg:classifiers":[
        {
            "category":"Health Services",
            "subcategory":"Doctor",
            "type":"Services"
        }
    ],
    "sg:phone":"+1 260 726 8822",
    "sg:postcode":"47371",
    "sg:province":"IN",
    "sg:tags":[
        "physician",
        "surgeon"
    ],
    "wof:name":"Family Practice Of Jay County",
    "wof:placetype":"venue"
},
  "geometry": {"coordinates":[-84.982866,40.439469],"type":"Point"}
}