{
  "type": "Feature",
  "properties": {
    "addr:full":"116 E Dustman Rd Bluffton IN 46714",
    "addr:housenumber":"116",
    "addr:postcode":"46714",
    "addr:street":"E Dustman Rd",
    "iso:country":"US",
    "sg:address":"116 E Dustman Rd",
    "sg:city":"Bluffton",
    "sg:classifiers":[
        {
            "category":"Health Services",
            "subcategory":"Doctor",
            "type":"Services"
        }
    ],
    "sg:phone":"+1 260 824 2811",
    "sg:postcode":"46714",
    "sg:province":"IN",
    "sg:tags":[
        "dentist"
    ],
    "wof:name":"Robley E Evans DDS",
    "wof:placetype":"venue"
},
  "geometry": {"coordinates":[-85.163881,40.756907],"type":"Point"}
}