{
  "type": "Feature",
  "properties": {
    "iso:country":"US",
    "sg:address":"15460 Herriman Blvd",
    "sg:city":"Noblesville",
    "sg:classifiers":[
        {
            "category":"Wholesale",
            "subcategory":"Durable Goods & Equipment",
            "type":"Manufacturing & Wholesale Goods"
        }
    ],
    "sg:phone":"+1 317 773 6660",
    "sg:postcode":"46060",
    "sg:province":"IN",
    "sg:tags":[
        "representative",
        "manufacturer"
    ],
    "wof:name":"Jackson & Assoc",
    "wof:placetype":"venue"
},
  "geometry": {"coordinates":[-86.004229,40.015702],"type":"Point"}
}