{
  "type": "Feature",
  "properties": {
    "iso:country":"US",
    "sg:address":"2500 S State Rd 57",
    "sg:city":"Washington",
    "sg:classifiers":[
        {
            "category":"Mining & Drilling",
            "type":"Manufacturing & Wholesale Goods"
        }
    ],
    "sg:phone":"+1 812 254 6807",
    "sg:postcode":"47501",
    "sg:province":"IN",
    "sg:tags":[
        "oil",
        "gas",
        "producer"
    ],
    "wof:name":"C E Taylor Oil Co",
    "wof:placetype":"venue"
},
  "geometry": {"coordinates":[-87.181799,38.62402],"type":"Point"}
}