{
  "type": "Feature",
  "properties": {
    "iso:country":"US",
    "sg:address":"8550 Broadway",
    "sg:city":"Merrillville",
    "sg:classifiers":[
        {
            "category":"Professional",
            "subcategory":"Lawyer & Legal Services",
            "type":"Services"
        }
    ],
    "sg:phone":"+1 219 769 5500",
    "sg:postcode":"46410",
    "sg:province":"IN",
    "sg:tags":[
        "attorney"
    ],
    "wof:name":"James E Daugherty Law Offices",
    "wof:placetype":"venue"
},
  "geometry": {"coordinates":[-87.335968,41.462754],"type":"Point"}
}