{
  "type": "Feature",
  "properties": {
    "iso:country":"US",
    "sg:address":"3312 S Adams St",
    "sg:city":"Marion",
    "sg:classifiers":[
        {
            "category":"Retail",
            "subcategory":"Auto Repair",
            "type":"Services"
        }
    ],
    "sg:phone":"+1 765 674 7172",
    "sg:postcode":"46953",
    "sg:province":"IN",
    "sg:tags":[
        "repairing",
        "automobile"
    ],
    "wof:name":"Marion Discount Brake",
    "wof:placetype":"venue"
},
  "geometry": {"coordinates":[-85.658602,40.529355],"type":"Point"}
}