{
  "type": "Feature",
  "properties": {
    "iso:country":"US",
    "sg:address":"2900 US Hwy 40 Scn",
    "sg:city":"Clayton",
    "sg:classifiers":[
        {
            "category":"Professional",
            "subcategory":"Engineering",
            "type":"Services"
        }
    ],
    "sg:phone":"+1 317 539 7811",
    "sg:postcode":"46118",
    "sg:province":"IN",
    "sg:tags":[
        "engineer"
    ],
    "wof:name":"Toric Engineering",
    "wof:placetype":"venue"
},
  "geometry": {"coordinates":[-86.573376,39.654205],"type":"Point"}
}