{
  "type": "Feature",
  "properties": {
    "iso:country":"US",
    "sg:address":"3300 Cassopolis St",
    "sg:city":"Elkhart",
    "sg:classifiers":[
        {
            "category":"Travel",
            "subcategory":"Hotels & Motels",
            "type":"Entertainment"
        }
    ],
    "sg:phone":"+1 574 264 4118",
    "sg:postcode":"46514",
    "sg:province":"IN",
    "wof:name":"Diplomat Motel",
    "wof:placetype":"venue"
},
  "geometry": {"coordinates":[-85.973608,41.733406],"type":"Point"}
}