{
  "type": "Feature",
  "properties": {
    "iso:country":"US",
    "sg:address":"575 Broadway",
    "sg:city":"Gary",
    "sg:classifiers":[
        {
            "category":"Government",
            "subcategory":"Office",
            "type":"Public Place"
        }
    ],
    "sg:phone":"+1 219 886 1226",
    "sg:postcode":"46407",
    "sg:province":"IN",
    "sg:tags":[
        "housing",
        "program"
    ],
    "wof:name":"Gary Housing Authority",
    "wof:placetype":"venue"
},
  "geometry": {"coordinates":[-87.33707800000001,41.601091],"type":"Point"}
}