{
  "type": "Feature",
  "properties": {
    "iso:country":"US",
    "sg:address":"8815 Arbor Way Ct",
    "sg:city":"Indianapolis",
    "sg:classifiers":[
        {
            "category":"Communications",
            "subcategory":"Film & Video Production",
            "type":"Services"
        }
    ],
    "sg:phone":"+1 317 679 0429",
    "sg:postcode":"46268",
    "sg:province":"IN",
    "sg:tags":[
        "motion"
    ],
    "wof:name":"Jolliff Digital Production",
    "wof:placetype":"venue"
},
  "geometry": {"coordinates":[-86.203835,39.915048],"type":"Point"}
}