{
  "type": "Feature",
  "properties": {
    "iso:country":"US",
    "sg:address":"108 N 25th St",
    "sg:city":"Terre Haute",
    "sg:classifiers":[
        {
            "category":"Personal",
            "type":"Services"
        }
    ],
    "sg:phone":"+1 812 234 6871",
    "sg:postcode":"47803",
    "sg:province":"IN",
    "sg:tags":[
        "wear",
        "formal"
    ],
    "wof:name":"Harvey's Formal Wear Stores",
    "wof:placetype":"venue"
},
  "geometry": {"coordinates":[-87.37897,39.472027],"type":"Point"}
}