{
  "type": "Feature",
  "properties": {
    "iso:country":"US",
    "sg:address":"211 W Franklin St",
    "sg:city":"Winchester",
    "sg:classifiers":[
        {
            "category":"Shopping",
            "subcategory":"Florist",
            "type":"Retail Goods"
        }
    ],
    "sg:phone":"+1 765 584 2531",
    "sg:postcode":"47394",
    "sg:province":"IN",
    "wof:name":"All About Flowers & Gifts",
    "wof:placetype":"venue"
},
  "geometry": {"coordinates":[-84.98313400000001,40.171554],"type":"Point"}
}