{
  "type": "Feature",
  "properties": {
    "iso:country":"US",
    "sg:address":"700 N High School Rd",
    "sg:city":"Indianapolis",
    "sg:classifiers":[
        {
            "category":"Government",
            "subcategory":"Fire Station",
            "type":"Public Place"
        }
    ],
    "sg:phone":"+1 317 247 8501",
    "sg:postcode":"46214",
    "sg:province":"IN",
    "sg:tags":[
        "department"
    ],
    "sg:website":"www.waynefire.org",
    "wof:name":"Wayne Twp Fire Dept",
    "wof:placetype":"venue"
},
  "geometry": {"coordinates":[-86.272408,39.777642],"type":"Point"}
}