{
  "type": "Feature",
  "properties": {
    "iso:country":"US",
    "sg:address":"901 Lake George Dr",
    "sg:city":"Hobart",
    "sg:classifiers":[
        {
            "category":"Professional",
            "type":"Services"
        }
    ],
    "sg:phone":"+1 219 942 4097",
    "sg:postcode":"46342",
    "sg:province":"IN",
    "wof:name":"Senior Community Svc",
    "wof:placetype":"venue"
},
  "geometry": {"coordinates":[-87.271563,41.531203],"type":"Point"}
}