{
  "type": "Feature",
  "properties": {
    "iso:country":"US",
    "sg:address":"306 N Main St",
    "sg:city":"Kouts",
    "sg:classifiers":[
        {
            "category":"Health Services",
            "subcategory":"Doctor",
            "type":"Services"
        }
    ],
    "sg:phone":"+1 219 766 3693",
    "sg:postcode":"46347",
    "sg:province":"IN",
    "sg:tags":[
        "dentist"
    ],
    "wof:name":"Kouts Dental Clinic",
    "wof:placetype":"venue"
},
  "geometry": {"coordinates":[-87.02577100000001,41.319081],"type":"Point"}
}