{
  "type": "Feature",
  "properties": {
    "iso:country":"US",
    "sg:address":"808 N Madison Ave",
    "sg:city":"Greenwood",
    "sg:classifiers":[
        {
            "category":"Real Estate",
            "subcategory":"Real Estate Agent",
            "type":"Services"
        }
    ],
    "sg:phone":"+1 317 882 2626",
    "sg:postcode":"46142",
    "sg:province":"IN",
    "sg:tags":[
        "property",
        "evaluation"
    ],
    "wof:name":"Rpe/Cobb & Associates",
    "wof:placetype":"venue"
},
  "geometry": {"coordinates":[-86.113787,39.625682],"type":"Point"}
}