{
  "type": "Feature",
  "properties": {
    "iso:country":"US",
    "sg:address":"2338 S Lynhurst Dr",
    "sg:city":"Indianapolis",
    "sg:classifiers":[
        {
            "category":"Professional",
            "subcategory":"Management & Consulting",
            "type":"Services"
        }
    ],
    "sg:phone":"+1 317 248 9295",
    "sg:postcode":"46241",
    "sg:province":"IN",
    "sg:tags":[
        "employment",
        "screening"
    ],
    "wof:name":"Employee Management Systems",
    "wof:placetype":"venue"
},
  "geometry": {"coordinates":[-86.250387,39.732915],"type":"Point"}
}