{
  "type": "Feature",
  "properties": {
    "iso:country":"US",
    "sg:address":"10043 Summerlakes Dr",
    "sg:city":"Carmel",
    "sg:classifiers":[
        {
            "category":"Health Services",
            "subcategory":"Doctor",
            "type":"Services"
        }
    ],
    "sg:phone":"+1 317 580 1123",
    "sg:postcode":"46032",
    "sg:province":"IN",
    "sg:tags":[
        "surgeon",
        "oral"
    ],
    "wof:name":"Lande Gerald M DDS",
    "wof:placetype":"venue"
},
  "geometry": {"coordinates":[-86.191299,39.930302],"type":"Point"}
}