{
  "type": "Feature",
  "properties": {
    "iso:country":"US",
    "sg:address":"1350 Blue Grass Pkwy",
    "sg:city":"Greenwood",
    "sg:classifiers":[
        {
            "category":"Professional",
            "subcategory":"Business Services",
            "type":"Services"
        }
    ],
    "sg:phone":"+1 317 888 8539",
    "sg:postcode":"46143",
    "sg:province":"IN",
    "wof:name":"Humanizing Technologies",
    "wof:placetype":"venue"
},
  "geometry": {"coordinates":[-86.089535,39.598346],"type":"Point"}
}