{
  "type": "Feature",
  "properties": {
    "iso:country":"US",
    "sg:address":"11281 E 600 S-57",
    "sg:city":"Huntertown",
    "sg:classifiers":[
        {
            "category":"Professional",
            "subcategory":"Management & Consulting",
            "type":"Services"
        }
    ],
    "sg:phone":"+1 260 637 6643",
    "sg:postcode":"46748",
    "sg:province":"IN",
    "sg:tags":[
        "consultant",
        "broker"
    ],
    "sg:website":"www.certifiedmarketingltd.com",
    "wof:name":"Certified Marketing Consultant",
    "wof:placetype":"venue"
},
  "geometry": {"coordinates":[-85.194094,41.264179],"type":"Point"}
}