{
  "type": "Feature",
  "properties": {
    "iso:country":"US",
    "sg:address":"515 Oolitic Rd",
    "sg:city":"Bedford",
    "sg:classifiers":[
        {
            "category":"Retail",
            "subcategory":"Veterinary Services",
            "type":"Services"
        }
    ],
    "sg:phone":"+1 812 275 7501",
    "sg:postcode":"47421",
    "sg:province":"IN",
    "sg:tags":[
        "veterinarian"
    ],
    "wof:name":"Bedford Veterinary Medical Ctr",
    "wof:placetype":"venue"
},
  "geometry": {"coordinates":[-86.501398,38.884299],"type":"Point"}
}