{
  "type": "Feature",
  "properties": {
    "addr:full":"3131 W US Hwy 40 Greenfield IN 46140",
    "addr:housenumber":"3131",
    "addr:postcode":"46140",
    "addr:street":"W Us Hwy 40",
    "iso:country":"US",
    "sg:address":"3131 W US Hwy 40",
    "sg:city":"Greenfield",
    "sg:classifiers":[
        {
            "category":"Manufacturing",
            "subcategory":"Rubber & Plastics",
            "type":"Manufacturing & Wholesale Goods"
        }
    ],
    "sg:phone":"+1 317 462 0733",
    "sg:postcode":"46140",
    "sg:province":"IN",
    "sg:tags":[
        "product"
    ],
    "wof:name":"A & M Chemical Inc",
    "wof:placetype":"venue"
},
  "geometry": {"coordinates":[-85.860726,39.780913],"type":"Point"}
}