{
  "type": "Feature",
  "properties": {
    "addr:full":"3561 W Co Rd 650 N Orleans IN 47452",
    "addr:housenumber":"3561;650",
    "addr:postcode":"47452",
    "addr:street":"W Co Rd;N Orleans",
    "iso:country":"US",
    "sg:address":"3561 W Co Rd 650 N",
    "sg:city":"Orleans",
    "sg:phone":"+1 812 865 3128",
    "sg:postcode":"47452",
    "sg:province":"IN",
    "sg:tags":[
        "farm",
        "field",
        "corn",
        "soybean",
        "crop"
    ],
    "wof:name":"Shelton John",
    "wof:placetype":"venue"
},
  "geometry": {"coordinates":[-86.524682,38.651155],"type":"Point"}
}