{
  "type": "Feature",
  "properties": {
    "iso:country":"US",
    "sg:address":"7020 Bluffgrove Ln",
    "sg:city":"Indianapolis",
    "sg:classifiers":[
        {
            "category":"Building & Trades",
            "subcategory":"Construction",
            "type":"Services"
        }
    ],
    "sg:phone":"+1 317 328 0457",
    "sg:postcode":"46278",
    "sg:province":"IN",
    "sg:tags":[
        "roofing",
        "contractor"
    ],
    "wof:name":"JMH Roofing Co Inc",
    "wof:placetype":"venue"
},
  "geometry": {"coordinates":[-86.2808,39.879444],"type":"Point"}
}