{
  "type": "Feature",
  "properties": {
    "iso:country":"US",
    "sg:address":"382 W 80th Pl",
    "sg:city":"Merrillville",
    "sg:classifiers":[
        {
            "category":"Shopping",
            "type":"Retail Goods"
        }
    ],
    "sg:phone":"+1 219 756 1060",
    "sg:postcode":"46410",
    "sg:province":"IN",
    "wof:name":"Beltone Hearing Center",
    "wof:placetype":"venue"
},
  "geometry": {"coordinates":[-87.33944,41.473474],"type":"Point"}
}