{
  "type": "Feature",
  "properties": {
    "iso:country":"US",
    "sg:address":"40 N Van Buren St",
    "sg:city":"Nashville",
    "sg:classifiers":[
        {
            "category":"Shopping",
            "type":"Retail Goods"
        }
    ],
    "sg:phone":"+1 812 988 6698",
    "sg:postcode":"47448",
    "sg:province":"IN",
    "sg:tags":[
        "art",
        "gallery",
        "dealer"
    ],
    "wof:name":"Affordable Art",
    "wof:placetype":"venue"
},
  "geometry": {"coordinates":[-86.24687,39.20812],"type":"Point"}
}