{
  "type": "Feature",
  "properties": {
    "iso:country":"US",
    "sg:address":"6842 Hawthorn Park Dr",
    "sg:city":"Indianapolis",
    "sg:classifiers":[
        {
            "category":"Wholesale",
            "subcategory":"Office Equipment",
            "type":"Manufacturing & Wholesale Goods"
        }
    ],
    "sg:phone":"+1 317 842 7000",
    "sg:postcode":"46220",
    "sg:province":"IN",
    "sg:tags":[
        "machine",
        "duplicating",
        "copying"
    ],
    "wof:name":"Copyfax",
    "wof:placetype":"venue"
},
  "geometry": {"coordinates":[-86.07569700000001,39.880496],"type":"Point"}
}