{
  "type": "Feature",
  "properties": {
    "iso:country":"US",
    "sg:address":"1707 W 86th St",
    "sg:city":"Indianapolis",
    "sg:classifiers":[
        {
            "category":"Health Services",
            "subcategory":"Doctor",
            "type":"Services"
        }
    ],
    "sg:phone":"+1 317 415 5545",
    "sg:postcode":"46260",
    "sg:province":"IN",
    "wof:name":"Oplinger Catherine Cpnp",
    "wof:placetype":"venue"
},
  "geometry": {"coordinates":[-86.190804,39.9119],"type":"Point"}
}