{
  "type": "Feature",
  "properties": {
    "addr:full":"12558 N Gray Rd Carmel IN 46033",
    "addr:housenumber":"12558",
    "addr:postcode":"46033",
    "addr:street":"N Gray Rd",
    "iso:country":"US",
    "sg:address":"12558 N Gray Rd",
    "sg:city":"Carmel",
    "sg:classifiers":[
        {
            "category":"Professional",
            "subcategory":"Lawyer & Legal Services",
            "type":"Services"
        }
    ],
    "sg:phone":"+1 317 846 4799",
    "sg:postcode":"46033",
    "sg:province":"IN",
    "wof:name":"Stein Richard P Atty",
    "wof:placetype":"venue"
},
  "geometry": {"coordinates":[-86.089302,39.970402],"type":"Point"}
}