{
  "type": "Feature",
  "properties": {
    "iso:country":"US",
    "sg:address":"1016 N Main St",
    "sg:city":"Evansville",
    "sg:classifiers":[
        {
            "category":"Building & Trades",
            "subcategory":"Plumbing",
            "type":"Services"
        }
    ],
    "sg:phone":"+1 812 425 8435",
    "sg:postcode":"47711",
    "sg:province":"IN",
    "sg:tags":[
        "conditioning",
        "air",
        "system",
        "contractor"
    ],
    "wof:name":"Baylor Heating & Air Cond Inc",
    "wof:placetype":"venue"
},
  "geometry": {"coordinates":[-87.563846,37.987321],"type":"Point"}
}