{
  "type": "Feature",
  "properties": {
    "iso:country":"US",
    "sg:address":"6635 Kennedy Ave",
    "sg:city":"Hammond",
    "sg:classifiers":[
        {
            "category":"Education",
            "subcategory":"Dance Studio",
            "type":"Public Place"
        }
    ],
    "sg:phone":"+1 219 844 6225",
    "sg:postcode":"46323",
    "sg:province":"IN",
    "sg:tags":[
        "art",
        "performing",
        "instruction",
        "dancing"
    ],
    "sg:website":"www.thedanceconnectiononline.com",
    "wof:name":"Dance Connection the",
    "wof:placetype":"venue"
},
  "geometry": {"coordinates":[-87.461502,41.592701],"type":"Point"}
}