{
  "type": "Feature",
  "properties": {
    "iso:country":"US",
    "sg:address":"1058 W 400 N",
    "sg:city":"Warsaw",
    "sg:classifiers":[
        {
            "category":"Manufacturing",
            "subcategory":"Building Materials",
            "type":"Manufacturing & Wholesale Goods"
        }
    ],
    "sg:phone":"+1 574 267 5879",
    "sg:postcode":"46582",
    "sg:province":"IN",
    "sg:tags":[
        "cabinet"
    ],
    "sg:website":"www.swpcabinetry.com",
    "wof:name":"Superior Wood Products",
    "wof:placetype":"venue"
},
  "geometry": {"coordinates":[-85.86302999999999,41.291814],"type":"Point"}
}