{
  "type": "Feature",
  "properties": {
    "iso:country":"US",
    "sg:address":"5779 US Hwy 6",
    "sg:city":"Portage",
    "sg:classifiers":[
        {
            "category":"Building & Trades",
            "subcategory":"Equipment Rental",
            "type":"Services"
        }
    ],
    "sg:phone":"+1 219 762 5501",
    "sg:postcode":"46368",
    "sg:province":"IN",
    "sg:tags":[
        "leasing",
        "furniture"
    ],
    "wof:name":"Rent Way",
    "wof:placetype":"venue"
},
  "geometry": {"coordinates":[-87.189926,41.550453],"type":"Point"}
}