{
  "type": "Feature",
  "properties": {
    "iso:country":"US",
    "sg:address":"2910 Fortune Cir W",
    "sg:city":"Indianapolis",
    "sg:classifiers":[
        {
            "category":"Freight",
            "type":"Transportation"
        }
    ],
    "sg:phone":"+1 317 243 7820",
    "sg:postcode":"46241",
    "sg:province":"IN",
    "wof:name":"USF Processors Inc",
    "wof:placetype":"venue"
},
  "geometry": {"coordinates":[-86.261032,39.722851],"type":"Point"}
}