{
  "type": "Feature",
  "properties": {
    "iso:country":"US",
    "sg:address":"3109 W Sycamore St",
    "sg:city":"Kokomo",
    "sg:classifiers":[
        {
            "category":"Health Services",
            "subcategory":"Health Practitioner",
            "type":"Services"
        }
    ],
    "sg:phone":"+1 765 457 8381",
    "sg:postcode":"46901",
    "sg:province":"IN",
    "sg:tags":[
        "nurse"
    ],
    "wof:name":"Ginny Delon",
    "wof:placetype":"venue"
},
  "geometry": {"coordinates":[-86.183066,40.487509],"type":"Point"}
}