{
  "type": "Feature",
  "properties": {
    "iso:country":"US",
    "sg:address":"773 E Main St",
    "sg:city":"Brownsburg",
    "sg:classifiers":[
        {
            "category":"Personal",
            "subcategory":"Beauty Salon",
            "type":"Services"
        }
    ],
    "sg:phone":"+1 317 852 4580",
    "sg:postcode":"46112",
    "sg:province":"IN",
    "wof:name":"Bo Rics Haircare",
    "wof:placetype":"venue"
},
  "geometry": {"coordinates":[-86.385737,39.839677],"type":"Point"}
}