{
  "type": "Feature",
  "properties": {
    "iso:country":"US",
    "sg:address":"1046 Summit Dr",
    "sg:city":"Carmel",
    "sg:classifiers":[
        {
            "category":"Professional",
            "subcategory":"Computer Services",
            "type":"Services"
        }
    ],
    "sg:phone":"+1 317 818 0814",
    "sg:postcode":"46032",
    "sg:province":"IN",
    "sg:tags":[
        "consultant",
        "designer"
    ],
    "wof:name":"Intellectual Technologies Inc",
    "wof:placetype":"venue"
},
  "geometry": {"coordinates":[-86.13327700000001,39.966369],"type":"Point"}
}