{
  "type": "Feature",
  "properties": {
    "iso:country":"US",
    "sg:address":"2320 Industrial Pkwy",
    "sg:city":"Elkhart",
    "sg:classifiers":[
        {
            "category":"Manufacturing",
            "subcategory":"Motor Vehicles & Parts",
            "type":"Manufacturing & Wholesale Goods"
        }
    ],
    "sg:phone":"+1 574 294 2511",
    "sg:postcode":"46516",
    "sg:province":"IN",
    "sg:tags":[
        "automobile",
        "supply"
    ],
    "sg:website":"www.dometic.com",
    "wof:name":"Dometic Corp",
    "wof:placetype":"venue"
},
  "geometry": {"coordinates":[-85.926245,41.686571],"type":"Point"}
}