{
  "type": "Feature",
  "properties": {
    "addr:full":"1922 Milburn Blvd Mishawaka IN 46544",
    "addr:housenumber":"1922",
    "addr:postcode":"46544",
    "addr:street":"Milburn Blvd",
    "iso:country":"US",
    "sg:address":"1922 Milburn Blvd",
    "sg:city":"Mishawaka",
    "sg:classifiers":[
        {
            "category":"Organizations",
            "subcategory":"Religious Organization",
            "type":"Services"
        }
    ],
    "sg:phone":"+1 574 255 6586",
    "sg:postcode":"46544",
    "sg:province":"IN",
    "sg:tags":[
        "church"
    ],
    "wof:name":"Inter Faith Chr-God In Christ",
    "wof:placetype":"venue"
},
  "geometry": {"coordinates":[-86.204137,41.65539],"type":"Point"}
}