{
  "type": "Feature",
  "properties": {
    "iso:country":"US",
    "sg:address":"525 Professional Way",
    "sg:city":"Kendallville",
    "sg:classifiers":[
        {
            "category":"Professional",
            "subcategory":"Accounting & Tax Preparation",
            "type":"Services"
        }
    ],
    "sg:phone":"+1 260 347 2583",
    "sg:postcode":"46755",
    "sg:province":"IN",
    "sg:tags":[
        "return",
        "filing"
    ],
    "wof:name":"H & R Block Tax Svc",
    "wof:placetype":"venue"
},
  "geometry": {"coordinates":[-85.247373,41.449731],"type":"Point"}
}