{
  "type": "Feature",
  "properties": {
    "iso:country":"US",
    "sg:address":"4462 E Co Rd 300 S",
    "sg:city":"Frankfort",
    "sg:classifiers":[
        {
            "category":"Building & Trades",
            "subcategory":"Electrical",
            "type":"Services"
        }
    ],
    "sg:phone":"+1 765 659 1212",
    "sg:postcode":"46041",
    "sg:province":"IN",
    "sg:tags":[
        "electrical",
        "contractor"
    ],
    "wof:name":"Dale Electric",
    "wof:placetype":"venue"
},
  "geometry": {"coordinates":[-86.383643,40.242978],"type":"Point"}
}