{
  "type": "Feature",
  "properties": {
    "iso:country":"US",
    "sg:address":"4113 National Rd W",
    "sg:city":"Richmond",
    "sg:classifiers":[
        {
            "category":"Building & Trades",
            "subcategory":"Plumbing",
            "type":"Services"
        }
    ],
    "sg:phone":"+1 765 962 7122",
    "sg:postcode":"47374",
    "sg:province":"IN",
    "sg:tags":[
        "plumbing",
        "contractor"
    ],
    "wof:name":"Rick Jenkins & Sons Plumbing",
    "wof:placetype":"venue"
},
  "geometry": {"coordinates":[-84.95568799999999,39.821114],"type":"Point"}
}