{
  "type": "Feature",
  "properties": {
    "iso:country":"US",
    "sg:address":"750 Oak St",
    "sg:city":"Terre Haute",
    "sg:classifiers":[
        {
            "category":"Shopping",
            "subcategory":"Shoes",
            "type":"Retail Goods"
        }
    ],
    "sg:phone":"+1 812 232 2290",
    "sg:postcode":"47807",
    "sg:province":"IN",
    "wof:name":"Coaches Corner",
    "wof:placetype":"venue"
},
  "geometry": {"coordinates":[-87.405699,39.461413],"type":"Point"}
}