{
  "type": "Feature",
  "properties": {
    "iso:country":"US",
    "sg:address":"8820 State Rd 26 E",
    "sg:city":"Lafayette",
    "sg:classifiers":[
        {
            "category":"Shopping",
            "subcategory":"Bicycles & Sporting Goods",
            "type":"Retail Goods"
        }
    ],
    "sg:phone":"+1 765 296 9786",
    "sg:postcode":"47905",
    "sg:province":"IN",
    "wof:name":"Shotters Den",
    "wof:placetype":"venue"
},
  "geometry": {"coordinates":[-86.73649399999999,40.419463],"type":"Point"}
}