{
  "type": "Feature",
  "properties": {
    "iso:country":"US",
    "sg:address":"4829 Calumet Ave",
    "sg:city":"Hammond",
    "sg:classifiers":[
        {
            "category":"Autos & Motor Vehicles",
            "subcategory":"Automobile Sales",
            "type":"Retail Goods"
        }
    ],
    "sg:phone":"+1 219 937 3069",
    "sg:postcode":"46327",
    "sg:province":"IN",
    "sg:tags":[
        "car",
        "dealer"
    ],
    "wof:name":"Father & Son Auto Sales",
    "wof:placetype":"venue"
},
  "geometry": {"coordinates":[-87.508733,41.62521],"type":"Point"}
}