{
  "type": "Feature",
  "properties": {
    "iso:country":"US",
    "sg:address":"9350 N Michigan Rd",
    "sg:city":"Indianapolis",
    "sg:classifiers":[
        {
            "category":"Bars & Pubs",
            "type":"Food & Drink"
        }
    ],
    "sg:phone":"+1 317 876 9815",
    "sg:postcode":"46268",
    "sg:province":"IN",
    "wof:name":"Circle T's",
    "wof:placetype":"venue"
},
  "geometry": {"coordinates":[-86.227785,39.922039],"type":"Point"}
}