{
  "type": "Feature",
  "properties": {
    "iso:country":"US",
    "sg:address":"1733 Central Ave",
    "sg:city":"Columbus",
    "sg:classifiers":[
        {
            "category":"Professional",
            "subcategory":"Accounting & Tax Preparation",
            "type":"Services"
        }
    ],
    "sg:phone":"+1 812 376 0491",
    "sg:postcode":"47201",
    "sg:province":"IN",
    "sg:tags":[
        "return",
        "filing"
    ],
    "wof:name":"Jackson Tax Svc",
    "wof:placetype":"venue"
},
  "geometry": {"coordinates":[-85.904034,39.216233],"type":"Point"}
}