{
  "type": "Feature",
  "properties": {
    "iso:country":"US",
    "sg:address":"2135 Prospect St",
    "sg:city":"Indianapolis",
    "sg:classifiers":[
        {
            "category":"Bars & Pubs",
            "type":"Food & Drink"
        }
    ],
    "sg:phone":"+1 317 631 0706",
    "sg:postcode":"46203",
    "sg:province":"IN",
    "sg:tags":[
        "drinking"
    ],
    "wof:name":"Prospect Tavern Inc",
    "wof:placetype":"venue"
},
  "geometry": {"coordinates":[-86.12438400000001,39.752354],"type":"Point"}
}