{
  "type": "Feature",
  "properties": {
    "iso:country":"US",
    "sg:address":"3241 Old Romney Rd",
    "sg:city":"Lafayette",
    "sg:classifiers":[
        {
            "category":"Building & Trades",
            "subcategory":"Construction",
            "type":"Services"
        }
    ],
    "sg:phone":"+1 765 477 7609",
    "sg:postcode":"47909",
    "sg:province":"IN",
    "sg:tags":[
        "project"
    ],
    "wof:name":"Dilley Construction Inc",
    "wof:placetype":"venue"
},
  "geometry": {"coordinates":[-86.909276,40.379606],"type":"Point"}
}