{
  "type": "Feature",
  "properties": {
    "iso:country":"US",
    "sg:address":"1134 Virginia St",
    "sg:city":"Gary",
    "sg:classifiers":[
        {
            "category":"Retail",
            "subcategory":"Auto Repair",
            "type":"Services"
        }
    ],
    "sg:phone":"+1 219 886 8683",
    "sg:postcode":"46407",
    "sg:province":"IN",
    "sg:tags":[
        "automobile",
        "diagnostic"
    ],
    "wof:name":"Fred's Autotech Inc",
    "wof:placetype":"venue"
},
  "geometry": {"coordinates":[-87.329843,41.590138],"type":"Point"}
}