{
  "type": "Feature",
  "properties": {
    "iso:country":"US",
    "sg:address":"4625 E 50 N",
    "sg:city":"Columbus",
    "sg:classifiers":[
        {
            "category":"Education",
            "subcategory":"School",
            "type":"Public Place"
        }
    ],
    "sg:phone":"+1 812 376 4342",
    "sg:postcode":"47203",
    "sg:province":"IN",
    "wof:name":"Clifty Creek Elementary School",
    "wof:placetype":"venue"
},
  "geometry": {"coordinates":[-85.86738,39.208652],"type":"Point"}
}