{
  "type": "Feature",
  "properties": {
    "iso:country":"US",
    "sg:address":"345 S Bowers St",
    "sg:city":"Whitestown",
    "sg:classifiers":[
        {
            "category":"Food & Beverages",
            "subcategory":"Specialty",
            "type":"Retail Goods"
        }
    ],
    "sg:phone":"+1 317 769 2739",
    "sg:postcode":"46075",
    "sg:province":"IN",
    "sg:tags":[
        "tea",
        "coffee"
    ],
    "wof:name":"Evans & King Microroasters",
    "wof:placetype":"venue"
},
  "geometry": {"coordinates":[-86.346935,39.993875],"type":"Point"}
}