{
  "type": "Feature",
  "properties": {
    "addr:full":"120 E Virginia St Evansville IN 47711",
    "addr:housenumber":"120",
    "addr:postcode":"47711",
    "addr:street":"E Virginia St",
    "iso:country":"US",
    "sg:address":"120 E Virginia St",
    "sg:city":"Evansville",
    "sg:classifiers":[
        {
            "category":"Building & Trades",
            "subcategory":"Plumbing",
            "type":"Services"
        }
    ],
    "sg:phone":"+1 812 423 4900",
    "sg:postcode":"47711",
    "sg:province":"IN",
    "sg:tags":[
        "conditioning",
        "air",
        "system",
        "contractor"
    ],
    "wof:name":"K E Simpson Heating & Air Cond",
    "wof:placetype":"venue"
},
  "geometry": {"coordinates":[-87.561407,37.982024],"type":"Point"}
}