{
  "type": "Feature",
  "properties": {
    "iso:country":"US",
    "sg:address":"19775 Bluff Dr",
    "sg:city":"Goshen",
    "sg:classifiers":[
        {
            "category":"Real Estate",
            "subcategory":"Real Estate Agent",
            "type":"Services"
        }
    ],
    "sg:phone":"+1 574 534 3533",
    "sg:postcode":"46526",
    "sg:province":"IN",
    "wof:name":"Empowering Enterprises Inc",
    "wof:placetype":"venue"
},
  "geometry": {"coordinates":[-85.842637,41.558745],"type":"Point"}
}