{
  "type": "Feature",
  "properties": {
    "iso:country":"US",
    "sg:address":"446 N 325 E",
    "sg:city":"Valparaiso",
    "sg:classifiers":[
        {
            "category":"Building & Trades",
            "subcategory":"Plumbing",
            "type":"Services"
        }
    ],
    "sg:phone":"+1 219 464 9942",
    "sg:postcode":"46383",
    "sg:province":"IN",
    "sg:tags":[
        "plumbing",
        "contractor"
    ],
    "wof:name":"Safe Flow Plumbing & Heating",
    "wof:placetype":"venue"
},
  "geometry": {"coordinates":[-87.003013,41.500416],"type":"Point"}
}