{
  "type": "Feature",
  "properties": {
    "iso:country":"US",
    "sg:address":"3011 Belvedere Rd",
    "sg:city":"Elkhart",
    "sg:classifiers":[
        {
            "category":"Travel",
            "subcategory":"Hotels & Motels",
            "type":"Entertainment"
        }
    ],
    "sg:phone":"+1 574 262 1581",
    "sg:postcode":"46514",
    "sg:province":"IN",
    "wof:name":"Ramada Inn",
    "wof:placetype":"venue"
},
  "geometry": {"coordinates":[-85.974064,41.729791],"type":"Point"}
}