{
  "type": "Feature",
  "properties": {
    "iso:country":"US",
    "sg:address":"41 E Washington St",
    "sg:city":"Indianapolis",
    "sg:classifiers":[
        {
            "category":"Health Services",
            "subcategory":"Clinic",
            "type":"Services"
        }
    ],
    "sg:phone":"+1 317 917 2057",
    "sg:postcode":"46204",
    "sg:province":"IN",
    "wof:name":"Harmony Wellcare",
    "wof:placetype":"venue"
},
  "geometry": {"coordinates":[-86.158092,39.767081],"type":"Point"}
}