{
  "type": "Feature",
  "properties": {
    "iso:country":"US",
    "sg:address":"29966 US Hwy 20",
    "sg:city":"Elkhart",
    "sg:classifiers":[
        {
            "category":"Insurance",
            "subcategory":"Insurance Agent",
            "type":"Services"
        }
    ],
    "sg:phone":"+1 574 522 1148",
    "sg:postcode":"46514",
    "sg:province":"IN",
    "wof:name":"State Farm Insurance",
    "wof:placetype":"venue"
},
  "geometry": {"coordinates":[-86.041872,41.688682],"type":"Point"}
}