{
  "type": "Feature",
  "properties": {
    "iso:country":"US",
    "sg:address":"108 E Walnut St",
    "sg:city":"Nappanee",
    "sg:classifiers":[
        {
            "category":"Arts & Performance",
            "subcategory":"Theater",
            "type":"Entertainment"
        }
    ],
    "sg:phone":"+1 574 773 3343",
    "sg:postcode":"46550",
    "sg:province":"IN",
    "sg:tags":[
        "group"
    ],
    "wof:name":"Lavern",
    "wof:placetype":"venue"
},
  "geometry": {"coordinates":[-86.00005299999999,41.443691],"type":"Point"}
}