{
  "type": "Feature",
  "properties": {
    "iso:country":"US",
    "sg:address":"4708 Shelbyville Rd",
    "sg:city":"Indianapolis",
    "sg:classifiers":[
        {
            "category":"Building & Trades",
            "subcategory":"Construction",
            "type":"Services"
        }
    ],
    "sg:phone":"+1 317 788 4703",
    "sg:postcode":"46237",
    "sg:province":"IN",
    "sg:tags":[
        "excavation",
        "grading"
    ],
    "wof:name":"Swineford Excavating",
    "wof:placetype":"venue"
},
  "geometry": {"coordinates":[-86.088319,39.691583],"type":"Point"}
}