{
  "type": "Feature",
  "properties": {
    "iso:country":"US",
    "sg:address":"2939 S Washington St",
    "sg:city":"Kokomo",
    "sg:classifiers":[
        {
            "category":"Shopping",
            "subcategory":"Bicycles & Sporting Goods",
            "type":"Retail Goods"
        }
    ],
    "sg:phone":"+1 765 453 4614",
    "sg:postcode":"46902",
    "sg:province":"IN",
    "wof:name":"Second Time Around Sports",
    "wof:placetype":"venue"
},
  "geometry": {"coordinates":[-86.128426,40.45308],"type":"Point"}
}