{
  "type": "Feature",
  "properties": {
    "iso:country":"US",
    "sg:address":"2999 E Lincoln Hwy",
    "sg:city":"Merrillville",
    "sg:classifiers":[
        {
            "category":"Manufacturing",
            "subcategory":"Tools & Machinery",
            "type":"Manufacturing & Wholesale Goods"
        }
    ],
    "sg:phone":"+1 219 942 0596",
    "sg:postcode":"46410",
    "sg:province":"IN",
    "sg:tags":[
        "equipment",
        "nurseryman",
        "supply"
    ],
    "wof:name":"Frank's Nursery & Crafts",
    "wof:placetype":"venue"
},
  "geometry": {"coordinates":[-87.300984,41.471072],"type":"Point"}
}