{
  "type": "Feature",
  "properties": {
    "addr:full":"8524 W State Road 56 French Lick IN 47432",
    "addr:housenumber":"8524",
    "addr:postcode":"lick;47432",
    "addr:street":"W State Road 56",
    "iso:country":"US",
    "sg:address":"8524 W State Road 56",
    "sg:city":"French Lick",
    "sg:classifiers":[
        {
            "category":"Restaurant",
            "type":"Food & Drink"
        }
    ],
    "sg:menulink":"http://www.allmenus.com/in/french-lick/120294-subway/menu/",
    "sg:phone":"+1 812 936 9770",
    "sg:postcode":"47432",
    "sg:province":"IN",
    "sg:tags":[
        "american",
        "sandwich"
    ],
    "wof:name":"Subway",
    "wof:placetype":"venue"
},
  "geometry": {"coordinates":[-86.613806,38.557939],"type":"Point"}
}