{
  "type": "Feature",
  "properties": {
    "addr:full":"6715 W 141st Ave Cedar Lake IN 46303",
    "addr:housenumber":"6715",
    "addr:postcode":"46303",
    "addr:street":"W 141St Ave",
    "iso:country":"US",
    "sg:address":"6715 W 141st Ave",
    "sg:city":"Cedar Lake",
    "sg:classifiers":[
        {
            "category":"Organizations",
            "subcategory":"Religious Organization",
            "type":"Services"
        }
    ],
    "sg:phone":"+1 219 374 5185",
    "sg:postcode":"46303",
    "sg:province":"IN",
    "sg:tags":[
        "church"
    ],
    "wof:name":"Apostolic Fellowship Inc",
    "wof:placetype":"venue"
},
  "geometry": {"coordinates":[-87.414738,41.362407],"type":"Point"}
}