{
  "type": "Feature",
  "properties": {
    "iso:country":"US",
    "sg:address":"5844 W State Rte 68",
    "sg:city":"Lynnville",
    "sg:classifiers":[
        {
            "category":"Retail",
            "subcategory":"Repair Shop",
            "type":"Services"
        }
    ],
    "sg:phone":"+1 812 922 5505",
    "sg:postcode":"47619",
    "sg:province":"IN",
    "wof:name":"Aigner Farms",
    "wof:placetype":"venue"
},
  "geometry": {"coordinates":[-87.3471,38.19347],"type":"Point"}
}