{
  "type": "Feature",
  "properties": {
    "addr:full":"310 Argonne Rd Warsaw IN 46580",
    "addr:housenumber":"310",
    "addr:postcode":"46580",
    "addr:street":"Argonne Rd",
    "iso:country":"US",
    "sg:address":"310 Argonne Rd",
    "sg:city":"Warsaw",
    "sg:classifiers":[
        {
            "category":"Building & Trades",
            "subcategory":"Construction",
            "type":"Services"
        }
    ],
    "sg:phone":"+1 574 267 2422",
    "sg:postcode":"46580",
    "sg:province":"IN",
    "sg:tags":[
        "paving",
        "contractor"
    ],
    "wof:name":"Ranger Materials",
    "wof:placetype":"venue"
},
  "geometry": {"coordinates":[-85.823215,41.235882],"type":"Point"}
}