{
  "type": "Feature",
  "properties": {
    "iso:country":"US",
    "sg:address":"8916 W 85th Ave",
    "sg:city":"Schererville",
    "sg:classifiers":[
        {
            "category":"Building & Trades",
            "subcategory":"Construction",
            "type":"Services"
        }
    ],
    "sg:phone":"+1 219 365 8185",
    "sg:postcode":"46375",
    "sg:province":"IN",
    "sg:tags":[
        "contractor"
    ],
    "wof:name":"Lake County Drywall",
    "wof:placetype":"venue"
},
  "geometry": {"coordinates":[-87.442668,41.464348],"type":"Point"}
}