{
  "type": "Feature",
  "properties": {
    "iso:country":"US",
    "sg:address":"2319 Magnolia Pl",
    "sg:city":"Indianapolis",
    "sg:classifiers":[
        {
            "category":"Retail",
            "subcategory":"Animal Services",
            "type":"Services"
        }
    ],
    "sg:phone":"+1 317 353 1106",
    "sg:postcode":"46219",
    "sg:province":"IN",
    "sg:tags":[
        "pet",
        "boarding",
        "sitting"
    ],
    "wof:name":"Caretakers",
    "wof:placetype":"venue"
},
  "geometry": {"coordinates":[-86.061183,39.799803],"type":"Point"}
}