{
  "type": "Feature",
  "properties": {
    "iso:country":"US",
    "sg:address":"2101 Lincoln Hwy E",
    "sg:city":"New Haven",
    "sg:classifiers":[
        {
            "category":"Home & Garden",
            "subcategory":"Building Materials",
            "type":"Retail Goods"
        }
    ],
    "sg:phone":"+1 260 493 4436",
    "sg:postcode":"46774",
    "sg:province":"IN",
    "sg:tags":[
        "lumber"
    ],
    "sg:website":"www.homelumberinc.com",
    "wof:name":"Home Lumber Of New Haven Inc",
    "wof:placetype":"venue"
},
  "geometry": {"coordinates":[-85.002094,41.070514],"type":"Point"}
}