{
  "type": "Feature",
  "properties": {
    "iso:country":"US",
    "sg:address":"7278 S Co Rd 550 W",
    "sg:city":"Vallonia",
    "sg:phone":"+1 812 358 4949",
    "sg:postcode":"47281",
    "sg:province":"IN",
    "sg:tags":[
        "farm",
        "corn",
        "soybean"
    ],
    "wof:name":"Lloyd Huffman",
    "wof:placetype":"venue"
},
  "geometry": {"coordinates":[-86.137669,38.771486],"type":"Point"}
}