{
  "type": "Feature",
  "properties": {
    "iso:country":"US",
    "sg:address":"17706 Downing Dr",
    "sg:city":"Lowell",
    "sg:classifiers":[
        {
            "category":"Building & Trades",
            "subcategory":"Construction",
            "type":"Services"
        }
    ],
    "sg:phone":"+1 219 696 7552",
    "sg:postcode":"46356",
    "sg:province":"IN",
    "sg:tags":[
        "house"
    ],
    "wof:name":"Sawblades Construction Inc",
    "wof:placetype":"venue"
},
  "geometry": {"coordinates":[-87.390902,41.296919],"type":"Point"}
}