{
  "type": "Feature",
  "properties": {
    "iso:country":"US",
    "sg:address":"8450 S Franklin Rd",
    "sg:city":"Indianapolis",
    "sg:classifiers":[
        {
            "category":"Building & Trades",
            "subcategory":"Construction",
            "type":"Services"
        }
    ],
    "sg:phone":"+1 317 862 9263",
    "sg:postcode":"46259",
    "sg:province":"IN",
    "sg:tags":[
        "house"
    ],
    "wof:name":"Epic Development & Constr",
    "wof:placetype":"venue"
},
  "geometry": {"coordinates":[-86.018949,39.63805],"type":"Point"}
}