{
  "type": "Feature",
  "properties": {
    "iso:country":"US",
    "sg:address":"1215 NW 5th St",
    "sg:city":"Richmond",
    "sg:classifiers":[
        {
            "category":"Food & Beverages",
            "subcategory":"Liquor & Beverages",
            "type":"Retail Goods"
        }
    ],
    "sg:phone":"+1 765 962 5123",
    "sg:postcode":"47374",
    "sg:province":"IN",
    "wof:name":"5th Amendment Liquors",
    "wof:placetype":"venue"
},
  "geometry": {"coordinates":[-84.907852,39.84363],"type":"Point"}
}