{
  "type": "Feature",
  "properties": {
    "addr:full":"550 W Beam St Porter IN 46304",
    "addr:housenumber":"550",
    "addr:postcode":"46304",
    "addr:street":"W Beam St",
    "iso:country":"US",
    "sg:address":"550 W Beam St",
    "sg:city":"Porter",
    "sg:classifiers":[
        {
            "category":"Building & Trades",
            "subcategory":"Construction",
            "type":"Services"
        }
    ],
    "sg:phone":"+1 219 926 4212",
    "sg:postcode":"46304",
    "sg:province":"IN",
    "sg:tags":[
        "marking",
        "maintenance",
        "parking"
    ],
    "wof:name":"Porter Street Dept",
    "wof:placetype":"venue"
},
  "geometry": {"coordinates":[-87.08144299999999,41.616774],"type":"Point"}
}