{
  "type": "Feature",
  "properties": {
    "iso:country":"US",
    "sg:address":"2901 E Co Rd 500 S",
    "sg:city":"New Castle",
    "sg:classifiers":[
        {
            "category":"Home & Garden",
            "subcategory":"Building Materials",
            "type":"Retail Goods"
        }
    ],
    "sg:phone":"+1 765 332 2304",
    "sg:postcode":"47362",
    "sg:province":"IN",
    "sg:tags":[
        "mixed",
        "concrete"
    ],
    "wof:name":"Williams General Concrete",
    "wof:placetype":"venue"
},
  "geometry": {"coordinates":[-85.338081,39.860095],"type":"Point"}
}