{
  "type": "Feature",
  "properties": {
    "addr:full":"804 S Woodland Ave Michigan City IN 46360",
    "addr:housenumber":"804",
    "addr:postcode":"46360",
    "addr:street":"S Woodland Ave",
    "iso:country":"US",
    "sg:address":"804 S Woodland Ave",
    "sg:city":"Michigan City",
    "sg:classifiers":[
        {
            "category":"Professional",
            "subcategory":"Accounting & Tax Preparation",
            "type":"Services"
        }
    ],
    "sg:phone":"+1 219 879 5330",
    "sg:postcode":"46360",
    "sg:province":"IN",
    "sg:tags":[
        "return"
    ],
    "wof:name":"Marvin Kominiarek",
    "wof:placetype":"venue"
},
  "geometry": {"coordinates":[-86.874448,41.699476],"type":"Point"}
}