{
  "type": "Feature",
  "properties": {
    "iso:country":"US",
    "sg:address":"3875 S 200 W",
    "sg:city":"Shelbyville",
    "sg:classifiers":[
        {
            "category":"Wholesale",
            "subcategory":"Construction Materials",
            "type":"Manufacturing & Wholesale Goods"
        }
    ],
    "sg:phone":"+1 317 729 5464",
    "sg:postcode":"46176",
    "sg:province":"IN",
    "sg:tags":[
        "building"
    ],
    "wof:name":"Weyerhaeuser Co",
    "wof:placetype":"venue"
},
  "geometry": {"coordinates":[-85.82017,39.470188],"type":"Point"}
}