{
  "type": "Feature",
  "properties": {
    "iso:country":"US",
    "sg:address":"11 W Iowa St",
    "sg:city":"Evansville",
    "sg:classifiers":[
        {
            "category":"Organizations",
            "subcategory":"Religious Organization",
            "type":"Services"
        }
    ],
    "sg:phone":"+1 812 464 1175",
    "sg:postcode":"47710",
    "sg:province":"IN",
    "wof:name":"Evangel Temple",
    "wof:placetype":"venue"
},
  "geometry": {"coordinates":[-87.565622,37.983013],"type":"Point"}
}