{
  "type": "Feature",
  "properties": {
    "iso:country":"US",
    "sg:address":"1421 W Market St",
    "sg:city":"Logansport",
    "sg:classifiers":[
        {
            "category":"Autos & Motor Vehicles",
            "subcategory":"Automobile Sales",
            "type":"Retail Goods"
        }
    ],
    "sg:phone":"+1 574 722 1957",
    "sg:postcode":"46947",
    "sg:province":"IN",
    "sg:tags":[
        "used"
    ],
    "wof:name":"CBA Sales",
    "wof:placetype":"venue"
},
  "geometry": {"coordinates":[-86.383067,40.755312],"type":"Point"}
}