{
  "type": "Feature",
  "properties": {
    "iso:country":"US",
    "sg:address":"7277 N Piqua Rd",
    "sg:city":"Decatur",
    "sg:classifiers":[
        {
            "category":"Building & Trades",
            "subcategory":"Construction",
            "type":"Services"
        }
    ],
    "sg:phone":"+1 260 724 3637",
    "sg:postcode":"46733",
    "sg:province":"IN",
    "sg:tags":[
        "residential"
    ],
    "wof:name":"Knous Construction",
    "wof:placetype":"venue"
},
  "geometry": {"coordinates":[-84.926861,40.851685],"type":"Point"}
}