{
  "type": "Feature",
  "properties": {
    "iso:country":"US",
    "sg:address":"2531 Broadway St",
    "sg:city":"Fort Wayne",
    "sg:classifiers":[
        {
            "category":"Autos & Motor Vehicles",
            "subcategory":"Fuel & Gas Station",
            "type":"Retail Goods"
        }
    ],
    "sg:phone":"+1 260 745 3588",
    "sg:postcode":"46807",
    "sg:province":"IN",
    "sg:tags":[
        "oil"
    ],
    "wof:name":"Broadway Pointe",
    "wof:placetype":"venue"
},
  "geometry": {"coordinates":[-85.152207,41.062411],"type":"Point"}
}