{
  "type": "Feature",
  "properties": {
    "iso:country":"US",
    "sg:address":"11701 S Co Rd 396 E",
    "sg:city":"Muncie",
    "sg:classifiers":[
        {
            "category":"Building & Trades",
            "subcategory":"Construction",
            "type":"Services"
        }
    ],
    "sg:phone":"+1 765 774 4142",
    "sg:postcode":"47302",
    "sg:province":"IN",
    "sg:tags":[
        "house"
    ],
    "wof:name":"Hunter Construction Inc",
    "wof:placetype":"venue"
},
  "geometry": {"coordinates":[-85.309403,40.086041],"type":"Point"}
}