{
  "type": "Feature",
  "properties": {
    "addr:full":"3224 Jasper St West Lafayette IN 47906",
    "addr:housenumber":"3224",
    "addr:postcode":"47906",
    "addr:street":"Jasper St",
    "iso:country":"US",
    "sg:address":"3224 Jasper St",
    "sg:city":"West Lafayette",
    "sg:classifiers":[
        {
            "category":"Organizations",
            "subcategory":"Religious Organization",
            "type":"Services"
        }
    ],
    "sg:phone":"+1 765 463 4772",
    "sg:postcode":"47906",
    "sg:province":"IN",
    "wof:name":"Lafayette Stake",
    "wof:placetype":"venue"
},
  "geometry": {"coordinates":[-86.902697,40.465038],"type":"Point"}
}