{
  "type": "Feature",
  "properties": {
    "iso:country":"US",
    "sg:address":"3385 N Arlington Ave",
    "sg:city":"Indianapolis",
    "sg:classifiers":[
        {
            "category":"Building & Trades",
            "subcategory":"Electrical",
            "type":"Services"
        }
    ],
    "sg:phone":"+1 317 545 7641",
    "sg:postcode":"46218",
    "sg:province":"IN",
    "sg:tags":[
        "electric",
        "contractor"
    ],
    "wof:name":"Midwestern Electric Inc",
    "wof:placetype":"venue"
},
  "geometry": {"coordinates":[-86.064621,39.817331],"type":"Point"}
}