{
  "type": "Feature",
  "properties": {
    "iso:country":"US",
    "sg:address":"812 19th St",
    "sg:city":"Bedford",
    "sg:classifiers":[
        {
            "category":"Building & Trades",
            "subcategory":"Construction",
            "type":"Services"
        }
    ],
    "sg:phone":"+1 812 275 4854",
    "sg:postcode":"47421",
    "sg:province":"IN",
    "sg:tags":[
        "contractor",
        "nonresidential"
    ],
    "wof:name":"Terrell Building Contractors",
    "wof:placetype":"venue"
},
  "geometry": {"coordinates":[-86.482091,38.857347],"type":"Point"}
}