{
  "type": "Feature",
  "properties": {
    "addr:full":"197 W State St East Brunswick IN 47834",
    "addr:housenumber":"197",
    "addr:postcode":"47834",
    "addr:street":"W State St",
    "iso:country":"US",
    "sg:address":"197 W State St",
    "sg:city":"East Brunswick",
    "sg:classifiers":[
        {
            "category":"Building & Trades",
            "subcategory":"Construction",
            "type":"Services"
        }
    ],
    "sg:phone":"+1 732 246 3388",
    "sg:postcode":"47834",
    "sg:province":"IN",
    "sg:tags":[
        "home",
        "builder"
    ],
    "wof:name":"KARA Homes Inc",
    "wof:placetype":"venue"
},
  "geometry": {"coordinates":[-87.129763,39.523863],"type":"Point"}
}