{
  "type": "Feature",
  "properties": {
    "iso:country":"US",
    "sg:address":"515 Euphemia St",
    "sg:city":"Lawrenceburg",
    "sg:classifiers":[
        {
            "category":"Organizations",
            "subcategory":"Religious Organization",
            "type":"Services"
        }
    ],
    "sg:phone":"+1 812 537 3735",
    "sg:postcode":"47025",
    "sg:province":"IN",
    "sg:tags":[
        "clergy"
    ],
    "wof:name":"Thomas Gannaway Jr",
    "wof:placetype":"venue"
},
  "geometry": {"coordinates":[-84.848294,39.101018],"type":"Point"}
}