{
  "type": "Feature",
  "properties": {
    "iso:country":"US",
    "sg:address":"6 N Shield St",
    "sg:city":"Knox",
    "sg:classifiers":[
        {
            "category":"Education",
            "subcategory":"School",
            "type":"Public Place"
        }
    ],
    "sg:phone":"+1 574 772 5131",
    "sg:postcode":"46534",
    "sg:province":"IN",
    "wof:name":"Starke County Adult Education",
    "wof:placetype":"venue"
},
  "geometry": {"coordinates":[-86.624267,41.298336],"type":"Point"}
}