{
  "type": "Feature",
  "properties": {
    "iso:country":"US",
    "sg:address":"2476 S 525 W",
    "sg:city":"Trafalgar",
    "sg:classifiers":[
        {
            "category":"Farming",
            "subcategory":"Nursery",
            "type":"Manufacturing & Wholesale Goods"
        }
    ],
    "sg:phone":"+1 317 878 5620",
    "sg:postcode":"46181",
    "sg:province":"IN",
    "sg:tags":[
        "turf"
    ],
    "wof:name":"Quality Turf Care & Landscpg",
    "wof:placetype":"venue"
},
  "geometry": {"coordinates":[-86.201255,39.438126],"type":"Point"}
}