{
  "type": "Feature",
  "properties": {
    "iso:country":"US",
    "sg:address":"221 N Main St",
    "sg:city":"Bourbon",
    "sg:classifiers":[
        {
            "category":"Government",
            "subcategory":"Post Office",
            "type":"Public Place"
        }
    ],
    "sg:phone":"+1 574 342 3175",
    "sg:postcode":"46504",
    "sg:province":"IN",
    "wof:name":"US Post Office",
    "wof:placetype":"venue"
},
  "geometry": {"coordinates":[-86.11635,41.297074],"type":"Point"}
}