{
  "type": "Feature",
  "properties": {
    "iso:country":"US",
    "sg:address":"2700 Dwenger Ave",
    "sg:city":"Fort Wayne",
    "sg:classifiers":[
        {
            "category":"Government",
            "subcategory":"Fire Station",
            "type":"Public Place"
        }
    ],
    "sg:phone":"+1 260 427 1246",
    "sg:postcode":"46803",
    "sg:province":"IN",
    "sg:tags":[
        "department"
    ],
    "wof:name":"Fort Wayne Fire Academy",
    "wof:placetype":"venue"
},
  "geometry": {"coordinates":[-85.106301,41.080236],"type":"Point"}
}