{
  "type": "Feature",
  "properties": {
    "addr:full":"318 W Main St Farmersburg IN 47850",
    "addr:housenumber":"318",
    "addr:postcode":"47850",
    "addr:street":"W Main St",
    "iso:country":"US",
    "sg:address":"318 W Main St",
    "sg:city":"Farmersburg",
    "sg:classifiers":[
        {
            "category":"Organizations",
            "subcategory":"Religious Organization",
            "type":"Services"
        }
    ],
    "sg:phone":"+1 812 696 2848",
    "sg:postcode":"47850",
    "sg:province":"IN",
    "sg:tags":[
        "church"
    ],
    "wof:name":"United Methodist Church",
    "wof:placetype":"venue"
},
  "geometry": {"coordinates":[-87.381925,39.253831],"type":"Point"}
}