{
  "type": "Feature",
  "properties": {
    "iso:country":"US",
    "sg:address":"420 S Emerson Ave",
    "sg:city":"Greenwood",
    "sg:classifiers":[
        {
            "category":"Real Estate",
            "subcategory":"Real Estate Agent",
            "type":"Services"
        }
    ],
    "sg:phone":"+1 317 881 6542",
    "sg:postcode":"46143",
    "sg:province":"IN",
    "wof:name":"Indiana Real Estate Group Inc",
    "wof:placetype":"venue"
},
  "geometry": {"coordinates":[-86.08268700000001,39.611433],"type":"Point"}
}