{
  "type": "Feature",
  "properties": {
    "iso:country":"US",
    "sg:address":"731 S Lafayette Blvd",
    "sg:city":"South Bend",
    "sg:classifiers":[
        {
            "category":"Government",
            "subcategory":"Office",
            "type":"Public Place"
        }
    ],
    "sg:phone":"+1 574 235 9444",
    "sg:postcode":"46601",
    "sg:province":"IN",
    "sg:tags":[
        "village"
    ],
    "wof:name":"South Bend Sewer Bureau",
    "wof:placetype":"venue"
},
  "geometry": {"coordinates":[-86.253495,41.668848],"type":"Point"}
}