{
  "type": "Feature",
  "properties": {
    "addr:full":"401 Hawthorne Dr Goshen IN 46526",
    "addr:housenumber":"401",
    "addr:postcode":"46526",
    "addr:street":"Hawthorne Dr",
    "iso:country":"US",
    "sg:address":"401 Hawthorne Dr",
    "sg:city":"Goshen",
    "sg:classifiers":[
        {
            "category":"Organizations",
            "subcategory":"Religious Organization",
            "type":"Services"
        }
    ],
    "sg:phone":"+1 574 533 6540",
    "sg:postcode":"46526",
    "sg:province":"IN",
    "wof:name":"Rev Terrell Timothy",
    "wof:placetype":"venue"
},
  "geometry": {"coordinates":[-85.87342200000001,41.590263],"type":"Point"}
}