{
  "type": "Feature",
  "properties": {
    "iso:country":"US",
    "sg:address":"508 W State Rd 26",
    "sg:city":"Sedalia",
    "sg:classifiers":[
        {
            "category":"Freight",
            "type":"Transportation"
        }
    ],
    "sg:phone":"+1 765 258 3002",
    "sg:postcode":"46041",
    "sg:province":"IN",
    "sg:tags":[
        "grain",
        "elevator"
    ],
    "wof:name":"Sedalia Grain Co",
    "wof:placetype":"venue"
},
  "geometry": {"coordinates":[-86.523914,40.416787],"type":"Point"}
}