{
  "type": "Feature",
  "properties": {
    "iso:country":"US",
    "sg:address":"8830 Southpointe Dr",
    "sg:city":"Indianapolis",
    "sg:classifiers":[
        {
            "category":"Social Services",
            "subcategory":"Child Care",
            "type":"Services"
        }
    ],
    "sg:phone":"+1 317 882 3988",
    "sg:postcode":"46227",
    "sg:province":"IN",
    "sg:tags":[
        "kindergarten",
        "academic",
        "school"
    ],
    "wof:name":"Kids World Of America Inc",
    "wof:placetype":"venue"
},
  "geometry": {"coordinates":[-86.137985,39.635737],"type":"Point"}
}