{
  "type": "Feature",
  "properties": {
    "iso:country":"US",
    "sg:address":"315 N Senate Ave Apt A",
    "sg:city":"Indianapolis",
    "sg:classifiers":[
        {
            "category":"Professional",
            "subcategory":"Art Services",
            "type":"Services"
        }
    ],
    "sg:phone":"+1 317 679 5713",
    "sg:postcode":"46204",
    "sg:province":"IN",
    "sg:tags":[
        "designer",
        "display",
        "producer"
    ],
    "wof:name":"November Concepts Incorporated",
    "wof:placetype":"venue"
},
  "geometry": {"coordinates":[-86.16336,39.771604],"type":"Point"}
}