{
  "type": "Feature",
  "properties": {
    "iso:country":"US",
    "sg:address":"104 Billings St",
    "sg:city":"Valparaiso",
    "sg:classifiers":[
        {
            "category":"Shopping",
            "subcategory":"Computers & Home Electronics",
            "type":"Retail Goods"
        }
    ],
    "sg:phone":"+1 219 465 1155",
    "sg:postcode":"46383",
    "sg:province":"IN",
    "sg:tags":[
        "parts",
        "supply"
    ],
    "wof:name":"Laser Systems Inc",
    "wof:placetype":"venue"
},
  "geometry": {"coordinates":[-87.056068,41.476937],"type":"Point"}
}