{
  "type": "Feature",
  "properties": {
    "iso:country":"US",
    "sg:address":"1950 W Bunkum Rd",
    "sg:city":"Rensselaer",
    "sg:classifiers":[
        {
            "category":"Real Estate",
            "subcategory":"Real Estate Services",
            "type":"Services"
        }
    ],
    "sg:phone":"+1 219 866 7665",
    "sg:postcode":"47978",
    "sg:province":"IN",
    "sg:tags":[
        "company",
        "title"
    ],
    "wof:name":"Diana L Dewey Inc",
    "wof:placetype":"venue"
},
  "geometry": {"coordinates":[-87.173965,40.932012],"type":"Point"}
}