{
  "type": "Feature",
  "properties": {
    "addr:full":"721 River Dr Munster IN 46321",
    "addr:housenumber":"721",
    "addr:postcode":"46321",
    "addr:street":"River Dr",
    "iso:country":"US",
    "sg:address":"721 River Dr",
    "sg:city":"Munster",
    "sg:classifiers":[
        {
            "category":"Building & Trades",
            "subcategory":"Landscaping Services",
            "type":"Services"
        }
    ],
    "sg:phone":"+1 219 836 6435",
    "sg:postcode":"46321",
    "sg:province":"IN",
    "wof:name":"Grasshopper Lawncare Services",
    "wof:placetype":"venue"
},
  "geometry": {"coordinates":[-87.51131700000001,41.570667],"type":"Point"}
}