{
  "type": "Feature",
  "properties": {
    "iso:country":"US",
    "sg:address":"29601 Smith Rd",
    "sg:city":"Walkerton",
    "sg:classifiers":[
        {
            "category":"Farming",
            "subcategory":"Farm",
            "type":"Manufacturing & Wholesale Goods"
        }
    ],
    "sg:phone":"+1 574 586 3191",
    "sg:postcode":"46574",
    "sg:province":"IN",
    "sg:tags":[
        "crop",
        "general"
    ],
    "wof:name":"K&M Farm",
    "wof:placetype":"venue"
},
  "geometry": {"coordinates":[-86.437952,41.48761],"type":"Point"}
}