{
  "type": "Feature",
  "properties": {
    "iso:country":"US",
    "sg:address":"128 N Walnut St",
    "sg:city":"Batesville",
    "sg:classifiers":[
        {
            "category":"Real Estate",
            "subcategory":"Real Estate Agent",
            "type":"Services"
        }
    ],
    "sg:phone":"+1 812 932 8550",
    "sg:postcode":"47006",
    "sg:province":"IN",
    "sg:tags":[
        "management"
    ],
    "wof:name":"Obermeyer Property Management",
    "wof:placetype":"venue"
},
  "geometry": {"coordinates":[-85.222169,39.300375],"type":"Point"}
}