{
  "type": "Feature",
  "properties": {
    "iso:country":"US",
    "sg:address":"10442 Connaught Dr",
    "sg:city":"Carmel",
    "sg:classifiers":[
        {
            "category":"Personal",
            "type":"Services"
        }
    ],
    "sg:phone":"+1 317 337 0494",
    "sg:postcode":"46032",
    "sg:province":"IN",
    "sg:tags":[
        "bureau"
    ],
    "wof:name":"Just Like Family Inc",
    "wof:placetype":"venue"
},
  "geometry": {"coordinates":[-86.21683,39.939155],"type":"Point"}
}