{
  "type": "Feature",
  "properties": {
    "iso:country":"US",
    "sg:address":"640 E 45th Ave",
    "sg:city":"Gary",
    "sg:classifiers":[
        {
            "category":"Organizations",
            "subcategory":"Religious Organization",
            "type":"Services"
        }
    ],
    "sg:phone":"+1 219 980 5006",
    "sg:postcode":"46409",
    "sg:province":"IN",
    "sg:tags":[
        "church"
    ],
    "wof:name":"New Providence Baptist Church",
    "wof:placetype":"venue"
},
  "geometry": {"coordinates":[-87.32818,41.536755],"type":"Point"}
}