{
  "type": "Feature",
  "properties": {
    "iso:country":"US",
    "sg:address":"8203 Indy Ct",
    "sg:city":"Indianapolis",
    "sg:classifiers":[
        {
            "category":"Organizations",
            "subcategory":"Religious Organization",
            "type":"Services"
        }
    ],
    "sg:phone":"+1 317 248 1435",
    "sg:postcode":"46214",
    "sg:province":"IN",
    "sg:tags":[
        "church"
    ],
    "wof:name":"Gateway Tabernacle",
    "wof:placetype":"venue"
},
  "geometry": {"coordinates":[-86.306061,39.790021],"type":"Point"}
}