{
  "type": "Feature",
  "properties": {
    "iso:country":"US",
    "sg:address":"5022 Central Ave",
    "sg:city":"Indianapolis",
    "sg:classifiers":[
        {
            "category":"Professional",
            "subcategory":"Art Services",
            "type":"Services"
        }
    ],
    "sg:phone":"+1 317 924 9801",
    "sg:postcode":"46205",
    "sg:province":"IN",
    "sg:tags":[
        "graphic",
        "designer"
    ],
    "wof:name":"Balance Designs",
    "wof:placetype":"venue"
},
  "geometry": {"coordinates":[-86.14998,39.844055],"type":"Point"}
}