{
  "type": "Feature",
  "properties": {
    "iso:country":"US",
    "sg:address":"277 N Thorne St",
    "sg:city":"Wabash",
    "sg:classifiers":[
        {
            "category":"Education",
            "subcategory":"College",
            "type":"Public Place"
        }
    ],
    "sg:phone":"+1 260 563 8828",
    "sg:postcode":"46992",
    "sg:province":"IN",
    "sg:tags":[
        "academic",
        "school"
    ],
    "wof:name":"Ivy Tech State College",
    "wof:placetype":"venue"
},
  "geometry": {"coordinates":[-85.831563,40.800662],"type":"Point"}
}