{
  "type": "Feature",
  "properties": {
    "iso:country":"US",
    "sg:address":"4211 E 62nd St",
    "sg:city":"Indianapolis",
    "sg:classifiers":[
        {
            "category":"Retail",
            "subcategory":"Laundry & Dry Cleaning",
            "type":"Services"
        }
    ],
    "sg:phone":"+1 317 253 6544",
    "sg:postcode":"46220",
    "sg:province":"IN",
    "sg:tags":[
        "cleaners"
    ],
    "wof:name":"Classic Cleaners",
    "wof:placetype":"venue"
},
  "geometry": {"coordinates":[-86.09497,39.868557],"type":"Point"}
}