{
  "type": "Feature",
  "properties": {
    "iso:country":"US",
    "sg:address":"2040 S Lynhurst Dr",
    "sg:city":"Indianapolis",
    "sg:classifiers":[
        {
            "category":"Wholesale",
            "subcategory":"Machinery & Supplies",
            "type":"Manufacturing & Wholesale Goods"
        }
    ],
    "sg:phone":"+1 317 247 4998",
    "sg:postcode":"46241",
    "sg:province":"IN",
    "sg:tags":[
        "casket"
    ],
    "wof:name":"Aurora Casket Co",
    "wof:placetype":"venue"
},
  "geometry": {"coordinates":[-86.250337,39.738351],"type":"Point"}
}