{
  "type": "Feature",
  "properties": {
    "iso:country":"US",
    "sg:address":"5311 N 350 W",
    "sg:city":"Thorntown",
    "sg:classifiers":[
        {
            "category":"Building & Trades",
            "subcategory":"Construction",
            "type":"Services"
        }
    ],
    "sg:phone":"+1 317 557 5236",
    "sg:postcode":"46071",
    "sg:province":"IN",
    "sg:tags":[
        "house"
    ],
    "wof:name":"K Marshall Construction",
    "wof:placetype":"venue"
},
  "geometry": {"coordinates":[-86.534256,40.117891],"type":"Point"}
}