{
  "type": "Feature",
  "properties": {
    "iso:country":"US",
    "sg:address":"6900 W Co Rd 575 S",
    "sg:city":"French Lick",
    "sg:classifiers":[
        {
            "category":"Building & Trades",
            "subcategory":"Construction",
            "type":"Services"
        }
    ],
    "sg:phone":"+1 812 936 4040",
    "sg:postcode":"47432",
    "sg:province":"IN",
    "sg:tags":[
        "excavating",
        "contractor"
    ],
    "wof:name":"Collins Excavating",
    "wof:placetype":"venue"
},
  "geometry": {"coordinates":[-86.585649,38.472544],"type":"Point"}
}