{
  "type": "Feature",
  "properties": {
    "iso:country":"US",
    "sg:address":"1904 Broad Ripple Ave",
    "sg:city":"Indianapolis",
    "sg:classifiers":[
        {
            "category":"Restaurant",
            "type":"Food & Drink"
        }
    ],
    "sg:phone":"+1 317 205 9130",
    "sg:postcode":"46220",
    "sg:province":"IN",
    "sg:tags":[
        "barbecue"
    ],
    "wof:name":"Barbeque Heaven",
    "wof:placetype":"venue"
},
  "geometry": {"coordinates":[-86.127039,39.868734],"type":"Point"}
}