{
  "type": "Feature",
  "properties": {
    "iso:country":"US",
    "sg:address":"2627 Charlestown Rd",
    "sg:city":"New Albany",
    "sg:classifiers":[
        {
            "category":"Banks & Credit Unions",
            "subcategory":"Bank",
            "type":"Services"
        }
    ],
    "sg:phone":"+1 812 944 7775",
    "sg:postcode":"47150",
    "sg:province":"IN",
    "sg:tags":[
        "loan",
        "real estate"
    ],
    "wof:name":"Covenant Mortgage",
    "wof:placetype":"venue"
},
  "geometry": {"coordinates":[-85.804191,38.316942],"type":"Point"}
}