{
  "type": "Feature",
  "properties": {
    "iso:country":"US",
    "sg:address":"1755 State Rd 39",
    "sg:city":"Danville",
    "sg:classifiers":[
        {
            "category":"Retail",
            "subcategory":"Repair Shop",
            "type":"Services"
        }
    ],
    "sg:phone":"+1 317 718 0385",
    "sg:postcode":"46122",
    "sg:province":"IN",
    "wof:name":"Smith Tank Cleaning Specialist",
    "wof:placetype":"venue"
},
  "geometry": {"coordinates":[-86.526995,39.734331],"type":"Point"}
}