{
  "type": "Feature",
  "properties": {
    "iso:country":"US",
    "sg:address":"143 N Illinois St",
    "sg:city":"Indianapolis",
    "sg:classifiers":[
        {
            "category":"Restaurant",
            "type":"Food & Drink"
        }
    ],
    "sg:phone":"+1 317 634 1144",
    "sg:postcode":"46204",
    "sg:province":"IN",
    "wof:name":"Enzo Pizza",
    "wof:placetype":"venue"
},
  "geometry": {"coordinates":[-86.15979799999999,39.769959],"type":"Point"}
}