{
  "type": "Feature",
  "properties": {
    "iso:country":"US",
    "sg:address":"8313 E Washington St",
    "sg:city":"Indianapolis",
    "sg:classifiers":[
        {
            "category":"Banks & Credit Unions",
            "subcategory":"Bank",
            "type":"Services"
        }
    ],
    "sg:phone":"+1 317 899 1440",
    "sg:postcode":"46219",
    "sg:province":"IN",
    "sg:tags":[
        "financing"
    ],
    "wof:name":"Beneficial Indiana Inc",
    "wof:placetype":"venue"
},
  "geometry": {"coordinates":[-86.019688,39.773323],"type":"Point"}
}