{
  "type": "Feature",
  "properties": {
    "addr:full":"4843 W 106th St Zionsville IN 46077",
    "addr:housenumber":"4843",
    "addr:postcode":"46077",
    "addr:street":"W 106Th St",
    "iso:country":"US",
    "sg:address":"4843 W 106th St",
    "sg:city":"Zionsville",
    "sg:classifiers":[
        {
            "category":"Professional",
            "subcategory":"Management & Consulting",
            "type":"Services"
        }
    ],
    "sg:phone":"+1 317 873 6976",
    "sg:postcode":"46077",
    "sg:province":"IN",
    "sg:tags":[
        "marketing",
        "consultant"
    ],
    "wof:name":"Marketwise Solutions",
    "wof:placetype":"venue"
},
  "geometry": {"coordinates":[-86.24108699999999,39.940651],"type":"Point"}
}