{
  "type": "Feature",
  "properties": {
    "iso:country":"US",
    "sg:address":"530 W Lincoln Ave",
    "sg:city":"Chandler",
    "sg:classifiers":[
        {
            "category":"Social Services",
            "subcategory":"Child Care",
            "type":"Services"
        }
    ],
    "sg:phone":"+1 812 925 9950",
    "sg:postcode":"47610",
    "sg:province":"IN",
    "wof:name":"Kiddie City Inc",
    "wof:placetype":"venue"
},
  "geometry": {"coordinates":[-87.375168,38.040606],"type":"Point"}
}