{
  "type": "Feature",
  "properties": {
    "iso:country":"US",
    "sg:address":"412 Canal Court S Dr",
    "sg:city":"Indianapolis",
    "sg:classifiers":[
        {
            "category":"Professional",
            "subcategory":"Management & Consulting",
            "type":"Services"
        }
    ],
    "sg:phone":"+1 317 955 8881",
    "sg:postcode":"46202",
    "sg:province":"IN",
    "wof:name":"Training & Development Resou",
    "wof:placetype":"venue"
},
  "geometry": {"coordinates":[-86.16654800000001,39.777906],"type":"Point"}
}