{
  "type": "Feature",
  "properties": {
    "iso:country":"US",
    "sg:address":"3802 Industrial Blvd",
    "sg:city":"Bloomington",
    "sg:classifiers":[
        {
            "category":"Wholesale",
            "subcategory":"Medical Equipment & Supplies",
            "type":"Manufacturing & Wholesale Goods"
        }
    ],
    "sg:phone":"+1 812 333 9901",
    "sg:postcode":"47403",
    "sg:province":"IN",
    "sg:tags":[
        "hospital"
    ],
    "wof:name":"Apria Healthcare",
    "wof:placetype":"venue"
},
  "geometry": {"coordinates":[-86.58096500000001,39.143934],"type":"Point"}
}