{
  "type": "Feature",
  "properties": {
    "addr:full":"220 N Maine St Remington IN 47977",
    "addr:housenumber":"220",
    "addr:postcode":"47977",
    "addr:street":"N Maine St",
    "iso:country":"US",
    "sg:address":"220 N Maine St",
    "sg:city":"Remington",
    "sg:classifiers":[
        {
            "category":"Real Estate",
            "subcategory":"Real Estate Operator",
            "type":"Services"
        }
    ],
    "sg:phone":"+1 219 261 3084",
    "sg:postcode":"47977",
    "sg:province":"IN",
    "sg:tags":[
        "building",
        "apartment"
    ],
    "wof:name":"Pines APT of Remington",
    "wof:placetype":"venue"
},
  "geometry": {"coordinates":[-87.153695,40.763258],"type":"Point"}
}