{
  "type": "Feature",
  "properties": {
    "iso:country":"US",
    "sg:address":"510 W Superior St",
    "sg:city":"Osceola",
    "sg:classifiers":[
        {
            "category":"Professional",
            "subcategory":"Accounting & Tax Preparation",
            "type":"Services"
        }
    ],
    "sg:phone":"+1 574 674 0738",
    "sg:postcode":"46561",
    "sg:province":"IN",
    "sg:tags":[
        "return",
        "filing"
    ],
    "wof:name":"Piper's Tax Svc",
    "wof:placetype":"venue"
},
  "geometry": {"coordinates":[-86.079126,41.661445],"type":"Point"}
}