{
  "type": "Feature",
  "properties": {
    "iso:country":"US",
    "sg:address":"377 W US Hwy 6",
    "sg:city":"Valparaiso",
    "sg:classifiers":[
        {
            "category":"Autos & Motor Vehicles",
            "subcategory":"Auto Supplies",
            "type":"Retail Goods"
        }
    ],
    "sg:phone":"+1 219 762 2545",
    "sg:postcode":"46385",
    "sg:province":"IN",
    "sg:tags":[
        "tire"
    ],
    "wof:name":"Al's Tire",
    "wof:placetype":"venue"
},
  "geometry": {"coordinates":[-87.139078,41.550295],"type":"Point"}
}