{
  "type": "Feature",
  "properties": {
    "iso:country":"US",
    "sg:address":"4672 W 38th St",
    "sg:city":"Indianapolis",
    "sg:classifiers":[
        {
            "category":"Shopping",
            "subcategory":"Clothing, Apparel, & Fashions",
            "type":"Retail Goods"
        }
    ],
    "sg:phone":"+1 317 347 0277",
    "sg:postcode":"46254",
    "sg:province":"IN",
    "wof:name":"Total Fashion",
    "wof:placetype":"venue"
},
  "geometry": {"coordinates":[-86.237416,39.824072],"type":"Point"}
}