{
  "type": "Feature",
  "properties": {
    "addr:full":"923 Kenmore Dr Evansville IN 47714",
    "addr:housenumber":"923",
    "addr:postcode":"47714",
    "addr:street":"Kenmore Dr",
    "iso:country":"US",
    "sg:address":"923 Kenmore Dr",
    "sg:city":"Evansville",
    "sg:classifiers":[
        {
            "category":"Education",
            "subcategory":"Special Training",
            "type":"Public Place"
        }
    ],
    "sg:phone":"+1 812 479 1150",
    "sg:postcode":"47714",
    "sg:province":"IN",
    "sg:tags":[
        "tutoring"
    ],
    "wof:name":"Sylvan Learning Ctr",
    "wof:placetype":"venue"
},
  "geometry": {"coordinates":[-87.496948,37.964514],"type":"Point"}
}