{
  "type": "Feature",
  "properties": {
    "addr:full":"12970 McKinley Hwy Mishawaka IN 46545",
    "addr:housenumber":"12970",
    "addr:postcode":"46545",
    "addr:street":"Mckinley Hwy",
    "iso:country":"US",
    "sg:address":"12970 McKinley Hwy",
    "sg:city":"Mishawaka",
    "sg:classifiers":[
        {
            "category":"Building & Trades",
            "subcategory":"Construction",
            "type":"Services"
        }
    ],
    "sg:phone":"+1 574 254 0801",
    "sg:postcode":"46545",
    "sg:province":"IN",
    "sg:tags":[
        "concrete",
        "restoration",
        "cleaning",
        "repair"
    ],
    "wof:name":"Surface Dimensions Of Indiana",
    "wof:placetype":"venue"
},
  "geometry": {"coordinates":[-86.118647,41.682215],"type":"Point"}
}