{
  "type": "Feature",
  "properties": {
    "iso:country":"US",
    "sg:address":"341 E 10th St",
    "sg:city":"Ferdinand",
    "sg:classifiers":[
        {
            "category":"Organizations",
            "subcategory":"Religious Organization",
            "type":"Services"
        }
    ],
    "sg:phone":"+1 812 367 1212",
    "sg:postcode":"47532",
    "sg:province":"IN",
    "sg:tags":[
        "church"
    ],
    "wof:name":"St Ferdinand's Church",
    "wof:placetype":"venue"
},
  "geometry": {"coordinates":[-86.859932,38.224135],"type":"Point"}
}