{
  "type": "Feature",
  "properties": {
    "addr:full":"618 Kimmell Rd Vincennes IN 47591",
    "addr:housenumber":"618",
    "addr:postcode":"47591",
    "addr:street":"Kimmell Rd",
    "iso:country":"US",
    "sg:address":"618 Kimmell Rd",
    "sg:city":"Vincennes",
    "sg:classifiers":[
        {
            "category":"Shopping",
            "subcategory":"Department Store",
            "type":"Retail Goods"
        }
    ],
    "sg:phone":"+1 812 886 4854",
    "sg:postcode":"47591",
    "sg:province":"IN",
    "wof:name":"Goody's Family Clothing",
    "wof:placetype":"venue"
},
  "geometry": {"coordinates":[-87.495779,38.668064],"type":"Point"}
}