{
  "type": "Feature",
  "properties": {
    "iso:country":"US",
    "sg:address":"40 W 79th Ave",
    "sg:city":"Merrillville",
    "sg:classifiers":[
        {
            "category":"Professional",
            "subcategory":"Employment Agencies",
            "type":"Services"
        }
    ],
    "sg:phone":"+1 219 756 8622",
    "sg:postcode":"46410",
    "sg:province":"IN",
    "sg:tags":[
        "help",
        "contractor"
    ],
    "wof:name":"Star Staffing Svc Inc",
    "wof:placetype":"venue"
},
  "geometry": {"coordinates":[-87.34582899999999,41.475437],"type":"Point"}
}