{
  "type": "Feature",
  "properties": {
    "iso:country":"US",
    "sg:address":"623 S Laurel St",
    "sg:city":"Mishawaka",
    "sg:classifiers":[
        {
            "category":"Wholesale",
            "subcategory":"Drugs",
            "type":"Manufacturing & Wholesale Goods"
        }
    ],
    "sg:phone":"+1 574 259 7473",
    "sg:postcode":"46544",
    "sg:province":"IN",
    "sg:tags":[
        "pharmaceutical",
        "product"
    ],
    "wof:name":"Amerisource",
    "wof:placetype":"venue"
},
  "geometry": {"coordinates":[-86.171588,41.655968],"type":"Point"}
}