{
  "type": "Feature",
  "properties": {
    "iso:country":"US",
    "sg:address":"819 E 64th St",
    "sg:city":"Indianapolis",
    "sg:classifiers":[
        {
            "category":"Professional",
            "type":"Services"
        }
    ],
    "sg:phone":"+1 317 466 0025",
    "sg:postcode":"46220",
    "sg:province":"IN",
    "sg:tags":[
        "establishment"
    ],
    "wof:name":"Jackie Leppert Lmhc",
    "wof:placetype":"venue"
},
  "geometry": {"coordinates":[-86.144669,39.872561],"type":"Point"}
}