{
  "type": "Feature",
  "properties": {
    "iso:country":"US",
    "sg:address":"357 Tanger Blvd",
    "sg:city":"Seymour",
    "sg:classifiers":[
        {
            "category":"Shopping",
            "subcategory":"Clothing, Apparel, & Fashions",
            "type":"Retail Goods"
        }
    ],
    "sg:phone":"+1 812 524 8094",
    "sg:postcode":"47274",
    "sg:province":"IN",
    "sg:website":"www.bonworth.com",
    "wof:name":"Bon Worth",
    "wof:placetype":"venue"
},
  "geometry": {"coordinates":[-85.840363,38.960897],"type":"Point"}
}