{
  "type": "Feature",
  "properties": {
    "addr:full":"201 E Floral Ave Portland IN 47371",
    "addr:housenumber":"201",
    "addr:postcode":"47371",
    "addr:street":"E Floral Ave",
    "iso:country":"US",
    "sg:address":"201 E Floral Ave",
    "sg:city":"Portland",
    "sg:classifiers":[
        {
            "category":"Organizations",
            "subcategory":"Religious Organization",
            "type":"Services"
        }
    ],
    "sg:phone":"+1 260 726 9874",
    "sg:postcode":"47371",
    "sg:province":"IN",
    "sg:tags":[
        "church"
    ],
    "wof:name":"Church Of The Brethren",
    "wof:placetype":"venue"
},
  "geometry": {"coordinates":[-84.975184,40.421016],"type":"Point"}
}