{
  "type": "Feature",
  "properties": {
    "addr:full":"4487 E 400 N Portland IN 47371",
    "addr:housenumber":"4487",
    "addr:postcode":"47371",
    "addr:street":"E 400 N",
    "iso:country":"US",
    "sg:address":"4487 E 400 N",
    "sg:city":"Portland",
    "sg:classifiers":[
        {
            "category":"Organizations",
            "subcategory":"Religious Organization",
            "type":"Services"
        }
    ],
    "sg:phone":"+1 260 726 6311",
    "sg:postcode":"47371",
    "sg:province":"IN",
    "sg:tags":[
        "church"
    ],
    "wof:name":"Westchester United Methodist",
    "wof:placetype":"venue"
},
  "geometry": {"coordinates":[-84.91370499999999,40.498036],"type":"Point"}
}