{
  "type": "Feature",
  "properties": {
    "iso:country":"US",
    "sg:address":"693 E 82nd St",
    "sg:city":"Indianapolis",
    "sg:classifiers":[
        {
            "category":"Professional",
            "subcategory":"Art Services",
            "type":"Services"
        }
    ],
    "sg:phone":"+1 317 254 8376",
    "sg:postcode":"46240",
    "sg:province":"IN",
    "sg:tags":[
        "photography",
        "commercial"
    ],
    "sg:website":"www.distelphoto.com",
    "wof:name":"Don Distel Photography",
    "wof:placetype":"venue"
},
  "geometry": {"coordinates":[-86.147396,39.90611],"type":"Point"}
}