{
  "type": "Feature",
  "properties": {
    "iso:country":"US",
    "sg:address":"51465 Bittersweet Rd",
    "sg:city":"Granger",
    "sg:classifiers":[
        {
            "category":"Wholesale",
            "subcategory":"Auto Parts",
            "type":"Manufacturing & Wholesale Goods"
        }
    ],
    "sg:phone":"+1 574 272 3840",
    "sg:postcode":"46530",
    "sg:province":"IN",
    "sg:tags":[
        "equipment",
        "truck"
    ],
    "wof:name":"Dwyer Equipment Co Inc",
    "wof:placetype":"venue"
},
  "geometry": {"coordinates":[-86.110944,41.744659],"type":"Point"}
}