{
  "type": "Feature",
  "properties": {
    "iso:country":"US",
    "sg:address":"8015 Pendleton Pike",
    "sg:city":"Indianapolis",
    "sg:classifiers":[
        {
            "category":"Professional",
            "subcategory":"Accounting & Tax Preparation",
            "type":"Services"
        }
    ],
    "sg:phone":"+1 317 899 1464",
    "sg:postcode":"46226",
    "sg:province":"IN",
    "sg:tags":[
        "return",
        "filing"
    ],
    "wof:name":"Jackson Hewitt Tax Svc",
    "wof:placetype":"venue"
},
  "geometry": {"coordinates":[-86.02520800000001,39.837154],"type":"Point"}
}