{
  "type": "Feature",
  "properties": {
    "iso:country":"US",
    "sg:address":"680 N 36th St",
    "sg:city":"Lafayette",
    "sg:classifiers":[
        {
            "category":"Social Services",
            "type":"Services"
        }
    ],
    "sg:phone":"+1 765 497 1115",
    "sg:postcode":"47905",
    "sg:province":"IN",
    "sg:tags":[
        "counselor",
        "marriage",
        "family"
    ],
    "wof:name":"Arlington Counseling",
    "wof:placetype":"venue"
},
  "geometry": {"coordinates":[-86.85092,40.424097],"type":"Point"}
}