{
  "type": "Feature",
  "properties": {
    "iso:country":"US",
    "sg:address":"510 N Main St",
    "sg:city":"Columbia City",
    "sg:classifiers":[
        {
            "category":"Real Estate",
            "subcategory":"Real Estate Agent",
            "type":"Services"
        }
    ],
    "sg:phone":"+1 260 244 1990",
    "sg:postcode":"46725",
    "sg:province":"IN",
    "wof:name":"Hoosier Real Estate Inc",
    "wof:placetype":"venue"
},
  "geometry": {"coordinates":[-85.486616,41.165806],"type":"Point"}
}