{
  "type": "Feature",
  "properties": {
    "iso:country":"US",
    "sg:address":"664 Main St",
    "sg:city":"Brookville",
    "sg:classifiers":[
        {
            "category":"Food & Beverages",
            "subcategory":"Liquor & Beverages",
            "type":"Retail Goods"
        }
    ],
    "sg:phone":"+1 765 647 6682",
    "sg:postcode":"47012",
    "sg:province":"IN",
    "wof:name":"Tebbe Package Liquor Store",
    "wof:placetype":"venue"
},
  "geometry": {"coordinates":[-85.012841,39.421188],"type":"Point"}
}