{
  "type": "Feature",
  "properties": {
    "addr:full":"2700 Meier Rd Evansville IN 47720",
    "addr:housenumber":"2700",
    "addr:postcode":"47720",
    "addr:street":"Meier Rd",
    "iso:country":"US",
    "sg:address":"2700 Meier Rd",
    "sg:city":"Evansville",
    "sg:classifiers":[
        {
            "category":"Farming",
            "subcategory":"Farm",
            "type":"Manufacturing & Wholesale Goods"
        }
    ],
    "sg:phone":"+1 812 963 6873",
    "sg:postcode":"47720",
    "sg:province":"IN",
    "sg:tags":[
        "crop",
        "general"
    ],
    "wof:name":"Jeffrey Meyer",
    "wof:placetype":"venue"
},
  "geometry": {"coordinates":[-87.605873,38.049709],"type":"Point"}
}