{
  "type": "Feature",
  "properties": {
    "iso:country":"US",
    "sg:address":"411 1st Ave NW",
    "sg:city":"Carmel",
    "sg:classifiers":[
        {
            "category":"Personal",
            "subcategory":"Day Spa",
            "type":"Services"
        }
    ],
    "sg:phone":"+1 317 819 0011",
    "sg:postcode":"46032",
    "sg:province":"IN",
    "wof:name":"Skin Sense",
    "wof:placetype":"venue"
},
  "geometry": {"coordinates":[-86.128314,39.981864],"type":"Point"}
}