{
  "type": "Feature",
  "properties": {
    "iso:country":"US",
    "sg:address":"224 S Main St",
    "sg:city":"Clinton",
    "sg:classifiers":[
        {
            "category":"Real Estate",
            "subcategory":"Real Estate Services",
            "type":"Services"
        }
    ],
    "sg:phone":"+1 765 832 2119",
    "sg:postcode":"47842",
    "sg:province":"IN",
    "wof:name":"Vermillion County Abstract Co",
    "wof:placetype":"venue"
},
  "geometry": {"coordinates":[-87.398224,39.6591],"type":"Point"}
}