{
  "type": "Feature",
  "properties": {
    "iso:country":"US",
    "sg:address":"210 E 9th St",
    "sg:city":"Auburn",
    "sg:classifiers":[
        {
            "category":"Government",
            "subcategory":"Office",
            "type":"Public Place"
        }
    ],
    "sg:phone":"+1 260 925 0365",
    "sg:postcode":"46706",
    "sg:province":"IN",
    "sg:tags":[
        "govt",
        "city"
    ],
    "sg:website":"www.ci.auburn.in.us",
    "wof:name":"Auburn Electric & Utility",
    "wof:placetype":"venue"
},
  "geometry": {"coordinates":[-85.053386,41.365949],"type":"Point"}
}