{
  "type": "Feature",
  "properties": {
    "iso:country":"US",
    "sg:address":"9535 E 59th St",
    "sg:city":"Indianapolis",
    "sg:classifiers":[
        {
            "category":"Wholesale",
            "subcategory":"Groceries",
            "type":"Manufacturing & Wholesale Goods"
        }
    ],
    "sg:phone":"+1 317 547 9413",
    "sg:postcode":"46216",
    "sg:province":"IN",
    "sg:tags":[
        "food",
        "broker"
    ],
    "wof:name":"Arvin Sales Co",
    "wof:placetype":"venue"
},
  "geometry": {"coordinates":[-85.998544,39.86286],"type":"Point"}
}