{
  "type": "Feature",
  "properties": {
    "iso:country":"US",
    "sg:address":"1415 N Pennsylvania St",
    "sg:city":"Indianapolis",
    "sg:classifiers":[
        {
            "category":"Retail",
            "subcategory":"Laundry & Dry Cleaning",
            "type":"Services"
        }
    ],
    "sg:phone":"+1 317 897 9928",
    "sg:postcode":"46202",
    "sg:province":"IN",
    "sg:tags":[
        "cleaner",
        "rug",
        "carpet"
    ],
    "wof:name":"Mark Johnson Mr",
    "wof:placetype":"venue"
},
  "geometry": {"coordinates":[-86.155748,39.786103],"type":"Point"}
}