{
  "type": "Feature",
  "properties": {
    "iso:country":"US",
    "sg:address":"103 N Jackson Ave",
    "sg:city":"Fowler",
    "sg:classifiers":[
        {
            "category":"Government",
            "subcategory":"Court House",
            "type":"Public Place"
        }
    ],
    "sg:phone":"+1 765 884 1511",
    "sg:postcode":"47944",
    "sg:province":"IN",
    "sg:tags":[
        "county",
        "counsel"
    ],
    "wof:name":"Benton County Attorney",
    "wof:placetype":"venue"
},
  "geometry": {"coordinates":[-87.318355,40.618182],"type":"Point"}
}