{
  "type": "Feature",
  "properties": {
    "iso:country":"US",
    "sg:address":"4231 Vogel Rd",
    "sg:city":"Evansville",
    "sg:classifiers":[
        {
            "category":"Autos & Motor Vehicles",
            "subcategory":"Auto Supplies",
            "type":"Retail Goods"
        }
    ],
    "sg:phone":"+1 812 477 8851",
    "sg:postcode":"47715",
    "sg:province":"IN",
    "sg:tags":[
        "automobile",
        "parts"
    ],
    "wof:name":"Automotive Wholesalers Inc",
    "wof:placetype":"venue"
},
  "geometry": {"coordinates":[-87.497787,37.987597],"type":"Point"}
}