{
  "type": "Feature",
  "properties": {
    "iso:country":"US",
    "sg:address":"1520 Spy Run Ave",
    "sg:city":"Fort Wayne",
    "sg:classifiers":[
        {
            "category":"Banks & Credit Unions",
            "subcategory":"Bank",
            "type":"Services"
        }
    ],
    "sg:phone":"+1 260 425 2324",
    "sg:postcode":"46805",
    "sg:province":"IN",
    "sg:tags":[
        "federal"
    ],
    "wof:name":"Power One Federal Credit Union",
    "wof:placetype":"venue"
},
  "geometry": {"coordinates":[-85.13459899999999,41.087846],"type":"Point"}
}