{
  "type": "Feature",
  "properties": {
    "iso:country":"US",
    "sg:address":"409 S Shelby St",
    "sg:city":"Hobart",
    "sg:classifiers":[
        {
            "category":"Building & Trades",
            "subcategory":"Plumbing",
            "type":"Services"
        }
    ],
    "sg:phone":"+1 219 942 7700",
    "sg:postcode":"46342",
    "sg:province":"IN",
    "sg:tags":[
        "conditioning",
        "air",
        "system",
        "contractor"
    ],
    "sg:website":"www.areasheetmetal.com",
    "wof:name":"Area Sheet Metal Inc",
    "wof:placetype":"venue"
},
  "geometry": {"coordinates":[-87.23545,41.531468],"type":"Point"}
}