{
  "type": "Feature",
  "properties": {
    "iso:country":"US",
    "sg:address":"5502 E 36th St",
    "sg:city":"Indianapolis",
    "sg:classifiers":[
        {
            "category":"Organizations",
            "subcategory":"Religious Organization",
            "type":"Services"
        }
    ],
    "sg:phone":"+1 317 549 9061",
    "sg:postcode":"46218",
    "sg:province":"IN",
    "sg:tags":[
        "clergy"
    ],
    "wof:name":"Williams, Sterling",
    "wof:placetype":"venue"
},
  "geometry": {"coordinates":[-86.07403100000001,39.821999],"type":"Point"}
}