{
  "type": "Feature",
  "properties": {
    "iso:country":"US",
    "sg:address":"801 E 2nd St",
    "sg:city":"Reynolds",
    "sg:classifiers":[
        {
            "category":"Wholesale",
            "subcategory":"Toys & Hobbies",
            "type":"Manufacturing & Wholesale Goods"
        }
    ],
    "sg:phone":"+1 219 984 9949",
    "sg:postcode":"47980",
    "sg:province":"IN",
    "sg:tags":[
        "wholesaler"
    ],
    "wof:name":"Popcorn Stand",
    "wof:placetype":"venue"
},
  "geometry": {"coordinates":[-86.86768,40.749349],"type":"Point"}
}