{
  "type": "Feature",
  "properties": {
    "iso:country":"US",
    "sg:address":"1600 S Lake Park Ave",
    "sg:city":"Hobart",
    "sg:classifiers":[
        {
            "category":"Health Services",
            "subcategory":"Doctor",
            "type":"Services"
        }
    ],
    "sg:phone":"+1 219 942 6501",
    "sg:postcode":"46342",
    "sg:province":"IN",
    "sg:tags":[
        "physician",
        "surgeon"
    ],
    "wof:name":"Spinal & Neuro Surgical Inst",
    "wof:placetype":"venue"
},
  "geometry": {"coordinates":[-87.259033,41.515652],"type":"Point"}
}