{
  "type": "Feature",
  "properties": {
    "iso:country":"US",
    "sg:address":"421 E State St",
    "sg:city":"Pendleton",
    "sg:classifiers":[
        {
            "category":"Government",
            "subcategory":"Office",
            "type":"Public Place"
        }
    ],
    "sg:phone":"+1 765 778 3784",
    "sg:postcode":"46064",
    "sg:province":"IN",
    "sg:tags":[
        "village"
    ],
    "wof:name":"Fall Creek Township Trustee",
    "wof:placetype":"venue"
},
  "geometry": {"coordinates":[-85.740544,40.001622],"type":"Point"}
}