{
  "type": "Feature",
  "properties": {
    "addr:full":"1321 Edgecombe Ave Indianapolis IN 46227",
    "addr:housenumber":"1321",
    "addr:postcode":"46227",
    "addr:street":"Edgecombe Ave",
    "iso:country":"US",
    "sg:address":"1321 Edgecombe Ave",
    "sg:city":"Indianapolis",
    "sg:classifiers":[
        {
            "category":"Shopping",
            "type":"Retail Goods"
        }
    ],
    "sg:phone":"+1 317 783 9755",
    "sg:postcode":"46227",
    "sg:province":"IN",
    "sg:tags":[
        "equipment",
        "telephone",
        "supply"
    ],
    "wof:name":"Communication Prospects Inc",
    "wof:placetype":"venue"
},
  "geometry": {"coordinates":[-86.13486899999999,39.71467],"type":"Point"}
}