{
  "type": "Feature",
  "properties": {
    "iso:country":"US",
    "sg:address":"9750 Lantern Rd",
    "sg:city":"Fishers",
    "sg:classifiers":[
        {
            "category":"Health Services",
            "subcategory":"Doctor",
            "type":"Services"
        }
    ],
    "sg:phone":"+1 317 577 9288",
    "sg:postcode":"46037",
    "sg:province":"IN",
    "sg:tags":[
        "dentist"
    ],
    "wof:name":"Ripley Orthodontics",
    "wof:placetype":"venue"
},
  "geometry": {"coordinates":[-86.013711,39.928191],"type":"Point"}
}