{
  "type": "Feature",
  "properties": {
    "iso:country":"US",
    "sg:address":"1281 S Boatman Rd",
    "sg:city":"Scottsburg",
    "sg:classifiers":[
        {
            "category":"Building & Trades",
            "subcategory":"Construction",
            "type":"Services"
        }
    ],
    "sg:phone":"+1 812 752 4075",
    "sg:postcode":"47170",
    "sg:province":"IN",
    "sg:tags":[
        "house"
    ],
    "wof:name":"Souders Construction",
    "wof:placetype":"venue"
},
  "geometry": {"coordinates":[-85.812968,38.673822],"type":"Point"}
}