{
  "type": "Feature",
  "properties": {
    "addr:full":"515 E Co Rd 350 N Cayuga IN 47928",
    "addr:housenumber":"515;350",
    "addr:postcode":"47928",
    "addr:street":"E Co Rd;N",
    "iso:country":"US",
    "sg:address":"515 E Co Rd 350 N",
    "sg:city":"Cayuga",
    "sg:classifiers":[
        {
            "category":"Farming",
            "subcategory":"Farm",
            "type":"Manufacturing & Wholesale Goods"
        }
    ],
    "sg:phone":"+1 765 492 3952",
    "sg:postcode":"47928",
    "sg:province":"IN",
    "wof:name":"Keith Little Farms",
    "wof:placetype":"venue"
},
  "geometry": {"coordinates":[-87.460359,39.933725],"type":"Point"}
}