{
  "type": "Feature",
  "properties": {
    "iso:country":"US",
    "sg:address":"5872 S 450 E",
    "sg:city":"Rushville",
    "sg:phone":"+1 765 932 5195",
    "sg:postcode":"46173",
    "sg:province":"IN",
    "sg:tags":[
        "farm",
        "corn",
        "soybean"
    ],
    "wof:name":"Thomas Bedel",
    "wof:placetype":"venue"
},
  "geometry": {"coordinates":[-85.357951,39.52723],"type":"Point"}
}