{
  "type": "Feature",
  "properties": {
    "iso:country":"US",
    "sg:address":"1531 Arcadia Ave",
    "sg:city":"South Bend",
    "sg:classifiers":[
        {
            "category":"Shopping",
            "subcategory":"Hobbies, Toys, & Games",
            "type":"Retail Goods"
        }
    ],
    "sg:phone":"+1 574 287 3797",
    "sg:postcode":"46635",
    "sg:province":"IN",
    "wof:name":"Disc Toys",
    "wof:placetype":"venue"
},
  "geometry": {"coordinates":[-86.20995000000001,41.696585],"type":"Point"}
}