{
  "type": "Feature",
  "properties": {
    "iso:country":"US",
    "sg:address":"4497 W Craig Dr",
    "sg:city":"Bloomington",
    "sg:classifiers":[
        {
            "category":"Professional",
            "subcategory":"Research",
            "type":"Services"
        }
    ],
    "sg:phone":"+1 812 876 9324",
    "sg:postcode":"47404",
    "sg:province":"IN",
    "sg:tags":[
        "scientific"
    ],
    "wof:name":"Doug Knapp",
    "wof:placetype":"venue"
},
  "geometry": {"coordinates":[-86.592229,39.209597],"type":"Point"}
}