{
  "type": "Feature",
  "properties": {
    "iso:country":"US",
    "sg:address":"7950 Pendleton Pike",
    "sg:city":"Indianapolis",
    "sg:classifiers":[
        {
            "category":"Personal",
            "subcategory":"Day Spa",
            "type":"Services"
        }
    ],
    "sg:phone":"+1 800 776 4711",
    "sg:postcode":"46226",
    "sg:province":"IN",
    "sg:tags":[
        "hot",
        "tub"
    ],
    "wof:name":"Carefree Spas",
    "wof:placetype":"venue"
},
  "geometry": {"coordinates":[-86.028412,39.835739],"type":"Point"}
}