{
  "type": "Feature",
  "properties": {
    "iso:country":"US",
    "sg:address":"509 S Poplar St",
    "sg:city":"Lagrange",
    "sg:classifiers":[
        {
            "category":"Manufacturing",
            "subcategory":"Apparel",
            "type":"Manufacturing & Wholesale Goods"
        }
    ],
    "sg:phone":"+1 260 463 2191",
    "sg:postcode":"46761",
    "sg:province":"IN",
    "sg:tags":[
        "awning",
        "canopy"
    ],
    "sg:website":"www.dometicusa.com",
    "wof:name":"Dometic Corportation",
    "wof:placetype":"venue"
},
  "geometry": {"coordinates":[-85.416472,41.64052],"type":"Point"}
}