{
  "type": "Feature",
  "properties": {
    "iso:country":"US",
    "sg:address":"5417 E 300 N",
    "sg:city":"Franklin",
    "sg:classifiers":[
        {
            "category":"Farming",
            "subcategory":"Farm",
            "type":"Manufacturing & Wholesale Goods"
        }
    ],
    "sg:phone":"+1 317 736 6960",
    "sg:postcode":"46131",
    "sg:province":"IN",
    "sg:tags":[
        "crop",
        "general"
    ],
    "wof:name":"Chris & Larry Campbell",
    "wof:placetype":"venue"
},
  "geometry": {"coordinates":[-86.003395,39.521812],"type":"Point"}
}