{
  "type": "Feature",
  "properties": {
    "addr:full":"7211 N Keystone Ave Indianapolis IN 46240",
    "addr:housenumber":"7211",
    "addr:postcode":"46240",
    "addr:street":"N Keystone Ave",
    "iso:country":"US",
    "sg:address":"7211 N Keystone Ave",
    "sg:city":"Indianapolis",
    "sg:classifiers":[
        {
            "category":"Wholesale",
            "subcategory":"Sporting Goods",
            "type":"Manufacturing & Wholesale Goods"
        }
    ],
    "sg:phone":"+1 317 257 7911",
    "sg:postcode":"46240",
    "sg:province":"IN",
    "sg:tags":[
        "equipment",
        "pool",
        "swimming"
    ],
    "wof:name":"Leslie's Swimming Pool Supply",
    "wof:placetype":"venue"
},
  "geometry": {"coordinates":[-86.122,39.885254],"type":"Point"}
}