{
  "type": "Feature",
  "properties": {
    "addr:full":"210 S Main St Kouts IN 46347",
    "addr:housenumber":"210",
    "addr:postcode":"46347",
    "addr:street":"S Main St",
    "iso:country":"US",
    "sg:address":"210 S Main St",
    "sg:city":"Kouts",
    "sg:classifiers":[
        {
            "category":"Government",
            "subcategory":"Police Station",
            "type":"Public Place"
        }
    ],
    "sg:phone":"+1 219 766 2332",
    "sg:postcode":"46347",
    "sg:province":"IN",
    "sg:tags":[
        "department"
    ],
    "wof:name":"Kouts Village Police",
    "wof:placetype":"venue"
},
  "geometry": {"coordinates":[-87.02592300000001,41.317386],"type":"Point"}
}