{
  "type": "Feature",
  "properties": {
    "addr:full":"356 Lakeview Dr Noblesville IN 46060",
    "addr:housenumber":"356",
    "addr:postcode":"46060",
    "addr:street":"Lakeview Dr",
    "iso:country":"US",
    "sg:address":"356 Lakeview Dr",
    "sg:city":"Noblesville",
    "sg:classifiers":[
        {
            "category":"Building & Trades",
            "subcategory":"Locksmith",
            "type":"Services"
        }
    ],
    "sg:phone":"+1 317 214 6367",
    "sg:postcode":"46060",
    "sg:province":"IN",
    "sg:tags":[
        "key"
    ],
    "wof:name":"Locksmith",
    "wof:placetype":"venue"
},
  "geometry": {"coordinates":[-86.023901,40.052776],"type":"Point"}
}