{
  "type": "Feature",
  "properties": {
    "iso:country":"US",
    "sg:address":"713 US Hwy 66 E",
    "sg:city":"Tell City",
    "sg:classifiers":[
        {
            "category":"Professional",
            "subcategory":"Business Services",
            "type":"Services"
        }
    ],
    "sg:phone":"+1 812 547 3814",
    "sg:postcode":"47586",
    "sg:province":"IN",
    "sg:tags":[
        "auctioneer"
    ],
    "wof:name":"Dixon & Dixon Auctioneers",
    "wof:placetype":"venue"
},
  "geometry": {"coordinates":[-86.764615,37.951878],"type":"Point"}
}