{
  "type": "Feature",
  "properties": {
    "iso:country":"US",
    "sg:address":"760 US Hwy 35",
    "sg:city":"Winamac",
    "sg:classifiers":[
        {
            "category":"Professional",
            "subcategory":"Computer Services",
            "type":"Services"
        }
    ],
    "sg:phone":"+1 574 946 6001",
    "sg:postcode":"46996",
    "sg:province":"IN",
    "sg:tags":[
        "repair"
    ],
    "wof:name":"Degroot Technology Svc",
    "wof:placetype":"venue"
},
  "geometry": {"coordinates":[-86.605261,41.058063],"type":"Point"}
}