{
  "type": "Feature",
  "properties": {
    "iso:country":"US",
    "sg:address":"505 Fulton St",
    "sg:city":"Indianapolis",
    "sg:classifiers":[
        {
            "category":"Freight",
            "type":"Transportation"
        }
    ],
    "sg:phone":"+1 317 635 2126",
    "sg:postcode":"46202",
    "sg:province":"IN",
    "sg:tags":[
        "commercial",
        "storage"
    ],
    "wof:name":"Storage USA",
    "wof:placetype":"venue"
},
  "geometry": {"coordinates":[-86.144007,39.775149],"type":"Point"}
}