{
  "type": "Feature",
  "properties": {
    "iso:country":"US",
    "sg:address":"420 W Washington St",
    "sg:city":"Muncie",
    "sg:classifiers":[
        {
            "category":"Professional",
            "subcategory":"Credit Reporting & Collection",
            "type":"Services"
        }
    ],
    "sg:phone":"+1 765 289 2114",
    "sg:postcode":"47305",
    "sg:province":"IN",
    "sg:tags":[
        "agency"
    ],
    "wof:name":"Atlas Collection Inc",
    "wof:placetype":"venue"
},
  "geometry": {"coordinates":[-85.390774,40.194701],"type":"Point"}
}