{
  "type": "Feature",
  "properties": {
    "addr:full":"5872 N Mishler Rd Huntington IN 46750",
    "addr:housenumber":"5872",
    "addr:postcode":"46750",
    "addr:street":"N Mishler Rd",
    "iso:country":"US",
    "sg:address":"5872 N Mishler Rd",
    "sg:city":"Huntington",
    "sg:classifiers":[
        {
            "category":"Building & Trades",
            "subcategory":"Construction",
            "type":"Services"
        }
    ],
    "sg:phone":"+1 260 356 3119",
    "sg:postcode":"46750",
    "sg:province":"IN",
    "sg:tags":[
        "excavating",
        "contractor"
    ],
    "wof:name":"Blomeke Excavating Inc",
    "wof:placetype":"venue"
},
  "geometry": {"coordinates":[-85.47909900000001,40.909195],"type":"Point"}
}