{
  "type": "Feature",
  "properties": {
    "iso:country":"US",
    "sg:address":"2621 N 6th St",
    "sg:city":"Vincennes",
    "sg:classifiers":[
        {
            "category":"Personal",
            "type":"Services"
        }
    ],
    "sg:phone":"+1 812 886 9740",
    "sg:postcode":"47591",
    "sg:province":"IN",
    "sg:tags":[
        "control",
        "weight"
    ],
    "wof:name":"L A Weight Loss Center Inc",
    "wof:placetype":"venue"
},
  "geometry": {"coordinates":[-87.506113,38.688737],"type":"Point"}
}