{
  "type": "Feature",
  "properties": {
    "iso:country":"US",
    "sg:address":"817 N Halleck St",
    "sg:city":"Demotte",
    "sg:classifiers":[
        {
            "category":"Personal",
            "type":"Services"
        }
    ],
    "sg:phone":"+1 219 987 2125",
    "sg:postcode":"46310",
    "sg:province":"IN",
    "sg:tags":[
        "therapist",
        "massage"
    ],
    "wof:name":"Golden Touch",
    "wof:placetype":"venue"
},
  "geometry": {"coordinates":[-87.198817,41.21107],"type":"Point"}
}