{
  "type": "Feature",
  "properties": {
    "iso:country":"US",
    "sg:address":"1615 4th Ave",
    "sg:city":"Terre Haute",
    "sg:classifiers":[
        {
            "category":"Shopping",
            "subcategory":"Bicycles & Sporting Goods",
            "type":"Retail Goods"
        }
    ],
    "sg:phone":"+1 812 235 1278",
    "sg:postcode":"47807",
    "sg:province":"IN",
    "sg:tags":[
        "tent"
    ],
    "wof:name":"Wabash Valley Tent Co Inc",
    "wof:placetype":"venue"
},
  "geometry": {"coordinates":[-87.388484,39.48107],"type":"Point"}
}