{
  "type": "Feature",
  "properties": {
    "addr:full":"8628 King George Rd Evansville IN 47725",
    "addr:housenumber":"8628",
    "addr:postcode":"47725",
    "addr:street":"King George Rd",
    "iso:country":"US",
    "sg:address":"8628 King George Rd",
    "sg:city":"Evansville",
    "sg:classifiers":[
        {
            "category":"Professional",
            "subcategory":"Employment Agencies",
            "type":"Services"
        }
    ],
    "sg:phone":"+1 812 867 0369",
    "sg:postcode":"47725",
    "sg:province":"IN",
    "wof:name":"DC Egan & Associates",
    "wof:placetype":"venue"
},
  "geometry": {"coordinates":[-87.53618899999999,38.05681],"type":"Point"}
}