{
  "type": "Feature",
  "properties": {
    "iso:country":"US",
    "sg:address":"416 Park Rd",
    "sg:city":"Tipton",
    "sg:classifiers":[
        {
            "category":"Real Estate",
            "subcategory":"Real Estate Agent",
            "type":"Services"
        }
    ],
    "sg:phone":"+1 765 675 8464",
    "sg:postcode":"46072",
    "sg:province":"IN",
    "wof:name":"Lewis D Harper Real Estate",
    "wof:placetype":"venue"
},
  "geometry": {"coordinates":[-86.03461799999999,40.275924],"type":"Point"}
}