{
  "type": "Feature",
  "properties": {
    "iso:country":"US",
    "sg:address":"900 Oakhill Ave",
    "sg:city":"Plymouth",
    "sg:classifiers":[
        {
            "category":"Government",
            "subcategory":"Office",
            "type":"Public Place"
        }
    ],
    "sg:phone":"+1 574 936 2368",
    "sg:postcode":"46563",
    "sg:province":"IN",
    "sg:tags":[
        "village"
    ],
    "wof:name":"Industrial Pretreatment",
    "wof:placetype":"venue"
},
  "geometry": {"coordinates":[-86.322594,41.331073],"type":"Point"}
}