{
  "type": "Feature",
  "properties": {
    "iso:country":"US",
    "sg:address":"314 E 13th St",
    "sg:city":"Huntingburg",
    "sg:classifiers":[
        {
            "category":"Restaurant",
            "type":"Food & Drink"
        }
    ],
    "sg:phone":"+1 812 683 4220",
    "sg:postcode":"47542",
    "sg:province":"IN",
    "wof:name":"Stop Inn",
    "wof:placetype":"venue"
},
  "geometry": {"coordinates":[-86.958881,38.307284],"type":"Point"}
}