{
  "type": "Feature",
  "properties": {
    "iso:country":"US",
    "sg:address":"735 N 250 W",
    "sg:city":"Flora",
    "sg:classifiers":[
        {
            "category":"Building & Trades",
            "subcategory":"Construction",
            "type":"Services"
        }
    ],
    "sg:phone":"+1 574 967 3886",
    "sg:postcode":"46929",
    "sg:province":"IN",
    "sg:tags":[
        "contractor"
    ],
    "wof:name":"K K Drywall",
    "wof:placetype":"venue"
},
  "geometry": {"coordinates":[-86.57232999999999,40.557139],"type":"Point"}
}