{
  "type": "Feature",
  "properties": {
    "iso:country":"US",
    "sg:address":"719 Tracee Ct",
    "sg:city":"Bloomington",
    "sg:classifiers":[
        {
            "category":"Real Estate",
            "subcategory":"Real Estate Agent",
            "type":"Services"
        }
    ],
    "sg:phone":"+1 812 331 9061",
    "sg:postcode":"47401",
    "sg:province":"IN",
    "wof:name":"Brink One",
    "wof:placetype":"venue"
},
  "geometry": {"coordinates":[-86.522871,39.12276],"type":"Point"}
}