{
  "type": "Feature",
  "properties": {
    "iso:country":"US",
    "sg:address":"13191 Dean Rd",
    "sg:city":"Aurora",
    "sg:phone":"+1 812 926 0837",
    "sg:postcode":"47001",
    "sg:province":"IN",
    "sg:tags":[
        "farm",
        "soybean"
    ],
    "wof:name":"Harry Dean",
    "wof:placetype":"venue"
},
  "geometry": {"coordinates":[-84.991772,39.065007],"type":"Point"}
}