{
  "type": "Feature",
  "properties": {
    "iso:country":"US",
    "sg:address":"314 E Rampart St",
    "sg:city":"Shelbyville",
    "sg:classifiers":[
        {
            "category":"Freight",
            "type":"Transportation"
        }
    ],
    "sg:phone":"+1 317 392 2224",
    "sg:postcode":"46176",
    "sg:province":"IN",
    "sg:tags":[
        "commercial",
        "storage"
    ],
    "wof:name":"Stoaway Self Storage",
    "wof:placetype":"venue"
},
  "geometry": {"coordinates":[-85.770122,39.547508],"type":"Point"}
}