{
  "type": "Feature",
  "properties": {
    "addr:full":"250 Fairview Ln Schererville IN 46375",
    "addr:housenumber":"250",
    "addr:postcode":"46375",
    "addr:street":"Fairview Ln",
    "iso:country":"US",
    "sg:address":"250 Fairview Ln",
    "sg:city":"Schererville",
    "sg:classifiers":[
        {
            "category":"Building & Trades",
            "subcategory":"Construction",
            "type":"Services"
        }
    ],
    "sg:phone":"+1 219 864 1190",
    "sg:postcode":"46375",
    "sg:province":"IN",
    "sg:tags":[
        "plastering",
        "contractor"
    ],
    "wof:name":"Pride View Construction",
    "wof:placetype":"venue"
},
  "geometry": {"coordinates":[-87.44347500000001,41.486259],"type":"Point"}
}