{
  "type": "Feature",
  "properties": {
    "iso:country":"US",
    "sg:address":"310 Huggins Dr",
    "sg:city":"Hartford City",
    "sg:classifiers":[
        {
            "category":"Banks & Credit Unions",
            "subcategory":"Bank",
            "type":"Services"
        }
    ],
    "sg:phone":"+1 765 348 1215",
    "sg:postcode":"47348",
    "sg:province":"IN",
    "wof:name":"Marion School Employees Fed CU",
    "wof:placetype":"venue"
},
  "geometry": {"coordinates":[-85.371604,40.470789],"type":"Point"}
}