{
  "type": "Feature",
  "properties": {
    "iso:country":"US",
    "sg:address":"431 Dewey St",
    "sg:city":"Monticello",
    "sg:classifiers":[
        {
            "category":"Wholesale",
            "subcategory":"Machinery & Supplies",
            "type":"Manufacturing & Wholesale Goods"
        }
    ],
    "sg:phone":"+1 574 583 7185",
    "sg:postcode":"47960",
    "sg:province":"IN",
    "sg:tags":[
        "farm",
        "equipment"
    ],
    "wof:name":"Howard & Sons Inc",
    "wof:placetype":"venue"
},
  "geometry": {"coordinates":[-86.765501,40.748582],"type":"Point"}
}