{
  "type": "Feature",
  "properties": {
    "iso:country":"US",
    "sg:address":"417 S 14th St",
    "sg:city":"New Castle",
    "sg:classifiers":[
        {
            "category":"Retail",
            "subcategory":"Portrait Studio",
            "type":"Services"
        }
    ],
    "sg:phone":"+1 765 521 3686",
    "sg:postcode":"47362",
    "sg:province":"IN",
    "sg:tags":[
        "photographer"
    ],
    "sg:website":"www.mckownstudio.com",
    "wof:name":"Mc Kown Studio & Galleries",
    "wof:placetype":"venue"
},
  "geometry": {"coordinates":[-85.368966,39.928692],"type":"Point"}
}