{
  "type": "Feature",
  "properties": {
    "iso:country":"US",
    "sg:address":"3567 W 100 N",
    "sg:city":"Warsaw",
    "sg:classifiers":[
        {
            "category":"Building & Trades",
            "subcategory":"Construction",
            "type":"Services"
        }
    ],
    "sg:phone":"+1 574 267 3570",
    "sg:postcode":"46580",
    "sg:province":"IN",
    "sg:tags":[
        "excavating",
        "contractor"
    ],
    "wof:name":"G & G Hauling & Excavating",
    "wof:placetype":"venue"
},
  "geometry": {"coordinates":[-85.912173,41.245672],"type":"Point"}
}