{
  "type": "Feature",
  "properties": {
    "iso:country":"US",
    "sg:address":"208 W Court Ave",
    "sg:city":"Jeffersonville",
    "sg:classifiers":[
        {
            "category":"Manufacturing",
            "subcategory":"Printing",
            "type":"Manufacturing & Wholesale Goods"
        }
    ],
    "sg:phone":"+1 812 288 6347",
    "sg:postcode":"47130",
    "sg:province":"IN",
    "sg:tags":[
        "commercial"
    ],
    "wof:name":"B & J Printing Svc",
    "wof:placetype":"venue"
},
  "geometry": {"coordinates":[-85.744393,38.27333],"type":"Point"}
}