{
  "type": "Feature",
  "properties": {
    "iso:country":"US",
    "sg:address":"709 Acadia Rd",
    "sg:city":"Valparaiso",
    "sg:classifiers":[
        {
            "category":"Building & Trades",
            "subcategory":"Construction",
            "type":"Services"
        }
    ],
    "sg:phone":"+1 219 759 3215",
    "sg:postcode":"46385",
    "sg:province":"IN",
    "sg:tags":[
        "sewer",
        "contractor"
    ],
    "wof:name":"South Haven Sewer Works",
    "wof:placetype":"venue"
},
  "geometry": {"coordinates":[-87.125303,41.537772],"type":"Point"}
}