{
  "type": "Feature",
  "properties": {
    "iso:country":"US",
    "sg:address":"507 E College Ave",
    "sg:city":"Kokomo",
    "sg:classifiers":[
        {
            "category":"Professional",
            "subcategory":"Accounting & Tax Preparation",
            "type":"Services"
        }
    ],
    "sg:phone":"+1 765 868 9268",
    "sg:postcode":"46962",
    "sg:province":"IN",
    "sg:tags":[
        "return",
        "filing"
    ],
    "wof:name":"Jackson Hewitt Tax Svc",
    "wof:placetype":"venue"
},
  "geometry": {"coordinates":[-85.764332,41.010074],"type":"Point"}
}