{
  "type": "Feature",
  "properties": {
    "iso:country":"US",
    "sg:address":"5300 Hanna St",
    "sg:city":"Fort Wayne",
    "sg:classifiers":[
        {
            "category":"Manufacturing",
            "subcategory":"Metals",
            "type":"Manufacturing & Wholesale Goods"
        }
    ],
    "sg:phone":"+1 260 744 4339",
    "sg:postcode":"46806",
    "sg:province":"IN",
    "sg:tags":[
        "plating"
    ],
    "wof:name":"Reckon Plating Inc",
    "wof:placetype":"venue"
},
  "geometry": {"coordinates":[-85.127521,41.034463],"type":"Point"}
}