{
  "type": "Feature",
  "properties": {
    "iso:country":"US",
    "sg:address":"607 Union St",
    "sg:city":"Valparaiso",
    "sg:classifiers":[
        {
            "category":"Organizations",
            "subcategory":"Community Association",
            "type":"Services"
        }
    ],
    "sg:phone":"+1 219 462 8692",
    "sg:postcode":"46383",
    "sg:province":"IN",
    "sg:tags":[
        "sorority",
        "fraternity"
    ],
    "wof:name":"Phi Sigma Kappa",
    "wof:placetype":"venue"
},
  "geometry": {"coordinates":[-87.052554,41.463693],"type":"Point"}
}