{
  "type": "Feature",
  "properties": {
    "iso:country":"US",
    "sg:address":"4130 Walcott St",
    "sg:city":"Evansville",
    "sg:classifiers":[
        {
            "category":"Real Estate",
            "subcategory":"Real Estate Agent",
            "type":"Services"
        }
    ],
    "sg:phone":"+1 812 422 3742",
    "sg:postcode":"47712",
    "sg:province":"IN",
    "wof:name":"B & T Enterprises",
    "wof:placetype":"venue"
},
  "geometry": {"coordinates":[-87.625497,37.983829],"type":"Point"}
}