{
  "type": "Feature",
  "properties": {
    "iso:country":"US",
    "sg:address":"1960 S Walnut St",
    "sg:city":"Bloomington",
    "sg:classifiers":[
        {
            "category":"Shopping",
            "subcategory":"Gifts & Souvenirs",
            "type":"Retail Goods"
        }
    ],
    "sg:phone":"+1 812 333 2802",
    "sg:postcode":"47401",
    "sg:province":"IN",
    "sg:tags":[
        "shop"
    ],
    "wof:name":"Home Sweet Home",
    "wof:placetype":"venue"
},
  "geometry": {"coordinates":[-86.531221,39.141906],"type":"Point"}
}