{
  "type": "Feature",
  "properties": {
    "addr:full":"420 N 7th St Terre Haute IN 47807",
    "addr:housenumber":"420",
    "addr:postcode":"47807",
    "addr:street":"N 7Th St",
    "iso:country":"US",
    "sg:address":"420 N 7th St",
    "sg:city":"Terre Haute",
    "sg:classifiers":[
        {
            "category":"Social Services",
            "type":"Services"
        }
    ],
    "sg:phone":"+1 812 232 8232",
    "sg:postcode":"47807",
    "sg:province":"IN",
    "sg:tags":[
        "organization",
        "welfare"
    ],
    "wof:name":"Zorah Shrine Temple Aaonms",
    "wof:placetype":"venue"
},
  "geometry": {"coordinates":[-87.40705800000001,39.470518],"type":"Point"}
}