{
  "type": "Feature",
  "properties": {
    "iso:country":"US",
    "sg:address":"602 Erie Ave",
    "sg:city":"Logansport",
    "sg:classifiers":[
        {
            "category":"Communications",
            "subcategory":"Film & Video Production",
            "type":"Services"
        }
    ],
    "sg:phone":"+1 574 722 3237",
    "sg:postcode":"46947",
    "sg:province":"IN",
    "sg:tags":[
        "taping"
    ],
    "wof:name":"Magichouse Productions Inc",
    "wof:placetype":"venue"
},
  "geometry": {"coordinates":[-86.362593,40.752626],"type":"Point"}
}