{
  "type": "Feature",
  "properties": {
    "iso:country":"US",
    "sg:address":"3301 Magnum Dr",
    "sg:city":"Elkhart",
    "sg:classifiers":[
        {
            "category":"Retail",
            "subcategory":"Auto Repair",
            "type":"Services"
        }
    ],
    "sg:phone":"+1 574 293 8787",
    "sg:postcode":"46516",
    "sg:province":"IN",
    "sg:tags":[
        "truck"
    ],
    "wof:name":"Miles Truck Svc",
    "wof:placetype":"venue"
},
  "geometry": {"coordinates":[-85.91521,41.677522],"type":"Point"}
}