{
  "type": "Feature",
  "properties": {
    "addr:full":"5720 Oak Hill Rd Evansville IN 47711",
    "addr:housenumber":"5720",
    "addr:postcode":"47711",
    "addr:street":"Oak Hill Rd",
    "iso:country":"US",
    "sg:address":"5720 Oak Hill Rd",
    "sg:city":"Evansville",
    "sg:classifiers":[
        {
            "category":"Organizations",
            "subcategory":"Religious Organization",
            "type":"Services"
        }
    ],
    "sg:phone":"+1 812 402 4954",
    "sg:postcode":"47711",
    "sg:province":"IN",
    "sg:tags":[
        "church"
    ],
    "wof:name":"Northwoods Church",
    "wof:placetype":"venue"
},
  "geometry": {"coordinates":[-87.51010100000001,38.032159],"type":"Point"}
}