{
  "type": "Feature",
  "properties": {
    "addr:full":"9216 N Co Rd 700 E Seymour IN 47274",
    "addr:housenumber":"9216;700 e",
    "addr:postcode":"47274",
    "addr:street":"N Co Rd",
    "iso:country":"US",
    "sg:address":"9216 N Co Rd 700 E",
    "sg:city":"Seymour",
    "sg:classifiers":[
        {
            "category":"Shopping",
            "subcategory":"Hobbies, Toys, & Games",
            "type":"Retail Goods"
        }
    ],
    "sg:phone":"+1 812 522 6319",
    "sg:postcode":"47274",
    "sg:province":"IN",
    "wof:name":"Wheeler Drywall",
    "wof:placetype":"venue"
},
  "geometry": {"coordinates":[-85.90869000000001,39.013917],"type":"Point"}
}