{
  "type": "Feature",
  "properties": {
    "iso:country":"US",
    "sg:address":"2213 Duke St",
    "sg:city":"Indianapolis",
    "sg:classifiers":[
        {
            "category":"Manufacturing",
            "subcategory":"Tools & Machinery",
            "type":"Manufacturing & Wholesale Goods"
        }
    ],
    "sg:phone":"+1 317 547 6127",
    "sg:postcode":"46205",
    "sg:province":"IN",
    "sg:tags":[
        "machine"
    ],
    "wof:name":"Tascon Corp",
    "wof:placetype":"venue"
},
  "geometry": {"coordinates":[-86.121995,39.837397],"type":"Point"}
}