{
  "type": "Feature",
  "properties": {
    "iso:country":"US",
    "sg:address":"3922 W 21st Ave",
    "sg:city":"Gary",
    "sg:classifiers":[
        {
            "category":"Social Services",
            "subcategory":"Child Care",
            "type":"Services"
        }
    ],
    "sg:phone":"+1 219 977 8089",
    "sg:postcode":"46404",
    "sg:province":"IN",
    "wof:name":"ABC Children's Playhouse",
    "wof:placetype":"venue"
},
  "geometry": {"coordinates":[-87.386096,41.580735],"type":"Point"}
}