{
  "type": "Feature",
  "properties": {
    "addr:full":"6144 Co Rd 64 St Joe IN 46785",
    "addr:housenumber":"6144;64",
    "addr:postcode":"46785",
    "addr:street":"Co Rd;St Joe In",
    "iso:country":"US",
    "sg:address":"6144 Co Rd 64",
    "sg:city":"St Joe",
    "sg:classifiers":[
        {
            "category":"Travel",
            "subcategory":"Campground",
            "type":"Entertainment"
        }
    ],
    "sg:phone":"+1 260 337 5736",
    "sg:postcode":"46785",
    "sg:province":"IN",
    "wof:name":"R & R Elk Ranch & Campground",
    "wof:placetype":"venue"
},
  "geometry": {"coordinates":[-84.887232,41.298141],"type":"Point"}
}