{
  "type": "Feature",
  "properties": {
    "iso:country":"US",
    "sg:address":"10476 E Gibbs Ave",
    "sg:city":"Rosedale",
    "sg:classifiers":[
        {
            "category":"Real Estate",
            "subcategory":"Real Estate Operator",
            "type":"Services"
        }
    ],
    "sg:phone":"+1 812 877 9427",
    "sg:postcode":"47874",
    "sg:province":"IN",
    "sg:tags":[
        "property",
        "lessor"
    ],
    "wof:name":"Judith Lemmons",
    "wof:placetype":"venue"
},
  "geometry": {"coordinates":[-87.256831,39.582399],"type":"Point"}
}