{
  "type": "Feature",
  "properties": {
    "iso:country":"US",
    "sg:address":"435 W Davis St",
    "sg:city":"Bloomfield",
    "sg:classifiers":[
        {
            "category":"Retail",
            "subcategory":"Auto Repair",
            "type":"Services"
        }
    ],
    "sg:phone":"+1 812 384 8638",
    "sg:postcode":"47424",
    "sg:province":"IN",
    "sg:tags":[
        "painting"
    ],
    "wof:name":"Clayton Painting",
    "wof:placetype":"venue"
},
  "geometry": {"coordinates":[-86.944282,39.023151],"type":"Point"}
}