{
  "type": "Feature",
  "properties": {
    "iso:country":"US",
    "sg:address":"990 Baylor Wissman Rd",
    "sg:city":"Lanesville",
    "sg:classifiers":[
        {
            "category":"Real Estate",
            "subcategory":"Architect",
            "type":"Services"
        }
    ],
    "sg:phone":"+1 812 952 8825",
    "sg:postcode":"47136",
    "sg:province":"IN",
    "wof:name":"Don Baldwin",
    "wof:placetype":"venue"
},
  "geometry": {"coordinates":[-85.955065,38.27678],"type":"Point"}
}