{
  "type": "Feature",
  "properties": {
    "iso:country":"US",
    "sg:address":"4942 Ivy St",
    "sg:city":"East Chicago",
    "sg:classifiers":[
        {
            "category":"Shopping",
            "subcategory":"Clothing, Apparel, & Fashions",
            "type":"Retail Goods"
        }
    ],
    "sg:phone":"+1 219 397 8205",
    "sg:postcode":"46312",
    "sg:province":"IN",
    "wof:name":"Lyvett S Bridal Servic",
    "wof:placetype":"venue"
},
  "geometry": {"coordinates":[-87.45325800000001,41.623549],"type":"Point"}
}