{
  "type": "Feature",
  "properties": {
    "iso:country":"US",
    "sg:address":"1 Washington St",
    "sg:city":"Columbus",
    "sg:classifiers":[
        {
            "category":"Organizations",
            "subcategory":"Community Association",
            "type":"Services"
        }
    ],
    "sg:phone":"+1 812 376 7075",
    "sg:postcode":"47201",
    "sg:province":"IN",
    "sg:tags":[
        "fraternal"
    ],
    "wof:name":"Fraternal Order Of Eagles",
    "wof:placetype":"venue"
},
  "geometry": {"coordinates":[-85.92088,39.199276],"type":"Point"}
}