{
  "type": "Feature",
  "properties": {
    "addr:full":"1575 US Hwy 41 Schererville IN 46375",
    "addr:housenumber":"1575",
    "addr:postcode":"46375",
    "addr:street":"Us Hwy 41",
    "iso:country":"US",
    "sg:address":"1575 US Hwy 41",
    "sg:city":"Schererville",
    "sg:classifiers":[
        {
            "category":"Cinema",
            "subcategory":"Movie Rental",
            "type":"Entertainment"
        }
    ],
    "sg:phone":"+1 219 322 1002",
    "sg:postcode":"46375",
    "sg:province":"IN",
    "sg:tags":[
        "leasing",
        "video",
        "disc",
        "tape"
    ],
    "wof:name":"Blockbuster Video",
    "wof:placetype":"venue"
},
  "geometry": {"coordinates":[-87.470828,41.492768],"type":"Point"}
}