{
  "type": "Feature",
  "properties": {
    "addr:full":"5525 US Hwy 40 Brazil IN 47834",
    "addr:housenumber":"5525",
    "addr:postcode":"47834",
    "addr:street":"Us Hwy 40",
    "iso:country":"US",
    "sg:address":"5525 US Hwy 40",
    "sg:city":"Brazil",
    "sg:classifiers":[
        {
            "category":"Organizations",
            "subcategory":"Religious Organization",
            "type":"Services"
        }
    ],
    "sg:phone":"+1 812 443 1177",
    "sg:postcode":"47834",
    "sg:province":"IN",
    "sg:website":"www.missionteens.com",
    "wof:name":"Mission Teens Inc",
    "wof:placetype":"venue"
},
  "geometry": {"coordinates":[-87.210154,39.503283],"type":"Point"}
}