{
  "type": "Feature",
  "properties": {
    "iso:country":"US",
    "sg:address":"13645 McKinley Hwy",
    "sg:city":"Mishawaka",
    "sg:classifiers":[
        {
            "category":"Retail",
            "subcategory":"Repair Shop",
            "type":"Services"
        }
    ],
    "sg:phone":"+1 574 252 5997",
    "sg:postcode":"46545",
    "sg:province":"IN",
    "sg:tags":[
        "vinyl"
    ],
    "wof:name":"Auto Cometics",
    "wof:placetype":"venue"
},
  "geometry": {"coordinates":[-86.131343,41.680601],"type":"Point"}
}