{
  "type": "Feature",
  "properties": {
    "iso:country":"US",
    "sg:address":"17 S 8th St",
    "sg:city":"Richmond",
    "sg:classifiers":[
        {
            "category":"Shopping",
            "subcategory":"Shoes",
            "type":"Retail Goods"
        }
    ],
    "sg:phone":"+1 765 962 1262",
    "sg:postcode":"47374",
    "sg:province":"IN",
    "wof:name":"Esmond's Shoes",
    "wof:placetype":"venue"
},
  "geometry": {"coordinates":[-84.89148,39.828753],"type":"Point"}
}