{
  "type": "Feature",
  "properties": {
    "iso:country":"US",
    "sg:address":"2525 Sunderland Dr",
    "sg:city":"Martinsville",
    "sg:classifiers":[
        {
            "category":"Utilities",
            "subcategory":"Refuse",
            "type":"Services"
        }
    ],
    "sg:phone":"+1 317 281 4778",
    "sg:postcode":"46151",
    "sg:province":"IN",
    "sg:tags":[
        "system"
    ],
    "wof:name":"Adams Removal & Hauling Inc",
    "wof:placetype":"venue"
},
  "geometry": {"coordinates":[-86.389898,39.464757],"type":"Point"}
}