{
  "type": "Feature",
  "properties": {
    "iso:country":"US",
    "sg:address":"4673 W Richland Plz",
    "sg:city":"Bloomington",
    "sg:classifiers":[
        {
            "category":"Shopping",
            "subcategory":"Pharmacy",
            "type":"Retail Goods"
        }
    ],
    "sg:phone":"+1 812 876 2915",
    "sg:postcode":"47404",
    "sg:province":"IN",
    "wof:name":"CVS Pharmacy",
    "wof:placetype":"venue"
},
  "geometry": {"coordinates":[-86.593863,39.2143],"type":"Point"}
}