{
  "type": "Feature",
  "properties": {
    "addr:full":"391 E 5th St Connersville IN 47331",
    "addr:housenumber":"391",
    "addr:postcode":"47331",
    "addr:street":"E 5Th St",
    "iso:country":"US",
    "sg:address":"391 E 5th St",
    "sg:city":"Connersville",
    "sg:classifiers":[
        {
            "category":"Shopping",
            "subcategory":"Jewelry",
            "type":"Retail Goods"
        }
    ],
    "sg:phone":"+1 765 827 6858",
    "sg:postcode":"47331",
    "sg:province":"IN",
    "sg:tags":[
        "jeweler"
    ],
    "wof:name":"Wulff's Jewelry & Collectables",
    "wof:placetype":"venue"
},
  "geometry": {"coordinates":[-85.135024,39.639888],"type":"Point"}
}