{
  "type": "Feature",
  "properties": {
    "iso:country":"US",
    "sg:address":"14371 Weeping Willow Ct",
    "sg:city":"Carmel",
    "sg:classifiers":[
        {
            "category":"Professional",
            "subcategory":"Management & Consulting",
            "type":"Services"
        }
    ],
    "sg:phone":"+1 317 815 8140",
    "sg:postcode":"46033",
    "sg:province":"IN",
    "sg:tags":[
        "business"
    ],
    "wof:name":"Judith Huntley",
    "wof:placetype":"venue"
},
  "geometry": {"coordinates":[-86.067031,39.994772],"type":"Point"}
}