{
  "type": "Feature",
  "properties": {
    "addr:full":"1221 S US Hwy 33 Wolflake IN 46701",
    "addr:housenumber":"1221",
    "addr:postcode":"46701",
    "addr:street":"S Us Hwy 33 Wolflake",
    "iso:country":"US",
    "sg:address":"1221 S US Hwy 33",
    "sg:city":"Wolflake",
    "sg:classifiers":[
        {
            "category":"Government",
            "subcategory":"Post Office",
            "type":"Public Place"
        }
    ],
    "sg:phone":"+1 260 635 2339",
    "sg:postcode":"46701",
    "sg:province":"IN",
    "wof:name":"US Post Office",
    "wof:placetype":"venue"
},
  "geometry": {"coordinates":[-85.496324,41.335251],"type":"Point"}
}