{
  "type": "Feature",
  "properties": {
    "iso:country":"US",
    "sg:address":"2450 Deelyn Dr",
    "sg:city":"Warsaw",
    "sg:classifiers":[
        {
            "category":"Manufacturing",
            "subcategory":"Metals",
            "type":"Manufacturing & Wholesale Goods"
        }
    ],
    "sg:phone":"+1 574 269 5900",
    "sg:postcode":"46580",
    "sg:province":"IN",
    "sg:tags":[
        "finisher"
    ],
    "wof:name":"Danco Anodizing",
    "wof:placetype":"venue"
},
  "geometry": {"coordinates":[-85.869715,41.268455],"type":"Point"}
}