{
  "type": "Feature",
  "properties": {
    "iso:country":"US",
    "sg:address":"3670 Highland Park Dr",
    "sg:city":"Greenwood",
    "sg:classifiers":[
        {
            "category":"Building & Trades",
            "subcategory":"Construction",
            "type":"Services"
        }
    ],
    "sg:phone":"+1 317 887 2425",
    "sg:postcode":"46143",
    "sg:province":"IN",
    "sg:tags":[
        "home",
        "general",
        "family",
        "contractor"
    ],
    "wof:name":"J Andrew Schoentrup Cnstr",
    "wof:placetype":"venue"
},
  "geometry": {"coordinates":[-86.174663,39.585138],"type":"Point"}
}