{
  "type": "Feature",
  "properties": {
    "iso:country":"US",
    "sg:address":"1518 Port Cove Dr",
    "sg:city":"Chesterton",
    "sg:classifiers":[
        {
            "category":"Building & Trades",
            "subcategory":"Plumbing",
            "type":"Services"
        }
    ],
    "sg:phone":"+1 219 983 1234",
    "sg:postcode":"46304",
    "sg:province":"IN",
    "sg:tags":[
        "contractor"
    ],
    "wof:name":"Ison Plumbing",
    "wof:placetype":"venue"
},
  "geometry": {"coordinates":[-87.09944,41.605287],"type":"Point"}
}