{
  "type": "Feature",
  "properties": {
    "iso:country":"US",
    "sg:address":"1404 W Washington St",
    "sg:city":"Greensburg",
    "sg:classifiers":[
        {
            "category":"Freight",
            "type":"Transportation"
        }
    ],
    "sg:phone":"+1 812 662 0533",
    "sg:postcode":"47240",
    "sg:province":"IN",
    "sg:tags":[
        "trucking"
    ],
    "wof:name":"Rolland Rose Trucking",
    "wof:placetype":"venue"
},
  "geometry": {"coordinates":[-85.501695,39.337575],"type":"Point"}
}