{
  "type": "Feature",
  "properties": {
    "iso:country":"US",
    "sg:address":"2332 Kenilworth Dr",
    "sg:city":"Elkhart",
    "sg:classifiers":[
        {
            "category":"Professional",
            "type":"Services"
        }
    ],
    "sg:phone":"+1 574 264 6171",
    "sg:postcode":"46514",
    "sg:province":"IN",
    "sg:tags":[
        "establishment"
    ],
    "wof:name":"Test Test",
    "wof:placetype":"venue"
},
  "geometry": {"coordinates":[-85.940684,41.709163],"type":"Point"}
}