{
  "type": "Feature",
  "properties": {
    "iso:country":"US",
    "sg:address":"427 E 9th St",
    "sg:city":"Rochester",
    "sg:classifiers":[
        {
            "category":"Personal",
            "subcategory":"Tanning Parlor",
            "type":"Services"
        }
    ],
    "sg:phone":"+1 574 224 2847",
    "sg:postcode":"46975",
    "sg:province":"IN",
    "sg:tags":[
        "salon"
    ],
    "wof:name":"CTHR",
    "wof:placetype":"venue"
},
  "geometry": {"coordinates":[-86.21034,41.064581],"type":"Point"}
}