{
  "type": "Feature",
  "properties": {
    "iso:country":"US",
    "sg:address":"5721 Hollister Dr",
    "sg:city":"Indianapolis",
    "sg:classifiers":[
        {
            "category":"Social Services",
            "subcategory":"Child Care",
            "type":"Services"
        }
    ],
    "sg:phone":"+1 317 293 8186",
    "sg:postcode":"46224",
    "sg:province":"IN",
    "sg:tags":[
        "day"
    ],
    "wof:name":"Bevs Day Care Inc",
    "wof:placetype":"venue"
},
  "geometry": {"coordinates":[-86.261846,39.807503],"type":"Point"}
}