{
  "type": "Feature",
  "properties": {
    "iso:country":"US",
    "sg:address":"434 S California St",
    "sg:city":"Galveston",
    "sg:classifiers":[
        {
            "category":"Food & Beverages",
            "subcategory":"Groceries & Convenience Stores",
            "type":"Retail Goods"
        }
    ],
    "sg:phone":"+1 574 699 0429",
    "sg:postcode":"46932",
    "sg:province":"IN",
    "wof:name":"Gas America",
    "wof:placetype":"venue"
},
  "geometry": {"coordinates":[-86.18947900000001,40.574131],"type":"Point"}
}