{
  "type": "Feature",
  "properties": {
    "iso:country":"US",
    "sg:address":"1308 Elm Park Dr",
    "sg:city":"Mitchell",
    "sg:classifiers":[
        {
            "category":"Real Estate",
            "subcategory":"Real Estate Operator",
            "type":"Services"
        }
    ],
    "sg:phone":"+1 812 849 4855",
    "sg:postcode":"47446",
    "sg:province":"IN",
    "sg:tags":[
        "apartment"
    ],
    "wof:name":"Elm Park Apartments",
    "wof:placetype":"venue"
},
  "geometry": {"coordinates":[-86.479215,38.72704],"type":"Point"}
}