{
  "type": "Feature",
  "properties": {
    "iso:country":"US",
    "sg:address":"12707 Adams Rd",
    "sg:city":"Granger",
    "sg:classifiers":[
        {
            "category":"Autos & Motor Vehicles",
            "subcategory":"Fuel & Gas Station",
            "type":"Retail Goods"
        }
    ],
    "sg:phone":"+1 574 272 2372",
    "sg:postcode":"46530",
    "sg:province":"IN",
    "sg:tags":[
        "oil"
    ],
    "wof:name":"Osborne's Amoco",
    "wof:placetype":"venue"
},
  "geometry": {"coordinates":[-86.116028,41.753611],"type":"Point"}
}