{
  "type": "Feature",
  "properties": {
    "iso:country":"US",
    "sg:address":"10135 E Co Rd 1000 N",
    "sg:city":"Seymour",
    "sg:classifiers":[
        {
            "category":"Wholesale",
            "subcategory":"Petroleum",
            "type":"Manufacturing & Wholesale Goods"
        },
        {
            "category":"Utilities",
            "subcategory":"Natural Gas",
            "type":"Services"
        }
    ],
    "sg:phone":"+1 812 522 4802",
    "sg:postcode":"47274",
    "sg:province":"IN",
    "sg:tags":[
        "transmission",
        "pipe",
        "company",
        "line",
        "facility"
    ],
    "wof:name":"Texas Eastern Transmission LP",
    "wof:placetype":"venue"
},
  "geometry": {"coordinates":[-85.850502,39.026722],"type":"Point"}
}