{
  "type": "Feature",
  "properties": {
    "iso:country":"US",
    "sg:address":"6344 Ferstel Rd",
    "sg:city":"Newburgh",
    "sg:phone":"+1 812 853 0223",
    "sg:postcode":"47630",
    "sg:province":"IN",
    "sg:tags":[
        "farm",
        "soybean"
    ],
    "wof:name":"Ronald Mossberger",
    "wof:placetype":"venue"
},
  "geometry": {"coordinates":[-87.367397,37.947658],"type":"Point"}
}