{
  "type": "Feature",
  "properties": {
    "iso:country":"US",
    "sg:address":"7168 N 450 E",
    "sg:city":"Falmouth",
    "sg:phone":"+1 765 645 5224",
    "sg:postcode":"46127",
    "sg:province":"IN",
    "sg:tags":[
        "farm",
        "corn"
    ],
    "wof:name":"Tim Shanahan",
    "wof:placetype":"venue"
},
  "geometry": {"coordinates":[-85.36519800000001,39.715881],"type":"Point"}
}