{
  "type": "Feature",
  "properties": {
    "iso:country":"US",
    "sg:address":"5117 E 38th St",
    "sg:city":"Indianapolis",
    "sg:classifiers":[
        {
            "category":"Travel",
            "subcategory":"Hotels & Motels",
            "type":"Entertainment"
        }
    ],
    "sg:phone":"+1 317 547 1100",
    "sg:postcode":"46218",
    "sg:province":"IN",
    "wof:name":"Basic Inn",
    "wof:placetype":"venue"
},
  "geometry": {"coordinates":[-86.082225,39.825421],"type":"Point"}
}