{
  "type": "Feature",
  "properties": {
    "iso:country":"US",
    "sg:address":"2717 Broadway St",
    "sg:city":"Fort Wayne",
    "sg:classifiers":[
        {
            "category":"Professional",
            "subcategory":"Art Services",
            "type":"Services"
        }
    ],
    "sg:phone":"+1 260 456 1116",
    "sg:postcode":"46807",
    "sg:province":"IN",
    "sg:tags":[
        "commercial",
        "design"
    ],
    "wof:name":"L A Berry Company",
    "wof:placetype":"venue"
},
  "geometry": {"coordinates":[-85.152136,41.060212],"type":"Point"}
}