{
  "type": "Feature",
  "properties": {
    "iso:country":"US",
    "sg:address":"118 E Melbourne Ave",
    "sg:city":"Logansport",
    "sg:classifiers":[
        {
            "category":"Retail",
            "subcategory":"Auto Repair",
            "type":"Services"
        }
    ],
    "sg:phone":"+1 574 722 1946",
    "sg:postcode":"46947",
    "sg:province":"IN",
    "sg:tags":[
        "body",
        "automobile",
        "painting"
    ],
    "wof:name":"Slusher's Garage & Body Shop",
    "wof:placetype":"venue"
},
  "geometry": {"coordinates":[-86.36833900000001,40.75133],"type":"Point"}
}