{
  "type": "Feature",
  "properties": {
    "iso:country":"US",
    "sg:address":"117 E 5th St",
    "sg:city":"Fowler",
    "sg:classifiers":[
        {
            "category":"Restaurant",
            "type":"Food & Drink"
        }
    ],
    "sg:phone":"+1 765 884 1700",
    "sg:postcode":"47944",
    "sg:province":"IN",
    "wof:name":"Pizza King",
    "wof:placetype":"venue"
},
  "geometry": {"coordinates":[-87.323312,40.617767],"type":"Point"}
}