{
  "type": "Feature",
  "properties": {
    "iso:country":"US",
    "sg:address":"310 W Washington St",
    "sg:city":"Frankfort",
    "sg:classifiers":[
        {
            "category":"Manufacturing",
            "subcategory":"Printing",
            "type":"Manufacturing & Wholesale Goods"
        }
    ],
    "sg:phone":"+1 765 654 7475",
    "sg:postcode":"46041",
    "sg:province":"IN",
    "sg:tags":[
        "lithographic",
        "commercial"
    ],
    "wof:name":"Heritage Lithographics",
    "wof:placetype":"venue"
},
  "geometry": {"coordinates":[-86.514135,40.281687],"type":"Point"}
}