{
  "type": "Feature",
  "properties": {
    "iso:country":"US",
    "sg:address":"111 Growth Pkwy",
    "sg:city":"Angola",
    "sg:classifiers":[
        {
            "category":"Building & Trades",
            "subcategory":"Electrical",
            "type":"Services"
        }
    ],
    "sg:phone":"+1 260 665 8020",
    "sg:postcode":"46703",
    "sg:province":"IN",
    "sg:tags":[
        "electric",
        "contractor"
    ],
    "wof:name":"Clear Lake Elec Inc",
    "wof:placetype":"venue"
},
  "geometry": {"coordinates":[-84.999734,41.665586],"type":"Point"}
}