{
  "type": "Feature",
  "properties": {
    "addr:full":"618 N Wayne St Angola IN 46703",
    "addr:housenumber":"618",
    "addr:postcode":"46703",
    "addr:street":"N Wayne St",
    "iso:country":"US",
    "sg:address":"618 N Wayne St",
    "sg:city":"Angola",
    "sg:classifiers":[
        {
            "category":"Restaurant",
            "type":"Food & Drink"
        }
    ],
    "sg:menulink":"http://www.allmenus.com/in/angola/198840-kfc---kentucky-fried-chicken/menu/",
    "sg:phone":"+1 260 665 9944",
    "sg:postcode":"46703",
    "sg:province":"IN",
    "sg:tags":[
        "american",
        "chicken"
    ],
    "wof:name":"KFC - Kentucky Fried Chicken",
    "wof:placetype":"venue"
},
  "geometry": {"coordinates":[-84.999438,41.640883],"type":"Point"}
}