{
  "type": "Feature",
  "properties": {
    "iso:country":"US",
    "sg:address":"5511 Epworth Rd",
    "sg:city":"Newburgh",
    "sg:classifiers":[
        {
            "category":"Real Estate",
            "subcategory":"Real Estate Agent",
            "type":"Services"
        }
    ],
    "sg:phone":"+1 812 858 0200",
    "sg:postcode":"47630",
    "sg:province":"IN",
    "sg:tags":[
        "appraiser"
    ],
    "wof:name":"Richard Reid Appraisal Co",
    "wof:placetype":"venue"
},
  "geometry": {"coordinates":[-87.441527,37.954296],"type":"Point"}
}