{
  "type": "Feature",
  "properties": {
    "iso:country":"US",
    "sg:address":"3098 S 800 E",
    "sg:city":"Walkerton",
    "sg:classifiers":[
        {
            "category":"Real Estate",
            "subcategory":"Real Estate Agent",
            "type":"Services"
        }
    ],
    "sg:phone":"+1 219 369 9066",
    "sg:postcode":"46574",
    "sg:province":"IN",
    "wof:name":"Fishlake Property Owners Assoc",
    "wof:placetype":"venue"
},
  "geometry": {"coordinates":[-86.54428299999999,41.563346],"type":"Point"}
}