{
  "type": "Feature",
  "properties": {
    "iso:country":"US",
    "sg:address":"100 N Center St",
    "sg:city":"Mishawaka",
    "sg:classifiers":[
        {
            "category":"Real Estate",
            "subcategory":"Real Estate Operator",
            "type":"Services"
        }
    ],
    "sg:phone":"+1 574 256 0616",
    "sg:postcode":"46544",
    "sg:province":"IN",
    "sg:tags":[
        "apartment"
    ],
    "wof:name":"100 Center Hi-Rise Apartments",
    "wof:placetype":"venue"
},
  "geometry": {"coordinates":[-86.18937699999999,41.661591],"type":"Point"}
}