{
  "type": "Feature",
  "properties": {
    "iso:country":"US",
    "sg:address":"3915 E 21st St",
    "sg:city":"Indianapolis",
    "sg:classifiers":[
        {
            "category":"Government",
            "subcategory":"Office",
            "type":"Public Place"
        }
    ],
    "sg:phone":"+1 317 327 2959",
    "sg:postcode":"46218",
    "sg:province":"IN",
    "sg:tags":[
        "general"
    ],
    "wof:name":"Public Works Dept",
    "wof:placetype":"venue"
},
  "geometry": {"coordinates":[-86.09870600000001,39.796044],"type":"Point"}
}