{
  "type": "Feature",
  "properties": {
    "iso:country":"US",
    "sg:address":"10729 N 200 W",
    "sg:city":"North Manchester",
    "sg:classifiers":[
        {
            "category":"Building & Trades",
            "subcategory":"Construction",
            "type":"Services"
        }
    ],
    "sg:phone":"+1 260 982 2208",
    "sg:postcode":"46962",
    "sg:province":"IN",
    "sg:tags":[
        "restoration",
        "cleaning",
        "patio",
        "deck"
    ],
    "wof:name":"Shoemaker & Shoemaker",
    "wof:placetype":"venue"
},
  "geometry": {"coordinates":[-85.833557,40.98988],"type":"Point"}
}