{
  "type": "Feature",
  "properties": {
    "iso:country":"US",
    "sg:address":"3877 State Rd 161 N",
    "sg:city":"Tennyson",
    "sg:classifiers":[
        {
            "category":"Manufacturing",
            "subcategory":"Printing",
            "type":"Manufacturing & Wholesale Goods"
        }
    ],
    "sg:phone":"+1 812 567 4510",
    "sg:postcode":"47637",
    "sg:province":"IN",
    "sg:tags":[
        "printer"
    ],
    "wof:name":"Your Face Our Place Print Shop",
    "wof:placetype":"venue"
},
  "geometry": {"coordinates":[-87.118173,38.086419],"type":"Point"}
}