{
  "type": "Feature",
  "properties": {
    "addr:full":"1134 NW T St Richmond IN 47374",
    "addr:housenumber":"1134",
    "addr:postcode":"47374",
    "addr:street":"Nw T St",
    "iso:country":"US",
    "sg:address":"1134 NW T St",
    "sg:city":"Richmond",
    "sg:classifiers":[
        {
            "category":"Manufacturing",
            "subcategory":"Metals",
            "type":"Manufacturing & Wholesale Goods"
        }
    ],
    "sg:phone":"+1 765 935 3979",
    "sg:postcode":"47374",
    "sg:province":"IN",
    "sg:tags":[
        "die",
        "casting",
        "aluminum"
    ],
    "wof:name":"Custom Die Casting Co",
    "wof:placetype":"venue"
},
  "geometry": {"coordinates":[-84.884834,39.813793],"type":"Point"}
}