{
  "type": "Feature",
  "properties": {
    "iso:country":"US",
    "sg:address":"7703 E 46th St",
    "sg:city":"Indianapolis",
    "sg:classifiers":[
        {
            "category":"Organizations",
            "subcategory":"Religious Organization",
            "type":"Services"
        }
    ],
    "sg:phone":"+1 317 545 2805",
    "sg:postcode":"46226",
    "sg:province":"IN",
    "sg:tags":[
        "church"
    ],
    "wof:name":"Korean Catholic Community Chr",
    "wof:placetype":"venue"
},
  "geometry": {"coordinates":[-86.03286900000001,39.840285],"type":"Point"}
}