{
  "type": "Feature",
  "properties": {
    "iso:country":"US",
    "sg:address":"919 173rd Pl",
    "sg:city":"Hammond",
    "sg:classifiers":[
        {
            "category":"Retail",
            "subcategory":"Animal Services",
            "type":"Services"
        }
    ],
    "sg:phone":"+1 219 808 2777",
    "sg:postcode":"46324",
    "sg:province":"IN",
    "wof:name":"Thunderpups Inc",
    "wof:placetype":"venue"
},
  "geometry": {"coordinates":[-87.506997,41.580178],"type":"Point"}
}