{
  "type": "Feature",
  "properties": {
    "iso:country":"US",
    "sg:address":"1128 W Oakdale Dr",
    "sg:city":"Fort Wayne",
    "sg:classifiers":[
        {
            "category":"Professional",
            "subcategory":"Art Services",
            "type":"Services"
        }
    ],
    "sg:phone":"+1 260 745 0393",
    "sg:postcode":"46807",
    "sg:province":"IN",
    "sg:tags":[
        "commercial",
        "design"
    ],
    "wof:name":"Case Graphics and Designs",
    "wof:placetype":"venue"
},
  "geometry": {"coordinates":[-85.15605100000001,41.052108],"type":"Point"}
}