{
  "type": "Feature",
  "properties": {
    "iso:country":"US",
    "sg:address":"5814 Twickingham Dr",
    "sg:city":"Evansville",
    "sg:classifiers":[
        {
            "category":"Professional",
            "subcategory":"Lawyer & Legal Services",
            "type":"Services"
        }
    ],
    "sg:phone":"+1 812 473 4236",
    "sg:postcode":"47711",
    "sg:province":"IN",
    "sg:tags":[
        "attorney"
    ],
    "wof:name":"R Jeff Dodson",
    "wof:placetype":"venue"
},
  "geometry": {"coordinates":[-87.522723,38.031797],"type":"Point"}
}