{
  "type": "Feature",
  "properties": {
    "iso:country":"US",
    "sg:address":"500 E 86th Ave",
    "sg:city":"Merrillville",
    "sg:classifiers":[
        {
            "category":"Professional",
            "subcategory":"Lawyer & Legal Services",
            "type":"Services"
        }
    ],
    "sg:phone":"+1 219 769 1300",
    "sg:postcode":"46410",
    "sg:province":"IN",
    "sg:tags":[
        "attorney"
    ],
    "wof:name":"Arnold Krevitz",
    "wof:placetype":"venue"
},
  "geometry": {"coordinates":[-87.326617,41.462922],"type":"Point"}
}