{
  "type": "Feature",
  "properties": {
    "iso:country":"US",
    "sg:address":"1793 E Estil Cemetary Rd",
    "sg:city":"Scottsburg",
    "sg:classifiers":[
        {
            "category":"Building & Trades",
            "subcategory":"Construction",
            "type":"Services"
        }
    ],
    "sg:phone":"+1 812 752 4228",
    "sg:postcode":"47170",
    "sg:province":"IN",
    "sg:tags":[
        "masonry",
        "contractor"
    ],
    "wof:name":"Robison & Hauer Masonry Corp",
    "wof:placetype":"venue"
},
  "geometry": {"coordinates":[-85.742697,38.663899],"type":"Point"}
}