{
  "type": "Feature",
  "properties": {
    "iso:country":"US",
    "sg:address":"2745 S Tibbs Ave",
    "sg:city":"Indianapolis",
    "sg:classifiers":[
        {
            "category":"Professional",
            "subcategory":"Business Services",
            "type":"Services"
        }
    ],
    "sg:phone":"+1 317 244 4812",
    "sg:postcode":"46241",
    "sg:province":"IN",
    "sg:tags":[
        "water",
        "treatment"
    ],
    "wof:name":"Poncho's Pools & Supplies Inc",
    "wof:placetype":"venue"
},
  "geometry": {"coordinates":[-86.215729,39.72627],"type":"Point"}
}