{
  "type": "Feature",
  "properties": {
    "iso:country":"US",
    "sg:address":"8550 Naab Rd",
    "sg:city":"Indianapolis",
    "sg:classifiers":[
        {
            "category":"Health Services",
            "subcategory":"Health Practitioner",
            "type":"Services"
        }
    ],
    "sg:phone":"+1 317 338 3364",
    "sg:postcode":"46260",
    "sg:province":"IN",
    "sg:tags":[
        "therapy",
        "physical"
    ],
    "sg:website":"www.stvincent.org",
    "wof:name":"St Vincent Hospitals",
    "wof:placetype":"venue"
},
  "geometry": {"coordinates":[-86.19847300000001,39.911405],"type":"Point"}
}