{
  "type": "Feature",
  "properties": {
    "iso:country":"US",
    "sg:address":"4650 E Southport Rd",
    "sg:city":"Indianapolis",
    "sg:classifiers":[
        {
            "category":"Home & Garden",
            "subcategory":"Furniture",
            "type":"Retail Goods"
        }
    ],
    "sg:phone":"+1 317 787 7464",
    "sg:postcode":"46237",
    "sg:province":"IN",
    "wof:name":"Kittle's Rooms Express",
    "wof:placetype":"venue"
},
  "geometry": {"coordinates":[-86.09409,39.665703],"type":"Point"}
}