{
  "type": "Feature",
  "properties": {
    "iso:country":"US",
    "sg:address":"6901 Crawfordsville Rd",
    "sg:city":"Indianapolis",
    "sg:classifiers":[
        {
            "category":"Museum",
            "subcategory":"Botanical Garden",
            "type":"Entertainment"
        }
    ],
    "sg:phone":"+1 317 297 2271",
    "sg:postcode":"46214",
    "sg:province":"IN",
    "wof:name":"African Adventure Aquarium Svc",
    "wof:placetype":"venue"
},
  "geometry": {"coordinates":[-86.278585,39.802283],"type":"Point"}
}