{
  "type": "Feature",
  "properties": {
    "addr:full":"17 Harding Ave Terre Haute IN 47807",
    "addr:housenumber":"17",
    "addr:postcode":"47807",
    "addr:street":"Harding Ave",
    "iso:country":"US",
    "sg:address":"17 Harding Ave",
    "sg:city":"Terre Haute",
    "sg:classifiers":[
        {
            "category":"Government",
            "subcategory":"Court House",
            "type":"Public Place"
        }
    ],
    "sg:phone":"+1 812 232 0697",
    "sg:postcode":"47807",
    "sg:province":"IN",
    "sg:tags":[
        "city"
    ],
    "wof:name":"Terre Haute Court Judge",
    "wof:placetype":"venue"
},
  "geometry": {"coordinates":[-87.415378,39.463555],"type":"Point"}
}