{
  "type": "Feature",
  "properties": {
    "iso:country":"US",
    "sg:address":"9202 E 33rd St",
    "sg:city":"Indianapolis",
    "sg:classifiers":[
        {
            "category":"Manufacturing",
            "subcategory":"Tools & Machinery",
            "type":"Manufacturing & Wholesale Goods"
        },
        {
            "category":"Wholesale",
            "subcategory":"Electrical",
            "type":"Manufacturing & Wholesale Goods"
        }
    ],
    "sg:phone":"+1 317 895 3612",
    "sg:postcode":"46235",
    "sg:province":"IN",
    "sg:tags":[
        "electric",
        "supply",
        "equipment",
        "supplies-wholesale",
        "manufacturer"
    ],
    "wof:name":"Trilithic Inc.",
    "wof:placetype":"venue"
},
  "geometry": {"coordinates":[-86.006795,39.816449],"type":"Point"}
}