{
  "type": "Feature",
  "properties": {
    "iso:country":"US",
    "sg:address":"10050 Jackson Rd",
    "sg:city":"Osceola",
    "sg:classifiers":[
        {
            "category":"Utilities",
            "subcategory":"Refuse",
            "type":"Services"
        }
    ],
    "sg:phone":"+1 574 522 3809",
    "sg:postcode":"46561",
    "sg:province":"IN",
    "sg:tags":[
        "garbage",
        "collection"
    ],
    "wof:name":"Al's Trash Svc",
    "wof:placetype":"venue"
},
  "geometry": {"coordinates":[-86.07906199999999,41.622796],"type":"Point"}
}