{
  "type": "Feature",
  "properties": {
    "iso:country":"US",
    "sg:address":"9320 Priority Way West Dr",
    "sg:city":"Indianapolis",
    "sg:classifiers":[
        {
            "category":"Insurance",
            "subcategory":"Hazard Insurance",
            "type":"Services"
        }
    ],
    "sg:phone":"+1 317 844 1251",
    "sg:postcode":"46240",
    "sg:province":"IN",
    "sg:tags":[
        "profit",
        "sharing",
        "pension",
        "plan"
    ],
    "sg:website":"www.sheridaninc.biz",
    "wof:name":"Sheridan & Assoc",
    "wof:placetype":"venue"
},
  "geometry": {"coordinates":[-86.106826,39.923211],"type":"Point"}
}