{
  "type": "Feature",
  "properties": {
    "iso:country":"US",
    "sg:address":"5356 W 38th St",
    "sg:city":"Indianapolis",
    "sg:classifiers":[
        {
            "category":"Restaurant",
            "type":"Food & Drink"
        }
    ],
    "sg:phone":"+1 317 388 8696",
    "sg:postcode":"46254",
    "sg:province":"IN",
    "wof:name":"Machu Picchu Restaurant",
    "wof:placetype":"venue"
},
  "geometry": {"coordinates":[-86.252865,39.823939],"type":"Point"}
}