{
  "type": "Feature",
  "properties": {
    "iso:country":"US",
    "sg:address":"799 Capitol Rd",
    "sg:city":"Valparaiso",
    "sg:classifiers":[
        {
            "category":"Organizations",
            "subcategory":"Religious Organization",
            "type":"Services"
        }
    ],
    "sg:phone":"+1 219 762 9191",
    "sg:postcode":"46385",
    "sg:province":"IN",
    "sg:tags":[
        "church"
    ],
    "wof:name":"Salvation Army",
    "wof:placetype":"venue"
},
  "geometry": {"coordinates":[-87.127735,41.537805],"type":"Point"}
}