{
  "type": "Feature",
  "properties": {
    "iso:country":"US",
    "sg:address":"2920 McIntyre Dr",
    "sg:city":"Bloomington",
    "sg:classifiers":[
        {
            "category":"Health Services",
            "subcategory":"Doctor",
            "type":"Services"
        }
    ],
    "sg:phone":"+1 812 331 0233",
    "sg:postcode":"47403",
    "sg:province":"IN",
    "sg:tags":[
        "physician",
        "surgeon"
    ],
    "wof:name":"Digestive Diseases Ctr",
    "wof:placetype":"venue"
},
  "geometry": {"coordinates":[-86.57001200000001,39.134708],"type":"Point"}
}