{
  "type": "Feature",
  "properties": {
    "iso:country":"US",
    "sg:address":"7344 Dean Rd",
    "sg:city":"Indianapolis",
    "sg:classifiers":[
        {
            "category":"Insurance",
            "subcategory":"Insurance Agent",
            "type":"Services"
        }
    ],
    "sg:phone":"+1 317 849 2335",
    "sg:postcode":"46240",
    "sg:province":"IN",
    "wof:name":"Stokesberry Insurance",
    "wof:placetype":"venue"
},
  "geometry": {"coordinates":[-86.098392,39.890097],"type":"Point"}
}