{
  "type": "Feature",
  "properties": {
    "addr:full":"900 W Gordon Pike Bloomington IN 47403",
    "addr:housenumber":"900",
    "addr:postcode":"47403",
    "addr:street":"W Gordon Pike",
    "iso:country":"US",
    "sg:address":"900 W Gordon Pike",
    "sg:city":"Bloomington",
    "sg:classifiers":[
        {
            "category":"Education",
            "subcategory":"School",
            "type":"Public Place"
        }
    ],
    "sg:phone":"+1 812 330 7763",
    "sg:postcode":"47403",
    "sg:province":"IN",
    "sg:tags":[
        "high",
        "middle",
        "elementary"
    ],
    "wof:name":"Schools",
    "wof:placetype":"venue"
},
  "geometry": {"coordinates":[-86.543092,39.12183],"type":"Point"}
}