{
  "type": "Feature",
  "properties": {
    "iso:country":"US",
    "sg:address":"820 Jefferson Ave",
    "sg:city":"Laporte",
    "sg:classifiers":[
        {
            "category":"Professional",
            "subcategory":"Lawyer & Legal Services",
            "type":"Services"
        }
    ],
    "sg:phone":"+1 219 362 7575",
    "sg:postcode":"46350",
    "sg:province":"IN",
    "sg:tags":[
        "attorney"
    ],
    "wof:name":"Sallwasser & Mc Cain",
    "wof:placetype":"venue"
},
  "geometry": {"coordinates":[-86.720829,41.610249],"type":"Point"}
}