{
  "type": "Feature",
  "properties": {
    "addr:full":"2419 White St Anderson IN 46012",
    "addr:housenumber":"2419",
    "addr:postcode":"46012",
    "addr:street":"White St",
    "iso:country":"US",
    "sg:address":"2419 White St",
    "sg:city":"Anderson",
    "sg:classifiers":[
        {
            "category":"Organizations",
            "subcategory":"Community Association",
            "type":"Services"
        }
    ],
    "sg:phone":"+1 765 643 2730",
    "sg:postcode":"46012",
    "sg:province":"IN",
    "sg:tags":[
        "fraternal"
    ],
    "wof:name":"Madison County Shrine Club",
    "wof:placetype":"venue"
},
  "geometry": {"coordinates":[-85.648224,40.100958],"type":"Point"}
}