{
  "type": "Feature",
  "properties": {
    "iso:country":"US",
    "sg:address":"801 W Riggin Rd",
    "sg:city":"Muncie",
    "sg:classifiers":[
        {
            "category":"Manufacturing",
            "subcategory":"Metals",
            "type":"Manufacturing & Wholesale Goods"
        }
    ],
    "sg:phone":"+1 765 289 2816",
    "sg:postcode":"47303",
    "sg:province":"IN",
    "sg:tags":[
        "brass",
        "foundry",
        "bronze"
    ],
    "wof:name":"Phillips Pattern & Casting Inc",
    "wof:placetype":"venue"
},
  "geometry": {"coordinates":[-85.398258,40.233403],"type":"Point"}
}