{
  "type": "Feature",
  "properties": {
    "iso:country":"US",
    "sg:address":"7135 W 200 N",
    "sg:city":"Shipshewana",
    "sg:classifiers":[
        {
            "category":"Retail",
            "subcategory":"Repair Shop",
            "type":"Services"
        }
    ],
    "sg:phone":"+1 260 768 7727",
    "sg:postcode":"46565",
    "sg:province":"IN",
    "sg:tags":[
        "electrical"
    ],
    "wof:name":"Lm Appliance",
    "wof:placetype":"venue"
},
  "geometry": {"coordinates":[-85.563225,41.669336],"type":"Point"}
}