{
  "type": "Feature",
  "properties": {
    "addr:full":"6022 Calumet Ave Hammond IN 46320",
    "addr:housenumber":"6022",
    "addr:postcode":"46320",
    "addr:street":"Calumet Ave",
    "iso:country":"US",
    "sg:address":"6022 Calumet Ave",
    "sg:city":"Hammond",
    "sg:classifiers":[
        {
            "category":"Shopping",
            "subcategory":"Pets & Pet Supplies",
            "type":"Retail Goods"
        }
    ],
    "sg:phone":"+1 219 803 7432",
    "sg:postcode":"46320",
    "sg:province":"IN",
    "sg:tags":[
        "specialty"
    ],
    "wof:name":"Cat Eyes Collection",
    "wof:placetype":"venue"
},
  "geometry": {"coordinates":[-87.50892399999999,41.603845],"type":"Point"}
}