{
  "type": "Feature",
  "properties": {
    "iso:country":"US",
    "sg:address":"823 Joliet St",
    "sg:city":"Dyer",
    "sg:classifiers":[
        {
            "category":"Shopping",
            "subcategory":"Computers & Home Electronics",
            "type":"Retail Goods"
        }
    ],
    "sg:phone":"+1 219 864 1583",
    "sg:postcode":"46311",
    "sg:province":"IN",
    "sg:tags":[
        "equipment",
        "satellite",
        "system"
    ],
    "wof:name":"Cellular Connection",
    "wof:placetype":"venue"
},
  "geometry": {"coordinates":[-87.507798,41.492903],"type":"Point"}
}