{
  "type": "Feature",
  "properties": {
    "iso:country":"US",
    "sg:address":"8896 State Rd 236",
    "sg:city":"Middletown",
    "sg:classifiers":[
        {
            "category":"Freight",
            "type":"Transportation"
        }
    ],
    "sg:phone":"+1 765 354 4393",
    "sg:postcode":"47356",
    "sg:province":"IN",
    "sg:tags":[
        "trucking"
    ],
    "wof:name":"Dawn's Transport",
    "wof:placetype":"venue"
},
  "geometry": {"coordinates":[-85.554983,40.062236],"type":"Point"}
}