{
  "type": "Feature",
  "properties": {
    "iso:country":"US",
    "sg:address":"55 Mission Dr",
    "sg:city":"Indianapolis",
    "sg:classifiers":[
        {
            "category":"Building & Trades",
            "subcategory":"Landscaping Services",
            "type":"Services"
        },
        {
            "category":"Real Estate",
            "subcategory":"Real Estate Operator",
            "type":"Services"
        },
        {
            "category":"Social Services",
            "subcategory":"Retirement Home",
            "type":"Services"
        }
    ],
    "sg:phone":"+1 317 244 2600",
    "sg:postcode":"46214",
    "sg:province":"IN",
    "sg:tags":[
        "living",
        "apartment",
        "nursing",
        "facility",
        "assisted",
        "community",
        "convalescent",
        "homes-institutional",
        "aged"
    ],
    "wof:name":"Summit Place West",
    "wof:placetype":"venue"
},
  "geometry": {"coordinates":[-86.273071,39.763869],"type":"Point"}
}