{
  "type": "Feature",
  "properties": {
    "iso:country":"US",
    "sg:address":"9202 N Meridian St",
    "sg:city":"Indianapolis",
    "sg:classifiers":[
        {
            "category":"Organizations",
            "subcategory":"Professional Association",
            "type":"Services"
        }
    ],
    "sg:phone":"+1 317 816 8900",
    "sg:postcode":"46260",
    "sg:province":"IN",
    "sg:website":"www.aptassociationindiana.org",
    "wof:name":"Apartment Association-Indiana",
    "wof:placetype":"venue"
},
  "geometry": {"coordinates":[-86.157995,39.921185],"type":"Point"}
}