{
  "type": "Feature",
  "properties": {
    "iso:country":"US",
    "sg:address":"4295 Co Rd 47",
    "sg:city":"Auburn",
    "sg:phone":"+1 260 925 0617",
    "sg:postcode":"46706",
    "sg:province":"IN",
    "sg:tags":[
        "farm"
    ],
    "wof:name":"Clayton Hursh",
    "wof:placetype":"venue"
},
  "geometry": {"coordinates":[-84.965469,41.376753],"type":"Point"}
}