{
  "type": "Feature",
  "properties": {
    "addr:full":"303 College St Ligonier IN 46767",
    "addr:housenumber":"303",
    "addr:postcode":"46767",
    "addr:street":"College St",
    "iso:country":"US",
    "sg:address":"303 College St",
    "sg:city":"Ligonier",
    "sg:classifiers":[
        {
            "category":"Building & Trades",
            "subcategory":"Construction",
            "type":"Services"
        }
    ],
    "sg:phone":"+1 260 894 4330",
    "sg:postcode":"46767",
    "sg:province":"IN",
    "wof:name":"Don's Pleasant Homes Inc",
    "wof:placetype":"venue"
},
  "geometry": {"coordinates":[-85.59231200000001,41.457183],"type":"Point"}
}