{
  "type": "Feature",
  "properties": {
    "iso:country":"US",
    "sg:address":"3540 Madison Ave",
    "sg:city":"Indianapolis",
    "sg:classifiers":[
        {
            "category":"Autos & Motor Vehicles",
            "subcategory":"Automobile Sales",
            "type":"Retail Goods"
        }
    ],
    "sg:phone":"+1 317 784 1400",
    "sg:postcode":"46227",
    "sg:province":"IN",
    "sg:tags":[
        "car",
        "dealer"
    ],
    "wof:name":"Shiber Auto Sales",
    "wof:placetype":"venue"
},
  "geometry": {"coordinates":[-86.145805,39.714212],"type":"Point"}
}