{
  "type": "Feature",
  "properties": {
    "iso:country":"US",
    "sg:address":"2020 Orchard St",
    "sg:city":"Madison",
    "sg:classifiers":[
        {
            "category":"Manufacturing",
            "subcategory":"Glass & Minerals",
            "type":"Manufacturing & Wholesale Goods"
        }
    ],
    "sg:phone":"+1 812 273 1428",
    "sg:postcode":"47250",
    "sg:province":"IN",
    "sg:tags":[
        "ready"
    ],
    "wof:name":"IMI",
    "wof:placetype":"venue"
},
  "geometry": {"coordinates":[-85.401067,38.762855],"type":"Point"}
}