{
  "type": "Feature",
  "properties": {
    "iso:country":"US",
    "sg:address":"1539 N Ironwood Dr",
    "sg:city":"South Bend",
    "sg:classifiers":[
        {
            "category":"Government",
            "subcategory":"Office",
            "type":"Public Place"
        }
    ],
    "sg:phone":"+1 574 277 1388",
    "sg:postcode":"46635",
    "sg:province":"IN",
    "sg:tags":[
        "state",
        "lottery"
    ],
    "wof:name":"Region 3",
    "wof:placetype":"venue"
},
  "geometry": {"coordinates":[-86.216564,41.697197],"type":"Point"}
}