{
  "type": "Feature",
  "properties": {
    "iso:country":"US",
    "sg:address":"1370 Veterans Pkwy",
    "sg:city":"Clarksville",
    "sg:classifiers":[
        {
            "category":"Personal",
            "subcategory":"Beauty Salon",
            "type":"Services"
        },
        {
            "category":"Personal",
            "subcategory":"Skin Care",
            "type":"Services"
        }
    ],
    "sg:phone":"+1 812 288 2300",
    "sg:postcode":"47129",
    "sg:province":"IN",
    "wof:name":"About Face Spa & Salon",
    "wof:placetype":"venue"
},
  "geometry": {"coordinates":[-85.75733200000001,38.329257],"type":"Point"}
}