{
  "type": "Feature",
  "properties": {
    "iso:country":"US",
    "sg:address":"10373 Illinois Rd",
    "sg:city":"Fort Wayne",
    "sg:classifiers":[
        {
            "category":"Banks & Credit Unions",
            "subcategory":"Bank",
            "type":"Services"
        }
    ],
    "sg:phone":"+1 260 427 7090",
    "sg:postcode":"46814",
    "sg:province":"IN",
    "wof:name":"Tower Bank & Trust Co",
    "wof:placetype":"venue"
},
  "geometry": {"coordinates":[-85.276722,41.074101],"type":"Point"}
}