{
  "type": "Feature",
  "properties": {
    "iso:country":"US",
    "sg:address":"11524 State Rd 3",
    "sg:city":"Marysville",
    "sg:classifiers":[
        {
            "category":"Restaurant",
            "type":"Food & Drink"
        }
    ],
    "sg:phone":"+1 812 889 2362",
    "sg:postcode":"47141",
    "sg:province":"IN",
    "wof:name":"Linda's Grocery & Deli",
    "wof:placetype":"venue"
},
  "geometry": {"coordinates":[-85.66066600000001,38.604948],"type":"Point"}
}