{
  "type": "Feature",
  "properties": {
    "iso:country":"US",
    "sg:address":"2 E Seminary St",
    "sg:city":"Liberty",
    "sg:classifiers":[
        {
            "category":"Education",
            "subcategory":"Library",
            "type":"Public Place"
        }
    ],
    "sg:phone":"+1 765 458 5355",
    "sg:postcode":"47353",
    "sg:province":"IN",
    "sg:website":"www.union-county.lib.in.us",
    "wof:name":"Union County Public Library",
    "wof:placetype":"venue"
},
  "geometry": {"coordinates":[-84.929724,39.634502],"type":"Point"}
}