{
  "type": "Feature",
  "properties": {
    "iso:country":"US",
    "sg:address":"222 Vine St",
    "sg:city":"Clinton",
    "sg:classifiers":[
        {
            "category":"Cinema",
            "subcategory":"Movie Rental",
            "type":"Entertainment"
        }
    ],
    "sg:phone":"+1 765 832 2744",
    "sg:postcode":"47842",
    "sg:province":"IN",
    "sg:tags":[
        "leasing",
        "video",
        "disc",
        "tape"
    ],
    "wof:name":"P & T Video",
    "wof:placetype":"venue"
},
  "geometry": {"coordinates":[-87.399454,39.660407],"type":"Point"}
}