{
  "type": "Feature",
  "properties": {
    "addr:full":"723 N 7th St Terre Haute IN 47807",
    "addr:housenumber":"723",
    "addr:postcode":"47807",
    "addr:street":"N 7Th St",
    "iso:country":"US",
    "sg:address":"723 N 7th St",
    "sg:city":"Terre Haute",
    "sg:classifiers":[
        {
            "category":"Retail",
            "subcategory":"Repair Shop",
            "type":"Services"
        }
    ],
    "sg:phone":"+1 812 235 8171",
    "sg:postcode":"47807",
    "sg:province":"IN",
    "sg:tags":[
        "water",
        "equipment",
        "softening"
    ],
    "wof:name":"Culligan Water Conditioning",
    "wof:placetype":"venue"
},
  "geometry": {"coordinates":[-87.40703499999999,39.476172],"type":"Point"}
}