{
  "type": "Feature",
  "properties": {
    "iso:country":"US",
    "sg:address":"3900 E 900 N",
    "sg:city":"Ossian",
    "sg:classifiers":[
        {
            "category":"Wholesale",
            "subcategory":"Machinery & Supplies",
            "type":"Manufacturing & Wholesale Goods"
        }
    ],
    "sg:phone":"+1 260 622 4042",
    "sg:postcode":"46777",
    "sg:province":"IN",
    "sg:tags":[
        "equipment",
        "system",
        "vacuum"
    ],
    "wof:name":"Beam Distribution",
    "wof:placetype":"venue"
},
  "geometry": {"coordinates":[-85.141966,40.873714],"type":"Point"}
}