{
  "type": "Feature",
  "properties": {
    "iso:country":"US",
    "sg:address":"922 Hoffman St",
    "sg:city":"Hammond",
    "sg:classifiers":[
        {
            "category":"Restaurant",
            "type":"Food & Drink"
        }
    ],
    "sg:phone":"+1 219 937 1561",
    "sg:postcode":"46320",
    "sg:province":"IN",
    "sg:tags":[
        "pizza"
    ],
    "wof:name":"Gomez Tacos & Pizza",
    "wof:placetype":"venue"
},
  "geometry": {"coordinates":[-87.505274,41.626365],"type":"Point"}
}