{
  "type": "Feature",
  "properties": {
    "iso:country":"US",
    "sg:address":"4410 Grape Rd",
    "sg:city":"Mishawaka",
    "sg:classifiers":[
        {
            "category":"Shopping",
            "subcategory":"Department Store",
            "type":"Retail Goods"
        }
    ],
    "sg:phone":"+1 574 273 6266",
    "sg:postcode":"46545",
    "sg:province":"IN",
    "wof:name":"Kohl's",
    "wof:placetype":"venue"
},
  "geometry": {"coordinates":[-86.187353,41.699721],"type":"Point"}
}