{
  "type": "Feature",
  "properties": {
    "iso:country":"US",
    "sg:address":"815 Main St",
    "sg:city":"Rochester",
    "sg:classifiers":[
        {
            "category":"Social Services",
            "type":"Services"
        }
    ],
    "sg:phone":"+1 574 223 4345",
    "sg:postcode":"46975",
    "sg:province":"IN",
    "sg:tags":[
        "probation"
    ],
    "wof:name":"Fulton County Probation Dept",
    "wof:placetype":"venue"
},
  "geometry": {"coordinates":[-86.215881,41.065897],"type":"Point"}
}