{
  "type": "Feature",
  "properties": {
    "addr:full":"108 N 25th St Terre Haute IN 47803",
    "addr:housenumber":"108",
    "addr:postcode":"47803",
    "addr:street":"N 25Th St",
    "iso:country":"US",
    "sg:address":"108 N 25th St",
    "sg:city":"Terre Haute",
    "sg:classifiers":[
        {
            "category":"Retail",
            "subcategory":"Photofinishing",
            "type":"Services"
        }
    ],
    "sg:phone":"+1 812 238 3686",
    "sg:postcode":"47803",
    "sg:province":"IN",
    "sg:tags":[
        "photo",
        "finishing"
    ],
    "wof:name":"House Of Photography",
    "wof:placetype":"venue"
},
  "geometry": {"coordinates":[-87.37897,39.472027],"type":"Point"}
}