{
  "type": "Feature",
  "properties": {
    "iso:country":"US",
    "sg:address":"2525 California St",
    "sg:city":"Columbus",
    "sg:classifiers":[
        {
            "category":"Health Services",
            "subcategory":"Optometrist",
            "type":"Services"
        }
    ],
    "sg:phone":"+1 812 379 9880",
    "sg:postcode":"47201",
    "sg:province":"IN",
    "wof:name":"William G Bickers OD",
    "wof:placetype":"venue"
},
  "geometry": {"coordinates":[-85.914553,39.227099],"type":"Point"}
}