{
  "type": "Feature",
  "properties": {
    "iso:country":"US",
    "sg:address":"10196 E Southport Rd",
    "sg:city":"Indianapolis",
    "sg:classifiers":[
        {
            "category":"Manufacturing",
            "subcategory":"Metals",
            "type":"Manufacturing & Wholesale Goods"
        }
    ],
    "sg:phone":"+1 317 862 9492",
    "sg:postcode":"46259",
    "sg:province":"IN",
    "sg:tags":[
        "sales"
    ],
    "wof:name":"Le Bronze Industriel",
    "wof:placetype":"venue"
},
  "geometry": {"coordinates":[-85.97686400000001,39.661278],"type":"Point"}
}