{
  "type": "Feature",
  "properties": {
    "addr:full":"6345 Massachusetts Ave Indianapolis IN 46226",
    "addr:housenumber":"6345",
    "addr:postcode":"46226",
    "addr:street":"Massachusetts Ave",
    "iso:country":"US",
    "sg:address":"6345 Massachusetts Ave",
    "sg:city":"Indianapolis",
    "sg:classifiers":[
        {
            "category":"Place Of Worship",
            "subcategory":"Church",
            "type":"Public Place"
        },
        {
            "category":"Place Of Worship",
            "type":"Public Place"
        }
    ],
    "sg:phone":"+1 317 731 4530",
    "sg:postcode":"46226",
    "sg:province":"IN",
    "sg:tags":[
        "churches-apostolic",
        "churches-pentecostal-apostolic"
    ],
    "wof:name":"New Life Community Church Of Truth",
    "wof:placetype":"venue"
},
  "geometry": {"coordinates":[-86.05932,39.820907],"type":"Point"}
}