{
  "type": "Feature",
  "properties": {
    "addr:full":"1560 W 500 N Winchester IN 47394",
    "addr:housenumber":"1560",
    "addr:postcode":"47394",
    "addr:street":"W 500 N",
    "iso:country":"US",
    "sg:address":"1560 W 500 N",
    "sg:city":"Winchester",
    "sg:classifiers":[
        {
            "category":"Freight",
            "type":"Transportation"
        }
    ],
    "sg:phone":"+1 765 584 6595",
    "sg:postcode":"47394",
    "sg:province":"IN",
    "sg:tags":[
        "grain",
        "elevator"
    ],
    "wof:name":"Stone Station Elevator",
    "wof:placetype":"venue"
},
  "geometry": {"coordinates":[-85.005501,40.236416],"type":"Point"}
}