{
  "type": "Feature",
  "properties": {
    "iso:country":"US",
    "sg:address":"14420 Cherry Tree Rd",
    "sg:city":"Carmel",
    "sg:classifiers":[
        {
            "category":"Professional",
            "subcategory":"Employment Agencies",
            "type":"Services"
        }
    ],
    "sg:phone":"+1 317 846 4321",
    "sg:postcode":"46033",
    "sg:province":"IN",
    "sg:tags":[
        "modeling"
    ],
    "wof:name":"Super Models Intl",
    "wof:placetype":"venue"
},
  "geometry": {"coordinates":[-86.058132,40.000254],"type":"Point"}
}