{
  "type": "Feature",
  "properties": {
    "iso:country":"US",
    "sg:address":"1309 Prairie St",
    "sg:city":"Elkhart",
    "sg:classifiers":[
        {
            "category":"Retail",
            "subcategory":"Repair Shop",
            "type":"Services"
        }
    ],
    "sg:phone":"+1 574 293 2849",
    "sg:postcode":"46516",
    "sg:province":"IN",
    "sg:tags":[
        "body",
        "auto"
    ],
    "wof:name":"Action Mobile Home Service",
    "wof:placetype":"venue"
},
  "geometry": {"coordinates":[-85.965597,41.675559],"type":"Point"}
}