{
  "type": "Feature",
  "properties": {
    "addr:full":"1000 Airport North Office Park Fort Wayne IN 46825",
    "addr:housenumber":"1000",
    "addr:postcode":"46825",
    "iso:country":"US",
    "sg:address":"1000 Airport North Office Park",
    "sg:city":"Fort Wayne",
    "sg:classifiers":[
        {
            "category":"Wholesale",
            "subcategory":"Medical Equipment & Supplies",
            "type":"Manufacturing & Wholesale Goods"
        }
    ],
    "sg:phone":"+1 260 489 5200",
    "sg:postcode":"46825",
    "sg:province":"IN",
    "sg:tags":[
        "physician",
        "surgeon"
    ],
    "wof:name":"National Seating & Mobility",
    "wof:placetype":"venue"
},
  "geometry": {"coordinates":[-85.16009699999999,41.144556],"type":"Point"}
}