{
  "type": "Feature",
  "properties": {
    "iso:country":"US",
    "sg:address":"501 S Elm St",
    "sg:city":"Paoli",
    "sg:classifiers":[
        {
            "category":"Education",
            "subcategory":"School",
            "type":"Public Place"
        }
    ],
    "sg:phone":"+1 812 723 4717",
    "sg:postcode":"47454",
    "sg:province":"IN",
    "wof:name":"Paoli Superintendent Office",
    "wof:placetype":"venue"
},
  "geometry": {"coordinates":[-86.476024,38.550723],"type":"Point"}
}