{
  "type": "Feature",
  "properties": {
    "iso:country":"US",
    "sg:address":"2540 W Lusher Ave",
    "sg:city":"Elkhart",
    "sg:classifiers":[
        {
            "category":"Freight",
            "type":"Transportation"
        }
    ],
    "sg:phone":"+1 574 293 1661",
    "sg:postcode":"46517",
    "sg:province":"IN",
    "wof:name":"Professional Transportation",
    "wof:placetype":"venue"
},
  "geometry": {"coordinates":[-86.00395,41.667006],"type":"Point"}
}