{
  "type": "Feature",
  "properties": {
    "iso:country":"US",
    "sg:address":"6794 N 600 W",
    "sg:city":"Mc Cordsville",
    "sg:classifiers":[
        {
            "category":"Travel",
            "subcategory":"Hotels & Motels",
            "type":"Entertainment"
        }
    ],
    "sg:phone":"+1 317 335 7023",
    "sg:postcode":"46055",
    "sg:province":"IN",
    "sg:tags":[
        "breakfast",
        "accommodation",
        "bed"
    ],
    "sg:website":"www.roundbarn-inn.com",
    "wof:name":"Roundbarn Inn Bed & Breakfast",
    "wof:placetype":"venue"
},
  "geometry": {"coordinates":[-85.919114,39.880399],"type":"Point"}
}