{
  "type": "Feature",
  "properties": {
    "iso:country":"US",
    "sg:address":"1600 US Hwy 31 S",
    "sg:city":"Greenwood",
    "sg:classifiers":[
        {
            "category":"Mining & Drilling",
            "type":"Manufacturing & Wholesale Goods"
        }
    ],
    "sg:phone":"+1 317 882 2869",
    "sg:postcode":"46143",
    "sg:province":"IN",
    "sg:tags":[
        "oil",
        "gas",
        "producer"
    ],
    "wof:name":"Thorton Oil Corp",
    "wof:placetype":"venue"
},
  "geometry": {"coordinates":[-86.10299999999999,39.59312],"type":"Point"}
}