{
  "type": "Feature",
  "properties": {
    "iso:country":"US",
    "sg:address":"4741 E Stop 11 Rd",
    "sg:city":"Indianapolis",
    "sg:classifiers":[
        {
            "category":"Professional",
            "subcategory":"Lawyer & Legal Services",
            "type":"Services"
        }
    ],
    "sg:phone":"+1 317 215 5258",
    "sg:postcode":"46237",
    "sg:province":"IN",
    "sg:tags":[
        "attorney",
        "law",
        "plan",
        "business",
        "bankruptcy"
    ],
    "sg:website":"http://indianapolis.citysearch.com/profile/external/629753970/indianapolis_in/chuck_roach_law.html?publisher=yellowpages&reference_id=15&placement=ypwebsitemip",
    "wof:name":"Chuck Roach Law",
    "wof:placetype":"venue"
},
  "geometry": {"coordinates":[-86.087644,39.65102],"type":"Point"}
}