{
  "type": "Feature",
  "properties": {
    "iso:country":"US",
    "sg:address":"4101 Glenellen Ct",
    "sg:city":"Mishawaka",
    "sg:classifiers":[
        {
            "category":"Organizations",
            "subcategory":"Religious Organization",
            "type":"Services"
        }
    ],
    "sg:phone":"+1 574 271 9844",
    "sg:postcode":"46545",
    "sg:province":"IN",
    "sg:tags":[
        "church"
    ],
    "wof:name":"Oasis Christian Fellowship",
    "wof:placetype":"venue"
},
  "geometry": {"coordinates":[-86.191615,41.696693],"type":"Point"}
}