{
  "type": "Feature",
  "properties": {
    "iso:country":"US",
    "sg:address":"278 Blacketor Dr",
    "sg:city":"Rochester",
    "sg:classifiers":[
        {
            "category":"Manufacturing",
            "subcategory":"Tools & Machinery",
            "type":"Manufacturing & Wholesale Goods"
        }
    ],
    "sg:phone":"+1 574 223 5655",
    "sg:postcode":"46975",
    "sg:province":"IN",
    "sg:tags":[
        "current",
        "wiring",
        "devices"
    ],
    "wof:name":"A & T Two Inc",
    "wof:placetype":"venue"
},
  "geometry": {"coordinates":[-86.19925000000001,41.073843],"type":"Point"}
}