{
  "type": "Feature",
  "properties": {
    "iso:country":"US",
    "sg:address":"102 Miles Ridge Rd",
    "sg:city":"Madison",
    "sg:classifiers":[
        {
            "category":"Professional",
            "subcategory":"Accounting & Tax Preparation",
            "type":"Services"
        }
    ],
    "sg:phone":"+1 812 273 1148",
    "sg:postcode":"47250",
    "sg:province":"IN",
    "sg:tags":[
        "return",
        "filing"
    ],
    "wof:name":"CPA Accounting Firm",
    "wof:placetype":"venue"
},
  "geometry": {"coordinates":[-85.38574800000001,38.770967],"type":"Point"}
}