{
  "type": "Feature",
  "properties": {
    "addr:full":"9117 Indianapolis Blvd Highland IN 46322",
    "addr:housenumber":"9117",
    "addr:postcode":"46322",
    "addr:street":"Indianapolis Blvd",
    "iso:country":"US",
    "sg:address":"9117 Indianapolis Blvd",
    "sg:city":"Highland",
    "sg:classifiers":[
        {
            "category":"Restaurant",
            "type":"Food & Drink"
        }
    ],
    "sg:phone":"+1 219 923 9634",
    "sg:postcode":"46322",
    "sg:province":"IN",
    "wof:name":"Mc Donald's",
    "wof:placetype":"venue"
},
  "geometry": {"coordinates":[-87.471272,41.544805],"type":"Point"}
}