{
  "type": "Feature",
  "properties": {
    "iso:country":"US",
    "sg:address":"3000 W Delaware St",
    "sg:city":"Evansville",
    "sg:classifiers":[
        {
            "category":"Social Services",
            "subcategory":"Child Care",
            "type":"Services"
        }
    ],
    "sg:phone":"+1 812 423 9602",
    "sg:postcode":"47720",
    "sg:province":"IN",
    "sg:tags":[
        "kindergarten",
        "academic",
        "school",
        "day"
    ],
    "wof:name":"Henze's Westside Pre-School",
    "wof:placetype":"venue"
},
  "geometry": {"coordinates":[-87.612718,37.98464],"type":"Point"}
}