{
  "type": "Feature",
  "properties": {
    "iso:country":"US",
    "sg:address":"12636 W 101st Ave",
    "sg:city":"St John",
    "sg:classifiers":[
        {
            "category":"Building & Trades",
            "subcategory":"Construction",
            "type":"Services"
        }
    ],
    "sg:phone":"+1 219 365 2600",
    "sg:postcode":"46373",
    "sg:province":"IN",
    "sg:tags":[
        "general",
        "contractor"
    ],
    "wof:name":"Tri-County Development Co",
    "wof:placetype":"venue"
},
  "geometry": {"coordinates":[-87.48762000000001,41.436597],"type":"Point"}
}