{
  "type": "Feature",
  "properties": {
    "iso:country":"US",
    "sg:address":"310 E South St",
    "sg:city":"Bremen",
    "sg:classifiers":[
        {
            "category":"Shopping",
            "subcategory":"Florist",
            "type":"Retail Goods"
        }
    ],
    "sg:phone":"+1 574 546 3277",
    "sg:postcode":"46506",
    "sg:province":"IN",
    "wof:name":"Paul's Flower Shop",
    "wof:placetype":"venue"
},
  "geometry": {"coordinates":[-86.14334,41.445607],"type":"Point"}
}