{
  "type": "Feature",
  "properties": {
    "iso:country":"US",
    "sg:address":"6080 State Rd 39",
    "sg:city":"Clayton",
    "sg:classifiers":[
        {
            "category":"Building & Trades",
            "subcategory":"Plumbing",
            "type":"Services"
        }
    ],
    "sg:phone":"+1 317 539 6009",
    "sg:postcode":"46118",
    "sg:province":"IN",
    "sg:tags":[
        "plumbing",
        "contractor"
    ],
    "wof:name":"Halcomb Plumbing",
    "wof:placetype":"venue"
},
  "geometry": {"coordinates":[-86.487737,39.673907],"type":"Point"}
}