{
  "type": "Feature",
  "properties": {
    "iso:country":"US",
    "sg:address":"911 Wood St",
    "sg:city":"Valparaiso",
    "sg:classifiers":[
        {
            "category":"Sports & Exercise",
            "subcategory":"Race Track",
            "type":"Entertainment"
        }
    ],
    "sg:phone":"+1 219 462 5619",
    "sg:postcode":"46383",
    "sg:province":"IN",
    "sg:tags":[
        "operation",
        "racing",
        "or"
    ],
    "wof:name":"George G Engel",
    "wof:placetype":"venue"
},
  "geometry": {"coordinates":[-87.04788,41.470957],"type":"Point"}
}