{
  "type": "Feature",
  "properties": {
    "iso:country":"US",
    "sg:address":"102 N Main St",
    "sg:city":"Tipton",
    "sg:classifiers":[
        {
            "category":"Banks & Credit Unions",
            "subcategory":"Bank",
            "type":"Services"
        }
    ],
    "sg:phone":"+1 765 675 2178",
    "sg:postcode":"46072",
    "sg:province":"IN",
    "wof:name":"National City Bank",
    "wof:placetype":"venue"
},
  "geometry": {"coordinates":[-86.041337,40.283523],"type":"Point"}
}