{
  "type": "Feature",
  "properties": {
    "iso:country":"US",
    "sg:address":"701 Thurman Ave",
    "sg:city":"Michigan City",
    "sg:classifiers":[
        {
            "category":"Building & Trades",
            "subcategory":"Construction",
            "type":"Services"
        }
    ],
    "sg:phone":"+1 219 879 9085",
    "sg:postcode":"46360",
    "sg:province":"IN",
    "sg:tags":[
        "masonry",
        "contractor"
    ],
    "wof:name":"D & K Masonry Inc",
    "wof:placetype":"venue"
},
  "geometry": {"coordinates":[-86.884568,41.709036],"type":"Point"}
}