{
  "type": "Feature",
  "properties": {
    "iso:country":"US",
    "sg:address":"315 W Commercial St",
    "sg:city":"Hartford City",
    "sg:classifiers":[
        {
            "category":"Insurance",
            "subcategory":"Hazard Insurance",
            "type":"Services"
        }
    ],
    "sg:phone":"+1 765 348 9901",
    "sg:postcode":"47348",
    "sg:province":"IN",
    "sg:tags":[
        "bond"
    ],
    "wof:name":"Apple Bail Bonds",
    "wof:placetype":"venue"
},
  "geometry": {"coordinates":[-85.37017899999999,40.448687],"type":"Point"}
}