{
  "type": "Feature",
  "properties": {
    "iso:country":"US",
    "sg:address":"443 NW L St",
    "sg:city":"Richmond",
    "sg:classifiers":[
        {
            "category":"Personal",
            "subcategory":"Beauty Salon",
            "type":"Services"
        }
    ],
    "sg:phone":"+1 765 966 4999",
    "sg:postcode":"47374",
    "sg:province":"IN",
    "wof:name":"Brenda Stover",
    "wof:placetype":"venue"
},
  "geometry": {"coordinates":[-84.906177,39.843774],"type":"Point"}
}