{
  "type": "Feature",
  "properties": {
    "iso:country":"US",
    "sg:address":"3029 Mounds Rd",
    "sg:city":"Anderson",
    "sg:classifiers":[
        {
            "category":"Organizations",
            "subcategory":"Religious Organization",
            "type":"Services"
        }
    ],
    "sg:phone":"+1 765 643 9368",
    "sg:postcode":"46016",
    "sg:province":"IN",
    "wof:name":"Church Of God Of Prophecy",
    "wof:placetype":"venue"
},
  "geometry": {"coordinates":[-85.639331,40.089597],"type":"Point"}
}