{
  "type": "Feature",
  "properties": {
    "iso:country":"US",
    "sg:address":"1210 S Briant St",
    "sg:city":"Huntington",
    "sg:classifiers":[
        {
            "category":"Recreation",
            "type":"Entertainment"
        }
    ],
    "sg:phone":"+1 260 355 0711",
    "sg:postcode":"46750",
    "sg:province":"IN",
    "sg:tags":[
        "martial",
        "arts",
        "instruction"
    ],
    "wof:name":"Universal Tangsoodo Karate",
    "wof:placetype":"venue"
},
  "geometry": {"coordinates":[-85.485135,40.870852],"type":"Point"}
}