{
  "type": "Feature",
  "properties": {
    "iso:country":"US",
    "sg:address":"11243 Thornburg Rd",
    "sg:city":"Economy",
    "sg:phone":"+1 765 886 5744",
    "sg:postcode":"47339",
    "sg:province":"IN",
    "sg:tags":[
        "farm",
        "corn"
    ],
    "wof:name":"Michael Craig",
    "wof:placetype":"venue"
},
  "geometry": {"coordinates":[-85.13176,39.99279],"type":"Point"}
}