{
  "type": "Feature",
  "properties": {
    "iso:country":"US",
    "sg:address":"9740 Olympia Dr",
    "sg:city":"Fishers",
    "sg:classifiers":[
        {
            "category":"Professional",
            "subcategory":"Lawyer & Legal Services",
            "type":"Services"
        }
    ],
    "sg:phone":"+1 317 577 3055",
    "sg:postcode":"46037",
    "sg:province":"IN",
    "sg:tags":[
        "attorney"
    ],
    "wof:name":"Todd W Parker",
    "wof:placetype":"venue"
},
  "geometry": {"coordinates":[-85.983238,39.929061],"type":"Point"}
}