{
  "type": "Feature",
  "properties": {
    "iso:country":"US",
    "sg:address":"10655 Andrade Dr",
    "sg:city":"Zionsville",
    "sg:classifiers":[
        {
            "category":"Home & Garden",
            "subcategory":"Hardware",
            "type":"Retail Goods"
        }
    ],
    "sg:phone":"+1 317 873 1316",
    "sg:postcode":"46077",
    "sg:province":"IN",
    "wof:name":"Phyllis Kennedy Antique Hdwr",
    "wof:placetype":"venue"
},
  "geometry": {"coordinates":[-86.244158,39.943227],"type":"Point"}
}