{
  "type": "Feature",
  "properties": {
    "iso:country":"US",
    "sg:address":"2559 E 55th Pl",
    "sg:city":"Indianapolis",
    "sg:classifiers":[
        {
            "category":"Retail",
            "subcategory":"Auto Repair",
            "type":"Services"
        }
    ],
    "sg:phone":"+1 317 259 7060",
    "sg:postcode":"46220",
    "sg:province":"IN",
    "sg:tags":[
        "transporter",
        "co",
        "drive",
        "automobile"
    ],
    "sg:website":"http://www.autodriveaway.com",
    "wof:name":"Auto Driveaway",
    "wof:placetype":"venue"
},
  "geometry": {"coordinates":[-86.11996600000001,39.853813],"type":"Point"}
}