{
  "type": "Feature",
  "properties": {
    "iso:country":"US",
    "sg:address":"2921 Clifty Dr",
    "sg:city":"Madison",
    "sg:classifiers":[
        {
            "category":"Building & Trades",
            "subcategory":"Pest Control",
            "type":"Services"
        }
    ],
    "sg:phone":"+1 812 273 3541",
    "sg:postcode":"47250",
    "sg:province":"IN",
    "wof:name":"Mr Pest Control & Termite Inc",
    "wof:placetype":"venue"
},
  "geometry": {"coordinates":[-85.450047,38.754742],"type":"Point"}
}