{
  "type": "Feature",
  "properties": {
    "iso:country":"US",
    "sg:address":"9521 E 37th Ave",
    "sg:city":"Hobart",
    "sg:classifiers":[
        {
            "category":"Food & Beverages",
            "subcategory":"Groceries & Convenience Stores",
            "type":"Retail Goods"
        }
    ],
    "sg:phone":"+1 219 942 4978",
    "sg:postcode":"46342",
    "sg:province":"IN",
    "wof:name":"Family Express Corp",
    "wof:placetype":"venue"
},
  "geometry": {"coordinates":[-87.22877699999999,41.550563],"type":"Point"}
}