{
  "type": "Feature",
  "properties": {
    "iso:country":"US",
    "sg:address":"911 E Court Ave",
    "sg:city":"Jeffersonville",
    "sg:classifiers":[
        {
            "category":"Professional",
            "subcategory":"Business Services",
            "type":"Services"
        }
    ],
    "sg:phone":"+1 812 218 9244",
    "sg:postcode":"47130",
    "sg:province":"IN",
    "sg:tags":[
        "auctioneer"
    ],
    "wof:name":"Mc Ginnis Auction & Appraisal",
    "wof:placetype":"venue"
},
  "geometry": {"coordinates":[-85.730141,38.280475],"type":"Point"}
}