{
  "type": "Feature",
  "properties": {
    "addr:full":"1202 Lincolnway La Porte IN 46350",
    "addr:housenumber":"1202",
    "addr:postcode":"46350",
    "addr:street":"Lincolnway La",
    "iso:country":"US",
    "sg:address":"1202 Lincolnway",
    "sg:city":"La Porte",
    "sg:classifiers":[
        {
            "category":"Restaurant",
            "type":"Food & Drink"
        }
    ],
    "sg:menulink":"http://www.allmenus.com/in/la-porte/174146-wendys/menu/",
    "sg:phone":"+1 219 362 1155",
    "sg:postcode":"46350",
    "sg:province":"IN",
    "sg:tags":[
        "burger",
        "american",
        "soup"
    ],
    "wof:name":"Wendy's",
    "wof:placetype":"venue"
},
  "geometry": {"coordinates":[-86.725236,41.609124],"type":"Point"}
}