{
  "type": "Feature",
  "properties": {
    "iso:country":"US",
    "sg:address":"8315 W Jefferson Blvd",
    "sg:city":"Fort Wayne",
    "sg:classifiers":[
        {
            "category":"Social Services",
            "type":"Services"
        }
    ],
    "sg:phone":"+1 260 432 9593",
    "sg:postcode":"46804",
    "sg:province":"IN",
    "sg:tags":[
        "youth",
        "organization",
        "center"
    ],
    "sg:website":"www.bsaawac.org",
    "wof:name":"Boy Scouts Of America",
    "wof:placetype":"venue"
},
  "geometry": {"coordinates":[-85.25206900000001,41.034145],"type":"Point"}
}