{
  "type": "Feature",
  "properties": {
    "iso:country":"US",
    "sg:address":"9120 Mount Tabor Rd",
    "sg:city":"Aurora",
    "sg:classifiers":[
        {
            "category":"Freight",
            "type":"Transportation"
        }
    ],
    "sg:phone":"+1 812 926 3075",
    "sg:postcode":"47001",
    "sg:province":"IN",
    "sg:tags":[
        "operator",
        "trucking"
    ],
    "wof:name":"Mark A Weddendorf",
    "wof:placetype":"venue"
},
  "geometry": {"coordinates":[-84.986601,39.023275],"type":"Point"}
}