{
  "type": "Feature",
  "properties": {
    "iso:country":"US",
    "sg:address":"747 E Main St",
    "sg:city":"Gas City",
    "sg:classifiers":[
        {
            "category":"Professional",
            "subcategory":"Accounting & Tax Preparation",
            "type":"Services"
        }
    ],
    "sg:phone":"+1 765 674 7712",
    "sg:postcode":"46933",
    "sg:province":"IN",
    "sg:tags":[
        "return",
        "filing"
    ],
    "wof:name":"H & R Block Tax Svc",
    "wof:placetype":"venue"
},
  "geometry": {"coordinates":[-85.601532,40.487968],"type":"Point"}
}