{
  "type": "Feature",
  "properties": {
    "iso:country":"US",
    "sg:address":"3122 N Pennsylvania St",
    "sg:city":"Indianapolis",
    "sg:classifiers":[
        {
            "category":"Professional",
            "subcategory":"Art Services",
            "type":"Services"
        }
    ],
    "sg:phone":"+1 317 921 0151",
    "sg:postcode":"46205",
    "sg:province":"IN",
    "sg:tags":[
        "graphic",
        "designer"
    ],
    "wof:name":"PRN Graphics",
    "wof:placetype":"venue"
},
  "geometry": {"coordinates":[-86.154746,39.812466],"type":"Point"}
}