{
  "type": "Feature",
  "properties": {
    "iso:country":"US",
    "sg:address":"9017 Coldwater Rd",
    "sg:city":"Fort Wayne",
    "sg:classifiers":[
        {
            "category":"Health Services",
            "subcategory":"Chiropractor",
            "type":"Services"
        }
    ],
    "sg:phone":"+1 260 489 8911",
    "sg:postcode":"46825",
    "sg:province":"IN",
    "wof:name":"Van Horn Chiropractic Ctr",
    "wof:placetype":"venue"
},
  "geometry": {"coordinates":[-85.13444,41.162153],"type":"Point"}
}