{
  "type": "Feature",
  "properties": {
    "iso:country":"US",
    "sg:address":"320 N Meridian St",
    "sg:city":"Indianapolis",
    "sg:classifiers":[
        {
            "category":"Health Services",
            "subcategory":"Doctor",
            "type":"Services"
        }
    ],
    "sg:phone":"+1 317 974 1943",
    "sg:postcode":"46204",
    "sg:province":"IN",
    "sg:tags":[
        "physician",
        "surgeon"
    ],
    "wof:name":"Robert Greenleaf MD",
    "wof:placetype":"venue"
},
  "geometry": {"coordinates":[-86.15799699999999,39.77143],"type":"Point"}
}