{
  "type": "Feature",
  "properties": {
    "iso:country":"US",
    "sg:address":"14227 Old State Rd 37",
    "sg:city":"Tell City",
    "sg:classifiers":[
        {
            "category":"Wholesale",
            "subcategory":"Machinery & Supplies",
            "type":"Manufacturing & Wholesale Goods"
        }
    ],
    "sg:phone":"+1 812 836 2121",
    "sg:postcode":"47586",
    "sg:province":"IN",
    "sg:tags":[
        "farm",
        "equipment"
    ],
    "wof:name":"Howell's Garage Inc",
    "wof:placetype":"venue"
},
  "geometry": {"coordinates":[-86.644447,38.05091],"type":"Point"}
}