{
  "type": "Feature",
  "properties": {
    "iso:country":"US",
    "sg:address":"105 N Walnut St",
    "sg:city":"Batesville",
    "sg:classifiers":[
        {
            "category":"Shopping",
            "subcategory":"Florist",
            "type":"Retail Goods"
        }
    ],
    "sg:phone":"+1 812 932 3100",
    "sg:postcode":"47006",
    "sg:province":"IN",
    "wof:name":"In Bloom",
    "wof:placetype":"venue"
},
  "geometry": {"coordinates":[-85.2226,39.300049],"type":"Point"}
}