{
  "type": "Feature",
  "properties": {
    "iso:country":"US",
    "sg:address":"2502 Glad St",
    "sg:city":"Warsaw",
    "sg:classifiers":[
        {
            "category":"Social Services",
            "subcategory":"Child Care",
            "type":"Services"
        }
    ],
    "sg:phone":"+1 574 268 0250",
    "sg:postcode":"46582",
    "sg:province":"IN",
    "wof:name":"Debbie's Daycare 1 & 2",
    "wof:placetype":"venue"
},
  "geometry": {"coordinates":[-85.82110400000001,41.252412],"type":"Point"}
}