{
  "type": "Feature",
  "properties": {
    "iso:country":"US",
    "sg:address":"1901 S L St",
    "sg:city":"Elwood",
    "sg:classifiers":[
        {
            "category":"Building & Trades",
            "subcategory":"Construction",
            "type":"Services"
        }
    ],
    "sg:phone":"+1 765 552 6732",
    "sg:postcode":"46036",
    "sg:province":"IN",
    "sg:tags":[
        "concrete",
        "contractor"
    ],
    "wof:name":"Snuffy Lineback Concrete Work",
    "wof:placetype":"venue"
},
  "geometry": {"coordinates":[-85.837262,40.265705],"type":"Point"}
}