{
  "type": "Feature",
  "properties": {
    "iso:country":"US",
    "sg:address":"2700 E 55th Pl Ste 15",
    "sg:city":"Indianapolis",
    "sg:classifiers":[
        {
            "category":"Communications",
            "subcategory":"Television Station",
            "type":"Services"
        }
    ],
    "sg:phone":"+1 317 253 0407",
    "sg:postcode":"46220",
    "sg:province":"IN",
    "sg:tags":[
        "satellite",
        "antenna",
        "cable",
        "tv",
        "system",
        "equipment"
    ],
    "wof:name":"Worldwide Satellite Television",
    "wof:placetype":"venue"
},
  "geometry": {"coordinates":[-86.118512,39.853793],"type":"Point"}
}