{
  "type": "Feature",
  "properties": {
    "iso:country":"US",
    "sg:address":"302 W Washington St E024",
    "sg:city":"Indianapolis",
    "sg:classifiers":[
        {
            "category":"Professional",
            "subcategory":"Management & Consulting",
            "type":"Services"
        },
        {
            "category":"Government",
            "subcategory":"Office",
            "type":"Public Place"
        }
    ],
    "sg:phone":"+1 317 233 3955",
    "sg:postcode":"46204",
    "sg:province":"IN",
    "sg:tags":[
        "planning",
        "consultant",
        "facility",
        "space"
    ],
    "wof:name":"Facilities Management",
    "wof:placetype":"venue"
},
  "geometry": {"coordinates":[-86.16350300000001,39.767201],"type":"Point"}
}