{
  "type": "Feature",
  "properties": {
    "iso:country":"US",
    "sg:address":"719 N Washington St",
    "sg:city":"Kokomo",
    "sg:classifiers":[
        {
            "category":"Autos & Motor Vehicles",
            "subcategory":"Automobile Sales",
            "type":"Retail Goods"
        }
    ],
    "sg:phone":"+1 765 452 6697",
    "sg:postcode":"46901",
    "sg:province":"IN",
    "sg:tags":[
        "car",
        "dealer"
    ],
    "wof:name":"Fast Lane Auto Sales",
    "wof:placetype":"venue"
},
  "geometry": {"coordinates":[-86.133787,40.492116],"type":"Point"}
}