{
  "type": "Feature",
  "properties": {
    "iso:country":"US",
    "sg:address":"902 Hendricks Dr",
    "sg:city":"Lebanon",
    "sg:classifiers":[
        {
            "category":"Manufacturing",
            "subcategory":"Metals",
            "type":"Manufacturing & Wholesale Goods"
        }
    ],
    "sg:phone":"+1 765 482 9802",
    "sg:postcode":"46052",
    "sg:province":"IN",
    "sg:tags":[
        "coating"
    ],
    "wof:name":"IBC Coatings Technology",
    "wof:placetype":"venue"
},
  "geometry": {"coordinates":[-86.45537899999999,40.034444],"type":"Point"}
}