{
  "type": "Feature",
  "properties": {
    "iso:country":"US",
    "sg:address":"124 S Hart St",
    "sg:city":"Princeton",
    "sg:classifiers":[
        {
            "category":"Education",
            "subcategory":"Library",
            "type":"Public Place"
        }
    ],
    "sg:phone":"+1 812 385 4464",
    "sg:postcode":"47670",
    "sg:province":"IN",
    "wof:name":"Princeton Public Library",
    "wof:placetype":"venue"
},
  "geometry": {"coordinates":[-87.56870000000001,38.35501],"type":"Point"}
}