{
  "type": "Feature",
  "properties": {
    "addr:full":"1727 S Franklin Rd Indianapolis IN 46239",
    "addr:housenumber":"1727",
    "addr:postcode":"46239",
    "addr:street":"S Franklin Rd",
    "iso:country":"US",
    "sg:address":"1727 S Franklin Rd",
    "sg:city":"Indianapolis",
    "sg:classifiers":[
        {
            "category":"Building & Trades",
            "subcategory":"Construction",
            "type":"Services"
        }
    ],
    "sg:phone":"+1 317 359 6938",
    "sg:postcode":"46239",
    "sg:province":"IN",
    "sg:tags":[
        "millwright"
    ],
    "wof:name":"Mitzel Projects Inc",
    "wof:placetype":"venue"
},
  "geometry": {"coordinates":[-86.02582200000001,39.742485],"type":"Point"}
}