{
  "type": "Feature",
  "properties": {
    "iso:country":"US",
    "sg:address":"1505 S 10th St",
    "sg:city":"Noblesville",
    "sg:classifiers":[
        {
            "category":"Retail",
            "subcategory":"Auto Repair",
            "type":"Services"
        }
    ],
    "sg:phone":"+1 317 773 0109",
    "sg:postcode":"46060",
    "sg:province":"IN",
    "sg:tags":[
        "brake"
    ],
    "wof:name":"Tires N Up",
    "wof:placetype":"venue"
},
  "geometry": {"coordinates":[-86.012169,40.032235],"type":"Point"}
}