{
  "type": "Feature",
  "properties": {
    "iso:country":"US",
    "sg:address":"1701 E Center St",
    "sg:city":"Warsaw",
    "sg:classifiers":[
        {
            "category":"Home & Garden",
            "subcategory":"Hardware",
            "type":"Retail Goods"
        }
    ],
    "sg:phone":"+1 574 267 5315",
    "sg:postcode":"46580",
    "sg:province":"IN",
    "sg:website":"www.acewarsaw.com",
    "wof:name":"Ace Hardware",
    "wof:placetype":"venue"
},
  "geometry": {"coordinates":[-85.834418,41.238017],"type":"Point"}
}