{
  "type": "Feature",
  "properties": {
    "iso:country":"US",
    "sg:address":"5700 W 15th Ave",
    "sg:city":"Gary",
    "sg:classifiers":[
        {
            "category":"Education",
            "subcategory":"School",
            "type":"Public Place"
        }
    ],
    "sg:phone":"+1 219 977 2136",
    "sg:postcode":"46406",
    "sg:province":"IN",
    "wof:name":"Invanhoe School",
    "wof:placetype":"venue"
},
  "geometry": {"coordinates":[-87.40772,41.587996],"type":"Point"}
}