{
  "type": "Feature",
  "properties": {
    "iso:country":"US",
    "sg:address":"1 N Governor St",
    "sg:city":"Evansville",
    "sg:classifiers":[
        {
            "category":"Shopping",
            "subcategory":"Gifts & Souvenirs",
            "type":"Retail Goods"
        }
    ],
    "sg:phone":"+1 812 468 8060",
    "sg:postcode":"47711",
    "sg:province":"IN",
    "sg:tags":[
        "collectible"
    ],
    "wof:name":"Kenny's Racing Collectables",
    "wof:placetype":"venue"
},
  "geometry": {"coordinates":[-87.558968,37.977596],"type":"Point"}
}