{
  "type": "Feature",
  "properties": {
    "addr:full":"17 Richmond Ave Richmond IN 47374",
    "addr:housenumber":"17",
    "addr:postcode":"47374",
    "addr:street":"Richmond Ave",
    "iso:country":"US",
    "sg:address":"17 Richmond Ave",
    "sg:city":"Richmond",
    "sg:classifiers":[
        {
            "category":"Retail",
            "subcategory":"Repair Shop",
            "type":"Services"
        }
    ],
    "sg:phone":"+1 765 962 1862",
    "sg:postcode":"47374",
    "sg:province":"IN",
    "sg:tags":[
        "related"
    ],
    "wof:name":"Powell Precision Tool Co LLC",
    "wof:placetype":"venue"
},
  "geometry": {"coordinates":[-84.89829,39.833903],"type":"Point"}
}