{
  "type": "Feature",
  "properties": {
    "addr:full":"6198 E 350 N Monticello IN 47960",
    "addr:housenumber":"6198",
    "addr:postcode":"47960",
    "addr:street":"E 350 N",
    "iso:country":"US",
    "sg:address":"6198 E 350 N",
    "sg:city":"Monticello",
    "sg:classifiers":[
        {
            "category":"Building & Trades",
            "subcategory":"Construction",
            "type":"Services"
        }
    ],
    "sg:phone":"+1 574 583 7405",
    "sg:postcode":"47960",
    "sg:province":"IN",
    "sg:tags":[
        "house",
        "general",
        "contractor"
    ],
    "wof:name":"Quality Construction Inc",
    "wof:placetype":"venue"
},
  "geometry": {"coordinates":[-86.751265,40.803138],"type":"Point"}
}