{
  "type": "Feature",
  "properties": {
    "addr:full":"1205 Old Post Rd Evansville IN 47710",
    "addr:housenumber":"1205",
    "addr:postcode":"47710",
    "addr:street":"Old Post Rd",
    "iso:country":"US",
    "sg:address":"1205 Old Post Rd",
    "sg:city":"Evansville",
    "sg:classifiers":[
        {
            "category":"Building & Trades",
            "subcategory":"Landscaping Services",
            "type":"Services"
        }
    ],
    "sg:phone":"+1 812 422 3362",
    "sg:postcode":"47710",
    "sg:province":"IN",
    "wof:name":"Tom Tracey Lawn Care",
    "wof:placetype":"venue"
},
  "geometry": {"coordinates":[-87.579937,38.030884],"type":"Point"}
}