{
  "type": "Feature",
  "properties": {
    "iso:country":"US",
    "sg:address":"3601 Edison Rd",
    "sg:city":"South Bend",
    "sg:classifiers":[
        {
            "category":"Banks & Credit Unions",
            "subcategory":"Bank",
            "type":"Services"
        }
    ],
    "sg:phone":"+1 574 247 5757",
    "sg:postcode":"46615",
    "sg:province":"IN",
    "sg:tags":[
        "cashing",
        "check"
    ],
    "wof:name":"E$Z Payday Loans Of Fort Wayne",
    "wof:placetype":"venue"
},
  "geometry": {"coordinates":[-86.197862,41.694785],"type":"Point"}
}