{
  "type": "Feature",
  "properties": {
    "iso:country":"US",
    "sg:address":"1601 Indianapolis Ave",
    "sg:city":"Lebanon",
    "sg:classifiers":[
        {
            "category":"Freight",
            "type":"Transportation"
        }
    ],
    "sg:phone":"+1 765 482 5155",
    "sg:postcode":"46052",
    "sg:province":"IN",
    "sg:tags":[
        "commercial",
        "storage"
    ],
    "wof:name":"Secure Storage",
    "wof:placetype":"venue"
},
  "geometry": {"coordinates":[-86.454004,40.035497],"type":"Point"}
}