{
  "type": "Feature",
  "properties": {
    "iso:country":"US",
    "sg:address":"7144 E Virginia St Ste A",
    "sg:city":"Evansville",
    "sg:classifiers":[
        {
            "category":"Banks & Credit Unions",
            "subcategory":"Financial Services",
            "type":"Services"
        }
    ],
    "sg:phone":"+1 812 477 8000",
    "sg:postcode":"47715",
    "sg:province":"IN",
    "sg:tags":[
        "broker",
        "mortgage"
    ],
    "sg:website":"www.mortgagemastersofindiana.com",
    "wof:name":"Mortgage Masters",
    "wof:placetype":"venue"
},
  "geometry": {"coordinates":[-87.46624199999999,37.98141],"type":"Point"}
}