{
  "type": "Feature",
  "properties": {
    "iso:country":"US",
    "sg:address":"1420 Main St",
    "sg:city":"Charlestown",
    "sg:classifiers":[
        {
            "category":"Building & Trades",
            "subcategory":"Construction",
            "type":"Services"
        }
    ],
    "sg:phone":"+1 812 256 3378",
    "sg:postcode":"47111",
    "sg:province":"IN",
    "sg:tags":[
        "waterproofing",
        "contractor"
    ],
    "wof:name":"Weatherall Co Inc",
    "wof:placetype":"venue"
},
  "geometry": {"coordinates":[-85.655298,38.446661],"type":"Point"}
}