{
  "type": "Feature",
  "properties": {
    "addr:full":"9785 Crosspoint Blvd Indianapolis IN 46256",
    "addr:housenumber":"9785",
    "addr:postcode":"46256",
    "addr:street":"Crosspoint Blvd",
    "iso:country":"US",
    "sg:address":"9785 Crosspoint Blvd",
    "sg:city":"Indianapolis",
    "sg:classifiers":[
        {
            "category":"Professional",
            "type":"Services"
        }
    ],
    "sg:phone":"+1 317 913 3900",
    "sg:postcode":"46256",
    "sg:province":"IN",
    "sg:tags":[
        "establishment"
    ],
    "wof:name":"Shared Technologies",
    "wof:placetype":"venue"
},
  "geometry": {"coordinates":[-86.028094,39.9322],"type":"Point"}
}