{
  "type": "Feature",
  "properties": {
    "addr:full":"316 Grant Line Center New Albany IN 47150",
    "addr:housenumber":"316",
    "addr:postcode":"47150",
    "addr:street":"Grant Line Center",
    "iso:country":"US",
    "sg:address":"316 Grant Line Center",
    "sg:city":"New Albany",
    "sg:classifiers":[
        {
            "category":"Banks & Credit Unions",
            "subcategory":"Bank",
            "type":"Services"
        }
    ],
    "sg:phone":"+1 812 944 6288",
    "sg:postcode":"47150",
    "sg:province":"IN",
    "sg:tags":[
        "financing"
    ],
    "wof:name":"Personal Finance Co",
    "wof:placetype":"venue"
},
  "geometry": {"coordinates":[-85.819866,38.323856],"type":"Point"}
}