{
  "type": "Feature",
  "properties": {
    "iso:country":"US",
    "sg:address":"1715 S Memorial Dr",
    "sg:city":"New Castle",
    "sg:classifiers":[
        {
            "category":"Shopping",
            "subcategory":"Department Store",
            "type":"Retail Goods"
        }
    ],
    "sg:phone":"+1 765 521 3020",
    "sg:postcode":"47362",
    "sg:province":"IN",
    "sg:tags":[
        "shop"
    ],
    "sg:website":"www.biglots.com",
    "wof:name":"Big Lots",
    "wof:placetype":"venue"
},
  "geometry": {"coordinates":[-85.384227,39.914878],"type":"Point"}
}