{
  "type": "Feature",
  "properties": {
    "addr:full":"5294 N US Hwy 33 Ligonier IN 46767",
    "addr:housenumber":"5294",
    "addr:postcode":"46767",
    "addr:street":"N Us Hwy 33",
    "iso:country":"US",
    "sg:address":"5294 N US Hwy 33",
    "sg:city":"Ligonier",
    "sg:classifiers":[
        {
            "category":"Education",
            "subcategory":"School",
            "type":"Public Place"
        }
    ],
    "sg:phone":"+1 260 894 3195",
    "sg:postcode":"46767",
    "sg:province":"IN",
    "wof:name":"West Noble Elementary School",
    "wof:placetype":"venue"
},
  "geometry": {"coordinates":[-85.58707099999999,41.429145],"type":"Point"}
}