{
  "type": "Feature",
  "properties": {
    "iso:country":"US",
    "sg:address":"504 Broadway",
    "sg:city":"Gary",
    "sg:classifiers":[
        {
            "category":"Professional",
            "subcategory":"Engineering",
            "type":"Services"
        }
    ],
    "sg:phone":"+1 219 882 6856",
    "sg:postcode":"46402",
    "sg:province":"IN",
    "sg:tags":[
        "engineer"
    ],
    "wof:name":"North-West Engineering",
    "wof:placetype":"venue"
},
  "geometry": {"coordinates":[-87.33723500000001,41.601628],"type":"Point"}
}