{
  "type": "Feature",
  "properties": {
    "iso:country":"US",
    "sg:address":"204 South St",
    "sg:city":"Batesville",
    "sg:classifiers":[
        {
            "category":"Professional",
            "subcategory":"Engineering",
            "type":"Services"
        }
    ],
    "sg:phone":"+1 812 934 5035",
    "sg:postcode":"47006",
    "sg:province":"IN",
    "sg:tags":[
        "engineer"
    ],
    "sg:website":"www.earthtek.com",
    "wof:name":"Earthtek Of Indiana",
    "wof:placetype":"venue"
},
  "geometry": {"coordinates":[-85.222447,39.297064],"type":"Point"}
}