{
  "type": "Feature",
  "properties": {
    "iso:country":"US",
    "sg:address":"427 Front St",
    "sg:city":"Logansport",
    "sg:classifiers":[
        {
            "category":"Insurance",
            "subcategory":"Insurance Agent",
            "type":"Services"
        }
    ],
    "sg:phone":"+1 574 737 8116",
    "sg:postcode":"46947",
    "sg:province":"IN",
    "sg:tags":[
        "adjuster"
    ],
    "wof:name":"Preferred Claims Svc Inc",
    "wof:placetype":"venue"
},
  "geometry": {"coordinates":[-86.373201,40.75208],"type":"Point"}
}