{
  "type": "Feature",
  "properties": {
    "iso:country":"US",
    "sg:address":"3208 S 18th St",
    "sg:city":"Lafayette",
    "sg:classifiers":[
        {
            "category":"Organizations",
            "subcategory":"Community Association",
            "type":"Services"
        }
    ],
    "sg:phone":"+1 765 474 1611",
    "sg:postcode":"47909",
    "sg:province":"IN",
    "sg:tags":[
        "fraternal"
    ],
    "sg:website":"www.foe.com",
    "wof:name":"Fraternal Order Of Eagles",
    "wof:placetype":"venue"
},
  "geometry": {"coordinates":[-86.87623499999999,40.379662],"type":"Point"}
}