{
  "type": "Feature",
  "properties": {
    "iso:country":"US",
    "sg:address":"707 S Main St",
    "sg:city":"Salem",
    "sg:classifiers":[
        {
            "category":"Autos & Motor Vehicles",
            "subcategory":"Motorcycle Sales",
            "type":"Retail Goods"
        }
    ],
    "sg:phone":"+1 812 896 0999",
    "sg:postcode":"47167",
    "sg:province":"IN",
    "sg:tags":[
        "all",
        "terrain"
    ],
    "wof:name":"R & R Quad Sports",
    "wof:placetype":"venue"
},
  "geometry": {"coordinates":[-86.10040600000001,38.598372],"type":"Point"}
}