{
  "type": "Feature",
  "properties": {
    "addr:full":"2976 Scatterfield Rd Anderson IN 46012",
    "addr:housenumber":"2976",
    "addr:postcode":"46012",
    "addr:street":"Scatterfield Rd",
    "iso:country":"US",
    "sg:address":"2976 Scatterfield Rd",
    "sg:city":"Anderson",
    "sg:classifiers":[
        {
            "category":"Real Estate",
            "subcategory":"Real Estate Agent",
            "type":"Services"
        }
    ],
    "sg:phone":"+1 765 644 2622",
    "sg:postcode":"46012",
    "sg:province":"IN",
    "sg:website":"www.cblunsford.com",
    "wof:name":"Coldwell Banker",
    "wof:placetype":"venue"
},
  "geometry": {"coordinates":[-85.669237,40.148673],"type":"Point"}
}