{
  "type": "Feature",
  "properties": {
    "iso:country":"US",
    "sg:address":"4106 W 100 N",
    "sg:city":"Rochester",
    "sg:classifiers":[
        {
            "category":"Shopping",
            "subcategory":"Computers & Home Electronics",
            "type":"Retail Goods"
        }
    ],
    "sg:phone":"+1 574 223 5740",
    "sg:postcode":"46975",
    "sg:province":"IN",
    "wof:name":"Airwave Electronics",
    "wof:placetype":"venue"
},
  "geometry": {"coordinates":[-86.32087799999999,41.069403],"type":"Point"}
}