{
  "type": "Feature",
  "properties": {
    "iso:country":"US",
    "sg:address":"710 N Gardner St",
    "sg:city":"Scottsburg",
    "sg:classifiers":[
        {
            "category":"Banks & Credit Unions",
            "subcategory":"Investment Brokerage",
            "type":"Services"
        }
    ],
    "sg:phone":"+1 812 752 5566",
    "sg:postcode":"47170",
    "sg:province":"IN",
    "sg:tags":[
        "security"
    ],
    "wof:name":"Edward Jones Investments",
    "wof:placetype":"venue"
},
  "geometry": {"coordinates":[-85.78160800000001,38.695594],"type":"Point"}
}