{
  "type": "Feature",
  "properties": {
    "iso:country":"US",
    "sg:address":"8900 Keystone Xing",
    "sg:city":"Indianapolis",
    "sg:classifiers":[
        {
            "category":"Wholesale",
            "subcategory":"Hardware",
            "type":"Manufacturing & Wholesale Goods"
        }
    ],
    "sg:phone":"+1 317 574 4500",
    "sg:postcode":"46240",
    "sg:province":"IN",
    "sg:tags":[
        "hardware-wholesale",
        "manufacturer"
    ],
    "wof:name":"Kallmyer J Brad",
    "wof:placetype":"venue"
},
  "geometry": {"coordinates":[-86.109596,39.917881],"type":"Point"}
}