{
  "type": "Feature",
  "properties": {
    "iso:country":"US",
    "sg:address":"2534 W 16th St",
    "sg:city":"Indianapolis",
    "sg:classifiers":[
        {
            "category":"Retail",
            "subcategory":"Auto Repair",
            "type":"Services"
        }
    ],
    "sg:phone":"+1 317 635 3764",
    "sg:postcode":"46222",
    "sg:province":"IN",
    "sg:tags":[
        "body",
        "automobile",
        "painting"
    ],
    "wof:name":"Speedway Body Shop",
    "wof:placetype":"venue"
},
  "geometry": {"coordinates":[-86.203807,39.788037],"type":"Point"}
}