{
  "type": "Feature",
  "properties": {
    "iso:country":"US",
    "sg:address":"14550 Clay Terrace Blvd",
    "sg:city":"Carmel",
    "sg:classifiers":[
        {
            "category":"Shopping",
            "subcategory":"Clothing, Apparel, & Fashions",
            "type":"Retail Goods"
        }
    ],
    "sg:phone":"+1 317 569 0127",
    "sg:postcode":"46032",
    "sg:province":"IN",
    "sg:tags":[
        "item",
        "boutique"
    ],
    "wof:name":"Claire's",
    "wof:placetype":"venue"
},
  "geometry": {"coordinates":[-86.130023,39.999273],"type":"Point"}
}