{
  "type": "Feature",
  "properties": {
    "addr:full":"5814 S Arlington Ave Indianapolis IN 46237",
    "addr:housenumber":"5814",
    "addr:postcode":"46237",
    "addr:street":"S Arlington Ave",
    "iso:country":"US",
    "sg:address":"5814 S Arlington Ave",
    "sg:city":"Indianapolis",
    "sg:classifiers":[
        {
            "category":"Education",
            "subcategory":"School",
            "type":"Public Place"
        }
    ],
    "sg:phone":"+1 317 782 4274",
    "sg:postcode":"46237",
    "sg:province":"IN",
    "wof:name":"Arlington Elementary School",
    "wof:placetype":"venue"
},
  "geometry": {"coordinates":[-86.063605,39.683039],"type":"Point"}
}