{
  "type": "Feature",
  "properties": {
    "iso:country":"US",
    "sg:address":"617 N 13th St",
    "sg:city":"Decatur",
    "sg:classifiers":[
        {
            "category":"Personal",
            "subcategory":"Beauty Salon",
            "type":"Services"
        }
    ],
    "sg:phone":"+1 260 724 8364",
    "sg:postcode":"46733",
    "sg:province":"IN",
    "wof:name":"Famous Hair",
    "wof:placetype":"venue"
},
  "geometry": {"coordinates":[-84.937836,40.836034],"type":"Point"}
}