{
  "type": "Feature",
  "properties": {
    "iso:country":"US",
    "sg:address":"9495 Keilman St",
    "sg:city":"St John",
    "sg:classifiers":[
        {
            "category":"Organizations",
            "subcategory":"Religious Organization",
            "type":"Services"
        }
    ],
    "sg:phone":"+1 219 558 2488",
    "sg:postcode":"46373",
    "sg:province":"IN",
    "sg:tags":[
        "church"
    ],
    "wof:name":"Harvest Ridge Church",
    "wof:placetype":"venue"
},
  "geometry": {"coordinates":[-87.472399,41.446535],"type":"Point"}
}