{
  "type": "Feature",
  "properties": {
    "addr:full":"101 W Ohio St Suite 2100 Indianapolis IN 46204",
    "addr:housenumber":"101",
    "addr:postcode":"46204",
    "addr:street":"W Ohio St Suite 2100",
    "iso:country":"US",
    "sg:address":"101 W Ohio St Suite 2100",
    "sg:city":"Indianapolis",
    "sg:classifiers":[
        {
            "category":"Professional",
            "subcategory":"Lawyer & Legal Services",
            "type":"Services"
        }
    ],
    "sg:phone":"+1 317 262 1001",
    "sg:postcode":"46204",
    "sg:province":"IN",
    "sg:tags":[
        "attorney",
        "business",
        "planning",
        "real estate",
        "law"
    ],
    "wof:name":"Schooley, J Bradley - Hostetler & Kowalik Pc",
    "wof:placetype":"venue"
},
  "geometry": {"coordinates":[-86.15979799999999,39.769951],"type":"Point"}
}