{
  "type": "Feature",
  "properties": {
    "iso:country":"US",
    "sg:address":"6679 E State Rd 164",
    "sg:city":"Celestine",
    "sg:classifiers":[
        {
            "category":"Restaurant",
            "type":"Food & Drink"
        }
    ],
    "sg:phone":"+1 812 482 6339",
    "sg:postcode":"47521",
    "sg:province":"IN",
    "wof:name":"Miller's Restaurant",
    "wof:placetype":"venue"
},
  "geometry": {"coordinates":[-86.779904,38.384945],"type":"Point"}
}