{
  "type": "Feature",
  "properties": {
    "iso:country":"US",
    "sg:address":"10998 E State Rd 18",
    "sg:city":"Galveston",
    "sg:classifiers":[
        {
            "category":"Home & Garden",
            "subcategory":"Garden Supply",
            "type":"Retail Goods"
        }
    ],
    "sg:phone":"+1 574 699 6571",
    "sg:postcode":"46932",
    "sg:province":"IN",
    "sg:tags":[
        "lawn",
        "mower"
    ],
    "wof:name":"Maple Grove Sales & Repair Svc",
    "wof:placetype":"venue"
},
  "geometry": {"coordinates":[-86.172528,40.584343],"type":"Point"}
}