{
  "type": "Feature",
  "properties": {
    "iso:country":"US",
    "sg:address":"7707 Records St",
    "sg:city":"Indianapolis",
    "sg:classifiers":[
        {
            "category":"Home & Garden",
            "subcategory":"Building Materials",
            "type":"Retail Goods"
        }
    ],
    "sg:phone":"+1 317 547 5467",
    "sg:postcode":"46226",
    "sg:province":"IN",
    "sg:tags":[
        "glass",
        "window",
        "plate"
    ],
    "wof:name":"American Art Glass & Mirror",
    "wof:placetype":"venue"
},
  "geometry": {"coordinates":[-86.029802,39.837253],"type":"Point"}
}