{
  "type": "Feature",
  "properties": {
    "iso:country":"US",
    "sg:address":"415 E Washington St",
    "sg:city":"Muncie",
    "sg:classifiers":[
        {
            "category":"Retail",
            "subcategory":"Funeral Services",
            "type":"Services"
        }
    ],
    "sg:phone":"+1 765 288 6669",
    "sg:postcode":"47305",
    "sg:province":"IN",
    "sg:tags":[
        "director"
    ],
    "sg:website":"www.meeksmortuary.com",
    "wof:name":"Meeks Mortuary",
    "wof:placetype":"venue"
},
  "geometry": {"coordinates":[-85.381847,40.194396],"type":"Point"}
}