{
  "type": "Feature",
  "properties": {
    "iso:country":"US",
    "sg:address":"1535 W Center St",
    "sg:city":"Warsaw",
    "sg:classifiers":[
        {
            "category":"Manufacturing",
            "subcategory":"Glass & Minerals",
            "type":"Manufacturing & Wholesale Goods"
        }
    ],
    "sg:phone":"+1 574 267 6121",
    "sg:postcode":"46580",
    "sg:province":"IN",
    "sg:tags":[
        "container"
    ],
    "wof:name":"Kimble Glass Inc",
    "wof:placetype":"venue"
},
  "geometry": {"coordinates":[-85.880835,41.239611],"type":"Point"}
}