{
  "type": "Feature",
  "properties": {
    "iso:country":"US",
    "sg:address":"451 N Old State Rd 67",
    "sg:city":"Mooresville",
    "sg:classifiers":[
        {
            "category":"Organizations",
            "subcategory":"Community Association",
            "type":"Services"
        }
    ],
    "sg:phone":"+1 317 831 5023",
    "sg:postcode":"46158",
    "sg:province":"IN",
    "sg:tags":[
        "fraternal"
    ],
    "wof:name":"Fraternal Order Of Eagles",
    "wof:placetype":"venue"
},
  "geometry": {"coordinates":[-86.37150699999999,39.553796],"type":"Point"}
}