{
  "type": "Feature",
  "properties": {
    "iso:country":"US",
    "sg:address":"2643 Highway Ave",
    "sg:city":"Highland",
    "sg:classifiers":[
        {
            "category":"Building & Trades",
            "subcategory":"Plumbing",
            "type":"Services"
        }
    ],
    "sg:phone":"+1 219 838 7700",
    "sg:postcode":"46322",
    "sg:province":"IN",
    "sg:tags":[
        "conditioning",
        "air",
        "system",
        "contractor"
    ],
    "wof:name":"Popa Sheet Metal Inc",
    "wof:placetype":"venue"
},
  "geometry": {"coordinates":[-87.464873,41.555593],"type":"Point"}
}