{
  "type": "Feature",
  "properties": {
    "iso:country":"US",
    "sg:address":"906 Broad St",
    "sg:city":"New Castle",
    "sg:classifiers":[
        {
            "category":"Shopping",
            "subcategory":"Department Store",
            "type":"Retail Goods"
        }
    ],
    "sg:phone":"+1 765 529 8108",
    "sg:postcode":"47362",
    "sg:province":"IN",
    "sg:tags":[
        "shop"
    ],
    "wof:name":"Dollar General",
    "wof:placetype":"venue"
},
  "geometry": {"coordinates":[-85.375065,39.931394],"type":"Point"}
}