{
  "type": "Feature",
  "properties": {
    "iso:country":"US",
    "sg:address":"16950 Joliet Rd",
    "sg:city":"Westfield",
    "sg:classifiers":[
        {
            "category":"Recreation",
            "type":"Entertainment"
        }
    ],
    "sg:phone":"+1 317 896 5540",
    "sg:postcode":"46074",
    "sg:province":"IN",
    "sg:tags":[
        "instruction",
        "golf"
    ],
    "wof:name":"Tague Golf",
    "wof:placetype":"venue"
},
  "geometry": {"coordinates":[-86.231329,40.032326],"type":"Point"}
}