{
  "type": "Feature",
  "properties": {
    "iso:country":"US",
    "sg:address":"11299 N State Rd 15",
    "sg:city":"Milford",
    "sg:classifiers":[
        {
            "category":"Local Transit",
            "type":"Transportation"
        }
    ],
    "sg:phone":"+1 574 658 9409",
    "sg:postcode":"46542",
    "sg:province":"IN",
    "wof:name":"Hoosier Transit & Tollable",
    "wof:placetype":"venue"
},
  "geometry": {"coordinates":[-85.855189,41.394743],"type":"Point"}
}