{
  "type": "Feature",
  "properties": {
    "iso:country":"US",
    "sg:address":"5645 Castle Creek Parkway North",
    "sg:city":"Indianapolis",
    "sg:classifiers":[
        {
            "category":"Real Estate",
            "subcategory":"Real Estate Services",
            "type":"Services"
        },
        {
            "category":"Real Estate",
            "subcategory":"Real Estate Agent",
            "type":"Services"
        },
        {
            "category":"Professional",
            "type":"Services"
        }
    ],
    "sg:phone":"+1 317 819 3300",
    "sg:postcode":"46250",
    "sg:province":"IN",
    "sg:tags":[
        "information",
        "consultant",
        "relocation",
        "broker",
        "buyer",
        "referral"
    ],
    "sg:website":"http://www.remax.com",
    "wof:name":"Carole Liszak - RE/MAX Legends Group",
    "wof:placetype":"venue"
},
  "geometry": {"coordinates":[-86.071457,39.915462],"type":"Point"}
}