{
  "type": "Feature",
  "properties": {
    "iso:country":"US",
    "sg:address":"14 N Shield St",
    "sg:city":"Knox",
    "sg:classifiers":[
        {
            "category":"Education",
            "subcategory":"Dance Studio",
            "type":"Public Place"
        }
    ],
    "sg:phone":"+1 574 772 4050",
    "sg:postcode":"46534",
    "sg:province":"IN",
    "sg:tags":[
        "instruction",
        "dancing"
    ],
    "wof:name":"Sandra Lee Studio Of Dance",
    "wof:placetype":"venue"
},
  "geometry": {"coordinates":[-86.624266,41.29826],"type":"Point"}
}