{
  "type": "Feature",
  "properties": {
    "iso:country":"US",
    "sg:address":"1420 S Grand Ave",
    "sg:city":"Evansville",
    "sg:classifiers":[
        {
            "category":"Shopping",
            "subcategory":"Clothing, Apparel, & Fashions",
            "type":"Retail Goods"
        }
    ],
    "sg:phone":"+1 812 426 1944",
    "sg:postcode":"47713",
    "sg:province":"IN",
    "wof:name":"Barbs Variety Shoppe",
    "wof:placetype":"venue"
},
  "geometry": {"coordinates":[-87.548935,37.957573],"type":"Point"}
}