{
  "type": "Feature",
  "properties": {
    "iso:country":"US",
    "sg:address":"1901 Lakeview Dr",
    "sg:city":"Fort Wayne",
    "sg:classifiers":[
        {
            "category":"Manufacturing",
            "subcategory":"Chemicals & Compounds",
            "type":"Manufacturing & Wholesale Goods"
        }
    ],
    "sg:phone":"+1 260 432 9467",
    "sg:postcode":"46808",
    "sg:province":"IN",
    "sg:website":"www.craftlabs.com",
    "wof:name":"Craft Laboratories Inc",
    "wof:placetype":"venue"
},
  "geometry": {"coordinates":[-85.174375,41.09412],"type":"Point"}
}