{
  "type": "Feature",
  "properties": {
    "iso:country":"US",
    "sg:address":"4510 Maplecrest Rd",
    "sg:city":"Fort Wayne",
    "sg:classifiers":[
        {
            "category":"Restaurant",
            "type":"Food & Drink"
        }
    ],
    "sg:menulink":"http://www.allmenus.com/in/st-joseph/167318-burger-king/menu/",
    "sg:phone":"+1 219 485 4899",
    "sg:postcode":"46835",
    "sg:province":"IN",
    "sg:tags":[
        "burger",
        "american"
    ],
    "wof:name":"Burger King",
    "wof:placetype":"venue"
},
  "geometry": {"coordinates":[-85.061646,41.120734],"type":"Point"}
}