{
  "type": "Feature",
  "properties": {
    "iso:country":"US",
    "sg:address":"7030 State Rd 311",
    "sg:city":"Sellersburg",
    "sg:classifiers":[
        {
            "category":"Wholesale",
            "subcategory":"Electrical",
            "type":"Manufacturing & Wholesale Goods"
        }
    ],
    "sg:phone":"+1 812 246 6460",
    "sg:postcode":"47172",
    "sg:province":"IN",
    "sg:tags":[
        "television"
    ],
    "wof:name":"Television Systems",
    "wof:placetype":"venue"
},
  "geometry": {"coordinates":[-85.77276500000001,38.37381],"type":"Point"}
}