{
  "type": "Feature",
  "properties": {
    "iso:country":"US",
    "sg:address":"234 S Franklin Rd",
    "sg:city":"Indianapolis",
    "sg:classifiers":[
        {
            "category":"Autos & Motor Vehicles",
            "subcategory":"Boat Sales",
            "type":"Retail Goods"
        }
    ],
    "sg:phone":"+1 317 352 1656",
    "sg:postcode":"46219",
    "sg:province":"IN",
    "sg:tags":[
        "dealer",
        "sales"
    ],
    "sg:website":"www.justaddwaterboats.com",
    "wof:name":"Just Add Water Boats",
    "wof:placetype":"venue"
},
  "geometry": {"coordinates":[-86.026261,39.765298],"type":"Point"}
}