{
  "type": "Feature",
  "properties": {
    "iso:country":"US",
    "sg:address":"4659 US Hwy 50",
    "sg:city":"Seymour",
    "sg:classifiers":[
        {
            "category":"Farming",
            "subcategory":"Dairy Farm",
            "type":"Manufacturing & Wholesale Goods"
        }
    ],
    "sg:phone":"+1 812 522 4449",
    "sg:postcode":"47274",
    "sg:province":"IN",
    "wof:name":"Moore Dairy",
    "wof:placetype":"venue"
},
  "geometry": {"coordinates":[-85.945665,38.930632],"type":"Point"}
}