{
  "type": "Feature",
  "properties": {
    "addr:full":"841 N Green St Brownsburg IN 46112",
    "addr:housenumber":"841",
    "addr:postcode":"46112",
    "addr:street":"N Green St",
    "iso:country":"US",
    "sg:address":"841 N Green St",
    "sg:city":"Brownsburg",
    "sg:classifiers":[
        {
            "category":"Shopping",
            "type":"Retail Goods"
        }
    ],
    "sg:phone":"+1 317 858 1777",
    "sg:postcode":"46112",
    "sg:province":"IN",
    "sg:tags":[
        "telephone",
        "cellular"
    ],
    "wof:name":"Communication One Inc",
    "wof:placetype":"venue"
},
  "geometry": {"coordinates":[-86.394683,39.852242],"type":"Point"}
}