{
  "type": "Feature",
  "properties": {
    "iso:country":"US",
    "sg:address":"1210 Bedford Rd",
    "sg:city":"Washington",
    "sg:classifiers":[
        {
            "category":"Wholesale",
            "subcategory":"Non-durable Goods",
            "type":"Manufacturing & Wholesale Goods"
        }
    ],
    "sg:phone":"+1 812 254 9099",
    "sg:postcode":"47501",
    "sg:province":"IN",
    "wof:name":"Francine Heckert",
    "wof:placetype":"venue"
},
  "geometry": {"coordinates":[-87.162126,38.660224],"type":"Point"}
}