{
  "type": "Feature",
  "properties": {
    "iso:country":"US",
    "sg:address":"7648 Camelback Dr",
    "sg:city":"Indianapolis",
    "sg:classifiers":[
        {
            "category":"Wholesale",
            "subcategory":"Durable Goods & Equipment",
            "type":"Manufacturing & Wholesale Goods"
        }
    ],
    "sg:phone":"+1 317 841 9280",
    "sg:postcode":"46250",
    "sg:province":"IN",
    "sg:tags":[
        "representative",
        "manufacturer"
    ],
    "wof:name":"Mab & Assoc Inc",
    "wof:placetype":"venue"
},
  "geometry": {"coordinates":[-86.06419,39.894278],"type":"Point"}
}