{
  "type": "Feature",
  "properties": {
    "addr:full":"1112 S Westwood Dr La Porte IN 46350",
    "addr:housenumber":"1112",
    "addr:postcode":"46350",
    "addr:street":"S Westwood Dr",
    "iso:country":"US",
    "sg:address":"1112 S Westwood Dr",
    "sg:city":"La Porte",
    "sg:classifiers":[
        {
            "category":"Home & Garden",
            "subcategory":"Carpets & Floor Coverings",
            "type":"Retail Goods"
        }
    ],
    "sg:phone":"+1 219 324 4399",
    "sg:postcode":"46350",
    "sg:province":"IN",
    "wof:name":"Cook Carpet",
    "wof:placetype":"venue"
},
  "geometry": {"coordinates":[-86.748627,41.588951],"type":"Point"}
}