{
  "type": "Feature",
  "properties": {
    "iso:country":"US",
    "sg:address":"1800 N Franklin Rd",
    "sg:city":"Indianapolis",
    "sg:classifiers":[
        {
            "category":"Education",
            "subcategory":"School",
            "type":"Public Place"
        }
    ],
    "sg:phone":"+1 317 532 3800",
    "sg:postcode":"46219",
    "sg:province":"IN",
    "wof:name":"Pleasant Run Elementary School",
    "wof:placetype":"venue"
},
  "geometry": {"coordinates":[-86.025274,39.793927],"type":"Point"}
}