{
  "type": "Feature",
  "properties": {
    "addr:full":"2809 W Godman Ave Muncie IN 47304",
    "addr:housenumber":"2809",
    "addr:postcode":"47304",
    "addr:street":"W Godman Ave",
    "iso:country":"US",
    "sg:address":"2809 W Godman Ave",
    "sg:city":"Muncie",
    "sg:classifiers":[
        {
            "category":"Personal",
            "type":"Services"
        }
    ],
    "sg:phone":"+1 765 287 1015",
    "sg:postcode":"47304",
    "sg:province":"IN",
    "sg:tags":[
        "paying",
        "bill"
    ],
    "wof:name":"Ambulance Billing Svc",
    "wof:placetype":"venue"
},
  "geometry": {"coordinates":[-85.420252,40.18941],"type":"Point"}
}