{
  "type": "Feature",
  "properties": {
    "iso:country":"US",
    "sg:address":"620 S Seminary St",
    "sg:city":"Bloomfield",
    "sg:classifiers":[
        {
            "category":"Building & Trades",
            "subcategory":"Construction",
            "type":"Services"
        }
    ],
    "sg:phone":"+1 812 384 8939",
    "sg:postcode":"47424",
    "sg:province":"IN",
    "sg:tags":[
        "house"
    ],
    "wof:name":"Wright Construction",
    "wof:placetype":"venue"
},
  "geometry": {"coordinates":[-86.941176,39.02091],"type":"Point"}
}