{
  "type": "Feature",
  "properties": {
    "iso:country":"US",
    "sg:address":"5201 S Camden Dr",
    "sg:city":"Fort Wayne",
    "sg:classifiers":[
        {
            "category":"Organizations",
            "subcategory":"Religious Organization",
            "type":"Services"
        }
    ],
    "sg:phone":"+1 260 482 1596",
    "sg:postcode":"46825",
    "sg:province":"IN",
    "sg:tags":[
        "church"
    ],
    "sg:website":"www.northchristian.com",
    "wof:name":"North Christian Church",
    "wof:placetype":"venue"
},
  "geometry": {"coordinates":[-85.134284,41.126222],"type":"Point"}
}