{
  "type": "Feature",
  "properties": {
    "iso:country":"US",
    "sg:address":"3213 Ivory Way",
    "sg:city":"Indianapolis",
    "sg:classifiers":[
        {
            "category":"Professional",
            "subcategory":"Computer Services",
            "type":"Services"
        }
    ],
    "sg:phone":"+1 317 888 6134",
    "sg:postcode":"46227",
    "sg:province":"IN",
    "sg:tags":[
        "consulting",
        "related"
    ],
    "wof:name":"Indy Computery",
    "wof:placetype":"venue"
},
  "geometry": {"coordinates":[-86.107643,39.654457],"type":"Point"}
}