{
  "type": "Feature",
  "properties": {
    "iso:country":"US",
    "sg:address":"3601 Timber Bridge Dr",
    "sg:city":"Valparaiso",
    "sg:classifiers":[
        {
            "category":"Food & Beverages",
            "subcategory":"Groceries & Convenience Stores",
            "type":"Retail Goods"
        }
    ],
    "sg:phone":"+1 219 462 3354",
    "sg:postcode":"46383",
    "sg:province":"IN",
    "wof:name":"C Noabert Stores Inc",
    "wof:placetype":"venue"
},
  "geometry": {"coordinates":[-87.038425,41.501436],"type":"Point"}
}