{
  "type": "Feature",
  "properties": {
    "iso:country":"US",
    "sg:address":"9707 W US Hwy 24",
    "sg:city":"Wolcott",
    "sg:classifiers":[
        {
            "category":"Personal",
            "subcategory":"Tanning Parlor",
            "type":"Services"
        }
    ],
    "sg:phone":"+1 219 279 2091",
    "sg:postcode":"47995",
    "sg:province":"IN",
    "sg:tags":[
        "salon"
    ],
    "wof:name":"Endless Sun-Tanning & More",
    "wof:placetype":"venue"
},
  "geometry": {"coordinates":[-87.052901,40.765161],"type":"Point"}
}