{
  "type": "Feature",
  "properties": {
    "iso:country":"US",
    "sg:address":"402 Highland Dr",
    "sg:city":"Valparaiso",
    "sg:classifiers":[
        {
            "category":"Building & Trades",
            "subcategory":"Construction",
            "type":"Services"
        }
    ],
    "sg:phone":"+1 219 464 8377",
    "sg:postcode":"46383",
    "sg:province":"IN",
    "sg:tags":[
        "general",
        "contractor"
    ],
    "wof:name":"Richard's Construction Mgmt",
    "wof:placetype":"venue"
},
  "geometry": {"coordinates":[-87.05624400000001,41.503188],"type":"Point"}
}