{
  "type": "Feature",
  "properties": {
    "addr:full":"6320 W 38th St Indianapolis IN 46254",
    "addr:housenumber":"6320",
    "addr:postcode":"46254",
    "addr:street":"W 38Th St",
    "iso:country":"US",
    "sg:address":"6320 W 38th St",
    "sg:city":"Indianapolis",
    "sg:classifiers":[
        {
            "category":"Ice Cream",
            "type":"Food & Drink"
        }
    ],
    "sg:menulink":"http://www.allmenus.com/in/pike/161701-dairy-queen/menu/",
    "sg:phone":"+1 317 293 3764",
    "sg:postcode":"46254",
    "sg:province":"IN",
    "sg:tags":[
        "burger",
        "american"
    ],
    "wof:name":"Dairy Queen",
    "wof:placetype":"venue"
},
  "geometry": {"coordinates":[-86.270377,39.823592],"type":"Point"}
}