{
  "type": "Feature",
  "properties": {
    "iso:country":"US",
    "sg:address":"7719 Waite St",
    "sg:city":"Merrillville",
    "sg:classifiers":[
        {
            "category":"Professional",
            "subcategory":"Business Services",
            "type":"Services"
        }
    ],
    "sg:phone":"+1 219 756 2973",
    "sg:postcode":"46410",
    "sg:province":"IN",
    "wof:name":"Pp Ltd Partnership",
    "wof:placetype":"venue"
},
  "geometry": {"coordinates":[-87.37564399999999,41.477601],"type":"Point"}
}