{
  "type": "Feature",
  "properties": {
    "iso:country":"US",
    "sg:address":"516 N Detroit St",
    "sg:city":"Lagrange",
    "sg:classifiers":[
        {
            "category":"Retail",
            "subcategory":"Portrait Studio",
            "type":"Services"
        }
    ],
    "sg:phone":"+1 260 463 2021",
    "sg:postcode":"46761",
    "sg:province":"IN",
    "sg:tags":[
        "photographer"
    ],
    "wof:name":"Stopher-King Photography Std",
    "wof:placetype":"venue"
},
  "geometry": {"coordinates":[-85.417851,41.648495],"type":"Point"}
}