{
  "type": "Feature",
  "properties": {
    "iso:country":"US",
    "sg:address":"4955 W Washington St",
    "sg:city":"Indianapolis",
    "sg:classifiers":[
        {
            "category":"Personal",
            "subcategory":"Beauty Salon",
            "type":"Services"
        }
    ],
    "sg:phone":"+1 317 247 0969",
    "sg:postcode":"46241",
    "sg:province":"IN",
    "sg:tags":[
        "shop"
    ],
    "wof:name":"Hairkeeper",
    "wof:placetype":"venue"
},
  "geometry": {"coordinates":[-86.243851,39.754701],"type":"Point"}
}