{
  "type": "Feature",
  "properties": {
    "iso:country":"US",
    "sg:address":"3701 W 16th St",
    "sg:city":"Indianapolis",
    "sg:classifiers":[
        {
            "category":"Bars & Pubs",
            "type":"Food & Drink"
        }
    ],
    "sg:phone":"+1 317 631 8807",
    "sg:postcode":"46222",
    "sg:province":"IN",
    "wof:name":"Mike's Speedway Lounge",
    "wof:placetype":"venue"
},
  "geometry": {"coordinates":[-86.224724,39.787651],"type":"Point"}
}