{
  "type": "Feature",
  "properties": {
    "iso:country":"US",
    "sg:address":"404 Industrial Dr",
    "sg:city":"Griffith",
    "sg:classifiers":[
        {
            "category":"Wholesale",
            "subcategory":"Machinery & Supplies",
            "type":"Manufacturing & Wholesale Goods"
        }
    ],
    "sg:phone":"+1 219 922 0191",
    "sg:postcode":"46319",
    "sg:province":"IN",
    "sg:tags":[
        "dry wall",
        "contractor"
    ],
    "wof:name":"Accurate Building",
    "wof:placetype":"venue"
},
  "geometry": {"coordinates":[-87.431324,41.520452],"type":"Point"}
}