{
  "type": "Feature",
  "properties": {
    "addr:full":"101 N Main St Batesville IN 47006",
    "addr:housenumber":"101",
    "addr:postcode":"47006",
    "addr:street":"N Main St",
    "iso:country":"US",
    "sg:address":"101 N Main St",
    "sg:city":"Batesville",
    "sg:classifiers":[
        {
            "category":"Restaurant",
            "type":"Food & Drink"
        }
    ],
    "sg:phone":"+1 812 934 2201",
    "sg:postcode":"47006",
    "sg:province":"IN",
    "wof:name":"Snikkers & Peanuts",
    "wof:placetype":"venue"
},
  "geometry": {"coordinates":[-85.22141499999999,39.300063],"type":"Point"}
}