{
  "type": "Feature",
  "properties": {
    "iso:country":"US",
    "sg:address":"1464 W Winona Ave",
    "sg:city":"Marion",
    "sg:classifiers":[
        {
            "category":"Retail",
            "subcategory":"Auto Repair",
            "type":"Services"
        }
    ],
    "sg:phone":"+1 765 664 1622",
    "sg:postcode":"46952",
    "sg:province":"IN",
    "sg:tags":[
        "repairing",
        "automobile"
    ],
    "wof:name":"Reed's Automotive",
    "wof:placetype":"venue"
},
  "geometry": {"coordinates":[-85.676627,40.566966],"type":"Point"}
}