{
  "type": "Feature",
  "properties": {
    "iso:country":"US",
    "sg:address":"3335 Scatterfield Rd",
    "sg:city":"Anderson",
    "sg:classifiers":[
        {
            "category":"Home & Garden",
            "subcategory":"Building Materials",
            "type":"Retail Goods"
        }
    ],
    "sg:phone":"+1 765 641 2586",
    "sg:postcode":"46013",
    "sg:province":"IN",
    "sg:tags":[
        "center"
    ],
    "wof:name":"Lowe's",
    "wof:placetype":"venue"
},
  "geometry": {"coordinates":[-85.652829,40.079555],"type":"Point"}
}