{
  "type": "Feature",
  "properties": {
    "addr:full":"414 3rd St Aurora IN 47001",
    "addr:housenumber":"414",
    "addr:postcode":"47001",
    "addr:street":"3Rd St",
    "iso:country":"US",
    "sg:address":"414 3rd St",
    "sg:city":"Aurora",
    "sg:classifiers":[
        {
            "category":"Manufacturing",
            "subcategory":"Printing",
            "type":"Manufacturing & Wholesale Goods"
        }
    ],
    "sg:phone":"+1 812 926 0063",
    "sg:postcode":"47001",
    "sg:province":"IN",
    "sg:tags":[
        "newspaper"
    ],
    "wof:name":"Journal Press",
    "wof:placetype":"venue"
},
  "geometry": {"coordinates":[-84.90186199999999,39.055798],"type":"Point"}
}