{
  "type": "Feature",
  "properties": {
    "iso:country":"US",
    "sg:address":"1736 E Riverside Dr",
    "sg:city":"Evansville",
    "sg:classifiers":[
        {
            "category":"Building & Trades",
            "subcategory":"Plumbing",
            "type":"Services"
        }
    ],
    "sg:phone":"+1 812 476 8426",
    "sg:postcode":"47714",
    "sg:province":"IN",
    "sg:tags":[
        "conditioning",
        "air",
        "system",
        "contractor"
    ],
    "wof:name":"A B White & Son",
    "wof:placetype":"venue"
},
  "geometry": {"coordinates":[-87.533765,37.945395],"type":"Point"}
}