{
  "type": "Feature",
  "properties": {
    "iso:country":"US",
    "sg:address":"10158 Delmar St",
    "sg:city":"Saint John",
    "sg:classifiers":[
        {
            "category":"Shopping",
            "subcategory":"Computers & Home Electronics",
            "type":"Retail Goods"
        }
    ],
    "sg:phone":"+1 219 365 0300",
    "sg:postcode":"46373",
    "sg:province":"IN",
    "sg:tags":[
        "equipment",
        "rental",
        "musical"
    ],
    "wof:name":"Disc Jockey Depot Incorporated",
    "wof:placetype":"venue"
},
  "geometry": {"coordinates":[-87.485378,41.434299],"type":"Point"}
}