{
  "type": "Feature",
  "properties": {
    "iso:country":"US",
    "sg:address":"921 S Penn St",
    "sg:city":"Muncie",
    "sg:classifiers":[
        {
            "category":"Organizations",
            "subcategory":"Religious Organization",
            "type":"Services"
        }
    ],
    "sg:phone":"+1 765 284 8531",
    "sg:postcode":"47302",
    "sg:province":"IN",
    "wof:name":"Original Church of God",
    "wof:placetype":"venue"
},
  "geometry": {"coordinates":[-85.372864,40.185833],"type":"Point"}
}