{
  "type": "Feature",
  "properties": {
    "iso:country":"US",
    "sg:address":"934 S Nebraska St",
    "sg:city":"Marion",
    "sg:classifiers":[
        {
            "category":"Manufacturing",
            "subcategory":"Metals",
            "type":"Manufacturing & Wholesale Goods"
        }
    ],
    "sg:phone":"+1 765 671 9847",
    "sg:postcode":"46953",
    "sg:province":"IN",
    "sg:tags":[
        "fabricator",
        "sheet"
    ],
    "wof:name":"Diamond K Sheet Metal",
    "wof:placetype":"venue"
},
  "geometry": {"coordinates":[-85.663439,40.55212],"type":"Point"}
}