{
  "type": "Feature",
  "properties": {
    "iso:country":"US",
    "sg:address":"4211 First Flight Cir",
    "sg:city":"Zionsville",
    "sg:classifiers":[
        {
            "category":"Home & Garden",
            "subcategory":"Garden Supply",
            "type":"Retail Goods"
        }
    ],
    "sg:phone":"+1 317 733 8587",
    "sg:postcode":"46077",
    "sg:province":"IN",
    "sg:tags":[
        "sprinkler"
    ],
    "wof:name":"Push Button Rain Inc",
    "wof:placetype":"venue"
},
  "geometry": {"coordinates":[-86.252661,39.981195],"type":"Point"}
}