{
  "type": "Feature",
  "properties": {
    "iso:country":"US",
    "sg:address":"2511 S Pleasant Valley Ct",
    "sg:city":"Monticello",
    "sg:classifiers":[
        {
            "category":"Professional",
            "subcategory":"Accounting & Tax Preparation",
            "type":"Services"
        }
    ],
    "sg:phone":"+1 574 583 8341",
    "sg:postcode":"47960",
    "sg:province":"IN",
    "sg:tags":[
        "return",
        "filing"
    ],
    "wof:name":"Marilee Goad Tax Svc & Real",
    "wof:placetype":"venue"
},
  "geometry": {"coordinates":[-86.761408,40.706461],"type":"Point"}
}