{
  "type": "Feature",
  "properties": {
    "iso:country":"US",
    "sg:address":"3965 W 106th St",
    "sg:city":"Carmel",
    "sg:classifiers":[
        {
            "category":"Health Services",
            "subcategory":"Optometrist",
            "type":"Services"
        }
    ],
    "sg:phone":"+1 317 875 9339",
    "sg:postcode":"46032",
    "sg:province":"IN",
    "wof:name":"Eyedentity",
    "wof:placetype":"venue"
},
  "geometry": {"coordinates":[-86.229046,39.940808],"type":"Point"}
}