{
  "type": "Feature",
  "properties": {
    "iso:country":"US",
    "sg:address":"56365 Peppermint Rd",
    "sg:city":"South Bend",
    "sg:classifiers":[
        {
            "category":"Social Services",
            "subcategory":"Job Training",
            "type":"Services"
        }
    ],
    "sg:phone":"+1 574 233 1721",
    "sg:postcode":"46619",
    "sg:province":"IN",
    "sg:tags":[
        "apprenticeship",
        "program"
    ],
    "wof:name":"South Bend & Vicinity Elec",
    "wof:placetype":"venue"
},
  "geometry": {"coordinates":[-86.357259,41.677109],"type":"Point"}
}