{
  "type": "Feature",
  "properties": {
    "iso:country":"US",
    "sg:address":"4686 S US Hwy 41",
    "sg:city":"Terre Haute",
    "sg:classifiers":[
        {
            "category":"Home & Garden",
            "subcategory":"Household Appliances",
            "type":"Retail Goods"
        }
    ],
    "sg:phone":"+1 812 244 0707",
    "sg:postcode":"47802",
    "sg:province":"IN",
    "sg:tags":[
        "cleaners",
        "vacuum"
    ],
    "wof:name":"Oreck Vacuums",
    "wof:placetype":"venue"
},
  "geometry": {"coordinates":[-87.413297,39.411484],"type":"Point"}
}