{
  "type": "Feature",
  "properties": {
    "iso:country":"US",
    "sg:address":"200 Billings St",
    "sg:city":"Valparaiso",
    "sg:classifiers":[
        {
            "category":"Restaurant",
            "type":"Food & Drink"
        }
    ],
    "sg:phone":"+1 219 464 2328",
    "sg:postcode":"46383",
    "sg:province":"IN",
    "sg:website":"www.eatatblue.com",
    "wof:name":"Blue",
    "wof:placetype":"venue"
},
  "geometry": {"coordinates":[-87.057248,41.476801],"type":"Point"}
}