{
  "type": "Feature",
  "properties": {
    "iso:country":"US",
    "sg:address":"1210 E State Blvd",
    "sg:city":"Fort Wayne",
    "sg:classifiers":[
        {
            "category":"Bars & Pubs",
            "type":"Food & Drink"
        }
    ],
    "sg:phone":"+1 260 483 5618",
    "sg:postcode":"46805",
    "sg:province":"IN",
    "wof:name":"State Grill",
    "wof:placetype":"venue"
},
  "geometry": {"coordinates":[-85.122445,41.096658],"type":"Point"}
}