{
  "type": "Feature",
  "properties": {
    "addr:full":"205 Broadway Chesterton IN 46304",
    "addr:housenumber":"205",
    "addr:postcode":"46304",
    "addr:street":"Broadway",
    "iso:country":"US",
    "sg:address":"205 Broadway",
    "sg:city":"Chesterton",
    "sg:classifiers":[
        {
            "category":"Wholesale",
            "subcategory":"Jewelry",
            "type":"Manufacturing & Wholesale Goods"
        }
    ],
    "sg:phone":"+1 219 921 0884",
    "sg:postcode":"46304",
    "sg:province":"IN",
    "sg:tags":[
        "beads"
    ],
    "wof:name":"Garden Of Beadin'",
    "wof:placetype":"venue"
},
  "geometry": {"coordinates":[-87.05451600000001,41.610846],"type":"Point"}
}