{
  "type": "Feature",
  "properties": {
    "addr:full":"210 Mall Rd Logansport IN 46947",
    "addr:housenumber":"210",
    "addr:postcode":"46947",
    "addr:street":"Mall Rd",
    "iso:country":"US",
    "sg:address":"210 Mall Rd",
    "sg:city":"Logansport",
    "sg:classifiers":[
        {
            "category":"Banks & Credit Unions",
            "subcategory":"Bank",
            "type":"Services"
        }
    ],
    "sg:phone":"+1 574 722 1000",
    "sg:postcode":"46947",
    "sg:province":"IN",
    "wof:name":"Sagamore Federal Credit Union",
    "wof:placetype":"venue"
},
  "geometry": {"coordinates":[-86.316768,40.762783],"type":"Point"}
}