{
  "type": "Feature",
  "properties": {
    "iso:country":"US",
    "sg:address":"230 Foster Dr",
    "sg:city":"Attica",
    "sg:classifiers":[
        {
            "category":"Retail",
            "subcategory":"Repair Shop",
            "type":"Services"
        }
    ],
    "sg:phone":"+1 765 762 2465",
    "sg:postcode":"47918",
    "sg:province":"IN",
    "sg:tags":[
        "related"
    ],
    "wof:name":"BML Diesel Inc",
    "wof:placetype":"venue"
},
  "geometry": {"coordinates":[-87.237734,40.28478],"type":"Point"}
}