{
  "type": "Feature",
  "properties": {
    "iso:country":"US",
    "sg:address":"201 S Capitol Ave",
    "sg:city":"Indianapolis",
    "sg:classifiers":[
        {
            "category":"Sports & Exercise",
            "subcategory":"Sports Center",
            "type":"Entertainment"
        },
        {
            "category":"Arena",
            "subcategory":"Sports Club",
            "type":"Entertainment"
        }
    ],
    "sg:phone":"+1 317 237 5780",
    "sg:postcode":"46225",
    "sg:province":"IN",
    "sg:tags":[
        "athletic",
        "health"
    ],
    "sg:website":"http://www.inswimming.org",
    "wof:name":"Indiana Swimming",
    "wof:placetype":"venue"
},
  "geometry": {"coordinates":[-86.16185,39.764332],"type":"Point"}
}