{
  "type": "Feature",
  "properties": {
    "iso:country":"US",
    "sg:address":"1008 W Oak St",
    "sg:city":"Zionsville",
    "sg:classifiers":[
        {
            "category":"Retail",
            "subcategory":"Veterinary Services",
            "type":"Services"
        }
    ],
    "sg:phone":"+1 317 873 4679",
    "sg:postcode":"46077",
    "sg:province":"IN",
    "sg:tags":[
        "hospital",
        "animal"
    ],
    "wof:name":"VCA Eagle Park Animal Hosp",
    "wof:placetype":"venue"
},
  "geometry": {"coordinates":[-86.272996,39.950273],"type":"Point"}
}