{
  "type": "Feature",
  "properties": {
    "addr:full":"2640 E 84th Pl Merrillville IN 46410",
    "addr:housenumber":"2640",
    "addr:postcode":"46410",
    "addr:street":"E 84Th Pl",
    "iso:country":"US",
    "sg:address":"2640 E 84th Pl",
    "sg:city":"Merrillville",
    "sg:classifiers":[
        {
            "category":"Manufacturing",
            "subcategory":"Chemicals & Compounds",
            "type":"Manufacturing & Wholesale Goods"
        },
        {
            "category":"Animal Shelter",
            "type":"Public Place"
        },
        {
            "category":"Building & Trades",
            "subcategory":"Pest Control",
            "type":"Services"
        }
    ],
    "sg:phone":"+1 866 574 1660",
    "sg:postcode":"46410",
    "sg:province":"IN",
    "sg:tags":[
        "industrial",
        "supply",
        "services-commercial",
        "termite",
        "bee",
        "equipment",
        "mothproofing",
        "removal"
    ],
    "sg:website":"http://signup.orkin.com/orkin/res/fun-Standard-pph_pcb_tph_tsch.aspx?cm_mmc=yahoo-yellowpages-_-yahoo-local-_-WEBYL-_-_&utm_source=yahoo-yellowpages&utm_content=yahoo-local&utm_medium=internet-yellow-pages&utm_campaign=WEBYL",
    "wof:name":"Orkin Pest & Termite Control",
    "wof:placetype":"venue"
},
  "geometry": {"coordinates":[-87.300372,41.464664],"type":"Point"}
}