{
  "type": "Feature",
  "properties": {
    "iso:country":"US",
    "sg:address":"4820 Candy Spots Dr",
    "sg:city":"Indianapolis",
    "sg:classifiers":[
        {
            "category":"Professional",
            "type":"Services"
        }
    ],
    "sg:phone":"+1 317 925 2435",
    "sg:postcode":"46237",
    "sg:province":"IN",
    "sg:tags":[
        "establishment"
    ],
    "wof:name":"Y2k 2help",
    "wof:placetype":"venue"
},
  "geometry": {"coordinates":[-86.070809,39.696475],"type":"Point"}
}