{
  "type": "Feature",
  "properties": {
    "iso:country":"US",
    "sg:address":"125 S Union St",
    "sg:city":"Pennville",
    "sg:classifiers":[
        {
            "category":"Government",
            "subcategory":"Post Office",
            "type":"Public Place"
        }
    ],
    "sg:phone":"+1 260 731 7771",
    "sg:postcode":"47369",
    "sg:province":"IN",
    "wof:name":"US Post Office",
    "wof:placetype":"venue"
},
  "geometry": {"coordinates":[-85.148143,40.49231],"type":"Point"}
}