{
  "type": "Feature",
  "properties": {
    "iso:country":"US",
    "sg:address":"7007 Graham Rd",
    "sg:city":"Indianapolis",
    "sg:classifiers":[
        {
            "category":"Personal",
            "type":"Services"
        }
    ],
    "sg:phone":"+1 317 578 8380",
    "sg:postcode":"46220",
    "sg:province":"IN",
    "sg:tags":[
        "therapist",
        "massage"
    ],
    "wof:name":"Professional Massage Therapy",
    "wof:placetype":"venue"
},
  "geometry": {"coordinates":[-86.069652,39.881886],"type":"Point"}
}