{
  "type": "Feature",
  "properties": {
    "iso:country":"US",
    "sg:address":"5512 W Main St",
    "sg:city":"Lowell",
    "sg:phone":"+1 219 696 1256",
    "sg:postcode":"46356",
    "sg:province":"IN",
    "wof:name":"Lake Dale Ale",
    "wof:placetype":"venue"
},
  "geometry": {"coordinates":[-87.401414,41.327192],"type":"Point"}
}