{
  "type": "Feature",
  "properties": {
    "iso:country":"US",
    "sg:address":"3825 N Kenwood Ave",
    "sg:city":"Indianapolis",
    "sg:classifiers":[
        {
            "category":"Personal",
            "subcategory":"Beauty Salon",
            "type":"Services"
        }
    ],
    "sg:phone":"+1 317 920 7998",
    "sg:postcode":"46208",
    "sg:province":"IN",
    "wof:name":"Amazing Hair",
    "wof:placetype":"venue"
},
  "geometry": {"coordinates":[-86.160326,39.825987],"type":"Point"}
}