{
  "type": "Feature",
  "properties": {
    "addr:full":"7399 N Shadeland Ave Indianapolis IN 46250",
    "addr:housenumber":"7399",
    "addr:postcode":"46250",
    "addr:street":"N Shadeland Ave",
    "iso:country":"US",
    "sg:address":"7399 N Shadeland Ave",
    "sg:city":"Indianapolis",
    "sg:classifiers":[
        {
            "category":"Professional",
            "subcategory":"Business Services",
            "type":"Services"
        }
    ],
    "sg:phone":"+1 317 987 2180",
    "sg:postcode":"46250",
    "sg:province":"IN",
    "sg:tags":[
        "development",
        "plan"
    ],
    "wof:name":"Fraser Machine Resources",
    "wof:placetype":"venue"
},
  "geometry": {"coordinates":[-86.046119,39.888269],"type":"Point"}
}