{
  "type": "Feature",
  "properties": {
    "iso:country":"US",
    "sg:address":"4723 State Rd 930",
    "sg:city":"Fort Wayne",
    "sg:classifiers":[
        {
            "category":"Building & Trades",
            "subcategory":"Construction",
            "type":"Services"
        }
    ],
    "sg:phone":"+1 260 424 4487",
    "sg:postcode":"46803",
    "sg:province":"IN",
    "sg:tags":[
        "dry wall",
        "contractor"
    ],
    "wof:name":"Rosema Corp",
    "wof:placetype":"venue"
},
  "geometry": {"coordinates":[-85.08426,41.073303],"type":"Point"}
}