{
  "type": "Feature",
  "properties": {
    "iso:country":"US",
    "sg:address":"500 Polk Ave",
    "sg:city":"Greenwood",
    "sg:classifiers":[
        {
            "category":"Social Services",
            "subcategory":"Job Training",
            "type":"Services"
        }
    ],
    "sg:phone":"+1 317 865 4952",
    "sg:postcode":"46143",
    "sg:province":"IN",
    "sg:tags":[
        "career",
        "counseling",
        "vocational"
    ],
    "wof:name":"Goodwill Industries",
    "wof:placetype":"venue"
},
  "geometry": {"coordinates":[-86.097984,39.608933],"type":"Point"}
}