{
  "type": "Feature",
  "properties": {
    "iso:country":"US",
    "sg:address":"307 N Pete Ellis Dr",
    "sg:city":"Bloomington",
    "sg:classifiers":[
        {
            "category":"Real Estate",
            "subcategory":"Real Estate Operator",
            "type":"Services"
        }
    ],
    "sg:phone":"+1 812 337 3507",
    "sg:postcode":"47408",
    "sg:province":"IN",
    "sg:tags":[
        "apartment"
    ],
    "wof:name":"Cambridge Square of Bloomington",
    "wof:placetype":"venue"
},
  "geometry": {"coordinates":[-86.496002,39.169201],"type":"Point"}
}