{
  "type": "Feature",
  "properties": {
    "addr:full":"2702 Guilford St Huntington IN 46750",
    "addr:housenumber":"2702",
    "addr:postcode":"46750",
    "addr:street":"Guilford St",
    "iso:country":"US",
    "sg:address":"2702 Guilford St",
    "sg:city":"Huntington",
    "sg:classifiers":[
        {
            "category":"Restaurant",
            "type":"Food & Drink"
        }
    ],
    "sg:menulink":"http://www.allmenus.com/in/huntington/159659-arbys/menu/",
    "sg:phone":"+1 260 356 7794",
    "sg:postcode":"46750",
    "sg:province":"IN",
    "sg:tags":[
        "burger",
        "american"
    ],
    "wof:name":"Arby's",
    "wof:placetype":"venue"
},
  "geometry": {"coordinates":[-85.505842,40.899782],"type":"Point"}
}