{
  "type": "Feature",
  "properties": {
    "iso:country":"US",
    "sg:address":"411 Gradle Dr",
    "sg:city":"Carmel",
    "sg:classifiers":[
        {
            "category":"Real Estate",
            "subcategory":"Real Estate Agent",
            "type":"Services"
        }
    ],
    "sg:phone":"+1 317 843 2216",
    "sg:postcode":"46032",
    "sg:province":"IN",
    "sg:tags":[
        "appraiser"
    ],
    "wof:name":"William M Sanders",
    "wof:placetype":"venue"
},
  "geometry": {"coordinates":[-86.129999,39.966005],"type":"Point"}
}