{
  "type": "Feature",
  "properties": {
    "iso:country":"US",
    "sg:address":"119 W 580 N",
    "sg:city":"Crawfordsville",
    "sg:classifiers":[
        {
            "category":"Manufacturing",
            "subcategory":"Metals",
            "type":"Manufacturing & Wholesale Goods"
        }
    ],
    "sg:phone":"+1 765 364 9460",
    "sg:postcode":"47933",
    "sg:province":"IN",
    "sg:tags":[
        "geothermal"
    ],
    "wof:name":"Flow Center Products",
    "wof:placetype":"venue"
},
  "geometry": {"coordinates":[-86.905163,40.122867],"type":"Point"}
}