{
  "type": "Feature",
  "properties": {
    "iso:country":"US",
    "sg:address":"207 State Rd 132",
    "sg:city":"Pendleton",
    "sg:classifiers":[
        {
            "category":"Organizations",
            "subcategory":"Religious Organization",
            "type":"Services"
        }
    ],
    "sg:phone":"+1 765 778 4433",
    "sg:postcode":"46064",
    "sg:province":"IN",
    "wof:name":"Pendleton Baptist Church",
    "wof:placetype":"venue"
},
  "geometry": {"coordinates":[-85.753446,40.010147],"type":"Point"}
}