{
  "type": "Feature",
  "properties": {
    "addr:full":"1248 E 600 N Jasper IN 47546",
    "addr:housenumber":"1248",
    "addr:postcode":"47546",
    "addr:street":"E 600 N",
    "iso:country":"US",
    "sg:address":"1248 E 600 N",
    "sg:city":"Jasper",
    "sg:classifiers":[
        {
            "category":"Organizations",
            "subcategory":"Community Association",
            "type":"Services"
        }
    ],
    "sg:phone":"+1 812 695 3891",
    "sg:postcode":"47546",
    "sg:province":"IN",
    "sg:tags":[
        "fraternal"
    ],
    "wof:name":"Fraternal Order Of Police",
    "wof:placetype":"venue"
},
  "geometry": {"coordinates":[-86.884141,38.466735],"type":"Point"}
}