{
  "type": "Feature",
  "properties": {
    "addr:full":"3905 Doral Ln Elkhart IN 46517",
    "addr:housenumber":"3905",
    "addr:postcode":"46517",
    "addr:street":"Doral Ln",
    "iso:country":"US",
    "sg:address":"3905 Doral Ln",
    "sg:city":"Elkhart",
    "sg:classifiers":[
        {
            "category":"Professional",
            "subcategory":"Business Services",
            "type":"Services"
        }
    ],
    "sg:phone":"+1 574 295 0039",
    "sg:postcode":"46517",
    "sg:province":"IN",
    "wof:name":"Pollution Solutions Assn",
    "wof:placetype":"venue"
},
  "geometry": {"coordinates":[-85.983608,41.640863],"type":"Point"}
}