{
  "type": "Feature",
  "properties": {
    "iso:country":"US",
    "sg:address":"9921 Dupont Circle Dr",
    "sg:city":"Fort Wayne",
    "sg:classifiers":[
        {
            "category":"Banks & Credit Unions",
            "subcategory":"Bank",
            "type":"Services"
        }
    ],
    "sg:phone":"+1 260 434 1970",
    "sg:postcode":"46825",
    "sg:province":"IN",
    "sg:tags":[
        "loan",
        "real estate"
    ],
    "sg:website":"www.upmco.com",
    "wof:name":"Union Pacific Mortgage",
    "wof:placetype":"venue"
},
  "geometry": {"coordinates":[-85.111296,41.175185],"type":"Point"}
}