{
  "type": "Feature",
  "properties": {
    "iso:country":"US",
    "sg:address":"1001 College Ave",
    "sg:city":"Terre Haute",
    "sg:classifiers":[
        {
            "category":"Retail",
            "subcategory":"Car Wash",
            "type":"Services"
        }
    ],
    "sg:phone":"+1 812 235 8359",
    "sg:postcode":"47802",
    "sg:province":"IN",
    "sg:tags":[
        "carwash"
    ],
    "wof:name":"Auto Clinic",
    "wof:placetype":"venue"
},
  "geometry": {"coordinates":[-87.40237999999999,39.455607],"type":"Point"}
}