{
  "type": "Feature",
  "properties": {
    "addr:full":"10995 Allisonville Rd Ste 101 Fishers IN 46038",
    "addr:housenumber":"10995",
    "addr:postcode":"46038",
    "addr:street":"Allisonville Rd Ste 101",
    "iso:country":"US",
    "sg:address":"10995 Allisonville Rd Ste 101",
    "sg:city":"Fishers",
    "sg:classifiers":[
        {
            "category":"Community Center",
            "type":"Public Place"
        }
    ],
    "sg:phone":"+1 317 845 9628",
    "sg:postcode":"46038",
    "sg:province":"IN",
    "sg:tags":[
        "medical"
    ],
    "wof:name":"Physiotherapy Associates",
    "wof:placetype":"venue"
},
  "geometry": {"coordinates":[-86.04361900000001,39.946268],"type":"Point"}
}