{
  "type": "Feature",
  "properties": {
    "iso:country":"US",
    "sg:address":"318 S 5th St",
    "sg:city":"Lafayette",
    "sg:classifiers":[
        {
            "category":"Building & Trades",
            "subcategory":"Construction",
            "type":"Services"
        }
    ],
    "sg:phone":"+1 765 742 0071",
    "sg:postcode":"47901",
    "sg:province":"IN",
    "sg:tags":[
        "contractor"
    ],
    "wof:name":"Bailey Steve Builders",
    "wof:placetype":"venue"
},
  "geometry": {"coordinates":[-86.891878,40.414335],"type":"Point"}
}