{
  "type": "Feature",
  "properties": {
    "iso:country":"US",
    "sg:address":"429 W Pike St",
    "sg:city":"Goshen",
    "sg:classifiers":[
        {
            "category":"Shopping",
            "subcategory":"Pharmacy",
            "type":"Retail Goods"
        }
    ],
    "sg:phone":"+1 574 534 7191",
    "sg:postcode":"46526",
    "sg:province":"IN",
    "wof:name":"Walgreens",
    "wof:placetype":"venue"
},
  "geometry": {"coordinates":[-85.84036,41.589196],"type":"Point"}
}