{
  "type": "Feature",
  "properties": {
    "iso:country":"US",
    "sg:address":"910 State Rd 212",
    "sg:city":"Michigan City",
    "sg:classifiers":[
        {
            "category":"Home & Garden",
            "subcategory":"Building Materials",
            "type":"Retail Goods"
        }
    ],
    "sg:phone":"+1 219 879 8265",
    "sg:postcode":"46360",
    "sg:province":"IN",
    "sg:tags":[
        "roofing"
    ],
    "wof:name":"GAF Materials Corp",
    "wof:placetype":"venue"
},
  "geometry": {"coordinates":[-86.825897,41.712555],"type":"Point"}
}