{
  "type": "Feature",
  "properties": {
    "iso:country":"US",
    "sg:address":"415 N Earl Ave",
    "sg:city":"Lafayette",
    "sg:classifiers":[
        {
            "category":"Professional",
            "type":"Services"
        }
    ],
    "sg:phone":"+1 765 742 6496",
    "sg:postcode":"47904",
    "sg:province":"IN",
    "sg:tags":[
        "establishment"
    ],
    "wof:name":"Onetouch Securtiy Plus",
    "wof:placetype":"venue"
},
  "geometry": {"coordinates":[-86.860699,40.417676],"type":"Point"}
}