{
  "type": "Feature",
  "properties": {
    "addr:full":"3355 W Delphi Pike Marion IN 46952",
    "addr:housenumber":"3355",
    "addr:postcode":"46952",
    "addr:street":"W Delphi Pike",
    "iso:country":"US",
    "sg:address":"3355 W Delphi Pike",
    "sg:city":"Marion",
    "sg:classifiers":[
        {
            "category":"Autos & Motor Vehicles",
            "subcategory":"Automobile Sales",
            "type":"Retail Goods"
        }
    ],
    "sg:phone":"+1 765 384 5175",
    "sg:postcode":"46952",
    "sg:province":"IN",
    "sg:tags":[
        "car",
        "dealer"
    ],
    "wof:name":"Riddle's Auto Sales",
    "wof:placetype":"venue"
},
  "geometry": {"coordinates":[-85.737602,40.566139],"type":"Point"}
}