{
  "type": "Feature",
  "properties": {
    "addr:full":"3668 S Morgantown Rd Greenwood IN 46143",
    "addr:housenumber":"3668",
    "addr:postcode":"46143",
    "addr:street":"S Morgantown Rd",
    "iso:country":"US",
    "sg:address":"3668 S Morgantown Rd",
    "sg:city":"Greenwood",
    "sg:classifiers":[
        {
            "category":"Professional",
            "subcategory":"Computer Services",
            "type":"Services"
        }
    ],
    "sg:phone":"+1 317 422 9524",
    "sg:postcode":"46143",
    "sg:province":"IN",
    "wof:name":"Pierces Technologies Inc",
    "wof:placetype":"venue"
},
  "geometry": {"coordinates":[-86.19689,39.563292],"type":"Point"}
}