{
  "type": "Feature",
  "properties": {
    "iso:country":"US",
    "sg:address":"10502 E 75th St",
    "sg:city":"Oaklandon",
    "sg:classifiers":[
        {
            "category":"Organizations",
            "subcategory":"Community Association",
            "type":"Services"
        }
    ],
    "sg:phone":"+1 317 823 4484",
    "sg:postcode":"46236",
    "sg:province":"IN",
    "sg:tags":[
        "club"
    ],
    "wof:name":"Indian Lake Country Club",
    "wof:placetype":"venue"
},
  "geometry": {"coordinates":[-85.984166,39.891068],"type":"Point"}
}