{
  "type": "Feature",
  "properties": {
    "iso:country":"US",
    "sg:address":"2525 Illinois St",
    "sg:city":"Columbus",
    "sg:classifiers":[
        {
            "category":"Social Services",
            "type":"Services"
        }
    ],
    "sg:phone":"+1 812 372 7118",
    "sg:postcode":"47201",
    "sg:province":"IN",
    "sg:tags":[
        "organization",
        "welfare"
    ],
    "wof:name":"Salvation Army",
    "wof:placetype":"venue"
},
  "geometry": {"coordinates":[-85.89539499999999,39.195758],"type":"Point"}
}