{
  "type": "Feature",
  "properties": {
    "iso:country":"US",
    "sg:address":"6325 Rod Ct",
    "sg:city":"Indianapolis",
    "sg:classifiers":[
        {
            "category":"Insurance",
            "subcategory":"Hazard Insurance",
            "type":"Services"
        },
        {
            "category":"Insurance",
            "subcategory":"Life Insurance",
            "type":"Services"
        }
    ],
    "sg:phone":"+1 317 626 9770",
    "sg:postcode":"46237",
    "sg:province":"IN",
    "wof:name":"Fire & Life Safety Institute Of Indiana",
    "wof:placetype":"venue"
},
  "geometry": {"coordinates":[-86.056059,39.676085],"type":"Point"}
}