{
  "type": "Feature",
  "properties": {
    "addr:full":"1625 W Gordon Rd Mooresville IN 46158",
    "addr:housenumber":"1625",
    "addr:postcode":"46158",
    "addr:street":"W Gordon Rd",
    "iso:country":"US",
    "sg:address":"1625 W Gordon Rd",
    "sg:city":"Mooresville",
    "sg:classifiers":[
        {
            "category":"Retail",
            "subcategory":"Repair Shop",
            "type":"Services"
        }
    ],
    "sg:phone":"+1 317 996 3744",
    "sg:postcode":"46158",
    "sg:province":"IN",
    "sg:tags":[
        "scooter",
        "motorcycle",
        "motor"
    ],
    "wof:name":"Four-Tech",
    "wof:placetype":"venue"
},
  "geometry": {"coordinates":[-86.456352,39.577738],"type":"Point"}
}