{
  "type": "Feature",
  "properties": {
    "iso:country":"US",
    "sg:address":"3935 E Southport Rd",
    "sg:city":"Indianapolis",
    "sg:classifiers":[
        {
            "category":"Health Services",
            "subcategory":"Dentist",
            "type":"Services"
        }
    ],
    "sg:phone":"+1 317 244 3000",
    "sg:postcode":"46237",
    "sg:province":"IN",
    "sg:tags":[
        "dental",
        "clinic",
        "hygienist"
    ],
    "sg:website":"http://www.aspendental.com/?utm_source=Yellowpages.com&utm_medium=fixed%2Bplacement&utm_campaign=trade%2Blistings",
    "wof:name":"Aspen Dental",
    "wof:placetype":"venue"
},
  "geometry": {"coordinates":[-86.099298,39.665383],"type":"Point"}
}