{
  "type": "Feature",
  "properties": {
    "addr:full":"159 E Washington St Shelbyville IN 46176",
    "addr:housenumber":"159",
    "addr:postcode":"46176",
    "addr:street":"E Washington St",
    "iso:country":"US",
    "sg:address":"159 E Washington St",
    "sg:city":"Shelbyville",
    "sg:classifiers":[
        {
            "category":"Personal",
            "subcategory":"Beauty Salon",
            "type":"Services"
        }
    ],
    "sg:phone":"+1 317 392 4044",
    "sg:postcode":"46176",
    "sg:province":"IN",
    "sg:tags":[
        "shop"
    ],
    "wof:name":"Unique Nails & Hair",
    "wof:placetype":"venue"
},
  "geometry": {"coordinates":[-85.773117,39.524358],"type":"Point"}
}