{
  "type": "Feature",
  "properties": {
    "iso:country":"US",
    "sg:address":"2233 S West St",
    "sg:city":"Indianapolis",
    "sg:classifiers":[
        {
            "category":"Manufacturing",
            "subcategory":"Tools & Machinery",
            "type":"Manufacturing & Wholesale Goods"
        }
    ],
    "sg:phone":"+1 317 784 0299",
    "sg:postcode":"46225",
    "sg:province":"IN",
    "sg:tags":[
        "machine",
        "shop"
    ],
    "wof:name":"Advantage Components Corp",
    "wof:placetype":"venue"
},
  "geometry": {"coordinates":[-86.168392,39.736624],"type":"Point"}
}