{
  "type": "Feature",
  "properties": {
    "addr:full":"9004 Lima Rd Fort Wayne IN 46818",
    "addr:housenumber":"9004",
    "addr:postcode":"46818",
    "addr:street":"Lima Rd",
    "iso:country":"US",
    "sg:address":"9004 Lima Rd",
    "sg:city":"Fort Wayne",
    "sg:classifiers":[
        {
            "category":"Home & Garden",
            "subcategory":"Mobile Homes",
            "type":"Retail Goods"
        }
    ],
    "sg:phone":"+1 260 489 3713",
    "sg:postcode":"46818",
    "sg:province":"IN",
    "wof:name":"ERI Housing",
    "wof:placetype":"venue"
},
  "geometry": {"coordinates":[-85.165672,41.164144],"type":"Point"}
}