{
  "type": "Feature",
  "properties": {
    "iso:country":"US",
    "sg:address":"6039 Stoney Creek Dr",
    "sg:city":"Fort Wayne",
    "sg:classifiers":[
        {
            "category":"Professional",
            "subcategory":"Advertising",
            "type":"Services"
        }
    ],
    "sg:phone":"+1 260 490 2002",
    "sg:postcode":"46825",
    "sg:province":"IN",
    "sg:tags":[
        "counselor"
    ],
    "sg:website":"www.askcolburn.com",
    "wof:name":"Colburn & Assoc Inc",
    "wof:placetype":"venue"
},
  "geometry": {"coordinates":[-85.139348,41.133462],"type":"Point"}
}