{
  "type": "Feature",
  "properties": {
    "iso:country":"US",
    "sg:address":"215 Aspen Dr",
    "sg:city":"Rushville",
    "sg:classifiers":[
        {
            "category":"Real Estate",
            "subcategory":"Real Estate Operator",
            "type":"Services"
        }
    ],
    "sg:phone":"+1 765 932 5311",
    "sg:postcode":"46173",
    "sg:province":"IN",
    "sg:tags":[
        "apartment"
    ],
    "wof:name":"Rushville Commons Apartments",
    "wof:placetype":"venue"
},
  "geometry": {"coordinates":[-85.44332199999999,39.626606],"type":"Point"}
}