{
  "type": "Feature",
  "properties": {
    "addr:full":"8643 Madison Ave Munster IN 46321",
    "addr:housenumber":"8643",
    "addr:postcode":"46321",
    "addr:street":"Madison Ave",
    "iso:country":"US",
    "sg:address":"8643 Madison Ave",
    "sg:city":"Munster",
    "sg:classifiers":[
        {
            "category":"Professional",
            "subcategory":"Management & Consulting",
            "type":"Services"
        }
    ],
    "sg:phone":"+1 219 513 0885",
    "sg:postcode":"46321",
    "sg:province":"IN",
    "sg:tags":[
        "marketing",
        "consultant"
    ],
    "wof:name":"Legend Business Group Inc",
    "wof:placetype":"venue"
},
  "geometry": {"coordinates":[-87.511522,41.557008],"type":"Point"}
}