{
  "type": "Feature",
  "properties": {
    "iso:country":"US",
    "sg:address":"389 State Rd 58",
    "sg:city":"Bedford",
    "sg:classifiers":[
        {
            "category":"Building & Trades",
            "subcategory":"Construction",
            "type":"Services"
        }
    ],
    "sg:phone":"+1 812 279 8604",
    "sg:postcode":"47421",
    "sg:province":"IN",
    "sg:tags":[
        "concrete",
        "contractor"
    ],
    "wof:name":"Cameron Asphalt Maintenance",
    "wof:placetype":"venue"
},
  "geometry": {"coordinates":[-86.474088,38.874923],"type":"Point"}
}