{
  "type": "Feature",
  "properties": {
    "addr:full":"5435 State Rd 19 Peru IN 46970",
    "addr:housenumber":"5435;19",
    "addr:postcode":"46970",
    "addr:street":"State Rd",
    "iso:country":"US",
    "sg:address":"5435 State Rd 19",
    "sg:city":"Peru",
    "sg:classifiers":[
        {
            "category":"Building & Trades",
            "subcategory":"Construction",
            "type":"Services"
        }
    ],
    "sg:phone":"+1 765 472 1141",
    "sg:postcode":"46970",
    "sg:province":"IN",
    "sg:tags":[
        "painter"
    ],
    "wof:name":"Wilkison & Sons",
    "wof:placetype":"venue"
},
  "geometry": {"coordinates":[-86.034656,40.843828],"type":"Point"}
}