{
  "type": "Feature",
  "properties": {
    "iso:country":"US",
    "sg:address":"3810 Andover Rd",
    "sg:city":"Anderson",
    "sg:classifiers":[
        {
            "category":"Personal",
            "type":"Services"
        }
    ],
    "sg:phone":"+1 765 608 1875",
    "sg:postcode":"46013",
    "sg:province":"IN",
    "wof:name":"Your Family Massage Shop",
    "wof:placetype":"venue"
},
  "geometry": {"coordinates":[-85.679913,40.075516],"type":"Point"}
}