{
  "type": "Feature",
  "properties": {
    "addr:full":"1030 E County Line Rd Indianapolis IN 46227",
    "addr:housenumber":"1030",
    "addr:postcode":"46227",
    "addr:street":"E County Line Rd",
    "iso:country":"US",
    "sg:address":"1030 E County Line Rd",
    "sg:city":"Indianapolis",
    "sg:classifiers":[
        {
            "category":"Health Services",
            "subcategory":"Doctor",
            "type":"Services"
        }
    ],
    "sg:phone":"+1 317 883 4736",
    "sg:postcode":"46227",
    "sg:province":"IN",
    "sg:tags":[
        "physician",
        "surgeon"
    ],
    "wof:name":"Complete Family Care",
    "wof:placetype":"venue"
},
  "geometry": {"coordinates":[-86.139548,39.635455],"type":"Point"}
}