{
  "type": "Feature",
  "properties": {
    "iso:country":"US",
    "sg:address":"22192 State Rd 19",
    "sg:city":"Cicero",
    "sg:classifiers":[
        {
            "category":"Building & Trades",
            "subcategory":"Construction",
            "type":"Services"
        }
    ],
    "sg:phone":"+1 317 984 5265",
    "sg:postcode":"46034",
    "sg:province":"IN",
    "sg:tags":[
        "contractor"
    ],
    "wof:name":"Central Indiana Stucco",
    "wof:placetype":"venue"
},
  "geometry": {"coordinates":[-86.013641,40.112252],"type":"Point"}
}