{
  "type": "Feature",
  "properties": {
    "iso:country":"US",
    "sg:address":"9585 N Park Ave",
    "sg:city":"Indianapolis",
    "sg:classifiers":[
        {
            "category":"Wholesale",
            "subcategory":"Non-durable Goods",
            "type":"Manufacturing & Wholesale Goods"
        }
    ],
    "sg:phone":"+1 317 523 9358",
    "sg:postcode":"46240",
    "sg:province":"IN",
    "wof:name":"Qxcnet",
    "wof:placetype":"venue"
},
  "geometry": {"coordinates":[-86.149029,39.925518],"type":"Point"}
}