{
  "type": "Feature",
  "properties": {
    "addr:full":"630 E Washington St Winchester IN 47394",
    "addr:housenumber":"630",
    "addr:postcode":"47394",
    "addr:street":"E Washington St",
    "iso:country":"US",
    "sg:address":"630 E Washington St",
    "sg:city":"Winchester",
    "sg:classifiers":[
        {
            "category":"Autos & Motor Vehicles",
            "subcategory":"Auto Supplies",
            "type":"Retail Goods"
        }
    ],
    "sg:phone":"+1 765 584 4891",
    "sg:postcode":"47394",
    "sg:province":"IN",
    "sg:tags":[
        "tire"
    ],
    "wof:name":"Team Tire & Auto",
    "wof:placetype":"venue"
},
  "geometry": {"coordinates":[-84.971054,40.172545],"type":"Point"}
}