{
  "type": "Feature",
  "properties": {
    "iso:country":"US",
    "sg:address":"200 S Stevens St",
    "sg:city":"Trafalgar",
    "sg:classifiers":[
        {
            "category":"Retail",
            "subcategory":"Car Wash",
            "type":"Services"
        }
    ],
    "sg:phone":"+1 812 247 2714",
    "sg:postcode":"46181",
    "sg:province":"IN",
    "sg:tags":[
        "truck",
        "cleaning"
    ],
    "wof:name":"Michael's Car & Truck Wash",
    "wof:placetype":"venue"
},
  "geometry": {"coordinates":[-86.14501,39.416019],"type":"Point"}
}