{
  "type": "Feature",
  "properties": {
    "iso:country":"US",
    "sg:address":"3367 Willowcreek Rd",
    "sg:city":"Portage",
    "sg:classifiers":[
        {
            "category":"Utilities",
            "subcategory":"Mobile Phone",
            "type":"Services"
        }
    ],
    "sg:phone":"+1 219 764 4997",
    "sg:postcode":"46368",
    "sg:province":"IN",
    "sg:tags":[
        "telephone",
        "cellular"
    ],
    "wof:name":"Nextel Communications Inc",
    "wof:placetype":"venue"
},
  "geometry": {"coordinates":[-87.182576,41.554945],"type":"Point"}
}