{
  "type": "Feature",
  "properties": {
    "addr:full":"2630 S Western Ave Marion IN 46953",
    "addr:housenumber":"2630",
    "addr:postcode":"46953",
    "addr:street":"S Western Ave",
    "iso:country":"US",
    "sg:address":"2630 S Western Ave",
    "sg:city":"Marion",
    "sg:classifiers":[
        {
            "category":"Shopping",
            "subcategory":"Stationery & Office Supplies",
            "type":"Retail Goods"
        }
    ],
    "sg:phone":"+1 765 651 9285",
    "sg:postcode":"46953",
    "sg:province":"IN",
    "wof:name":"Staples The Office Superstore",
    "wof:placetype":"venue"
},
  "geometry": {"coordinates":[-85.673783,40.537807],"type":"Point"}
}