{
  "type": "Feature",
  "properties": {
    "addr:full":"220 Hamilton St Crawfordsville IN 47933",
    "addr:housenumber":"220",
    "addr:postcode":"47933",
    "addr:street":"Hamilton St",
    "iso:country":"US",
    "sg:address":"220 Hamilton St",
    "sg:city":"Crawfordsville",
    "sg:classifiers":[
        {
            "category":"Professional",
            "subcategory":"Accounting & Tax Preparation",
            "type":"Services"
        }
    ],
    "sg:phone":"+1 765 364 1200",
    "sg:postcode":"47933",
    "sg:province":"IN",
    "wof:name":"Checks & Balances",
    "wof:placetype":"venue"
},
  "geometry": {"coordinates":[-86.885805,40.043124],"type":"Point"}
}