{
  "type": "Feature",
  "properties": {
    "iso:country":"US",
    "sg:address":"300 N Union St",
    "sg:city":"Kokomo",
    "sg:classifiers":[
        {
            "category":"Manufacturing",
            "subcategory":"Printing",
            "type":"Manufacturing & Wholesale Goods"
        }
    ],
    "sg:phone":"+1 765 459 3121",
    "sg:postcode":"46901",
    "sg:province":"IN",
    "sg:tags":[
        "newspaper"
    ],
    "sg:website":"www.kokomotribune.com",
    "wof:name":"Kokomo Tribune",
    "wof:placetype":"venue"
},
  "geometry": {"coordinates":[-86.130017,40.489289],"type":"Point"}
}