{
  "type": "Feature",
  "properties": {
    "iso:country":"US",
    "sg:address":"1105 S 17th St",
    "sg:city":"Kokomo",
    "sg:classifiers":[
        {
            "category":"Personal",
            "subcategory":"Beauty Salon",
            "type":"Services"
        }
    ],
    "sg:phone":"+1 765 457 5184",
    "sg:postcode":"46902",
    "sg:province":"IN",
    "sg:tags":[
        "shop"
    ],
    "wof:name":"Carousel Styling Salon",
    "wof:placetype":"venue"
},
  "geometry": {"coordinates":[-86.110935,40.473755],"type":"Point"}
}