{
  "type": "Feature",
  "properties": {
    "iso:country":"US",
    "sg:address":"3130 Madison Ave",
    "sg:city":"Indianapolis",
    "sg:classifiers":[
        {
            "category":"Autos & Motor Vehicles",
            "subcategory":"Boat Sales",
            "type":"Retail Goods"
        }
    ],
    "sg:phone":"+1 317 786 4088",
    "sg:postcode":"46227",
    "sg:province":"IN",
    "sg:tags":[
        "dealer",
        "sales"
    ],
    "wof:name":"Indy Boat Salvage",
    "wof:placetype":"venue"
},
  "geometry": {"coordinates":[-86.14926800000001,39.720714],"type":"Point"}
}