{
  "type": "Feature",
  "properties": {
    "iso:country":"US",
    "sg:address":"3608 Woodland Streams Ct",
    "sg:city":"Greenwood",
    "sg:classifiers":[
        {
            "category":"Real Estate",
            "subcategory":"Real Estate Services",
            "type":"Services"
        },
        {
            "category":"Real Estate",
            "subcategory":"Real Estate Operator",
            "type":"Services"
        }
    ],
    "sg:phone":"+1 317 535 4853",
    "sg:postcode":"46143",
    "sg:province":"IN",
    "sg:tags":[
        "management",
        "apartment",
        "condominium"
    ],
    "wof:name":"501 Madison",
    "wof:placetype":"venue"
},
  "geometry": {"coordinates":[-86.183741,39.566514],"type":"Point"}
}