{
  "type": "Feature",
  "properties": {
    "addr:full":"214 E Main St Greenfield IN 46140",
    "addr:housenumber":"214",
    "addr:postcode":"46140",
    "addr:street":"E Main St",
    "iso:country":"US",
    "sg:address":"214 E Main St",
    "sg:city":"Greenfield",
    "sg:classifiers":[
        {
            "category":"Organizations",
            "subcategory":"Membership Organization",
            "type":"Services"
        }
    ],
    "sg:phone":"+1 317 462 5404",
    "sg:postcode":"46140",
    "sg:province":"IN",
    "sg:tags":[
        "society",
        "humane"
    ],
    "wof:name":"Humane Society Of Hancock Cnty",
    "wof:placetype":"venue"
},
  "geometry": {"coordinates":[-85.766575,39.785418],"type":"Point"}
}