{
  "type": "Feature",
  "properties": {
    "iso:country":"US",
    "sg:address":"906 US Hwy 31 N",
    "sg:city":"Greenwood",
    "sg:classifiers":[
        {
            "category":"Shopping",
            "subcategory":"Gifts & Souvenirs",
            "type":"Retail Goods"
        }
    ],
    "sg:phone":"+1 317 888 8101",
    "sg:postcode":"46142",
    "sg:province":"IN",
    "sg:tags":[
        "cards",
        "party",
        "supply"
    ],
    "wof:name":"Factory Card Outlet 148",
    "wof:placetype":"venue"
},
  "geometry": {"coordinates":[-86.12173,39.628299],"type":"Point"}
}