{
  "type": "Feature",
  "properties": {
    "iso:country":"US",
    "sg:address":"7974 US Hwy 41",
    "sg:city":"St John",
    "sg:classifiers":[
        {
            "category":"Shopping",
            "subcategory":"Clothing, Apparel, & Fashions",
            "type":"Retail Goods"
        }
    ],
    "sg:phone":"+1 219 365 1735",
    "sg:postcode":"46373",
    "sg:province":"IN",
    "sg:tags":[
        "shop",
        "bridal"
    ],
    "wof:name":"Char's The Wedding Shoppe",
    "wof:placetype":"venue"
},
  "geometry": {"coordinates":[-87.470501,41.474196],"type":"Point"}
}