{
  "type": "Feature",
  "properties": {
    "iso:country":"US",
    "sg:address":"10020 Lima Rd",
    "sg:city":"Fort Wayne",
    "sg:classifiers":[
        {
            "category":"Restaurant",
            "type":"Food & Drink"
        }
    ],
    "sg:menulink":"http://www.allmenus.com/in/washington/47882-dawsons/menu/",
    "sg:phone":"+1 260 489 8782",
    "sg:postcode":"46818",
    "sg:province":"IN",
    "sg:tags":[
        "american"
    ],
    "wof:name":"Dawson's",
    "wof:placetype":"venue"
},
  "geometry": {"coordinates":[-85.165435,41.161176],"type":"Point"}
}