{
  "type": "Feature",
  "properties": {
    "iso:country":"US",
    "sg:address":"416 Locust St",
    "sg:city":"Evansville",
    "sg:classifiers":[
        {
            "category":"Parking",
            "type":"Transportation"
        }
    ],
    "sg:phone":"+1 812 435 6100",
    "sg:postcode":"47708",
    "sg:province":"IN",
    "sg:tags":[
        "garage"
    ],
    "wof:name":"Locust Street Parking Garage",
    "wof:placetype":"venue"
},
  "geometry": {"coordinates":[-87.56948800000001,37.971234],"type":"Point"}
}