{
  "type": "Feature",
  "properties": {
    "iso:country":"US",
    "sg:address":"6226 E Bootjack Rd",
    "sg:city":"Rolling Prairie",
    "sg:classifiers":[
        {
            "category":"Retail",
            "subcategory":"Auto Repair",
            "type":"Services"
        }
    ],
    "sg:phone":"+1 219 778 9700",
    "sg:postcode":"46371",
    "sg:province":"IN",
    "sg:tags":[
        "body",
        "automobile",
        "painting"
    ],
    "wof:name":"Don's Service Ctr Inc",
    "wof:placetype":"venue"
},
  "geometry": {"coordinates":[-86.57453700000001,41.687518],"type":"Point"}
}