{
  "type": "Feature",
  "properties": {
    "iso:country":"US",
    "sg:address":"245 S Jefferson St",
    "sg:city":"Nashville",
    "sg:classifiers":[
        {
            "category":"Travel",
            "subcategory":"Hotels & Motels",
            "type":"Entertainment"
        }
    ],
    "sg:phone":"+1 812 988 8400",
    "sg:postcode":"47448",
    "sg:province":"IN",
    "sg:website":"www.hotelnashville.com",
    "wof:name":"Hotel Nashville Resort",
    "wof:placetype":"venue"
},
  "geometry": {"coordinates":[-86.248071,39.205983],"type":"Point"}
}