{
  "type": "Feature",
  "properties": {
    "addr:full":"52800 Higgins Blvd Elkhart IN 46514",
    "addr:postcode":"52800;46514",
    "addr:street":"Higgins Blvd",
    "iso:country":"US",
    "sg:address":"52800 Higgins Blvd",
    "sg:city":"Elkhart",
    "sg:classifiers":[
        {
            "category":"Manufacturing",
            "subcategory":"Metals",
            "type":"Manufacturing & Wholesale Goods"
        }
    ],
    "sg:phone":"+1 574 262 3451",
    "sg:postcode":"46514",
    "sg:province":"IN",
    "sg:tags":[
        "rolling",
        "extruding",
        "drawing"
    ],
    "sg:website":"www.specialmetals.com",
    "wof:name":"Special Metals Corp",
    "wof:placetype":"venue"
},
  "geometry": {"coordinates":[-85.96135,41.726192],"type":"Point"}
}