{
  "type": "Feature",
  "properties": {
    "iso:country":"US",
    "sg:address":"15101 Brunson Rd",
    "sg:city":"Hoagland",
    "sg:classifiers":[
        {
            "category":"Real Estate",
            "subcategory":"Real Estate Agent",
            "type":"Services"
        }
    ],
    "sg:phone":"+1 260 639 0099",
    "sg:postcode":"46745",
    "sg:province":"IN",
    "sg:tags":[
        "appraiser"
    ],
    "wof:name":"Associated Appraisers",
    "wof:placetype":"venue"
},
  "geometry": {"coordinates":[-85.016981,40.946375],"type":"Point"}
}