{
  "type": "Feature",
  "properties": {
    "iso:country":"US",
    "sg:address":"3508 S Lafountain St",
    "sg:city":"Kokomo",
    "sg:classifiers":[
        {
            "category":"Health Services",
            "subcategory":"Doctor",
            "type":"Services"
        }
    ],
    "sg:phone":"+1 765 864 8727",
    "sg:postcode":"46902",
    "sg:province":"IN",
    "sg:tags":[
        "physician",
        "surgeon"
    ],
    "wof:name":"Lynette Hazelbaker MD",
    "wof:placetype":"venue"
},
  "geometry": {"coordinates":[-86.127014,40.446699],"type":"Point"}
}