{
  "type": "Feature",
  "properties": {
    "iso:country":"US",
    "sg:address":"3503 W Fox Ridge Ln",
    "sg:city":"Muncie",
    "sg:classifiers":[
        {
            "category":"Real Estate",
            "subcategory":"Real Estate Services",
            "type":"Services"
        }
    ],
    "sg:phone":"+1 765 288 1045",
    "sg:postcode":"47304",
    "sg:province":"IN",
    "sg:tags":[
        "company",
        "title"
    ],
    "wof:name":"Rowland Title",
    "wof:placetype":"venue"
},
  "geometry": {"coordinates":[-85.427261,40.220331],"type":"Point"}
}