{
  "type": "Feature",
  "properties": {
    "iso:country":"US",
    "sg:address":"6700 Covington Creek Trl",
    "sg:city":"Fort Wayne",
    "sg:classifiers":[
        {
            "category":"Real Estate",
            "subcategory":"Real Estate Operator",
            "type":"Services"
        }
    ],
    "sg:phone":"+1 260 432 4312",
    "sg:postcode":"46804",
    "sg:province":"IN",
    "sg:tags":[
        "condominium"
    ],
    "wof:name":"Covington Creek Condominium",
    "wof:placetype":"venue"
},
  "geometry": {"coordinates":[-85.22921,41.05862],"type":"Point"}
}