{
  "type": "Feature",
  "properties": {
    "addr:full":"3089 E Fort Wayne Rd Rochester IN 46975",
    "addr:housenumber":"3089",
    "addr:postcode":"46975",
    "addr:street":"E Fort Wayne Rd",
    "iso:country":"US",
    "sg:address":"3089 E Fort Wayne Rd",
    "sg:city":"Rochester",
    "sg:classifiers":[
        {
            "category":"Building & Trades",
            "subcategory":"Construction",
            "type":"Services"
        }
    ],
    "sg:phone":"+1 574 223 4794",
    "sg:postcode":"46975",
    "sg:province":"IN",
    "wof:name":"Manufactured Structure",
    "wof:placetype":"venue"
},
  "geometry": {"coordinates":[-86.186008,41.072008],"type":"Point"}
}