{
  "type": "Feature",
  "properties": {
    "addr:full":"950 Crown Ct Crown Point IN 46307",
    "addr:housenumber":"950",
    "addr:postcode":"46307",
    "addr:street":"Crown Ct",
    "iso:country":"US",
    "sg:address":"950 Crown Ct",
    "sg:city":"Crown Point",
    "sg:classifiers":[
        {
            "category":"Health Services",
            "subcategory":"Doctor",
            "type":"Services"
        }
    ],
    "sg:phone":"+1 219 662 3855",
    "sg:postcode":"46307",
    "sg:province":"IN",
    "wof:name":"Ralph Rucinski DDS",
    "wof:placetype":"venue"
},
  "geometry": {"coordinates":[-87.353886,41.431279],"type":"Point"}
}