{
  "type": "Feature",
  "properties": {
    "iso:country":"US",
    "sg:address":"311 S Berkley Rd",
    "sg:city":"Kokomo",
    "sg:classifiers":[
        {
            "category":"Health Services",
            "subcategory":"Doctor",
            "type":"Services"
        }
    ],
    "sg:phone":"+1 765 864 8727",
    "sg:postcode":"46901",
    "sg:province":"IN",
    "sg:tags":[
        "physician",
        "surgeon"
    ],
    "wof:name":"Kokomo Internal Medicine",
    "wof:placetype":"venue"
},
  "geometry": {"coordinates":[-86.155466,40.487123],"type":"Point"}
}