{
  "type": "Feature",
  "properties": {
    "iso:country":"US",
    "sg:address":"4900 W Luther Rd",
    "sg:city":"Floyds Knobs",
    "sg:classifiers":[
        {
            "category":"Organizations",
            "subcategory":"Religious Organization",
            "type":"Services"
        }
    ],
    "sg:phone":"+1 812 923 2501",
    "sg:postcode":"47119",
    "sg:province":"IN",
    "sg:tags":[
        "church"
    ],
    "wof:name":"Remnant Church Of JCLDS",
    "wof:placetype":"venue"
},
  "geometry": {"coordinates":[-85.90048299999999,38.326696],"type":"Point"}
}