{
  "type": "Feature",
  "properties": {
    "iso:country":"US",
    "sg:address":"7546 E Co Rd 900 N",
    "sg:city":"Roachdale",
    "sg:classifiers":[
        {
            "category":"Farming",
            "subcategory":"Dairy Farm",
            "type":"Manufacturing & Wholesale Goods"
        }
    ],
    "sg:phone":"+1 765 522 1606",
    "sg:postcode":"46172",
    "sg:province":"IN",
    "wof:name":"Mc Guire John",
    "wof:placetype":"venue"
},
  "geometry": {"coordinates":[-86.714433,39.790637],"type":"Point"}
}