{
  "type": "Feature",
  "properties": {
    "iso:country":"US",
    "sg:address":"8774 W 700 N",
    "sg:city":"Winamac",
    "sg:classifiers":[
        {
            "category":"Autos & Motor Vehicles",
            "subcategory":"Motorcycle Sales",
            "type":"Retail Goods"
        }
    ],
    "sg:phone":"+1 574 896 2974",
    "sg:postcode":"46996",
    "sg:province":"IN",
    "sg:tags":[
        "scooter"
    ],
    "sg:website":"www.kerstingscycle.com",
    "wof:name":"Kersting's Cycle Ctr Inc",
    "wof:placetype":"venue"
},
  "geometry": {"coordinates":[-86.758137,41.157429],"type":"Point"}
}