{
  "type": "Feature",
  "properties": {
    "addr:full":"5901 Oak Grove Rd Evansville IN 47715",
    "addr:housenumber":"5901",
    "addr:postcode":"47715",
    "addr:street":"Oak Grove Rd",
    "iso:country":"US",
    "sg:address":"5901 Oak Grove Rd",
    "sg:city":"Evansville",
    "sg:classifiers":[
        {
            "category":"Wholesale",
            "subcategory":"Construction Materials",
            "type":"Manufacturing & Wholesale Goods"
        }
    ],
    "sg:phone":"+1 812 475 1080",
    "sg:postcode":"47715",
    "sg:province":"IN",
    "sg:tags":[
        "concrete",
        "product"
    ],
    "wof:name":"Concrete Depot Of Evansville",
    "wof:placetype":"venue"
},
  "geometry": {"coordinates":[-87.47731899999999,37.991149],"type":"Point"}
}