{
  "type": "Feature",
  "properties": {
    "addr:full":"4615 N Pennsylvania St Indianapolis IN 46205",
    "addr:housenumber":"4615",
    "addr:postcode":"46205",
    "addr:street":"N Pennsylvania St",
    "iso:country":"US",
    "sg:address":"4615 N Pennsylvania St",
    "sg:city":"Indianapolis",
    "sg:classifiers":[
        {
            "category":"Professional",
            "subcategory":"Business Services",
            "type":"Services"
        }
    ],
    "sg:phone":"+1 317 283 5847",
    "sg:postcode":"46205",
    "sg:province":"IN",
    "wof:name":"Van Mook David",
    "wof:placetype":"venue"
},
  "geometry": {"coordinates":[-86.154563,39.84041],"type":"Point"}
}