{
  "type": "Feature",
  "properties": {
    "iso:country":"US",
    "sg:address":"11 Burnetts Rd",
    "sg:city":"West Lafayette",
    "sg:classifiers":[
        {
            "category":"Building & Trades",
            "subcategory":"Construction",
            "type":"Services"
        }
    ],
    "sg:phone":"+1 765 463 6575",
    "sg:postcode":"47906",
    "sg:province":"IN",
    "sg:tags":[
        "concrete",
        "contractor"
    ],
    "wof:name":"Purdy Concrete",
    "wof:placetype":"venue"
},
  "geometry": {"coordinates":[-86.868953,40.490866],"type":"Point"}
}