{
  "type": "Feature",
  "properties": {
    "iso:country":"US",
    "sg:address":"415 N Pendleton Ave",
    "sg:city":"Pendleton",
    "sg:classifiers":[
        {
            "category":"Arts & Performance",
            "subcategory":"Theater",
            "type":"Entertainment"
        }
    ],
    "sg:phone":"+1 765 778 8572",
    "sg:postcode":"46064",
    "sg:province":"IN",
    "sg:tags":[
        "theatrical",
        "agency"
    ],
    "wof:name":"Lee's Youth Theatrical School",
    "wof:placetype":"venue"
},
  "geometry": {"coordinates":[-85.74542,40.006227],"type":"Point"}
}