{
  "type": "Feature",
  "properties": {
    "iso:country":"US",
    "sg:address":"6831 Kingswood Blvd",
    "sg:city":"Fort Wayne",
    "sg:classifiers":[
        {
            "category":"Building & Trades",
            "subcategory":"Cleaning & Sanitation",
            "type":"Services"
        }
    ],
    "sg:phone":"+1 260 436 8880",
    "sg:postcode":"46804",
    "sg:province":"IN",
    "sg:tags":[
        "janitor"
    ],
    "wof:name":"Focus Cleaning Svc",
    "wof:placetype":"venue"
},
  "geometry": {"coordinates":[-85.273967,41.019956],"type":"Point"}
}