{
  "type": "Feature",
  "properties": {
    "iso:country":"US",
    "sg:address":"1117 Bridgeport Rd",
    "sg:city":"Indianapolis",
    "sg:classifiers":[
        {
            "category":"Social Services",
            "subcategory":"Child Care",
            "type":"Services"
        }
    ],
    "sg:phone":"+1 317 247 7778",
    "sg:postcode":"46231",
    "sg:province":"IN",
    "wof:name":"Horizon Christian Preschool",
    "wof:placetype":"venue"
},
  "geometry": {"coordinates":[-86.31714599999999,39.750718],"type":"Point"}
}