{
  "type": "Feature",
  "properties": {
    "iso:country":"US",
    "sg:address":"1010 E Markland Ave",
    "sg:city":"Kokomo",
    "sg:classifiers":[
        {
            "category":"Insurance",
            "subcategory":"Insurance Agent",
            "type":"Services"
        }
    ],
    "sg:phone":"+1 765 457 1118",
    "sg:postcode":"46901",
    "sg:province":"IN",
    "wof:name":"David Isaac & Assoc",
    "wof:placetype":"venue"
},
  "geometry": {"coordinates":[-86.11978499999999,40.47664],"type":"Point"}
}