{
  "type": "Feature",
  "properties": {
    "iso:country":"US",
    "sg:address":"359 N Lynhurst Dr",
    "sg:city":"Indianapolis",
    "sg:classifiers":[
        {
            "category":"Retail",
            "subcategory":"Auto Repair",
            "type":"Services"
        }
    ],
    "sg:phone":"+1 317 487 0505",
    "sg:postcode":"46224",
    "sg:province":"IN",
    "sg:tags":[
        "general"
    ],
    "wof:name":"Budget Transmission",
    "wof:placetype":"venue"
},
  "geometry": {"coordinates":[-86.250371,39.771666],"type":"Point"}
}