{
  "type": "Feature",
  "properties": {
    "iso:country":"US",
    "sg:address":"4200 N Michigan Rd",
    "sg:city":"Shelbyville",
    "sg:classifiers":[
        {
            "category":"Restaurant",
            "type":"Food & Drink"
        }
    ],
    "sg:phone":"+1 317 421 0000",
    "sg:postcode":"46176",
    "sg:province":"IN",
    "sg:tags":[
        "banquet",
        "rooms"
    ],
    "sg:website":"www.indianadowns.com",
    "wof:name":"Indiana Downs",
    "wof:placetype":"venue"
},
  "geometry": {"coordinates":[-85.822813,39.585451],"type":"Point"}
}