{
  "type": "Feature",
  "properties": {
    "iso:country":"US",
    "sg:address":"7177 Yankeetown Rd",
    "sg:city":"Newburgh",
    "sg:classifiers":[
        {
            "category":"Shopping",
            "subcategory":"Optical Goods",
            "type":"Retail Goods"
        }
    ],
    "sg:phone":"+1 812 853 5001",
    "sg:postcode":"47630",
    "sg:province":"IN",
    "wof:name":"Eyeglass Factory Outlet",
    "wof:placetype":"venue"
},
  "geometry": {"coordinates":[-87.297292,37.926991],"type":"Point"}
}