{
  "type": "Feature",
  "properties": {
    "addr:full":"2544 Cannon St New Albany IN 47150",
    "addr:housenumber":"2544",
    "addr:postcode":"47150",
    "addr:street":"Cannon St",
    "iso:country":"US",
    "sg:address":"2544 Cannon St",
    "sg:city":"New Albany",
    "sg:classifiers":[
        {
            "category":"Wholesale",
            "subcategory":"Machinery & Supplies",
            "type":"Manufacturing & Wholesale Goods"
        }
    ],
    "sg:phone":"+1 812 944 9684",
    "sg:postcode":"47150",
    "sg:province":"IN",
    "sg:tags":[
        "compressor",
        "gas"
    ],
    "wof:name":"Air Services Kentuckiana",
    "wof:placetype":"venue"
},
  "geometry": {"coordinates":[-85.81621699999999,38.312553],"type":"Point"}
}