{
  "type": "Feature",
  "properties": {
    "iso:country":"US",
    "sg:address":"1739 W Division Rd",
    "sg:city":"Huntington",
    "sg:classifiers":[
        {
            "category":"Professional",
            "subcategory":"Advertising",
            "type":"Services"
        }
    ],
    "sg:phone":"+1 260 468 2870",
    "sg:postcode":"46750",
    "sg:province":"IN",
    "sg:tags":[
        "agency"
    ],
    "wof:name":"Creative Chameleon",
    "wof:placetype":"venue"
},
  "geometry": {"coordinates":[-85.482951,40.82929],"type":"Point"}
}