{
  "type": "Feature",
  "properties": {
    "iso:country":"US",
    "sg:address":"6809 Columbia Ave",
    "sg:city":"Hammond",
    "sg:classifiers":[
        {
            "category":"Real Estate",
            "subcategory":"Real Estate Services",
            "type":"Services"
        },
        {
            "category":"Real Estate",
            "subcategory":"Real Estate Agent",
            "type":"Services"
        }
    ],
    "sg:phone":"+1 219 989 9070",
    "sg:postcode":"46324",
    "sg:province":"IN",
    "sg:tags":[
        "buyer",
        "broker"
    ],
    "wof:name":"Meier's Real Estate Plaza",
    "wof:placetype":"venue"
},
  "geometry": {"coordinates":[-87.50018300000001,41.58984],"type":"Point"}
}