{
  "type": "Feature",
  "properties": {
    "iso:country":"US",
    "sg:address":"2466 Galaxy Ln",
    "sg:city":"Indianapolis",
    "sg:classifiers":[
        {
            "category":"Building & Trades",
            "subcategory":"Construction",
            "type":"Services"
        }
    ],
    "sg:phone":"+1 317 899 5683",
    "sg:postcode":"46229",
    "sg:province":"IN",
    "sg:tags":[
        "hanging",
        "contractor"
    ],
    "wof:name":"Naptown Painting & Cnstr",
    "wof:placetype":"venue"
},
  "geometry": {"coordinates":[-86.006973,39.80372],"type":"Point"}
}