{
  "type": "Feature",
  "properties": {
    "iso:country":"US",
    "sg:address":"304 E 10th St",
    "sg:city":"Auburn",
    "sg:classifiers":[
        {
            "category":"Shopping",
            "subcategory":"Discount & Variety Stores",
            "type":"Retail Goods"
        }
    ],
    "sg:phone":"+1 260 925 1148",
    "sg:postcode":"46706",
    "sg:province":"IN",
    "wof:name":"Curiosity Shop",
    "wof:placetype":"venue"
},
  "geometry": {"coordinates":[-85.052446,41.365422],"type":"Point"}
}