{
  "type": "Feature",
  "properties": {
    "addr:full":"4942 Comanche Ln Indianapolis IN 46254",
    "addr:housenumber":"4942",
    "addr:postcode":"46254",
    "addr:street":"Comanche Ln",
    "iso:country":"US",
    "sg:address":"4942 Comanche Ln",
    "sg:city":"Indianapolis",
    "sg:classifiers":[
        {
            "category":"Building & Trades",
            "subcategory":"Construction",
            "type":"Services"
        }
    ],
    "sg:phone":"+1 317 299 8876",
    "sg:postcode":"46254",
    "sg:province":"IN",
    "sg:tags":[
        "house"
    ],
    "wof:name":"McKinzie Builders",
    "wof:placetype":"venue"
},
  "geometry": {"coordinates":[-86.274815,39.842896],"type":"Point"}
}