{
  "type": "Feature",
  "properties": {
    "addr:full":"11810 E Washington St Indianapolis IN 46229",
    "addr:housenumber":"11810",
    "addr:postcode":"46229",
    "addr:street":"E Washington St",
    "iso:country":"US",
    "sg:address":"11810 E Washington St",
    "sg:city":"Indianapolis",
    "sg:classifiers":[
        {
            "category":"Personal",
            "subcategory":"Beauty Salon",
            "type":"Services"
        }
    ],
    "sg:phone":"+1 317 894 0581",
    "sg:postcode":"46229",
    "sg:province":"IN",
    "wof:name":"Hair Gallery",
    "wof:placetype":"venue"
},
  "geometry": {"coordinates":[-85.956159,39.776586],"type":"Point"}
}