{
  "type": "Feature",
  "properties": {
    "addr:full":"912 Middlebury St Goshen IN 46528",
    "addr:housenumber":"912",
    "addr:postcode":"46528",
    "addr:street":"Middlebury St",
    "iso:country":"US",
    "sg:address":"912 Middlebury St",
    "sg:city":"Goshen",
    "sg:classifiers":[
        {
            "category":"Social Services",
            "type":"Services"
        }
    ],
    "sg:phone":"+1 574 533 4590",
    "sg:postcode":"46528",
    "sg:province":"IN",
    "sg:tags":[
        "youth",
        "organization",
        "center"
    ],
    "wof:name":"Camp Fire Council Of Elkhart",
    "wof:placetype":"venue"
},
  "geometry": {"coordinates":[-85.819605,41.597918],"type":"Point"}
}