{
  "type": "Feature",
  "properties": {
    "iso:country":"US",
    "sg:address":"301 N Elm St",
    "sg:city":"Nappanee",
    "sg:classifiers":[
        {
            "category":"Professional",
            "subcategory":"Management & Consulting",
            "type":"Services"
        }
    ],
    "sg:phone":"+1 574 773 3339",
    "sg:postcode":"46550",
    "sg:province":"IN",
    "sg:tags":[
        "marketing",
        "consultant"
    ],
    "sg:website":"www.naugahyde.com",
    "wof:name":"Fales Marketing Inc",
    "wof:placetype":"venue"
},
  "geometry": {"coordinates":[-85.999971,41.445517],"type":"Point"}
}