{
  "type": "Feature",
  "properties": {
    "iso:country":"US",
    "sg:address":"8555 Taft St",
    "sg:city":"Merrillville",
    "sg:classifiers":[
        {
            "category":"Health Services",
            "subcategory":"Doctor",
            "type":"Services"
        },
        {
            "category":"Social Services",
            "type":"Services"
        },
        {
            "category":"Personal",
            "type":"Services"
        },
        {
            "category":"Health Services",
            "subcategory":"Health Practitioner",
            "type":"Services"
        },
        {
            "category":"Health Services",
            "subcategory":"Clinic",
            "type":"Services"
        }
    ],
    "sg:phone":"+1 219 769 4005",
    "sg:postcode":"46410",
    "sg:province":"IN",
    "sg:tags":[
        "information",
        "mental",
        "family",
        "physician",
        "surgeons",
        "abuse",
        "drug",
        "individual",
        "marriage",
        "treatment",
        "child",
        "psychiatry",
        "counseling",
        "addiction",
        "counselor",
        "alcoholism"
    ],
    "sg:website":"http://www.regionalmentalhealth.org",
    "wof:name":"Regional Mental Health Center",
    "wof:placetype":"venue"
},
  "geometry": {"coordinates":[-87.36494,41.462062],"type":"Point"}
}