{
  "type": "Feature",
  "properties": {
    "iso:country":"US",
    "sg:address":"90 N Celestine Rd S",
    "sg:city":"Celestine",
    "sg:classifiers":[
        {
            "category":"Professional",
            "type":"Services"
        }
    ],
    "sg:phone":"+1 812 482 6405",
    "sg:postcode":"47521",
    "sg:province":"IN",
    "sg:tags":[
        "establishment"
    ],
    "wof:name":"Celestine J C's",
    "wof:placetype":"venue"
},
  "geometry": {"coordinates":[-86.77903999999999,38.382154],"type":"Point"}
}