{
  "type": "Feature",
  "properties": {
    "iso:country":"US",
    "sg:address":"9595 Whitley Dr",
    "sg:city":"Indianapolis",
    "sg:classifiers":[
        {
            "category":"Professional",
            "subcategory":"Lawyer & Legal Services",
            "type":"Services"
        }
    ],
    "sg:phone":"+1 317 846 4657",
    "sg:postcode":"46240",
    "sg:province":"IN",
    "sg:tags":[
        "attorney"
    ],
    "wof:name":"Roger W Shinness",
    "wof:placetype":"venue"
},
  "geometry": {"coordinates":[-86.115019,39.924121],"type":"Point"}
}