{
  "type": "Feature",
  "properties": {
    "iso:country":"US",
    "sg:address":"1400 Fountain Ave",
    "sg:city":"Evansville",
    "sg:classifiers":[
        {
            "category":"Building & Trades",
            "subcategory":"Plumbing",
            "type":"Services"
        }
    ],
    "sg:phone":"+1 812 425 0165",
    "sg:postcode":"47710",
    "sg:province":"IN",
    "sg:tags":[
        "plumbing",
        "contractor"
    ],
    "wof:name":"Hoffman Plumbing Co",
    "wof:placetype":"venue"
},
  "geometry": {"coordinates":[-87.584076,37.986516],"type":"Point"}
}