{
  "type": "Feature",
  "properties": {
    "iso:country":"US",
    "sg:address":"5804 Ridgeland Dr",
    "sg:city":"Brownsburg",
    "sg:classifiers":[
        {
            "category":"Professional",
            "subcategory":"Business Services",
            "type":"Services"
        }
    ],
    "sg:phone":"+1 317 852 9646",
    "sg:postcode":"46112",
    "sg:province":"IN",
    "sg:tags":[
        "paging",
        "answering"
    ],
    "wof:name":"React Technologies Inc",
    "wof:placetype":"venue"
},
  "geometry": {"coordinates":[-86.424066,39.821609],"type":"Point"}
}