{
  "type": "Feature",
  "properties": {
    "iso:country":"US",
    "sg:address":"7945 S Voyles Rd",
    "sg:city":"Pekin",
    "sg:classifiers":[
        {
            "category":"Building & Trades",
            "subcategory":"Construction",
            "type":"Services"
        }
    ],
    "sg:phone":"+1 812 967 3589",
    "sg:postcode":"47165",
    "sg:province":"IN",
    "sg:tags":[
        "house"
    ],
    "wof:name":"Leenen Construction",
    "wof:placetype":"venue"
},
  "geometry": {"coordinates":[-86.002955,38.484053],"type":"Point"}
}