{
  "type": "Feature",
  "properties": {
    "addr:full":"3545 S Washington St Marion IN 46953",
    "addr:housenumber":"3545",
    "addr:postcode":"46953",
    "addr:street":"S Washington St",
    "iso:country":"US",
    "sg:address":"3545 S Washington St",
    "sg:city":"Marion",
    "sg:classifiers":[
        {
            "category":"Government",
            "subcategory":"Office",
            "type":"Public Place"
        }
    ],
    "sg:phone":"+1 765 674 1677",
    "sg:postcode":"46953",
    "sg:province":"IN",
    "sg:tags":[
        "village"
    ],
    "wof:name":"Center Township Trustees Ofc",
    "wof:placetype":"venue"
},
  "geometry": {"coordinates":[-85.66341799999999,40.526748],"type":"Point"}
}