{
  "type": "Feature",
  "properties": {
    "addr:full":"100 Vernon St North Vernon IN 47265",
    "addr:housenumber":"100",
    "addr:postcode":"47265",
    "addr:street":"Vernon St",
    "iso:country":"US",
    "sg:address":"100 Vernon St",
    "sg:city":"North Vernon",
    "sg:classifiers":[
        {
            "category":"Education",
            "subcategory":"School",
            "type":"Public Place"
        }
    ],
    "sg:phone":"+1 812 346 7830",
    "sg:postcode":"47265",
    "sg:province":"IN",
    "wof:name":"Jennings County Early Learning",
    "wof:placetype":"venue"
},
  "geometry": {"coordinates":[-85.622833,39.002843],"type":"Point"}
}