{
  "type": "Feature",
  "properties": {
    "iso:country":"US",
    "sg:address":"1023 Highway 62",
    "sg:city":"Charlestown",
    "sg:classifiers":[
        {
            "category":"Food & Beverages",
            "subcategory":"Groceries & Convenience Stores",
            "type":"Retail Goods"
        }
    ],
    "sg:phone":"+1 812 256 2332",
    "sg:postcode":"47111",
    "sg:province":"IN",
    "wof:name":"Spalding B P",
    "wof:placetype":"venue"
},
  "geometry": {"coordinates":[-85.68733,38.383741],"type":"Point"}
}