{
  "type": "Feature",
  "properties": {
    "iso:country":"US",
    "sg:address":"8337 Jackson Ave",
    "sg:city":"Munster",
    "sg:classifiers":[
        {
            "category":"Retail",
            "subcategory":"Laundry & Dry Cleaning",
            "type":"Services"
        }
    ],
    "sg:phone":"+1 219 836 2292",
    "sg:postcode":"46321",
    "sg:province":"IN",
    "sg:tags":[
        "cleaners"
    ],
    "wof:name":"Coit Drapery Cleaners Inc",
    "wof:placetype":"venue"
},
  "geometry": {"coordinates":[-87.513802,41.560725],"type":"Point"}
}