{
  "type": "Feature",
  "properties": {
    "iso:country":"US",
    "sg:address":"6141 N Independence Pine Village Rd",
    "sg:city":"Pine Village",
    "sg:classifiers":[
        {
            "category":"Real Estate",
            "subcategory":"Real Estate Agent",
            "type":"Services"
        }
    ],
    "sg:phone":"+1 765 385 2225",
    "sg:postcode":"47975",
    "sg:province":"IN",
    "wof:name":"Rainbow Realty",
    "wof:placetype":"venue"
},
  "geometry": {"coordinates":[-87.23965099999999,40.41096],"type":"Point"}
}