{
  "type": "Feature",
  "properties": {
    "iso:country":"US",
    "sg:address":"8670 Rawles Ave",
    "sg:city":"Indianapolis",
    "sg:classifiers":[
        {
            "category":"Personal",
            "type":"Services"
        }
    ],
    "sg:phone":"+1 317 895 8113",
    "sg:postcode":"46219",
    "sg:province":"IN",
    "wof:name":"Treasured Weddings Brdl Consln",
    "wof:placetype":"venue"
},
  "geometry": {"coordinates":[-86.013722,39.762175],"type":"Point"}
}