{
  "type": "Feature",
  "properties": {
    "iso:country":"US",
    "sg:address":"3853 N Washington Blvd",
    "sg:city":"Indianapolis",
    "sg:classifiers":[
        {
            "category":"Personal",
            "subcategory":"Beauty Salon",
            "type":"Services"
        }
    ],
    "sg:phone":"+1 317 545 0452",
    "sg:postcode":"46205",
    "sg:province":"IN",
    "sg:tags":[
        "cosmetologist"
    ],
    "wof:name":"Harold O Bishop",
    "wof:placetype":"venue"
},
  "geometry": {"coordinates":[-86.152075,39.827625],"type":"Point"}
}