{
  "type": "Feature",
  "properties": {
    "iso:country":"US",
    "sg:address":"1724 N Lindsay St",
    "sg:city":"Kokomo",
    "sg:classifiers":[
        {
            "category":"Organizations",
            "subcategory":"Religious Organization",
            "type":"Services"
        }
    ],
    "sg:phone":"+1 765 457 5426",
    "sg:postcode":"46901",
    "sg:province":"IN",
    "sg:tags":[
        "church"
    ],
    "wof:name":"Kokomo Missionary Baptist Chr",
    "wof:placetype":"venue"
},
  "geometry": {"coordinates":[-86.144345,40.503217],"type":"Point"}
}