{
  "type": "Feature",
  "properties": {
    "iso:country":"US",
    "sg:address":"2021 W Lloyd Expy",
    "sg:city":"Evansville",
    "sg:classifiers":[
        {
            "category":"Shopping",
            "subcategory":"Stationery & Office Supplies",
            "type":"Retail Goods"
        }
    ],
    "sg:phone":"+1 812 423 6475",
    "sg:postcode":"47712",
    "sg:province":"IN",
    "sg:website":"www.royalofficeproducts.net",
    "wof:name":"Royal Office Products Inc",
    "wof:placetype":"venue"
},
  "geometry": {"coordinates":[-87.595487,37.977957],"type":"Point"}
}