{
  "type": "Feature",
  "properties": {
    "addr:full":"244 N Jefferson St Cromwell IN 46732",
    "addr:housenumber":"244",
    "addr:postcode":"46732",
    "addr:street":"N Jefferson St",
    "iso:country":"US",
    "sg:address":"244 N Jefferson St",
    "sg:city":"Cromwell",
    "sg:classifiers":[
        {
            "category":"Organizations",
            "subcategory":"Religious Organization",
            "type":"Services"
        }
    ],
    "sg:phone":"+1 260 856 2577",
    "sg:postcode":"46732",
    "sg:province":"IN",
    "sg:tags":[
        "clergy"
    ],
    "wof:name":"Cromwell United Methodist Chr",
    "wof:placetype":"venue"
},
  "geometry": {"coordinates":[-85.61491100000001,41.401489],"type":"Point"}
}