{
  "type": "Feature",
  "properties": {
    "iso:country":"US",
    "sg:address":"1256 Washington St",
    "sg:city":"Columbus",
    "sg:classifiers":[
        {
            "category":"Manufacturing",
            "subcategory":"Electronics",
            "type":"Manufacturing & Wholesale Goods"
        }
    ],
    "sg:phone":"+1 812 378 5903",
    "sg:postcode":"47201",
    "sg:province":"IN",
    "sg:tags":[
        "instrument",
        "electronic"
    ],
    "sg:website":"www.flexcell.com",
    "wof:name":"Cybermetrix",
    "wof:placetype":"venue"
},
  "geometry": {"coordinates":[-85.92154,39.21226],"type":"Point"}
}