{
  "type": "Feature",
  "properties": {
    "iso:country":"US",
    "sg:address":"638 Laura Ln",
    "sg:city":"Sweetser",
    "sg:classifiers":[
        {
            "category":"Professional",
            "subcategory":"Management & Consulting",
            "type":"Services"
        }
    ],
    "sg:phone":"+1 765 384 7997",
    "sg:postcode":"46987",
    "sg:province":"IN",
    "sg:tags":[
        "selling",
        "establishment",
        "direct"
    ],
    "wof:name":"Shaklee Distributor",
    "wof:placetype":"venue"
},
  "geometry": {"coordinates":[-85.760514,40.576581],"type":"Point"}
}