{
  "type": "Feature",
  "properties": {
    "iso:country":"US",
    "sg:address":"6848 Columbia Ave",
    "sg:city":"Hammond",
    "sg:classifiers":[
        {
            "category":"Autos & Motor Vehicles",
            "subcategory":"Automobile Sales",
            "type":"Retail Goods"
        }
    ],
    "sg:phone":"+1 219 932 4899",
    "sg:postcode":"46324",
    "sg:province":"IN",
    "sg:tags":[
        "used"
    ],
    "wof:name":"A One Motors",
    "wof:placetype":"venue"
},
  "geometry": {"coordinates":[-87.49996899999999,41.58916],"type":"Point"}
}