{
  "type": "Feature",
  "properties": {
    "iso:country":"US",
    "sg:address":"2346 S Lynhurst Dr",
    "sg:city":"Indianapolis",
    "sg:classifiers":[
        {
            "category":"Building & Trades",
            "subcategory":"Construction",
            "type":"Services"
        }
    ],
    "sg:phone":"+1 317 240 1130",
    "sg:postcode":"46241",
    "sg:province":"IN",
    "sg:tags":[
        "fire",
        "restoration",
        "damage"
    ],
    "wof:name":"Munters Moisture Control Svc",
    "wof:placetype":"venue"
},
  "geometry": {"coordinates":[-86.250387,39.73303],"type":"Point"}
}