{
  "type": "Feature",
  "properties": {
    "addr:full":"217 Main St Vincennes IN 47591",
    "addr:housenumber":"217",
    "addr:postcode":"47591",
    "addr:street":"Main St",
    "iso:country":"US",
    "sg:address":"217 Main St",
    "sg:city":"Vincennes",
    "sg:classifiers":[
        {
            "category":"Shopping",
            "subcategory":"Jewelry",
            "type":"Retail Goods"
        }
    ],
    "sg:phone":"+1 812 882 7603",
    "sg:postcode":"47591",
    "sg:province":"IN",
    "sg:tags":[
        "jeweler"
    ],
    "wof:name":"Jewel Craft Jewelers",
    "wof:placetype":"venue"
},
  "geometry": {"coordinates":[-87.53232800000001,38.679737],"type":"Point"}
}