{
  "type": "Feature",
  "properties": {
    "iso:country":"US",
    "sg:address":"802 S Washington St",
    "sg:city":"Kokomo",
    "sg:classifiers":[
        {
            "category":"Real Estate",
            "subcategory":"Real Estate Operator",
            "type":"Services"
        }
    ],
    "sg:phone":"+1 765 452 1474",
    "sg:postcode":"46901",
    "sg:province":"IN",
    "sg:tags":[
        "apartment"
    ],
    "wof:name":"Source One Property Management",
    "wof:placetype":"venue"
},
  "geometry": {"coordinates":[-86.133517,40.477728],"type":"Point"}
}