{
  "type": "Feature",
  "properties": {
    "iso:country":"US",
    "sg:address":"9145 E 56th St",
    "sg:city":"Indianapolis",
    "sg:classifiers":[
        {
            "category":"Bakery",
            "type":"Food & Drink"
        }
    ],
    "sg:menulink":"http://www.allmenus.com/in/lawrence/102990-panera-bread/menu/",
    "sg:phone":"+1 317 542 7450",
    "sg:postcode":"46216",
    "sg:province":"IN",
    "sg:tags":[
        "american",
        "sandwich",
        "pastry"
    ],
    "wof:name":"Panera Bread",
    "wof:placetype":"venue"
},
  "geometry": {"coordinates":[-86.007007,39.854853],"type":"Point"}
}