{
  "type": "Feature",
  "properties": {
    "iso:country":"US",
    "sg:address":"36 Cottonwood Dr",
    "sg:city":"Garrett",
    "sg:classifiers":[
        {
            "category":"Travel",
            "subcategory":"Travel Agent",
            "type":"Entertainment"
        }
    ],
    "sg:phone":"+1 260 925 0437",
    "sg:postcode":"46738",
    "sg:province":"IN",
    "sg:tags":[
        "agency",
        "bureau"
    ],
    "wof:name":"Walton Travel",
    "wof:placetype":"venue"
},
  "geometry": {"coordinates":[-85.131797,41.283809],"type":"Point"}
}