{
  "type": "Feature",
  "properties": {
    "addr:full":"3240 S Adams St Marion IN 46953",
    "addr:housenumber":"3240",
    "addr:postcode":"46953",
    "addr:street":"S Adams St",
    "iso:country":"US",
    "sg:address":"3240 S Adams St",
    "sg:city":"Marion",
    "sg:classifiers":[
        {
            "category":"Retail",
            "subcategory":"Laundry & Dry Cleaning",
            "type":"Services"
        }
    ],
    "sg:phone":"+1 765 662 1525",
    "sg:postcode":"46953",
    "sg:province":"IN",
    "sg:tags":[
        "cleaners"
    ],
    "wof:name":"Red Dot Cleaners",
    "wof:placetype":"venue"
},
  "geometry": {"coordinates":[-85.658674,40.530882],"type":"Point"}
}