{
  "type": "Feature",
  "properties": {
    "iso:country":"US",
    "sg:address":"1277 Maxwell Ave",
    "sg:city":"Evansville",
    "sg:classifiers":[
        {
            "category":"Freight",
            "type":"Transportation"
        }
    ],
    "sg:phone":"+1 812 422 2830",
    "sg:postcode":"47711",
    "sg:province":"IN",
    "sg:tags":[
        "trucking"
    ],
    "wof:name":"Hamrick's Diesel Svc",
    "wof:placetype":"venue"
},
  "geometry": {"coordinates":[-87.541628,37.993677],"type":"Point"}
}