{
  "type": "Feature",
  "properties": {
    "iso:country":"US",
    "sg:address":"1203 Trace 12",
    "sg:city":"West Lafayette",
    "sg:classifiers":[
        {
            "category":"Health Services",
            "subcategory":"Doctor",
            "type":"Services"
        }
    ],
    "sg:phone":"+1 765 497 2424",
    "sg:postcode":"47906",
    "sg:province":"IN",
    "sg:tags":[
        "medical"
    ],
    "wof:name":"Neurodiagnostics",
    "wof:placetype":"venue"
},
  "geometry": {"coordinates":[-86.92061,40.448552],"type":"Point"}
}