{
  "type": "Feature",
  "properties": {
    "iso:country":"US",
    "sg:address":"706 E Main St",
    "sg:city":"Plainfield",
    "sg:phone":"+1 317 839 0492",
    "sg:postcode":"46168",
    "sg:province":"IN",
    "sg:tags":[
        "farm",
        "corn",
        "wheat",
        "soybean"
    ],
    "wof:name":"Broyles Farms",
    "wof:placetype":"venue"
},
  "geometry": {"coordinates":[-86.39215799999999,39.70621],"type":"Point"}
}