{
  "type": "Feature",
  "properties": {
    "iso:country":"US",
    "sg:address":"521 E 86th Ave",
    "sg:city":"Merrillville",
    "sg:classifiers":[
        {
            "category":"Health Services",
            "subcategory":"Hospital",
            "type":"Services"
        }
    ],
    "sg:phone":"+1 219 576 7610",
    "sg:postcode":"46410",
    "sg:province":"IN",
    "sg:tags":[
        "equipment",
        "supply"
    ],
    "sg:website":"http://www.patientadvocatehomecare.com",
    "wof:name":"Your Home Medical Equipment Specialist",
    "wof:placetype":"venue"
},
  "geometry": {"coordinates":[-87.33026,41.462372],"type":"Point"}
}