{
  "type": "Feature",
  "properties": {
    "addr:full":"2840 S Sunrise Dr New Palestine IN 46163",
    "addr:housenumber":"2840",
    "addr:postcode":"46163",
    "addr:street":"S Sunrise Dr",
    "iso:country":"US",
    "sg:address":"2840 S Sunrise Dr",
    "sg:city":"New Palestine",
    "sg:classifiers":[
        {
            "category":"Personal",
            "subcategory":"Beauty Salon",
            "type":"Services"
        }
    ],
    "sg:phone":"+1 317 861 5657",
    "sg:postcode":"46163",
    "sg:province":"IN",
    "sg:tags":[
        "shop"
    ],
    "wof:name":"Pfeiffer Julie Hair Technique",
    "wof:placetype":"venue"
},
  "geometry": {"coordinates":[-85.94555099999999,39.746235],"type":"Point"}
}