{
  "type": "Feature",
  "properties": {
    "iso:country":"US",
    "sg:address":"4494 Wozniak Rd",
    "sg:city":"Michigan City",
    "sg:classifiers":[
        {
            "category":"Wholesale",
            "subcategory":"Machinery & Supplies",
            "type":"Manufacturing & Wholesale Goods"
        }
    ],
    "sg:phone":"+1 219 874 5383",
    "sg:postcode":"46360",
    "sg:province":"IN",
    "sg:tags":[
        "equipment",
        "hydraulic"
    ],
    "wof:name":"Barenie Products Inc",
    "wof:placetype":"venue"
},
  "geometry": {"coordinates":[-86.84515399999999,41.666603],"type":"Point"}
}