{
  "type": "Feature",
  "properties": {
    "iso:country":"US",
    "sg:address":"700 4th St NW",
    "sg:city":"Linton",
    "sg:classifiers":[
        {
            "category":"Professional",
            "subcategory":"Management & Consulting",
            "type":"Services"
        }
    ],
    "sg:phone":"+1 812 847 3452",
    "sg:postcode":"47441",
    "sg:province":"IN",
    "sg:tags":[
        "consultant"
    ],
    "wof:name":"Decision Services Inc",
    "wof:placetype":"venue"
},
  "geometry": {"coordinates":[-87.170502,39.041132],"type":"Point"}
}