{
  "type": "Feature",
  "properties": {
    "iso:country":"US",
    "sg:address":"298 Gasoline Aly",
    "sg:city":"Indianapolis",
    "sg:classifiers":[
        {
            "category":"Manufacturing",
            "subcategory":"Tools & Machinery",
            "type":"Manufacturing & Wholesale Goods"
        }
    ],
    "sg:phone":"+1 317 241 3428",
    "sg:postcode":"46222",
    "sg:province":"IN",
    "sg:tags":[
        "machine",
        "shop"
    ],
    "wof:name":"Merritt Machine Corp",
    "wof:placetype":"venue"
},
  "geometry": {"coordinates":[-86.23535,39.769965],"type":"Point"}
}