{
  "type": "Feature",
  "properties": {
    "iso:country":"US",
    "sg:address":"1901 W 11th Ave",
    "sg:city":"Gary",
    "sg:classifiers":[
        {
            "category":"Shopping",
            "subcategory":"Clothing, Apparel, & Fashions",
            "type":"Retail Goods"
        }
    ],
    "sg:phone":"+1 219 883 2838",
    "sg:postcode":"46404",
    "sg:province":"IN",
    "wof:name":"Arines Shop & Run Clothing",
    "wof:placetype":"venue"
},
  "geometry": {"coordinates":[-87.361764,41.591481],"type":"Point"}
}