{
  "type": "Feature",
  "properties": {
    "iso:country":"US",
    "sg:address":"62888 US Hwy 31",
    "sg:city":"South Bend",
    "sg:classifiers":[
        {
            "category":"Freight",
            "type":"Transportation"
        }
    ],
    "sg:phone":"+1 574 291 0000",
    "sg:postcode":"46614",
    "sg:province":"IN",
    "sg:tags":[
        "commercial",
        "storage"
    ],
    "wof:name":"ABC Mini Storage & Warehouse",
    "wof:placetype":"venue"
},
  "geometry": {"coordinates":[-86.262215,41.580335],"type":"Point"}
}