{
  "type": "Feature",
  "properties": {
    "iso:country":"US",
    "sg:address":"7916 Zionsville Rd",
    "sg:city":"Indianapolis",
    "sg:classifiers":[
        {
            "category":"Wholesale",
            "subcategory":"Machinery & Supplies",
            "type":"Manufacturing & Wholesale Goods"
        }
    ],
    "sg:phone":"+1 317 872 6772",
    "sg:postcode":"46268",
    "sg:province":"IN",
    "sg:tags":[
        "tool"
    ],
    "sg:website":"www.alcorn-inc.com",
    "wof:name":"Alcorn Industrial",
    "wof:placetype":"venue"
},
  "geometry": {"coordinates":[-86.25992599999999,39.897846],"type":"Point"}
}