{
  "type": "Feature",
  "properties": {
    "addr:full":"2602 E 55th St Indianapolis IN 46220",
    "addr:housenumber":"2602",
    "addr:postcode":"46220",
    "addr:street":"E 55Th St",
    "iso:country":"US",
    "sg:address":"2602 E 55th St",
    "sg:city":"Indianapolis",
    "sg:classifiers":[
        {
            "category":"Manufacturing",
            "subcategory":"Metals",
            "type":"Manufacturing & Wholesale Goods"
        }
    ],
    "sg:phone":"+1 317 259 6283",
    "sg:postcode":"46220",
    "sg:province":"IN",
    "sg:tags":[
        "lock",
        "safe",
        "coin",
        "vault"
    ],
    "wof:name":"Security Group Inc",
    "wof:placetype":"venue"
},
  "geometry": {"coordinates":[-86.1177,39.852722],"type":"Point"}
}