{
  "type": "Feature",
  "properties": {
    "iso:country":"US",
    "sg:address":"4710 US Hwy 40 Scn",
    "sg:city":"Plainfield",
    "sg:classifiers":[
        {
            "category":"Organizations",
            "subcategory":"Community Association",
            "type":"Services"
        }
    ],
    "sg:phone":"+1 317 839 2186",
    "sg:postcode":"46168",
    "sg:province":"IN",
    "sg:tags":[
        "fraternal"
    ],
    "wof:name":"Elks Lodge",
    "wof:placetype":"venue"
},
  "geometry": {"coordinates":[-86.437743,39.690971],"type":"Point"}
}