{
  "type": "Feature",
  "properties": {
    "iso:country":"US",
    "sg:address":"986 S Center St",
    "sg:city":"Plainfield",
    "sg:classifiers":[
        {
            "category":"Building & Trades",
            "subcategory":"Construction",
            "type":"Services"
        }
    ],
    "sg:phone":"+1 317 839 3490",
    "sg:postcode":"46168",
    "sg:province":"IN",
    "sg:tags":[
        "marking",
        "maintenance",
        "parking"
    ],
    "wof:name":"Plainfield Public Works",
    "wof:placetype":"venue"
},
  "geometry": {"coordinates":[-86.39453,39.692424],"type":"Point"}
}