{
  "type": "Feature",
  "properties": {
    "iso:country":"US",
    "sg:address":"13934 S 700 E",
    "sg:city":"Clarks Hill",
    "sg:classifiers":[
        {
            "category":"Wholesale",
            "subcategory":"Farm Supplies",
            "type":"Manufacturing & Wholesale Goods"
        }
    ],
    "sg:phone":"+1 765 523 2787",
    "sg:postcode":"47930",
    "sg:province":"IN",
    "sg:tags":[
        "fertilizer"
    ],
    "wof:name":"Crop Production Svc Inc",
    "wof:placetype":"venue"
},
  "geometry": {"coordinates":[-86.771174,40.215554],"type":"Point"}
}