{
  "type": "Feature",
  "properties": {
    "iso:country":"US",
    "sg:address":"350 Canal Walk",
    "sg:city":"Indianapolis",
    "sg:classifiers":[
        {
            "category":"Professional",
            "subcategory":"Management & Consulting",
            "type":"Services"
        }
    ],
    "sg:phone":"+1 317 472 0099",
    "sg:postcode":"46202",
    "sg:province":"IN",
    "sg:tags":[
        "counselor",
        "public",
        "relations"
    ],
    "wof:name":"Robert K Johnson",
    "wof:placetype":"venue"
},
  "geometry": {"coordinates":[-86.164641,39.772151],"type":"Point"}
}