{
  "type": "Feature",
  "properties": {
    "iso:country":"US",
    "sg:address":"19 S Green St",
    "sg:city":"Cambridge City",
    "sg:classifiers":[
        {
            "category":"Personal",
            "subcategory":"Beauty Salon",
            "type":"Services"
        }
    ],
    "sg:phone":"+1 765 478 9607",
    "sg:postcode":"47327",
    "sg:province":"IN",
    "wof:name":"New Look",
    "wof:placetype":"venue"
},
  "geometry": {"coordinates":[-85.173507,39.81229],"type":"Point"}
}