{
  "type": "Feature",
  "properties": {
    "iso:country":"US",
    "sg:address":"551 E Main St",
    "sg:city":"Hagerstown",
    "sg:classifiers":[
        {
            "category":"Manufacturing",
            "subcategory":"Tools & Machinery",
            "type":"Manufacturing & Wholesale Goods"
        }
    ],
    "sg:phone":"+1 765 489 6302",
    "sg:postcode":"47346",
    "sg:province":"IN",
    "sg:tags":[
        "physician",
        "surgeon"
    ],
    "wof:name":"Precision Wire Assembly Inc",
    "wof:placetype":"venue"
},
  "geometry": {"coordinates":[-85.152679,39.91049],"type":"Point"}
}