{
  "type": "Feature",
  "properties": {
    "iso:country":"US",
    "sg:address":"123 NW 4th St",
    "sg:city":"Evansville",
    "sg:classifiers":[
        {
            "category":"Professional",
            "subcategory":"Business Services",
            "type":"Services"
        }
    ],
    "sg:phone":"+1 812 425 6247",
    "sg:postcode":"47708",
    "sg:province":"IN",
    "wof:name":"Tri State Business Group Hlth",
    "wof:placetype":"venue"
},
  "geometry": {"coordinates":[-87.572273,37.973101],"type":"Point"}
}