{
  "type": "Feature",
  "properties": {
    "iso:country":"US",
    "sg:address":"4207 W 96th St",
    "sg:city":"Indianapolis",
    "sg:classifiers":[
        {
            "category":"Wholesale",
            "subcategory":"Meat",
            "type":"Manufacturing & Wholesale Goods"
        },
        {
            "category":"Restaurant",
            "type":"Food & Drink"
        }
    ],
    "sg:phone":"+1 317 876 8878",
    "sg:postcode":"46268",
    "sg:province":"IN",
    "sg:tags":[
        "meat-wholesale"
    ],
    "sg:website":"http://www.heavenlyham.com",
    "wof:name":"Heavenly Hams",
    "wof:placetype":"venue"
},
  "geometry": {"coordinates":[-86.23168200000001,39.92614],"type":"Point"}
}