{
  "type": "Feature",
  "properties": {
    "iso:country":"US",
    "sg:address":"1621 S Base Rd",
    "sg:city":"Rushville",
    "sg:classifiers":[
        {
            "category":"Manufacturing",
            "subcategory":"Tools & Machinery",
            "type":"Manufacturing & Wholesale Goods"
        }
    ],
    "sg:phone":"+1 765 938 4480",
    "sg:postcode":"46173",
    "sg:province":"IN",
    "sg:tags":[
        "adhesive",
        "gluing",
        "equipment"
    ],
    "wof:name":"Rand Chemical Corp",
    "wof:placetype":"venue"
},
  "geometry": {"coordinates":[-85.444486,39.591219],"type":"Point"}
}