{
  "type": "Feature",
  "properties": {
    "iso:country":"US",
    "sg:address":"595 N Easton Dr",
    "sg:city":"Angola",
    "sg:classifiers":[
        {
            "category":"Building & Trades",
            "subcategory":"Construction",
            "type":"Services"
        }
    ],
    "sg:phone":"+1 260 665 6423",
    "sg:postcode":"46703",
    "sg:province":"IN",
    "sg:tags":[
        "product",
        "asphalt"
    ],
    "wof:name":"Asphalt Seal Coating & Patch",
    "wof:placetype":"venue"
},
  "geometry": {"coordinates":[-84.982991,41.650756],"type":"Point"}
}