{
  "type": "Feature",
  "properties": {
    "addr:full":"1017 W 6th St Bloomington IN 47404",
    "addr:housenumber":"1017",
    "addr:postcode":"47404",
    "addr:street":"W 6Th St",
    "iso:country":"US",
    "sg:address":"1017 W 6th St",
    "sg:city":"Bloomington",
    "sg:classifiers":[
        {
            "category":"Building & Trades",
            "subcategory":"Construction",
            "type":"Services"
        }
    ],
    "sg:phone":"+1 812 332 5787",
    "sg:postcode":"47404",
    "sg:province":"IN",
    "sg:tags":[
        "painter"
    ],
    "wof:name":"Fish Painting & Maintenance",
    "wof:placetype":"venue"
},
  "geometry": {"coordinates":[-86.54668599999999,39.167558],"type":"Point"}
}