{
  "type": "Feature",
  "properties": {
    "iso:country":"US",
    "sg:address":"916 S Anthony Blvd",
    "sg:city":"Fort Wayne",
    "sg:classifiers":[
        {
            "category":"Autos & Motor Vehicles",
            "subcategory":"Automobile Sales",
            "type":"Retail Goods"
        }
    ],
    "sg:phone":"+1 260 426 2278",
    "sg:postcode":"46803",
    "sg:province":"IN",
    "sg:tags":[
        "car",
        "dealer"
    ],
    "wof:name":"Premier Acceptance Corp",
    "wof:placetype":"venue"
},
  "geometry": {"coordinates":[-85.114722,41.079277],"type":"Point"}
}