{
  "type": "Feature",
  "properties": {
    "iso:country":"US",
    "sg:address":"3101 N Benton Rd",
    "sg:city":"Muncie",
    "sg:classifiers":[
        {
            "category":"Organizations",
            "subcategory":"Religious Organization",
            "type":"Services"
        }
    ],
    "sg:phone":"+1 765 759 8586",
    "sg:postcode":"47304",
    "sg:province":"IN",
    "wof:name":"Rev J Mark Dill",
    "wof:placetype":"venue"
},
  "geometry": {"coordinates":[-85.452267,40.217767],"type":"Point"}
}