{
  "type": "Feature",
  "properties": {
    "iso:country":"US",
    "sg:address":"3601 W Laytons Dr",
    "sg:city":"Westport",
    "sg:classifiers":[
        {
            "category":"Building & Trades",
            "subcategory":"Construction",
            "type":"Services"
        }
    ],
    "sg:phone":"+1 812 591 2826",
    "sg:postcode":"47283",
    "sg:province":"IN",
    "sg:tags":[
        "house"
    ],
    "wof:name":"Kearneys Construction",
    "wof:placetype":"venue"
},
  "geometry": {"coordinates":[-85.546959,39.168559],"type":"Point"}
}