{
  "type": "Feature",
  "properties": {
    "iso:country":"US",
    "sg:address":"821 Brookshire Dr",
    "sg:city":"Evansville",
    "sg:classifiers":[
        {
            "category":"Professional",
            "subcategory":"Art Services",
            "type":"Services"
        }
    ],
    "sg:phone":"+1 812 475 8688",
    "sg:postcode":"47715",
    "sg:province":"IN",
    "sg:tags":[
        "commercial",
        "design"
    ],
    "wof:name":"Worthington Hill Design",
    "wof:placetype":"venue"
},
  "geometry": {"coordinates":[-87.457194,37.965858],"type":"Point"}
}