{
  "type": "Feature",
  "properties": {
    "iso:country":"US",
    "sg:address":"274 Wyondotte Ct",
    "sg:city":"Noblesville",
    "sg:classifiers":[
        {
            "category":"Organizations",
            "subcategory":"Religious Organization",
            "type":"Services"
        }
    ],
    "sg:phone":"+1 317 844 3689",
    "sg:postcode":"46060",
    "sg:province":"IN",
    "wof:name":"Bethany Chapel Inc",
    "wof:placetype":"venue"
},
  "geometry": {"coordinates":[-85.987893,40.022064],"type":"Point"}
}