{
  "type": "Feature",
  "properties": {
    "addr:full":"496 W Eads Pkwy Lawrenceburg IN 47025",
    "addr:housenumber":"496",
    "addr:postcode":"47025",
    "addr:street":"W Eads Pkwy",
    "iso:country":"US",
    "sg:address":"496 W Eads Pkwy",
    "sg:city":"Lawrenceburg",
    "sg:classifiers":[
        {
            "category":"Retail",
            "subcategory":"Car Wash",
            "type":"Services"
        }
    ],
    "sg:phone":"+1 812 537 1913",
    "sg:postcode":"47025",
    "sg:province":"IN",
    "sg:tags":[
        "polishing",
        "washing"
    ],
    "wof:name":"Classic Car Wash",
    "wof:placetype":"venue"
},
  "geometry": {"coordinates":[-84.86114499999999,39.095323],"type":"Point"}
}