{
  "type": "Feature",
  "properties": {
    "iso:country":"US",
    "sg:address":"9878 N Baldwin St",
    "sg:city":"Rosedale",
    "sg:classifiers":[
        {
            "category":"Building & Trades",
            "subcategory":"Electrical",
            "type":"Services"
        }
    ],
    "sg:phone":"+1 812 877 9077",
    "sg:postcode":"47874",
    "sg:province":"IN",
    "sg:tags":[
        "electric",
        "contractor"
    ],
    "wof:name":"C D Electric Inc",
    "wof:placetype":"venue"
},
  "geometry": {"coordinates":[-87.243573,39.582656],"type":"Point"}
}