{
  "type": "Feature",
  "properties": {
    "addr:full":"4864 Tingler Rd W Richmond IN 47374",
    "addr:housenumber":"4864",
    "addr:postcode":"47374",
    "addr:street":"Tingler Rd W",
    "iso:country":"US",
    "sg:address":"4864 Tingler Rd W",
    "sg:city":"Richmond",
    "sg:classifiers":[
        {
            "category":"Real Estate",
            "subcategory":"Real Estate Operator",
            "type":"Services"
        }
    ],
    "sg:phone":"+1 765 962 9390",
    "sg:postcode":"47374",
    "sg:province":"IN",
    "sg:tags":[
        "farm",
        "corn",
        "property",
        "soybean",
        "lessor"
    ],
    "wof:name":"Charlton Onnie",
    "wof:placetype":"venue"
},
  "geometry": {"coordinates":[-84.970507,39.889143],"type":"Point"}
}