{
  "type": "Feature",
  "properties": {
    "iso:country":"US",
    "sg:address":"444 Pine Lake Ave",
    "sg:city":"Laporte",
    "sg:classifiers":[
        {
            "category":"Personal",
            "subcategory":"Beauty Salon",
            "type":"Services"
        }
    ],
    "sg:phone":"+1 219 326 6857",
    "sg:postcode":"46350",
    "sg:province":"IN",
    "wof:name":"Santa Fe Beauty Salon",
    "wof:placetype":"venue"
},
  "geometry": {"coordinates":[-86.738112,41.622317],"type":"Point"}
}