{
  "type": "Feature",
  "properties": {
    "iso:country":"US",
    "sg:address":"601 E 9th St",
    "sg:city":"Auburn",
    "sg:classifiers":[
        {
            "category":"Personal",
            "subcategory":"Beauty Salon",
            "type":"Services"
        }
    ],
    "sg:phone":"+1 260 925 9590",
    "sg:postcode":"46706",
    "sg:province":"IN",
    "wof:name":"Shear Expressions",
    "wof:placetype":"venue"
},
  "geometry": {"coordinates":[-85.048655,41.365953],"type":"Point"}
}