{
  "type": "Feature",
  "properties": {
    "iso:country":"US",
    "sg:address":"2119 Cozy Ct",
    "sg:city":"Fort Wayne",
    "sg:classifiers":[
        {
            "category":"Building & Trades",
            "subcategory":"Landscaping Services",
            "type":"Services"
        }
    ],
    "sg:phone":"+1 260 312 4933",
    "sg:postcode":"46802",
    "sg:province":"IN",
    "sg:tags":[
        "tree"
    ],
    "wof:name":"B J's Hawk Tree Svc",
    "wof:placetype":"venue"
},
  "geometry": {"coordinates":[-85.16605,41.065772],"type":"Point"}
}