{
  "type": "Feature",
  "properties": {
    "iso:country":"US",
    "sg:address":"26106 Co Rd 54",
    "sg:city":"Nappanee",
    "sg:classifiers":[
        {
            "category":"Organizations",
            "subcategory":"Religious Organization",
            "type":"Services"
        }
    ],
    "sg:phone":"+1 574 773 3570",
    "sg:postcode":"46550",
    "sg:province":"IN",
    "sg:tags":[
        "church"
    ],
    "wof:name":"Bethel Conservative Church",
    "wof:placetype":"venue"
},
  "geometry": {"coordinates":[-85.964401,41.449989],"type":"Point"}
}