{
  "type": "Feature",
  "properties": {
    "iso:country":"US",
    "sg:address":"1503 Hurd St",
    "sg:city":"Fort Wayne",
    "sg:classifiers":[
        {
            "category":"Autos & Motor Vehicles",
            "subcategory":"Automobile Sales",
            "type":"Retail Goods"
        }
    ],
    "sg:phone":"+1 260 744 7209",
    "sg:postcode":"46803",
    "sg:province":"IN",
    "sg:tags":[
        "car",
        "dealer"
    ],
    "wof:name":"Hagler Auto Sales",
    "wof:placetype":"venue"
},
  "geometry": {"coordinates":[-85.116466,41.064127],"type":"Point"}
}