{
  "type": "Feature",
  "properties": {
    "iso:country":"US",
    "sg:address":"1427 Cedar St",
    "sg:city":"Clarksville",
    "sg:classifiers":[
        {
            "category":"Home & Garden",
            "subcategory":"Building Materials",
            "type":"Retail Goods"
        }
    ],
    "sg:phone":"+1 812 284 4300",
    "sg:postcode":"47129",
    "sg:province":"IN",
    "sg:tags":[
        "glass",
        "window",
        "plate"
    ],
    "wof:name":"Safelite Auto Glass",
    "wof:placetype":"venue"
},
  "geometry": {"coordinates":[-85.759882,38.322559],"type":"Point"}
}