{
  "type": "Feature",
  "properties": {
    "iso:country":"US",
    "sg:address":"5451 US Hwy 50",
    "sg:city":"Holton",
    "sg:classifiers":[
        {
            "category":"Manufacturing",
            "subcategory":"Lumber",
            "type":"Manufacturing & Wholesale Goods"
        }
    ],
    "sg:phone":"+1 812 689 6201",
    "sg:postcode":"47023",
    "sg:province":"IN",
    "sg:tags":[
        "sawmill"
    ],
    "wof:name":"Beach Lumber Co",
    "wof:placetype":"venue"
},
  "geometry": {"coordinates":[-85.357265,39.0749],"type":"Point"}
}