{
  "type": "Feature",
  "properties": {
    "iso:country":"US",
    "sg:address":"2200 S US Hwy 35",
    "sg:city":"Knox",
    "sg:classifiers":[
        {
            "category":"Wholesale",
            "subcategory":"Tobacco Products",
            "type":"Manufacturing & Wholesale Goods"
        }
    ],
    "sg:phone":"+1 574 772 7721",
    "sg:postcode":"46534",
    "sg:province":"IN",
    "sg:tags":[
        "cigarette",
        "cigar",
        "dealer"
    ],
    "wof:name":"Smoke Shop",
    "wof:placetype":"venue"
},
  "geometry": {"coordinates":[-86.620581,41.270786],"type":"Point"}
}