{
  "type": "Feature",
  "properties": {
    "iso:country":"US",
    "sg:address":"927 S 9th St",
    "sg:city":"Richmond",
    "sg:classifiers":[
        {
            "category":"Shopping",
            "subcategory":"Computers & Home Electronics",
            "type":"Retail Goods"
        }
    ],
    "sg:phone":"+1 765 966 5550",
    "sg:postcode":"47374",
    "sg:province":"IN",
    "sg:tags":[
        "equipment",
        "dealer"
    ],
    "wof:name":"USA Computers",
    "wof:placetype":"venue"
},
  "geometry": {"coordinates":[-84.889915,39.81665],"type":"Point"}
}