{
  "type": "Feature",
  "properties": {
    "iso:country":"US",
    "sg:address":"4179 N Rd 500 W",
    "sg:city":"Bargersville",
    "sg:classifiers":[
        {
            "category":"Shopping",
            "subcategory":"Computers & Home Electronics",
            "type":"Retail Goods"
        }
    ],
    "sg:phone":"+1 317 422 1668",
    "sg:postcode":"46106",
    "sg:province":"IN",
    "sg:tags":[
        "equipment",
        "electronic",
        "supply"
    ],
    "wof:name":"Kem-Tron Inc",
    "wof:placetype":"venue"
},
  "geometry": {"coordinates":[-86.1965,39.534479],"type":"Point"}
}