{
  "type": "Feature",
  "properties": {
    "addr:full":"116 W 6th St Auburn IN 46706",
    "addr:housenumber":"116",
    "addr:postcode":"46706",
    "addr:street":"W 6Th St",
    "iso:country":"US",
    "sg:address":"116 W 6th St",
    "sg:city":"Auburn",
    "sg:classifiers":[
        {
            "category":"Professional",
            "subcategory":"Accounting & Tax Preparation",
            "type":"Services"
        }
    ],
    "sg:phone":"+1 260 925 1619",
    "sg:postcode":"46706",
    "sg:province":"IN",
    "sg:tags":[
        "accountant"
    ],
    "wof:name":"Seigel Group",
    "wof:placetype":"venue"
},
  "geometry": {"coordinates":[-85.056034,41.367536],"type":"Point"}
}