{
  "type": "Feature",
  "properties": {
    "iso:country":"US",
    "sg:address":"8799 Washington Blvd E Dr",
    "sg:city":"Indianapolis",
    "sg:classifiers":[
        {
            "category":"Health Services",
            "subcategory":"Doctor",
            "type":"Services"
        }
    ],
    "sg:phone":"+1 317 846 1896",
    "sg:postcode":"46240",
    "sg:province":"IN",
    "sg:tags":[
        "pediatrician"
    ],
    "wof:name":"Philip Hedrick MD",
    "wof:placetype":"venue"
},
  "geometry": {"coordinates":[-86.153069,39.913365],"type":"Point"}
}