{
  "type": "Feature",
  "properties": {
    "iso:country":"US",
    "sg:address":"622 S Cardinal Ln",
    "sg:city":"Scottsburg",
    "sg:classifiers":[
        {
            "category":"Manufacturing",
            "subcategory":"Tools & Machinery",
            "type":"Manufacturing & Wholesale Goods"
        }
    ],
    "sg:phone":"+1 812 752 5760",
    "sg:postcode":"47170",
    "sg:province":"IN",
    "sg:tags":[
        "industrial",
        "mfg"
    ],
    "wof:name":"Comer Machine Shop",
    "wof:placetype":"venue"
},
  "geometry": {"coordinates":[-85.822599,38.68439],"type":"Point"}
}