{
  "type": "Feature",
  "properties": {
    "iso:country":"US",
    "sg:address":"3110 S Lafountain St",
    "sg:city":"Kokomo",
    "sg:classifiers":[
        {
            "category":"Shopping",
            "type":"Retail Goods"
        }
    ],
    "sg:phone":"+1 765 453 0200",
    "sg:postcode":"46902",
    "sg:province":"IN",
    "sg:tags":[
        "hearing",
        "equipment",
        "supply",
        "impaired"
    ],
    "wof:name":"Hearing Center Inc",
    "wof:placetype":"venue"
},
  "geometry": {"coordinates":[-86.127072,40.451952],"type":"Point"}
}