{
  "type": "Feature",
  "properties": {
    "iso:country":"US",
    "sg:address":"401 Pennsylvania Pkwy",
    "sg:city":"Indianapolis",
    "sg:classifiers":[
        {
            "category":"Banks & Credit Unions",
            "subcategory":"Bank",
            "type":"Services"
        }
    ],
    "sg:phone":"+1 317 383 2328",
    "sg:postcode":"46280",
    "sg:province":"IN",
    "wof:name":"Fifth Third Bank",
    "wof:placetype":"venue"
},
  "geometry": {"coordinates":[-86.14970599999999,39.932672],"type":"Point"}
}