{
  "type": "Feature",
  "properties": {
    "addr:full":"209 N Franklin Rd Greenwood IN 46143",
    "addr:housenumber":"209",
    "addr:postcode":"46143",
    "addr:street":"N Franklin Rd",
    "iso:country":"US",
    "sg:address":"209 N Franklin Rd",
    "sg:city":"Greenwood",
    "sg:classifiers":[
        {
            "category":"Home & Garden",
            "subcategory":"Garden Supply",
            "type":"Retail Goods"
        }
    ],
    "sg:phone":"+1 317 508 1497",
    "sg:postcode":"46143",
    "sg:province":"IN",
    "sg:tags":[
        "sprinkler"
    ],
    "wof:name":"Warweg & Co",
    "wof:placetype":"venue"
},
  "geometry": {"coordinates":[-86.018885,39.61231],"type":"Point"}
}