{
  "type": "Feature",
  "properties": {
    "iso:country":"US",
    "sg:address":"620 W Fisher St",
    "sg:city":"Monticello",
    "sg:classifiers":[
        {
            "category":"Manufacturing",
            "subcategory":"Glass & Minerals",
            "type":"Manufacturing & Wholesale Goods"
        }
    ],
    "sg:phone":"+1 574 583 7101",
    "sg:postcode":"47960",
    "sg:province":"IN",
    "sg:tags":[
        "concrete",
        "brick",
        "prod",
        "block"
    ],
    "wof:name":"Brim Concrete",
    "wof:placetype":"venue"
},
  "geometry": {"coordinates":[-86.771605,40.756018],"type":"Point"}
}