{
  "type": "Feature",
  "properties": {
    "addr:full":"1212 W Jefferson St Kokomo IN 46901",
    "addr:housenumber":"1212",
    "addr:postcode":"46901",
    "addr:street":"W Jefferson St",
    "iso:country":"US",
    "sg:address":"1212 W Jefferson St",
    "sg:city":"Kokomo",
    "sg:classifiers":[
        {
            "category":"Organizations",
            "subcategory":"Religious Organization",
            "type":"Services"
        }
    ],
    "sg:phone":"+1 765 868 0537",
    "sg:postcode":"46901",
    "sg:province":"IN",
    "wof:name":"Albert Neher Rev",
    "wof:placetype":"venue"
},
  "geometry": {"coordinates":[-86.145612,40.490863],"type":"Point"}
}