{
  "type": "Feature",
  "properties": {
    "iso:country":"US",
    "sg:address":"8914 Bay Breeze Ln",
    "sg:city":"Indianapolis",
    "sg:classifiers":[
        {
            "category":"Education",
            "subcategory":"Special Training",
            "type":"Public Place"
        }
    ],
    "sg:phone":"+1 317 823 7239",
    "sg:postcode":"46236",
    "sg:province":"IN",
    "sg:tags":[
        "school",
        "instruction",
        "art"
    ],
    "wof:name":"Kid's Kaleidoscope Of Art",
    "wof:placetype":"venue"
},
  "geometry": {"coordinates":[-85.96387199999999,39.917577],"type":"Point"}
}