{
  "type": "Feature",
  "properties": {
    "iso:country":"US",
    "sg:address":"7702 Woodland Dr",
    "sg:city":"Indianapolis",
    "sg:classifiers":[
        {
            "category":"Shopping",
            "subcategory":"Computers & Home Electronics",
            "type":"Retail Goods"
        }
    ],
    "sg:phone":"+1 317 872 5220",
    "sg:postcode":"46278",
    "sg:province":"IN",
    "sg:tags":[
        "software"
    ],
    "wof:name":"Softchoice Corp",
    "wof:placetype":"venue"
},
  "geometry": {"coordinates":[-86.265607,39.890649],"type":"Point"}
}