{
  "type": "Feature",
  "properties": {
    "addr:full":"23013 Park Ln Woodburn IN 46797",
    "addr:housenumber":"23013",
    "addr:postcode":"46797",
    "addr:street":"Park Ln",
    "iso:country":"US",
    "sg:address":"23013 Park Ln",
    "sg:city":"Woodburn",
    "sg:classifiers":[
        {
            "category":"Retail",
            "subcategory":"Repair Shop",
            "type":"Services"
        }
    ],
    "sg:phone":"+1 260 632 5014",
    "sg:postcode":"46797",
    "sg:province":"IN",
    "sg:tags":[
        "appliance"
    ],
    "wof:name":"Allen County Appliance Repair",
    "wof:placetype":"venue"
},
  "geometry": {"coordinates":[-84.846014,41.127393],"type":"Point"}
}