{
  "type": "Feature",
  "properties": {
    "iso:country":"US",
    "sg:address":"102 W Lincoln Ave",
    "sg:city":"Goshen",
    "sg:classifiers":[
        {
            "category":"Professional",
            "subcategory":"Business Services",
            "type":"Services"
        }
    ],
    "sg:phone":"+1 574 533 4520",
    "sg:postcode":"46526",
    "sg:province":"IN",
    "sg:tags":[
        "appraiser"
    ],
    "wof:name":"Appraisals Solutions",
    "wof:placetype":"venue"
},
  "geometry": {"coordinates":[-85.835305,41.586356],"type":"Point"}
}