{
  "type": "Feature",
  "properties": {
    "iso:country":"US",
    "sg:address":"595 E 350 N",
    "sg:city":"Warsaw",
    "sg:classifiers":[
        {
            "category":"Organizations",
            "subcategory":"Religious Organization",
            "type":"Services"
        }
    ],
    "sg:phone":"+1 574 268 2858",
    "sg:postcode":"46582",
    "sg:province":"IN",
    "wof:name":"Living Hope Ministries",
    "wof:placetype":"venue"
},
  "geometry": {"coordinates":[-85.83156,41.284942],"type":"Point"}
}