{
  "type": "Feature",
  "properties": {
    "iso:country":"US",
    "sg:address":"11991 E Davis Ave",
    "sg:city":"Brazil",
    "sg:classifiers":[
        {
            "category":"Organizations",
            "subcategory":"Religious Organization",
            "type":"Services"
        }
    ],
    "sg:phone":"+1 812 466 6674",
    "sg:postcode":"47834",
    "sg:province":"IN",
    "wof:name":"Harvest Prayer Ministries",
    "wof:placetype":"venue"
},
  "geometry": {"coordinates":[-87.231212,39.534856],"type":"Point"}
}