{
  "type": "Feature",
  "properties": {
    "addr:full":"5729 E 86th St Indianapolis IN 46250",
    "addr:housenumber":"5729",
    "addr:postcode":"46250",
    "addr:street":"E 86Th St",
    "iso:country":"US",
    "sg:address":"5729 E 86th St",
    "sg:city":"Indianapolis",
    "sg:classifiers":[
        {
            "category":"Shopping",
            "subcategory":"Discount & Variety Stores",
            "type":"Retail Goods"
        }
    ],
    "sg:postcode":"46250",
    "sg:province":"IN",
    "sg:tags":[
        "outlet"
    ],
    "wof:name":"Halloween USA",
    "wof:placetype":"venue"
},
  "geometry": {"coordinates":[-86.06999500000001,39.911014],"type":"Point"}
}