{
  "type": "Feature",
  "properties": {
    "iso:country":"US",
    "sg:address":"510 W Church St",
    "sg:city":"Hebron",
    "sg:classifiers":[
        {
            "category":"Government",
            "subcategory":"Office",
            "type":"Public Place"
        }
    ],
    "sg:phone":"+1 219 996 7121",
    "sg:postcode":"46341",
    "sg:province":"IN",
    "sg:tags":[
        "village"
    ],
    "wof:name":"Boone Township Trustee",
    "wof:placetype":"venue"
},
  "geometry": {"coordinates":[-87.206688,41.317572],"type":"Point"}
}