{
  "type": "Feature",
  "properties": {
    "iso:country":"US",
    "sg:address":"7695 Crosspoint Cmn",
    "sg:city":"Fishers",
    "sg:classifiers":[
        {
            "category":"Restaurant",
            "type":"Food & Drink"
        }
    ],
    "sg:phone":"+1 317 577 4422",
    "sg:postcode":"46038",
    "sg:province":"IN",
    "wof:name":"Schlotzsky's Deli",
    "wof:placetype":"venue"
},
  "geometry": {"coordinates":[-86.033997,39.928501],"type":"Point"}
}