{
  "type": "Feature",
  "properties": {
    "iso:country":"US",
    "sg:address":"5300 Decatur Rd",
    "sg:city":"Fort Wayne",
    "sg:classifiers":[
        {
            "category":"Shopping",
            "subcategory":"Pharmacy",
            "type":"Retail Goods"
        }
    ],
    "sg:phone":"+1 260 458 0840",
    "sg:postcode":"46806",
    "sg:province":"IN",
    "wof:name":"Keltsch Pharmacy",
    "wof:placetype":"venue"
},
  "geometry": {"coordinates":[-85.128376,41.034208],"type":"Point"}
}