{
  "type": "Feature",
  "properties": {
    "addr:full":"10466 N State Rd 39 Laporte IN 46350",
    "addr:housenumber":"10466;39",
    "addr:postcode":"46350",
    "addr:street":"N State Rd",
    "iso:country":"US",
    "sg:address":"10466 N State Rd 39",
    "sg:city":"Laporte",
    "sg:classifiers":[
        {
            "category":"Wholesale",
            "subcategory":"Toys & Hobbies",
            "type":"Manufacturing & Wholesale Goods"
        },
        {
            "category":"Shopping",
            "subcategory":"Gifts & Souvenirs",
            "type":"Retail Goods"
        }
    ],
    "sg:phone":"+1 219 362 7029",
    "sg:postcode":"46350",
    "sg:province":"IN",
    "sg:tags":[
        "firework",
        "novelty"
    ],
    "wof:name":"Novak Novelty & Fireworks",
    "wof:placetype":"venue"
},
  "geometry": {"coordinates":[-86.722809,41.758745],"type":"Point"}
}