{
  "type": "Feature",
  "properties": {
    "iso:country":"US",
    "sg:address":"445 S Sheridan St",
    "sg:city":"South Bend",
    "sg:classifiers":[
        {
            "category":"Professional",
            "type":"Services"
        }
    ],
    "sg:phone":"+1 574 288 5009",
    "sg:postcode":"46619",
    "sg:province":"IN",
    "sg:tags":[
        "establishment"
    ],
    "wof:name":"Metech International Inc",
    "wof:placetype":"venue"
},
  "geometry": {"coordinates":[-86.30337,41.670412],"type":"Point"}
}