{
  "type": "Feature",
  "properties": {
    "addr:full":"12440 W State Rd 28 Gaston IN 47342",
    "addr:housenumber":"12440;28",
    "addr:postcode":"47342",
    "addr:street":"W State Rd",
    "iso:country":"US",
    "sg:address":"12440 W State Rd 28",
    "sg:city":"Gaston",
    "sg:classifiers":[
        {
            "category":"Autos & Motor Vehicles",
            "subcategory":"Automobile Sales",
            "type":"Retail Goods"
        }
    ],
    "sg:phone":"+1 765 358 3556",
    "sg:postcode":"47342",
    "sg:province":"IN",
    "sg:tags":[
        "used"
    ],
    "wof:name":"Gene Christie Auto Sales",
    "wof:placetype":"venue"
},
  "geometry": {"coordinates":[-85.53367900000001,40.276891],"type":"Point"}
}