{
  "type": "Feature",
  "properties": {
    "addr:full":"210 Cypress Dr Schererville IN 46375",
    "addr:housenumber":"210",
    "addr:postcode":"46375",
    "addr:street":"Cypress Dr",
    "iso:country":"US",
    "sg:address":"210 Cypress Dr",
    "sg:city":"Schererville",
    "sg:classifiers":[
        {
            "category":"Building & Trades",
            "subcategory":"Plumbing",
            "type":"Services"
        }
    ],
    "sg:phone":"+1 219 836 0107",
    "sg:postcode":"46375",
    "sg:province":"IN",
    "sg:tags":[
        "plumbing",
        "contractor"
    ],
    "wof:name":"A-1 Economy S & D",
    "wof:placetype":"venue"
},
  "geometry": {"coordinates":[-87.480935,41.520034],"type":"Point"}
}