{
  "type": "Feature",
  "properties": {
    "iso:country":"US",
    "sg:address":"2025 E 10th St",
    "sg:city":"Indianapolis",
    "sg:classifiers":[
        {
            "category":"Retail",
            "subcategory":"Self-service Laundry",
            "type":"Services"
        }
    ],
    "sg:phone":"+1 317 638 0400",
    "sg:postcode":"46201",
    "sg:province":"IN",
    "sg:tags":[
        "garment",
        "coin",
        "agent",
        "who"
    ],
    "wof:name":"Peirsons Laundrymat",
    "wof:placetype":"venue"
},
  "geometry": {"coordinates":[-86.125401,39.781231],"type":"Point"}
}