{
  "type": "Feature",
  "properties": {
    "iso:country":"US",
    "sg:address":"6610 Little Leaf Pl",
    "sg:city":"Indianapolis",
    "sg:classifiers":[
        {
            "category":"Building & Trades",
            "subcategory":"Landscaping Services",
            "type":"Services"
        }
    ],
    "sg:phone":"+1 317 538 1262",
    "sg:postcode":"46203",
    "sg:province":"IN",
    "sg:tags":[
        "landscape",
        "contractor"
    ],
    "wof:name":"Zimmerman Landscaping",
    "wof:placetype":"venue"
},
  "geometry": {"coordinates":[-86.051725,39.705442],"type":"Point"}
}