{
  "type": "Feature",
  "properties": {
    "addr:full":"2111 W Frederick Dr Marion IN 46952",
    "addr:housenumber":"2111",
    "addr:postcode":"46952",
    "addr:street":"W Frederick Dr",
    "iso:country":"US",
    "sg:address":"2111 W Frederick Dr",
    "sg:city":"Marion",
    "sg:classifiers":[
        {
            "category":"Real Estate",
            "subcategory":"Real Estate Operator",
            "type":"Services"
        }
    ],
    "sg:phone":"+1 765 662 3333",
    "sg:postcode":"46952",
    "sg:province":"IN",
    "sg:tags":[
        "apartment"
    ],
    "wof:name":"Somerset Apartments",
    "wof:placetype":"venue"
},
  "geometry": {"coordinates":[-85.690641,40.572474],"type":"Point"}
}