{
  "type": "Feature",
  "properties": {
    "iso:country":"US",
    "sg:address":"4300 E Stop 11 Rd",
    "sg:city":"Indianapolis",
    "sg:classifiers":[
        {
            "category":"Government",
            "subcategory":"Fire Station",
            "type":"Public Place"
        }
    ],
    "sg:phone":"+1 317 889 5262",
    "sg:postcode":"46237",
    "sg:province":"IN",
    "sg:tags":[
        "department"
    ],
    "wof:name":"Perry Township Fire Station",
    "wof:placetype":"venue"
},
  "geometry": {"coordinates":[-86.097331,39.650769],"type":"Point"}
}