{
  "type": "Feature",
  "properties": {
    "iso:country":"US",
    "sg:address":"727 Dellinger Dr",
    "sg:city":"Jeffersonville",
    "sg:classifiers":[
        {
            "category":"Building & Trades",
            "subcategory":"Construction",
            "type":"Services"
        }
    ],
    "sg:phone":"+1 812 282 8314",
    "sg:postcode":"47130",
    "sg:province":"IN",
    "wof:name":"Christiansen Robynne",
    "wof:placetype":"venue"
},
  "geometry": {"coordinates":[-85.687862,38.309111],"type":"Point"}
}