{
  "type": "Feature",
  "properties": {
    "addr:full":"1941 Newton Ave Evansville IN 47715",
    "addr:housenumber":"1941",
    "addr:postcode":"47715",
    "addr:street":"Newton Ave",
    "iso:country":"US",
    "sg:address":"1941 Newton Ave",
    "sg:city":"Evansville",
    "sg:classifiers":[
        {
            "category":"Communications",
            "subcategory":"Film & Video Production",
            "type":"Services"
        }
    ],
    "sg:phone":"+1 812 476 7254",
    "sg:postcode":"47715",
    "sg:province":"IN",
    "sg:tags":[
        "motion"
    ],
    "wof:name":"Solar Flair Productions",
    "wof:placetype":"venue"
},
  "geometry": {"coordinates":[-87.497505,37.994911],"type":"Point"}
}