{
  "type": "Feature",
  "properties": {
    "addr:full":"6955 State Rd 5 Topeka IN 46571",
    "addr:housenumber":"6955",
    "addr:postcode":"46571",
    "addr:street":"State Rd 5",
    "iso:country":"US",
    "sg:address":"6955 State Rd 5",
    "sg:city":"Topeka",
    "sg:classifiers":[
        {
            "category":"Food & Beverages",
            "subcategory":"Groceries & Convenience Stores",
            "type":"Retail Goods"
        }
    ],
    "sg:phone":"+1 260 593 2161",
    "sg:postcode":"46571",
    "sg:province":"IN",
    "wof:name":"Westedge Express",
    "wof:placetype":"venue"
},
  "geometry": {"coordinates":[-85.57788600000001,41.539357],"type":"Point"}
}