{
  "type": "Feature",
  "properties": {
    "addr:full":"7040 N Pennsylvania St Indianapolis IN 46220",
    "addr:housenumber":"7040",
    "addr:postcode":"46220",
    "addr:street":"N Pennsylvania St",
    "iso:country":"US",
    "sg:address":"7040 N Pennsylvania St",
    "sg:city":"Indianapolis",
    "sg:classifiers":[
        {
            "category":"Real Estate",
            "subcategory":"Real Estate Operator",
            "type":"Services"
        }
    ],
    "sg:phone":"+1 317 251 5808",
    "sg:postcode":"46220",
    "sg:province":"IN",
    "sg:tags":[
        "property",
        "lessor"
    ],
    "wof:name":"Emily Sturman",
    "wof:placetype":"venue"
},
  "geometry": {"coordinates":[-86.155522,39.880421],"type":"Point"}
}