{
  "type": "Feature",
  "properties": {
    "iso:country":"US",
    "sg:address":"97 S Co Rd 400 E",
    "sg:city":"Avon",
    "sg:classifiers":[
        {
            "category":"Real Estate",
            "subcategory":"Architect",
            "type":"Services"
        }
    ],
    "sg:phone":"+1 317 272 7800",
    "sg:postcode":"46123",
    "sg:province":"IN",
    "sg:website":"www.sebreearchitects.com",
    "wof:name":"Sebree & Assoc Architects",
    "wof:placetype":"venue"
},
  "geometry": {"coordinates":[-86.457195,39.760628],"type":"Point"}
}