{
  "type": "Feature",
  "properties": {
    "iso:country":"US",
    "sg:address":"2752 Sangster Ave",
    "sg:city":"Indianapolis",
    "sg:classifiers":[
        {
            "category":"Social Services",
            "subcategory":"Child Care",
            "type":"Services"
        }
    ],
    "sg:phone":"+1 317 925 0626",
    "sg:postcode":"46218",
    "sg:province":"IN",
    "sg:tags":[
        "day"
    ],
    "wof:name":"Pollards Daycare",
    "wof:placetype":"venue"
},
  "geometry": {"coordinates":[-86.128776,39.806095],"type":"Point"}
}