{
  "type": "Feature",
  "properties": {
    "iso:country":"US",
    "sg:address":"132 N Iowa St",
    "sg:city":"Chandler",
    "sg:classifiers":[
        {
            "category":"Government",
            "subcategory":"Fire Station",
            "type":"Public Place"
        }
    ],
    "sg:phone":"+1 812 925 6128",
    "sg:postcode":"47610",
    "sg:province":"IN",
    "sg:tags":[
        "department"
    ],
    "wof:name":"Chandler Fire Dept",
    "wof:placetype":"venue"
},
  "geometry": {"coordinates":[-87.372544,38.043483],"type":"Point"}
}