{
  "type": "Feature",
  "properties": {
    "addr:full":"5446 W 86th St Indianapolis IN 46268",
    "addr:housenumber":"5446",
    "addr:postcode":"46268",
    "addr:street":"W 86Th St",
    "iso:country":"US",
    "sg:address":"5446 W 86th St",
    "sg:city":"Indianapolis",
    "sg:classifiers":[
        {
            "category":"Manufacturing",
            "subcategory":"Rubber & Plastics",
            "type":"Manufacturing & Wholesale Goods"
        },
        {
            "category":"Shopping",
            "type":"Retail Goods"
        }
    ],
    "sg:phone":"+1 317 875 8952",
    "sg:postcode":"46268",
    "sg:province":"IN",
    "sg:tags":[
        "equipment",
        "clothing",
        "safety",
        "clothing-wholesale",
        "manufacturer"
    ],
    "wof:name":"Iron Age Safety Shoes",
    "wof:placetype":"venue"
},
  "geometry": {"coordinates":[-86.25663,39.9109],"type":"Point"}
}