{
  "type": "Feature",
  "properties": {
    "addr:full":"222 Southwood Dr Michigan City IN 46360",
    "addr:housenumber":"222",
    "addr:postcode":"46360",
    "addr:street":"Southwood Dr",
    "iso:country":"US",
    "sg:address":"222 Southwood Dr",
    "sg:city":"Michigan City",
    "sg:classifiers":[
        {
            "category":"Professional",
            "subcategory":"Secretarial Services",
            "type":"Services"
        }
    ],
    "sg:phone":"+1 219 872 2411",
    "sg:postcode":"46360",
    "sg:province":"IN",
    "sg:tags":[
        "reporting",
        "court"
    ],
    "wof:name":"R & J Enterprises",
    "wof:placetype":"venue"
},
  "geometry": {"coordinates":[-86.896979,41.689816],"type":"Point"}
}