{
  "type": "Feature",
  "properties": {
    "iso:country":"US",
    "sg:address":"215 S Broadway",
    "sg:city":"Peru",
    "sg:classifiers":[
        {
            "category":"Retail",
            "subcategory":"Self-service Laundry",
            "type":"Services"
        }
    ],
    "sg:phone":"+1 765 472 2311",
    "sg:postcode":"46970",
    "sg:province":"IN",
    "wof:name":"Gallahan KWIK Mart & Laundry",
    "wof:placetype":"venue"
},
  "geometry": {"coordinates":[-86.065922,40.74953],"type":"Point"}
}