{
  "type": "Feature",
  "properties": {
    "iso:country":"US",
    "sg:address":"9005 E 17th St",
    "sg:city":"Indianapolis",
    "sg:classifiers":[
        {
            "category":"Building & Trades",
            "subcategory":"Electrical",
            "type":"Services"
        }
    ],
    "sg:phone":"+1 317 897 1723",
    "sg:postcode":"46229",
    "sg:province":"IN",
    "sg:tags":[
        "equipment",
        "protection",
        "lightning"
    ],
    "wof:name":"B & D Magee's Inc",
    "wof:placetype":"venue"
},
  "geometry": {"coordinates":[-86.00497900000001,39.790904],"type":"Point"}
}