{
  "type": "Feature",
  "properties": {
    "iso:country":"US",
    "sg:address":"800 US Hwy 31 N",
    "sg:city":"Greenwood",
    "sg:classifiers":[
        {
            "category":"Autos & Motor Vehicles",
            "subcategory":"Fuel & Gas Station",
            "type":"Retail Goods"
        }
    ],
    "sg:phone":"+1 317 882 3030",
    "sg:postcode":"46142",
    "sg:province":"IN",
    "sg:tags":[
        "oil"
    ],
    "wof:name":"Shell Service Station",
    "wof:placetype":"venue"
},
  "geometry": {"coordinates":[-86.119639,39.62543],"type":"Point"}
}