{
  "type": "Feature",
  "properties": {
    "iso:country":"US",
    "sg:address":"12788 E 191st St",
    "sg:city":"Noblesville",
    "sg:classifiers":[
        {
            "category":"Home & Garden",
            "subcategory":"Garden Supply",
            "type":"Retail Goods"
        }
    ],
    "sg:phone":"+1 317 770 7678",
    "sg:postcode":"46060",
    "sg:province":"IN",
    "sg:tags":[
        "nurseryman"
    ],
    "wof:name":"Miller's Manor Gardens",
    "wof:placetype":"venue"
},
  "geometry": {"coordinates":[-85.94689099999999,40.066234],"type":"Point"}
}