{
  "type": "Feature",
  "properties": {
    "iso:country":"US",
    "sg:address":"11401 Anderson Rd",
    "sg:city":"Granger",
    "sg:classifiers":[
        {
            "category":"Organizations",
            "subcategory":"Religious Organization",
            "type":"Services"
        }
    ],
    "sg:phone":"+1 574 277 5313",
    "sg:postcode":"46530",
    "sg:province":"IN",
    "sg:tags":[
        "church"
    ],
    "wof:name":"Open Door Christian Fellows",
    "wof:placetype":"venue"
},
  "geometry": {"coordinates":[-86.088528,41.742712],"type":"Point"}
}