{
  "type": "Feature",
  "properties": {
    "addr:full":"1020 Reder Rd Griffith IN 46319",
    "addr:housenumber":"1020",
    "addr:postcode":"46319",
    "addr:street":"Reder Rd",
    "iso:country":"US",
    "sg:address":"1020 Reder Rd",
    "sg:city":"Griffith",
    "sg:classifiers":[
        {
            "category":"Retail",
            "subcategory":"Repair Shop",
            "type":"Services"
        }
    ],
    "sg:phone":"+1 219 922 4888",
    "sg:postcode":"46319",
    "sg:province":"IN",
    "sg:tags":[
        "commercial",
        "welding"
    ],
    "wof:name":"Weldco Inc",
    "wof:placetype":"venue"
},
  "geometry": {"coordinates":[-87.41740799999999,41.511727],"type":"Point"}
}