{
  "type": "Feature",
  "properties": {
    "addr:full":"1180 Clark Dr Greenwood IN 46143",
    "addr:housenumber":"1180",
    "addr:postcode":"46143",
    "addr:street":"Clark Dr",
    "iso:country":"US",
    "sg:address":"1180 Clark Dr",
    "sg:city":"Greenwood",
    "sg:classifiers":[
        {
            "category":"Retail",
            "subcategory":"Auto Repair",
            "type":"Services"
        }
    ],
    "sg:phone":"+1 317 859 8371",
    "sg:postcode":"46143",
    "sg:province":"IN",
    "sg:tags":[
        "automotive"
    ],
    "wof:name":"Rob Hook Automotive",
    "wof:placetype":"venue"
},
  "geometry": {"coordinates":[-86.136673,39.601145],"type":"Point"}
}