{
  "type": "Feature",
  "properties": {
    "iso:country":"US",
    "sg:address":"7914 Dunston Dr",
    "sg:city":"Indianapolis",
    "sg:classifiers":[
        {
            "category":"Building & Trades",
            "subcategory":"Construction",
            "type":"Services"
        }
    ],
    "sg:phone":"+1 317 352 1119",
    "sg:postcode":"46239",
    "sg:province":"IN",
    "sg:tags":[
        "painter"
    ],
    "wof:name":"Adams Apple Painting",
    "wof:placetype":"venue"
},
  "geometry": {"coordinates":[-86.027311,39.760781],"type":"Point"}
}