{
  "type": "Feature",
  "properties": {
    "iso:country":"US",
    "sg:address":"931 Ridge Rd",
    "sg:city":"Munster",
    "sg:classifiers":[
        {
            "category":"Health Services",
            "subcategory":"Health Practitioner",
            "type":"Services"
        }
    ],
    "sg:phone":"+1 219 836 2800",
    "sg:postcode":"46321",
    "sg:province":"IN",
    "sg:tags":[
        "therapy",
        "physical"
    ],
    "wof:name":"Premier Physical Therapy",
    "wof:placetype":"venue"
},
  "geometry": {"coordinates":[-87.50619500000001,41.561044],"type":"Point"}
}