{
  "type": "Feature",
  "properties": {
    "iso:country":"US",
    "sg:address":"934 S 27th St",
    "sg:city":"South Bend",
    "sg:classifiers":[
        {
            "category":"Building & Trades",
            "subcategory":"Cleaning & Sanitation",
            "type":"Services"
        }
    ],
    "sg:phone":"+1 574 289 6979",
    "sg:postcode":"46615",
    "sg:province":"IN",
    "sg:tags":[
        "window"
    ],
    "wof:name":"Mason's Window Cleaning Svc",
    "wof:placetype":"venue"
},
  "geometry": {"coordinates":[-86.208805,41.665472],"type":"Point"}
}