{
  "type": "Feature",
  "properties": {
    "iso:country":"US",
    "sg:address":"321 Mitchell Ave",
    "sg:city":"Batesville",
    "sg:classifiers":[
        {
            "category":"Health Services",
            "subcategory":"Doctor",
            "type":"Services"
        }
    ],
    "sg:phone":"+1 812 934 5653",
    "sg:postcode":"47006",
    "sg:province":"IN",
    "sg:tags":[
        "clinic"
    ],
    "wof:name":"Renal Treatment Ctr Inc",
    "wof:placetype":"venue"
},
  "geometry": {"coordinates":[-85.224714,39.304905],"type":"Point"}
}