{
  "type": "Feature",
  "properties": {
    "iso:country":"US",
    "sg:address":"5080 S Co Rd 125 W",
    "sg:city":"New Castle",
    "sg:classifiers":[
        {
            "category":"Wholesale",
            "subcategory":"Auto Parts",
            "type":"Manufacturing & Wholesale Goods"
        }
    ],
    "sg:phone":"+1 765 987 1236",
    "sg:postcode":"47362",
    "sg:province":"IN",
    "sg:tags":[
        "automobile",
        "rebuilt"
    ],
    "wof:name":"Hartley Truck Parts",
    "wof:placetype":"venue"
},
  "geometry": {"coordinates":[-85.41044100000001,39.859465],"type":"Point"}
}