{
  "type": "Feature",
  "properties": {
    "iso:country":"US",
    "sg:address":"615 Sunblest Blvd",
    "sg:city":"Fishers",
    "sg:classifiers":[
        {
            "category":"Professional",
            "type":"Services"
        }
    ],
    "sg:phone":"+1 317 594 0645",
    "sg:postcode":"46038",
    "sg:province":"IN",
    "wof:name":"Ronald Fleming",
    "wof:placetype":"venue"
},
  "geometry": {"coordinates":[-86.036482,39.962198],"type":"Point"}
}