{
  "type": "Feature",
  "properties": {
    "iso:country":"US",
    "sg:address":"4776 Co Rd 34",
    "sg:city":"Waterloo",
    "sg:phone":"+1 260 837 2103",
    "sg:postcode":"46793",
    "sg:province":"IN",
    "sg:tags":[
        "farm",
        "corn",
        "soybean"
    ],
    "wof:name":"Harold Stafford",
    "wof:placetype":"venue"
},
  "geometry": {"coordinates":[-84.96774600000001,41.405733],"type":"Point"}
}