{
  "type": "Feature",
  "properties": {
    "iso:country":"US",
    "sg:address":"100 S Washington St",
    "sg:city":"Marion",
    "sg:classifiers":[
        {
            "category":"Banks & Credit Unions",
            "subcategory":"Bank",
            "type":"Services"
        }
    ],
    "sg:phone":"+1 765 668 7575",
    "sg:postcode":"46952",
    "sg:province":"IN",
    "sg:website":"www.oldnational.com",
    "wof:name":"Old National Bank",
    "wof:placetype":"venue"
},
  "geometry": {"coordinates":[-85.65978,40.559748],"type":"Point"}
}