{
  "type": "Feature",
  "properties": {
    "iso:country":"US",
    "sg:address":"148 N Buckeye St",
    "sg:city":"Osgood",
    "sg:classifiers":[
        {
            "category":"Retail",
            "subcategory":"Repair Shop",
            "type":"Services"
        }
    ],
    "sg:phone":"+1 812 689 4536",
    "sg:postcode":"47037",
    "sg:province":"IN",
    "wof:name":"Turner Store",
    "wof:placetype":"venue"
},
  "geometry": {"coordinates":[-85.291426,39.129272],"type":"Point"}
}