{
  "type": "Feature",
  "properties": {
    "iso:country":"US",
    "sg:address":"802 Indiana Ave",
    "sg:city":"La Porte",
    "sg:classifiers":[
        {
            "category":"Organizations",
            "subcategory":"Religious Organization",
            "type":"Services"
        }
    ],
    "sg:phone":"+1 219 362 6419",
    "sg:postcode":"46350",
    "sg:province":"IN",
    "wof:name":"First Baptst Church of Laporte",
    "wof:placetype":"venue"
},
  "geometry": {"coordinates":[-86.72175900000001,41.609842],"type":"Point"}
}