{
  "type": "Feature",
  "properties": {
    "iso:country":"US",
    "sg:address":"851 S Range Line Rd",
    "sg:city":"Carmel",
    "sg:classifiers":[
        {
            "category":"Professional",
            "subcategory":"Lawyer & Legal Services",
            "type":"Services"
        }
    ],
    "sg:phone":"+1 317 788 6434",
    "sg:postcode":"46032",
    "sg:province":"IN",
    "sg:tags":[
        "attorney"
    ],
    "wof:name":"Accident Attorney At Law",
    "wof:placetype":"venue"
},
  "geometry": {"coordinates":[-86.126886,39.96736],"type":"Point"}
}