{
  "type": "Feature",
  "properties": {
    "iso:country":"US",
    "sg:address":"224 N Main St",
    "sg:city":"Camden",
    "sg:classifiers":[
        {
            "category":"Building & Trades",
            "subcategory":"Construction",
            "type":"Services"
        }
    ],
    "sg:phone":"+1 937 452 3271",
    "sg:postcode":"45311",
    "sg:province":"IN",
    "sg:tags":[
        "contractor"
    ],
    "wof:name":"Doran Roof Systems",
    "wof:placetype":"venue"
},
  "geometry": {"coordinates":[-84.64622199999999,39.632936],"type":"Point"}
}