{
  "type": "Feature",
  "properties": {
    "iso:country":"US",
    "sg:address":"420 N Main St",
    "sg:city":"Middlebury",
    "sg:classifiers":[
        {
            "category":"Manufacturing",
            "subcategory":"Motor Vehicles & Parts",
            "type":"Manufacturing & Wholesale Goods"
        }
    ],
    "sg:phone":"+1 574 825 5233",
    "sg:postcode":"46540",
    "sg:province":"IN",
    "sg:tags":[
        "trailer"
    ],
    "wof:name":"Woodies Custom Graphics",
    "wof:placetype":"venue"
},
  "geometry": {"coordinates":[-85.703057,41.681851],"type":"Point"}
}