{
  "type": "Feature",
  "properties": {
    "addr:full":"6319 S East St Indianapolis IN 46227",
    "addr:housenumber":"6319",
    "addr:postcode":"46227",
    "addr:street":"S East St",
    "iso:country":"US",
    "sg:address":"6319 S East St",
    "sg:city":"Indianapolis",
    "sg:classifiers":[
        {
            "category":"Professional",
            "subcategory":"Management & Consulting",
            "type":"Services"
        }
    ],
    "sg:phone":"+1 317 402 5167",
    "sg:postcode":"46227",
    "sg:province":"IN",
    "sg:tags":[
        "firm"
    ],
    "wof:name":"Eands Consulting and Mktg LLC",
    "wof:placetype":"venue"
},
  "geometry": {"coordinates":[-86.149169,39.671987],"type":"Point"}
}