{
  "type": "Feature",
  "properties": {
    "addr:full":"205 W Church St Alexandria IN 46001",
    "addr:housenumber":"205",
    "addr:postcode":"46001",
    "addr:street":"W Church St",
    "iso:country":"US",
    "sg:address":"205 W Church St",
    "sg:city":"Alexandria",
    "sg:classifiers":[
        {
            "category":"Government",
            "subcategory":"Post Office",
            "type":"Public Place"
        }
    ],
    "sg:phone":"+1 765 724 3628",
    "sg:postcode":"46001",
    "sg:province":"IN",
    "sg:tags":[
        "postal",
        "us"
    ],
    "wof:name":"US Post Office",
    "wof:placetype":"venue"
},
  "geometry": {"coordinates":[-85.67611599999999,40.26363],"type":"Point"}
}