{
  "type": "Feature",
  "properties": {
    "addr:full":"111 W Elm St Gaston IN 47342",
    "addr:housenumber":"111",
    "addr:postcode":"47342",
    "addr:street":"W Elm St",
    "iso:country":"US",
    "sg:address":"111 W Elm St",
    "sg:city":"Gaston",
    "sg:classifiers":[
        {
            "category":"Government",
            "subcategory":"Post Office",
            "type":"Public Place"
        }
    ],
    "sg:phone":"+1 765 358 4886",
    "sg:postcode":"47342",
    "sg:province":"IN",
    "wof:name":"US Post Office",
    "wof:placetype":"venue"
},
  "geometry": {"coordinates":[-85.500924,40.313687],"type":"Point"}
}