{
  "type": "Feature",
  "properties": {
    "iso:country":"US",
    "sg:address":"3348 Orchard Ave",
    "sg:city":"Indianapolis",
    "sg:classifiers":[
        {
            "category":"Organizations",
            "subcategory":"Religious Organization",
            "type":"Services"
        }
    ],
    "sg:phone":"+1 317 926 0912",
    "sg:postcode":"46218",
    "sg:province":"IN",
    "sg:tags":[
        "clergy"
    ],
    "wof:name":"Nathaniel L Smith",
    "wof:placetype":"venue"
},
  "geometry": {"coordinates":[-86.12824000000001,39.817075],"type":"Point"}
}