{
  "type": "Feature",
  "properties": {
    "addr:full":"7318 US Hwy 36 Danville IN 46122",
    "addr:housenumber":"7318",
    "addr:postcode":"46122",
    "addr:street":"Us Hwy 36",
    "iso:country":"US",
    "sg:address":"7318 US Hwy 36",
    "sg:city":"Danville",
    "sg:classifiers":[
        {
            "category":"Shopping",
            "subcategory":"Computers & Home Electronics",
            "type":"Retail Goods"
        }
    ],
    "sg:phone":"+1 317 745 7555",
    "sg:postcode":"46122",
    "sg:province":"IN",
    "sg:tags":[
        "equipment",
        "satellite",
        "system"
    ],
    "wof:name":"Wingler & Son",
    "wof:placetype":"venue"
},
  "geometry": {"coordinates":[-86.66512899999999,39.760728],"type":"Point"}
}