{
  "type": "Feature",
  "properties": {
    "iso:country":"US",
    "sg:address":"1220 5th St",
    "sg:city":"Bedford",
    "sg:classifiers":[
        {
            "category":"Bars & Pubs",
            "type":"Food & Drink"
        }
    ],
    "sg:phone":"+1 812 279 2818",
    "sg:postcode":"47421",
    "sg:province":"IN",
    "wof:name":"Bandana's",
    "wof:placetype":"venue"
},
  "geometry": {"coordinates":[-86.48893700000001,38.874304],"type":"Point"}
}