{
  "type": "Feature",
  "properties": {
    "iso:country":"US",
    "sg:address":"20 Vernon St",
    "sg:city":"North Vernon",
    "sg:classifiers":[
        {
            "category":"Real Estate",
            "subcategory":"Real Estate Services",
            "type":"Services"
        }
    ],
    "sg:phone":"+1 812 346 2259",
    "sg:postcode":"47265",
    "sg:province":"IN",
    "wof:name":"North Vernon Abstract",
    "wof:placetype":"venue"
},
  "geometry": {"coordinates":[-85.624048,39.00203],"type":"Point"}
}