{
  "type": "Feature",
  "properties": {
    "iso:country":"US",
    "sg:address":"6311 Central Ave",
    "sg:city":"Portage",
    "sg:classifiers":[
        {
            "category":"Professional",
            "subcategory":"Accounting & Tax Preparation",
            "type":"Services"
        }
    ],
    "sg:phone":"+1 219 763 3971",
    "sg:postcode":"46368",
    "sg:province":"IN",
    "wof:name":"Brenda Ames CPA",
    "wof:placetype":"venue"
},
  "geometry": {"coordinates":[-87.170561,41.575834],"type":"Point"}
}