{
  "type": "Feature",
  "properties": {
    "iso:country":"US",
    "sg:address":"9350 E 43rd St",
    "sg:city":"Indianapolis",
    "sg:classifiers":[
        {
            "category":"Professional",
            "subcategory":"Business Services",
            "type":"Services"
        }
    ],
    "sg:phone":"+1 317 898 2211",
    "sg:postcode":"46235",
    "sg:province":"IN",
    "sg:tags":[
        "apartment",
        "complex"
    ],
    "wof:name":"Sutton Place Apartments",
    "wof:placetype":"venue"
},
  "geometry": {"coordinates":[-86.004282,39.834827],"type":"Point"}
}