{
  "type": "Feature",
  "properties": {
    "iso:country":"US",
    "sg:address":"103 S Willow St",
    "sg:city":"Flora",
    "sg:classifiers":[
        {
            "category":"Organizations",
            "subcategory":"Religious Organization",
            "type":"Services"
        }
    ],
    "sg:phone":"+1 574 967 3020",
    "sg:postcode":"46929",
    "sg:province":"IN",
    "sg:tags":[
        "church"
    ],
    "wof:name":"Flora Grace Brethren Church",
    "wof:placetype":"venue"
},
  "geometry": {"coordinates":[-86.526346,40.547126],"type":"Point"}
}