{
  "type": "Feature",
  "properties": {
    "iso:country":"US",
    "sg:address":"900 S Tekoppel Ave",
    "sg:city":"Evansville",
    "sg:classifiers":[
        {
            "category":"Government",
            "subcategory":"Office",
            "type":"Public Place"
        }
    ],
    "sg:phone":"+1 812 428 0557",
    "sg:postcode":"47712",
    "sg:province":"IN",
    "sg:tags":[
        "govt",
        "city"
    ],
    "wof:name":"Evansville Water Treatment",
    "wof:placetype":"venue"
},
  "geometry": {"coordinates":[-87.61926,37.961698],"type":"Point"}
}