{
  "type": "Feature",
  "properties": {
    "addr:full":"5901 State Rd 68 Poseyville IN 47633",
    "addr:housenumber":"5901;68",
    "addr:postcode":"poseyville;47633",
    "addr:street":"State Rd",
    "iso:country":"US",
    "sg:address":"5901 State Rd 68",
    "sg:city":"Poseyville",
    "sg:classifiers":[
        {
            "category":"Building & Trades",
            "subcategory":"Plumbing",
            "type":"Services"
        }
    ],
    "sg:phone":"+1 812 874 3149",
    "sg:postcode":"47633",
    "sg:province":"IN",
    "sg:tags":[
        "heating",
        "contractor"
    ],
    "wof:name":"Fred Beuligmann Heating & AC",
    "wof:placetype":"venue"
},
  "geometry": {"coordinates":[-87.791049,38.164768],"type":"Point"}
}