{
  "type": "Feature",
  "properties": {
    "addr:full":"6100 Paint Creek Four Mile Rd Camden IN 45311",
    "addr:housenumber":"6100",
    "addr:postcode":"45311",
    "addr:street":"Paint Creek Four Mile Rd",
    "iso:country":"US",
    "sg:address":"6100 Paint Creek Four Mile Rd",
    "sg:city":"Camden",
    "sg:phone":"+1 937 452 1598",
    "sg:postcode":"45311",
    "sg:province":"IN",
    "sg:tags":[
        "farm",
        "corn"
    ],
    "wof:name":"Don Keehner",
    "wof:placetype":"venue"
},
  "geometry": {"coordinates":[-84.745159,39.65556],"type":"Point"}
}