{
  "type": "Feature",
  "properties": {
    "addr:full":"10475 Crosspoint Blvd Indianapolis IN 46256",
    "addr:postcode":"10475;46256",
    "addr:street":"Crosspoint Blvd",
    "iso:country":"US",
    "sg:address":"10475 Crosspoint Blvd",
    "sg:city":"Indianapolis",
    "sg:classifiers":[
        {
            "category":"Professional",
            "subcategory":"Employment Agencies",
            "type":"Services"
        }
    ],
    "sg:phone":"+1 317 815 9490",
    "sg:postcode":"46256",
    "sg:province":"IN",
    "sg:tags":[
        "opportunity"
    ],
    "sg:website":"www.accountemps.com",
    "wof:name":"Accountemps",
    "wof:placetype":"venue"
},
  "geometry": {"coordinates":[-86.024303,39.937554],"type":"Point"}
}