{
  "type": "Feature",
  "properties": {
    "iso:country":"US",
    "sg:address":"1046 W Knable Rd",
    "sg:city":"Georgetown",
    "sg:classifiers":[
        {
            "category":"Real Estate",
            "subcategory":"Developer",
            "type":"Services"
        }
    ],
    "sg:phone":"+1 812 923 9823",
    "sg:postcode":"47122",
    "sg:province":"IN",
    "wof:name":"Indiana Land Co",
    "wof:placetype":"venue"
},
  "geometry": {"coordinates":[-85.913348,38.288797],"type":"Point"}
}