{
  "type": "Feature",
  "properties": {
    "iso:country":"US",
    "sg:address":"6185 Guilford Ave",
    "sg:city":"Indianapolis",
    "sg:classifiers":[
        {
            "category":"Place Of Worship",
            "subcategory":"Church",
            "type":"Public Place"
        },
        {
            "category":"Place Of Worship",
            "type":"Public Place"
        }
    ],
    "sg:phone":"+1 317 251 5049",
    "sg:postcode":"46220",
    "sg:province":"IN",
    "sg:tags":[
        "churches-methodist"
    ],
    "wof:name":"Broad Ripple United Methodist Church",
    "wof:placetype":"venue"
},
  "geometry": {"coordinates":[-86.143209,39.867969],"type":"Point"}
}