{
  "type": "Feature",
  "properties": {
    "iso:country":"US",
    "sg:address":"4004 Madison Ave",
    "sg:city":"Indianapolis",
    "sg:classifiers":[
        {
            "category":"Manufacturing",
            "subcategory":"Printing",
            "type":"Manufacturing & Wholesale Goods"
        }
    ],
    "sg:phone":"+1 317 786 3488",
    "sg:postcode":"46227",
    "sg:province":"IN",
    "sg:tags":[
        "commercial"
    ],
    "wof:name":"Triangle Printing Co",
    "wof:placetype":"venue"
},
  "geometry": {"coordinates":[-86.14225399999999,39.707377],"type":"Point"}
}