{
  "type": "Feature",
  "properties": {
    "iso:country":"US",
    "sg:address":"2 S Main St",
    "sg:city":"Knox",
    "sg:classifiers":[
        {
            "category":"Shopping",
            "subcategory":"Discount & Variety Stores",
            "type":"Retail Goods"
        }
    ],
    "sg:phone":"+1 574 772 5795",
    "sg:postcode":"46534",
    "sg:province":"IN",
    "wof:name":"B/Lo Variety",
    "wof:placetype":"venue"
},
  "geometry": {"coordinates":[-86.623255,41.297471],"type":"Point"}
}