{
  "type": "Feature",
  "properties": {
    "addr:full":"24 E Rand St Hobart IN 46342",
    "addr:housenumber":"24",
    "addr:postcode":"46342",
    "addr:street":"E Rand St",
    "iso:country":"US",
    "sg:address":"24 E Rand St",
    "sg:city":"Hobart",
    "sg:classifiers":[
        {
            "category":"Health Services",
            "subcategory":"Medical Lab",
            "type":"Services"
        }
    ],
    "sg:phone":"+1 219 947 2890",
    "sg:postcode":"46342",
    "sg:province":"IN",
    "sg:tags":[
        "laboratory",
        "dental"
    ],
    "wof:name":"Moon Dental Laboratory",
    "wof:placetype":"venue"
},
  "geometry": {"coordinates":[-87.25551900000001,41.547182],"type":"Point"}
}