{
  "type": "Feature",
  "properties": {
    "iso:country":"US",
    "sg:address":"3200 E 73rd Ave",
    "sg:city":"Merrillville",
    "sg:classifiers":[
        {
            "category":"Retail",
            "subcategory":"Auto Repair",
            "type":"Services"
        }
    ],
    "sg:phone":"+1 219 942 6311",
    "sg:postcode":"46410",
    "sg:province":"IN",
    "sg:tags":[
        "repairing",
        "automobile"
    ],
    "wof:name":"Mroz Complete Auto Inc",
    "wof:placetype":"venue"
},
  "geometry": {"coordinates":[-87.28147,41.486496],"type":"Point"}
}