{
  "type": "Feature",
  "properties": {
    "iso:country":"US",
    "sg:address":"1 E Court St",
    "sg:city":"Paoli",
    "sg:classifiers":[
        {
            "category":"Government",
            "subcategory":"Office",
            "type":"Public Place"
        }
    ],
    "sg:phone":"+1 812 723 2649",
    "sg:postcode":"47454",
    "sg:province":"IN",
    "sg:tags":[
        "county"
    ],
    "wof:name":"Orange County Clerk",
    "wof:placetype":"venue"
},
  "geometry": {"coordinates":[-86.468001,38.55601],"type":"Point"}
}