{
  "type": "Feature",
  "properties": {
    "iso:country":"US",
    "sg:address":"15290 Stony Creek Way",
    "sg:city":"Noblesville",
    "sg:classifiers":[
        {
            "category":"Manufacturing",
            "subcategory":"Tools & Machinery",
            "type":"Manufacturing & Wholesale Goods"
        }
    ],
    "sg:phone":"+1 317 770 6925",
    "sg:postcode":"46060",
    "sg:province":"IN",
    "sg:tags":[
        "fasteners-industrial"
    ],
    "sg:website":"http://www.trainorassoc.com",
    "wof:name":"Trainor Associates",
    "wof:placetype":"venue"
},
  "geometry": {"coordinates":[-86.007685,40.007511],"type":"Point"}
}