{
  "type": "Feature",
  "properties": {
    "iso:country":"US",
    "sg:address":"110 Lantern Ln",
    "sg:city":"Carmel",
    "sg:classifiers":[
        {
            "category":"Professional",
            "type":"Services"
        }
    ],
    "sg:phone":"+1 317 566 8863",
    "sg:postcode":"46032",
    "sg:province":"IN",
    "wof:name":"Flowers Communications Inc",
    "wof:placetype":"venue"
},
  "geometry": {"coordinates":[-86.138712,39.976169],"type":"Point"}
}