{
  "type": "Feature",
  "properties": {
    "iso:country":"US",
    "sg:address":"109 W Sycamore St",
    "sg:city":"Kokomo",
    "sg:classifiers":[
        {
            "category":"Professional",
            "subcategory":"Lawyer & Legal Services",
            "type":"Services"
        }
    ],
    "sg:phone":"+1 765 457 9121",
    "sg:postcode":"46901",
    "sg:province":"IN",
    "sg:tags":[
        "attorney"
    ],
    "wof:name":"Stephanie Doran",
    "wof:placetype":"venue"
},
  "geometry": {"coordinates":[-86.132357,40.48639],"type":"Point"}
}