{
  "type": "Feature",
  "properties": {
    "iso:country":"US",
    "sg:address":"79 N Co Rd 625 E",
    "sg:city":"Avon",
    "sg:classifiers":[
        {
            "category":"Health Services",
            "subcategory":"Hospital",
            "type":"Services"
        },
        {
            "category":"Social Services",
            "type":"Services"
        }
    ],
    "sg:phone":"+1 317 272 6999",
    "sg:postcode":"46123",
    "sg:province":"IN",
    "sg:tags":[
        "mental"
    ],
    "wof:name":"Avon Christian Counseling Ctr",
    "wof:placetype":"venue"
},
  "geometry": {"coordinates":[-86.414291,39.76272],"type":"Point"}
}