{
  "type": "Feature",
  "properties": {
    "addr:full":"5331 Claybrooke Dr Indianapolis IN 46221",
    "addr:housenumber":"5331",
    "addr:postcode":"46221",
    "addr:street":"Claybrooke Dr",
    "iso:country":"US",
    "sg:address":"5331 Claybrooke Dr",
    "sg:city":"Indianapolis",
    "sg:classifiers":[
        {
            "category":"Coffee & Tea",
            "type":"Food & Drink"
        },
        {
            "category":"Restaurant",
            "type":"Food & Drink"
        }
    ],
    "sg:phone":"+1 317 354 3751",
    "sg:postcode":"46221",
    "sg:province":"IN",
    "sg:tags":[
        "espresso"
    ],
    "wof:name":"Mama Boulets Cajun Cafe",
    "wof:placetype":"venue"
},
  "geometry": {"coordinates":[-86.25129800000001,39.69353],"type":"Point"}
}