{
  "type": "Feature",
  "properties": {
    "iso:country":"US",
    "sg:address":"384 N West St",
    "sg:city":"Bloomingdale",
    "sg:classifiers":[
        {
            "category":"Government",
            "subcategory":"Office",
            "type":"Public Place"
        }
    ],
    "sg:phone":"+1 765 498 8132",
    "sg:postcode":"47838",
    "sg:province":"IN",
    "sg:tags":[
        "village"
    ],
    "wof:name":"Bloomingdale Park Bd President",
    "wof:placetype":"venue"
},
  "geometry": {"coordinates":[-87.398715,38.961227],"type":"Point"}
}