{
  "type": "Feature",
  "properties": {
    "iso:country":"US",
    "sg:address":"7409 Lower Huntington Rd",
    "sg:city":"Fort Wayne",
    "sg:classifiers":[
        {
            "category":"Professional",
            "type":"Services"
        }
    ],
    "sg:phone":"+1 260 747 6464",
    "sg:postcode":"46809",
    "sg:province":"IN",
    "wof:name":"Vicki Junk Wright",
    "wof:placetype":"venue"
},
  "geometry": {"coordinates":[-85.241022,41.004739],"type":"Point"}
}