{
  "type": "Feature",
  "properties": {
    "iso:country":"US",
    "sg:address":"975 E Jefferson St",
    "sg:city":"Tipton",
    "sg:classifiers":[
        {
            "category":"Freight",
            "type":"Transportation"
        }
    ],
    "sg:phone":"+1 765 675 6165",
    "sg:postcode":"46072",
    "sg:province":"IN",
    "sg:tags":[
        "commercial",
        "storage"
    ],
    "wof:name":"Self Storage",
    "wof:placetype":"venue"
},
  "geometry": {"coordinates":[-86.031786,40.2825],"type":"Point"}
}