{
  "type": "Feature",
  "properties": {
    "iso:country":"US",
    "sg:address":"633 Yosemite Dr",
    "sg:city":"Indianapolis",
    "sg:classifiers":[
        {
            "category":"Wholesale",
            "subcategory":"Furniture",
            "type":"Manufacturing & Wholesale Goods"
        }
    ],
    "sg:phone":"+1 317 782 3323",
    "sg:postcode":"46217",
    "sg:province":"IN",
    "sg:tags":[
        "equipment",
        "school"
    ],
    "wof:name":"Sumner Equipment Co",
    "wof:placetype":"venue"
},
  "geometry": {"coordinates":[-86.170237,39.667771],"type":"Point"}
}