{
  "type": "Feature",
  "properties": {
    "iso:country":"US",
    "sg:address":"3818 N Illinois St",
    "sg:city":"Indianapolis",
    "sg:classifiers":[
        {
            "category":"Shopping",
            "subcategory":"Clothing, Apparel, & Fashions",
            "type":"Retail Goods"
        }
    ],
    "sg:phone":"+1 317 925 6406",
    "sg:postcode":"46208",
    "sg:province":"IN",
    "sg:tags":[
        "theatrical",
        "costume"
    ],
    "wof:name":"Costumes By Margie",
    "wof:placetype":"venue"
},
  "geometry": {"coordinates":[-86.159284,39.82562],"type":"Point"}
}