{
  "type": "Feature",
  "properties": {
    "iso:country":"US",
    "sg:address":"310 W Main St",
    "sg:city":"Delphi",
    "sg:classifiers":[
        {
            "category":"Government",
            "subcategory":"Jail",
            "type":"Public Place"
        }
    ],
    "sg:phone":"+1 765 564 2413",
    "sg:postcode":"46923",
    "sg:province":"IN",
    "sg:tags":[
        "county",
        "govt",
        "institution"
    ],
    "wof:name":"County Jail",
    "wof:placetype":"venue"
},
  "geometry": {"coordinates":[-86.676244,40.585205],"type":"Point"}
}