{
  "type": "Feature",
  "properties": {
    "iso:country":"US",
    "sg:address":"3305 South St",
    "sg:city":"Lafayette",
    "sg:classifiers":[
        {
            "category":"Home & Garden",
            "subcategory":"Building Materials",
            "type":"Retail Goods"
        }
    ],
    "sg:phone":"+1 765 446 4200",
    "sg:postcode":"47904",
    "sg:province":"IN",
    "sg:tags":[
        "glass",
        "window",
        "plate"
    ],
    "wof:name":"Auto Glass Experts",
    "wof:placetype":"venue"
},
  "geometry": {"coordinates":[-86.858144,40.417548],"type":"Point"}
}