{
  "type": "Feature",
  "properties": {
    "iso:country":"US",
    "sg:address":"107 Lange Ln",
    "sg:city":"Angola",
    "sg:classifiers":[
        {
            "category":"Retail",
            "subcategory":"Auto Repair",
            "type":"Services"
        }
    ],
    "sg:phone":"+1 260 668 7484",
    "sg:postcode":"46703",
    "sg:province":"IN",
    "sg:tags":[
        "repairing",
        "automobile"
    ],
    "wof:name":"Angola Auto Svc",
    "wof:placetype":"venue"
},
  "geometry": {"coordinates":[-84.997163,41.625186],"type":"Point"}
}