{
  "type": "Feature",
  "properties": {
    "addr:full":"2993 E Main St Richmond IN 47374",
    "addr:housenumber":"2993",
    "addr:postcode":"47374",
    "addr:street":"E Main St",
    "iso:country":"US",
    "sg:address":"2993 E Main St",
    "sg:city":"Richmond",
    "sg:classifiers":[
        {
            "category":"Retail",
            "subcategory":"Auto Repair",
            "type":"Services"
        }
    ],
    "sg:phone":"+1 765 962 7344",
    "sg:postcode":"47374",
    "sg:province":"IN",
    "sg:tags":[
        "automobile",
        "lubrication"
    ],
    "wof:name":"Jiffy Lube",
    "wof:placetype":"venue"
},
  "geometry": {"coordinates":[-84.862054,39.830692],"type":"Point"}
}