{
  "type": "Feature",
  "properties": {
    "iso:country":"US",
    "sg:address":"2212 Lincoln Way W",
    "sg:city":"Mishawaka",
    "sg:classifiers":[
        {
            "category":"Insurance",
            "subcategory":"Insurance Agent",
            "type":"Services"
        }
    ],
    "sg:phone":"+1 574 255 2714",
    "sg:postcode":"46544",
    "sg:province":"IN",
    "wof:name":"Chris Skodinski",
    "wof:placetype":"venue"
},
  "geometry": {"coordinates":[-86.204353,41.658018],"type":"Point"}
}