{
  "type": "Feature",
  "properties": {
    "iso:country":"US",
    "sg:address":"4050 Eagle Cove W Dr",
    "sg:city":"Indianapolis",
    "sg:classifiers":[
        {
            "category":"Building & Trades",
            "subcategory":"Landscaping Services",
            "type":"Services"
        }
    ],
    "sg:phone":"+1 317 329 2749",
    "sg:postcode":"46254",
    "sg:province":"IN",
    "sg:tags":[
        "lawn",
        "maintenance",
        "grounds"
    ],
    "wof:name":"Tyler Lawn Care & Hauling Svc",
    "wof:placetype":"venue"
},
  "geometry": {"coordinates":[-86.287854,39.828408],"type":"Point"}
}