{
  "type": "Feature",
  "properties": {
    "iso:country":"US",
    "sg:address":"2211 N Schomburg Dr",
    "sg:city":"Fort Wayne",
    "sg:classifiers":[
        {
            "category":"Building & Trades",
            "subcategory":"Construction",
            "type":"Services"
        }
    ],
    "sg:phone":"+1 260 482 8825",
    "sg:postcode":"46808",
    "sg:province":"IN",
    "sg:tags":[
        "house"
    ],
    "wof:name":"Cardinal Renovations Inc",
    "wof:placetype":"venue"
},
  "geometry": {"coordinates":[-85.169764,41.115875],"type":"Point"}
}