{
  "type": "Feature",
  "properties": {
    "addr:full":"213 W Main St Vevay IN 47043",
    "addr:housenumber":"213",
    "addr:postcode":"47043",
    "addr:street":"W Main St",
    "iso:country":"US",
    "sg:address":"213 W Main St",
    "sg:city":"Vevay",
    "sg:classifiers":[
        {
            "category":"Health Services",
            "subcategory":"Doctor",
            "type":"Services"
        }
    ],
    "sg:phone":"+1 812 427 2911",
    "sg:postcode":"47043",
    "sg:province":"IN",
    "sg:tags":[
        "physician",
        "surgeon"
    ],
    "wof:name":"Madison Clinic-Kings Daughters",
    "wof:placetype":"venue"
},
  "geometry": {"coordinates":[-85.06811399999999,38.7469],"type":"Point"}
}