{
  "type": "Feature",
  "properties": {
    "iso:country":"US",
    "sg:address":"8253 Virginia St",
    "sg:city":"Merrillville",
    "sg:classifiers":[
        {
            "category":"Health Services",
            "subcategory":"Nursing And Care Facility",
            "type":"Services"
        }
    ],
    "sg:phone":"+1 219 736 9383",
    "sg:postcode":"46410",
    "sg:province":"IN",
    "sg:tags":[
        "home",
        "convalescent"
    ],
    "wof:name":"Alterra Sterling House",
    "wof:placetype":"venue"
},
  "geometry": {"coordinates":[-87.3292,41.468306],"type":"Point"}
}