{
  "type": "Feature",
  "properties": {
    "iso:country":"US",
    "sg:address":"137 N Harrison St",
    "sg:city":"Knightstown",
    "sg:classifiers":[
        {
            "category":"Professional",
            "subcategory":"Business Services",
            "type":"Services"
        }
    ],
    "sg:phone":"+1 765 345 5551",
    "sg:postcode":"46148",
    "sg:province":"IN",
    "sg:tags":[
        "embroidery"
    ],
    "wof:name":"A P Embroidery",
    "wof:placetype":"venue"
},
  "geometry": {"coordinates":[-85.528886,39.796412],"type":"Point"}
}