{
  "type": "Feature",
  "properties": {
    "addr:full":"742 Clifty Dr Madison IN 47250",
    "addr:housenumber":"742",
    "addr:postcode":"47250",
    "addr:street":"Clifty Dr",
    "iso:country":"US",
    "sg:address":"742 Clifty Dr",
    "sg:city":"Madison",
    "sg:classifiers":[
        {
            "category":"Home & Garden",
            "subcategory":"Building Materials",
            "type":"Retail Goods"
        }
    ],
    "sg:phone":"+1 812 265 2834",
    "sg:postcode":"47250",
    "sg:province":"IN",
    "sg:tags":[
        "paint"
    ],
    "wof:name":"Sherwin-Williams Paints",
    "wof:placetype":"venue"
},
  "geometry": {"coordinates":[-85.404124,38.774744],"type":"Point"}
}