{
  "type": "Feature",
  "properties": {
    "addr:full":"5391 Rockville Rd Indianapolis IN 46224",
    "addr:housenumber":"5391",
    "addr:postcode":"46224",
    "addr:street":"Rockville Rd",
    "iso:country":"US",
    "sg:address":"5391 Rockville Rd",
    "sg:city":"Indianapolis",
    "sg:classifiers":[
        {
            "category":"Restaurant",
            "type":"Food & Drink"
        }
    ],
    "sg:phone":"+1 317 472 3900",
    "sg:postcode":"46224",
    "sg:province":"IN",
    "wof:name":"Pizza Magia",
    "wof:placetype":"venue"
},
  "geometry": {"coordinates":[-86.25385300000001,39.765069],"type":"Point"}
}