{
  "type": "Feature",
  "properties": {
    "addr:full":"1631 E State Rd 44 Shelbyville IN 46176",
    "addr:housenumber":"1631;44",
    "addr:postcode":"46176",
    "addr:street":"E State Rd",
    "iso:country":"US",
    "sg:address":"1631 E State Rd 44",
    "sg:city":"Shelbyville",
    "sg:classifiers":[
        {
            "category":"Restaurant",
            "type":"Food & Drink"
        }
    ],
    "sg:phone":"+1 317 398 0257",
    "sg:postcode":"46176",
    "sg:province":"IN",
    "wof:name":"Mc Donald's",
    "wof:placetype":"venue"
},
  "geometry": {"coordinates":[-85.753303,39.519786],"type":"Point"}
}