{
  "type": "Feature",
  "properties": {
    "iso:country":"US",
    "sg:address":"124 N Baltimore St",
    "sg:city":"Bremen",
    "sg:classifiers":[
        {
            "category":"Organizations",
            "subcategory":"Religious Organization",
            "type":"Services"
        }
    ],
    "sg:phone":"+1 574 546 2049",
    "sg:postcode":"46506",
    "sg:province":"IN",
    "sg:tags":[
        "church"
    ],
    "wof:name":"Bremen Bible Church",
    "wof:placetype":"venue"
},
  "geometry": {"coordinates":[-86.153662,41.447154],"type":"Point"}
}