{
  "type": "Feature",
  "properties": {
    "iso:country":"US",
    "sg:address":"3012 Covert Ave",
    "sg:city":"Evansville",
    "sg:classifiers":[
        {
            "category":"Restaurant",
            "type":"Food & Drink"
        }
    ],
    "sg:phone":"+1 812 475 9880",
    "sg:postcode":"47714",
    "sg:province":"IN",
    "sg:tags":[
        "eating"
    ],
    "wof:name":"Frank Jr's Barbeque & Catering",
    "wof:placetype":"venue"
},
  "geometry": {"coordinates":[-87.511342,37.955122],"type":"Point"}
}