{
  "type": "Feature",
  "properties": {
    "iso:country":"US",
    "sg:address":"266 W Parr Rd",
    "sg:city":"Berne",
    "sg:phone":"+1 260 589 2748",
    "sg:postcode":"46711",
    "sg:province":"IN",
    "sg:tags":[
        "farm",
        "corn",
        "soybean"
    ],
    "wof:name":"Betty Grimm",
    "wof:placetype":"venue"
},
  "geometry": {"coordinates":[-84.952034,40.665058],"type":"Point"}
}