{
  "type": "Feature",
  "properties": {
    "addr:full":"1001 W 1st St Rushville IN 46173",
    "addr:housenumber":"1001",
    "addr:postcode":"46173",
    "addr:street":"W 1St St",
    "iso:country":"US",
    "sg:address":"1001 W 1st St",
    "sg:city":"Rushville",
    "sg:classifiers":[
        {
            "category":"Building & Trades",
            "subcategory":"Cleaning & Sanitation",
            "type":"Services"
        }
    ],
    "sg:phone":"+1 765 938 1232",
    "sg:postcode":"46173",
    "sg:province":"IN",
    "sg:tags":[
        "janitor"
    ],
    "wof:name":"Cleaning Serivce",
    "wof:placetype":"venue"
},
  "geometry": {"coordinates":[-85.457841,39.606623],"type":"Point"}
}