{
  "type": "Feature",
  "properties": {
    "iso:country":"US",
    "sg:address":"1140 S Calumet Rd",
    "sg:city":"Chesterton",
    "sg:classifiers":[
        {
            "category":"Sports & Exercise",
            "subcategory":"Gym",
            "type":"Entertainment"
        }
    ],
    "sg:phone":"+1 219 929 5798",
    "sg:postcode":"46304",
    "sg:province":"IN",
    "sg:tags":[
        "club",
        "health",
        "studio",
        "gymnasium"
    ],
    "wof:name":"Bill's Fitness Ctr",
    "wof:placetype":"venue"
},
  "geometry": {"coordinates":[-87.048743,41.599627],"type":"Point"}
}