{
  "type": "Feature",
  "properties": {
    "iso:country":"US",
    "sg:address":"1018 Maxwell Ave",
    "sg:city":"Evansville",
    "sg:classifiers":[
        {
            "category":"Retail",
            "subcategory":"Auto Repair",
            "type":"Services"
        }
    ],
    "sg:phone":"+1 812 423 6295",
    "sg:postcode":"47711",
    "sg:province":"IN",
    "sg:tags":[
        "body",
        "automobile",
        "painting"
    ],
    "sg:website":"www.millsbodyshops.com",
    "wof:name":"Mills Body Shops",
    "wof:placetype":"venue"
},
  "geometry": {"coordinates":[-87.545895,37.993949],"type":"Point"}
}