{
  "type": "Feature",
  "properties": {
    "addr:full":"1207 W 9th St Anderson IN 46016",
    "addr:housenumber":"1207",
    "addr:postcode":"46016",
    "addr:street":"W 9Th St",
    "iso:country":"US",
    "sg:address":"1207 W 9th St",
    "sg:city":"Anderson",
    "sg:classifiers":[
        {
            "category":"Organizations",
            "subcategory":"Religious Organization",
            "type":"Services"
        }
    ],
    "sg:phone":"+1 765 640 2970",
    "sg:postcode":"46016",
    "sg:province":"IN",
    "sg:tags":[
        "church"
    ],
    "wof:name":"World Prayer Ctr Intl",
    "wof:placetype":"venue"
},
  "geometry": {"coordinates":[-85.696566,40.106898],"type":"Point"}
}