{
  "type": "Feature",
  "properties": {
    "iso:country":"US",
    "sg:address":"421 E Main St",
    "sg:city":"Jamestown",
    "sg:classifiers":[
        {
            "category":"Government",
            "subcategory":"Office",
            "type":"Public Place"
        }
    ],
    "sg:phone":"+1 765 676 6331",
    "sg:postcode":"46147",
    "sg:province":"IN",
    "sg:tags":[
        "village"
    ],
    "wof:name":"Jamestown Town Building",
    "wof:placetype":"venue"
},
  "geometry": {"coordinates":[-86.62441,39.924535],"type":"Point"}
}