{
  "type": "Feature",
  "properties": {
    "iso:country":"US",
    "sg:address":"8728 Robbins Rd",
    "sg:city":"Indianapolis",
    "sg:classifiers":[
        {
            "category":"Building & Trades",
            "subcategory":"Construction",
            "type":"Services"
        }
    ],
    "sg:phone":"+1 317 334 1810",
    "sg:postcode":"46268",
    "sg:province":"IN",
    "sg:tags":[
        "general",
        "contractor"
    ],
    "sg:website":"www.corbittconst.com",
    "wof:name":"Corbitt & Sons Construction Co",
    "wof:placetype":"venue"
},
  "geometry": {"coordinates":[-86.254304,39.913928],"type":"Point"}
}