{
  "type": "Feature",
  "properties": {
    "iso:country":"US",
    "sg:address":"5674 N State Line Rd",
    "sg:city":"Liberty",
    "sg:classifiers":[
        {
            "category":"Farming",
            "subcategory":"Farm & Veterinary Services",
            "type":"Manufacturing & Wholesale Goods"
        }
    ],
    "sg:phone":"+1 765 458 9216",
    "sg:postcode":"47353",
    "sg:province":"IN",
    "sg:tags":[
        "breeder",
        "livestock"
    ],
    "wof:name":"Wolfe Farms Show Cattle",
    "wof:placetype":"venue"
},
  "geometry": {"coordinates":[-84.814459,39.723913],"type":"Point"}
}