{
  "type": "Feature",
  "properties": {
    "iso:country":"US",
    "sg:address":"10530 N Co Rd 1300 E",
    "sg:city":"Seymour",
    "sg:classifiers":[
        {
            "category":"Farming",
            "subcategory":"Farm",
            "type":"Manufacturing & Wholesale Goods"
        }
    ],
    "sg:phone":"+1 812 445 3490",
    "sg:postcode":"47274",
    "sg:province":"IN",
    "sg:tags":[
        "crop",
        "general"
    ],
    "wof:name":"Bill Brooks",
    "wof:placetype":"venue"
},
  "geometry": {"coordinates":[-85.798315,39.034217],"type":"Point"}
}