{
  "type": "Feature",
  "properties": {
    "iso:country":"US",
    "sg:address":"6586 Caressa Way",
    "sg:city":"Indianapolis",
    "sg:classifiers":[
        {
            "category":"Banks & Credit Unions",
            "subcategory":"Financial Services",
            "type":"Services"
        }
    ],
    "sg:phone":"+1 317 446 1564",
    "sg:postcode":"46259",
    "sg:province":"IN",
    "sg:tags":[
        "trust",
        "investment",
        "real estate"
    ],
    "wof:name":"Reliable Real Estate Research",
    "wof:placetype":"venue"
},
  "geometry": {"coordinates":[-86.01426499999999,39.672158],"type":"Point"}
}