{
  "type": "Feature",
  "properties": {
    "iso:country":"US",
    "sg:address":"5858 Spearsville Rd",
    "sg:city":"Morgantown",
    "sg:classifiers":[
        {
            "category":"Organizations",
            "subcategory":"Religious Organization",
            "type":"Services"
        }
    ],
    "sg:phone":"+1 812 988 4161",
    "sg:postcode":"46160",
    "sg:province":"IN",
    "wof:name":"Bean Blossom Baptist Church",
    "wof:placetype":"venue"
},
  "geometry": {"coordinates":[-86.242182,39.279016],"type":"Point"}
}