{
  "type": "Feature",
  "properties": {
    "iso:country":"US",
    "sg:address":"2622 16th St",
    "sg:city":"Bedford",
    "sg:classifiers":[
        {
            "category":"Banks & Credit Unions",
            "subcategory":"Bank",
            "type":"Services"
        }
    ],
    "sg:phone":"+1 812 275 2022",
    "sg:postcode":"47421",
    "sg:province":"IN",
    "sg:tags":[
        "loan",
        "real estate"
    ],
    "wof:name":"Mortgage Co",
    "wof:placetype":"venue"
},
  "geometry": {"coordinates":[-86.50798399999999,38.860933],"type":"Point"}
}