{
  "type": "Feature",
  "properties": {
    "iso:country":"US",
    "sg:address":"314 S Clark St",
    "sg:city":"Colfax",
    "sg:classifiers":[
        {
            "category":"Organizations",
            "subcategory":"Religious Organization",
            "type":"Services"
        }
    ],
    "sg:phone":"+1 765 324 2745",
    "sg:postcode":"46035",
    "sg:province":"IN",
    "sg:tags":[
        "church"
    ],
    "wof:name":"Colfax Christian Church",
    "wof:placetype":"venue"
},
  "geometry": {"coordinates":[-86.665181,40.19166],"type":"Point"}
}