{
  "type": "Feature",
  "properties": {
    "addr:full":"425 W Deffenbaugh St Kokomo IN 46902",
    "addr:housenumber":"425",
    "addr:postcode":"46902",
    "addr:street":"W Deffenbaugh St",
    "iso:country":"US",
    "sg:address":"425 W Deffenbaugh St",
    "sg:city":"Kokomo",
    "sg:classifiers":[
        {
            "category":"Personal",
            "subcategory":"Beauty Salon",
            "type":"Services"
        }
    ],
    "sg:phone":"+1 765 452 2039",
    "sg:postcode":"46902",
    "sg:province":"IN",
    "wof:name":"Amy's Beauty Shop",
    "wof:placetype":"venue"
},
  "geometry": {"coordinates":[-86.13557400000001,40.469359],"type":"Point"}
}