{
  "type": "Feature",
  "properties": {
    "iso:country":"US",
    "sg:address":"5040 E 62nd St",
    "sg:city":"Indianapolis",
    "sg:classifiers":[
        {
            "category":"Personal",
            "subcategory":"Beauty Salon",
            "type":"Services"
        }
    ],
    "sg:phone":"+1 317 255 4959",
    "sg:postcode":"46220",
    "sg:province":"IN",
    "wof:name":"Amy L Redmon Studio",
    "wof:placetype":"venue"
},
  "geometry": {"coordinates":[-86.085337,39.868737],"type":"Point"}
}