{
  "type": "Feature",
  "properties": {
    "addr:full":"7333 State Rd 9 Howe IN 46746",
    "addr:housenumber":"7333;9",
    "addr:postcode":"46746",
    "addr:street":"State Rd",
    "iso:country":"US",
    "sg:address":"7333 State Rd 9",
    "sg:city":"Howe",
    "sg:classifiers":[
        {
            "category":"Travel",
            "subcategory":"Hotels & Motels",
            "type":"Entertainment"
        }
    ],
    "sg:phone":"+1 260 562 2828",
    "sg:postcode":"46746",
    "sg:province":"IN",
    "sg:website":"www.super8.com",
    "wof:name":"Super 8 Motel",
    "wof:placetype":"venue"
},
  "geometry": {"coordinates":[-85.42657699999999,41.746518],"type":"Point"}
}