{
  "type": "Feature",
  "properties": {
    "addr:full":"1305 Inverness Farms Rd Martinsville IN 46151",
    "addr:housenumber":"1305",
    "addr:postcode":"46151",
    "addr:street":"Inverness Farms Rd",
    "iso:country":"US",
    "sg:address":"1305 Inverness Farms Rd",
    "sg:city":"Martinsville",
    "sg:classifiers":[
        {
            "category":"Building & Trades",
            "subcategory":"Pest Control",
            "type":"Services"
        }
    ],
    "sg:phone":"+1 765 342 3313",
    "sg:postcode":"46151",
    "sg:province":"IN",
    "wof:name":"Inter Tec",
    "wof:placetype":"venue"
},
  "geometry": {"coordinates":[-86.49894999999999,39.417177],"type":"Point"}
}