{
  "type": "Feature",
  "properties": {
    "addr:full":"507 Airport North Office Park Fort Wayne IN 46825",
    "addr:housenumber":"507",
    "addr:postcode":"46825",
    "iso:country":"US",
    "sg:address":"507 Airport North Office Park",
    "sg:city":"Fort Wayne",
    "sg:classifiers":[
        {
            "category":"Social Services",
            "type":"Services"
        }
    ],
    "sg:phone":"+1 260 490 6364",
    "sg:postcode":"46825",
    "sg:province":"IN",
    "sg:tags":[
        "care",
        "center",
        "day"
    ],
    "wof:name":"Grammy & Grampy's Adult Day",
    "wof:placetype":"venue"
},
  "geometry": {"coordinates":[-85.161416,41.145454],"type":"Point"}
}