{
  "type": "Feature",
  "properties": {
    "iso:country":"US",
    "sg:address":"1421 N Lasalle St",
    "sg:city":"Indianapolis",
    "sg:classifiers":[
        {
            "category":"Building & Trades",
            "subcategory":"Cleaning & Sanitation",
            "type":"Services"
        }
    ],
    "sg:phone":"+1 317 916 0766",
    "sg:postcode":"46201",
    "sg:province":"IN",
    "sg:tags":[
        "janitor"
    ],
    "wof:name":"Hoosier Kleen Building Svc",
    "wof:placetype":"venue"
},
  "geometry": {"coordinates":[-86.109663,39.788524],"type":"Point"}
}