{
  "type": "Feature",
  "properties": {
    "iso:country":"US",
    "sg:address":"8155 E Main St",
    "sg:city":"Dugger",
    "sg:classifiers":[
        {
            "category":"Organizations",
            "subcategory":"Community Association",
            "type":"Services"
        }
    ],
    "sg:phone":"+1 812 648 2666",
    "sg:postcode":"47848",
    "sg:province":"IN",
    "sg:tags":[
        "military"
    ],
    "wof:name":"American Legion",
    "wof:placetype":"venue"
},
  "geometry": {"coordinates":[-87.256753,39.06776],"type":"Point"}
}