{
  "type": "Feature",
  "properties": {
    "iso:country":"US",
    "sg:address":"800 Vigo St",
    "sg:city":"Vincennes",
    "sg:classifiers":[
        {
            "category":"Education",
            "subcategory":"School",
            "type":"Public Place"
        }
    ],
    "sg:phone":"+1 812 882 5460",
    "sg:postcode":"47591",
    "sg:province":"IN",
    "wof:name":"Flaget Elementary School",
    "wof:placetype":"venue"
},
  "geometry": {"coordinates":[-87.528916,38.674597],"type":"Point"}
}