{
  "type": "Feature",
  "properties": {
    "iso:country":"US",
    "sg:address":"4868 US Hwy 35",
    "sg:city":"La Porte",
    "sg:classifiers":[
        {
            "category":"Building & Trades",
            "subcategory":"Construction",
            "type":"Services"
        }
    ],
    "sg:phone":"+1 219 326 6832",
    "sg:postcode":"46350",
    "sg:province":"IN",
    "sg:tags":[
        "contractor"
    ],
    "wof:name":"Delarme Tile Company",
    "wof:placetype":"venue"
},
  "geometry": {"coordinates":[-86.784397,41.675815],"type":"Point"}
}