{
  "type": "Feature",
  "properties": {
    "iso:country":"US",
    "sg:address":"201 Main St",
    "sg:city":"Jasper",
    "sg:classifiers":[
        {
            "category":"Restaurant",
            "type":"Food & Drink"
        }
    ],
    "sg:phone":"+1 812 482 3411",
    "sg:postcode":"47546",
    "sg:province":"IN",
    "wof:name":"Headquarters Inc",
    "wof:placetype":"venue"
},
  "geometry": {"coordinates":[-86.93082699999999,38.389196],"type":"Point"}
}