{
  "type": "Feature",
  "properties": {
    "iso:country":"US",
    "sg:address":"4901 Council Ring Blvd",
    "sg:city":"Kokomo",
    "sg:classifiers":[
        {
            "category":"Government",
            "subcategory":"Office",
            "type":"Public Place"
        }
    ],
    "sg:phone":"+1 765 453 0466",
    "sg:postcode":"46902",
    "sg:province":"IN",
    "sg:tags":[
        "village"
    ],
    "wof:name":"Taylor Twp Trustee",
    "wof:placetype":"venue"
},
  "geometry": {"coordinates":[-86.120094,40.432385],"type":"Point"}
}