{
  "type": "Feature",
  "properties": {
    "addr:full":"1126 Broadway Fort Wayne IN 46802",
    "addr:housenumber":"1126",
    "addr:postcode":"46802",
    "addr:street":"Broadway",
    "iso:country":"US",
    "sg:address":"1126 Broadway",
    "sg:city":"Fort Wayne",
    "sg:classifiers":[
        {
            "category":"Shopping",
            "subcategory":"Gifts & Souvenirs",
            "type":"Retail Goods"
        }
    ],
    "sg:phone":"+1 260 420 4023",
    "sg:postcode":"46802",
    "sg:province":"IN",
    "sg:tags":[
        "indian"
    ],
    "wof:name":"Sage Smoke Traders",
    "wof:placetype":"venue"
},
  "geometry": {"coordinates":[-85.147921,41.074749],"type":"Point"}
}