{
  "type": "Feature",
  "properties": {
    "iso:country":"US",
    "sg:address":"54 Monument Cir",
    "sg:city":"Indianapolis",
    "sg:classifiers":[
        {
            "category":"Shopping",
            "subcategory":"Optical Goods",
            "type":"Retail Goods"
        }
    ],
    "sg:phone":"+1 317 631 1200",
    "sg:postcode":"46204",
    "sg:province":"IN",
    "wof:name":"Ossip",
    "wof:placetype":"venue"
},
  "geometry": {"coordinates":[-86.158592,39.768052],"type":"Point"}
}