{
  "type": "Feature",
  "properties": {
    "iso:country":"US",
    "sg:address":"37 E Mill St",
    "sg:city":"Urbana",
    "sg:classifiers":[
        {
            "category":"Retail",
            "subcategory":"Repair Shop",
            "type":"Services"
        }
    ],
    "sg:phone":"+1 260 774 9309",
    "sg:postcode":"46990",
    "sg:province":"IN",
    "sg:tags":[
        "ironwork"
    ],
    "wof:name":"Iron Customs",
    "wof:placetype":"venue"
},
  "geometry": {"coordinates":[-85.791903,40.898501],"type":"Point"}
}