{
  "type": "Feature",
  "properties": {
    "addr:full":"3314 N Keystone Ave Indianapolis IN 46218",
    "addr:housenumber":"3314",
    "addr:postcode":"46218",
    "addr:street":"N Keystone Ave",
    "iso:country":"US",
    "sg:address":"3314 N Keystone Ave",
    "sg:city":"Indianapolis",
    "sg:classifiers":[
        {
            "category":"Shopping",
            "type":"Retail Goods"
        }
    ],
    "sg:phone":"+1 317 925 5466",
    "sg:postcode":"46218",
    "sg:province":"IN",
    "sg:tags":[
        "merchandise"
    ],
    "wof:name":"Carey Body Shop",
    "wof:placetype":"venue"
},
  "geometry": {"coordinates":[-86.121644,39.816169],"type":"Point"}
}