{
  "type": "Feature",
  "properties": {
    "iso:country":"US",
    "sg:address":"106 S Range St",
    "sg:city":"Wolcott",
    "sg:classifiers":[
        {
            "category":"Home & Garden",
            "subcategory":"Hardware",
            "type":"Retail Goods"
        }
    ],
    "sg:phone":"+1 219 279 2999",
    "sg:postcode":"47995",
    "sg:province":"IN",
    "wof:name":"Jerry's Hardware & Saddle",
    "wof:placetype":"venue"
},
  "geometry": {"coordinates":[-87.041645,40.75825],"type":"Point"}
}