{
  "type": "Feature",
  "properties": {
    "iso:country":"US",
    "sg:address":"2238 E State Rd 64",
    "sg:city":"Winslow",
    "sg:classifiers":[
        {
            "category":"Mining & Drilling",
            "type":"Manufacturing & Wholesale Goods"
        }
    ],
    "sg:phone":"+1 812 789 5351",
    "sg:postcode":"47598",
    "sg:province":"IN",
    "sg:tags":[
        "company"
    ],
    "wof:name":"Triad Mining Inc",
    "wof:placetype":"venue"
},
  "geometry": {"coordinates":[-87.237521,38.333257],"type":"Point"}
}