{
  "type": "Feature",
  "properties": {
    "iso:country":"US",
    "sg:address":"101 W Kirkwood Ave",
    "sg:city":"Bloomington",
    "sg:classifiers":[
        {
            "category":"Personal",
            "subcategory":"Massage",
            "type":"Services"
        }
    ],
    "sg:phone":"+1 415 938 7365",
    "sg:postcode":"47404",
    "sg:province":"IN",
    "sg:website":"www.intunereiki.com",
    "wof:name":"In Tune Reiki",
    "wof:placetype":"venue"
},
  "geometry": {"coordinates":[-86.533672,39.166577],"type":"Point"}
}