{
  "type": "Feature",
  "properties": {
    "iso:country":"US",
    "sg:address":"715 W 8th St",
    "sg:city":"Greensburg",
    "sg:classifiers":[
        {
            "category":"Building & Trades",
            "subcategory":"Construction",
            "type":"Services"
        }
    ],
    "sg:phone":"+1 812 663 5650",
    "sg:postcode":"47240",
    "sg:province":"IN",
    "sg:tags":[
        "house"
    ],
    "wof:name":"Erhart Construction",
    "wof:placetype":"venue"
},
  "geometry": {"coordinates":[-85.494373,39.351572],"type":"Point"}
}