{
  "type": "Feature",
  "properties": {
    "iso:country":"US",
    "sg:address":"4089 N Killion Ct",
    "sg:city":"Bloomington",
    "sg:classifiers":[
        {
            "category":"Wholesale",
            "subcategory":"Medical Equipment & Supplies",
            "type":"Manufacturing & Wholesale Goods"
        }
    ],
    "sg:phone":"+1 812 876 6800",
    "sg:postcode":"47404",
    "sg:province":"IN",
    "sg:tags":[
        "massage"
    ],
    "wof:name":"Honest Product Marketing",
    "wof:placetype":"venue"
},
  "geometry": {"coordinates":[-86.59910000000001,39.209658],"type":"Point"}
}