{
  "type": "Feature",
  "properties": {
    "iso:country":"US",
    "sg:address":"301 N 19th St",
    "sg:city":"Richmond",
    "sg:classifiers":[
        {
            "category":"Education",
            "subcategory":"School",
            "type":"Public Place"
        }
    ],
    "sg:phone":"+1 765 973 3426",
    "sg:postcode":"47374",
    "sg:province":"IN",
    "sg:website":"www.rcs.k12.in.us",
    "wof:name":"Starr Elementary School",
    "wof:placetype":"venue"
},
  "geometry": {"coordinates":[-84.876424,39.834387],"type":"Point"}
}