{
  "type": "Feature",
  "properties": {
    "iso:country":"US",
    "sg:address":"825 N Indiana St",
    "sg:city":"Mooresville",
    "sg:classifiers":[
        {
            "category":"Organizations",
            "subcategory":"Religious Organization",
            "type":"Services"
        }
    ],
    "sg:phone":"+1 317 831 0659",
    "sg:postcode":"46158",
    "sg:province":"IN",
    "sg:tags":[
        "church"
    ],
    "wof:name":"Mooresville Church Of Nazarene",
    "wof:placetype":"venue"
},
  "geometry": {"coordinates":[-86.375041,39.624165],"type":"Point"}
}