{
  "type": "Feature",
  "properties": {
    "iso:country":"US",
    "sg:address":"1605 N 6th St",
    "sg:city":"Vincennes",
    "sg:classifiers":[
        {
            "category":"Cinema",
            "subcategory":"Movie Rental",
            "type":"Entertainment"
        }
    ],
    "sg:phone":"+1 812 895 0711",
    "sg:postcode":"47591",
    "sg:province":"IN",
    "sg:tags":[
        "leasing",
        "video",
        "disc",
        "tape"
    ],
    "wof:name":"Sunstar Video",
    "wof:placetype":"venue"
},
  "geometry": {"coordinates":[-87.5137,38.685059],"type":"Point"}
}