{
  "type": "Feature",
  "properties": {
    "iso:country":"US",
    "sg:address":"4347 W 51st Ave",
    "sg:city":"Griffith",
    "sg:classifiers":[
        {
            "category":"Building & Trades",
            "subcategory":"Construction",
            "type":"Services"
        }
    ],
    "sg:phone":"+1 219 980 4896",
    "sg:postcode":"46319",
    "sg:province":"IN",
    "sg:tags":[
        "hanging",
        "contractor"
    ],
    "wof:name":"Olson Painting Services T",
    "wof:placetype":"venue"
},
  "geometry": {"coordinates":[-87.39125,41.526158],"type":"Point"}
}