{
  "type": "Feature",
  "properties": {
    "iso:country":"US",
    "sg:address":"1215 S Q St",
    "sg:city":"Richmond",
    "sg:classifiers":[
        {
            "category":"Retail",
            "subcategory":"Auto Repair",
            "type":"Services"
        }
    ],
    "sg:phone":"+1 765 966 1502",
    "sg:postcode":"47374",
    "sg:province":"IN",
    "sg:tags":[
        "body",
        "automobile",
        "painting"
    ],
    "wof:name":"Cate's Auto Svc Inc",
    "wof:placetype":"venue"
},
  "geometry": {"coordinates":[-84.88624,39.806845],"type":"Point"}
}