{
  "type": "Feature",
  "properties": {
    "iso:country":"US",
    "sg:address":"506 N Main St",
    "sg:city":"Walton",
    "sg:classifiers":[
        {
            "category":"Restaurant",
            "type":"Food & Drink"
        }
    ],
    "sg:phone":"+1 574 626 2717",
    "sg:postcode":"46994",
    "sg:province":"IN",
    "wof:name":"Dog Shed",
    "wof:placetype":"venue"
},
  "geometry": {"coordinates":[-86.24597799999999,40.665369],"type":"Point"}
}