{
  "type": "Feature",
  "properties": {
    "iso:country":"US",
    "sg:address":"2905 W Bonaire Ave",
    "sg:city":"Muncie",
    "sg:classifiers":[
        {
            "category":"Real Estate",
            "subcategory":"Real Estate Operator",
            "type":"Services"
        }
    ],
    "sg:phone":"+1 765 289 5906",
    "sg:postcode":"47302",
    "sg:province":"IN",
    "sg:tags":[
        "building",
        "apartment"
    ],
    "wof:name":"S&D Rentals",
    "wof:placetype":"venue"
},
  "geometry": {"coordinates":[-85.418269,40.148495],"type":"Point"}
}