{
  "type": "Feature",
  "properties": {
    "iso:country":"US",
    "sg:address":"66540 State Rd 19",
    "sg:city":"Wakarusa",
    "sg:classifiers":[
        {
            "category":"Freight",
            "type":"Transportation"
        }
    ],
    "sg:phone":"+1 574 862 2382",
    "sg:postcode":"46573",
    "sg:province":"IN",
    "sg:tags":[
        "commercial",
        "storage"
    ],
    "wof:name":"Caboose Store & Lock",
    "wof:placetype":"venue"
},
  "geometry": {"coordinates":[-86.00130299999999,41.526161],"type":"Point"}
}