{
  "type": "Feature",
  "properties": {
    "iso:country":"US",
    "sg:address":"13957 Stamper Rd",
    "sg:city":"Moores Hill",
    "sg:classifiers":[
        {
            "category":"Insurance",
            "subcategory":"Insurance Agent",
            "type":"Services"
        }
    ],
    "sg:phone":"+1 812 744 5600",
    "sg:postcode":"47032",
    "sg:province":"IN",
    "wof:name":"AFLAC",
    "wof:placetype":"venue"
},
  "geometry": {"coordinates":[-85.080339,39.104704],"type":"Point"}
}