{
  "type": "Feature",
  "properties": {
    "iso:country":"US",
    "sg:address":"1727 Expo Ln",
    "sg:city":"Indianapolis",
    "sg:classifiers":[
        {
            "category":"Manufacturing",
            "subcategory":"Food",
            "type":"Manufacturing & Wholesale Goods"
        },
        {
            "category":"Food & Beverages",
            "subcategory":"Groceries & Convenience Stores",
            "type":"Retail Goods"
        }
    ],
    "sg:phone":"+1 317 271 0862",
    "sg:postcode":"46214",
    "sg:province":"IN",
    "sg:tags":[
        "processing"
    ],
    "wof:name":"Food Specialties Inc",
    "wof:placetype":"venue"
},
  "geometry": {"coordinates":[-86.30458900000001,39.788043],"type":"Point"}
}