{
  "type": "Feature",
  "properties": {
    "iso:country":"US",
    "sg:address":"209 N Main St",
    "sg:city":"Kokomo",
    "sg:classifiers":[
        {
            "category":"Professional",
            "type":"Services"
        }
    ],
    "sg:phone":"+1 765 454 6509",
    "sg:postcode":"46901",
    "sg:province":"IN",
    "sg:tags":[
        "establishment"
    ],
    "wof:name":"Young Ideas",
    "wof:placetype":"venue"
},
  "geometry": {"coordinates":[-86.131308,40.488269],"type":"Point"}
}