{
  "type": "Feature",
  "properties": {
    "iso:country":"US",
    "sg:address":"56912 Elk Ct",
    "sg:city":"Elkhart",
    "sg:classifiers":[
        {
            "category":"Wholesale",
            "subcategory":"Furniture",
            "type":"Manufacturing & Wholesale Goods"
        }
    ],
    "sg:phone":"+1 574 522 0630",
    "sg:postcode":"46516",
    "sg:province":"IN",
    "sg:tags":[
        "seating",
        "company"
    ],
    "wof:name":"Paul's Seating",
    "wof:placetype":"venue"
},
  "geometry": {"coordinates":[-86.035913,41.669351],"type":"Point"}
}