{
  "type": "Feature",
  "properties": {
    "iso:country":"US",
    "sg:address":"6122 E Lonnis Hill Rd",
    "sg:city":"Madison",
    "sg:classifiers":[
        {
            "category":"Professional",
            "type":"Services"
        }
    ],
    "sg:phone":"+1 812 839 3670",
    "sg:postcode":"47250",
    "sg:province":"IN",
    "sg:tags":[
        "establishment"
    ],
    "wof:name":"Golden Rule Enterprises",
    "wof:placetype":"venue"
},
  "geometry": {"coordinates":[-85.261724,38.839298],"type":"Point"}
}