{
  "type": "Feature",
  "properties": {
    "iso:country":"US",
    "sg:address":"2104 Ekin Ave",
    "sg:city":"New Albany",
    "sg:classifiers":[
        {
            "category":"Real Estate",
            "subcategory":"Real Estate Agent",
            "type":"Services"
        }
    ],
    "sg:phone":"+1 812 944 6207",
    "sg:postcode":"47150",
    "sg:province":"IN",
    "wof:name":"Twin Corp",
    "wof:placetype":"venue"
},
  "geometry": {"coordinates":[-85.80178,38.300693],"type":"Point"}
}