{
  "type": "Feature",
  "properties": {
    "iso:country":"US",
    "sg:address":"3130 Windsor Ct",
    "sg:city":"Elkhart",
    "sg:classifiers":[
        {
            "category":"Shopping",
            "subcategory":"Computers & Home Electronics",
            "type":"Retail Goods"
        }
    ],
    "sg:phone":"+1 574 262 4938",
    "sg:postcode":"46514",
    "sg:province":"IN",
    "sg:tags":[
        "equipment",
        "dealer"
    ],
    "sg:website":"www.pioneercomputer.com",
    "wof:name":"Pioneer Computer Corp",
    "wof:placetype":"venue"
},
  "geometry": {"coordinates":[-85.969549,41.728493],"type":"Point"}
}