{
  "type": "Feature",
  "properties": {
    "iso:country":"US",
    "sg:address":"3901 N Meridian St",
    "sg:city":"Indianapolis",
    "sg:classifiers":[
        {
            "category":"Social Services",
            "type":"Services"
        }
    ],
    "sg:phone":"+1 317 921 1261",
    "sg:postcode":"46208",
    "sg:province":"IN",
    "sg:tags":[
        "organization",
        "welfare"
    ],
    "wof:name":"Bridges To Success",
    "wof:placetype":"venue"
},
  "geometry": {"coordinates":[-86.156863,39.826384],"type":"Point"}
}