{
  "type": "Feature",
  "properties": {
    "iso:country":"US",
    "sg:address":"1347 Marshall St",
    "sg:city":"Gary",
    "sg:classifiers":[
        {
            "category":"Retail",
            "subcategory":"Animal Services",
            "type":"Services"
        }
    ],
    "sg:phone":"+1 219 944 1149",
    "sg:postcode":"46404",
    "sg:province":"IN",
    "sg:tags":[
        "pet",
        "grooming",
        "washing"
    ],
    "wof:name":"Pet's Salon",
    "wof:placetype":"venue"
},
  "geometry": {"coordinates":[-87.370719,41.588754],"type":"Point"}
}