{
  "type": "Feature",
  "properties": {
    "addr:full":"1811 Executive Dr Indianapolis IN 46241",
    "addr:housenumber":"1811",
    "addr:postcode":"46241",
    "addr:street":"Executive Dr",
    "iso:country":"US",
    "sg:address":"1811 Executive Dr",
    "sg:city":"Indianapolis",
    "sg:classifiers":[
        {
            "category":"Real Estate",
            "subcategory":"Real Estate Agent",
            "type":"Services"
        }
    ],
    "sg:phone":"+1 317 481 0870",
    "sg:postcode":"46241",
    "sg:province":"IN",
    "wof:name":"Duke Weeks Realty Corp",
    "wof:placetype":"venue"
},
  "geometry": {"coordinates":[-86.253591,39.739985],"type":"Point"}
}