{
  "type": "Feature",
  "properties": {
    "addr:full":"2563 N 875 W Waynetown IN 47990",
    "addr:housenumber":"2563",
    "addr:postcode":"47990",
    "addr:street":"N 875 W",
    "iso:country":"US",
    "sg:address":"2563 N 875 W",
    "sg:city":"Waynetown",
    "sg:phone":"+1 765 234 2344",
    "sg:postcode":"47990",
    "sg:province":"IN",
    "sg:tags":[
        "farm",
        "grain",
        "cash"
    ],
    "wof:name":"Lightle Farm",
    "wof:placetype":"venue"
},
  "geometry": {"coordinates":[-87.068443,40.076339],"type":"Point"}
}