{
  "type": "Feature",
  "properties": {
    "iso:country":"US",
    "sg:address":"117 S Indiana Ave",
    "sg:city":"Sellersburg",
    "sg:classifiers":[
        {
            "category":"Health Services",
            "subcategory":"Doctor",
            "type":"Services"
        }
    ],
    "sg:phone":"+1 812 246 3395",
    "sg:postcode":"47172",
    "sg:province":"IN",
    "sg:tags":[
        "physician",
        "surgeon"
    ],
    "wof:name":"Community Medical Assoc",
    "wof:placetype":"venue"
},
  "geometry": {"coordinates":[-85.756518,38.398063],"type":"Point"}
}