{
  "type": "Feature",
  "properties": {
    "iso:country":"US",
    "sg:address":"506 N McKinley Ave",
    "sg:city":"Muncie",
    "sg:classifiers":[
        {
            "category":"Professional",
            "subcategory":"Printing & Photocopies",
            "type":"Services"
        }
    ],
    "sg:phone":"+1 765 289 2700",
    "sg:postcode":"47303",
    "sg:province":"IN",
    "sg:tags":[
        "duplicating",
        "copying"
    ],
    "wof:name":"Hiatt Printing",
    "wof:placetype":"venue"
},
  "geometry": {"coordinates":[-85.40771599999999,40.198516],"type":"Point"}
}