{
  "type": "Feature",
  "properties": {
    "iso:country":"US",
    "sg:address":"9114 E Co Rd 150 S",
    "sg:city":"Greensburg",
    "sg:classifiers":[
        {
            "category":"Farming",
            "subcategory":"Farm",
            "type":"Manufacturing & Wholesale Goods"
        }
    ],
    "sg:phone":"+1 812 663 6976",
    "sg:postcode":"47240",
    "sg:province":"IN",
    "sg:tags":[
        "crop",
        "general"
    ],
    "wof:name":"D & S Volk Farming Inc",
    "wof:placetype":"venue"
},
  "geometry": {"coordinates":[-85.31040299999999,39.317291],"type":"Point"}
}