{
  "type": "Feature",
  "properties": {
    "iso:country":"US",
    "sg:address":"140 W Monroe St",
    "sg:city":"Decatur",
    "sg:classifiers":[
        {
            "category":"Organizations",
            "subcategory":"Community Association",
            "type":"Services"
        }
    ],
    "sg:phone":"+1 260 724 3321",
    "sg:postcode":"46733",
    "sg:province":"IN",
    "sg:tags":[
        "fraternal"
    ],
    "wof:name":"Eagles Lodge",
    "wof:placetype":"venue"
},
  "geometry": {"coordinates":[-84.92354400000001,40.831522],"type":"Point"}
}