{
  "type": "Feature",
  "properties": {
    "iso:country":"US",
    "sg:address":"1225 Bedford St",
    "sg:city":"Indianapolis",
    "sg:classifiers":[
        {
            "category":"Wholesale",
            "subcategory":"Construction Materials",
            "type":"Manufacturing & Wholesale Goods"
        }
    ],
    "sg:phone":"+1 317 687 9020",
    "sg:postcode":"46221",
    "sg:province":"IN",
    "sg:tags":[
        "pallet",
        "skid"
    ],
    "wof:name":"A Pallet Co",
    "wof:placetype":"venue"
},
  "geometry": {"coordinates":[-86.203925,39.749339],"type":"Point"}
}