{
  "type": "Feature",
  "properties": {
    "iso:country":"US",
    "sg:address":"52 E South St",
    "sg:city":"Frankfort",
    "sg:classifiers":[
        {
            "category":"Retail",
            "subcategory":"Auto Repair",
            "type":"Services"
        }
    ],
    "sg:phone":"+1 765 654 4564",
    "sg:postcode":"46041",
    "sg:province":"IN",
    "sg:tags":[
        "automotive",
        "general"
    ],
    "wof:name":"A&E Truck & Trailor Service",
    "wof:placetype":"venue"
},
  "geometry": {"coordinates":[-86.511358,40.27795],"type":"Point"}
}