{
  "type": "Feature",
  "properties": {
    "iso:country":"US",
    "sg:address":"3256 Muriel Pl",
    "sg:city":"Columbus",
    "sg:classifiers":[
        {
            "category":"Sports & Exercise",
            "subcategory":"Gym",
            "type":"Entertainment"
        }
    ],
    "sg:phone":"+1 812 378 0703",
    "sg:postcode":"47203",
    "sg:province":"IN",
    "sg:tags":[
        "club",
        "health",
        "studio",
        "gymnasium"
    ],
    "wof:name":"Lord's Personal Training",
    "wof:placetype":"venue"
},
  "geometry": {"coordinates":[-85.903046,39.233765],"type":"Point"}
}