{
  "type": "Feature",
  "properties": {
    "iso:country":"US",
    "sg:address":"5150 Loop Rd",
    "sg:city":"Jeffersonville",
    "sg:classifiers":[
        {
            "category":"Manufacturing",
            "subcategory":"Metals",
            "type":"Manufacturing & Wholesale Goods"
        }
    ],
    "sg:phone":"+1 812 282 4770",
    "sg:postcode":"47130",
    "sg:province":"IN",
    "sg:tags":[
        "steel",
        "processing"
    ],
    "wof:name":"Eagle Steel Products Inc",
    "wof:placetype":"venue"
},
  "geometry": {"coordinates":[-85.67898599999999,38.320544],"type":"Point"}
}