{
  "type": "Feature",
  "properties": {
    "iso:country":"US",
    "sg:address":"2500 Broadway St",
    "sg:city":"Anderson",
    "sg:classifiers":[
        {
            "category":"Food & Beverages",
            "subcategory":"Groceries & Convenience Stores",
            "type":"Retail Goods"
        }
    ],
    "sg:phone":"+1 765 644 9664",
    "sg:postcode":"46012",
    "sg:province":"IN",
    "sg:website":"www.rickers.net",
    "wof:name":"Ricker's Petro Mart",
    "wof:placetype":"venue"
},
  "geometry": {"coordinates":[-85.67652699999999,40.145165],"type":"Point"}
}