{
  "type": "Feature",
  "properties": {
    "iso:country":"US",
    "sg:address":"2105 N Meridian St",
    "sg:city":"Indianapolis",
    "sg:classifiers":[
        {
            "category":"Professional",
            "subcategory":"Business Services",
            "type":"Services"
        }
    ],
    "sg:phone":"+1 317 924 1636",
    "sg:postcode":"46202",
    "sg:province":"IN",
    "sg:tags":[
        "interior",
        "consultant",
        "designer",
        "design",
        "decorator"
    ],
    "wof:name":"Bob Mead Interiors Inc",
    "wof:placetype":"venue"
},
  "geometry": {"coordinates":[-86.157257,39.796046],"type":"Point"}
}