{
  "type": "Feature",
  "properties": {
    "iso:country":"US",
    "sg:address":"5230 Park Emerson Dr",
    "sg:city":"Indianapolis",
    "sg:classifiers":[
        {
            "category":"Building & Trades",
            "subcategory":"Electrical",
            "type":"Services"
        }
    ],
    "sg:phone":"+1 317 881 2239",
    "sg:postcode":"46203",
    "sg:province":"IN",
    "sg:tags":[
        "datum",
        "wiring",
        "contractor"
    ],
    "wof:name":"Future Home Technologies LLC",
    "wof:placetype":"venue"
},
  "geometry": {"coordinates":[-86.079824,39.707671],"type":"Point"}
}