{
  "type": "Feature",
  "properties": {
    "iso:country":"US",
    "sg:address":"401 SE 6th St",
    "sg:city":"Evansville",
    "sg:classifiers":[
        {
            "category":"Health Services",
            "subcategory":"Doctor",
            "type":"Services"
        }
    ],
    "sg:phone":"+1 812 485 5800",
    "sg:postcode":"47713",
    "sg:province":"IN",
    "sg:tags":[
        "physician",
        "surgeon"
    ],
    "wof:name":"Saint Mary's Senior Health Ctr",
    "wof:placetype":"venue"
},
  "geometry": {"coordinates":[-87.56555,37.96848],"type":"Point"}
}