{
  "type": "Feature",
  "properties": {
    "iso:country":"US",
    "sg:address":"4352 S 500 W",
    "sg:city":"Laporte",
    "sg:classifiers":[
        {
            "category":"Building & Trades",
            "subcategory":"Construction",
            "type":"Services"
        }
    ],
    "sg:phone":"+1 219 324 8828",
    "sg:postcode":"46350",
    "sg:province":"IN",
    "sg:tags":[
        "general",
        "contractor"
    ],
    "wof:name":"C R Homes",
    "wof:placetype":"venue"
},
  "geometry": {"coordinates":[-86.798822,41.541421],"type":"Point"}
}