{
  "type": "Feature",
  "properties": {
    "iso:country":"US",
    "sg:address":"2409 N Old Towne Ln",
    "sg:city":"Muncie",
    "sg:classifiers":[
        {
            "category":"Utilities",
            "subcategory":"Telephone",
            "type":"Services"
        }
    ],
    "sg:phone":"+1 765 282 3157",
    "sg:postcode":"47304",
    "sg:province":"IN",
    "sg:tags":[
        "telecommunication"
    ],
    "wof:name":"Phone Guy",
    "wof:placetype":"venue"
},
  "geometry": {"coordinates":[-85.446014,40.212886],"type":"Point"}
}