{
  "type": "Feature",
  "properties": {
    "iso:country":"US",
    "sg:address":"5080 N Co Rd 500 W",
    "sg:city":"Scipio",
    "sg:classifiers":[
        {
            "category":"Shopping",
            "subcategory":"Clothing, Apparel, & Fashions",
            "type":"Retail Goods"
        }
    ],
    "sg:phone":"+1 812 392 2344",
    "sg:postcode":"47273",
    "sg:province":"IN",
    "sg:tags":[
        "customized"
    ],
    "wof:name":"Triple J Sports",
    "wof:placetype":"venue"
},
  "geometry": {"coordinates":[-85.704926,39.060156],"type":"Point"}
}