{
  "type": "Feature",
  "properties": {
    "iso:country":"US",
    "sg:address":"327 W Water St",
    "sg:city":"Bremen",
    "sg:classifiers":[
        {
            "category":"Communications",
            "subcategory":"Film & Video Production",
            "type":"Services"
        }
    ],
    "sg:phone":"+1 574 546 3069",
    "sg:postcode":"46506",
    "sg:province":"IN",
    "sg:tags":[
        "motion"
    ],
    "wof:name":"Bremen Theater",
    "wof:placetype":"venue"
},
  "geometry": {"coordinates":[-86.149846,41.450977],"type":"Point"}
}