{
  "type": "Feature",
  "properties": {
    "iso:country":"US",
    "sg:address":"423 E Main St",
    "sg:city":"Washington",
    "sg:classifiers":[
        {
            "category":"Home & Garden",
            "subcategory":"Furniture",
            "type":"Retail Goods"
        }
    ],
    "sg:phone":"+1 812 254 6532",
    "sg:postcode":"47501",
    "sg:province":"IN",
    "wof:name":"Robert's Furniture & Appliance",
    "wof:placetype":"venue"
},
  "geometry": {"coordinates":[-87.170375,38.656878],"type":"Point"}
}