{
  "type": "Feature",
  "properties": {
    "iso:country":"US",
    "sg:address":"407 Ohio St",
    "sg:city":"La Porte",
    "sg:classifiers":[
        {
            "category":"Professional",
            "subcategory":"Art Services",
            "type":"Services"
        }
    ],
    "sg:phone":"+1 219 324 2271",
    "sg:postcode":"46350",
    "sg:province":"IN",
    "sg:tags":[
        "commercial",
        "design"
    ],
    "wof:name":"Dave Lemelin",
    "wof:placetype":"venue"
},
  "geometry": {"coordinates":[-86.71083299999999,41.610277],"type":"Point"}
}