{
  "type": "Feature",
  "properties": {
    "iso:country":"US",
    "sg:address":"621 S State St",
    "sg:city":"Greenfield",
    "sg:classifiers":[
        {
            "category":"Real Estate",
            "subcategory":"Developer",
            "type":"Services"
        }
    ],
    "sg:phone":"+1 317 477 4387",
    "sg:postcode":"46140",
    "sg:province":"IN",
    "sg:tags":[
        "cemetery"
    ],
    "wof:name":"Greenfield Cemetery",
    "wof:placetype":"venue"
},
  "geometry": {"coordinates":[-85.768288,39.778528],"type":"Point"}
}