{
  "type": "Feature",
  "properties": {
    "addr:full":"65716 State Rd 331 Bremen IN 46506",
    "addr:housenumber":"65716;331",
    "addr:postcode":"46506",
    "addr:street":"State Rd",
    "iso:country":"US",
    "sg:address":"65716 State Rd 331",
    "sg:city":"Bremen",
    "sg:classifiers":[
        {
            "category":"Professional",
            "type":"Services"
        }
    ],
    "sg:phone":"+1 574 633 0141",
    "sg:postcode":"46506",
    "sg:province":"IN",
    "sg:tags":[
        "establishment"
    ],
    "wof:name":"SBA Towers Inc",
    "wof:placetype":"venue"
},
  "geometry": {"coordinates":[-86.172656,41.545952],"type":"Point"}
}