{
  "type": "Feature",
  "properties": {
    "iso:country":"US",
    "sg:address":"600 NE 6th St",
    "sg:city":"Washington",
    "sg:classifiers":[
        {
            "category":"Education",
            "subcategory":"School",
            "type":"Public Place"
        }
    ],
    "sg:phone":"+1 812 254 8363",
    "sg:postcode":"47501",
    "sg:province":"IN",
    "wof:name":"North Elementary School",
    "wof:placetype":"venue"
},
  "geometry": {"coordinates":[-87.169282,38.662839],"type":"Point"}
}