{
  "type": "Feature",
  "properties": {
    "iso:country":"US",
    "sg:address":"596 W Oak St",
    "sg:city":"Campbellsburg",
    "sg:classifiers":[
        {
            "category":"Manufacturing",
            "subcategory":"Chemicals & Compounds",
            "type":"Manufacturing & Wholesale Goods"
        }
    ],
    "sg:phone":"+1 812 755 4501",
    "sg:postcode":"47108",
    "sg:province":"IN",
    "sg:tags":[
        "metal"
    ],
    "sg:website":"www.hawkprecision.com",
    "wof:name":"Hawk Precision Components",
    "wof:placetype":"venue"
},
  "geometry": {"coordinates":[-86.270352,38.651275],"type":"Point"}
}