{
  "type": "Feature",
  "properties": {
    "iso:country":"US",
    "sg:address":"1951 S Elizabeth St",
    "sg:city":"Kokomo",
    "sg:classifiers":[
        {
            "category":"Personal",
            "subcategory":"Beauty Salon",
            "type":"Services"
        }
    ],
    "sg:phone":"+1 765 457 9050",
    "sg:postcode":"46902",
    "sg:province":"IN",
    "wof:name":"Takin' Time For Me",
    "wof:placetype":"venue"
},
  "geometry": {"coordinates":[-86.113561,40.464312],"type":"Point"}
}