{
  "type": "Feature",
  "properties": {
    "iso:country":"US",
    "sg:address":"494 W Plaza Dr",
    "sg:city":"Columbia City",
    "sg:classifiers":[
        {
            "category":"Food & Beverages",
            "subcategory":"Specialty",
            "type":"Retail Goods"
        }
    ],
    "sg:phone":"+1 260 244 5952",
    "sg:postcode":"46725",
    "sg:province":"IN",
    "sg:tags":[
        "health",
        "diet"
    ],
    "wof:name":"GNC",
    "wof:placetype":"venue"
},
  "geometry": {"coordinates":[-85.491692,41.17009],"type":"Point"}
}