{
  "type": "Feature",
  "properties": {
    "addr:full":"3813 S Madison St Muncie IN 47302",
    "addr:housenumber":"3813",
    "addr:postcode":"47302",
    "addr:street":"S Madison St",
    "iso:country":"US",
    "sg:address":"3813 S Madison St",
    "sg:city":"Muncie",
    "sg:classifiers":[
        {
            "category":"Health Services",
            "subcategory":"Health Practitioner",
            "type":"Services"
        }
    ],
    "sg:phone":"+1 765 751 3308",
    "sg:postcode":"47302",
    "sg:province":"IN",
    "sg:tags":[
        "therapist",
        "physical"
    ],
    "wof:name":"Health Strategies",
    "wof:placetype":"venue"
},
  "geometry": {"coordinates":[-85.382047,40.158087],"type":"Point"}
}