{
  "type": "Feature",
  "properties": {
    "addr:full":"11467 S State Road 63 Clinton IN 47842",
    "addr:housenumber":"11467",
    "addr:postcode":"47842",
    "addr:street":"S State Road 63",
    "iso:country":"US",
    "sg:address":"11467 S State Road 63",
    "sg:city":"Clinton",
    "sg:classifiers":[
        {
            "category":"Manufacturing",
            "subcategory":"Chemicals & Compounds",
            "type":"Manufacturing & Wholesale Goods"
        },
        {
            "category":"Utilities",
            "subcategory":"Water",
            "type":"Services"
        },
        {
            "category":"Building & Trades",
            "subcategory":"Plumbing",
            "type":"Services"
        },
        {
            "category":"Home & Garden",
            "subcategory":"Hardware",
            "type":"Retail Goods"
        }
    ],
    "sg:phone":"+1 765 832 3838",
    "sg:postcode":"47842",
    "sg:province":"IN",
    "sg:tags":[
        "companies-bottled",
        "filtration",
        "softening",
        "supply",
        "work",
        "purification",
        "bulk",
        "equipment",
        "conditioning",
        "equipment-service",
        "salt",
        "treatment"
    ],
    "sg:website":"http://www.kennedylacrosse.com",
    "wof:name":"Kennedy's Water Conditioning",
    "wof:placetype":"venue"
},
  "geometry": {"coordinates":[-87.39865899999999,39.714116],"type":"Point"}
}