{
  "type": "Feature",
  "properties": {
    "iso:country":"US",
    "sg:address":"1201 W 1000 N",
    "sg:city":"Decatur",
    "sg:classifiers":[
        {
            "category":"Real Estate",
            "subcategory":"Real Estate Agent",
            "type":"Services"
        }
    ],
    "sg:phone":"+1 260 724 4508",
    "sg:postcode":"46733",
    "sg:province":"IN",
    "sg:tags":[
        "inspection"
    ],
    "wof:name":"JCL Home Improvement",
    "wof:placetype":"venue"
},
  "geometry": {"coordinates":[-84.960116,40.890538],"type":"Point"}
}