{
  "type": "Feature",
  "properties": {
    "iso:country":"US",
    "sg:address":"720 Erie Ave",
    "sg:city":"Logansport",
    "sg:classifiers":[
        {
            "category":"Building & Trades",
            "subcategory":"Construction",
            "type":"Services"
        }
    ],
    "sg:phone":"+1 574 722 6690",
    "sg:postcode":"46947",
    "sg:province":"IN",
    "sg:tags":[
        "general",
        "contractor"
    ],
    "wof:name":"Shepler Construction Inc",
    "wof:placetype":"venue"
},
  "geometry": {"coordinates":[-86.360428,40.75205],"type":"Point"}
}