{
  "type": "Feature",
  "properties": {
    "iso:country":"US",
    "sg:address":"3939 Gray Pond Ct",
    "sg:city":"Indianapolis",
    "sg:classifiers":[
        {
            "category":"Professional",
            "subcategory":"Lawyer & Legal Services",
            "type":"Services"
        }
    ],
    "sg:phone":"+1 317 777 3607",
    "sg:postcode":"46237",
    "sg:province":"IN",
    "sg:tags":[
        "attorney",
        "copyright",
        "patent",
        "practice",
        "trademark",
        "law"
    ],
    "wof:name":"Myers, Michael A",
    "wof:placetype":"venue"
},
  "geometry": {"coordinates":[-86.100516,39.661404],"type":"Point"}
}