{
  "type": "Feature",
  "properties": {
    "iso:country":"US",
    "sg:address":"4331 Winters Rd",
    "sg:city":"Fort Wayne",
    "sg:classifiers":[
        {
            "category":"Professional",
            "type":"Services"
        }
    ],
    "sg:phone":"+1 260 747 7223",
    "sg:postcode":"46809",
    "sg:province":"IN",
    "sg:tags":[
        "establishment"
    ],
    "wof:name":"Baer Field Speedway",
    "wof:placetype":"venue"
},
  "geometry": {"coordinates":[-85.194291,40.973897],"type":"Point"}
}