{
  "type": "Feature",
  "properties": {
    "iso:country":"US",
    "sg:address":"219 N Stockwell Rd",
    "sg:city":"Evansville",
    "sg:classifiers":[
        {
            "category":"Insurance",
            "subcategory":"Insurance Agent",
            "type":"Services"
        }
    ],
    "sg:phone":"+1 812 985 1009",
    "sg:postcode":"47715",
    "sg:province":"IN",
    "sg:tags":[
        "processing"
    ],
    "wof:name":"Health Claim Specialists Inc",
    "wof:placetype":"venue"
},
  "geometry": {"coordinates":[-87.50148,38.001134],"type":"Point"}
}