{
  "type": "Feature",
  "properties": {
    "addr:full":"564 Eastern Blvd Clarksville IN 47129",
    "addr:housenumber":"564",
    "addr:postcode":"47129",
    "addr:street":"Eastern Blvd",
    "iso:country":"US",
    "sg:address":"564 Eastern Blvd",
    "sg:city":"Clarksville",
    "sg:classifiers":[
        {
            "category":"Restaurant",
            "type":"Food & Drink"
        }
    ],
    "sg:phone":"+1 812 282 4673",
    "sg:postcode":"47129",
    "sg:province":"IN",
    "wof:name":"Hungry Pelican",
    "wof:placetype":"venue"
},
  "geometry": {"coordinates":[-85.760784,38.298058],"type":"Point"}
}