{
  "type": "Feature",
  "properties": {
    "addr:full":"13141 West Rd Westfield IN 46074",
    "addr:housenumber":"13141",
    "addr:postcode":"46074",
    "addr:street":"West Rd",
    "iso:country":"US",
    "sg:address":"13141 West Rd",
    "sg:city":"Westfield",
    "sg:classifiers":[
        {
            "category":"Manufacturing",
            "subcategory":"Tools & Machinery",
            "type":"Manufacturing & Wholesale Goods"
        },
        {
            "category":"Industrial Area",
            "type":"Public Place"
        }
    ],
    "sg:phone":"+1 317 758 6200",
    "sg:postcode":"46074",
    "sg:province":"IN",
    "sg:tags":[
        "repair",
        "equipment-repairing",
        "machinery-rebuild"
    ],
    "wof:name":"Pontius Equipment Repair",
    "wof:placetype":"venue"
},
  "geometry": {"coordinates":[-86.23566599999999,39.977721],"type":"Point"}
}