{
  "type": "Feature",
  "properties": {
    "iso:country":"US",
    "sg:address":"9699 W State Rte 662",
    "sg:city":"Newburgh",
    "sg:classifiers":[
        {
            "category":"Building & Trades",
            "subcategory":"Landscaping Services",
            "type":"Services"
        }
    ],
    "sg:phone":"+1 812 853 5947",
    "sg:postcode":"47630",
    "sg:province":"IN",
    "sg:tags":[
        "tree"
    ],
    "wof:name":"Busy Beaver Stump Removal",
    "wof:placetype":"venue"
},
  "geometry": {"coordinates":[-87.427313,37.951225],"type":"Point"}
}