{
  "type": "Feature",
  "properties": {
    "iso:country":"US",
    "sg:address":"19615 Kern Rd",
    "sg:city":"South Bend",
    "sg:classifiers":[
        {
            "category":"Retail",
            "subcategory":"Repair Shop",
            "type":"Services"
        }
    ],
    "sg:phone":"+1 574 291 6001",
    "sg:postcode":"46614",
    "sg:province":"IN",
    "sg:tags":[
        "upholsterer"
    ],
    "wof:name":"Thompson Upholstery",
    "wof:placetype":"venue"
},
  "geometry": {"coordinates":[-86.247756,41.608202],"type":"Point"}
}