{
  "type": "Feature",
  "properties": {
    "iso:country":"US",
    "sg:address":"8553 State Rd 144",
    "sg:city":"Mooresville",
    "sg:classifiers":[
        {
            "category":"Wholesale",
            "subcategory":"Construction Materials",
            "type":"Manufacturing & Wholesale Goods"
        }
    ],
    "sg:phone":"+1 317 831 2203",
    "sg:postcode":"46158",
    "sg:province":"IN",
    "sg:tags":[
        "sand",
        "gravel"
    ],
    "wof:name":"Beaver Materials",
    "wof:placetype":"venue"
},
  "geometry": {"coordinates":[-86.259817,39.56744],"type":"Point"}
}