{
  "type": "Feature",
  "properties": {
    "iso:country":"US",
    "sg:address":"8307 N Co Rd 900 W",
    "sg:city":"Greensburg",
    "sg:classifiers":[
        {
            "category":"Farming",
            "subcategory":"Livestock Farm",
            "type":"Manufacturing & Wholesale Goods"
        }
    ],
    "sg:phone":"+1 812 591 3922",
    "sg:postcode":"47240",
    "sg:province":"IN",
    "sg:tags":[
        "beef",
        "feedlot",
        "cattle"
    ],
    "wof:name":"Paul Wenning",
    "wof:placetype":"venue"
},
  "geometry": {"coordinates":[-85.415863,39.204866],"type":"Point"}
}