{
  "type": "Feature",
  "properties": {
    "iso:country":"US",
    "sg:address":"801 Southfield Dr",
    "sg:city":"Plainfield",
    "sg:classifiers":[
        {
            "category":"Food & Beverages",
            "subcategory":"Groceries & Convenience Stores",
            "type":"Retail Goods"
        }
    ],
    "sg:phone":"+1 317 838 3847",
    "sg:postcode":"46168",
    "sg:province":"IN",
    "wof:name":"Village Pantry",
    "wof:placetype":"venue"
},
  "geometry": {"coordinates":[-86.372383,39.693669],"type":"Point"}
}