{
  "type": "Feature",
  "properties": {
    "iso:country":"US",
    "sg:address":"5601 Progress Rd",
    "sg:city":"Indianapolis",
    "sg:classifiers":[
        {
            "category":"Building & Trades",
            "subcategory":"Cleaning & Sanitation",
            "type":"Services"
        }
    ],
    "sg:phone":"+1 317 284 0377",
    "sg:postcode":"46241",
    "sg:province":"IN",
    "sg:tags":[
        "control",
        "hazardous",
        "material",
        "removal"
    ],
    "wof:name":"Summit Environmental Services Inc",
    "wof:placetype":"venue"
},
  "geometry": {"coordinates":[-86.25726400000001,39.741171],"type":"Point"}
}