{
  "type": "Feature",
  "properties": {
    "iso:country":"US",
    "sg:address":"23734 Co Rd 32",
    "sg:city":"Goshen",
    "sg:classifiers":[
        {
            "category":"Farming",
            "subcategory":"Dairy Farm",
            "type":"Manufacturing & Wholesale Goods"
        }
    ],
    "sg:phone":"+1 574 875 8178",
    "sg:postcode":"46526",
    "sg:province":"IN",
    "wof:name":"Timothy Witmer",
    "wof:placetype":"venue"
},
  "geometry": {"coordinates":[-85.919979,41.580156],"type":"Point"}
}