{
  "type": "Feature",
  "properties": {
    "iso:country":"US",
    "sg:address":"120 Lincolnway E",
    "sg:city":"Osceola",
    "sg:classifiers":[
        {
            "category":"Autos & Motor Vehicles",
            "subcategory":"Automobile Sales",
            "type":"Retail Goods"
        }
    ],
    "sg:phone":"+1 574 679 4385",
    "sg:postcode":"46561",
    "sg:province":"IN",
    "sg:tags":[
        "car",
        "dealer"
    ],
    "wof:name":"Instant Auto Finance",
    "wof:placetype":"venue"
},
  "geometry": {"coordinates":[-86.06964499999999,41.66323],"type":"Point"}
}