{
  "type": "Feature",
  "properties": {
    "iso:country":"US",
    "sg:address":"214 E Brown St",
    "sg:city":"Knightstown",
    "sg:classifiers":[
        {
            "category":"Organizations",
            "subcategory":"Religious Organization",
            "type":"Services"
        }
    ],
    "sg:phone":"+1 765 345 2371",
    "sg:postcode":"46148",
    "sg:province":"IN",
    "sg:tags":[
        "church"
    ],
    "wof:name":"Knightstown Friends Church",
    "wof:placetype":"venue"
},
  "geometry": {"coordinates":[-85.524464,39.796747],"type":"Point"}
}