{
  "type": "Feature",
  "properties": {
    "iso:country":"US",
    "sg:address":"202 W High St",
    "sg:city":"Mooresville",
    "sg:classifiers":[
        {
            "category":"Professional",
            "subcategory":"Lawyer & Legal Services",
            "type":"Services"
        }
    ],
    "sg:phone":"+1 317 831 6606",
    "sg:postcode":"46158",
    "sg:province":"IN",
    "sg:tags":[
        "attorney"
    ],
    "wof:name":"Siddons Law Office",
    "wof:placetype":"venue"
},
  "geometry": {"coordinates":[-86.37974,39.610442],"type":"Point"}
}