{
  "type": "Feature",
  "properties": {
    "iso:country":"US",
    "sg:address":"2800 N Granville Ave",
    "sg:city":"Muncie",
    "sg:classifiers":[
        {
            "category":"Retail",
            "subcategory":"Auto Repair",
            "type":"Services"
        }
    ],
    "sg:phone":"+1 765 288 9815",
    "sg:postcode":"47303",
    "sg:province":"IN",
    "sg:tags":[
        "body",
        "automobile",
        "painting"
    ],
    "wof:name":"Chuck Murray's Auto Body Shop",
    "wof:placetype":"venue"
},
  "geometry": {"coordinates":[-85.376727,40.215931],"type":"Point"}
}