{
  "type": "Feature",
  "properties": {
    "iso:country":"US",
    "sg:address":"7708 Hohman Ave",
    "sg:city":"Munster",
    "sg:classifiers":[
        {
            "category":"Professional",
            "subcategory":"Accounting & Tax Preparation",
            "type":"Services"
        }
    ],
    "sg:phone":"+1 219 836 2388",
    "sg:postcode":"46321",
    "sg:province":"IN",
    "sg:tags":[
        "accountant"
    ],
    "wof:name":"Devries R W & Assoc",
    "wof:placetype":"venue"
},
  "geometry": {"coordinates":[-87.522499,41.5737],"type":"Point"}
}