{
  "type": "Feature",
  "properties": {
    "addr:full":"5603 W Raymond St Indianapolis IN 46241",
    "addr:housenumber":"5603",
    "addr:postcode":"46241",
    "addr:street":"W Raymond St",
    "iso:country":"US",
    "sg:address":"5603 W Raymond St",
    "sg:city":"Indianapolis",
    "sg:classifiers":[
        {
            "category":"Manufacturing",
            "subcategory":"Printing",
            "type":"Manufacturing & Wholesale Goods"
        }
    ],
    "sg:phone":"+1 317 484 8000",
    "sg:postcode":"46241",
    "sg:province":"IN",
    "sg:tags":[
        "commercial"
    ],
    "wof:name":"Moore Langen Printing Co",
    "wof:placetype":"venue"
},
  "geometry": {"coordinates":[-86.254868,39.735748],"type":"Point"}
}