{
  "type": "Feature",
  "properties": {
    "iso:country":"US",
    "sg:address":"112 W Main Cross St",
    "sg:city":"Edinburgh",
    "sg:classifiers":[
        {
            "category":"Health Services",
            "subcategory":"Chiropractor",
            "type":"Services"
        }
    ],
    "sg:phone":"+1 812 526 0797",
    "sg:postcode":"46124",
    "sg:province":"IN",
    "wof:name":"Total Family Chiropractic",
    "wof:placetype":"venue"
},
  "geometry": {"coordinates":[-85.967029,39.354365],"type":"Point"}
}