{
  "type": "Feature",
  "properties": {
    "iso:country":"US",
    "sg:address":"2626 E Jefferson St",
    "sg:city":"Warsaw",
    "sg:classifiers":[
        {
            "category":"Personal",
            "subcategory":"Beauty Salon",
            "type":"Services"
        }
    ],
    "sg:phone":"+1 574 269 4957",
    "sg:postcode":"46580",
    "sg:province":"IN",
    "wof:name":"Think Young Styling Studio",
    "wof:placetype":"venue"
},
  "geometry": {"coordinates":[-85.82121,41.23599],"type":"Point"}
}