{
  "type": "Feature",
  "properties": {
    "iso:country":"US",
    "sg:address":"7971 Calumet Ave",
    "sg:city":"Munster",
    "sg:classifiers":[
        {
            "category":"Shopping",
            "subcategory":"Computers & Home Electronics",
            "type":"Retail Goods"
        }
    ],
    "sg:phone":"+1 219 836 6059",
    "sg:postcode":"46321",
    "sg:province":"IN",
    "sg:tags":[
        "equipment",
        "video"
    ],
    "sg:website":"www.ebgames.com",
    "wof:name":"Eb Games",
    "wof:placetype":"venue"
},
  "geometry": {"coordinates":[-87.508771,41.56825],"type":"Point"}
}