{
  "type": "Feature",
  "properties": {
    "iso:country":"US",
    "sg:address":"235 Pearl St",
    "sg:city":"Fort Wayne",
    "sg:classifiers":[
        {
            "category":"Real Estate",
            "subcategory":"Real Estate Agent",
            "type":"Services"
        }
    ],
    "sg:phone":"+1 260 426 3016",
    "sg:postcode":"46802",
    "sg:province":"IN",
    "wof:name":"John F Popp & Assoc",
    "wof:placetype":"venue"
},
  "geometry": {"coordinates":[-85.143692,41.080234],"type":"Point"}
}