{
  "type": "Feature",
  "properties": {
    "iso:country":"US",
    "sg:address":"24 Saratoga Dr",
    "sg:city":"Batesville",
    "sg:classifiers":[
        {
            "category":"Home & Garden",
            "subcategory":"Home Furnishings",
            "type":"Retail Goods"
        }
    ],
    "sg:phone":"+1 812 932 3264",
    "sg:postcode":"47006",
    "sg:province":"IN",
    "sg:tags":[
        "quilting"
    ],
    "wof:name":"Kleidoscope Quilting",
    "wof:placetype":"venue"
},
  "geometry": {"coordinates":[-85.212861,39.312192],"type":"Point"}
}