{
  "type": "Feature",
  "properties": {
    "iso:country":"US",
    "sg:address":"320 Chicago Ave",
    "sg:city":"Goshen",
    "sg:classifiers":[
        {
            "category":"Real Estate",
            "subcategory":"Real Estate Services",
            "type":"Services"
        }
    ],
    "sg:phone":"+1 574 533 9409",
    "sg:postcode":"46528",
    "sg:province":"IN",
    "sg:tags":[
        "company",
        "title"
    ],
    "wof:name":"Century Title Svc",
    "wof:placetype":"venue"
},
  "geometry": {"coordinates":[-85.842943,41.589421],"type":"Point"}
}