{
  "type": "Feature",
  "properties": {
    "iso:country":"US",
    "sg:address":"5853 N Sherman Ave",
    "sg:city":"Indianapolis",
    "sg:classifiers":[
        {
            "category":"Professional",
            "subcategory":"Business Services",
            "type":"Services"
        }
    ],
    "sg:phone":"+1 317 257 2286",
    "sg:postcode":"46220",
    "sg:province":"IN",
    "sg:tags":[
        "interior",
        "consultant",
        "design",
        "decorator"
    ],
    "wof:name":"Company I Keep",
    "wof:placetype":"venue"
},
  "geometry": {"coordinates":[-86.103531,39.862084],"type":"Point"}
}