{
  "type": "Feature",
  "properties": {
    "iso:country":"US",
    "sg:address":"2740 Charlestown Rd",
    "sg:city":"New Albany",
    "sg:classifiers":[
        {
            "category":"Restaurant",
            "type":"Food & Drink"
        }
    ],
    "sg:phone":"+1 812 944 6845",
    "sg:postcode":"47150",
    "sg:province":"IN",
    "sg:tags":[
        "parlor",
        "ice",
        "cream"
    ],
    "wof:name":"Zesto",
    "wof:placetype":"venue"
},
  "geometry": {"coordinates":[-85.801575,38.323333],"type":"Point"}
}