{
  "type": "Feature",
  "properties": {
    "iso:country":"US",
    "sg:address":"112 E 5th St",
    "sg:city":"Connersville",
    "sg:classifiers":[
        {
            "category":"Manufacturing",
            "subcategory":"Tobacco Products",
            "type":"Manufacturing & Wholesale Goods"
        }
    ],
    "sg:phone":"+1 765 825 3213",
    "sg:postcode":"47331",
    "sg:province":"IN",
    "sg:tags":[
        "cigar",
        "mfg"
    ],
    "wof:name":"Mecca Cigar Store",
    "wof:placetype":"venue"
},
  "geometry": {"coordinates":[-85.13921,39.641344],"type":"Point"}
}