{
  "type": "Feature",
  "properties": {
    "iso:country":"US",
    "sg:address":"7606 Broadway",
    "sg:city":"Merrillville",
    "sg:classifiers":[
        {
            "category":"Retail",
            "subcategory":"Laundry & Dry Cleaning",
            "type":"Services"
        }
    ],
    "sg:phone":"+1 219 769 7171",
    "sg:postcode":"46410",
    "sg:province":"IN",
    "sg:tags":[
        "cleaners"
    ],
    "wof:name":"Merri-Kleen",
    "wof:placetype":"venue"
},
  "geometry": {"coordinates":[-87.336075,41.480477],"type":"Point"}
}