{
  "type": "Feature",
  "properties": {
    "iso:country":"US",
    "sg:address":"401 E Indiana St",
    "sg:city":"Evansville",
    "sg:classifiers":[
        {
            "category":"Communications",
            "subcategory":"Film & Video Production",
            "type":"Services"
        }
    ],
    "sg:phone":"+1 812 423 6088",
    "sg:postcode":"47711",
    "sg:province":"IN",
    "sg:tags":[
        "audio"
    ],
    "wof:name":"Magnetic Image Video",
    "wof:placetype":"venue"
},
  "geometry": {"coordinates":[-87.557816,37.978214],"type":"Point"}
}