{
  "type": "Feature",
  "properties": {
    "iso:country":"US",
    "sg:address":"7720 S 775 E",
    "sg:city":"Zionsville",
    "sg:classifiers":[
        {
            "category":"Personal",
            "type":"Services"
        }
    ],
    "sg:phone":"+1 317 873 9636",
    "sg:postcode":"46077",
    "sg:province":"IN",
    "sg:tags":[
        "therapist",
        "massage"
    ],
    "wof:name":"Morning Dove Therapeutic",
    "wof:placetype":"venue"
},
  "geometry": {"coordinates":[-86.321485,39.928809],"type":"Point"}
}