{
  "type": "Feature",
  "properties": {
    "addr:full":"59 N Plank St Rossville IN 46065",
    "addr:housenumber":"59",
    "addr:postcode":"46065",
    "addr:street":"N Plank St",
    "iso:country":"US",
    "sg:address":"59 N Plank St",
    "sg:city":"Rossville",
    "sg:classifiers":[
        {
            "category":"Education",
            "subcategory":"School",
            "type":"Public Place"
        }
    ],
    "sg:phone":"+1 765 379 2518",
    "sg:postcode":"46065",
    "sg:province":"IN",
    "wof:name":"New Hope School Inc",
    "wof:placetype":"venue"
},
  "geometry": {"coordinates":[-86.594888,40.417326],"type":"Point"}
}