{
  "type": "Feature",
  "properties": {
    "iso:country":"US",
    "sg:address":"315 W Jackson St",
    "sg:city":"Shelbyville",
    "sg:classifiers":[
        {
            "category":"Organizations",
            "subcategory":"Non-profit Organization",
            "type":"Services"
        }
    ],
    "sg:phone":"+1 317 398 4567",
    "sg:postcode":"46176",
    "sg:province":"IN",
    "sg:tags":[
        "alternative",
        "abortion"
    ],
    "wof:name":"Hope's Door Pregnancy Resource",
    "wof:placetype":"venue"
},
  "geometry": {"coordinates":[-85.783816,39.523635],"type":"Point"}
}