{
  "type": "Feature",
  "properties": {
    "iso:country":"US",
    "sg:address":"4622 N Broadway Ave",
    "sg:city":"Muncie",
    "sg:classifiers":[
        {
            "category":"Organizations",
            "subcategory":"Religious Organization",
            "type":"Services"
        }
    ],
    "sg:phone":"+1 765 288 8383",
    "sg:postcode":"47303",
    "sg:province":"IN",
    "sg:tags":[
        "church"
    ],
    "sg:website":"www.unionchapel.com",
    "wof:name":"Union Chapel United Methodist",
    "wof:placetype":"venue"
},
  "geometry": {"coordinates":[-85.365111,40.22892],"type":"Point"}
}