{
  "type": "Feature",
  "properties": {
    "iso:country":"US",
    "sg:address":"301 B St",
    "sg:city":"La Porte",
    "sg:classifiers":[
        {
            "category":"Organizations",
            "subcategory":"Community Association",
            "type":"Services"
        }
    ],
    "sg:phone":"+1 219 362 3894",
    "sg:postcode":"46350",
    "sg:province":"IN",
    "wof:name":"Foe 2439",
    "wof:placetype":"venue"
},
  "geometry": {"coordinates":[-86.720451,41.604694],"type":"Point"}
}