{
  "type": "Feature",
  "properties": {
    "addr:full":"202 E Washington St Mooresville IN 46158",
    "addr:housenumber":"202",
    "addr:postcode":"46158",
    "addr:street":"E Washington St",
    "iso:country":"US",
    "sg:address":"202 E Washington St",
    "sg:city":"Mooresville",
    "sg:classifiers":[
        {
            "category":"Professional",
            "subcategory":"Lawyer & Legal Services",
            "type":"Services"
        }
    ],
    "sg:phone":"+1 317 831 9109",
    "sg:postcode":"46158",
    "sg:province":"IN",
    "sg:tags":[
        "attorney"
    ],
    "wof:name":"Susan J Leib Law Office",
    "wof:placetype":"venue"
},
  "geometry": {"coordinates":[-86.369767,39.613942],"type":"Point"}
}