{
  "type": "Feature",
  "properties": {
    "iso:country":"US",
    "sg:address":"409 Church Dr",
    "sg:city":"Anderson",
    "sg:classifiers":[
        {
            "category":"Autos & Motor Vehicles",
            "subcategory":"Auto Supplies",
            "type":"Retail Goods"
        }
    ],
    "sg:phone":"+1 765 642 9933",
    "sg:postcode":"46016",
    "sg:province":"IN",
    "sg:tags":[
        "automobile",
        "parts"
    ],
    "sg:website":"www.gwpierce.com",
    "wof:name":"G W Pierce Auto Parts Co",
    "wof:placetype":"venue"
},
  "geometry": {"coordinates":[-85.640092,40.087804],"type":"Point"}
}