{
  "type": "Feature",
  "properties": {
    "iso:country":"US",
    "sg:address":"61 Ridgeway Dr",
    "sg:city":"Brownsburg",
    "sg:classifiers":[
        {
            "category":"Professional",
            "subcategory":"Management & Consulting",
            "type":"Services"
        }
    ],
    "sg:phone":"+1 317 852 3291",
    "sg:postcode":"46112",
    "sg:province":"IN",
    "wof:name":"Tucker Group LLC",
    "wof:placetype":"venue"
},
  "geometry": {"coordinates":[-86.400918,39.852848],"type":"Point"}
}