{
  "type": "Feature",
  "properties": {
    "addr:full":"3708 Commercial Dr Indianapolis IN 46222",
    "addr:housenumber":"3708",
    "addr:postcode":"46222",
    "addr:street":"Commercial Dr",
    "iso:country":"US",
    "sg:address":"3708 Commercial Dr",
    "sg:city":"Indianapolis",
    "sg:classifiers":[
        {
            "category":"Manufacturing",
            "subcategory":"Textiles",
            "type":"Manufacturing & Wholesale Goods"
        },
        {
            "category":"Building & Trades",
            "subcategory":"Construction",
            "type":"Services"
        },
        {
            "category":"Manufacturing",
            "subcategory":"Building Materials",
            "type":"Manufacturing & Wholesale Goods"
        },
        {
            "category":"Home & Garden",
            "subcategory":"Carpets & Floor Coverings",
            "type":"Retail Goods"
        }
    ],
    "sg:phone":"+1 317 329 0400",
    "sg:postcode":"46222",
    "sg:province":"IN",
    "sg:tags":[
        "materials-wholesale",
        "rug",
        "tile-contractors",
        "tile-wholesale",
        "linoleum",
        "manufacturer"
    ],
    "wof:name":"Tile Mart",
    "wof:placetype":"venue"
},
  "geometry": {"coordinates":[-86.228448,39.820972],"type":"Point"}
}