{
  "type": "Feature",
  "properties": {
    "iso:country":"US",
    "sg:address":"533 Henry St",
    "sg:city":"Huntington",
    "sg:classifiers":[
        {
            "category":"Professional",
            "subcategory":"Management & Consulting",
            "type":"Services"
        }
    ],
    "sg:phone":"+1 260 356 6092",
    "sg:postcode":"46750",
    "sg:province":"IN",
    "sg:tags":[
        "consultant",
        "business"
    ],
    "wof:name":"Huntington Quality Assoc",
    "wof:placetype":"venue"
},
  "geometry": {"coordinates":[-85.492839,40.876926],"type":"Point"}
}