{
  "type": "Feature",
  "properties": {
    "iso:country":"US",
    "sg:address":"5056 Milton St",
    "sg:city":"Coatesville",
    "sg:classifiers":[
        {
            "category":"Home & Garden",
            "subcategory":"Building Materials",
            "type":"Retail Goods"
        }
    ],
    "sg:phone":"+1 765 386 2500",
    "sg:postcode":"46121",
    "sg:province":"IN",
    "wof:name":"Saw Mill Pride LLC",
    "wof:placetype":"venue"
},
  "geometry": {"coordinates":[-86.669948,39.687389],"type":"Point"}
}