{
  "type": "Feature",
  "properties": {
    "iso:country":"US",
    "sg:address":"4855 State Route 261",
    "sg:city":"Newburgh",
    "sg:classifiers":[
        {
            "category":"Health Services",
            "subcategory":"Doctor",
            "type":"Services"
        }
    ],
    "sg:phone":"+1 812 853 6168",
    "sg:postcode":"47630",
    "sg:province":"IN",
    "sg:tags":[
        "surgeon",
        "oral"
    ],
    "sg:website":"www.advancedoralsurg.com",
    "wof:name":"Rodgers Steven F DDS",
    "wof:placetype":"venue"
},
  "geometry": {"coordinates":[-87.398003,37.964199],"type":"Point"}
}