{
  "type": "Feature",
  "properties": {
    "iso:country":"US",
    "sg:address":"8433 Sycamore Dr",
    "sg:city":"Newburgh",
    "sg:classifiers":[
        {
            "category":"Arts & Performance",
            "subcategory":"Theater",
            "type":"Entertainment"
        }
    ],
    "sg:phone":"+1 812 490 4351",
    "sg:postcode":"47630",
    "sg:province":"IN",
    "sg:tags":[
        "live",
        "music"
    ],
    "wof:name":"On The Mike Productions",
    "wof:placetype":"venue"
},
  "geometry": {"coordinates":[-87.400238,37.966128],"type":"Point"}
}