{
  "type": "Feature",
  "properties": {
    "iso:country":"US",
    "sg:address":"5950 W US Hwy 36",
    "sg:city":"Greencastle",
    "sg:classifiers":[
        {
            "category":"Wholesale",
            "subcategory":"Farm Supplies",
            "type":"Manufacturing & Wholesale Goods"
        }
    ],
    "sg:phone":"+1 765 739 6651",
    "sg:postcode":"46135",
    "sg:province":"IN",
    "sg:tags":[
        "feed"
    ],
    "wof:name":"Kountry Feeds Inc",
    "wof:placetype":"venue"
},
  "geometry": {"coordinates":[-86.93934299999999,39.763001],"type":"Point"}
}