{
  "type": "Feature",
  "properties": {
    "iso:country":"US",
    "sg:address":"16128 Haddam Ln",
    "sg:city":"Noblesville",
    "sg:classifiers":[
        {
            "category":"Building & Trades",
            "subcategory":"Construction",
            "type":"Services"
        }
    ],
    "sg:phone":"+1 317 867 3331",
    "sg:postcode":"46062",
    "sg:province":"IN",
    "sg:tags":[
        "home",
        "builder"
    ],
    "wof:name":"Lee Custom Homes",
    "wof:placetype":"venue"
},
  "geometry": {"coordinates":[-86.097719,40.02482],"type":"Point"}
}