{
  "type": "Feature",
  "properties": {
    "addr:full":"2700 N Wheeling Ave Muncie IN 47303",
    "addr:housenumber":"2700",
    "addr:postcode":"47303",
    "addr:street":"N Wheeling Ave",
    "iso:country":"US",
    "sg:address":"2700 N Wheeling Ave",
    "sg:city":"Muncie",
    "sg:classifiers":[
        {
            "category":"Insurance",
            "subcategory":"Insurance Agent",
            "type":"Services"
        }
    ],
    "sg:phone":"+1 765 286 9962",
    "sg:postcode":"47303",
    "sg:province":"IN",
    "wof:name":"Brights Insurance",
    "wof:placetype":"venue"
},
  "geometry": {"coordinates":[-85.401037,40.216142],"type":"Point"}
}