{
  "type": "Feature",
  "properties": {
    "iso:country":"US",
    "sg:address":"967 W McClain St",
    "sg:city":"Scottsburg",
    "sg:classifiers":[
        {
            "category":"Real Estate",
            "subcategory":"Real Estate Agent",
            "type":"Services"
        }
    ],
    "sg:phone":"+1 812 752 2255",
    "sg:postcode":"47170",
    "sg:province":"IN",
    "wof:name":"Remax Hometown Professionals",
    "wof:placetype":"venue"
},
  "geometry": {"coordinates":[-85.781332,38.685529],"type":"Point"}
}