{
  "type": "Feature",
  "properties": {
    "iso:country":"US",
    "sg:address":"1231 W Plymouth St",
    "sg:city":"Bremen",
    "sg:classifiers":[
        {
            "category":"Autos & Motor Vehicles",
            "subcategory":"Auto Supplies",
            "type":"Retail Goods"
        }
    ],
    "sg:phone":"+1 574 546 5356",
    "sg:postcode":"46506",
    "sg:province":"IN",
    "sg:tags":[
        "automobile",
        "parts"
    ],
    "wof:name":"Bremen Carquest Auto Parts",
    "wof:placetype":"venue"
},
  "geometry": {"coordinates":[-86.16137500000001,41.4465],"type":"Point"}
}