{
  "type": "Feature",
  "properties": {
    "iso:country":"US",
    "sg:address":"2000 N 19th St",
    "sg:city":"Terre Haute",
    "sg:classifiers":[
        {
            "category":"Building & Trades",
            "subcategory":"Cleaning & Sanitation",
            "type":"Services"
        }
    ],
    "sg:phone":"+1 812 238 1757",
    "sg:postcode":"47804",
    "sg:province":"IN",
    "sg:tags":[
        "filter"
    ],
    "wof:name":"R & A Sales & Svc Corp",
    "wof:placetype":"venue"
},
  "geometry": {"coordinates":[-87.388483,39.489938],"type":"Point"}
}