{
  "type": "Feature",
  "properties": {
    "addr:full":"1601 S 7th St Terre Haute IN 47802",
    "addr:housenumber":"1601",
    "addr:postcode":"47802",
    "addr:street":"S 7Th St",
    "iso:country":"US",
    "sg:address":"1601 S 7th St",
    "sg:city":"Terre Haute",
    "sg:classifiers":[
        {
            "category":"Insurance",
            "subcategory":"Insurance Agent",
            "type":"Services"
        }
    ],
    "sg:phone":"+1 812 238 9913",
    "sg:postcode":"47802",
    "sg:province":"IN",
    "wof:name":"Gene Jarvis Insurance",
    "wof:placetype":"venue"
},
  "geometry": {"coordinates":[-87.40691700000001,39.448254],"type":"Point"}
}