{
  "type": "Feature",
  "properties": {
    "iso:country":"US",
    "sg:address":"7510 Rosegate Dr Indianapolis",
    "sg:city":"Indianapolis",
    "sg:classifiers":[
        {
            "category":"Social Services",
            "subcategory":"Job Training",
            "type":"Services"
        },
        {
            "category":"Health Services",
            "subcategory":"Nursing And Care Facility",
            "type":"Services"
        },
        {
            "category":"Social Services",
            "subcategory":"Retirement Home",
            "type":"Services"
        },
        {
            "category":"Health Services",
            "subcategory":"Clinic",
            "type":"Services"
        }
    ],
    "sg:phone":"+1 317 215 5043",
    "sg:postcode":"46237",
    "sg:province":"IN",
    "sg:tags":[
        "living",
        "homes-skilled",
        "people",
        "assisted",
        "homes-elderly",
        "rehabilitation"
    ],
    "sg:website":"http://americansrcommunities.com/rsg/",
    "wof:name":"Rosegate Village",
    "wof:placetype":"venue"
},
  "geometry": {"coordinates":[-86.080915,39.658102],"type":"Point"}
}