{
  "type": "Feature",
  "properties": {
    "addr:full":"423 S Nebraska St Marion IN 46953",
    "addr:housenumber":"423",
    "addr:postcode":"46953",
    "addr:street":"S Nebraska St",
    "iso:country":"US",
    "sg:address":"423 S Nebraska St",
    "sg:city":"Marion",
    "sg:classifiers":[
        {
            "category":"Retail",
            "subcategory":"Auto Repair",
            "type":"Services"
        }
    ],
    "sg:phone":"+1 765 662 3022",
    "sg:postcode":"46953",
    "sg:province":"IN",
    "sg:tags":[
        "muffler",
        "exhaust",
        "system"
    ],
    "wof:name":"Brown's Muffler Ctr",
    "wof:placetype":"venue"
},
  "geometry": {"coordinates":[-85.663273,40.557139],"type":"Point"}
}