{
  "type": "Feature",
  "properties": {
    "iso:country":"US",
    "sg:address":"125 N Van Rensselaer St",
    "sg:city":"Rensselaer",
    "sg:classifiers":[
        {
            "category":"Manufacturing",
            "subcategory":"Printing",
            "type":"Manufacturing & Wholesale Goods"
        }
    ],
    "sg:phone":"+1 219 866 5913",
    "sg:postcode":"47978",
    "sg:province":"IN",
    "sg:tags":[
        "commercial"
    ],
    "sg:website":"www.printing-by-campbell.com",
    "wof:name":"Campbell Printing Co",
    "wof:placetype":"venue"
},
  "geometry": {"coordinates":[-87.152385,40.936675],"type":"Point"}
}