{
  "type": "Feature",
  "properties": {
    "iso:country":"US",
    "sg:address":"2830 S Main St",
    "sg:city":"Elkhart",
    "sg:classifiers":[
        {
            "category":"Autos & Motor Vehicles",
            "subcategory":"Auto Supplies",
            "type":"Retail Goods"
        }
    ],
    "sg:phone":"+1 574 295 5118",
    "sg:postcode":"46517",
    "sg:province":"IN",
    "sg:tags":[
        "automobile",
        "parts"
    ],
    "wof:name":"Autozone",
    "wof:placetype":"venue"
},
  "geometry": {"coordinates":[-85.946494,41.65814],"type":"Point"}
}