{
  "type": "Feature",
  "properties": {
    "iso:country":"US",
    "sg:address":"2930 S Lynhurst Dr",
    "sg:city":"Indianapolis",
    "sg:classifiers":[
        {
            "category":"Freight",
            "type":"Transportation"
        }
    ],
    "sg:phone":"+1 317 240 1007",
    "sg:postcode":"46241",
    "sg:province":"IN",
    "sg:tags":[
        "commercial",
        "storage"
    ],
    "wof:name":"Lynhurst Storage",
    "wof:placetype":"venue"
},
  "geometry": {"coordinates":[-86.250415,39.72102],"type":"Point"}
}