{
  "type": "Feature",
  "properties": {
    "iso:country":"US",
    "sg:address":"6416 Hohman Ave",
    "sg:city":"Hammond",
    "sg:classifiers":[
        {
            "category":"Education",
            "subcategory":"School",
            "type":"Public Place"
        }
    ],
    "sg:phone":"+1 219 933 2469",
    "sg:postcode":"46324",
    "sg:province":"IN",
    "wof:name":"Schools Public",
    "wof:placetype":"venue"
},
  "geometry": {"coordinates":[-87.522102,41.5965],"type":"Point"}
}