{
  "type": "Feature",
  "properties": {
    "addr:full":"965 Grizzly Cub Dr Franklin IN 46131",
    "addr:housenumber":"965",
    "addr:postcode":"46131",
    "addr:street":"Grizzly Cub Dr",
    "iso:country":"US",
    "sg:address":"965 Grizzly Cub Dr",
    "sg:city":"Franklin",
    "sg:classifiers":[
        {
            "category":"Education",
            "subcategory":"School",
            "type":"Public Place"
        }
    ],
    "sg:phone":"+1 317 738 5740",
    "sg:postcode":"46131",
    "sg:province":"IN",
    "sg:website":"www.fcsc.k12.in.us",
    "wof:name":"Northwood Elementary School",
    "wof:placetype":"venue"
},
  "geometry": {"coordinates":[-86.06383599999999,39.489056],"type":"Point"}
}