{
  "type": "Feature",
  "properties": {
    "iso:country":"US",
    "sg:address":"1512 S Western Ave",
    "sg:city":"Marion",
    "sg:classifiers":[
        {
            "category":"Restaurant",
            "type":"Food & Drink"
        }
    ],
    "sg:phone":"+1 765 671 9953",
    "sg:postcode":"46953",
    "sg:province":"IN",
    "wof:name":"Sebrees",
    "wof:placetype":"venue"
},
  "geometry": {"coordinates":[-85.673855,40.545971],"type":"Point"}
}