{
  "type": "Feature",
  "properties": {
    "iso:country":"US",
    "sg:address":"617 Indiana Ave",
    "sg:city":"Indianapolis",
    "sg:classifiers":[
        {
            "category":"Professional",
            "subcategory":"Employment Agencies",
            "type":"Services"
        }
    ],
    "sg:phone":"+1 317 423 0609",
    "sg:postcode":"46202",
    "sg:province":"IN",
    "sg:tags":[
        "opportunity"
    ],
    "sg:website":"www.bryantgroupjobs.com",
    "wof:name":"Bryant Group",
    "wof:placetype":"venue"
},
  "geometry": {"coordinates":[-86.168098,39.776335],"type":"Point"}
}