{
  "type": "Feature",
  "properties": {
    "iso:country":"US",
    "sg:address":"107 E Locust St",
    "sg:city":"Fort Branch",
    "sg:classifiers":[
        {
            "category":"Education",
            "subcategory":"Library",
            "type":"Public Place"
        }
    ],
    "sg:phone":"+1 812 753 4212",
    "sg:postcode":"47648",
    "sg:province":"IN",
    "wof:name":"Fort Branch Public Library",
    "wof:placetype":"venue"
},
  "geometry": {"coordinates":[-87.578299,38.247338],"type":"Point"}
}