{
  "type": "Feature",
  "properties": {
    "iso:country":"US",
    "sg:address":"7995 S Co Rd 350 W",
    "sg:city":"Stilesville",
    "sg:classifiers":[
        {
            "category":"Building & Trades",
            "subcategory":"Landscaping Services",
            "type":"Services"
        }
    ],
    "sg:phone":"+1 317 539 4558",
    "sg:postcode":"46180",
    "sg:province":"IN",
    "sg:tags":[
        "landscape"
    ],
    "wof:name":"Sunset Design Inc",
    "wof:placetype":"venue"
},
  "geometry": {"coordinates":[-86.58501200000001,39.645233],"type":"Point"}
}