{
  "type": "Feature",
  "properties": {
    "iso:country":"US",
    "sg:address":"12624 US Hwy 33 N",
    "sg:city":"Churubusco",
    "sg:classifiers":[
        {
            "category":"Professional",
            "subcategory":"Business Services",
            "type":"Services"
        }
    ],
    "sg:phone":"+1 260 693 2137",
    "sg:postcode":"46723",
    "sg:province":"IN",
    "sg:tags":[
        "water",
        "treatment"
    ],
    "wof:name":"Aquatek Water Treatment Sys",
    "wof:placetype":"venue"
},
  "geometry": {"coordinates":[-85.298899,41.196355],"type":"Point"}
}