{
  "type": "Feature",
  "properties": {
    "iso:country":"US",
    "sg:address":"207 N 250 W",
    "sg:city":"Valparaiso",
    "sg:classifiers":[
        {
            "category":"Building & Trades",
            "subcategory":"Construction",
            "type":"Services"
        }
    ],
    "sg:phone":"+1 219 464 9156",
    "sg:postcode":"46385",
    "sg:province":"IN",
    "sg:tags":[
        "concrete",
        "contractor"
    ],
    "wof:name":"Custom Curbs",
    "wof:placetype":"venue"
},
  "geometry": {"coordinates":[-87.114129,41.464352],"type":"Point"}
}