{
  "type": "Feature",
  "properties": {
    "addr:full":"2229 S 3rd St Terre Haute IN 47802",
    "addr:housenumber":"2229",
    "addr:postcode":"47802",
    "addr:street":"S 3Rd St",
    "iso:country":"US",
    "sg:address":"2229 S 3rd St",
    "sg:city":"Terre Haute",
    "sg:classifiers":[
        {
            "category":"Professional",
            "subcategory":"Employment Agencies",
            "type":"Services"
        }
    ],
    "sg:phone":"+1 812 232 9090",
    "sg:postcode":"47802",
    "sg:province":"IN",
    "sg:tags":[
        "opportunity"
    ],
    "wof:name":"Express Personnel Svc",
    "wof:placetype":"venue"
},
  "geometry": {"coordinates":[-87.413758,39.442323],"type":"Point"}
}