{
  "type": "Feature",
  "properties": {
    "iso:country":"US",
    "sg:address":"4520 State Rd 46 E",
    "sg:city":"Nashville",
    "sg:classifiers":[
        {
            "category":"Manufacturing",
            "subcategory":"Food",
            "type":"Manufacturing & Wholesale Goods"
        }
    ],
    "sg:phone":"+1 812 988 6144",
    "sg:postcode":"47448",
    "sg:province":"IN",
    "sg:tags":[
        "winery"
    ],
    "wof:name":"Brown County Wine Co",
    "wof:placetype":"venue"
},
  "geometry": {"coordinates":[-86.155172,39.1911],"type":"Point"}
}