{
  "type": "Feature",
  "properties": {
    "iso:country":"US",
    "sg:address":"4431 W State Rd 28",
    "sg:city":"Frankfort",
    "sg:classifiers":[
        {
            "category":"Organizations",
            "subcategory":"Non-profit Organization",
            "type":"Services"
        }
    ],
    "sg:phone":"+1 765 659 1339",
    "sg:postcode":"46041",
    "sg:province":"IN",
    "wof:name":"Clinton Prairie School Corp",
    "wof:placetype":"venue"
},
  "geometry": {"coordinates":[-86.588424,40.279193],"type":"Point"}
}