{
  "type": "Feature",
  "properties": {
    "iso:country":"US",
    "sg:address":"13819 Stone Dr",
    "sg:city":"Carmel",
    "sg:classifiers":[
        {
            "category":"Professional",
            "subcategory":"Management & Consulting",
            "type":"Services"
        }
    ],
    "sg:phone":"+1 317 580 0925",
    "sg:postcode":"46032",
    "sg:province":"IN",
    "sg:tags":[
        "consultant",
        "search",
        "executive"
    ],
    "wof:name":"Spahn J & Assoc",
    "wof:placetype":"venue"
},
  "geometry": {"coordinates":[-86.17175400000001,39.99011],"type":"Point"}
}