{
  "type": "Feature",
  "properties": {
    "iso:country":"US",
    "sg:address":"5037 N State Rd 15",
    "sg:city":"Warsaw",
    "sg:classifiers":[
        {
            "category":"Retail",
            "subcategory":"Laundry & Dry Cleaning",
            "type":"Services"
        }
    ],
    "sg:phone":"+1 574 269 1487",
    "sg:postcode":"46582",
    "sg:province":"IN",
    "wof:name":"Alice Loher",
    "wof:placetype":"venue"
},
  "geometry": {"coordinates":[-85.854968,41.298461],"type":"Point"}
}