{
  "type": "Feature",
  "properties": {
    "addr:full":"3419 English Ave Indianapolis IN 46201",
    "addr:housenumber":"3419",
    "addr:postcode":"46201",
    "addr:street":"English Ave",
    "iso:country":"US",
    "sg:address":"3419 English Ave",
    "sg:city":"Indianapolis",
    "sg:classifiers":[
        {
            "category":"Shopping",
            "subcategory":"Department Store",
            "type":"Retail Goods"
        }
    ],
    "sg:phone":"+1 317 916 1685",
    "sg:postcode":"46201",
    "sg:province":"IN",
    "sg:tags":[
        "shop",
        "variety"
    ],
    "sg:website":"http://www.familydollar.com",
    "wof:name":"Family Dollar Stores",
    "wof:placetype":"venue"
},
  "geometry": {"coordinates":[-86.108142,39.759932],"type":"Point"}
}