{
  "type": "Feature",
  "properties": {
    "iso:country":"US",
    "sg:address":"61 Indiana Ave",
    "sg:city":"Valparaiso",
    "sg:classifiers":[
        {
            "category":"Banks & Credit Unions",
            "subcategory":"Investment Brokerage",
            "type":"Services"
        }
    ],
    "sg:phone":"+1 219 464 4481",
    "sg:postcode":"46383",
    "sg:province":"IN",
    "sg:tags":[
        "consultant",
        "planning",
        "financial"
    ],
    "wof:name":"Financial Resource Group",
    "wof:placetype":"venue"
},
  "geometry": {"coordinates":[-87.061217,41.466728],"type":"Point"}
}