{
  "type": "Feature",
  "properties": {
    "iso:country":"US",
    "sg:address":"3801 Meadows Dr",
    "sg:city":"Indianapolis",
    "sg:classifiers":[
        {
            "category":"Banks & Credit Unions",
            "subcategory":"Bank",
            "type":"Services"
        }
    ],
    "sg:phone":"+1 317 547 7979",
    "sg:postcode":"46205",
    "sg:province":"IN",
    "sg:tags":[
        "cashing",
        "check"
    ],
    "wof:name":"Payroll Check Cashing",
    "wof:placetype":"venue"
},
  "geometry": {"coordinates":[-86.11509700000001,39.825511],"type":"Point"}
}