{
  "type": "Feature",
  "properties": {
    "iso:country":"US",
    "sg:address":"4201 Coldwater Rd",
    "sg:city":"Fort Wayne",
    "sg:classifiers":[
        {
            "category":"Shopping",
            "subcategory":"Clothing, Apparel, & Fashions",
            "type":"Retail Goods"
        }
    ],
    "sg:phone":"+1 260 483 0040",
    "sg:postcode":"46805",
    "sg:province":"IN",
    "wof:name":"Delia's",
    "wof:placetype":"venue"
},
  "geometry": {"coordinates":[-85.135188,41.114794],"type":"Point"}
}