{
  "type": "Feature",
  "properties": {
    "iso:country":"US",
    "sg:address":"1818 Coliseum Blvd S",
    "sg:city":"Fort Wayne",
    "sg:classifiers":[
        {
            "category":"Bars & Pubs",
            "type":"Food & Drink"
        }
    ],
    "sg:phone":"+1 260 422 8330",
    "sg:postcode":"46803",
    "sg:province":"IN",
    "wof:name":"Cloverleaf Bar",
    "wof:placetype":"venue"
},
  "geometry": {"coordinates":[-85.087629,41.070076],"type":"Point"}
}