{
  "type": "Feature",
  "properties": {
    "iso:country":"US",
    "sg:address":"8848 State Rd 114",
    "sg:city":"Rensselaer",
    "sg:classifiers":[
        {
            "category":"Restaurant",
            "type":"Food & Drink"
        }
    ],
    "sg:phone":"+1 219 866 8385",
    "sg:postcode":"47978",
    "sg:province":"IN",
    "wof:name":"Arby's",
    "wof:placetype":"venue"
},
  "geometry": {"coordinates":[-87.221214,40.940803],"type":"Point"}
}