{
  "type": "Feature",
  "properties": {
    "iso:country":"US",
    "sg:address":"350 S Depot St",
    "sg:city":"Marengo",
    "sg:classifiers":[
        {
            "category":"Bars & Pubs",
            "type":"Food & Drink"
        }
    ],
    "sg:phone":"+1 812 365 7000",
    "sg:postcode":"47140",
    "sg:province":"IN",
    "wof:name":"Marengo Tavern",
    "wof:placetype":"venue"
},
  "geometry": {"coordinates":[-86.342931,38.367354],"type":"Point"}
}