{
  "type": "Feature",
  "properties": {
    "iso:country":"US",
    "sg:address":"25516 State Rd 2",
    "sg:city":"South Bend",
    "sg:classifiers":[
        {
            "category":"Home & Garden",
            "subcategory":"Home Furnishings",
            "type":"Retail Goods"
        }
    ],
    "sg:phone":"+1 574 288 6478",
    "sg:postcode":"46619",
    "sg:province":"IN",
    "sg:tags":[
        "quilting"
    ],
    "wof:name":"Heckaman's Quilting & Yarn",
    "wof:placetype":"venue"
},
  "geometry": {"coordinates":[-86.360796,41.671783],"type":"Point"}
}