{
  "type": "Feature",
  "properties": {
    "addr:full":"1 W Washington St Knightstown IN 46148",
    "addr:housenumber":"1",
    "addr:postcode":"46148",
    "addr:street":"W Washington St",
    "iso:country":"US",
    "sg:address":"1 W Washington St",
    "sg:city":"Knightstown",
    "sg:classifiers":[
        {
            "category":"Shopping",
            "subcategory":"Books",
            "type":"Retail Goods"
        }
    ],
    "sg:phone":"+1 765 345 9262",
    "sg:postcode":"46148",
    "sg:province":"IN",
    "sg:tags":[
        "dealer"
    ],
    "wof:name":"Book Mark",
    "wof:placetype":"venue"
},
  "geometry": {"coordinates":[-85.52490899999999,39.796105],"type":"Point"}
}