{
  "type": "Feature",
  "properties": {
    "iso:country":"US",
    "sg:address":"2601 Fortune Cir E",
    "sg:city":"Indianapolis",
    "sg:classifiers":[
        {
            "category":"Insurance",
            "subcategory":"Insurance Agent",
            "type":"Services"
        }
    ],
    "sg:phone":"+1 317 243 6721",
    "sg:postcode":"46241",
    "sg:province":"IN",
    "sg:website":"www.bituminousinsurance.com",
    "wof:name":"Bituminous Insurance Co",
    "wof:placetype":"venue"
},
  "geometry": {"coordinates":[-86.25529299999999,39.727719],"type":"Point"}
}