{
  "type": "Feature",
  "properties": {
    "iso:country":"US",
    "sg:address":"3105 Crossbow Ln",
    "sg:city":"Evansville",
    "sg:classifiers":[
        {
            "category":"Health Services",
            "subcategory":"Clinic",
            "type":"Services"
        }
    ],
    "sg:phone":"+1 812 476 6764",
    "sg:postcode":"47715",
    "sg:province":"IN",
    "wof:name":"Gregory Sherman",
    "wof:placetype":"venue"
},
  "geometry": {"coordinates":[-87.500892,38.00502],"type":"Point"}
}