{
  "type": "Feature",
  "properties": {
    "iso:country":"US",
    "sg:address":"5930 E State Rd 334",
    "sg:city":"Whitestown",
    "sg:classifiers":[
        {
            "category":"Restaurant",
            "type":"Food & Drink"
        }
    ],
    "sg:phone":"+1 317 769 3291",
    "sg:postcode":"46075",
    "sg:province":"IN",
    "wof:name":"Popeyes Chicken & Biscuits",
    "wof:placetype":"venue"
},
  "geometry": {"coordinates":[-86.353877,39.9473],"type":"Point"}
}