{
  "type": "Feature",
  "properties": {
    "iso:country":"US",
    "sg:address":"67 N Madison Ave",
    "sg:city":"Greenwood",
    "sg:phone":"+1 317 859 1888",
    "sg:postcode":"46142",
    "sg:province":"IN",
    "wof:name":"Yokohama Japanese Cuisine & Sushi Bar",
    "wof:placetype":"venue"
},
  "geometry": {"coordinates":[-86.110623,39.616425],"type":"Point"}
}