{
  "type": "Feature",
  "properties": {
    "iso:country":"US",
    "sg:address":"21526 C St",
    "sg:city":"Elkhart",
    "sg:classifiers":[
        {
            "category":"Manufacturing",
            "subcategory":"Building Materials",
            "type":"Manufacturing & Wholesale Goods"
        }
    ],
    "sg:phone":"+1 574 293 7113",
    "sg:postcode":"46516",
    "sg:province":"IN",
    "sg:tags":[
        "cabinet"
    ],
    "wof:name":"Academy Inc",
    "wof:placetype":"venue"
},
  "geometry": {"coordinates":[-85.87761,41.698695],"type":"Point"}
}