{
  "type": "Feature",
  "properties": {
    "iso:country":"US",
    "sg:address":"1426 Main St",
    "sg:city":"Mt Vernon",
    "sg:classifiers":[
        {
            "category":"Real Estate",
            "subcategory":"Real Estate Operator",
            "type":"Services"
        }
    ],
    "sg:phone":"+1 812 838 0665",
    "sg:postcode":"47620",
    "sg:province":"IN",
    "sg:tags":[
        "apartment"
    ],
    "wof:name":"Village Apts Of Mt Vernon",
    "wof:placetype":"venue"
},
  "geometry": {"coordinates":[-87.897156,37.944479],"type":"Point"}
}