{
  "type": "Feature",
  "properties": {
    "iso:country":"US",
    "sg:address":"1509 W Broadway St",
    "sg:city":"Princeton",
    "sg:classifiers":[
        {
            "category":"Building & Trades",
            "subcategory":"Equipment Rental",
            "type":"Services"
        }
    ],
    "sg:phone":"+1 812 385 4830",
    "sg:postcode":"47670",
    "sg:province":"IN",
    "sg:tags":[
        "leasing",
        "furniture"
    ],
    "wof:name":"American Rental",
    "wof:placetype":"venue"
},
  "geometry": {"coordinates":[-87.584391,38.355323],"type":"Point"}
}