{
  "type": "Feature",
  "properties": {
    "addr:full":"12081 N Co Rd 50 W Batesville IN 47006",
    "addr:housenumber":"12081;50",
    "addr:postcode":"47006",
    "addr:street":"N Co Rd;W Batesville",
    "iso:country":"US",
    "sg:address":"12081 N Co Rd 50 W",
    "sg:city":"Batesville",
    "sg:classifiers":[
        {
            "category":"Farming",
            "subcategory":"Livestock Farm",
            "type":"Manufacturing & Wholesale Goods"
        }
    ],
    "sg:phone":"+1 812 934 5838",
    "sg:postcode":"47006",
    "sg:province":"IN",
    "sg:tags":[
        "hog",
        "or",
        "feedlot"
    ],
    "wof:name":"Robert Siebert",
    "wof:placetype":"venue"
},
  "geometry": {"coordinates":[-85.267838,39.251138],"type":"Point"}
}