{
  "type": "Feature",
  "properties": {
    "iso:country":"US",
    "sg:address":"201 W Illinois St",
    "sg:city":"Evansville",
    "sg:classifiers":[
        {
            "category":"Restaurant",
            "type":"Food & Drink"
        }
    ],
    "sg:phone":"+1 812 421 0024",
    "sg:postcode":"47710",
    "sg:province":"IN",
    "wof:name":"Brick House Bar & Grill",
    "wof:placetype":"venue"
},
  "geometry": {"coordinates":[-87.568483,37.979275],"type":"Point"}
}