{
  "type": "Feature",
  "properties": {
    "iso:country":"US",
    "sg:address":"9506 N Meridian St",
    "sg:city":"Indianapolis",
    "sg:classifiers":[
        {
            "category":"Manufacturing",
            "subcategory":"Retail Goods",
            "type":"Manufacturing & Wholesale Goods"
        }
    ],
    "sg:phone":"+1 317 844 1929",
    "sg:postcode":"46260",
    "sg:province":"IN",
    "sg:tags":[
        "product",
        "mfg"
    ],
    "wof:name":"Paramus Enterprise Inc",
    "wof:placetype":"venue"
},
  "geometry": {"coordinates":[-86.158107,39.92408],"type":"Point"}
}