{
  "type": "Feature",
  "properties": {
    "iso:country":"US",
    "sg:address":"101 Lockwood St",
    "sg:city":"Salem",
    "sg:classifiers":[
        {
            "category":"Restaurant",
            "type":"Food & Drink"
        }
    ],
    "sg:phone":"+1 812 883 6770",
    "sg:postcode":"47167",
    "sg:province":"IN",
    "sg:tags":[
        "eating"
    ],
    "wof:name":"Vance Concession",
    "wof:placetype":"venue"
},
  "geometry": {"coordinates":[-86.110754,38.605466],"type":"Point"}
}