{
  "type": "Feature",
  "properties": {
    "iso:country":"US",
    "sg:address":"8235 State Rd 26 E",
    "sg:city":"Lafayette",
    "sg:classifiers":[
        {
            "category":"Wholesale",
            "subcategory":"Hardware",
            "type":"Manufacturing & Wholesale Goods"
        }
    ],
    "sg:phone":"+1 765 296 2538",
    "sg:postcode":"47905",
    "sg:province":"IN",
    "sg:tags":[
        "prevention",
        "flow",
        "back",
        "devices"
    ],
    "wof:name":"Chekback Inc",
    "wof:placetype":"venue"
},
  "geometry": {"coordinates":[-86.74909,40.419733],"type":"Point"}
}