{
  "type": "Feature",
  "properties": {
    "iso:country":"US",
    "sg:address":"1503 N F St",
    "sg:city":"Elwood",
    "sg:classifiers":[
        {
            "category":"Wholesale",
            "subcategory":"Auto Parts",
            "type":"Manufacturing & Wholesale Goods"
        }
    ],
    "sg:phone":"+1 765 552 9299",
    "sg:postcode":"46036",
    "sg:province":"IN",
    "sg:tags":[
        "automobile",
        "supply"
    ],
    "wof:name":"Network Parts Co Inc",
    "wof:placetype":"venue"
},
  "geometry": {"coordinates":[-85.841554,40.282399],"type":"Point"}
}