{
  "type": "Feature",
  "properties": {
    "iso:country":"US",
    "sg:address":"3777 E Co Rd 150 S",
    "sg:city":"Frankfort",
    "sg:classifiers":[
        {
            "category":"Real Estate",
            "subcategory":"Real Estate Agent",
            "type":"Services"
        }
    ],
    "sg:phone":"+1 765 654 9533",
    "sg:postcode":"46041",
    "sg:province":"IN",
    "sg:tags":[
        "appraiser"
    ],
    "wof:name":"Luse & Assoc",
    "wof:placetype":"venue"
},
  "geometry": {"coordinates":[-86.442233,40.264284],"type":"Point"}
}