{
  "type": "Feature",
  "properties": {
    "iso:country":"US",
    "sg:address":"2600 Ferry St",
    "sg:city":"Lafayette",
    "sg:classifiers":[
        {
            "category":"Shopping",
            "subcategory":"Pharmacy",
            "type":"Retail Goods"
        }
    ],
    "sg:phone":"+1 765 448 8000",
    "sg:postcode":"47904",
    "sg:province":"IN",
    "wof:name":"Arnett Pharmacy",
    "wof:placetype":"venue"
},
  "geometry": {"coordinates":[-86.866377,40.41904],"type":"Point"}
}