{
  "type": "Feature",
  "properties": {
    "iso:country":"US",
    "sg:address":"1017 S Bend Ave",
    "sg:city":"South Bend",
    "sg:classifiers":[
        {
            "category":"Professional",
            "subcategory":"Lawyer & Legal Services",
            "type":"Services"
        }
    ],
    "sg:phone":"+1 574 233 7165",
    "sg:postcode":"46617",
    "sg:province":"IN",
    "sg:tags":[
        "attorney"
    ],
    "wof:name":"Timothy P Mc Laughlin Law Ofc",
    "wof:placetype":"venue"
},
  "geometry": {"coordinates":[-86.235517,41.687377],"type":"Point"}
}