{
  "type": "Feature",
  "properties": {
    "iso:country":"US",
    "sg:address":"4671 W 500 S",
    "sg:city":"Bringhurst",
    "sg:classifiers":[
        {
            "category":"Professional",
            "type":"Services"
        }
    ],
    "sg:phone":"+1 765 379 2815",
    "sg:postcode":"46913",
    "sg:province":"IN",
    "sg:tags":[
        "establishment"
    ],
    "wof:name":"Wirtz & Yates Inc",
    "wof:placetype":"venue"
},
  "geometry": {"coordinates":[-86.60875799999999,40.475049],"type":"Point"}
}