{
  "type": "Feature",
  "properties": {
    "iso:country":"US",
    "sg:address":"3403 Mechanicsburg Dr",
    "sg:city":"Indianapolis",
    "sg:classifiers":[
        {
            "category":"Manufacturing",
            "subcategory":"Printing",
            "type":"Manufacturing & Wholesale Goods"
        }
    ],
    "sg:phone":"+1 317 859 2198",
    "sg:postcode":"46227",
    "sg:province":"IN",
    "sg:tags":[
        "multimedia"
    ],
    "wof:name":"American Media Mfg",
    "wof:placetype":"venue"
},
  "geometry": {"coordinates":[-86.10756600000001,39.643425],"type":"Point"}
}