{
  "type": "Feature",
  "properties": {
    "addr:full":"326 N Geiger St Huntingburg IN 47542",
    "addr:housenumber":"326",
    "addr:postcode":"47542",
    "addr:street":"N Geiger St",
    "iso:country":"US",
    "sg:address":"326 N Geiger St",
    "sg:city":"Huntingburg",
    "sg:classifiers":[
        {
            "category":"Organizations",
            "subcategory":"Religious Organization",
            "type":"Services"
        }
    ],
    "sg:phone":"+1 812 683 2335",
    "sg:postcode":"47542",
    "sg:province":"IN",
    "sg:tags":[
        "church"
    ],
    "wof:name":"First Baptist Church",
    "wof:placetype":"venue"
},
  "geometry": {"coordinates":[-86.95723599999999,38.295869],"type":"Point"}
}