{
  "type": "Feature",
  "properties": {
    "iso:country":"US",
    "sg:address":"255 Meadow Dr",
    "sg:city":"Danville",
    "sg:classifiers":[
        {
            "category":"Health Services",
            "subcategory":"Nursing And Care Facility",
            "type":"Services"
        }
    ],
    "sg:phone":"+1 317 745 5451",
    "sg:postcode":"46122",
    "sg:province":"IN",
    "sg:tags":[
        "home",
        "convalescent"
    ],
    "wof:name":"Danville Regional Rehab Ctr",
    "wof:placetype":"venue"
},
  "geometry": {"coordinates":[-86.499569,39.76342],"type":"Point"}
}