{
  "type": "Feature",
  "properties": {
    "iso:country":"US",
    "sg:address":"620 E Springhill Dr",
    "sg:city":"Terre Haute",
    "sg:classifiers":[
        {
            "category":"Shopping",
            "subcategory":"Tobacco",
            "type":"Retail Goods"
        }
    ],
    "sg:phone":"+1 812 235 2623",
    "sg:postcode":"47802",
    "sg:province":"IN",
    "sg:tags":[
        "cigarette",
        "cigar",
        "dealer"
    ],
    "wof:name":"Tobacco Barn",
    "wof:placetype":"venue"
},
  "geometry": {"coordinates":[-87.407993,39.412447],"type":"Point"}
}