{
  "type": "Feature",
  "properties": {
    "iso:country":"US",
    "sg:address":"867 E Walnut St",
    "sg:city":"Evansville",
    "sg:classifiers":[
        {
            "category":"Organizations",
            "subcategory":"Religious Organization",
            "type":"Services"
        }
    ],
    "sg:phone":"+1 812 424 7368",
    "sg:postcode":"47713",
    "sg:province":"IN",
    "sg:tags":[
        "church"
    ],
    "wof:name":"Nazarene Baptist Church",
    "wof:placetype":"venue"
},
  "geometry": {"coordinates":[-87.549222,37.973516],"type":"Point"}
}