{
  "type": "Feature",
  "properties": {
    "iso:country":"US",
    "sg:address":"2429 S Sampson Rd",
    "sg:city":"Woodburn",
    "sg:phone":"+1 260 623 3376",
    "sg:postcode":"46797",
    "sg:province":"IN",
    "sg:tags":[
        "farm",
        "corn",
        "soybean"
    ],
    "wof:name":"Donald Johns",
    "wof:placetype":"venue"
},
  "geometry": {"coordinates":[-84.88488,41.070902],"type":"Point"}
}