{
  "type": "Feature",
  "properties": {
    "addr:full":"435 S Mount Zion Rd Lebanon IN 46052",
    "addr:housenumber":"435",
    "addr:postcode":"46052",
    "addr:street":"S Mount Zion Rd",
    "iso:country":"US",
    "sg:address":"435 S Mount Zion Rd",
    "sg:city":"Lebanon",
    "sg:classifiers":[
        {
            "category":"Restaurant",
            "type":"Food & Drink"
        }
    ],
    "sg:menulink":"http://www.allmenus.com/in/lebanon/208080-taco-bell/menu/",
    "sg:phone":"+1 765 482 2355",
    "sg:postcode":"46052",
    "sg:province":"IN",
    "sg:tags":[
        "mexican"
    ],
    "wof:name":"Taco Bell",
    "wof:placetype":"venue"
},
  "geometry": {"coordinates":[-86.50109500000001,40.032283],"type":"Point"}
}