{
  "type": "Feature",
  "properties": {
    "addr:full":"728 S Main St Bluffton IN 46714",
    "addr:housenumber":"728",
    "addr:postcode":"46714",
    "addr:street":"S Main St",
    "iso:country":"US",
    "sg:address":"728 S Main St",
    "sg:city":"Bluffton",
    "sg:classifiers":[
        {
            "category":"Restaurant",
            "type":"Food & Drink"
        }
    ],
    "sg:phone":"+1 260 824 8260",
    "sg:postcode":"46714",
    "sg:province":"IN",
    "sg:tags":[
        "caterer"
    ],
    "wof:name":"Legacy Catering",
    "wof:placetype":"venue"
},
  "geometry": {"coordinates":[-85.171513,40.733073],"type":"Point"}
}