{
  "type": "Feature",
  "properties": {
    "iso:country":"US",
    "sg:address":"7346 W Co Rd 400 N",
    "sg:city":"Leiters Ford",
    "sg:classifiers":[
        {
            "category":"Professional",
            "type":"Services"
        }
    ],
    "sg:phone":"+1 574 542 2001",
    "sg:postcode":"46978",
    "sg:province":"IN",
    "sg:tags":[
        "establishment"
    ],
    "wof:name":"Braun Seating Inc",
    "wof:placetype":"venue"
},
  "geometry": {"coordinates":[-86.525344,40.823719],"type":"Point"}
}