{
  "type": "Feature",
  "properties": {
    "iso:country":"US",
    "sg:address":"2458 N Chamberlain St",
    "sg:city":"Terre Haute",
    "sg:classifiers":[
        {
            "category":"Retail",
            "subcategory":"Veterinary Services",
            "type":"Services"
        }
    ],
    "sg:phone":"+1 812 877 1545",
    "sg:postcode":"47805",
    "sg:province":"IN",
    "sg:tags":[
        "veterinarian"
    ],
    "wof:name":"Schering-Plough Animal Health",
    "wof:placetype":"venue"
},
  "geometry": {"coordinates":[-87.295346,39.495068],"type":"Point"}
}