{
  "type": "Feature",
  "properties": {
    "iso:country":"US",
    "sg:address":"828 N Scott St",
    "sg:city":"Rensselaer",
    "sg:classifiers":[
        {
            "category":"Manufacturing",
            "subcategory":"Tools & Machinery",
            "type":"Manufacturing & Wholesale Goods"
        }
    ],
    "sg:phone":"+1 219 866 3018",
    "sg:postcode":"47978",
    "sg:province":"IN",
    "wof:name":"Morris Machine & Tool",
    "wof:placetype":"venue"
},
  "geometry": {"coordinates":[-87.146036,40.94501],"type":"Point"}
}