{
  "type": "Feature",
  "properties": {
    "iso:country":"US",
    "sg:address":"3313 S Hamilton Ave",
    "sg:city":"Muncie",
    "sg:classifiers":[
        {
            "category":"Professional",
            "type":"Services"
        }
    ],
    "sg:phone":"+1 765 284 9545",
    "sg:postcode":"47302",
    "sg:province":"IN",
    "sg:tags":[
        "establishment"
    ],
    "wof:name":"Smart Products Inc",
    "wof:placetype":"venue"
},
  "geometry": {"coordinates":[-85.414568,40.162433],"type":"Point"}
}