{
  "type": "Feature",
  "properties": {
    "addr:full":"2636 W 15th Ave Gary IN 46404",
    "addr:housenumber":"2636",
    "addr:postcode":"46404",
    "addr:street":"W 15Th Ave",
    "iso:country":"US",
    "sg:address":"2636 W 15th Ave",
    "sg:city":"Gary",
    "sg:classifiers":[
        {
            "category":"Real Estate",
            "subcategory":"Real Estate Agent",
            "type":"Services"
        }
    ],
    "sg:phone":"+1 219 949 9700",
    "sg:postcode":"46404",
    "sg:province":"IN",
    "sg:website":"www.century21powers.com",
    "wof:name":"Century 21",
    "wof:placetype":"venue"
},
  "geometry": {"coordinates":[-87.370392,41.587937],"type":"Point"}
}