{
  "type": "Feature",
  "properties": {
    "iso:country":"US",
    "sg:address":"3758 W Old 24",
    "sg:city":"Wabash",
    "sg:classifiers":[
        {
            "category":"Manufacturing",
            "subcategory":"Paper Products",
            "type":"Manufacturing & Wholesale Goods"
        }
    ],
    "sg:phone":"+1 260 563 7411",
    "sg:postcode":"46992",
    "sg:province":"IN",
    "sg:tags":[
        "converted",
        "prod"
    ],
    "wof:name":"Custom Cartons Inc",
    "wof:placetype":"venue"
},
  "geometry": {"coordinates":[-85.862032,40.797177],"type":"Point"}
}