{
  "type": "Feature",
  "properties": {
    "iso:country":"US",
    "sg:address":"3302 N Drexel Ave",
    "sg:city":"Indianapolis",
    "sg:classifiers":[
        {
            "category":"Social Services",
            "subcategory":"Child Care",
            "type":"Services"
        }
    ],
    "sg:phone":"+1 317 549 9616",
    "sg:postcode":"46218",
    "sg:province":"IN",
    "wof:name":"Mackida Loveal Outreach Minist",
    "wof:placetype":"venue"
},
  "geometry": {"coordinates":[-86.09266599999999,39.818215],"type":"Point"}
}