{
  "type": "Feature",
  "properties": {
    "iso:country":"US",
    "sg:address":"494 US Hwy 31 N",
    "sg:city":"Greenwood",
    "sg:classifiers":[
        {
            "category":"Banks & Credit Unions",
            "subcategory":"Bank",
            "type":"Services"
        }
    ],
    "sg:phone":"+1 317 889 4444",
    "sg:postcode":"46142",
    "sg:province":"IN",
    "sg:tags":[
        "cashing",
        "check"
    ],
    "wof:name":"Cash Today",
    "wof:placetype":"venue"
},
  "geometry": {"coordinates":[-86.116869,39.620789],"type":"Point"}
}