{
  "type": "Feature",
  "properties": {
    "addr:full":"221 US Hwy 41 Schererville IN 46375",
    "addr:housenumber":"221",
    "addr:postcode":"46375",
    "addr:street":"Us Hwy 41",
    "iso:country":"US",
    "sg:address":"221 US Hwy 41",
    "sg:city":"Schererville",
    "sg:classifiers":[
        {
            "category":"Social Services",
            "subcategory":"Job Training",
            "type":"Services"
        }
    ],
    "sg:phone":"+1 219 322 2037",
    "sg:postcode":"46375",
    "sg:province":"IN",
    "sg:tags":[
        "rehabilitation"
    ],
    "sg:website":"www.ssfhs.com",
    "wof:name":"St Margaret Mercy Pediatric",
    "wof:placetype":"venue"
},
  "geometry": {"coordinates":[-87.47122299999999,41.520261],"type":"Point"}
}