{
  "type": "Feature",
  "properties": {
    "iso:country":"US",
    "sg:address":"600 W Temperance St",
    "sg:city":"Ellettsville",
    "sg:classifiers":[
        {
            "category":"Education",
            "subcategory":"Library",
            "type":"Public Place"
        }
    ],
    "sg:phone":"+1 812 876 1272",
    "sg:postcode":"47429",
    "sg:province":"IN",
    "sg:website":"www.monroe.lib.in.us",
    "wof:name":"Ellettsville Branch Library",
    "wof:placetype":"venue"
},
  "geometry": {"coordinates":[-86.625172,39.234103],"type":"Point"}
}