{
  "type": "Feature",
  "properties": {
    "addr:full":"3400 Ridge Rd Highland IN 46322",
    "addr:housenumber":"3400",
    "addr:postcode":"46322",
    "addr:street":"Ridge Rd",
    "iso:country":"US",
    "sg:address":"3400 Ridge Rd",
    "sg:city":"Highland",
    "sg:classifiers":[
        {
            "category":"Personal",
            "subcategory":"Barber",
            "type":"Services"
        }
    ],
    "sg:phone":"+1 219 838 1109",
    "sg:postcode":"46322",
    "sg:province":"IN",
    "wof:name":"Hair Currents",
    "wof:placetype":"venue"
},
  "geometry": {"coordinates":[-87.447098,41.553299],"type":"Point"}
}