{
  "type": "Feature",
  "properties": {
    "iso:country":"US",
    "sg:address":"104 W Walnut St",
    "sg:city":"Odon",
    "sg:classifiers":[
        {
            "category":"Health Services",
            "subcategory":"Health Practitioner",
            "type":"Services"
        }
    ],
    "sg:phone":"+1 812 636 7382",
    "sg:postcode":"47562",
    "sg:province":"IN",
    "sg:tags":[
        "nurse"
    ],
    "wof:name":"Odon Family Practice",
    "wof:placetype":"venue"
},
  "geometry": {"coordinates":[-86.991938,38.842038],"type":"Point"}
}