{
  "type": "Feature",
  "properties": {
    "iso:country":"US",
    "sg:address":"459 W Morgan St",
    "sg:city":"Spencer",
    "sg:classifiers":[
        {
            "category":"Food & Beverages",
            "subcategory":"Groceries & Convenience Stores",
            "type":"Retail Goods"
        }
    ],
    "sg:phone":"+1 812 829 2231",
    "sg:postcode":"47460",
    "sg:province":"IN",
    "sg:tags":[
        "grocer"
    ],
    "wof:name":"Supervalu",
    "wof:placetype":"venue"
},
  "geometry": {"coordinates":[-86.767819,39.287073],"type":"Point"}
}