{
  "type": "Feature",
  "properties": {
    "iso:country":"US",
    "sg:address":"7508 Wood Ct",
    "sg:city":"Fishers",
    "sg:classifiers":[
        {
            "category":"Government",
            "subcategory":"Fire Station",
            "type":"Public Place"
        },
        {
            "category":"Wholesale",
            "subcategory":"Machinery & Supplies",
            "type":"Manufacturing & Wholesale Goods"
        }
    ],
    "sg:phone":"+1 317 594 0070",
    "sg:postcode":"46038",
    "sg:province":"IN",
    "sg:tags":[
        "equipment",
        "protection",
        "department"
    ],
    "wof:name":"Virtua",
    "wof:placetype":"venue"
},
  "geometry": {"coordinates":[-86.046886,39.9455],"type":"Point"}
}