{
  "type": "Feature",
  "properties": {
    "iso:country":"US",
    "sg:address":"1644 N Co Rd 900 E",
    "sg:city":"Avon",
    "sg:classifiers":[
        {
            "category":"Personal",
            "subcategory":"Beauty Salon",
            "type":"Services"
        }
    ],
    "sg:phone":"+1 317 271 6127",
    "sg:postcode":"46123",
    "sg:province":"IN",
    "sg:tags":[
        "cosmetologist"
    ],
    "wof:name":"Betty Jo Waldon",
    "wof:placetype":"venue"
},
  "geometry": {"coordinates":[-86.362272,39.788317],"type":"Point"}
}