{
  "type": "Feature",
  "properties": {
    "addr:full":"6079 W 600 N Winamac IN 46996",
    "addr:housenumber":"6079",
    "addr:postcode":"46996",
    "addr:street":"W 600 N",
    "iso:country":"US",
    "sg:address":"6079 W 600 N",
    "sg:city":"Winamac",
    "sg:phone":"+1 574 896 3592",
    "sg:postcode":"46996",
    "sg:province":"IN",
    "sg:tags":[
        "beef",
        "farm",
        "corn",
        "soybean",
        "cattle",
        "feedlot"
    ],
    "wof:name":"Ray Katschke",
    "wof:placetype":"venue"
},
  "geometry": {"coordinates":[-86.717636,41.1428],"type":"Point"}
}