{
  "type": "Feature",
  "properties": {
    "addr:full":"101 E Elnora St Odon IN 47562",
    "addr:housenumber":"101",
    "addr:postcode":"47562",
    "addr:street":"E Elnora St",
    "iso:country":"US",
    "sg:address":"101 E Elnora St",
    "sg:city":"Odon",
    "sg:classifiers":[
        {
            "category":"Health Services",
            "subcategory":"Optometrist",
            "type":"Services"
        }
    ],
    "sg:phone":"+1 812 636 8030",
    "sg:postcode":"47562",
    "sg:province":"IN",
    "wof:name":"Odon Optical",
    "wof:placetype":"venue"
},
  "geometry": {"coordinates":[-86.989423,38.844518],"type":"Point"}
}