{
  "type": "Feature",
  "properties": {
    "addr:full":"815 E Main St Washington IN 47501",
    "addr:housenumber":"815",
    "addr:postcode":"47501",
    "addr:street":"E Main St",
    "iso:country":"US",
    "sg:address":"815 E Main St",
    "sg:city":"Washington",
    "sg:classifiers":[
        {
            "category":"Shopping",
            "subcategory":"Used Merchandise",
            "type":"Retail Goods"
        }
    ],
    "sg:phone":"+1 812 254 6678",
    "sg:postcode":"47501",
    "sg:province":"IN",
    "sg:tags":[
        "shop",
        "thrift"
    ],
    "wof:name":"St Vincent De Paul",
    "wof:placetype":"venue"
},
  "geometry": {"coordinates":[-87.166163,38.65688],"type":"Point"}
}