{
  "type": "Feature",
  "properties": {
    "iso:country":"US",
    "sg:address":"125 N Chippewa St",
    "sg:city":"Roann",
    "sg:classifiers":[
        {
            "category":"Insurance",
            "subcategory":"Insurance Agent",
            "type":"Services"
        }
    ],
    "sg:phone":"+1 765 833 4444",
    "sg:postcode":"46974",
    "sg:province":"IN",
    "wof:name":"Central Indiana Insurance Svc",
    "wof:placetype":"venue"
},
  "geometry": {"coordinates":[-85.924393,40.911924],"type":"Point"}
}