{
  "type": "Feature",
  "properties": {
    "iso:country":"US",
    "sg:address":"1914 N Walnut St",
    "sg:city":"Muncie",
    "sg:classifiers":[
        {
            "category":"Shopping",
            "subcategory":"Clothing, Apparel, & Fashions",
            "type":"Retail Goods"
        }
    ],
    "sg:phone":"+1 765 289 8637",
    "sg:postcode":"47303",
    "sg:province":"IN",
    "sg:tags":[
        "dancing",
        "supply"
    ],
    "wof:name":"Hot Toes Active Wear",
    "wof:placetype":"venue"
},
  "geometry": {"coordinates":[-85.38684499999999,40.211055],"type":"Point"}
}