{
  "type": "Feature",
  "properties": {
    "iso:country":"US",
    "sg:address":"4015 S State Rd 39",
    "sg:city":"Frankfort",
    "sg:classifiers":[
        {
            "category":"Building & Trades",
            "subcategory":"Construction",
            "type":"Services"
        },
        {
            "category":"Retail",
            "subcategory":"Auto Repair",
            "type":"Services"
        }
    ],
    "sg:phone":"+1 765 654 5073",
    "sg:postcode":"46041",
    "sg:province":"IN",
    "sg:tags":[
        "glass",
        "coating",
        "tinting",
        "contractor"
    ],
    "wof:name":"Marchand's Window Tinting",
    "wof:placetype":"venue"
},
  "geometry": {"coordinates":[-86.502416,40.222429],"type":"Point"}
}