{
  "type": "Feature",
  "properties": {
    "iso:country":"US",
    "sg:address":"1503 S Tibbs Ave",
    "sg:city":"Indianapolis",
    "sg:classifiers":[
        {
            "category":"Organizations",
            "subcategory":"Religious Organization",
            "type":"Services"
        }
    ],
    "sg:phone":"+1 317 241 4524",
    "sg:postcode":"46241",
    "sg:province":"IN",
    "sg:tags":[
        "church"
    ],
    "wof:name":"Oak Park Baptist Church",
    "wof:placetype":"venue"
},
  "geometry": {"coordinates":[-86.215923,39.742895],"type":"Point"}
}