{
  "type": "Feature",
  "properties": {
    "iso:country":"US",
    "sg:address":"2311 Broadway St",
    "sg:city":"Anderson",
    "sg:classifiers":[
        {
            "category":"Manufacturing",
            "subcategory":"Metals",
            "type":"Manufacturing & Wholesale Goods"
        }
    ],
    "sg:phone":"+1 765 640 8668",
    "sg:postcode":"46012",
    "sg:province":"IN",
    "sg:tags":[
        "ornamental",
        "work"
    ],
    "wof:name":"Falcon Awning & Ornamental",
    "wof:placetype":"venue"
},
  "geometry": {"coordinates":[-85.67751800000001,40.140456],"type":"Point"}
}