{
  "type": "Feature",
  "properties": {
    "addr:full":"4025 Huth Dr Fort Wayne IN 46804",
    "addr:postcode":"4025;46804",
    "addr:street":"Huth Dr",
    "iso:country":"US",
    "sg:address":"4025 Huth Dr",
    "sg:city":"Fort Wayne",
    "sg:classifiers":[
        {
            "category":"Building & Trades",
            "subcategory":"Cleaning & Sanitation",
            "type":"Services"
        }
    ],
    "sg:phone":"+1 260 459 2254",
    "sg:postcode":"46804",
    "sg:province":"IN",
    "sg:tags":[
        "janitor"
    ],
    "wof:name":"R & R Cleaning",
    "wof:placetype":"venue"
},
  "geometry": {"coordinates":[-85.24247800000001,41.046955],"type":"Point"}
}