{
  "type": "Feature",
  "properties": {
    "iso:country":"US",
    "sg:address":"2175 E Kelly Rd",
    "sg:city":"Frankfort",
    "sg:classifiers":[
        {
            "category":"Manufacturing",
            "subcategory":"Pet Food",
            "type":"Manufacturing & Wholesale Goods"
        }
    ],
    "sg:phone":"+1 765 659 4711",
    "sg:postcode":"46041",
    "sg:province":"IN",
    "sg:tags":[
        "feed"
    ],
    "wof:name":"Prairie Stream Farms",
    "wof:placetype":"venue"
},
  "geometry": {"coordinates":[-86.480274,40.264218],"type":"Point"}
}