{
  "type": "Feature",
  "properties": {
    "iso:country":"US",
    "sg:address":"722 E County Line Rd",
    "sg:city":"Indianapolis",
    "sg:classifiers":[
        {
            "category":"Place Of Worship",
            "subcategory":"Church",
            "type":"Public Place"
        },
        {
            "category":"Place Of Worship",
            "type":"Public Place"
        },
        {
            "category":"Education",
            "subcategory":"School",
            "type":"Public Place"
        }
    ],
    "sg:phone":"+1 317 888 3366",
    "sg:postcode":"46227",
    "sg:province":"IN",
    "sg:tags":[
        "k-",
        "churches-baptist-general",
        "private",
        "churches-baptist-independent",
        "churches-baptist"
    ],
    "sg:website":"http://www.suburbanbaptist.org",
    "wof:name":"Suburban Baptist Church",
    "wof:placetype":"venue"
},
  "geometry": {"coordinates":[-86.144265,39.635264],"type":"Point"}
}