{
  "type": "Feature",
  "properties": {
    "iso:country":"US",
    "sg:address":"5820 Grape Rd",
    "sg:city":"Bremen",
    "sg:classifiers":[
        {
            "category":"Shopping",
            "type":"Retail Goods"
        }
    ],
    "sg:phone":"+1 574 546 3203",
    "sg:postcode":"46506",
    "sg:province":"IN",
    "sg:tags":[
        "merchandise"
    ],
    "wof:name":"Rita Seitz",
    "wof:placetype":"venue"
},
  "geometry": {"coordinates":[-86.179508,41.393719],"type":"Point"}
}