{
  "type": "Feature",
  "properties": {
    "iso:country":"US",
    "sg:address":"1904 Wayne St",
    "sg:city":"Auburn",
    "sg:classifiers":[
        {
            "category":"Wholesale",
            "subcategory":"Sporting Goods",
            "type":"Manufacturing & Wholesale Goods"
        }
    ],
    "sg:phone":"+1 260 925 2780",
    "sg:postcode":"46706",
    "sg:province":"IN",
    "sg:tags":[
        "equipment",
        "archery",
        "supply"
    ],
    "wof:name":"Storm Archery",
    "wof:placetype":"venue"
},
  "geometry": {"coordinates":[-85.059409,41.352283],"type":"Point"}
}