{
  "type": "Feature",
  "properties": {
    "iso:country":"US",
    "sg:address":"3949 S Dixon Rd",
    "sg:city":"Kokomo",
    "sg:classifiers":[
        {
            "category":"Food & Beverages",
            "subcategory":"Groceries & Convenience Stores",
            "type":"Retail Goods"
        }
    ],
    "sg:phone":"+1 765 453 7244",
    "sg:postcode":"46902",
    "sg:province":"IN",
    "sg:tags":[
        "grocer"
    ],
    "wof:name":"Express",
    "wof:placetype":"venue"
},
  "geometry": {"coordinates":[-86.165196,40.41944],"type":"Point"}
}