{
  "type": "Feature",
  "properties": {
    "iso:country":"US",
    "sg:address":"325 W Main St",
    "sg:city":"Greensburg",
    "sg:classifiers":[
        {
            "category":"Personal",
            "subcategory":"Beauty Salon",
            "type":"Services"
        }
    ],
    "sg:phone":"+1 812 662 0606",
    "sg:postcode":"47240",
    "sg:province":"IN",
    "wof:name":"Main Design Styling Salon",
    "wof:placetype":"venue"
},
  "geometry": {"coordinates":[-85.48759699999999,39.336479],"type":"Point"}
}