{
  "type": "Feature",
  "properties": {
    "addr:full":"1315 Read St Evansville IN 47710",
    "addr:housenumber":"1315",
    "addr:postcode":"47710",
    "addr:street":"Read St",
    "iso:country":"US",
    "sg:address":"1315 Read St",
    "sg:city":"Evansville",
    "sg:classifiers":[
        {
            "category":"Wholesale",
            "subcategory":"Construction Materials",
            "type":"Manufacturing & Wholesale Goods"
        }
    ],
    "sg:phone":"+1 812 429 1001",
    "sg:postcode":"47710",
    "sg:province":"IN",
    "sg:tags":[
        "glass"
    ],
    "wof:name":"King's Distributors",
    "wof:placetype":"venue"
},
  "geometry": {"coordinates":[-87.567832,37.990129],"type":"Point"}
}