{
  "type": "Feature",
  "properties": {
    "iso:country":"US",
    "sg:address":"400 S Harbour Dr",
    "sg:city":"Noblesville",
    "sg:classifiers":[
        {
            "category":"Government",
            "subcategory":"Fire Station",
            "type":"Public Place"
        }
    ],
    "sg:phone":"+1 317 776 6346",
    "sg:postcode":"46062",
    "sg:province":"IN",
    "sg:tags":[
        "department"
    ],
    "wof:name":"Noblesville Fire Dept",
    "wof:placetype":"venue"
},
  "geometry": {"coordinates":[-86.049964,40.060774],"type":"Point"}
}