{
  "type": "Feature",
  "properties": {
    "iso:country":"US",
    "sg:address":"10850 S Hwy 11 SE",
    "sg:city":"Laconia",
    "sg:classifiers":[
        {
            "category":"Government",
            "subcategory":"Fire Station",
            "type":"Public Place"
        }
    ],
    "sg:phone":"+1 812 737 1952",
    "sg:postcode":"47135",
    "sg:province":"IN",
    "sg:tags":[
        "department"
    ],
    "wof:name":"Boone Township Volunteer Fire",
    "wof:placetype":"venue"
},
  "geometry": {"coordinates":[-86.08214099999999,38.039728],"type":"Point"}
}