{
  "type": "Feature",
  "properties": {
    "iso:country":"US",
    "sg:address":"106 N Ferguson St",
    "sg:city":"Henryville",
    "sg:classifiers":[
        {
            "category":"Organizations",
            "subcategory":"Religious Organization",
            "type":"Services"
        }
    ],
    "sg:phone":"+1 812 294 4633",
    "sg:postcode":"47126",
    "sg:province":"IN",
    "wof:name":"Henryvlcommunity Presbt Church",
    "wof:placetype":"venue"
},
  "geometry": {"coordinates":[-85.768106,38.542417],"type":"Point"}
}