{
  "type": "Feature",
  "properties": {
    "iso:country":"US",
    "sg:address":"108 S 4th St",
    "sg:city":"Jeffersonville",
    "sg:classifiers":[
        {
            "category":"Restaurant",
            "type":"Food & Drink"
        }
    ],
    "sg:phone":"+1 812 288 2411",
    "sg:postcode":"47130",
    "sg:province":"IN",
    "wof:name":"Babby's Steakhouse",
    "wof:placetype":"venue"
},
  "geometry": {"coordinates":[-85.652661,38.335905],"type":"Point"}
}