{
  "type": "Feature",
  "properties": {
    "addr:full":"6321 Constitution Dr Fort Wayne IN 46804",
    "addr:housenumber":"6321",
    "addr:postcode":"46804",
    "addr:street":"Constitution Dr",
    "iso:country":"US",
    "sg:address":"6321 Constitution Dr",
    "sg:city":"Fort Wayne",
    "sg:classifiers":[
        {
            "category":"Personal",
            "subcategory":"Beauty Salon",
            "type":"Services"
        }
    ],
    "sg:phone":"+1 260 432 2886",
    "sg:postcode":"46804",
    "sg:province":"IN",
    "wof:name":"Jeffrey Deetz Inc",
    "wof:placetype":"venue"
},
  "geometry": {"coordinates":[-85.226474,41.067863],"type":"Point"}
}