{
  "type": "Feature",
  "properties": {
    "iso:country":"US",
    "sg:address":"230 S Hall St",
    "sg:city":"Francisco",
    "sg:classifiers":[
        {
            "category":"Government",
            "subcategory":"Office",
            "type":"Public Place"
        }
    ],
    "sg:phone":"+1 812 782 3573",
    "sg:postcode":"47670",
    "sg:province":"IN",
    "sg:tags":[
        "city"
    ],
    "wof:name":"Francisco Town Hall",
    "wof:placetype":"venue"
},
  "geometry": {"coordinates":[-87.57120399999999,38.353925],"type":"Point"}
}