{
  "type": "Feature",
  "properties": {
    "addr:full":"7965 US Hwy 31 S Indianapolis IN 46227",
    "addr:housenumber":"7965",
    "addr:postcode":"46227",
    "addr:street":"Us Hwy 31 S",
    "iso:country":"US",
    "sg:address":"7965 US Hwy 31 S",
    "sg:city":"Indianapolis",
    "sg:classifiers":[
        {
            "category":"Home & Garden",
            "subcategory":"Building Materials",
            "type":"Retail Goods"
        }
    ],
    "sg:phone":"+1 317 887 6625",
    "sg:postcode":"46227",
    "sg:province":"IN",
    "sg:tags":[
        "glass",
        "window",
        "plate"
    ],
    "wof:name":"Harmon Auto Glass",
    "wof:placetype":"venue"
},
  "geometry": {"coordinates":[-86.137513,39.651016],"type":"Point"}
}