{
  "type": "Feature",
  "properties": {
    "iso:country":"US",
    "sg:address":"412 S Main St",
    "sg:city":"New Castle",
    "sg:classifiers":[
        {
            "category":"Banks & Credit Unions",
            "subcategory":"Investment Brokerage",
            "type":"Services"
        }
    ],
    "sg:phone":"+1 765 593 2485",
    "sg:postcode":"47362",
    "sg:province":"IN",
    "sg:tags":[
        "advisory",
        "financial"
    ],
    "wof:name":"Shoreline Asset Management",
    "wof:placetype":"venue"
},
  "geometry": {"coordinates":[-85.370206,39.92875],"type":"Point"}
}