{
  "type": "Feature",
  "properties": {
    "iso:country":"US",
    "sg:address":"1948 Louisiana St",
    "sg:city":"Gary",
    "sg:classifiers":[
        {
            "category":"Social Services",
            "subcategory":"Child Care",
            "type":"Services"
        }
    ],
    "sg:phone":"+1 219 880 0488",
    "sg:postcode":"46407",
    "sg:province":"IN",
    "wof:name":"Su-Ze-Que's Develomental Day",
    "wof:placetype":"venue"
},
  "geometry": {"coordinates":[-87.320091,41.582502],"type":"Point"}
}