{
  "type": "Feature",
  "properties": {
    "iso:country":"US",
    "sg:address":"14046 Calumet Ave",
    "sg:city":"Cedar Lake",
    "sg:classifiers":[
        {
            "category":"Farming",
            "subcategory":"Farm",
            "type":"Manufacturing & Wholesale Goods"
        }
    ],
    "sg:phone":"+1 219 374 5091",
    "sg:postcode":"46303",
    "sg:province":"IN",
    "sg:tags":[
        "crop",
        "general"
    ],
    "wof:name":"Willy Dairy Farm",
    "wof:placetype":"venue"
},
  "geometry": {"coordinates":[-87.508058,41.36435],"type":"Point"}
}