{
  "type": "Feature",
  "properties": {
    "addr:full":"6232 Webster St Fort Wayne IN 46807",
    "addr:housenumber":"6232",
    "addr:postcode":"46807",
    "addr:street":"Webster St",
    "iso:country":"US",
    "sg:address":"6232 Webster St",
    "sg:city":"Fort Wayne",
    "sg:classifiers":[
        {
            "category":"Building & Trades",
            "subcategory":"Construction",
            "type":"Services"
        }
    ],
    "sg:phone":"+1 260 744 6595",
    "sg:postcode":"46807",
    "sg:province":"IN",
    "sg:tags":[
        "home",
        "builder"
    ],
    "wof:name":"Leslie Home Office",
    "wof:placetype":"venue"
},
  "geometry": {"coordinates":[-85.13924799999999,41.026946],"type":"Point"}
}