{
  "type": "Feature",
  "properties": {
    "iso:country":"US",
    "sg:address":"8111 US Hwy 36",
    "sg:city":"Avon",
    "sg:classifiers":[
        {
            "category":"Shopping",
            "type":"Retail Goods"
        }
    ],
    "sg:phone":"+1 317 272 1810",
    "sg:postcode":"46123",
    "sg:province":"IN",
    "sg:tags":[
        "spa",
        "hot",
        "tub"
    ],
    "wof:name":"Hotspring Spas",
    "wof:placetype":"venue"
},
  "geometry": {"coordinates":[-86.390187,39.762751],"type":"Point"}
}