{
  "type": "Feature",
  "properties": {
    "iso:country":"US",
    "sg:address":"1060 3rd Ave",
    "sg:city":"Jasper",
    "sg:classifiers":[
        {
            "category":"Building & Trades",
            "subcategory":"Construction",
            "type":"Services"
        }
    ],
    "sg:phone":"+1 812 482 1125",
    "sg:postcode":"47546",
    "sg:province":"IN",
    "sg:tags":[
        "general",
        "contractor"
    ],
    "sg:website":"www.jasperlumberonline.com",
    "wof:name":"Jasper Lumber Co Inc",
    "wof:placetype":"venue"
},
  "geometry": {"coordinates":[-86.912993,38.374164],"type":"Point"}
}