{
  "type": "Feature",
  "properties": {
    "iso:country":"US",
    "sg:address":"6676 S Co Rd 725 E",
    "sg:city":"Plainfield",
    "sg:classifiers":[
        {
            "category":"Freight",
            "type":"Transportation"
        }
    ],
    "sg:phone":"+1 317 839 5584",
    "sg:postcode":"46168",
    "sg:province":"IN",
    "sg:tags":[
        "trucking"
    ],
    "wof:name":"Robert P Pedigo Inc",
    "wof:placetype":"venue"
},
  "geometry": {"coordinates":[-86.39533900000001,39.662357],"type":"Point"}
}