{
  "type": "Feature",
  "properties": {
    "iso:country":"US",
    "sg:address":"33 N 5th St",
    "sg:city":"Scottsburg",
    "sg:classifiers":[
        {
            "category":"Real Estate",
            "subcategory":"Real Estate Operator",
            "type":"Services"
        }
    ],
    "sg:phone":"+1 812 754 0949",
    "sg:postcode":"47170",
    "sg:province":"IN",
    "sg:tags":[
        "building",
        "apartment"
    ],
    "wof:name":"Valley Manor Apartments",
    "wof:placetype":"venue"
},
  "geometry": {"coordinates":[-85.76497999999999,38.686344],"type":"Point"}
}