{
  "type": "Feature",
  "properties": {
    "iso:country":"US",
    "sg:address":"581 W Whitney St",
    "sg:city":"Montpelier",
    "sg:classifiers":[
        {
            "category":"Recreation",
            "type":"Entertainment"
        }
    ],
    "sg:phone":"+1 765 728 8808",
    "sg:postcode":"47359",
    "sg:province":"IN",
    "sg:tags":[
        "parks"
    ],
    "wof:name":"Montpelier Community Park",
    "wof:placetype":"venue"
},
  "geometry": {"coordinates":[-85.287009,40.549576],"type":"Point"}
}