{
  "type": "Feature",
  "properties": {
    "iso:country":"US",
    "sg:address":"1101 E 1st St",
    "sg:city":"Muncie",
    "sg:classifiers":[
        {
            "category":"Food & Beverages",
            "subcategory":"Bakery",
            "type":"Retail Goods"
        }
    ],
    "sg:phone":"+1 765 282 0717",
    "sg:postcode":"47302",
    "sg:province":"IN",
    "sg:tags":[
        "baker"
    ],
    "wof:name":"Traci's Bakery",
    "wof:placetype":"venue"
},
  "geometry": {"coordinates":[-85.373893,40.187595],"type":"Point"}
}