{
  "type": "Feature",
  "properties": {
    "addr:full":"1 W Mill Rd Evansville IN 47710",
    "addr:housenumber":"1",
    "addr:postcode":"47710",
    "addr:street":"W Mill Rd",
    "iso:country":"US",
    "sg:address":"1 W Mill Rd",
    "sg:city":"Evansville",
    "sg:classifiers":[
        {
            "category":"Government",
            "subcategory":"Office",
            "type":"Public Place"
        }
    ],
    "sg:phone":"+1 812 436 4927",
    "sg:postcode":"47710",
    "sg:province":"IN",
    "sg:tags":[
        "village"
    ],
    "wof:name":"Evansville Human Relations",
    "wof:placetype":"venue"
},
  "geometry": {"coordinates":[-87.567752,38.021268],"type":"Point"}
}