{
  "type": "Feature",
  "properties": {
    "iso:country":"US",
    "sg:address":"17041 Westfield Park Rd",
    "sg:city":"Westfield",
    "sg:classifiers":[
        {
            "category":"Building & Trades",
            "subcategory":"Construction",
            "type":"Services"
        }
    ],
    "sg:phone":"+1 317 867 2606",
    "sg:postcode":"46074",
    "sg:province":"IN",
    "sg:tags":[
        "excavating",
        "contractor"
    ],
    "wof:name":"Excavating Specialists LLC",
    "wof:placetype":"venue"
},
  "geometry": {"coordinates":[-86.138573,40.042674],"type":"Point"}
}