{
  "type": "Feature",
  "properties": {
    "iso:country":"US",
    "sg:address":"307 S Main St",
    "sg:city":"South Bend",
    "sg:classifiers":[
        {
            "category":"Retail",
            "subcategory":"Repair Shop",
            "type":"Services"
        }
    ],
    "sg:phone":"+1 574 236 5535",
    "sg:postcode":"46601",
    "sg:province":"IN",
    "sg:tags":[
        "equipment",
        "telephone",
        "system"
    ],
    "wof:name":"Indiana Bell Comms Inc",
    "wof:placetype":"venue"
},
  "geometry": {"coordinates":[-86.251991,41.673066],"type":"Point"}
}