{
  "type": "Feature",
  "properties": {
    "iso:country":"US",
    "sg:address":"22230 Farmwood Dr",
    "sg:city":"Bristol",
    "sg:classifiers":[
        {
            "category":"Building & Trades",
            "subcategory":"Construction",
            "type":"Services"
        }
    ],
    "sg:phone":"+1 574 264 4403",
    "sg:postcode":"46507",
    "sg:province":"IN",
    "sg:tags":[
        "painter"
    ],
    "wof:name":"Jeffrey Cooper Painting",
    "wof:placetype":"venue"
},
  "geometry": {"coordinates":[-85.893555,41.714221],"type":"Point"}
}