{
  "type": "Feature",
  "properties": {
    "iso:country":"US",
    "sg:address":"401 Coliseum Blvd E",
    "sg:city":"Fort Wayne",
    "sg:classifiers":[
        {
            "category":"Professional",
            "subcategory":"Computer Services",
            "type":"Services"
        }
    ],
    "sg:phone":"+1 260 482 8727",
    "sg:postcode":"46805",
    "sg:province":"IN",
    "sg:tags":[
        "repair"
    ],
    "wof:name":"Virtual Computers",
    "wof:placetype":"venue"
},
  "geometry": {"coordinates":[-85.128485,41.117964],"type":"Point"}
}