{
  "type": "Feature",
  "properties": {
    "iso:country":"US",
    "sg:address":"2550 N Park Rd",
    "sg:city":"Connersville",
    "sg:classifiers":[
        {
            "category":"Government",
            "subcategory":"Office",
            "type":"Public Place"
        }
    ],
    "sg:phone":"+1 765 825 8995",
    "sg:postcode":"47331",
    "sg:province":"IN",
    "sg:tags":[
        "village"
    ],
    "wof:name":"Connersville Treatment Plant",
    "wof:placetype":"venue"
},
  "geometry": {"coordinates":[-85.129035,39.664502],"type":"Point"}
}