{
  "type": "Feature",
  "properties": {
    "addr:full":"1709 Driftwood Dr Clarksville IN 47129",
    "addr:housenumber":"1709",
    "addr:postcode":"47129",
    "addr:street":"Driftwood Dr",
    "iso:country":"US",
    "sg:address":"1709 Driftwood Dr",
    "sg:city":"Clarksville",
    "sg:classifiers":[
        {
            "category":"Building & Trades",
            "subcategory":"Construction",
            "type":"Services"
        }
    ],
    "sg:phone":"+1 812 945 1032",
    "sg:postcode":"47129",
    "sg:province":"IN",
    "sg:tags":[
        "general",
        "contractor"
    ],
    "wof:name":"Adams Construction Svc",
    "wof:placetype":"venue"
},
  "geometry": {"coordinates":[-85.779376,38.313655],"type":"Point"}
}