{
  "type": "Feature",
  "properties": {
    "iso:country":"US",
    "sg:address":"409 E 1st St",
    "sg:city":"Fowler",
    "sg:classifiers":[
        {
            "category":"Real Estate",
            "subcategory":"Real Estate Operator",
            "type":"Services"
        }
    ],
    "sg:phone":"+1 765 884 1247",
    "sg:postcode":"47944",
    "sg:province":"IN",
    "sg:tags":[
        "property",
        "lessor"
    ],
    "wof:name":"Robert Freeland",
    "wof:placetype":"venue"
},
  "geometry": {"coordinates":[-87.319178,40.621591],"type":"Point"}
}