{
  "type": "Feature",
  "properties": {
    "iso:country":"US",
    "sg:address":"116 S Main St",
    "sg:city":"Bluffton",
    "sg:classifiers":[
        {
            "category":"Real Estate",
            "subcategory":"Real Estate Services",
            "type":"Services"
        }
    ],
    "sg:phone":"+1 260 824 5263",
    "sg:postcode":"46714",
    "sg:province":"IN",
    "sg:tags":[
        "company",
        "title"
    ],
    "wof:name":"Wells County Land Title",
    "wof:placetype":"venue"
},
  "geometry": {"coordinates":[-85.17153,40.739596],"type":"Point"}
}