{
  "type": "Feature",
  "properties": {
    "iso:country":"US",
    "sg:address":"1201 E Chicago Ave",
    "sg:city":"East Chicago",
    "sg:classifiers":[
        {
            "category":"Wholesale",
            "subcategory":"Groceries",
            "type":"Manufacturing & Wholesale Goods"
        }
    ],
    "sg:phone":"+1 219 397 0015",
    "sg:postcode":"46312",
    "sg:province":"IN",
    "sg:tags":[
        "food",
        "broker"
    ],
    "wof:name":"Carniceria LA Chiquita",
    "wof:placetype":"venue"
},
  "geometry": {"coordinates":[-87.45544099999999,41.628834],"type":"Point"}
}