{
  "type": "Feature",
  "properties": {
    "iso:country":"US",
    "sg:address":"45 Chestnut St",
    "sg:city":"Shoals",
    "sg:classifiers":[
        {
            "category":"Local Transit",
            "type":"Transportation"
        }
    ],
    "sg:phone":"+1 812 247 2545",
    "sg:postcode":"47581",
    "sg:province":"IN",
    "sg:tags":[
        "ambulance"
    ],
    "wof:name":"W & G Ambulance",
    "wof:placetype":"venue"
},
  "geometry": {"coordinates":[-86.798236,38.671025],"type":"Point"}
}