{
  "type": "Feature",
  "properties": {
    "iso:country":"US",
    "sg:address":"1200 N Detroit St",
    "sg:city":"Lagrange",
    "sg:classifiers":[
        {
            "category":"Manufacturing",
            "subcategory":"Motor Vehicles & Parts",
            "type":"Manufacturing & Wholesale Goods"
        }
    ],
    "sg:phone":"+1 260 463 8800",
    "sg:postcode":"46761",
    "sg:province":"IN",
    "sg:tags":[
        "recreational",
        "camper"
    ],
    "wof:name":"Starcraft Rv Inc",
    "wof:placetype":"venue"
},
  "geometry": {"coordinates":[-85.425276,41.65866],"type":"Point"}
}