{
  "type": "Feature",
  "properties": {
    "addr:full":"6520 S 950 W South Whitley IN 46787",
    "addr:housenumber":"6520;950",
    "addr:postcode":"46787",
    "addr:street":"S;W South",
    "iso:country":"US",
    "sg:address":"6520 S 950 W",
    "sg:city":"South Whitley",
    "sg:classifiers":[
        {
            "category":"Building & Trades",
            "subcategory":"Construction",
            "type":"Services"
        }
    ],
    "sg:phone":"+1 260 723 5875",
    "sg:postcode":"46787",
    "sg:province":"IN",
    "sg:tags":[
        "painter"
    ],
    "wof:name":"Chris Westrick Painting",
    "wof:placetype":"venue"
},
  "geometry": {"coordinates":[-85.679361,41.069461],"type":"Point"}
}