{
  "type": "Feature",
  "properties": {
    "iso:country":"US",
    "sg:address":"322 S Main St",
    "sg:city":"Kokomo",
    "sg:classifiers":[
        {
            "category":"Health Services",
            "subcategory":"Clinic",
            "type":"Services"
        }
    ],
    "sg:phone":"+1 765 452 0495",
    "sg:postcode":"46901",
    "sg:province":"IN",
    "wof:name":"Howard Regional Health",
    "wof:placetype":"venue"
},
  "geometry": {"coordinates":[-86.131135,40.481643],"type":"Point"}
}