{
  "type": "Feature",
  "properties": {
    "iso:country":"US",
    "sg:address":"8910 US 31 S",
    "sg:city":"Indianapolis",
    "sg:classifiers":[
        {
            "category":"Banks & Credit Unions",
            "subcategory":"Investment Brokerage",
            "type":"Services"
        },
        {
            "category":"Banks & Credit Unions",
            "subcategory":"Bank",
            "type":"Services"
        },
        {
            "category":"Banks & Credit Unions",
            "subcategory":"Financial Services",
            "type":"Services"
        }
    ],
    "sg:phone":"+1 317 266 5100",
    "sg:postcode":"46227",
    "sg:province":"IN",
    "sg:tags":[
        "loan"
    ],
    "sg:website":"http://www.chase.com",
    "wof:name":"Chase -County Line South",
    "wof:placetype":"venue"
},
  "geometry": {"coordinates":[-86.128174,39.637285],"type":"Point"}
}