{
  "type": "Feature",
  "properties": {
    "iso:country":"US",
    "sg:address":"107 S Water St",
    "sg:city":"Salem",
    "sg:classifiers":[
        {
            "category":"Shopping",
            "type":"Retail Goods"
        }
    ],
    "sg:phone":"+1 812 883 4600",
    "sg:postcode":"47167",
    "sg:province":"IN",
    "sg:tags":[
        "feed",
        "fertilizer"
    ],
    "wof:name":"Farmers Produce Company",
    "wof:placetype":"venue"
},
  "geometry": {"coordinates":[-86.102131,38.605668],"type":"Point"}
}