{
  "type": "Feature",
  "properties": {
    "iso:country":"US",
    "sg:address":"8793 N Baltimore Rd",
    "sg:city":"Monrovia",
    "sg:classifiers":[
        {
            "category":"Retail",
            "subcategory":"Auto Repair",
            "type":"Services"
        }
    ],
    "sg:phone":"+1 317 996 2675",
    "sg:postcode":"46157",
    "sg:province":"IN",
    "sg:tags":[
        "automobile",
        "customizing"
    ],
    "wof:name":"Thompson Striping Inc",
    "wof:placetype":"venue"
},
  "geometry": {"coordinates":[-86.484107,39.554079],"type":"Point"}
}