{
  "type": "Feature",
  "properties": {
    "iso:country":"US",
    "sg:address":"89 Woodcrest Dr",
    "sg:city":"Martinsville",
    "sg:classifiers":[
        {
            "category":"Professional",
            "subcategory":"Lawyer & Legal Services",
            "type":"Services"
        }
    ],
    "sg:phone":"+1 765 342 3211",
    "sg:postcode":"46151",
    "sg:province":"IN",
    "sg:tags":[
        "attorney"
    ],
    "wof:name":"William H Wehrle Law Office",
    "wof:placetype":"venue"
},
  "geometry": {"coordinates":[-86.393017,39.437813],"type":"Point"}
}