{
  "type": "Feature",
  "properties": {
    "addr:full":"6307 English Ave Indianapolis IN 46219",
    "addr:housenumber":"6307",
    "addr:postcode":"46219",
    "addr:street":"English Ave",
    "iso:country":"US",
    "sg:address":"6307 English Ave",
    "sg:city":"Indianapolis",
    "sg:classifiers":[
        {
            "category":"Real Estate",
            "subcategory":"Real Estate Agent",
            "type":"Services"
        }
    ],
    "sg:phone":"+1 317 353 2467",
    "sg:postcode":"46219",
    "sg:province":"IN",
    "wof:name":"Refuge Property Management",
    "wof:placetype":"venue"
},
  "geometry": {"coordinates":[-86.058284,39.761032],"type":"Point"}
}