{
  "type": "Feature",
  "properties": {
    "iso:country":"US",
    "sg:address":"4898 Highland Dr",
    "sg:city":"Trafalgar",
    "sg:classifiers":[
        {
            "category":"Communications",
            "type":"Services"
        }
    ],
    "sg:phone":"+1 317 878 4315",
    "sg:postcode":"46181",
    "sg:province":"IN",
    "wof:name":"Jayess Communications",
    "wof:placetype":"venue"
},
  "geometry": {"coordinates":[-86.193892,39.359706],"type":"Point"}
}