{
  "type": "Feature",
  "properties": {
    "iso:country":"US",
    "sg:address":"3690 W 30th St",
    "sg:city":"Indianapolis",
    "sg:classifiers":[
        {
            "category":"Personal",
            "subcategory":"Beauty Salon",
            "type":"Services"
        }
    ],
    "sg:phone":"+1 317 920 9580",
    "sg:postcode":"46222",
    "sg:province":"IN",
    "wof:name":"Designer Touch",
    "wof:placetype":"venue"
},
  "geometry": {"coordinates":[-86.22323400000001,39.809655],"type":"Point"}
}