{
  "type": "Feature",
  "properties": {
    "iso:country":"US",
    "sg:address":"302 S Washington St",
    "sg:city":"Marion",
    "sg:classifiers":[
        {
            "category":"Banks & Credit Unions",
            "subcategory":"Bank",
            "type":"Services"
        }
    ],
    "sg:phone":"+1 765 662 6611",
    "sg:postcode":"46952",
    "sg:province":"IN",
    "wof:name":"Salin Bank & Trust Co",
    "wof:placetype":"venue"
},
  "geometry": {"coordinates":[-85.659855,40.557902],"type":"Point"}
}