{
  "type": "Feature",
  "properties": {
    "iso:country":"US",
    "sg:address":"204 E Main St",
    "sg:city":"Plainfield",
    "sg:classifiers":[
        {
            "category":"Professional",
            "subcategory":"Accounting & Tax Preparation",
            "type":"Services"
        }
    ],
    "sg:phone":"+1 317 839 2462",
    "sg:postcode":"46168",
    "sg:province":"IN",
    "sg:tags":[
        "accountant"
    ],
    "wof:name":"Terry L Dillon & Co",
    "wof:placetype":"venue"
},
  "geometry": {"coordinates":[-86.399476,39.703872],"type":"Point"}
}