{
  "type": "Feature",
  "properties": {
    "iso:country":"US",
    "sg:address":"655 Tracy Rd",
    "sg:city":"Whiteland",
    "sg:classifiers":[
        {
            "category":"Manufacturing",
            "subcategory":"Printing",
            "type":"Manufacturing & Wholesale Goods"
        }
    ],
    "sg:phone":"+1 317 535 1250",
    "sg:postcode":"46184",
    "sg:province":"IN",
    "sg:tags":[
        "printer"
    ],
    "wof:name":"Print Works Inc",
    "wof:placetype":"venue"
},
  "geometry": {"coordinates":[-86.114581,39.563963],"type":"Point"}
}