{
  "type": "Feature",
  "properties": {
    "addr:full":"3311 Holmans Ln Jeffersonville IN 47130",
    "addr:housenumber":"3311",
    "addr:postcode":"47130",
    "addr:street":"Holmans Ln",
    "iso:country":"US",
    "sg:address":"3311 Holmans Ln",
    "sg:city":"Jeffersonville",
    "sg:classifiers":[
        {
            "category":"Organizations",
            "subcategory":"Religious Organization",
            "type":"Services"
        }
    ],
    "sg:phone":"+1 812 284 0903",
    "sg:postcode":"47130",
    "sg:province":"IN",
    "wof:name":"First Church Of God",
    "wof:placetype":"venue"
},
  "geometry": {"coordinates":[-85.719516,38.329591],"type":"Point"}
}