{
  "type": "Feature",
  "properties": {
    "iso:country":"US",
    "sg:address":"5835 Michigan Rd",
    "sg:city":"Plymouth",
    "sg:classifiers":[
        {
            "category":"Autos & Motor Vehicles",
            "subcategory":"Automobile Sales",
            "type":"Retail Goods"
        }
    ],
    "sg:phone":"+1 574 936 3415",
    "sg:postcode":"46563",
    "sg:province":"IN",
    "sg:tags":[
        "car",
        "dealer"
    ],
    "wof:name":"Snyder Automotive Sales",
    "wof:placetype":"venue"
},
  "geometry": {"coordinates":[-86.313983,41.392165],"type":"Point"}
}