{
  "type": "Feature",
  "properties": {
    "iso:country":"US",
    "sg:address":"2025 E Oregon Church Rd",
    "sg:city":"Terre Haute",
    "sg:classifiers":[
        {
            "category":"Building & Trades",
            "subcategory":"Construction",
            "type":"Services"
        }
    ],
    "sg:phone":"+1 812 299 0082",
    "sg:postcode":"47802",
    "sg:province":"IN",
    "sg:tags":[
        "home",
        "builder"
    ],
    "wof:name":"Mariet Homes Inc",
    "wof:placetype":"venue"
},
  "geometry": {"coordinates":[-87.379333,39.331827],"type":"Point"}
}