{
  "type": "Feature",
  "properties": {
    "addr:full":"11525 Diamond Island Rd Wadesville IN 47638",
    "addr:housenumber":"11525",
    "addr:postcode":"47638",
    "addr:street":"Diamond Island Rd",
    "iso:country":"US",
    "sg:address":"11525 Diamond Island Rd",
    "sg:city":"Wadesville",
    "sg:classifiers":[
        {
            "category":"Manufacturing",
            "subcategory":"Wood Products",
            "type":"Manufacturing & Wholesale Goods"
        }
    ],
    "sg:phone":"+1 812 963 6114",
    "sg:postcode":"47638",
    "sg:province":"IN",
    "sg:tags":[
        "mfg"
    ],
    "wof:name":"P&C Pallet Service",
    "wof:placetype":"venue"
},
  "geometry": {"coordinates":[-87.70016200000001,38.08854],"type":"Point"}
}