{
  "type": "Feature",
  "properties": {
    "iso:country":"US",
    "sg:address":"33 Pine Lake Ave",
    "sg:city":"Laporte",
    "sg:classifiers":[
        {
            "category":"Shopping",
            "type":"Retail Goods"
        }
    ],
    "sg:phone":"+1 219 324 4100",
    "sg:postcode":"46350",
    "sg:province":"IN",
    "sg:tags":[
        "cosmetic",
        "perfume"
    ],
    "wof:name":"Merle Norman Cosmetics",
    "wof:placetype":"venue"
},
  "geometry": {"coordinates":[-86.729254,41.614379],"type":"Point"}
}