{
  "type": "Feature",
  "properties": {
    "iso:country":"US",
    "sg:address":"3240 Lincoln Way E",
    "sg:city":"Mishawaka",
    "sg:classifiers":[
        {
            "category":"Autos & Motor Vehicles",
            "subcategory":"Automobile Sales",
            "type":"Retail Goods"
        }
    ],
    "sg:phone":"+1 574 255 5175",
    "sg:postcode":"46544",
    "sg:province":"IN",
    "sg:tags":[
        "car",
        "dealer"
    ],
    "wof:name":"Car Co",
    "wof:placetype":"venue"
},
  "geometry": {"coordinates":[-86.126366,41.662979],"type":"Point"}
}