{
  "type": "Feature",
  "properties": {
    "addr:full":"360 Brown St West Lafayette IN 47906",
    "addr:housenumber":"360",
    "addr:postcode":"47906",
    "addr:street":"Brown St",
    "iso:country":"US",
    "sg:address":"360 Brown St",
    "sg:city":"West Lafayette",
    "sg:classifiers":[
        {
            "category":"Restaurant",
            "type":"Food & Drink"
        }
    ],
    "sg:phone":"+1 765 743 1188",
    "sg:postcode":"47906",
    "sg:province":"IN",
    "wof:name":"Buffalo Wild Wings Grill & Bar",
    "wof:placetype":"venue"
},
  "geometry": {"coordinates":[-86.899686,40.422083],"type":"Point"}
}