{
  "type": "Feature",
  "properties": {
    "iso:country":"US",
    "sg:address":"202 N Chauncey St",
    "sg:city":"Columbia City",
    "sg:classifiers":[
        {
            "category":"Organizations",
            "subcategory":"Religious Organization",
            "type":"Services"
        }
    ],
    "sg:phone":"+1 260 244 7461",
    "sg:postcode":"46725",
    "sg:province":"IN",
    "wof:name":"First Presbyterian Church",
    "wof:placetype":"venue"
},
  "geometry": {"coordinates":[-85.489796,41.159191],"type":"Point"}
}