{
  "type": "Feature",
  "properties": {
    "iso:country":"US",
    "sg:address":"2854 Co Rd 250 W",
    "sg:city":"Liberty",
    "sg:classifiers":[
        {
            "category":"Home & Garden",
            "subcategory":"Garden Supply",
            "type":"Retail Goods"
        }
    ],
    "sg:phone":"+1 765 458 5400",
    "sg:postcode":"47353",
    "sg:province":"IN",
    "sg:tags":[
        "nurseryman"
    ],
    "wof:name":"Byrd Tree Planting Svc",
    "wof:placetype":"venue"
},
  "geometry": {"coordinates":[-84.973983,39.671846],"type":"Point"}
}