{
  "type": "Feature",
  "properties": {
    "addr:full":"5450 Totten Ford Rd NW Depauw IN 47115",
    "addr:housenumber":"5450",
    "addr:postcode":"depauw;47115",
    "addr:street":"Totten Ford Rd Nw",
    "iso:country":"US",
    "sg:address":"5450 Totten Ford Rd NW",
    "sg:city":"Depauw",
    "sg:classifiers":[
        {
            "category":"Manufacturing",
            "subcategory":"Printing",
            "type":"Manufacturing & Wholesale Goods"
        }
    ],
    "sg:phone":"+1 812 347 3842",
    "sg:postcode":"47115",
    "sg:province":"IN",
    "sg:tags":[
        "publishing"
    ],
    "wof:name":"Creative Publishing",
    "wof:placetype":"venue"
},
  "geometry": {"coordinates":[-86.231886,38.378571],"type":"Point"}
}