{
  "type": "Feature",
  "properties": {
    "addr:full":"1252 S US Hwy 33 Wolflake IN 46767",
    "addr:housenumber":"1252",
    "addr:postcode":"46767",
    "addr:street":"S Us Hwy 33 Wolflake",
    "iso:country":"US",
    "sg:address":"1252 S US Hwy 33",
    "sg:city":"Wolflake",
    "sg:classifiers":[
        {
            "category":"Bars & Pubs",
            "type":"Food & Drink"
        }
    ],
    "sg:phone":"+1 260 635 8249",
    "sg:postcode":"46767",
    "sg:province":"IN",
    "wof:name":"Wolf Lake Bar & Grill",
    "wof:placetype":"venue"
},
  "geometry": {"coordinates":[-85.499054,41.337129],"type":"Point"}
}