{
  "type": "Feature",
  "properties": {
    "iso:country":"US",
    "sg:address":"204 E Morgan St",
    "sg:city":"Kokomo",
    "sg:classifiers":[
        {
            "category":"Wholesale",
            "subcategory":"Farm Supplies",
            "type":"Manufacturing & Wholesale Goods"
        }
    ],
    "sg:phone":"+1 765 457 4383",
    "sg:postcode":"46901",
    "sg:province":"IN",
    "wof:name":"North Central Cooperative Inc",
    "wof:placetype":"venue"
},
  "geometry": {"coordinates":[-86.12952900000001,40.505487],"type":"Point"}
}