{
  "type": "Feature",
  "properties": {
    "iso:country":"US",
    "sg:address":"1011 S Main St",
    "sg:city":"South Bend",
    "sg:classifiers":[
        {
            "category":"Wholesale",
            "subcategory":"Painting Supplies",
            "type":"Manufacturing & Wholesale Goods"
        }
    ],
    "sg:phone":"+1 574 237 9750",
    "sg:postcode":"46601",
    "sg:province":"IN",
    "sg:tags":[
        "paint"
    ],
    "wof:name":"Finish Stop",
    "wof:placetype":"venue"
},
  "geometry": {"coordinates":[-86.251785,41.663566],"type":"Point"}
}