{
  "type": "Feature",
  "properties": {
    "iso:country":"US",
    "sg:address":"54306 Co Rd 5",
    "sg:city":"Elkhart",
    "sg:classifiers":[
        {
            "category":"Retail",
            "subcategory":"Animal Services",
            "type":"Services"
        }
    ],
    "sg:phone":"+1 574 262 3166",
    "sg:postcode":"46514",
    "sg:province":"IN",
    "sg:tags":[
        "pet",
        "grooming",
        "washing"
    ],
    "wof:name":"All My Four Legged Friends",
    "wof:placetype":"venue"
},
  "geometry": {"coordinates":[-85.990239,41.704155],"type":"Point"}
}