{
  "type": "Feature",
  "properties": {
    "iso:country":"US",
    "sg:address":"163 Big Doe Run Rd",
    "sg:city":"Madison",
    "sg:classifiers":[
        {
            "category":"Shopping",
            "subcategory":"Gifts & Souvenirs",
            "type":"Retail Goods"
        }
    ],
    "sg:phone":"+1 812 427 2203",
    "sg:postcode":"47250",
    "sg:province":"IN",
    "sg:tags":[
        "craft"
    ],
    "wof:name":"Lees Country Woodcraft",
    "wof:placetype":"venue"
},
  "geometry": {"coordinates":[-85.184309,38.772486],"type":"Point"}
}