{
  "type": "Feature",
  "properties": {
    "iso:country":"US",
    "sg:address":"7755 Crossgate Ln",
    "sg:city":"Indianapolis",
    "sg:classifiers":[
        {
            "category":"Food & Beverages",
            "subcategory":"Specialty",
            "type":"Retail Goods"
        }
    ],
    "sg:phone":"+1 317 889 6338",
    "sg:postcode":"46227",
    "sg:province":"IN",
    "sg:tags":[
        "gourmet",
        "coffee",
        "product",
        "related"
    ],
    "wof:name":"Barnies Coffee and Tea",
    "wof:placetype":"venue"
},
  "geometry": {"coordinates":[-86.112761,39.654842],"type":"Point"}
}