{
  "type": "Feature",
  "properties": {
    "iso:country":"US",
    "sg:address":"3087 Wabash Ave",
    "sg:city":"Terre Haute",
    "sg:classifiers":[
        {
            "category":"Restaurant",
            "type":"Food & Drink"
        }
    ],
    "sg:phone":"+1 812 238 9790",
    "sg:postcode":"47803",
    "sg:province":"IN",
    "wof:name":"Burger King",
    "wof:placetype":"venue"
},
  "geometry": {"coordinates":[-87.368512,39.472459],"type":"Point"}
}