{
  "type": "Feature",
  "properties": {
    "addr:full":"1 Court House Plz Shelbyville IN 46140",
    "addr:housenumber":"1",
    "addr:postcode":"46140",
    "addr:street":"Court House Plz",
    "iso:country":"US",
    "sg:address":"1 Court House Plz",
    "sg:city":"Shelbyville",
    "sg:classifiers":[
        {
            "category":"Recreation",
            "type":"Entertainment"
        }
    ],
    "sg:phone":"+1 317 421 2141",
    "sg:postcode":"46140",
    "sg:province":"IN",
    "sg:tags":[
        "carnival"
    ],
    "wof:name":"Riley Festival",
    "wof:placetype":"venue"
},
  "geometry": {"coordinates":[-86.38759400000001,39.70632],"type":"Point"}
}