{
  "type": "Feature",
  "properties": {
    "addr:full":"3101 Elmwood Ave Lafayette IN 47904",
    "addr:housenumber":"3101",
    "addr:postcode":"47904",
    "addr:street":"Elmwood Ave",
    "iso:country":"US",
    "sg:address":"3101 Elmwood Ave",
    "sg:city":"Lafayette",
    "sg:classifiers":[
        {
            "category":"Education",
            "subcategory":"School",
            "type":"Public Place"
        }
    ],
    "sg:phone":"+1 765 771 6140",
    "sg:postcode":"47904",
    "sg:province":"IN",
    "wof:name":"Vinton Elementary School",
    "wof:placetype":"venue"
},
  "geometry": {"coordinates":[-86.862163,40.43622],"type":"Point"}
}