{
  "type": "Feature",
  "properties": {
    "iso:country":"US",
    "sg:address":"722 3rd St",
    "sg:city":"Columbus",
    "sg:classifiers":[
        {
            "category":"Professional",
            "subcategory":"Lawyer & Legal Services",
            "type":"Services"
        }
    ],
    "sg:phone":"+1 812 372 8818",
    "sg:postcode":"47201",
    "sg:province":"IN",
    "sg:tags":[
        "attorney"
    ],
    "wof:name":"Aaron Edwards",
    "wof:placetype":"venue"
},
  "geometry": {"coordinates":[-85.916035,39.201649],"type":"Point"}
}