{
  "type": "Feature",
  "properties": {
    "iso:country":"US",
    "sg:address":"15241 Stoney Creek Way",
    "sg:city":"Noblesville",
    "sg:classifiers":[
        {
            "category":"Manufacturing",
            "subcategory":"Tools & Machinery",
            "type":"Manufacturing & Wholesale Goods"
        }
    ],
    "sg:phone":"+1 317 776 8817",
    "sg:postcode":"46060",
    "sg:province":"IN",
    "sg:tags":[
        "equipment",
        "electric"
    ],
    "sg:website":"www.breakersunlimited.com",
    "wof:name":"Breakers Unlimited Inc",
    "wof:placetype":"venue"
},
  "geometry": {"coordinates":[-86.007757,40.00809],"type":"Point"}
}