{
  "type": "Feature",
  "properties": {
    "iso:country":"US",
    "sg:address":"324 Mount Pleasant Rd",
    "sg:city":"Bedford",
    "sg:classifiers":[
        {
            "category":"Retail",
            "subcategory":"Auto Repair",
            "type":"Services"
        }
    ],
    "sg:phone":"+1 812 275 5469",
    "sg:postcode":"47421",
    "sg:province":"IN",
    "sg:tags":[
        "general"
    ],
    "wof:name":"Pete S Auto",
    "wof:placetype":"venue"
},
  "geometry": {"coordinates":[-86.470269,38.882719],"type":"Point"}
}