{
  "type": "Feature",
  "properties": {
    "iso:country":"US",
    "sg:address":"9200 W Smith St",
    "sg:city":"Yorktown",
    "sg:classifiers":[
        {
            "category":"Shopping",
            "subcategory":"Hobbies, Toys, & Games",
            "type":"Retail Goods"
        }
    ],
    "sg:phone":"+1 765 759 3852",
    "sg:postcode":"47396",
    "sg:province":"IN",
    "wof:name":"Belle E Buttons",
    "wof:placetype":"venue"
},
  "geometry": {"coordinates":[-85.494917,40.173306],"type":"Point"}
}