{
  "type": "Feature",
  "properties": {
    "iso:country":"US",
    "sg:address":"4150 Crooked Creek Overlook St",
    "sg:city":"Indianapolis",
    "sg:classifiers":[
        {
            "category":"Organizations",
            "subcategory":"Religious Organization",
            "type":"Services"
        }
    ],
    "sg:phone":"+1 317 291 4586",
    "sg:postcode":"46228",
    "sg:province":"IN",
    "wof:name":"J L Thornton Rev",
    "wof:placetype":"venue"
},
  "geometry": {"coordinates":[-86.202486,39.827391],"type":"Point"}
}