{
  "type": "Feature",
  "properties": {
    "iso:country":"US",
    "sg:address":"90 Joseph Ln",
    "sg:city":"Whiteland",
    "sg:classifiers":[
        {
            "category":"Real Estate",
            "subcategory":"Real Estate Services",
            "type":"Services"
        }
    ],
    "sg:phone":"+1 317 535 9791",
    "sg:postcode":"46184",
    "sg:province":"IN",
    "sg:tags":[
        "abstract",
        "title"
    ],
    "wof:name":"Ketcham Kwik Service",
    "wof:placetype":"venue"
},
  "geometry": {"coordinates":[-86.096665,39.539052],"type":"Point"}
}