{
  "type": "Feature",
  "properties": {
    "addr:full":"9193 US Hwy 36 Avon IN 46123",
    "addr:housenumber":"9193",
    "addr:postcode":"46123",
    "addr:street":"Us Hwy 36",
    "iso:country":"US",
    "sg:address":"9193 US Hwy 36",
    "sg:city":"Avon",
    "sg:classifiers":[
        {
            "category":"Wholesale",
            "subcategory":"Auto Parts",
            "type":"Manufacturing & Wholesale Goods"
        }
    ],
    "sg:phone":"+1 317 273 9999",
    "sg:postcode":"46123",
    "sg:province":"IN",
    "sg:tags":[
        "truck",
        "accessory"
    ],
    "wof:name":"Avon Truck-N-Trim",
    "wof:placetype":"venue"
},
  "geometry": {"coordinates":[-86.35168,39.763691],"type":"Point"}
}