{
  "type": "Feature",
  "properties": {
    "iso:country":"US",
    "sg:address":"10 SW 9th St",
    "sg:city":"Richmond",
    "sg:classifiers":[
        {
            "category":"Retail",
            "subcategory":"Laundry & Dry Cleaning",
            "type":"Services"
        }
    ],
    "sg:phone":"+1 765 966 1951",
    "sg:postcode":"47374",
    "sg:province":"IN",
    "sg:tags":[
        "cleaners"
    ],
    "wof:name":"Graham Cleaners Inc",
    "wof:placetype":"venue"
},
  "geometry": {"coordinates":[-84.914843,39.829026],"type":"Point"}
}