{
  "type": "Feature",
  "properties": {
    "iso:country":"US",
    "sg:address":"3844 Rockville Ave",
    "sg:city":"Indianapolis",
    "sg:classifiers":[
        {
            "category":"Autos & Motor Vehicles",
            "subcategory":"Auto Supplies",
            "type":"Retail Goods"
        }
    ],
    "sg:phone":"+1 317 241 2262",
    "sg:postcode":"46241",
    "sg:province":"IN",
    "sg:tags":[
        "tire"
    ],
    "wof:name":"Americas Best Tire",
    "wof:placetype":"venue"
},
  "geometry": {"coordinates":[-86.227188,39.761311],"type":"Point"}
}