{
  "type": "Feature",
  "properties": {
    "iso:country":"US",
    "sg:address":"11854 S 300 W",
    "sg:city":"Brookston",
    "sg:classifiers":[
        {
            "category":"Professional",
            "subcategory":"Business Services",
            "type":"Services"
        }
    ],
    "sg:phone":"+1 765 563 5017",
    "sg:postcode":"47923",
    "sg:province":"IN",
    "wof:name":"Hall Enterprises",
    "wof:placetype":"venue"
},
  "geometry": {"coordinates":[-86.925294,40.577874],"type":"Point"}
}