{
  "type": "Feature",
  "properties": {
    "iso:country":"US",
    "sg:address":"604 S Walsh St",
    "sg:city":"Garrett",
    "sg:classifiers":[
        {
            "category":"Shopping",
            "subcategory":"Florist",
            "type":"Retail Goods"
        }
    ],
    "sg:phone":"+1 260 357 3301",
    "sg:postcode":"46738",
    "sg:province":"IN",
    "wof:name":"Garrett Greenhouse Flower-Gift",
    "wof:placetype":"venue"
},
  "geometry": {"coordinates":[-85.131979,41.345372],"type":"Point"}
}