{
  "type": "Feature",
  "properties": {
    "iso:country":"US",
    "sg:address":"715 S Walnut St",
    "sg:city":"Hartford City",
    "sg:classifiers":[
        {
            "category":"Autos & Motor Vehicles",
            "subcategory":"Automobile Sales",
            "type":"Retail Goods"
        }
    ],
    "sg:phone":"+1 765 348 5246",
    "sg:postcode":"47348",
    "sg:province":"IN",
    "sg:tags":[
        "car",
        "dealer"
    ],
    "wof:name":"Kahn's Auto Sales",
    "wof:placetype":"venue"
},
  "geometry": {"coordinates":[-85.370119,40.444841],"type":"Point"}
}