{
  "type": "Feature",
  "properties": {
    "iso:country":"US",
    "sg:address":"120 Indian Ridge Blvd",
    "sg:city":"Mishawaka",
    "sg:classifiers":[
        {
            "category":"Banks & Credit Unions",
            "subcategory":"Bank",
            "type":"Services"
        }
    ],
    "sg:phone":"+1 574 273 8132",
    "sg:postcode":"46545",
    "sg:province":"IN",
    "wof:name":"Union Federal Savings Loan",
    "wof:placetype":"venue"
},
  "geometry": {"coordinates":[-86.179331,41.712901],"type":"Point"}
}