{
  "type": "Feature",
  "properties": {
    "addr:full":"5681 Broadway Merrillville IN 46410",
    "addr:housenumber":"5681",
    "addr:postcode":"46410",
    "addr:street":"Broadway",
    "iso:country":"US",
    "sg:address":"5681 Broadway",
    "sg:city":"Merrillville",
    "sg:classifiers":[
        {
            "category":"Insurance",
            "subcategory":"Insurance Agent",
            "type":"Services"
        }
    ],
    "sg:phone":"+1 219 985 1111",
    "sg:postcode":"46410",
    "sg:province":"IN",
    "wof:name":"NWN",
    "wof:placetype":"venue"
},
  "geometry": {"coordinates":[-87.336034,41.513855],"type":"Point"}
}