{
  "type": "Feature",
  "properties": {
    "iso:country":"US",
    "sg:address":"418 N Constitution Ave",
    "sg:city":"Goshen",
    "sg:classifiers":[
        {
            "category":"Building & Trades",
            "subcategory":"Construction",
            "type":"Services"
        }
    ],
    "sg:phone":"+1 574 534 0352",
    "sg:postcode":"46526",
    "sg:province":"IN",
    "sg:tags":[
        "masonry",
        "contractor"
    ],
    "wof:name":"Lantz Masonry Inc",
    "wof:placetype":"venue"
},
  "geometry": {"coordinates":[-85.869162,41.588809],"type":"Point"}
}