{
  "type": "Feature",
  "properties": {
    "iso:country":"US",
    "sg:address":"7796 Four Leaf Dr",
    "sg:city":"Greenville",
    "sg:classifiers":[
        {
            "category":"Professional",
            "type":"Services"
        },
        {
            "category":"Retail",
            "subcategory":"Auto Repair",
            "type":"Services"
        }
    ],
    "sg:phone":"+1 812 923 1984",
    "sg:postcode":"47124",
    "sg:province":"IN",
    "sg:tags":[
        "automotive"
    ],
    "wof:name":"Industrial Control System Inc",
    "wof:placetype":"venue"
},
  "geometry": {"coordinates":[-85.948362,38.350694],"type":"Point"}
}