{
  "type": "Feature",
  "properties": {
    "addr:full":"1329 E 12th St Mishawaka IN 46544",
    "addr:housenumber":"1329",
    "addr:postcode":"46544",
    "addr:street":"E 12Th St",
    "iso:country":"US",
    "sg:address":"1329 E 12th St",
    "sg:city":"Mishawaka",
    "sg:classifiers":[
        {
            "category":"Food & Beverages",
            "subcategory":"Groceries & Convenience Stores",
            "type":"Retail Goods"
        }
    ],
    "sg:phone":"+1 574 255 2127",
    "sg:postcode":"46544",
    "sg:province":"IN",
    "wof:name":"7-Eleven",
    "wof:placetype":"venue"
},
  "geometry": {"coordinates":[-86.158349,41.651199],"type":"Point"}
}