{
  "type": "Feature",
  "properties": {
    "iso:country":"US",
    "sg:address":"1623 Estes St",
    "sg:city":"New Castle",
    "sg:classifiers":[
        {
            "category":"Real Estate",
            "subcategory":"Real Estate Operator",
            "type":"Services"
        }
    ],
    "sg:phone":"+1 765 529 2216",
    "sg:postcode":"47362",
    "sg:province":"IN",
    "sg:tags":[
        "apartment"
    ],
    "wof:name":"Mansard Apartments",
    "wof:placetype":"venue"
},
  "geometry": {"coordinates":[-85.364184,39.905895],"type":"Point"}
}