{
  "type": "Feature",
  "properties": {
    "iso:country":"US",
    "sg:address":"5230 W 30th St",
    "sg:city":"Indianapolis",
    "sg:classifiers":[
        {
            "category":"Restaurant",
            "type":"Food & Drink"
        }
    ],
    "sg:phone":"+1 317 299 7378",
    "sg:postcode":"46224",
    "sg:province":"IN",
    "wof:name":"Pepe's Bar & Restaurant",
    "wof:placetype":"venue"
},
  "geometry": {"coordinates":[-86.251637,39.809284],"type":"Point"}
}