{
  "type": "Feature",
  "properties": {
    "iso:country":"US",
    "sg:address":"1125 S Meridian St",
    "sg:city":"Indianapolis",
    "sg:classifiers":[
        {
            "category":"Restaurant",
            "type":"Food & Drink"
        }
    ],
    "sg:phone":"+1 317 639 6241",
    "sg:postcode":"46225",
    "sg:province":"IN",
    "sg:tags":[
        "site",
        "reception",
        "wedding"
    ],
    "wof:name":"Sacred Heart Parish",
    "wof:placetype":"venue"
},
  "geometry": {"coordinates":[-86.159124,39.752456],"type":"Point"}
}