{
  "type": "Feature",
  "properties": {
    "iso:country":"US",
    "sg:address":"54095 Co Rd 39",
    "sg:city":"Middlebury",
    "sg:classifiers":[
        {
            "category":"Building & Trades",
            "subcategory":"Plumbing",
            "type":"Services"
        }
    ],
    "sg:phone":"+1 574 825 5941",
    "sg:postcode":"46540",
    "sg:province":"IN",
    "sg:tags":[
        "tank",
        "septic"
    ],
    "wof:name":"Akins Excavating Inc",
    "wof:placetype":"venue"
},
  "geometry": {"coordinates":[-85.707591,41.712175],"type":"Point"}
}