{
  "type": "Feature",
  "properties": {
    "iso:country":"US",
    "sg:address":"3333 W 800 N",
    "sg:city":"Edinburgh",
    "sg:classifiers":[
        {
            "category":"Freight",
            "type":"Transportation"
        }
    ],
    "sg:phone":"+1 812 526 2694",
    "sg:postcode":"46124",
    "sg:province":"IN",
    "sg:tags":[
        "trucking"
    ],
    "sg:website":"www.iwxmf.com",
    "wof:name":"Indiana Western Express Inc",
    "wof:placetype":"venue"
},
  "geometry": {"coordinates":[-85.961983,39.317683],"type":"Point"}
}