{
  "type": "Feature",
  "properties": {
    "addr:full":"220 Dean Johnson Blvd South Bend IN 46601",
    "addr:housenumber":"220",
    "addr:postcode":"46601",
    "addr:street":"Dean Johnson Blvd",
    "iso:country":"US",
    "sg:address":"220 Dean Johnson Blvd",
    "sg:city":"South Bend",
    "sg:classifiers":[
        {
            "category":"Education",
            "subcategory":"College",
            "type":"Public Place"
        }
    ],
    "sg:phone":"+1 574 289 7001",
    "sg:postcode":"46601",
    "sg:province":"IN",
    "sg:tags":[
        "academic",
        "school"
    ],
    "sg:website":"www.ivytech.edu",
    "wof:name":"Ivy Tech State College",
    "wof:placetype":"venue"
},
  "geometry": {"coordinates":[-86.247933,41.66304],"type":"Point"}
}