{
  "type": "Feature",
  "properties": {
    "iso:country":"US",
    "sg:address":"610 Church St",
    "sg:city":"New Harmony",
    "sg:classifiers":[
        {
            "category":"Restaurant",
            "type":"Food & Drink"
        }
    ],
    "sg:phone":"+1 812 682 3607",
    "sg:postcode":"47631",
    "sg:province":"IN",
    "sg:tags":[
        "caterer"
    ],
    "wof:name":"Cooper House Kitchen & Ctrng",
    "wof:placetype":"venue"
},
  "geometry": {"coordinates":[-87.933231,38.129901],"type":"Point"}
}