{
  "type": "Feature",
  "properties": {
    "iso:country":"US",
    "sg:address":"4388 W Vernal Pike",
    "sg:city":"Bloomington",
    "sg:classifiers":[
        {
            "category":"Building & Trades",
            "subcategory":"Construction",
            "type":"Services"
        }
    ],
    "sg:phone":"+1 812 334 3559",
    "sg:postcode":"47404",
    "sg:province":"IN",
    "sg:tags":[
        "general",
        "contractor"
    ],
    "wof:name":"Meyer & Najem Corp",
    "wof:placetype":"venue"
},
  "geometry": {"coordinates":[-86.588623,39.179273],"type":"Point"}
}