{
  "type": "Feature",
  "properties": {
    "iso:country":"US",
    "sg:address":"120 Tulip Cir",
    "sg:city":"Bremen",
    "sg:classifiers":[
        {
            "category":"Home & Garden",
            "subcategory":"Furniture",
            "type":"Retail Goods"
        }
    ],
    "sg:phone":"+1 574 546 4220",
    "sg:postcode":"46506",
    "sg:province":"IN",
    "sg:tags":[
        "builder",
        "custom"
    ],
    "wof:name":"Jamestree Corp",
    "wof:placetype":"venue"
},
  "geometry": {"coordinates":[-86.132389,41.43759],"type":"Point"}
}