{
  "type": "Feature",
  "properties": {
    "iso:country":"US",
    "sg:address":"2707 Progressive Blvd",
    "sg:city":"Sellersburg",
    "sg:classifiers":[
        {
            "category":"Wholesale",
            "subcategory":"Auto Parts",
            "type":"Manufacturing & Wholesale Goods"
        }
    ],
    "sg:phone":"+1 812 246 0999",
    "sg:postcode":"47172",
    "sg:province":"IN",
    "sg:tags":[
        "equipment",
        "truck"
    ],
    "wof:name":"Mid America Truck Parts",
    "wof:placetype":"venue"
},
  "geometry": {"coordinates":[-85.744715,38.384724],"type":"Point"}
}