{
  "type": "Feature",
  "properties": {
    "iso:country":"US",
    "sg:address":"4601 Illinois Rd",
    "sg:city":"Fort Wayne",
    "sg:classifiers":[
        {
            "category":"Retail",
            "subcategory":"Car Wash",
            "type":"Services"
        }
    ],
    "sg:phone":"+1 260 436 7172",
    "sg:postcode":"46804",
    "sg:province":"IN",
    "sg:tags":[
        "polishing",
        "washing"
    ],
    "wof:name":"Jefferson Pointe Laser Wash",
    "wof:placetype":"venue"
},
  "geometry": {"coordinates":[-85.204908,41.074491],"type":"Point"}
}