{
  "type": "Feature",
  "properties": {
    "iso:country":"US",
    "sg:address":"728 Roosevelt Rd",
    "sg:city":"Walkerton",
    "sg:classifiers":[
        {
            "category":"Food & Beverages",
            "subcategory":"Liquor & Beverages",
            "type":"Retail Goods"
        }
    ],
    "sg:phone":"+1 574 586 3513",
    "sg:postcode":"46574",
    "sg:province":"IN",
    "wof:name":"M-J Package Store Inc",
    "wof:placetype":"venue"
},
  "geometry": {"coordinates":[-86.482143,41.465952],"type":"Point"}
}