{
  "type": "Feature",
  "properties": {
    "iso:country":"US",
    "sg:address":"121 S Independence St",
    "sg:city":"Tipton",
    "sg:classifiers":[
        {
            "category":"Professional",
            "subcategory":"Accounting & Tax Preparation",
            "type":"Services"
        }
    ],
    "sg:phone":"+1 765 675 7444",
    "sg:postcode":"46072",
    "sg:province":"IN",
    "sg:tags":[
        "accountant"
    ],
    "wof:name":"Margaret L Harper Real Estate",
    "wof:placetype":"venue"
},
  "geometry": {"coordinates":[-86.039409,40.282026],"type":"Point"}
}