{
  "type": "Feature",
  "properties": {
    "addr:full":"302 W Broadway St Monticello IN 47960",
    "addr:housenumber":"302",
    "addr:postcode":"47960",
    "addr:street":"W Broadway St",
    "iso:country":"US",
    "sg:address":"302 W Broadway St",
    "sg:city":"Monticello",
    "sg:classifiers":[
        {
            "category":"Autos & Motor Vehicles",
            "subcategory":"Fuel & Gas Station",
            "type":"Retail Goods"
        }
    ],
    "sg:phone":"+1 574 583 9366",
    "sg:postcode":"47960",
    "sg:province":"IN",
    "sg:tags":[
        "oil"
    ],
    "wof:name":"Soker's Host",
    "wof:placetype":"venue"
},
  "geometry": {"coordinates":[-86.764588,40.744985],"type":"Point"}
}