{
  "type": "Feature",
  "properties": {
    "iso:country":"US",
    "sg:address":"1074 Joliet St",
    "sg:city":"Dyer",
    "sg:classifiers":[
        {
            "category":"Bars & Pubs",
            "type":"Food & Drink"
        }
    ],
    "sg:phone":"+1 219 865 9896",
    "sg:postcode":"46311",
    "sg:province":"IN",
    "wof:name":"Finnegan's Wake Irish Pub",
    "wof:placetype":"venue"
},
  "geometry": {"coordinates":[-87.506745,41.492652],"type":"Point"}
}