{
  "type": "Feature",
  "properties": {
    "iso:country":"US",
    "sg:address":"51 E 8th St",
    "sg:city":"Peru",
    "sg:classifiers":[
        {
            "category":"Building & Trades",
            "subcategory":"Construction",
            "type":"Services"
        }
    ],
    "sg:phone":"+1 765 472 7430",
    "sg:postcode":"46970",
    "sg:province":"IN",
    "sg:tags":[
        "resurfacing",
        "laying",
        "refinishing",
        "floor"
    ],
    "wof:name":"Jones Flooring",
    "wof:placetype":"venue"
},
  "geometry": {"coordinates":[-86.066368,40.758503],"type":"Point"}
}