{
  "type": "Feature",
  "properties": {
    "addr:full":"3410 N Wheeling Ave Muncie IN 47304",
    "addr:housenumber":"3410",
    "addr:postcode":"47304",
    "addr:street":"N Wheeling Ave",
    "iso:country":"US",
    "sg:address":"3410 N Wheeling Ave",
    "sg:city":"Muncie",
    "sg:classifiers":[
        {
            "category":"Shopping",
            "subcategory":"Gifts & Souvenirs",
            "type":"Retail Goods"
        }
    ],
    "sg:phone":"+1 765 282 5567",
    "sg:postcode":"47304",
    "sg:province":"IN",
    "sg:tags":[
        "novelty"
    ],
    "wof:name":"Pleasures",
    "wof:placetype":"venue"
},
  "geometry": {"coordinates":[-85.40441199999999,40.222076],"type":"Point"}
}