{
  "type": "Feature",
  "properties": {
    "addr:full":"855 S Emerson Ave Indianapolis IN 46203",
    "addr:housenumber":"855",
    "addr:postcode":"46203",
    "addr:street":"S Emerson Ave",
    "iso:country":"US",
    "sg:address":"855 S Emerson Ave",
    "sg:city":"Indianapolis",
    "sg:classifiers":[
        {
            "category":"Railroad",
            "type":"Transportation"
        }
    ],
    "sg:phone":"+1 317 267 4440",
    "sg:postcode":"46203",
    "sg:province":"IN",
    "wof:name":"Csx Transflo",
    "wof:placetype":"venue"
},
  "geometry": {"coordinates":[-86.082843,39.756228],"type":"Point"}
}