{
  "type": "Feature",
  "properties": {
    "iso:country":"US",
    "sg:address":"3311 Liverpool Rd",
    "sg:city":"Lake Station",
    "sg:classifiers":[
        {
            "category":"Freight",
            "type":"Transportation"
        }
    ],
    "sg:phone":"+1 219 962 7803",
    "sg:postcode":"46405",
    "sg:province":"IN",
    "sg:tags":[
        "trucking"
    ],
    "wof:name":"S & J Transport",
    "wof:placetype":"venue"
},
  "geometry": {"coordinates":[-87.293241,41.557643],"type":"Point"}
}