{
  "type": "Feature",
  "properties": {
    "iso:country":"US",
    "sg:address":"589 S Main St",
    "sg:city":"Churubusco",
    "sg:classifiers":[
        {
            "category":"Manufacturing",
            "subcategory":"Rubber & Plastics",
            "type":"Manufacturing & Wholesale Goods"
        }
    ],
    "sg:phone":"+1 260 693 2171",
    "sg:postcode":"46723",
    "sg:province":"IN",
    "sg:tags":[
        "cut",
        "gd",
        "molded"
    ],
    "sg:website":"www.brcrp.com",
    "wof:name":"Brc Rubber Group",
    "wof:placetype":"venue"
},
  "geometry": {"coordinates":[-85.318029,41.227293],"type":"Point"}
}