{
  "type": "Feature",
  "properties": {
    "iso:country":"US",
    "sg:address":"1953 Broadway",
    "sg:city":"Gary",
    "sg:classifiers":[
        {
            "category":"Manufacturing",
            "subcategory":"Printing",
            "type":"Manufacturing & Wholesale Goods"
        }
    ],
    "sg:phone":"+1 219 880 1772",
    "sg:postcode":"46407",
    "sg:province":"IN",
    "sg:tags":[
        "printer"
    ],
    "wof:name":"AAA Express Printing",
    "wof:placetype":"venue"
},
  "geometry": {"coordinates":[-87.336891,41.583171],"type":"Point"}
}