{
  "type": "Feature",
  "properties": {
    "iso:country":"US",
    "sg:address":"104 N Randolph St",
    "sg:city":"Garrett",
    "sg:classifiers":[
        {
            "category":"Personal",
            "subcategory":"Beauty Salon",
            "type":"Services"
        }
    ],
    "sg:phone":"+1 260 357 3189",
    "sg:postcode":"46738",
    "sg:province":"IN",
    "wof:name":"Hair Depot",
    "wof:placetype":"venue"
},
  "geometry": {"coordinates":[-85.135729,41.351361],"type":"Point"}
}