{
  "type": "Feature",
  "properties": {
    "iso:country":"US",
    "sg:address":"36 Warren St",
    "sg:city":"Hammond",
    "sg:classifiers":[
        {
            "category":"Building & Trades",
            "subcategory":"Construction",
            "type":"Services"
        }
    ],
    "sg:phone":"+1 219 931 6242",
    "sg:postcode":"46320",
    "sg:province":"IN",
    "sg:tags":[
        "nonresidential"
    ],
    "wof:name":"Jaakkola John",
    "wof:placetype":"venue"
},
  "geometry": {"coordinates":[-87.52239899999999,41.608492],"type":"Point"}
}