{
  "type": "Feature",
  "properties": {
    "iso:country":"US",
    "sg:address":"5280 N Murphy Rd",
    "sg:city":"Brazil",
    "sg:classifiers":[
        {
            "category":"Shopping",
            "subcategory":"Crafts & Fabrics",
            "type":"Retail Goods"
        }
    ],
    "sg:phone":"+1 812 446 5502",
    "sg:postcode":"47834",
    "sg:province":"IN",
    "sg:tags":[
        "material",
        "quilting",
        "supply"
    ],
    "wof:name":"Dorothy's Quilt & Crafts",
    "wof:placetype":"venue"
},
  "geometry": {"coordinates":[-87.108447,39.46383],"type":"Point"}
}