{
  "type": "Feature",
  "properties": {
    "iso:country":"US",
    "sg:address":"1408 Miami Ct S",
    "sg:city":"Plainfield",
    "sg:classifiers":[
        {
            "category":"Manufacturing",
            "subcategory":"Retail Goods",
            "type":"Manufacturing & Wholesale Goods"
        }
    ],
    "sg:phone":"+1 317 839 3574",
    "sg:postcode":"46168",
    "sg:province":"IN",
    "sg:tags":[
        "product",
        "mfg"
    ],
    "wof:name":"SLM Industries LLC",
    "wof:placetype":"venue"
},
  "geometry": {"coordinates":[-86.383899,39.69874],"type":"Point"}
}