{
  "type": "Feature",
  "properties": {
    "addr:full":"937 N 12th St Richmond IN 47374",
    "addr:housenumber":"937",
    "addr:postcode":"47374",
    "addr:street":"N 12Th St",
    "iso:country":"US",
    "sg:address":"937 N 12th St",
    "sg:city":"Richmond",
    "sg:classifiers":[
        {
            "category":"Food & Beverages",
            "subcategory":"Liquor & Beverages",
            "type":"Retail Goods"
        }
    ],
    "sg:phone":"+1 765 966 0252",
    "sg:postcode":"47374",
    "sg:province":"IN",
    "wof:name":"J Street Carry Out",
    "wof:placetype":"venue"
},
  "geometry": {"coordinates":[-84.885256,39.840341],"type":"Point"}
}