{
  "type": "Feature",
  "properties": {
    "addr:full":"8311 Lima Rd Fort Wayne IN 46818",
    "addr:housenumber":"8311",
    "addr:postcode":"46818",
    "addr:street":"Lima Rd",
    "iso:country":"US",
    "sg:address":"8311 Lima Rd",
    "sg:city":"Fort Wayne",
    "sg:classifiers":[
        {
            "category":"Restaurant",
            "type":"Food & Drink"
        }
    ],
    "sg:menulink":"http://www.allmenus.com/in/washington/79493-pizza-hut/menu/",
    "sg:phone":"+1 260 969 2400",
    "sg:postcode":"46818",
    "sg:province":"IN",
    "sg:tags":[
        "american",
        "pizza"
    ],
    "wof:name":"Pizza Hut",
    "wof:placetype":"venue"
},
  "geometry": {"coordinates":[-85.165536,41.15636],"type":"Point"}
}