{
  "type": "Feature",
  "properties": {
    "iso:country":"US",
    "sg:address":"15500 Herriman Blvd",
    "sg:city":"Noblesville",
    "sg:classifiers":[
        {
            "category":"Manufacturing",
            "subcategory":"Tools & Machinery",
            "type":"Manufacturing & Wholesale Goods"
        }
    ],
    "sg:phone":"+1 317 773 5600",
    "sg:postcode":"46060",
    "sg:province":"IN",
    "sg:tags":[
        "equipment",
        "system",
        "automation"
    ],
    "sg:website":"www.cimrobotics.com",
    "wof:name":"Cim Systems Inc",
    "wof:placetype":"venue"
},
  "geometry": {"coordinates":[-86.004226,40.01552],"type":"Point"}
}