{
  "type": "Feature",
  "properties": {
    "iso:country":"US",
    "sg:address":"1770 US Hwy 231 N",
    "sg:city":"Crawfordsville",
    "sg:classifiers":[
        {
            "category":"Wholesale",
            "subcategory":"Farm Supplies",
            "type":"Manufacturing & Wholesale Goods"
        }
    ],
    "sg:phone":"+1 765 362 6595",
    "sg:postcode":"47933",
    "sg:province":"IN",
    "sg:tags":[
        "chemical",
        "agricultural"
    ],
    "wof:name":"Thurston Genetics",
    "wof:placetype":"venue"
},
  "geometry": {"coordinates":[-86.908053,40.065622],"type":"Point"}
}