{
  "type": "Feature",
  "properties": {
    "addr:full":"8049 Brookville Rd Indianapolis IN 46239",
    "addr:housenumber":"8049",
    "addr:postcode":"46239",
    "addr:street":"Brookville Rd",
    "iso:country":"US",
    "sg:address":"8049 Brookville Rd",
    "sg:city":"Indianapolis",
    "sg:classifiers":[
        {
            "category":"Retail",
            "subcategory":"Veterinary Services",
            "type":"Services"
        }
    ],
    "sg:phone":"+1 317 353 6143",
    "sg:postcode":"46239",
    "sg:province":"IN",
    "sg:tags":[
        "hospital",
        "animal"
    ],
    "wof:name":"Brookville Road Animal Hosp",
    "wof:placetype":"venue"
},
  "geometry": {"coordinates":[-86.00937500000001,39.746296],"type":"Point"}
}