{
  "type": "Feature",
  "properties": {
    "iso:country":"US",
    "sg:address":"5315 W 74th St",
    "sg:city":"Indianapolis",
    "sg:classifiers":[
        {
            "category":"Health Services",
            "subcategory":"Medical Lab",
            "type":"Services"
        }
    ],
    "sg:phone":"+1 317 532 1099",
    "sg:postcode":"46268",
    "sg:province":"IN",
    "sg:tags":[
        "laboratory"
    ],
    "wof:name":"Zahn Dental",
    "wof:placetype":"venue"
},
  "geometry": {"coordinates":[-86.253019,39.887653],"type":"Point"}
}