{
  "type": "Feature",
  "properties": {
    "iso:country":"US",
    "sg:address":"1100 E 5th St",
    "sg:city":"Anderson",
    "sg:classifiers":[
        {
            "category":"Recreation",
            "type":"Entertainment"
        }
    ],
    "sg:phone":"+1 765 641 4145",
    "sg:postcode":"46012",
    "sg:province":"IN",
    "sg:tags":[
        "hall",
        "auditorium"
    ],
    "sg:website":"www.anderson.edu",
    "wof:name":"Reardon Auditorium Ticket Ofc",
    "wof:placetype":"venue"
},
  "geometry": {"coordinates":[-85.664825,40.111157],"type":"Point"}
}