{
  "type": "Feature",
  "properties": {
    "iso:country":"US",
    "sg:address":"204 W 3rd St",
    "sg:city":"Brookston",
    "sg:classifiers":[
        {
            "category":"Shopping",
            "subcategory":"Used Merchandise",
            "type":"Retail Goods"
        }
    ],
    "sg:phone":"+1 765 563 1000",
    "sg:postcode":"47923",
    "sg:province":"IN",
    "wof:name":"Locust Hill Antiques",
    "wof:placetype":"venue"
},
  "geometry": {"coordinates":[-86.869327,40.602627],"type":"Point"}
}