{
  "type": "Feature",
  "properties": {
    "addr:full":"3916 Saint Joseph Rd New Albany IN 47150",
    "addr:housenumber":"3916",
    "addr:postcode":"47150",
    "addr:street":"Saint Joseph Rd",
    "iso:country":"US",
    "sg:address":"3916 Saint Joseph Rd",
    "sg:city":"New Albany",
    "sg:classifiers":[
        {
            "category":"Building & Trades",
            "subcategory":"Construction",
            "type":"Services"
        }
    ],
    "sg:phone":"+1 502 296 1085",
    "sg:postcode":"47150",
    "sg:province":"IN",
    "sg:tags":[
        "residential"
    ],
    "wof:name":"Byrd Construction Co",
    "wof:placetype":"venue"
},
  "geometry": {"coordinates":[-85.80920399999999,38.349557],"type":"Point"}
}