{
  "type": "Feature",
  "properties": {
    "iso:country":"US",
    "sg:address":"5351 N Co Rd 450 W",
    "sg:city":"Middletown",
    "sg:classifiers":[
        {
            "category":"Professional",
            "type":"Services"
        }
    ],
    "sg:phone":"+1 765 779 0109",
    "sg:postcode":"47356",
    "sg:province":"IN",
    "sg:tags":[
        "establishment"
    ],
    "wof:name":"Just For You",
    "wof:placetype":"venue"
},
  "geometry": {"coordinates":[-85.47114,40.014145],"type":"Point"}
}