{
  "type": "Feature",
  "properties": {
    "addr:full":"209 Oak St Owensville IN 47665",
    "addr:housenumber":"209",
    "addr:postcode":"47665",
    "addr:street":"Oak St",
    "iso:country":"US",
    "sg:address":"209 Oak St",
    "sg:city":"Owensville",
    "sg:classifiers":[
        {
            "category":"Autos & Motor Vehicles",
            "subcategory":"Auto Supplies",
            "type":"Retail Goods"
        }
    ],
    "sg:phone":"+1 812 724 4066",
    "sg:postcode":"47665",
    "sg:province":"IN",
    "sg:tags":[
        "automobile",
        "parts"
    ],
    "wof:name":"Owensville Auto & Parts Supply",
    "wof:placetype":"venue"
},
  "geometry": {"coordinates":[-87.695179,38.27135],"type":"Point"}
}