{
  "type": "Feature",
  "properties": {
    "iso:country":"US",
    "sg:address":"219 Pine Lake Ave",
    "sg:city":"Laporte",
    "sg:classifiers":[
        {
            "category":"Restaurant",
            "type":"Food & Drink"
        }
    ],
    "sg:phone":"+1 219 326 5817",
    "sg:postcode":"46350",
    "sg:province":"IN",
    "wof:name":"Round The Clock Restaurant",
    "wof:placetype":"venue"
},
  "geometry": {"coordinates":[-86.734684,41.61817],"type":"Point"}
}