{
  "type": "Feature",
  "properties": {
    "iso:country":"US",
    "sg:address":"205 S Main St",
    "sg:city":"Elkhart",
    "sg:classifiers":[
        {
            "category":"Home & Garden",
            "subcategory":"Household Appliances",
            "type":"Retail Goods"
        }
    ],
    "sg:phone":"+1 574 293 1001",
    "sg:postcode":"46516",
    "sg:province":"IN",
    "sg:tags":[
        "machine",
        "sewing"
    ],
    "wof:name":"Bueter's Sewing Ctr",
    "wof:placetype":"venue"
},
  "geometry": {"coordinates":[-85.972791,41.685749],"type":"Point"}
}