{
  "type": "Feature",
  "properties": {
    "iso:country":"US",
    "sg:address":"832 Cedar Pkwy",
    "sg:city":"Schererville",
    "sg:classifiers":[
        {
            "category":"Freight",
            "type":"Transportation"
        }
    ],
    "sg:phone":"+1 219 865 4245",
    "sg:postcode":"46375",
    "sg:province":"IN",
    "sg:tags":[
        "commercial",
        "storage"
    ],
    "wof:name":"AAAU-Lock",
    "wof:placetype":"venue"
},
  "geometry": {"coordinates":[-87.47365600000001,41.514257],"type":"Point"}
}