{
  "type": "Feature",
  "properties": {
    "iso:country":"US",
    "sg:address":"1884 S Hickory Corner Rd",
    "sg:city":"Vincennes",
    "sg:classifiers":[
        {
            "category":"Retail",
            "subcategory":"Auto Repair",
            "type":"Services"
        }
    ],
    "sg:phone":"+1 812 726 4909",
    "sg:postcode":"47591",
    "sg:province":"IN",
    "sg:tags":[
        "repairing",
        "automobile"
    ],
    "wof:name":"Ray Marchino",
    "wof:placetype":"venue"
},
  "geometry": {"coordinates":[-87.441671,38.645757],"type":"Point"}
}