{
  "type": "Feature",
  "properties": {
    "addr:full":"6886 Parke Dr Avon IN 46123",
    "addr:housenumber":"6886",
    "addr:postcode":"46123",
    "addr:street":"Parke Dr",
    "iso:country":"US",
    "sg:address":"6886 Parke Dr",
    "sg:city":"Avon",
    "sg:classifiers":[
        {
            "category":"Professional",
            "subcategory":"Computer Services",
            "type":"Services"
        }
    ],
    "sg:phone":"+1 317 507 4057",
    "sg:postcode":"46123",
    "sg:province":"IN",
    "sg:tags":[
        "related"
    ],
    "wof:name":"Aspen Solutions Group Inc",
    "wof:placetype":"venue"
},
  "geometry": {"coordinates":[-86.399805,39.74413],"type":"Point"}
}