{
  "type": "Feature",
  "properties": {
    "iso:country":"US",
    "sg:address":"112 W Jefferson Blvd",
    "sg:city":"South Bend",
    "sg:classifiers":[
        {
            "category":"Professional",
            "subcategory":"Lawyer & Legal Services",
            "type":"Services"
        }
    ],
    "sg:phone":"+1 574 232 3393",
    "sg:postcode":"46601",
    "sg:province":"IN",
    "sg:tags":[
        "attorney"
    ],
    "wof:name":"Mirkin Law Offices",
    "wof:placetype":"venue"
},
  "geometry": {"coordinates":[-86.25082500000001,41.674948],"type":"Point"}
}