{
  "type": "Feature",
  "properties": {
    "iso:country":"US",
    "sg:address":"4235 W 3rd St",
    "sg:city":"Bloomington",
    "sg:classifiers":[
        {
            "category":"Organizations",
            "subcategory":"Religious Organization",
            "type":"Services"
        }
    ],
    "sg:phone":"+1 812 332 0314",
    "sg:postcode":"47404",
    "sg:province":"IN",
    "sg:tags":[
        "church"
    ],
    "wof:name":"Church Of Jesus Christ Of Lds",
    "wof:placetype":"venue"
},
  "geometry": {"coordinates":[-86.592129,39.16479],"type":"Point"}
}