{
  "type": "Feature",
  "properties": {
    "iso:country":"US",
    "sg:address":"25189 Ray Parker Rd",
    "sg:city":"Arcadia",
    "sg:classifiers":[
        {
            "category":"Freight",
            "type":"Transportation"
        }
    ],
    "sg:phone":"+1 765 552 0024",
    "sg:postcode":"46030",
    "sg:province":"IN",
    "sg:tags":[
        "operator",
        "trucking"
    ],
    "wof:name":"Pritchard Enterprises",
    "wof:placetype":"venue"
},
  "geometry": {"coordinates":[-85.911088,40.150766],"type":"Point"}
}