{
  "type": "Feature",
  "properties": {
    "iso:country":"US",
    "sg:address":"56 N Van Buren St",
    "sg:city":"Nashville",
    "sg:classifiers":[
        {
            "category":"Food & Beverages",
            "subcategory":"Candy",
            "type":"Retail Goods"
        }
    ],
    "sg:phone":"+1 812 988 0709",
    "sg:postcode":"47448",
    "sg:province":"IN",
    "sg:tags":[
        "confectionery"
    ],
    "wof:name":"Nashville Fudge Kitchen",
    "wof:placetype":"venue"
},
  "geometry": {"coordinates":[-86.246869,39.208029],"type":"Point"}
}