{
  "type": "Feature",
  "properties": {
    "addr:full":"152 E Jefferson St Franklin IN 46131",
    "addr:housenumber":"152",
    "addr:postcode":"46131",
    "addr:street":"E Jefferson St",
    "iso:country":"US",
    "sg:address":"152 E Jefferson St",
    "sg:city":"Franklin",
    "sg:classifiers":[
        {
            "category":"Shopping",
            "subcategory":"Used Merchandise",
            "type":"Retail Goods"
        }
    ],
    "sg:phone":"+1 317 346 7323",
    "sg:postcode":"46131",
    "sg:province":"IN",
    "sg:tags":[
        "book",
        "rare",
        "dealer"
    ],
    "wof:name":"Read Already Used Books",
    "wof:placetype":"venue"
},
  "geometry": {"coordinates":[-86.053134,39.480713],"type":"Point"}
}