{
  "type": "Feature",
  "properties": {
    "iso:country":"US",
    "sg:address":"1904 W McGalliard Rd",
    "sg:city":"Muncie",
    "sg:classifiers":[
        {
            "category":"Shopping",
            "subcategory":"Optical Goods",
            "type":"Retail Goods"
        }
    ],
    "sg:phone":"+1 765 288 1575",
    "sg:postcode":"47304",
    "sg:province":"IN",
    "wof:name":"Vision Associates",
    "wof:placetype":"venue"
},
  "geometry": {"coordinates":[-85.407631,40.219004],"type":"Point"}
}