{
  "type": "Feature",
  "properties": {
    "iso:country":"US",
    "sg:address":"9225 Harrison Park Ct",
    "sg:city":"Indianapolis",
    "sg:classifiers":[
        {
            "category":"Shopping",
            "subcategory":"Computers & Home Electronics",
            "type":"Retail Goods"
        }
    ],
    "sg:phone":"+1 317 544 0499",
    "sg:postcode":"46216",
    "sg:province":"IN",
    "sg:tags":[
        "player",
        "recorder",
        "video"
    ],
    "wof:name":"WSI Multimedia",
    "wof:placetype":"venue"
},
  "geometry": {"coordinates":[-86.005577,39.85295],"type":"Point"}
}