{
  "type": "Feature",
  "properties": {
    "addr:full":"13430 N Meridian St Carmel IN 46032",
    "addr:housenumber":"13430",
    "addr:postcode":"46032",
    "addr:street":"N Meridian St",
    "iso:country":"US",
    "sg:address":"13430 N Meridian St",
    "sg:city":"Carmel",
    "sg:classifiers":[
        {
            "category":"Health Services",
            "subcategory":"Doctor",
            "type":"Services"
        }
    ],
    "sg:phone":"+1 317 415 8100",
    "sg:postcode":"46032",
    "sg:province":"IN",
    "wof:name":"Sumners James MD",
    "wof:placetype":"venue"
},
  "geometry": {"coordinates":[-86.147227,39.983441],"type":"Point"}
}