{
  "type": "Feature",
  "properties": {
    "iso:country":"US",
    "sg:address":"9784 N Co Rd 300 E",
    "sg:city":"Brazil",
    "sg:classifiers":[
        {
            "category":"Sports & Exercise",
            "subcategory":"Golf",
            "type":"Entertainment"
        }
    ],
    "sg:phone":"+1 812 446 4653",
    "sg:postcode":"47834",
    "sg:province":"IN",
    "sg:tags":[
        "course"
    ],
    "wof:name":"Oak Ridge Golf Course",
    "wof:placetype":"venue"
},
  "geometry": {"coordinates":[-87.051766,39.529633],"type":"Point"}
}