{
  "type": "Feature",
  "properties": {
    "iso:country":"US",
    "sg:address":"914 Lincolnway W",
    "sg:city":"South Bend",
    "sg:classifiers":[
        {
            "category":"Organizations",
            "subcategory":"Professional Association",
            "type":"Services"
        }
    ],
    "sg:phone":"+1 574 289 2123",
    "sg:postcode":"46616",
    "sg:province":"IN",
    "wof:name":"NAACP",
    "wof:placetype":"venue"
},
  "geometry": {"coordinates":[-86.262883,41.682018],"type":"Point"}
}