{
  "type": "Feature",
  "properties": {
    "iso:country":"US",
    "sg:address":"833 Manhattan Ave",
    "sg:city":"Indianapolis",
    "sg:classifiers":[
        {
            "category":"Building & Trades",
            "subcategory":"Construction",
            "type":"Services"
        }
    ],
    "sg:phone":"+1 317 241 7145",
    "sg:postcode":"46241",
    "sg:province":"IN",
    "sg:tags":[
        "contractor"
    ],
    "wof:name":"T & A Siding Soffit",
    "wof:placetype":"venue"
},
  "geometry": {"coordinates":[-86.251306,39.752517],"type":"Point"}
}