{
  "type": "Feature",
  "properties": {
    "iso:country":"US",
    "sg:address":"1501 Sagamore Pkwy N",
    "sg:city":"Lafayette",
    "sg:classifiers":[
        {
            "category":"Banks & Credit Unions",
            "subcategory":"Bank",
            "type":"Services"
        }
    ],
    "sg:phone":"+1 765 429 2880",
    "sg:postcode":"47904",
    "sg:province":"IN",
    "wof:name":"Lafayette Savings Bank",
    "wof:placetype":"venue"
},
  "geometry": {"coordinates":[-86.858272,40.435352],"type":"Point"}
}