{
  "type": "Feature",
  "properties": {
    "iso:country":"US",
    "sg:address":"113 W Washington St",
    "sg:city":"Goshen",
    "sg:classifiers":[
        {
            "category":"Restaurant",
            "type":"Food & Drink"
        }
    ],
    "sg:phone":"+1 574 535 9091",
    "sg:postcode":"46526",
    "sg:province":"IN",
    "wof:name":"Dembufsky",
    "wof:placetype":"venue"
},
  "geometry": {"coordinates":[-85.83514,41.585123],"type":"Point"}
}