{
  "type": "Feature",
  "properties": {
    "iso:country":"US",
    "sg:address":"246 W Lagrange Rd",
    "sg:city":"Hanover",
    "sg:classifiers":[
        {
            "category":"Wholesale",
            "subcategory":"Chemicals & Plastics",
            "type":"Manufacturing & Wholesale Goods"
        }
    ],
    "sg:phone":"+1 812 866 6572",
    "sg:postcode":"47243",
    "sg:province":"IN",
    "sg:tags":[
        "oxygen"
    ],
    "wof:name":"All American Oxygen Inc",
    "wof:placetype":"venue"
},
  "geometry": {"coordinates":[-85.479188,38.714686],"type":"Point"}
}