{
  "type": "Feature",
  "properties": {
    "iso:country":"US",
    "sg:address":"721 Main St",
    "sg:city":"Clay City",
    "sg:classifiers":[
        {
            "category":"Restaurant",
            "type":"Food & Drink"
        }
    ],
    "sg:phone":"+1 812 939 2266",
    "sg:postcode":"47841",
    "sg:province":"IN",
    "wof:name":"Main Street Pizza",
    "wof:placetype":"venue"
},
  "geometry": {"coordinates":[-87.112734,39.277427],"type":"Point"}
}