{
  "type": "Feature",
  "properties": {
    "iso:country":"US",
    "sg:address":"2511 N Emerson Ave",
    "sg:city":"Indianapolis",
    "sg:classifiers":[
        {
            "category":"Manufacturing",
            "subcategory":"Signs",
            "type":"Manufacturing & Wholesale Goods"
        }
    ],
    "sg:phone":"+1 317 546 5606",
    "sg:postcode":"46218",
    "sg:province":"IN",
    "wof:name":"J & T Reimaging",
    "wof:placetype":"venue"
},
  "geometry": {"coordinates":[-86.083309,39.803342],"type":"Point"}
}