{
  "type": "Feature",
  "properties": {
    "addr:full":"613 Lincoln Ave Bedford IN 47421",
    "addr:housenumber":"613",
    "addr:postcode":"47421",
    "addr:street":"Lincoln Ave",
    "iso:country":"US",
    "sg:address":"613 Lincoln Ave",
    "sg:city":"Bedford",
    "sg:classifiers":[
        {
            "category":"Shopping",
            "type":"Retail Goods"
        }
    ],
    "sg:phone":"+1 812 275 6666",
    "sg:postcode":"47421",
    "sg:province":"IN",
    "sg:tags":[
        "pet",
        "food",
        "supply"
    ],
    "wof:name":"Pet Corner",
    "wof:placetype":"venue"
},
  "geometry": {"coordinates":[-86.49058100000001,38.872958],"type":"Point"}
}