{
  "type": "Feature",
  "properties": {
    "iso:country":"US",
    "sg:address":"8 Wood Ct",
    "sg:city":"Hebron",
    "sg:classifiers":[
        {
            "category":"Shopping",
            "subcategory":"Hobbies, Toys, & Games",
            "type":"Retail Goods"
        }
    ],
    "sg:phone":"+1 219 996 6288",
    "sg:postcode":"46341",
    "sg:province":"IN",
    "sg:tags":[
        "model",
        "supply"
    ],
    "wof:name":"Rimfire Raceway & Hobbie Shop",
    "wof:placetype":"venue"
},
  "geometry": {"coordinates":[-87.19502799999999,41.323182],"type":"Point"}
}