{
  "type": "Feature",
  "properties": {
    "iso:country":"US",
    "sg:address":"907 W Pike St",
    "sg:city":"Goshen",
    "sg:classifiers":[
        {
            "category":"Home & Garden",
            "subcategory":"Building Materials",
            "type":"Retail Goods"
        }
    ],
    "sg:phone":"+1 574 534 1541",
    "sg:postcode":"46526",
    "sg:province":"IN",
    "sg:tags":[
        "glass",
        "window",
        "plate"
    ],
    "sg:website":"www.quality-glass.com",
    "wof:name":"Quality Glass Svc",
    "wof:placetype":"venue"
},
  "geometry": {"coordinates":[-85.84724,41.589046],"type":"Point"}
}