{
  "type": "Feature",
  "properties": {
    "addr:full":"410 S Chestnut St Seymour IN 47274",
    "addr:housenumber":"410",
    "addr:postcode":"47274",
    "addr:street":"S Chestnut St",
    "iso:country":"US",
    "sg:address":"410 S Chestnut St",
    "sg:city":"Seymour",
    "sg:classifiers":[
        {
            "category":"Health Services",
            "subcategory":"Podiatrist",
            "type":"Services"
        }
    ],
    "sg:phone":"+1 812 524 9221",
    "sg:postcode":"47274",
    "sg:province":"IN",
    "wof:name":"Foot & Ankle Ctr Of Seymour",
    "wof:placetype":"venue"
},
  "geometry": {"coordinates":[-85.88875899999999,38.954435],"type":"Point"}
}