{
  "type": "Feature",
  "properties": {
    "iso:country":"US",
    "sg:address":"5108 Topp Dr",
    "sg:city":"Indianapolis",
    "sg:classifiers":[
        {
            "category":"Building & Trades",
            "subcategory":"Construction",
            "type":"Services"
        }
    ],
    "sg:phone":"+1 317 549 1833",
    "sg:postcode":"46218",
    "sg:province":"IN",
    "sg:tags":[
        "marking",
        "maintenance",
        "parking"
    ],
    "wof:name":"ACI Construction Co",
    "wof:placetype":"venue"
},
  "geometry": {"coordinates":[-86.08192200000001,39.808824],"type":"Point"}
}