{
  "type": "Feature",
  "properties": {
    "addr:full":"1200 6th Ave Terre Haute IN 47807",
    "addr:housenumber":"1200",
    "addr:postcode":"47807",
    "addr:street":"6Th Ave",
    "iso:country":"US",
    "sg:address":"1200 6th Ave",
    "sg:city":"Terre Haute",
    "sg:classifiers":[
        {
            "category":"Home & Garden",
            "subcategory":"Furniture",
            "type":"Retail Goods"
        }
    ],
    "sg:phone":"+1 812 235 8061",
    "sg:postcode":"47807",
    "sg:province":"IN",
    "sg:tags":[
        "cabinet"
    ],
    "wof:name":"Indiana Wholesalers Inc",
    "wof:placetype":"venue"
},
  "geometry": {"coordinates":[-87.39873299999999,39.48298],"type":"Point"}
}