{
  "type": "Feature",
  "properties": {
    "iso:country":"US",
    "sg:address":"119 N Broadway St",
    "sg:city":"Greenfield",
    "sg:classifiers":[
        {
            "category":"Organizations",
            "subcategory":"Religious Organization",
            "type":"Services"
        }
    ],
    "sg:phone":"+1 317 462 5477",
    "sg:postcode":"46140",
    "sg:province":"IN",
    "sg:tags":[
        "church"
    ],
    "wof:name":"Church Of God",
    "wof:placetype":"venue"
},
  "geometry": {"coordinates":[-85.779176,39.786508],"type":"Point"}
}