{
  "type": "Feature",
  "properties": {
    "iso:country":"US",
    "sg:address":"11825 E 46th St",
    "sg:city":"Indianapolis",
    "sg:classifiers":[
        {
            "category":"Education",
            "subcategory":"School",
            "type":"Public Place"
        }
    ],
    "sg:phone":"+1 317 964 6800",
    "sg:postcode":"46235",
    "sg:province":"IN",
    "wof:name":"Winding Ridge Elementary Schl",
    "wof:placetype":"venue"
},
  "geometry": {"coordinates":[-85.957471,39.841293],"type":"Point"}
}