{
  "type": "Feature",
  "properties": {
    "iso:country":"US",
    "sg:address":"1301 W 2nd St",
    "sg:city":"Marion",
    "sg:classifiers":[
        {
            "category":"Retail",
            "subcategory":"Portrait Studio",
            "type":"Services"
        }
    ],
    "sg:phone":"+1 765 662 3909",
    "sg:postcode":"46952",
    "sg:province":"IN",
    "sg:tags":[
        "photographer"
    ],
    "wof:name":"Photography By Dino",
    "wof:placetype":"venue"
},
  "geometry": {"coordinates":[-85.67576099999999,40.560013],"type":"Point"}
}