{
  "type": "Feature",
  "properties": {
    "iso:country":"US",
    "sg:address":"7783 N 600 W",
    "sg:city":"Michigan City",
    "sg:classifiers":[
        {
            "category":"Freight",
            "type":"Transportation"
        }
    ],
    "sg:phone":"+1 219 879 0334",
    "sg:postcode":"46360",
    "sg:province":"IN",
    "sg:tags":[
        "commercial",
        "storage"
    ],
    "wof:name":"Store With Us",
    "wof:placetype":"venue"
},
  "geometry": {"coordinates":[-86.816158,41.720358],"type":"Point"}
}