{
  "type": "Feature",
  "properties": {
    "iso:country":"US",
    "sg:address":"2898 Branifield Dr",
    "sg:city":"Franklin",
    "sg:classifiers":[
        {
            "category":"Building & Trades",
            "subcategory":"Construction",
            "type":"Services"
        }
    ],
    "sg:phone":"+1 317 738 3556",
    "sg:postcode":"46131",
    "sg:province":"IN",
    "sg:tags":[
        "home",
        "builder"
    ],
    "wof:name":"Crossmann Communities",
    "wof:placetype":"venue"
},
  "geometry": {"coordinates":[-86.07606,39.514779],"type":"Point"}
}