{
  "type": "Feature",
  "properties": {
    "iso:country":"US",
    "sg:address":"6507 Carrollton Ave",
    "sg:city":"Indianapolis",
    "sg:classifiers":[
        {
            "category":"Building & Trades",
            "subcategory":"Construction",
            "type":"Services"
        }
    ],
    "sg:phone":"+1 317 251 8740",
    "sg:postcode":"46220",
    "sg:province":"IN",
    "sg:tags":[
        "home",
        "builder"
    ],
    "wof:name":"Sears Steven Building Co Inc",
    "wof:placetype":"venue"
},
  "geometry": {"coordinates":[-86.144599,39.874162],"type":"Point"}
}