{
  "type": "Feature",
  "properties": {
    "addr:full":"6190 W 330 S New Palestine IN 46163",
    "addr:housenumber":"6190",
    "addr:postcode":"46163",
    "addr:street":"W 330 S",
    "iso:country":"US",
    "sg:address":"6190 W 330 S",
    "sg:city":"New Palestine",
    "sg:classifiers":[
        {
            "category":"Building & Trades",
            "subcategory":"Construction",
            "type":"Services"
        }
    ],
    "sg:phone":"+1 317 861 9983",
    "sg:postcode":"46163",
    "sg:province":"IN",
    "sg:tags":[
        "house"
    ],
    "wof:name":"Masterpiece Builders Inc",
    "wof:placetype":"venue"
},
  "geometry": {"coordinates":[-85.91422,39.737376],"type":"Point"}
}