{
  "type": "Feature",
  "properties": {
    "iso:country":"US",
    "sg:address":"2059 E 300 S",
    "sg:city":"Bluffton",
    "sg:classifiers":[
        {
            "category":"Social Services",
            "subcategory":"Child Care",
            "type":"Services"
        }
    ],
    "sg:phone":"+1 260 824 2465",
    "sg:postcode":"46714",
    "sg:province":"IN",
    "sg:tags":[
        "day"
    ],
    "wof:name":"Lollipop Kids Day Care",
    "wof:placetype":"venue"
},
  "geometry": {"coordinates":[-85.166792,40.699135],"type":"Point"}
}