{
  "type": "Feature",
  "properties": {
    "iso:country":"US",
    "sg:address":"105 Drexel Pkwy",
    "sg:city":"Rensselaer",
    "sg:classifiers":[
        {
            "category":"Professional",
            "type":"Services"
        }
    ],
    "sg:phone":"+1 219 866 7616",
    "sg:postcode":"47978",
    "sg:province":"IN",
    "wof:name":"Steve Specialized Services",
    "wof:placetype":"venue"
},
  "geometry": {"coordinates":[-87.141962,40.923033],"type":"Point"}
}