{
  "type": "Feature",
  "properties": {
    "iso:country":"US",
    "sg:address":"3140 N Shadeland Ave",
    "sg:city":"Indianapolis",
    "sg:classifiers":[
        {
            "category":"Wholesale",
            "subcategory":"Machinery & Supplies",
            "type":"Manufacturing & Wholesale Goods"
        }
    ],
    "sg:phone":"+1 317 545 6572",
    "sg:postcode":"46226",
    "sg:province":"IN",
    "sg:tags":[
        "compressor",
        "gas"
    ],
    "wof:name":"Power Air",
    "wof:placetype":"venue"
},
  "geometry": {"coordinates":[-86.045813,39.812473],"type":"Point"}
}