{
  "type": "Feature",
  "properties": {
    "iso:country":"US",
    "sg:address":"1177 The Pines Rd",
    "sg:city":"Batesville",
    "sg:classifiers":[
        {
            "category":"Building & Trades",
            "subcategory":"Construction",
            "type":"Services"
        }
    ],
    "sg:phone":"+1 812 934 4618",
    "sg:postcode":"47006",
    "sg:province":"IN",
    "sg:tags":[
        "house"
    ],
    "wof:name":"Kenny Pfeiffer Constructi",
    "wof:placetype":"venue"
},
  "geometry": {"coordinates":[-85.204714,39.320962],"type":"Point"}
}