{
  "type": "Feature",
  "properties": {
    "addr:full":"508 S Main St Summitville IN 46070",
    "addr:housenumber":"508",
    "addr:postcode":"46070",
    "addr:street":"S Main St",
    "iso:country":"US",
    "sg:address":"508 S Main St",
    "sg:city":"Summitville",
    "sg:classifiers":[
        {
            "category":"Retail",
            "subcategory":"Repair Shop",
            "type":"Services"
        }
    ],
    "sg:phone":"+1 765 536 4048",
    "sg:postcode":"46070",
    "sg:province":"IN",
    "sg:tags":[
        "television",
        "radio"
    ],
    "wof:name":"Greg Mc Duffee TV & Antenna",
    "wof:placetype":"venue"
},
  "geometry": {"coordinates":[-85.64637,40.332272],"type":"Point"}
}