{
  "type": "Feature",
  "properties": {
    "iso:country":"US",
    "sg:address":"1021 S Main St",
    "sg:city":"Princeton",
    "sg:classifiers":[
        {
            "category":"Bars & Pubs",
            "type":"Food & Drink"
        }
    ],
    "sg:phone":"+1 812 385 9941",
    "sg:postcode":"47670",
    "sg:province":"IN",
    "wof:name":"Da Club",
    "wof:placetype":"venue"
},
  "geometry": {"coordinates":[-87.567621,38.34574],"type":"Point"}
}