{
  "type": "Feature",
  "properties": {
    "iso:country":"US",
    "sg:address":"125 E Stansifer Ave",
    "sg:city":"Clarksville",
    "sg:classifiers":[
        {
            "category":"Government",
            "subcategory":"Fire Station",
            "type":"Public Place"
        }
    ],
    "sg:phone":"+1 812 282 7619",
    "sg:postcode":"47129",
    "sg:province":"IN",
    "sg:tags":[
        "town"
    ],
    "wof:name":"Clarksville Fire Dept",
    "wof:placetype":"venue"
},
  "geometry": {"coordinates":[-85.757765,38.284873],"type":"Point"}
}