{
  "type": "Feature",
  "properties": {
    "iso:country":"US",
    "sg:address":"5451 Riley Rd",
    "sg:city":"Terre Haute",
    "sg:classifiers":[
        {
            "category":"Mining & Drilling",
            "type":"Manufacturing & Wholesale Goods"
        }
    ],
    "sg:phone":"+1 812 894 2096",
    "sg:postcode":"47802",
    "sg:province":"IN",
    "sg:tags":[
        "oil",
        "gas",
        "producer"
    ],
    "wof:name":"Hux Oil",
    "wof:placetype":"venue"
},
  "geometry": {"coordinates":[-87.333975,39.409629],"type":"Point"}
}