{
  "type": "Feature",
  "properties": {
    "iso:country":"US",
    "sg:address":"25 Pines Dr",
    "sg:city":"Spencer",
    "sg:classifiers":[
        {
            "category":"Real Estate",
            "subcategory":"Real Estate Operator",
            "type":"Services"
        }
    ],
    "sg:phone":"+1 812 829 4171",
    "sg:postcode":"47460",
    "sg:province":"IN",
    "sg:tags":[
        "apartment"
    ],
    "wof:name":"Pine Apartments Of Spencer",
    "wof:placetype":"venue"
},
  "geometry": {"coordinates":[-86.774046,39.290337],"type":"Point"}
}