{
  "type": "Feature",
  "properties": {
    "addr:full":"2051 N Emerson Ave Indianapolis IN 46218",
    "addr:housenumber":"2051",
    "addr:postcode":"46218",
    "addr:street":"N Emerson Ave",
    "iso:country":"US",
    "sg:address":"2051 N Emerson Ave",
    "sg:city":"Indianapolis",
    "sg:classifiers":[
        {
            "category":"Professional",
            "subcategory":"Accounting & Tax Preparation",
            "type":"Services"
        }
    ],
    "sg:phone":"+1 317 308 2935",
    "sg:postcode":"46218",
    "sg:province":"IN",
    "sg:tags":[
        "return",
        "filing"
    ],
    "wof:name":"Freedom Tax Svc",
    "wof:placetype":"venue"
},
  "geometry": {"coordinates":[-86.083231,39.795807],"type":"Point"}
}