{
  "type": "Feature",
  "properties": {
    "iso:country":"US",
    "sg:address":"1109 Treadway Rd",
    "sg:city":"Munster",
    "sg:classifiers":[
        {
            "category":"Professional",
            "subcategory":"Business Services",
            "type":"Services"
        }
    ],
    "sg:phone":"+1 219 924 0286",
    "sg:postcode":"46321",
    "sg:province":"IN",
    "sg:tags":[
        "packaging"
    ],
    "wof:name":"Empire-Emco",
    "wof:placetype":"venue"
},
  "geometry": {"coordinates":[-87.50078999999999,41.52822],"type":"Point"}
}