{
  "type": "Feature",
  "properties": {
    "iso:country":"US",
    "sg:address":"1162 S Main St",
    "sg:city":"Dunkirk",
    "sg:classifiers":[
        {
            "category":"Food & Beverages",
            "subcategory":"Groceries & Convenience Stores",
            "type":"Retail Goods"
        }
    ],
    "sg:phone":"+1 765 768 7605",
    "sg:postcode":"47336",
    "sg:province":"IN",
    "wof:name":"Denney's On The Go Inc",
    "wof:placetype":"venue"
},
  "geometry": {"coordinates":[-85.217353,40.365319],"type":"Point"}
}