{
  "type": "Feature",
  "properties": {
    "iso:country":"US",
    "sg:address":"13295 Meridian Corners Blvd",
    "sg:city":"Carmel",
    "sg:classifiers":[
        {
            "category":"Real Estate",
            "subcategory":"Real Estate Agent",
            "type":"Services"
        }
    ],
    "sg:phone":"+1 317 844 3692",
    "sg:postcode":"46032",
    "sg:province":"IN",
    "wof:name":"CNC Properties",
    "wof:placetype":"venue"
},
  "geometry": {"coordinates":[-86.155868,39.981533],"type":"Point"}
}