{
  "type": "Feature",
  "properties": {
    "iso:country":"US",
    "sg:address":"1842 E 8 Square Rd",
    "sg:city":"Warsaw",
    "sg:classifiers":[
        {
            "category":"Real Estate",
            "subcategory":"Real Estate Operator",
            "type":"Services"
        }
    ],
    "sg:phone":"+1 574 267 5633",
    "sg:postcode":"46580",
    "sg:province":"IN",
    "sg:tags":[
        "property",
        "lessor"
    ],
    "wof:name":"Russell Fahl",
    "wof:placetype":"venue"
},
  "geometry": {"coordinates":[-85.800017,41.292665],"type":"Point"}
}