{
  "type": "Feature",
  "properties": {
    "iso:country":"US",
    "sg:address":"8902 Otis Ave",
    "sg:city":"Indianapolis",
    "sg:classifiers":[
        {
            "category":"Shopping",
            "subcategory":"Computers & Home Electronics",
            "type":"Retail Goods"
        }
    ],
    "sg:phone":"+1 317 546 0891",
    "sg:postcode":"46216",
    "sg:province":"IN",
    "sg:tags":[
        "software"
    ],
    "wof:name":"N Focus Technologies",
    "wof:placetype":"venue"
},
  "geometry": {"coordinates":[-86.011129,39.856783],"type":"Point"}
}