{
  "type": "Feature",
  "properties": {
    "iso:country":"US",
    "sg:address":"4700 S 975 E",
    "sg:city":"Zionsville",
    "sg:classifiers":[
        {
            "category":"Education",
            "subcategory":"School",
            "type":"Public Place"
        }
    ],
    "sg:phone":"+1 317 873 2376",
    "sg:postcode":"46077",
    "sg:province":"IN",
    "wof:name":"Pleasant View Lower Elem Schl",
    "wof:placetype":"venue"
},
  "geometry": {"coordinates":[-86.283906,39.971383],"type":"Point"}
}