{
  "type": "Feature",
  "properties": {
    "iso:country":"US",
    "sg:address":"1538 Lafayette Ave",
    "sg:city":"Terre Haute",
    "sg:classifiers":[
        {
            "category":"Autos & Motor Vehicles",
            "subcategory":"Automobile Sales",
            "type":"Retail Goods"
        }
    ],
    "sg:phone":"+1 812 466 3612",
    "sg:postcode":"47804",
    "sg:province":"IN",
    "sg:tags":[
        "car",
        "dealer"
    ],
    "wof:name":"Ron Dodson Classic Cars",
    "wof:placetype":"venue"
},
  "geometry": {"coordinates":[-87.391689,39.500762],"type":"Point"}
}