{
  "type": "Feature",
  "properties": {
    "addr:full":"205 S Madison Ave Greenwood IN 46142",
    "addr:housenumber":"205",
    "addr:postcode":"46142",
    "addr:street":"S Madison Ave",
    "iso:country":"US",
    "sg:address":"205 S Madison Ave",
    "sg:city":"Greenwood",
    "sg:classifiers":[
        {
            "category":"Organizations",
            "subcategory":"Membership Organization",
            "type":"Services"
        }
    ],
    "sg:phone":"+1 317 882 8090",
    "sg:postcode":"46142",
    "sg:province":"IN",
    "sg:tags":[
        "athletic"
    ],
    "wof:name":"Heartland Collegiate Athletic",
    "wof:placetype":"venue"
},
  "geometry": {"coordinates":[-86.10944499999999,39.613168],"type":"Point"}
}