{
  "type": "Feature",
  "properties": {
    "iso:country":"US",
    "sg:address":"5603 Mexico Dr",
    "sg:city":"Fort Wayne",
    "sg:classifiers":[
        {
            "category":"Professional",
            "subcategory":"Accounting & Tax Preparation",
            "type":"Services"
        }
    ],
    "sg:phone":"+1 260 434 0887",
    "sg:postcode":"46804",
    "sg:province":"IN",
    "sg:tags":[
        "accountant"
    ],
    "wof:name":"Mike Davis CPA",
    "wof:placetype":"venue"
},
  "geometry": {"coordinates":[-85.270557,41.032405],"type":"Point"}
}