{
  "type": "Feature",
  "properties": {
    "addr:full":"7922 N Old US Hwy 31 Argos IN 46501",
    "addr:housenumber":"7922",
    "addr:postcode":"46501",
    "addr:street":"N Old Us Hwy 31 Argos",
    "iso:country":"US",
    "sg:address":"7922 N Old US Hwy 31",
    "sg:city":"Argos",
    "sg:classifiers":[
        {
            "category":"Utilities",
            "subcategory":"Refuse",
            "type":"Services"
        }
    ],
    "sg:phone":"+1 574 892 6483",
    "sg:postcode":"46501",
    "sg:province":"IN",
    "sg:tags":[
        "landfill"
    ],
    "wof:name":"County Line Landfill",
    "wof:placetype":"venue"
},
  "geometry": {"coordinates":[-86.22793299999999,41.157291],"type":"Point"}
}