{
  "type": "Feature",
  "properties": {
    "iso:country":"US",
    "sg:address":"518 N Meridian St",
    "sg:city":"Greenwood",
    "sg:classifiers":[
        {
            "category":"Retail",
            "subcategory":"Self-service Laundry",
            "type":"Services"
        }
    ],
    "sg:phone":"+1 317 881 5700",
    "sg:postcode":"46143",
    "sg:province":"IN",
    "wof:name":"Greenwood Laundromat",
    "wof:placetype":"venue"
},
  "geometry": {"coordinates":[-86.106369,39.624904],"type":"Point"}
}