{
  "type": "Feature",
  "properties": {
    "iso:country":"US",
    "sg:address":"820 W Vineyard St",
    "sg:city":"Anderson",
    "sg:classifiers":[
        {
            "category":"Real Estate",
            "subcategory":"Real Estate Agent",
            "type":"Services"
        }
    ],
    "sg:phone":"+1 765 643 6054",
    "sg:postcode":"46011",
    "sg:province":"IN",
    "wof:name":"Lee Givens Realtor & Appraiser",
    "wof:placetype":"venue"
},
  "geometry": {"coordinates":[-85.68616900000001,40.129939],"type":"Point"}
}