{
  "type": "Feature",
  "properties": {
    "iso:country":"US",
    "sg:address":"4419 North Dr",
    "sg:city":"Quincy",
    "sg:classifiers":[
        {
            "category":"Retail",
            "subcategory":"Portrait Studio",
            "type":"Services"
        }
    ],
    "sg:phone":"+1 765 528 2461",
    "sg:postcode":"47456",
    "sg:province":"IN",
    "sg:tags":[
        "photographer",
        "photo"
    ],
    "wof:name":"Sheri's Creative Photography",
    "wof:placetype":"venue"
},
  "geometry": {"coordinates":[-86.62419300000001,39.491184],"type":"Point"}
}