{
  "type": "Feature",
  "properties": {
    "iso:country":"US",
    "sg:address":"939 Main St",
    "sg:city":"New Haven",
    "sg:classifiers":[
        {
            "category":"Retail",
            "subcategory":"Repair Shop",
            "type":"Services"
        }
    ],
    "sg:phone":"+1 260 493 6024",
    "sg:postcode":"46774",
    "sg:province":"IN",
    "sg:tags":[
        "upholsterer"
    ],
    "wof:name":"Chuck's Furniture Repair",
    "wof:placetype":"venue"
},
  "geometry": {"coordinates":[-85.014886,41.073664],"type":"Point"}
}