{
  "type": "Feature",
  "properties": {
    "addr:full":"51831 Co Rd 11 Elkhart IN 46514",
    "addr:housenumber":"51831;11",
    "addr:postcode":"46514",
    "addr:street":"Co Rd",
    "iso:country":"US",
    "sg:address":"51831 Co Rd 11",
    "sg:city":"Elkhart",
    "sg:classifiers":[
        {
            "category":"Building & Trades",
            "subcategory":"Landscaping Services",
            "type":"Services"
        }
    ],
    "sg:phone":"+1 574 264 1543",
    "sg:postcode":"46514",
    "sg:province":"IN",
    "sg:tags":[
        "tree"
    ],
    "wof:name":"Northcutt Tree Inc",
    "wof:placetype":"venue"
},
  "geometry": {"coordinates":[-85.942307,41.746456],"type":"Point"}
}