{
  "type": "Feature",
  "properties": {
    "iso:country":"US",
    "sg:address":"133 E Spring St",
    "sg:city":"New Albany",
    "sg:classifiers":[
        {
            "category":"Banks & Credit Unions",
            "subcategory":"Investment Brokerage",
            "type":"Services"
        }
    ],
    "sg:phone":"+1 812 944 8312",
    "sg:postcode":"47150",
    "sg:province":"IN",
    "sg:tags":[
        "stock",
        "bond"
    ],
    "wof:name":"Edward Jones Co",
    "wof:placetype":"venue"
},
  "geometry": {"coordinates":[-85.822113,38.2864],"type":"Point"}
}