{
  "type": "Feature",
  "properties": {
    "iso:country":"US",
    "sg:address":"4508 Columbia Ave",
    "sg:city":"Hammond",
    "sg:classifiers":[
        {
            "category":"Professional",
            "subcategory":"Research",
            "type":"Services"
        }
    ],
    "sg:phone":"+1 219 937 6060",
    "sg:postcode":"46327",
    "sg:province":"IN",
    "sg:tags":[
        "environmental",
        "ecological"
    ],
    "wof:name":"Environmental Restoration Syst",
    "wof:placetype":"venue"
},
  "geometry": {"coordinates":[-87.500184,41.63068],"type":"Point"}
}