{
  "type": "Feature",
  "properties": {
    "iso:country":"US",
    "sg:address":"420 Nantucket Rd",
    "sg:city":"Valparaiso",
    "sg:classifiers":[
        {
            "category":"Building & Trades",
            "subcategory":"Electrical",
            "type":"Services"
        }
    ],
    "sg:phone":"+1 219 759 3390",
    "sg:postcode":"46385",
    "sg:province":"IN",
    "sg:tags":[
        "electric",
        "contractor"
    ],
    "wof:name":"On Line Electric Co",
    "wof:placetype":"venue"
},
  "geometry": {"coordinates":[-87.146469,41.528168],"type":"Point"}
}