{
  "type": "Feature",
  "properties": {
    "iso:country":"US",
    "sg:address":"14550 Amstutz Rd",
    "sg:city":"Leo",
    "sg:classifiers":[
        {
            "category":"Shopping",
            "subcategory":"Department Store",
            "type":"Retail Goods"
        }
    ],
    "sg:phone":"+1 260 627 5470",
    "sg:postcode":"46765",
    "sg:province":"IN",
    "sg:tags":[
        "shop"
    ],
    "wof:name":"Dollar General",
    "wof:placetype":"venue"
},
  "geometry": {"coordinates":[-85.018973,41.22282],"type":"Point"}
}