{
  "type": "Feature",
  "properties": {
    "iso:country":"US",
    "sg:address":"4444 S Harding St",
    "sg:city":"Indianapolis",
    "sg:classifiers":[
        {
            "category":"Bars & Pubs",
            "type":"Food & Drink"
        }
    ],
    "sg:phone":"+1 317 787 3442",
    "sg:postcode":"46217",
    "sg:province":"IN",
    "sg:tags":[
        "club",
        "night"
    ],
    "wof:name":"Classy Chassy",
    "wof:placetype":"venue"
},
  "geometry": {"coordinates":[-86.186965,39.701435],"type":"Point"}
}