{
  "type": "Feature",
  "properties": {
    "addr:full":"2130 Central Ave Indianapolis IN 46202",
    "addr:housenumber":"2130",
    "addr:postcode":"46202",
    "addr:street":"Central Ave",
    "iso:country":"US",
    "sg:address":"2130 Central Ave",
    "sg:city":"Indianapolis",
    "sg:classifiers":[
        {
            "category":"Shopping",
            "subcategory":"Department Store",
            "type":"Retail Goods"
        }
    ],
    "sg:phone":"+1 317 923 9410",
    "sg:postcode":"46202",
    "sg:province":"IN",
    "sg:tags":[
        "shop",
        "variety"
    ],
    "sg:website":"http://www.familydollar.com",
    "wof:name":"Family Dollar Stores",
    "wof:placetype":"venue"
},
  "geometry": {"coordinates":[-86.149483,39.796322],"type":"Point"}
}