{
  "type": "Feature",
  "properties": {
    "iso:country":"US",
    "sg:address":"39 Lori Lee Dr",
    "sg:city":"Lafayette",
    "sg:classifiers":[
        {
            "category":"Professional",
            "subcategory":"Management & Consulting",
            "type":"Services"
        }
    ],
    "sg:phone":"+1 765 447 5185",
    "sg:postcode":"47905",
    "sg:province":"IN",
    "sg:tags":[
        "consultant",
        "security",
        "system"
    ],
    "wof:name":"Andy Frain Svc Inc",
    "wof:placetype":"venue"
},
  "geometry": {"coordinates":[-86.856269,40.409325],"type":"Point"}
}