{
  "type": "Feature",
  "properties": {
    "iso:country":"US",
    "sg:address":"6787 E 100 S",
    "sg:city":"Schnellville",
    "sg:classifiers":[
        {
            "category":"Building & Trades",
            "subcategory":"Construction",
            "type":"Services"
        }
    ],
    "sg:phone":"+1 812 389 2207",
    "sg:postcode":"47580",
    "sg:province":"IN",
    "sg:tags":[
        "insulation",
        "heat",
        "contractor"
    ],
    "wof:name":"Betz's Insulating",
    "wof:placetype":"venue"
},
  "geometry": {"coordinates":[-86.782344,38.365367],"type":"Point"}
}