{
  "type": "Feature",
  "properties": {
    "iso:country":"US",
    "sg:address":"6308 Rucker Rd",
    "sg:city":"Indianapolis",
    "sg:classifiers":[
        {
            "category":"Professional",
            "subcategory":"Management & Consulting",
            "type":"Services"
        }
    ],
    "sg:phone":"+1 317 465 9609",
    "sg:postcode":"46220",
    "sg:province":"IN",
    "sg:tags":[
        "consultant",
        "hygiene",
        "industrial"
    ],
    "wof:name":"CIC",
    "wof:placetype":"venue"
},
  "geometry": {"coordinates":[-86.079346,39.868726],"type":"Point"}
}