{
  "type": "Feature",
  "properties": {
    "iso:country":"US",
    "sg:address":"4102 Rockville Rd",
    "sg:city":"Indianapolis",
    "sg:classifiers":[
        {
            "category":"Home & Garden",
            "subcategory":"Garden Supply",
            "type":"Retail Goods"
        }
    ],
    "sg:phone":"+1 317 244 7479",
    "sg:postcode":"46222",
    "sg:province":"IN",
    "sg:tags":[
        "lawn",
        "mower"
    ],
    "wof:name":"Brent's Lawn Mower Sales & Svc",
    "wof:placetype":"venue"
},
  "geometry": {"coordinates":[-86.234162,39.763715],"type":"Point"}
}