{
  "type": "Feature",
  "properties": {
    "addr:full":"8802 US 31 S Indianapolis IN 46227",
    "addr:housenumber":"8802",
    "addr:postcode":"46227",
    "addr:street":"Us 31 S",
    "iso:country":"US",
    "sg:address":"8802 US 31 S",
    "sg:city":"Indianapolis",
    "sg:classifiers":[
        {
            "category":"Manufacturing",
            "subcategory":"Toys & Sporting Goods",
            "type":"Manufacturing & Wholesale Goods"
        },
        {
            "category":"Utilities",
            "subcategory":"Natural Gas",
            "type":"Services"
        }
    ],
    "sg:phone":"+1 317 859 1073",
    "sg:postcode":"46227",
    "sg:province":"IN",
    "sg:tags":[
        "fireworks-wholesale",
        "firework",
        "manufacturer"
    ],
    "wof:name":"Usa Halloween Planet",
    "wof:placetype":"venue"
},
  "geometry": {"coordinates":[-86.12886,39.638252],"type":"Point"}
}