{
  "type": "Feature",
  "properties": {
    "iso:country":"US",
    "sg:address":"1725 S Belle St",
    "sg:city":"Brazil",
    "sg:classifiers":[
        {
            "category":"Education",
            "subcategory":"Vocational School",
            "type":"Public Place"
        }
    ],
    "sg:phone":"+1 812 448 8321",
    "sg:postcode":"47834",
    "sg:province":"IN",
    "sg:tags":[
        "technical",
        "trade"
    ],
    "wof:name":"Building Trades",
    "wof:placetype":"venue"
},
  "geometry": {"coordinates":[-87.098809,39.529728],"type":"Point"}
}