{
  "type": "Feature",
  "properties": {
    "iso:country":"US",
    "sg:address":"2810 Mount Vernon Ave",
    "sg:city":"Evansville",
    "sg:classifiers":[
        {
            "category":"Shopping",
            "subcategory":"Used Merchandise",
            "type":"Retail Goods"
        }
    ],
    "sg:phone":"+1 812 424 5850",
    "sg:postcode":"47712",
    "sg:province":"IN",
    "sg:tags":[
        "appliance"
    ],
    "wof:name":"C & D Appliance",
    "wof:placetype":"venue"
},
  "geometry": {"coordinates":[-87.609551,37.983214],"type":"Point"}
}