{
  "type": "Feature",
  "properties": {
    "iso:country":"US",
    "sg:address":"2307 Allentown Rd",
    "sg:city":"Sellersburg",
    "sg:classifiers":[
        {
            "category":"Professional",
            "subcategory":"Management & Consulting",
            "type":"Services"
        }
    ],
    "sg:phone":"+1 812 246 0109",
    "sg:postcode":"47172",
    "sg:province":"IN",
    "sg:tags":[
        "town",
        "city",
        "regional",
        "planner"
    ],
    "sg:website":"www.skwinc.com",
    "wof:name":"S K Wilson Assoc Inc",
    "wof:placetype":"venue"
},
  "geometry": {"coordinates":[-85.783663,38.419757],"type":"Point"}
}