{
  "type": "Feature",
  "properties": {
    "iso:country":"US",
    "sg:address":"302 N Jackson St",
    "sg:city":"Greencastle",
    "sg:classifiers":[
        {
            "category":"Personal",
            "subcategory":"Beauty Salon",
            "type":"Services"
        }
    ],
    "sg:phone":"+1 765 653 3839",
    "sg:postcode":"46135",
    "sg:province":"IN",
    "sg:tags":[
        "shop"
    ],
    "wof:name":"Hair It Is",
    "wof:placetype":"venue"
},
  "geometry": {"coordinates":[-86.865385,39.647401],"type":"Point"}
}