{
  "type": "Feature",
  "properties": {
    "iso:country":"US",
    "sg:address":"69 Franklin St",
    "sg:city":"Valparaiso",
    "sg:classifiers":[
        {
            "category":"Restaurant",
            "type":"Food & Drink"
        }
    ],
    "sg:phone":"+1 219 462 2141",
    "sg:postcode":"46383",
    "sg:province":"IN",
    "wof:name":"Court Restaurant & Banquet",
    "wof:placetype":"venue"
},
  "geometry": {"coordinates":[-87.05982,41.467178],"type":"Point"}
}