{
  "type": "Feature",
  "properties": {
    "iso:country":"US",
    "sg:address":"17398 Bonnie Ln",
    "sg:city":"Lowell",
    "sg:classifiers":[
        {
            "category":"Professional",
            "subcategory":"Accounting & Tax Preparation",
            "type":"Services"
        }
    ],
    "sg:phone":"+1 219 696 3454",
    "sg:postcode":"46356",
    "sg:province":"IN",
    "wof:name":"Theresa A Brown CPA",
    "wof:placetype":"venue"
},
  "geometry": {"coordinates":[-87.405532,41.301111],"type":"Point"}
}