{
  "type": "Feature",
  "properties": {
    "iso:country":"US",
    "sg:address":"112 W Jefferson Blvd",
    "sg:city":"South Bend",
    "sg:classifiers":[
        {
            "category":"Banks & Credit Unions",
            "subcategory":"Bank",
            "type":"Services"
        }
    ],
    "sg:phone":"+1 574 232 8213",
    "sg:postcode":"46601",
    "sg:province":"IN",
    "sg:tags":[
        "company",
        "trust"
    ],
    "wof:name":"Oliver Estate Inc",
    "wof:placetype":"venue"
},
  "geometry": {"coordinates":[-86.25082500000001,41.674948],"type":"Point"}
}