{
  "type": "Feature",
  "properties": {
    "iso:country":"US",
    "sg:address":"3240 Fickas Rd",
    "sg:city":"Evansville",
    "sg:classifiers":[
        {
            "category":"Retail",
            "subcategory":"Auto Repair",
            "type":"Services"
        }
    ],
    "sg:phone":"+1 812 402 8746",
    "sg:postcode":"47714",
    "sg:province":"IN",
    "sg:tags":[
        "automobile",
        "top",
        "upholstery"
    ],
    "wof:name":"Awesome Upholstery",
    "wof:placetype":"venue"
},
  "geometry": {"coordinates":[-87.505988,37.940689],"type":"Point"}
}