{
  "type": "Feature",
  "properties": {
    "iso:country":"US",
    "sg:address":"3715 Casa Grande Dr",
    "sg:city":"Fort Wayne",
    "sg:classifiers":[
        {
            "category":"Organizations",
            "subcategory":"Religious Organization",
            "type":"Services"
        }
    ],
    "sg:phone":"+1 260 493 6062",
    "sg:postcode":"46815",
    "sg:province":"IN",
    "wof:name":"Manna Ministries Inc",
    "wof:placetype":"venue"
},
  "geometry": {"coordinates":[-85.038066,41.112529],"type":"Point"}
}