{
  "type": "Feature",
  "properties": {
    "iso:country":"US",
    "sg:address":"875 Bethel Ave",
    "sg:city":"Beech Grove",
    "sg:classifiers":[
        {
            "category":"Building & Trades",
            "subcategory":"Plumbing",
            "type":"Services"
        }
    ],
    "sg:phone":"+1 317 787 5371",
    "sg:postcode":"46107",
    "sg:province":"IN",
    "sg:tags":[
        "heating",
        "contractor"
    ],
    "wof:name":"H & H Heating & Cooling Inc",
    "wof:placetype":"venue"
},
  "geometry": {"coordinates":[-86.09164199999999,39.729512],"type":"Point"}
}