{
  "type": "Feature",
  "properties": {
    "addr:full":"1000 W Bishop Blvd Mitchell IN 47446",
    "addr:housenumber":"1000",
    "addr:postcode":"47446",
    "addr:street":"W Bishop Blvd",
    "iso:country":"US",
    "sg:address":"1000 W Bishop Blvd",
    "sg:city":"Mitchell",
    "sg:classifiers":[
        {
            "category":"Communications",
            "subcategory":"Radio Station",
            "type":"Services"
        }
    ],
    "sg:phone":"+1 812 849 2179",
    "sg:postcode":"47446",
    "sg:province":"IN",
    "sg:tags":[
        "company",
        "broadcasting"
    ],
    "wof:name":"Radio Station WWEG",
    "wof:placetype":"venue"
},
  "geometry": {"coordinates":[-86.47863599999999,38.737475],"type":"Point"}
}