{
  "type": "Feature",
  "properties": {
    "iso:country":"US",
    "sg:address":"4363 Idlewild Ln",
    "sg:city":"Carmel",
    "sg:classifiers":[
        {
            "category":"Social Services",
            "type":"Services"
        }
    ],
    "sg:phone":"+1 317 843 0850",
    "sg:postcode":"46033",
    "sg:province":"IN",
    "wof:name":"Neo Fight Inc",
    "wof:placetype":"venue"
},
  "geometry": {"coordinates":[-86.097558,39.93874],"type":"Point"}
}