{
  "type": "Feature",
  "properties": {
    "iso:country":"US",
    "sg:address":"6409 E 750 S",
    "sg:city":"Ladoga",
    "sg:classifiers":[
        {
            "category":"Real Estate",
            "subcategory":"Real Estate Operator",
            "type":"Services"
        }
    ],
    "sg:phone":"+1 765 942 2384",
    "sg:postcode":"47954",
    "sg:province":"IN",
    "sg:tags":[
        "property",
        "lessor"
    ],
    "wof:name":"Samuel Mahorney",
    "wof:placetype":"venue"
},
  "geometry": {"coordinates":[-86.784182,39.930189],"type":"Point"}
}