{
  "type": "Feature",
  "properties": {
    "iso:country":"US",
    "sg:address":"14747 Lutterbach Rd",
    "sg:city":"Evansville",
    "sg:classifiers":[
        {
            "category":"Farming",
            "subcategory":"Livestock Farm",
            "type":"Manufacturing & Wholesale Goods"
        }
    ],
    "sg:phone":"+1 812 963 5044",
    "sg:postcode":"47720",
    "sg:province":"IN",
    "sg:tags":[
        "real",
        "wheat",
        "lessor",
        "beef",
        "cattle",
        "property",
        "feedlot"
    ],
    "wof:name":"Maasberg Farms",
    "wof:placetype":"venue"
},
  "geometry": {"coordinates":[-87.63402499999999,38.11804],"type":"Point"}
}