{
  "type": "Feature",
  "properties": {
    "iso:country":"US",
    "sg:address":"7442 Co Rd 750 W",
    "sg:city":"Frankton",
    "sg:phone":"+1 765 754 8539",
    "sg:postcode":"46044",
    "sg:province":"IN",
    "sg:tags":[
        "farm",
        "corn"
    ],
    "wof:name":"Robert Odle",
    "wof:placetype":"venue"
},
  "geometry": {"coordinates":[-85.814263,40.215077],"type":"Point"}
}