{
  "type": "Feature",
  "properties": {
    "iso:country":"US",
    "sg:address":"631 W Main St",
    "sg:city":"Mitchell",
    "sg:classifiers":[
        {
            "category":"Shopping",
            "subcategory":"Used Merchandise",
            "type":"Retail Goods"
        }
    ],
    "sg:phone":"+1 812 849 9355",
    "sg:postcode":"47446",
    "sg:province":"IN",
    "wof:name":"Ecectria",
    "wof:placetype":"venue"
},
  "geometry": {"coordinates":[-86.472624,38.733065],"type":"Point"}
}