{
  "type": "Feature",
  "properties": {
    "addr:full":"2307 Edison Rd South Bend IN 46615",
    "addr:housenumber":"2307",
    "addr:postcode":"46615",
    "addr:street":"Edison Rd",
    "iso:country":"US",
    "sg:address":"2307 Edison Rd",
    "sg:city":"South Bend",
    "sg:classifiers":[
        {
            "category":"Food & Beverages",
            "subcategory":"Meat & Fish",
            "type":"Retail Goods"
        }
    ],
    "sg:phone":"+1 574 288 4267",
    "sg:postcode":"46615",
    "sg:province":"IN",
    "wof:name":"Heavenly Ham",
    "wof:placetype":"venue"
},
  "geometry": {"coordinates":[-86.215851,41.694579],"type":"Point"}
}