{
  "type": "Feature",
  "properties": {
    "addr:full":"541 Airport Rd Kendallville IN 46755",
    "addr:housenumber":"541",
    "addr:postcode":"46755",
    "addr:street":"Airport Rd",
    "iso:country":"US",
    "sg:address":"541 Airport Rd",
    "sg:city":"Kendallville",
    "sg:classifiers":[
        {
            "category":"Farming",
            "subcategory":"Farm & Veterinary Services",
            "type":"Manufacturing & Wholesale Goods"
        }
    ],
    "sg:phone":"+1 260 347 4444",
    "sg:postcode":"46755",
    "sg:province":"IN",
    "sg:tags":[
        "crop"
    ],
    "wof:name":"Aerial Application Service",
    "wof:placetype":"venue"
},
  "geometry": {"coordinates":[-85.25343599999999,41.470578],"type":"Point"}
}