{
  "type": "Feature",
  "properties": {
    "iso:country":"US",
    "sg:address":"555 E Morton St",
    "sg:city":"Marion",
    "sg:classifiers":[
        {
            "category":"Organizations",
            "subcategory":"Membership Organization",
            "type":"Services"
        }
    ],
    "sg:phone":"+1 765 668 4422",
    "sg:postcode":"46952",
    "sg:province":"IN",
    "sg:tags":[
        "athletic"
    ],
    "wof:name":"Marion Police Athletic League",
    "wof:placetype":"venue"
},
  "geometry": {"coordinates":[-85.650832,40.570035],"type":"Point"}
}