{
  "type": "Feature",
  "properties": {
    "addr:full":"1525 N Co Rd 750 E Hagerstown IN 47346",
    "addr:housenumber":"1525;750 e",
    "addr:postcode":"47346",
    "addr:street":"N Co Rd",
    "iso:country":"US",
    "sg:address":"1525 N Co Rd 750 E",
    "sg:city":"Hagerstown",
    "sg:classifiers":[
        {
            "category":"Museum",
            "type":"Entertainment"
        }
    ],
    "sg:phone":"+1 765 332 2495",
    "sg:postcode":"47346",
    "sg:province":"IN",
    "wof:name":"Wilbur Wright Birthplace Inc",
    "wof:placetype":"venue"
},
  "geometry": {"coordinates":[-85.242689,39.950627],"type":"Point"}
}