{
  "type": "Feature",
  "properties": {
    "iso:country":"US",
    "sg:address":"118 N Indiana St",
    "sg:city":"Greencastle",
    "sg:classifiers":[
        {
            "category":"Building & Trades",
            "subcategory":"Construction",
            "type":"Services"
        }
    ],
    "sg:phone":"+1 765 653 7210",
    "sg:postcode":"46135",
    "sg:province":"IN",
    "sg:tags":[
        "contractor"
    ],
    "wof:name":"Castle Builders Inc",
    "wof:placetype":"venue"
},
  "geometry": {"coordinates":[-86.86453,39.645341],"type":"Point"}
}