{
  "type": "Feature",
  "properties": {
    "iso:country":"US",
    "sg:address":"118 E Walnut St",
    "sg:city":"Rensselaer",
    "sg:classifiers":[
        {
            "category":"Retail",
            "subcategory":"Auto Rental",
            "type":"Services"
        }
    ],
    "sg:phone":"+1 219 866 7563",
    "sg:postcode":"47978",
    "sg:province":"IN",
    "sg:tags":[
        "automobile",
        "leasing"
    ],
    "wof:name":"White Freedom Lease",
    "wof:placetype":"venue"
},
  "geometry": {"coordinates":[-87.154061,40.943722],"type":"Point"}
}