{
  "type": "Feature",
  "properties": {
    "addr:full":"3425 Crescent Ave Fort Wayne IN 46805",
    "addr:housenumber":"3425",
    "addr:postcode":"46805",
    "addr:street":"Crescent Ave",
    "iso:country":"US",
    "sg:address":"3425 Crescent Ave",
    "sg:city":"Fort Wayne",
    "sg:classifiers":[
        {
            "category":"Organizations",
            "subcategory":"Religious Organization",
            "type":"Services"
        }
    ],
    "sg:phone":"+1 260 483 3173",
    "sg:postcode":"46805",
    "sg:province":"IN",
    "sg:tags":[
        "church"
    ],
    "sg:website":"www.holycrossfw.org",
    "wof:name":"Holy Cross Lutheran Church",
    "wof:placetype":"venue"
},
  "geometry": {"coordinates":[-85.113277,41.107117],"type":"Point"}
}