{
  "type": "Feature",
  "properties": {
    "addr:full":"3169 Ripley St Lake Station IN 46342",
    "addr:housenumber":"3169",
    "addr:postcode":"46342",
    "addr:street":"Ripley St",
    "iso:country":"US",
    "sg:address":"3169 Ripley St",
    "sg:city":"Lake Station",
    "sg:classifiers":[
        {
            "category":"Real Estate",
            "subcategory":"Architect",
            "type":"Services"
        }
    ],
    "sg:phone":"+1 219 962 3488",
    "sg:postcode":"46342",
    "sg:province":"IN",
    "wof:name":"Joseph B Martin Architect",
    "wof:placetype":"venue"
},
  "geometry": {"coordinates":[-87.24109300000001,41.567245],"type":"Point"}
}