{
  "type": "Feature",
  "properties": {
    "iso:country":"US",
    "sg:address":"729 W Hubbard Ave",
    "sg:city":"Elkhart",
    "sg:classifiers":[
        {
            "category":"Social Services",
            "subcategory":"Child Care",
            "type":"Services"
        }
    ],
    "sg:phone":"+1 574 389 7892",
    "sg:postcode":"46516",
    "sg:province":"IN",
    "wof:name":"Fox Child Care",
    "wof:placetype":"venue"
},
  "geometry": {"coordinates":[-85.977292,41.668536],"type":"Point"}
}