{
  "type": "Feature",
  "properties": {
    "addr:full":"7920 S 900 W-90 Warren IN 46792",
    "addr:housenumber":"7920;w-90",
    "addr:postcode":"warren in 46792",
    "addr:street":"S 900",
    "iso:country":"US",
    "sg:address":"7920 S 900 W-90",
    "sg:city":"Warren",
    "sg:classifiers":[
        {
            "category":"Manufacturing",
            "subcategory":"Printing",
            "type":"Manufacturing & Wholesale Goods"
        }
    ],
    "sg:phone":"+1 260 375 3531",
    "sg:postcode":"46792",
    "sg:province":"IN",
    "sg:tags":[
        "newspaper"
    ],
    "wof:name":"Warren Weekly",
    "wof:placetype":"venue"
},
  "geometry": {"coordinates":[-85.391034,40.626005],"type":"Point"}
}