{
  "type": "Feature",
  "properties": {
    "addr:full":"2401 Durkees Ferry Rd New Goshen IN 47885",
    "addr:housenumber":"2401",
    "addr:postcode":"47885",
    "addr:street":"Durkees Ferry Rd",
    "iso:country":"US",
    "sg:address":"2401 Durkees Ferry Rd",
    "sg:city":"New Goshen",
    "sg:classifiers":[
        {
            "category":"Food & Beverages",
            "subcategory":"Groceries & Convenience Stores",
            "type":"Retail Goods"
        }
    ],
    "sg:phone":"+1 812 535 4889",
    "sg:postcode":"47885",
    "sg:province":"IN",
    "wof:name":"New Goshen Mini Mart",
    "wof:placetype":"venue"
},
  "geometry": {"coordinates":[-87.45634200000001,39.575168],"type":"Point"}
}