{
  "type": "Feature",
  "properties": {
    "addr:full":"3024 Ridgeview Dr Indianapolis IN 46226",
    "addr:housenumber":"3024",
    "addr:postcode":"46226",
    "addr:street":"Ridgeview Dr",
    "iso:country":"US",
    "sg:address":"3024 Ridgeview Dr",
    "sg:city":"Indianapolis",
    "sg:classifiers":[
        {
            "category":"Manufacturing",
            "subcategory":"Buildings",
            "type":"Manufacturing & Wholesale Goods"
        },
        {
            "category":"Building & Trades",
            "subcategory":"Construction",
            "type":"Services"
        }
    ],
    "sg:phone":"+1 317 454 8596",
    "sg:postcode":"46226",
    "sg:province":"IN",
    "sg:tags":[
        "consultant",
        "builder",
        "management",
        "contractor",
        "home"
    ],
    "wof:name":"Rollins Construction Co",
    "wof:placetype":"venue"
},
  "geometry": {"coordinates":[-86.057602,39.81142],"type":"Point"}
}