{
  "type": "Feature",
  "properties": {
    "iso:country":"US",
    "sg:address":"8840 Calumet Ave Ste 103",
    "sg:city":"Munster",
    "sg:classifiers":[
        {
            "category":"Health Services",
            "subcategory":"Doctor",
            "type":"Services"
        }
    ],
    "sg:phone":"+1 219 836 7246",
    "sg:postcode":"46321",
    "sg:province":"IN",
    "sg:website":"www.spinemw.com",
    "wof:name":"Midwest Interventional Spine Specialists",
    "wof:placetype":"venue"
},
  "geometry": {"coordinates":[-87.509168,41.552866],"type":"Point"}
}