{
  "type": "Feature",
  "properties": {
    "iso:country":"US",
    "sg:address":"6721 Lake Valley Ct",
    "sg:city":"Fort Wayne",
    "sg:classifiers":[
        {
            "category":"Wholesale",
            "subcategory":"Electrical",
            "type":"Manufacturing & Wholesale Goods"
        }
    ],
    "sg:phone":"+1 260 749 7093",
    "sg:postcode":"46815",
    "sg:province":"IN",
    "sg:tags":[
        "electric",
        "motor"
    ],
    "wof:name":"Dayton Motor Group",
    "wof:placetype":"venue"
},
  "geometry": {"coordinates":[-85.052438,41.094027],"type":"Point"}
}