{
  "type": "Feature",
  "properties": {
    "iso:country":"US",
    "sg:address":"43 Aled Ln",
    "sg:city":"Valparaiso",
    "sg:classifiers":[
        {
            "category":"Building & Trades",
            "subcategory":"Construction",
            "type":"Services"
        }
    ],
    "sg:phone":"+1 219 926 3905",
    "sg:postcode":"46383",
    "sg:province":"IN",
    "sg:tags":[
        "house"
    ],
    "wof:name":"Equity Builders",
    "wof:placetype":"venue"
},
  "geometry": {"coordinates":[-87.058502,41.556459],"type":"Point"}
}