{
  "type": "Feature",
  "properties": {
    "addr:full":"6825 Hillsdale Ct Indianapolis IN 46250",
    "addr:housenumber":"6825",
    "addr:postcode":"46250",
    "addr:street":"Hillsdale Ct",
    "iso:country":"US",
    "sg:address":"6825 Hillsdale Ct",
    "sg:city":"Indianapolis",
    "sg:classifiers":[
        {
            "category":"Organizations",
            "subcategory":"Professional Association",
            "type":"Services"
        }
    ],
    "sg:phone":"+1 317 596 4950",
    "sg:postcode":"46250",
    "sg:province":"IN",
    "sg:website":"www.abc.org",
    "wof:name":"Associated Builders & Contrs",
    "wof:placetype":"venue"
},
  "geometry": {"coordinates":[-86.050062,39.896092],"type":"Point"}
}