{
  "type": "Feature",
  "properties": {
    "iso:country":"US",
    "sg:address":"1517 Emison St",
    "sg:city":"Vincennes",
    "sg:classifiers":[
        {
            "category":"Real Estate",
            "subcategory":"Real Estate Operator",
            "type":"Services"
        }
    ],
    "sg:phone":"+1 812 882 4968",
    "sg:postcode":"47591",
    "sg:province":"IN",
    "sg:tags":[
        "apartment"
    ],
    "wof:name":"Vincennes Niblack Apartments",
    "wof:placetype":"venue"
},
  "geometry": {"coordinates":[-87.5341,38.657144],"type":"Point"}
}