{
  "type": "Feature",
  "properties": {
    "iso:country":"US",
    "sg:address":"315 W Jefferson Blvd",
    "sg:city":"South Bend",
    "sg:classifiers":[
        {
            "category":"Real Estate",
            "subcategory":"Real Estate Operator",
            "type":"Services"
        }
    ],
    "sg:phone":"+1 574 236 4000",
    "sg:postcode":"46601",
    "sg:province":"IN",
    "sg:tags":[
        "building",
        "nonresidential"
    ],
    "wof:name":"Health Realty 9",
    "wof:placetype":"venue"
},
  "geometry": {"coordinates":[-86.25418999999999,41.675068],"type":"Point"}
}