{
  "type": "Feature",
  "properties": {
    "iso:country":"US",
    "sg:address":"4729 Prospect St",
    "sg:city":"Indianapolis",
    "sg:classifiers":[
        {
            "category":"Building & Trades",
            "subcategory":"Landscaping Services",
            "type":"Services"
        }
    ],
    "sg:phone":"+1 317 353 0241",
    "sg:postcode":"46203",
    "sg:province":"IN",
    "sg:tags":[
        "tree"
    ],
    "wof:name":"A Whitham's Tree",
    "wof:placetype":"venue"
},
  "geometry": {"coordinates":[-86.08914,39.752718],"type":"Point"}
}