{
  "type": "Feature",
  "properties": {
    "iso:country":"US",
    "sg:address":"508 S Green St",
    "sg:city":"Cambridge City",
    "sg:classifiers":[
        {
            "category":"Shopping",
            "type":"Retail Goods"
        }
    ],
    "sg:phone":"+1 765 962 4811",
    "sg:postcode":"47327",
    "sg:province":"IN",
    "sg:tags":[
        "ice"
    ],
    "wof:name":"Miller Corp",
    "wof:placetype":"venue"
},
  "geometry": {"coordinates":[-85.173141,39.808657],"type":"Point"}
}