{
  "type": "Feature",
  "properties": {
    "iso:country":"US",
    "sg:address":"1810 S Harrison St",
    "sg:city":"Alexandria",
    "sg:classifiers":[
        {
            "category":"Organizations",
            "subcategory":"Community Association",
            "type":"Services"
        }
    ],
    "sg:phone":"+1 765 724 7441",
    "sg:postcode":"46001",
    "sg:province":"IN",
    "sg:tags":[
        "fraternal"
    ],
    "wof:name":"Elks Lodge",
    "wof:placetype":"venue"
},
  "geometry": {"coordinates":[-85.673315,40.24661],"type":"Point"}
}