{
  "type": "Feature",
  "properties": {
    "iso:country":"US",
    "sg:address":"80 Ln 101B Hamilton Lake",
    "sg:city":"Hamilton",
    "sg:classifiers":[
        {
            "category":"Autos & Motor Vehicles",
            "subcategory":"Boat Sales",
            "type":"Retail Goods"
        }
    ],
    "sg:phone":"+1 260 488 2169",
    "sg:postcode":"46742",
    "sg:province":"IN",
    "sg:tags":[
        "dealer",
        "sales"
    ],
    "sg:website":"www.clarkslandingmarina.com",
    "wof:name":"Clark's Landing Marina",
    "wof:placetype":"venue"
},
  "geometry": {"coordinates":[-84.91163,41.561081],"type":"Point"}
}