{
  "type": "Feature",
  "properties": {
    "iso:country":"US",
    "sg:address":"316 Walnut St",
    "sg:city":"Lawrenceburg",
    "sg:classifiers":[
        {
            "category":"Wholesale",
            "subcategory":"Stationery",
            "type":"Manufacturing & Wholesale Goods"
        }
    ],
    "sg:phone":"+1 812 539 3030",
    "sg:postcode":"47025",
    "sg:province":"IN",
    "wof:name":"Touch-It Inc",
    "wof:placetype":"venue"
},
  "geometry": {"coordinates":[-84.850822,39.095141],"type":"Point"}
}