{
  "type": "Feature",
  "properties": {
    "iso:country":"US",
    "sg:address":"52317 Country Ct",
    "sg:city":"Elkhart",
    "sg:classifiers":[
        {
            "category":"Professional",
            "subcategory":"Management & Consulting",
            "type":"Services"
        }
    ],
    "sg:phone":"+1 574 970 0610",
    "sg:postcode":"46514",
    "sg:province":"IN",
    "sg:tags":[
        "consultant",
        "business"
    ],
    "wof:name":"Moreno Support Svc & Consltng",
    "wof:placetype":"venue"
},
  "geometry": {"coordinates":[-85.989258,41.734036],"type":"Point"}
}