{
  "type": "Feature",
  "properties": {
    "iso:country":"US",
    "sg:address":"7001 Hawthorn Park Dr",
    "sg:city":"Indianapolis",
    "sg:classifiers":[
        {
            "category":"Wholesale",
            "subcategory":"Construction Materials",
            "type":"Manufacturing & Wholesale Goods"
        }
    ],
    "sg:phone":"+1 317 849 5400",
    "sg:postcode":"46220",
    "sg:province":"IN",
    "sg:tags":[
        "marble"
    ],
    "sg:website":"www.tileinfo.com",
    "wof:name":"American Equipment Marlbe",
    "wof:placetype":"venue"
},
  "geometry": {"coordinates":[-86.072018,39.88335],"type":"Point"}
}