{
  "type": "Feature",
  "properties": {
    "iso:country":"US",
    "sg:address":"4343 State Rd 26 E",
    "sg:city":"Lafayette",
    "sg:classifiers":[
        {
            "category":"Travel",
            "subcategory":"Hotels & Motels",
            "type":"Entertainment"
        }
    ],
    "sg:phone":"+1 765 447 0575",
    "sg:postcode":"47905",
    "sg:province":"IN",
    "wof:name":"Radisson Hotel",
    "wof:placetype":"venue"
},
  "geometry": {"coordinates":[-86.82289,40.417544],"type":"Point"}
}