{
  "type": "Feature",
  "properties": {
    "iso:country":"US",
    "sg:address":"105 S Main St",
    "sg:city":"Topeka",
    "sg:classifiers":[
        {
            "category":"Personal",
            "subcategory":"Beauty Salon",
            "type":"Services"
        }
    ],
    "sg:phone":"+1 260 593 2134",
    "sg:postcode":"46571",
    "sg:province":"IN",
    "wof:name":"Silhouette",
    "wof:placetype":"venue"
},
  "geometry": {"coordinates":[-85.539466,41.539231],"type":"Point"}
}