{
  "type": "Feature",
  "properties": {
    "iso:country":"US",
    "sg:address":"302 N Hart St",
    "sg:city":"Princeton",
    "sg:classifiers":[
        {
            "category":"Organizations",
            "subcategory":"Community Association",
            "type":"Services"
        }
    ],
    "sg:phone":"+1 812 385 2518",
    "sg:postcode":"47670",
    "sg:province":"IN",
    "sg:tags":[
        "fraternal"
    ],
    "wof:name":"Elks Lodge",
    "wof:placetype":"venue"
},
  "geometry": {"coordinates":[-87.56866100000001,38.35816],"type":"Point"}
}