{
  "type": "Feature",
  "properties": {
    "iso:country":"US",
    "sg:address":"915 Main St",
    "sg:city":"Evansville",
    "sg:classifiers":[
        {
            "category":"Building & Trades",
            "subcategory":"Cleaning & Sanitation",
            "type":"Services"
        }
    ],
    "sg:phone":"+1 812 425 3673",
    "sg:postcode":"47708",
    "sg:province":"IN",
    "sg:tags":[
        "janitor"
    ],
    "wof:name":"J J's Cleaning Enterprise",
    "wof:placetype":"venue"
},
  "geometry": {"coordinates":[-87.56489999999999,37.975494],"type":"Point"}
}