{
  "type": "Feature",
  "properties": {
    "iso:country":"US",
    "sg:address":"1091 Hospital Rd",
    "sg:city":"Needham",
    "sg:classifiers":[
        {
            "category":"Government",
            "subcategory":"Fire Station",
            "type":"Public Place"
        }
    ],
    "sg:phone":"+1 317 736 4343",
    "sg:postcode":"46124",
    "sg:province":"IN",
    "sg:tags":[
        "department"
    ],
    "wof:name":"Needham Fire Dept",
    "wof:placetype":"venue"
},
  "geometry": {"coordinates":[-86.08278799999999,39.362443],"type":"Point"}
}