{
  "type": "Feature",
  "properties": {
    "addr:full":"477 S Landmark Ave Bloomington IN 47403",
    "addr:housenumber":"477",
    "addr:postcode":"47403",
    "addr:street":"S Landmark Ave",
    "iso:country":"US",
    "sg:address":"477 S Landmark Ave",
    "sg:city":"Bloomington",
    "sg:classifiers":[
        {
            "category":"Health Services",
            "subcategory":"Dentist",
            "type":"Services"
        }
    ],
    "sg:phone":"+1 812 355 0855",
    "sg:postcode":"47403",
    "sg:province":"IN",
    "sg:tags":[
        "pediatric"
    ],
    "sg:website":"www.bloomingtonpediatricdentistr...",
    "wof:name":"Bloomington Pediatric Dentistry",
    "wof:placetype":"venue"
},
  "geometry": {"coordinates":[-86.556257,39.163985],"type":"Point"}
}