{
  "type": "Feature",
  "properties": {
    "addr:full":"5983 Laurel Ridge Dr Newburgh IN 47630",
    "addr:housenumber":"5983",
    "addr:postcode":"47630",
    "addr:street":"Laurel Ridge Dr",
    "iso:country":"US",
    "sg:address":"5983 Laurel Ridge Dr",
    "sg:city":"Newburgh",
    "sg:classifiers":[
        {
            "category":"Building & Trades",
            "subcategory":"Locksmith",
            "type":"Services"
        }
    ],
    "sg:phone":"+1 812 473 3536",
    "sg:postcode":"47630",
    "sg:province":"IN",
    "sg:tags":[
        "key"
    ],
    "wof:name":"A-1 Lock & Safe Co. Inc.",
    "wof:placetype":"venue"
},
  "geometry": {"coordinates":[-87.369214,38.002302],"type":"Point"}
}