{
  "type": "Feature",
  "properties": {
    "addr:full":"7340 Oak Knoll Dr Indianapolis IN 46217",
    "addr:housenumber":"7340",
    "addr:postcode":"46217",
    "addr:street":"Oak Knoll Dr",
    "iso:country":"US",
    "sg:address":"7340 Oak Knoll Dr",
    "sg:city":"Indianapolis",
    "sg:classifiers":[
        {
            "category":"Professional",
            "subcategory":"Business Services",
            "type":"Services"
        }
    ],
    "sg:phone":"+1 317 881 9900",
    "sg:postcode":"46217",
    "sg:province":"IN",
    "sg:tags":[
        "broker"
    ],
    "wof:name":"Anthony Wayne Bus Exch",
    "wof:placetype":"venue"
},
  "geometry": {"coordinates":[-86.180672,39.658177],"type":"Point"}
}