{
  "type": "Feature",
  "properties": {
    "iso:country":"US",
    "sg:address":"959 Beechwood Ave",
    "sg:city":"Middletown",
    "sg:classifiers":[
        {
            "category":"Organizations",
            "subcategory":"Community Association",
            "type":"Services"
        }
    ],
    "sg:phone":"+1 765 354 9293",
    "sg:postcode":"47356",
    "sg:province":"IN",
    "sg:tags":[
        "fraternal"
    ],
    "wof:name":"Masonic Lodge",
    "wof:placetype":"venue"
},
  "geometry": {"coordinates":[-85.53851,40.061264],"type":"Point"}
}