{
  "type": "Feature",
  "properties": {
    "addr:full":"1030 Springwater Cir Greenwood IN 46143",
    "addr:housenumber":"1030",
    "addr:postcode":"46143",
    "addr:street":"Springwater Cir",
    "iso:country":"US",
    "sg:address":"1030 Springwater Cir",
    "sg:city":"Greenwood",
    "sg:classifiers":[
        {
            "category":"Professional",
            "subcategory":"Accounting & Tax Preparation",
            "type":"Services"
        }
    ],
    "sg:phone":"+1 317 859 0095",
    "sg:postcode":"46143",
    "sg:province":"IN",
    "sg:tags":[
        "accountant"
    ],
    "wof:name":"Shawn Antell",
    "wof:placetype":"venue"
},
  "geometry": {"coordinates":[-86.079763,39.600639],"type":"Point"}
}