{
  "type": "Feature",
  "properties": {
    "iso:country":"US",
    "sg:address":"4832 Hanna St",
    "sg:city":"Fort Wayne",
    "sg:classifiers":[
        {
            "category":"Social Services",
            "subcategory":"Child Care",
            "type":"Services"
        }
    ],
    "sg:phone":"+1 260 456 4411",
    "sg:postcode":"46806",
    "sg:province":"IN",
    "wof:name":"Dominica's Child Care",
    "wof:placetype":"venue"
},
  "geometry": {"coordinates":[-85.12735499999999,41.039359],"type":"Point"}
}