{
  "type": "Feature",
  "properties": {
    "iso:country":"US",
    "sg:address":"23561 US Hwy 33",
    "sg:city":"Elkhart",
    "sg:classifiers":[
        {
            "category":"Retail",
            "subcategory":"Auto Repair",
            "type":"Services"
        }
    ],
    "sg:phone":"+1 574 875 7759",
    "sg:postcode":"46517",
    "sg:province":"IN",
    "sg:tags":[
        "body",
        "automobile",
        "painting"
    ],
    "wof:name":"Dan's Body Shop Inc",
    "wof:placetype":"venue"
},
  "geometry": {"coordinates":[-85.920762,41.635612],"type":"Point"}
}