{
  "type": "Feature",
  "properties": {
    "addr:full":"10202 Broadway Crown Point IN 46307",
    "addr:housenumber":"10202",
    "addr:postcode":"46307",
    "addr:street":"Broadway",
    "iso:country":"US",
    "sg:address":"10202 Broadway",
    "sg:city":"Crown Point",
    "sg:classifiers":[
        {
            "category":"Organizations",
            "subcategory":"Religious Organization",
            "type":"Services"
        }
    ],
    "sg:phone":"+1 219 663 9200",
    "sg:postcode":"46307",
    "sg:province":"IN",
    "sg:tags":[
        "church"
    ],
    "sg:website":"www.bethelweb.org",
    "wof:name":"Bethel Baptist Church",
    "wof:placetype":"venue"
},
  "geometry": {"coordinates":[-87.335572,41.432941],"type":"Point"}
}