{
  "type": "Feature",
  "properties": {
    "addr:full":"500 Frank St Shelbyville IN 46176",
    "addr:housenumber":"500",
    "addr:postcode":"46176",
    "addr:street":"Frank St",
    "iso:country":"US",
    "sg:address":"500 Frank St",
    "sg:city":"Shelbyville",
    "sg:classifiers":[
        {
            "category":"Professional",
            "type":"Services"
        },
        {
            "category":"Arena",
            "subcategory":"Sports Club",
            "type":"Entertainment"
        }
    ],
    "sg:phone":"+1 317 392 1612",
    "sg:postcode":"46176",
    "sg:province":"IN",
    "sg:tags":[
        "fairground",
        "shows",
        "exposition",
        "fair",
        "trade"
    ],
    "wof:name":"Shelby County Fair Association Inc",
    "wof:placetype":"venue"
},
  "geometry": {"coordinates":[-85.76062,39.525848],"type":"Point"}
}