{
  "type": "Feature",
  "properties": {
    "iso:country":"US",
    "sg:address":"23746 Co Rd 36",
    "sg:city":"Goshen",
    "sg:classifiers":[
        {
            "category":"Farming",
            "subcategory":"Livestock Farm",
            "type":"Manufacturing & Wholesale Goods"
        }
    ],
    "sg:phone":"+1 574 875 6457",
    "sg:postcode":"46526",
    "sg:province":"IN",
    "sg:tags":[
        "beef",
        "feedlot",
        "cattle"
    ],
    "wof:name":"Russell Drudge",
    "wof:placetype":"venue"
},
  "geometry": {"coordinates":[-85.919765,41.565656],"type":"Point"}
}