{
  "type": "Feature",
  "properties": {
    "iso:country":"US",
    "sg:address":"2508 E 5th St",
    "sg:city":"Anderson",
    "sg:classifiers":[
        {
            "category":"Retail",
            "subcategory":"Repair Shop",
            "type":"Services"
        }
    ],
    "sg:phone":"+1 765 640 4131",
    "sg:postcode":"46012",
    "sg:province":"IN",
    "sg:tags":[
        "related"
    ],
    "wof:name":"Quality Handpiece Repair",
    "wof:placetype":"venue"
},
  "geometry": {"coordinates":[-85.645858,40.111197],"type":"Point"}
}