{
  "type": "Feature",
  "properties": {
    "iso:country":"US",
    "sg:address":"14649 US Hwy 41",
    "sg:city":"Evansville",
    "sg:classifiers":[
        {
            "category":"Building & Trades",
            "subcategory":"Construction",
            "type":"Services"
        }
    ],
    "sg:phone":"+1 812 867 6635",
    "sg:postcode":"47725",
    "sg:province":"IN",
    "sg:tags":[
        "excavating",
        "contractor"
    ],
    "sg:website":"www.koesterco.com",
    "wof:name":"Koester Contracting Corp",
    "wof:placetype":"venue"
},
  "geometry": {"coordinates":[-87.547968,37.931467],"type":"Point"}
}