{
  "type": "Feature",
  "properties": {
    "iso:country":"US",
    "sg:address":"1401 E Ridge Rd",
    "sg:city":"Gary",
    "sg:classifiers":[
        {
            "category":"Autos & Motor Vehicles",
            "subcategory":"Fuel & Gas Station",
            "type":"Retail Goods"
        }
    ],
    "sg:phone":"+1 219 887 3982",
    "sg:postcode":"46409",
    "sg:province":"IN",
    "sg:tags":[
        "oil"
    ],
    "wof:name":"A & K Oil",
    "wof:placetype":"venue"
},
  "geometry": {"coordinates":[-87.318434,41.551109],"type":"Point"}
}