{
  "type": "Feature",
  "properties": {
    "iso:country":"US",
    "sg:address":"5512 US Hwy 36",
    "sg:city":"Middletown",
    "sg:classifiers":[
        {
            "category":"Wholesale",
            "subcategory":"Scrap",
            "type":"Manufacturing & Wholesale Goods"
        }
    ],
    "sg:phone":"+1 765 533 4156",
    "sg:postcode":"47356",
    "sg:province":"IN",
    "sg:tags":[
        "metal",
        "iron"
    ],
    "wof:name":"Joe's Wrecking & Salvage Inc",
    "wof:placetype":"venue"
},
  "geometry": {"coordinates":[-85.490021,40.004668],"type":"Point"}
}