{
  "type": "Feature",
  "properties": {
    "addr:full":"2823 Martha St Hammond IN 46323",
    "addr:housenumber":"2823",
    "addr:postcode":"46323",
    "addr:street":"Martha St",
    "iso:country":"US",
    "sg:address":"2823 Martha St",
    "sg:city":"Hammond",
    "sg:classifiers":[
        {
            "category":"Social Services",
            "type":"Services"
        }
    ],
    "sg:phone":"+1 219 844 4856",
    "sg:postcode":"46323",
    "sg:province":"IN",
    "sg:tags":[
        "organization",
        "welfare"
    ],
    "wof:name":"New Life Single Parent Resrc",
    "wof:placetype":"venue"
},
  "geometry": {"coordinates":[-87.460705,41.59065],"type":"Point"}
}