{
  "type": "Feature",
  "properties": {
    "iso:country":"US",
    "sg:address":"7448 Brookville Rd",
    "sg:city":"Indianapolis",
    "sg:classifiers":[
        {
            "category":"Building & Trades",
            "subcategory":"Construction",
            "type":"Services"
        }
    ],
    "sg:phone":"+1 317 356 8584",
    "sg:postcode":"46239",
    "sg:province":"IN",
    "sg:tags":[
        "contractor"
    ],
    "wof:name":"Ashmore Masonry Inc",
    "wof:placetype":"venue"
},
  "geometry": {"coordinates":[-86.037921,39.752386],"type":"Point"}
}