{
  "type": "Feature",
  "properties": {
    "iso:country":"US",
    "sg:address":"700 Western Ave",
    "sg:city":"Winchester",
    "sg:classifiers":[
        {
            "category":"Government",
            "subcategory":"Office",
            "type":"Public Place"
        }
    ],
    "sg:phone":"+1 765 584 1463",
    "sg:postcode":"47394",
    "sg:province":"IN",
    "wof:name":"Randolph County Veteran's Ofc",
    "wof:placetype":"venue"
},
  "geometry": {"coordinates":[-84.985953,40.163881],"type":"Point"}
}