{
  "type": "Feature",
  "properties": {
    "iso:country":"US",
    "sg:address":"820 Goshen Ave",
    "sg:city":"Fort Wayne",
    "sg:classifiers":[
        {
            "category":"Restaurant",
            "type":"Food & Drink"
        }
    ],
    "sg:phone":"+1 260 483 2387",
    "sg:postcode":"46808",
    "sg:province":"IN",
    "sg:tags":[
        "eating"
    ],
    "wof:name":"Lon Sen Chinese Restaurant",
    "wof:placetype":"venue"
},
  "geometry": {"coordinates":[-85.151487,41.097314],"type":"Point"}
}