{
  "type": "Feature",
  "properties": {
    "iso:country":"US",
    "sg:address":"906 S Hudson St",
    "sg:city":"Sheridan",
    "sg:classifiers":[
        {
            "category":"Shopping",
            "subcategory":"Computers & Home Electronics",
            "type":"Retail Goods"
        }
    ],
    "sg:phone":"+1 317 758 4176",
    "sg:postcode":"46069",
    "sg:province":"IN",
    "sg:tags":[
        "equipment",
        "satellite",
        "system"
    ],
    "wof:name":"Bob's Satellite TV",
    "wof:placetype":"venue"
},
  "geometry": {"coordinates":[-86.214069,40.130759],"type":"Point"}
}