{
  "type": "Feature",
  "properties": {
    "addr:full":"6103 W Jefferson Blvd Fort Wayne IN 46804",
    "addr:housenumber":"6103",
    "addr:postcode":"46804",
    "addr:street":"W Jefferson Blvd",
    "iso:country":"US",
    "sg:address":"6103 W Jefferson Blvd",
    "sg:city":"Fort Wayne",
    "sg:classifiers":[
        {
            "category":"Retail",
            "subcategory":"Repair Shop",
            "type":"Services"
        }
    ],
    "sg:phone":"+1 260 432 8080",
    "sg:postcode":"46804",
    "sg:province":"IN",
    "sg:tags":[
        "shaver"
    ],
    "wof:name":"Peter's Shaver Shop",
    "wof:placetype":"venue"
},
  "geometry": {"coordinates":[-85.221526,41.057618],"type":"Point"}
}