{
  "type": "Feature",
  "properties": {
    "iso:country":"US",
    "sg:address":"311 W 1st St",
    "sg:city":"New Albany",
    "sg:classifiers":[
        {
            "category":"Government",
            "subcategory":"Police Station",
            "type":"Public Place"
        }
    ],
    "sg:phone":"+1 812 948 5400",
    "sg:postcode":"47150",
    "sg:province":"IN",
    "sg:tags":[
        "sheriff"
    ],
    "wof:name":"Floyd County Sheriff Dept",
    "wof:placetype":"venue"
},
  "geometry": {"coordinates":[-85.825183,38.285205],"type":"Point"}
}