{
  "type": "Feature",
  "properties": {
    "addr:full":"108 S Main St South Bend IN 46601",
    "addr:housenumber":"108",
    "addr:postcode":"46601",
    "addr:street":"S Main St",
    "iso:country":"US",
    "sg:address":"108 S Main St",
    "sg:city":"South Bend",
    "sg:classifiers":[
        {
            "category":"Health Services",
            "subcategory":"Health Practitioner",
            "type":"Services"
        }
    ],
    "sg:phone":"+1 574 234 7244",
    "sg:postcode":"46601",
    "sg:province":"IN",
    "sg:tags":[
        "pathologist",
        "speech"
    ],
    "wof:name":"Speech Pathology Enterprises",
    "wof:placetype":"venue"
},
  "geometry": {"coordinates":[-86.251959,41.675008],"type":"Point"}
}