{
  "type": "Feature",
  "properties": {
    "addr:full":"2130 S Bend Ave South Bend IN 46637",
    "addr:housenumber":"2130",
    "addr:postcode":"46637",
    "addr:street":"S Bend Ave",
    "iso:country":"US",
    "sg:address":"2130 S Bend Ave",
    "sg:city":"South Bend",
    "sg:classifiers":[
        {
            "category":"Shopping",
            "type":"Retail Goods"
        }
    ],
    "sg:phone":"+1 574 272 2245",
    "sg:postcode":"46637",
    "sg:province":"IN",
    "sg:tags":[
        "hearing",
        "equipment",
        "supply",
        "impaired"
    ],
    "wof:name":"Miracle-Ear",
    "wof:placetype":"venue"
},
  "geometry": {"coordinates":[-86.217752,41.699286],"type":"Point"}
}