{
  "type": "Feature",
  "properties": {
    "iso:country":"US",
    "sg:address":"1301 W J F K Dr",
    "sg:city":"North Vernon",
    "sg:classifiers":[
        {
            "category":"Building & Trades",
            "subcategory":"Construction",
            "type":"Services"
        }
    ],
    "sg:phone":"+1 812 346 9400",
    "sg:postcode":"47265",
    "sg:province":"IN",
    "sg:tags":[
        "home",
        "improvement"
    ],
    "sg:website":"www.lowes.com",
    "wof:name":"Lowe's",
    "wof:placetype":"venue"
},
  "geometry": {"coordinates":[-85.622483,39.003109],"type":"Point"}
}