{
  "type": "Feature",
  "properties": {
    "iso:country":"US",
    "sg:address":"55 Monument Cir Ste 1014",
    "sg:city":"Indianapolis",
    "sg:classifiers":[
        {
            "category":"Organizations",
            "subcategory":"Non-profit Organization",
            "type":"Services"
        }
    ],
    "sg:phone":"+1 317 639 9501",
    "sg:postcode":"46204",
    "sg:province":"IN",
    "sg:tags":[
        "charity",
        "foundations-educational",
        "philanthropic",
        "research"
    ],
    "wof:name":"The Virginia Kells Basso Foundation",
    "wof:placetype":"venue"
},
  "geometry": {"coordinates":[-86.157504,39.768205],"type":"Point"}
}