{
  "type": "Feature",
  "properties": {
    "iso:country":"US",
    "sg:address":"1402 W 22nd St",
    "sg:city":"Anderson",
    "sg:classifiers":[
        {
            "category":"Manufacturing",
            "subcategory":"Metals",
            "type":"Manufacturing & Wholesale Goods"
        }
    ],
    "sg:phone":"+1 765 643 6688",
    "sg:postcode":"46016",
    "sg:province":"IN",
    "sg:tags":[
        "fabricator",
        "sheet"
    ],
    "wof:name":"ATA Inc",
    "wof:placetype":"venue"
},
  "geometry": {"coordinates":[-85.69886,40.094396],"type":"Point"}
}