{
  "type": "Feature",
  "properties": {
    "iso:country":"US",
    "sg:address":"1155 W Mishawaka Ave",
    "sg:city":"South Bend",
    "sg:classifiers":[
        {
            "category":"Retail",
            "subcategory":"Auto Repair",
            "type":"Services"
        }
    ],
    "sg:phone":"+1 574 234 3999",
    "sg:postcode":"46615",
    "sg:province":"IN",
    "sg:tags":[
        "repairing",
        "automobile"
    ],
    "wof:name":"Wiegand's Service Ctr",
    "wof:placetype":"venue"
},
  "geometry": {"coordinates":[-86.233884,41.666996],"type":"Point"}
}