{
  "type": "Feature",
  "properties": {
    "addr:full":"6704 E State Blvd Fort Wayne IN 46815",
    "addr:housenumber":"6704",
    "addr:postcode":"fort;46815",
    "addr:street":"E State Blvd",
    "iso:country":"US",
    "sg:address":"6704 E State Blvd",
    "sg:city":"Fort Wayne",
    "sg:classifiers":[
        {
            "category":"Banks & Credit Unions",
            "subcategory":"Bank",
            "type":"Services"
        }
    ],
    "sg:phone":"+1 260 427 8213",
    "sg:postcode":"46815",
    "sg:province":"IN",
    "wof:name":"Bank One",
    "wof:placetype":"venue"
},
  "geometry": {"coordinates":[-85.054563,41.103964],"type":"Point"}
}