{
  "type": "Feature",
  "properties": {
    "iso:country":"US",
    "sg:address":"5260 Commerce Cir",
    "sg:city":"Indianapolis",
    "sg:classifiers":[
        {
            "category":"Freight",
            "type":"Transportation"
        }
    ],
    "sg:phone":"+1 317 887 1406",
    "sg:postcode":"46237",
    "sg:province":"IN",
    "sg:tags":[
        "commercial",
        "storage"
    ],
    "wof:name":"Storage USA",
    "wof:placetype":"venue"
},
  "geometry": {"coordinates":[-86.079528,39.655435],"type":"Point"}
}