{
  "type": "Feature",
  "properties": {
    "addr:full":"5004 White Oak Ter Lowell IN 46356",
    "addr:housenumber":"5004",
    "addr:postcode":"46356",
    "addr:street":"White Oak Ter",
    "iso:country":"US",
    "sg:address":"5004 White Oak Ter",
    "sg:city":"Lowell",
    "sg:classifiers":[
        {
            "category":"Home & Garden",
            "subcategory":"Garden Supply",
            "type":"Retail Goods"
        }
    ],
    "sg:phone":"+1 219 696 9315",
    "sg:postcode":"46356",
    "sg:province":"IN",
    "sg:tags":[
        "house",
        "bird",
        "feeder"
    ],
    "wof:name":"Magnum Feeders Inc",
    "wof:placetype":"venue"
},
  "geometry": {"coordinates":[-87.39393800000001,41.332522],"type":"Point"}
}