{
  "type": "Feature",
  "properties": {
    "iso:country":"US",
    "sg:address":"7626 W Highland Dr",
    "sg:city":"Ligonier",
    "sg:classifiers":[
        {
            "category":"Personal",
            "subcategory":"Beauty Salon",
            "type":"Services"
        }
    ],
    "sg:phone":"+1 260 894 4161",
    "sg:postcode":"46767",
    "sg:province":"IN",
    "sg:tags":[
        "shop"
    ],
    "wof:name":"Style Rite Beauty Shop",
    "wof:placetype":"venue"
},
  "geometry": {"coordinates":[-85.567986,41.435836],"type":"Point"}
}