{
  "type": "Feature",
  "properties": {
    "iso:country":"US",
    "sg:address":"320 N East St",
    "sg:city":"Lebanon",
    "sg:classifiers":[
        {
            "category":"Insurance",
            "subcategory":"Insurance Agent",
            "type":"Services"
        }
    ],
    "sg:phone":"+1 765 482 0640",
    "sg:postcode":"46052",
    "sg:province":"IN",
    "wof:name":"Boone Mutual Agency Inc",
    "wof:placetype":"venue"
},
  "geometry": {"coordinates":[-86.466925,40.049599],"type":"Point"}
}