{
  "type": "Feature",
  "properties": {
    "addr:full":"1560 N State St Greenfield IN 46140",
    "addr:housenumber":"1560",
    "addr:postcode":"46140",
    "addr:street":"N State St",
    "iso:country":"US",
    "sg:address":"1560 N State St",
    "sg:city":"Greenfield",
    "sg:classifiers":[
        {
            "category":"Organizations",
            "subcategory":"Religious Organization",
            "type":"Services"
        }
    ],
    "sg:phone":"+1 317 477 0052",
    "sg:postcode":"46140",
    "sg:province":"IN",
    "sg:tags":[
        "church"
    ],
    "wof:name":"Acts 1:8 Baptist Church",
    "wof:placetype":"venue"
},
  "geometry": {"coordinates":[-85.76987099999999,39.805349],"type":"Point"}
}