{
  "type": "Feature",
  "properties": {
    "iso:country":"US",
    "sg:address":"23805 Co Rd 6",
    "sg:city":"Elkhart",
    "sg:classifiers":[
        {
            "category":"Real Estate",
            "subcategory":"Developer",
            "type":"Services"
        }
    ],
    "sg:phone":"+1 574 262 2576",
    "sg:postcode":"46514",
    "sg:province":"IN",
    "wof:name":"Northland Corp",
    "wof:placetype":"venue"
},
  "geometry": {"coordinates":[-85.926735,41.723954],"type":"Point"}
}