{
  "type": "Feature",
  "properties": {
    "iso:country":"US",
    "sg:address":"1852 US Hwy 40 Scn",
    "sg:city":"Clayton",
    "sg:classifiers":[
        {
            "category":"Organizations",
            "subcategory":"Religious Organization",
            "type":"Services"
        }
    ],
    "sg:phone":"+1 317 539 5258",
    "sg:postcode":"46118",
    "sg:province":"IN",
    "sg:tags":[
        "church"
    ],
    "wof:name":"Belleville Church Of Christ",
    "wof:placetype":"venue"
},
  "geometry": {"coordinates":[-86.487743,39.677508],"type":"Point"}
}