{
  "type": "Feature",
  "properties": {
    "iso:country":"US",
    "sg:address":"2230 US Hwy 421",
    "sg:city":"Osgood",
    "sg:classifiers":[
        {
            "category":"Manufacturing",
            "subcategory":"Lumber",
            "type":"Manufacturing & Wholesale Goods"
        }
    ],
    "sg:phone":"+1 812 654 4199",
    "sg:postcode":"47037",
    "sg:province":"IN",
    "sg:tags":[
        "company",
        "logging"
    ],
    "wof:name":"David Benham Logging",
    "wof:placetype":"venue"
},
  "geometry": {"coordinates":[-85.280253,39.113874],"type":"Point"}
}