{
  "type": "Feature",
  "properties": {
    "iso:country":"US",
    "sg:address":"2844 Priscilla Ave",
    "sg:city":"Indianapolis",
    "sg:classifiers":[
        {
            "category":"Shopping",
            "subcategory":"Discount & Variety Stores",
            "type":"Retail Goods"
        }
    ],
    "sg:phone":"+1 317 545 6887",
    "sg:postcode":"46218",
    "sg:province":"IN",
    "wof:name":"Rachelle's Variety",
    "wof:placetype":"venue"
},
  "geometry": {"coordinates":[-86.068269,39.809199],"type":"Point"}
}