{
  "type": "Feature",
  "properties": {
    "iso:country":"US",
    "sg:address":"9003 Calumet Ave",
    "sg:city":"Munster",
    "sg:classifiers":[
        {
            "category":"Health Services",
            "subcategory":"Doctor",
            "type":"Services"
        }
    ],
    "sg:phone":"+1 219 836 0306",
    "sg:postcode":"46321",
    "sg:province":"IN",
    "sg:tags":[
        "physician",
        "surgeon"
    ],
    "wof:name":"Nephrology Specialists PC",
    "wof:placetype":"venue"
},
  "geometry": {"coordinates":[-87.508934,41.548962],"type":"Point"}
}