{
  "type": "Feature",
  "properties": {
    "iso:country":"US",
    "sg:address":"6122 Goshen Rd",
    "sg:city":"Fort Wayne",
    "sg:classifiers":[
        {
            "category":"Organizations",
            "subcategory":"Community Association",
            "type":"Services"
        }
    ],
    "sg:phone":"+1 260 489 6300",
    "sg:postcode":"46818",
    "sg:province":"IN",
    "sg:tags":[
        "business"
    ],
    "wof:name":"Daughters of Isabella 246",
    "wof:placetype":"venue"
},
  "geometry": {"coordinates":[-85.219933,41.150404],"type":"Point"}
}