{
  "type": "Feature",
  "properties": {
    "iso:country":"US",
    "sg:address":"4483 N 625 E",
    "sg:city":"Crawfordsville",
    "sg:classifiers":[
        {
            "category":"Autos & Motor Vehicles",
            "subcategory":"Fuel & Gas Station",
            "type":"Retail Goods"
        },
        {
            "category":"Food & Beverages",
            "subcategory":"Groceries & Convenience Stores",
            "type":"Retail Goods"
        }
    ],
    "sg:phone":"+1 765 794 4858",
    "sg:postcode":"47933",
    "sg:province":"IN",
    "wof:name":"Darlington Mini Mart Inc",
    "wof:placetype":"venue"
},
  "geometry": {"coordinates":[-86.78602100000001,40.101297],"type":"Point"}
}