{
  "type": "Feature",
  "properties": {
    "iso:country":"US",
    "sg:address":"9200 Zionsville Rd",
    "sg:city":"Indianapolis",
    "sg:classifiers":[
        {
            "category":"Manufacturing",
            "subcategory":"Rubber & Plastics",
            "type":"Manufacturing & Wholesale Goods"
        }
    ],
    "sg:phone":"+1 317 291 1213",
    "sg:postcode":"46268",
    "sg:province":"IN",
    "sg:website":"www.elliottfoam.com",
    "wof:name":"Elliott Co Of Indianapolis Inc",
    "wof:placetype":"venue"
},
  "geometry": {"coordinates":[-86.259939,39.914586],"type":"Point"}
}