{
  "type": "Feature",
  "properties": {
    "iso:country":"US",
    "sg:address":"13661 Golden Ridge Ln",
    "sg:city":"Mc Cordsville",
    "sg:classifiers":[
        {
            "category":"Professional",
            "type":"Services"
        }
    ],
    "sg:phone":"+1 317 335 7262",
    "sg:postcode":"46055",
    "sg:province":"IN",
    "wof:name":"Rick D Schofield",
    "wof:placetype":"venue"
},
  "geometry": {"coordinates":[-85.922912,39.938036],"type":"Point"}
}