{
  "type": "Feature",
  "properties": {
    "iso:country":"US",
    "sg:address":"402 N Huntington St",
    "sg:city":"Syracuse",
    "sg:classifiers":[
        {
            "category":"Government",
            "subcategory":"Office",
            "type":"Public Place"
        }
    ],
    "sg:phone":"+1 574 457 4100",
    "sg:postcode":"46567",
    "sg:province":"IN",
    "sg:tags":[
        "village"
    ],
    "wof:name":"City Ambulance",
    "wof:placetype":"venue"
},
  "geometry": {"coordinates":[-85.75082999999999,41.425746],"type":"Point"}
}