{
  "type": "Feature",
  "properties": {
    "iso:country":"US",
    "sg:address":"3430 Backmeyer Rd",
    "sg:city":"Richmond",
    "sg:classifiers":[
        {
            "category":"Organizations",
            "subcategory":"Religious Organization",
            "type":"Services"
        }
    ],
    "sg:phone":"+1 765 962 7738",
    "sg:postcode":"47374",
    "sg:province":"IN",
    "sg:tags":[
        "church"
    ],
    "sg:website":"www.christunitedchurch.com",
    "wof:name":"Christ United Church",
    "wof:placetype":"venue"
},
  "geometry": {"coordinates":[-84.856017,39.82266],"type":"Point"}
}