{
  "type": "Feature",
  "properties": {
    "iso:country":"US",
    "sg:address":"3730 W 16th St",
    "sg:city":"Indianapolis",
    "sg:classifiers":[
        {
            "category":"Bars & Pubs",
            "type":"Food & Drink"
        },
        {
            "category":"Restaurant",
            "type":"Food & Drink"
        }
    ],
    "sg:phone":"+1 317 635 9820",
    "sg:postcode":"46222",
    "sg:province":"IN",
    "sg:tags":[
        "brew"
    ],
    "wof:name":"500 International Sports Bar & Grill",
    "wof:placetype":"venue"
},
  "geometry": {"coordinates":[-86.2248,39.78764],"type":"Point"}
}