{
  "type": "Feature",
  "properties": {
    "iso:country":"US",
    "sg:address":"812 W Main St",
    "sg:city":"Peru",
    "sg:classifiers":[
        {
            "category":"Restaurant",
            "type":"Food & Drink"
        }
    ],
    "sg:menulink":"http://www.allmenus.com/in/peru/159199-arbys/menu/",
    "sg:phone":"+1 765 473 3966",
    "sg:postcode":"46970",
    "sg:province":"IN",
    "sg:tags":[
        "burger",
        "american"
    ],
    "wof:name":"Arby's",
    "wof:placetype":"venue"
},
  "geometry": {"coordinates":[-86.09122499999999,40.745238],"type":"Point"}
}