{
  "type": "Feature",
  "properties": {
    "addr:full":"60810 Co Rd 1 Elkhart IN 46517",
    "addr:housenumber":"60810",
    "addr:postcode":"46517",
    "addr:street":"Co Rd 1",
    "iso:country":"US",
    "sg:address":"60810 Co Rd 1",
    "sg:city":"Elkhart",
    "sg:phone":"+1 574 522 7555",
    "sg:postcode":"46517",
    "sg:province":"IN",
    "sg:tags":[
        "farm",
        "corn",
        "soybean"
    ],
    "wof:name":"Dale Stickel",
    "wof:placetype":"venue"
},
  "geometry": {"coordinates":[-86.041059,41.611374],"type":"Point"}
}