{
  "type": "Feature",
  "properties": {
    "iso:country":"US",
    "sg:address":"5559 Vicksburg Dr",
    "sg:city":"Indianapolis",
    "sg:classifiers":[
        {
            "category":"Building & Trades",
            "subcategory":"Landscaping Services",
            "type":"Services"
        }
    ],
    "sg:phone":"+1 317 698 0052",
    "sg:postcode":"46254",
    "sg:province":"IN",
    "sg:tags":[
        "aged",
        "homes-institutional"
    ],
    "wof:name":"My Mother's Home",
    "wof:placetype":"venue"
},
  "geometry": {"coordinates":[-86.258368,39.862575],"type":"Point"}
}