{
  "type": "Feature",
  "properties": {
    "iso:country":"US",
    "sg:address":"3940 N Hartman Dr",
    "sg:city":"Indianapolis",
    "sg:classifiers":[
        {
            "category":"Freight",
            "type":"Transportation"
        }
    ],
    "sg:phone":"+1 317 542 8518",
    "sg:postcode":"46226",
    "sg:province":"IN",
    "sg:tags":[
        "piano",
        "moving",
        "organ"
    ],
    "wof:name":"Indy Movers",
    "wof:placetype":"venue"
},
  "geometry": {"coordinates":[-86.03906600000001,39.829622],"type":"Point"}
}