{
  "type": "Feature",
  "properties": {
    "iso:country":"US",
    "sg:address":"6824 N Centerville Rd",
    "sg:city":"Williamsburg",
    "sg:classifiers":[
        {
            "category":"Building & Trades",
            "subcategory":"Landscaping Services",
            "type":"Services"
        }
    ],
    "sg:phone":"+1 765 886 5017",
    "sg:postcode":"47393",
    "sg:province":"IN",
    "sg:tags":[
        "lawn",
        "care"
    ],
    "wof:name":"Ladd Lawn Care",
    "wof:placetype":"venue"
},
  "geometry": {"coordinates":[-84.996376,39.932321],"type":"Point"}
}