{
  "type": "Feature",
  "properties": {
    "addr:full":"Located in Castleton Square Mall 6020 East 82nd Street Suite LL02 Indianapolis IN 46250",
    "addr:housenumber":"6020",
    "addr:postcode":"46250",
    "addr:street":"In Castleton Square;East 82Nd Street Suite Ll02",
    "iso:country":"US",
    "sg:address":"Located in Castleton Square Mall 6020 East 82nd Street Suite LL02",
    "sg:city":"Indianapolis",
    "sg:classifiers":[
        {
            "category":"Bars & Pubs",
            "type":"Food & Drink"
        },
        {
            "category":"Restaurant",
            "type":"Food & Drink"
        }
    ],
    "sg:phone":"+1 317 845 9428",
    "sg:postcode":"46250",
    "sg:province":"IN",
    "sg:tags":[
        "new",
        "american"
    ],
    "sg:website":"houlihans.com/",
    "wof:name":"Houlihan's",
    "wof:placetype":"venue"
},
  "geometry": {"coordinates":[-86.065236,39.906433],"type":"Point"}
}