{
  "type": "Feature",
  "properties": {
    "iso:country":"US",
    "sg:address":"310 Cmns Mall",
    "sg:city":"Columbus",
    "sg:classifiers":[
        {
            "category":"Restaurant",
            "type":"Food & Drink"
        }
    ],
    "sg:phone":"+1 812 376 7650",
    "sg:postcode":"47201",
    "sg:province":"IN",
    "wof:name":"Bistro 310 American Bistro Bar",
    "wof:placetype":"venue"
},
  "geometry": {"coordinates":[-85.922045,39.202172],"type":"Point"}
}