{
  "type": "Feature",
  "properties": {
    "iso:country":"US",
    "sg:address":"813 Eastern Blvd",
    "sg:city":"Clarksville",
    "sg:classifiers":[
        {
            "category":"Real Estate",
            "subcategory":"Real Estate Operator",
            "type":"Services"
        }
    ],
    "sg:phone":"+1 812 282 3265",
    "sg:postcode":"47129",
    "sg:province":"IN",
    "sg:tags":[
        "apartment"
    ],
    "wof:name":"Evergreen Court",
    "wof:placetype":"venue"
},
  "geometry": {"coordinates":[-85.76445699999999,38.302698],"type":"Point"}
}