{
  "type": "Feature",
  "properties": {
    "iso:country":"US",
    "sg:address":"117 S Main St",
    "sg:city":"Owensville",
    "sg:classifiers":[
        {
            "category":"Personal",
            "subcategory":"Beauty Salon",
            "type":"Services"
        }
    ],
    "sg:phone":"+1 812 724 3013",
    "sg:postcode":"47665",
    "sg:province":"IN",
    "wof:name":"Classic Trendz",
    "wof:placetype":"venue"
},
  "geometry": {"coordinates":[-87.691323,38.272241],"type":"Point"}
}