{
  "type": "Feature",
  "properties": {
    "iso:country":"US",
    "sg:address":"4353 Massachusetts St",
    "sg:city":"Gary",
    "sg:classifiers":[
        {
            "category":"Organizations",
            "subcategory":"Religious Organization",
            "type":"Services"
        }
    ],
    "sg:phone":"+1 219 887 0064",
    "sg:postcode":"46409",
    "sg:province":"IN",
    "sg:tags":[
        "church"
    ],
    "wof:name":"Pearl Faith Center Cogic",
    "wof:placetype":"venue"
},
  "geometry": {"coordinates":[-87.33499500000001,41.53952],"type":"Point"}
}