{
  "type": "Feature",
  "properties": {
    "iso:country":"US",
    "sg:address":"4015 National Rd W",
    "sg:city":"Richmond",
    "sg:classifiers":[
        {
            "category":"Organizations",
            "subcategory":"Religious Organization",
            "type":"Services"
        }
    ],
    "sg:phone":"+1 765 935 3303",
    "sg:postcode":"47374",
    "sg:province":"IN",
    "sg:tags":[
        "church"
    ],
    "wof:name":"Faith United Lutheran Church",
    "wof:placetype":"venue"
},
  "geometry": {"coordinates":[-84.954561,39.821262],"type":"Point"}
}