{
  "type": "Feature",
  "properties": {
    "iso:country":"US",
    "sg:address":"650 E Carmel Dr",
    "sg:city":"Carmel",
    "sg:classifiers":[
        {
            "category":"Professional",
            "subcategory":"Lawyer & Legal Services",
            "type":"Services"
        }
    ],
    "sg:phone":"+1 317 819 5001",
    "sg:postcode":"46032",
    "sg:province":"IN",
    "sg:tags":[
        "attorney"
    ],
    "wof:name":"Michael Owen",
    "wof:placetype":"venue"
},
  "geometry": {"coordinates":[-86.115945,39.962114],"type":"Point"}
}