{
  "type": "Feature",
  "properties": {
    "addr:full":"122 Creekside Dr Kokomo IN 46901",
    "addr:housenumber":"122",
    "addr:postcode":"46901",
    "addr:street":"Creekside Dr",
    "iso:country":"US",
    "sg:address":"122 Creekside Dr",
    "sg:city":"Kokomo",
    "sg:classifiers":[
        {
            "category":"Shopping",
            "subcategory":"Stationery & Office Supplies",
            "type":"Retail Goods"
        }
    ],
    "sg:phone":"+1 765 868 9263",
    "sg:postcode":"46901",
    "sg:province":"IN",
    "sg:tags":[
        "album",
        "scrapbook"
    ],
    "wof:name":"Scrapbook Magic Inc",
    "wof:placetype":"venue"
},
  "geometry": {"coordinates":[-86.108306,40.487459],"type":"Point"}
}