{
  "type": "Feature",
  "properties": {
    "iso:country":"US",
    "sg:address":"5500 State Rd 38 E",
    "sg:city":"Lafayette",
    "sg:classifiers":[
        {
            "category":"Professional",
            "type":"Services"
        }
    ],
    "sg:phone":"+1 765 446 0414",
    "sg:postcode":"47905",
    "sg:province":"IN",
    "wof:name":"Heritage Interactive Svc",
    "wof:placetype":"venue"
},
  "geometry": {"coordinates":[-86.790368,40.374162],"type":"Point"}
}