{
  "type": "Feature",
  "properties": {
    "iso:country":"US",
    "sg:address":"7051 Pointe Inverness Way",
    "sg:city":"Fort Wayne",
    "sg:classifiers":[
        {
            "category":"Real Estate",
            "subcategory":"Real Estate Operator",
            "type":"Services"
        }
    ],
    "sg:phone":"+1 260 436 8100",
    "sg:postcode":"46804",
    "sg:province":"IN",
    "sg:tags":[
        "apartment"
    ],
    "wof:name":"Pointe Inverness Apartments",
    "wof:placetype":"venue"
},
  "geometry": {"coordinates":[-85.234354,41.071663],"type":"Point"}
}