{
  "type": "Feature",
  "properties": {
    "iso:country":"US",
    "sg:address":"1629 W 13th St",
    "sg:city":"Anderson",
    "sg:classifiers":[
        {
            "category":"Shopping",
            "subcategory":"Gifts & Souvenirs",
            "type":"Retail Goods"
        }
    ],
    "sg:phone":"+1 765 641 0137",
    "sg:postcode":"46016",
    "sg:province":"IN",
    "sg:tags":[
        "basket",
        "parcel"
    ],
    "wof:name":"Ni Ni's Spot",
    "wof:placetype":"venue"
},
  "geometry": {"coordinates":[-85.700516,40.102467],"type":"Point"}
}