{
  "type": "Feature",
  "properties": {
    "iso:country":"US",
    "sg:address":"12646 US Hwy 40",
    "sg:city":"Cambridge City",
    "sg:classifiers":[
        {
            "category":"Freight",
            "type":"Transportation"
        }
    ],
    "sg:phone":"+1 765 478 9606",
    "sg:postcode":"47327",
    "sg:province":"IN",
    "sg:tags":[
        "trucking"
    ],
    "wof:name":"R & N Transport",
    "wof:placetype":"venue"
},
  "geometry": {"coordinates":[-85.114552,39.813731],"type":"Point"}
}