{
  "type": "Feature",
  "properties": {
    "addr:full":"12646 US Hwy 40 Cambridge City IN 47327",
    "addr:housenumber":"12646",
    "addr:postcode":"47327",
    "addr:street":"Us Hwy 40",
    "iso:country":"US",
    "sg:address":"12646 US Hwy 40",
    "sg:city":"Cambridge City",
    "sg:classifiers":[
        {
            "category":"Freight",
            "type":"Transportation"
        }
    ],
    "sg:phone":"+1 765 478 9606",
    "sg:postcode":"47327",
    "sg:province":"IN",
    "sg:tags":[
        "trucking"
    ],
    "wof:name":"R & N Transport",
    "wof:placetype":"venue"
},
  "geometry": {"coordinates":[-85.114552,39.813731],"type":"Point"}
}