{
  "type": "Feature",
  "properties": {
    "iso:country":"US",
    "sg:address":"101 E Hively Ave",
    "sg:city":"Elkhart",
    "sg:classifiers":[
        {
            "category":"Organizations",
            "subcategory":"Non-profit Organization",
            "type":"Services"
        }
    ],
    "sg:phone":"+1 574 295 6596",
    "sg:postcode":"46517",
    "sg:province":"IN",
    "sg:website":"www.familyserviceselkhart.com",
    "wof:name":"Family Services Of Elkhart Inc",
    "wof:placetype":"venue"
},
  "geometry": {"coordinates":[-85.96473,41.65942],"type":"Point"}
}