{
  "type": "Feature",
  "properties": {
    "iso:country":"US",
    "sg:address":"1555 S State Rd 39",
    "sg:city":"Laporte",
    "sg:classifiers":[
        {
            "category":"Manufacturing",
            "subcategory":"Tools & Machinery",
            "type":"Manufacturing & Wholesale Goods"
        }
    ],
    "sg:phone":"+1 219 325 3060",
    "sg:postcode":"46350",
    "sg:province":"IN",
    "sg:tags":[
        "industry",
        "special"
    ],
    "sg:website":"www.epakmachinery.com",
    "wof:name":"E-Pak Machinery Inc",
    "wof:placetype":"venue"
},
  "geometry": {"coordinates":[-86.739228,41.58593],"type":"Point"}
}