{
  "type": "Feature",
  "properties": {
    "addr:full":"3585 W State Road 45 Bloomington IN 47403",
    "addr:housenumber":"3585",
    "addr:postcode":"47403",
    "addr:street":"W State Road 45",
    "iso:country":"US",
    "sg:address":"3585 W State Road 45",
    "sg:city":"Bloomington",
    "sg:classifiers":[
        {
            "category":"Shopping",
            "subcategory":"Department Store",
            "type":"Retail Goods"
        },
        {
            "category":"Shopping",
            "subcategory":"Mobile Phones",
            "type":"Retail Goods"
        },
        {
            "category":"Food & Beverages",
            "subcategory":"Groceries & Convenience Stores",
            "type":"Retail Goods"
        }
    ],
    "sg:phone":"+1 812 337 0002",
    "sg:postcode":"47403",
    "sg:province":"IN",
    "sg:website":"www.walmart.com",
    "wof:name":"Walmart",
    "wof:placetype":"venue"
},
  "geometry": {"coordinates":[-86.4933,39.171522],"type":"Point"}
}