{
  "type": "Feature",
  "properties": {
    "addr:full":"615 N Fairview St Bloomington IN 47404",
    "addr:housenumber":"615",
    "addr:postcode":"47404",
    "addr:street":"N Fairview St",
    "iso:country":"US",
    "sg:address":"615 N Fairview St",
    "sg:city":"Bloomington",
    "sg:classifiers":[
        {
            "category":"Social Services",
            "type":"Services"
        }
    ],
    "sg:phone":"+1 812 334 8374",
    "sg:postcode":"47404",
    "sg:province":"IN",
    "sg:tags":[
        "food",
        "banks"
    ],
    "wof:name":"Hoosier Hills Food Bank",
    "wof:placetype":"venue"
},
  "geometry": {"coordinates":[-86.541174,39.172149],"type":"Point"}
}