{
  "type": "Feature",
  "properties": {
    "addr:full":"7465 E 82nd St Indianapolis IN 46256",
    "addr:housenumber":"7465",
    "addr:postcode":"46256",
    "addr:street":"E 82Nd St",
    "iso:country":"US",
    "sg:address":"7465 E 82nd St",
    "sg:city":"Indianapolis",
    "sg:classifiers":[
        {
            "category":"Health Services",
            "subcategory":"Doctor",
            "type":"Services"
        }
    ],
    "sg:phone":"+1 317 841 1111",
    "sg:postcode":"46256",
    "sg:province":"IN",
    "sg:tags":[
        "surgeon",
        "oral"
    ],
    "sg:website":"www.smilesbygeorge.com",
    "wof:name":"Kirtley George E DDS",
    "wof:placetype":"venue"
},
  "geometry": {"coordinates":[-86.0382,39.905201],"type":"Point"}
}