{
  "type": "Feature",
  "properties": {
    "iso:country":"US",
    "sg:address":"1947 E Spring St",
    "sg:city":"New Albany",
    "sg:classifiers":[
        {
            "category":"Professional",
            "subcategory":"Lawyer & Legal Services",
            "type":"Services"
        }
    ],
    "sg:phone":"+1 812 949 1114",
    "sg:postcode":"47150",
    "sg:province":"IN",
    "sg:tags":[
        "attorney"
    ],
    "sg:website":"www.wardtylerscott.com",
    "wof:name":"Ward Tyler & Scott",
    "wof:placetype":"venue"
},
  "geometry": {"coordinates":[-85.80224699999999,38.295377],"type":"Point"}
}