{
  "type": "Feature",
  "properties": {
    "iso:country":"US",
    "sg:address":"2717 W 10th St",
    "sg:city":"Indianapolis",
    "sg:classifiers":[
        {
            "category":"Organizations",
            "subcategory":"Community Association",
            "type":"Services"
        }
    ],
    "sg:phone":"+1 317 632 0619",
    "sg:postcode":"46222",
    "sg:province":"IN",
    "sg:tags":[
        "club"
    ],
    "wof:name":"Slovenian National Home",
    "wof:placetype":"venue"
},
  "geometry": {"coordinates":[-86.206078,39.7806],"type":"Point"}
}