{
  "type": "Feature",
  "properties": {
    "addr:full":"4810 Mecca St Indianapolis IN 46241",
    "addr:housenumber":"4810",
    "addr:postcode":"46241",
    "addr:street":"Mecca St",
    "iso:country":"US",
    "sg:address":"4810 Mecca St",
    "sg:city":"Indianapolis",
    "sg:classifiers":[
        {
            "category":"Organizations",
            "subcategory":"Religious Organization",
            "type":"Services"
        }
    ],
    "sg:phone":"+1 317 243 7407",
    "sg:postcode":"46241",
    "sg:province":"IN",
    "wof:name":"Life Temple Church Inc",
    "wof:placetype":"venue"
},
  "geometry": {"coordinates":[-86.240415,39.737133],"type":"Point"}
}