{
  "type": "Feature",
  "properties": {
    "iso:country":"US",
    "sg:address":"704 Main St",
    "sg:city":"Jasper",
    "sg:classifiers":[
        {
            "category":"Home & Garden",
            "subcategory":"Home Furnishings",
            "type":"Retail Goods"
        }
    ],
    "sg:phone":"+1 812 482 4040",
    "sg:postcode":"47546",
    "sg:province":"IN",
    "sg:tags":[
        "curtain",
        "made",
        "drapery"
    ],
    "wof:name":"Corbin's Drapery Inc",
    "wof:placetype":"venue"
},
  "geometry": {"coordinates":[-86.930718,38.392901],"type":"Point"}
}