{
  "type": "Feature",
  "properties": {
    "addr:full":"7420 W 83rd Ln Crown Point IN 46307",
    "addr:housenumber":"7420",
    "addr:postcode":"46307",
    "addr:street":"W 83Rd Ln",
    "iso:country":"US",
    "sg:address":"7420 W 83rd Ln",
    "sg:city":"Crown Point",
    "sg:classifiers":[
        {
            "category":"Manufacturing",
            "subcategory":"Glass & Minerals",
            "type":"Manufacturing & Wholesale Goods"
        }
    ],
    "sg:phone":"+1 219 365 9320",
    "sg:postcode":"46307",
    "sg:province":"IN",
    "sg:tags":[
        "product",
        "mfg"
    ],
    "wof:name":"Century 21",
    "wof:placetype":"venue"
},
  "geometry": {"coordinates":[-87.42459700000001,41.466495],"type":"Point"}
}