{
  "type": "Feature",
  "properties": {
    "iso:country":"US",
    "sg:address":"4920 N Warren Dr",
    "sg:city":"Columbus",
    "sg:classifiers":[
        {
            "category":"Manufacturing",
            "subcategory":"Tools & Machinery",
            "type":"Manufacturing & Wholesale Goods"
        }
    ],
    "sg:phone":"+1 812 378 9691",
    "sg:postcode":"47203",
    "sg:province":"IN",
    "sg:tags":[
        "mold"
    ],
    "wof:name":"Design Tek Engineering Svc",
    "wof:placetype":"venue"
},
  "geometry": {"coordinates":[-85.909449,39.253254],"type":"Point"}
}