{
  "type": "Feature",
  "properties": {
    "iso:country":"US",
    "sg:address":"252 N Locke St",
    "sg:city":"Nappanee",
    "sg:classifiers":[
        {
            "category":"Personal",
            "subcategory":"Beauty Salon",
            "type":"Services"
        }
    ],
    "sg:phone":"+1 574 773 4011",
    "sg:postcode":"46550",
    "sg:province":"IN",
    "sg:tags":[
        "shop"
    ],
    "wof:name":"Lehmans",
    "wof:placetype":"venue"
},
  "geometry": {"coordinates":[-86.003935,41.444537],"type":"Point"}
}