{
  "type": "Feature",
  "properties": {
    "addr:full":"9616 S 100 E Pendleton IN 46064",
    "addr:housenumber":"9616;100 e",
    "addr:postcode":"46064",
    "addr:street":"S",
    "iso:country":"US",
    "sg:address":"9616 S 100 E",
    "sg:city":"Pendleton",
    "sg:classifiers":[
        {
            "category":"Farming",
            "subcategory":"Farm",
            "type":"Manufacturing & Wholesale Goods"
        }
    ],
    "sg:phone":"+1 765 778 3670",
    "sg:postcode":"46064",
    "sg:province":"IN",
    "sg:tags":[
        "crop",
        "general"
    ],
    "wof:name":"Meadow Run Farms Inc",
    "wof:placetype":"venue"
},
  "geometry": {"coordinates":[-85.65269499999999,39.964877],"type":"Point"}
}