{
  "type": "Feature",
  "properties": {
    "iso:country":"US",
    "sg:address":"1950 Brentford Dr",
    "sg:city":"Indianapolis",
    "sg:classifiers":[
        {
            "category":"Real Estate",
            "subcategory":"Real Estate Operator",
            "type":"Services"
        }
    ],
    "sg:phone":"+1 317 899 1212",
    "sg:postcode":"46219",
    "sg:province":"IN",
    "sg:tags":[
        "condominium"
    ],
    "wof:name":"Chatham Walk Townhouses Inc",
    "wof:placetype":"venue"
},
  "geometry": {"coordinates":[-86.0231,39.794398],"type":"Point"}
}