{
  "type": "Feature",
  "properties": {
    "iso:country":"US",
    "sg:address":"10798 US Hwy 136",
    "sg:city":"Indianapolis",
    "sg:classifiers":[
        {
            "category":"Home & Garden",
            "subcategory":"Garden Supply",
            "type":"Retail Goods"
        }
    ],
    "sg:phone":"+1 317 291 2185",
    "sg:postcode":"46234",
    "sg:province":"IN",
    "sg:tags":[
        "engine"
    ],
    "wof:name":"Bob's Raceway Lawn & Garden",
    "wof:placetype":"venue"
},
  "geometry": {"coordinates":[-86.331386,39.819102],"type":"Point"}
}