{
  "type": "Feature",
  "properties": {
    "iso:country":"US",
    "sg:address":"2344 Sagamore Pkwy N",
    "sg:city":"Lafayette",
    "sg:classifiers":[
        {
            "category":"Retail",
            "subcategory":"Auto Repair",
            "type":"Services"
        }
    ],
    "sg:phone":"+1 765 423 2155",
    "sg:postcode":"47904",
    "sg:province":"IN",
    "sg:tags":[
        "brake"
    ],
    "wof:name":"Meineke Car Care Ctr",
    "wof:placetype":"venue"
},
  "geometry": {"coordinates":[-86.864474,40.441337],"type":"Point"}
}