{
  "type": "Feature",
  "properties": {
    "iso:country":"US",
    "sg:address":"1617 Woodside Ave",
    "sg:city":"Fort Wayne",
    "sg:classifiers":[
        {
            "category":"Retail",
            "subcategory":"Auto Repair",
            "type":"Services"
        }
    ],
    "sg:phone":"+1 260 447 4772",
    "sg:postcode":"46816",
    "sg:province":"IN",
    "sg:tags":[
        "repairing",
        "automobile"
    ],
    "wof:name":"Alexander's Auto Svc",
    "wof:placetype":"venue"
},
  "geometry": {"coordinates":[-85.113298,41.018457],"type":"Point"}
}