{
  "type": "Feature",
  "properties": {
    "iso:country":"US",
    "sg:address":"5101 Massachusetts Ave",
    "sg:city":"Indianapolis",
    "sg:classifiers":[
        {
            "category":"Building & Trades",
            "subcategory":"Construction",
            "type":"Services"
        }
    ],
    "sg:phone":"+1 317 543 3110",
    "sg:postcode":"46218",
    "sg:province":"IN",
    "sg:tags":[
        "erectors",
        "machinery"
    ],
    "wof:name":"Trident Industrial Contracting",
    "wof:placetype":"venue"
},
  "geometry": {"coordinates":[-86.082427,39.811219],"type":"Point"}
}