{
  "type": "Feature",
  "properties": {
    "addr:full":"3328 S US Hwy 421 Greensburg IN 47240",
    "addr:housenumber":"3328",
    "addr:postcode":"47240",
    "addr:street":"S Us Hwy 421",
    "iso:country":"US",
    "sg:address":"3328 S US Hwy 421",
    "sg:city":"Greensburg",
    "sg:classifiers":[
        {
            "category":"Farming",
            "subcategory":"Farm",
            "type":"Manufacturing & Wholesale Goods"
        }
    ],
    "sg:phone":"+1 812 663 7419",
    "sg:postcode":"47240",
    "sg:province":"IN",
    "sg:tags":[
        "crop",
        "general"
    ],
    "wof:name":"Dean Farms",
    "wof:placetype":"venue"
},
  "geometry": {"coordinates":[-85.414495,39.288382],"type":"Point"}
}