{
  "type": "Feature",
  "properties": {
    "iso:country":"US",
    "sg:address":"415 S Branson St",
    "sg:city":"Marion",
    "sg:classifiers":[
        {
            "category":"Government",
            "subcategory":"Office",
            "type":"Public Place"
        }
    ],
    "sg:phone":"+1 765 662 9961",
    "sg:postcode":"46953",
    "sg:province":"IN",
    "sg:tags":[
        "state",
        "program"
    ],
    "wof:name":"Vocational Rehabilitation Div",
    "wof:placetype":"venue"
},
  "geometry": {"coordinates":[-85.657254,40.557066],"type":"Point"}
}