{
  "type": "Feature",
  "properties": {
    "iso:country":"US",
    "sg:address":"1343 S Jackson St",
    "sg:city":"Auburn",
    "sg:classifiers":[
        {
            "category":"Professional",
            "subcategory":"Management & Consulting",
            "type":"Services"
        }
    ],
    "sg:phone":"+1 260 927 1600",
    "sg:postcode":"46706",
    "sg:province":"IN",
    "sg:tags":[
        "business"
    ],
    "wof:name":"Applied Envmtl Resources",
    "wof:placetype":"venue"
},
  "geometry": {"coordinates":[-85.056905,41.35881],"type":"Point"}
}