{
  "type": "Feature",
  "properties": {
    "iso:country":"US",
    "sg:address":"5801 Saint Joe Rd",
    "sg:city":"Fort Wayne",
    "sg:classifiers":[
        {
            "category":"Restaurant",
            "type":"Food & Drink"
        }
    ],
    "sg:menulink":"http://www.allmenus.com/in/st-joseph/79494-pizza-hut/menu/",
    "sg:phone":"+1 260 485 7593",
    "sg:postcode":"46835",
    "sg:province":"IN",
    "sg:tags":[
        "american",
        "pizza"
    ],
    "wof:name":"Pizza Hut",
    "wof:placetype":"venue"
},
  "geometry": {"coordinates":[-85.100251,41.132957],"type":"Point"}
}