{
  "type": "Feature",
  "properties": {
    "iso:country":"US",
    "sg:address":"6818 Poorhouse Hill Rd",
    "sg:city":"Rising Sun",
    "sg:classifiers":[
        {
            "category":"Professional",
            "subcategory":"Business Services",
            "type":"Services"
        }
    ],
    "sg:phone":"+1 812 438 4638",
    "sg:postcode":"47040",
    "sg:province":"IN",
    "sg:tags":[
        "inspection"
    ],
    "wof:name":"Weldert Inspection Svc",
    "wof:placetype":"venue"
},
  "geometry": {"coordinates":[-84.90472699999999,38.969969],"type":"Point"}
}