{
  "type": "Feature",
  "properties": {
    "addr:full":"2849 169th St Hammond IN 46323",
    "addr:housenumber":"2849",
    "addr:postcode":"46323",
    "addr:street":"169Th St",
    "iso:country":"US",
    "sg:address":"2849 169th St",
    "sg:city":"Hammond",
    "sg:classifiers":[
        {
            "category":"Autos & Motor Vehicles",
            "subcategory":"Fuel & Gas Station",
            "type":"Retail Goods"
        }
    ],
    "sg:phone":"+1 219 844 6230",
    "sg:postcode":"46323",
    "sg:province":"IN",
    "sg:tags":[
        "oil"
    ],
    "wof:name":"Lubana Inc",
    "wof:placetype":"venue"
},
  "geometry": {"coordinates":[-87.460297,41.588402],"type":"Point"}
}