{
  "type": "Feature",
  "properties": {
    "iso:country":"US",
    "sg:address":"401 W Walnut St",
    "sg:city":"Kokomo",
    "sg:classifiers":[
        {
            "category":"Professional",
            "subcategory":"Lawyer & Legal Services",
            "type":"Services"
        }
    ],
    "sg:phone":"+1 765 456 1318",
    "sg:postcode":"46901",
    "sg:province":"IN",
    "sg:tags":[
        "attorney"
    ],
    "wof:name":"William E Beck II",
    "wof:placetype":"venue"
},
  "geometry": {"coordinates":[-86.135249,40.487312],"type":"Point"}
}