{
  "type": "Feature",
  "properties": {
    "iso:country":"US",
    "sg:address":"8215 Lipps Rd",
    "sg:city":"Guilford",
    "sg:classifiers":[
        {
            "category":"Farming",
            "subcategory":"Livestock Farm",
            "type":"Manufacturing & Wholesale Goods"
        }
    ],
    "sg:phone":"+1 812 623 2220",
    "sg:postcode":"47022",
    "sg:province":"IN",
    "sg:tags":[
        "beef",
        "feedlot",
        "cattle"
    ],
    "wof:name":"Terrance Miller",
    "wof:placetype":"venue"
},
  "geometry": {"coordinates":[-84.969734,39.220754],"type":"Point"}
}