{
  "type": "Feature",
  "properties": {
    "iso:country":"US",
    "sg:address":"701 W 1st St",
    "sg:city":"Rushville",
    "sg:classifiers":[
        {
            "category":"Manufacturing",
            "subcategory":"Tools & Machinery",
            "type":"Manufacturing & Wholesale Goods"
        }
    ],
    "sg:phone":"+1 765 938 4801",
    "sg:postcode":"46173",
    "sg:province":"IN",
    "sg:tags":[
        "machine",
        "shop"
    ],
    "wof:name":"Jerry & Sons Machine & Tool",
    "wof:placetype":"venue"
},
  "geometry": {"coordinates":[-85.45397699999999,39.607096],"type":"Point"}
}