{
  "type": "Feature",
  "properties": {
    "iso:country":"US",
    "sg:address":"4156 N Meridian St",
    "sg:city":"Indianapolis",
    "sg:classifiers":[
        {
            "category":"Professional",
            "subcategory":"Management & Consulting",
            "type":"Services"
        }
    ],
    "sg:phone":"+1 317 926 6362",
    "sg:postcode":"46208",
    "sg:province":"IN",
    "sg:tags":[
        "consultant",
        "business"
    ],
    "wof:name":"S J Sylvester & Assoc",
    "wof:placetype":"venue"
},
  "geometry": {"coordinates":[-86.156965,39.829255],"type":"Point"}
}