{
  "type": "Feature",
  "properties": {
    "addr:full":"728 S Meridian St Indianapolis IN 46225",
    "addr:housenumber":"728",
    "addr:postcode":"46225",
    "addr:street":"S Meridian St",
    "iso:country":"US",
    "sg:address":"728 S Meridian St",
    "sg:city":"Indianapolis",
    "sg:classifiers":[
        {
            "category":"Professional",
            "subcategory":"Lawyer & Legal Services",
            "type":"Services"
        }
    ],
    "sg:phone":"+1 317 637 3170",
    "sg:postcode":"46225",
    "sg:province":"IN",
    "sg:tags":[
        "attorney"
    ],
    "wof:name":"Linder & Hollowell",
    "wof:placetype":"venue"
},
  "geometry": {"coordinates":[-86.159115,39.757253],"type":"Point"}
}