{
  "type": "Feature",
  "properties": {
    "iso:country":"US",
    "sg:address":"247 N Sandy Creek Dr",
    "sg:city":"Seymour",
    "sg:classifiers":[
        {
            "category":"Travel",
            "subcategory":"Hotels & Motels",
            "type":"Entertainment"
        }
    ],
    "sg:phone":"+1 812 523 2409",
    "sg:postcode":"47274",
    "sg:province":"IN",
    "wof:name":"Hampton Inn",
    "wof:placetype":"venue"
},
  "geometry": {"coordinates":[-85.84804699999999,38.95865],"type":"Point"}
}