{
  "type": "Feature",
  "properties": {
    "iso:country":"US",
    "sg:address":"1326 Delta Blvd",
    "sg:city":"Fort Wayne",
    "sg:classifiers":[
        {
            "category":"Professional",
            "subcategory":"Lawyer & Legal Services",
            "type":"Services"
        }
    ],
    "sg:phone":"+1 260 426 0256",
    "sg:postcode":"46805",
    "sg:province":"IN",
    "sg:tags":[
        "plan"
    ],
    "wof:name":"Tri-State Attorney Svc",
    "wof:placetype":"venue"
},
  "geometry": {"coordinates":[-85.119738,41.088172],"type":"Point"}
}