{
  "type": "Feature",
  "properties": {
    "iso:country":"US",
    "sg:address":"8131 E 400 N",
    "sg:city":"Pierceton",
    "sg:classifiers":[
        {
            "category":"Retail",
            "subcategory":"Repair Shop",
            "type":"Services"
        }
    ],
    "sg:phone":"+1 574 834 4147",
    "sg:postcode":"46562",
    "sg:province":"IN",
    "sg:tags":[
        "repairing",
        "lawn",
        "mower"
    ],
    "wof:name":"Harolds' Mower Shop",
    "wof:placetype":"venue"
},
  "geometry": {"coordinates":[-85.689416,41.294345],"type":"Point"}
}