{
  "type": "Feature",
  "properties": {
    "iso:country":"US",
    "sg:address":"603 W Main St",
    "sg:city":"Peru",
    "sg:classifiers":[
        {
            "category":"Food & Beverages",
            "subcategory":"Candy",
            "type":"Retail Goods"
        }
    ],
    "sg:phone":"+1 765 475 9866",
    "sg:postcode":"46970",
    "sg:province":"IN",
    "sg:tags":[
        "confectionery"
    ],
    "wof:name":"Candy Bouquet",
    "wof:placetype":"venue"
},
  "geometry": {"coordinates":[-86.08693700000001,40.74651],"type":"Point"}
}