{
  "type": "Feature",
  "properties": {
    "addr:full":"6547 W Lost River Rd Salem IN 47167",
    "addr:housenumber":"6547",
    "addr:postcode":"47167",
    "addr:street":"W Lost River Rd",
    "iso:country":"US",
    "sg:address":"6547 W Lost River Rd",
    "sg:city":"Salem",
    "sg:classifiers":[
        {
            "category":"Restaurant",
            "type":"Food & Drink"
        }
    ],
    "sg:phone":"+1 812 896 0949",
    "sg:postcode":"47167",
    "sg:province":"IN",
    "sg:tags":[
        "parlor",
        "ice",
        "cream"
    ],
    "wof:name":"Truly Scrumtious",
    "wof:placetype":"venue"
},
  "geometry": {"coordinates":[-86.208522,38.627626],"type":"Point"}
}