{
  "type": "Feature",
  "properties": {
    "iso:country":"US",
    "sg:address":"7060 State Rd 311",
    "sg:city":"Sellersburg",
    "sg:classifiers":[
        {
            "category":"Recreation",
            "type":"Entertainment"
        }
    ],
    "sg:phone":"+1 812 248 0505",
    "sg:postcode":"47172",
    "sg:province":"IN",
    "sg:tags":[
        "instruction",
        "gymnastic"
    ],
    "wof:name":"Twist N Turns Tumbling",
    "wof:placetype":"venue"
},
  "geometry": {"coordinates":[-85.772561,38.374237],"type":"Point"}
}