{
  "type": "Feature",
  "properties": {
    "iso:country":"US",
    "sg:address":"520 S State Rd 39",
    "sg:city":"Lebanon",
    "sg:classifiers":[
        {
            "category":"Autos & Motor Vehicles",
            "subcategory":"Fuel & Gas Station",
            "type":"Retail Goods"
        }
    ],
    "sg:phone":"+1 765 483 9755",
    "sg:postcode":"46052",
    "sg:province":"IN",
    "sg:tags":[
        "plaza",
        "truck",
        "stops"
    ],
    "sg:website":"www.flyingj.com",
    "wof:name":"Flying J Travel Plaza",
    "wof:placetype":"venue"
},
  "geometry": {"coordinates":[-86.472429,40.030785],"type":"Point"}
}