{
  "type": "Feature",
  "properties": {
    "iso:country":"US",
    "sg:address":"3051 Wooded Way",
    "sg:city":"Jeffersonville",
    "sg:classifiers":[
        {
            "category":"Professional",
            "subcategory":"Secretarial Services",
            "type":"Services"
        }
    ],
    "sg:phone":"+1 812 284 4417",
    "sg:postcode":"47130",
    "sg:province":"IN",
    "sg:tags":[
        "hearing",
        "reporter"
    ],
    "wof:name":"Francine E Todd",
    "wof:placetype":"venue"
},
  "geometry": {"coordinates":[-85.705778,38.322286],"type":"Point"}
}