{
  "type": "Feature",
  "properties": {
    "iso:country":"US",
    "sg:address":"3855 S Grant City Rd",
    "sg:city":"Shirley",
    "sg:classifiers":[
        {
            "category":"Recreation",
            "type":"Entertainment"
        }
    ],
    "sg:phone":"+1 765 737 6539",
    "sg:postcode":"47384",
    "sg:province":"IN",
    "wof:name":"Grant Wilfong Stable",
    "wof:placetype":"venue"
},
  "geometry": {"coordinates":[-85.543326,39.874888],"type":"Point"}
}