{
  "type": "Feature",
  "properties": {
    "iso:country":"US",
    "sg:address":"716 14th St",
    "sg:city":"Demotte",
    "sg:classifiers":[
        {
            "category":"Professional",
            "subcategory":"Management & Consulting",
            "type":"Services"
        }
    ],
    "sg:phone":"+1 219 987 6192",
    "sg:postcode":"46310",
    "sg:province":"IN",
    "sg:tags":[
        "consultant",
        "public",
        "utility"
    ],
    "sg:website":"www.cescontrols4air.com",
    "wof:name":"Centrifugal Equipment Svc Corp",
    "wof:placetype":"venue"
},
  "geometry": {"coordinates":[-87.189452,41.188988],"type":"Point"}
}