{
  "type": "Feature",
  "properties": {
    "iso:country":"US",
    "sg:address":"1493 Tunnelton Rd",
    "sg:city":"Mitchell",
    "sg:phone":"+1 812 849 5945",
    "sg:postcode":"47421",
    "sg:province":"IN",
    "sg:tags":[
        "farm",
        "corn",
        "soybean"
    ],
    "wof:name":"Stewart Farms",
    "wof:placetype":"venue"
},
  "geometry": {"coordinates":[-86.44221899999999,38.850939],"type":"Point"}
}