{
  "type": "Feature",
  "properties": {
    "iso:country":"US",
    "sg:address":"5618 Coldwater Rd",
    "sg:city":"Fort Wayne",
    "sg:classifiers":[
        {
            "category":"Shopping",
            "subcategory":"Shoes",
            "type":"Retail Goods"
        }
    ],
    "sg:phone":"+1 260 482 2783",
    "sg:postcode":"46825",
    "sg:province":"IN",
    "wof:name":"Chesser's Womens & Mens Shoe",
    "wof:placetype":"venue"
},
  "geometry": {"coordinates":[-85.135734,41.128267],"type":"Point"}
}