{
  "type": "Feature",
  "properties": {
    "iso:country":"US",
    "sg:address":"1210 E Bocock Rd",
    "sg:city":"Marion",
    "sg:classifiers":[
        {
            "category":"Building & Trades",
            "subcategory":"Construction",
            "type":"Services"
        }
    ],
    "sg:phone":"+1 765 668 1000",
    "sg:postcode":"46952",
    "sg:province":"IN",
    "sg:tags":[
        "general",
        "contractor"
    ],
    "wof:name":"M R Construction",
    "wof:placetype":"venue"
},
  "geometry": {"coordinates":[-85.640078,40.6051],"type":"Point"}
}