{
  "type": "Feature",
  "properties": {
    "iso:country":"US",
    "sg:address":"1641 Sterling Ave",
    "sg:city":"Elkhart",
    "sg:classifiers":[
        {
            "category":"Manufacturing",
            "subcategory":"Tools & Machinery",
            "type":"Manufacturing & Wholesale Goods"
        }
    ],
    "sg:phone":"+1 574 970 4364",
    "sg:postcode":"46516",
    "sg:province":"IN",
    "sg:tags":[
        "machine",
        "shop"
    ],
    "wof:name":"Elkhart Machine Group",
    "wof:placetype":"venue"
},
  "geometry": {"coordinates":[-85.957718,41.673022],"type":"Point"}
}