{
  "type": "Feature",
  "properties": {
    "addr:full":"54820 Co Rd 1 Elkhart IN 46514",
    "addr:housenumber":"54820",
    "addr:postcode":"46514",
    "addr:street":"Co Rd 1",
    "iso:country":"US",
    "sg:address":"54820 Co Rd 1",
    "sg:city":"Elkhart",
    "sg:classifiers":[
        {
            "category":"Organizations",
            "subcategory":"Religious Organization",
            "type":"Services"
        }
    ],
    "sg:phone":"+1 574 266 0054",
    "sg:postcode":"46514",
    "sg:province":"IN",
    "wof:name":"Harvest Ministries",
    "wof:placetype":"venue"
},
  "geometry": {"coordinates":[-86.047304,41.696781],"type":"Point"}
}