{
  "type": "Feature",
  "properties": {
    "iso:country":"US",
    "sg:address":"3970 E Bellefontaine Rd",
    "sg:city":"Hamilton",
    "sg:classifiers":[
        {
            "category":"Bars & Pubs",
            "type":"Food & Drink"
        }
    ],
    "sg:phone":"+1 260 488 3056",
    "sg:postcode":"46742",
    "sg:province":"IN",
    "wof:name":"Rio Bar",
    "wof:placetype":"venue"
},
  "geometry": {"coordinates":[-84.913442,41.533602],"type":"Point"}
}