{
  "type": "Feature",
  "properties": {
    "iso:country":"US",
    "sg:address":"120 E Jefferson St",
    "sg:city":"Franklin",
    "sg:classifiers":[
        {
            "category":"Real Estate",
            "subcategory":"Real Estate Services",
            "type":"Services"
        }
    ],
    "sg:phone":"+1 317 736 0920",
    "sg:postcode":"46131",
    "sg:province":"IN",
    "sg:tags":[
        "company",
        "title"
    ],
    "wof:name":"Indiana Title Searching Svc",
    "wof:placetype":"venue"
},
  "geometry": {"coordinates":[-86.05271399999999,39.480738],"type":"Point"}
}