{
  "type": "Feature",
  "properties": {
    "iso:country":"US",
    "sg:address":"3415 Conestoga Dr",
    "sg:city":"Fort Wayne",
    "sg:classifiers":[
        {
            "category":"Autos & Motor Vehicles",
            "subcategory":"Recreational Vehicle Sales",
            "type":"Retail Goods"
        }
    ],
    "sg:phone":"+1 260 482 4826",
    "sg:postcode":"46808",
    "sg:province":"IN",
    "sg:tags":[
        "canopy",
        "shell",
        "truck",
        "cap"
    ],
    "sg:website":"www.powrtrain.com",
    "wof:name":"Power Train Of Fort Wayne",
    "wof:placetype":"venue"
},
  "geometry": {"coordinates":[-85.18286000000001,41.105112],"type":"Point"}
}