{
  "type": "Feature",
  "properties": {
    "iso:country":"US",
    "sg:address":"303 S Main St",
    "sg:city":"Winchester",
    "sg:classifiers":[
        {
            "category":"Insurance",
            "subcategory":"Hazard Insurance",
            "type":"Services"
        }
    ],
    "sg:phone":"+1 765 584 3388",
    "sg:postcode":"47394",
    "sg:province":"IN",
    "sg:tags":[
        "bond"
    ],
    "wof:name":"Aul Bail Bonds",
    "wof:placetype":"venue"
},
  "geometry": {"coordinates":[-84.981207,40.170419],"type":"Point"}
}