{
  "type": "Feature",
  "properties": {
    "iso:country":"US",
    "sg:address":"103 S Main St",
    "sg:city":"Monticello",
    "sg:classifiers":[
        {
            "category":"Shopping",
            "subcategory":"Gifts & Souvenirs",
            "type":"Retail Goods"
        }
    ],
    "sg:phone":"+1 574 583 8081",
    "sg:postcode":"47960",
    "sg:province":"IN",
    "sg:tags":[
        "shop"
    ],
    "wof:name":"Christine's Hallmark",
    "wof:placetype":"venue"
},
  "geometry": {"coordinates":[-86.761844,40.744914],"type":"Point"}
}