{
  "type": "Feature",
  "properties": {
    "iso:country":"US",
    "sg:address":"3137 Northview Dr",
    "sg:city":"Elkhart",
    "sg:classifiers":[
        {
            "category":"Insurance",
            "subcategory":"Insurance Agent",
            "type":"Services"
        }
    ],
    "sg:phone":"+1 574 264 5755",
    "sg:postcode":"46514",
    "sg:province":"IN",
    "wof:name":"State Farm Insurance",
    "wof:placetype":"venue"
},
  "geometry": {"coordinates":[-85.97731,41.734283],"type":"Point"}
}