{
  "type": "Feature",
  "properties": {
    "addr:full":"55767 State Rd 15 Bristol IN 46507",
    "addr:housenumber":"55767;15",
    "addr:postcode":"46507",
    "addr:street":"State Rd",
    "iso:country":"US",
    "sg:address":"55767 State Rd 15",
    "sg:city":"Bristol",
    "sg:classifiers":[
        {
            "category":"Building & Trades",
            "subcategory":"Landscaping Services",
            "type":"Services"
        }
    ],
    "sg:phone":"+1 574 848 1864",
    "sg:postcode":"46507",
    "sg:province":"IN",
    "wof:name":"Smartt Enterprises",
    "wof:placetype":"venue"
},
  "geometry": {"coordinates":[-85.81546,41.687009],"type":"Point"}
}