{
  "type": "Feature",
  "properties": {
    "iso:country":"US",
    "sg:address":"255 McCrea St",
    "sg:city":"Indianapolis",
    "sg:classifiers":[
        {
            "category":"Professional",
            "subcategory":"Art Services",
            "type":"Services"
        }
    ],
    "sg:phone":"+1 317 631 2250",
    "sg:postcode":"46225",
    "sg:province":"IN",
    "sg:tags":[
        "graphic",
        "designer"
    ],
    "wof:name":"Revolve",
    "wof:placetype":"venue"
},
  "geometry": {"coordinates":[-86.159132,39.763149],"type":"Point"}
}