{
  "type": "Feature",
  "properties": {
    "addr:full":"59192 Lower Dr Goshen IN 46528",
    "addr:postcode":"59192;46528",
    "addr:street":"Lower Dr",
    "iso:country":"US",
    "sg:address":"59192 Lower Dr",
    "sg:city":"Goshen",
    "sg:classifiers":[
        {
            "category":"Building & Trades",
            "subcategory":"Construction",
            "type":"Services"
        }
    ],
    "sg:phone":"+1 574 537 9285",
    "sg:postcode":"46528",
    "sg:province":"IN",
    "sg:tags":[
        "roofing",
        "contractor"
    ],
    "wof:name":"A Roofing Specialist & Home",
    "wof:placetype":"venue"
},
  "geometry": {"coordinates":[-85.828012,41.637338],"type":"Point"}
}