{
  "type": "Feature",
  "properties": {
    "iso:country":"US",
    "sg:address":"8807 E 38th St",
    "sg:city":"Indianapolis",
    "sg:classifiers":[
        {
            "category":"Professional",
            "subcategory":"Accounting & Tax Preparation",
            "type":"Services"
        }
    ],
    "sg:phone":"+1 317 898 6788",
    "sg:postcode":"46226",
    "sg:province":"IN",
    "sg:tags":[
        "return",
        "filing"
    ],
    "wof:name":"Liberty Tax Svc",
    "wof:placetype":"venue"
},
  "geometry": {"coordinates":[-86.010013,39.825972],"type":"Point"}
}