{
  "type": "Feature",
  "properties": {
    "iso:country":"US",
    "sg:address":"1633 E 900 S",
    "sg:city":"Geneva",
    "sg:phone":"+1 260 589 2039",
    "sg:postcode":"46740",
    "sg:province":"IN",
    "sg:tags":[
        "farm",
        "corn",
        "wheat",
        "soybean"
    ],
    "wof:name":"Phil Wulliman",
    "wof:placetype":"venue"
},
  "geometry": {"coordinates":[-84.90470500000001,40.615085],"type":"Point"}
}