{
  "type": "Feature",
  "properties": {
    "iso:country":"US",
    "sg:address":"15602 Carey Rd",
    "sg:city":"Noblesville",
    "sg:classifiers":[
        {
            "category":"Manufacturing",
            "subcategory":"Tools & Machinery",
            "type":"Manufacturing & Wholesale Goods"
        }
    ],
    "sg:phone":"+1 317 844 7991",
    "sg:postcode":"46060",
    "sg:province":"IN",
    "sg:tags":[
        "machine",
        "shop"
    ],
    "sg:website":"www.westfieldmfg.com",
    "wof:name":"Westfield Manufacturing Corp",
    "wof:placetype":"venue"
},
  "geometry": {"coordinates":[-86.108563,40.013172],"type":"Point"}
}