{
  "type": "Feature",
  "properties": {
    "iso:country":"US",
    "sg:address":"422 Monte Vista Dr",
    "sg:city":"Fort Wayne",
    "sg:classifiers":[
        {
            "category":"Professional",
            "subcategory":"Business Services",
            "type":"Services"
        }
    ],
    "sg:phone":"+1 260 625 6668",
    "sg:postcode":"46814",
    "sg:province":"IN",
    "wof:name":"Whitacre Assoc Inc",
    "wof:placetype":"venue"
},
  "geometry": {"coordinates":[-85.287305,41.07901],"type":"Point"}
}