{
  "type": "Feature",
  "properties": {
    "iso:country":"US",
    "sg:address":"108 N Water St",
    "sg:city":"Salem",
    "sg:classifiers":[
        {
            "category":"Retail",
            "subcategory":"Laundry & Dry Cleaning",
            "type":"Services"
        }
    ],
    "sg:phone":"+1 812 883 5303",
    "sg:postcode":"47167",
    "sg:province":"IN",
    "sg:tags":[
        "drycleaning",
        "plant"
    ],
    "wof:name":"Bobs Cleaners",
    "wof:placetype":"venue"
},
  "geometry": {"coordinates":[-86.102154,38.606663],"type":"Point"}
}