{
  "type": "Feature",
  "properties": {
    "iso:country":"US",
    "sg:address":"5844 E State Rd 10",
    "sg:city":"Demotte",
    "sg:classifiers":[
        {
            "category":"Manufacturing",
            "subcategory":"Metals",
            "type":"Manufacturing & Wholesale Goods"
        }
    ],
    "sg:phone":"+1 219 987 6196",
    "sg:postcode":"46310",
    "sg:province":"IN",
    "sg:tags":[
        "machine",
        "screw",
        "product"
    ],
    "wof:name":"Demotte Manufacturing",
    "wof:placetype":"venue"
},
  "geometry": {"coordinates":[-87.278677,41.14449],"type":"Point"}
}