{
  "type": "Feature",
  "properties": {
    "iso:country":"US",
    "sg:address":"105 S Court St",
    "sg:city":"Crown Point",
    "sg:classifiers":[
        {
            "category":"Personal",
            "type":"Services"
        }
    ],
    "sg:phone":"+1 219 663 3290",
    "sg:postcode":"46307",
    "sg:province":"IN",
    "sg:tags":[
        "sewing",
        "alteration"
    ],
    "wof:name":"Sophie's Alterations & Tailoring",
    "wof:placetype":"venue"
},
  "geometry": {"coordinates":[-87.365303,41.417099],"type":"Point"}
}