{
  "type": "Feature",
  "properties": {
    "iso:country":"US",
    "sg:address":"5731 W Ohio Ridge Rd",
    "sg:city":"Columbus",
    "sg:classifiers":[
        {
            "category":"Professional",
            "subcategory":"Business Services",
            "type":"Services"
        }
    ],
    "sg:phone":"+1 812 526 6849",
    "sg:postcode":"47201",
    "sg:province":"IN",
    "wof:name":"Kleinhenz Interiors Tracy",
    "wof:placetype":"venue"
},
  "geometry": {"coordinates":[-85.987697,39.282581],"type":"Point"}
}