{
  "type": "Feature",
  "properties": {
    "iso:country":"US",
    "sg:address":"1161 Church Ave",
    "sg:city":"Corydon",
    "sg:classifiers":[
        {
            "category":"Health Services",
            "subcategory":"Doctor",
            "type":"Services"
        }
    ],
    "sg:phone":"+1 812 738 2166",
    "sg:postcode":"47112",
    "sg:province":"IN",
    "sg:tags":[
        "dentist"
    ],
    "wof:name":"Dawn R Durbin DDS",
    "wof:placetype":"venue"
},
  "geometry": {"coordinates":[-86.14231700000001,38.218217],"type":"Point"}
}