{
  "type": "Feature",
  "properties": {
    "iso:country":"US",
    "sg:address":"302 S Main St",
    "sg:city":"Crown Point",
    "sg:classifiers":[
        {
            "category":"Restaurant",
            "type":"Food & Drink"
        }
    ],
    "sg:phone":"+1 219 661 5829",
    "sg:postcode":"46307",
    "sg:province":"IN",
    "sg:tags":[
        "italian"
    ],
    "sg:website":"www.lucreziacafe.com",
    "wof:name":"Lucrezia Italian Ristorante",
    "wof:placetype":"venue"
},
  "geometry": {"coordinates":[-87.364502,41.415001],"type":"Point"}
}