{
  "type": "Feature",
  "properties": {
    "iso:country":"US",
    "sg:address":"102 E Sycamore St",
    "sg:city":"Boonville",
    "sg:classifiers":[
        {
            "category":"Social Services",
            "type":"Services"
        }
    ],
    "sg:phone":"+1 812 897 4229",
    "sg:postcode":"47601",
    "sg:province":"IN",
    "sg:tags":[
        "organization",
        "welfare"
    ],
    "wof:name":"Salvation Army",
    "wof:placetype":"venue"
},
  "geometry": {"coordinates":[-87.274238,38.051038],"type":"Point"}
}