{
  "type": "Feature",
  "properties": {
    "iso:country":"US",
    "sg:address":"8421 Plum Valley Dr",
    "sg:city":"Sellersburg",
    "sg:classifiers":[
        {
            "category":"Manufacturing",
            "subcategory":"Retail Goods",
            "type":"Manufacturing & Wholesale Goods"
        }
    ],
    "sg:phone":"+1 812 246 4643",
    "sg:postcode":"47172",
    "sg:province":"IN",
    "sg:tags":[
        "product",
        "mfg"
    ],
    "wof:name":"Essex Industries",
    "wof:placetype":"venue"
},
  "geometry": {"coordinates":[-85.77651299999999,38.379353],"type":"Point"}
}