{
  "type": "Feature",
  "properties": {
    "iso:country":"US",
    "sg:address":"105 E Main St",
    "sg:city":"Henryville",
    "sg:classifiers":[
        {
            "category":"Wholesale",
            "subcategory":"Farm Supplies",
            "type":"Manufacturing & Wholesale Goods"
        }
    ],
    "sg:phone":"+1 812 294 1677",
    "sg:postcode":"47126",
    "sg:province":"IN",
    "sg:tags":[
        "feed"
    ],
    "wof:name":"Lynch Feed & Supply",
    "wof:placetype":"venue"
},
  "geometry": {"coordinates":[-85.767133,38.540381],"type":"Point"}
}