{
  "type": "Feature",
  "properties": {
    "iso:country":"US",
    "sg:address":"3425 Budd Rd",
    "sg:city":"New Albany",
    "sg:classifiers":[
        {
            "category":"Building & Trades",
            "subcategory":"Landscaping Services",
            "type":"Services"
        }
    ],
    "sg:phone":"+1 812 949 2846",
    "sg:postcode":"47150",
    "sg:province":"IN",
    "sg:tags":[
        "tree"
    ],
    "wof:name":"Cut Rate Tree Svc",
    "wof:placetype":"venue"
},
  "geometry": {"coordinates":[-85.876828,38.254764],"type":"Point"}
}