{
  "type": "Feature",
  "properties": {
    "iso:country":"US",
    "sg:address":"3022 W State Route 62",
    "sg:city":"Boonville",
    "sg:classifiers":[
        {
            "category":"Real Estate",
            "subcategory":"Real Estate Services",
            "type":"Services"
        }
    ],
    "sg:phone":"+1 812 897 8102",
    "sg:postcode":"47601",
    "sg:province":"IN",
    "wof:name":"Era First Advantage Realty",
    "wof:placetype":"venue"
},
  "geometry": {"coordinates":[-87.30220799999999,38.048284],"type":"Point"}
}