{
  "type": "Feature",
  "properties": {
    "iso:country":"US",
    "sg:address":"200 S Green River Rd",
    "sg:city":"Evansville",
    "sg:classifiers":[
        {
            "category":"Shopping",
            "subcategory":"Used Merchandise",
            "type":"Retail Goods"
        }
    ],
    "sg:phone":"+1 812 477 0478",
    "sg:postcode":"47715",
    "sg:province":"IN",
    "sg:tags":[
        "shop",
        "consignment"
    ],
    "wof:name":"Opportunity Shop",
    "wof:placetype":"venue"
},
  "geometry": {"coordinates":[-87.492611,37.974371],"type":"Point"}
}