{
  "type": "Feature",
  "properties": {
    "iso:country":"US",
    "sg:address":"203 W 10th St",
    "sg:city":"Mt Vernon",
    "sg:classifiers":[
        {
            "category":"Retail",
            "subcategory":"Auto Repair",
            "type":"Services"
        }
    ],
    "sg:phone":"+1 812 838 2107",
    "sg:postcode":"47620",
    "sg:province":"IN",
    "sg:tags":[
        "repairing",
        "automobile"
    ],
    "wof:name":"Eaton Auto Repair",
    "wof:placetype":"venue"
},
  "geometry": {"coordinates":[-87.899742,37.937334],"type":"Point"}
}