{
  "type": "Feature",
  "properties": {
    "iso:country":"US",
    "sg:address":"20186 Laurel Rd",
    "sg:city":"Laurel",
    "sg:classifiers":[
        {
            "category":"Building & Trades",
            "subcategory":"Landscaping Services",
            "type":"Services"
        }
    ],
    "sg:phone":"+1 765 698 2039",
    "sg:postcode":"47024",
    "sg:province":"IN",
    "sg:tags":[
        "tree"
    ],
    "wof:name":"Nate's Tree Svc",
    "wof:placetype":"venue"
},
  "geometry": {"coordinates":[-85.15312,39.516334],"type":"Point"}
}