{
  "type": "Feature",
  "properties": {
    "iso:country":"US",
    "sg:address":"11160 Co Rd 4",
    "sg:city":"Middlebury",
    "sg:classifiers":[
        {
            "category":"Professional",
            "type":"Services"
        }
    ],
    "sg:phone":"+1 574 825 8177",
    "sg:postcode":"46540",
    "sg:province":"IN",
    "sg:tags":[
        "establishment"
    ],
    "wof:name":"Star Fleet Inc",
    "wof:placetype":"venue"
},
  "geometry": {"coordinates":[-85.681916,41.740272],"type":"Point"}
}