{
  "type": "Feature",
  "properties": {
    "iso:country":"US",
    "sg:address":"3214 E State Rd 104",
    "sg:city":"Laporte",
    "sg:classifiers":[
        {
            "category":"Education",
            "subcategory":"School",
            "type":"Public Place"
        }
    ],
    "sg:phone":"+1 219 369 9016",
    "sg:postcode":"46350",
    "sg:province":"IN",
    "wof:name":"Indian Trail Elementary School",
    "wof:placetype":"venue"
},
  "geometry": {"coordinates":[-86.610193,41.564029],"type":"Point"}
}