{
  "type": "Feature",
  "properties": {
    "addr:full":"1430 S Range Line Rd Carmel IN 46032",
    "addr:housenumber":"1430",
    "addr:postcode":"46032",
    "addr:street":"S Range Line Rd",
    "iso:country":"US",
    "sg:address":"1430 S Range Line Rd",
    "sg:city":"Carmel",
    "sg:classifiers":[
        {
            "category":"Banks & Credit Unions",
            "subcategory":"Bank",
            "type":"Services"
        },
        {
            "category":"Banks & Credit Unions",
            "subcategory":"Financial Services",
            "type":"Services"
        }
    ],
    "sg:phone":"+1 317 705 7700",
    "sg:postcode":"46032",
    "sg:province":"IN",
    "sg:tags":[
        "broker",
        "mortgage"
    ],
    "wof:name":"Old National",
    "wof:placetype":"venue"
},
  "geometry": {"coordinates":[-86.12690000000001,39.957001],"type":"Point"}
}