{
  "type": "Feature",
  "properties": {
    "addr:full":"6050 US Hwy 6 Portage IN 46368",
    "addr:housenumber":"6050",
    "addr:postcode":"46368",
    "addr:street":"Us Hwy 6",
    "iso:country":"US",
    "sg:address":"6050 US Hwy 6",
    "sg:city":"Portage",
    "sg:classifiers":[
        {
            "category":"Personal",
            "subcategory":"Beauty Salon",
            "type":"Services"
        }
    ],
    "sg:phone":"+1 219 763 0450",
    "sg:postcode":"46368",
    "sg:province":"IN",
    "wof:name":"Bo Rics Haircare",
    "wof:placetype":"venue"
},
  "geometry": {"coordinates":[-87.18120399999999,41.550563],"type":"Point"}
}