{
  "type": "Feature",
  "properties": {
    "iso:country":"US",
    "sg:address":"1919 Steven Ave",
    "sg:city":"Bedford",
    "sg:classifiers":[
        {
            "category":"Government",
            "subcategory":"Office",
            "type":"Public Place"
        }
    ],
    "sg:phone":"+1 812 278 3176",
    "sg:postcode":"47421",
    "sg:province":"IN",
    "wof:name":"Lawrence County Soil & Water",
    "wof:placetype":"venue"
},
  "geometry": {"coordinates":[-86.51981,38.858538],"type":"Point"}
}