{
  "type": "Feature",
  "properties": {
    "iso:country":"US",
    "sg:address":"1602 N Center St",
    "sg:city":"Attica",
    "sg:classifiers":[
        {
            "category":"Autos & Motor Vehicles",
            "subcategory":"Automobile Sales",
            "type":"Retail Goods"
        },
        {
            "category":"Autos & Motor Vehicles",
            "subcategory":"Auto Supplies",
            "type":"Retail Goods"
        }
    ],
    "sg:phone":"+1 765 762 3858",
    "sg:postcode":"47918",
    "sg:province":"IN",
    "sg:tags":[
        "car",
        "parts",
        "accessory",
        "part",
        "supplies-used",
        "accessories-wholesale",
        "new",
        "rebuilt",
        "manufacturer"
    ],
    "wof:name":"Purcell Auto Parts",
    "wof:placetype":"venue"
},
  "geometry": {"coordinates":[-87.281925,40.338727],"type":"Point"}
}