{
  "type": "Feature",
  "properties": {
    "iso:country":"US",
    "sg:address":"207 N Washington St",
    "sg:city":"Delphi",
    "sg:classifiers":[
        {
            "category":"Organizations",
            "subcategory":"Religious Organization",
            "type":"Services"
        }
    ],
    "sg:phone":"+1 765 564 2407",
    "sg:postcode":"46923",
    "sg:province":"IN",
    "sg:tags":[
        "church"
    ],
    "wof:name":"St Joseph Catholic Church",
    "wof:placetype":"venue"
},
  "geometry": {"coordinates":[-86.67549,40.588601],"type":"Point"}
}