{
  "type": "Feature",
  "properties": {
    "iso:country":"US",
    "sg:address":"3008 W 53rd St",
    "sg:city":"Anderson",
    "sg:classifiers":[
        {
            "category":"Professional",
            "subcategory":"Management & Consulting",
            "type":"Services"
        }
    ],
    "sg:phone":"+1 765 644 1732",
    "sg:postcode":"46011",
    "sg:province":"IN",
    "sg:tags":[
        "business"
    ],
    "wof:name":"Computer Engineering Tech LLC",
    "wof:placetype":"venue"
},
  "geometry": {"coordinates":[-85.730058,40.061274],"type":"Point"}
}