{
  "type": "Feature",
  "properties": {
    "iso:country":"US",
    "sg:address":"3860 W 950 S",
    "sg:city":"Silver Lake",
    "sg:classifiers":[
        {
            "category":"Food & Beverages",
            "subcategory":"Groceries & Convenience Stores",
            "type":"Retail Goods"
        }
    ],
    "sg:phone":"+1 260 352 2859",
    "sg:postcode":"46982",
    "sg:province":"IN",
    "wof:name":"Sand's Corp",
    "wof:placetype":"venue"
},
  "geometry": {"coordinates":[-85.905254,41.093953],"type":"Point"}
}