{
  "type": "Feature",
  "properties": {
    "iso:country":"US",
    "sg:address":"307 W 500 N",
    "sg:city":"Valparaiso",
    "sg:classifiers":[
        {
            "category":"Building & Trades",
            "subcategory":"Construction",
            "type":"Services"
        }
    ],
    "sg:phone":"+1 219 462 3549",
    "sg:postcode":"46385",
    "sg:province":"IN",
    "sg:tags":[
        "home",
        "builder"
    ],
    "wof:name":"Creative Home Resources",
    "wof:placetype":"venue"
},
  "geometry": {"coordinates":[-87.12490200000001,41.507115],"type":"Point"}
}