{
  "type": "Feature",
  "properties": {
    "iso:country":"US",
    "sg:address":"2903 Kentucky Ave",
    "sg:city":"Indianapolis",
    "sg:classifiers":[
        {
            "category":"Restaurant",
            "type":"Food & Drink"
        }
    ],
    "sg:menulink":"http://www.allmenus.com/in/speedway/174114-wendys/menu/",
    "sg:phone":"+1 317 247 0498",
    "sg:postcode":"46221",
    "sg:province":"IN",
    "sg:tags":[
        "burger",
        "american",
        "soup"
    ],
    "wof:name":"Wendy's",
    "wof:placetype":"venue"
},
  "geometry": {"coordinates":[-86.21835799999999,39.723191],"type":"Point"}
}