{
  "type": "Feature",
  "properties": {
    "iso:country":"US",
    "sg:address":"720 N 1st St",
    "sg:city":"Austin",
    "sg:classifiers":[
        {
            "category":"Retail",
            "subcategory":"Animal Services",
            "type":"Services"
        }
    ],
    "sg:phone":"+1 812 794 4258",
    "sg:postcode":"47102",
    "sg:province":"IN",
    "wof:name":"Pet Paradise Dog Grooming",
    "wof:placetype":"venue"
},
  "geometry": {"coordinates":[-85.80814100000001,38.750145],"type":"Point"}
}