{
  "type": "Feature",
  "properties": {
    "iso:country":"US",
    "sg:address":"1717 Washington Ave",
    "sg:city":"Vincennes",
    "sg:classifiers":[
        {
            "category":"Shopping",
            "subcategory":"Used Merchandise",
            "type":"Retail Goods"
        }
    ],
    "sg:phone":"+1 812 882 9372",
    "sg:postcode":"47591",
    "sg:province":"IN",
    "wof:name":"Hitching Post",
    "wof:placetype":"venue"
},
  "geometry": {"coordinates":[-87.508884,38.682363],"type":"Point"}
}