{
  "type": "Feature",
  "properties": {
    "addr:full":"16865 Clover Rd Noblesville IN 46060",
    "addr:housenumber":"16865",
    "addr:postcode":"46060",
    "addr:street":"Clover Rd",
    "iso:country":"US",
    "sg:address":"16865 Clover Rd",
    "sg:city":"Noblesville",
    "sg:classifiers":[
        {
            "category":"Restaurant",
            "type":"Food & Drink"
        }
    ],
    "sg:menulink":"http://www.allmenus.com/in/noblesville/119988-subway/menu/",
    "sg:phone":"+1 317 770 9027",
    "sg:postcode":"46060",
    "sg:province":"IN",
    "sg:tags":[
        "american",
        "sandwich"
    ],
    "wof:name":"Subway",
    "wof:placetype":"venue"
},
  "geometry": {"coordinates":[-85.998305,40.033906],"type":"Point"}
}