{
  "type": "Feature",
  "properties": {
    "iso:country":"US",
    "sg:address":"6400 Oak Hill Rd",
    "sg:city":"Evansville",
    "sg:classifiers":[
        {
            "category":"Organizations",
            "subcategory":"Religious Organization",
            "type":"Services"
        }
    ],
    "sg:phone":"+1 812 867 2497",
    "sg:postcode":"47725",
    "sg:province":"IN",
    "sg:tags":[
        "church"
    ],
    "sg:website":"www.bethlehemucc.org",
    "wof:name":"Bethlehem United Church-Christ",
    "wof:placetype":"venue"
},
  "geometry": {"coordinates":[-87.509917,38.03521],"type":"Point"}
}