{
  "type": "Feature",
  "properties": {
    "addr:full":"60065 Co Rd 21 Goshen IN 46528",
    "addr:housenumber":"60065;21",
    "addr:postcode":"46528",
    "addr:street":"Co Rd",
    "iso:country":"US",
    "sg:address":"60065 Co Rd 21",
    "sg:city":"Goshen",
    "sg:classifiers":[
        {
            "category":"Building & Trades",
            "subcategory":"Plumbing",
            "type":"Services"
        }
    ],
    "sg:phone":"+1 574 534 8552",
    "sg:postcode":"46528",
    "sg:province":"IN",
    "sg:tags":[
        "refrigeration",
        "contractor"
    ],
    "wof:name":"Trent's Refrigeration",
    "wof:placetype":"venue"
},
  "geometry": {"coordinates":[-85.849941,41.62248],"type":"Point"}
}