{
  "type": "Feature",
  "properties": {
    "iso:country":"US",
    "sg:address":"407 S Berkley Rd",
    "sg:city":"Kokomo",
    "sg:classifiers":[
        {
            "category":"Insurance",
            "subcategory":"Insurance Agent",
            "type":"Services"
        }
    ],
    "sg:phone":"+1 765 452 2687",
    "sg:postcode":"46901",
    "sg:province":"IN",
    "wof:name":"Rouch Financial Svc",
    "wof:placetype":"venue"
},
  "geometry": {"coordinates":[-86.155471,40.485425],"type":"Point"}
}