{
  "type": "Feature",
  "properties": {
    "iso:country":"US",
    "sg:address":"2605 Lafayette Ave",
    "sg:city":"Crawfordsville",
    "sg:classifiers":[
        {
            "category":"Food & Beverages",
            "subcategory":"Groceries & Convenience Stores",
            "type":"Retail Goods"
        }
    ],
    "sg:phone":"+1 765 362 2098",
    "sg:postcode":"47933",
    "sg:province":"IN",
    "wof:name":"Gas America",
    "wof:placetype":"venue"
},
  "geometry": {"coordinates":[-86.904955,40.077258],"type":"Point"}
}