{
  "type": "Feature",
  "properties": {
    "iso:country":"US",
    "sg:address":"2606 Wilshire Ave",
    "sg:city":"West Lafayette",
    "sg:classifiers":[
        {
            "category":"Organizations",
            "subcategory":"Religious Organization",
            "type":"Services"
        }
    ],
    "sg:phone":"+1 765 463 4600",
    "sg:postcode":"47906",
    "sg:province":"IN",
    "sg:tags":[
        "church"
    ],
    "wof:name":"Riverside Covenant Church",
    "wof:placetype":"venue"
},
  "geometry": {"coordinates":[-86.906881,40.455659],"type":"Point"}
}