{
  "type": "Feature",
  "properties": {
    "addr:full":"579 Lincoln Ave Evansville IN 47713",
    "addr:housenumber":"579",
    "addr:postcode":"47713",
    "addr:street":"Lincoln Ave",
    "iso:country":"US",
    "sg:address":"579 Lincoln Ave",
    "sg:city":"Evansville",
    "sg:classifiers":[
        {
            "category":"Museum",
            "type":"Entertainment"
        }
    ],
    "sg:phone":"+1 812 423 5188",
    "sg:postcode":"47713",
    "sg:province":"IN",
    "wof:name":"Evansville African American",
    "wof:placetype":"venue"
},
  "geometry": {"coordinates":[-87.557518,37.970058],"type":"Point"}
}