{
  "type": "Feature",
  "properties": {
    "iso:country":"US",
    "sg:address":"723 E 1st St",
    "sg:city":"Madison",
    "sg:classifiers":[
        {
            "category":"Freight",
            "type":"Transportation"
        }
    ],
    "sg:phone":"+1 812 265 6902",
    "sg:postcode":"47250",
    "sg:province":"IN",
    "sg:tags":[
        "commercial",
        "storage"
    ],
    "wof:name":"Charlene Wariner",
    "wof:placetype":"venue"
},
  "geometry": {"coordinates":[-85.371594,38.734046],"type":"Point"}
}