{
  "type": "Feature",
  "properties": {
    "iso:country":"US",
    "sg:address":"4033 E 31st St",
    "sg:city":"Indianapolis",
    "sg:classifiers":[
        {
            "category":"Organizations",
            "subcategory":"Religious Organization",
            "type":"Services"
        }
    ],
    "sg:phone":"+1 317 591 0597",
    "sg:postcode":"46218",
    "sg:province":"IN",
    "sg:tags":[
        "church"
    ],
    "wof:name":"Spiritual Israel Church",
    "wof:placetype":"venue"
},
  "geometry": {"coordinates":[-86.10066,39.81154],"type":"Point"}
}