{
  "type": "Feature",
  "properties": {
    "iso:country":"US",
    "sg:address":"1351 W Buena Vista Rd",
    "sg:city":"Evansville",
    "sg:classifiers":[
        {
            "category":"Social Services",
            "type":"Services"
        }
    ],
    "sg:phone":"+1 812 424 4663",
    "sg:postcode":"47710",
    "sg:province":"IN",
    "sg:tags":[
        "organization",
        "welfare"
    ],
    "sg:website":"www.evvgoodwill.org",
    "wof:name":"Goodwill Family Ctr",
    "wof:placetype":"venue"
},
  "geometry": {"coordinates":[-87.584344,38.014947],"type":"Point"}
}