{
  "type": "Feature",
  "properties": {
    "iso:country":"US",
    "sg:address":"1702 S 9th St",
    "sg:city":"Richmond",
    "sg:classifiers":[
        {
            "category":"Communications",
            "subcategory":"Television Station",
            "type":"Services"
        }
    ],
    "sg:phone":"+1 765 935 2390",
    "sg:postcode":"47374",
    "sg:province":"IN",
    "sg:tags":[
        "broadcasting",
        "co"
    ],
    "sg:website":"www.tbn.org",
    "wof:name":"Trinity Broadcasting Network",
    "wof:placetype":"venue"
},
  "geometry": {"coordinates":[-84.89007100000001,39.807611],"type":"Point"}
}