{
  "type": "Feature",
  "properties": {
    "iso:country":"US",
    "sg:address":"904 S 17th St",
    "sg:city":"Vincennes",
    "sg:classifiers":[
        {
            "category":"Organizations",
            "subcategory":"Community Association",
            "type":"Services"
        }
    ],
    "sg:phone":"+1 812 882 6056",
    "sg:postcode":"47591",
    "sg:province":"IN",
    "sg:tags":[
        "fraternal"
    ],
    "wof:name":"Loyal Order Of Moose",
    "wof:placetype":"venue"
},
  "geometry": {"coordinates":[-87.527236,38.661745],"type":"Point"}
}