{
  "type": "Feature",
  "properties": {
    "iso:country":"US",
    "sg:address":"2710 Co Rd 60",
    "sg:city":"Auburn",
    "sg:classifiers":[
        {
            "category":"Airport",
            "type":"Transportation"
        }
    ],
    "sg:phone":"+1 260 927 8779",
    "sg:postcode":"46706",
    "sg:province":"IN",
    "sg:tags":[
        "aircraft",
        "maintenance"
    ],
    "wof:name":"Mid America Avionics",
    "wof:placetype":"venue"
},
  "geometry": {"coordinates":[-85.073796,41.309359],"type":"Point"}
}