{
  "type": "Feature",
  "properties": {
    "iso:country":"US",
    "sg:address":"1150 Wedeking Ave",
    "sg:city":"Evansville",
    "sg:classifiers":[
        {
            "category":"Freight",
            "type":"Transportation"
        }
    ],
    "sg:phone":"+1 812 475 8462",
    "sg:postcode":"47711",
    "sg:province":"IN",
    "sg:tags":[
        "warehouse"
    ],
    "wof:name":"Baumbergers Mattress Plus",
    "wof:placetype":"venue"
},
  "geometry": {"coordinates":[-87.544568,37.997719],"type":"Point"}
}