{
  "type": "Feature",
  "properties": {
    "iso:country":"US",
    "sg:address":"6615 S Boundary Rd",
    "sg:city":"Portage",
    "sg:classifiers":[
        {
            "category":"Health Services",
            "subcategory":"Health Practitioner",
            "type":"Services"
        }
    ],
    "sg:phone":"+1 219 787 8662",
    "sg:postcode":"46368",
    "sg:province":"IN",
    "sg:tags":[
        "occupational",
        "safety"
    ],
    "wof:name":"Hoosier Healthcare LLC",
    "wof:placetype":"venue"
},
  "geometry": {"coordinates":[-87.158462,41.621921],"type":"Point"}
}