{
  "type": "Feature",
  "properties": {
    "addr:full":"2535 Chestnut St Columbus IN 47201",
    "addr:housenumber":"2535",
    "addr:postcode":"47201",
    "addr:street":"Chestnut St",
    "iso:country":"US",
    "sg:address":"2535 Chestnut St",
    "sg:city":"Columbus",
    "sg:classifiers":[
        {
            "category":"Building & Trades",
            "subcategory":"Construction",
            "type":"Services"
        }
    ],
    "sg:phone":"+1 812 379 2630",
    "sg:postcode":"47201",
    "sg:province":"IN",
    "sg:tags":[
        "house"
    ],
    "wof:name":"Knaepple Construction Services",
    "wof:placetype":"venue"
},
  "geometry": {"coordinates":[-85.915706,39.226669],"type":"Point"}
}