{
  "type": "Feature",
  "properties": {
    "addr:city":"Indianapolis",
    "addr:full":"1230 N Delaware St Indianapolis, In 46202-2531",
    "addr:house_number":"1230",
    "addr:housenumber":"1230",
    "addr:phone":"+1 317-631-1898",
    "addr:postcode":"46202-2531",
    "addr:road":"N Delaware St",
    "addr:state":"IN",
    "addr:street":"N Delaware St",
    "iso:country":"US",
    "sg:address":"1230 N Delaware St",
    "sg:city":"Indianapolis",
    "sg:classifiers":[
        {
            "category":"Landmark",
            "subcategory":"Historic",
            "type":"Public Place"
        },
        {
            "category":"Museum",
            "type":"Entertainment"
        }
    ],
    "sg:phone":"+1 317 631 1888",
    "sg:postcode":"46202",
    "sg:province":"IN",
    "sg:tags":[
        "historical"
    ],
    "sg:website":"http://www.pbhh.org",
    "wof:airports":[
        102534155
    ],
    "wof:name":"President Benjamin Harrison Foundation",
    "wof:placetype":"venue"
},
  "geometry": {"coordinates":[-86.15403999999999,39.78334],"type":"Point"}
}