{
  "type": "Feature",
  "properties": {
    "iso:country":"US",
    "sg:address":"1230 N Delaware St",
    "sg:city":"Indianapolis",
    "sg:classifiers":[
        {
            "category":"Landmark",
            "subcategory":"Historic",
            "type":"Public Place"
        },
        {
            "category":"Museum",
            "type":"Entertainment"
        }
    ],
    "sg:phone":"+1 317 631 1888",
    "sg:postcode":"46202",
    "sg:province":"IN",
    "sg:tags":[
        "historical"
    ],
    "sg:website":"http://www.pbhh.org",
    "wof:name":"Benjamin Harrison Presidential Home",
    "wof:placetype":"venue"
},
  "geometry": {"coordinates":[-86.153943,39.783596],"type":"Point"}
}