{
  "type": "Feature",
  "properties": {
    "iso:country":"US",
    "sg:address":"402 S Walnut St",
    "sg:city":"Seymour",
    "sg:classifiers":[
        {
            "category":"Bars & Pubs",
            "type":"Food & Drink"
        }
    ],
    "sg:phone":"+1 812 522 2818",
    "sg:postcode":"47274",
    "sg:province":"IN",
    "wof:name":"Bubba's Place",
    "wof:placetype":"venue"
},
  "geometry": {"coordinates":[-85.890549,38.954512],"type":"Point"}
}