{
  "type": "Feature",
  "properties": {
    "iso:country":"US",
    "sg:address":"1529 Shining Armor Ln",
    "sg:city":"West Lafayette",
    "sg:classifiers":[
        {
            "category":"Wholesale",
            "subcategory":"Drugs",
            "type":"Manufacturing & Wholesale Goods"
        }
    ],
    "sg:phone":"+1 765 463 1372",
    "sg:postcode":"47906",
    "sg:province":"IN",
    "wof:name":"Bayer Corporation",
    "wof:placetype":"venue"
},
  "geometry": {"coordinates":[-86.93729500000001,40.480264],"type":"Point"}
}