{
  "type": "Feature",
  "properties": {
    "iso:country":"US",
    "sg:address":"104 W 30th St",
    "sg:city":"Connersville",
    "sg:classifiers":[
        {
            "category":"Food & Beverages",
            "subcategory":"Groceries & Convenience Stores",
            "type":"Retail Goods"
        }
    ],
    "sg:phone":"+1 765 825 0519",
    "sg:postcode":"47331",
    "sg:province":"IN",
    "wof:name":"Gas America",
    "wof:placetype":"venue"
},
  "geometry": {"coordinates":[-85.129804,39.671675],"type":"Point"}
}