{
  "type": "Feature",
  "properties": {
    "iso:country":"US",
    "sg:address":"201 Walnut St",
    "sg:city":"Lawrenceburg",
    "sg:classifiers":[
        {
            "category":"Home & Garden",
            "subcategory":"Hardware",
            "type":"Retail Goods"
        }
    ],
    "sg:phone":"+1 812 537 3220",
    "sg:postcode":"47025",
    "sg:province":"IN",
    "wof:name":"Jackson Hardware & Ind Supls",
    "wof:placetype":"venue"
},
  "geometry": {"coordinates":[-84.84960599999999,39.094187],"type":"Point"}
}