{
  "type": "Feature",
  "properties": {
    "iso:country":"US",
    "sg:address":"915 Main St",
    "sg:city":"Evansville",
    "sg:classifiers":[
        {
            "category":"Professional",
            "subcategory":"Lawyer & Legal Services",
            "type":"Services"
        }
    ],
    "sg:phone":"+1 812 425 5223",
    "sg:postcode":"47708",
    "sg:province":"IN",
    "sg:tags":[
        "attorney"
    ],
    "sg:website":"http://www.statham-aj.com",
    "wof:name":"Statham Allega & Jessen",
    "wof:placetype":"venue"
},
  "geometry": {"coordinates":[-87.565414,37.975069],"type":"Point"}
}