{
  "type": "Feature",
  "properties": {
    "iso:country":"US",
    "sg:address":"6910 N Shadeland Ave",
    "sg:city":"Indianapolis",
    "sg:classifiers":[
        {
            "category":"Real Estate",
            "subcategory":"Developer",
            "type":"Services"
        }
    ],
    "sg:phone":"+1 317 890 2462",
    "sg:postcode":"46250",
    "sg:province":"IN",
    "wof:name":"R S Development",
    "wof:placetype":"venue"
},
  "geometry": {"coordinates":[-86.04620300000001,39.881138],"type":"Point"}
}