{
  "type": "Feature",
  "properties": {
    "iso:country":"US",
    "sg:address":"3351 US Hwy 50",
    "sg:city":"Holton",
    "sg:classifiers":[
        {
            "category":"Building & Trades",
            "subcategory":"Construction",
            "type":"Services"
        }
    ],
    "sg:phone":"+1 812 689 5260",
    "sg:postcode":"47023",
    "sg:province":"IN",
    "sg:tags":[
        "excavation",
        "contractor"
    ],
    "wof:name":"Daves Excavating",
    "wof:placetype":"venue"
},
  "geometry": {"coordinates":[-85.32032599999999,39.074945],"type":"Point"}
}