{
  "type": "Feature",
  "properties": {
    "iso:country":"US",
    "sg:address":"505 Bowser Ave",
    "sg:city":"Chesterton",
    "sg:classifiers":[
        {
            "category":"Social Services",
            "subcategory":"Child Care",
            "type":"Services"
        }
    ],
    "sg:phone":"+1 219 926 3631",
    "sg:postcode":"46304",
    "sg:province":"IN",
    "sg:tags":[
        "group",
        "center",
        "day"
    ],
    "wof:name":"Fay Popp",
    "wof:placetype":"venue"
},
  "geometry": {"coordinates":[-87.043403,41.60777],"type":"Point"}
}