{
  "type": "Feature",
  "properties": {
    "iso:country":"US",
    "sg:address":"954 Kenmore Dr",
    "sg:city":"Evansville",
    "sg:classifiers":[
        {
            "category":"Health Services",
            "subcategory":"Optometrist",
            "type":"Services"
        }
    ],
    "sg:phone":"+1 812 476 2000",
    "sg:postcode":"47714",
    "sg:province":"IN",
    "wof:name":"Miles Optometric",
    "wof:placetype":"venue"
},
  "geometry": {"coordinates":[-87.496805,37.964682],"type":"Point"}
}