{
  "type": "Feature",
  "properties": {
    "iso:country":"US",
    "sg:address":"351 N Jefferson St",
    "sg:city":"Cromwell",
    "sg:classifiers":[
        {
            "category":"Building & Trades",
            "subcategory":"Construction",
            "type":"Services"
        }
    ],
    "sg:phone":"+1 260 894 7423",
    "sg:postcode":"46732",
    "sg:province":"IN",
    "sg:tags":[
        "general",
        "contractor"
    ],
    "wof:name":"B & B Construction Co",
    "wof:placetype":"venue"
},
  "geometry": {"coordinates":[-85.613855,41.40341],"type":"Point"}
}