{
  "type": "Feature",
  "properties": {
    "iso:country":"US",
    "sg:address":"213 W Wayne St",
    "sg:city":"Fort Wayne",
    "sg:classifiers":[
        {
            "category":"Wholesale",
            "subcategory":"Machinery & Supplies",
            "type":"Manufacturing & Wholesale Goods"
        }
    ],
    "sg:phone":"+1 260 423 1402",
    "sg:postcode":"46802",
    "sg:province":"IN",
    "sg:tags":[
        "belting"
    ],
    "wof:name":"Kaman Industrial Tech",
    "wof:placetype":"venue"
},
  "geometry": {"coordinates":[-85.14225999999999,41.077733],"type":"Point"}
}