{
  "type": "Feature",
  "properties": {
    "iso:country":"US",
    "sg:address":"101 Nakomis St",
    "sg:city":"Noblesville",
    "sg:classifiers":[
        {
            "category":"Building & Trades",
            "subcategory":"Construction",
            "type":"Services"
        }
    ],
    "sg:phone":"+1 317 776 3075",
    "sg:postcode":"46062",
    "sg:province":"IN",
    "sg:tags":[
        "concrete",
        "contractor"
    ],
    "wof:name":"Harvey's Concrete Inc",
    "wof:placetype":"venue"
},
  "geometry": {"coordinates":[-85.967837,40.101614],"type":"Point"}
}