{
  "type": "Feature",
  "properties": {
    "iso:country":"US",
    "sg:address":"628 S A St",
    "sg:city":"Elwood",
    "sg:classifiers":[
        {
            "category":"Real Estate",
            "subcategory":"Real Estate Agent",
            "type":"Services"
        }
    ],
    "sg:phone":"+1 765 552 5801",
    "sg:postcode":"46036",
    "sg:province":"IN",
    "wof:name":"Bill Brogdon Realty",
    "wof:placetype":"venue"
},
  "geometry": {"coordinates":[-85.85378900000001,40.276076],"type":"Point"}
}