{
  "type": "Feature",
  "properties": {
    "iso:country":"US",
    "sg:address":"309 S 1st St",
    "sg:city":"Pierceton",
    "sg:classifiers":[
        {
            "category":"Organizations",
            "subcategory":"Religious Organization",
            "type":"Services"
        }
    ],
    "sg:phone":"+1 574 594 2613",
    "sg:postcode":"46562",
    "sg:province":"IN",
    "sg:tags":[
        "church"
    ],
    "wof:name":"Presbyterian Church",
    "wof:placetype":"venue"
},
  "geometry": {"coordinates":[-85.705195,41.196959],"type":"Point"}
}