{
  "type": "Feature",
  "properties": {
    "addr:full":"5845 Sunnyside Rd Indianapolis IN 46235",
    "addr:housenumber":"5845",
    "addr:postcode":"46235",
    "addr:street":"Sunnyside Rd",
    "iso:country":"US",
    "sg:address":"5845 Sunnyside Rd",
    "sg:city":"Indianapolis",
    "sg:classifiers":[
        {
            "category":"Shopping",
            "subcategory":"Clothing, Apparel, & Fashions",
            "type":"Retail Goods"
        }
    ],
    "sg:phone":"+1 317 823 9288",
    "sg:postcode":"46235",
    "sg:province":"IN",
    "wof:name":"Cato",
    "wof:placetype":"venue"
},
  "geometry": {"coordinates":[-85.97260900000001,39.862861],"type":"Point"}
}