{
  "type": "Feature",
  "properties": {
    "iso:country":"US",
    "sg:address":"925 S Union St",
    "sg:city":"Kokomo",
    "sg:classifiers":[
        {
            "category":"Health Services",
            "subcategory":"Chiropractor",
            "type":"Services"
        }
    ],
    "sg:phone":"+1 765 452 1330",
    "sg:postcode":"46901",
    "sg:province":"IN",
    "wof:name":"Robert A Clements DC",
    "wof:placetype":"venue"
},
  "geometry": {"coordinates":[-86.129885,40.477311],"type":"Point"}
}