{
  "type": "Feature",
  "properties": {
    "iso:country":"US",
    "sg:address":"330 Orange St",
    "sg:city":"Indianapolis",
    "sg:classifiers":[
        {
            "category":"Building & Trades",
            "subcategory":"Construction",
            "type":"Services"
        }
    ],
    "sg:phone":"+1 317 263 0007",
    "sg:postcode":"46225",
    "sg:province":"IN",
    "sg:tags":[
        "general",
        "contractor"
    ],
    "wof:name":"Handwork Corp",
    "wof:placetype":"venue"
},
  "geometry": {"coordinates":[-86.151644,39.74992],"type":"Point"}
}