{
  "type": "Feature",
  "properties": {
    "iso:country":"US",
    "sg:address":"427 W Pike St",
    "sg:city":"Goshen",
    "sg:classifiers":[
        {
            "category":"Health Services",
            "subcategory":"Nursing And Care Facility",
            "type":"Services"
        }
    ],
    "sg:phone":"+1 574 534 3964",
    "sg:postcode":"46526",
    "sg:province":"IN",
    "sg:tags":[
        "home",
        "retirement",
        "community"
    ],
    "sg:website":"www.kavillages.com",
    "wof:name":"Kolb & Assoc LTD",
    "wof:placetype":"venue"
},
  "geometry": {"coordinates":[-85.84037600000001,41.589196],"type":"Point"}
}