{
  "type": "Feature",
  "properties": {
    "addr:full":"10854 Co Rd W 100 S Russiaville IN 46979",
    "addr:housenumber":"10854;100",
    "addr:postcode":"46979",
    "addr:street":"Co Rd W;S",
    "iso:country":"US",
    "sg:address":"10854 Co Rd W 100 S",
    "sg:city":"Russiaville",
    "sg:classifiers":[
        {
            "category":"Organizations",
            "subcategory":"Religious Organization",
            "type":"Services"
        }
    ],
    "sg:phone":"+1 765 452 3300",
    "sg:postcode":"46979",
    "sg:province":"IN",
    "sg:tags":[
        "church"
    ],
    "wof:name":"Seventh Day Adventist Church",
    "wof:placetype":"venue"
},
  "geometry": {"coordinates":[-86.334936,40.460767],"type":"Point"}
}