{
  "type": "Feature",
  "properties": {
    "iso:country":"US",
    "sg:address":"1 N Weinbach Ave",
    "sg:city":"Evansville",
    "sg:classifiers":[
        {
            "category":"Banks & Credit Unions",
            "subcategory":"Investment Brokerage",
            "type":"Services"
        }
    ],
    "sg:phone":"+1 812 476 9622",
    "sg:postcode":"47711",
    "sg:province":"IN",
    "sg:tags":[
        "advisory",
        "financial"
    ],
    "wof:name":"ACA Financial",
    "wof:placetype":"venue"
},
  "geometry": {"coordinates":[-87.52933,37.977162],"type":"Point"}
}