{
  "type": "Feature",
  "properties": {
    "iso:country":"US",
    "sg:address":"1965 S Henderson St",
    "sg:city":"Bloomington",
    "sg:classifiers":[
        {
            "category":"Sports & Exercise",
            "subcategory":"Ice Rink",
            "type":"Entertainment"
        }
    ],
    "sg:phone":"+1 812 349 3740",
    "sg:postcode":"47401",
    "sg:province":"IN",
    "sg:tags":[
        "skating"
    ],
    "wof:name":"Frank Southern Center/Ice Arena",
    "wof:placetype":"venue"
},
  "geometry": {"coordinates":[-86.526802,39.146702],"type":"Point"}
}