{
  "type": "Feature",
  "properties": {
    "iso:country":"US",
    "sg:address":"8425 W 85th St",
    "sg:city":"Indianapolis",
    "sg:classifiers":[
        {
            "category":"Farming",
            "subcategory":"Fish & Marine Products",
            "type":"Manufacturing & Wholesale Goods"
        }
    ],
    "sg:phone":"+1 317 297 8679",
    "sg:postcode":"46278",
    "sg:province":"IN",
    "wof:name":"Wigginton Soil Consulting Inc",
    "wof:placetype":"venue"
},
  "geometry": {"coordinates":[-86.310519,39.908053],"type":"Point"}
}