{
  "type": "Feature",
  "properties": {
    "addr:full":"8632 State Rd 109 Knightstown IN 46148",
    "addr:housenumber":"8632",
    "addr:postcode":"46148",
    "addr:street":"State Rd 109 Knightstown",
    "iso:country":"US",
    "sg:address":"8632 State Rd 109",
    "sg:city":"Knightstown",
    "sg:classifiers":[
        {
            "category":"Education",
            "subcategory":"School",
            "type":"Public Place"
        }
    ],
    "sg:phone":"+1 765 345 2151",
    "sg:postcode":"46148",
    "sg:province":"IN",
    "wof:name":"Knightstown Elementary School",
    "wof:placetype":"venue"
},
  "geometry": {"coordinates":[-85.532195,39.807343],"type":"Point"}
}