{
  "type": "Feature",
  "properties": {
    "iso:country":"US",
    "sg:address":"1701 E 12th St",
    "sg:city":"Muncie",
    "sg:classifiers":[
        {
            "category":"Autos & Motor Vehicles",
            "subcategory":"Automobile Sales",
            "type":"Retail Goods"
        }
    ],
    "sg:phone":"+1 765 282 4328",
    "sg:postcode":"47302",
    "sg:province":"IN",
    "sg:tags":[
        "car",
        "used",
        "dealer"
    ],
    "wof:name":"R K Auto Sales",
    "wof:placetype":"venue"
},
  "geometry": {"coordinates":[-85.366468,40.178312],"type":"Point"}
}