{
  "type": "Feature",
  "properties": {
    "iso:country":"US",
    "sg:address":"916 N Michigan St",
    "sg:city":"Elkhart",
    "sg:classifiers":[
        {
            "category":"Home & Garden",
            "subcategory":"Carpets & Floor Coverings",
            "type":"Retail Goods"
        }
    ],
    "sg:phone":"+1 574 522 7883",
    "sg:postcode":"46514",
    "sg:province":"IN",
    "sg:tags":[
        "dealer",
        "rug"
    ],
    "sg:website":"www.magiccarpetdesigns.com",
    "wof:name":"Magic Carpet Designs",
    "wof:placetype":"venue"
},
  "geometry": {"coordinates":[-85.985383,41.693811],"type":"Point"}
}