{
  "type": "Feature",
  "properties": {
    "iso:country":"US",
    "sg:address":"357 S State Rd 341",
    "sg:city":"Hillsboro",
    "sg:classifiers":[
        {
            "category":"Bars & Pubs",
            "type":"Food & Drink"
        }
    ],
    "sg:phone":"+1 765 798 9295",
    "sg:postcode":"47949",
    "sg:province":"IN",
    "wof:name":"Quincy's Bar & Grill",
    "wof:placetype":"venue"
},
  "geometry": {"coordinates":[-87.14863,40.114277],"type":"Point"}
}