{
  "type": "Feature",
  "properties": {
    "iso:country":"US",
    "sg:address":"224 E Elm St",
    "sg:city":"New Albany",
    "sg:classifiers":[
        {
            "category":"Personal",
            "subcategory":"Beauty Salon",
            "type":"Services"
        }
    ],
    "sg:phone":"+1 812 945 6245",
    "sg:postcode":"47150",
    "sg:province":"IN",
    "sg:tags":[
        "manicuring"
    ],
    "wof:name":"Nancye's Nail Spa",
    "wof:placetype":"venue"
},
  "geometry": {"coordinates":[-85.82167,38.287634],"type":"Point"}
}