{
  "type": "Feature",
  "properties": {
    "iso:country":"US",
    "sg:address":"1600 Wabash Ave",
    "sg:city":"Terre Haute",
    "sg:classifiers":[
        {
            "category":"Retail",
            "subcategory":"Auto Repair",
            "type":"Services"
        }
    ],
    "sg:phone":"+1 812 232 0339",
    "sg:postcode":"47807",
    "sg:province":"IN",
    "sg:tags":[
        "transmission"
    ],
    "wof:name":"Precision Transmission",
    "wof:placetype":"venue"
},
  "geometry": {"coordinates":[-87.390711,39.468921],"type":"Point"}
}