{
  "type": "Feature",
  "properties": {
    "addr:full":"119 W Washington St Williamsport IN 47993",
    "addr:housenumber":"119",
    "addr:postcode":"47993",
    "addr:street":"W Washington St",
    "iso:country":"US",
    "sg:address":"119 W Washington St",
    "sg:city":"Williamsport",
    "sg:classifiers":[
        {
            "category":"Farming",
            "subcategory":"Farm",
            "type":"Manufacturing & Wholesale Goods"
        }
    ],
    "sg:phone":"+1 765 762 2114",
    "sg:postcode":"47993",
    "sg:province":"IN",
    "sg:tags":[
        "crop",
        "general"
    ],
    "wof:name":"Tmf Machine",
    "wof:placetype":"venue"
},
  "geometry": {"coordinates":[-87.29606699999999,40.279774],"type":"Point"}
}