{
  "type": "Feature",
  "properties": {
    "iso:country":"US",
    "sg:address":"1123 Wabash Ave",
    "sg:city":"Terre Haute",
    "sg:classifiers":[
        {
            "category":"Personal",
            "subcategory":"Beauty Salon",
            "type":"Services"
        }
    ],
    "sg:phone":"+1 812 232 6243",
    "sg:postcode":"47807",
    "sg:province":"IN",
    "sg:tags":[
        "school"
    ],
    "wof:name":"Longs School Of Hair Design",
    "wof:placetype":"venue"
},
  "geometry": {"coordinates":[-87.399597,39.467378],"type":"Point"}
}