{
  "type": "Feature",
  "properties": {
    "iso:country":"US",
    "sg:address":"3990 Garfield St",
    "sg:city":"Gary",
    "sg:classifiers":[
        {
            "category":"Shopping",
            "subcategory":"Florist",
            "type":"Retail Goods"
        }
    ],
    "sg:phone":"+1 219 588 5360",
    "sg:postcode":"46408",
    "sg:province":"IN",
    "wof:name":"Elegant Wedding Creations",
    "wof:placetype":"venue"
},
  "geometry": {"coordinates":[-87.35824,41.546342],"type":"Point"}
}