{
  "type": "Feature",
  "properties": {
    "addr:full":"201 E Locust St Fort Branch IN 47648",
    "addr:housenumber":"201",
    "addr:postcode":"47648",
    "addr:street":"E Locust St",
    "iso:country":"US",
    "sg:address":"201 E Locust St",
    "sg:city":"Fort Branch",
    "sg:classifiers":[
        {
            "category":"Retail",
            "subcategory":"Repair Shop",
            "type":"Services"
        }
    ],
    "sg:phone":"+1 812 753 3688",
    "sg:postcode":"47648",
    "sg:province":"IN",
    "wof:name":"Seilers Cylinder Service Inc",
    "wof:placetype":"venue"
},
  "geometry": {"coordinates":[-87.57718800000001,38.247394],"type":"Point"}
}