{
  "type": "Feature",
  "properties": {
    "iso:country":"US",
    "sg:address":"3725 E 38th St",
    "sg:city":"Indianapolis",
    "sg:classifiers":[
        {
            "category":"Professional",
            "subcategory":"Accounting & Tax Preparation",
            "type":"Services"
        }
    ],
    "sg:phone":"+1 317 546 3313",
    "sg:postcode":"46218",
    "sg:province":"IN",
    "sg:tags":[
        "return",
        "filing"
    ],
    "wof:name":"Speedy Tax Svc",
    "wof:placetype":"venue"
},
  "geometry": {"coordinates":[-86.103017,39.825258],"type":"Point"}
}