{
  "type": "Feature",
  "properties": {
    "iso:country":"US",
    "sg:address":"11819 Coralberry Ct",
    "sg:city":"Fort Wayne",
    "sg:classifiers":[
        {
            "category":"Professional",
            "subcategory":"Employment Agencies",
            "type":"Services"
        }
    ],
    "sg:phone":"+1 260 672 9785",
    "sg:postcode":"46814",
    "sg:province":"IN",
    "sg:tags":[
        "consultant",
        "search",
        "executive"
    ],
    "sg:website":"www.geminies.com",
    "wof:name":"Gemini Executive Search",
    "wof:placetype":"venue"
},
  "geometry": {"coordinates":[-85.297467,41.019206],"type":"Point"}
}