{
  "type": "Feature",
  "properties": {
    "iso:country":"US",
    "sg:address":"109 Baum St",
    "sg:city":"Avilla",
    "sg:classifiers":[
        {
            "category":"Manufacturing",
            "subcategory":"Printing",
            "type":"Manufacturing & Wholesale Goods"
        }
    ],
    "sg:phone":"+1 260 897 2674",
    "sg:postcode":"46710",
    "sg:province":"IN",
    "sg:tags":[
        "newspaper"
    ],
    "wof:name":"Avillaotto Nooz",
    "wof:placetype":"venue"
},
  "geometry": {"coordinates":[-85.237642,41.367809],"type":"Point"}
}