{
  "type": "Feature",
  "properties": {
    "iso:country":"US",
    "sg:address":"7215 N Keystone Ave",
    "sg:city":"Indianapolis",
    "sg:classifiers":[
        {
            "category":"Building & Trades",
            "subcategory":"Landscaping Services",
            "type":"Services"
        }
    ],
    "sg:phone":"+1 317 253 3064",
    "sg:postcode":"46240",
    "sg:province":"IN",
    "sg:tags":[
        "tree"
    ],
    "wof:name":"Cantrell's Tree Removal",
    "wof:placetype":"venue"
},
  "geometry": {"coordinates":[-86.122001,39.885081],"type":"Point"}
}