{
  "type": "Feature",
  "properties": {
    "iso:country":"US",
    "sg:address":"2218 Bellemeade Ave",
    "sg:city":"Evansville",
    "sg:classifiers":[
        {
            "category":"Shopping",
            "subcategory":"Photographic Equipment",
            "type":"Retail Goods"
        }
    ],
    "sg:phone":"+1 812 477 3008",
    "sg:postcode":"47714",
    "sg:province":"IN",
    "sg:tags":[
        "photo",
        "supply"
    ],
    "wof:name":"Lawndale Camera Shop",
    "wof:placetype":"venue"
},
  "geometry": {"coordinates":[-87.52419399999999,37.968038],"type":"Point"}
}