{
  "type": "Feature",
  "properties": {
    "addr:full":"5290 Charles Ct Carmel IN 46033",
    "addr:housenumber":"5290",
    "addr:postcode":"46033",
    "addr:street":"Charles Ct",
    "iso:country":"US",
    "sg:address":"5290 Charles Ct",
    "sg:city":"Carmel",
    "sg:classifiers":[
        {
            "category":"Building & Trades",
            "subcategory":"Construction",
            "type":"Services"
        }
    ],
    "sg:phone":"+1 317 575 0476",
    "sg:postcode":"46033",
    "sg:province":"IN",
    "sg:tags":[
        "home",
        "builder",
        "contractor"
    ],
    "wof:name":"Huff Harold Builder Inc",
    "wof:placetype":"venue"
},
  "geometry": {"coordinates":[-86.079498,39.9944],"type":"Point"}
}