{
  "type": "Feature",
  "properties": {
    "iso:country":"US",
    "sg:address":"17505 State Rd 37",
    "sg:city":"Harlan",
    "sg:classifiers":[
        {
            "category":"Banks & Credit Unions",
            "subcategory":"Bank",
            "type":"Services"
        }
    ],
    "sg:phone":"+1 260 657 5125",
    "sg:postcode":"46741",
    "sg:province":"IN",
    "wof:name":"Grabill Bank",
    "wof:placetype":"venue"
},
  "geometry": {"coordinates":[-84.919581,41.196156],"type":"Point"}
}