{
  "type": "Feature",
  "properties": {
    "addr:full":"4015 State Rd 9 Anderson IN 46012",
    "addr:housenumber":"4015",
    "addr:postcode":"46012",
    "addr:street":"State Rd 9",
    "iso:country":"US",
    "sg:address":"4015 State Rd 9",
    "sg:city":"Anderson",
    "sg:classifiers":[
        {
            "category":"Real Estate",
            "subcategory":"Real Estate Operator",
            "type":"Services"
        }
    ],
    "sg:phone":"+1 765 643 4793",
    "sg:postcode":"46012",
    "sg:province":"IN",
    "sg:tags":[
        "mobile",
        "home",
        "site",
        "community"
    ],
    "wof:name":"Resting Wheels Mobile Home Crt",
    "wof:placetype":"venue"
},
  "geometry": {"coordinates":[-85.67182200000001,40.164803],"type":"Point"}
}