{
  "type": "Feature",
  "properties": {
    "iso:country":"US",
    "sg:address":"1372 S 10th St",
    "sg:city":"Noblesville",
    "sg:classifiers":[
        {
            "category":"Retail",
            "subcategory":"Auto Rental",
            "type":"Services"
        }
    ],
    "sg:phone":"+1 317 773 4920",
    "sg:postcode":"46060",
    "sg:province":"IN",
    "sg:tags":[
        "renting",
        "truck",
        "leasing"
    ],
    "wof:name":"Budget Truck Rental",
    "wof:placetype":"venue"
},
  "geometry": {"coordinates":[-86.012052,40.033761],"type":"Point"}
}