{
  "type": "Feature",
  "properties": {
    "iso:country":"US",
    "sg:address":"13736 N Meridian St",
    "sg:city":"Carmel",
    "sg:classifiers":[
        {
            "category":"Real Estate",
            "subcategory":"Real Estate Agent",
            "type":"Services"
        }
    ],
    "sg:phone":"+1 317 843 5222",
    "sg:postcode":"46032",
    "sg:province":"IN",
    "wof:name":"Donald B Thornberry",
    "wof:placetype":"venue"
},
  "geometry": {"coordinates":[-86.135565,39.987789],"type":"Point"}
}