{
  "type": "Feature",
  "properties": {
    "iso:country":"US",
    "sg:address":"2633 S Gertrude St",
    "sg:city":"South Bend",
    "sg:classifiers":[
        {
            "category":"Freight",
            "type":"Transportation"
        }
    ],
    "sg:phone":"+1 574 289 3997",
    "sg:postcode":"46614",
    "sg:province":"IN",
    "sg:tags":[
        "trucking"
    ],
    "wof:name":"Patgent Line & Sons Inc",
    "wof:placetype":"venue"
},
  "geometry": {"coordinates":[-86.273132,41.643863],"type":"Point"}
}