{
  "type": "Feature",
  "properties": {
    "iso:country":"US",
    "sg:address":"201 N Jefferson St",
    "sg:city":"Huntington",
    "sg:classifiers":[
        {
            "category":"Government",
            "subcategory":"Court House",
            "type":"Public Place"
        }
    ],
    "sg:phone":"+1 260 358 4865",
    "sg:postcode":"46750",
    "sg:province":"IN",
    "sg:tags":[
        "county"
    ],
    "wof:name":"Violations Clerk County Court",
    "wof:placetype":"venue"
},
  "geometry": {"coordinates":[-85.49422199999999,40.881159],"type":"Point"}
}