{
  "type": "Feature",
  "properties": {
    "iso:country":"US",
    "sg:address":"712 Spring St",
    "sg:city":"New Castle",
    "sg:classifiers":[
        {
            "category":"Professional",
            "subcategory":"Management & Consulting",
            "type":"Services"
        }
    ],
    "sg:phone":"+1 765 529 0507",
    "sg:postcode":"47362",
    "sg:province":"IN",
    "sg:tags":[
        "retail",
        "direct",
        "sales"
    ],
    "wof:name":"Norick Fuel Oil",
    "wof:placetype":"venue"
},
  "geometry": {"coordinates":[-85.376899,39.933339],"type":"Point"}
}