{
  "type": "Feature",
  "properties": {
    "addr:full":"54163 Beech Rd Osceola IN 46561",
    "addr:housenumber":"54163",
    "addr:postcode":"46561",
    "addr:street":"Beech Rd",
    "iso:country":"US",
    "sg:address":"54163 Beech Rd",
    "sg:city":"Osceola",
    "sg:classifiers":[
        {
            "category":"Building & Trades",
            "subcategory":"Cleaning & Sanitation",
            "type":"Services"
        }
    ],
    "sg:phone":"+1 574 255 6447",
    "sg:postcode":"46561",
    "sg:province":"IN",
    "sg:tags":[
        "maintenance"
    ],
    "wof:name":"Marla Santuro",
    "wof:placetype":"venue"
},
  "geometry": {"coordinates":[-86.08132999999999,41.70874],"type":"Point"}
}