{
  "type": "Feature",
  "properties": {
    "addr:full":"1412 Camelot Dr Winona Lake IN 46590",
    "addr:housenumber":"1412",
    "addr:postcode":"46590",
    "addr:street":"Camelot Dr",
    "iso:country":"US",
    "sg:address":"1412 Camelot Dr",
    "sg:city":"Winona Lake",
    "sg:classifiers":[
        {
            "category":"Organizations",
            "subcategory":"Religious Organization",
            "type":"Services"
        }
    ],
    "sg:phone":"+1 574 269 9742",
    "sg:postcode":"46590",
    "sg:province":"IN",
    "sg:tags":[
        "church"
    ],
    "wof:name":"Church Development Ministries",
    "wof:placetype":"venue"
},
  "geometry": {"coordinates":[-85.79786799999999,41.221731],"type":"Point"}
}