{
  "type": "Feature",
  "properties": {
    "addr:full":"723 W Pearl St Union City IN 47390",
    "addr:housenumber":"723",
    "addr:postcode":"47390",
    "addr:street":"W Pearl St",
    "iso:country":"US",
    "sg:address":"723 W Pearl St",
    "sg:city":"Union City",
    "sg:classifiers":[
        {
            "category":"Home & Garden",
            "subcategory":"Furniture",
            "type":"Retail Goods"
        }
    ],
    "sg:phone":"+1 765 964 3147",
    "sg:postcode":"47390",
    "sg:province":"IN",
    "sg:tags":[
        "cabinet"
    ],
    "sg:website":"www.armstrong.com",
    "wof:name":"Armstrong Cabinets",
    "wof:placetype":"venue"
},
  "geometry": {"coordinates":[-84.815133,40.197472],"type":"Point"}
}