{
  "type": "Feature",
  "properties": {
    "iso:country":"US",
    "sg:address":"3 E Canal St",
    "sg:city":"Peru",
    "sg:classifiers":[
        {
            "category":"Autos & Motor Vehicles",
            "subcategory":"Automobile Sales",
            "type":"Retail Goods"
        }
    ],
    "sg:phone":"+1 765 472 1011",
    "sg:postcode":"46970",
    "sg:province":"IN",
    "sg:tags":[
        "car",
        "dealer"
    ],
    "wof:name":"South Side Sales",
    "wof:placetype":"venue"
},
  "geometry": {"coordinates":[-86.065579,40.751782],"type":"Point"}
}