{
  "type": "Feature",
  "properties": {
    "iso:country":"US",
    "sg:address":"5052 Co Rd 16",
    "sg:city":"Waterloo",
    "sg:classifiers":[
        {
            "category":"Building & Trades",
            "subcategory":"Construction",
            "type":"Services"
        }
    ],
    "sg:phone":"+1 260 837 3062",
    "sg:postcode":"46793",
    "sg:province":"IN",
    "sg:tags":[
        "general",
        "contractor"
    ],
    "wof:name":"Dirksen Construction",
    "wof:placetype":"venue"
},
  "geometry": {"coordinates":[-84.958659,41.470829],"type":"Point"}
}