{
  "type": "Feature",
  "properties": {
    "addr:full":"421 S Main St Princeton IN 47670",
    "addr:housenumber":"421",
    "addr:postcode":"47670",
    "addr:street":"S Main St",
    "iso:country":"US",
    "sg:address":"421 S Main St",
    "sg:city":"Princeton",
    "sg:classifiers":[
        {
            "category":"Social Services",
            "subcategory":"Child Care",
            "type":"Services"
        }
    ],
    "sg:phone":"+1 812 385 4968",
    "sg:postcode":"47670",
    "sg:province":"IN",
    "sg:website":"www.gcarc.org",
    "wof:name":"Building Blocks Day Care Ctr",
    "wof:placetype":"venue"
},
  "geometry": {"coordinates":[-87.567707,38.351767],"type":"Point"}
}