{
  "type": "Feature",
  "properties": {
    "iso:country":"US",
    "sg:address":"3827 N Arms Pl",
    "sg:city":"St Mary Of Woods",
    "sg:classifiers":[
        {
            "category":"Organizations",
            "subcategory":"Religious Organization",
            "type":"Services"
        }
    ],
    "sg:phone":"+1 812 535 1261",
    "sg:postcode":"47885",
    "sg:province":"IN",
    "sg:tags":[
        "church"
    ],
    "wof:name":"St Mary's Village Parish",
    "wof:placetype":"venue"
},
  "geometry": {"coordinates":[-87.470788,39.516476],"type":"Point"}
}