{
  "type": "Feature",
  "properties": {
    "iso:country":"US",
    "sg:address":"2403 State Rd 160",
    "sg:city":"Charlestown",
    "sg:classifiers":[
        {
            "category":"Retail",
            "subcategory":"Repair Shop",
            "type":"Services"
        }
    ],
    "sg:phone":"+1 812 256 6222",
    "sg:postcode":"47111",
    "sg:province":"IN",
    "sg:tags":[
        "welding"
    ],
    "wof:name":"Foster's Welding Svc",
    "wof:placetype":"venue"
},
  "geometry": {"coordinates":[-85.696784,38.47881],"type":"Point"}
}