{
  "type": "Feature",
  "properties": {
    "iso:country":"US",
    "sg:address":"1010 Reder Rd",
    "sg:city":"Griffith",
    "sg:classifiers":[
        {
            "category":"Wholesale",
            "subcategory":"Machinery & Supplies",
            "type":"Manufacturing & Wholesale Goods"
        }
    ],
    "sg:phone":"+1 219 922 9830",
    "sg:postcode":"46319",
    "sg:province":"IN",
    "sg:tags":[
        "truck"
    ],
    "wof:name":"Cigler Trucking Co",
    "wof:placetype":"venue"
},
  "geometry": {"coordinates":[-87.417093,41.511823],"type":"Point"}
}