{
  "type": "Feature",
  "properties": {
    "iso:country":"US",
    "sg:address":"600 State Rd 67",
    "sg:city":"Mooresville",
    "sg:classifiers":[
        {
            "category":"Restaurant",
            "type":"Food & Drink"
        }
    ],
    "sg:phone":"+1 317 831 0406",
    "sg:postcode":"46158",
    "sg:province":"IN",
    "sg:tags":[
        "eating"
    ],
    "wof:name":"Joes Grill 4 Inc",
    "wof:placetype":"venue"
},
  "geometry": {"coordinates":[-86.357758,39.611076],"type":"Point"}
}