{
  "type": "Feature",
  "properties": {
    "addr:full":"113 Catherine Dr Carmel IN 46032",
    "addr:housenumber":"113",
    "addr:postcode":"46032",
    "addr:street":"Catherine Dr",
    "iso:country":"US",
    "sg:address":"113 Catherine Dr",
    "sg:city":"Carmel",
    "sg:classifiers":[
        {
            "category":"Manufacturing",
            "subcategory":"Furniture",
            "type":"Manufacturing & Wholesale Goods"
        }
    ],
    "sg:phone":"+1 317 569 0439",
    "sg:postcode":"46032",
    "sg:province":"IN",
    "sg:tags":[
        "drapery",
        "mfg"
    ],
    "wof:name":"King of Kings Window",
    "wof:placetype":"venue"
},
  "geometry": {"coordinates":[-86.14894,39.979943],"type":"Point"}
}