{
  "type": "Feature",
  "properties": {
    "addr:full":"53 W Main St Peru IN 46970",
    "addr:housenumber":"53",
    "addr:postcode":"46970",
    "addr:street":"W Main St",
    "iso:country":"US",
    "sg:address":"53 W Main St",
    "sg:city":"Peru",
    "sg:classifiers":[
        {
            "category":"Organizations",
            "subcategory":"Religious Organization",
            "type":"Services"
        }
    ],
    "sg:phone":"+1 765 473 3105",
    "sg:postcode":"46970",
    "sg:province":"IN",
    "sg:tags":[
        "church"
    ],
    "sg:website":"www.fccperu.org",
    "wof:name":"First Christian Church",
    "wof:placetype":"venue"
},
  "geometry": {"coordinates":[-86.070618,40.752948],"type":"Point"}
}