{
  "type": "Feature",
  "properties": {
    "iso:country":"US",
    "sg:address":"108 E Monroe St",
    "sg:city":"Williamsport",
    "sg:classifiers":[
        {
            "category":"Professional",
            "subcategory":"Computer Services",
            "type":"Services"
        }
    ],
    "sg:phone":"+1 765 764 4916",
    "sg:postcode":"47993",
    "sg:province":"IN",
    "sg:tags":[
        "consultant",
        "designer"
    ],
    "wof:name":"Thomas Engineering & Consultng",
    "wof:placetype":"venue"
},
  "geometry": {"coordinates":[-87.29150199999999,40.285044],"type":"Point"}
}