{
  "type": "Feature",
  "properties": {
    "iso:country":"US",
    "sg:address":"33 Meadow Dr",
    "sg:city":"Danville",
    "sg:classifiers":[
        {
            "category":"Health Services",
            "subcategory":"Doctor",
            "type":"Services"
        }
    ],
    "sg:phone":"+1 317 745 0833",
    "sg:postcode":"46122",
    "sg:province":"IN",
    "sg:tags":[
        "physician",
        "surgeon"
    ],
    "wof:name":"Thomas L Gross MD",
    "wof:placetype":"venue"
},
  "geometry": {"coordinates":[-86.499539,39.762536],"type":"Point"}
}