{
  "type": "Feature",
  "properties": {
    "iso:country":"US",
    "sg:address":"1362 Oak Dale Dr",
    "sg:city":"South Bend",
    "sg:classifiers":[
        {
            "category":"Building & Trades",
            "subcategory":"Electrical",
            "type":"Services"
        }
    ],
    "sg:phone":"+1 574 291 1720",
    "sg:postcode":"46614",
    "sg:province":"IN",
    "sg:tags":[
        "electrical",
        "contractor"
    ],
    "wof:name":"Terrys Electric",
    "wof:placetype":"venue"
},
  "geometry": {"coordinates":[-86.226614,41.630502],"type":"Point"}
}