{
  "type": "Feature",
  "properties": {
    "iso:country":"US",
    "sg:address":"3000 E Wabash St",
    "sg:city":"Frankfort",
    "sg:classifiers":[
        {
            "category":"Social Services",
            "subcategory":"Child Care",
            "type":"Services"
        }
    ],
    "sg:phone":"+1 765 659 4662",
    "sg:postcode":"46041",
    "sg:province":"IN",
    "wof:name":"Heritage Child Care Ministry",
    "wof:placetype":"venue"
},
  "geometry": {"coordinates":[-86.46863399999999,40.278749],"type":"Point"}
}