{
  "type": "Feature",
  "properties": {
    "iso:country":"US",
    "sg:address":"1240 A St NE",
    "sg:city":"Linton",
    "sg:classifiers":[
        {
            "category":"Home & Garden",
            "subcategory":"Building Materials",
            "type":"Retail Goods"
        }
    ],
    "sg:phone":"+1 812 847 9770",
    "sg:postcode":"47441",
    "sg:province":"IN",
    "sg:tags":[
        "glass",
        "window",
        "plate"
    ],
    "wof:name":"American Eagle Auto Glass",
    "wof:placetype":"venue"
},
  "geometry": {"coordinates":[-87.149873,39.037211],"type":"Point"}
}