{
  "type": "Feature",
  "properties": {
    "iso:country":"US",
    "sg:address":"5156 N Co Rd 100 E",
    "sg:city":"Osgood",
    "sg:classifiers":[
        {
            "category":"Autos & Motor Vehicles",
            "subcategory":"Auto Supplies",
            "type":"Retail Goods"
        }
    ],
    "sg:phone":"+1 812 689 4547",
    "sg:postcode":"47037",
    "sg:province":"IN",
    "sg:tags":[
        "tire"
    ],
    "wof:name":"J & S Auto Care",
    "wof:placetype":"venue"
},
  "geometry": {"coordinates":[-85.245989,39.150718],"type":"Point"}
}