{
  "type": "Feature",
  "properties": {
    "iso:country":"US",
    "sg:address":"1655 Gateway Ct",
    "sg:city":"Elkhart",
    "sg:classifiers":[
        {
            "category":"Manufacturing",
            "subcategory":"Textiles",
            "type":"Manufacturing & Wholesale Goods"
        }
    ],
    "sg:phone":"+1 574 262 5190",
    "sg:postcode":"46514",
    "sg:province":"IN",
    "sg:tags":[
        "lining"
    ],
    "sg:website":"www.shadeswc.com",
    "wof:name":"Specialty Window Coverings",
    "wof:placetype":"venue"
},
  "geometry": {"coordinates":[-86.00798500000001,41.729243],"type":"Point"}
}