{
  "type": "Feature",
  "properties": {
    "iso:country":"US",
    "sg:address":"4984 N 500 E",
    "sg:city":"Marion",
    "sg:classifiers":[
        {
            "category":"Building & Trades",
            "subcategory":"Construction",
            "type":"Services"
        }
    ],
    "sg:phone":"+1 765 662 6202",
    "sg:postcode":"46952",
    "sg:province":"IN",
    "sg:tags":[
        "general",
        "contractor"
    ],
    "wof:name":"Central Indiana Roofing",
    "wof:placetype":"venue"
},
  "geometry": {"coordinates":[-85.580921,40.631706],"type":"Point"}
}