{
  "type": "Feature",
  "properties": {
    "iso:country":"US",
    "sg:address":"3540 Delmar Rd",
    "sg:city":"Indianapolis",
    "sg:classifiers":[
        {
            "category":"Real Estate",
            "subcategory":"Real Estate Agent",
            "type":"Services"
        }
    ],
    "sg:phone":"+1 317 255 4331",
    "sg:postcode":"46220",
    "sg:province":"IN",
    "sg:tags":[
        "inspection"
    ],
    "wof:name":"Stein Home Inspection",
    "wof:placetype":"venue"
},
  "geometry": {"coordinates":[-86.10507,39.848267],"type":"Point"}
}