{
  "type": "Feature",
  "properties": {
    "iso:country":"US",
    "sg:address":"632 Mill St",
    "sg:city":"Tipton",
    "sg:classifiers":[
        {
            "category":"Manufacturing",
            "subcategory":"Tools & Machinery",
            "type":"Manufacturing & Wholesale Goods"
        }
    ],
    "sg:phone":"+1 765 675 7593",
    "sg:postcode":"46072",
    "sg:province":"IN",
    "sg:tags":[
        "die",
        "maker"
    ],
    "wof:name":"Progress Tool & Die",
    "wof:placetype":"venue"
},
  "geometry": {"coordinates":[-86.03694400000001,40.291146],"type":"Point"}
}