{
  "type": "Feature",
  "properties": {
    "addr:full":"1720 Lafayette Ave Crawfordsville IN 47933",
    "addr:housenumber":"1720",
    "addr:postcode":"47933",
    "addr:street":"Lafayette Ave",
    "iso:country":"US",
    "sg:address":"1720 Lafayette Ave",
    "sg:city":"Crawfordsville",
    "sg:classifiers":[
        {
            "category":"Health Services",
            "subcategory":"Doctor",
            "type":"Services"
        }
    ],
    "sg:phone":"+1 765 362 1010",
    "sg:postcode":"47933",
    "sg:province":"IN",
    "sg:tags":[
        "physician",
        "surgeon"
    ],
    "wof:name":"Culver Women's Ctr",
    "wof:placetype":"venue"
},
  "geometry": {"coordinates":[-86.908143,40.064695],"type":"Point"}
}