{
  "type": "Feature",
  "properties": {
    "iso:country":"US",
    "sg:address":"239 Factory St",
    "sg:city":"Laporte",
    "sg:classifiers":[
        {
            "category":"Wholesale",
            "subcategory":"Stationery",
            "type":"Manufacturing & Wholesale Goods"
        }
    ],
    "sg:phone":"+1 219 326 1350",
    "sg:postcode":"46350",
    "sg:province":"IN",
    "sg:tags":[
        "box",
        "fiber"
    ],
    "sg:website":"www.packaginglogic.com",
    "wof:name":"Packaging Logic",
    "wof:placetype":"venue"
},
  "geometry": {"coordinates":[-86.702519,41.622091],"type":"Point"}
}