{
  "type": "Feature",
  "properties": {
    "iso:country":"US",
    "sg:address":"352 E South St",
    "sg:city":"Wheatfield",
    "sg:classifiers":[
        {
            "category":"Organizations",
            "subcategory":"Religious Organization",
            "type":"Services"
        }
    ],
    "sg:phone":"+1 219 956 4964",
    "sg:postcode":"46392",
    "sg:province":"IN",
    "wof:name":"Pentecstal Chrch God Whatfield",
    "wof:placetype":"venue"
},
  "geometry": {"coordinates":[-87.04917,41.190872],"type":"Point"}
}