{
  "type": "Feature",
  "properties": {
    "iso:country":"US",
    "sg:address":"100 Washington Ave",
    "sg:city":"Frankfort",
    "sg:classifiers":[
        {
            "category":"Government",
            "subcategory":"Post Office",
            "type":"Public Place"
        }
    ],
    "sg:phone":"+1 765 654 5553",
    "sg:postcode":"46041",
    "sg:province":"IN",
    "sg:website":"www.usps.com",
    "wof:name":"US Post Office",
    "wof:placetype":"venue"
},
  "geometry": {"coordinates":[-86.507131,40.282189],"type":"Point"}
}