{
  "type": "Feature",
  "properties": {
    "addr:full":"4507 National Rd E Richmond IN 47374",
    "addr:housenumber":"4507",
    "addr:postcode":"47374",
    "addr:street":"National Rd E",
    "iso:country":"US",
    "sg:address":"4507 National Rd E",
    "sg:city":"Richmond",
    "sg:classifiers":[
        {
            "category":"Bars & Pubs",
            "type":"Food & Drink"
        }
    ],
    "sg:phone":"+1 765 935 3883",
    "sg:postcode":"47374",
    "sg:province":"IN",
    "wof:name":"Rascal's Lounge",
    "wof:placetype":"venue"
},
  "geometry": {"coordinates":[-84.830741,39.831848],"type":"Point"}
}