{
  "type": "Feature",
  "properties": {
    "iso:country":"US",
    "sg:address":"1502 Knoll Crest Dr",
    "sg:city":"Kendallville",
    "sg:classifiers":[
        {
            "category":"Professional",
            "subcategory":"Management & Consulting",
            "type":"Services"
        }
    ],
    "sg:phone":"+1 260 347 5896",
    "sg:postcode":"46755",
    "sg:province":"IN",
    "sg:tags":[
        "business"
    ],
    "wof:name":"New Century Consulting",
    "wof:placetype":"venue"
},
  "geometry": {"coordinates":[-85.244441,41.44736],"type":"Point"}
}