{
  "type": "Feature",
  "properties": {
    "addr:full":"4041 Old Mill Rd Fort Wayne IN 46807",
    "addr:housenumber":"4041",
    "addr:postcode":"46807",
    "addr:street":"Old Mill Rd",
    "iso:country":"US",
    "sg:address":"4041 Old Mill Rd",
    "sg:city":"Fort Wayne",
    "sg:classifiers":[
        {
            "category":"Health Services",
            "subcategory":"Clinic",
            "type":"Services"
        }
    ],
    "sg:phone":"+1 260 744 3505",
    "sg:postcode":"46807",
    "sg:province":"IN",
    "wof:name":"Advance Nutritional Solutions",
    "wof:placetype":"venue"
},
  "geometry": {"coordinates":[-85.156869,41.047452],"type":"Point"}
}