{
  "type": "Feature",
  "properties": {
    "iso:country":"US",
    "sg:address":"219 Meisner Ave",
    "sg:city":"Elkhart",
    "sg:classifiers":[
        {
            "category":"Arts & Performance",
            "subcategory":"Theater",
            "type":"Entertainment"
        }
    ],
    "sg:phone":"+1 574 296 9900",
    "sg:postcode":"46514",
    "sg:province":"IN",
    "sg:tags":[
        "group"
    ],
    "wof:name":"A Jim Strauss Production",
    "wof:placetype":"venue"
},
  "geometry": {"coordinates":[-85.999357,41.681379],"type":"Point"}
}