{
  "type": "Feature",
  "properties": {
    "iso:country":"US",
    "sg:address":"805 S Gardener St",
    "sg:city":"Scottsburg",
    "sg:classifiers":[
        {
            "category":"Organizations",
            "subcategory":"Membership Organization",
            "type":"Services"
        }
    ],
    "sg:phone":"+1 812 752 6992",
    "sg:postcode":"47170",
    "sg:province":"IN",
    "wof:name":"Moose Lodge",
    "wof:placetype":"venue"
},
  "geometry": {"coordinates":[-85.778041,38.676966],"type":"Point"}
}