{
  "type": "Feature",
  "properties": {
    "addr:full":"3000 Michigan Rd Madison IN 47250",
    "addr:housenumber":"3000",
    "addr:postcode":"47250",
    "addr:street":"Michigan Rd",
    "iso:country":"US",
    "sg:address":"3000 Michigan Rd",
    "sg:city":"Madison",
    "sg:classifiers":[
        {
            "category":"Wholesale",
            "subcategory":"Painting Supplies",
            "type":"Manufacturing & Wholesale Goods"
        }
    ],
    "sg:phone":"+1 812 273 4040",
    "sg:postcode":"47250",
    "sg:province":"IN",
    "sg:tags":[
        "paint"
    ],
    "wof:name":"Bailey Manufacturing Corp",
    "wof:placetype":"venue"
},
  "geometry": {"coordinates":[-85.38725100000001,38.783145],"type":"Point"}
}