{
  "type": "Feature",
  "properties": {
    "iso:country":"US",
    "sg:address":"102 Executive Blvd",
    "sg:city":"Vincennes",
    "sg:classifiers":[
        {
            "category":"Freight",
            "type":"Transportation"
        }
    ],
    "sg:phone":"+1 812 882 6977",
    "sg:postcode":"47591",
    "sg:province":"IN",
    "sg:tags":[
        "commercial",
        "storage"
    ],
    "wof:name":"Executive Storage",
    "wof:placetype":"venue"
},
  "geometry": {"coordinates":[-87.497249,38.69567],"type":"Point"}
}