{
  "type": "Feature",
  "properties": {
    "iso:country":"US",
    "sg:address":"2002 Hanley St",
    "sg:city":"Gary",
    "sg:classifiers":[
        {
            "category":"Real Estate",
            "subcategory":"Real Estate Operator",
            "type":"Services"
        }
    ],
    "sg:phone":"+1 219 949 4136",
    "sg:postcode":"46406",
    "sg:province":"IN",
    "sg:tags":[
        "apartment"
    ],
    "wof:name":"L-B Residential Management",
    "wof:placetype":"venue"
},
  "geometry": {"coordinates":[-87.401133,41.581962],"type":"Point"}
}