{
  "type": "Feature",
  "properties": {
    "iso:country":"US",
    "sg:address":"3701 N Shadeland Ave",
    "sg:city":"Indianapolis",
    "sg:classifiers":[
        {
            "category":"Taxi",
            "type":"Transportation"
        }
    ],
    "sg:phone":"+1 317 897 2122",
    "sg:postcode":"46226",
    "sg:province":"IN",
    "sg:tags":[
        "taxicab"
    ],
    "wof:name":"Lawrence Rainbow Cab",
    "wof:placetype":"venue"
},
  "geometry": {"coordinates":[-86.045798,39.823947],"type":"Point"}
}