{
  "type": "Feature",
  "properties": {
    "iso:country":"US",
    "sg:address":"5610 S Concord St",
    "sg:city":"Indianapolis",
    "sg:classifiers":[
        {
            "category":"Retail",
            "subcategory":"Repair Shop",
            "type":"Services"
        }
    ],
    "sg:phone":"+1 317 710 3228",
    "sg:postcode":"46217",
    "sg:province":"IN",
    "sg:tags":[
        "bathtub",
        "sink",
        "refinishing"
    ],
    "wof:name":"Suzette's Tub Saver",
    "wof:placetype":"venue"
},
  "geometry": {"coordinates":[-86.210966,39.684704],"type":"Point"}
}