{
  "type": "Feature",
  "properties": {
    "iso:country":"US",
    "sg:address":"2570 Commercial Rd",
    "sg:city":"Fort Wayne",
    "sg:classifiers":[
        {
            "category":"Building & Trades",
            "subcategory":"Construction",
            "type":"Services"
        }
    ],
    "sg:phone":"+1 260 747 9335",
    "sg:postcode":"46809",
    "sg:province":"IN",
    "sg:tags":[
        "fabricator",
        "metal"
    ],
    "wof:name":"Trifab",
    "wof:placetype":"venue"
},
  "geometry": {"coordinates":[-85.173007,41.008827],"type":"Point"}
}