{
  "type": "Feature",
  "properties": {
    "iso:country":"US",
    "sg:address":"1100 W Beardsley Ave",
    "sg:city":"Elkhart",
    "sg:classifiers":[
        {
            "category":"Manufacturing",
            "subcategory":"Rubber & Plastics",
            "type":"Manufacturing & Wholesale Goods"
        }
    ],
    "sg:phone":"+1 574 294 3920",
    "sg:postcode":"46514",
    "sg:province":"IN",
    "sg:tags":[
        "product",
        "mfg"
    ],
    "wof:name":"M K Tool",
    "wof:placetype":"venue"
},
  "geometry": {"coordinates":[-85.99206,41.692682],"type":"Point"}
}