{
  "type": "Feature",
  "properties": {
    "iso:country":"US",
    "sg:address":"109 E South St",
    "sg:city":"Martinsville",
    "sg:classifiers":[
        {
            "category":"Personal",
            "subcategory":"Barber",
            "type":"Services"
        }
    ],
    "sg:phone":"+1 765 342 9057",
    "sg:postcode":"46151",
    "sg:province":"IN",
    "sg:tags":[
        "shop"
    ],
    "wof:name":"Bill S Barber Shop",
    "wof:placetype":"venue"
},
  "geometry": {"coordinates":[-86.426344,39.41602],"type":"Point"}
}