{
  "type": "Feature",
  "properties": {
    "iso:country":"US",
    "sg:address":"1750 W Epler Ave",
    "sg:city":"Indianapolis",
    "sg:classifiers":[
        {
            "category":"Utilities",
            "subcategory":"Fuel Oil & Lpg",
            "type":"Services"
        }
    ],
    "sg:phone":"+1 317 783 0236",
    "sg:postcode":"46217",
    "sg:province":"IN",
    "sg:tags":[
        "propane",
        "gas"
    ],
    "sg:website":"www.ferrellgas.com",
    "wof:name":"Ferrellgas",
    "wof:placetype":"venue"
},
  "geometry": {"coordinates":[-86.19362700000001,39.685761],"type":"Point"}
}