{
  "type": "Feature",
  "properties": {
    "iso:country":"US",
    "sg:address":"54 E Washington St",
    "sg:city":"Frankfort",
    "sg:classifiers":[
        {
            "category":"Professional",
            "subcategory":"Business Services",
            "type":"Services"
        }
    ],
    "sg:phone":"+1 765 654 4167",
    "sg:postcode":"46041",
    "sg:province":"IN",
    "sg:tags":[
        "embroidery"
    ],
    "wof:name":"Athletic Annex/Namely Yours",
    "wof:placetype":"venue"
},
  "geometry": {"coordinates":[-86.511384,40.2817],"type":"Point"}
}