{
  "type": "Feature",
  "properties": {
    "iso:country":"US",
    "sg:address":"232 W Van Buren St",
    "sg:city":"Columbia City",
    "sg:classifiers":[
        {
            "category":"Shopping",
            "type":"Retail Goods"
        }
    ],
    "sg:phone":"+1 260 244 2660",
    "sg:postcode":"46725",
    "sg:province":"IN",
    "sg:tags":[
        "art",
        "gallery",
        "dealer"
    ],
    "wof:name":"Raupfer Gallery",
    "wof:placetype":"venue"
},
  "geometry": {"coordinates":[-85.490845,41.157092],"type":"Point"}
}