{
  "type": "Feature",
  "properties": {
    "iso:country":"US",
    "sg:address":"2134 25th St",
    "sg:city":"Columbus",
    "sg:classifiers":[
        {
            "category":"Shopping",
            "subcategory":"Clothing, Apparel, & Fashions",
            "type":"Retail Goods"
        }
    ],
    "sg:phone":"+1 812 378 8986",
    "sg:postcode":"47201",
    "sg:province":"IN",
    "sg:tags":[
        "sportswear"
    ],
    "sg:website":"www.ae.com",
    "wof:name":"American Eagle Outfitters",
    "wof:placetype":"venue"
},
  "geometry": {"coordinates":[-85.901462,39.223023],"type":"Point"}
}