{
  "type": "Feature",
  "properties": {
    "addr:full":"994 E Buckingham Dr Bloomington IN 47401",
    "addr:housenumber":"994",
    "addr:postcode":"47401",
    "addr:street":"E Buckingham Dr",
    "iso:country":"US",
    "sg:address":"994 E Buckingham Dr",
    "sg:city":"Bloomington",
    "sg:classifiers":[
        {
            "category":"Wholesale",
            "subcategory":"Machinery & Supplies",
            "type":"Manufacturing & Wholesale Goods"
        }
    ],
    "sg:phone":"+1 812 339 9660",
    "sg:postcode":"47401",
    "sg:province":"IN",
    "sg:tags":[
        "equipment",
        "establishment"
    ],
    "wof:name":"Tech-Chem",
    "wof:placetype":"venue"
},
  "geometry": {"coordinates":[-86.522127,39.134412],"type":"Point"}
}