{
  "type": "Feature",
  "properties": {
    "addr:full":"6037 Co Rd 52 Saint Joe IN 46785",
    "addr:housenumber":"6037;52",
    "addr:postcode":"46785",
    "addr:street":"Co Rd",
    "iso:country":"US",
    "sg:address":"6037 Co Rd 52",
    "sg:city":"Saint Joe",
    "sg:classifiers":[
        {
            "category":"Farming",
            "subcategory":"Farm",
            "type":"Manufacturing & Wholesale Goods"
        }
    ],
    "sg:phone":"+1 260 337 0101",
    "sg:postcode":"46785",
    "sg:province":"IN",
    "sg:tags":[
        "crop",
        "general"
    ],
    "wof:name":"Pathway Pastures",
    "wof:placetype":"venue"
},
  "geometry": {"coordinates":[-84.88885500000001,41.341861],"type":"Point"}
}