{
  "type": "Feature",
  "properties": {
    "iso:country":"US",
    "sg:address":"3140 N Smith Pike",
    "sg:city":"Bloomington",
    "sg:classifiers":[
        {
            "category":"Retail",
            "subcategory":"Veterinary Services",
            "type":"Services"
        }
    ],
    "sg:phone":"+1 812 332 1429",
    "sg:postcode":"47404",
    "sg:province":"IN",
    "sg:tags":[
        "veterinarian"
    ],
    "wof:name":"Towne & Country Vet Clinic",
    "wof:placetype":"venue"
},
  "geometry": {"coordinates":[-86.583034,39.193658],"type":"Point"}
}