{
  "type": "Feature",
  "properties": {
    "iso:country":"US",
    "sg:address":"104 W Pearl St",
    "sg:city":"Batesville",
    "sg:classifiers":[
        {
            "category":"Building & Trades",
            "subcategory":"Construction",
            "type":"Services"
        }
    ],
    "sg:phone":"+1 812 934 2445",
    "sg:postcode":"47006",
    "sg:province":"IN",
    "sg:tags":[
        "home",
        "builder"
    ],
    "wof:name":"Eagles Home",
    "wof:placetype":"venue"
},
  "geometry": {"coordinates":[-85.22479,39.299866],"type":"Point"}
}