{
  "type": "Feature",
  "properties": {
    "addr:full":"2213 Scatterfield Rd Anderson IN 46016",
    "addr:housenumber":"2213",
    "addr:postcode":"46016",
    "addr:street":"Scatterfield Rd",
    "iso:country":"US",
    "sg:address":"2213 Scatterfield Rd",
    "sg:city":"Anderson",
    "sg:classifiers":[
        {
            "category":"Shopping",
            "type":"Retail Goods"
        }
    ],
    "sg:phone":"+1 765 649 2222",
    "sg:postcode":"46016",
    "sg:province":"IN",
    "sg:tags":[
        "hearing",
        "equipment",
        "supply",
        "impaired"
    ],
    "wof:name":"Beltone Hearing Aid Ctr",
    "wof:placetype":"venue"
},
  "geometry": {"coordinates":[-85.65275099999999,40.09507],"type":"Point"}
}