{
  "type": "Feature",
  "properties": {
    "iso:country":"US",
    "sg:address":"661 Main St",
    "sg:city":"Lafayette",
    "sg:classifiers":[
        {
            "category":"Autos & Motor Vehicles",
            "subcategory":"Auto Supplies",
            "type":"Retail Goods"
        }
    ],
    "sg:phone":"+1 765 742 7676",
    "sg:postcode":"47901",
    "sg:province":"IN",
    "sg:tags":[
        "wheel",
        "cover"
    ],
    "wof:name":"Budgett Wheels",
    "wof:placetype":"venue"
},
  "geometry": {"coordinates":[-86.889759,40.419058],"type":"Point"}
}