{
  "type": "Feature",
  "properties": {
    "iso:country":"US",
    "sg:address":"1909 N Greensburg Xing",
    "sg:city":"Greensburg",
    "sg:classifiers":[
        {
            "category":"Insurance",
            "subcategory":"Insurance Agent",
            "type":"Services"
        }
    ],
    "sg:phone":"+1 812 663 2537",
    "sg:postcode":"47240",
    "sg:province":"IN",
    "wof:name":"R L Bergstrom & Assoc",
    "wof:placetype":"venue"
},
  "geometry": {"coordinates":[-85.61994300000001,39.351988],"type":"Point"}
}