{
  "type": "Feature",
  "properties": {
    "iso:country":"US",
    "sg:address":"800 E Tipton St",
    "sg:city":"Seymour",
    "sg:classifiers":[
        {
            "category":"Restaurant",
            "type":"Food & Drink"
        }
    ],
    "sg:menulink":"http://www.allmenus.com/in/jackson/76438-dominos-pizza/menu/",
    "sg:phone":"+1 812 523 3959",
    "sg:postcode":"47274",
    "sg:province":"IN",
    "sg:tags":[
        "american",
        "wing",
        "pizza"
    ],
    "wof:name":"Domino's Pizza",
    "wof:placetype":"venue"
},
  "geometry": {"coordinates":[-85.87806399999999,38.958128],"type":"Point"}
}