{
  "type": "Feature",
  "properties": {
    "addr:full":"1180 E State Rd 234 Fortville IN 46040",
    "addr:housenumber":"1180",
    "addr:postcode":"46040",
    "addr:street":"E State Rd 234",
    "iso:country":"US",
    "sg:address":"1180 E State Rd 234",
    "sg:city":"Fortville",
    "sg:classifiers":[
        {
            "category":"Building & Trades",
            "subcategory":"Construction",
            "type":"Services"
        }
    ],
    "sg:phone":"+1 317 326 2921",
    "sg:postcode":"46040",
    "sg:province":"IN",
    "sg:tags":[
        "repairing",
        "residential",
        "remodeling",
        "house",
        "contractor"
    ],
    "wof:name":"T R Beechler Enterprises",
    "wof:placetype":"venue"
},
  "geometry": {"coordinates":[-85.784538,39.900973],"type":"Point"}
}