{
  "type": "Feature",
  "properties": {
    "iso:country":"US",
    "sg:address":"918 S Green River Rd",
    "sg:city":"Evansville",
    "sg:classifiers":[
        {
            "category":"Shopping",
            "subcategory":"Books",
            "type":"Retail Goods"
        }
    ],
    "sg:phone":"+1 812 477 7784",
    "sg:postcode":"47715",
    "sg:province":"IN",
    "sg:tags":[
        "dealer"
    ],
    "sg:website":"www.booksamillion.com",
    "wof:name":"Books-A-Million",
    "wof:placetype":"venue"
},
  "geometry": {"coordinates":[-87.49258,37.963368],"type":"Point"}
}