{
  "type": "Feature",
  "properties": {
    "iso:country":"US",
    "sg:address":"101 E Main St",
    "sg:city":"Greensburg",
    "sg:classifiers":[
        {
            "category":"Organizations",
            "subcategory":"Non-profit Organization",
            "type":"Services"
        }
    ],
    "sg:phone":"+1 812 663 3342",
    "sg:postcode":"47240",
    "sg:province":"IN",
    "wof:name":"United Fund",
    "wof:placetype":"venue"
},
  "geometry": {"coordinates":[-85.484212,39.336569],"type":"Point"}
}