{
  "type": "Feature",
  "properties": {
    "addr:full":"2667 E Bridgewater Rd Scottsburg IN 47170",
    "addr:housenumber":"2667",
    "addr:postcode":"47170",
    "addr:street":"E Bridgewater Rd",
    "iso:country":"US",
    "sg:address":"2667 E Bridgewater Rd",
    "sg:city":"Scottsburg",
    "sg:phone":"+1 812 752 7373",
    "sg:postcode":"47170",
    "sg:province":"IN",
    "sg:tags":[
        "farm",
        "tobacco"
    ],
    "wof:name":"Robert Backus",
    "wof:placetype":"venue"
},
  "geometry": {"coordinates":[-85.72166199999999,38.635014],"type":"Point"}
}