{
  "type": "Feature",
  "properties": {
    "addr:full":"378 N Gardner St Scottsburg IN 47170",
    "addr:housenumber":"378",
    "addr:postcode":"47170",
    "addr:street":"N Gardner St",
    "iso:country":"US",
    "sg:address":"378 N Gardner St",
    "sg:city":"Scottsburg",
    "sg:classifiers":[
        {
            "category":"Wholesale",
            "subcategory":"Durable Goods & Equipment",
            "type":"Manufacturing & Wholesale Goods"
        }
    ],
    "sg:phone":"+1 812 752 5152",
    "sg:postcode":"47170",
    "sg:province":"IN",
    "sg:tags":[
        "importer"
    ],
    "wof:name":"H & H Imports",
    "wof:placetype":"venue"
},
  "geometry": {"coordinates":[-85.77977799999999,38.691695],"type":"Point"}
}