{
  "type": "Feature",
  "properties": {
    "iso:country":"US",
    "sg:address":"1107 Ohio St",
    "sg:city":"Terre Haute",
    "sg:classifiers":[
        {
            "category":"Building & Trades",
            "subcategory":"Electrical",
            "type":"Services"
        }
    ],
    "sg:phone":"+1 812 232 7879",
    "sg:postcode":"47807",
    "sg:province":"IN",
    "sg:tags":[
        "electric",
        "contractor"
    ],
    "wof:name":"Royal Electric Inc",
    "wof:placetype":"venue"
},
  "geometry": {"coordinates":[-87.400116,39.46538],"type":"Point"}
}