{
  "type": "Feature",
  "properties": {
    "iso:country":"US",
    "sg:address":"8218 Huguenard Rd",
    "sg:city":"Fort Wayne",
    "sg:classifiers":[
        {
            "category":"Sports & Exercise",
            "subcategory":"Golf",
            "type":"Entertainment"
        }
    ],
    "sg:phone":"+1 260 489 5121",
    "sg:postcode":"46818",
    "sg:province":"IN",
    "sg:tags":[
        "course"
    ],
    "sg:website":"www.colonialgc.com",
    "wof:name":"Colonial Oaks Golf Club",
    "wof:placetype":"venue"
},
  "geometry": {"coordinates":[-85.192741,41.15002],"type":"Point"}
}