{
  "type": "Feature",
  "properties": {
    "iso:country":"US",
    "sg:address":"23809 US Hwy 33",
    "sg:city":"Elkhart",
    "sg:classifiers":[
        {
            "category":"Insurance",
            "subcategory":"Insurance Agent",
            "type":"Services"
        }
    ],
    "sg:phone":"+1 574 875 2525",
    "sg:postcode":"46517",
    "sg:province":"IN",
    "wof:name":"State Farm Insurance",
    "wof:placetype":"venue"
},
  "geometry": {"coordinates":[-85.92417500000001,41.637623],"type":"Point"}
}