{
  "type": "Feature",
  "properties": {
    "addr:full":"311 E Winslow Rd Bloomington IN 47401",
    "addr:housenumber":"311",
    "addr:postcode":"47401",
    "addr:street":"E Winslow Rd",
    "iso:country":"US",
    "sg:address":"311 E Winslow Rd",
    "sg:city":"Bloomington",
    "sg:classifiers":[
        {
            "category":"Arts & Performance",
            "subcategory":"Arts Center",
            "type":"Entertainment"
        }
    ],
    "sg:phone":"+1 812 822 0050",
    "sg:postcode":"47401",
    "sg:province":"IN",
    "sg:tags":[
        "performing"
    ],
    "wof:name":"Panache School of Ballroom and Social Dance",
    "wof:placetype":"venue"
},
  "geometry": {"coordinates":[-86.526642,39.136141],"type":"Point"}
}