{
  "type": "Feature",
  "properties": {
    "addr:full":"1931 Grant Line Rd New Albany IN 47150",
    "addr:housenumber":"1931",
    "addr:postcode":"47150",
    "addr:street":"Grant Line Rd",
    "iso:country":"US",
    "sg:address":"1931 Grant Line Rd",
    "sg:city":"New Albany",
    "sg:classifiers":[
        {
            "category":"Autos & Motor Vehicles",
            "subcategory":"Auto Supplies",
            "type":"Retail Goods"
        }
    ],
    "sg:phone":"+1 812 542 1454",
    "sg:postcode":"47150",
    "sg:province":"IN",
    "sg:tags":[
        "automobile",
        "parts"
    ],
    "wof:name":"Autozone",
    "wof:placetype":"venue"
},
  "geometry": {"coordinates":[-85.818738,38.302737],"type":"Point"}
}