{
  "type": "Feature",
  "properties": {
    "iso:country":"US",
    "sg:address":"1250 Conner St",
    "sg:city":"Noblesville",
    "sg:classifiers":[
        {
            "category":"Farming",
            "subcategory":"Farm & Veterinary Services",
            "type":"Manufacturing & Wholesale Goods"
        }
    ],
    "sg:phone":"+1 317 776 3600",
    "sg:postcode":"46060",
    "sg:province":"IN",
    "sg:tags":[
        "consultant",
        "herbicide"
    ],
    "sg:website":"www.geniherbs.com",
    "wof:name":"Geni Herbs Inc",
    "wof:placetype":"venue"
},
  "geometry": {"coordinates":[-86.00942000000001,40.045676],"type":"Point"}
}