{
  "type": "Feature",
  "properties": {
    "addr:full":"1127 E Virginia St Evansville IN 47711",
    "addr:housenumber":"1127",
    "addr:postcode":"47711",
    "addr:street":"E Virginia St",
    "iso:country":"US",
    "sg:address":"1127 E Virginia St",
    "sg:city":"Evansville",
    "sg:classifiers":[
        {
            "category":"Manufacturing",
            "subcategory":"Glass & Minerals",
            "type":"Manufacturing & Wholesale Goods"
        }
    ],
    "sg:phone":"+1 812 425 3466",
    "sg:postcode":"47711",
    "sg:province":"IN",
    "sg:tags":[
        "refractory"
    ],
    "wof:name":"Tri State Refractories",
    "wof:placetype":"venue"
},
  "geometry": {"coordinates":[-87.54485099999999,37.981451],"type":"Point"}
}