{
  "type": "Feature",
  "properties": {
    "iso:country":"US",
    "sg:address":"215 Lafayette Ave",
    "sg:city":"Lebanon",
    "sg:classifiers":[
        {
            "category":"Organizations",
            "subcategory":"Community Association",
            "type":"Services"
        }
    ],
    "sg:phone":"+1 765 482 1360",
    "sg:postcode":"46052",
    "sg:province":"IN",
    "sg:tags":[
        "fraternal"
    ],
    "wof:name":"Elks Lodge",
    "wof:placetype":"venue"
},
  "geometry": {"coordinates":[-86.474428,40.048887],"type":"Point"}
}