{
  "type": "Feature",
  "properties": {
    "iso:country":"US",
    "sg:address":"7714 Lima Rd",
    "sg:city":"Fort Wayne",
    "sg:classifiers":[
        {
            "category":"Building & Trades",
            "subcategory":"Landscaping Services",
            "type":"Services"
        }
    ],
    "sg:phone":"+1 260 489 6707",
    "sg:postcode":"46818",
    "sg:province":"IN",
    "sg:tags":[
        "tree"
    ],
    "wof:name":"Elderberry Tree House Shoppe",
    "wof:placetype":"venue"
},
  "geometry": {"coordinates":[-85.165282,41.150897],"type":"Point"}
}