{
  "type": "Feature",
  "properties": {
    "iso:country":"US",
    "sg:address":"3230 Fairfield Ave",
    "sg:city":"Fort Wayne",
    "sg:classifiers":[
        {
            "category":"Food & Beverages",
            "subcategory":"Groceries & Convenience Stores",
            "type":"Retail Goods"
        }
    ],
    "sg:phone":"+1 260 744 1301",
    "sg:postcode":"46807",
    "sg:province":"IN",
    "sg:tags":[
        "grocer"
    ],
    "wof:name":"Mark City Market",
    "wof:placetype":"venue"
},
  "geometry": {"coordinates":[-85.144904,41.055356],"type":"Point"}
}