{
  "type": "Feature",
  "properties": {
    "addr:full":"123 S Gentry St Bloomington IN 47404",
    "addr:housenumber":"123",
    "addr:postcode":"47404",
    "addr:street":"S Gentry St",
    "iso:country":"US",
    "sg:address":"123 S Gentry St",
    "sg:city":"Bloomington",
    "sg:classifiers":[
        {
            "category":"Restaurant",
            "type":"Food & Drink"
        }
    ],
    "sg:phone":"+1 812 337 0881",
    "sg:postcode":"47404",
    "sg:province":"IN",
    "wof:name":"Peterson's Restaurant",
    "wof:placetype":"venue"
},
  "geometry": {"coordinates":[-86.535528,39.165822],"type":"Point"}
}