{
  "type": "Feature",
  "properties": {
    "addr:full":"9916 W 1050 N Nappanee IN 46550",
    "addr:housenumber":"9916",
    "addr:postcode":"46550",
    "addr:street":"W 1050 N",
    "iso:country":"US",
    "sg:address":"9916 W 1050 N",
    "sg:city":"Nappanee",
    "sg:classifiers":[
        {
            "category":"Freight",
            "type":"Transportation"
        }
    ],
    "sg:phone":"+1 574 646 3865",
    "sg:postcode":"46550",
    "sg:province":"IN",
    "sg:tags":[
        "company",
        "local",
        "trucking"
    ],
    "wof:name":"Ron Anglin",
    "wof:placetype":"venue"
},
  "geometry": {"coordinates":[-86.028451,41.384331],"type":"Point"}
}