{
  "type": "Feature",
  "properties": {
    "addr:full":"160 W Carmel Dr Carmel IN 46032",
    "addr:housenumber":"160",
    "addr:postcode":"46032",
    "addr:street":"W Carmel Dr",
    "iso:country":"US",
    "sg:address":"160 W Carmel Dr",
    "sg:city":"Carmel",
    "sg:classifiers":[
        {
            "category":"Education",
            "subcategory":"Special Training",
            "type":"Public Place"
        }
    ],
    "sg:phone":"+1 317 569 0797",
    "sg:postcode":"46032",
    "sg:province":"IN",
    "sg:tags":[
        "school",
        "language"
    ],
    "wof:name":"Spanish Language Success",
    "wof:placetype":"venue"
},
  "geometry": {"coordinates":[-86.128602,39.961454],"type":"Point"}
}