{
  "type": "Feature",
  "properties": {
    "addr:full":"9655 Lotticks Corner Rd SE Elizabeth IN 47117",
    "addr:housenumber":"9655",
    "addr:postcode":"47117",
    "addr:street":"Lotticks Corner Rd Se",
    "iso:country":"US",
    "sg:address":"9655 Lotticks Corner Rd SE",
    "sg:city":"Elizabeth",
    "sg:classifiers":[
        {
            "category":"Professional",
            "subcategory":"Accounting & Tax Preparation",
            "type":"Services"
        }
    ],
    "sg:phone":"+1 812 969 2599",
    "sg:postcode":"47117",
    "sg:province":"IN",
    "wof:name":"Kenneth Roberts CPA",
    "wof:placetype":"venue"
},
  "geometry": {"coordinates":[-85.946361,38.1714],"type":"Point"}
}