{
  "type": "Feature",
  "properties": {
    "iso:country":"US",
    "sg:address":"3220 Kratzville Rd",
    "sg:city":"Evansville",
    "sg:classifiers":[
        {
            "category":"Wholesale",
            "subcategory":"Machinery & Supplies",
            "type":"Manufacturing & Wholesale Goods"
        }
    ],
    "sg:phone":"+1 812 477 2120",
    "sg:postcode":"47710",
    "sg:province":"IN",
    "sg:tags":[
        "valve"
    ],
    "wof:name":"Hydronic Sales Inc",
    "wof:placetype":"venue"
},
  "geometry": {"coordinates":[-87.582779,38.00892],"type":"Point"}
}