{
  "type": "Feature",
  "properties": {
    "addr:full":"133 Boyd Cir Michigan City IN 46360",
    "addr:housenumber":"133",
    "addr:postcode":"46360",
    "addr:street":"Boyd Cir",
    "iso:country":"US",
    "sg:address":"133 Boyd Cir",
    "sg:city":"Michigan City",
    "sg:classifiers":[
        {
            "category":"Home & Garden",
            "subcategory":"Carpets & Floor Coverings",
            "type":"Retail Goods"
        }
    ],
    "sg:phone":"+1 219 879 5233",
    "sg:postcode":"46360",
    "sg:province":"IN",
    "wof:name":"Flying Carpet Travelogue",
    "wof:placetype":"venue"
},
  "geometry": {"coordinates":[-86.89255799999999,41.690544],"type":"Point"}
}