{
  "type": "Feature",
  "properties": {
    "iso:country":"US",
    "sg:address":"304 S Water St",
    "sg:city":"Salem",
    "sg:classifiers":[
        {
            "category":"Recreation",
            "type":"Entertainment"
        }
    ],
    "sg:phone":"+1 812 883 0309",
    "sg:postcode":"47167",
    "sg:province":"IN",
    "sg:tags":[
        "parlor",
        "billiard"
    ],
    "wof:name":"Salem Pinball & Billiards",
    "wof:placetype":"venue"
},
  "geometry": {"coordinates":[-86.101949,38.603659],"type":"Point"}
}