{
  "type": "Feature",
  "properties": {
    "iso:country":"US",
    "sg:address":"1519 W McGalliard Rd",
    "sg:city":"Muncie",
    "sg:classifiers":[
        {
            "category":"Shopping",
            "subcategory":"Used Merchandise",
            "type":"Retail Goods"
        }
    ],
    "sg:phone":"+1 765 281 0040",
    "sg:postcode":"47304",
    "sg:province":"IN",
    "sg:tags":[
        "shop",
        "consignment"
    ],
    "wof:name":"Growing Inch By Inch Inc",
    "wof:placetype":"venue"
},
  "geometry": {"coordinates":[-85.405633,40.218856],"type":"Point"}
}