{
  "type": "Feature",
  "properties": {
    "iso:country":"US",
    "sg:address":"1485 N 175 E",
    "sg:city":"Warsaw",
    "sg:classifiers":[
        {
            "category":"Building & Trades",
            "subcategory":"Electrical",
            "type":"Services"
        }
    ],
    "sg:phone":"+1 574 267 8852",
    "sg:postcode":"46582",
    "sg:province":"IN",
    "sg:tags":[
        "electric",
        "contractor"
    ],
    "wof:name":"Derry Electric Inc",
    "wof:placetype":"venue"
},
  "geometry": {"coordinates":[-85.810474,41.257236],"type":"Point"}
}