{
  "type": "Feature",
  "properties": {
    "iso:country":"US",
    "sg:address":"158 Beissinger Rd",
    "sg:city":"Hamilton",
    "sg:classifiers":[
        {
            "category":"Building & Trades",
            "subcategory":"Electrical",
            "type":"Services"
        }
    ],
    "sg:phone":"+1 513 868 3487",
    "sg:postcode":"45013",
    "sg:province":"IN",
    "sg:tags":[
        "electric",
        "contractor"
    ],
    "wof:name":"Mechanics Electric Inc",
    "wof:placetype":"venue"
},
  "geometry": {"coordinates":[-84.557315,39.44313],"type":"Point"}
}