{
  "type": "Feature",
  "properties": {
    "addr:full":"13421 Old Meridian St Carmel IN 46032",
    "addr:housenumber":"13421",
    "addr:postcode":"46032",
    "addr:street":"Old Meridian St",
    "iso:country":"US",
    "sg:address":"13421 Old Meridian St",
    "sg:city":"Carmel",
    "sg:classifiers":[
        {
            "category":"Health Services",
            "subcategory":"Doctor",
            "type":"Services"
        }
    ],
    "sg:phone":"+1 317 844 5273",
    "sg:postcode":"46032",
    "sg:province":"IN",
    "wof:name":"Park Patrick Y MD",
    "wof:placetype":"venue"
},
  "geometry": {"coordinates":[-86.14313900000001,39.980637],"type":"Point"}
}