{
  "type": "Feature",
  "properties": {
    "iso:country":"US",
    "sg:address":"2439 Fairfield Ave",
    "sg:city":"Fort Wayne",
    "sg:classifiers":[
        {
            "category":"Social Services",
            "type":"Services"
        }
    ],
    "sg:phone":"+1 260 456 1600",
    "sg:postcode":"46807",
    "sg:province":"IN",
    "sg:tags":[
        "organization",
        "welfare"
    ],
    "sg:website":"www.bbbsnei.org",
    "wof:name":"Big Brothers & Big Sisters",
    "wof:placetype":"venue"
},
  "geometry": {"coordinates":[-85.14502899999999,41.062335],"type":"Point"}
}