{
  "type": "Feature",
  "properties": {
    "iso:country":"US",
    "sg:address":"8800 E 25 N",
    "sg:city":"Knox",
    "sg:classifiers":[
        {
            "category":"Building & Trades",
            "subcategory":"Construction",
            "type":"Services"
        }
    ],
    "sg:phone":"+1 574 772 4212",
    "sg:postcode":"46534",
    "sg:province":"IN",
    "sg:tags":[
        "layer",
        "carpet"
    ],
    "wof:name":"George's Carpet Installation",
    "wof:placetype":"venue"
},
  "geometry": {"coordinates":[-86.52826899999999,41.306166],"type":"Point"}
}