{
  "type": "Feature",
  "properties": {
    "iso:country":"US",
    "sg:address":"2922 Broadway Ave",
    "sg:city":"Evansville",
    "sg:classifiers":[
        {
            "category":"Retail",
            "subcategory":"Laundry & Dry Cleaning",
            "type":"Services"
        }
    ],
    "sg:phone":"+1 812 468 8284",
    "sg:postcode":"47712",
    "sg:province":"IN",
    "sg:tags":[
        "cleaners",
        "rug",
        "carpet"
    ],
    "wof:name":"Dillback's Carpet & Janitorial",
    "wof:placetype":"venue"
},
  "geometry": {"coordinates":[-87.61107699999999,37.96272],"type":"Point"}
}