{
  "type": "Feature",
  "properties": {
    "iso:country":"US",
    "sg:address":"100 Ballard Ln",
    "sg:city":"Greencastle",
    "sg:classifiers":[
        {
            "category":"Insurance",
            "subcategory":"Hazard Insurance",
            "type":"Services"
        }
    ],
    "sg:phone":"+1 765 653 0070",
    "sg:postcode":"46135",
    "sg:province":"IN",
    "sg:tags":[
        "warranty",
        "program"
    ],
    "wof:name":"Dixie Chopper Warranty Sales",
    "wof:placetype":"venue"
},
  "geometry": {"coordinates":[-86.81752899999999,39.638678],"type":"Point"}
}