{
  "type": "Feature",
  "properties": {
    "iso:country":"US",
    "sg:address":"1701 Wabash Ave",
    "sg:city":"Terre Haute",
    "sg:classifiers":[
        {
            "category":"Autos & Motor Vehicles",
            "subcategory":"Automobile Sales",
            "type":"Retail Goods"
        }
    ],
    "sg:phone":"+1 812 235 9090",
    "sg:postcode":"47807",
    "sg:province":"IN",
    "sg:tags":[
        "car",
        "dealer"
    ],
    "wof:name":"Tanoos Auto Detailing",
    "wof:placetype":"venue"
},
  "geometry": {"coordinates":[-87.390158,39.469016],"type":"Point"}
}