{
  "type": "Feature",
  "properties": {
    "addr:full":"26849 Co Rd 44 Nappanee IN 46550",
    "addr:housenumber":"26849;44",
    "addr:postcode":"46550",
    "addr:street":"Co Rd",
    "iso:country":"US",
    "sg:address":"26849 Co Rd 44",
    "sg:city":"Nappanee",
    "sg:classifiers":[
        {
            "category":"Real Estate",
            "subcategory":"Real Estate Operator",
            "type":"Services"
        }
    ],
    "sg:phone":"+1 574 862 4285",
    "sg:postcode":"46550",
    "sg:province":"IN",
    "sg:tags":[
        "property",
        "lessor"
    ],
    "wof:name":"Bdg Dairy Farm",
    "wof:placetype":"venue"
},
  "geometry": {"coordinates":[-85.978177,41.50817],"type":"Point"}
}