{
  "type": "Feature",
  "properties": {
    "iso:country":"US",
    "sg:address":"1461 N Queen Rd",
    "sg:city":"Walkerton",
    "sg:classifiers":[
        {
            "category":"Retail",
            "subcategory":"Animal Services",
            "type":"Services"
        }
    ],
    "sg:phone":"+1 574 784 2670",
    "sg:postcode":"46574",
    "sg:province":"IN",
    "wof:name":"Teegarden Kennels",
    "wof:placetype":"venue"
},
  "geometry": {"coordinates":[-86.37766499999999,41.456377],"type":"Point"}
}