{
  "type": "Feature",
  "properties": {
    "iso:country":"US",
    "sg:address":"1754 Raccoon Creek Ct",
    "sg:city":"Valparaiso",
    "sg:classifiers":[
        {
            "category":"Recreation",
            "type":"Entertainment"
        }
    ],
    "sg:phone":"+1 219 462 0734",
    "sg:postcode":"46385",
    "sg:province":"IN",
    "sg:tags":[
        "club",
        "membership"
    ],
    "wof:name":"Valparaiso Swim Club",
    "wof:placetype":"venue"
},
  "geometry": {"coordinates":[-87.082688,41.45044],"type":"Point"}
}