{
  "type": "Feature",
  "properties": {
    "iso:country":"US",
    "sg:address":"1717 Judson St",
    "sg:city":"Evansville",
    "sg:classifiers":[
        {
            "category":"Organizations",
            "subcategory":"Religious Organization",
            "type":"Services"
        }
    ],
    "sg:phone":"+1 812 421 0462",
    "sg:postcode":"47713",
    "sg:province":"IN",
    "sg:tags":[
        "church"
    ],
    "wof:name":"Church Of God In Christ",
    "wof:placetype":"venue"
},
  "geometry": {"coordinates":[-87.5612,37.953211],"type":"Point"}
}