{
  "type": "Feature",
  "properties": {
    "iso:country":"US",
    "sg:address":"28468 Co Rd 26",
    "sg:city":"Elkhart",
    "sg:classifiers":[
        {
            "category":"Real Estate",
            "subcategory":"Real Estate Agent",
            "type":"Services"
        }
    ],
    "sg:phone":"+1 574 293 8959",
    "sg:postcode":"46517",
    "sg:province":"IN",
    "sg:tags":[
        "investment"
    ],
    "wof:name":"C-L Building & Leasing Inc",
    "wof:placetype":"venue"
},
  "geometry": {"coordinates":[-86.015888,41.623195],"type":"Point"}
}