{
  "type": "Feature",
  "properties": {
    "addr:full":"5505 Bull Rapids Rd Woodburn IN 46797",
    "addr:housenumber":"5505",
    "addr:postcode":"46797",
    "addr:street":"Bull Rapids Rd",
    "iso:country":"US",
    "sg:address":"5505 Bull Rapids Rd",
    "sg:city":"Woodburn",
    "sg:phone":"+1 260 632 5505",
    "sg:postcode":"46797",
    "sg:province":"IN",
    "sg:tags":[
        "farm",
        "grain",
        "cash"
    ],
    "wof:name":"Roger Hadley II",
    "wof:placetype":"venue"
},
  "geometry": {"coordinates":[-84.86292899999999,41.138394],"type":"Point"}
}