{
  "type": "Feature",
  "properties": {
    "iso:country":"US",
    "sg:address":"3031 N Old State Road 37",
    "sg:city":"Bloomington",
    "sg:classifiers":[
        {
            "category":"Government",
            "subcategory":"Office",
            "type":"Public Place"
        }
    ],
    "sg:phone":"+1 812 334 9744",
    "sg:postcode":"47404",
    "sg:province":"IN",
    "sg:tags":[
        "village"
    ],
    "wof:name":"Lower Cascade Ballfield",
    "wof:placetype":"venue"
},
  "geometry": {"coordinates":[-86.534082,39.189398],"type":"Point"}
}