{
  "type": "Feature",
  "properties": {
    "iso:country":"US",
    "sg:address":"5250 N Co Rd 100 W",
    "sg:city":"Orleans",
    "sg:classifiers":[
        {
            "category":"Retail",
            "subcategory":"Animal Services",
            "type":"Services"
        }
    ],
    "sg:phone":"+1 812 865 3757",
    "sg:postcode":"47452",
    "sg:province":"IN",
    "wof:name":"Pridemore Jarod",
    "wof:placetype":"venue"
},
  "geometry": {"coordinates":[-86.47760700000001,38.630099],"type":"Point"}
}