{
  "type": "Feature",
  "properties": {
    "iso:country":"US",
    "sg:address":"502 E Hosler Rd",
    "sg:city":"Huntington",
    "sg:classifiers":[
        {
            "category":"Wholesale",
            "subcategory":"Chemicals & Plastics",
            "type":"Manufacturing & Wholesale Goods"
        }
    ],
    "sg:phone":"+1 260 356 7191",
    "sg:postcode":"46750",
    "sg:province":"IN",
    "sg:tags":[
        "ammonia"
    ],
    "wof:name":"Koch Nitrogen Co",
    "wof:placetype":"venue"
},
  "geometry": {"coordinates":[-85.451863,40.88724],"type":"Point"}
}