{
  "type": "Feature",
  "properties": {
    "iso:country":"US",
    "sg:address":"704 W 700 N",
    "sg:city":"Hobart",
    "sg:classifiers":[
        {
            "category":"Organizations",
            "subcategory":"Religious Organization",
            "type":"Services"
        }
    ],
    "sg:phone":"+1 219 759 5200",
    "sg:postcode":"46342",
    "sg:province":"IN",
    "sg:tags":[
        "church"
    ],
    "wof:name":"Central Baptist Church",
    "wof:placetype":"venue"
},
  "geometry": {"coordinates":[-87.202521,41.536017],"type":"Point"}
}