{
  "type": "Feature",
  "properties": {
    "iso:country":"US",
    "sg:address":"23 W Riley St",
    "sg:city":"Medora",
    "sg:classifiers":[
        {
            "category":"Retail",
            "subcategory":"Funeral Services",
            "type":"Services"
        }
    ],
    "sg:phone":"+1 812 966 2681",
    "sg:postcode":"47260",
    "sg:province":"IN",
    "sg:tags":[
        "director"
    ],
    "wof:name":"Hague Funeral Home",
    "wof:placetype":"venue"
},
  "geometry": {"coordinates":[-86.170441,38.824043],"type":"Point"}
}