{
  "type": "Feature",
  "properties": {
    "addr:full":"10131 S Edison Pl Terre Haute IN 47802",
    "addr:housenumber":"10131",
    "addr:postcode":"47802",
    "addr:street":"S Edison Pl",
    "iso:country":"US",
    "sg:address":"10131 S Edison Pl",
    "sg:city":"Terre Haute",
    "sg:classifiers":[
        {
            "category":"Building & Trades",
            "subcategory":"Construction",
            "type":"Services"
        }
    ],
    "sg:phone":"+1 812 299 4083",
    "sg:postcode":"47802",
    "sg:province":"IN",
    "sg:tags":[
        "contractor"
    ],
    "wof:name":"Town & Country Glass Inc",
    "wof:placetype":"venue"
},
  "geometry": {"coordinates":[-87.46965,39.344352],"type":"Point"}
}