{
  "type": "Feature",
  "properties": {
    "addr:full":"71593 Co Rd 100 Nappanee IN 46550",
    "addr:housenumber":"71593",
    "addr:postcode":"46550",
    "addr:street":"Co Rd 100",
    "iso:country":"US",
    "sg:address":"71593 Co Rd 100",
    "sg:city":"Nappanee",
    "sg:phone":"+1 574 773 7355",
    "sg:postcode":"46550",
    "sg:province":"IN",
    "sg:tags":[
        "farm",
        "field",
        "crop"
    ],
    "wof:name":"Myron Netzler",
    "wof:placetype":"venue"
},
  "geometry": {"coordinates":[-86.049733,41.456149],"type":"Point"}
}