{
  "type": "Feature",
  "properties": {
    "iso:country":"US",
    "sg:address":"3484 E 150 S",
    "sg:city":"Hobbs",
    "sg:classifiers":[
        {
            "category":"Government",
            "subcategory":"Post Office",
            "type":"Public Place"
        }
    ],
    "sg:phone":"+1 765 675 2506",
    "sg:postcode":"46047",
    "sg:province":"IN",
    "wof:name":"US Post Office",
    "wof:placetype":"venue"
},
  "geometry": {"coordinates":[-85.947846,40.283472],"type":"Point"}
}