{
  "type": "Feature",
  "properties": {
    "addr:full":"1811 Dogwood Dr Kokomo IN 46902",
    "addr:housenumber":"1811",
    "addr:postcode":"46902",
    "addr:street":"Dogwood Dr",
    "iso:country":"US",
    "sg:address":"1811 Dogwood Dr",
    "sg:city":"Kokomo",
    "sg:classifiers":[
        {
            "category":"Health Services",
            "subcategory":"Doctor",
            "type":"Services"
        }
    ],
    "sg:phone":"+1 765 457 4000",
    "sg:postcode":"46902",
    "sg:province":"IN",
    "sg:tags":[
        "dentist"
    ],
    "wof:name":"Hearn Dental Care",
    "wof:placetype":"venue"
},
  "geometry": {"coordinates":[-86.117953,40.465388],"type":"Point"}
}