{
  "type": "Feature",
  "properties": {
    "iso:country":"US",
    "sg:address":"407 Ridge Ave",
    "sg:city":"Greendale",
    "sg:classifiers":[
        {
            "category":"Real Estate",
            "subcategory":"Real Estate Agent",
            "type":"Services"
        }
    ],
    "sg:phone":"+1 812 539 4663",
    "sg:postcode":"47025",
    "sg:province":"IN",
    "sg:website":"www.century21hometeam.cc",
    "wof:name":"Home Team",
    "wof:placetype":"venue"
},
  "geometry": {"coordinates":[-84.861991,39.106253],"type":"Point"}
}