{
  "type": "Feature",
  "properties": {
    "addr:full":"1058 Indianapolis Rd Greencastle IN 46135",
    "addr:housenumber":"1058",
    "addr:postcode":"46135",
    "addr:street":"Indianapolis Rd",
    "iso:country":"US",
    "sg:address":"1058 Indianapolis Rd",
    "sg:city":"Greencastle",
    "sg:classifiers":[
        {
            "category":"Restaurant",
            "type":"Food & Drink"
        }
    ],
    "sg:phone":"+1 765 653 4302",
    "sg:postcode":"46135",
    "sg:province":"IN",
    "wof:name":"Double Decker Drive In",
    "wof:placetype":"venue"
},
  "geometry": {"coordinates":[-86.83798,39.646182],"type":"Point"}
}