{
  "type": "Feature",
  "properties": {
    "iso:country":"US",
    "sg:address":"6963 Hillsdale Ct",
    "sg:city":"Indianapolis",
    "sg:classifiers":[
        {
            "category":"Insurance",
            "subcategory":"Insurance Agent",
            "type":"Services"
        }
    ],
    "sg:phone":"+1 317 915 8888",
    "sg:postcode":"46250",
    "sg:province":"IN",
    "sg:tags":[
        "adjuster"
    ],
    "sg:website":"www.ncagroup.com",
    "wof:name":"NCA Inc",
    "wof:placetype":"venue"
},
  "geometry": {"coordinates":[-86.04696199999999,39.896088],"type":"Point"}
}