{
  "type": "Feature",
  "properties": {
    "addr:full":"4233 Gateway Blvd Newburgh IN 47630",
    "addr:housenumber":"4233",
    "addr:postcode":"47630",
    "addr:street":"Gateway Blvd",
    "iso:country":"US",
    "sg:address":"4233 Gateway Blvd",
    "sg:city":"Newburgh",
    "sg:classifiers":[
        {
            "category":"Health Services",
            "subcategory":"Doctor",
            "type":"Services"
        }
    ],
    "sg:phone":"+1 812 426 9510",
    "sg:postcode":"47630",
    "sg:province":"IN",
    "wof:name":"Shelton Bruce MD",
    "wof:placetype":"venue"
},
  "geometry": {"coordinates":[-87.441913,37.97366],"type":"Point"}
}