{
  "type": "Feature",
  "properties": {
    "iso:country":"US",
    "sg:address":"3025 N Oakwood Ave",
    "sg:city":"Muncie",
    "sg:classifiers":[
        {
            "category":"Health Services",
            "subcategory":"Doctor",
            "type":"Services"
        }
    ],
    "sg:phone":"+1 765 286 0862",
    "sg:postcode":"47304",
    "sg:province":"IN",
    "sg:tags":[
        "clinic"
    ],
    "sg:website":"www.ushealthworks.com",
    "wof:name":"U S Health Works",
    "wof:placetype":"venue"
},
  "geometry": {"coordinates":[-85.409678,40.217627],"type":"Point"}
}