{
  "type": "Feature",
  "properties": {
    "iso:country":"US",
    "sg:address":"2001 W Washington St",
    "sg:city":"Indianapolis",
    "sg:classifiers":[
        {
            "category":"Shopping",
            "subcategory":"Music",
            "type":"Retail Goods"
        }
    ],
    "sg:phone":"+1 317 955 9330",
    "sg:postcode":"46222",
    "sg:province":"IN",
    "sg:tags":[
        "compact",
        "record",
        "disc",
        "tape"
    ],
    "wof:name":"Gonzalez Records Of Ny Inc",
    "wof:placetype":"venue"
},
  "geometry": {"coordinates":[-86.196901,39.766239],"type":"Point"}
}