{
  "type": "Feature",
  "properties": {
    "iso:country":"US",
    "sg:address":"7101 Broadway",
    "sg:city":"Merrillville",
    "sg:classifiers":[
        {
            "category":"Restaurant",
            "type":"Food & Drink"
        }
    ],
    "sg:phone":"+1 219 736 0325",
    "sg:postcode":"46410",
    "sg:province":"IN",
    "sg:tags":[
        "eating"
    ],
    "wof:name":"Seventy First Street Cafe",
    "wof:placetype":"venue"
},
  "geometry": {"coordinates":[-87.335954,41.489939],"type":"Point"}
}