{
  "type": "Feature",
  "properties": {
    "iso:country":"US",
    "sg:address":"1316 S 5th St",
    "sg:city":"Lafayette",
    "sg:classifiers":[
        {
            "category":"Freight",
            "type":"Transportation"
        }
    ],
    "sg:phone":"+1 765 477 1670",
    "sg:postcode":"47905",
    "sg:province":"IN",
    "sg:tags":[
        "operator",
        "local",
        "trucking"
    ],
    "wof:name":"Tnm Delivery Inc",
    "wof:placetype":"venue"
},
  "geometry": {"coordinates":[-86.89175899999999,40.403588],"type":"Point"}
}