{
  "type": "Feature",
  "properties": {
    "iso:country":"US",
    "sg:address":"2802 Glenwood Ave",
    "sg:city":"Fort Wayne",
    "sg:classifiers":[
        {
            "category":"Building & Trades",
            "subcategory":"Construction",
            "type":"Services"
        }
    ],
    "sg:phone":"+1 260 471 2815",
    "sg:postcode":"46805",
    "sg:province":"IN",
    "sg:tags":[
        "contractor"
    ],
    "wof:name":"Phase One Construction",
    "wof:placetype":"venue"
},
  "geometry": {"coordinates":[-85.101526,41.103637],"type":"Point"}
}