{
  "type": "Feature",
  "properties": {
    "iso:country":"US",
    "sg:address":"1955 W Kelley Rd",
    "sg:city":"Boonville",
    "sg:classifiers":[
        {
            "category":"Shopping",
            "subcategory":"Gifts & Souvenirs",
            "type":"Retail Goods"
        }
    ],
    "sg:phone":"+1 812 897 1689",
    "sg:postcode":"47601",
    "sg:province":"IN",
    "wof:name":"K & K Ceramics",
    "wof:placetype":"venue"
},
  "geometry": {"coordinates":[-87.272094,38.12023],"type":"Point"}
}