{
  "type": "Feature",
  "properties": {
    "iso:country":"US",
    "sg:address":"3000 Kent Ave",
    "sg:city":"West Lafayette",
    "sg:classifiers":[
        {
            "category":"Professional",
            "subcategory":"Management & Consulting",
            "type":"Services"
        }
    ],
    "sg:phone":"+1 765 775 2105",
    "sg:postcode":"47906",
    "sg:province":"IN",
    "sg:tags":[
        "consultant"
    ],
    "wof:name":"Westech Consulting Group",
    "wof:placetype":"venue"
},
  "geometry": {"coordinates":[-86.930418,40.462668],"type":"Point"}
}