{
  "type": "Feature",
  "properties": {
    "iso:country":"US",
    "sg:address":"109 E Washington St",
    "sg:city":"North Webster",
    "sg:classifiers":[
        {
            "category":"Personal",
            "subcategory":"Beauty Salon",
            "type":"Services"
        }
    ],
    "sg:phone":"+1 574 834 2922",
    "sg:postcode":"46555",
    "sg:province":"IN",
    "wof:name":"Princess Parlor",
    "wof:placetype":"venue"
},
  "geometry": {"coordinates":[-85.697378,41.325598],"type":"Point"}
}