{
  "type": "Feature",
  "properties": {
    "iso:country":"US",
    "sg:address":"13910 Spring Hollow Rd",
    "sg:city":"Fort Wayne",
    "sg:classifiers":[
        {
            "category":"Banks & Credit Unions",
            "subcategory":"Financial Services",
            "type":"Services"
        }
    ],
    "sg:phone":"+1 260 672 8023",
    "sg:postcode":"46814",
    "sg:province":"IN",
    "sg:tags":[
        "trust",
        "nonprofit",
        "management"
    ],
    "wof:name":"Dyer Family Foundation Inc",
    "wof:placetype":"venue"
},
  "geometry": {"coordinates":[-85.322578,41.030237],"type":"Point"}
}