{
  "type": "Feature",
  "properties": {
    "iso:country":"US",
    "sg:address":"4722 Century Plaza Rd",
    "sg:city":"Indianapolis",
    "sg:classifiers":[
        {
            "category":"Personal",
            "subcategory":"Beauty Salon",
            "type":"Services"
        }
    ],
    "sg:phone":"+1 317 297 9875",
    "sg:postcode":"46254",
    "sg:province":"IN",
    "wof:name":"Snazee Hair Salon",
    "wof:placetype":"venue"
},
  "geometry": {"coordinates":[-86.243028,39.83571],"type":"Point"}
}