{
  "type": "Feature",
  "properties": {
    "iso:country":"US",
    "sg:address":"330 E McGalliard Rd",
    "sg:city":"Muncie",
    "sg:classifiers":[
        {
            "category":"Banks & Credit Unions",
            "subcategory":"Bank",
            "type":"Services"
        }
    ],
    "sg:phone":"+1 765 284 7781",
    "sg:postcode":"47303",
    "sg:province":"IN",
    "sg:tags":[
        "financing"
    ],
    "wof:name":"American General Finance Inc",
    "wof:placetype":"venue"
},
  "geometry": {"coordinates":[-85.383374,40.219085],"type":"Point"}
}