{
  "type": "Feature",
  "properties": {
    "iso:country":"US",
    "sg:address":"551 State Rd 46 E",
    "sg:city":"Nashville",
    "sg:classifiers":[
        {
            "category":"Travel",
            "subcategory":"Hotels & Motels",
            "type":"Entertainment"
        }
    ],
    "sg:phone":"+1 812 988 1149",
    "sg:postcode":"47448",
    "sg:province":"IN",
    "wof:name":"Salt Creek Inn Inc",
    "wof:placetype":"venue"
},
  "geometry": {"coordinates":[-86.245684,39.202887],"type":"Point"}
}