{
  "type": "Feature",
  "properties": {
    "iso:country":"US",
    "sg:address":"3181 N High School Rd",
    "sg:city":"Indianapolis",
    "sg:classifiers":[
        {
            "category":"Personal",
            "subcategory":"Beauty Salon",
            "type":"Services"
        }
    ],
    "sg:phone":"+1 317 290 9727",
    "sg:postcode":"46224",
    "sg:province":"IN",
    "sg:tags":[
        "body",
        "wrap"
    ],
    "wof:name":"Lady Di's Inc",
    "wof:placetype":"venue"
},
  "geometry": {"coordinates":[-86.269966,39.810753],"type":"Point"}
}