{
  "type": "Feature",
  "properties": {
    "iso:country":"US",
    "sg:address":"6457 E 82nd St",
    "sg:city":"Indianapolis",
    "sg:classifiers":[
        {
            "category":"Shopping",
            "subcategory":"Bicycles & Sporting Goods",
            "type":"Retail Goods"
        }
    ],
    "sg:phone":"+1 317 577 5966",
    "sg:postcode":"46250",
    "sg:province":"IN",
    "sg:tags":[
        "equipment",
        "playground"
    ],
    "sg:website":"www.hoosierhoops.com",
    "wof:name":"Hoosier Hoops & Swings",
    "wof:placetype":"venue"
},
  "geometry": {"coordinates":[-86.05511,39.905255],"type":"Point"}
}