{
  "type": "Feature",
  "properties": {
    "iso:country":"US",
    "sg:address":"1800 N Fruitridge Ave",
    "sg:city":"Terre Haute",
    "sg:classifiers":[
        {
            "category":"Manufacturing",
            "subcategory":"Electronics",
            "type":"Manufacturing & Wholesale Goods"
        }
    ],
    "sg:phone":"+1 812 462 8100",
    "sg:postcode":"47804",
    "sg:province":"IN",
    "sg:tags":[
        "video",
        "disc",
        "tape"
    ],
    "wof:name":"Digital Audio Disc Corp",
    "wof:placetype":"venue"
},
  "geometry": {"coordinates":[-87.36019,39.503206],"type":"Point"}
}