{
  "type": "Feature",
  "properties": {
    "iso:country":"US",
    "sg:address":"111 S Range Line Rd",
    "sg:city":"Carmel",
    "sg:classifiers":[
        {
            "category":"Shopping",
            "subcategory":"Used Merchandise",
            "type":"Retail Goods"
        }
    ],
    "sg:phone":"+1 317 848 2308",
    "sg:postcode":"46032",
    "sg:province":"IN",
    "sg:tags":[
        "furniture"
    ],
    "wof:name":"Favorite Finds Inc",
    "wof:placetype":"venue"
},
  "geometry": {"coordinates":[-86.126987,39.976749],"type":"Point"}
}