{
  "type": "Feature",
  "properties": {
    "iso:country":"US",
    "sg:address":"4937 E Co Rd 400 S",
    "sg:city":"Connersville",
    "sg:classifiers":[
        {
            "category":"Freight",
            "type":"Transportation"
        }
    ],
    "sg:phone":"+1 765 827 4666",
    "sg:postcode":"47331",
    "sg:province":"IN",
    "sg:tags":[
        "trucking"
    ],
    "wof:name":"Whitaker Trucking",
    "wof:placetype":"venue"
},
  "geometry": {"coordinates":[-85.046892,39.583854],"type":"Point"}
}