{
  "type": "Feature",
  "properties": {
    "addr:full":"628 E 9th St Rochester IN 46975",
    "addr:housenumber":"628",
    "addr:postcode":"46975",
    "addr:street":"E 9Th St",
    "iso:country":"US",
    "sg:address":"628 E 9th St",
    "sg:city":"Rochester",
    "sg:classifiers":[
        {
            "category":"Retail",
            "subcategory":"Car Wash",
            "type":"Services"
        }
    ],
    "sg:phone":"+1 574 224 4929",
    "sg:postcode":"46975",
    "sg:province":"IN",
    "sg:tags":[
        "automobile",
        "detail",
        "clean"
    ],
    "wof:name":"Reflections Auto Polishing",
    "wof:placetype":"venue"
},
  "geometry": {"coordinates":[-86.20845300000001,41.064615],"type":"Point"}
}