{
  "type": "Feature",
  "properties": {
    "iso:country":"US",
    "sg:address":"3305 S 7th St",
    "sg:city":"Terre Haute",
    "sg:classifiers":[
        {
            "category":"Food & Beverages",
            "subcategory":"Liquor & Beverages",
            "type":"Retail Goods"
        }
    ],
    "sg:phone":"+1 812 232 3003",
    "sg:postcode":"47802",
    "sg:province":"IN",
    "wof:name":"Bower's 7th & 70 Liquor",
    "wof:placetype":"venue"
},
  "geometry": {"coordinates":[-87.406877,39.430386],"type":"Point"}
}