{
  "type": "Feature",
  "properties": {
    "iso:country":"US",
    "sg:address":"3044 N 100 W",
    "sg:city":"Winchester",
    "sg:classifiers":[
        {
            "category":"Building & Trades",
            "subcategory":"Plumbing",
            "type":"Services"
        }
    ],
    "sg:phone":"+1 765 584 7295",
    "sg:postcode":"47394",
    "sg:province":"IN",
    "sg:tags":[
        "septic"
    ],
    "wof:name":"Barnes Sewer & Septic Svc",
    "wof:placetype":"venue"
},
  "geometry": {"coordinates":[-84.99491399999999,40.208504],"type":"Point"}
}