{
  "type": "Feature",
  "properties": {
    "iso:country":"US",
    "sg:address":"207 S Shelby St",
    "sg:city":"Salem",
    "sg:classifiers":[
        {
            "category":"Real Estate",
            "subcategory":"Developer",
            "type":"Services"
        }
    ],
    "sg:phone":"+1 812 883 2833",
    "sg:postcode":"47167",
    "sg:province":"IN",
    "sg:tags":[
        "cemetery"
    ],
    "wof:name":"Crown Hill Cemetery",
    "wof:placetype":"venue"
},
  "geometry": {"coordinates":[-86.10741,38.604565],"type":"Point"}
}