{
  "type": "Feature",
  "properties": {
    "addr:full":"2277 Eby Rd Boonville IN 47601",
    "addr:housenumber":"2277",
    "addr:postcode":"47601",
    "addr:street":"Eby Rd",
    "iso:country":"US",
    "sg:address":"2277 Eby Rd",
    "sg:city":"Boonville",
    "sg:classifiers":[
        {
            "category":"Home & Garden",
            "subcategory":"Building Materials",
            "type":"Retail Goods"
        }
    ],
    "sg:phone":"+1 812 897 1201",
    "sg:postcode":"47601",
    "sg:province":"IN",
    "sg:tags":[
        "mixed",
        "concrete"
    ],
    "wof:name":"Irving Materials Inc",
    "wof:placetype":"venue"
},
  "geometry": {"coordinates":[-87.264578,38.072964],"type":"Point"}
}