{
  "type": "Feature",
  "properties": {
    "iso:country":"US",
    "sg:address":"2401 N Home St",
    "sg:city":"Mishawaka",
    "sg:classifiers":[
        {
            "category":"Home & Garden",
            "subcategory":"Hardware",
            "type":"Retail Goods"
        }
    ],
    "sg:phone":"+1 574 259 3130",
    "sg:postcode":"46545",
    "sg:province":"IN",
    "sg:tags":[
        "tool",
        "used"
    ],
    "wof:name":"Spartan Tool LLC",
    "wof:placetype":"venue"
},
  "geometry": {"coordinates":[-86.148297,41.682],"type":"Point"}
}