{
  "type": "Feature",
  "properties": {
    "iso:country":"US",
    "sg:address":"53881 S Bend Dr",
    "sg:city":"South Bend",
    "sg:classifiers":[
        {
            "category":"Professional",
            "subcategory":"Management & Consulting",
            "type":"Services"
        }
    ],
    "sg:phone":"+1 574 287 2783",
    "sg:postcode":"46628",
    "sg:province":"IN",
    "wof:name":"Eg Financial",
    "wof:placetype":"venue"
},
  "geometry": {"coordinates":[-86.372167,41.713893],"type":"Point"}
}