{
  "type": "Feature",
  "properties": {
    "iso:country":"US",
    "sg:address":"2150 State St",
    "sg:city":"New Albany",
    "sg:classifiers":[
        {
            "category":"Banks & Credit Unions",
            "subcategory":"Bank",
            "type":"Services"
        }
    ],
    "sg:phone":"+1 812 948 4474",
    "sg:postcode":"47150",
    "sg:province":"IN",
    "wof:name":"National City Bank",
    "wof:placetype":"venue"
},
  "geometry": {"coordinates":[-85.839018,38.304275],"type":"Point"}
}