{
  "type": "Feature",
  "properties": {
    "addr:full":"4906 E 580 S Wolcottville IN 46795",
    "addr:housenumber":"4906",
    "addr:postcode":"46795",
    "addr:street":"E 580 S",
    "iso:country":"US",
    "sg:address":"4906 E 580 S",
    "sg:city":"Wolcottville",
    "sg:classifiers":[
        {
            "category":"Professional",
            "subcategory":"Engineering",
            "type":"Services"
        }
    ],
    "sg:phone":"+1 260 854 3940",
    "sg:postcode":"46795",
    "sg:province":"IN",
    "sg:tags":[
        "engineer"
    ],
    "wof:name":"Ellis Environmental Group",
    "wof:placetype":"venue"
},
  "geometry": {"coordinates":[-85.327923,41.559607],"type":"Point"}
}