{
  "type": "Feature",
  "properties": {
    "iso:country":"US",
    "sg:address":"109 E Black Ln",
    "sg:city":"Royal Center",
    "sg:classifiers":[
        {
            "category":"Education",
            "subcategory":"School",
            "type":"Public Place"
        }
    ],
    "sg:phone":"+1 574 643 2255",
    "sg:postcode":"46978",
    "sg:province":"IN",
    "wof:name":"Pioneer Elementary School",
    "wof:placetype":"venue"
},
  "geometry": {"coordinates":[-86.50236700000001,40.866882],"type":"Point"}
}