{
  "type": "Feature",
  "properties": {
    "iso:country":"US",
    "sg:address":"235 E McKinley Ave",
    "sg:city":"Mishawaka",
    "sg:classifiers":[
        {
            "category":"Professional",
            "type":"Services"
        }
    ],
    "sg:phone":"+1 574 255 5511",
    "sg:postcode":"46545",
    "sg:province":"IN",
    "sg:tags":[
        "establishment"
    ],
    "wof:name":"Stefanie Ross Agency",
    "wof:placetype":"venue"
},
  "geometry": {"coordinates":[-86.178335,41.680363],"type":"Point"}
}