{
  "type": "Feature",
  "properties": {
    "iso:country":"US",
    "sg:address":"100 E Sycamore St",
    "sg:city":"Evansville",
    "sg:classifiers":[
        {
            "category":"Government",
            "subcategory":"Office",
            "type":"Public Place"
        }
    ],
    "sg:phone":"+1 812 425 2124",
    "sg:postcode":"47713",
    "sg:province":"IN",
    "wof:name":"Vanderburgh Cnty Child Prtctn",
    "wof:placetype":"venue"
},
  "geometry": {"coordinates":[-87.561292,37.975556],"type":"Point"}
}