{
  "type": "Feature",
  "properties": {
    "iso:country":"US",
    "sg:address":"4280 State Rd 67",
    "sg:city":"Martinsville",
    "sg:classifiers":[
        {
            "category":"Freight",
            "type":"Transportation"
        }
    ],
    "sg:phone":"+1 765 349 1599",
    "sg:postcode":"46151",
    "sg:province":"IN",
    "sg:tags":[
        "commercial",
        "storage"
    ],
    "wof:name":"R & S Leisure Enterprises",
    "wof:placetype":"venue"
},
  "geometry": {"coordinates":[-86.417872,39.508464],"type":"Point"}
}