{
  "type": "Feature",
  "properties": {
    "iso:country":"US",
    "sg:address":"3616 S Calhoun St",
    "sg:city":"Fort Wayne",
    "sg:classifiers":[
        {
            "category":"Personal",
            "subcategory":"Beauty Salon",
            "type":"Services"
        }
    ],
    "sg:phone":"+1 260 456 9599",
    "sg:postcode":"46807",
    "sg:province":"IN",
    "wof:name":"Modern Hair Design",
    "wof:placetype":"venue"
},
  "geometry": {"coordinates":[-85.13754400000001,41.05274],"type":"Point"}
}