{
  "type": "Feature",
  "properties": {
    "addr:full":"2109 Southlake Mall Merrillville IN 46410",
    "addr:housenumber":"2109",
    "addr:postcode":"46410",
    "addr:street":"Southlake Mall",
    "iso:country":"US",
    "sg:address":"2109 Southlake Mall",
    "sg:city":"Merrillville",
    "sg:classifiers":[
        {
            "category":"Restaurant",
            "type":"Food & Drink"
        }
    ],
    "sg:menulink":"http://www.allmenus.com/in/ross/240265-panda-express/menu/",
    "sg:phone":"+1 219 756 7834",
    "sg:postcode":"46410",
    "sg:province":"IN",
    "sg:tags":[
        "asian",
        "chinese"
    ],
    "wof:name":"Panda Express",
    "wof:placetype":"venue"
},
  "geometry": {"coordinates":[-87.30610799999999,41.468893],"type":"Point"}
}