{
  "type": "Feature",
  "properties": {
    "iso:country":"US",
    "sg:address":"275 Fort Wayne Ave",
    "sg:city":"Richmond",
    "sg:classifiers":[
        {
            "category":"Utilities",
            "subcategory":"Refuse",
            "type":"Services"
        }
    ],
    "sg:phone":"+1 765 935 0559",
    "sg:postcode":"47374",
    "sg:province":"IN",
    "sg:tags":[
        "disposal",
        "waste"
    ],
    "wof:name":"Rumpke",
    "wof:placetype":"venue"
},
  "geometry": {"coordinates":[-84.892049,39.833886],"type":"Point"}
}