{
  "type": "Feature",
  "properties": {
    "iso:country":"US",
    "sg:address":"10070 Stonybrook Cir B",
    "sg:city":"Indianapolis",
    "sg:classifiers":[
        {
            "category":"Wholesale",
            "subcategory":"Machinery & Supplies",
            "type":"Manufacturing & Wholesale Goods"
        }
    ],
    "sg:phone":"+1 317 891 0711",
    "sg:postcode":"46229",
    "sg:province":"IN",
    "sg:tags":[
        "equipment",
        "industrial"
    ],
    "wof:name":"Indy Equipment Express",
    "wof:placetype":"venue"
},
  "geometry": {"coordinates":[-85.98853099999999,39.783822],"type":"Point"}
}