{
  "type": "Feature",
  "properties": {
    "iso:country":"US",
    "sg:address":"7933 E 30th St",
    "sg:city":"Indianapolis",
    "sg:classifiers":[
        {
            "category":"Retail",
            "subcategory":"Laundry & Dry Cleaning",
            "type":"Services"
        }
    ],
    "sg:phone":"+1 317 897 6700",
    "sg:postcode":"46219",
    "sg:province":"IN",
    "sg:tags":[
        "cleaners"
    ],
    "wof:name":"Malone & Sons One Hour Cleaner",
    "wof:placetype":"venue"
},
  "geometry": {"coordinates":[-86.02842,39.811018],"type":"Point"}
}