{
  "type": "Feature",
  "properties": {
    "iso:country":"US",
    "sg:address":"6301 S Bell Ln",
    "sg:city":"Yorktown",
    "sg:classifiers":[
        {
            "category":"Professional",
            "type":"Services"
        }
    ],
    "sg:phone":"+1 765 759 9021",
    "sg:postcode":"47396",
    "sg:province":"IN",
    "wof:name":"Wanda Snider",
    "wof:placetype":"venue"
},
  "geometry": {"coordinates":[-85.463007,40.136231],"type":"Point"}
}