{
  "type": "Feature",
  "properties": {
    "iso:country":"US",
    "sg:address":"4919 W US Hwy 36",
    "sg:city":"Greencastle",
    "sg:classifiers":[
        {
            "category":"Shopping",
            "subcategory":"Bicycles & Sporting Goods",
            "type":"Retail Goods"
        }
    ],
    "sg:phone":"+1 765 739 6566",
    "sg:postcode":"46135",
    "sg:province":"IN",
    "sg:tags":[
        "bait",
        "fishing"
    ],
    "wof:name":"Morton Hook & Sinker Bait Shop",
    "wof:placetype":"venue"
},
  "geometry": {"coordinates":[-86.937608,39.763123],"type":"Point"}
}