{
  "type": "Feature",
  "properties": {
    "iso:country":"US",
    "sg:address":"755 E Main St",
    "sg:city":"Greenwood",
    "sg:classifiers":[
        {
            "category":"Insurance",
            "subcategory":"Insurance Agent",
            "type":"Services"
        }
    ],
    "sg:phone":"+1 317 889 2578",
    "sg:postcode":"46143",
    "sg:province":"IN",
    "wof:name":"Tim Warren Insurance",
    "wof:placetype":"venue"
},
  "geometry": {"coordinates":[-86.091013,39.614028],"type":"Point"}
}