{
  "type": "Feature",
  "properties": {
    "iso:country":"US",
    "sg:address":"8951 N Middlefork Rd",
    "sg:city":"Dupont",
    "sg:classifiers":[
        {
            "category":"Shopping",
            "subcategory":"Gifts & Souvenirs",
            "type":"Retail Goods"
        }
    ],
    "sg:phone":"+1 812 873 8396",
    "sg:postcode":"47231",
    "sg:province":"IN",
    "wof:name":"Zannis",
    "wof:placetype":"venue"
},
  "geometry": {"coordinates":[-85.490907,38.858182],"type":"Point"}
}