{
  "type": "Feature",
  "properties": {
    "iso:country":"US",
    "sg:address":"24158 Hilltop Rd",
    "sg:city":"Oldenburg",
    "sg:classifiers":[
        {
            "category":"Building & Trades",
            "subcategory":"Construction",
            "type":"Services"
        }
    ],
    "sg:phone":"+1 812 934 5358",
    "sg:postcode":"47036",
    "sg:province":"IN",
    "sg:tags":[
        "excavating",
        "contractor"
    ],
    "wof:name":"Leising Excavating",
    "wof:placetype":"venue"
},
  "geometry": {"coordinates":[-85.228884,39.392014],"type":"Point"}
}