{
  "type": "Feature",
  "properties": {
    "iso:country":"US",
    "sg:address":"52304 Dorchester Ct",
    "sg:city":"Granger",
    "sg:classifiers":[
        {
            "category":"Banks & Credit Unions",
            "subcategory":"Bank",
            "type":"Services"
        }
    ],
    "sg:phone":"+1 574 360 4700",
    "sg:postcode":"46530",
    "sg:province":"IN",
    "sg:tags":[
        "financing"
    ],
    "wof:name":"Harper Financial Svc Inc",
    "wof:placetype":"venue"
},
  "geometry": {"coordinates":[-86.173103,41.735444],"type":"Point"}
}