{
  "type": "Feature",
  "properties": {
    "iso:country":"US",
    "sg:address":"11551 State Rd 49",
    "sg:city":"Wheatfield",
    "sg:classifiers":[
        {
            "category":"Freight",
            "type":"Transportation"
        }
    ],
    "sg:phone":"+1 219 956 3964",
    "sg:postcode":"46392",
    "sg:province":"IN",
    "sg:tags":[
        "trucking"
    ],
    "wof:name":"ATM Trucking Inc",
    "wof:placetype":"venue"
},
  "geometry": {"coordinates":[-87.045289,41.174237],"type":"Point"}
}