{
  "type": "Feature",
  "properties": {
    "addr:full":"11846 Allisonville Rd Fishers IN 46038",
    "addr:housenumber":"11846",
    "addr:postcode":"46038",
    "addr:street":"Allisonville Rd",
    "iso:country":"US",
    "sg:address":"11846 Allisonville Rd",
    "sg:city":"Fishers",
    "sg:classifiers":[
        {
            "category":"Shopping",
            "subcategory":"Discount & Variety Stores",
            "type":"Retail Goods"
        }
    ],
    "sg:phone":"+1 317 579 0566",
    "sg:postcode":"46038",
    "sg:province":"IN",
    "wof:name":"Dollar Deals LLC",
    "wof:placetype":"venue"
},
  "geometry": {"coordinates":[-86.038933,39.96025],"type":"Point"}
}