{
  "type": "Feature",
  "properties": {
    "iso:country":"US",
    "sg:address":"2809 N Franklin Rd",
    "sg:city":"Indianapolis",
    "sg:classifiers":[
        {
            "category":"Restaurant",
            "type":"Food & Drink"
        }
    ],
    "sg:phone":"+1 317 897 3905",
    "sg:postcode":"46219",
    "sg:province":"IN",
    "wof:name":"O B's Pizza Palace",
    "wof:placetype":"venue"
},
  "geometry": {"coordinates":[-86.026679,39.810121],"type":"Point"}
}