{
  "type": "Feature",
  "properties": {
    "iso:country":"US",
    "sg:address":"515 E Jackson Blvd",
    "sg:city":"Elkhart",
    "sg:classifiers":[
        {
            "category":"Retail",
            "subcategory":"Auto Repair",
            "type":"Services"
        }
    ],
    "sg:phone":"+1 574 293 8711",
    "sg:postcode":"46516",
    "sg:province":"IN",
    "sg:tags":[
        "automobile",
        "top",
        "upholstery"
    ],
    "wof:name":"Dygert's Trim & Glass",
    "wof:placetype":"venue"
},
  "geometry": {"coordinates":[-85.966891,41.68911],"type":"Point"}
}