{
  "type": "Feature",
  "properties": {
    "iso:country":"US",
    "sg:address":"659 Covered Wagon Trl",
    "sg:city":"Valparaiso",
    "sg:classifiers":[
        {
            "category":"Wholesale",
            "subcategory":"Machinery & Supplies",
            "type":"Manufacturing & Wholesale Goods"
        }
    ],
    "sg:phone":"+1 219 548 5744",
    "sg:postcode":"46383",
    "sg:province":"IN",
    "sg:tags":[
        "equipment",
        "industrial"
    ],
    "wof:name":"Universal Instruments",
    "wof:placetype":"venue"
},
  "geometry": {"coordinates":[-87.01834599999999,41.529085],"type":"Point"}
}