{
  "type": "Feature",
  "properties": {
    "iso:country":"US",
    "sg:address":"1600 E Monroe St",
    "sg:city":"Goshen",
    "sg:classifiers":[
        {
            "category":"Building & Trades",
            "subcategory":"Construction",
            "type":"Services"
        }
    ],
    "sg:phone":"+1 574 533 0380",
    "sg:postcode":"46528",
    "sg:province":"IN",
    "sg:tags":[
        "home",
        "builder"
    ],
    "wof:name":"Richard Miller Constr Inc",
    "wof:placetype":"venue"
},
  "geometry": {"coordinates":[-85.810018,41.580635],"type":"Point"}
}