{
  "type": "Feature",
  "properties": {
    "iso:country":"US",
    "sg:address":"3008 Sieveking Rd",
    "sg:city":"New Albany",
    "sg:classifiers":[
        {
            "category":"Retail",
            "subcategory":"Repair Shop",
            "type":"Services"
        }
    ],
    "sg:phone":"+1 812 945 9454",
    "sg:postcode":"47150",
    "sg:province":"IN",
    "sg:tags":[
        "welding"
    ],
    "wof:name":"Allens Specialty's Inc",
    "wof:placetype":"venue"
},
  "geometry": {"coordinates":[-85.84181,38.323849],"type":"Point"}
}