{
  "type": "Feature",
  "properties": {
    "iso:country":"US",
    "sg:address":"1902 S East St",
    "sg:city":"Indianapolis",
    "sg:classifiers":[
        {
            "category":"Utilities",
            "subcategory":"Telephone",
            "type":"Services"
        }
    ],
    "sg:phone":"+1 317 951 2275",
    "sg:postcode":"46225",
    "sg:province":"IN",
    "sg:tags":[
        "company"
    ],
    "wof:name":"Qwest Communications",
    "wof:placetype":"venue"
},
  "geometry": {"coordinates":[-86.149488,39.741643],"type":"Point"}
}