{
  "type": "Feature",
  "properties": {
    "iso:country":"US",
    "sg:address":"1659 Mishawaka St",
    "sg:city":"Elkhart",
    "sg:classifiers":[
        {
            "category":"Banks & Credit Unions",
            "subcategory":"Investment Brokerage",
            "type":"Services"
        }
    ],
    "sg:phone":"+1 574 264 2111",
    "sg:postcode":"46514",
    "sg:province":"IN",
    "sg:tags":[
        "advisory",
        "financial"
    ],
    "wof:name":"Crittson Financial Corp",
    "wof:placetype":"venue"
},
  "geometry": {"coordinates":[-86.00076300000001,41.695292],"type":"Point"}
}