{
  "type": "Feature",
  "properties": {
    "iso:country":"US",
    "sg:address":"5905 Murvihill Rd",
    "sg:city":"Valparaiso",
    "sg:classifiers":[
        {
            "category":"Manufacturing",
            "subcategory":"Printing",
            "type":"Manufacturing & Wholesale Goods"
        }
    ],
    "sg:phone":"+1 219 462 9921",
    "sg:postcode":"46383",
    "sg:province":"IN",
    "sg:tags":[
        "screen"
    ],
    "wof:name":"Elegan Graphics",
    "wof:placetype":"venue"
},
  "geometry": {"coordinates":[-86.9893,41.44902],"type":"Point"}
}