{
  "type": "Feature",
  "properties": {
    "addr:full":"1936 S Lynhurst Dr Indianapolis IN 46241",
    "addr:housenumber":"1936",
    "addr:postcode":"46241",
    "addr:street":"S Lynhurst Dr",
    "iso:country":"US",
    "sg:address":"1936 S Lynhurst Dr",
    "sg:city":"Indianapolis",
    "sg:classifiers":[
        {
            "category":"Wholesale",
            "subcategory":"Medical Equipment & Supplies",
            "type":"Manufacturing & Wholesale Goods"
        },
        {
            "category":"Shopping",
            "subcategory":"Pharmacy",
            "type":"Retail Goods"
        }
    ],
    "sg:phone":"+1 317 487 0758",
    "sg:postcode":"46241",
    "sg:province":"IN",
    "sg:tags":[
        "home",
        "health",
        "care"
    ],
    "wof:name":"National Seating & Mobility",
    "wof:placetype":"venue"
},
  "geometry": {"coordinates":[-86.25023899999999,39.739702],"type":"Point"}
}