{
  "type": "Feature",
  "properties": {
    "iso:country":"US",
    "sg:address":"6125 US Hwy 31",
    "sg:city":"Indianapolis",
    "sg:classifiers":[
        {
            "category":"Professional",
            "subcategory":"Lawyer & Legal Services",
            "type":"Services"
        }
    ],
    "sg:phone":"+1 317 788 4000",
    "sg:postcode":"46227",
    "sg:province":"IN",
    "sg:tags":[
        "attorney"
    ],
    "wof:name":"Lunn & Assoc",
    "wof:placetype":"venue"
},
  "geometry": {"coordinates":[-86.14903200000001,39.676471],"type":"Point"}
}