{
  "type": "Feature",
  "properties": {
    "iso:country":"US",
    "sg:address":"10241 Saint Wendel Rd",
    "sg:city":"Evansville",
    "sg:classifiers":[
        {
            "category":"Building & Trades",
            "subcategory":"Construction",
            "type":"Services"
        }
    ],
    "sg:phone":"+1 812 963 9112",
    "sg:postcode":"47720",
    "sg:province":"IN",
    "sg:tags":[
        "home",
        "builder"
    ],
    "wof:name":"Schapker Construction Co",
    "wof:placetype":"venue"
},
  "geometry": {"coordinates":[-87.650516,38.071906],"type":"Point"}
}