{
  "type": "Feature",
  "properties": {
    "addr:full":"537 Stadium Dr Fort Wayne IN 46805",
    "addr:housenumber":"537",
    "addr:postcode":"46805",
    "addr:street":"Stadium Dr",
    "iso:country":"US",
    "sg:address":"537 Stadium Dr",
    "sg:city":"Fort Wayne",
    "sg:classifiers":[
        {
            "category":"Organizations",
            "subcategory":"Community Association",
            "type":"Services"
        }
    ],
    "sg:phone":"+1 260 482 3052",
    "sg:postcode":"46805",
    "sg:province":"IN",
    "sg:tags":[
        "club"
    ],
    "wof:name":"Sports Car Club Of America",
    "wof:placetype":"venue"
},
  "geometry": {"coordinates":[-85.13297300000001,41.099712],"type":"Point"}
}