{
  "type": "Feature",
  "properties": {
    "iso:country":"US",
    "sg:address":"1519 W Jefferson St",
    "sg:city":"Plymouth",
    "sg:classifiers":[
        {
            "category":"Building & Trades",
            "subcategory":"Construction",
            "type":"Services"
        }
    ],
    "sg:phone":"+1 574 936 4642",
    "sg:postcode":"46563",
    "sg:province":"IN",
    "sg:tags":[
        "tile",
        "dealer"
    ],
    "wof:name":"Beldon Interiors Inc",
    "wof:placetype":"venue"
},
  "geometry": {"coordinates":[-86.327381,41.34242],"type":"Point"}
}