{
  "type": "Feature",
  "properties": {
    "iso:country":"US",
    "sg:address":"2214 Miami Rd",
    "sg:city":"South Bend",
    "sg:classifiers":[
        {
            "category":"Professional",
            "subcategory":"Business Services",
            "type":"Services"
        }
    ],
    "sg:phone":"+1 574 282 4920",
    "sg:postcode":"46613",
    "sg:province":"IN",
    "sg:tags":[
        "paging",
        "answering"
    ],
    "wof:name":"ACCI",
    "wof:placetype":"venue"
},
  "geometry": {"coordinates":[-86.234821,41.652035],"type":"Point"}
}