{
  "type": "Feature",
  "properties": {
    "iso:country":"US",
    "sg:address":"409 W Lexington Ave",
    "sg:city":"Elkhart",
    "sg:classifiers":[
        {
            "category":"Professional",
            "subcategory":"Lawyer & Legal Services",
            "type":"Services"
        }
    ],
    "sg:phone":"+1 574 522 2119",
    "sg:postcode":"46516",
    "sg:province":"IN",
    "sg:tags":[
        "attorney"
    ],
    "wof:name":"Mark W Doty",
    "wof:placetype":"venue"
},
  "geometry": {"coordinates":[-85.978641,41.684633],"type":"Point"}
}