{
  "type": "Feature",
  "properties": {
    "iso:country":"US",
    "sg:address":"8855 S 400 W",
    "sg:city":"Wabash",
    "sg:classifiers":[
        {
            "category":"Professional",
            "subcategory":"Accounting & Tax Preparation",
            "type":"Services"
        }
    ],
    "sg:phone":"+1 260 571 5922",
    "sg:postcode":"46992",
    "sg:province":"IN",
    "sg:tags":[
        "return",
        "filing"
    ],
    "wof:name":"Smt Tax Svc",
    "wof:placetype":"venue"
},
  "geometry": {"coordinates":[-85.865885,40.695259],"type":"Point"}
}