{
  "type": "Feature",
  "properties": {
    "iso:country":"US",
    "sg:address":"411 Watt St",
    "sg:city":"Jeffersonville",
    "sg:classifiers":[
        {
            "category":"Professional",
            "subcategory":"Lawyer & Legal Services",
            "type":"Services"
        }
    ],
    "sg:phone":"+1 812 288 4442",
    "sg:postcode":"47130",
    "sg:province":"IN",
    "sg:tags":[
        "attorney"
    ],
    "wof:name":"Gillenwater Law Offices",
    "wof:placetype":"venue"
},
  "geometry": {"coordinates":[-85.737306,38.276516],"type":"Point"}
}