{
  "type": "Feature",
  "properties": {
    "iso:country":"US",
    "sg:address":"115 E Division St",
    "sg:city":"Remington",
    "sg:classifiers":[
        {
            "category":"Food & Beverages",
            "subcategory":"Groceries & Convenience Stores",
            "type":"Retail Goods"
        }
    ],
    "sg:phone":"+1 219 261 2542",
    "sg:postcode":"47977",
    "sg:province":"IN",
    "sg:tags":[
        "grocer"
    ],
    "wof:name":"Remington Food Market Inc",
    "wof:placetype":"venue"
},
  "geometry": {"coordinates":[-87.148644,40.765797],"type":"Point"}
}