{
  "type": "Feature",
  "properties": {
    "iso:country":"US",
    "sg:address":"201 N Shortridge Rd",
    "sg:city":"Indianapolis",
    "sg:classifiers":[
        {
            "category":"Insurance",
            "subcategory":"Insurance Agent",
            "type":"Services"
        }
    ],
    "sg:phone":"+1 317 356 0951",
    "sg:postcode":"46219",
    "sg:province":"IN",
    "wof:name":"A W Schmadeke Insurance",
    "wof:placetype":"venue"
},
  "geometry": {"coordinates":[-86.040537,39.776162],"type":"Point"}
}