{
  "type": "Feature",
  "properties": {
    "iso:country":"US",
    "sg:address":"5801 N Mason Ln",
    "sg:city":"Martinsville",
    "sg:classifiers":[
        {
            "category":"Organizations",
            "subcategory":"Religious Organization",
            "type":"Services"
        }
    ],
    "sg:phone":"+1 317 831 2365",
    "sg:postcode":"46151",
    "sg:province":"IN",
    "wof:name":"Reorganized Church of LDS",
    "wof:placetype":"venue"
},
  "geometry": {"coordinates":[-86.408837,39.511071],"type":"Point"}
}