{
  "type": "Feature",
  "properties": {
    "iso:country":"US",
    "sg:address":"3015 Co Rd 600 N",
    "sg:city":"Galveston",
    "sg:classifiers":[
        {
            "category":"Professional",
            "type":"Services"
        }
    ],
    "sg:phone":"+1 574 699 6179",
    "sg:postcode":"46932",
    "sg:province":"IN",
    "wof:name":"McDonald Mike Sales Inc",
    "wof:placetype":"venue"
},
  "geometry": {"coordinates":[-86.184847,40.56238],"type":"Point"}
}