{
  "type": "Feature",
  "properties": {
    "iso:country":"US",
    "sg:address":"212 N Elm St",
    "sg:city":"Muncie",
    "sg:classifiers":[
        {
            "category":"Organizations",
            "subcategory":"Religious Organization",
            "type":"Services"
        }
    ],
    "sg:phone":"+1 765 741 8189",
    "sg:postcode":"47305",
    "sg:province":"IN",
    "sg:tags":[
        "church"
    ],
    "wof:name":"Christian Missionary Alliance",
    "wof:placetype":"venue"
},
  "geometry": {"coordinates":[-85.382753,40.195241],"type":"Point"}
}