{
  "type": "Feature",
  "properties": {
    "addr:full":"2401 Hickory Dr Dyer IN 46311",
    "addr:housenumber":"2401",
    "addr:postcode":"46311",
    "addr:street":"Hickory Dr",
    "iso:country":"US",
    "sg:address":"2401 Hickory Dr",
    "sg:city":"Dyer",
    "sg:classifiers":[
        {
            "category":"Wholesale",
            "subcategory":"Construction Materials",
            "type":"Manufacturing & Wholesale Goods"
        }
    ],
    "sg:phone":"+1 219 865 3275",
    "sg:postcode":"46311",
    "sg:province":"IN",
    "sg:tags":[
        "fence"
    ],
    "wof:name":"FWA Decks & Fencing",
    "wof:placetype":"venue"
},
  "geometry": {"coordinates":[-87.509632,41.488264],"type":"Point"}
}