{
  "type": "Feature",
  "properties": {
    "iso:country":"US",
    "sg:address":"201 E Louisiana St",
    "sg:city":"Evansville",
    "sg:classifiers":[
        {
            "category":"Food & Beverages",
            "subcategory":"Groceries & Convenience Stores",
            "type":"Retail Goods"
        }
    ],
    "sg:phone":"+1 812 461 2301",
    "sg:postcode":"47711",
    "sg:province":"IN",
    "wof:name":"Tobacco Road",
    "wof:placetype":"venue"
},
  "geometry": {"coordinates":[-87.558824,37.98838],"type":"Point"}
}