{
  "type": "Feature",
  "properties": {
    "addr:full":"1357 S Randolph St Garrett IN 46738",
    "addr:housenumber":"1357",
    "addr:postcode":"46738",
    "addr:street":"S Randolph St",
    "iso:country":"US",
    "sg:address":"1357 S Randolph St",
    "sg:city":"Garrett",
    "sg:classifiers":[
        {
            "category":"Organizations",
            "subcategory":"Religious Organization",
            "type":"Services"
        }
    ],
    "sg:phone":"+1 260 357 4755",
    "sg:postcode":"46738",
    "sg:province":"IN",
    "wof:name":"First Baptist Church",
    "wof:placetype":"venue"
},
  "geometry": {"coordinates":[-85.13477399999999,41.333235],"type":"Point"}
}