{
  "type": "Feature",
  "properties": {
    "iso:country":"US",
    "sg:address":"1300 S Walnut St",
    "sg:city":"South Bend",
    "sg:classifiers":[
        {
            "category":"Freight",
            "type":"Transportation"
        }
    ],
    "sg:phone":"+1 574 289 9217",
    "sg:postcode":"46619",
    "sg:province":"IN",
    "sg:tags":[
        "trucking"
    ],
    "wof:name":"Yellow Transportation Inc",
    "wof:placetype":"venue"
},
  "geometry": {"coordinates":[-86.270808,41.662945],"type":"Point"}
}