{
  "type": "Feature",
  "properties": {
    "iso:country":"US",
    "sg:address":"2015 S Pennsylvania St",
    "sg:city":"Indianapolis",
    "sg:classifiers":[
        {
            "category":"Wholesale",
            "subcategory":"Scrap",
            "type":"Manufacturing & Wholesale Goods"
        }
    ],
    "sg:phone":"+1 317 780 6100",
    "sg:postcode":"46225",
    "sg:province":"IN",
    "sg:tags":[
        "recycling",
        "center"
    ],
    "wof:name":"Plastic Recycling Inc",
    "wof:placetype":"venue"
},
  "geometry": {"coordinates":[-86.156525,39.739042],"type":"Point"}
}