{
  "type": "Feature",
  "properties": {
    "iso:country":"US",
    "sg:address":"5837 N Lake Road 52 W",
    "sg:city":"Monticello",
    "sg:classifiers":[
        {
            "category":"Autos & Motor Vehicles",
            "subcategory":"Boat Sales",
            "type":"Retail Goods"
        }
    ],
    "sg:phone":"+1 219 253 7901",
    "sg:postcode":"47960",
    "sg:province":"IN",
    "sg:tags":[
        "equipment",
        "marine",
        "supply"
    ],
    "wof:name":"M & B Marine Svc",
    "wof:placetype":"venue"
},
  "geometry": {"coordinates":[-86.777285,40.839006],"type":"Point"}
}