{
  "type": "Feature",
  "properties": {
    "iso:country":"US",
    "sg:address":"4425 US Hwy 20",
    "sg:city":"Lagrange",
    "sg:classifiers":[
        {
            "category":"Shopping",
            "subcategory":"Clothing, Apparel, & Fashions",
            "type":"Retail Goods"
        }
    ],
    "sg:phone":"+1 260 463 4908",
    "sg:postcode":"46761",
    "sg:province":"IN",
    "sg:tags":[
        "salvage",
        "surplus",
        "merchandise"
    ],
    "wof:name":"Shipshewana Surplus",
    "wof:placetype":"venue"
},
  "geometry": {"coordinates":[-85.509969,41.640756],"type":"Point"}
}