{
  "type": "Feature",
  "properties": {
    "addr:full":"120 E Jefferson St Tipton IN 46072",
    "addr:housenumber":"120",
    "addr:postcode":"46072",
    "addr:street":"E Jefferson St",
    "iso:country":"US",
    "sg:address":"120 E Jefferson St",
    "sg:city":"Tipton",
    "sg:classifiers":[
        {
            "category":"Real Estate",
            "subcategory":"Real Estate Agent",
            "type":"Services"
        }
    ],
    "sg:phone":"+1 765 675 2468",
    "sg:postcode":"46072",
    "sg:province":"IN",
    "wof:name":"Tipton Realty Svc",
    "wof:placetype":"venue"
},
  "geometry": {"coordinates":[-86.040921,40.282329],"type":"Point"}
}