{
  "type": "Feature",
  "properties": {
    "iso:country":"US",
    "sg:address":"731 N Monticello St",
    "sg:city":"Winamac",
    "sg:classifiers":[
        {
            "category":"Personal",
            "subcategory":"Beauty Salon",
            "type":"Services"
        }
    ],
    "sg:phone":"+1 574 946 3800",
    "sg:postcode":"46996",
    "sg:province":"IN",
    "wof:name":"Heat Waves",
    "wof:placetype":"venue"
},
  "geometry": {"coordinates":[-86.605419,41.058398],"type":"Point"}
}