{
  "type": "Feature",
  "properties": {
    "iso:country":"US",
    "sg:address":"1540 N Morton St",
    "sg:city":"Franklin",
    "sg:classifiers":[
        {
            "category":"Wholesale",
            "subcategory":"Farm Supplies",
            "type":"Manufacturing & Wholesale Goods"
        }
    ],
    "sg:phone":"+1 317 346 0015",
    "sg:postcode":"46131",
    "sg:province":"IN",
    "sg:website":"www.tsc.com",
    "wof:name":"Tractor Supply Co",
    "wof:placetype":"venue"
},
  "geometry": {"coordinates":[-86.065283,39.494692],"type":"Point"}
}