{
  "type": "Feature",
  "properties": {
    "iso:country":"US",
    "sg:address":"3167 S State Rd 3",
    "sg:city":"New Castle",
    "sg:classifiers":[
        {
            "category":"Restaurant",
            "type":"Food & Drink"
        }
    ],
    "sg:phone":"+1 765 529 6160",
    "sg:postcode":"47362",
    "sg:province":"IN",
    "wof:name":"Mc Donald's",
    "wof:placetype":"venue"
},
  "geometry": {"coordinates":[-85.385784,39.885598],"type":"Point"}
}