{
  "type": "Feature",
  "properties": {
    "iso:country":"US",
    "sg:address":"2300 N 2nd St",
    "sg:city":"Vincennes",
    "sg:classifiers":[
        {
            "category":"Organizations",
            "subcategory":"Religious Organization",
            "type":"Services"
        }
    ],
    "sg:phone":"+1 812 882 6933",
    "sg:postcode":"47591",
    "sg:province":"IN",
    "sg:tags":[
        "membership"
    ],
    "wof:name":"Salvation Army Services Inc",
    "wof:placetype":"venue"
},
  "geometry": {"coordinates":[-87.50702699999999,38.690556],"type":"Point"}
}