{
  "type": "Feature",
  "properties": {
    "iso:country":"US",
    "sg:address":"350 E Washington Ave",
    "sg:city":"Peru",
    "sg:classifiers":[
        {
            "category":"Food & Beverages",
            "subcategory":"Groceries & Convenience Stores",
            "type":"Retail Goods"
        }
    ],
    "sg:phone":"+1 765 473 3741",
    "sg:postcode":"46970",
    "sg:province":"IN",
    "wof:name":"Village Market II",
    "wof:placetype":"venue"
},
  "geometry": {"coordinates":[-86.060839,40.763774],"type":"Point"}
}