{
  "type": "Feature",
  "properties": {
    "iso:country":"US",
    "sg:address":"802 Van Buren St",
    "sg:city":"South Bend",
    "sg:classifiers":[
        {
            "category":"Professional",
            "type":"Services"
        }
    ],
    "sg:phone":"+1 574 289 6952",
    "sg:postcode":"46616",
    "sg:province":"IN",
    "sg:tags":[
        "organization",
        "religious"
    ],
    "wof:name":"New Peters Rock Mssnry Bpt Ch",
    "wof:placetype":"venue"
},
  "geometry": {"coordinates":[-86.26185700000001,41.685953],"type":"Point"}
}