{
  "type": "Feature",
  "properties": {
    "iso:country":"US",
    "sg:address":"1200 N 2nd St",
    "sg:city":"Decatur",
    "sg:classifiers":[
        {
            "category":"Manufacturing",
            "subcategory":"Food",
            "type":"Manufacturing & Wholesale Goods"
        }
    ],
    "sg:phone":"+1 260 724 2101",
    "sg:postcode":"46733",
    "sg:province":"IN",
    "sg:tags":[
        "oil",
        "seed"
    ],
    "wof:name":"Bunge Oilseed Processing",
    "wof:placetype":"venue"
},
  "geometry": {"coordinates":[-84.93141799999999,40.841592],"type":"Point"}
}