{
  "type": "Feature",
  "properties": {
    "iso:country":"US",
    "sg:address":"200 E Walnut St",
    "sg:city":"Washington",
    "sg:classifiers":[
        {
            "category":"Government",
            "subcategory":"Office",
            "type":"Public Place"
        }
    ],
    "sg:phone":"+1 812 254 8665",
    "sg:postcode":"47501",
    "sg:province":"IN",
    "wof:name":"Community Correction Director",
    "wof:placetype":"venue"
},
  "geometry": {"coordinates":[-87.172337,38.658646],"type":"Point"}
}