{
  "type": "Feature",
  "properties": {
    "iso:country":"US",
    "sg:address":"4305 N State Rd 9",
    "sg:city":"Shelbyville",
    "sg:classifiers":[
        {
            "category":"Real Estate",
            "subcategory":"Real Estate Agent",
            "type":"Services"
        }
    ],
    "sg:phone":"+1 317 398 2470",
    "sg:postcode":"46176",
    "sg:province":"IN",
    "wof:name":"B C Commercial Real Estate",
    "wof:placetype":"venue"
},
  "geometry": {"coordinates":[-85.776462,39.596776],"type":"Point"}
}