{
  "type": "Feature",
  "properties": {
    "iso:country":"US",
    "sg:address":"479 N Huntington St",
    "sg:city":"Wabash",
    "sg:classifiers":[
        {
            "category":"Personal",
            "subcategory":"Beauty Salon",
            "type":"Services"
        }
    ],
    "sg:phone":"+1 260 563 0499",
    "sg:postcode":"46992",
    "sg:province":"IN",
    "wof:name":"Tangles",
    "wof:placetype":"venue"
},
  "geometry": {"coordinates":[-85.819878,40.803508],"type":"Point"}
}