{
  "type": "Feature",
  "properties": {
    "iso:country":"US",
    "sg:address":"204 S 3rd St",
    "sg:city":"Boonville",
    "sg:classifiers":[
        {
            "category":"Wholesale",
            "subcategory":"Non-durable Goods",
            "type":"Manufacturing & Wholesale Goods"
        }
    ],
    "sg:phone":"+1 812 897 8806",
    "sg:postcode":"47601",
    "sg:province":"IN",
    "sg:tags":[
        "advertising"
    ],
    "wof:name":"American Advertising",
    "wof:placetype":"venue"
},
  "geometry": {"coordinates":[-87.274292,38.048988],"type":"Point"}
}