{
  "type": "Feature",
  "properties": {
    "iso:country":"US",
    "sg:address":"846 S 600 W",
    "sg:city":"Huntingburg",
    "sg:classifiers":[
        {
            "category":"Shopping",
            "subcategory":"Crafts & Fabrics",
            "type":"Retail Goods"
        }
    ],
    "sg:phone":"+1 812 683 2907",
    "sg:postcode":"47542",
    "sg:province":"IN",
    "sg:tags":[
        "sewing"
    ],
    "wof:name":"Magic Cloth",
    "wof:placetype":"venue"
},
  "geometry": {"coordinates":[-87.017071,38.366497],"type":"Point"}
}