{
  "type": "Feature",
  "properties": {
    "iso:country":"US",
    "sg:address":"8760 Lemode Ct Ofc",
    "sg:city":"Indianapolis",
    "sg:classifiers":[
        {
            "category":"Real Estate",
            "subcategory":"Real Estate Operator",
            "type":"Services"
        }
    ],
    "sg:phone":"+1 317 872 0203",
    "sg:postcode":"46268",
    "sg:province":"IN",
    "sg:tags":[
        "apartment"
    ],
    "wof:name":"Villa Nova Apartments",
    "wof:placetype":"venue"
},
  "geometry": {"coordinates":[-86.214203,39.9132],"type":"Point"}
}