{
  "type": "Feature",
  "properties": {
    "addr:full":"7816 Camberwood Dr Indianapolis IN 46268",
    "addr:housenumber":"7816",
    "addr:postcode":"46268",
    "addr:street":"Camberwood Dr",
    "iso:country":"US",
    "sg:address":"7816 Camberwood Dr",
    "sg:city":"Indianapolis",
    "sg:classifiers":[
        {
            "category":"Utilities",
            "subcategory":"Mobile Phone",
            "type":"Services"
        }
    ],
    "sg:phone":"+1 317 879 9532",
    "sg:postcode":"46268",
    "sg:province":"IN",
    "sg:tags":[
        "telephone",
        "cellular"
    ],
    "wof:name":"Connect By Reading Inc",
    "wof:placetype":"venue"
},
  "geometry": {"coordinates":[-86.224183,39.896489],"type":"Point"}
}