{
  "type": "Feature",
  "properties": {
    "addr:full":"1827 S Meridian St Indianapolis IN 46225",
    "addr:housenumber":"1827",
    "addr:postcode":"46225",
    "addr:street":"S Meridian St",
    "iso:country":"US",
    "sg:address":"1827 S Meridian St",
    "sg:city":"Indianapolis",
    "sg:classifiers":[
        {
            "category":"Food & Beverages",
            "subcategory":"Candy",
            "type":"Retail Goods"
        }
    ],
    "sg:phone":"+1 317 972 0941",
    "sg:postcode":"46225",
    "sg:province":"IN",
    "sg:tags":[
        "confectionery"
    ],
    "wof:name":"The Peanut King",
    "wof:placetype":"venue"
},
  "geometry": {"coordinates":[-86.15907300000001,39.742779],"type":"Point"}
}