{
  "type": "Feature",
  "properties": {
    "addr:full":"23103 Roosevelt Rd South Bend IN 46614",
    "addr:housenumber":"23103",
    "addr:postcode":"46614",
    "addr:street":"Roosevelt Rd",
    "iso:country":"US",
    "sg:address":"23103 Roosevelt Rd",
    "sg:city":"South Bend",
    "sg:classifiers":[
        {
            "category":"Retail",
            "subcategory":"Laundry & Dry Cleaning",
            "type":"Services"
        }
    ],
    "sg:phone":"+1 574 935 3125",
    "sg:postcode":"46614",
    "sg:province":"IN",
    "sg:tags":[
        "cleaners",
        "rug",
        "carpet"
    ],
    "wof:name":"Superior Fire & Water",
    "wof:placetype":"venue"
},
  "geometry": {"coordinates":[-86.314042,41.59349],"type":"Point"}
}