{
  "type": "Feature",
  "properties": {
    "iso:country":"US",
    "sg:address":"418 W Dupont Rd",
    "sg:city":"Fort Wayne",
    "sg:classifiers":[
        {
            "category":"Banks & Credit Unions",
            "subcategory":"Bank",
            "type":"Services"
        }
    ],
    "sg:phone":"+1 260 490 6800",
    "sg:postcode":"46825",
    "sg:province":"IN",
    "sg:tags":[
        "loan",
        "real estate"
    ],
    "wof:name":"MVP Mortgage Corp",
    "wof:placetype":"venue"
},
  "geometry": {"coordinates":[-85.147198,41.178028],"type":"Point"}
}