{
  "type": "Feature",
  "properties": {
    "addr:full":"3226 S Pixley Knob Rd Henryville IN 47126",
    "addr:housenumber":"3226",
    "addr:postcode":"47126",
    "addr:street":"S Pixley Knob Rd",
    "iso:country":"US",
    "sg:address":"3226 S Pixley Knob Rd",
    "sg:city":"Henryville",
    "sg:classifiers":[
        {
            "category":"Professional",
            "subcategory":"Business Services",
            "type":"Services"
        },
        {
            "category":"Home & Garden",
            "subcategory":"Home Furnishings",
            "type":"Retail Goods"
        }
    ],
    "sg:phone":"+1 812 967 4328",
    "sg:postcode":"47126",
    "sg:province":"IN",
    "sg:tags":[
        "wood"
    ],
    "wof:name":"Chestnut Hill Enterprises Inc",
    "wof:placetype":"venue"
},
  "geometry": {"coordinates":[-85.862865,38.561226],"type":"Point"}
}