{
  "type": "Feature",
  "properties": {
    "iso:country":"US",
    "sg:address":"3129 Blackiston Mill Rd",
    "sg:city":"New Albany",
    "sg:classifiers":[
        {
            "category":"Restaurant",
            "type":"Food & Drink"
        }
    ],
    "sg:phone":"+1 812 945 4321",
    "sg:postcode":"47150",
    "sg:province":"IN",
    "wof:name":"A Nice Restaurant",
    "wof:placetype":"venue"
},
  "geometry": {"coordinates":[-85.796767,38.334917],"type":"Point"}
}