{
  "type": "Feature",
  "properties": {
    "iso:country":"US",
    "sg:address":"306 Daugherty Ln",
    "sg:city":"Crawfordsville",
    "sg:classifiers":[
        {
            "category":"Building & Trades",
            "subcategory":"Construction",
            "type":"Services"
        }
    ],
    "sg:phone":"+1 765 362 4068",
    "sg:postcode":"47933",
    "sg:province":"IN",
    "sg:tags":[
        "concrete",
        "contractor"
    ],
    "wof:name":"Mercer Building Svc Inc",
    "wof:placetype":"venue"
},
  "geometry": {"coordinates":[-86.862801,40.039479],"type":"Point"}
}