{
  "type": "Feature",
  "properties": {
    "iso:country":"US",
    "sg:address":"1425 E Main St",
    "sg:city":"Richmond",
    "sg:classifiers":[
        {
            "category":"Social Services",
            "type":"Services"
        }
    ],
    "sg:phone":"+1 765 939 2228",
    "sg:postcode":"47374",
    "sg:province":"IN",
    "sg:tags":[
        "youth",
        "organization",
        "center"
    ],
    "wof:name":"Boys & Girls Clubs At Central",
    "wof:placetype":"venue"
},
  "geometry": {"coordinates":[-84.882006,39.829445],"type":"Point"}
}