{
  "type": "Feature",
  "properties": {
    "iso:country":"US",
    "sg:address":"8809 E 38th St",
    "sg:city":"Indianapolis",
    "sg:classifiers":[
        {
            "category":"Personal",
            "subcategory":"Barber",
            "type":"Services"
        }
    ],
    "sg:phone":"+1 317 898 7768",
    "sg:postcode":"46226",
    "sg:province":"IN",
    "wof:name":"Spot Barber & Beauty Shop",
    "wof:placetype":"venue"
},
  "geometry": {"coordinates":[-86.010043,39.825971],"type":"Point"}
}