{
  "type": "Feature",
  "properties": {
    "iso:country":"US",
    "sg:address":"200 N Monticello St",
    "sg:city":"Winamac",
    "sg:classifiers":[
        {
            "category":"Shopping",
            "subcategory":"Florist",
            "type":"Retail Goods"
        }
    ],
    "sg:phone":"+1 574 946 3441",
    "sg:postcode":"46996",
    "sg:province":"IN",
    "sg:website":"www.camelot-flowers.com",
    "wof:name":"Camelot Flowers",
    "wof:placetype":"venue"
},
  "geometry": {"coordinates":[-86.603935,41.05309],"type":"Point"}
}