{
  "type": "Feature",
  "properties": {
    "addr:full":"10520 Big Cynthiana Rd Evansville IN 47720",
    "addr:housenumber":"10520",
    "addr:postcode":"47720",
    "addr:street":"Big Cynthiana Rd",
    "iso:country":"US",
    "sg:address":"10520 Big Cynthiana Rd",
    "sg:city":"Evansville",
    "sg:classifiers":[
        {
            "category":"Professional",
            "type":"Services"
        }
    ],
    "sg:phone":"+1 812 963 6796",
    "sg:postcode":"47720",
    "sg:province":"IN",
    "wof:name":"Marbeck Family LP",
    "wof:placetype":"venue"
},
  "geometry": {"coordinates":[-87.641559,38.075497],"type":"Point"}
}