{
  "type": "Feature",
  "properties": {
    "iso:country":"US",
    "sg:address":"1908 Tulip Ln",
    "sg:city":"Munster",
    "sg:classifiers":[
        {
            "category":"Ice Cream",
            "type":"Food & Drink"
        }
    ],
    "sg:phone":"+1 219 838 3049",
    "sg:postcode":"46321",
    "sg:province":"IN",
    "wof:name":"Mikes Ice Cream",
    "wof:placetype":"venue"
},
  "geometry": {"coordinates":[-87.48394399999999,41.546292],"type":"Point"}
}