{
  "type": "Feature",
  "properties": {
    "addr:full":"68657 Sycamore Rd Walkerton IN 46574",
    "addr:housenumber":"68657",
    "addr:postcode":"46574",
    "addr:street":"Sycamore Rd",
    "iso:country":"US",
    "sg:address":"68657 Sycamore Rd",
    "sg:city":"Walkerton",
    "sg:phone":"+1 574 656 8853",
    "sg:postcode":"46574",
    "sg:province":"IN",
    "sg:tags":[
        "farm",
        "field",
        "grain",
        "cash",
        "crop"
    ],
    "wof:name":"Dale Borton",
    "wof:placetype":"venue"
},
  "geometry": {"coordinates":[-86.407308,41.496521],"type":"Point"}
}