{
  "type": "Feature",
  "properties": {
    "iso:country":"US",
    "sg:address":"251 W Main St",
    "sg:city":"Jasonville",
    "sg:classifiers":[
        {
            "category":"Professional",
            "subcategory":"Credit Reporting & Collection",
            "type":"Services"
        }
    ],
    "sg:phone":"+1 812 665 2462",
    "sg:postcode":"47438",
    "sg:province":"IN",
    "sg:tags":[
        "agency"
    ],
    "wof:name":"Paradise Ross Willford & Gdc",
    "wof:placetype":"venue"
},
  "geometry": {"coordinates":[-87.200563,39.163163],"type":"Point"}
}