{
  "type": "Feature",
  "properties": {
    "iso:country":"US",
    "sg:address":"5848 N US Hwy 35",
    "sg:city":"Laporte",
    "sg:classifiers":[
        {
            "category":"Building & Trades",
            "subcategory":"Construction",
            "type":"Services"
        }
    ],
    "sg:phone":"+1 219 872 5955",
    "sg:postcode":"46350",
    "sg:province":"IN",
    "sg:tags":[
        "paving",
        "contractor"
    ],
    "wof:name":"E & L Paving & Construction",
    "wof:placetype":"venue"
},
  "geometry": {"coordinates":[-86.802812,41.690134],"type":"Point"}
}