{
  "type": "Feature",
  "properties": {
    "iso:country":"US",
    "sg:address":"3100 W 5th Ave",
    "sg:city":"Gary",
    "sg:classifiers":[
        {
            "category":"Bars & Pubs",
            "type":"Food & Drink"
        }
    ],
    "sg:phone":"+1 219 949 1810",
    "sg:postcode":"46406",
    "sg:province":"IN",
    "sg:tags":[
        "drinking"
    ],
    "wof:name":"Parker's Lounge",
    "wof:placetype":"venue"
},
  "geometry": {"coordinates":[-87.375778,41.60191],"type":"Point"}
}