{
  "type": "Feature",
  "properties": {
    "iso:country":"US",
    "sg:address":"312 S Main St",
    "sg:city":"Columbia City",
    "sg:classifiers":[
        {
            "category":"Food & Beverages",
            "subcategory":"Liquor & Beverages",
            "type":"Retail Goods"
        }
    ],
    "sg:phone":"+1 260 244 6363",
    "sg:postcode":"46725",
    "sg:province":"IN",
    "wof:name":"Scott Package Liquors",
    "wof:placetype":"venue"
},
  "geometry": {"coordinates":[-85.488423,41.154712],"type":"Point"}
}