{
  "type": "Feature",
  "properties": {
    "iso:country":"US",
    "sg:address":"1104 N Baldwin Ave",
    "sg:city":"Marion",
    "sg:classifiers":[
        {
            "category":"Shopping",
            "subcategory":"Department Store",
            "type":"Retail Goods"
        }
    ],
    "sg:phone":"+1 765 662 8139",
    "sg:postcode":"46952",
    "sg:province":"IN",
    "sg:tags":[
        "shop"
    ],
    "wof:name":"Dollar General",
    "wof:placetype":"venue"
},
  "geometry": {"coordinates":[-85.675958,40.570623],"type":"Point"}
}