{
  "type": "Feature",
  "properties": {
    "iso:country":"US",
    "sg:address":"3920 N State Rd 39",
    "sg:city":"Lebanon",
    "sg:classifiers":[
        {
            "category":"Health Services",
            "subcategory":"Chiropractor",
            "type":"Services"
        }
    ],
    "sg:phone":"+1 765 482 1610",
    "sg:postcode":"46052",
    "sg:province":"IN",
    "wof:name":"Boone County Chiropractic",
    "wof:placetype":"venue"
},
  "geometry": {"coordinates":[-86.478797,40.094452],"type":"Point"}
}