{
  "type": "Feature",
  "properties": {
    "iso:country":"US",
    "sg:address":"6200 State Rd 62",
    "sg:city":"Jeffersonville",
    "sg:classifiers":[
        {
            "category":"Building & Trades",
            "subcategory":"Construction",
            "type":"Services"
        }
    ],
    "sg:phone":"+1 812 280 4404",
    "sg:postcode":"47130",
    "sg:province":"IN",
    "sg:tags":[
        "project"
    ],
    "wof:name":"American Contracting",
    "wof:placetype":"venue"
},
  "geometry": {"coordinates":[-85.697898,38.366806],"type":"Point"}
}