{
  "type": "Feature",
  "properties": {
    "iso:country":"US",
    "sg:address":"2516 Ashwood Ave",
    "sg:city":"Evansville",
    "sg:classifiers":[
        {
            "category":"Manufacturing",
            "subcategory":"Metals",
            "type":"Manufacturing & Wholesale Goods"
        }
    ],
    "sg:phone":"+1 812 474 9003",
    "sg:postcode":"47711",
    "sg:province":"IN",
    "sg:tags":[
        "tool",
        "mfg"
    ],
    "wof:name":"Snap-On Tools",
    "wof:placetype":"venue"
},
  "geometry": {"coordinates":[-87.516705,38.022753],"type":"Point"}
}