{
  "type": "Feature",
  "properties": {
    "iso:country":"US",
    "sg:address":"11359 N Syracuse Webster Rd",
    "sg:city":"Syracuse",
    "sg:classifiers":[
        {
            "category":"Manufacturing",
            "subcategory":"Apparel",
            "type":"Manufacturing & Wholesale Goods"
        }
    ],
    "sg:phone":"+1 574 457 4638",
    "sg:postcode":"46567",
    "sg:province":"IN",
    "sg:tags":[
        "product",
        "canvas",
        "related",
        "mfg"
    ],
    "wof:name":"Farber Upholstery & Canvas",
    "wof:placetype":"venue"
},
  "geometry": {"coordinates":[-85.753984,41.404707],"type":"Point"}
}