{
  "type": "Feature",
  "properties": {
    "addr:full":"7602 Butt Rd Fort Wayne IN 46818",
    "addr:housenumber":"7602",
    "addr:postcode":"46818",
    "addr:street":"Butt Rd",
    "iso:country":"US",
    "sg:address":"7602 Butt Rd",
    "sg:city":"Fort Wayne",
    "sg:classifiers":[
        {
            "category":"Building & Trades",
            "subcategory":"Pest Control",
            "type":"Services"
        }
    ],
    "sg:phone":"+1 260 625 6032",
    "sg:postcode":"46818",
    "sg:province":"IN",
    "wof:name":"All Creatures Great & Small",
    "wof:placetype":"venue"
},
  "geometry": {"coordinates":[-85.32317500000001,41.153798],"type":"Point"}
}