{
  "type": "Feature",
  "properties": {
    "iso:country":"US",
    "sg:address":"1049 A St NE",
    "sg:city":"Linton",
    "sg:classifiers":[
        {
            "category":"Shopping",
            "subcategory":"Computers & Home Electronics",
            "type":"Retail Goods"
        }
    ],
    "sg:phone":"+1 812 847 0001",
    "sg:postcode":"47441",
    "sg:province":"IN",
    "sg:tags":[
        "software"
    ],
    "wof:name":"Galaxy Holdings",
    "wof:placetype":"venue"
},
  "geometry": {"coordinates":[-87.154385,39.036385],"type":"Point"}
}