{
  "type": "Feature",
  "properties": {
    "iso:country":"US",
    "sg:address":"16768 Wicker Ave",
    "sg:city":"Lowell",
    "sg:classifiers":[
        {
            "category":"Professional",
            "subcategory":"Research",
            "type":"Services"
        }
    ],
    "sg:phone":"+1 219 696 9298",
    "sg:postcode":"46356",
    "sg:province":"IN",
    "sg:tags":[
        "environmental",
        "ecological"
    ],
    "wof:name":"Missal Environmental",
    "wof:placetype":"venue"
},
  "geometry": {"coordinates":[-87.469291,41.314196],"type":"Point"}
}