{
  "type": "Feature",
  "properties": {
    "addr:full":"86 Lee St Franklin IN 46151",
    "addr:housenumber":"86",
    "addr:postcode":"46151",
    "addr:street":"Lee St",
    "iso:country":"US",
    "sg:address":"86 Lee St",
    "sg:city":"Franklin",
    "sg:classifiers":[
        {
            "category":"Government",
            "subcategory":"Office",
            "type":"Public Place"
        }
    ],
    "sg:phone":"+1 317 736 3745",
    "sg:postcode":"46151",
    "sg:province":"IN",
    "sg:tags":[
        "county",
        "taxation"
    ],
    "wof:name":"Johnson County Auditor",
    "wof:placetype":"venue"
},
  "geometry": {"coordinates":[-86.41507900000001,39.421956],"type":"Point"}
}