{
  "type": "Feature",
  "properties": {
    "addr:full":"119 E Main St Crawfordsville IN 47933",
    "addr:housenumber":"119",
    "addr:postcode":"47933",
    "addr:street":"E Main St",
    "iso:country":"US",
    "sg:address":"119 E Main St",
    "sg:city":"Crawfordsville",
    "sg:classifiers":[
        {
            "category":"Banks & Credit Unions",
            "subcategory":"Bank",
            "type":"Services"
        }
    ],
    "sg:phone":"+1 765 362 7881",
    "sg:postcode":"47933",
    "sg:province":"IN",
    "sg:tags":[
        "company",
        "trust"
    ],
    "wof:name":"Community Trust & Investment",
    "wof:placetype":"venue"
},
  "geometry": {"coordinates":[-86.901191,40.041648],"type":"Point"}
}