{
  "type": "Feature",
  "properties": {
    "iso:country":"US",
    "sg:address":"11358 S State Rd 3",
    "sg:city":"Westport",
    "sg:classifiers":[
        {
            "category":"Building & Trades",
            "subcategory":"Construction",
            "type":"Services"
        }
    ],
    "sg:phone":"+1 812 591 0141",
    "sg:postcode":"47283",
    "sg:province":"IN",
    "sg:tags":[
        "general",
        "contractor"
    ],
    "wof:name":"D & K Builders",
    "wof:placetype":"venue"
},
  "geometry": {"coordinates":[-85.601957,39.165063],"type":"Point"}
}