{
  "type": "Feature",
  "properties": {
    "iso:country":"US",
    "sg:address":"115 W Jackson St",
    "sg:city":"Sullivan",
    "sg:classifiers":[
        {
            "category":"Manufacturing",
            "subcategory":"Printing",
            "type":"Manufacturing & Wholesale Goods"
        }
    ],
    "sg:phone":"+1 812 268 6356",
    "sg:postcode":"47882",
    "sg:province":"IN",
    "sg:tags":[
        "newspaper"
    ],
    "wof:name":"Sullivan Daily Times",
    "wof:placetype":"venue"
},
  "geometry": {"coordinates":[-87.409507,39.094342],"type":"Point"}
}