{
  "type": "Feature",
  "properties": {
    "iso:country":"US",
    "sg:address":"608 Wynterbrooke Dr",
    "sg:city":"Kokomo",
    "sg:classifiers":[
        {
            "category":"Building & Trades",
            "subcategory":"Construction",
            "type":"Services"
        }
    ],
    "sg:phone":"+1 765 868 1087",
    "sg:postcode":"46901",
    "sg:province":"IN",
    "sg:tags":[
        "house"
    ],
    "wof:name":"Melody Homes Inc",
    "wof:placetype":"venue"
},
  "geometry": {"coordinates":[-86.169217,40.491208],"type":"Point"}
}