{
  "type": "Feature",
  "properties": {
    "iso:country":"US",
    "sg:address":"202 S Buffalo St",
    "sg:city":"Warsaw",
    "sg:classifiers":[
        {
            "category":"Retail",
            "subcategory":"Portrait Studio",
            "type":"Services"
        }
    ],
    "sg:phone":"+1 574 267 5212",
    "sg:postcode":"46580",
    "sg:province":"IN",
    "sg:tags":[
        "photographer"
    ],
    "wof:name":"Bob List Photography",
    "wof:placetype":"venue"
},
  "geometry": {"coordinates":[-85.85672099999999,41.237077],"type":"Point"}
}