{
  "type": "Feature",
  "properties": {
    "iso:country":"US",
    "sg:address":"730 N Clark Blvd",
    "sg:city":"Clarksville",
    "sg:classifiers":[
        {
            "category":"Social Services",
            "type":"Services"
        }
    ],
    "sg:phone":"+1 812 280 9000",
    "sg:postcode":"47129",
    "sg:province":"IN",
    "sg:tags":[
        "organization",
        "welfare"
    ],
    "wof:name":"Friends For Life",
    "wof:placetype":"venue"
},
  "geometry": {"coordinates":[-85.772188,38.297052],"type":"Point"}
}