{
  "type": "Feature",
  "properties": {
    "iso:country":"US",
    "sg:address":"11929 E 65th St",
    "sg:city":"Indianapolis",
    "sg:classifiers":[
        {
            "category":"Retail",
            "subcategory":"Veterinary Services",
            "type":"Services"
        }
    ],
    "sg:phone":"+1 317 823 3464",
    "sg:postcode":"46236",
    "sg:province":"IN",
    "sg:tags":[
        "veterinarian"
    ],
    "wof:name":"Oaklandon Animal Clinic",
    "wof:placetype":"venue"
},
  "geometry": {"coordinates":[-85.955897,39.876881],"type":"Point"}
}