{
  "type": "Feature",
  "properties": {
    "iso:country":"US",
    "sg:address":"105 W Main St",
    "sg:city":"Crothersville",
    "sg:classifiers":[
        {
            "category":"Organizations",
            "subcategory":"Community Association",
            "type":"Services"
        }
    ],
    "sg:phone":"+1 812 793 3565",
    "sg:postcode":"47229",
    "sg:province":"IN",
    "sg:tags":[
        "military"
    ],
    "wof:name":"Veterans Of Foreign Wars 1083",
    "wof:placetype":"venue"
},
  "geometry": {"coordinates":[-85.84078,38.794408],"type":"Point"}
}