{
  "type": "Feature",
  "properties": {
    "iso:country":"US",
    "sg:address":"105 S 10th St",
    "sg:city":"Noblesville",
    "sg:classifiers":[
        {
            "category":"Professional",
            "type":"Services"
        }
    ],
    "sg:phone":"+1 317 776 3100",
    "sg:postcode":"46060",
    "sg:province":"IN",
    "sg:tags":[
        "establishment"
    ],
    "wof:name":"Exequest Limited",
    "wof:placetype":"venue"
},
  "geometry": {"coordinates":[-86.01232,40.044634],"type":"Point"}
}