{
  "type": "Feature",
  "properties": {
    "iso:country":"US",
    "sg:address":"340 NW Court St",
    "sg:city":"Paoli",
    "sg:classifiers":[
        {
            "category":"Real Estate",
            "subcategory":"Real Estate Services",
            "type":"Services"
        }
    ],
    "sg:phone":"+1 812 723 2771",
    "sg:postcode":"47454",
    "sg:province":"IN",
    "wof:name":"Dillard Abstract Co",
    "wof:placetype":"venue"
},
  "geometry": {"coordinates":[-86.468998,38.556308],"type":"Point"}
}