{
  "type": "Feature",
  "properties": {
    "iso:country":"US",
    "sg:address":"1001 N Washington St",
    "sg:city":"Marion",
    "sg:classifiers":[
        {
            "category":"Shopping",
            "subcategory":"Clothing, Apparel, & Fashions",
            "type":"Retail Goods"
        }
    ],
    "sg:phone":"+1 765 668 4195",
    "sg:postcode":"46952",
    "sg:province":"IN",
    "sg:tags":[
        "family"
    ],
    "wof:name":"Eltzroth",
    "wof:placetype":"venue"
},
  "geometry": {"coordinates":[-85.65898199999999,40.575921],"type":"Point"}
}