{
  "type": "Feature",
  "properties": {
    "addr:full":"850 E Smith St Warsaw IN 46580",
    "addr:housenumber":"850",
    "addr:postcode":"46580",
    "addr:street":"E Smith St",
    "iso:country":"US",
    "sg:address":"850 E Smith St",
    "sg:city":"Warsaw",
    "sg:classifiers":[
        {
            "category":"Social Services",
            "type":"Services"
        }
    ],
    "sg:phone":"+1 574 267 5380",
    "sg:postcode":"46580",
    "sg:province":"IN",
    "sg:tags":[
        "organization",
        "welfare"
    ],
    "wof:name":"Kosciusko Literacy Volunteers",
    "wof:placetype":"venue"
},
  "geometry": {"coordinates":[-85.84448999999999,41.234362],"type":"Point"}
}