{
  "type": "Feature",
  "properties": {
    "iso:country":"US",
    "sg:address":"9054 Columbia Ave",
    "sg:city":"Munster",
    "sg:classifiers":[
        {
            "category":"Health Services",
            "subcategory":"Doctor",
            "type":"Services"
        }
    ],
    "sg:phone":"+1 219 836 1014",
    "sg:postcode":"46321",
    "sg:province":"IN",
    "sg:tags":[
        "physician",
        "surgeon"
    ],
    "wof:name":"Northwest Oncology",
    "wof:placetype":"venue"
},
  "geometry": {"coordinates":[-87.504947,41.549066],"type":"Point"}
}