{
  "type": "Feature",
  "properties": {
    "iso:country":"US",
    "sg:address":"1930 S 4th St",
    "sg:city":"Lafayette",
    "sg:classifiers":[
        {
            "category":"Food & Beverages",
            "subcategory":"Groceries & Convenience Stores",
            "type":"Retail Goods"
        }
    ],
    "sg:phone":"+1 765 474 0059",
    "sg:postcode":"47905",
    "sg:province":"IN",
    "wof:name":"Clark Oil & Refining",
    "wof:placetype":"venue"
},
  "geometry": {"coordinates":[-86.895252,40.396754],"type":"Point"}
}