{
  "type": "Feature",
  "properties": {
    "iso:country":"US",
    "sg:address":"1117 N Jackson St",
    "sg:city":"Bloomington",
    "sg:classifiers":[
        {
            "category":"Retail",
            "subcategory":"Auto Repair",
            "type":"Services"
        }
    ],
    "sg:phone":"+1 812 332 2171",
    "sg:postcode":"47404",
    "sg:province":"IN",
    "sg:tags":[
        "glass",
        "coating",
        "tinting"
    ],
    "wof:name":"SCS Window Tinting",
    "wof:placetype":"venue"
},
  "geometry": {"coordinates":[-86.539747,39.17881],"type":"Point"}
}