{
  "type": "Feature",
  "properties": {
    "iso:country":"US",
    "sg:address":"675 W 18th St",
    "sg:city":"Rochester",
    "sg:classifiers":[
        {
            "category":"Retail",
            "subcategory":"Repair Shop",
            "type":"Services"
        }
    ],
    "sg:phone":"+1 574 223 2469",
    "sg:postcode":"46975",
    "sg:province":"IN",
    "sg:tags":[
        "repairing",
        "lawn",
        "mower"
    ],
    "wof:name":"Ray's Lawn Mower Shop",
    "wof:placetype":"venue"
},
  "geometry": {"coordinates":[-86.225137,41.054218],"type":"Point"}
}