{
  "type": "Feature",
  "properties": {
    "iso:country":"US",
    "sg:address":"1208 W 20th St",
    "sg:city":"Laporte",
    "sg:classifiers":[
        {
            "category":"Building & Trades",
            "subcategory":"Landscaping Services",
            "type":"Services"
        }
    ],
    "sg:phone":"+1 219 324 6189",
    "sg:postcode":"46350",
    "sg:province":"IN",
    "sg:tags":[
        "landscape",
        "contractor"
    ],
    "wof:name":"Quality Tree & Landscaping",
    "wof:placetype":"venue"
},
  "geometry": {"coordinates":[-86.732804,41.588773],"type":"Point"}
}