{
  "type": "Feature",
  "properties": {
    "iso:country":"US",
    "sg:address":"101 W Spring St",
    "sg:city":"New Albany",
    "sg:classifiers":[
        {
            "category":"Banks & Credit Unions",
            "subcategory":"Investment Brokerage",
            "type":"Services"
        }
    ],
    "sg:phone":"+1 812 981 7377",
    "sg:postcode":"47150",
    "sg:province":"IN",
    "sg:tags":[
        "security"
    ],
    "wof:name":"Smith Barney Investment Bank",
    "wof:placetype":"venue"
},
  "geometry": {"coordinates":[-85.825159,38.285348],"type":"Point"}
}