{
  "type": "Feature",
  "properties": {
    "iso:country":"US",
    "sg:address":"138 Lynwood Dr",
    "sg:city":"Whiteland",
    "sg:classifiers":[
        {
            "category":"Organizations",
            "subcategory":"Professional Association",
            "type":"Services"
        }
    ],
    "sg:phone":"+1 317 535 0899",
    "sg:postcode":"46184",
    "sg:province":"IN",
    "wof:name":"Indiana Association-Certified",
    "wof:placetype":"venue"
},
  "geometry": {"coordinates":[-86.099686,39.5506],"type":"Point"}
}