{
  "type": "Feature",
  "properties": {
    "iso:country":"US",
    "sg:address":"13430 E 179th St",
    "sg:city":"Noblesville",
    "sg:classifiers":[
        {
            "category":"Building & Trades",
            "subcategory":"Construction",
            "type":"Services"
        }
    ],
    "sg:phone":"+1 317 773 3833",
    "sg:postcode":"46060",
    "sg:province":"IN",
    "sg:tags":[
        "marble",
        "terrazzo"
    ],
    "wof:name":"Marble Shiners Superior Marble",
    "wof:placetype":"venue"
},
  "geometry": {"coordinates":[-85.927614,40.048137],"type":"Point"}
}