{
  "type": "Feature",
  "properties": {
    "iso:country":"US",
    "sg:address":"815 Airport North Office Park",
    "sg:city":"Fort Wayne",
    "sg:classifiers":[
        {
            "category":"Banks & Credit Unions",
            "subcategory":"Investment Brokerage",
            "type":"Services"
        }
    ],
    "sg:phone":"+1 260 490 8950",
    "sg:postcode":"46825",
    "sg:province":"IN",
    "sg:tags":[
        "consultant",
        "planning",
        "financial"
    ],
    "wof:name":"Asset Preservation Group",
    "wof:placetype":"venue"
},
  "geometry": {"coordinates":[-85.161277,41.145361],"type":"Point"}
}