{
  "type": "Feature",
  "properties": {
    "iso:country":"US",
    "sg:address":"255 E College St",
    "sg:city":"Hagerstown",
    "sg:classifiers":[
        {
            "category":"Restaurant",
            "type":"Food & Drink"
        }
    ],
    "sg:phone":"+1 765 489 4726",
    "sg:postcode":"47346",
    "sg:province":"IN",
    "wof:name":"K C's Pizza",
    "wof:placetype":"venue"
},
  "geometry": {"coordinates":[-85.158609,39.911537],"type":"Point"}
}