{
  "type": "Feature",
  "properties": {
    "iso:country":"US",
    "sg:address":"2008 W Lincoln Hwy",
    "sg:city":"Merrillville",
    "sg:classifiers":[
        {
            "category":"Professional",
            "subcategory":"Management & Consulting",
            "type":"Services"
        }
    ],
    "sg:phone":"+1 219 887 0070",
    "sg:postcode":"46410",
    "sg:province":"IN",
    "sg:tags":[
        "construction"
    ],
    "wof:name":"Rossi Construction",
    "wof:placetype":"venue"
},
  "geometry": {"coordinates":[-87.360448,41.471187],"type":"Point"}
}