{
  "type": "Feature",
  "properties": {
    "iso:country":"US",
    "sg:address":"325 N Main St",
    "sg:city":"Kokomo",
    "sg:classifiers":[
        {
            "category":"Travel",
            "subcategory":"Hotels & Motels",
            "type":"Entertainment"
        },
        {
            "category":"Organizations",
            "subcategory":"Professional Association",
            "type":"Services"
        }
    ],
    "sg:phone":"+1 765 454 7926",
    "sg:postcode":"46901",
    "sg:province":"IN",
    "sg:tags":[
        "residential",
        "membership",
        "construction",
        "lodging"
    ],
    "wof:name":"Kokomo Main Street Assoc",
    "wof:placetype":"venue"
},
  "geometry": {"coordinates":[-86.131316,40.488581],"type":"Point"}
}