{
  "type": "Feature",
  "properties": {
    "iso:country":"US",
    "sg:address":"222 W Beech St",
    "sg:city":"Sullivan",
    "sg:classifiers":[
        {
            "category":"Health Services",
            "subcategory":"Doctor",
            "type":"Services"
        }
    ],
    "sg:phone":"+1 812 268 3901",
    "sg:postcode":"47882",
    "sg:province":"IN",
    "sg:tags":[
        "physician",
        "surgeon"
    ],
    "wof:name":"Sullivan Medical Clinic",
    "wof:placetype":"venue"
},
  "geometry": {"coordinates":[-87.411399,39.097367],"type":"Point"}
}