{
  "type": "Feature",
  "properties": {
    "iso:country":"US",
    "sg:address":"126 Eastern Ave",
    "sg:city":"Sunman",
    "sg:classifiers":[
        {
            "category":"Government",
            "subcategory":"Fire Station",
            "type":"Public Place"
        }
    ],
    "sg:phone":"+1 812 623 2498",
    "sg:postcode":"47041",
    "sg:province":"IN",
    "sg:tags":[
        "department"
    ],
    "wof:name":"Sunman Fire Dept",
    "wof:placetype":"venue"
},
  "geometry": {"coordinates":[-85.094097,39.236871],"type":"Point"}
}