{
  "type": "Feature",
  "properties": {
    "iso:country":"US",
    "sg:address":"5140 Yorkridge Rd",
    "sg:city":"Guilford",
    "sg:classifiers":[
        {
            "category":"Building & Trades",
            "subcategory":"Landscaping Services",
            "type":"Services"
        }
    ],
    "sg:phone":"+1 812 487 2293",
    "sg:postcode":"47022",
    "sg:province":"IN",
    "sg:tags":[
        "landscape"
    ],
    "wof:name":"Martini Landscaping Inc",
    "wof:placetype":"venue"
},
  "geometry": {"coordinates":[-84.913964,39.169286],"type":"Point"}
}