{
  "type": "Feature",
  "properties": {
    "addr:full":"608 Mulberry St Madison IN 47250",
    "addr:housenumber":"608",
    "addr:postcode":"47250",
    "addr:street":"Mulberry St",
    "iso:country":"US",
    "sg:address":"608 Mulberry St",
    "sg:city":"Madison",
    "sg:classifiers":[
        {
            "category":"Professional",
            "type":"Services"
        }
    ],
    "sg:phone":"+1 812 265 4203",
    "sg:postcode":"47250",
    "sg:province":"IN",
    "sg:tags":[
        "writer"
    ],
    "wof:name":"Big Ring Media Team Inc",
    "wof:placetype":"venue"
},
  "geometry": {"coordinates":[-85.37864399999999,38.739027],"type":"Point"}
}