{
  "type": "Feature",
  "properties": {
    "iso:country":"US",
    "sg:address":"904 S Union St",
    "sg:city":"Warsaw",
    "sg:classifiers":[
        {
            "category":"Health Services",
            "subcategory":"Doctor",
            "type":"Services"
        }
    ],
    "sg:phone":"+1 574 267 8466",
    "sg:postcode":"46580",
    "sg:province":"IN",
    "sg:tags":[
        "dentist"
    ],
    "sg:website":"www.dentalhealthpc.com",
    "wof:name":"Dental Health",
    "wof:placetype":"venue"
},
  "geometry": {"coordinates":[-85.861816,41.228897],"type":"Point"}
}