{
  "type": "Feature",
  "properties": {
    "iso:country":"US",
    "sg:address":"302 N 6th St",
    "sg:city":"Monticello",
    "sg:classifiers":[
        {
            "category":"Autos & Motor Vehicles",
            "subcategory":"Automobile Sales",
            "type":"Retail Goods"
        }
    ],
    "sg:phone":"+1 574 583 4595",
    "sg:postcode":"47960",
    "sg:province":"IN",
    "sg:tags":[
        "car",
        "dealer"
    ],
    "wof:name":"Joseph Motors Inc",
    "wof:placetype":"venue"
},
  "geometry": {"coordinates":[-86.775275,40.749071],"type":"Point"}
}