{
  "type": "Feature",
  "properties": {
    "addr:full":"2230 Applegate Dr Columbus IN 47203",
    "addr:housenumber":"2230",
    "addr:postcode":"47203",
    "addr:street":"Applegate Dr",
    "iso:country":"US",
    "sg:address":"2230 Applegate Dr",
    "sg:city":"Columbus",
    "sg:classifiers":[
        {
            "category":"Real Estate",
            "subcategory":"Real Estate Operator",
            "type":"Services"
        }
    ],
    "sg:phone":"+1 812 372 6004",
    "sg:postcode":"47203",
    "sg:province":"IN",
    "sg:tags":[
        "apartment"
    ],
    "wof:name":"Applegate Apartments",
    "wof:placetype":"venue"
},
  "geometry": {"coordinates":[-85.874942,39.221391],"type":"Point"}
}