{
  "type": "Feature",
  "properties": {
    "addr:full":"4904 Betholm Dr Indianapolis IN 46239",
    "addr:housenumber":"4904",
    "addr:postcode":"46239",
    "addr:street":"Betholm Dr",
    "iso:country":"US",
    "sg:address":"4904 Betholm Dr",
    "sg:city":"Indianapolis",
    "sg:classifiers":[
        {
            "category":"Wholesale",
            "subcategory":"Auto Parts",
            "type":"Manufacturing & Wholesale Goods"
        }
    ],
    "sg:phone":"+1 317 862 3212",
    "sg:postcode":"46239",
    "sg:province":"IN",
    "sg:tags":[
        "us",
        "supply"
    ],
    "wof:name":"Indianapolis Battery Company",
    "wof:placetype":"venue"
},
  "geometry": {"coordinates":[-86.00064399999999,39.697781],"type":"Point"}
}