{
  "type": "Feature",
  "properties": {
    "iso:country":"US",
    "sg:address":"461 Town Center Dr",
    "sg:city":"Mooresville",
    "sg:classifiers":[
        {
            "category":"Restaurant",
            "type":"Food & Drink"
        }
    ],
    "sg:phone":"+1 317 831 8866",
    "sg:postcode":"46158",
    "sg:province":"IN",
    "wof:name":"China King",
    "wof:placetype":"venue"
},
  "geometry": {"coordinates":[-86.353877,39.617242],"type":"Point"}
}