{
  "type": "Feature",
  "properties": {
    "iso:country":"US",
    "sg:address":"221 W Washington St",
    "sg:city":"Rensselaer",
    "sg:classifiers":[
        {
            "category":"Home & Garden",
            "subcategory":"Furniture",
            "type":"Retail Goods"
        }
    ],
    "sg:phone":"+1 219 866 7299",
    "sg:postcode":"47978",
    "sg:province":"IN",
    "wof:name":"T J's Unfinished Furniture",
    "wof:placetype":"venue"
},
  "geometry": {"coordinates":[-87.15261700000001,40.9354],"type":"Point"}
}