{
  "type": "Feature",
  "properties": {
    "addr:full":"7145 State Rd 62 Dale IN 47523",
    "addr:housenumber":"7145;62",
    "addr:postcode":"47523",
    "addr:street":"State Rd;Dale In",
    "iso:country":"US",
    "sg:address":"7145 State Rd 62",
    "sg:city":"Dale",
    "sg:classifiers":[
        {
            "category":"Wholesale",
            "subcategory":"Farm Supplies",
            "type":"Manufacturing & Wholesale Goods"
        }
    ],
    "sg:phone":"+1 812 937 2053",
    "sg:postcode":"47523",
    "sg:province":"IN",
    "wof:name":"Jims Feed Service",
    "wof:placetype":"venue"
},
  "geometry": {"coordinates":[-86.919481,38.16654],"type":"Point"}
}