{
  "type": "Feature",
  "properties": {
    "iso:country":"US",
    "sg:address":"402 E 13th St",
    "sg:city":"Jasper",
    "sg:classifiers":[
        {
            "category":"Manufacturing",
            "subcategory":"Furniture",
            "type":"Manufacturing & Wholesale Goods"
        }
    ],
    "sg:phone":"+1 812 482 5154",
    "sg:postcode":"47546",
    "sg:province":"IN",
    "sg:website":"www.jofco.com",
    "wof:name":"JOFCO Intl",
    "wof:placetype":"venue"
},
  "geometry": {"coordinates":[-86.92743,38.396661],"type":"Point"}
}