{
  "type": "Feature",
  "properties": {
    "iso:country":"US",
    "sg:address":"69170 Linden Rd",
    "sg:city":"Lakeville",
    "sg:classifiers":[
        {
            "category":"Building & Trades",
            "subcategory":"Construction",
            "type":"Services"
        }
    ],
    "sg:phone":"+1 574 784 9425",
    "sg:postcode":"46536",
    "sg:province":"IN",
    "sg:tags":[
        "siding",
        "replacement"
    ],
    "wof:name":"Shirley Home Improvement",
    "wof:placetype":"venue"
},
  "geometry": {"coordinates":[-86.272034,41.489487],"type":"Point"}
}