{
  "type": "Feature",
  "properties": {
    "iso:country":"US",
    "sg:address":"23146 W Ireland Rd",
    "sg:city":"South Bend",
    "sg:classifiers":[
        {
            "category":"Manufacturing",
            "subcategory":"Tools & Machinery",
            "type":"Manufacturing & Wholesale Goods"
        }
    ],
    "sg:phone":"+1 574 287 2329",
    "sg:postcode":"46614",
    "sg:province":"IN",
    "sg:tags":[
        "machine",
        "shop"
    ],
    "wof:name":"Bracom Corp",
    "wof:placetype":"venue"
},
  "geometry": {"coordinates":[-86.314085,41.628341],"type":"Point"}
}