{
  "type": "Feature",
  "properties": {
    "iso:country":"US",
    "sg:address":"1205 Waterstone Dr",
    "sg:city":"Lafayette",
    "sg:classifiers":[
        {
            "category":"Retail",
            "subcategory":"Repair Shop",
            "type":"Services"
        }
    ],
    "sg:phone":"+1 765 474 8776",
    "sg:postcode":"47909",
    "sg:province":"IN",
    "wof:name":"Eds Dent Repair Inc",
    "wof:placetype":"venue"
},
  "geometry": {"coordinates":[-86.881649,40.365822],"type":"Point"}
}