{
  "type": "Feature",
  "properties": {
    "iso:country":"US",
    "sg:address":"230 Royal Oak Ct",
    "sg:city":"Zionsville",
    "sg:classifiers":[
        {
            "category":"Professional",
            "subcategory":"Management & Consulting",
            "type":"Services"
        }
    ],
    "sg:phone":"+1 317 697 5367",
    "sg:postcode":"46077",
    "sg:province":"IN",
    "sg:tags":[
        "business"
    ],
    "wof:name":"N2s Solutions Inc",
    "wof:placetype":"venue"
},
  "geometry": {"coordinates":[-86.271944,39.967926],"type":"Point"}
}