{
  "type": "Feature",
  "properties": {
    "iso:country":"US",
    "sg:address":"3980 S State Rd 257",
    "sg:city":"Velpen",
    "sg:classifiers":[
        {
            "category":"Utilities",
            "subcategory":"Refuse",
            "type":"Services"
        }
    ],
    "sg:phone":"+1 812 354 3280",
    "sg:postcode":"47590",
    "sg:province":"IN",
    "sg:tags":[
        "garbage",
        "collection"
    ],
    "wof:name":"C & D Velpen Fill Site",
    "wof:placetype":"venue"
},
  "geometry": {"coordinates":[-87.09166,38.36519],"type":"Point"}
}