{
  "type": "Feature",
  "properties": {
    "addr:full":"2413 W Sycamore St Kokomo IN 46901",
    "addr:housenumber":"2413",
    "addr:postcode":"46901",
    "addr:street":"W Sycamore St",
    "iso:country":"US",
    "sg:address":"2413 W Sycamore St",
    "sg:city":"Kokomo",
    "sg:classifiers":[
        {
            "category":"Food & Beverages",
            "subcategory":"Groceries & Convenience Stores",
            "type":"Retail Goods"
        }
    ],
    "sg:phone":"+1 765 459 3866",
    "sg:postcode":"46901",
    "sg:province":"IN",
    "sg:tags":[
        "grocer"
    ],
    "wof:name":"Woody's Food Stores",
    "wof:placetype":"venue"
},
  "geometry": {"coordinates":[-86.165762,40.487654],"type":"Point"}
}