{
  "type": "Feature",
  "properties": {
    "addr:full":"7517 E Blue River Rd Pekin IN 47165",
    "addr:housenumber":"7517",
    "addr:postcode":"47165",
    "addr:street":"E Blue River Rd",
    "iso:country":"US",
    "sg:address":"7517 E Blue River Rd",
    "sg:city":"Pekin",
    "sg:classifiers":[
        {
            "category":"Professional",
            "subcategory":"Business Services",
            "type":"Services"
        }
    ],
    "sg:phone":"+1 812 967 3564",
    "sg:postcode":"47165",
    "sg:province":"IN",
    "sg:tags":[
        "auctioneer"
    ],
    "wof:name":"T & S Auction Svc",
    "wof:placetype":"venue"
},
  "geometry": {"coordinates":[-85.95724,38.523446],"type":"Point"}
}