{
  "type": "Feature",
  "properties": {
    "iso:country":"US",
    "sg:address":"2205 Park Rd",
    "sg:city":"Anderson",
    "sg:classifiers":[
        {
            "category":"Organizations",
            "subcategory":"Religious Organization",
            "type":"Services"
        }
    ],
    "sg:phone":"+1 765 643 2969",
    "sg:postcode":"46011",
    "sg:province":"IN",
    "sg:tags":[
        "church"
    ],
    "sg:website":"www.westanderson.com",
    "wof:name":"Church Of God",
    "wof:placetype":"venue"
},
  "geometry": {"coordinates":[-85.73016,40.092675],"type":"Point"}
}