{
  "type": "Feature",
  "properties": {
    "iso:country":"US",
    "sg:address":"201 W Allen St",
    "sg:city":"Kentland",
    "sg:classifiers":[
        {
            "category":"Home & Garden",
            "subcategory":"Household Appliances",
            "type":"Retail Goods"
        }
    ],
    "sg:phone":"+1 219 474 5588",
    "sg:postcode":"47951",
    "sg:province":"IN",
    "wof:name":"Miller's Appliance Sales & Svc",
    "wof:placetype":"venue"
},
  "geometry": {"coordinates":[-87.454877,40.766442],"type":"Point"}
}