{
  "type": "Feature",
  "properties": {
    "addr:full":"8012 Tyler St Merrillville IN 46410",
    "addr:housenumber":"8012",
    "addr:postcode":"46410",
    "addr:street":"Tyler St",
    "iso:country":"US",
    "sg:address":"8012 Tyler St",
    "sg:city":"Merrillville",
    "sg:classifiers":[
        {
            "category":"Shopping",
            "subcategory":"Computers & Home Electronics",
            "type":"Retail Goods"
        }
    ],
    "sg:phone":"+1 219 793 9703",
    "sg:postcode":"46410",
    "sg:province":"IN",
    "sg:tags":[
        "equipment",
        "dealer"
    ],
    "wof:name":"Precise Computers Inc",
    "wof:placetype":"venue"
},
  "geometry": {"coordinates":[-87.347257,41.472009],"type":"Point"}
}