{
  "type": "Feature",
  "properties": {
    "iso:country":"US",
    "sg:address":"2190 S Co Rd 600 W",
    "sg:city":"Rockport",
    "sg:classifiers":[
        {
            "category":"Building & Trades",
            "subcategory":"Landscaping Services",
            "type":"Services"
        }
    ],
    "sg:phone":"+1 812 359 4395",
    "sg:postcode":"47635",
    "sg:province":"IN",
    "sg:tags":[
        "lawn"
    ],
    "wof:name":"Mancuso Landscaping",
    "wof:placetype":"venue"
},
  "geometry": {"coordinates":[-87.169846,37.852968],"type":"Point"}
}