{
  "type": "Feature",
  "properties": {
    "iso:country":"US",
    "sg:address":"201 E Plymouth St",
    "sg:city":"Bremen",
    "sg:classifiers":[
        {
            "category":"Retail",
            "subcategory":"Laundry & Dry Cleaning",
            "type":"Services"
        }
    ],
    "sg:phone":"+1 574 546 3463",
    "sg:postcode":"46506",
    "sg:province":"IN",
    "sg:tags":[
        "cleaners",
        "rug",
        "carpet"
    ],
    "wof:name":"Max X Tract Industries LLC",
    "wof:placetype":"venue"
},
  "geometry": {"coordinates":[-86.145009,41.44654],"type":"Point"}
}