{
  "type": "Feature",
  "properties": {
    "iso:country":"US",
    "sg:address":"2801 Covington Rd",
    "sg:city":"Fort Wayne",
    "sg:classifiers":[
        {
            "category":"Wholesale",
            "subcategory":"Stationery",
            "type":"Manufacturing & Wholesale Goods"
        }
    ],
    "sg:phone":"+1 260 432 4570",
    "sg:postcode":"46802",
    "sg:province":"IN",
    "sg:tags":[
        "box",
        "fiber"
    ],
    "sg:website":"www.kellybox.com",
    "wof:name":"Kelly Box & Packaging Corp",
    "wof:placetype":"venue"
},
  "geometry": {"coordinates":[-85.177131,41.060221],"type":"Point"}
}