{
  "type": "Feature",
  "properties": {
    "addr:full":"6436 Purcell Station Rd Vincennes IN 47591",
    "addr:housenumber":"6436",
    "addr:postcode":"47591",
    "addr:street":"Purcell Station Rd",
    "iso:country":"US",
    "sg:address":"6436 Purcell Station Rd",
    "sg:city":"Vincennes",
    "sg:phone":"+1 812 882 2928",
    "sg:postcode":"47591",
    "sg:province":"IN",
    "sg:tags":[
        "farm",
        "corn",
        "wheat",
        "soybean"
    ],
    "wof:name":"Gartner John",
    "wof:placetype":"venue"
},
  "geometry": {"coordinates":[-87.538439,38.58285],"type":"Point"}
}