{
  "type": "Feature",
  "properties": {
    "iso:country":"US",
    "sg:address":"2300 W Tapp Rd",
    "sg:city":"Bloomington",
    "sg:classifiers":[
        {
            "category":"Building & Trades",
            "subcategory":"Construction",
            "type":"Services"
        }
    ],
    "sg:phone":"+1 812 336 2065",
    "sg:postcode":"47403",
    "sg:province":"IN",
    "sg:tags":[
        "contractor"
    ],
    "wof:name":"Preservation Development Inc",
    "wof:placetype":"venue"
},
  "geometry": {"coordinates":[-86.561662,39.136596],"type":"Point"}
}