{
  "type": "Feature",
  "properties": {
    "iso:country":"US",
    "sg:address":"6010 W Ridge Rd",
    "sg:city":"Gary",
    "sg:classifiers":[
        {
            "category":"Food & Beverages",
            "subcategory":"Groceries & Convenience Stores",
            "type":"Retail Goods"
        }
    ],
    "sg:phone":"+1 219 923 8107",
    "sg:postcode":"46408",
    "sg:province":"IN",
    "sg:tags":[
        "grocer"
    ],
    "wof:name":"Pay Low",
    "wof:placetype":"venue"
},
  "geometry": {"coordinates":[-87.410948,41.549429],"type":"Point"}
}