{
  "type": "Feature",
  "properties": {
    "iso:country":"US",
    "sg:address":"4330 Edison Lakes Pkwy",
    "sg:city":"Mishawaka",
    "sg:classifiers":[
        {
            "category":"Health Services",
            "subcategory":"Doctor",
            "type":"Services"
        }
    ],
    "sg:phone":"+1 574 271 0120",
    "sg:postcode":"46545",
    "sg:province":"IN",
    "sg:tags":[
        "physician",
        "surgeon"
    ],
    "sg:website":"www.gecenter.com",
    "wof:name":"Grossnickle Eye Ctr",
    "wof:placetype":"venue"
},
  "geometry": {"coordinates":[-86.17629100000001,41.700159],"type":"Point"}
}