{
  "type": "Feature",
  "properties": {
    "iso:country":"US",
    "sg:address":"1723 W 3rd St",
    "sg:city":"Bloomington",
    "sg:classifiers":[
        {
            "category":"Personal",
            "subcategory":"Beauty Salon",
            "type":"Services"
        }
    ],
    "sg:phone":"+1 812 339 0379",
    "sg:postcode":"47404",
    "sg:province":"IN",
    "wof:name":"Posh Salon",
    "wof:placetype":"venue"
},
  "geometry": {"coordinates":[-86.554548,39.164331],"type":"Point"}
}