{
  "type": "Feature",
  "properties": {
    "iso:country":"US",
    "sg:address":"28652 Phillips St",
    "sg:city":"Elkhart",
    "sg:classifiers":[
        {
            "category":"Shopping",
            "subcategory":"Hobbies, Toys, & Games",
            "type":"Retail Goods"
        }
    ],
    "sg:phone":"+1 574 262 4097",
    "sg:postcode":"46514",
    "sg:province":"IN",
    "sg:tags":[
        "sponge",
        "rubber",
        "foam"
    ],
    "sg:website":"www.ohiodec.com",
    "wof:name":"Flexible Foam Products Inc",
    "wof:placetype":"venue"
},
  "geometry": {"coordinates":[-86.022761,41.694281],"type":"Point"}
}