{
  "type": "Feature",
  "properties": {
    "addr:full":"5170 E Neitzel Rd Mooresville IN 46158",
    "addr:housenumber":"5170",
    "addr:postcode":"46158",
    "addr:street":"E Neitzel Rd",
    "iso:country":"US",
    "sg:address":"5170 E Neitzel Rd",
    "sg:city":"Mooresville",
    "sg:classifiers":[
        {
            "category":"Shopping",
            "subcategory":"Bicycles & Sporting Goods",
            "type":"Retail Goods"
        }
    ],
    "sg:phone":"+1 317 831 2803",
    "sg:postcode":"46158",
    "sg:province":"IN",
    "sg:tags":[
        "shop",
        "tack"
    ],
    "wof:name":"Spotted Rump Ranch Tack Shop",
    "wof:placetype":"venue"
},
  "geometry": {"coordinates":[-86.312999,39.596446],"type":"Point"}
}