{
  "type": "Feature",
  "properties": {
    "iso:country":"US",
    "sg:address":"5118 E Hall Creek Rd",
    "sg:city":"Saint Anthony",
    "sg:classifiers":[
        {
            "category":"Farming",
            "subcategory":"Livestock Farm",
            "type":"Manufacturing & Wholesale Goods"
        }
    ],
    "sg:phone":"+1 812 634 1973",
    "sg:postcode":"47575",
    "sg:province":"IN",
    "sg:tags":[
        "beef",
        "feedlot",
        "cattle"
    ],
    "wof:name":"Eugene Burke",
    "wof:placetype":"venue"
},
  "geometry": {"coordinates":[-86.808224,38.368308],"type":"Point"}
}