{
  "type": "Feature",
  "properties": {
    "iso:country":"US",
    "sg:address":"4901 E 82nd St",
    "sg:city":"Indianapolis",
    "sg:classifiers":[
        {
            "category":"Professional",
            "type":"Services"
        }
    ],
    "sg:phone":"+1 317 915 1617",
    "sg:postcode":"46250",
    "sg:province":"IN",
    "sg:tags":[
        "establishment"
    ],
    "wof:name":"Kids N Motion",
    "wof:placetype":"venue"
},
  "geometry": {"coordinates":[-86.088905,39.90568],"type":"Point"}
}