{
  "type": "Feature",
  "properties": {
    "addr:full":"525 N Country Club Rd Columbus IN 47201",
    "addr:housenumber":"525",
    "addr:postcode":"47201",
    "addr:street":"N Country Club Rd",
    "iso:country":"US",
    "sg:address":"525 N Country Club Rd",
    "sg:city":"Columbus",
    "sg:classifiers":[
        {
            "category":"Manufacturing",
            "subcategory":"Tools & Machinery",
            "type":"Manufacturing & Wholesale Goods"
        }
    ],
    "sg:phone":"+1 812 342 1585",
    "sg:postcode":"47201",
    "sg:province":"IN",
    "sg:tags":[
        "industry",
        "mfg"
    ],
    "wof:name":"Jus Fly Inc",
    "wof:placetype":"venue"
},
  "geometry": {"coordinates":[-86.02271500000001,39.201051],"type":"Point"}
}