{
  "type": "Feature",
  "properties": {
    "iso:country":"US",
    "sg:address":"1340 Co Rd 425 W",
    "sg:city":"Columbia City",
    "sg:classifiers":[
        {
            "category":"Building & Trades",
            "subcategory":"Landscaping Services",
            "type":"Services"
        }
    ],
    "sg:phone":"+1 260 248 8121",
    "sg:postcode":"46725",
    "sg:province":"IN",
    "sg:tags":[
        "landscape",
        "contractor"
    ],
    "wof:name":"Advanced Lawn & Landscape",
    "wof:placetype":"venue"
},
  "geometry": {"coordinates":[-85.572549,41.142345],"type":"Point"}
}