{
  "type": "Feature",
  "properties": {
    "iso:country":"US",
    "sg:address":"6280 E Co Rd 200 S",
    "sg:city":"Butlerville",
    "sg:classifiers":[
        {
            "category":"Organizations",
            "subcategory":"Religious Organization",
            "type":"Services"
        }
    ],
    "sg:phone":"+1 812 873 6475",
    "sg:postcode":"47223",
    "sg:province":"IN",
    "sg:tags":[
        "clergy"
    ],
    "wof:name":"Graham Baptist Parsonage",
    "wof:placetype":"venue"
},
  "geometry": {"coordinates":[-85.495632,38.956662],"type":"Point"}
}