{
  "type": "Feature",
  "properties": {
    "iso:country":"US",
    "sg:address":"6545 Guion Rd",
    "sg:city":"Indianapolis",
    "sg:classifiers":[
        {
            "category":"Autos & Motor Vehicles",
            "subcategory":"Automobile Sales",
            "type":"Retail Goods"
        }
    ],
    "sg:phone":"+1 317 297 2177",
    "sg:postcode":"46268",
    "sg:province":"IN",
    "sg:tags":[
        "car",
        "equipment",
        "race",
        "performance",
        "sport",
        "racing"
    ],
    "wof:name":"Mark One Composites",
    "wof:placetype":"venue"
},
  "geometry": {"coordinates":[-86.23156,39.87272],"type":"Point"}
}