{
  "type": "Feature",
  "properties": {
    "iso:country":"US",
    "sg:address":"9856 N State Rd 66",
    "sg:city":"Tell City",
    "sg:classifiers":[
        {
            "category":"Manufacturing",
            "subcategory":"Metals",
            "type":"Manufacturing & Wholesale Goods"
        }
    ],
    "sg:phone":"+1 812 547 1580",
    "sg:postcode":"47586",
    "sg:province":"IN",
    "sg:tags":[
        "foundry"
    ],
    "wof:name":"Waupaca Foundry Inc",
    "wof:placetype":"venue"
},
  "geometry": {"coordinates":[-86.532567,37.990804],"type":"Point"}
}