{
  "type": "Feature",
  "properties": {
    "addr:full":"6225 Stellhorn Rd Fort Wayne IN 46815",
    "addr:housenumber":"6225",
    "addr:postcode":"46815",
    "addr:street":"Stellhorn Rd",
    "iso:country":"US",
    "sg:address":"6225 Stellhorn Rd",
    "sg:city":"Fort Wayne",
    "sg:classifiers":[
        {
            "category":"Banks & Credit Unions",
            "subcategory":"Bank",
            "type":"Services"
        }
    ],
    "sg:phone":"+1 260 427 8146",
    "sg:postcode":"46815",
    "sg:province":"IN",
    "wof:name":"Bank One",
    "wof:placetype":"venue"
},
  "geometry": {"coordinates":[-85.065707,41.12028],"type":"Point"}
}