{
  "type": "Feature",
  "properties": {
    "iso:country":"US",
    "sg:address":"6320 Brixton Ln",
    "sg:city":"Indianapolis",
    "sg:classifiers":[
        {
            "category":"Shopping",
            "subcategory":"Computers & Home Electronics",
            "type":"Retail Goods"
        }
    ],
    "sg:phone":"+1 317 251 7466",
    "sg:postcode":"46220",
    "sg:province":"IN",
    "sg:tags":[
        "software"
    ],
    "wof:name":"Indyjax Software",
    "wof:placetype":"venue"
},
  "geometry": {"coordinates":[-86.076164,39.872568],"type":"Point"}
}