{
  "type": "Feature",
  "properties": {
    "iso:country":"US",
    "sg:address":"1191 Matthews Ct",
    "sg:city":"Greenwood",
    "sg:classifiers":[
        {
            "category":"Recreation",
            "type":"Entertainment"
        }
    ],
    "sg:phone":"+1 317 887 1621",
    "sg:postcode":"46131",
    "sg:province":"IN",
    "sg:tags":[
        "stable"
    ],
    "wof:name":"Copeland Horse Farm",
    "wof:placetype":"venue"
},
  "geometry": {"coordinates":[-86.083344,39.490391],"type":"Point"}
}