{
  "type": "Feature",
  "properties": {
    "iso:country":"US",
    "sg:address":"2801 E Bristol St",
    "sg:city":"Elkhart",
    "sg:classifiers":[
        {
            "category":"Building & Trades",
            "subcategory":"Construction",
            "type":"Services"
        }
    ],
    "sg:phone":"+1 574 262 4264",
    "sg:postcode":"46514",
    "sg:province":"IN",
    "sg:tags":[
        "general",
        "contractor"
    ],
    "wof:name":"Gary Floyd Construction",
    "wof:placetype":"venue"
},
  "geometry": {"coordinates":[-85.934618,41.702262],"type":"Point"}
}