{
  "type": "Feature",
  "properties": {
    "iso:country":"US",
    "sg:address":"8605 Samantha Dr",
    "sg:city":"Fort Wayne",
    "sg:classifiers":[
        {
            "category":"Wholesale",
            "subcategory":"Hardware",
            "type":"Manufacturing & Wholesale Goods"
        }
    ],
    "sg:phone":"+1 260 485 2422",
    "sg:postcode":"46835",
    "sg:province":"IN",
    "wof:name":"Mechanic Tools",
    "wof:placetype":"venue"
},
  "geometry": {"coordinates":[-85.068786,41.164983],"type":"Point"}
}