{
  "type": "Feature",
  "properties": {
    "iso:country":"US",
    "sg:address":"1638 E Saint Clair St",
    "sg:city":"Vincennes",
    "sg:classifiers":[
        {
            "category":"Retail",
            "subcategory":"Repair Shop",
            "type":"Services"
        }
    ],
    "sg:phone":"+1 812 882 0528",
    "sg:postcode":"47591",
    "sg:province":"IN",
    "sg:tags":[
        "sewing"
    ],
    "wof:name":"Changing Look Inc",
    "wof:placetype":"venue"
},
  "geometry": {"coordinates":[-87.507344,38.675671],"type":"Point"}
}