{
  "type": "Feature",
  "properties": {
    "iso:country":"US",
    "sg:address":"858 Rams Gates Rd",
    "sg:city":"Greenwood",
    "sg:classifiers":[
        {
            "category":"Building & Trades",
            "subcategory":"Construction",
            "type":"Services"
        }
    ],
    "sg:phone":"+1 317 865 0383",
    "sg:postcode":"46143",
    "sg:province":"IN",
    "sg:tags":[
        "roofing",
        "contractor"
    ],
    "wof:name":"K D Robinson Construction",
    "wof:placetype":"venue"
},
  "geometry": {"coordinates":[-86.176566,39.602112],"type":"Point"}
}