{
  "type": "Feature",
  "properties": {
    "addr:full":"8341 N Michigan Rd Indianapolis IN 46268",
    "addr:housenumber":"8341",
    "addr:postcode":"46268",
    "addr:street":"N Michigan Rd",
    "iso:country":"US",
    "sg:address":"8341 N Michigan Rd",
    "sg:city":"Indianapolis",
    "sg:classifiers":[
        {
            "category":"Shopping",
            "subcategory":"Florist",
            "type":"Retail Goods"
        }
    ],
    "sg:phone":"+1 317 824 1111",
    "sg:postcode":"46268",
    "sg:province":"IN",
    "wof:name":"Flowers By Valrie",
    "wof:placetype":"venue"
},
  "geometry": {"coordinates":[-86.22145500000001,39.909123],"type":"Point"}
}