{
  "type": "Feature",
  "properties": {
    "addr:full":"300 E Boyd Ave Greenfield IN 46140",
    "addr:housenumber":"300",
    "addr:postcode":"46140",
    "addr:street":"E Boyd Ave",
    "iso:country":"US",
    "sg:address":"300 E Boyd Ave",
    "sg:city":"Greenfield",
    "sg:classifiers":[
        {
            "category":"Health Services",
            "subcategory":"Doctor",
            "type":"Services"
        }
    ],
    "sg:phone":"+1 317 468 4599",
    "sg:postcode":"46140",
    "sg:province":"IN",
    "sg:tags":[
        "physician",
        "surgeon"
    ],
    "wof:name":"Patsy D Needham PC",
    "wof:placetype":"venue"
},
  "geometry": {"coordinates":[-85.76655700000001,39.793732],"type":"Point"}
}