{
  "type": "Feature",
  "properties": {
    "addr:full":"4041 E 30th St Indianapolis IN 46218",
    "addr:housenumber":"4041",
    "addr:postcode":"46218",
    "addr:street":"E 30Th St",
    "iso:country":"US",
    "sg:address":"4041 E 30th St",
    "sg:city":"Indianapolis",
    "sg:classifiers":[
        {
            "category":"Personal",
            "subcategory":"Barber",
            "type":"Services"
        }
    ],
    "sg:phone":"+1 317 547 8550",
    "sg:postcode":"46218",
    "sg:province":"IN",
    "wof:name":"Tee's Barber Shop",
    "wof:placetype":"venue"
},
  "geometry": {"coordinates":[-86.098281,39.810738],"type":"Point"}
}