{
  "type": "Feature",
  "properties": {
    "addr:full":"410 E Diamond Ave Evansville IN 47711",
    "addr:housenumber":"410",
    "addr:postcode":"47711",
    "addr:street":"E Diamond Ave",
    "iso:country":"US",
    "sg:address":"410 E Diamond Ave",
    "sg:city":"Evansville",
    "sg:classifiers":[
        {
            "category":"Shopping",
            "subcategory":"Department Store",
            "type":"Retail Goods"
        }
    ],
    "sg:phone":"+1 812 423 9315",
    "sg:postcode":"47711",
    "sg:province":"IN",
    "sg:tags":[
        "shop"
    ],
    "wof:name":"Big Lots",
    "wof:placetype":"venue"
},
  "geometry": {"coordinates":[-87.555149,37.999592],"type":"Point"}
}