{
  "type": "Feature",
  "properties": {
    "iso:country":"US",
    "sg:address":"3950 25th St",
    "sg:city":"Columbus",
    "sg:classifiers":[
        {
            "category":"Banks & Credit Unions",
            "subcategory":"Bank",
            "type":"Services"
        }
    ],
    "sg:phone":"+1 812 376 9201",
    "sg:postcode":"47203",
    "sg:province":"IN",
    "wof:name":"Salin Bank & Trust Co",
    "wof:placetype":"venue"
},
  "geometry": {"coordinates":[-85.877839,39.223534],"type":"Point"}
}