{
  "type": "Feature",
  "properties": {
    "iso:country":"US",
    "sg:address":"986 State Rd 13",
    "sg:city":"Lapel",
    "sg:classifiers":[
        {
            "category":"Personal",
            "subcategory":"Beauty Salon",
            "type":"Services"
        }
    ],
    "sg:phone":"+1 765 534 4559",
    "sg:postcode":"46051",
    "sg:province":"IN",
    "sg:tags":[
        "shop"
    ],
    "wof:name":"Country Corner Hair Design",
    "wof:placetype":"venue"
},
  "geometry": {"coordinates":[-85.863214,40.093933],"type":"Point"}
}