{
  "type": "Feature",
  "properties": {
    "iso:country":"US",
    "sg:address":"8425 Broadway",
    "sg:city":"Merrillville",
    "sg:classifiers":[
        {
            "category":"Restaurant",
            "type":"Food & Drink"
        }
    ],
    "sg:menulink":"http://www.allmenus.com/in/ross/88599-applebees/menu/",
    "sg:phone":"+1 219 736 1811",
    "sg:postcode":"46410",
    "sg:province":"IN",
    "sg:tags":[
        "burger",
        "american",
        "sandwich",
        "soup"
    ],
    "wof:name":"Applebee's",
    "wof:placetype":"venue"
},
  "geometry": {"coordinates":[-87.335904,41.475313],"type":"Point"}
}