{
  "type": "Feature",
  "properties": {
    "iso:country":"US",
    "sg:address":"6480 S Kidd Rd",
    "sg:city":"Connersville",
    "sg:classifiers":[
        {
            "category":"Farming",
            "subcategory":"Orchard",
            "type":"Manufacturing & Wholesale Goods"
        }
    ],
    "sg:phone":"+1 765 825 6106",
    "sg:postcode":"47331",
    "sg:province":"IN",
    "sg:tags":[
        "grove",
        "management"
    ],
    "wof:name":"Rusty Acres Orchard",
    "wof:placetype":"venue"
},
  "geometry": {"coordinates":[-85.065245,39.548157],"type":"Point"}
}