{
  "type": "Feature",
  "properties": {
    "addr:full":"206 W State St Princeton IN 47670",
    "addr:housenumber":"206",
    "addr:postcode":"47670",
    "addr:street":"W State St",
    "iso:country":"US",
    "sg:address":"206 W State St",
    "sg:city":"Princeton",
    "sg:classifiers":[
        {
            "category":"Real Estate",
            "subcategory":"Developer",
            "type":"Services"
        }
    ],
    "sg:phone":"+1 812 385 2438",
    "sg:postcode":"47670",
    "sg:province":"IN",
    "sg:tags":[
        "cemetery"
    ],
    "wof:name":"IOOF Cemetery",
    "wof:placetype":"venue"
},
  "geometry": {"coordinates":[-87.56994299999999,38.35632],"type":"Point"}
}