{
  "type": "Feature",
  "properties": {
    "iso:country":"US",
    "sg:address":"315 Maple St",
    "sg:city":"Crown Point",
    "sg:classifiers":[
        {
            "category":"Professional",
            "subcategory":"Management & Consulting",
            "type":"Services"
        }
    ],
    "sg:phone":"+1 219 663 7481",
    "sg:postcode":"46307",
    "sg:province":"IN",
    "sg:tags":[
        "retail",
        "direct",
        "sales"
    ],
    "wof:name":"Denise Grabski",
    "wof:placetype":"venue"
},
  "geometry": {"coordinates":[-87.369231,41.431366],"type":"Point"}
}