{
  "type": "Feature",
  "properties": {
    "iso:country":"US",
    "sg:address":"55169 Co Rd 3",
    "sg:city":"Elkhart",
    "sg:classifiers":[
        {
            "category":"Wholesale",
            "subcategory":"Machinery & Supplies",
            "type":"Manufacturing & Wholesale Goods"
        }
    ],
    "sg:phone":"+1 574 264 3437",
    "sg:postcode":"46514",
    "sg:province":"IN",
    "sg:tags":[
        "equipment",
        "hydraulic"
    ],
    "sg:website":"www.equalizersystems.com",
    "wof:name":"Equalizer Systems",
    "wof:placetype":"venue"
},
  "geometry": {"coordinates":[-86.023212,41.695188],"type":"Point"}
}