{
  "type": "Feature",
  "properties": {
    "iso:country":"US",
    "sg:address":"744 Clifty Dr",
    "sg:city":"Madison",
    "sg:classifiers":[
        {
            "category":"Cinema",
            "subcategory":"Movie Theater",
            "type":"Entertainment"
        }
    ],
    "sg:phone":"+1 812 273 6061",
    "sg:postcode":"47250",
    "sg:province":"IN",
    "wof:name":"Great Escapes",
    "wof:placetype":"venue"
},
  "geometry": {"coordinates":[-85.404169,38.774742],"type":"Point"}
}