{
  "type": "Feature",
  "properties": {
    "iso:country":"US",
    "sg:address":"5265 S Co Rd 60 SW",
    "sg:city":"Greensburg",
    "sg:classifiers":[
        {
            "category":"Building & Trades",
            "subcategory":"Construction",
            "type":"Services"
        }
    ],
    "sg:phone":"+1 812 662 9751",
    "sg:postcode":"47240",
    "sg:province":"IN",
    "sg:tags":[
        "excavating",
        "contractor"
    ],
    "wof:name":"Alpha Excavating Inc",
    "wof:placetype":"venue"
},
  "geometry": {"coordinates":[-85.510804,39.257852],"type":"Point"}
}