{
  "type": "Feature",
  "properties": {
    "addr:full":"440 N Meridian St Indianapolis IN 46204",
    "addr:housenumber":"440",
    "addr:postcode":"46204",
    "addr:street":"N Meridian St",
    "iso:country":"US",
    "sg:address":"440 N Meridian St",
    "sg:city":"Indianapolis",
    "sg:classifiers":[
        {
            "category":"Health Services",
            "subcategory":"Doctor",
            "type":"Services"
        }
    ],
    "sg:phone":"+1 317 635 7546",
    "sg:postcode":"46204",
    "sg:province":"IN",
    "sg:tags":[
        "physician",
        "surgeon"
    ],
    "wof:name":"Preferred Dermatologists",
    "wof:placetype":"venue"
},
  "geometry": {"coordinates":[-86.15789599999999,39.773993],"type":"Point"}
}