{
  "type": "Feature",
  "properties": {
    "iso:country":"US",
    "sg:address":"249 W Washington St",
    "sg:city":"Morgantown",
    "sg:classifiers":[
        {
            "category":"Shopping",
            "subcategory":"Gifts & Souvenirs",
            "type":"Retail Goods"
        }
    ],
    "sg:phone":"+1 812 597 2900",
    "sg:postcode":"46160",
    "sg:province":"IN",
    "sg:tags":[
        "collectible"
    ],
    "wof:name":"Looking Back At Debra's",
    "wof:placetype":"venue"
},
  "geometry": {"coordinates":[-86.263507,39.371214],"type":"Point"}
}