{
  "type": "Feature",
  "properties": {
    "iso:country":"US",
    "sg:address":"521 S 31st St",
    "sg:city":"South Bend",
    "sg:classifiers":[
        {
            "category":"Wholesale",
            "subcategory":"Vending Machines",
            "type":"Manufacturing & Wholesale Goods"
        }
    ],
    "sg:phone":"+1 574 234 3273",
    "sg:postcode":"46615",
    "sg:province":"IN",
    "sg:tags":[
        "operator"
    ],
    "wof:name":"Lil Snack Vending",
    "wof:placetype":"venue"
},
  "geometry": {"coordinates":[-86.203963,41.670634],"type":"Point"}
}