{
  "type": "Feature",
  "properties": {
    "iso:country":"US",
    "sg:address":"5915 S Emerson Ave",
    "sg:city":"Indianapolis",
    "sg:classifiers":[
        {
            "category":"Banks & Credit Unions",
            "subcategory":"Bank",
            "type":"Services"
        }
    ],
    "sg:phone":"+1 317 780 7600",
    "sg:postcode":"46237",
    "sg:province":"IN",
    "sg:tags":[
        "loan",
        "real estate"
    ],
    "wof:name":"Direct Mortgage Funding",
    "wof:placetype":"venue"
},
  "geometry": {"coordinates":[-86.082454,39.680853],"type":"Point"}
}