{
  "type": "Feature",
  "properties": {
    "iso:country":"US",
    "sg:address":"427 E Main St",
    "sg:city":"Attica",
    "sg:classifiers":[
        {
            "category":"Banks & Credit Unions",
            "subcategory":"Bank",
            "type":"Services"
        }
    ],
    "sg:phone":"+1 765 762 6727",
    "sg:postcode":"47918",
    "sg:province":"IN",
    "wof:name":"Fountain Trust Co",
    "wof:placetype":"venue"
},
  "geometry": {"coordinates":[-87.244965,40.29219],"type":"Point"}
}