{
  "type": "Feature",
  "properties": {
    "iso:country":"US",
    "sg:address":"3520 Calhoun St",
    "sg:city":"Indianapolis",
    "sg:classifiers":[
        {
            "category":"Real Estate",
            "subcategory":"Real Estate Operator",
            "type":"Services"
        }
    ],
    "sg:phone":"+1 317 783 7672",
    "sg:postcode":"46203",
    "sg:province":"IN",
    "sg:tags":[
        "apartment"
    ],
    "wof:name":"Grandville Cooperative Inc",
    "wof:placetype":"venue"
},
  "geometry": {"coordinates":[-86.106764,39.740452],"type":"Point"}
}