{
  "type": "Feature",
  "properties": {
    "iso:country":"US",
    "sg:address":"12730 Canyon Creek Blvd",
    "sg:city":"Fort Wayne",
    "sg:classifiers":[
        {
            "category":"Real Estate",
            "subcategory":"Real Estate Agent",
            "type":"Services"
        }
    ],
    "sg:phone":"+1 260 637 1404",
    "sg:postcode":"46845",
    "sg:province":"IN",
    "wof:name":"Susan Fyfe Appraisal Services",
    "wof:placetype":"venue"
},
  "geometry": {"coordinates":[-85.123994,41.20186],"type":"Point"}
}