{
  "type": "Feature",
  "properties": {
    "iso:country":"US",
    "sg:address":"1233 W Hively Ave",
    "sg:city":"Elkhart",
    "sg:classifiers":[
        {
            "category":"Wholesale",
            "subcategory":"Construction Materials",
            "type":"Manufacturing & Wholesale Goods"
        }
    ],
    "sg:phone":"+1 574 295 5228",
    "sg:postcode":"46517",
    "sg:province":"IN",
    "sg:tags":[
        "molding"
    ],
    "wof:name":"MJB Wood Grp",
    "wof:placetype":"venue"
},
  "geometry": {"coordinates":[-85.986109,41.659574],"type":"Point"}
}