{
  "type": "Feature",
  "properties": {
    "addr:full":"218 N 250 W Valparaiso IN 46385",
    "addr:housenumber":"218",
    "addr:postcode":"46385",
    "addr:street":"N 250 W",
    "iso:country":"US",
    "sg:address":"218 N 250 W",
    "sg:city":"Valparaiso",
    "sg:classifiers":[
        {
            "category":"Shopping",
            "subcategory":"Bicycles & Sporting Goods",
            "type":"Retail Goods"
        }
    ],
    "sg:phone":"+1 219 462 7181",
    "sg:postcode":"46385",
    "sg:province":"IN",
    "wof:name":"Bullshooter Supply",
    "wof:placetype":"venue"
},
  "geometry": {"coordinates":[-87.11427500000001,41.466054],"type":"Point"}
}