{
  "type": "Feature",
  "properties": {
    "iso:country":"US",
    "sg:address":"218 N 250 W",
    "sg:city":"Valparaiso",
    "sg:classifiers":[
        {
            "category":"Shopping",
            "subcategory":"Bicycles & Sporting Goods",
            "type":"Retail Goods"
        }
    ],
    "sg:phone":"+1 219 462 7181",
    "sg:postcode":"46385",
    "sg:province":"IN",
    "wof:name":"Bullshooter Supply",
    "wof:placetype":"venue"
},
  "geometry": {"coordinates":[-87.114275,41.466054],"type":"Point"}
}