{
  "type": "Feature",
  "properties": {
    "iso:country":"US",
    "sg:address":"2210 Sagamore Pkwy S",
    "sg:city":"Lafayette",
    "sg:classifiers":[
        {
            "category":"Restaurant",
            "type":"Food & Drink"
        }
    ],
    "sg:phone":"+1 765 474 7200",
    "sg:postcode":"47905",
    "sg:province":"IN",
    "wof:name":"Old Country Restaurant II",
    "wof:placetype":"venue"
},
  "geometry": {"coordinates":[-86.856119,40.395274],"type":"Point"}
}