{
  "type": "Feature",
  "properties": {
    "iso:country":"US",
    "sg:address":"809 Sibley St",
    "sg:city":"Hammond",
    "sg:classifiers":[
        {
            "category":"Autos & Motor Vehicles",
            "subcategory":"Automobile Sales",
            "type":"Retail Goods"
        }
    ],
    "sg:phone":"+1 219 933 0307",
    "sg:postcode":"46320",
    "sg:province":"IN",
    "sg:tags":[
        "car",
        "used",
        "dealer"
    ],
    "wof:name":"Sanchezs Auto Sales",
    "wof:placetype":"venue"
},
  "geometry": {"coordinates":[-87.50632,41.613702],"type":"Point"}
}