{
  "type": "Feature",
  "properties": {
    "iso:country":"US",
    "sg:address":"8270 State Rd 64",
    "sg:city":"Georgetown",
    "sg:classifiers":[
        {
            "category":"Personal",
            "subcategory":"Beauty Salon",
            "type":"Services"
        }
    ],
    "sg:phone":"+1 812 951 2737",
    "sg:postcode":"47122",
    "sg:province":"IN",
    "sg:tags":[
        "manicuring"
    ],
    "wof:name":"Classy Nails & Spa Too",
    "wof:placetype":"venue"
},
  "geometry": {"coordinates":[-85.96238,38.295216],"type":"Point"}
}