{
  "type": "Feature",
  "properties": {
    "addr:full":"Graham Plz Bloomington IN 47401",
    "addr:postcode":"47401",
    "addr:street":"Graham Plz",
    "iso:country":"US",
    "sg:address":"Graham Plz",
    "sg:city":"Bloomington",
    "sg:classifiers":[
        {
            "category":"Professional",
            "subcategory":"Accounting & Tax Preparation",
            "type":"Services"
        },
        {
            "category":"Professional",
            "subcategory":"Lawyer & Legal Services",
            "type":"Services"
        }
    ],
    "sg:phone":"+1 812 332 0557",
    "sg:postcode":"47401",
    "sg:province":"IN",
    "sg:tags":[
        "divorce",
        "accountant",
        "law",
        "family"
    ],
    "wof:name":"Miller Stephen R CPA",
    "wof:placetype":"venue"
},
  "geometry": {"coordinates":[-86.496498,39.135899],"type":"Point"}
}