{
  "type": "Feature",
  "properties": {
    "iso:country":"US",
    "sg:address":"3101 W 5th Ave",
    "sg:city":"Gary",
    "sg:classifiers":[
        {
            "category":"Restaurant",
            "type":"Food & Drink"
        }
    ],
    "sg:phone":"+1 219 977 1301",
    "sg:postcode":"46406",
    "sg:province":"IN",
    "wof:name":"Joy Fish & Chicken",
    "wof:placetype":"venue"
},
  "geometry": {"coordinates":[-87.375778,41.60191],"type":"Point"}
}