{
  "type": "Feature",
  "properties": {
    "iso:country":"US",
    "sg:address":"301 Henry St",
    "sg:city":"North Vernon",
    "sg:classifiers":[
        {
            "category":"Health Services",
            "subcategory":"Doctor",
            "type":"Services"
        }
    ],
    "sg:phone":"+1 812 346 6200",
    "sg:postcode":"47265",
    "sg:province":"IN",
    "sg:tags":[
        "physician",
        "surgeon"
    ],
    "wof:name":"Southern Indiana Orthopedics",
    "wof:placetype":"venue"
},
  "geometry": {"coordinates":[-85.643841,39.011444],"type":"Point"}
}