{
  "type": "Feature",
  "properties": {
    "addr:full":"60 N 1st St Zionsville IN 46077",
    "addr:housenumber":"60",
    "addr:postcode":"46077",
    "addr:street":"N 1St St",
    "iso:country":"US",
    "sg:address":"60 N 1st St",
    "sg:city":"Zionsville",
    "sg:classifiers":[
        {
            "category":"Insurance",
            "subcategory":"Insurance Agent",
            "type":"Services"
        }
    ],
    "sg:phone":"+1 317 733 1402",
    "sg:postcode":"46077",
    "sg:province":"IN",
    "wof:name":"Judy Cummings",
    "wof:placetype":"venue"
},
  "geometry": {"coordinates":[-86.262749,39.951932],"type":"Point"}
}