{
  "type": "Feature",
  "properties": {
    "iso:country":"US",
    "sg:address":"204 W Mishawaka Ave",
    "sg:city":"Mishawaka",
    "sg:classifiers":[
        {
            "category":"Personal",
            "subcategory":"Beauty Salon",
            "type":"Services"
        }
    ],
    "sg:phone":"+1 574 257 4283",
    "sg:postcode":"46545",
    "sg:province":"IN",
    "sg:tags":[
        "shop"
    ],
    "wof:name":"Diana Olivier",
    "wof:placetype":"venue"
},
  "geometry": {"coordinates":[-86.184737,41.666194],"type":"Point"}
}