{
  "type": "Feature",
  "properties": {
    "iso:country":"US",
    "sg:address":"434 Canal Court S Dr",
    "sg:city":"Indianapolis",
    "sg:classifiers":[
        {
            "category":"Real Estate",
            "subcategory":"Real Estate Operator",
            "type":"Services"
        }
    ],
    "sg:phone":"+1 317 636 2126",
    "sg:postcode":"46202",
    "sg:province":"IN",
    "sg:tags":[
        "apartment"
    ],
    "wof:name":"Gardens Canal Court",
    "wof:placetype":"venue"
},
  "geometry": {"coordinates":[-86.166696,39.777905],"type":"Point"}
}