{
  "type": "Feature",
  "properties": {
    "iso:country":"US",
    "sg:address":"1525 US Hwy 41",
    "sg:city":"Schererville",
    "sg:classifiers":[
        {
            "category":"Personal",
            "subcategory":"Tanning Parlor",
            "type":"Services"
        }
    ],
    "sg:phone":"+1 219 864 8688",
    "sg:postcode":"46375",
    "sg:province":"IN",
    "sg:tags":[
        "salon"
    ],
    "sg:website":"www.executivetans.com",
    "wof:name":"Executive Tans",
    "wof:placetype":"venue"
},
  "geometry": {"coordinates":[-87.470821,41.491927],"type":"Point"}
}