{
  "type": "Feature",
  "properties": {
    "iso:country":"US",
    "sg:address":"602 N 5th St",
    "sg:city":"Middletown",
    "sg:classifiers":[
        {
            "category":"Health Services",
            "subcategory":"Doctor",
            "type":"Services"
        }
    ],
    "sg:phone":"+1 765 354 2062",
    "sg:postcode":"47356",
    "sg:province":"IN",
    "sg:tags":[
        "clinic"
    ],
    "wof:name":"Middletown Family Practice",
    "wof:placetype":"venue"
},
  "geometry": {"coordinates":[-85.53347599999999,40.062448],"type":"Point"}
}