{
  "type": "Feature",
  "properties": {
    "iso:country":"US",
    "sg:address":"9604 Coldwater Rd",
    "sg:city":"Fort Wayne",
    "sg:classifiers":[
        {
            "category":"Professional",
            "subcategory":"Lawyer & Legal Services",
            "type":"Services"
        }
    ],
    "sg:phone":"+1 260 490 1222",
    "sg:postcode":"46825",
    "sg:province":"IN",
    "sg:tags":[
        "attorney"
    ],
    "wof:name":"Butz & Hiestand",
    "wof:placetype":"venue"
},
  "geometry": {"coordinates":[-85.132606,41.166198],"type":"Point"}
}