{
  "type": "Feature",
  "properties": {
    "addr:full":"165 S Boehning St Indianapolis IN 46219",
    "addr:housenumber":"165",
    "addr:postcode":"46219",
    "addr:street":"S Boehning St",
    "iso:country":"US",
    "sg:address":"165 S Boehning St",
    "sg:city":"Indianapolis",
    "sg:classifiers":[
        {
            "category":"Professional",
            "subcategory":"Business Services",
            "type":"Services"
        }
    ],
    "sg:phone":"+1 317 898 9773",
    "sg:postcode":"46219",
    "sg:province":"IN",
    "sg:website":"www.abcoinspections.com",
    "wof:name":"Abco Indy Home Inspections",
    "wof:placetype":"venue"
},
  "geometry": {"coordinates":[-86.01097,39.768686],"type":"Point"}
}