{
  "type": "Feature",
  "properties": {
    "iso:country":"US",
    "sg:address":"579 W Maple St",
    "sg:city":"Wabash",
    "sg:classifiers":[
        {
            "category":"Personal",
            "subcategory":"Beauty Salon",
            "type":"Services"
        }
    ],
    "sg:phone":"+1 260 563 1645",
    "sg:postcode":"46992",
    "sg:province":"IN",
    "sg:tags":[
        "shop"
    ],
    "wof:name":"Maricias Beauty Salon",
    "wof:placetype":"venue"
},
  "geometry": {"coordinates":[-85.830929,40.799806],"type":"Point"}
}