{
  "type": "Feature",
  "properties": {
    "iso:country":"US",
    "sg:address":"2920 N Keystone Ave",
    "sg:city":"Indianapolis",
    "sg:classifiers":[
        {
            "category":"Communications",
            "type":"Services"
        }
    ],
    "sg:phone":"+1 317 926 2111",
    "sg:postcode":"46218",
    "sg:province":"IN",
    "wof:name":"Westek Communications",
    "wof:placetype":"venue"
},
  "geometry": {"coordinates":[-86.121673,39.810376],"type":"Point"}
}