{
  "type": "Feature",
  "properties": {
    "iso:country":"US",
    "sg:address":"9475 State Rd 7",
    "sg:city":"Elizabethtown",
    "sg:classifiers":[
        {
            "category":"Autos & Motor Vehicles",
            "subcategory":"Automobile Sales",
            "type":"Retail Goods"
        }
    ],
    "sg:phone":"+1 812 579 0040",
    "sg:postcode":"47232",
    "sg:province":"IN",
    "sg:tags":[
        "car",
        "dealer"
    ],
    "wof:name":"Garris Auto Sales & Body",
    "wof:placetype":"venue"
},
  "geometry": {"coordinates":[-85.76315200000001,39.122139],"type":"Point"}
}