{
  "type": "Feature",
  "properties": {
    "iso:country":"US",
    "sg:address":"1604 E Main St",
    "sg:city":"Richmond",
    "sg:classifiers":[
        {
            "category":"Banks & Credit Unions",
            "subcategory":"Investment Brokerage",
            "type":"Services"
        }
    ],
    "sg:phone":"+1 765 962 6161",
    "sg:postcode":"47374",
    "sg:province":"IN",
    "sg:tags":[
        "stock",
        "bond"
    ],
    "wof:name":"Edward Jones Co",
    "wof:placetype":"venue"
},
  "geometry": {"coordinates":[-84.87953400000001,39.829765],"type":"Point"}
}