{
  "type": "Feature",
  "properties": {
    "iso:country":"US",
    "sg:address":"984 N Main St",
    "sg:city":"Bluffton",
    "sg:classifiers":[
        {
            "category":"Restaurant",
            "type":"Food & Drink"
        }
    ],
    "sg:menulink":"http://www.allmenus.com/in/lancaster/186265-mcdonalds/menu/",
    "sg:postcode":"46714",
    "sg:province":"IN",
    "sg:tags":[
        "burger",
        "american"
    ],
    "wof:name":"McDonald's",
    "wof:placetype":"venue"
},
  "geometry": {"coordinates":[-85.16671599999999,40.755933],"type":"Point"}
}