{
  "type": "Feature",
  "properties": {
    "addr:full":"4103 Evans Ave Valparaiso IN 46383",
    "addr:housenumber":"4103",
    "addr:postcode":"46383",
    "addr:street":"Evans Ave",
    "iso:country":"US",
    "sg:address":"4103 Evans Ave",
    "sg:city":"Valparaiso",
    "sg:classifiers":[
        {
            "category":"Manufacturing",
            "subcategory":"Chemicals & Compounds",
            "type":"Manufacturing & Wholesale Goods"
        }
    ],
    "sg:phone":"+1 219 531 4196",
    "sg:postcode":"46383",
    "sg:province":"IN",
    "sg:tags":[
        "gas"
    ],
    "wof:name":"Industrial Gas Svc Inc",
    "wof:placetype":"venue"
},
  "geometry": {"coordinates":[-87.011897,41.478204],"type":"Point"}
}