{
  "type": "Feature",
  "properties": {
    "iso:country":"US",
    "sg:address":"3929 Ann Ave",
    "sg:city":"Lafayette",
    "sg:classifiers":[
        {
            "category":"Real Estate",
            "subcategory":"Developer",
            "type":"Services"
        }
    ],
    "sg:phone":"+1 765 446 2663",
    "sg:postcode":"47905",
    "sg:province":"IN",
    "sg:tags":[
        "mobile",
        "home"
    ],
    "wof:name":"Vista Point Estates",
    "wof:placetype":"venue"
},
  "geometry": {"coordinates":[-86.832858,40.383511],"type":"Point"}
}