{
  "type": "Feature",
  "properties": {
    "iso:country":"US",
    "sg:address":"450 N 9th St",
    "sg:city":"Elwood",
    "sg:classifiers":[
        {
            "category":"Manufacturing",
            "subcategory":"Metals",
            "type":"Manufacturing & Wholesale Goods"
        }
    ],
    "sg:phone":"+1 765 552 5047",
    "sg:postcode":"46036",
    "sg:province":"IN",
    "sg:tags":[
        "plating"
    ],
    "sg:website":"www.stateplating.com",
    "wof:name":"State Plating Inc",
    "wof:placetype":"venue"
},
  "geometry": {"coordinates":[-85.850264,40.280113],"type":"Point"}
}