{
  "type": "Feature",
  "properties": {
    "addr:full":"5933 W 71st St Indianapolis IN 46278",
    "addr:housenumber":"5933",
    "addr:postcode":"46278",
    "addr:street":"W 71St St",
    "iso:country":"US",
    "sg:address":"5933 W 71st St",
    "sg:city":"Indianapolis",
    "sg:classifiers":[
        {
            "category":"Professional",
            "subcategory":"Testing Lab",
            "type":"Services"
        }
    ],
    "sg:phone":"+1 317 290 1471",
    "sg:postcode":"46278",
    "sg:province":"IN",
    "sg:tags":[
        "analytical",
        "laboratory"
    ],
    "wof:name":"Environmental Service Group",
    "wof:placetype":"venue"
},
  "geometry": {"coordinates":[-86.26545299999999,39.880798],"type":"Point"}
}