{
  "type": "Feature",
  "properties": {
    "iso:country":"US",
    "sg:address":"951 N 13th St",
    "sg:city":"Decatur",
    "sg:classifiers":[
        {
            "category":"Retail",
            "subcategory":"Auto Repair",
            "type":"Services"
        }
    ],
    "sg:phone":"+1 260 724 4747",
    "sg:postcode":"46733",
    "sg:province":"IN",
    "sg:tags":[
        "automobile",
        "lubrication"
    ],
    "wof:name":"Quick Stop Oil Change",
    "wof:placetype":"venue"
},
  "geometry": {"coordinates":[-84.937812,40.838947],"type":"Point"}
}