{
  "type": "Feature",
  "properties": {
    "iso:country":"US",
    "sg:address":"2300 Ohio Ave",
    "sg:city":"Connersville",
    "sg:classifiers":[
        {
            "category":"Government",
            "subcategory":"Office",
            "type":"Public Place"
        }
    ],
    "sg:phone":"+1 765 825 2621",
    "sg:postcode":"47331",
    "sg:province":"IN",
    "sg:tags":[
        "govt",
        "city"
    ],
    "wof:name":"Utilities-Service Plant",
    "wof:placetype":"venue"
},
  "geometry": {"coordinates":[-85.130378,39.662817],"type":"Point"}
}