{
  "type": "Feature",
  "properties": {
    "addr:full":"10513 E 500 N Lafayette IN 47905",
    "addr:housenumber":"10513",
    "addr:postcode":"47905",
    "addr:street":"E 500 N",
    "iso:country":"US",
    "sg:address":"10513 E 500 N",
    "sg:city":"Lafayette",
    "sg:classifiers":[
        {
            "category":"Farming",
            "subcategory":"Livestock Farm",
            "type":"Manufacturing & Wholesale Goods"
        }
    ],
    "sg:phone":"+1 765 589 3779",
    "sg:postcode":"47905",
    "sg:province":"IN",
    "sg:tags":[
        "feedlot",
        "cattle"
    ],
    "wof:name":"Nathan Rinehart",
    "wof:placetype":"venue"
},
  "geometry": {"coordinates":[-86.700771,40.489517],"type":"Point"}
}