{
  "type": "Feature",
  "properties": {
    "iso:country":"US",
    "sg:address":"5353 W Southern Ave",
    "sg:city":"Indianapolis",
    "sg:classifiers":[
        {
            "category":"Manufacturing",
            "subcategory":"Chemicals & Compounds",
            "type":"Manufacturing & Wholesale Goods"
        },
        {
            "category":"Wholesale",
            "subcategory":"Machinery & Supplies",
            "type":"Manufacturing & Wholesale Goods"
        },
        {
            "category":"Wholesale",
            "subcategory":"Chemicals & Plastics",
            "type":"Manufacturing & Wholesale Goods"
        },
        {
            "category":"Utilities",
            "subcategory":"Natural Gas",
            "type":"Services"
        }
    ],
    "sg:phone":"+1 317 248 0651",
    "sg:postcode":"46241",
    "sg:province":"IN",
    "sg:tags":[
        "gas-industrial",
        "propane",
        "bulk",
        "medical-cylinder",
        "chemicals-wholesale",
        "helium",
        "manufacturer"
    ],
    "wof:name":"American Welding and Gas",
    "wof:placetype":"venue"
},
  "geometry": {"coordinates":[-86.251603,39.728098],"type":"Point"}
}