{
  "type": "Feature",
  "properties": {
    "iso:country":"US",
    "sg:address":"1808 N 1575 W",
    "sg:city":"Deputy",
    "sg:phone":"+1 812 866 5810",
    "sg:postcode":"47230",
    "sg:province":"IN",
    "sg:tags":[
        "farm",
        "corn",
        "soybean"
    ],
    "wof:name":"Michael Owens",
    "wof:placetype":"venue"
},
  "geometry": {"coordinates":[-85.67912,38.766705],"type":"Point"}
}