{
  "type": "Feature",
  "properties": {
    "iso:country":"US",
    "sg:address":"925 Morningside Dr",
    "sg:city":"Lebanon",
    "sg:classifiers":[
        {
            "category":"Banks & Credit Unions",
            "subcategory":"Bank",
            "type":"Services"
        }
    ],
    "sg:phone":"+1 765 482 3575",
    "sg:postcode":"46052",
    "sg:province":"IN",
    "sg:tags":[
        "loan",
        "real estate"
    ],
    "wof:name":"Landmark Financial Svc",
    "wof:placetype":"venue"
},
  "geometry": {"coordinates":[-86.455461,40.054374],"type":"Point"}
}