{
  "type": "Feature",
  "properties": {
    "addr:full":"1908 E Riverside Dr Evansville IN 47714",
    "addr:housenumber":"1908",
    "addr:postcode":"47714",
    "addr:street":"E Riverside Dr",
    "iso:country":"US",
    "sg:address":"1908 E Riverside Dr",
    "sg:city":"Evansville",
    "sg:classifiers":[
        {
            "category":"Social Services",
            "type":"Services"
        }
    ],
    "sg:phone":"+1 812 477 5199",
    "sg:postcode":"47714",
    "sg:province":"IN",
    "sg:tags":[
        "counselor",
        "marriage",
        "family"
    ],
    "wof:name":"Center For Marital-Individual",
    "wof:placetype":"venue"
},
  "geometry": {"coordinates":[-87.53168100000001,37.944565],"type":"Point"}
}