{
  "type": "Feature",
  "properties": {
    "iso:country":"US",
    "sg:address":"2795 Jaquelyn Ct",
    "sg:city":"Kokomo",
    "sg:classifiers":[
        {
            "category":"Utilities",
            "subcategory":"Telephone",
            "type":"Services"
        }
    ],
    "sg:phone":"+1 765 455 0908",
    "sg:postcode":"46902",
    "sg:province":"IN",
    "sg:tags":[
        "communications"
    ],
    "wof:name":"Campuslife Online",
    "wof:placetype":"venue"
},
  "geometry": {"coordinates":[-86.052424,40.436465],"type":"Point"}
}