{
  "type": "Feature",
  "properties": {
    "addr:full":"10 N Eastern Ave Indianapolis IN 46201",
    "addr:housenumber":"10",
    "addr:postcode":"46201",
    "addr:street":"N Eastern Ave",
    "iso:country":"US",
    "sg:address":"10 N Eastern Ave",
    "sg:city":"Indianapolis",
    "sg:classifiers":[
        {
            "category":"Social Services",
            "subcategory":"Child Care",
            "type":"Services"
        }
    ],
    "sg:phone":"+1 317 635 7026",
    "sg:postcode":"46201",
    "sg:province":"IN",
    "wof:name":"Powell's Daycare",
    "wof:placetype":"venue"
},
  "geometry": {"coordinates":[-86.117696,39.771709],"type":"Point"}
}