{
  "type": "Feature",
  "properties": {
    "iso:country":"US",
    "sg:address":"110 N Main St",
    "sg:city":"Monticello",
    "sg:classifiers":[
        {
            "category":"Government",
            "subcategory":"Office",
            "type":"Public Place"
        }
    ],
    "sg:phone":"+1 574 583 5771",
    "sg:postcode":"47960",
    "sg:province":"IN",
    "sg:tags":[
        "county",
        "taxation"
    ],
    "wof:name":"White County Treasurer",
    "wof:placetype":"venue"
},
  "geometry": {"coordinates":[-86.761999,40.745401],"type":"Point"}
}