{
  "type": "Feature",
  "properties": {
    "iso:country":"US",
    "sg:address":"427 E Broadway",
    "sg:city":"Logansport",
    "sg:classifiers":[
        {
            "category":"Shopping",
            "subcategory":"Clothing, Apparel, & Fashions",
            "type":"Retail Goods"
        }
    ],
    "sg:phone":"+1 574 722 6200",
    "sg:postcode":"46947",
    "sg:province":"IN",
    "sg:tags":[
        "furnishing"
    ],
    "wof:name":"J Adkins Broadway At Fifth",
    "wof:placetype":"venue"
},
  "geometry": {"coordinates":[-86.364581,40.754154],"type":"Point"}
}