{
  "type": "Feature",
  "properties": {
    "iso:country":"US",
    "sg:address":"6501 E Washington St",
    "sg:city":"Indianapolis",
    "sg:classifiers":[
        {
            "category":"Restaurant",
            "type":"Food & Drink"
        }
    ],
    "sg:menulink":"http://www.allmenus.com/in/warren/208062-taco-bell/menu/",
    "sg:phone":"+1 317 353 1761",
    "sg:postcode":"46219",
    "sg:province":"IN",
    "sg:tags":[
        "mexican"
    ],
    "wof:name":"Taco Bell",
    "wof:placetype":"venue"
},
  "geometry": {"coordinates":[-86.056135,39.77152],"type":"Point"}
}