{
  "type": "Feature",
  "properties": {
    "iso:country":"US",
    "sg:address":"7020 N Michigan Rd",
    "sg:city":"Indianapolis",
    "sg:classifiers":[
        {
            "category":"Food & Beverages",
            "subcategory":"Liquor & Beverages",
            "type":"Retail Goods"
        }
    ],
    "sg:phone":"+1 317 291 3070",
    "sg:postcode":"46268",
    "sg:province":"IN",
    "wof:name":"Twenty First Amendment",
    "wof:placetype":"venue"
},
  "geometry": {"coordinates":[-86.209298,39.883255],"type":"Point"}
}