{
  "type": "Feature",
  "properties": {
    "addr:full":"215 S 2nd St Elkhart IN 46516",
    "addr:housenumber":"215",
    "addr:postcode":"46516",
    "addr:street":"S 2Nd St",
    "iso:country":"US",
    "sg:address":"215 S 2nd St",
    "sg:city":"Elkhart",
    "sg:classifiers":[
        {
            "category":"Banks & Credit Unions",
            "subcategory":"Bank",
            "type":"Services"
        }
    ],
    "sg:phone":"+1 574 293 9199",
    "sg:postcode":"46516",
    "sg:province":"IN",
    "sg:tags":[
        "loan",
        "real estate"
    ],
    "wof:name":"Unlimited Mortgage",
    "wof:placetype":"venue"
},
  "geometry": {"coordinates":[-85.974299,41.685498],"type":"Point"}
}