{
  "type": "Feature",
  "properties": {
    "iso:country":"US",
    "sg:address":"811 Lincoln Hwy W",
    "sg:city":"New Haven",
    "sg:classifiers":[
        {
            "category":"Shopping",
            "subcategory":"Computers & Home Electronics",
            "type":"Retail Goods"
        }
    ],
    "sg:phone":"+1 260 493 4305",
    "sg:postcode":"46774",
    "sg:province":"IN",
    "sg:tags":[
        "equipment",
        "electronic",
        "supply"
    ],
    "wof:name":"Radio Shack",
    "wof:placetype":"venue"
},
  "geometry": {"coordinates":[-85.03734,41.069898],"type":"Point"}
}