{
  "type": "Feature",
  "properties": {
    "iso:country":"US",
    "sg:address":"7 Purdue Airport",
    "sg:city":"West Lafayette",
    "sg:classifiers":[
        {
            "category":"Building & Trades",
            "subcategory":"Construction",
            "type":"Services"
        }
    ],
    "sg:phone":"+1 765 746 1555",
    "sg:postcode":"47906",
    "sg:province":"IN",
    "sg:tags":[
        "general",
        "contractor"
    ],
    "wof:name":"Spire Group",
    "wof:placetype":"venue"
},
  "geometry": {"coordinates":[-86.934926,40.416141],"type":"Point"}
}