{
  "type": "Feature",
  "properties": {
    "iso:country":"US",
    "sg:address":"1428 S Main St",
    "sg:city":"Kokomo",
    "sg:classifiers":[
        {
            "category":"Professional",
            "subcategory":"Accounting & Tax Preparation",
            "type":"Services"
        }
    ],
    "sg:phone":"+1 765 868 2380",
    "sg:postcode":"46902",
    "sg:province":"IN",
    "sg:tags":[
        "accountant"
    ],
    "wof:name":"Kelly & Co",
    "wof:placetype":"venue"
},
  "geometry": {"coordinates":[-86.130925,40.469832],"type":"Point"}
}