{
  "type": "Feature",
  "properties": {
    "iso:country":"US",
    "sg:address":"902 E Court Ave",
    "sg:city":"Jeffersonville",
    "sg:classifiers":[
        {
            "category":"Manufacturing",
            "subcategory":"Signs",
            "type":"Manufacturing & Wholesale Goods"
        }
    ],
    "sg:phone":"+1 812 288 9480",
    "sg:postcode":"47130",
    "sg:province":"IN",
    "sg:tags":[
        "advertising",
        "specialty"
    ],
    "wof:name":"Davis Humbert Consulting Grp",
    "wof:placetype":"venue"
},
  "geometry": {"coordinates":[-85.729984,38.280402],"type":"Point"}
}