{
  "type": "Feature",
  "properties": {
    "iso:country":"US",
    "sg:address":"3615 N Clinton St",
    "sg:city":"Fort Wayne",
    "sg:classifiers":[
        {
            "category":"Shopping",
            "subcategory":"Tobacco",
            "type":"Retail Goods"
        }
    ],
    "sg:phone":"+1 260 484 4711",
    "sg:postcode":"46805",
    "sg:province":"IN",
    "sg:tags":[
        "cigarette",
        "cigar",
        "dealer"
    ],
    "wof:name":"Rainbow Palace",
    "wof:placetype":"venue"
},
  "geometry": {"coordinates":[-85.136312,41.109517],"type":"Point"}
}