{
  "type": "Feature",
  "properties": {
    "addr:full":"1423 S Green River Rd Evansville IN 47715",
    "addr:housenumber":"1423",
    "addr:postcode":"47715",
    "addr:street":"S Green River Rd",
    "iso:country":"US",
    "sg:address":"1423 S Green River Rd",
    "sg:city":"Evansville",
    "sg:classifiers":[
        {
            "category":"Autos & Motor Vehicles",
            "subcategory":"Recreational Vehicle Sales",
            "type":"Retail Goods"
        }
    ],
    "sg:phone":"+1 812 476 6814",
    "sg:postcode":"47715",
    "sg:province":"IN",
    "wof:name":"Melchiors Trailers",
    "wof:placetype":"venue"
},
  "geometry": {"coordinates":[-87.492874,37.957132],"type":"Point"}
}