{
  "type": "Feature",
  "properties": {
    "iso:country":"US",
    "sg:address":"4012 W 32nd St",
    "sg:city":"Anderson",
    "sg:classifiers":[
        {
            "category":"Retail",
            "subcategory":"Animal Services",
            "type":"Services"
        }
    ],
    "sg:phone":"+1 765 642 9447",
    "sg:postcode":"46011",
    "sg:province":"IN",
    "sg:tags":[
        "pet"
    ],
    "wof:name":"Dogs Against Drugs Law",
    "wof:placetype":"venue"
},
  "geometry": {"coordinates":[-85.747851,40.083219],"type":"Point"}
}