{
  "type": "Feature",
  "properties": {
    "iso:country":"US",
    "sg:address":"1527 Vermont Ave",
    "sg:city":"Connersville",
    "sg:classifiers":[
        {
            "category":"Manufacturing",
            "subcategory":"Metals",
            "type":"Manufacturing & Wholesale Goods"
        }
    ],
    "sg:phone":"+1 765 825 4443",
    "sg:postcode":"47331",
    "sg:province":"IN",
    "sg:tags":[
        "steel"
    ],
    "sg:website":"www.arrowmetals.net",
    "wof:name":"Arrow Metals Inc",
    "wof:placetype":"venue"
},
  "geometry": {"coordinates":[-85.136493,39.651278],"type":"Point"}
}