{
  "type": "Feature",
  "properties": {
    "iso:country":"US",
    "sg:address":"2660 S 200 W",
    "sg:city":"Tipton",
    "sg:classifiers":[
        {
            "category":"Building & Trades",
            "subcategory":"Electrical",
            "type":"Services"
        }
    ],
    "sg:phone":"+1 765 675 6713",
    "sg:postcode":"46072",
    "sg:province":"IN",
    "sg:tags":[
        "electric",
        "contractor"
    ],
    "wof:name":"Peters Electric",
    "wof:placetype":"venue"
},
  "geometry": {"coordinates":[-86.050516,40.265378],"type":"Point"}
}