{
  "type": "Feature",
  "properties": {
    "iso:country":"US",
    "sg:address":"3227 N Co Rd 25 W",
    "sg:city":"Brazil",
    "sg:classifiers":[
        {
            "category":"Professional",
            "subcategory":"Management & Consulting",
            "type":"Services"
        }
    ],
    "sg:phone":"+1 812 835 3605",
    "sg:postcode":"47834",
    "sg:province":"IN",
    "sg:tags":[
        "business"
    ],
    "wof:name":"Wrightmen Associates  Inc",
    "wof:placetype":"venue"
},
  "geometry": {"coordinates":[-87.113739,39.433334],"type":"Point"}
}