{
  "type": "Feature",
  "properties": {
    "iso:country":"US",
    "sg:address":"1839 W Jefferson St",
    "sg:city":"Plymouth",
    "sg:classifiers":[
        {
            "category":"Building & Trades",
            "subcategory":"Construction",
            "type":"Services"
        }
    ],
    "sg:phone":"+1 574 935 5656",
    "sg:postcode":"46563",
    "sg:province":"IN",
    "sg:tags":[
        "layer",
        "carpet"
    ],
    "wof:name":"Pratt's Floor Covering",
    "wof:placetype":"venue"
},
  "geometry": {"coordinates":[-86.331467,41.342901],"type":"Point"}
}