{
  "type": "Feature",
  "properties": {
    "iso:country":"US",
    "sg:address":"903 Eastern Blvd",
    "sg:city":"Clarksville",
    "sg:classifiers":[
        {
            "category":"Personal",
            "subcategory":"Beauty Salon",
            "type":"Services"
        }
    ],
    "sg:phone":"+1 812 218 0484",
    "sg:postcode":"47129",
    "sg:province":"IN",
    "wof:name":"Shirley's & Sherry's Coiffures",
    "wof:placetype":"venue"
},
  "geometry": {"coordinates":[-85.76557699999999,38.303973],"type":"Point"}
}