{
  "type": "Feature",
  "properties": {
    "iso:country":"US",
    "sg:address":"7150 Indianapolis Blvd",
    "sg:city":"Hammond",
    "sg:classifiers":[
        {
            "category":"Health Services",
            "subcategory":"Doctor",
            "type":"Services"
        }
    ],
    "sg:phone":"+1 219 845 2030",
    "sg:postcode":"46324",
    "sg:province":"IN",
    "sg:tags":[
        "physician",
        "surgeon"
    ],
    "wof:name":"Willardo Medical Clinic",
    "wof:placetype":"venue"
},
  "geometry": {"coordinates":[-87.48100100000001,41.583688],"type":"Point"}
}