{
  "type": "Feature",
  "properties": {
    "iso:country":"US",
    "sg:address":"113 E 2nd St",
    "sg:city":"Lynnville",
    "sg:classifiers":[
        {
            "category":"Bars & Pubs",
            "type":"Food & Drink"
        }
    ],
    "sg:phone":"+1 812 922 5250",
    "sg:postcode":"47619",
    "sg:province":"IN",
    "wof:name":"Old Fox Inn",
    "wof:placetype":"venue"
},
  "geometry": {"coordinates":[-87.296907,38.199171],"type":"Point"}
}