{
  "type": "Feature",
  "properties": {
    "addr:full":"2122 N Meridian St Indianapolis IN 46202",
    "addr:housenumber":"2122",
    "addr:postcode":"46202",
    "addr:street":"N Meridian St",
    "iso:country":"US",
    "sg:address":"2122 N Meridian St",
    "sg:city":"Indianapolis",
    "sg:classifiers":[
        {
            "category":"Manufacturing",
            "subcategory":"Tools & Machinery",
            "type":"Manufacturing & Wholesale Goods"
        }
    ],
    "sg:phone":"+1 317 926 4594",
    "sg:postcode":"46202",
    "sg:province":"IN",
    "sg:tags":[
        "die",
        "maker"
    ],
    "wof:name":"Hittle Machine & Tool Co",
    "wof:placetype":"venue"
},
  "geometry": {"coordinates":[-86.15744100000001,39.795631],"type":"Point"}
}