{
  "type": "Feature",
  "properties": {
    "iso:country":"US",
    "sg:address":"1403 Snead Ave",
    "sg:city":"Chesterton",
    "sg:classifiers":[
        {
            "category":"Professional",
            "type":"Services"
        }
    ],
    "sg:phone":"+1 219 929 1180",
    "sg:postcode":"46304",
    "sg:province":"IN",
    "wof:name":"J M Bennett & Associates",
    "wof:placetype":"venue"
},
  "geometry": {"coordinates":[-87.028849,41.598205],"type":"Point"}
}