{
  "type": "Feature",
  "properties": {
    "iso:country":"US",
    "sg:address":"1614 Douglas St",
    "sg:city":"Logansport",
    "sg:classifiers":[
        {
            "category":"Building & Trades",
            "subcategory":"Plumbing",
            "type":"Services"
        }
    ],
    "sg:phone":"+1 574 753 6973",
    "sg:postcode":"46947",
    "sg:province":"IN",
    "sg:tags":[
        "conditioning",
        "air",
        "system",
        "contractor"
    ],
    "wof:name":"Hathaway's Heating & Air Cond",
    "wof:placetype":"venue"
},
  "geometry": {"coordinates":[-86.350033,40.760954],"type":"Point"}
}