{
  "type": "Feature",
  "properties": {
    "addr:full":"1075 Woodland Ave Corydon IN 47112",
    "addr:housenumber":"1075",
    "addr:postcode":"47112",
    "addr:street":"Woodland Ave",
    "iso:country":"US",
    "sg:address":"1075 Woodland Ave",
    "sg:city":"Corydon",
    "sg:classifiers":[
        {
            "category":"Organizations",
            "subcategory":"Community Association",
            "type":"Services"
        }
    ],
    "sg:phone":"+1 812 738 4239",
    "sg:postcode":"47112",
    "sg:province":"IN",
    "wof:name":"Delta Kppa Gmma Soc Intrntonal",
    "wof:placetype":"venue"
},
  "geometry": {"coordinates":[-86.132383,38.214203],"type":"Point"}
}