{
  "type": "Feature",
  "properties": {
    "iso:country":"US",
    "sg:address":"8 Circle Lane Dr",
    "sg:city":"West Lafayette",
    "sg:classifiers":[
        {
            "category":"Communications",
            "subcategory":"Film & Video Production",
            "type":"Services"
        }
    ],
    "sg:phone":"+1 765 743 3053",
    "sg:postcode":"47906",
    "sg:province":"IN",
    "sg:tags":[
        "motion"
    ],
    "wof:name":"Vikas Productions",
    "wof:placetype":"venue"
},
  "geometry": {"coordinates":[-86.96534699999999,40.419084],"type":"Point"}
}