{
  "type": "Feature",
  "properties": {
    "iso:country":"US",
    "sg:address":"930 N 14th St",
    "sg:city":"New Castle",
    "sg:classifiers":[
        {
            "category":"Health Services",
            "subcategory":"Hospital",
            "type":"Services"
        }
    ],
    "sg:phone":"+1 765 521 2450",
    "sg:postcode":"47362",
    "sg:province":"IN",
    "sg:tags":[
        "mental"
    ],
    "wof:name":"Comprehensive Mental Health",
    "wof:placetype":"venue"
},
  "geometry": {"coordinates":[-85.36700999999999,39.940447],"type":"Point"}
}