{
  "type": "Feature",
  "properties": {
    "iso:country":"US",
    "sg:address":"1051 Coliseum Blvd N",
    "sg:city":"Fort Wayne",
    "sg:classifiers":[
        {
            "category":"Autos & Motor Vehicles",
            "subcategory":"Fuel & Gas Station",
            "type":"Retail Goods"
        }
    ],
    "sg:phone":"+1 260 484 6401",
    "sg:postcode":"46805",
    "sg:province":"IN",
    "sg:tags":[
        "oil"
    ],
    "wof:name":"Coliseum Shell East",
    "wof:placetype":"venue"
},
  "geometry": {"coordinates":[-85.087811,41.083433],"type":"Point"}
}