{
  "type": "Feature",
  "properties": {
    "addr:full":"2451 US Hwy 231 N Crawfordsville IN 47933",
    "addr:housenumber":"2451",
    "addr:postcode":"47933",
    "addr:street":"Us Hwy 231 N",
    "iso:country":"US",
    "sg:address":"2451 US Hwy 231 N",
    "sg:city":"Crawfordsville",
    "sg:classifiers":[
        {
            "category":"Manufacturing",
            "subcategory":"Metals",
            "type":"Manufacturing & Wholesale Goods"
        }
    ],
    "sg:phone":"+1 765 362 2182",
    "sg:postcode":"47933",
    "sg:province":"IN",
    "sg:tags":[
        "fabricator",
        "sheet"
    ],
    "wof:name":"W & W Fabricating",
    "wof:placetype":"venue"
},
  "geometry": {"coordinates":[-86.905782,40.074475],"type":"Point"}
}