{
  "type": "Feature",
  "properties": {
    "iso:country":"US",
    "sg:address":"10408 Pendleton Pike",
    "sg:city":"Oaklandon",
    "sg:classifiers":[
        {
            "category":"Autos & Motor Vehicles",
            "subcategory":"Automobile Sales",
            "type":"Retail Goods"
        }
    ],
    "sg:phone":"+1 317 823 1850",
    "sg:postcode":"46236",
    "sg:province":"IN",
    "sg:tags":[
        "truck"
    ],
    "wof:name":"Mike's Used Cars & Trucks",
    "wof:placetype":"venue"
},
  "geometry": {"coordinates":[-85.981996,39.857993],"type":"Point"}
}