{
  "type": "Feature",
  "properties": {
    "iso:country":"US",
    "sg:address":"1145 Birch Ave",
    "sg:city":"Schererville",
    "sg:classifiers":[
        {
            "category":"Manufacturing",
            "subcategory":"Tools & Machinery",
            "type":"Manufacturing & Wholesale Goods"
        }
    ],
    "sg:phone":"+1 219 322 1550",
    "sg:postcode":"46375",
    "sg:province":"IN",
    "sg:tags":[
        "mfg",
        "industrial",
        "general"
    ],
    "sg:website":"www.endustrafilters.com",
    "wof:name":"Endustra Filters Manufacturers",
    "wof:placetype":"venue"
},
  "geometry": {"coordinates":[-87.468447,41.501031],"type":"Point"}
}