{
  "type": "Feature",
  "properties": {
    "addr:full":"201 N Francke Rd Henryville IN 47126",
    "addr:housenumber":"201",
    "addr:postcode":"47126",
    "addr:street":"N Francke Rd",
    "iso:country":"US",
    "sg:address":"201 N Francke Rd",
    "sg:city":"Henryville",
    "sg:classifiers":[
        {
            "category":"Food & Beverages",
            "subcategory":"Groceries & Convenience Stores",
            "type":"Retail Goods"
        }
    ],
    "sg:phone":"+1 812 294 3933",
    "sg:postcode":"47126",
    "sg:province":"IN",
    "wof:name":"PBR Foodmart",
    "wof:placetype":"venue"
},
  "geometry": {"coordinates":[-85.77346799999999,38.540329],"type":"Point"}
}