{
  "type": "Feature",
  "properties": {
    "iso:country":"US",
    "sg:address":"800 Heath St",
    "sg:city":"Lafayette",
    "sg:classifiers":[
        {
            "category":"Manufacturing",
            "subcategory":"Motor Vehicles & Parts",
            "type":"Manufacturing & Wholesale Goods"
        }
    ],
    "sg:phone":"+1 765 423 5377",
    "sg:postcode":"47904",
    "sg:province":"IN",
    "sg:tags":[
        "equipment",
        "steering",
        "system"
    ],
    "wof:name":"TRW Commercial Steering",
    "wof:placetype":"venue"
},
  "geometry": {"coordinates":[-86.88704199999999,40.428846],"type":"Point"}
}