{
  "type": "Feature",
  "properties": {
    "iso:country":"US",
    "sg:address":"1903 Production Rd",
    "sg:city":"Fort Wayne",
    "sg:classifiers":[
        {
            "category":"Shopping",
            "type":"Retail Goods"
        }
    ],
    "sg:phone":"+1 260 482 8286",
    "sg:postcode":"46808",
    "sg:province":"IN",
    "sg:tags":[
        "equipment",
        "care",
        "health",
        "home"
    ],
    "wof:name":"Praxair Healthcare Svc",
    "wof:placetype":"venue"
},
  "geometry": {"coordinates":[-85.170884,41.121403],"type":"Point"}
}