{
  "type": "Feature",
  "properties": {
    "addr:full":"6061 Stoney Creek Dr Fort Wayne IN 46825",
    "addr:housenumber":"6061",
    "addr:postcode":"46825",
    "addr:street":"Stoney Creek Dr",
    "iso:country":"US",
    "sg:address":"6061 Stoney Creek Dr",
    "sg:city":"Fort Wayne",
    "sg:classifiers":[
        {
            "category":"Personal",
            "subcategory":"Beauty Salon",
            "type":"Services"
        }
    ],
    "sg:phone":"+1 260 484 8241",
    "sg:postcode":"46825",
    "sg:province":"IN",
    "sg:tags":[
        "manicuring"
    ],
    "wof:name":"Polished Touch",
    "wof:placetype":"venue"
},
  "geometry": {"coordinates":[-85.13934399999999,41.133347],"type":"Point"}
}