{
  "type": "Feature",
  "properties": {
    "addr:full":"65764 US Hwy 33 Goshen IN 46526",
    "addr:postcode":"65764;46526",
    "addr:street":"Us Hwy 33",
    "iso:country":"US",
    "sg:address":"65764 US Hwy 33",
    "sg:city":"Goshen",
    "sg:classifiers":[
        {
            "category":"Utilities",
            "subcategory":"Refuse",
            "type":"Services"
        }
    ],
    "sg:phone":"+1 574 831 2361",
    "sg:postcode":"46526",
    "sg:province":"IN",
    "sg:tags":[
        "garbage",
        "collection"
    ],
    "wof:name":"TLC Hauling Svc",
    "wof:placetype":"venue"
},
  "geometry": {"coordinates":[-85.779927,41.540772],"type":"Point"}
}