{
  "type": "Feature",
  "properties": {
    "iso:country":"US",
    "sg:address":"5841 Crawfordsville Rd",
    "sg:city":"Indianapolis",
    "sg:classifiers":[
        {
            "category":"Banks & Credit Unions",
            "subcategory":"Financial Services",
            "type":"Services"
        }
    ],
    "sg:phone":"+1 317 481 1844",
    "sg:postcode":"46224",
    "sg:province":"IN",
    "sg:tags":[
        "cashing",
        "loan",
        "payday",
        "alternative",
        "check"
    ],
    "sg:website":"http://www.acecashexpress.com",
    "wof:name":"ACE Cash Express",
    "wof:placetype":"venue"
},
  "geometry": {"coordinates":[-86.26114099999999,39.796133],"type":"Point"}
}