{
  "type": "Feature",
  "properties": {
    "iso:country":"US",
    "sg:address":"3111 N Arsenal Ave",
    "sg:city":"Indianapolis",
    "sg:classifiers":[
        {
            "category":"Building & Trades",
            "subcategory":"Landscaping Services",
            "type":"Services"
        }
    ],
    "sg:phone":"+1 317 924 3340",
    "sg:postcode":"46218",
    "sg:province":"IN",
    "sg:tags":[
        "landscape",
        "contractor"
    ],
    "wof:name":"A & T Landscaping",
    "wof:placetype":"venue"
},
  "geometry": {"coordinates":[-86.134004,39.811857],"type":"Point"}
}