{
  "type": "Feature",
  "properties": {
    "addr:full":"2040 W 81st Ave Merrillville IN 46410",
    "addr:housenumber":"2040",
    "addr:postcode":"46410",
    "addr:street":"W 81St Ave",
    "iso:country":"US",
    "sg:address":"2040 W 81st Ave",
    "sg:city":"Merrillville",
    "sg:classifiers":[
        {
            "category":"Professional",
            "subcategory":"Accounting & Tax Preparation",
            "type":"Services"
        }
    ],
    "sg:phone":"+1 219 736 5158",
    "sg:postcode":"46410",
    "sg:province":"IN",
    "sg:tags":[
        "return",
        "filing"
    ],
    "wof:name":"Jackson Hewitt Tax Svc",
    "wof:placetype":"venue"
},
  "geometry": {"coordinates":[-87.360125,41.471186],"type":"Point"}
}