{
  "type": "Feature",
  "properties": {
    "iso:country":"US",
    "sg:address":"900 Lincolnway E",
    "sg:city":"Goshen",
    "sg:classifiers":[
        {
            "category":"Travel",
            "subcategory":"Hotels & Motels",
            "type":"Entertainment"
        }
    ],
    "sg:phone":"+1 574 533 0408",
    "sg:postcode":"46526",
    "sg:province":"IN",
    "wof:name":"Best Western Inn",
    "wof:placetype":"venue"
},
  "geometry": {"coordinates":[-85.817702,41.577512],"type":"Point"}
}