{
  "type": "Feature",
  "properties": {
    "iso:country":"US",
    "sg:address":"1717 Cremer Ave",
    "sg:city":"Fort Wayne",
    "sg:classifiers":[
        {
            "category":"Banks & Credit Unions",
            "subcategory":"Bank",
            "type":"Services"
        }
    ],
    "sg:phone":"+1 260 489 1760",
    "sg:postcode":"46818",
    "sg:province":"IN",
    "sg:tags":[
        "financing"
    ],
    "wof:name":"Heritage Acceptance Corp",
    "wof:placetype":"venue"
},
  "geometry": {"coordinates":[-85.168273,41.165963],"type":"Point"}
}