{
  "type": "Feature",
  "properties": {
    "iso:country":"US",
    "sg:address":"3218 Abby Ln",
    "sg:city":"Bloomington",
    "sg:classifiers":[
        {
            "category":"Professional",
            "subcategory":"Management & Consulting",
            "type":"Services"
        }
    ],
    "sg:phone":"+1 812 323 1041",
    "sg:postcode":"47401",
    "sg:province":"IN",
    "sg:tags":[
        "business"
    ],
    "wof:name":"Sturgis Consulting",
    "wof:placetype":"venue"
},
  "geometry": {"coordinates":[-86.511726,39.134358],"type":"Point"}
}