{
  "type": "Feature",
  "properties": {
    "iso:country":"US",
    "sg:address":"641 W Walnut St",
    "sg:city":"Albany",
    "sg:classifiers":[
        {
            "category":"Food & Beverages",
            "subcategory":"Groceries & Convenience Stores",
            "type":"Retail Goods"
        }
    ],
    "sg:phone":"+1 219 789 4004",
    "sg:postcode":"47320",
    "sg:province":"IN",
    "wof:name":"Marsh",
    "wof:placetype":"venue"
},
  "geometry": {"coordinates":[-85.24353000000001,40.303741],"type":"Point"}
}