{
  "type": "Feature",
  "properties": {
    "iso:country":"US",
    "sg:address":"1 Juniper Rd",
    "sg:city":"Valparaiso",
    "sg:classifiers":[
        {
            "category":"Building & Trades",
            "subcategory":"Construction",
            "type":"Services"
        }
    ],
    "sg:phone":"+1 219 759 0232",
    "sg:postcode":"46385",
    "sg:province":"IN",
    "sg:tags":[
        "contractor"
    ],
    "wof:name":"Branham Builders",
    "wof:placetype":"venue"
},
  "geometry": {"coordinates":[-87.136172,41.54649],"type":"Point"}
}