{
  "type": "Feature",
  "properties": {
    "iso:country":"US",
    "sg:address":"7995 State Rte 59",
    "sg:city":"Brazil",
    "sg:classifiers":[
        {
            "category":"Banks & Credit Unions",
            "subcategory":"Bank",
            "type":"Services"
        }
    ],
    "sg:phone":"+1 812 443 4481",
    "sg:postcode":"47834",
    "sg:province":"IN",
    "sg:website":"www.first-online.com",
    "wof:name":"First State Bank",
    "wof:placetype":"venue"
},
  "geometry": {"coordinates":[-87.125558,39.50361],"type":"Point"}
}