{
  "type": "Feature",
  "properties": {
    "addr:full":"345 Massachusetts Ave Indianapolis IN 46204",
    "addr:housenumber":"345",
    "addr:postcode":"46204",
    "addr:street":"Massachusetts Ave",
    "iso:country":"US",
    "sg:address":"345 Massachusetts Ave",
    "sg:city":"Indianapolis",
    "sg:classifiers":[
        {
            "category":"Professional",
            "subcategory":"Advertising",
            "type":"Services"
        },
        {
            "category":"Communications",
            "subcategory":"Film & Video Production",
            "type":"Services"
        }
    ],
    "sg:phone":"+1 317 822 3715",
    "sg:postcode":"46204",
    "sg:province":"IN",
    "sg:tags":[
        "agency",
        "specialty"
    ],
    "wof:name":"Creative Street Media Group",
    "wof:placetype":"venue"
},
  "geometry": {"coordinates":[-86.15377599999999,39.771621],"type":"Point"}
}