{
  "type": "Feature",
  "properties": {
    "iso:country":"US",
    "sg:address":"5124 E 1000 S",
    "sg:city":"Claypool",
    "sg:classifiers":[
        {
            "category":"Professional",
            "type":"Services"
        }
    ],
    "sg:phone":"+1 260 839 0028",
    "sg:postcode":"46510",
    "sg:province":"IN",
    "wof:name":"Brent Montel",
    "wof:placetype":"venue"
},
  "geometry": {"coordinates":[-85.725408,41.088484],"type":"Point"}
}