{
  "type": "Feature",
  "properties": {
    "iso:country":"US",
    "sg:address":"1395 Carolina St",
    "sg:city":"Gary",
    "sg:classifiers":[
        {
            "category":"Recreation",
            "type":"Entertainment"
        }
    ],
    "sg:phone":"+1 219 885 8301",
    "sg:postcode":"46407",
    "sg:province":"IN",
    "sg:tags":[
        "parks"
    ],
    "wof:name":"Carolina Park",
    "wof:placetype":"venue"
},
  "geometry": {"coordinates":[-87.32847599999999,41.589911],"type":"Point"}
}