{
  "type": "Feature",
  "properties": {
    "iso:country":"US",
    "sg:address":"2011 Northwestern Ave",
    "sg:city":"Princeton",
    "sg:classifiers":[
        {
            "category":"Personal",
            "subcategory":"Beauty Salon",
            "type":"Services"
        }
    ],
    "sg:phone":"+1 812 386 1651",
    "sg:postcode":"47670",
    "sg:province":"IN",
    "sg:tags":[
        "shop"
    ],
    "wof:name":"Mane Topic",
    "wof:placetype":"venue"
},
  "geometry": {"coordinates":[-87.57032,38.335061],"type":"Point"}
}