{
  "type": "Feature",
  "properties": {
    "iso:country":"US",
    "sg:address":"41 N Harbison Ave",
    "sg:city":"Indianapolis",
    "sg:classifiers":[
        {
            "category":"Professional",
            "subcategory":"Engineering",
            "type":"Services"
        }
    ],
    "sg:phone":"+1 317 898 3878",
    "sg:postcode":"46219",
    "sg:province":"IN",
    "sg:tags":[
        "electrical",
        "electronic",
        "engineer"
    ],
    "sg:website":"http://www.spiritsolutionsinc.com",
    "wof:name":"Spirit Solutions Inc",
    "wof:placetype":"venue"
},
  "geometry": {"coordinates":[-86.01469,39.774282],"type":"Point"}
}