{
  "type": "Feature",
  "properties": {
    "iso:country":"US",
    "sg:address":"4101 N Co Rd 300 E",
    "sg:city":"Greencastle",
    "sg:classifiers":[
        {
            "category":"Recreation",
            "type":"Entertainment"
        }
    ],
    "sg:phone":"+1 765 522 1306",
    "sg:postcode":"46135",
    "sg:province":"IN",
    "sg:tags":[
        "stable"
    ],
    "wof:name":"Centerline Stables Inc",
    "wof:placetype":"venue"
},
  "geometry": {"coordinates":[-86.793494,39.719858],"type":"Point"}
}