{
  "type": "Feature",
  "properties": {
    "iso:country":"US",
    "sg:address":"9595 Whitley Dr Ste 104",
    "sg:city":"Indianapolis",
    "sg:classifiers":[
        {
            "category":"Manufacturing",
            "subcategory":"Jewelry",
            "type":"Manufacturing & Wholesale Goods"
        }
    ],
    "sg:phone":"+1 317 566 0375",
    "sg:postcode":"46240",
    "sg:province":"IN",
    "sg:tags":[
        "jewelers-wholesale",
        "manufacturer"
    ],
    "wof:name":"O C Tanner Recognition Co",
    "wof:placetype":"venue"
},
  "geometry": {"coordinates":[-86.115059,39.926842],"type":"Point"}
}