{
  "type": "Feature",
  "properties": {
    "iso:country":"US",
    "sg:address":"8228 E 21st St",
    "sg:city":"Indianapolis",
    "sg:classifiers":[
        {
            "category":"Building & Trades",
            "subcategory":"Pest Control",
            "type":"Services"
        }
    ],
    "sg:phone":"+1 317 897 3052",
    "sg:postcode":"46219",
    "sg:province":"IN",
    "wof:name":"Karress Pest Pro",
    "wof:placetype":"venue"
},
  "geometry": {"coordinates":[-86.021765,39.796661],"type":"Point"}
}