{
  "type": "Feature",
  "properties": {
    "iso:country":"US",
    "sg:address":"9245 Calumet Ave Ste 101",
    "sg:city":"Munster",
    "sg:classifiers":[
        {
            "category":"Professional",
            "subcategory":"Accounting & Tax Preparation",
            "type":"Services"
        },
        {
            "category":"Health Services",
            "subcategory":"Doctor",
            "type":"Services"
        }
    ],
    "sg:phone":"+1 219 836 9900",
    "sg:postcode":"46321",
    "sg:province":"IN",
    "sg:tags":[
        "accountant"
    ],
    "wof:name":"Seehausen & Co PC",
    "wof:placetype":"venue"
},
  "geometry": {"coordinates":[-87.50900300000001,41.545601],"type":"Point"}
}