{
  "type": "Feature",
  "properties": {
    "iso:country":"US",
    "sg:address":"5353 W 38th St",
    "sg:city":"Indianapolis",
    "sg:classifiers":[
        {
            "category":"Retail",
            "subcategory":"Car Wash",
            "type":"Services"
        }
    ],
    "sg:phone":"+1 317 298 9448",
    "sg:postcode":"46254",
    "sg:province":"IN",
    "sg:tags":[
        "automobile",
        "detail",
        "clean"
    ],
    "wof:name":"Ultimate Images Inc",
    "wof:placetype":"venue"
},
  "geometry": {"coordinates":[-86.24458799999999,39.823852],"type":"Point"}
}