{
  "type": "Feature",
  "properties": {
    "iso:country":"US",
    "sg:address":"237 E Main St",
    "sg:city":"Gas City",
    "sg:classifiers":[
        {
            "category":"Personal",
            "subcategory":"Barber",
            "type":"Services"
        }
    ],
    "sg:phone":"+1 765 674 8665",
    "sg:postcode":"46933",
    "sg:province":"IN",
    "wof:name":"Max's Barber Shop",
    "wof:placetype":"venue"
},
  "geometry": {"coordinates":[-85.611699,40.487966],"type":"Point"}
}