{
  "type": "Feature",
  "properties": {
    "iso:country":"US",
    "sg:address":"303 E Porter Ave",
    "sg:city":"Chesterton",
    "sg:classifiers":[
        {
            "category":"Real Estate",
            "subcategory":"Real Estate Agent",
            "type":"Services"
        }
    ],
    "sg:phone":"+1 219 921 4515",
    "sg:postcode":"46304",
    "sg:province":"IN",
    "sg:tags":[
        "inspection"
    ],
    "wof:name":"Panther Home Inspection",
    "wof:placetype":"venue"
},
  "geometry": {"coordinates":[-87.047644,41.606796],"type":"Point"}
}