{
  "type": "Feature",
  "properties": {
    "addr:full":"510 Hawthorn Trl North Manchester IN 46962",
    "addr:housenumber":"510",
    "addr:postcode":"46962",
    "addr:street":"Hawthorn Trl North",
    "iso:country":"US",
    "sg:address":"510 Hawthorn Trl",
    "sg:city":"North Manchester",
    "sg:classifiers":[
        {
            "category":"Organizations",
            "subcategory":"Community Association",
            "type":"Services"
        }
    ],
    "sg:phone":"+1 260 982 1807",
    "sg:postcode":"46962",
    "sg:province":"IN",
    "wof:name":"Kiwanis International",
    "wof:placetype":"venue"
},
  "geometry": {"coordinates":[-85.756546,41.023039],"type":"Point"}
}