{
  "type": "Feature",
  "properties": {
    "iso:country":"US",
    "sg:address":"9597 N 425 W",
    "sg:city":"Milford",
    "sg:classifiers":[
        {
            "category":"Building & Trades",
            "subcategory":"Landscaping Services",
            "type":"Services"
        }
    ],
    "sg:phone":"+1 574 658 9815",
    "sg:postcode":"46542",
    "sg:province":"IN",
    "sg:tags":[
        "lawn",
        "maintenance",
        "grounds"
    ],
    "wof:name":"Beer's Lawn Installation",
    "wof:placetype":"venue"
},
  "geometry": {"coordinates":[-85.92859,41.364004],"type":"Point"}
}