{
  "type": "Feature",
  "properties": {
    "addr:full":"3801 E 82nd St Indianapolis IN 46240",
    "addr:housenumber":"3801",
    "addr:postcode":"46240",
    "addr:street":"E 82Nd St",
    "iso:country":"US",
    "sg:address":"3801 E 82nd St",
    "sg:city":"Indianapolis",
    "sg:classifiers":[
        {
            "category":"Real Estate",
            "subcategory":"Real Estate Services",
            "type":"Services"
        }
    ],
    "sg:phone":"+1 317 558 7826",
    "sg:postcode":"46240",
    "sg:province":"IN",
    "wof:name":"Peoni John Fredrick Rl Est",
    "wof:placetype":"venue"
},
  "geometry": {"coordinates":[-86.101501,39.908901],"type":"Point"}
}