{
  "type": "Feature",
  "properties": {
    "iso:country":"US",
    "sg:address":"710 W North St",
    "sg:city":"Kendallville",
    "sg:classifiers":[
        {
            "category":"Autos & Motor Vehicles",
            "subcategory":"Automobile Sales",
            "type":"Retail Goods"
        }
    ],
    "sg:phone":"+1 260 347 3200",
    "sg:postcode":"46755",
    "sg:province":"IN",
    "sg:tags":[
        "used"
    ],
    "wof:name":"K&E Auto Center",
    "wof:placetype":"venue"
},
  "geometry": {"coordinates":[-85.27614199999999,41.452436],"type":"Point"}
}