{
  "type": "Feature",
  "properties": {
    "addr:full":"218 N Main St Monticello IN 47960",
    "addr:housenumber":"218",
    "addr:postcode":"47960",
    "addr:street":"N Main St",
    "iso:country":"US",
    "sg:address":"218 N Main St",
    "sg:city":"Monticello",
    "sg:classifiers":[
        {
            "category":"Organizations",
            "subcategory":"Non-profit Organization",
            "type":"Services"
        }
    ],
    "sg:phone":"+1 574 583 9784",
    "sg:postcode":"47960",
    "sg:province":"IN",
    "sg:website":"www.sflecc.com",
    "wof:name":"SFLECC",
    "wof:placetype":"venue"
},
  "geometry": {"coordinates":[-86.76200799999999,40.747068],"type":"Point"}
}