{
  "type": "Feature",
  "properties": {
    "iso:country":"US",
    "sg:address":"1255 Main St",
    "sg:city":"Indianapolis",
    "sg:classifiers":[
        {
            "category":"Real Estate",
            "subcategory":"Real Estate Agent",
            "type":"Services"
        }
    ],
    "sg:phone":"+1 317 247 7551",
    "sg:postcode":"46224",
    "sg:province":"IN",
    "wof:name":"Anderson Property Preservation",
    "wof:placetype":"venue"
},
  "geometry": {"coordinates":[-86.240944,39.783758],"type":"Point"}
}