{
  "type": "Feature",
  "properties": {
    "iso:country":"US",
    "sg:address":"8500 Keystone Xing Ste 590",
    "sg:city":"Indianapolis",
    "sg:classifiers":[
        {
            "category":"Building & Trades",
            "subcategory":"Construction",
            "type":"Services"
        }
    ],
    "sg:phone":"+1 317 255 9900",
    "sg:postcode":"46240",
    "sg:province":"IN",
    "sg:tags":[
        "contractor"
    ],
    "sg:website":"www.mihomes.com",
    "wof:name":"M I Homes",
    "wof:placetype":"venue"
},
  "geometry": {"coordinates":[-86.11295,39.910826],"type":"Point"}
}