{
  "type": "Feature",
  "properties": {
    "iso:country":"US",
    "sg:address":"2424 E 5th St",
    "sg:city":"Mishawaka",
    "sg:classifiers":[
        {
            "category":"Health Services",
            "subcategory":"Doctor",
            "type":"Services"
        }
    ],
    "sg:phone":"+1 574 259 1464",
    "sg:postcode":"46544",
    "sg:province":"IN",
    "sg:tags":[
        "dentist"
    ],
    "wof:name":"Szabo Family Dentistry",
    "wof:placetype":"venue"
},
  "geometry": {"coordinates":[-86.13995,41.658321],"type":"Point"}
}