{
  "type": "Feature",
  "properties": {
    "iso:country":"US",
    "sg:address":"20 W Market St",
    "sg:city":"Huntington",
    "sg:classifiers":[
        {
            "category":"Real Estate",
            "subcategory":"Real Estate Agent",
            "type":"Services"
        }
    ],
    "sg:phone":"+1 260 358 1200",
    "sg:postcode":"46750",
    "sg:province":"IN",
    "wof:name":"Huntington Area Assn of Rltors",
    "wof:placetype":"venue"
},
  "geometry": {"coordinates":[-85.495047,40.881896],"type":"Point"}
}