{
  "type": "Feature",
  "properties": {
    "iso:country":"US",
    "sg:address":"2845 Roadway Dr",
    "sg:city":"Columbus",
    "sg:classifiers":[
        {
            "category":"Building & Trades",
            "subcategory":"Construction",
            "type":"Services"
        }
    ],
    "sg:phone":"+1 812 372 8409",
    "sg:postcode":"47201",
    "sg:province":"IN",
    "sg:tags":[
        "roofing",
        "contractor"
    ],
    "wof:name":"HRC Roofing & Sheet Metal Co",
    "wof:placetype":"venue"
},
  "geometry": {"coordinates":[-85.890653,39.185938],"type":"Point"}
}