{
  "type": "Feature",
  "properties": {
    "iso:country":"US",
    "sg:address":"323 S Center St",
    "sg:city":"Bremen",
    "sg:classifiers":[
        {
            "category":"Organizations",
            "subcategory":"Religious Organization",
            "type":"Services"
        }
    ],
    "sg:phone":"+1 574 546 2459",
    "sg:postcode":"46506",
    "sg:province":"IN",
    "sg:tags":[
        "church"
    ],
    "wof:name":"First United Church Of Christ",
    "wof:placetype":"venue"
},
  "geometry": {"coordinates":[-86.14656100000001,41.444654],"type":"Point"}
}