{
  "type": "Feature",
  "properties": {
    "iso:country":"US",
    "sg:address":"1611 E 226th St",
    "sg:city":"Cicero",
    "sg:classifiers":[
        {
            "category":"Professional",
            "subcategory":"Business Services",
            "type":"Services"
        }
    ],
    "sg:phone":"+1 317 758 4641",
    "sg:postcode":"46034",
    "sg:province":"IN",
    "sg:tags":[
        "fund",
        "promotion",
        "raising"
    ],
    "wof:name":"Duncan Promotions",
    "wof:placetype":"venue"
},
  "geometry": {"coordinates":[-86.134324,40.115606],"type":"Point"}
}