{
  "type": "Feature",
  "properties": {
    "addr:full":"805 W Edison Rd Mishawaka IN 46545",
    "addr:housenumber":"805",
    "addr:postcode":"46545",
    "addr:street":"W Edison Rd",
    "iso:country":"US",
    "sg:address":"805 W Edison Rd",
    "sg:city":"Mishawaka",
    "sg:classifiers":[
        {
            "category":"Building & Trades",
            "subcategory":"Equipment Rental",
            "type":"Services"
        }
    ],
    "sg:phone":"+1 574 256 1110",
    "sg:postcode":"46545",
    "sg:province":"IN",
    "sg:tags":[
        "table"
    ],
    "wof:name":"Aay's Rent-All Co Inc",
    "wof:placetype":"venue"
},
  "geometry": {"coordinates":[-86.192189,41.694692],"type":"Point"}
}