{
  "type": "Feature",
  "properties": {
    "addr:full":"2311 E 10th St Anderson IN 46012",
    "addr:housenumber":"2311",
    "addr:postcode":"46012",
    "addr:street":"E 10Th St",
    "iso:country":"US",
    "sg:address":"2311 E 10th St",
    "sg:city":"Anderson",
    "sg:classifiers":[
        {
            "category":"Building & Trades",
            "subcategory":"Plumbing",
            "type":"Services"
        }
    ],
    "sg:phone":"+1 765 683 0847",
    "sg:postcode":"46012",
    "sg:province":"IN",
    "sg:tags":[
        "plumbing",
        "contractor"
    ],
    "wof:name":"Sweigart's Plumbing",
    "wof:placetype":"venue"
},
  "geometry": {"coordinates":[-85.650808,40.105773],"type":"Point"}
}