{
  "type": "Feature",
  "properties": {
    "addr:full":"3112 S Lafountain St Kokomo IN 46902",
    "addr:housenumber":"3112",
    "addr:postcode":"46902",
    "addr:street":"S Lafountain St",
    "iso:country":"US",
    "sg:address":"3112 S Lafountain St",
    "sg:city":"Kokomo",
    "sg:classifiers":[
        {
            "category":"Personal",
            "type":"Services"
        }
    ],
    "sg:phone":"+1 765 455 1104",
    "sg:postcode":"46902",
    "sg:province":"IN",
    "sg:tags":[
        "credit",
        "debt",
        "counseling"
    ],
    "wof:name":"Debt Doctors",
    "wof:placetype":"venue"
},
  "geometry": {"coordinates":[-86.12708000000001,40.449717],"type":"Point"}
}