{
  "type": "Feature",
  "properties": {
    "addr:full":"1700 Bay View Dr Fort Wayne IN 46815",
    "addr:housenumber":"1700",
    "addr:postcode":"46815",
    "addr:street":"Bay View Dr",
    "iso:country":"US",
    "sg:address":"1700 Bay View Dr",
    "sg:city":"Fort Wayne",
    "sg:classifiers":[
        {
            "category":"Real Estate",
            "subcategory":"Real Estate Operator",
            "type":"Services"
        }
    ],
    "sg:phone":"+1 260 423 3636",
    "sg:postcode":"46815",
    "sg:province":"IN",
    "sg:tags":[
        "apartment"
    ],
    "wof:name":"Arbor Lakes Apartments",
    "wof:placetype":"venue"
},
  "geometry": {"coordinates":[-85.08165200000001,41.09212],"type":"Point"}
}