{
  "type": "Feature",
  "properties": {
    "iso:country":"US",
    "sg:address":"1122 W Plymouth St",
    "sg:city":"Bremen",
    "sg:classifiers":[
        {
            "category":"Banks & Credit Unions",
            "subcategory":"Bank",
            "type":"Services"
        }
    ],
    "sg:phone":"+1 574 546 5666",
    "sg:postcode":"46506",
    "sg:province":"IN",
    "wof:name":"Taper Lock Credit Union",
    "wof:placetype":"venue"
},
  "geometry": {"coordinates":[-86.15902800000001,41.446361],"type":"Point"}
}