{
  "type": "Feature",
  "properties": {
    "addr:full":"210 E Graham St Kentland IN 47951",
    "addr:housenumber":"210",
    "addr:postcode":"47951",
    "addr:street":"E Graham St",
    "iso:country":"US",
    "sg:address":"210 E Graham St",
    "sg:city":"Kentland",
    "sg:classifiers":[
        {
            "category":"Organizations",
            "subcategory":"Religious Organization",
            "type":"Services"
        }
    ],
    "sg:phone":"+1 219 474 9710",
    "sg:postcode":"47951",
    "sg:province":"IN",
    "wof:name":"Newton County Baptist Church",
    "wof:placetype":"venue"
},
  "geometry": {"coordinates":[-87.446893,40.769235],"type":"Point"}
}