{
  "type": "Feature",
  "properties": {
    "iso:country":"US",
    "sg:address":"110 N Walnut St",
    "sg:city":"Bloomington",
    "sg:classifiers":[
        {
            "category":"Restaurant",
            "type":"Food & Drink"
        }
    ],
    "sg:phone":"+1 812 333 7287",
    "sg:postcode":"47404",
    "sg:province":"IN",
    "sg:website":"www.opietaylors.com",
    "wof:name":"Opie Taylor's",
    "wof:placetype":"venue"
},
  "geometry": {"coordinates":[-86.533501,39.166801],"type":"Point"}
}