{
  "type": "Feature",
  "properties": {
    "addr:full":"2070 W 81st Ave Merrillville IN 46410",
    "addr:housenumber":"2070",
    "addr:postcode":"46410",
    "addr:street":"W 81St Ave",
    "iso:country":"US",
    "sg:address":"2070 W 81st Ave",
    "sg:city":"Merrillville",
    "sg:classifiers":[
        {
            "category":"Retail",
            "subcategory":"Auto Repair",
            "type":"Services"
        }
    ],
    "sg:phone":"+1 219 736 1502",
    "sg:postcode":"46410",
    "sg:province":"IN",
    "sg:tags":[
        "repairing",
        "automobile"
    ],
    "wof:name":"Glenn's Complete Car Care",
    "wof:placetype":"venue"
},
  "geometry": {"coordinates":[-87.35982199999999,41.471186],"type":"Point"}
}