{
  "type": "Feature",
  "properties": {
    "iso:country":"US",
    "sg:address":"4720 W 61st Ave",
    "sg:city":"Hobart",
    "sg:classifiers":[
        {
            "category":"Retail",
            "subcategory":"Auto Repair",
            "type":"Services"
        }
    ],
    "sg:phone":"+1 219 769 7880",
    "sg:postcode":"46342",
    "sg:province":"IN",
    "sg:tags":[
        "transmission"
    ],
    "wof:name":"I 65 Transmission",
    "wof:placetype":"venue"
},
  "geometry": {"coordinates":[-87.315347,41.507386],"type":"Point"}
}