{
  "type": "Feature",
  "properties": {
    "iso:country":"US",
    "sg:address":"2421 S Nappanee St",
    "sg:city":"Elkhart",
    "sg:classifiers":[
        {
            "category":"Wholesale",
            "subcategory":"Beer",
            "type":"Manufacturing & Wholesale Goods"
        }
    ],
    "sg:phone":"+1 574 295 3565",
    "sg:postcode":"46517",
    "sg:province":"IN",
    "sg:tags":[
        "ale"
    ],
    "wof:name":"Beer Guy Distributing LLC",
    "wof:placetype":"venue"
},
  "geometry": {"coordinates":[-86.00314,41.663852],"type":"Point"}
}