{
  "type": "Feature",
  "properties": {
    "iso:country":"US",
    "sg:address":"2427 N 6th St",
    "sg:city":"Vincennes",
    "sg:classifiers":[
        {
            "category":"Food & Beverages",
            "subcategory":"Groceries & Convenience Stores",
            "type":"Retail Goods"
        }
    ],
    "sg:phone":"+1 812 882 2613",
    "sg:postcode":"47591",
    "sg:province":"IN",
    "sg:tags":[
        "grocer"
    ],
    "sg:website":"www.buylowstores.com",
    "wof:name":"Buehler BUY-Low",
    "wof:placetype":"venue"
},
  "geometry": {"coordinates":[-87.504611,38.689432],"type":"Point"}
}