{
  "type": "Feature",
  "properties": {
    "addr:full":"10099 Broadway Merrillville IN 46410",
    "addr:housenumber":"10099",
    "addr:postcode":"46410",
    "addr:street":"Broadway",
    "iso:country":"US",
    "sg:address":"10099 Broadway",
    "sg:city":"Merrillville",
    "sg:classifiers":[
        {
            "category":"Restaurant",
            "type":"Food & Drink"
        }
    ],
    "sg:phone":"+1 219 736 1099",
    "sg:postcode":"46410",
    "sg:province":"IN",
    "sg:tags":[
        "eating"
    ],
    "wof:name":"William T McDonalds Modr",
    "wof:placetype":"venue"
},
  "geometry": {"coordinates":[-87.33553499999999,41.434823],"type":"Point"}
}