{
  "type": "Feature",
  "properties": {
    "iso:country":"US",
    "sg:address":"302 Main St",
    "sg:city":"Jasper",
    "sg:classifiers":[
        {
            "category":"Professional",
            "subcategory":"Lawyer & Legal Services",
            "type":"Services"
        }
    ],
    "sg:phone":"+1 812 482 9232",
    "sg:postcode":"47546",
    "sg:province":"IN",
    "sg:tags":[
        "attorney"
    ],
    "wof:name":"Fischer & Fritch",
    "wof:placetype":"venue"
},
  "geometry": {"coordinates":[-86.93074900000001,38.389926],"type":"Point"}
}