{
  "type": "Feature",
  "properties": {
    "addr:full":"705 Ridge Gate Dr Brownsburg IN 46112",
    "addr:housenumber":"705",
    "addr:postcode":"46112",
    "addr:street":"Ridge Gate Dr",
    "iso:country":"US",
    "sg:address":"705 Ridge Gate Dr",
    "sg:city":"Brownsburg",
    "sg:classifiers":[
        {
            "category":"Building & Trades",
            "subcategory":"Construction",
            "type":"Services"
        }
    ],
    "sg:phone":"+1 317 858 3100",
    "sg:postcode":"46112",
    "sg:province":"IN",
    "sg:tags":[
        "home",
        "builder"
    ],
    "wof:name":"Silverthorne Homes",
    "wof:placetype":"venue"
},
  "geometry": {"coordinates":[-86.41079000000001,39.856367],"type":"Point"}
}