{
  "type": "Feature",
  "properties": {
    "iso:country":"US",
    "sg:address":"811 N Illinois St",
    "sg:city":"Indianapolis",
    "sg:classifiers":[
        {
            "category":"Food & Beverages",
            "subcategory":"Liquor & Beverages",
            "type":"Retail Goods"
        }
    ],
    "sg:phone":"+1 317 637 9697",
    "sg:postcode":"46204",
    "sg:province":"IN",
    "sg:tags":[
        "convenience",
        "store"
    ],
    "wof:name":"Lee's Liquor",
    "wof:placetype":"venue"
},
  "geometry": {"coordinates":[-86.159488,39.778177],"type":"Point"}
}