{
  "type": "Feature",
  "properties": {
    "iso:country":"US",
    "sg:address":"1621 E Greyhound Pass",
    "sg:city":"Carmel",
    "sg:classifiers":[
        {
            "category":"Insurance",
            "subcategory":"Insurance Agent",
            "type":"Services"
        }
    ],
    "sg:phone":"+1 317 815 9000",
    "sg:postcode":"46032",
    "sg:province":"IN",
    "wof:name":"Howard Fry & Son",
    "wof:placetype":"venue"
},
  "geometry": {"coordinates":[-86.129453,40.004724],"type":"Point"}
}