{
  "type": "Feature",
  "properties": {
    "iso:country":"US",
    "sg:address":"1145 Commercial Dr",
    "sg:city":"Schererville",
    "sg:classifiers":[
        {
            "category":"Building & Trades",
            "subcategory":"Construction",
            "type":"Services"
        }
    ],
    "sg:phone":"+1 219 864 0069",
    "sg:postcode":"46375",
    "sg:province":"IN",
    "sg:tags":[
        "hanging",
        "painter",
        "contractor"
    ],
    "wof:name":"Wooden Shoe Painting & Decor",
    "wof:placetype":"venue"
},
  "geometry": {"coordinates":[-87.467447,41.501144],"type":"Point"}
}