{
  "type": "Feature",
  "properties": {
    "iso:country":"US",
    "sg:address":"201 S Howard St",
    "sg:city":"Oxford",
    "sg:classifiers":[
        {
            "category":"Food & Beverages",
            "subcategory":"Groceries & Convenience Stores",
            "type":"Retail Goods"
        }
    ],
    "sg:phone":"+1 765 385 2928",
    "sg:postcode":"47971",
    "sg:province":"IN",
    "sg:tags":[
        "grocer"
    ],
    "wof:name":"Fellure's IGA",
    "wof:placetype":"venue"
},
  "geometry": {"coordinates":[-87.249024,40.519732],"type":"Point"}
}