{
  "type": "Feature",
  "properties": {
    "addr:full":"3388 S 380 E Anderson IN 46017",
    "addr:housenumber":"3388;380 e",
    "addr:postcode":"46017",
    "addr:street":"S",
    "iso:country":"US",
    "sg:address":"3388 S 380 E",
    "sg:city":"Anderson",
    "sg:classifiers":[
        {
            "category":"Farming",
            "subcategory":"Farm",
            "type":"Manufacturing & Wholesale Goods"
        }
    ],
    "sg:phone":"+1 765 378 6292",
    "sg:postcode":"46017",
    "sg:province":"IN",
    "sg:tags":[
        "crop",
        "general"
    ],
    "wof:name":"Adams Dirt & Gravel",
    "wof:placetype":"venue"
},
  "geometry": {"coordinates":[-85.600221,40.055559],"type":"Point"}
}