{
  "type": "Feature",
  "properties": {
    "addr:full":"8219 Zionsville Rd Indianapolis IN 46268",
    "addr:housenumber":"8219",
    "addr:postcode":"46268",
    "addr:street":"Zionsville Rd",
    "iso:country":"US",
    "sg:address":"8219 Zionsville Rd",
    "sg:city":"Indianapolis",
    "sg:classifiers":[
        {
            "category":"Wholesale",
            "subcategory":"Durable Goods & Equipment",
            "type":"Manufacturing & Wholesale Goods"
        }
    ],
    "sg:phone":"+1 317 334 7188",
    "sg:postcode":"46268",
    "sg:province":"IN",
    "sg:tags":[
        "importer"
    ],
    "sg:website":"www.cottagefuton.com",
    "wof:name":"Midwest Imports",
    "wof:placetype":"venue"
},
  "geometry": {"coordinates":[-86.259793,39.903005],"type":"Point"}
}