{
  "type": "Feature",
  "properties": {
    "iso:country":"US",
    "sg:address":"6372 Guilford Ave",
    "sg:city":"Indianapolis",
    "sg:classifiers":[
        {
            "category":"Personal",
            "subcategory":"Beauty Salon",
            "type":"Services"
        }
    ],
    "sg:phone":"+1 317 255 3178",
    "sg:postcode":"46220",
    "sg:province":"IN",
    "wof:name":"Hair Care Ctr",
    "wof:placetype":"venue"
},
  "geometry": {"coordinates":[-86.142961,39.87239],"type":"Point"}
}