{
  "type": "Feature",
  "properties": {
    "iso:country":"US",
    "sg:address":"8518 Stonewall Dr",
    "sg:city":"Indianapolis",
    "sg:classifiers":[
        {
            "category":"Professional",
            "subcategory":"Business Services",
            "type":"Services"
        }
    ],
    "sg:phone":"+1 317 247 4661",
    "sg:postcode":"46231",
    "sg:province":"IN",
    "wof:name":"Csi Claim Solutions Inc",
    "wof:placetype":"venue"
},
  "geometry": {"coordinates":[-86.311981,39.757179],"type":"Point"}
}