{
  "type": "Feature",
  "properties": {
    "iso:country":"US",
    "sg:address":"975 W 6th Ave",
    "sg:city":"Gary",
    "sg:classifiers":[
        {
            "category":"Organizations",
            "subcategory":"Religious Organization",
            "type":"Services"
        }
    ],
    "sg:phone":"+1 219 883 0252",
    "sg:postcode":"46402",
    "sg:province":"IN",
    "sg:tags":[
        "church"
    ],
    "wof:name":"African American Ministries",
    "wof:placetype":"venue"
},
  "geometry": {"coordinates":[-87.34894300000001,41.600058],"type":"Point"}
}