{
  "type": "Feature",
  "properties": {
    "iso:country":"US",
    "sg:address":"3701 Posey County Line Rd N",
    "sg:city":"Evansville",
    "sg:classifiers":[
        {
            "category":"Retail",
            "subcategory":"Veterinary Services",
            "type":"Services"
        }
    ],
    "sg:phone":"+1 812 985 2605",
    "sg:postcode":"47712",
    "sg:province":"IN",
    "sg:tags":[
        "veterinarian"
    ],
    "wof:name":"County Line Clinic",
    "wof:placetype":"venue"
},
  "geometry": {"coordinates":[-87.698911,37.981422],"type":"Point"}
}