{
  "type": "Feature",
  "properties": {
    "iso:country":"US",
    "sg:address":"1000 S Clark Blvd",
    "sg:city":"Clarksville",
    "sg:classifiers":[
        {
            "category":"Home & Garden",
            "subcategory":"Building Materials",
            "type":"Retail Goods"
        }
    ],
    "sg:phone":"+1 812 282 0470",
    "sg:postcode":"47129",
    "sg:province":"IN",
    "sg:tags":[
        "center"
    ],
    "sg:website":"www.homedepot.com",
    "wof:name":"Home Depot",
    "wof:placetype":"venue"
},
  "geometry": {"coordinates":[-85.75669000000001,38.276337],"type":"Point"}
}