{
  "type": "Feature",
  "properties": {
    "iso:country":"US",
    "sg:address":"3500 N Morrison Rd",
    "sg:city":"Muncie",
    "sg:classifiers":[
        {
            "category":"Autos & Motor Vehicles",
            "subcategory":"Auto Supplies",
            "type":"Retail Goods"
        }
    ],
    "sg:phone":"+1 765 284 4660",
    "sg:postcode":"47304",
    "sg:province":"IN",
    "sg:tags":[
        "automobile",
        "stereo",
        "radio"
    ],
    "sg:website":"www.circuitcity.com",
    "wof:name":"Car Stereo Installations",
    "wof:placetype":"venue"
},
  "geometry": {"coordinates":[-85.442618,40.219595],"type":"Point"}
}