{
  "type": "Feature",
  "properties": {
    "iso:country":"US",
    "sg:address":"3459 S Devils Hollow Rd",
    "sg:city":"Milltown",
    "sg:classifiers":[
        {
            "category":"Retail",
            "subcategory":"Repair Shop",
            "type":"Services"
        }
    ],
    "sg:phone":"+1 812 633 4377",
    "sg:postcode":"47145",
    "sg:province":"IN",
    "sg:tags":[
        "refrigeration"
    ],
    "wof:name":"M & M Refrigeration Inc",
    "wof:placetype":"venue"
},
  "geometry": {"coordinates":[-86.29979400000001,38.311175],"type":"Point"}
}