{
  "type": "Feature",
  "properties": {
    "iso:country":"US",
    "sg:address":"1824 W Dupont Rd",
    "sg:city":"Fort Wayne",
    "sg:classifiers":[
        {
            "category":"Health Services",
            "subcategory":"Doctor",
            "type":"Services"
        }
    ],
    "sg:phone":"+1 260 490 0338",
    "sg:postcode":"46818",
    "sg:province":"IN",
    "sg:tags":[
        "dentist"
    ],
    "wof:name":"Dentists",
    "wof:placetype":"venue"
},
  "geometry": {"coordinates":[-85.174189,41.177686],"type":"Point"}
}