{
  "type": "Feature",
  "properties": {
    "iso:country":"US",
    "sg:address":"2406 Brown St",
    "sg:city":"Anderson",
    "sg:classifiers":[
        {
            "category":"Professional",
            "type":"Services"
        }
    ],
    "sg:phone":"+1 765 644 0443",
    "sg:postcode":"46016",
    "sg:province":"IN",
    "sg:tags":[
        "establishment"
    ],
    "wof:name":"Petrey's Quick Clean",
    "wof:placetype":"venue"
},
  "geometry": {"coordinates":[-85.68237,40.091022],"type":"Point"}
}