{
  "type": "Feature",
  "properties": {
    "addr:full":"2516 Industrial Park Dr S Goshen IN 46526",
    "addr:housenumber":"2516",
    "addr:postcode":"46526",
    "addr:street":"Industrial Park Dr S",
    "iso:country":"US",
    "sg:address":"2516 Industrial Park Dr S",
    "sg:city":"Goshen",
    "sg:classifiers":[
        {
            "category":"Manufacturing",
            "subcategory":"Printing",
            "type":"Manufacturing & Wholesale Goods"
        }
    ],
    "sg:phone":"+1 574 534 6270",
    "sg:postcode":"46526",
    "sg:province":"IN",
    "sg:tags":[
        "printer"
    ],
    "sg:website":"www.economyoffset.com",
    "wof:name":"Economy Offset Printing",
    "wof:placetype":"venue"
},
  "geometry": {"coordinates":[-85.820274,41.553271],"type":"Point"}
}