{
  "type": "Feature",
  "properties": {
    "iso:country":"US",
    "sg:address":"2410 E State Blvd",
    "sg:city":"Fort Wayne",
    "sg:classifiers":[
        {
            "category":"Shopping",
            "subcategory":"Pharmacy",
            "type":"Retail Goods"
        }
    ],
    "sg:phone":"+1 260 483 2128",
    "sg:postcode":"46805",
    "sg:province":"IN",
    "wof:name":"Walgreens",
    "wof:placetype":"venue"
},
  "geometry": {"coordinates":[-85.107382,41.096999],"type":"Point"}
}