{
  "type": "Feature",
  "properties": {
    "iso:country":"US",
    "sg:address":"68354 Main St",
    "sg:city":"New Paris",
    "sg:classifiers":[
        {
            "category":"Professional",
            "type":"Services"
        }
    ],
    "sg:phone":"+1 574 831 5877",
    "sg:postcode":"46553",
    "sg:province":"IN",
    "sg:tags":[
        "establishment"
    ],
    "wof:name":"Don't Call",
    "wof:placetype":"venue"
},
  "geometry": {"coordinates":[-85.830523,41.499891],"type":"Point"}
}