{
  "type": "Feature",
  "properties": {
    "iso:country":"US",
    "sg:address":"6101 N Keystone Ave",
    "sg:city":"Indianapolis",
    "sg:classifiers":[
        {
            "category":"Utilities",
            "subcategory":"Mobile Phone",
            "type":"Services"
        }
    ],
    "sg:phone":"+1 317 253 5097",
    "sg:postcode":"46220",
    "sg:province":"IN",
    "sg:tags":[
        "telephone",
        "cellular"
    ],
    "wof:name":"Wireless 4U",
    "wof:placetype":"venue"
},
  "geometry": {"coordinates":[-86.122154,39.866857],"type":"Point"}
}