{
  "type": "Feature",
  "properties": {
    "iso:country":"US",
    "sg:address":"8634 Louisiana Pl",
    "sg:city":"Merrillville",
    "sg:classifiers":[
        {
            "category":"Professional",
            "subcategory":"Engineering",
            "type":"Services"
        }
    ],
    "sg:phone":"+1 219 795 1271",
    "sg:postcode":"46410",
    "sg:province":"IN",
    "sg:tags":[
        "engineer"
    ],
    "wof:name":"Midwest Engineering Svc",
    "wof:placetype":"venue"
},
  "geometry": {"coordinates":[-87.319777,41.46081],"type":"Point"}
}