{
  "type": "Feature",
  "properties": {
    "iso:country":"US",
    "sg:address":"1600 E Clinton St",
    "sg:city":"Frankfort",
    "sg:classifiers":[
        {
            "category":"Organizations",
            "subcategory":"Religious Organization",
            "type":"Services"
        }
    ],
    "sg:phone":"+1 765 659 2206",
    "sg:postcode":"46041",
    "sg:province":"IN",
    "sg:tags":[
        "church"
    ],
    "wof:name":"Grace Church",
    "wof:placetype":"venue"
},
  "geometry": {"coordinates":[-86.491917,40.280767],"type":"Point"}
}