{
  "type": "Feature",
  "properties": {
    "addr:full":"1435 Christian Blvd Franklin IN 46131",
    "addr:housenumber":"1435",
    "addr:postcode":"46131",
    "addr:street":"Christian Blvd",
    "iso:country":"US",
    "sg:address":"1435 Christian Blvd",
    "sg:city":"Franklin",
    "sg:classifiers":[
        {
            "category":"Social Services",
            "subcategory":"Adult Care",
            "type":"Services"
        }
    ],
    "sg:phone":"+1 317 535 6550",
    "sg:postcode":"46131",
    "sg:province":"IN",
    "sg:tags":[
        "home",
        "residential"
    ],
    "wof:name":"Christina House",
    "wof:placetype":"venue"
},
  "geometry": {"coordinates":[-86.08334600000001,39.538457],"type":"Point"}
}