{
  "type": "Feature",
  "properties": {
    "iso:country":"US",
    "sg:address":"70021 Willow Rd",
    "sg:city":"Walkerton",
    "sg:classifiers":[
        {
            "category":"Personal",
            "subcategory":"Beauty Salon",
            "type":"Services"
        }
    ],
    "sg:phone":"+1 574 586 3893",
    "sg:postcode":"46574",
    "sg:province":"IN",
    "sg:tags":[
        "shop"
    ],
    "wof:name":"Imogene's Beauty Shop",
    "wof:placetype":"venue"
},
  "geometry": {"coordinates":[-86.48630199999999,41.475799],"type":"Point"}
}