{
  "type": "Feature",
  "properties": {
    "iso:country":"US",
    "sg:address":"136 S Section St",
    "sg:city":"Sullivan",
    "sg:classifiers":[
        {
            "category":"Retail",
            "subcategory":"Repair Shop",
            "type":"Services"
        }
    ],
    "sg:phone":"+1 812 268 3276",
    "sg:postcode":"47882",
    "sg:province":"IN",
    "sg:tags":[
        "equipment",
        "telephone",
        "system"
    ],
    "wof:name":"DHOM Telecom",
    "wof:placetype":"venue"
},
  "geometry": {"coordinates":[-87.409726,39.093863],"type":"Point"}
}