{
  "type": "Feature",
  "properties": {
    "iso:country":"US",
    "sg:address":"1604 Broadway",
    "sg:city":"Gary",
    "sg:classifiers":[
        {
            "category":"Personal",
            "subcategory":"Beauty Salon",
            "type":"Services"
        }
    ],
    "sg:phone":"+1 219 885 9730",
    "sg:postcode":"46407",
    "sg:province":"IN",
    "wof:name":"Queen's Hair Fashion",
    "wof:placetype":"venue"
},
  "geometry": {"coordinates":[-87.337085,41.585973],"type":"Point"}
}