{
  "type": "Feature",
  "properties": {
    "iso:country":"US",
    "sg:address":"9145 Mallard Pt",
    "sg:city":"Zionsville",
    "sg:classifiers":[
        {
            "category":"Manufacturing",
            "subcategory":"Apparel",
            "type":"Manufacturing & Wholesale Goods"
        }
    ],
    "sg:phone":"+1 317 769 2207",
    "sg:postcode":"46077",
    "sg:province":"IN",
    "sg:tags":[
        "drapery",
        "custom"
    ],
    "wof:name":"Custom Draperies By Betsy",
    "wof:placetype":"venue"
},
  "geometry": {"coordinates":[-86.297446,40.016864],"type":"Point"}
}