{
  "type": "Feature",
  "properties": {
    "iso:country":"US",
    "sg:address":"3816 Grant St",
    "sg:city":"Gary",
    "sg:classifiers":[
        {
            "category":"Personal",
            "subcategory":"Beauty Salon",
            "type":"Services"
        }
    ],
    "sg:phone":"+1 219 985 2540",
    "sg:postcode":"46408",
    "sg:province":"IN",
    "wof:name":"Precise Hair Designs",
    "wof:placetype":"venue"
},
  "geometry": {"coordinates":[-87.355896,41.548823],"type":"Point"}
}