{
  "type": "Feature",
  "properties": {
    "iso:country":"US",
    "sg:address":"1550 Hampton Ct",
    "sg:city":"Mishawaka",
    "sg:classifiers":[
        {
            "category":"Education",
            "subcategory":"School",
            "type":"Public Place"
        }
    ],
    "sg:phone":"+1 574 254 1595",
    "sg:postcode":"46544",
    "sg:province":"IN",
    "wof:name":"Middle C Piano & Organ Co",
    "wof:placetype":"venue"
},
  "geometry": {"coordinates":[-86.132846,41.645926],"type":"Point"}
}