{
  "type": "Feature",
  "properties": {
    "iso:country":"US",
    "sg:address":"907 Michigan Ave",
    "sg:city":"Laporte",
    "sg:classifiers":[
        {
            "category":"Organizations",
            "subcategory":"Religious Organization",
            "type":"Services"
        }
    ],
    "sg:phone":"+1 219 362 4932",
    "sg:postcode":"46350",
    "sg:province":"IN",
    "sg:tags":[
        "church"
    ],
    "wof:name":"Trinity Lutheran Church",
    "wof:placetype":"venue"
},
  "geometry": {"coordinates":[-86.719945,41.609729],"type":"Point"}
}