{
  "type": "Feature",
  "properties": {
    "iso:country":"US",
    "sg:address":"2214 E Chicago Ave",
    "sg:city":"East Chicago",
    "sg:classifiers":[
        {
            "category":"Insurance",
            "subcategory":"Hazard Insurance",
            "type":"Services"
        }
    ],
    "sg:phone":"+1 219 397 4007",
    "sg:postcode":"46312",
    "sg:province":"IN",
    "sg:tags":[
        "bond"
    ],
    "wof:name":"In Code Personal Bonding Svc",
    "wof:placetype":"venue"
},
  "geometry": {"coordinates":[-87.433871,41.628919],"type":"Point"}
}