{
  "type": "Feature",
  "properties": {
    "addr:full":"12720 North St Dillsboro IN 47018",
    "addr:housenumber":"12720",
    "addr:postcode":"47018",
    "addr:street":"North St",
    "iso:country":"US",
    "sg:address":"12720 North St",
    "sg:city":"Dillsboro",
    "sg:classifiers":[
        {
            "category":"Travel",
            "subcategory":"Travel Agent",
            "type":"Entertainment"
        }
    ],
    "sg:phone":"+1 812 432 5431",
    "sg:postcode":"47018",
    "sg:province":"IN",
    "sg:tags":[
        "agency",
        "bureau"
    ],
    "wof:name":"Nina's Hair & Care Ctr",
    "wof:placetype":"venue"
},
  "geometry": {"coordinates":[-85.05514700000001,39.017758],"type":"Point"}
}