{
  "type": "Feature",
  "properties": {
    "iso:country":"US",
    "sg:address":"12998 S 450 W",
    "sg:city":"Hanna",
    "sg:classifiers":[
        {
            "category":"Building & Trades",
            "subcategory":"Construction",
            "type":"Services"
        }
    ],
    "sg:phone":"+1 219 797 5885",
    "sg:postcode":"46340",
    "sg:province":"IN",
    "sg:tags":[
        "pavement",
        "marking"
    ],
    "wof:name":"Line Makers Inc",
    "wof:placetype":"venue"
},
  "geometry": {"coordinates":[-86.78486100000001,41.418445],"type":"Point"}
}