{
  "type": "Feature",
  "properties": {
    "iso:country":"US",
    "sg:address":"212 W Main St",
    "sg:city":"Portland",
    "sg:classifiers":[
        {
            "category":"Real Estate",
            "subcategory":"Real Estate Agent",
            "type":"Services"
        }
    ],
    "sg:phone":"+1 260 726 2700",
    "sg:postcode":"47371",
    "sg:province":"IN",
    "sg:tags":[
        "business"
    ],
    "wof:name":"Ernest Loy Auctioneer RE",
    "wof:placetype":"venue"
},
  "geometry": {"coordinates":[-84.97927799999999,40.433402],"type":"Point"}
}