{
  "type": "Feature",
  "properties": {
    "iso:country":"US",
    "sg:address":"54641 Gillman Dr",
    "sg:city":"Mishawaka",
    "sg:classifiers":[
        {
            "category":"Building & Trades",
            "subcategory":"Electrical",
            "type":"Services"
        }
    ],
    "sg:phone":"+1 574 254 1639",
    "sg:postcode":"46545",
    "sg:province":"IN",
    "sg:tags":[
        "electric",
        "contractor"
    ],
    "wof:name":"Mann Electric",
    "wof:placetype":"venue"
},
  "geometry": {"coordinates":[-86.112436,41.700103],"type":"Point"}
}