{
  "type": "Feature",
  "properties": {
    "iso:country":"US",
    "sg:address":"2101 N Green River Rd",
    "sg:city":"Evansville",
    "sg:classifiers":[
        {
            "category":"Autos & Motor Vehicles",
            "subcategory":"Fuel & Gas Station",
            "type":"Retail Goods"
        }
    ],
    "sg:phone":"+1 812 473 3941",
    "sg:postcode":"47715",
    "sg:province":"IN",
    "sg:tags":[
        "oil"
    ],
    "wof:name":"Swifty Oil Co",
    "wof:placetype":"venue"
},
  "geometry": {"coordinates":[-87.49248,37.992061],"type":"Point"}
}