{
  "type": "Feature",
  "properties": {
    "iso:country":"US",
    "sg:address":"701 W Main St",
    "sg:city":"Paoli",
    "sg:phone":"+1 812 723 2927",
    "sg:postcode":"47454",
    "sg:province":"IN",
    "sg:tags":[
        "oil"
    ],
    "wof:name":"Ackerman Oil Co",
    "wof:placetype":"venue"
},
  "geometry": {"coordinates":[-86.477704,38.556176],"type":"Point"}
}