{
  "type": "Feature",
  "properties": {
    "iso:country":"US",
    "sg:address":"8600 Grand Blvd",
    "sg:city":"Merrillville",
    "sg:classifiers":[
        {
            "category":"Organizations",
            "subcategory":"Religious Organization",
            "type":"Services"
        }
    ],
    "sg:phone":"+1 219 947 4748",
    "sg:postcode":"46410",
    "sg:province":"IN",
    "sg:tags":[
        "church"
    ],
    "sg:website":"www.ptvm.com",
    "wof:name":"Protection Of The Virgin Mary",
    "wof:placetype":"venue"
},
  "geometry": {"coordinates":[-87.258484,41.461289],"type":"Point"}
}