{
  "type": "Feature",
  "properties": {
    "iso:country":"US",
    "sg:address":"655 E Myers Rd",
    "sg:city":"Boonville",
    "sg:classifiers":[
        {
            "category":"Real Estate",
            "subcategory":"Real Estate Operator",
            "type":"Services"
        }
    ],
    "sg:phone":"+1 812 897 5559",
    "sg:postcode":"47601",
    "sg:province":"IN",
    "sg:tags":[
        "property",
        "lessor"
    ],
    "wof:name":"Sonya Boyer",
    "wof:placetype":"venue"
},
  "geometry": {"coordinates":[-87.224587,37.974871],"type":"Point"}
}