{
  "type": "Feature",
  "properties": {
    "addr:full":"1860 N Rolling Hills Ct Monticello IN 47960",
    "addr:housenumber":"1860",
    "addr:postcode":"47960",
    "addr:street":"N Rolling Hills Ct",
    "iso:country":"US",
    "sg:address":"1860 N Rolling Hills Ct",
    "sg:city":"Monticello",
    "sg:classifiers":[
        {
            "category":"Sports & Exercise",
            "subcategory":"Bowling",
            "type":"Entertainment"
        }
    ],
    "sg:phone":"+1 574 583 2459",
    "sg:postcode":"47960",
    "sg:province":"IN",
    "sg:tags":[
        "center"
    ],
    "wof:name":"American Bowling Congress",
    "wof:placetype":"venue"
},
  "geometry": {"coordinates":[-86.761796,40.777377],"type":"Point"}
}