{
  "type": "Feature",
  "properties": {
    "iso:country":"US",
    "sg:address":"907 S Burlington Dr",
    "sg:city":"Muncie",
    "sg:classifiers":[
        {
            "category":"Manufacturing",
            "subcategory":"Metals",
            "type":"Manufacturing & Wholesale Goods"
        }
    ],
    "sg:phone":"+1 765 284 5594",
    "sg:postcode":"47302",
    "sg:province":"IN",
    "sg:tags":[
        "fabricator",
        "sheet"
    ],
    "wof:name":"Brand Sheet Metal Works",
    "wof:placetype":"venue"
},
  "geometry": {"coordinates":[-85.364631,40.187312],"type":"Point"}
}