{
  "type": "Feature",
  "properties": {
    "iso:country":"US",
    "sg:address":"107 Mack Dr",
    "sg:city":"New Albany",
    "sg:classifiers":[
        {
            "category":"Professional",
            "subcategory":"Employment Agencies",
            "type":"Services"
        }
    ],
    "sg:phone":"+1 812 949 6152",
    "sg:postcode":"47150",
    "sg:province":"IN",
    "sg:tags":[
        "help",
        "supply"
    ],
    "wof:name":"Peter Juodikis Inc",
    "wof:placetype":"venue"
},
  "geometry": {"coordinates":[-85.812401,38.3442],"type":"Point"}
}