{
  "type": "Feature",
  "properties": {
    "iso:country":"US",
    "sg:address":"2620 Laporte Ave",
    "sg:city":"Valparaiso",
    "sg:classifiers":[
        {
            "category":"Personal",
            "subcategory":"Beauty Salon",
            "type":"Services"
        }
    ],
    "sg:phone":"+1 219 531 0296",
    "sg:postcode":"46383",
    "sg:province":"IN",
    "wof:name":"Hair Cuttery",
    "wof:placetype":"venue"
},
  "geometry": {"coordinates":[-87.027427,41.46905],"type":"Point"}
}