{
  "type": "Feature",
  "properties": {
    "addr:full":"5104 N Clinton St Fort Wayne IN 46825",
    "addr:housenumber":"5104",
    "addr:postcode":"46825",
    "addr:street":"N Clinton St",
    "iso:country":"US",
    "sg:address":"5104 N Clinton St",
    "sg:city":"Fort Wayne",
    "sg:classifiers":[
        {
            "category":"Health Services",
            "subcategory":"Doctor",
            "type":"Services"
        }
    ],
    "sg:phone":"+1 260 422 2481",
    "sg:postcode":"46825",
    "sg:province":"IN",
    "sg:tags":[
        "physician",
        "surgeon"
    ],
    "wof:name":"First Care Family Physicians",
    "wof:placetype":"venue"
},
  "geometry": {"coordinates":[-85.12468699999999,41.128448],"type":"Point"}
}