{
  "type": "Feature",
  "properties": {
    "iso:country":"US",
    "sg:address":"1400 Washington Ave",
    "sg:city":"Vincennes",
    "sg:classifiers":[
        {
            "category":"Food & Beverages",
            "subcategory":"Bakery",
            "type":"Retail Goods"
        }
    ],
    "sg:phone":"+1 812 886 9311",
    "sg:postcode":"47591",
    "sg:province":"IN",
    "sg:tags":[
        "baker"
    ],
    "wof:name":"Harold's Jay C Food Store",
    "wof:placetype":"venue"
},
  "geometry": {"coordinates":[-87.513573,38.681886],"type":"Point"}
}