{
  "type": "Feature",
  "properties": {
    "addr:full":"1531 Indiana Ave Indianapolis IN 46202",
    "addr:housenumber":"1531",
    "addr:postcode":"46202",
    "addr:street":"Indiana Ave",
    "iso:country":"US",
    "sg:address":"1531 Indiana Ave",
    "sg:city":"Indianapolis",
    "sg:classifiers":[
        {
            "category":"Professional",
            "type":"Services"
        }
    ],
    "sg:phone":"+1 317 803 9553",
    "sg:postcode":"46202",
    "sg:province":"IN",
    "sg:tags":[
        "transportation"
    ],
    "wof:name":"Transportation",
    "wof:placetype":"venue"
},
  "geometry": {"coordinates":[-86.17521000000001,39.780715],"type":"Point"}
}