{
  "type": "Feature",
  "properties": {
    "addr:full":"8060 Rhode Ct Dyer IN 46311",
    "addr:housenumber":"8060",
    "addr:postcode":"46311",
    "addr:street":"Rhode Ct",
    "iso:country":"US",
    "sg:address":"8060 Rhode Ct",
    "sg:city":"Dyer",
    "sg:classifiers":[
        {
            "category":"Building & Trades",
            "subcategory":"Construction",
            "type":"Services"
        }
    ],
    "sg:phone":"+1 219 746 6399",
    "sg:postcode":"46311",
    "sg:province":"IN",
    "sg:tags":[
        "house"
    ],
    "wof:name":"PJ Reed & Associates",
    "wof:placetype":"venue"
},
  "geometry": {"coordinates":[-87.50652700000001,41.47232],"type":"Point"}
}