{
  "type": "Feature",
  "properties": {
    "addr:full":"6944 Kennedy Ave Hammond IN 46323",
    "addr:housenumber":"6944",
    "addr:postcode":"46323",
    "addr:street":"Kennedy Ave",
    "iso:country":"US",
    "sg:address":"6944 Kennedy Ave",
    "sg:city":"Hammond",
    "sg:classifiers":[
        {
            "category":"Shopping",
            "type":"Retail Goods"
        }
    ],
    "sg:phone":"+1 219 845 7387",
    "sg:postcode":"46323",
    "sg:province":"IN",
    "sg:tags":[
        "pet",
        "food",
        "store",
        "supply"
    ],
    "wof:name":"Pet Playground",
    "wof:placetype":"venue"
},
  "geometry": {"coordinates":[-87.46181300000001,41.587541],"type":"Point"}
}