{
  "type": "Feature",
  "properties": {
    "addr:full":"7800 E 96th St Fishers IN 46038",
    "addr:housenumber":"7800",
    "addr:postcode":"46038",
    "addr:street":"E 96Th St",
    "iso:country":"US",
    "sg:address":"7800 E 96th St",
    "sg:city":"Fishers",
    "sg:classifiers":[
        {
            "category":"Freight",
            "type":"Transportation"
        },
        {
            "category":"Professional",
            "subcategory":"Printing & Photocopies",
            "type":"Services"
        }
    ],
    "sg:phone":"+1 317 578 3232",
    "sg:postcode":"46038",
    "sg:province":"IN",
    "sg:tags":[
        "shipping"
    ],
    "sg:website":"www.fedex.com/us/office/",
    "wof:name":"FedEx Office Print & Ship Center",
    "wof:placetype":"venue"
},
  "geometry": {"coordinates":[-86.02481899999999,39.927389],"type":"Point"}
}