{
  "type": "Feature",
  "properties": {
    "iso:country":"US",
    "sg:address":"100 Coliseum Blvd N",
    "sg:city":"Fort Wayne",
    "sg:classifiers":[
        {
            "category":"Autos & Motor Vehicles",
            "subcategory":"Automobile Sales",
            "type":"Retail Goods"
        }
    ],
    "sg:phone":"+1 260 484 1533",
    "sg:postcode":"46805",
    "sg:province":"IN",
    "sg:tags":[
        "car",
        "dealer"
    ],
    "sg:website":"www.glenbrookdodge.com",
    "wof:name":"Glenbrook Dodge/Hyundai",
    "wof:placetype":"venue"
},
  "geometry": {"coordinates":[-85.087932,41.088615],"type":"Point"}
}