{
  "type": "Feature",
  "properties": {
    "iso:country":"US",
    "sg:address":"219 Main St",
    "sg:city":"Michigantown",
    "sg:classifiers":[
        {
            "category":"Banks & Credit Unions",
            "subcategory":"Bank",
            "type":"Services"
        }
    ],
    "sg:phone":"+1 765 249 2216",
    "sg:postcode":"46057",
    "sg:province":"IN",
    "wof:name":"Farmers Bank",
    "wof:placetype":"venue"
},
  "geometry": {"coordinates":[-86.39285700000001,40.325013],"type":"Point"}
}