{
  "type": "Feature",
  "properties": {
    "iso:country":"US",
    "sg:address":"1722 W Mishawaka Rd",
    "sg:city":"Elkhart",
    "sg:classifiers":[
        {
            "category":"Manufacturing",
            "subcategory":"Motor Vehicles & Parts",
            "type":"Manufacturing & Wholesale Goods"
        }
    ],
    "sg:phone":"+1 574 295 8060",
    "sg:postcode":"46517",
    "sg:province":"IN",
    "sg:tags":[
        "home"
    ],
    "sg:website":"www.monacocoach.com",
    "wof:name":"Monaco Coach Corp",
    "wof:placetype":"venue"
},
  "geometry": {"coordinates":[-86.002844,41.656112],"type":"Point"}
}