{
  "type": "Feature",
  "properties": {
    "iso:country":"US",
    "sg:address":"525 Main St",
    "sg:city":"Hope",
    "sg:classifiers":[
        {
            "category":"Restaurant",
            "type":"Food & Drink"
        }
    ],
    "sg:phone":"+1 812 546 5950",
    "sg:postcode":"47246",
    "sg:province":"IN",
    "wof:name":"Corner Cafe",
    "wof:placetype":"venue"
},
  "geometry": {"coordinates":[-85.77150899999999,39.302158],"type":"Point"}
}