{
  "type": "Feature",
  "properties": {
    "iso:country":"US",
    "sg:address":"1940 Etna Ave",
    "sg:city":"Huntington",
    "sg:classifiers":[
        {
            "category":"Home & Garden",
            "subcategory":"Carpets & Floor Coverings",
            "type":"Retail Goods"
        }
    ],
    "sg:phone":"+1 260 356 7226",
    "sg:postcode":"46750",
    "sg:province":"IN",
    "sg:tags":[
        "dealer",
        "rug"
    ],
    "wof:name":"Lehman Floor Covering Inc",
    "wof:placetype":"venue"
},
  "geometry": {"coordinates":[-85.506849,40.859469],"type":"Point"}
}