{
  "type": "Feature",
  "properties": {
    "iso:country":"US",
    "sg:address":"421 S 2nd St",
    "sg:city":"Elkhart",
    "sg:classifiers":[
        {
            "category":"Insurance",
            "subcategory":"Insurance Agent",
            "type":"Services"
        }
    ],
    "sg:phone":"+1 574 293 1803",
    "sg:postcode":"46516",
    "sg:province":"IN",
    "wof:name":"Equitable Life Assurance Soc",
    "wof:placetype":"venue"
},
  "geometry": {"coordinates":[-85.973027,41.682903],"type":"Point"}
}