{
  "type": "Feature",
  "properties": {
    "iso:country":"US",
    "sg:address":"14623 Roeriver Ct",
    "sg:city":"Noblesville",
    "sg:classifiers":[
        {
            "category":"Building & Trades",
            "subcategory":"Construction",
            "type":"Services"
        }
    ],
    "sg:phone":"+1 317 774 0674",
    "sg:postcode":"46060",
    "sg:province":"IN",
    "sg:tags":[
        "house"
    ],
    "wof:name":"Royston Construction & Remodel",
    "wof:placetype":"venue"
},
  "geometry": {"coordinates":[-85.955073,40.001915],"type":"Point"}
}