{
  "type": "Feature",
  "properties": {
    "iso:country":"US",
    "sg:address":"8024 Hogue Rd",
    "sg:city":"Evansville",
    "sg:classifiers":[
        {
            "category":"Building & Trades",
            "subcategory":"Construction",
            "type":"Services"
        }
    ],
    "sg:phone":"+1 812 985 3034",
    "sg:postcode":"47712",
    "sg:province":"IN",
    "sg:tags":[
        "house"
    ],
    "wof:name":"Allied Remodelers",
    "wof:placetype":"venue"
},
  "geometry": {"coordinates":[-87.674351,37.982106],"type":"Point"}
}