{
  "type": "Feature",
  "properties": {
    "iso:country":"US",
    "sg:address":"5471 State Rd 101",
    "sg:city":"Saint Joe",
    "sg:phone":"+1 260 337 5363",
    "sg:postcode":"46785",
    "sg:province":"IN",
    "sg:tags":[
        "farm",
        "corn",
        "soybean"
    ],
    "wof:name":"Holman Farms Inc",
    "wof:placetype":"venue"
},
  "geometry": {"coordinates":[-84.868268,41.33573],"type":"Point"}
}