{
  "type": "Feature",
  "properties": {
    "iso:country":"US",
    "sg:address":"2070 Indianapolis Ave",
    "sg:city":"Lebanon",
    "sg:classifiers":[
        {
            "category":"Manufacturing",
            "subcategory":"Tools & Machinery",
            "type":"Manufacturing & Wholesale Goods"
        }
    ],
    "sg:phone":"+1 765 482 1345",
    "sg:postcode":"46052",
    "sg:province":"IN",
    "sg:tags":[
        "mold",
        "special"
    ],
    "wof:name":"Qualified Tool & Die",
    "wof:placetype":"venue"
},
  "geometry": {"coordinates":[-86.44663,40.026056],"type":"Point"}
}