{
  "type": "Feature",
  "properties": {
    "addr:full":"7712 89th St Indianapolis IN 46256",
    "addr:housenumber":"7712",
    "addr:postcode":"46256",
    "addr:street":"89Th St",
    "iso:country":"US",
    "sg:address":"7712 89th St",
    "sg:city":"Indianapolis",
    "sg:classifiers":[
        {
            "category":"Wholesale",
            "subcategory":"Machinery & Supplies",
            "type":"Manufacturing & Wholesale Goods"
        }
    ],
    "sg:phone":"+1 317 842 3320",
    "sg:postcode":"46256",
    "sg:province":"IN",
    "sg:tags":[
        "tool"
    ],
    "wof:name":"Indiana Consolidated Distr",
    "wof:placetype":"venue"
},
  "geometry": {"coordinates":[-86.029922,39.917611],"type":"Point"}
}