{
  "type": "Feature",
  "properties": {
    "addr:full":"2179 E Franklin St Evansville IN 47711",
    "addr:housenumber":"2179",
    "addr:postcode":"47711",
    "addr:street":"E Franklin St",
    "iso:country":"US",
    "sg:address":"2179 E Franklin St",
    "sg:city":"Evansville",
    "sg:classifiers":[
        {
            "category":"Retail",
            "subcategory":"Portrait Studio",
            "type":"Services"
        }
    ],
    "sg:phone":"+1 812 473 4815",
    "sg:postcode":"47711",
    "sg:province":"IN",
    "sg:tags":[
        "photographer"
    ],
    "wof:name":"Owen Small Photography",
    "wof:placetype":"venue"
},
  "geometry": {"coordinates":[-87.5258,37.980179],"type":"Point"}
}