{
  "type": "Feature",
  "properties": {
    "iso:country":"US",
    "sg:address":"4 N 6th St",
    "sg:city":"Richmond",
    "sg:classifiers":[
        {
            "category":"Insurance",
            "subcategory":"Insurance Agent",
            "type":"Services"
        }
    ],
    "sg:phone":"+1 765 983 3888",
    "sg:postcode":"47374",
    "sg:province":"IN",
    "wof:name":"Affordable Insurance",
    "wof:placetype":"venue"
},
  "geometry": {"coordinates":[-84.894052,39.829695],"type":"Point"}
}