{
  "type": "Feature",
  "properties": {
    "addr:full":"5010 W Division Rd Jasper IN 47546",
    "addr:housenumber":"5010",
    "addr:postcode":"47546",
    "addr:street":"W Division Rd",
    "iso:country":"US",
    "sg:address":"5010 W Division Rd",
    "sg:city":"Jasper",
    "sg:classifiers":[
        {
            "category":"Food & Beverages",
            "subcategory":"Groceries & Convenience Stores",
            "type":"Retail Goods"
        }
    ],
    "sg:phone":"+1 812 482 7496",
    "sg:postcode":"47546",
    "sg:province":"IN",
    "sg:tags":[
        "business"
    ],
    "wof:name":"Todd Sales",
    "wof:placetype":"venue"
},
  "geometry": {"coordinates":[-86.994376,38.378285],"type":"Point"}
}