{
  "type": "Feature",
  "properties": {
    "iso:country":"US",
    "sg:address":"208 8th St",
    "sg:city":"Monroe City",
    "sg:classifiers":[
        {
            "category":"Organizations",
            "subcategory":"Religious Organization",
            "type":"Services"
        }
    ],
    "sg:phone":"+1 812 743 5171",
    "sg:postcode":"47557",
    "sg:province":"IN",
    "sg:tags":[
        "church"
    ],
    "wof:name":"Cumberland Presbyterian Church",
    "wof:placetype":"venue"
},
  "geometry": {"coordinates":[-87.354963,38.614867],"type":"Point"}
}