{
  "type": "Feature",
  "properties": {
    "iso:country":"US",
    "sg:address":"8450 Beckinhill Ct",
    "sg:city":"Indianapolis",
    "sg:classifiers":[
        {
            "category":"Insurance",
            "subcategory":"Insurance Agent",
            "type":"Services"
        }
    ],
    "sg:phone":"+1 317 842 1277",
    "sg:postcode":"46256",
    "sg:province":"IN",
    "wof:name":"Handley Benefits",
    "wof:placetype":"venue"
},
  "geometry": {"coordinates":[-86.018057,39.911681],"type":"Point"}
}