{
  "type": "Feature",
  "properties": {
    "iso:country":"US",
    "sg:address":"3700 E Pontiac St",
    "sg:city":"Fort Wayne",
    "sg:classifiers":[
        {
            "category":"Freight",
            "type":"Transportation"
        }
    ],
    "sg:phone":"+1 260 420 4885",
    "sg:postcode":"46803",
    "sg:province":"IN",
    "sg:tags":[
        "warehouse"
    ],
    "wof:name":"Fort Wayne Liquid Coatings",
    "wof:placetype":"venue"
},
  "geometry": {"coordinates":[-85.08942999999999,41.061575],"type":"Point"}
}