{
  "type": "Feature",
  "properties": {
    "iso:country":"US",
    "sg:address":"7542 E Co Rd 800 N",
    "sg:city":"Twelve Mile",
    "sg:classifiers":[
        {
            "category":"Building & Trades",
            "subcategory":"Electrical",
            "type":"Services"
        }
    ],
    "sg:phone":"+1 574 664 4014",
    "sg:postcode":"46988",
    "sg:province":"IN",
    "sg:tags":[
        "electric",
        "contractor"
    ],
    "wof:name":"WRAY Contracting",
    "wof:placetype":"venue"
},
  "geometry": {"coordinates":[-86.225171,40.879181],"type":"Point"}
}