{
  "type": "Feature",
  "properties": {
    "iso:country":"US",
    "sg:address":"9011 N Meridian St",
    "sg:city":"Indianapolis",
    "sg:classifiers":[
        {
            "category":"Building & Trades",
            "subcategory":"Construction",
            "type":"Services"
        }
    ],
    "sg:phone":"+1 317 574 0840",
    "sg:postcode":"46260",
    "sg:province":"IN",
    "sg:tags":[
        "residential",
        "builder",
        "home"
    ],
    "wof:name":"US Home",
    "wof:placetype":"venue"
},
  "geometry": {"coordinates":[-86.157852,39.917106],"type":"Point"}
}