{
  "type": "Feature",
  "properties": {
    "iso:country":"US",
    "sg:address":"1055 Division St",
    "sg:city":"Noblesville",
    "sg:classifiers":[
        {
            "category":"Organizations",
            "subcategory":"Religious Organization",
            "type":"Services"
        }
    ],
    "sg:phone":"+1 317 773 3686",
    "sg:postcode":"46060",
    "sg:province":"IN",
    "sg:tags":[
        "church"
    ],
    "wof:name":"Friends Church",
    "wof:placetype":"venue"
},
  "geometry": {"coordinates":[-86.011526,40.042252],"type":"Point"}
}