{
  "type": "Feature",
  "properties": {
    "iso:country":"US",
    "sg:address":"612 E Bristol St",
    "sg:city":"Elkhart",
    "sg:classifiers":[
        {
            "category":"Social Services",
            "type":"Services"
        }
    ],
    "sg:phone":"+1 574 522 4323",
    "sg:postcode":"46514",
    "sg:province":"IN",
    "sg:tags":[
        "counselor",
        "marriage",
        "family"
    ],
    "wof:name":"Reaching Out Counseling LLC",
    "wof:placetype":"venue"
},
  "geometry": {"coordinates":[-85.96861,41.702658],"type":"Point"}
}