{
  "type": "Feature",
  "properties": {
    "iso:country":"US",
    "sg:address":"8465 Keystone Xing",
    "sg:city":"Indianapolis",
    "sg:classifiers":[
        {
            "category":"Professional",
            "subcategory":"Accounting & Tax Preparation",
            "type":"Services"
        }
    ],
    "sg:phone":"+1 317 257 4100",
    "sg:postcode":"46240",
    "sg:province":"IN",
    "sg:tags":[
        "accountant"
    ],
    "wof:name":"Gartrell H Lynn CPA",
    "wof:placetype":"venue"
},
  "geometry": {"coordinates":[-86.1147,39.910198],"type":"Point"}
}