{
  "type": "Feature",
  "properties": {
    "iso:country":"US",
    "sg:address":"207 E Water St",
    "sg:city":"Paoli",
    "sg:classifiers":[
        {
            "category":"Personal",
            "subcategory":"Beauty Salon",
            "type":"Services"
        }
    ],
    "sg:phone":"+1 812 723 5698",
    "sg:postcode":"47454",
    "sg:province":"IN",
    "wof:name":"Hair Affair",
    "wof:placetype":"venue"
},
  "geometry": {"coordinates":[-86.46707000000001,38.554992],"type":"Point"}
}