{
  "type": "Feature",
  "properties": {
    "iso:country":"US",
    "sg:address":"1900 Springland Ave",
    "sg:city":"Michigan City",
    "sg:classifiers":[
        {
            "category":"Organizations",
            "subcategory":"Community Association",
            "type":"Services"
        }
    ],
    "sg:phone":"+1 219 872 8624",
    "sg:postcode":"46360",
    "sg:province":"IN",
    "sg:tags":[
        "club"
    ],
    "sg:website":"www.pottawattomie.com",
    "wof:name":"Pottawattomie Country Club",
    "wof:placetype":"venue"
},
  "geometry": {"coordinates":[-86.85533100000001,41.716649],"type":"Point"}
}