{
  "type": "Feature",
  "properties": {
    "iso:country":"US",
    "sg:address":"634 E Lake Shore Dr",
    "sg:city":"Culver",
    "sg:classifiers":[
        {
            "category":"Restaurant",
            "type":"Food & Drink"
        }
    ],
    "sg:phone":"+1 574 842 6326",
    "sg:postcode":"46511",
    "sg:province":"IN",
    "sg:tags":[
        "shop",
        "coffee"
    ],
    "wof:name":"Culver Coffee Co",
    "wof:placetype":"venue"
},
  "geometry": {"coordinates":[-86.41868599999999,41.218873],"type":"Point"}
}