{
  "type": "Feature",
  "properties": {
    "addr:full":"60 S 2nd St Zionsville IN 46077",
    "addr:housenumber":"60",
    "addr:postcode":"46077",
    "addr:street":"S 2Nd St",
    "iso:country":"US",
    "sg:address":"60 S 2nd St",
    "sg:city":"Zionsville",
    "sg:classifiers":[
        {
            "category":"Manufacturing",
            "subcategory":"Lumber",
            "type":"Manufacturing & Wholesale Goods"
        }
    ],
    "sg:phone":"+1 317 873 3792",
    "sg:postcode":"46077",
    "sg:province":"IN",
    "sg:tags":[
        "operation",
        "timber",
        "tract"
    ],
    "wof:name":"Ralph Stacy",
    "wof:placetype":"venue"
},
  "geometry": {"coordinates":[-86.262941,39.951015],"type":"Point"}
}