{
  "type": "Feature",
  "properties": {
    "iso:country":"US",
    "sg:address":"7350 Twin Beech Dr",
    "sg:city":"Indianapolis",
    "sg:classifiers":[
        {
            "category":"Professional",
            "type":"Services"
        }
    ],
    "sg:phone":"+1 317 377 0616",
    "sg:postcode":"46226",
    "sg:province":"IN",
    "wof:name":"Chance Nelson Closing Svc Inc",
    "wof:placetype":"venue"
},
  "geometry": {"coordinates":[-86.039107,39.848111],"type":"Point"}
}