{
  "type": "Feature",
  "properties": {
    "iso:country":"US",
    "sg:address":"8 Chase Park",
    "sg:city":"Logansport",
    "sg:classifiers":[
        {
            "category":"Health Services",
            "subcategory":"Doctor",
            "type":"Services"
        }
    ],
    "sg:phone":"+1 574 722 6365",
    "sg:postcode":"46947",
    "sg:province":"IN",
    "sg:tags":[
        "dentist"
    ],
    "wof:name":"OMS Ctr Of Lafayette",
    "wof:placetype":"venue"
},
  "geometry": {"coordinates":[-86.35236,40.76981],"type":"Point"}
}