{
  "type": "Feature",
  "properties": {
    "iso:country":"US",
    "sg:address":"6117 Guilford Ave",
    "sg:city":"Indianapolis",
    "sg:classifiers":[
        {
            "category":"Banks & Credit Unions",
            "subcategory":"Bank",
            "type":"Services"
        }
    ],
    "sg:phone":"+1 317 251 5686",
    "sg:postcode":"46220",
    "sg:province":"IN",
    "sg:tags":[
        "loan",
        "real estate"
    ],
    "wof:name":"Premier Mortgage Funding Inc",
    "wof:placetype":"venue"
},
  "geometry": {"coordinates":[-86.14322,39.866347],"type":"Point"}
}