{
  "type": "Feature",
  "properties": {
    "iso:country":"US",
    "sg:address":"400 N Market St",
    "sg:city":"Monon",
    "sg:classifiers":[
        {
            "category":"Professional",
            "type":"Services"
        }
    ],
    "sg:phone":"+1 219 253 9369",
    "sg:postcode":"47959",
    "sg:province":"IN",
    "sg:tags":[
        "establishment"
    ],
    "wof:name":"Monon Civic Ctr",
    "wof:placetype":"venue"
},
  "geometry": {"coordinates":[-86.87908,40.864409],"type":"Point"}
}