{
  "type": "Feature",
  "properties": {
    "iso:country":"US",
    "sg:address":"3351 Central Ave",
    "sg:city":"Indianapolis",
    "sg:classifiers":[
        {
            "category":"Restaurant",
            "type":"Food & Drink"
        }
    ],
    "sg:phone":"+1 317 931 1591",
    "sg:postcode":"46205",
    "sg:province":"IN",
    "wof:name":"Central Seafood",
    "wof:placetype":"venue"
},
  "geometry": {"coordinates":[-86.149602,39.816694],"type":"Point"}
}