{
  "type": "Feature",
  "properties": {
    "iso:country":"US",
    "sg:address":"10150 Zionsville Rd",
    "sg:city":"Zionsville",
    "sg:classifiers":[
        {
            "category":"Utilities",
            "subcategory":"Refuse",
            "type":"Services"
        }
    ],
    "sg:phone":"+1 317 873 4939",
    "sg:postcode":"46077",
    "sg:province":"IN",
    "sg:tags":[
        "landfill"
    ],
    "wof:name":"Worman Enterprises Organic",
    "wof:placetype":"venue"
},
  "geometry": {"coordinates":[-86.25991999999999,39.942747],"type":"Point"}
}