{
  "type": "Feature",
  "properties": {
    "iso:country":"US",
    "sg:address":"319 W Lusher Ave",
    "sg:city":"Elkhart",
    "sg:classifiers":[
        {
            "category":"Shopping",
            "subcategory":"Clothing, Apparel, & Fashions",
            "type":"Retail Goods"
        }
    ],
    "sg:phone":"+1 574 522 6450",
    "sg:postcode":"46517",
    "sg:province":"IN",
    "sg:tags":[
        "family"
    ],
    "wof:name":"Cuadra Western Wear",
    "wof:placetype":"venue"
},
  "geometry": {"coordinates":[-85.972275,41.666662],"type":"Point"}
}