{
  "type": "Feature",
  "properties": {
    "addr:full":"110 W Washington St Indianapolis IN 46204",
    "addr:housenumber":"110",
    "addr:postcode":"46204",
    "addr:street":"W Washington St",
    "iso:country":"US",
    "sg:address":"110 W Washington St",
    "sg:city":"Indianapolis",
    "sg:classifiers":[
        {
            "category":"Shopping",
            "subcategory":"Clothing, Apparel, & Fashions",
            "type":"Retail Goods"
        }
    ],
    "sg:phone":"+1 317 955 8949",
    "sg:postcode":"46204",
    "sg:province":"IN",
    "sg:website":"www.oldnavy.com",
    "wof:name":"Old Navy",
    "wof:placetype":"venue"
},
  "geometry": {"coordinates":[-86.161721,39.767162],"type":"Point"}
}