{
  "type": "Feature",
  "properties": {
    "addr:full":"8596 W 700 S Francesville IN 47946",
    "addr:housenumber":"8596",
    "addr:postcode":"47946",
    "addr:street":"W 700 S",
    "iso:country":"US",
    "sg:address":"8596 W 700 S",
    "sg:city":"Francesville",
    "sg:classifiers":[
        {
            "category":"Wholesale",
            "subcategory":"Poultry",
            "type":"Manufacturing & Wholesale Goods"
        }
    ],
    "sg:phone":"+1 574 595 6102",
    "sg:postcode":"47946",
    "sg:province":"IN",
    "sg:tags":[
        "eggs"
    ],
    "sg:website":"www.goodegg.com",
    "wof:name":"Rose Acre Farms",
    "wof:placetype":"venue"
},
  "geometry": {"coordinates":[-86.829719,40.9559],"type":"Point"}
}