{
  "type": "Feature",
  "properties": {
    "iso:country":"US",
    "sg:address":"203 S Mc Creary St",
    "sg:city":"Fort Branch",
    "sg:classifiers":[
        {
            "category":"Manufacturing",
            "subcategory":"Printing",
            "type":"Manufacturing & Wholesale Goods"
        }
    ],
    "sg:phone":"+1 812 753 3553",
    "sg:postcode":"47648",
    "sg:province":"IN",
    "sg:tags":[
        "newspaper"
    ],
    "wof:name":"South Gibson Star Times",
    "wof:placetype":"venue"
},
  "geometry": {"coordinates":[-87.580032,38.24653],"type":"Point"}
}