{
  "type": "Feature",
  "properties": {
    "iso:country":"US",
    "sg:address":"2601 S Mary's Ln",
    "sg:city":"Rensselaer",
    "sg:classifiers":[
        {
            "category":"Freight",
            "type":"Transportation"
        }
    ],
    "sg:phone":"+1 219 866 3899",
    "sg:postcode":"47978",
    "sg:province":"IN",
    "sg:tags":[
        "trucking"
    ],
    "wof:name":"Reggie's",
    "wof:placetype":"venue"
},
  "geometry": {"coordinates":[-87.156618,40.908997],"type":"Point"}
}