{
  "type": "Feature",
  "properties": {
    "iso:country":"US",
    "sg:address":"120 Center St",
    "sg:city":"Greenfield",
    "sg:classifiers":[
        {
            "category":"Retail",
            "subcategory":"Auto Repair",
            "type":"Services"
        }
    ],
    "sg:phone":"+1 317 462 4337",
    "sg:postcode":"46140",
    "sg:province":"IN",
    "sg:tags":[
        "automotive"
    ],
    "wof:name":"G T S Towing Service",
    "wof:placetype":"venue"
},
  "geometry": {"coordinates":[-85.77685,39.783297],"type":"Point"}
}