{
  "type": "Feature",
  "properties": {
    "iso:country":"US",
    "sg:address":"1125 W Florida St",
    "sg:city":"Evansville",
    "sg:classifiers":[
        {
            "category":"Freight",
            "type":"Transportation"
        }
    ],
    "sg:phone":"+1 812 424 3542",
    "sg:postcode":"47710",
    "sg:province":"IN",
    "sg:tags":[
        "trucking"
    ],
    "wof:name":"Shirley Cartage",
    "wof:placetype":"venue"
},
  "geometry": {"coordinates":[-87.580544,37.989474],"type":"Point"}
}