{
  "type": "Feature",
  "properties": {
    "iso:country":"US",
    "sg:address":"1350 Brookville Way",
    "sg:city":"Indianapolis",
    "sg:classifiers":[
        {
            "category":"Airline",
            "type":"Transportation"
        }
    ],
    "sg:phone":"+1 317 241 4464",
    "sg:postcode":"46239",
    "sg:province":"IN",
    "sg:tags":[
        "scheduled",
        "air"
    ],
    "wof:name":"D H L Worldwide Express",
    "wof:placetype":"venue"
},
  "geometry": {"coordinates":[-86.045342,39.753015],"type":"Point"}
}