{
  "type": "Feature",
  "properties": {
    "addr:full":"607 E Lincolnway Laporte IN 46350",
    "addr:housenumber":"607",
    "addr:postcode":"46350",
    "addr:street":"E Lincolnway",
    "iso:country":"US",
    "sg:address":"607 E Lincolnway",
    "sg:city":"Laporte",
    "sg:classifiers":[
        {
            "category":"Personal",
            "subcategory":"Beauty Salon",
            "type":"Services"
        }
    ],
    "sg:phone":"+1 219 325 0084",
    "sg:postcode":"46350",
    "sg:province":"IN",
    "sg:tags":[
        "school"
    ],
    "wof:name":"Classic College Of Beauty",
    "wof:placetype":"venue"
},
  "geometry": {"coordinates":[-86.707117,41.617836],"type":"Point"}
}