{
  "type": "Feature",
  "properties": {
    "iso:country":"US",
    "sg:address":"873 Lafayette Ave",
    "sg:city":"Terre Haute",
    "sg:classifiers":[
        {
            "category":"Retail",
            "subcategory":"Auto Repair",
            "type":"Services"
        }
    ],
    "sg:phone":"+1 812 238 1832",
    "sg:postcode":"47807",
    "sg:province":"IN",
    "sg:tags":[
        "automobile",
        "top",
        "upholstery"
    ],
    "wof:name":"Myles Auto Svc",
    "wof:placetype":"venue"
},
  "geometry": {"coordinates":[-87.404512,39.484082],"type":"Point"}
}