{
  "type": "Feature",
  "properties": {
    "iso:country":"US",
    "sg:address":"3204 E Paulding Rd",
    "sg:city":"Fort Wayne",
    "sg:classifiers":[
        {
            "category":"Restaurant",
            "type":"Food & Drink"
        }
    ],
    "sg:phone":"+1 260 447 2874",
    "sg:postcode":"46816",
    "sg:province":"IN",
    "wof:name":"Taqueria Flores",
    "wof:placetype":"venue"
},
  "geometry": {"coordinates":[-85.089666,41.032515],"type":"Point"}
}