{
  "type": "Feature",
  "properties": {
    "iso:country":"US",
    "sg:address":"4318 Gaywood Dr",
    "sg:city":"Fort Wayne",
    "sg:classifiers":[
        {
            "category":"Retail",
            "subcategory":"Auto Repair",
            "type":"Services"
        }
    ],
    "sg:phone":"+1 260 456 6149",
    "sg:postcode":"46806",
    "sg:province":"IN",
    "sg:tags":[
        "body",
        "automobile",
        "painting"
    ],
    "wof:name":"Warfield's Body Shop",
    "wof:placetype":"venue"
},
  "geometry": {"coordinates":[-85.122803,41.045294],"type":"Point"}
}