{
  "type": "Feature",
  "properties": {
    "iso:country":"US",
    "sg:address":"930 Maplewood Dr",
    "sg:city":"New Castle",
    "sg:classifiers":[
        {
            "category":"Retail",
            "subcategory":"Repair Shop",
            "type":"Services"
        }
    ],
    "sg:phone":"+1 765 529 9746",
    "sg:postcode":"47362",
    "sg:province":"IN",
    "wof:name":"Piano Tuning",
    "wof:placetype":"venue"
},
  "geometry": {"coordinates":[-85.374946,39.924236],"type":"Point"}
}