{
  "type": "Feature",
  "properties": {
    "iso:country":"US",
    "sg:address":"4897 Kentucky Ave",
    "sg:city":"Indianapolis",
    "sg:classifiers":[
        {
            "category":"Sports & Exercise",
            "subcategory":"Golf",
            "type":"Entertainment"
        }
    ],
    "sg:phone":"+1 317 856 6596",
    "sg:postcode":"46221",
    "sg:province":"IN",
    "sg:tags":[
        "course"
    ],
    "wof:name":"Buffer Park Golf Course",
    "wof:placetype":"venue"
},
  "geometry": {"coordinates":[-86.26511600000001,39.698522],"type":"Point"}
}