{
  "type": "Feature",
  "properties": {
    "iso:country":"US",
    "sg:address":"621 S Bend Ave",
    "sg:city":"South Bend",
    "sg:classifiers":[
        {
            "category":"Personal",
            "subcategory":"Beauty Salon",
            "type":"Services"
        }
    ],
    "sg:phone":"+1 574 287 0971",
    "sg:postcode":"46617",
    "sg:province":"IN",
    "sg:tags":[
        "shop"
    ],
    "wof:name":"Rumor's Hair Design",
    "wof:placetype":"venue"
},
  "geometry": {"coordinates":[-86.242483,41.682946],"type":"Point"}
}