{
  "type": "Feature",
  "properties": {
    "addr:full":"1925 Main St Ferdinand IN 47532",
    "addr:housenumber":"1925",
    "addr:postcode":"47532",
    "addr:street":"Main St Ferdinand In",
    "iso:country":"US",
    "sg:address":"1925 Main St",
    "sg:city":"Ferdinand",
    "sg:classifiers":[
        {
            "category":"Shopping",
            "subcategory":"Pharmacy",
            "type":"Retail Goods"
        }
    ],
    "sg:phone":"+1 812 367 0558",
    "sg:postcode":"47532",
    "sg:province":"IN",
    "wof:name":"CVS Pharmacy",
    "wof:placetype":"venue"
},
  "geometry": {"coordinates":[-86.861385,38.232378],"type":"Point"}
}