{
  "type": "Feature",
  "properties": {
    "iso:country":"US",
    "sg:address":"55 W Madison St",
    "sg:city":"Franklin",
    "sg:classifiers":[
        {
            "category":"Government",
            "subcategory":"Office",
            "type":"Public Place"
        }
    ],
    "sg:phone":"+1 317 736 3609",
    "sg:postcode":"46131",
    "sg:province":"IN",
    "sg:tags":[
        "city"
    ],
    "wof:name":"Franklin City Clerk",
    "wof:placetype":"venue"
},
  "geometry": {"coordinates":[-86.056475,39.481427],"type":"Point"}
}