{
  "type": "Feature",
  "properties": {
    "iso:country":"US",
    "sg:address":"6363 Grand Blvd",
    "sg:city":"Hobart",
    "sg:classifiers":[
        {
            "category":"Sports & Exercise",
            "subcategory":"Golf",
            "type":"Entertainment"
        }
    ],
    "sg:phone":"+1 219 942 6850",
    "sg:postcode":"46342",
    "sg:province":"IN",
    "sg:tags":[
        "course"
    ],
    "wof:name":"Indian Ridge Golf Course",
    "wof:placetype":"venue"
},
  "geometry": {"coordinates":[-87.258646,41.501512],"type":"Point"}
}