{
  "type": "Feature",
  "properties": {
    "addr:full":"1420 W Madison St Plymouth IN 46563",
    "addr:housenumber":"1420",
    "addr:postcode":"46563",
    "addr:street":"W Madison St",
    "iso:country":"US",
    "sg:address":"1420 W Madison St",
    "sg:city":"Plymouth",
    "sg:classifiers":[
        {
            "category":"Real Estate",
            "subcategory":"Real Estate Operator",
            "type":"Services"
        }
    ],
    "sg:phone":"+1 574 936 8754",
    "sg:postcode":"46563",
    "sg:province":"IN",
    "sg:tags":[
        "apartment"
    ],
    "wof:name":"Country Place Apartments",
    "wof:placetype":"venue"
},
  "geometry": {"coordinates":[-86.325062,41.34424],"type":"Point"}
}