{
  "type": "Feature",
  "properties": {
    "iso:country":"US",
    "sg:address":"231 S State Road 135",
    "sg:city":"Greenwood",
    "sg:classifiers":[
        {
            "category":"Shopping",
            "subcategory":"Party Supplies",
            "type":"Retail Goods"
        },
        {
            "category":"Personal",
            "type":"Services"
        }
    ],
    "sg:phone":"+1 317 885 9734",
    "sg:postcode":"46142",
    "sg:province":"IN",
    "sg:tags":[
        "favors",
        "decoration",
        "planning",
        "event"
    ],
    "wof:name":"Discount Party",
    "wof:placetype":"venue"
},
  "geometry": {"coordinates":[-86.15839,39.610823],"type":"Point"}
}