{
  "type": "Feature",
  "properties": {
    "iso:country":"US",
    "sg:address":"2621 Corrinado Ct",
    "sg:city":"Fort Wayne",
    "sg:classifiers":[
        {
            "category":"Manufacturing",
            "subcategory":"Tools & Machinery",
            "type":"Manufacturing & Wholesale Goods"
        }
    ],
    "sg:phone":"+1 260 373 1917",
    "sg:postcode":"46808",
    "sg:province":"IN",
    "sg:tags":[
        "equipment",
        "dental",
        "supply"
    ],
    "wof:name":"Athena Technology Inc",
    "wof:placetype":"venue"
},
  "geometry": {"coordinates":[-85.180082,41.109597],"type":"Point"}
}