{
  "type": "Feature",
  "properties": {
    "addr:full":"8140 Castleton Rd Indianapolis IN 46250",
    "addr:housenumber":"8140",
    "addr:postcode":"46250",
    "addr:street":"Castleton Rd",
    "iso:country":"US",
    "sg:address":"8140 Castleton Rd",
    "sg:city":"Indianapolis",
    "sg:classifiers":[
        {
            "category":"Personal",
            "type":"Services"
        }
    ],
    "sg:phone":"+1 317 579 0600",
    "sg:postcode":"46250",
    "sg:province":"IN",
    "sg:tags":[
        "hair",
        "replacement"
    ],
    "wof:name":"Gentleman's Headquarters",
    "wof:placetype":"venue"
},
  "geometry": {"coordinates":[-86.050753,39.904065],"type":"Point"}
}