{
  "type": "Feature",
  "properties": {
    "iso:country":"US",
    "sg:address":"40 W Hill St",
    "sg:city":"Wabash",
    "sg:classifiers":[
        {
            "category":"Freight",
            "type":"Transportation"
        }
    ],
    "sg:phone":"+1 260 563 4262",
    "sg:postcode":"46992",
    "sg:province":"IN",
    "sg:tags":[
        "commercial",
        "storage"
    ],
    "wof:name":"Mini-Mac Warehouses",
    "wof:placetype":"venue"
},
  "geometry": {"coordinates":[-85.821478,40.798817],"type":"Point"}
}