{
  "type": "Feature",
  "properties": {
    "iso:country":"US",
    "sg:address":"9135 W Smith St",
    "sg:city":"Yorktown",
    "sg:classifiers":[
        {
            "category":"Restaurant",
            "type":"Food & Drink"
        }
    ],
    "sg:phone":"+1 765 759 6784",
    "sg:postcode":"47396",
    "sg:province":"IN",
    "sg:tags":[
        "parlor",
        "ice",
        "cream"
    ],
    "wof:name":"Dairy Queen",
    "wof:placetype":"venue"
},
  "geometry": {"coordinates":[-85.494062,40.173439],"type":"Point"}
}