{
  "type": "Feature",
  "properties": {
    "iso:country":"US",
    "sg:address":"7211 Whiffletree Dr",
    "sg:city":"Newburgh",
    "sg:classifiers":[
        {
            "category":"Professional",
            "subcategory":"Lawyer & Legal Services",
            "type":"Services"
        }
    ],
    "sg:phone":"+1 812 491 8205",
    "sg:postcode":"47630",
    "sg:province":"IN",
    "wof:name":"GSM Sports",
    "wof:placetype":"venue"
},
  "geometry": {"coordinates":[-87.38047,37.939112],"type":"Point"}
}