{
  "type": "Feature",
  "properties": {
    "iso:country":"US",
    "sg:address":"627 Eastern Blvd",
    "sg:city":"Clarksville",
    "sg:classifiers":[
        {
            "category":"Shopping",
            "subcategory":"Pharmacy",
            "type":"Retail Goods"
        }
    ],
    "sg:phone":"+1 812 283 7941",
    "sg:postcode":"47129",
    "sg:province":"IN",
    "wof:name":"Mc Clure Drugs & Gift Shop",
    "wof:placetype":"venue"
},
  "geometry": {"coordinates":[-85.76204799999999,38.299549],"type":"Point"}
}