{
  "type": "Feature",
  "properties": {
    "addr:full":"36 E Market St Chrisney IN 47611",
    "addr:housenumber":"36",
    "addr:postcode":"47611",
    "addr:street":"E Market St",
    "iso:country":"US",
    "sg:address":"36 E Market St",
    "sg:city":"Chrisney",
    "sg:classifiers":[
        {
            "category":"Retail",
            "subcategory":"Funeral Services",
            "type":"Services"
        }
    ],
    "sg:phone":"+1 812 362 7671",
    "sg:postcode":"47611",
    "sg:province":"IN",
    "sg:tags":[
        "director"
    ],
    "wof:name":"Youngblood Funeral Home",
    "wof:placetype":"venue"
},
  "geometry": {"coordinates":[-87.035151,38.014646],"type":"Point"}
}