{
  "type": "Feature",
  "properties": {
    "iso:country":"US",
    "sg:address":"2401 Beech St",
    "sg:city":"Valparaiso",
    "sg:classifiers":[
        {
            "category":"Insurance",
            "subcategory":"Insurance Agent",
            "type":"Services"
        }
    ],
    "sg:phone":"+1 219 548 3292",
    "sg:postcode":"46383",
    "sg:province":"IN",
    "wof:name":"Met Life",
    "wof:placetype":"venue"
},
  "geometry": {"coordinates":[-87.028212,41.473979],"type":"Point"}
}