{
  "type": "Feature",
  "properties": {
    "iso:country":"US",
    "sg:address":"3404 Chestnut St",
    "sg:city":"Fort Wayne",
    "sg:classifiers":[
        {
            "category":"Organizations",
            "subcategory":"Religious Organization",
            "type":"Services"
        }
    ],
    "sg:phone":"+1 260 422 7884",
    "sg:postcode":"46803",
    "sg:province":"IN",
    "wof:name":"Tabernacle Baptist Church",
    "wof:placetype":"venue"
},
  "geometry": {"coordinates":[-85.092201,41.069703],"type":"Point"}
}