{
  "type": "Feature",
  "properties": {
    "addr:full":"301 S Michigan St South Bend IN 46601",
    "addr:housenumber":"301",
    "addr:postcode":"46601",
    "addr:street":"S Michigan St",
    "iso:country":"US",
    "sg:address":"301 S Michigan St",
    "sg:city":"South Bend",
    "sg:classifiers":[
        {
            "category":"Restaurant",
            "type":"Food & Drink"
        }
    ],
    "sg:menulink":"http://www.allmenus.com/in/portage/17537-number-1-chinese/menu/",
    "sg:phone":"+1 574 234 8888",
    "sg:postcode":"46601",
    "sg:province":"IN",
    "sg:tags":[
        "asian",
        "chinese"
    ],
    "wof:name":"Number 1 Chinese",
    "wof:placetype":"venue"
},
  "geometry": {"coordinates":[-86.25032299999999,41.673537],"type":"Point"}
}