{
  "type": "Feature",
  "properties": {
    "addr:full":"106 Carolina Dr Walkerton IN 46574",
    "addr:housenumber":"106",
    "addr:postcode":"walkerton;46574",
    "addr:street":"Carolina Dr",
    "iso:country":"US",
    "sg:address":"106 Carolina Dr",
    "sg:city":"Walkerton",
    "sg:classifiers":[
        {
            "category":"Organizations",
            "subcategory":"Community Association",
            "type":"Services"
        }
    ],
    "sg:phone":"+1 219 369 9931",
    "sg:postcode":"46574",
    "sg:province":"IN",
    "sg:tags":[
        "club"
    ],
    "wof:name":"Fish Lake Conservation Club",
    "wof:placetype":"venue"
},
  "geometry": {"coordinates":[-86.550792,41.570023],"type":"Point"}
}