{
  "type": "Feature",
  "properties": {
    "iso:country":"US",
    "sg:address":"408 S Detroit St",
    "sg:city":"Warsaw",
    "sg:classifiers":[
        {
            "category":"Personal",
            "subcategory":"Beauty Salon",
            "type":"Services"
        }
    ],
    "sg:phone":"+1 574 269 9644",
    "sg:postcode":"46580",
    "sg:province":"IN",
    "sg:tags":[
        "cosmetologist"
    ],
    "wof:name":"Karen J Wood",
    "wof:placetype":"venue"
},
  "geometry": {"coordinates":[-85.852896,41.235079],"type":"Point"}
}