{
  "type": "Feature",
  "properties": {
    "addr:full":"519 N Grant St Crown Point IN 46307",
    "addr:housenumber":"519",
    "addr:postcode":"46307",
    "addr:street":"N Grant St",
    "iso:country":"US",
    "sg:address":"519 N Grant St",
    "sg:city":"Crown Point",
    "sg:classifiers":[
        {
            "category":"Sports & Exercise",
            "subcategory":"Bowling",
            "type":"Entertainment"
        }
    ],
    "sg:phone":"+1 219 663 0529",
    "sg:postcode":"46307",
    "sg:province":"IN",
    "wof:name":"Fricke's Recreation",
    "wof:placetype":"venue"
},
  "geometry": {"coordinates":[-87.361,41.423302],"type":"Point"}
}