{
  "type": "Feature",
  "properties": {
    "iso:country":"US",
    "sg:address":"10 N Van Buren St",
    "sg:city":"Nashville",
    "sg:classifiers":[
        {
            "category":"Social Services",
            "type":"Services"
        }
    ],
    "sg:phone":"+1 812 988 8170",
    "sg:postcode":"47448",
    "sg:province":"IN",
    "sg:tags":[
        "organization",
        "welfare"
    ],
    "wof:name":"Big Brothers & Big Sisters",
    "wof:placetype":"venue"
},
  "geometry": {"coordinates":[-86.246871,39.208288],"type":"Point"}
}