{
  "type": "Feature",
  "properties": {
    "iso:country":"US",
    "sg:address":"200 Hoosier Dr",
    "sg:city":"Angola",
    "sg:classifiers":[
        {
            "category":"Health Services",
            "subcategory":"Hospital",
            "type":"Services"
        }
    ],
    "sg:phone":"+1 260 665 9494",
    "sg:postcode":"46703",
    "sg:province":"IN",
    "sg:tags":[
        "mental"
    ],
    "sg:website":"www.northeasterncenter.org",
    "wof:name":"Northeastern Center",
    "wof:placetype":"venue"
},
  "geometry": {"coordinates":[-85.0022,41.663762],"type":"Point"}
}