{
  "type": "Feature",
  "properties": {
    "iso:country":"US",
    "sg:address":"2 McKinley Ave",
    "sg:city":"Frankfort",
    "sg:classifiers":[
        {
            "category":"Professional",
            "subcategory":"Management & Consulting",
            "type":"Services"
        }
    ],
    "sg:phone":"+1 765 654 6195",
    "sg:postcode":"46041",
    "sg:province":"IN",
    "sg:tags":[
        "consultant",
        "automation"
    ],
    "wof:name":"Stoeller Automation Inc",
    "wof:placetype":"venue"
},
  "geometry": {"coordinates":[-86.519879,40.280743],"type":"Point"}
}