{
  "type": "Feature",
  "properties": {
    "iso:country":"US",
    "sg:address":"7011 Grandview Dr",
    "sg:city":"Indianapolis",
    "sg:classifiers":[
        {
            "category":"Taxi",
            "type":"Transportation"
        }
    ],
    "sg:phone":"+1 317 257 9000",
    "sg:postcode":"46260",
    "sg:province":"IN",
    "wof:name":"Follow Car",
    "wof:placetype":"venue"
},
  "geometry": {"coordinates":[-86.18866,39.881556],"type":"Point"}
}