{
  "type": "Feature",
  "properties": {
    "iso:country":"US",
    "sg:address":"10022 State Rd 229",
    "sg:city":"Laurel",
    "sg:classifiers":[
        {
            "category":"Organizations",
            "subcategory":"Religious Organization",
            "type":"Services"
        }
    ],
    "sg:phone":"+1 765 698 3963",
    "sg:postcode":"47030",
    "sg:province":"IN",
    "sg:tags":[
        "church"
    ],
    "wof:name":"Light House Full Gospel",
    "wof:placetype":"venue"
},
  "geometry": {"coordinates":[-85.152246,39.435924],"type":"Point"}
}