{
  "type": "Feature",
  "properties": {
    "iso:country":"US",
    "sg:address":"920 State Rd 5",
    "sg:city":"Shipshewana",
    "sg:classifiers":[
        {
            "category":"Retail",
            "subcategory":"Auto Repair",
            "type":"Services"
        }
    ],
    "sg:phone":"+1 260 768 7119",
    "sg:postcode":"46565",
    "sg:province":"IN",
    "sg:tags":[
        "repairing",
        "automobile"
    ],
    "wof:name":"Shipshe Service Station",
    "wof:placetype":"venue"
},
  "geometry": {"coordinates":[-85.580571,41.669389],"type":"Point"}
}