{
  "type": "Feature",
  "properties": {
    "iso:country":"US",
    "sg:address":"2149 Sheldon St",
    "sg:city":"Indianapolis",
    "sg:classifiers":[
        {
            "category":"Organizations",
            "subcategory":"Religious Organization",
            "type":"Services"
        }
    ],
    "sg:phone":"+1 317 923 5064",
    "sg:postcode":"46218",
    "sg:province":"IN",
    "sg:tags":[
        "churches-baptist"
    ],
    "wof:name":"The Greater Canaan Baptist Church",
    "wof:placetype":"venue"
},
  "geometry": {"coordinates":[-86.13315,39.796569],"type":"Point"}
}