{
  "type": "Feature",
  "properties": {
    "addr:full":"9640 W 900 S Fairmount IN 46928",
    "addr:housenumber":"9640",
    "addr:postcode":"46928",
    "addr:street":"W 900 S Fairmount",
    "iso:country":"US",
    "sg:address":"9640 W 900 S",
    "sg:city":"Fairmount",
    "sg:phone":"+1 765 922 7613",
    "sg:postcode":"46928",
    "sg:province":"IN",
    "sg:tags":[
        "farm",
        "corn",
        "soybean"
    ],
    "wof:name":"Charles Wingardner",
    "wof:placetype":"venue"
},
  "geometry": {"coordinates":[-85.85529099999999,40.421514],"type":"Point"}
}