{
  "type": "Feature",
  "properties": {
    "addr:full":"4000 E 96th St Indianapolis IN 46240",
    "addr:housenumber":"4000",
    "addr:postcode":"46240",
    "addr:street":"E 96Th St",
    "iso:country":"US",
    "sg:address":"4000 E 96th St",
    "sg:city":"Indianapolis",
    "sg:classifiers":[
        {
            "category":"Wholesale",
            "subcategory":"Hardware",
            "type":"Manufacturing & Wholesale Goods"
        }
    ],
    "sg:phone":"+1 317 844 9362",
    "sg:postcode":"46240",
    "sg:province":"IN",
    "sg:tags":[
        "plumbing",
        "fixture",
        "supply"
    ],
    "sg:website":"www.llirep.com",
    "wof:name":"Lugar-Lutron Inc",
    "wof:placetype":"venue"
},
  "geometry": {"coordinates":[-86.100506,39.926884],"type":"Point"}
}