{
  "type": "Feature",
  "properties": {
    "iso:country":"US",
    "sg:address":"929 S Main St",
    "sg:city":"Elkhart",
    "sg:classifiers":[
        {
            "category":"Retail",
            "subcategory":"Auto Repair",
            "type":"Services"
        }
    ],
    "sg:phone":"+1 574 293 2196",
    "sg:postcode":"46516",
    "sg:province":"IN",
    "sg:tags":[
        "alternator",
        "generator"
    ],
    "wof:name":"Elkhart Starter & Alternator",
    "wof:placetype":"venue"
},
  "geometry": {"coordinates":[-85.967462,41.679223],"type":"Point"}
}