{
  "type": "Feature",
  "properties": {
    "addr:full":"6317 University Cmns South Bend IN 46635",
    "addr:housenumber":"6317",
    "addr:postcode":"46635",
    "addr:street":"University Cmns",
    "iso:country":"US",
    "sg:address":"6317 University Cmns",
    "sg:city":"South Bend",
    "sg:classifiers":[
        {
            "category":"Banks & Credit Unions",
            "subcategory":"Bank",
            "type":"Services"
        }
    ],
    "sg:phone":"+1 574 277 9971",
    "sg:postcode":"46635",
    "sg:province":"IN",
    "sg:tags":[
        "personal",
        "consulting",
        "management",
        "institution"
    ],
    "wof:name":"Associates Financial",
    "wof:placetype":"venue"
},
  "geometry": {"coordinates":[-86.19625600000001,41.717139],"type":"Point"}
}