{
  "type": "Feature",
  "properties": {
    "iso:country":"US",
    "sg:address":"2333 Washington Ave",
    "sg:city":"Evansville",
    "sg:classifiers":[
        {
            "category":"Health Services",
            "subcategory":"Chiropractor",
            "type":"Services"
        }
    ],
    "sg:phone":"+1 812 477 5201",
    "sg:postcode":"47714",
    "sg:province":"IN",
    "wof:name":"Evansville Family Chiropractic",
    "wof:placetype":"venue"
},
  "geometry": {"coordinates":[-87.520392,37.9626],"type":"Point"}
}