{
  "type": "Feature",
  "properties": {
    "iso:country":"US",
    "sg:address":"1406 N Park Ave",
    "sg:city":"Indianapolis",
    "sg:classifiers":[
        {
            "category":"Building & Trades",
            "subcategory":"Construction",
            "type":"Services"
        }
    ],
    "sg:phone":"+1 317 637 2555",
    "sg:postcode":"46202",
    "sg:province":"IN",
    "sg:tags":[
        "house"
    ],
    "wof:name":"Anthony Constr Co",
    "wof:placetype":"venue"
},
  "geometry": {"coordinates":[-86.14776000000001,39.786522],"type":"Point"}
}