{
  "type": "Feature",
  "properties": {
    "iso:country":"US",
    "sg:address":"597 W Jefferson St",
    "sg:city":"Franklin",
    "sg:classifiers":[
        {
            "category":"Insurance",
            "subcategory":"Insurance Agent",
            "type":"Services"
        }
    ],
    "sg:phone":"+1 317 738 5998",
    "sg:postcode":"46131",
    "sg:province":"IN",
    "wof:name":"Farmers Insurance Group",
    "wof:placetype":"venue"
},
  "geometry": {"coordinates":[-86.062932,39.480097],"type":"Point"}
}