{
  "type": "Feature",
  "properties": {
    "iso:country":"US",
    "sg:address":"790 Irving Dr",
    "sg:city":"Clarksville",
    "sg:classifiers":[
        {
            "category":"Real Estate",
            "subcategory":"Real Estate Operator",
            "type":"Services"
        }
    ],
    "sg:phone":"+1 812 282 7911",
    "sg:postcode":"47129",
    "sg:province":"IN",
    "sg:tags":[
        "apartment"
    ],
    "wof:name":"Olde Towne Village Apartments",
    "wof:placetype":"venue"
},
  "geometry": {"coordinates":[-85.755416,38.3054],"type":"Point"}
}