{
  "type": "Feature",
  "properties": {
    "iso:country":"US",
    "sg:address":"330 N Columbia St",
    "sg:city":"Union City",
    "sg:classifiers":[
        {
            "category":"Personal",
            "subcategory":"Beauty Salon",
            "type":"Services"
        }
    ],
    "sg:phone":"+1 765 964 3921",
    "sg:postcode":"47390",
    "sg:province":"IN",
    "sg:tags":[
        "shop"
    ],
    "wof:name":"Dave's Styling Salon",
    "wof:placetype":"venue"
},
  "geometry": {"coordinates":[-84.80842199999999,40.200086],"type":"Point"}
}