{
  "type": "Feature",
  "properties": {
    "iso:country":"US",
    "sg:address":"807 Elizabeth St",
    "sg:city":"Goshen",
    "sg:classifiers":[
        {
            "category":"Manufacturing",
            "subcategory":"Wood Products",
            "type":"Manufacturing & Wholesale Goods"
        }
    ],
    "sg:phone":"+1 574 533 8890",
    "sg:postcode":"46526",
    "sg:province":"IN",
    "sg:tags":[
        "mfg"
    ],
    "wof:name":"Dutch Country Kitchens",
    "wof:placetype":"venue"
},
  "geometry": {"coordinates":[-85.86158,41.595907],"type":"Point"}
}