{
  "type": "Feature",
  "properties": {
    "iso:country":"US",
    "sg:address":"606 Riley Ln",
    "sg:city":"West Lafayette",
    "sg:classifiers":[
        {
            "category":"Professional",
            "subcategory":"Research",
            "type":"Services"
        }
    ],
    "sg:phone":"+1 765 463 3077",
    "sg:postcode":"47906",
    "sg:province":"IN",
    "sg:tags":[
        "not",
        "profit",
        "genetic",
        "for"
    ],
    "wof:name":"Genetics Inst For Fuse & Chem",
    "wof:placetype":"venue"
},
  "geometry": {"coordinates":[-86.91474100000001,40.442529],"type":"Point"}
}