{
  "type": "Feature",
  "properties": {
    "iso:country":"US",
    "sg:address":"7115 Bethlehem New Washington Rd",
    "sg:city":"New Washington",
    "sg:classifiers":[
        {
            "category":"Sports & Exercise",
            "subcategory":"Gym",
            "type":"Entertainment"
        }
    ],
    "sg:phone":"+1 812 293 3335",
    "sg:postcode":"47162",
    "sg:province":"IN",
    "sg:tags":[
        "fitness",
        "physical",
        "facility"
    ],
    "wof:name":"Vaughn Aerobics Inc",
    "wof:placetype":"venue"
},
  "geometry": {"coordinates":[-85.523827,38.563128],"type":"Point"}
}