{
  "type": "Feature",
  "properties": {
    "iso:country":"US",
    "sg:address":"11809 Allisonville Rd",
    "sg:city":"Fishers",
    "sg:classifiers":[
        {
            "category":"Personal",
            "subcategory":"Beauty Salon",
            "type":"Services"
        }
    ],
    "sg:phone":"+1 317 842 6025",
    "sg:postcode":"46038",
    "sg:province":"IN",
    "wof:name":"Fantastic Sam's",
    "wof:placetype":"venue"
},
  "geometry": {"coordinates":[-86.039034,39.959705],"type":"Point"}
}