{
  "type": "Feature",
  "properties": {
    "iso:country":"US",
    "sg:address":"4349 National Rd W",
    "sg:city":"Richmond",
    "sg:classifiers":[
        {
            "category":"Banks & Credit Unions",
            "subcategory":"Bank",
            "type":"Services"
        }
    ],
    "sg:phone":"+1 765 965 3699",
    "sg:postcode":"47374",
    "sg:province":"IN",
    "sg:tags":[
        "loan",
        "real estate"
    ],
    "sg:website":"www.thehonorstatebankwholesale.com",
    "wof:name":"Honor State Bank",
    "wof:placetype":"venue"
},
  "geometry": {"coordinates":[-84.958969,39.820801],"type":"Point"}
}