{
  "type": "Feature",
  "properties": {
    "iso:country":"US",
    "sg:address":"926 Neubling Ave",
    "sg:city":"Evansville",
    "sg:classifiers":[
        {
            "category":"Retail",
            "subcategory":"Auto Repair",
            "type":"Services"
        }
    ],
    "sg:phone":"+1 812 422 3833",
    "sg:postcode":"47713",
    "sg:province":"IN",
    "sg:tags":[
        "body",
        "automobile",
        "painting"
    ],
    "wof:name":"Dave's Body Shop",
    "wof:placetype":"venue"
},
  "geometry": {"coordinates":[-87.549058,37.947189],"type":"Point"}
}