{
  "type": "Feature",
  "properties": {
    "iso:country":"US",
    "sg:address":"2919 George St",
    "sg:city":"Anderson",
    "sg:classifiers":[
        {
            "category":"Professional",
            "type":"Services"
        }
    ],
    "sg:phone":"+1 765 683 0089",
    "sg:postcode":"46016",
    "sg:province":"IN",
    "sg:tags":[
        "establishment"
    ],
    "wof:name":"Preventative Aftercare Inc",
    "wof:placetype":"venue"
},
  "geometry": {"coordinates":[-85.669328,40.08542],"type":"Point"}
}