{
  "type": "Feature",
  "properties": {
    "iso:country":"US",
    "sg:address":"801 E North St",
    "sg:city":"Kendallville",
    "sg:classifiers":[
        {
            "category":"Autos & Motor Vehicles",
            "subcategory":"Auto Supplies",
            "type":"Retail Goods"
        }
    ],
    "sg:phone":"+1 260 347 3210",
    "sg:postcode":"46755",
    "sg:province":"IN",
    "sg:tags":[
        "automobile",
        "parts"
    ],
    "sg:website":"www.advanceautoparts.com",
    "wof:name":"Advance Auto Parts Inc",
    "wof:placetype":"venue"
},
  "geometry": {"coordinates":[-85.252387,41.452247],"type":"Point"}
}