{
  "type": "Feature",
  "properties": {
    "iso:country":"US",
    "sg:address":"4624 N 100 E",
    "sg:city":"Howe",
    "sg:classifiers":[
        {
            "category":"Organizations",
            "subcategory":"Professional Association",
            "type":"Services"
        }
    ],
    "sg:phone":"+1 260 562 9302",
    "sg:postcode":"46746",
    "sg:province":"IN",
    "wof:name":"Grandview Bend Community Assn",
    "wof:placetype":"venue"
},
  "geometry": {"coordinates":[-85.408134,41.709126],"type":"Point"}
}