{
  "type": "Feature",
  "properties": {
    "iso:country":"US",
    "sg:address":"112 Brown St",
    "sg:city":"Valparaiso",
    "sg:classifiers":[
        {
            "category":"Professional",
            "subcategory":"Research",
            "type":"Services"
        }
    ],
    "sg:phone":"+1 219 464 7612",
    "sg:postcode":"46383",
    "sg:province":"IN",
    "sg:tags":[
        "organization",
        "noncommercial"
    ],
    "wof:name":"Public Research Inst",
    "wof:placetype":"venue"
},
  "geometry": {"coordinates":[-87.058755,41.46481],"type":"Point"}
}