{
  "type": "Feature",
  "properties": {
    "iso:country":"US",
    "sg:address":"23672 Old US Hwy 20 W",
    "sg:city":"Elkhart",
    "sg:classifiers":[
        {
            "category":"Education",
            "subcategory":"Special Training",
            "type":"Public Place"
        }
    ],
    "sg:phone":"+1 574 389 7648",
    "sg:postcode":"46516",
    "sg:province":"IN",
    "sg:tags":[
        "instruction",
        "driving"
    ],
    "sg:website":"www.premierdrivinginstitute.com",
    "wof:name":"Premier Driving Institute Inc",
    "wof:placetype":"venue"
},
  "geometry": {"coordinates":[-85.922285,41.676135],"type":"Point"}
}