{
  "type": "Feature",
  "properties": {
    "iso:country":"US",
    "sg:address":"6677 E 82nd St",
    "sg:city":"Indianapolis",
    "sg:classifiers":[
        {
            "category":"Insurance",
            "subcategory":"Insurance Agent",
            "type":"Services"
        }
    ],
    "sg:phone":"+1 317 595 8925",
    "sg:postcode":"46250",
    "sg:province":"IN",
    "wof:name":"Liberty Mutual Insurance",
    "wof:placetype":"venue"
},
  "geometry": {"coordinates":[-86.052899,39.905175],"type":"Point"}
}