{
  "type": "Feature",
  "properties": {
    "iso:country":"US",
    "sg:address":"5470 W 760 N",
    "sg:city":"Orland",
    "sg:classifiers":[
        {
            "category":"Retail",
            "subcategory":"Car Wash",
            "type":"Services"
        }
    ],
    "sg:phone":"+1 260 833 8805",
    "sg:postcode":"46776",
    "sg:province":"IN",
    "sg:tags":[
        "carwash"
    ],
    "wof:name":"David A Roth",
    "wof:placetype":"venue"
},
  "geometry": {"coordinates":[-85.09776599999999,41.754045],"type":"Point"}
}