{
  "type": "Feature",
  "properties": {
    "iso:country":"US",
    "sg:address":"17735 Sun Park Dr",
    "sg:city":"Westfield",
    "sg:classifiers":[
        {
            "category":"Retail",
            "subcategory":"Veterinary Services",
            "type":"Services"
        }
    ],
    "sg:phone":"+1 317 896 2539",
    "sg:postcode":"46074",
    "sg:province":"IN",
    "sg:tags":[
        "veterinarian"
    ],
    "wof:name":"Westfield Veterinary Care",
    "wof:placetype":"venue"
},
  "geometry": {"coordinates":[-86.1399,40.043499],"type":"Point"}
}