{
  "type": "Feature",
  "properties": {
    "iso:country":"US",
    "sg:address":"128 S Glick St",
    "sg:city":"Mulberry",
    "sg:classifiers":[
        {
            "category":"Government",
            "subcategory":"Office",
            "type":"Public Place"
        }
    ],
    "sg:phone":"+1 765 296 2455",
    "sg:postcode":"46058",
    "sg:province":"IN",
    "sg:tags":[
        "village"
    ],
    "wof:name":"Mulberry Sewage Dept",
    "wof:placetype":"venue"
},
  "geometry": {"coordinates":[-86.666399,40.344355],"type":"Point"}
}