{
  "type": "Feature",
  "properties": {
    "addr:full":"224 N College Ave Bloomington IN 47404",
    "addr:housenumber":"224",
    "addr:postcode":"47404",
    "addr:street":"N College Ave",
    "iso:country":"US",
    "sg:address":"224 N College Ave",
    "sg:city":"Bloomington",
    "sg:classifiers":[
        {
            "category":"Shopping",
            "type":"Retail Goods"
        }
    ],
    "sg:phone":"+1 812 330 1990",
    "sg:postcode":"47404",
    "sg:province":"IN",
    "sg:tags":[
        "art",
        "gallery",
        "dealer"
    ],
    "wof:name":"Wandering Turtle Art Gallery",
    "wof:placetype":"venue"
},
  "geometry": {"coordinates":[-86.53478200000001,39.168313],"type":"Point"}
}