{
  "type": "Feature",
  "properties": {
    "iso:country":"US",
    "sg:address":"235 S 5th St",
    "sg:city":"Richmond",
    "sg:classifiers":[
        {
            "category":"Organizations",
            "subcategory":"Religious Organization",
            "type":"Services"
        }
    ],
    "sg:phone":"+1 765 962 3902",
    "sg:postcode":"47374",
    "sg:province":"IN",
    "sg:tags":[
        "church"
    ],
    "sg:website":"www.richmondcatholiccommunity.com",
    "wof:name":"St Andrew Catholic Church",
    "wof:placetype":"venue"
},
  "geometry": {"coordinates":[-84.89558,39.825533],"type":"Point"}
}