{
  "type": "Feature",
  "properties": {
    "addr:full":"8281 S Co Rd 188 E Muncie IN 47302",
    "addr:housenumber":"8281;188 e",
    "addr:postcode":"47302",
    "addr:street":"S Co Rd",
    "iso:country":"US",
    "sg:address":"8281 S Co Rd 188 E",
    "sg:city":"Muncie",
    "sg:classifiers":[
        {
            "category":"Retail",
            "subcategory":"Animal Services",
            "type":"Services"
        }
    ],
    "sg:phone":"+1 765 282 3403",
    "sg:postcode":"47302",
    "sg:province":"IN",
    "wof:name":"Wagoners Southern Creek Farm",
    "wof:placetype":"venue"
},
  "geometry": {"coordinates":[-85.350236,40.12658],"type":"Point"}
}