{
  "type": "Feature",
  "properties": {
    "iso:country":"US",
    "sg:address":"17004 Mill Pond Trl",
    "sg:city":"Plymouth",
    "sg:classifiers":[
        {
            "category":"Building & Trades",
            "subcategory":"Landscaping Services",
            "type":"Services"
        }
    ],
    "sg:phone":"+1 574 936 5818",
    "sg:postcode":"46563",
    "sg:province":"IN",
    "sg:tags":[
        "tree"
    ],
    "wof:name":"Hooters Tree Svc",
    "wof:placetype":"venue"
},
  "geometry": {"coordinates":[-86.379581,41.295296],"type":"Point"}
}