{
  "type": "Feature",
  "properties": {
    "addr:full":"367 Woodland Trail Dr Indianapolis IN 46239",
    "addr:housenumber":"367",
    "addr:postcode":"46239",
    "addr:street":"Woodland Trail Dr",
    "iso:country":"US",
    "sg:address":"367 Woodland Trail Dr",
    "sg:city":"Indianapolis",
    "sg:classifiers":[
        {
            "category":"Professional",
            "subcategory":"Art Services",
            "type":"Services"
        }
    ],
    "sg:phone":"+1 317 251 3435",
    "sg:postcode":"46239",
    "sg:province":"IN",
    "sg:tags":[
        "graphic",
        "designer"
    ],
    "wof:name":"Muddyline Studio",
    "wof:placetype":"venue"
},
  "geometry": {"coordinates":[-85.965874,39.764089],"type":"Point"}
}