{
  "type": "Feature",
  "properties": {
    "iso:country":"US",
    "sg:address":"3624 S 200 W",
    "sg:city":"Hartford City",
    "sg:classifiers":[
        {
            "category":"Building & Trades",
            "subcategory":"Construction",
            "type":"Services"
        }
    ],
    "sg:phone":"+1 765 348 4159",
    "sg:postcode":"47348",
    "sg:province":"IN",
    "sg:tags":[
        "roofing",
        "contractor"
    ],
    "wof:name":"Hochadel Roofing Co",
    "wof:placetype":"venue"
},
  "geometry": {"coordinates":[-85.408006,40.395942],"type":"Point"}
}