{
  "type": "Feature",
  "properties": {
    "iso:country":"US",
    "sg:address":"19828 Co Rd 8",
    "sg:city":"Bristol",
    "sg:classifiers":[
        {
            "category":"Autos & Motor Vehicles",
            "subcategory":"Recreational Vehicle Sales",
            "type":"Retail Goods"
        }
    ],
    "sg:phone":"+1 574 848 0585",
    "sg:postcode":"46507",
    "sg:province":"IN",
    "sg:website":"www.openroadrvs.com",
    "wof:name":"Pilgrim International",
    "wof:placetype":"venue"
},
  "geometry": {"coordinates":[-85.847268,41.718181],"type":"Point"}
}