{
  "type": "Feature",
  "properties": {
    "iso:country":"US",
    "sg:address":"12400 N Meridian St",
    "sg:city":"Carmel",
    "sg:classifiers":[
        {
            "category":"Shopping",
            "type":"Retail Goods"
        }
    ],
    "sg:phone":"+1 317 566 3360",
    "sg:postcode":"46032",
    "sg:province":"IN",
    "sg:tags":[
        "equipment",
        "telephone",
        "supply"
    ],
    "sg:website":"www.cti-indy.com",
    "wof:name":"CTI Solutions",
    "wof:placetype":"venue"
},
  "geometry": {"coordinates":[-86.15794699999999,39.969631],"type":"Point"}
}