{
  "type": "Feature",
  "properties": {
    "iso:country":"US",
    "sg:address":"45 W Washington St",
    "sg:city":"Shelbyville",
    "sg:classifiers":[
        {
            "category":"Professional",
            "subcategory":"Lawyer & Legal Services",
            "type":"Services"
        }
    ],
    "sg:phone":"+1 317 398 0183",
    "sg:postcode":"46176",
    "sg:province":"IN",
    "sg:tags":[
        "attorney"
    ],
    "wof:name":"Yeager Good & Baldwin",
    "wof:placetype":"venue"
},
  "geometry": {"coordinates":[-85.779058,39.524367],"type":"Point"}
}