{
  "type": "Feature",
  "properties": {
    "iso:country":"US",
    "sg:address":"12114 Golden Bluff Ct",
    "sg:city":"Indianapolis",
    "sg:classifiers":[
        {
            "category":"Professional",
            "subcategory":"Engineering",
            "type":"Services"
        }
    ],
    "sg:phone":"+1 317 823 6709",
    "sg:postcode":"46236",
    "sg:province":"IN",
    "wof:name":"Balfour Systems Inc",
    "wof:placetype":"venue"
},
  "geometry": {"coordinates":[-85.949778,39.917806],"type":"Point"}
}