{
  "type": "Feature",
  "properties": {
    "addr:full":"10 Surrey Ln Grabill IN 46741",
    "addr:housenumber":"10",
    "addr:postcode":"46741",
    "addr:street":"Surrey Ln",
    "iso:country":"US",
    "sg:address":"10 Surrey Ln",
    "sg:city":"Grabill",
    "sg:classifiers":[
        {
            "category":"Real Estate",
            "subcategory":"Real Estate Operator",
            "type":"Services"
        }
    ],
    "sg:phone":"+1 260 627 2400",
    "sg:postcode":"46741",
    "sg:province":"IN",
    "sg:tags":[
        "apartment"
    ],
    "wof:name":"Woodland Glen Apts",
    "wof:placetype":"venue"
},
  "geometry": {"coordinates":[-84.97154999999999,41.205368],"type":"Point"}
}