{
  "type": "Feature",
  "properties": {
    "addr:full":"1024 State Rd 229 Batesville IN 47006",
    "addr:housenumber":"1024;229",
    "addr:postcode":"47006",
    "addr:street":"State Rd",
    "iso:country":"US",
    "sg:address":"1024 State Rd 229",
    "sg:city":"Batesville",
    "sg:classifiers":[
        {
            "category":"Wholesale",
            "subcategory":"Toys & Hobbies",
            "type":"Manufacturing & Wholesale Goods"
        }
    ],
    "sg:phone":"+1 812 933 9996",
    "sg:postcode":"47006",
    "sg:province":"IN",
    "sg:tags":[
        "firework"
    ],
    "wof:name":"Tnt Fireworks",
    "wof:placetype":"venue"
},
  "geometry": {"coordinates":[-85.20835599999999,39.320293],"type":"Point"}
}