{
  "type": "Feature",
  "properties": {
    "iso:country":"US",
    "sg:address":"3380 Willowcreek Rd",
    "sg:city":"Portage",
    "sg:classifiers":[
        {
            "category":"Restaurant",
            "type":"Food & Drink"
        }
    ],
    "sg:phone":"+1 219 763 3833",
    "sg:postcode":"46368",
    "sg:province":"IN",
    "wof:name":"El Amigo",
    "wof:placetype":"venue"
},
  "geometry": {"coordinates":[-87.18268500000001,41.552904],"type":"Point"}
}