{
  "type": "Feature",
  "properties": {
    "addr:full":"6470 Michigan Rd Indianapolis IN 46268",
    "addr:housenumber":"6470",
    "addr:postcode":"46268",
    "addr:street":"Michigan Rd",
    "iso:country":"US",
    "sg:address":"6470 Michigan Rd",
    "sg:city":"Indianapolis",
    "sg:phone":"+1 317 257 4516",
    "sg:postcode":"46268",
    "sg:province":"IN",
    "sg:website":"http://allpointstreeservice.com",
    "wof:name":"All Points Tree Service",
    "wof:placetype":"venue"
},
  "geometry": {"coordinates":[-86.204806,39.874462],"type":"Point"}
}