{
  "type": "Feature",
  "properties": {
    "iso:country":"US",
    "sg:address":"125 N 10th St",
    "sg:city":"Middletown",
    "sg:classifiers":[
        {
            "category":"Sports & Exercise",
            "subcategory":"Gym",
            "type":"Entertainment"
        }
    ],
    "sg:phone":"+1 765 354 9205",
    "sg:postcode":"47356",
    "sg:province":"IN",
    "sg:tags":[
        "club",
        "health",
        "studio",
        "gymnasium"
    ],
    "wof:name":"Everett's Gym & Tanning",
    "wof:placetype":"venue"
},
  "geometry": {"coordinates":[-85.542153,40.05429],"type":"Point"}
}