{
  "type": "Feature",
  "properties": {
    "iso:country":"US",
    "sg:address":"36 E US Hwy 30",
    "sg:city":"Schererville",
    "sg:classifiers":[
        {
            "category":"Shopping",
            "subcategory":"Florist",
            "type":"Retail Goods"
        }
    ],
    "sg:phone":"+1 219 322 6540",
    "sg:postcode":"46375",
    "sg:province":"IN",
    "wof:name":"Wicker Gardens",
    "wof:placetype":"venue"
},
  "geometry": {"coordinates":[-87.448992,41.485493],"type":"Point"}
}