{
  "type": "Feature",
  "properties": {
    "iso:country":"US",
    "sg:address":"655 Saint Peters Church Rd SE",
    "sg:city":"Corydon",
    "sg:classifiers":[
        {
            "category":"Organizations",
            "subcategory":"Religious Organization",
            "type":"Services"
        }
    ],
    "sg:phone":"+1 812 952 2151",
    "sg:postcode":"47112",
    "sg:province":"IN",
    "sg:tags":[
        "church"
    ],
    "wof:name":"St Peter's Lutheran Church",
    "wof:placetype":"venue"
},
  "geometry": {"coordinates":[-86.01805299999999,38.189977],"type":"Point"}
}