{
  "type": "Feature",
  "properties": {
    "iso:country":"US",
    "sg:address":"2461 Directors Row",
    "sg:city":"Indianapolis",
    "sg:classifiers":[
        {
            "category":"Wholesale",
            "subcategory":"Chemicals & Plastics",
            "type":"Manufacturing & Wholesale Goods"
        }
    ],
    "sg:phone":"+1 317 227 8055",
    "sg:postcode":"46241",
    "sg:province":"IN",
    "sg:tags":[
        "oxygen"
    ],
    "wof:name":"Respiratory Partners",
    "wof:placetype":"venue"
},
  "geometry": {"coordinates":[-86.261571,39.730527],"type":"Point"}
}