{
  "type": "Feature",
  "properties": {
    "iso:country":"US",
    "sg:address":"1641 W Co Rd 1300 N",
    "sg:city":"Batesville",
    "sg:phone":"+1 812 852 4247",
    "sg:postcode":"47006",
    "sg:province":"IN",
    "sg:tags":[
        "farm",
        "corn",
        "soybean"
    ],
    "wof:name":"Alvin Siebert",
    "wof:placetype":"venue"
},
  "geometry": {"coordinates":[-85.29654600000001,39.264802],"type":"Point"}
}