{
  "type": "Feature",
  "properties": {
    "iso:country":"US",
    "sg:address":"1102 W Mishawaka Rd",
    "sg:city":"Elkhart",
    "sg:classifiers":[
        {
            "category":"Personal",
            "subcategory":"Tanning Parlor",
            "type":"Services"
        },
        {
            "category":"Personal",
            "type":"Services"
        }
    ],
    "sg:phone":"+1 574 293 0350",
    "sg:postcode":"46517",
    "sg:province":"IN",
    "sg:tags":[
        "salon"
    ],
    "wof:name":"Southern Tan",
    "wof:placetype":"venue"
},
  "geometry": {"coordinates":[-85.983217,41.654029],"type":"Point"}
}