{
  "type": "Feature",
  "properties": {
    "iso:country":"US",
    "sg:address":"2120 Broadway",
    "sg:city":"Gary",
    "sg:classifiers":[
        {
            "category":"Social Services",
            "type":"Services"
        }
    ],
    "sg:phone":"+1 219 882 4459",
    "sg:postcode":"46407",
    "sg:province":"IN",
    "sg:tags":[
        "organization",
        "welfare"
    ],
    "wof:name":"Brother's Keeper",
    "wof:placetype":"venue"
},
  "geometry": {"coordinates":[-87.336982,41.578924],"type":"Point"}
}