{
  "type": "Feature",
  "properties": {
    "iso:country":"US",
    "sg:address":"1474 W 86th St",
    "sg:city":"Indianapolis",
    "sg:classifiers":[
        {
            "category":"Shopping",
            "subcategory":"Clothing, Apparel, & Fashions",
            "type":"Retail Goods"
        }
    ],
    "sg:phone":"+1 317 872 0671",
    "sg:postcode":"46260",
    "sg:province":"IN",
    "sg:tags":[
        "furnishing"
    ],
    "wof:name":"Peruviani",
    "wof:placetype":"venue"
},
  "geometry": {"coordinates":[-86.18758,39.912243],"type":"Point"}
}