{
  "type": "Feature",
  "properties": {
    "iso:country":"US",
    "sg:address":"55 S Jackson St",
    "sg:city":"Frankfort",
    "sg:classifiers":[
        {
            "category":"Insurance",
            "subcategory":"Insurance Agent",
            "type":"Services"
        }
    ],
    "sg:phone":"+1 765 654 5236",
    "sg:postcode":"46041",
    "sg:province":"IN",
    "wof:name":"Insurance Recovery Inc",
    "wof:placetype":"venue"
},
  "geometry": {"coordinates":[-86.510589,40.280122],"type":"Point"}
}