{
  "type": "Feature",
  "properties": {
    "iso:country":"US",
    "sg:address":"650 Smokey Ln",
    "sg:city":"Carmel",
    "sg:classifiers":[
        {
            "category":"Shopping",
            "subcategory":"Gifts & Souvenirs",
            "type":"Retail Goods"
        }
    ],
    "sg:phone":"+1 317 816 0724",
    "sg:postcode":"46033",
    "sg:province":"IN",
    "wof:name":"Dianas Gift Shop",
    "wof:placetype":"venue"
},
  "geometry": {"coordinates":[-86.092341,39.986566],"type":"Point"}
}