{
  "type": "Feature",
  "properties": {
    "iso:country":"US",
    "sg:address":"1231 E Jackson St",
    "sg:city":"Muncie",
    "sg:classifiers":[
        {
            "category":"Retail",
            "subcategory":"Auto Repair",
            "type":"Services"
        }
    ],
    "sg:phone":"+1 765 289 7811",
    "sg:postcode":"47305",
    "sg:province":"IN",
    "sg:tags":[
        "repairing",
        "automobile"
    ],
    "wof:name":"Johnny's Automotive Svc",
    "wof:placetype":"venue"
},
  "geometry": {"coordinates":[-85.372763,40.19251],"type":"Point"}
}