{
  "type": "Feature",
  "properties": {
    "iso:country":"US",
    "sg:address":"1919 Steven Ave",
    "sg:city":"Bedford",
    "sg:classifiers":[
        {
            "category":"Government",
            "subcategory":"Office",
            "type":"Public Place"
        }
    ],
    "sg:phone":"+1 812 279 3391",
    "sg:postcode":"47421",
    "sg:province":"IN",
    "sg:tags":[
        "state"
    ],
    "wof:name":"Natural Resources Dept",
    "wof:placetype":"venue"
},
  "geometry": {"coordinates":[-86.51981000000001,38.858538],"type":"Point"}
}