{
  "type": "Feature",
  "properties": {
    "iso:country":"US",
    "sg:address":"1477 S Stevenson Station Rd",
    "sg:city":"Chandler",
    "sg:classifiers":[
        {
            "category":"Autos & Motor Vehicles",
            "subcategory":"Boat Sales",
            "type":"Retail Goods"
        },
        {
            "category":"Recreation",
            "subcategory":"Marina",
            "type":"Entertainment"
        }
    ],
    "sg:phone":"+1 812 925 6472",
    "sg:postcode":"47610",
    "sg:province":"IN",
    "sg:tags":[
        "repairing"
    ],
    "wof:name":"Mac's Marine",
    "wof:placetype":"venue"
},
  "geometry": {"coordinates":[-87.43662,38.014464],"type":"Point"}
}