{
  "type": "Feature",
  "properties": {
    "iso:country":"US",
    "sg:address":"1206 James Ave",
    "sg:city":"Bedford",
    "sg:classifiers":[
        {
            "category":"Wholesale",
            "subcategory":"Machinery & Supplies",
            "type":"Manufacturing & Wholesale Goods"
        }
    ],
    "sg:phone":"+1 812 275 8705",
    "sg:postcode":"47421",
    "sg:province":"IN",
    "sg:tags":[
        "salon",
        "beauty"
    ],
    "wof:name":"Sally Beauty Supply",
    "wof:placetype":"venue"
},
  "geometry": {"coordinates":[-86.518901,38.865431],"type":"Point"}
}