{
  "type": "Feature",
  "properties": {
    "iso:country":"US",
    "sg:address":"4007 N Keystone Ave",
    "sg:city":"Indianapolis",
    "sg:classifiers":[
        {
            "category":"Retail",
            "subcategory":"Portrait Studio",
            "type":"Services"
        }
    ],
    "sg:phone":"+1 317 562 1057",
    "sg:postcode":"46205",
    "sg:province":"IN",
    "sg:tags":[
        "photo"
    ],
    "sg:website":"www.pridephotography.com",
    "wof:name":"Pride Photography",
    "wof:placetype":"venue"
},
  "geometry": {"coordinates":[-86.121716,39.829738],"type":"Point"}
}