{
  "type": "Feature",
  "properties": {
    "addr:full":"632 S 13th St Decatur IN 46733",
    "addr:housenumber":"632",
    "addr:postcode":"46733",
    "addr:street":"S 13Th St",
    "iso:country":"US",
    "sg:address":"632 S 13th St",
    "sg:city":"Decatur",
    "sg:classifiers":[
        {
            "category":"Banks & Credit Unions",
            "subcategory":"Bank",
            "type":"Services"
        }
    ],
    "sg:phone":"+1 260 724 9929",
    "sg:postcode":"46733",
    "sg:province":"IN",
    "wof:name":"Professional Federal CU",
    "wof:placetype":"venue"
},
  "geometry": {"coordinates":[-84.93755899999999,40.822623],"type":"Point"}
}