{
  "type": "Feature",
  "properties": {
    "iso:country":"US",
    "sg:address":"216 W Walnut St",
    "sg:city":"Sharpsville",
    "sg:classifiers":[
        {
            "category":"Professional",
            "type":"Services"
        }
    ],
    "sg:phone":"+1 765 963 6899",
    "sg:postcode":"46068",
    "sg:province":"IN",
    "sg:tags":[
        "establishment"
    ],
    "wof:name":"P C",
    "wof:placetype":"venue"
},
  "geometry": {"coordinates":[-86.08725,40.377748],"type":"Point"}
}