{
  "type": "Feature",
  "properties": {
    "iso:country":"US",
    "sg:address":"1925 Westview Dr",
    "sg:city":"Indianapolis",
    "sg:classifiers":[
        {
            "category":"Real Estate",
            "subcategory":"Real Estate Operator",
            "type":"Services"
        }
    ],
    "sg:phone":"+1 317 951 8388",
    "sg:postcode":"46221",
    "sg:province":"IN",
    "sg:tags":[
        "apartment"
    ],
    "wof:name":"South Side Partners Inc",
    "wof:placetype":"venue"
},
  "geometry": {"coordinates":[-86.196521,39.751854],"type":"Point"}
}