{
  "type": "Feature",
  "properties": {
    "addr:full":"11900 Highway 62 Charlestown IN 47111",
    "addr:housenumber":"11900",
    "addr:postcode":"47111",
    "addr:street":"Highway 62",
    "iso:country":"US",
    "sg:address":"11900 Highway 62",
    "sg:city":"Charlestown",
    "sg:classifiers":[
        {
            "category":"Retail",
            "subcategory":"Car Wash",
            "type":"Services"
        }
    ],
    "sg:phone":"+1 812 256 6546",
    "sg:postcode":"47111",
    "sg:province":"IN",
    "wof:name":"Crystal Clean Car Care",
    "wof:placetype":"venue"
},
  "geometry": {"coordinates":[-85.61923299999999,38.464807],"type":"Point"}
}