{
  "type": "Feature",
  "properties": {
    "iso:country":"US",
    "sg:address":"5950 E 38th St",
    "sg:city":"Indianapolis",
    "sg:classifiers":[
        {
            "category":"Food & Beverages",
            "subcategory":"Liquor & Beverages",
            "type":"Retail Goods"
        }
    ],
    "sg:phone":"+1 317 547 6085",
    "sg:postcode":"46218",
    "sg:province":"IN",
    "wof:name":"Community Spirits",
    "wof:placetype":"venue"
},
  "geometry": {"coordinates":[-86.067197,39.82554],"type":"Point"}
}