{
  "type": "Feature",
  "properties": {
    "iso:country":"US",
    "sg:address":"8691 Connecticut St",
    "sg:city":"Merrillville",
    "sg:classifiers":[
        {
            "category":"Health Services",
            "subcategory":"Doctor",
            "type":"Services"
        }
    ],
    "sg:phone":"+1 219 757 5700",
    "sg:postcode":"46410",
    "sg:province":"IN",
    "sg:tags":[
        "dentist"
    ],
    "wof:name":"Oral Surgery Group Inc",
    "wof:placetype":"venue"
},
  "geometry": {"coordinates":[-87.33259200000001,41.459594],"type":"Point"}
}