{
  "type": "Feature",
  "properties": {
    "iso:country":"US",
    "sg:address":"405 E Main St",
    "sg:city":"Flora",
    "sg:classifiers":[
        {
            "category":"Building & Trades",
            "subcategory":"Construction",
            "type":"Services"
        }
    ],
    "sg:phone":"+1 574 967 4722",
    "sg:postcode":"46929",
    "sg:province":"IN",
    "sg:tags":[
        "hanging",
        "contractor"
    ],
    "wof:name":"Hollis Painting",
    "wof:placetype":"venue"
},
  "geometry": {"coordinates":[-86.519836,40.547994],"type":"Point"}
}