{
  "type": "Feature",
  "properties": {
    "iso:country":"US",
    "sg:address":"1454 W Boys Club Rd",
    "sg:city":"Connersville",
    "sg:classifiers":[
        {
            "category":"Organizations",
            "subcategory":"Community Association",
            "type":"Services"
        }
    ],
    "sg:phone":"+1 765 825 7846",
    "sg:postcode":"47331",
    "sg:province":"IN",
    "sg:tags":[
        "club"
    ],
    "wof:name":"Boys Club",
    "wof:placetype":"venue"
},
  "geometry": {"coordinates":[-85.149076,39.55128],"type":"Point"}
}