{
  "type": "Feature",
  "properties": {
    "addr:full":"3006 W Co Rd 400 N Connersville IN 47331",
    "addr:housenumber":"3006",
    "addr:postcode":"47331",
    "addr:street":"W Co Rd 400 N",
    "iso:country":"US",
    "sg:address":"3006 W Co Rd 400 N",
    "sg:city":"Connersville",
    "sg:phone":"+1 765 825 2427",
    "sg:postcode":"47331",
    "sg:province":"IN",
    "sg:tags":[
        "farm",
        "corn"
    ],
    "wof:name":"David Caldwell",
    "wof:placetype":"venue"
},
  "geometry": {"coordinates":[-85.192108,39.701076],"type":"Point"}
}