{
  "type": "Feature",
  "properties": {
    "iso:country":"US",
    "sg:address":"2501 Co Rd 600 N",
    "sg:city":"Whiteland",
    "sg:classifiers":[
        {
            "category":"Freight",
            "type":"Transportation"
        }
    ],
    "sg:phone":"+1 317 535 4551",
    "sg:postcode":"46184",
    "sg:province":"IN",
    "sg:tags":[
        "operator",
        "local",
        "trucking"
    ],
    "wof:name":"Berry Incorporated",
    "wof:placetype":"venue"
},
  "geometry": {"coordinates":[-86.155029,39.563004],"type":"Point"}
}