{
  "type": "Feature",
  "properties": {
    "iso:country":"US",
    "sg:address":"601 State St",
    "sg:city":"Laporte",
    "sg:classifiers":[
        {
            "category":"Professional",
            "subcategory":"Lawyer & Legal Services",
            "type":"Services"
        }
    ],
    "sg:phone":"+1 219 324 9099",
    "sg:postcode":"46350",
    "sg:province":"IN",
    "sg:tags":[
        "attorney"
    ],
    "wof:name":"Mark J Moryl",
    "wof:placetype":"venue"
},
  "geometry": {"coordinates":[-86.720142,41.612918],"type":"Point"}
}