{
  "type": "Feature",
  "properties": {
    "iso:country":"US",
    "sg:address":"262 E McKeever St",
    "sg:city":"Andrews",
    "sg:classifiers":[
        {
            "category":"Organizations",
            "subcategory":"Religious Organization",
            "type":"Services"
        }
    ],
    "sg:phone":"+1 260 356 0252",
    "sg:postcode":"46702",
    "sg:province":"IN",
    "sg:tags":[
        "church"
    ],
    "wof:name":"Andrews Church Of The Brethren",
    "wof:placetype":"venue"
},
  "geometry": {"coordinates":[-85.598203,40.857098],"type":"Point"}
}