{
  "type": "Feature",
  "properties": {
    "iso:country":"US",
    "sg:address":"5230 US Hwy 35 S",
    "sg:city":"Star City",
    "sg:classifiers":[
        {
            "category":"Personal",
            "subcategory":"Tanning Parlor",
            "type":"Services"
        }
    ],
    "sg:phone":"+1 574 595 7132",
    "sg:postcode":"46985",
    "sg:province":"IN",
    "sg:tags":[
        "salon"
    ],
    "wof:name":"Sherry's Country Tanning Salon",
    "wof:placetype":"venue"
},
  "geometry": {"coordinates":[-86.554596,40.975614],"type":"Point"}
}