{
  "type": "Feature",
  "properties": {
    "addr:full":"1220 Brookville Way Indianapolis IN 46239",
    "addr:housenumber":"1220",
    "addr:postcode":"46239",
    "addr:street":"Brookville Way",
    "iso:country":"US",
    "sg:address":"1220 Brookville Way",
    "sg:city":"Indianapolis",
    "sg:classifiers":[
        {
            "category":"Professional",
            "subcategory":"Management & Consulting",
            "type":"Services"
        }
    ],
    "sg:phone":"+1 317 356 4000",
    "sg:postcode":"46239",
    "sg:province":"IN",
    "sg:tags":[
        "consultant",
        "motel",
        "hotel"
    ],
    "wof:name":"Midwest Hospitality Group, Inc",
    "wof:placetype":"venue"
},
  "geometry": {"coordinates":[-86.04548800000001,39.753602],"type":"Point"}
}