{
  "type": "Feature",
  "properties": {
    "addr:full":"4620 S Gadbury Rd Hartford City IN 47348",
    "addr:housenumber":"4620",
    "addr:postcode":"47348",
    "addr:street":"S Gadbury Rd",
    "iso:country":"US",
    "sg:address":"4620 S Gadbury Rd",
    "sg:city":"Hartford City",
    "sg:classifiers":[
        {
            "category":"Professional",
            "subcategory":"Business Services",
            "type":"Services"
        }
    ],
    "sg:phone":"+1 765 348 5242",
    "sg:postcode":"47348",
    "sg:province":"IN",
    "sg:tags":[
        "recording",
        "studio"
    ],
    "wof:name":"Mohee Studios",
    "wof:placetype":"venue"
},
  "geometry": {"coordinates":[-85.40723,40.388376],"type":"Point"}
}