{
  "type": "Feature",
  "properties": {
    "addr:full":"1931 N Ewing St Seymour IN 47274",
    "addr:housenumber":"1931",
    "addr:postcode":"47274",
    "addr:street":"N Ewing St",
    "iso:country":"US",
    "sg:address":"1931 N Ewing St",
    "sg:city":"Seymour",
    "sg:classifiers":[
        {
            "category":"Manufacturing",
            "subcategory":"Leather Goods",
            "type":"Manufacturing & Wholesale Goods"
        }
    ],
    "sg:phone":"+1 812 523 3728",
    "sg:postcode":"47274",
    "sg:province":"IN",
    "sg:tags":[
        "shoes",
        "mfg"
    ],
    "wof:name":"Discount Boots & Tack",
    "wof:placetype":"venue"
},
  "geometry": {"coordinates":[-85.891256,38.976868],"type":"Point"}
}