{
  "type": "Feature",
  "properties": {
    "iso:country":"US",
    "sg:address":"1228 Broadway St",
    "sg:city":"Anderson",
    "sg:classifiers":[
        {
            "category":"Personal",
            "subcategory":"Beauty Salon",
            "type":"Services"
        }
    ],
    "sg:phone":"+1 765 640 8981",
    "sg:postcode":"46012",
    "sg:province":"IN",
    "sg:tags":[
        "shop"
    ],
    "wof:name":"Sharon Stegall",
    "wof:placetype":"venue"
},
  "geometry": {"coordinates":[-85.678295,40.124527],"type":"Point"}
}