{
  "type": "Feature",
  "properties": {
    "addr:full":"1504 S Meridian Rd Jasper IN 47546",
    "addr:housenumber":"1504",
    "addr:postcode":"47546",
    "addr:street":"S Meridian Rd",
    "iso:country":"US",
    "sg:address":"1504 S Meridian Rd",
    "sg:city":"Jasper",
    "sg:classifiers":[
        {
            "category":"Wholesale",
            "subcategory":"Hardware",
            "type":"Manufacturing & Wholesale Goods"
        }
    ],
    "sg:phone":"+1 812 482 3123",
    "sg:postcode":"47546",
    "sg:province":"IN",
    "sg:tags":[
        "plumbing",
        "fixture",
        "supply"
    ],
    "wof:name":"Mauck Supply Inc",
    "wof:placetype":"venue"
},
  "geometry": {"coordinates":[-86.91005,38.369628],"type":"Point"}
}