{
  "type": "Feature",
  "properties": {
    "iso:country":"US",
    "sg:address":"16801 Cleveland Rd",
    "sg:city":"Granger",
    "sg:classifiers":[
        {
            "category":"Professional",
            "subcategory":"Lawyer & Legal Services",
            "type":"Services"
        }
    ],
    "sg:phone":"+1 574 271 4920",
    "sg:postcode":"46530",
    "sg:province":"IN",
    "sg:tags":[
        "attorney"
    ],
    "wof:name":"Patrick G Boulac",
    "wof:placetype":"venue"
},
  "geometry": {"coordinates":[-86.197051,41.723888],"type":"Point"}
}