{
  "type": "Feature",
  "properties": {
    "iso:country":"US",
    "sg:address":"865 N Johnson Rd",
    "sg:city":"Columbia City",
    "sg:classifiers":[
        {
            "category":"Personal",
            "type":"Services"
        }
    ],
    "sg:phone":"+1 260 693 6143",
    "sg:postcode":"46725",
    "sg:province":"IN",
    "sg:tags":[
        "therapy",
        "massage"
    ],
    "wof:name":"Riverbend Therapeutics",
    "wof:placetype":"venue"
},
  "geometry": {"coordinates":[-85.350157,41.178785],"type":"Point"}
}