{
  "type": "Feature",
  "properties": {
    "iso:country":"US",
    "sg:address":"207 E Main St",
    "sg:city":"North Manchester",
    "sg:classifiers":[
        {
            "category":"Organizations",
            "subcategory":"Community Association",
            "type":"Services"
        }
    ],
    "sg:phone":"+1 260 982 8211",
    "sg:postcode":"46962",
    "sg:province":"IN",
    "wof:name":"Moose Fmly Ctr 1518 - N Mnche",
    "wof:placetype":"venue"
},
  "geometry": {"coordinates":[-85.815894,40.798217],"type":"Point"}
}