{
  "type": "Feature",
  "properties": {
    "iso:country":"US",
    "sg:address":"3701 W 10th St",
    "sg:city":"Indianapolis",
    "sg:classifiers":[
        {
            "category":"Professional",
            "subcategory":"Business Services",
            "type":"Services"
        }
    ],
    "sg:phone":"+1 317 236 7162",
    "sg:postcode":"46222",
    "sg:province":"IN",
    "sg:tags":[
        "holding"
    ],
    "wof:name":"Wcs Holdings",
    "wof:placetype":"venue"
},
  "geometry": {"coordinates":[-86.22296900000001,39.780411],"type":"Point"}
}