{
  "type": "Feature",
  "properties": {
    "addr:full":"1633 S Co Rd 1233 W Lexington IN 47138",
    "addr:housenumber":"1633;1233",
    "addr:postcode":"47138",
    "addr:street":"S Co Rd;W Lexington",
    "iso:country":"US",
    "sg:address":"1633 S Co Rd 1233 W",
    "sg:city":"Lexington",
    "sg:classifiers":[
        {
            "category":"Professional",
            "type":"Services"
        }
    ],
    "sg:phone":"+1 812 866 1615",
    "sg:postcode":"47138",
    "sg:province":"IN",
    "sg:tags":[
        "establishment"
    ],
    "wof:name":"G & S Technologies Midwest",
    "wof:placetype":"venue"
},
  "geometry": {"coordinates":[-85.61383499999999,38.713183],"type":"Point"}
}