{
  "type": "Feature",
  "properties": {
    "iso:country":"US",
    "sg:address":"319 W Ohio Ave",
    "sg:city":"Hartford City",
    "sg:classifiers":[
        {
            "category":"Government",
            "subcategory":"Office",
            "type":"Public Place"
        }
    ],
    "sg:phone":"+1 765 348 1404",
    "sg:postcode":"47348",
    "sg:province":"IN",
    "sg:tags":[
        "federal"
    ],
    "wof:name":"Natural Resources Conservation",
    "wof:placetype":"venue"
},
  "geometry": {"coordinates":[-85.371027,40.462137],"type":"Point"}
}