{
  "type": "Feature",
  "properties": {
    "iso:country":"US",
    "sg:address":"5433 Keystone Dr",
    "sg:city":"Fort Wayne",
    "sg:classifiers":[
        {
            "category":"Wholesale",
            "subcategory":"Machinery & Supplies",
            "type":"Manufacturing & Wholesale Goods"
        }
    ],
    "sg:phone":"+1 260 484 4224",
    "sg:postcode":"46825",
    "sg:province":"IN",
    "sg:tags":[
        "equipment",
        "material",
        "handling"
    ],
    "wof:name":"Gallo Equipment Co",
    "wof:placetype":"venue"
},
  "geometry": {"coordinates":[-85.144039,41.126387],"type":"Point"}
}