{
  "type": "Feature",
  "properties": {
    "iso:country":"US",
    "sg:address":"4924 E 900 N",
    "sg:city":"Roanoke",
    "sg:phone":"+1 260 672 2501",
    "sg:postcode":"46783",
    "sg:province":"IN",
    "sg:tags":[
        "farm",
        "corn",
        "soybean"
    ],
    "wof:name":"Edwin Hegerfeld",
    "wof:placetype":"venue"
},
  "geometry": {"coordinates":[-85.365352,40.96051],"type":"Point"}
}