{
  "type": "Feature",
  "properties": {
    "iso:country":"US",
    "sg:address":"1301 W Market St",
    "sg:city":"Logansport",
    "sg:classifiers":[
        {
            "category":"Shopping",
            "subcategory":"Department Store",
            "type":"Retail Goods"
        }
    ],
    "sg:phone":"+1 574 722 4593",
    "sg:postcode":"46947",
    "sg:province":"IN",
    "sg:tags":[
        "shop"
    ],
    "wof:name":"Dollar General",
    "wof:placetype":"venue"
},
  "geometry": {"coordinates":[-86.383005,40.753855],"type":"Point"}
}