{
  "type": "Feature",
  "properties": {
    "iso:country":"US",
    "sg:address":"4026 N High School Rd",
    "sg:city":"Indianapolis",
    "sg:classifiers":[
        {
            "category":"Education",
            "subcategory":"Vocational School",
            "type":"Public Place"
        },
        {
            "category":"Personal",
            "subcategory":"Barber",
            "type":"Services"
        }
    ],
    "sg:phone":"+1 317 329 9000",
    "sg:postcode":"46254",
    "sg:province":"IN",
    "wof:name":"K J's Barber College Inc",
    "wof:placetype":"venue"
},
  "geometry": {"coordinates":[-86.27055799999999,39.831713],"type":"Point"}
}