{
  "type": "Feature",
  "properties": {
    "addr:full":"2126 Cass Ave Evansville IN 47714",
    "addr:housenumber":"2126",
    "addr:postcode":"47714",
    "addr:street":"Cass Ave",
    "iso:country":"US",
    "sg:address":"2126 Cass Ave",
    "sg:city":"Evansville",
    "sg:classifiers":[
        {
            "category":"Organizations",
            "subcategory":"Religious Organization",
            "type":"Services"
        }
    ],
    "sg:phone":"+1 812 476 1075",
    "sg:postcode":"47714",
    "sg:province":"IN",
    "sg:tags":[
        "church"
    ],
    "wof:name":"Soul's Harbor Baptist Church",
    "wof:placetype":"venue"
},
  "geometry": {"coordinates":[-87.52432899999999,37.953512],"type":"Point"}
}