{
  "type": "Feature",
  "properties": {
    "iso:country":"US",
    "sg:address":"829 Canal St",
    "sg:city":"Evansville",
    "sg:classifiers":[
        {
            "category":"Bus Charters",
            "type":"Transportation"
        }
    ],
    "sg:phone":"+1 812 426 7905",
    "sg:postcode":"47713",
    "sg:province":"IN",
    "sg:tags":[
        "rental"
    ],
    "wof:name":"I V Coaches Charters & Tours",
    "wof:placetype":"venue"
},
  "geometry": {"coordinates":[-87.550321,37.975887],"type":"Point"}
}