{
  "type": "Feature",
  "properties": {
    "iso:country":"US",
    "sg:address":"3919 Madison Ave",
    "sg:city":"Indianapolis",
    "sg:classifiers":[
        {
            "category":"Banks & Credit Unions",
            "subcategory":"Bank",
            "type":"Services"
        }
    ],
    "sg:phone":"+1 317 782 3014",
    "sg:postcode":"46227",
    "sg:province":"IN",
    "wof:name":"Union Federal Bank",
    "wof:placetype":"venue"
},
  "geometry": {"coordinates":[-86.142759,39.708687],"type":"Point"}
}