{
  "type": "Feature",
  "properties": {
    "iso:country":"US",
    "sg:address":"2822 Main St",
    "sg:city":"Anderson",
    "sg:classifiers":[
        {
            "category":"Restaurant",
            "type":"Food & Drink"
        }
    ],
    "sg:phone":"+1 765 643 4447",
    "sg:postcode":"46016",
    "sg:province":"IN",
    "sg:tags":[
        "pizza"
    ],
    "wof:name":"Art's Varsity Pizza",
    "wof:placetype":"venue"
},
  "geometry": {"coordinates":[-85.677653,40.088207],"type":"Point"}
}