{
  "type": "Feature",
  "properties": {
    "iso:country":"US",
    "sg:address":"101 Suzie Ln",
    "sg:city":"Attica",
    "sg:classifiers":[
        {
            "category":"Shopping",
            "subcategory":"Clothing, Apparel, & Fashions",
            "type":"Retail Goods"
        }
    ],
    "sg:phone":"+1 765 762 3685",
    "sg:postcode":"47918",
    "sg:province":"IN",
    "wof:name":"Judy's Fashions",
    "wof:placetype":"venue"
},
  "geometry": {"coordinates":[-87.240788,40.288976],"type":"Point"}
}