{
  "type": "Feature",
  "properties": {
    "iso:country":"US",
    "sg:address":"745 Ridge Rd",
    "sg:city":"Munster",
    "sg:classifiers":[
        {
            "category":"Restaurant",
            "type":"Food & Drink"
        }
    ],
    "sg:phone":"+1 219 836 4009",
    "sg:postcode":"46321",
    "sg:province":"IN",
    "sg:tags":[
        "out"
    ],
    "wof:name":"Commander Restaurant",
    "wof:placetype":"venue"
},
  "geometry": {"coordinates":[-87.510892,41.561678],"type":"Point"}
}