{
  "type": "Feature",
  "properties": {
    "iso:country":"US",
    "sg:address":"600 N Lincoln Rd",
    "sg:city":"Rockville",
    "sg:classifiers":[
        {
            "category":"Autos & Motor Vehicles",
            "subcategory":"Fuel & Gas Station",
            "type":"Retail Goods"
        }
    ],
    "sg:phone":"+1 765 569 6343",
    "sg:postcode":"47872",
    "sg:province":"IN",
    "sg:tags":[
        "oil"
    ],
    "wof:name":"Rockville 66 Food Plaza",
    "wof:placetype":"venue"
},
  "geometry": {"coordinates":[-87.236251,39.767507],"type":"Point"}
}