{
  "type": "Feature",
  "properties": {
    "iso:country":"US",
    "sg:address":"4119 Campbell Ave",
    "sg:city":"Indianapolis",
    "sg:classifiers":[
        {
            "category":"Building & Trades",
            "subcategory":"Landscaping Services",
            "type":"Services"
        }
    ],
    "sg:phone":"+1 317 545 3645",
    "sg:postcode":"46226",
    "sg:province":"IN",
    "sg:tags":[
        "lawn",
        "maintenance",
        "grounds"
    ],
    "wof:name":"D & S Lawn Care",
    "wof:placetype":"venue"
},
  "geometry": {"coordinates":[-86.066092,39.832673],"type":"Point"}
}