{
  "type": "Feature",
  "properties": {
    "iso:country":"US",
    "sg:address":"1801 E Bristol St",
    "sg:city":"Elkhart",
    "sg:classifiers":[
        {
            "category":"Insurance",
            "subcategory":"Insurance Agent",
            "type":"Services"
        }
    ],
    "sg:phone":"+1 574 264 0621",
    "sg:postcode":"46514",
    "sg:province":"IN",
    "wof:name":"Financial Partners Inc",
    "wof:placetype":"venue"
},
  "geometry": {"coordinates":[-85.94805599999999,41.702617],"type":"Point"}
}