{
  "type": "Feature",
  "properties": {
    "iso:country":"US",
    "sg:address":"131 S Main St",
    "sg:city":"Rushville",
    "sg:classifiers":[
        {
            "category":"Food & Beverages",
            "subcategory":"Bakery",
            "type":"Retail Goods"
        }
    ],
    "sg:phone":"+1 765 932 3693",
    "sg:postcode":"46173",
    "sg:province":"IN",
    "sg:tags":[
        "baker"
    ],
    "wof:name":"Mr Freshie Donuts",
    "wof:placetype":"venue"
},
  "geometry": {"coordinates":[-85.444698,39.606681],"type":"Point"}
}