{
  "type": "Feature",
  "properties": {
    "iso:country":"US",
    "sg:address":"2413 Endress Pl",
    "sg:city":"Greenwood",
    "sg:classifiers":[
        {
            "category":"Manufacturing",
            "subcategory":"Tools & Machinery",
            "type":"Manufacturing & Wholesale Goods"
        }
    ],
    "sg:phone":"+1 317 535 5447",
    "sg:postcode":"46143",
    "sg:province":"IN",
    "sg:tags":[
        "die",
        "cutting"
    ],
    "wof:name":"First Choice Dies",
    "wof:placetype":"venue"
},
  "geometry": {"coordinates":[-86.092273,39.584473],"type":"Point"}
}