{
  "type": "Feature",
  "properties": {
    "iso:country":"US",
    "sg:address":"700 Broadway",
    "sg:city":"Chesterton",
    "sg:classifiers":[
        {
            "category":"Shopping",
            "subcategory":"Used Merchandise",
            "type":"Retail Goods"
        }
    ],
    "sg:phone":"+1 219 926 2268",
    "sg:postcode":"46304",
    "sg:province":"IN",
    "sg:tags":[
        "antique"
    ],
    "wof:name":"Yesterday's Treasures Antique",
    "wof:placetype":"venue"
},
  "geometry": {"coordinates":[-87.062985,41.61164],"type":"Point"}
}