{
  "type": "Feature",
  "properties": {
    "iso:country":"US",
    "sg:address":"1844 N Linwood Ave",
    "sg:city":"Indianapolis",
    "sg:classifiers":[
        {
            "category":"Building & Trades",
            "subcategory":"Construction",
            "type":"Services"
        }
    ],
    "sg:phone":"+1 317 359 7887",
    "sg:postcode":"46218",
    "sg:province":"IN",
    "sg:tags":[
        "house"
    ],
    "wof:name":"McQuick Handyman Services",
    "wof:placetype":"venue"
},
  "geometry": {"coordinates":[-86.093493,39.792407],"type":"Point"}
}