{
  "type": "Feature",
  "properties": {
    "addr:full":"2315 E Michigan Blvd Michigan City IN 46360",
    "addr:housenumber":"2315",
    "addr:postcode":"46360",
    "addr:street":"E Michigan Blvd",
    "iso:country":"US",
    "sg:address":"2315 E Michigan Blvd",
    "sg:city":"Michigan City",
    "sg:classifiers":[
        {
            "category":"Restaurant",
            "type":"Food & Drink"
        }
    ],
    "sg:menulink":"http://www.allmenus.com/in/michigan/120057-subway/menu/",
    "sg:phone":"+1 219 878 1730",
    "sg:postcode":"46360",
    "sg:province":"IN",
    "sg:tags":[
        "american",
        "sandwich"
    ],
    "wof:name":"Subway",
    "wof:placetype":"venue"
},
  "geometry": {"coordinates":[-86.871622,41.709099],"type":"Point"}
}