{
  "type": "Feature",
  "properties": {
    "iso:country":"US",
    "sg:address":"18916 Clapp Rd",
    "sg:city":"Otisco",
    "sg:classifiers":[
        {
            "category":"Freight",
            "type":"Transportation"
        }
    ],
    "sg:phone":"+1 812 293 3166",
    "sg:postcode":"47163",
    "sg:province":"IN",
    "sg:tags":[
        "company",
        "trucking"
    ],
    "wof:name":"Jim Rose Trucking",
    "wof:placetype":"venue"
},
  "geometry": {"coordinates":[-85.620642,38.570466],"type":"Point"}
}