{
  "type": "Feature",
  "properties": {
    "iso:country":"US",
    "sg:address":"2026 Indiana Ave",
    "sg:city":"La Porte",
    "sg:classifiers":[
        {
            "category":"Insurance",
            "subcategory":"Insurance Agent",
            "type":"Services"
        }
    ],
    "sg:phone":"+1 219 324 9181",
    "sg:postcode":"46350",
    "sg:province":"IN",
    "wof:name":"McGrath & Assoc",
    "wof:placetype":"venue"
},
  "geometry": {"coordinates":[-86.70874000000001,41.595942],"type":"Point"}
}