{
  "type": "Feature",
  "properties": {
    "iso:country":"US",
    "sg:address":"6105 Southeastern Ave",
    "sg:city":"Indianapolis",
    "sg:classifiers":[
        {
            "category":"Home & Garden",
            "subcategory":"Building Materials",
            "type":"Retail Goods"
        },
        {
            "category":"Building & Trades",
            "subcategory":"Construction",
            "type":"Services"
        },
        {
            "category":"Military Area",
            "subcategory":"Armory",
            "type":"Public Place"
        }
    ],
    "sg:phone":"+1 317 356 9679",
    "sg:postcode":"46203",
    "sg:province":"IN",
    "sg:tags":[
        "repair",
        "fence",
        "altering",
        "contractor",
        "improvement",
        "remodeling",
        "fence-sales"
    ],
    "wof:name":"Quality Fence Co",
    "wof:placetype":"venue"
},
  "geometry": {"coordinates":[-86.060835,39.73324],"type":"Point"}
}