{
  "type": "Feature",
  "properties": {
    "iso:country":"US",
    "sg:address":"1203 E Angelica St",
    "sg:city":"Rensselaer",
    "sg:classifiers":[
        {
            "category":"Retail",
            "subcategory":"Auto Repair",
            "type":"Services"
        }
    ],
    "sg:phone":"+1 219 866 7892",
    "sg:postcode":"47978",
    "sg:province":"IN",
    "sg:tags":[
        "general"
    ],
    "wof:name":"Bus Maintenance Group",
    "wof:placetype":"venue"
},
  "geometry": {"coordinates":[-87.138206,40.939312],"type":"Point"}
}