{
  "type": "Feature",
  "properties": {
    "iso:country":"US",
    "sg:address":"399 Westchester Ln",
    "sg:city":"Valparaiso",
    "sg:classifiers":[
        {
            "category":"Professional",
            "type":"Services"
        }
    ],
    "sg:phone":"+1 219 465 7240",
    "sg:postcode":"46385",
    "sg:province":"IN",
    "wof:name":"Nl Pappas Inc",
    "wof:placetype":"venue"
},
  "geometry": {"coordinates":[-87.144079,41.453333],"type":"Point"}
}