{
  "type": "Feature",
  "properties": {
    "iso:country":"US",
    "sg:address":"8623 E Washington St",
    "sg:city":"Indianapolis",
    "sg:classifiers":[
        {
            "category":"Autos & Motor Vehicles",
            "subcategory":"Automobile Sales",
            "type":"Retail Goods"
        }
    ],
    "sg:phone":"+1 317 897 2906",
    "sg:postcode":"46219",
    "sg:province":"IN",
    "sg:tags":[
        "car",
        "dealer"
    ],
    "wof:name":"Mark Motors Inc",
    "wof:placetype":"venue"
},
  "geometry": {"coordinates":[-86.01485,39.773569],"type":"Point"}
}