{
  "type": "Feature",
  "properties": {
    "iso:country":"US",
    "sg:address":"10645 Deme Dr",
    "sg:city":"Indianapolis",
    "sg:classifiers":[
        {
            "category":"Home & Garden",
            "subcategory":"Furniture",
            "type":"Retail Goods"
        }
    ],
    "sg:phone":"+1 317 826 7730",
    "sg:postcode":"46236",
    "sg:province":"IN",
    "wof:name":"Patio Wicker & More",
    "wof:placetype":"venue"
},
  "geometry": {"coordinates":[-85.979491,39.861399],"type":"Point"}
}