{
  "type": "Feature",
  "properties": {
    "iso:country":"US",
    "sg:address":"667 Greenfield Rd",
    "sg:city":"Evansville",
    "sg:classifiers":[
        {
            "category":"Wholesale",
            "subcategory":"Machinery & Supplies",
            "type":"Manufacturing & Wholesale Goods"
        }
    ],
    "sg:phone":"+1 812 842 0712",
    "sg:postcode":"47715",
    "sg:province":"IN",
    "sg:tags":[
        "equipment",
        "irrigation",
        "system"
    ],
    "wof:name":"Rick's Rain Irrigation Inc",
    "wof:placetype":"venue"
},
  "geometry": {"coordinates":[-87.471493,37.967236],"type":"Point"}
}