{
  "type": "Feature",
  "properties": {
    "iso:country":"US",
    "sg:address":"202 W Seymour St",
    "sg:city":"Kentland",
    "sg:classifiers":[
        {
            "category":"Retail",
            "subcategory":"Auto Repair",
            "type":"Services"
        }
    ],
    "sg:phone":"+1 219 474 3222",
    "sg:postcode":"47951",
    "sg:province":"IN",
    "sg:tags":[
        "truck"
    ],
    "wof:name":"Daniel Truckline",
    "wof:placetype":"venue"
},
  "geometry": {"coordinates":[-87.451762,40.768314],"type":"Point"}
}