{
  "type": "Feature",
  "properties": {
    "iso:country":"US",
    "sg:address":"710 Plain St",
    "sg:city":"Laporte",
    "sg:classifiers":[
        {
            "category":"Building & Trades",
            "subcategory":"Electrical",
            "type":"Services"
        }
    ],
    "sg:phone":"+1 219 362 6525",
    "sg:postcode":"46350",
    "sg:province":"IN",
    "sg:tags":[
        "electrical",
        "electric",
        "contractor"
    ],
    "wof:name":"G D Richardson Electric",
    "wof:placetype":"venue"
},
  "geometry": {"coordinates":[-86.707827,41.608242],"type":"Point"}
}