{
  "type": "Feature",
  "properties": {
    "iso:country":"US",
    "sg:address":"1820 S Ohio St",
    "sg:city":"Martinsville",
    "sg:classifiers":[
        {
            "category":"Restaurant",
            "type":"Food & Drink"
        }
    ],
    "sg:phone":"+1 765 342 8143",
    "sg:postcode":"46151",
    "sg:province":"IN",
    "sg:website":"www.burgerking.com",
    "wof:name":"Burger King",
    "wof:placetype":"venue"
},
  "geometry": {"coordinates":[-86.42337000000001,39.411157],"type":"Point"}
}