{
  "type": "Feature",
  "properties": {
    "addr:full":"309 N Meridian St Portland IN 47371",
    "addr:housenumber":"309",
    "addr:postcode":"47371",
    "addr:street":"N Meridian St",
    "iso:country":"US",
    "sg:address":"309 N Meridian St",
    "sg:city":"Portland",
    "sg:classifiers":[
        {
            "category":"Building & Trades",
            "subcategory":"Construction",
            "type":"Services"
        }
    ],
    "sg:phone":"+1 260 726 4511",
    "sg:postcode":"47371",
    "sg:province":"IN",
    "sg:tags":[
        "house"
    ],
    "wof:name":"McDowell Leasing",
    "wof:placetype":"venue"
},
  "geometry": {"coordinates":[-84.977867,40.436242],"type":"Point"}
}