{
  "type": "Feature",
  "properties": {
    "iso:country":"US",
    "sg:address":"3282 W US Hwy 40",
    "sg:city":"Greenfield",
    "sg:classifiers":[
        {
            "category":"Freight",
            "type":"Transportation"
        }
    ],
    "sg:phone":"+1 317 462 7251",
    "sg:postcode":"46140",
    "sg:province":"IN",
    "sg:tags":[
        "trucking"
    ],
    "wof:name":"Hammons Equipment Co Inc",
    "wof:placetype":"venue"
},
  "geometry": {"coordinates":[-85.86209,39.780988],"type":"Point"}
}