{
  "type": "Feature",
  "properties": {
    "addr:full":"4201 S Washington St Marion IN 46953",
    "addr:housenumber":"4201",
    "addr:postcode":"46953",
    "addr:street":"S Washington St",
    "iso:country":"US",
    "sg:address":"4201 S Washington St",
    "sg:city":"Marion",
    "sg:classifiers":[
        {
            "category":"Communications",
            "subcategory":"Television Station",
            "type":"Services"
        }
    ],
    "sg:phone":"+1 765 677 2775",
    "sg:postcode":"46953",
    "sg:province":"IN",
    "sg:tags":[
        "broadcasting",
        "co"
    ],
    "sg:website":"www.indwes.edu",
    "wof:name":"Wiwu TV 51",
    "wof:placetype":"venue"
},
  "geometry": {"coordinates":[-85.668977,40.518039],"type":"Point"}
}