{
  "type": "Feature",
  "properties": {
    "iso:country":"US",
    "sg:address":"240 E 4th St",
    "sg:city":"Avilla",
    "sg:classifiers":[
        {
            "category":"Shopping",
            "subcategory":"Clothing, Apparel, & Fashions",
            "type":"Retail Goods"
        }
    ],
    "sg:phone":"+1 260 897 3118",
    "sg:postcode":"46792",
    "sg:province":"IN",
    "sg:tags":[
        "industrial",
        "glove"
    ],
    "sg:website":"www.parkerglove.com",
    "wof:name":"Parker Glove & Supply Co",
    "wof:placetype":"venue"
},
  "geometry": {"coordinates":[-85.424447,40.683887],"type":"Point"}
}