{
  "type": "Feature",
  "properties": {
    "iso:country":"US",
    "sg:address":"3727 E Vermont St",
    "sg:city":"Indianapolis",
    "sg:classifiers":[
        {
            "category":"Social Services",
            "subcategory":"Child Care",
            "type":"Services"
        }
    ],
    "sg:phone":"+1 317 351 5914",
    "sg:postcode":"46201",
    "sg:province":"IN",
    "wof:name":"Barb's Daycare",
    "wof:placetype":"venue"
},
  "geometry": {"coordinates":[-86.10254,39.772929],"type":"Point"}
}