{
  "type": "Feature",
  "properties": {
    "addr:full":"834 N State St Greenfield IN 46140",
    "addr:housenumber":"834",
    "addr:postcode":"46140",
    "addr:street":"N State St",
    "iso:country":"US",
    "sg:address":"834 N State St",
    "sg:city":"Greenfield",
    "sg:classifiers":[
        {
            "category":"Building & Trades",
            "subcategory":"Plumbing",
            "type":"Services"
        }
    ],
    "sg:phone":"+1 317 462 3065",
    "sg:postcode":"46140",
    "sg:province":"IN",
    "sg:tags":[
        "heating",
        "contractor"
    ],
    "wof:name":"Bob Williams Air Cond & Htg",
    "wof:placetype":"venue"
},
  "geometry": {"coordinates":[-85.769679,39.794964],"type":"Point"}
}