{
  "type": "Feature",
  "properties": {
    "iso:country":"US",
    "sg:address":"1145 Locust Dr",
    "sg:city":"Martinsville",
    "sg:classifiers":[
        {
            "category":"Professional",
            "subcategory":"Engineering",
            "type":"Services"
        }
    ],
    "sg:phone":"+1 317 306 7547",
    "sg:postcode":"46151",
    "sg:province":"IN",
    "sg:tags":[
        "consulting",
        "engineer"
    ],
    "wof:name":"DCS Corporation",
    "wof:placetype":"venue"
},
  "geometry": {"coordinates":[-86.452716,39.452061],"type":"Point"}
}