{
  "type": "Feature",
  "properties": {
    "iso:country":"US",
    "sg:address":"1321 N Fulton Ave",
    "sg:city":"Evansville",
    "sg:classifiers":[
        {
            "category":"Food & Beverages",
            "subcategory":"Groceries & Convenience Stores",
            "type":"Retail Goods"
        }
    ],
    "sg:phone":"+1 812 424 2383",
    "sg:postcode":"47710",
    "sg:province":"IN",
    "wof:name":"Pantry",
    "wof:placetype":"venue"
},
  "geometry": {"coordinates":[-87.58083499999999,37.990484],"type":"Point"}
}