{
  "type": "Feature",
  "properties": {
    "iso:country":"US",
    "sg:address":"2007 Kossuth St",
    "sg:city":"Lafayette",
    "sg:classifiers":[
        {
            "category":"Home & Garden",
            "subcategory":"Building Materials",
            "type":"Retail Goods"
        }
    ],
    "sg:phone":"+1 765 447 1300",
    "sg:postcode":"47905",
    "sg:province":"IN",
    "sg:tags":[
        "door"
    ],
    "wof:name":"Barrier Windows Of Lafayette",
    "wof:placetype":"venue"
},
  "geometry": {"coordinates":[-86.87397799999999,40.409987],"type":"Point"}
}