{
  "type": "Feature",
  "properties": {
    "iso:country":"US",
    "sg:address":"4300 S Whitney Rd",
    "sg:city":"Selma",
    "sg:classifiers":[
        {
            "category":"Farming",
            "subcategory":"Farm",
            "type":"Manufacturing & Wholesale Goods"
        }
    ],
    "sg:phone":"+1 765 282 3430",
    "sg:postcode":"47383",
    "sg:province":"IN",
    "sg:tags":[
        "crop",
        "general"
    ],
    "wof:name":"Charles White",
    "wof:placetype":"venue"
},
  "geometry": {"coordinates":[-85.301441,40.153463],"type":"Point"}
}