{
  "type": "Feature",
  "properties": {
    "iso:country":"US",
    "sg:address":"4629 Lima Rd",
    "sg:city":"Fort Wayne",
    "sg:classifiers":[
        {
            "category":"Manufacturing",
            "subcategory":"Tools & Machinery",
            "type":"Manufacturing & Wholesale Goods"
        }
    ],
    "sg:phone":"+1 260 484 5527",
    "sg:postcode":"46808",
    "sg:province":"IN",
    "sg:tags":[
        "instrument",
        "optical",
        "lense"
    ],
    "wof:name":"Walman Optical Co",
    "wof:placetype":"venue"
},
  "geometry": {"coordinates":[-85.152484,41.121611],"type":"Point"}
}