{
  "type": "Feature",
  "properties": {
    "iso:country":"US",
    "sg:address":"875 Kelly St Exd",
    "sg:city":"Rome City",
    "sg:classifiers":[
        {
            "category":"Retail",
            "subcategory":"Veterinary Services",
            "type":"Services"
        }
    ],
    "sg:phone":"+1 260 854 2130",
    "sg:postcode":"46784",
    "sg:province":"IN",
    "sg:tags":[
        "veterinarian"
    ],
    "wof:name":"Sylvan Lake Animal Clinic",
    "wof:placetype":"venue"
},
  "geometry": {"coordinates":[-85.37611,41.485748],"type":"Point"}
}