{
  "type": "Feature",
  "properties": {
    "iso:country":"US",
    "sg:address":"12422 Springbrooke Run",
    "sg:city":"Carmel",
    "sg:classifiers":[
        {
            "category":"Wholesale",
            "subcategory":"Jewelry",
            "type":"Manufacturing & Wholesale Goods"
        }
    ],
    "sg:phone":"+1 317 846 3551",
    "sg:postcode":"46033",
    "sg:province":"IN",
    "sg:tags":[
        "jeweler"
    ],
    "wof:name":"Vincent Jewelry Designs",
    "wof:placetype":"venue"
},
  "geometry": {"coordinates":[-86.07595499999999,39.966099],"type":"Point"}
}