{
  "type": "Feature",
  "properties": {
    "iso:country":"US",
    "sg:address":"3801 Ridge Rd",
    "sg:city":"Highland",
    "sg:classifiers":[
        {
            "category":"Health Services",
            "subcategory":"Doctor",
            "type":"Services"
        }
    ],
    "sg:phone":"+1 219 838 0066",
    "sg:postcode":"46322",
    "sg:province":"IN",
    "sg:tags":[
        "physician",
        "surgeon"
    ],
    "wof:name":"Highland Clinic",
    "wof:placetype":"venue"
},
  "geometry": {"coordinates":[-87.432531,41.551581],"type":"Point"}
}