{
  "type": "Feature",
  "properties": {
    "iso:country":"US",
    "sg:address":"1301 E National Hwy",
    "sg:city":"Washington",
    "sg:classifiers":[
        {
            "category":"Retail",
            "subcategory":"Car Wash",
            "type":"Services"
        }
    ],
    "sg:phone":"+1 812 254 3432",
    "sg:postcode":"47501",
    "sg:province":"IN",
    "sg:tags":[
        "polishing",
        "washing"
    ],
    "wof:name":"Superwash Inc",
    "wof:placetype":"venue"
},
  "geometry": {"coordinates":[-87.156307,38.652901],"type":"Point"}
}