{
  "type": "Feature",
  "properties": {
    "iso:country":"US",
    "sg:address":"9 Laurel Dr",
    "sg:city":"Jeffersonville",
    "sg:classifiers":[
        {
            "category":"Manufacturing",
            "subcategory":"Retail Goods",
            "type":"Manufacturing & Wholesale Goods"
        }
    ],
    "sg:phone":"+1 812 285 9732",
    "sg:postcode":"47130",
    "sg:province":"IN",
    "sg:tags":[
        "product",
        "mfg"
    ],
    "wof:name":"Js Mfg Inc",
    "wof:placetype":"venue"
},
  "geometry": {"coordinates":[-85.692541,38.310571],"type":"Point"}
}