{
  "type": "Feature",
  "properties": {
    "iso:country":"US",
    "sg:address":"1514 E 400 S",
    "sg:city":"Chalmers",
    "sg:classifiers":[
        {
            "category":"Building & Trades",
            "subcategory":"Landscaping Services",
            "type":"Services"
        }
    ],
    "sg:phone":"+1 219 984 5118",
    "sg:postcode":"47929",
    "sg:province":"IN",
    "wof:name":"Hansell Lawn Care",
    "wof:placetype":"venue"
},
  "geometry": {"coordinates":[-86.83680699999999,40.692613],"type":"Point"}
}