{
  "type": "Feature",
  "properties": {
    "iso:country":"US",
    "sg:address":"645 S State St",
    "sg:city":"Greenfield",
    "sg:classifiers":[
        {
            "category":"Professional",
            "type":"Services"
        }
    ],
    "sg:phone":"+1 317 462 2407",
    "sg:postcode":"46140",
    "sg:province":"IN",
    "sg:tags":[
        "establishment"
    ],
    "wof:name":"Brandywine Pre-School",
    "wof:placetype":"venue"
},
  "geometry": {"coordinates":[-85.768227,39.778302],"type":"Point"}
}