{
  "type": "Feature",
  "properties": {
    "iso:country":"US",
    "sg:address":"13235 Sunset Dr",
    "sg:city":"Dillsboro",
    "sg:classifiers":[
        {
            "category":"Social Services",
            "subcategory":"Child Care",
            "type":"Services"
        }
    ],
    "sg:phone":"+1 812 432 9262",
    "sg:postcode":"47018",
    "sg:province":"IN",
    "wof:name":"Land Of Little People Inc",
    "wof:placetype":"venue"
},
  "geometry": {"coordinates":[-85.065079,39.014947],"type":"Point"}
}