{
  "type": "Feature",
  "properties": {
    "iso:country":"US",
    "sg:address":"834 E Markland Ave",
    "sg:city":"Kokomo",
    "sg:classifiers":[
        {
            "category":"Wholesale",
            "subcategory":"Electrical",
            "type":"Manufacturing & Wholesale Goods"
        }
    ],
    "sg:phone":"+1 765 452 7054",
    "sg:postcode":"46901",
    "sg:province":"IN",
    "sg:tags":[
        "appliance"
    ],
    "wof:name":"Bass Appliance Parts & Rpr Svc",
    "wof:placetype":"venue"
},
  "geometry": {"coordinates":[-86.122373,40.476619],"type":"Point"}
}