{
  "type": "Feature",
  "properties": {
    "iso:country":"US",
    "sg:address":"67136 State Rd 15",
    "sg:city":"New Paris",
    "sg:classifiers":[
        {
            "category":"Organizations",
            "subcategory":"Religious Organization",
            "type":"Services"
        }
    ],
    "sg:phone":"+1 574 831 6880",
    "sg:postcode":"46553",
    "sg:province":"IN",
    "wof:name":"New Parish Church of Nazarane",
    "wof:placetype":"venue"
},
  "geometry": {"coordinates":[-85.82843099999999,41.520853],"type":"Point"}
}