{
  "type": "Feature",
  "properties": {
    "iso:country":"US",
    "sg:address":"1015 W Wayne St",
    "sg:city":"Muncie",
    "sg:classifiers":[
        {
            "category":"Professional",
            "subcategory":"Accounting & Tax Preparation",
            "type":"Services"
        }
    ],
    "sg:phone":"+1 765 289 5628",
    "sg:postcode":"47303",
    "sg:province":"IN",
    "sg:tags":[
        "accountant"
    ],
    "wof:name":"Public Accountant",
    "wof:placetype":"venue"
},
  "geometry": {"coordinates":[-85.398274,40.202224],"type":"Point"}
}