{
  "type": "Feature",
  "properties": {
    "iso:country":"US",
    "sg:address":"462 E Jefferson St",
    "sg:city":"Franklin",
    "sg:classifiers":[
        {
            "category":"Shopping",
            "subcategory":"Gifts & Souvenirs",
            "type":"Retail Goods"
        }
    ],
    "sg:phone":"+1 317 738 4237",
    "sg:postcode":"46131",
    "sg:province":"IN",
    "sg:tags":[
        "shop"
    ],
    "wof:name":"Townhouse",
    "wof:placetype":"venue"
},
  "geometry": {"coordinates":[-86.049004,39.480908],"type":"Point"}
}