{
  "type": "Feature",
  "properties": {
    "iso:country":"US",
    "sg:address":"13549 Saint Wendel Rd",
    "sg:city":"Evansville",
    "sg:classifiers":[
        {
            "category":"Building & Trades",
            "subcategory":"Landscaping Services",
            "type":"Services"
        }
    ],
    "sg:phone":"+1 812 963 3317",
    "sg:postcode":"47720",
    "sg:province":"IN",
    "sg:tags":[
        "landscape",
        "contractor"
    ],
    "wof:name":"Arrowhead Custom Lawn Care Inc",
    "wof:placetype":"venue"
},
  "geometry": {"coordinates":[-87.694422,38.096905],"type":"Point"}
}