{
  "type": "Feature",
  "properties": {
    "iso:country":"US",
    "sg:address":"1562 S Fairlawn Ave",
    "sg:city":"Evansville",
    "sg:classifiers":[
        {
            "category":"Shopping",
            "type":"Retail Goods"
        }
    ],
    "sg:phone":"+1 812 479 7303",
    "sg:postcode":"47714",
    "sg:province":"IN",
    "sg:tags":[
        "hearing",
        "equipment",
        "supply",
        "impaired"
    ],
    "wof:name":"Hearing Aid Assoc LTD",
    "wof:placetype":"venue"
},
  "geometry": {"coordinates":[-87.523781,37.955848],"type":"Point"}
}