{
  "type": "Feature",
  "properties": {
    "iso:country":"US",
    "sg:address":"10053 E 42nd St",
    "sg:city":"Indianapolis",
    "sg:classifiers":[
        {
            "category":"Personal",
            "subcategory":"Beauty Salon",
            "type":"Services"
        }
    ],
    "sg:phone":"+1 317 897 2384",
    "sg:postcode":"46235",
    "sg:province":"IN",
    "wof:name":"Nina's Salon",
    "wof:placetype":"venue"
},
  "geometry": {"coordinates":[-85.989458,39.833595],"type":"Point"}
}