{
  "type": "Feature",
  "properties": {
    "iso:country":"US",
    "sg:address":"315 Washington St",
    "sg:city":"Hope",
    "sg:classifiers":[
        {
            "category":"Freight",
            "type":"Transportation"
        }
    ],
    "sg:phone":"+1 812 546 9037",
    "sg:postcode":"47246",
    "sg:province":"IN",
    "sg:tags":[
        "broker",
        "trucking"
    ],
    "wof:name":"Berod Logistics Inc",
    "wof:placetype":"venue"
},
  "geometry": {"coordinates":[-85.771356,39.302856],"type":"Point"}
}