{
  "type": "Feature",
  "properties": {
    "iso:country":"US",
    "sg:address":"12540 N Gray Rd",
    "sg:city":"Carmel",
    "sg:classifiers":[
        {
            "category":"Retail",
            "subcategory":"Laundry & Dry Cleaning",
            "type":"Services"
        }
    ],
    "sg:phone":"+1 317 848 5820",
    "sg:postcode":"46033",
    "sg:province":"IN",
    "wof:name":"Curley's Cleaners",
    "wof:placetype":"venue"
},
  "geometry": {"coordinates":[-86.089302,39.969799],"type":"Point"}
}