{
  "type": "Feature",
  "properties": {
    "addr:full":"9948 Park Davis Dr Indianapolis IN 46235",
    "addr:housenumber":"9948",
    "addr:postcode":"46235",
    "addr:street":"Park Davis Dr",
    "iso:country":"US",
    "sg:address":"9948 Park Davis Dr",
    "sg:city":"Indianapolis",
    "sg:classifiers":[
        {
            "category":"Building & Trades",
            "subcategory":"Equipment Rental",
            "type":"Services"
        }
    ],
    "sg:phone":"+1 317 899 4050",
    "sg:postcode":"46235",
    "sg:province":"IN",
    "sg:tags":[
        "supplies-renting",
        "hospital",
        "wheelchairs-rental"
    ],
    "wof:name":"United Hospital Services Inc",
    "wof:placetype":"venue"
},
  "geometry": {"coordinates":[-85.992372,39.820431],"type":"Point"}
}