{
  "type": "Feature",
  "properties": {
    "iso:country":"US",
    "sg:address":"4728 Hohman Ave",
    "sg:city":"Hammond",
    "sg:classifiers":[
        {
            "category":"Home & Garden",
            "subcategory":"Household Appliances",
            "type":"Retail Goods"
        }
    ],
    "sg:phone":"+1 219 933 3079",
    "sg:postcode":"46327",
    "sg:province":"IN",
    "wof:name":"Applaince Depot",
    "wof:placetype":"venue"
},
  "geometry": {"coordinates":[-87.517383,41.627141],"type":"Point"}
}