{
  "type": "Feature",
  "properties": {
    "iso:country":"US",
    "sg:address":"8868 E 56th St",
    "sg:city":"Indianapolis",
    "sg:classifiers":[
        {
            "category":"Professional",
            "subcategory":"Detective & Security Services",
            "type":"Services"
        }
    ],
    "sg:phone":"+1 317 510 3711",
    "sg:postcode":"46216",
    "sg:province":"IN",
    "sg:tags":[
        "information",
        "bureau"
    ],
    "wof:name":"Gsa Federal Telecomm Services",
    "wof:placetype":"venue"
},
  "geometry": {"coordinates":[-86.012457,39.855326],"type":"Point"}
}