{
  "type": "Feature",
  "properties": {
    "iso:country":"US",
    "sg:address":"300 E Market St",
    "sg:city":"Indianapolis",
    "sg:classifiers":[
        {
            "category":"Professional",
            "type":"Services"
        }
    ],
    "sg:phone":"+1 317 630 1123",
    "sg:postcode":"46204",
    "sg:province":"IN",
    "sg:tags":[
        "establishment"
    ],
    "wof:name":"WJCP",
    "wof:placetype":"venue"
},
  "geometry": {"coordinates":[-86.150791,39.768353],"type":"Point"}
}