{
  "type": "Feature",
  "properties": {
    "iso:country":"US",
    "sg:address":"321 Mitchell Ave",
    "sg:city":"Batesville",
    "sg:classifiers":[
        {
            "category":"Health Services",
            "subcategory":"Doctor",
            "type":"Services"
        }
    ],
    "sg:phone":"+1 812 933 5110",
    "sg:postcode":"47006",
    "sg:province":"IN",
    "sg:tags":[
        "physician",
        "surgeon"
    ],
    "wof:name":"Louis J Schott MD",
    "wof:placetype":"venue"
},
  "geometry": {"coordinates":[-85.22471400000001,39.304905],"type":"Point"}
}