{
  "type": "Feature",
  "properties": {
    "iso:country":"US",
    "sg:address":"8981 E 116th St",
    "sg:city":"Fishers",
    "sg:classifiers":[
        {
            "category":"Shopping",
            "subcategory":"Shoes",
            "type":"Retail Goods"
        }
    ],
    "sg:phone":"+1 317 845 1210",
    "sg:postcode":"46038",
    "sg:province":"IN",
    "wof:name":"Birkenstock Sole Satisfaction",
    "wof:placetype":"venue"
},
  "geometry": {"coordinates":[-86.010628,39.95673],"type":"Point"}
}