{
  "type": "Feature",
  "properties": {
    "iso:country":"US",
    "sg:address":"1635 W Michigan St",
    "sg:city":"Indianapolis",
    "sg:classifiers":[
        {
            "category":"Education",
            "subcategory":"School",
            "type":"Public Place"
        }
    ],
    "sg:phone":"+1 317 524 4638",
    "sg:postcode":"46222",
    "sg:province":"IN",
    "sg:tags":[
        "high",
        "k-",
        "private"
    ],
    "wof:name":"Indianapolis Metropolitan High School",
    "wof:placetype":"venue"
},
  "geometry": {"coordinates":[-86.19093100000001,39.774712],"type":"Point"}
}