{
  "type": "Feature",
  "properties": {
    "iso:country":"US",
    "sg:address":"6061 Guion Rd",
    "sg:city":"Indianapolis",
    "sg:classifiers":[
        {
            "category":"Manufacturing",
            "subcategory":"Rubber & Plastics",
            "type":"Manufacturing & Wholesale Goods"
        }
    ],
    "sg:phone":"+1 317 297 4638",
    "sg:postcode":"46254",
    "sg:province":"IN",
    "sg:tags":[
        "product"
    ],
    "sg:website":"www.nampac.com",
    "wof:name":"NAMPAC",
    "wof:placetype":"venue"
},
  "geometry": {"coordinates":[-86.23156899999999,39.867003],"type":"Point"}
}