{
  "type": "Feature",
  "properties": {
    "iso:country":"US",
    "sg:address":"2193 E 150 S",
    "sg:city":"Rochester",
    "sg:classifiers":[
        {
            "category":"Personal",
            "subcategory":"Beauty Salon",
            "type":"Services"
        }
    ],
    "sg:phone":"+1 574 224 3862",
    "sg:postcode":"46975",
    "sg:province":"IN",
    "sg:tags":[
        "shop"
    ],
    "wof:name":"Aimee's Place",
    "wof:placetype":"venue"
},
  "geometry": {"coordinates":[-86.200704,41.03243],"type":"Point"}
}