{
  "type": "Feature",
  "properties": {
    "iso:country":"US",
    "sg:address":"506 Broadway",
    "sg:city":"Chesterton",
    "sg:classifiers":[
        {
            "category":"Building & Trades",
            "subcategory":"Construction",
            "type":"Services"
        }
    ],
    "sg:phone":"+1 219 926 5167",
    "sg:postcode":"46304",
    "sg:province":"IN",
    "sg:tags":[
        "contractor"
    ],
    "sg:website":"www.2wayelectronics.com",
    "wof:name":"2-Way Electronics Comms",
    "wof:placetype":"venue"
},
  "geometry": {"coordinates":[-87.05898500000001,41.611423],"type":"Point"}
}