{
  "type": "Feature",
  "properties": {
    "addr:full":"3800 E 3rd St Bloomington IN 47401",
    "addr:housenumber":"3800",
    "addr:postcode":"47401",
    "addr:street":"E 3Rd St",
    "iso:country":"US",
    "sg:address":"3800 E 3rd St",
    "sg:city":"Bloomington",
    "sg:classifiers":[
        {
            "category":"Organizations",
            "subcategory":"Religious Organization",
            "type":"Services"
        }
    ],
    "sg:phone":"+1 812 332 5252",
    "sg:postcode":"47401",
    "sg:province":"IN",
    "sg:tags":[
        "church"
    ],
    "sg:website":"www.stlconline.org",
    "wof:name":"St Thomas Lutheran Church",
    "wof:placetype":"venue"
},
  "geometry": {"coordinates":[-86.481201,39.1642],"type":"Point"}
}