{
  "type": "Feature",
  "properties": {
    "iso:country":"US",
    "sg:address":"3017 School Rd",
    "sg:city":"West Harrison",
    "sg:classifiers":[
        {
            "category":"Building & Trades",
            "subcategory":"Construction",
            "type":"Services"
        }
    ],
    "sg:phone":"+1 812 637 2844",
    "sg:postcode":"47060",
    "sg:province":"IN",
    "sg:tags":[
        "general",
        "contractor"
    ],
    "wof:name":"Steve Wilhelm Contracting",
    "wof:placetype":"venue"
},
  "geometry": {"coordinates":[-84.86856400000001,39.346457],"type":"Point"}
}