{
  "type": "Feature",
  "properties": {
    "iso:country":"US",
    "sg:address":"2505 College Ave",
    "sg:city":"Terre Haute",
    "sg:classifiers":[
        {
            "category":"Organizations",
            "subcategory":"Religious Organization",
            "type":"Services"
        }
    ],
    "sg:phone":"+1 812 232 2137",
    "sg:postcode":"47803",
    "sg:province":"IN",
    "wof:name":"Faith Baptist Church",
    "wof:placetype":"venue"
},
  "geometry": {"coordinates":[-87.378213,39.455587],"type":"Point"}
}