{
  "type": "Feature",
  "properties": {
    "addr:full":"7118 N Shadeland Ave Indianapolis IN 46250",
    "addr:housenumber":"7118",
    "addr:postcode":"46250",
    "addr:street":"N Shadeland Ave",
    "iso:country":"US",
    "sg:address":"7118 N Shadeland Ave",
    "sg:city":"Indianapolis",
    "sg:classifiers":[
        {
            "category":"Health Services",
            "subcategory":"Doctor",
            "type":"Services"
        }
    ],
    "sg:phone":"+1 317 849 6776",
    "sg:postcode":"46250",
    "sg:province":"IN",
    "sg:tags":[
        "dentist"
    ],
    "wof:name":"Borkowski & Borkowski",
    "wof:placetype":"venue"
},
  "geometry": {"coordinates":[-86.046161,39.887526],"type":"Point"}
}