{
  "type": "Feature",
  "properties": {
    "iso:country":"US",
    "sg:address":"19 N Indiana St",
    "sg:city":"Greencastle",
    "sg:classifiers":[
        {
            "category":"Professional",
            "type":"Services"
        }
    ],
    "sg:phone":"+1 765 653 1827",
    "sg:postcode":"46135",
    "sg:province":"IN",
    "sg:tags":[
        "establishment"
    ],
    "wof:name":"M & D's Draperies",
    "wof:placetype":"venue"
},
  "geometry": {"coordinates":[-86.864475,39.644614],"type":"Point"}
}