{
  "type": "Feature",
  "properties": {
    "iso:country":"US",
    "sg:address":"518 Park St",
    "sg:city":"Westfield",
    "sg:classifiers":[
        {
            "category":"Restaurant",
            "type":"Food & Drink"
        }
    ],
    "sg:phone":"+1 317 896 3964",
    "sg:postcode":"46074",
    "sg:province":"IN",
    "sg:website":"www.hardees.com",
    "wof:name":"Hardees of Westfield",
    "wof:placetype":"venue"
},
  "geometry": {"coordinates":[-86.13490299999999,40.040501],"type":"Point"}
}