{
  "type": "Feature",
  "properties": {
    "iso:country":"US",
    "sg:address":"405 Canterbury Rd",
    "sg:city":"Griffith",
    "sg:classifiers":[
        {
            "category":"Building & Trades",
            "subcategory":"Construction",
            "type":"Services"
        }
    ],
    "sg:phone":"+1 219 922 9582",
    "sg:postcode":"46319",
    "sg:province":"IN",
    "sg:tags":[
        "home",
        "builder"
    ],
    "wof:name":"Homestyle Builders",
    "wof:placetype":"venue"
},
  "geometry": {"coordinates":[-87.430953,41.513191],"type":"Point"}
}