{
  "type": "Feature",
  "properties": {
    "addr:full":"8325 S Emerson Ave Indianapolis IN 46237",
    "addr:housenumber":"8325",
    "addr:postcode":"46237",
    "addr:street":"S Emerson Ave",
    "iso:country":"US",
    "sg:address":"8325 S Emerson Ave",
    "sg:city":"Indianapolis",
    "sg:classifiers":[
        {
            "category":"Health Services",
            "subcategory":"Doctor",
            "type":"Services"
        }
    ],
    "sg:phone":"+1 317 881 8737",
    "sg:postcode":"46237",
    "sg:province":"IN",
    "sg:tags":[
        "physician",
        "surgeon"
    ],
    "wof:name":"Clown Pediatrics PC",
    "wof:placetype":"venue"
},
  "geometry": {"coordinates":[-86.082579,39.650402],"type":"Point"}
}