{
  "type": "Feature",
  "properties": {
    "addr:full":"603 W Main St Newburgh IN 47630",
    "addr:housenumber":"603",
    "addr:postcode":"47630",
    "addr:street":"W Main St",
    "iso:country":"US",
    "sg:address":"603 W Main St",
    "sg:city":"Newburgh",
    "sg:classifiers":[
        {
            "category":"Manufacturing",
            "subcategory":"Pet Food",
            "type":"Manufacturing & Wholesale Goods"
        }
    ],
    "sg:phone":"+1 812 858 9645",
    "sg:postcode":"47630",
    "sg:province":"IN",
    "sg:tags":[
        "dog",
        "cat"
    ],
    "wof:name":"Pet Food Ctr",
    "wof:placetype":"venue"
},
  "geometry": {"coordinates":[-87.412138,37.947095],"type":"Point"}
}