{
  "type": "Feature",
  "properties": {
    "iso:country":"US",
    "sg:address":"916 Russell Ave",
    "sg:city":"Fort Wayne",
    "sg:classifiers":[
        {
            "category":"Retail",
            "subcategory":"Auto Repair",
            "type":"Services"
        }
    ],
    "sg:phone":"+1 260 471 0154",
    "sg:postcode":"46808",
    "sg:province":"IN",
    "sg:tags":[
        "general"
    ],
    "wof:name":"Elite Automotive",
    "wof:placetype":"venue"
},
  "geometry": {"coordinates":[-85.153968,41.100285],"type":"Point"}
}