{
  "type": "Feature",
  "properties": {
    "iso:country":"US",
    "sg:address":"203 E 9th St",
    "sg:city":"Auburn",
    "sg:classifiers":[
        {
            "category":"Retail",
            "subcategory":"Auto Repair",
            "type":"Services"
        }
    ],
    "sg:phone":"+1 260 927 9360",
    "sg:postcode":"46706",
    "sg:province":"IN",
    "sg:tags":[
        "general"
    ],
    "wof:name":"Classic City Body & Paint",
    "wof:placetype":"venue"
},
  "geometry": {"coordinates":[-85.053303,41.365801],"type":"Point"}
}