{
  "type": "Feature",
  "properties": {
    "addr:full":"624 State Rd 930 E New Haven IN 46774",
    "addr:housenumber":"624",
    "addr:postcode":"46774",
    "addr:street":"State Rd 930 E",
    "iso:country":"US",
    "sg:address":"624 State Rd 930 E",
    "sg:city":"New Haven",
    "sg:classifiers":[
        {
            "category":"Autos & Motor Vehicles",
            "subcategory":"Automobile Sales",
            "type":"Retail Goods"
        }
    ],
    "sg:phone":"+1 260 749 9674",
    "sg:postcode":"46774",
    "sg:province":"IN",
    "sg:tags":[
        "car",
        "dealer"
    ],
    "wof:name":"Crumback-Symons Chevrolet Inc",
    "wof:placetype":"venue"
},
  "geometry": {"coordinates":[-85.02112200000001,41.067295],"type":"Point"}
}