{
  "type": "Feature",
  "properties": {
    "iso:country":"US",
    "sg:address":"3530 Michigan St",
    "sg:city":"Hobart",
    "sg:classifiers":[
        {
            "category":"Manufacturing",
            "subcategory":"Tools & Machinery",
            "type":"Manufacturing & Wholesale Goods"
        }
    ],
    "sg:phone":"+1 219 962 7514",
    "sg:postcode":"46342",
    "sg:province":"IN",
    "sg:tags":[
        "instrumentation",
        "industrial"
    ],
    "wof:name":"A & M Engineering Inc",
    "wof:placetype":"venue"
},
  "geometry": {"coordinates":[-87.274515,41.552755],"type":"Point"}
}