{
  "type": "Feature",
  "properties": {
    "iso:country":"US",
    "sg:address":"719 Massachusetts Ave",
    "sg:city":"Indianapolis",
    "sg:classifiers":[
        {
            "category":"Professional",
            "type":"Services"
        }
    ],
    "sg:phone":"+1 317 955 9200",
    "sg:postcode":"46204",
    "sg:province":"IN",
    "sg:tags":[
        "establishment"
    ],
    "wof:name":"Burgett Enterprises",
    "wof:placetype":"venue"
},
  "geometry": {"coordinates":[-86.145453,39.777345],"type":"Point"}
}