{
  "type": "Feature",
  "properties": {
    "iso:country":"US",
    "sg:address":"6130 S Belmont Ave",
    "sg:city":"Indianapolis",
    "sg:classifiers":[
        {
            "category":"Wholesale",
            "subcategory":"Vending Machines",
            "type":"Manufacturing & Wholesale Goods"
        }
    ],
    "sg:phone":"+1 317 787 8363",
    "sg:postcode":"46217",
    "sg:province":"IN",
    "wof:name":"River City Vending",
    "wof:placetype":"venue"
},
  "geometry": {"coordinates":[-86.196617,39.671773],"type":"Point"}
}