{
  "type": "Feature",
  "properties": {
    "iso:country":"US",
    "sg:address":"6734 Millside Dr",
    "sg:city":"Indianapolis",
    "sg:classifiers":[
        {
            "category":"Health Services",
            "subcategory":"Nursing And Care Facility",
            "type":"Services"
        }
    ],
    "sg:phone":"+1 317 856 3295",
    "sg:postcode":"46221",
    "sg:province":"IN",
    "sg:tags":[
        "home",
        "retirement",
        "community"
    ],
    "wof:name":"Home Place Apartments",
    "wof:placetype":"venue"
},
  "geometry": {"coordinates":[-86.273117,39.666283],"type":"Point"}
}