{
  "type": "Feature",
  "properties": {
    "iso:country":"US",
    "sg:address":"1440 Michigan St",
    "sg:city":"Ferdinand",
    "sg:classifiers":[
        {
            "category":"Education",
            "subcategory":"School",
            "type":"Public Place"
        }
    ],
    "sg:phone":"+1 812 367 1831",
    "sg:postcode":"47532",
    "sg:province":"IN",
    "wof:name":"Forest Park High School",
    "wof:placetype":"venue"
},
  "geometry": {"coordinates":[-86.858492,38.227217],"type":"Point"}
}