{
  "type": "Feature",
  "properties": {
    "iso:country":"US",
    "sg:address":"9004 Flynn Rd",
    "sg:city":"Indianapolis",
    "sg:classifiers":[
        {
            "category":"Building & Trades",
            "subcategory":"Construction",
            "type":"Services"
        }
    ],
    "sg:phone":"+1 317 856 3575",
    "sg:postcode":"46241",
    "sg:province":"IN",
    "sg:tags":[
        "foundation"
    ],
    "wof:name":"Foundations By Thompson Inc",
    "wof:placetype":"venue"
},
  "geometry": {"coordinates":[-86.321725,39.669167],"type":"Point"}
}