{
  "type": "Feature",
  "properties": {
    "iso:country":"US",
    "sg:address":"1709 E Lincoln Rd",
    "sg:city":"Kokomo",
    "sg:classifiers":[
        {
            "category":"Travel",
            "subcategory":"Hotels & Motels",
            "type":"Entertainment"
        }
    ],
    "sg:phone":"+1 765 459 8001",
    "sg:postcode":"46902",
    "sg:province":"IN",
    "wof:name":"First City Hotel",
    "wof:placetype":"venue"
},
  "geometry": {"coordinates":[-86.112211,40.455191],"type":"Point"}
}