{
  "type": "Feature",
  "properties": {
    "addr:full":"1150 US Hwy 41 Schererville IN 46375",
    "addr:housenumber":"1150",
    "addr:postcode":"46375",
    "addr:street":"Us Hwy 41",
    "iso:country":"US",
    "sg:address":"1150 US Hwy 41",
    "sg:city":"Schererville",
    "sg:classifiers":[
        {
            "category":"Shopping",
            "subcategory":"Computers & Home Electronics",
            "type":"Retail Goods"
        }
    ],
    "sg:phone":"+1 219 865 9222",
    "sg:postcode":"46375",
    "sg:province":"IN",
    "sg:tags":[
        "equipment",
        "dealer"
    ],
    "wof:name":"Computer Renaissance",
    "wof:placetype":"venue"
},
  "geometry": {"coordinates":[-87.47119600000001,41.503151],"type":"Point"}
}