{
  "type": "Feature",
  "properties": {
    "iso:country":"US",
    "sg:address":"3440 Hancock Ridge Rd",
    "sg:city":"Martinsville",
    "sg:classifiers":[
        {
            "category":"Wholesale",
            "subcategory":"Groceries",
            "type":"Manufacturing & Wholesale Goods"
        }
    ],
    "sg:phone":"+1 765 537 9430",
    "sg:postcode":"46151",
    "sg:province":"IN",
    "sg:tags":[
        "honey"
    ],
    "sg:website":"www.huntershoneyfarm.com",
    "wof:name":"Hunter's Honey Farm",
    "wof:placetype":"venue"
},
  "geometry": {"coordinates":[-86.548154,39.475471],"type":"Point"}
}