{
  "type": "Feature",
  "properties": {
    "iso:country":"US",
    "sg:address":"530 Eastern Ave",
    "sg:city":"Shelbyville",
    "sg:classifiers":[
        {
            "category":"Building & Trades",
            "subcategory":"Construction",
            "type":"Services"
        }
    ],
    "sg:phone":"+1 317 392 1292",
    "sg:postcode":"46176",
    "sg:province":"IN",
    "sg:tags":[
        "general",
        "contractor"
    ],
    "wof:name":"Cord Brothers Inc",
    "wof:placetype":"venue"
},
  "geometry": {"coordinates":[-85.756395,39.517902],"type":"Point"}
}