{
  "type": "Feature",
  "properties": {
    "iso:country":"US",
    "sg:address":"3900 4th Pkwy",
    "sg:city":"Terre Haute",
    "sg:classifiers":[
        {
            "category":"Freight",
            "type":"Transportation"
        }
    ],
    "sg:phone":"+1 812 460 4856",
    "sg:postcode":"47804",
    "sg:province":"IN",
    "sg:tags":[
        "a",
        "contract",
        "carrier",
        "intrastate",
        "interstate",
        "common"
    ],
    "wof:name":"Prime America Freight Systems",
    "wof:placetype":"venue"
},
  "geometry": {"coordinates":[-87.358058,39.499149],"type":"Point"}
}