{
  "type": "Feature",
  "properties": {
    "iso:country":"US",
    "sg:address":"10427 Oak Valley Rd",
    "sg:city":"Fort Wayne",
    "sg:classifiers":[
        {
            "category":"Personal",
            "subcategory":"Beauty Salon",
            "type":"Services"
        }
    ],
    "sg:phone":"+1 260 482 2173",
    "sg:postcode":"46845",
    "sg:province":"IN",
    "sg:tags":[
        "shop"
    ],
    "wof:name":"Elite Visions",
    "wof:placetype":"venue"
},
  "geometry": {"coordinates":[-85.072846,41.180661],"type":"Point"}
}