{
  "type": "Feature",
  "properties": {
    "iso:country":"US",
    "sg:address":"8210 Windfall Ln",
    "sg:city":"Camby",
    "sg:classifiers":[
        {
            "category":"Restaurant",
            "type":"Food & Drink"
        }
    ],
    "sg:menulink":"http://www.allmenus.com/in/guilford/79397-pizza-hut/menu/",
    "sg:phone":"+1 317 856 9989",
    "sg:postcode":"46113",
    "sg:province":"IN",
    "sg:tags":[
        "american",
        "pizza"
    ],
    "wof:name":"Pizza Hut",
    "wof:placetype":"venue"
},
  "geometry": {"coordinates":[-86.33125200000001,39.643382],"type":"Point"}
}