{
  "type": "Feature",
  "properties": {
    "iso:country":"US",
    "sg:address":"1001 Main St",
    "sg:city":"Vincennes",
    "sg:classifiers":[
        {
            "category":"Manufacturing",
            "subcategory":"Printing",
            "type":"Manufacturing & Wholesale Goods"
        }
    ],
    "sg:phone":"+1 812 882 6203",
    "sg:postcode":"47591",
    "sg:province":"IN",
    "sg:tags":[
        "screen"
    ],
    "wof:name":"Screen Printing Plus",
    "wof:placetype":"venue"
},
  "geometry": {"coordinates":[-87.526293,38.673764],"type":"Point"}
}