{
  "type": "Feature",
  "properties": {
    "iso:country":"US",
    "sg:address":"202 5th St",
    "sg:city":"Laporte",
    "sg:classifiers":[
        {
            "category":"Retail",
            "subcategory":"Auto Repair",
            "type":"Services"
        }
    ],
    "sg:phone":"+1 219 362 1231",
    "sg:postcode":"46350",
    "sg:province":"IN",
    "sg:tags":[
        "repairing",
        "automobile"
    ],
    "wof:name":"Kendall's Service",
    "wof:placetype":"venue"
},
  "geometry": {"coordinates":[-86.721694,41.602846],"type":"Point"}
}