{
  "type": "Feature",
  "properties": {
    "iso:country":"US",
    "sg:address":"4134 E 500 S",
    "sg:city":"Kokomo",
    "sg:phone":"+1 765 453 3789",
    "sg:postcode":"46902",
    "sg:province":"IN",
    "sg:tags":[
        "farm",
        "corn",
        "soybean"
    ],
    "wof:name":"Joe Adair",
    "wof:placetype":"venue"
},
  "geometry": {"coordinates":[-85.93585899999999,40.406445],"type":"Point"}
}