{
  "type": "Feature",
  "properties": {
    "iso:country":"US",
    "sg:address":"2647 Waterfront Pkwy East Dr",
    "sg:city":"Indianapolis",
    "sg:classifiers":[
        {
            "category":"Professional",
            "subcategory":"Business Services",
            "type":"Services"
        }
    ],
    "sg:phone":"+1 317 472 3028",
    "sg:postcode":"46214",
    "sg:province":"IN",
    "sg:tags":[
        "appraiser"
    ],
    "wof:name":"Choice One",
    "wof:placetype":"venue"
},
  "geometry": {"coordinates":[-86.27957600000001,39.803211],"type":"Point"}
}