{
  "type": "Feature",
  "properties": {
    "iso:country":"US",
    "sg:address":"1447 E 5th St",
    "sg:city":"Connersville",
    "sg:classifiers":[
        {
            "category":"Farming",
            "subcategory":"Nursery",
            "type":"Manufacturing & Wholesale Goods"
        }
    ],
    "sg:phone":"+1 765 827 6400",
    "sg:postcode":"47331",
    "sg:province":"IN",
    "sg:tags":[
        "greenhouse"
    ],
    "wof:name":"Flower Depot",
    "wof:placetype":"venue"
},
  "geometry": {"coordinates":[-85.116207,39.639054],"type":"Point"}
}