{
  "type": "Feature",
  "properties": {
    "iso:country":"US",
    "sg:address":"604 W Berry St",
    "sg:city":"Fort Wayne",
    "sg:classifiers":[
        {
            "category":"Health Services",
            "subcategory":"Doctor",
            "type":"Services"
        }
    ],
    "sg:phone":"+1 260 423 1331",
    "sg:postcode":"46802",
    "sg:province":"IN",
    "sg:tags":[
        "physician",
        "surgeon"
    ],
    "wof:name":"Allen County Cardiology",
    "wof:placetype":"venue"
},
  "geometry": {"coordinates":[-85.148576,41.077973],"type":"Point"}
}