{
  "type": "Feature",
  "properties": {
    "iso:country":"US",
    "sg:address":"520 N Pendleton Ave",
    "sg:city":"Pendleton",
    "sg:classifiers":[
        {
            "category":"Food & Beverages",
            "subcategory":"Groceries & Convenience Stores",
            "type":"Retail Goods"
        }
    ],
    "sg:phone":"+1 765 778 3263",
    "sg:postcode":"46064",
    "sg:province":"IN",
    "sg:tags":[
        "grocer"
    ],
    "wof:name":"Lo Bill Foods",
    "wof:placetype":"venue"
},
  "geometry": {"coordinates":[-85.74507699999999,40.006376],"type":"Point"}
}