{
  "type": "Feature",
  "properties": {
    "addr:full":"8300 E 96th St Fishers IN 46038",
    "addr:housenumber":"8300",
    "addr:postcode":"46038",
    "addr:street":"E 96Th St",
    "iso:country":"US",
    "sg:address":"8300 E 96th St",
    "sg:city":"Fishers",
    "sg:classifiers":[
        {
            "category":"Banks & Credit Unions",
            "subcategory":"Bank",
            "type":"Services"
        }
    ],
    "sg:phone":"+1 317 595 9418",
    "sg:postcode":"46038",
    "sg:province":"IN",
    "wof:name":"Flagstar Bank",
    "wof:placetype":"venue"
},
  "geometry": {"coordinates":[-86.021896,39.927101],"type":"Point"}
}