{
  "type": "Feature",
  "properties": {
    "addr:full":"230 W 19th St Connersville IN 47331",
    "addr:housenumber":"230",
    "addr:postcode":"47331",
    "addr:street":"W 19Th St",
    "iso:country":"US",
    "sg:address":"230 W 19th St",
    "sg:city":"Connersville",
    "sg:classifiers":[
        {
            "category":"Health Services",
            "subcategory":"Doctor",
            "type":"Services"
        }
    ],
    "sg:phone":"+1 765 825 8000",
    "sg:postcode":"47331",
    "sg:province":"IN",
    "sg:tags":[
        "dentist"
    ],
    "wof:name":"David A Niemiec DDS",
    "wof:placetype":"venue"
},
  "geometry": {"coordinates":[-85.13078400000001,39.655345],"type":"Point"}
}