{
  "type": "Feature",
  "properties": {
    "iso:country":"US",
    "sg:address":"101 N Main St",
    "sg:city":"Monticello",
    "sg:classifiers":[
        {
            "category":"Government",
            "subcategory":"Office",
            "type":"Public Place"
        }
    ],
    "sg:phone":"+1 574 583 4866",
    "sg:postcode":"47960",
    "sg:province":"IN",
    "wof:name":"White County Custodian",
    "wof:placetype":"venue"
},
  "geometry": {"coordinates":[-86.76192399999999,40.745523],"type":"Point"}
}