{
  "type": "Feature",
  "properties": {
    "iso:country":"US",
    "sg:address":"2915 E State Blvd",
    "sg:city":"Fort Wayne",
    "sg:classifiers":[
        {
            "category":"Bars & Pubs",
            "type":"Food & Drink"
        }
    ],
    "sg:phone":"+1 260 482 2441",
    "sg:postcode":"46805",
    "sg:province":"IN",
    "wof:name":"North Star Bar",
    "wof:placetype":"venue"
},
  "geometry": {"coordinates":[-85.101261,41.09734],"type":"Point"}
}