{
  "type": "Feature",
  "properties": {
    "iso:country":"US",
    "sg:address":"13221 Iowa St",
    "sg:city":"Crown Point",
    "sg:classifiers":[
        {
            "category":"Building & Trades",
            "subcategory":"Construction",
            "type":"Services"
        }
    ],
    "sg:phone":"+1 219 663 6546",
    "sg:postcode":"46307",
    "sg:province":"IN",
    "sg:tags":[
        "roofing",
        "contractor"
    ],
    "wof:name":"Ryco Roofing Inc",
    "wof:placetype":"venue"
},
  "geometry": {"coordinates":[-87.306437,41.379889],"type":"Point"}
}