{
  "type": "Feature",
  "properties": {
    "addr:full":"4300 N County Line Rd E Delphi IN 47905",
    "addr:housenumber":"4300",
    "addr:postcode":"47905",
    "addr:street":"N County Line Rd E",
    "iso:country":"US",
    "sg:address":"4300 N County Line Rd E",
    "sg:city":"Delphi",
    "sg:phone":"+1 765 589 8374",
    "sg:postcode":"47905",
    "sg:province":"IN",
    "sg:tags":[
        "farm",
        "corn"
    ],
    "wof:name":"Jack Buck",
    "wof:placetype":"venue"
},
  "geometry": {"coordinates":[-86.694909,40.475471],"type":"Point"}
}