{
  "type": "Feature",
  "properties": {
    "addr:full":"128 N Railroad St E Monticello IN 47960",
    "addr:housenumber":"128",
    "addr:postcode":"47960",
    "addr:street":"N Railroad St E",
    "iso:country":"US",
    "sg:address":"128 N Railroad St E",
    "sg:city":"Monticello",
    "sg:classifiers":[
        {
            "category":"Retail",
            "subcategory":"Auto Repair",
            "type":"Services"
        }
    ],
    "sg:phone":"+1 574 583 7228",
    "sg:postcode":"47960",
    "sg:province":"IN",
    "sg:tags":[
        "muffler",
        "exhaust",
        "system"
    ],
    "wof:name":"Beck Muffler & Brake",
    "wof:placetype":"venue"
},
  "geometry": {"coordinates":[-86.76414699999999,40.745333],"type":"Point"}
}