{
  "type": "Feature",
  "properties": {
    "addr:full":"2411 Hobson Rd Fort Wayne IN 46805",
    "addr:housenumber":"2411",
    "addr:postcode":"46805",
    "addr:street":"Hobson Rd",
    "iso:country":"US",
    "sg:address":"2411 Hobson Rd",
    "sg:city":"Fort Wayne",
    "sg:classifiers":[
        {
            "category":"Personal",
            "subcategory":"Beauty Salon",
            "type":"Services"
        }
    ],
    "sg:phone":"+1 260 482 1902",
    "sg:postcode":"46805",
    "sg:province":"IN",
    "wof:name":"Hi-Tech Hair Design",
    "wof:placetype":"venue"
},
  "geometry": {"coordinates":[-85.098776,41.098182],"type":"Point"}
}