{
  "type": "Feature",
  "properties": {
    "iso:country":"US",
    "sg:address":"2865 E Dupont Rd",
    "sg:city":"Fort Wayne",
    "sg:classifiers":[
        {
            "category":"Professional",
            "type":"Services"
        }
    ],
    "sg:phone":"+1 260 490 2682",
    "sg:postcode":"46825",
    "sg:province":"IN",
    "sg:tags":[
        "establishment"
    ],
    "wof:name":"Convenant Capital LLC",
    "wof:placetype":"venue"
},
  "geometry": {"coordinates":[-85.1056,41.178852],"type":"Point"}
}