{
  "type": "Feature",
  "properties": {
    "iso:country":"US",
    "sg:address":"630 N Central Ave",
    "sg:city":"Connersville",
    "sg:classifiers":[
        {
            "category":"Banks & Credit Unions",
            "subcategory":"Bank",
            "type":"Services"
        }
    ],
    "sg:phone":"+1 765 825 5121",
    "sg:postcode":"47331",
    "sg:province":"IN",
    "sg:website":"www.heritagecb.com",
    "wof:name":"First Financial Bank",
    "wof:placetype":"venue"
},
  "geometry": {"coordinates":[-85.1384,39.642487],"type":"Point"}
}