{
  "type": "Feature",
  "properties": {
    "iso:country":"US",
    "sg:address":"1902 S Michigan St",
    "sg:city":"South Bend",
    "sg:classifiers":[
        {
            "category":"Retail",
            "subcategory":"Auto Repair",
            "type":"Services"
        }
    ],
    "sg:phone":"+1 574 288 8770",
    "sg:postcode":"46613",
    "sg:province":"IN",
    "sg:tags":[
        "repairing",
        "automobile"
    ],
    "wof:name":"Denny Moon's Autotech",
    "wof:placetype":"venue"
},
  "geometry": {"coordinates":[-86.249727,41.653854],"type":"Point"}
}