{
  "type": "Feature",
  "properties": {
    "iso:country":"US",
    "sg:address":"250 N Water St",
    "sg:city":"Franklin",
    "sg:classifiers":[
        {
            "category":"Home & Garden",
            "subcategory":"Building Materials",
            "type":"Retail Goods"
        }
    ],
    "sg:phone":"+1 317 738 0030",
    "sg:postcode":"46131",
    "sg:province":"IN",
    "sg:tags":[
        "glass",
        "window",
        "plate"
    ],
    "wof:name":"One Source Inc",
    "wof:placetype":"venue"
},
  "geometry": {"coordinates":[-86.05391899999999,39.48358],"type":"Point"}
}