{
  "type": "Feature",
  "properties": {
    "iso:country":"US",
    "sg:address":"2100 E Chicago Ave",
    "sg:city":"East Chicago",
    "sg:classifiers":[
        {
            "category":"Retail",
            "subcategory":"Auto Repair",
            "type":"Services"
        }
    ],
    "sg:phone":"+1 219 391 1810",
    "sg:postcode":"46312",
    "sg:province":"IN",
    "sg:tags":[
        "exhaust"
    ],
    "wof:name":"American Muffler Shop",
    "wof:placetype":"venue"
},
  "geometry": {"coordinates":[-87.452015,41.629189],"type":"Point"}
}