{
  "type": "Feature",
  "properties": {
    "iso:country":"US",
    "sg:address":"2306 E 44th St",
    "sg:city":"Indianapolis",
    "sg:classifiers":[
        {
            "category":"Home & Garden",
            "subcategory":"Furniture",
            "type":"Retail Goods"
        }
    ],
    "sg:phone":"+1 317 541 9511",
    "sg:postcode":"46205",
    "sg:province":"IN",
    "sg:tags":[
        "top",
        "counter"
    ],
    "wof:name":"Chemlleon Marble & Granite",
    "wof:placetype":"venue"
},
  "geometry": {"coordinates":[-86.123059,39.836622],"type":"Point"}
}