{
  "type": "Feature",
  "properties": {
    "iso:country":"US",
    "sg:address":"1002 NE 6th St",
    "sg:city":"Washington",
    "sg:classifiers":[
        {
            "category":"Organizations",
            "subcategory":"Religious Organization",
            "type":"Services"
        }
    ],
    "sg:phone":"+1 812 254 0950",
    "sg:postcode":"47501",
    "sg:province":"IN",
    "wof:name":"Good Shepherd Lutheran Church",
    "wof:placetype":"venue"
},
  "geometry": {"coordinates":[-87.169244,38.665906],"type":"Point"}
}