{
  "type": "Feature",
  "properties": {
    "addr:full":"111 Monument Cir Indianapolis IN 46204",
    "addr:housenumber":"111",
    "addr:postcode":"46204",
    "addr:street":"Monument Cir",
    "iso:country":"US",
    "sg:address":"111 Monument Cir",
    "sg:city":"Indianapolis",
    "sg:classifiers":[
        {
            "category":"Insurance",
            "subcategory":"Insurance Agent",
            "type":"Services"
        }
    ],
    "sg:phone":"+1 317 237 2222",
    "sg:postcode":"46204",
    "sg:province":"IN",
    "sg:website":"www.indydt.com",
    "wof:name":"Indianapolis Downtown Inc",
    "wof:placetype":"venue"
},
  "geometry": {"coordinates":[-86.15789599999999,39.769152],"type":"Point"}
}