{
  "type": "Feature",
  "properties": {
    "addr:full":"1722 S 500 E Union City IN 47394",
    "addr:housenumber":"1722;500 e",
    "addr:postcode":"47394",
    "addr:street":"S",
    "iso:country":"US",
    "sg:address":"1722 S 500 E",
    "sg:city":"Union City",
    "sg:phone":"+1 765 584 8500",
    "sg:postcode":"47394",
    "sg:province":"IN",
    "sg:tags":[
        "farm",
        "grain",
        "cash"
    ],
    "wof:name":"Noel Carpenter",
    "wof:placetype":"venue"
},
  "geometry": {"coordinates":[-84.882907,40.141945],"type":"Point"}
}