{
  "type": "Feature",
  "properties": {
    "iso:country":"US",
    "sg:address":"218 S 3rd St",
    "sg:city":"Elkhart",
    "sg:classifiers":[
        {
            "category":"Shopping",
            "type":"Retail Goods"
        }
    ],
    "sg:phone":"+1 574 293 4851",
    "sg:postcode":"46516",
    "sg:province":"IN",
    "sg:tags":[
        "hearing",
        "equipment",
        "supply",
        "merchandise",
        "impaired"
    ],
    "wof:name":"Hills Hr-More Hearing Aid Svc",
    "wof:placetype":"venue"
},
  "geometry": {"coordinates":[-85.97559200000001,41.685198],"type":"Point"}
}