{
  "type": "Feature",
  "properties": {
    "iso:country":"US",
    "sg:address":"1805 Cadillac Ct",
    "sg:city":"Kokomo",
    "sg:classifiers":[
        {
            "category":"Building & Trades",
            "subcategory":"Landscaping Services",
            "type":"Services"
        }
    ],
    "sg:phone":"+1 765 459 0648",
    "sg:postcode":"46902",
    "sg:province":"IN",
    "wof:name":"Higgins Lawn Care",
    "wof:placetype":"venue"
},
  "geometry": {"coordinates":[-86.103449,40.465661],"type":"Point"}
}