{
  "type": "Feature",
  "properties": {
    "iso:country":"US",
    "sg:address":"7101 Kremer Rd",
    "sg:city":"Evansville",
    "sg:classifiers":[
        {
            "category":"Shopping",
            "subcategory":"Gifts & Souvenirs",
            "type":"Retail Goods"
        }
    ],
    "sg:phone":"+1 812 423 3890",
    "sg:postcode":"47720",
    "sg:province":"IN",
    "sg:tags":[
        "shop"
    ],
    "sg:website":"www.differentthingsinc.com",
    "wof:name":"Different Things",
    "wof:placetype":"venue"
},
  "geometry": {"coordinates":[-87.621652,38.047773],"type":"Point"}
}