{
  "type": "Feature",
  "properties": {
    "iso:country":"US",
    "sg:address":"146 E Main St",
    "sg:city":"Nashville",
    "sg:classifiers":[
        {
            "category":"Food & Beverages",
            "subcategory":"Specialty",
            "type":"Retail Goods"
        }
    ],
    "sg:phone":"+1 812 988 9890",
    "sg:postcode":"47448",
    "sg:province":"IN",
    "sg:tags":[
        "health",
        "diet"
    ],
    "wof:name":"Health For U",
    "wof:placetype":"venue"
},
  "geometry": {"coordinates":[-86.245057,39.206991],"type":"Point"}
}