{
  "type": "Feature",
  "properties": {
    "iso:country":"US",
    "sg:address":"64 E Marion St",
    "sg:city":"Danville",
    "sg:classifiers":[
        {
            "category":"Manufacturing",
            "subcategory":"Printing",
            "type":"Manufacturing & Wholesale Goods"
        }
    ],
    "sg:phone":"+1 317 745 7535",
    "sg:postcode":"46122",
    "sg:province":"IN",
    "sg:tags":[
        "printer"
    ],
    "sg:website":"www.gotcs.com",
    "wof:name":"Bobbie's Tru-Color System",
    "wof:placetype":"venue"
},
  "geometry": {"coordinates":[-86.52330600000001,39.759938],"type":"Point"}
}