{
  "type": "Feature",
  "properties": {
    "addr:full":"4095 Pitkin Rd Martinsville IN 46151",
    "addr:housenumber":"4095",
    "addr:postcode":"46151",
    "addr:street":"Pitkin Rd",
    "iso:country":"US",
    "sg:address":"4095 Pitkin Rd",
    "sg:city":"Martinsville",
    "sg:classifiers":[
        {
            "category":"Building & Trades",
            "subcategory":"Construction",
            "type":"Services"
        }
    ],
    "sg:phone":"+1 765 349 1333",
    "sg:postcode":"46151",
    "sg:province":"IN",
    "sg:tags":[
        "contractor"
    ],
    "wof:name":"Jack & The Boys Custom Homes",
    "wof:placetype":"venue"
},
  "geometry": {"coordinates":[-86.493126,39.488631],"type":"Point"}
}