{
  "type": "Feature",
  "properties": {
    "iso:country":"US",
    "sg:address":"11016 US Hwy 50",
    "sg:city":"Dillsboro",
    "sg:classifiers":[
        {
            "category":"Manufacturing",
            "subcategory":"Pet Food",
            "type":"Manufacturing & Wholesale Goods"
        }
    ],
    "sg:phone":"+1 812 432 5267",
    "sg:postcode":"47018",
    "sg:province":"IN",
    "sg:tags":[
        "milling"
    ],
    "wof:name":"Laughery Valley Ag Co-Op Inc",
    "wof:placetype":"venue"
},
  "geometry": {"coordinates":[-85.031576,39.019897],"type":"Point"}
}