{
  "type": "Feature",
  "properties": {
    "iso:country":"US",
    "sg:address":"4577 W State Rd 56",
    "sg:city":"Scottsburg",
    "sg:classifiers":[
        {
            "category":"Travel",
            "subcategory":"Campground",
            "type":"Entertainment"
        }
    ],
    "sg:phone":"+1 812 752 4062",
    "sg:postcode":"47170",
    "sg:province":"IN",
    "wof:name":"Yogi Bear Jellystone-Raintree",
    "wof:placetype":"venue"
},
  "geometry": {"coordinates":[-85.862211,38.681598],"type":"Point"}
}