{
  "type": "Feature",
  "properties": {
    "iso:country":"US",
    "sg:address":"7310 W Morris St",
    "sg:city":"Indianapolis",
    "sg:classifiers":[
        {
            "category":"Banks & Credit Unions",
            "subcategory":"Bank",
            "type":"Services"
        }
    ],
    "sg:phone":"+1 317 248 9900",
    "sg:postcode":"46231",
    "sg:province":"IN",
    "wof:name":"All Seasons Federal CU",
    "wof:placetype":"venue"
},
  "geometry": {"coordinates":[-86.300796,39.749576],"type":"Point"}
}