{
  "type": "Feature",
  "properties": {
    "iso:country":"US",
    "sg:address":"3037 Pebble Brk",
    "sg:city":"Jeffersonville",
    "sg:classifiers":[
        {
            "category":"Food & Beverages",
            "subcategory":"Groceries & Convenience Stores",
            "type":"Retail Goods"
        }
    ],
    "sg:phone":"+1 812 590 3670",
    "sg:postcode":"47130",
    "sg:province":"IN",
    "sg:tags":[
        "chip",
        "potato"
    ],
    "wof:name":"Bettinger Potato Chips",
    "wof:placetype":"venue"
},
  "geometry": {"coordinates":[-85.73997300000001,38.31328],"type":"Point"}
}