{
  "type": "Feature",
  "properties": {
    "addr:full":"2301 Surrey Rd Jeffersonville IN 47130",
    "addr:housenumber":"2301",
    "addr:postcode":"47130",
    "addr:street":"Surrey Rd",
    "iso:country":"US",
    "sg:address":"2301 Surrey Rd",
    "sg:city":"Jeffersonville",
    "sg:classifiers":[
        {
            "category":"Building & Trades",
            "subcategory":"Construction",
            "type":"Services"
        }
    ],
    "sg:phone":"+1 502 550 9116",
    "sg:postcode":"47130",
    "sg:province":"IN",
    "sg:tags":[
        "contractor"
    ],
    "wof:name":"Mch Inc",
    "wof:placetype":"venue"
},
  "geometry": {"coordinates":[-85.685868,38.340611],"type":"Point"}
}