{
  "type": "Feature",
  "properties": {
    "iso:country":"US",
    "sg:address":"45 S Jefferson St",
    "sg:city":"Nashville",
    "sg:classifiers":[
        {
            "category":"Shopping",
            "subcategory":"Used Merchandise",
            "type":"Retail Goods"
        }
    ],
    "sg:phone":"+1 812 988 1448",
    "sg:postcode":"47448",
    "sg:province":"IN",
    "sg:tags":[
        "antique"
    ],
    "wof:name":"Lee's Antiques",
    "wof:placetype":"venue"
},
  "geometry": {"coordinates":[-86.248064,39.206953],"type":"Point"}
}