{
  "type": "Feature",
  "properties": {
    "iso:country":"US",
    "sg:address":"7734 Graham Rd",
    "sg:city":"Indianapolis",
    "sg:classifiers":[
        {
            "category":"Education",
            "subcategory":"Special Training",
            "type":"Public Place"
        }
    ],
    "sg:phone":"+1 317 845 1032",
    "sg:postcode":"46250",
    "sg:province":"IN",
    "sg:tags":[
        "tutoring"
    ],
    "wof:name":"Find A Way Learning Center",
    "wof:placetype":"venue"
},
  "geometry": {"coordinates":[-86.06974200000001,39.895096],"type":"Point"}
}