{
  "type": "Feature",
  "properties": {
    "iso:country":"US",
    "sg:address":"5343 Pearl Dr",
    "sg:city":"Evansville",
    "sg:classifiers":[
        {
            "category":"Banks & Credit Unions",
            "subcategory":"Bank",
            "type":"Services"
        }
    ],
    "sg:phone":"+1 812 423 3171",
    "sg:postcode":"47712",
    "sg:province":"IN",
    "wof:name":"Heritage Federal Credit Union",
    "wof:placetype":"venue"
},
  "geometry": {"coordinates":[-87.64260899999999,37.973999],"type":"Point"}
}