{
  "type": "Feature",
  "properties": {
    "iso:country":"US",
    "sg:address":"408 W 37th Ave",
    "sg:city":"Hobart",
    "sg:classifiers":[
        {
            "category":"Restaurant",
            "type":"Food & Drink"
        }
    ],
    "sg:phone":"+1 219 962 1589",
    "sg:postcode":"46342",
    "sg:province":"IN",
    "wof:name":"Mystery Pizza",
    "wof:placetype":"venue"
},
  "geometry": {"coordinates":[-87.271248,41.550821],"type":"Point"}
}