{
  "type": "Feature",
  "properties": {
    "iso:country":"US",
    "sg:address":"217 E Main St",
    "sg:city":"Brownsburg",
    "sg:classifiers":[
        {
            "category":"Personal",
            "subcategory":"Beauty Salon",
            "type":"Services"
        }
    ],
    "sg:phone":"+1 317 852 2887",
    "sg:postcode":"46112",
    "sg:province":"IN",
    "wof:name":"Cut Ups",
    "wof:placetype":"venue"
},
  "geometry": {"coordinates":[-86.394501,39.842278],"type":"Point"}
}