{
  "type": "Feature",
  "properties": {
    "addr:full":"2815 W 38th Ave Hobart IN 46342",
    "addr:housenumber":"2815",
    "addr:postcode":"46342",
    "addr:street":"W 38Th Ave",
    "iso:country":"US",
    "sg:address":"2815 W 38th Ave",
    "sg:city":"Hobart",
    "sg:classifiers":[
        {
            "category":"Restaurant",
            "type":"Food & Drink"
        }
    ],
    "sg:phone":"+1 219 947 0080",
    "sg:postcode":"46342",
    "sg:province":"IN",
    "sg:tags":[
        "shop",
        "coffee"
    ],
    "wof:name":"Brewed Awakening",
    "wof:placetype":"venue"
},
  "geometry": {"coordinates":[-87.29510500000001,41.549159],"type":"Point"}
}