{
  "type": "Feature",
  "properties": {
    "iso:country":"US",
    "sg:address":"301 E 11th St",
    "sg:city":"Jeffersonville",
    "sg:classifiers":[
        {
            "category":"Education",
            "subcategory":"School",
            "type":"Public Place"
        }
    ],
    "sg:phone":"+1 812 288 4821",
    "sg:postcode":"47130",
    "sg:province":"IN",
    "sg:website":"http://www.gcs.k12.in.us",
    "wof:name":"Greater Clark County School Corporation Administrative Offices",
    "wof:placetype":"venue"
},
  "geometry": {"coordinates":[-85.744499,38.28157],"type":"Point"}
}