{
  "type": "Feature",
  "properties": {
    "iso:country":"US",
    "sg:address":"3750 E 50 N",
    "sg:city":"Knox",
    "sg:classifiers":[
        {
            "category":"Building & Trades",
            "subcategory":"Construction",
            "type":"Services"
        }
    ],
    "sg:phone":"+1 574 772 4311",
    "sg:postcode":"46534",
    "sg:province":"IN",
    "sg:tags":[
        "culvert"
    ],
    "wof:name":"Shilling & Shilling Excavating",
    "wof:placetype":"venue"
},
  "geometry": {"coordinates":[-86.625517,41.309902],"type":"Point"}
}