{
  "type": "Feature",
  "properties": {
    "iso:country":"US",
    "sg:address":"6868 S 350 E",
    "sg:city":"Cutler",
    "sg:classifiers":[
        {
            "category":"Farming",
            "subcategory":"Farm",
            "type":"Manufacturing & Wholesale Goods"
        }
    ],
    "sg:phone":"+1 765 258 3431",
    "sg:postcode":"46920",
    "sg:province":"IN",
    "sg:tags":[
        "crop",
        "general"
    ],
    "wof:name":"Helen Pullen",
    "wof:placetype":"venue"
},
  "geometry": {"coordinates":[-86.458967,40.449044],"type":"Point"}
}