{
  "type": "Feature",
  "properties": {
    "addr:full":"425 N High St Muncie IN 47305",
    "addr:housenumber":"425",
    "addr:postcode":"47305",
    "addr:street":"N High St",
    "iso:country":"US",
    "sg:address":"425 N High St",
    "sg:city":"Muncie",
    "sg:classifiers":[
        {
            "category":"Professional",
            "subcategory":"Employment Agencies",
            "type":"Services"
        }
    ],
    "sg:phone":"+1 765 284 6395",
    "sg:postcode":"47305",
    "sg:province":"IN",
    "sg:tags":[
        "opportunity"
    ],
    "wof:name":"Manpower Temporary Svc",
    "wof:placetype":"venue"
},
  "geometry": {"coordinates":[-85.387754,40.195942],"type":"Point"}
}