{
  "type": "Feature",
  "properties": {
    "addr:full":"11563 N Co Rd 400 E Batesville IN 47037",
    "addr:housenumber":"11563",
    "addr:postcode":"47037",
    "addr:street":"N Co Rd 400 E",
    "iso:country":"US",
    "sg:address":"11563 N Co Rd 400 E",
    "sg:city":"Batesville",
    "sg:classifiers":[
        {
            "category":"Real Estate",
            "subcategory":"Real Estate Operator",
            "type":"Services"
        }
    ],
    "sg:phone":"+1 812 934 6354",
    "sg:postcode":"47037",
    "sg:province":"IN",
    "sg:tags":[
        "property",
        "lessor"
    ],
    "wof:name":"Hartman Trenching",
    "wof:placetype":"venue"
},
  "geometry": {"coordinates":[-85.188755,39.243043],"type":"Point"}
}