{
  "type": "Feature",
  "properties": {
    "iso:country":"US",
    "sg:address":"5901 Grape Rd",
    "sg:city":"Mishawaka",
    "sg:classifiers":[
        {
            "category":"Shopping",
            "subcategory":"Department Store",
            "type":"Retail Goods"
        }
    ],
    "sg:phone":"+1 574 273 3200",
    "sg:postcode":"46545",
    "sg:province":"IN",
    "sg:tags":[
        "shop"
    ],
    "sg:website":"www.vcds.com",
    "wof:name":"Value City Department Store",
    "wof:placetype":"venue"
},
  "geometry": {"coordinates":[-86.187741,41.713688],"type":"Point"}
}