{
  "type": "Feature",
  "properties": {
    "iso:country":"US",
    "sg:address":"4214 Hobson Rd",
    "sg:city":"Fort Wayne",
    "sg:classifiers":[
        {
            "category":"Health Services",
            "subcategory":"Health Practitioner",
            "type":"Services"
        }
    ],
    "sg:phone":"+1 260 486 5251",
    "sg:postcode":"46815",
    "sg:province":"IN",
    "sg:tags":[
        "psychologist"
    ],
    "wof:name":"Consulting & Counseling Assoc",
    "wof:placetype":"venue"
},
  "geometry": {"coordinates":[-85.099691,41.116755],"type":"Point"}
}