{
  "type": "Feature",
  "properties": {
    "iso:country":"US",
    "sg:address":"2859 Northpark Ave",
    "sg:city":"Huntington",
    "sg:classifiers":[
        {
            "category":"Shopping",
            "type":"Retail Goods"
        }
    ],
    "sg:phone":"+1 260 356 4000",
    "sg:postcode":"46750",
    "sg:province":"IN",
    "sg:tags":[
        "telephone",
        "cellular"
    ],
    "wof:name":"Huntington Communications",
    "wof:placetype":"venue"
},
  "geometry": {"coordinates":[-85.509224,40.901775],"type":"Point"}
}