{
  "type": "Feature",
  "properties": {
    "iso:country":"US",
    "sg:address":"10120 Coldwater Rd",
    "sg:city":"Fort Wayne",
    "sg:classifiers":[
        {
            "category":"Banks & Credit Unions",
            "subcategory":"Bank",
            "type":"Services"
        }
    ],
    "sg:phone":"+1 260 427 8000",
    "sg:postcode":"46825",
    "sg:province":"IN",
    "wof:name":"Bank One",
    "wof:placetype":"venue"
},
  "geometry": {"coordinates":[-85.13094,41.175252],"type":"Point"}
}