{
  "type": "Feature",
  "properties": {
    "iso:country":"US",
    "sg:address":"13028 Wicker Ave",
    "sg:city":"Cedar Lake",
    "sg:classifiers":[
        {
            "category":"Autos & Motor Vehicles",
            "subcategory":"Motorcycle Sales",
            "type":"Retail Goods"
        }
    ],
    "sg:phone":"+1 219 374 2242",
    "sg:postcode":"46303",
    "sg:province":"IN",
    "sg:tags":[
        "scooter"
    ],
    "wof:name":"Hypersports",
    "wof:placetype":"venue"
},
  "geometry": {"coordinates":[-87.470099,41.383341],"type":"Point"}
}