{
  "type": "Feature",
  "properties": {
    "iso:country":"US",
    "sg:address":"215 S Adams St",
    "sg:city":"Marion",
    "sg:classifiers":[
        {
            "category":"Professional",
            "subcategory":"Lawyer & Legal Services",
            "type":"Services"
        }
    ],
    "sg:phone":"+1 765 662 0475",
    "sg:postcode":"46952",
    "sg:province":"IN",
    "sg:tags":[
        "attorney"
    ],
    "wof:name":"Craig Persinger",
    "wof:placetype":"venue"
},
  "geometry": {"coordinates":[-85.658476,40.558946],"type":"Point"}
}