{
  "type": "Feature",
  "properties": {
    "iso:country":"US",
    "sg:address":"4680 S 300 W",
    "sg:city":"Marion",
    "sg:classifiers":[
        {
            "category":"Farming",
            "subcategory":"Farm",
            "type":"Manufacturing & Wholesale Goods"
        }
    ],
    "sg:phone":"+1 765 384 7656",
    "sg:postcode":"46953",
    "sg:province":"IN",
    "sg:tags":[
        "crop",
        "general"
    ],
    "wof:name":"Shinn John",
    "wof:placetype":"venue"
},
  "geometry": {"coordinates":[-85.72944699999999,40.484919],"type":"Point"}
}