{
  "type": "Feature",
  "properties": {
    "addr:full":"926 S 10th St Lafayette IN 47905",
    "addr:housenumber":"926",
    "addr:postcode":"47905",
    "addr:street":"S 10Th St",
    "iso:country":"US",
    "sg:address":"926 S 10th St",
    "sg:city":"Lafayette",
    "sg:classifiers":[
        {
            "category":"Social Services",
            "subcategory":"Adult Care",
            "type":"Services"
        }
    ],
    "sg:phone":"+1 765 423 4280",
    "sg:postcode":"47905",
    "sg:province":"IN",
    "sg:tags":[
        "home",
        "group"
    ],
    "wof:name":"REM Ind Inc",
    "wof:placetype":"venue"
},
  "geometry": {"coordinates":[-86.885251,40.406709],"type":"Point"}
}