{
  "type": "Feature",
  "properties": {
    "iso:country":"US",
    "sg:address":"2037 E Ireland Rd",
    "sg:city":"South Bend",
    "sg:classifiers":[
        {
            "category":"Insurance",
            "subcategory":"Insurance Agent",
            "type":"Services"
        }
    ],
    "sg:phone":"+1 574 232 6945",
    "sg:postcode":"46614",
    "sg:province":"IN",
    "wof:name":"Allstate Insurance",
    "wof:placetype":"venue"
},
  "geometry": {"coordinates":[-86.219176,41.629561],"type":"Point"}
}