{
  "type": "Feature",
  "properties": {
    "iso:country":"US",
    "sg:address":"830 E Main St",
    "sg:city":"Brownsburg",
    "sg:classifiers":[
        {
            "category":"Shopping",
            "subcategory":"Department Store",
            "type":"Retail Goods"
        }
    ],
    "sg:phone":"+1 317 858 1609",
    "sg:postcode":"46112",
    "sg:province":"IN",
    "sg:tags":[
        "shop"
    ],
    "wof:name":"Dollar General",
    "wof:placetype":"venue"
},
  "geometry": {"coordinates":[-86.38503,39.839396],"type":"Point"}
}