{
  "type": "Feature",
  "properties": {
    "iso:country":"US",
    "sg:address":"3010 N Shun Pike Rd",
    "sg:city":"Madison",
    "sg:classifiers":[
        {
            "category":"Wholesale",
            "subcategory":"Machinery & Supplies",
            "type":"Manufacturing & Wholesale Goods"
        }
    ],
    "sg:phone":"+1 812 265 1516",
    "sg:postcode":"47250",
    "sg:province":"IN",
    "sg:tags":[
        "equipment",
        "industrial"
    ],
    "wof:name":"Fastenal Co",
    "wof:placetype":"venue"
},
  "geometry": {"coordinates":[-85.405877,38.782618],"type":"Point"}
}