{
  "type": "Feature",
  "properties": {
    "iso:country":"US",
    "sg:address":"326 E Court Ave",
    "sg:city":"Jeffersonville",
    "sg:classifiers":[
        {
            "category":"Real Estate",
            "subcategory":"Real Estate Services",
            "type":"Services"
        }
    ],
    "sg:phone":"+1 812 282 1321",
    "sg:postcode":"47130",
    "sg:province":"IN",
    "sg:tags":[
        "company",
        "title"
    ],
    "wof:name":"Clark County Abstract & Title",
    "wof:placetype":"venue"
},
  "geometry": {"coordinates":[-85.739591,38.27546],"type":"Point"}
}