{
  "type": "Feature",
  "properties": {
    "iso:country":"US",
    "sg:address":"15907 Houk Rd",
    "sg:city":"Hoagland",
    "sg:phone":"+1 260 639 6538",
    "sg:postcode":"46745",
    "sg:province":"IN",
    "sg:tags":[
        "farm",
        "corn",
        "soybean"
    ],
    "wof:name":"Wayne Bultemeier",
    "wof:placetype":"venue"
},
  "geometry": {"coordinates":[-84.95897600000001,40.938722],"type":"Point"}
}