{
  "type": "Feature",
  "properties": {
    "iso:country":"US",
    "sg:address":"1125 W Beardsley Ave",
    "sg:city":"Elkhart",
    "sg:classifiers":[
        {
            "category":"Building & Trades",
            "subcategory":"Construction",
            "type":"Services"
        }
    ],
    "sg:phone":"+1 574 293 3624",
    "sg:postcode":"46514",
    "sg:province":"IN",
    "sg:tags":[
        "hanging",
        "contractor"
    ],
    "wof:name":"Toms Painting",
    "wof:placetype":"venue"
},
  "geometry": {"coordinates":[-85.99165000000001,41.692614],"type":"Point"}
}