{
  "type": "Feature",
  "properties": {
    "iso:country":"US",
    "sg:address":"310 Main St W",
    "sg:city":"Greenwood",
    "sg:classifiers":[
        {
            "category":"Communications",
            "subcategory":"Film & Video Production",
            "type":"Services"
        }
    ],
    "sg:phone":"+1 317 865 8810",
    "sg:postcode":"46142",
    "sg:province":"IN",
    "sg:tags":[
        "taping"
    ],
    "wof:name":"Dream Vision MP",
    "wof:placetype":"venue"
},
  "geometry": {"coordinates":[-86.109799,39.613704],"type":"Point"}
}