{
  "type": "Feature",
  "properties": {
    "iso:country":"US",
    "sg:address":"5383 W Barnwood Dr",
    "sg:city":"New Palestine",
    "sg:classifiers":[
        {
            "category":"Professional",
            "subcategory":"Management & Consulting",
            "type":"Services"
        }
    ],
    "sg:phone":"+1 317 861 5935",
    "sg:postcode":"46163",
    "sg:province":"IN",
    "sg:tags":[
        "consultant",
        "business"
    ],
    "sg:website":"www.bottomlineperformance.com",
    "wof:name":"Bottom Line Performance Inc",
    "wof:placetype":"venue"
},
  "geometry": {"coordinates":[-85.903869,39.731042],"type":"Point"}
}