{
  "type": "Feature",
  "properties": {
    "iso:country":"US",
    "sg:address":"53172 Chelle Ln",
    "sg:city":"Granger",
    "sg:classifiers":[
        {
            "category":"Real Estate",
            "subcategory":"Real Estate Agent",
            "type":"Services"
        }
    ],
    "sg:phone":"+1 574 247 0534",
    "sg:postcode":"46530",
    "sg:province":"IN",
    "sg:tags":[
        "appraiser"
    ],
    "wof:name":"Lighthouse Appraisals Inc",
    "wof:placetype":"venue"
},
  "geometry": {"coordinates":[-86.156124,41.720949],"type":"Point"}
}