{
  "type": "Feature",
  "properties": {
    "addr:full":"270 N Monroe St Mooresville IN 46158",
    "addr:housenumber":"270",
    "addr:postcode":"46158",
    "addr:street":"N Monroe St",
    "iso:country":"US",
    "sg:address":"270 N Monroe St",
    "sg:city":"Mooresville",
    "sg:classifiers":[
        {
            "category":"Shopping",
            "subcategory":"Bicycles & Sporting Goods",
            "type":"Retail Goods"
        },
        {
            "category":"Personal",
            "subcategory":"Sauna",
            "type":"Services"
        },
        {
            "category":"Sports & Exercise",
            "subcategory":"Swimming Pool",
            "type":"Entertainment"
        }
    ],
    "sg:phone":"+1 317 831 9770",
    "sg:postcode":"46158",
    "sg:province":"IN",
    "sg:tags":[
        "equipment",
        "supply"
    ],
    "wof:name":"Leisure Time Pools & Spas Inc",
    "wof:placetype":"venue"
},
  "geometry": {"coordinates":[-86.379696,39.610546],"type":"Point"}
}