{
  "type": "Feature",
  "properties": {
    "iso:country":"US",
    "sg:address":"5233 S Scatterfield Rd",
    "sg:city":"Anderson",
    "sg:classifiers":[
        {
            "category":"Restaurant",
            "type":"Food & Drink"
        }
    ],
    "sg:menulink":"http://www.allmenus.com/in/anderson/186247-mcdonalds/menu/",
    "sg:postcode":"46013",
    "sg:province":"IN",
    "sg:tags":[
        "burger",
        "american"
    ],
    "wof:name":"McDonald's",
    "wof:placetype":"venue"
},
  "geometry": {"coordinates":[-85.652953,40.062328],"type":"Point"}
}