{
  "type": "Feature",
  "properties": {
    "addr:full":"2706 E 900 N Laporte IN 46350",
    "addr:housenumber":"2706",
    "addr:postcode":"46350",
    "addr:street":"E 900 N",
    "iso:country":"US",
    "sg:address":"2706 E 900 N",
    "sg:city":"Laporte",
    "sg:classifiers":[
        {
            "category":"Building & Trades",
            "subcategory":"Construction",
            "type":"Services"
        }
    ],
    "sg:phone":"+1 219 778 4990",
    "sg:postcode":"46350",
    "sg:province":"IN",
    "sg:tags":[
        "general",
        "contractor"
    ],
    "wof:name":"Richard Knoll & Son Custom",
    "wof:placetype":"venue"
},
  "geometry": {"coordinates":[-86.65396,41.73821],"type":"Point"}
}