{
  "type": "Feature",
  "properties": {
    "iso:country":"US",
    "sg:address":"925 Main St",
    "sg:city":"New Haven",
    "sg:classifiers":[
        {
            "category":"Social Services",
            "type":"Services"
        }
    ],
    "sg:phone":"+1 260 449 7437",
    "sg:postcode":"46774",
    "sg:province":"IN",
    "sg:tags":[
        "probation"
    ],
    "wof:name":"Allen County Probation",
    "wof:placetype":"venue"
},
  "geometry": {"coordinates":[-85.017285,41.073252],"type":"Point"}
}