{
  "type": "Feature",
  "properties": {
    "iso:country":"US",
    "sg:address":"915 Lafayette St",
    "sg:city":"Fort Wayne",
    "sg:classifiers":[
        {
            "category":"Building & Trades",
            "subcategory":"Construction",
            "type":"Services"
        }
    ],
    "sg:phone":"+1 260 423 3577",
    "sg:postcode":"46802",
    "sg:province":"IN",
    "sg:tags":[
        "general",
        "contractor"
    ],
    "wof:name":"Hamilton Hunter Builders Inc",
    "wof:placetype":"venue"
},
  "geometry": {"coordinates":[-85.1342,41.078159],"type":"Point"}
}