{
  "type": "Feature",
  "properties": {
    "addr:full":"714 Broad Ripple Ave Indianapolis IN 46220",
    "addr:housenumber":"714",
    "addr:postcode":"46220",
    "addr:street":"Broad Ripple Ave",
    "iso:country":"US",
    "sg:address":"714 Broad Ripple Ave",
    "sg:city":"Indianapolis",
    "sg:classifiers":[
        {
            "category":"Banks & Credit Unions",
            "subcategory":"Bank",
            "type":"Services"
        }
    ],
    "sg:phone":"+1 317 254 3135",
    "sg:postcode":"46220",
    "sg:province":"IN",
    "wof:name":"First Indiana Bank",
    "wof:placetype":"venue"
},
  "geometry": {"coordinates":[-86.144919,39.869764],"type":"Point"}
}