{
  "type": "Feature",
  "properties": {
    "iso:country":"US",
    "sg:address":"100 N Colfax St",
    "sg:city":"Griffith",
    "sg:classifiers":[
        {
            "category":"Food & Beverages",
            "subcategory":"Liquor & Beverages",
            "type":"Retail Goods"
        }
    ],
    "sg:phone":"+1 219 922 8534",
    "sg:postcode":"46319",
    "sg:province":"IN",
    "wof:name":"Colfax Liquors Inc",
    "wof:placetype":"venue"
},
  "geometry": {"coordinates":[-87.413136,41.523921],"type":"Point"}
}