{
  "type": "Feature",
  "properties": {
    "iso:country":"US",
    "sg:address":"3490 S Co Rd 500 E",
    "sg:city":"Dupont",
    "sg:classifiers":[
        {
            "category":"Shopping",
            "subcategory":"Clothing, Apparel, & Fashions",
            "type":"Retail Goods"
        }
    ],
    "sg:phone":"+1 812 352 1557",
    "sg:postcode":"47231",
    "sg:province":"IN",
    "sg:tags":[
        "alteration"
    ],
    "wof:name":"Donna's Alterations & More",
    "wof:placetype":"venue"
},
  "geometry": {"coordinates":[-85.52019199999999,38.935364],"type":"Point"}
}