{
  "type": "Feature",
  "properties": {
    "iso:country":"US",
    "sg:address":"4931 S US Hwy 41",
    "sg:city":"Terre Haute",
    "sg:classifiers":[
        {
            "category":"Wholesale",
            "subcategory":"Farm Supplies",
            "type":"Manufacturing & Wholesale Goods"
        }
    ],
    "sg:phone":"+1 812 299 2161",
    "sg:postcode":"47802",
    "sg:province":"IN",
    "wof:name":"Tractor Supply Co",
    "wof:placetype":"venue"
},
  "geometry": {"coordinates":[-87.408365,39.406617],"type":"Point"}
}