{
  "type": "Feature",
  "properties": {
    "iso:country":"US",
    "sg:address":"217 McKinley Rd",
    "sg:city":"Jasper",
    "sg:classifiers":[
        {
            "category":"Home & Garden",
            "subcategory":"Hardware",
            "type":"Retail Goods"
        }
    ],
    "sg:phone":"+1 812 482 9348",
    "sg:postcode":"47546",
    "sg:province":"IN",
    "sg:tags":[
        "nut",
        "bolt"
    ],
    "wof:name":"Jasper Bolt & Screw Co Inc",
    "wof:placetype":"venue"
},
  "geometry": {"coordinates":[-86.945249,38.383731],"type":"Point"}
}