{
  "type": "Feature",
  "properties": {
    "iso:country":"US",
    "sg:address":"120 E 5th St",
    "sg:city":"Rochester",
    "sg:classifiers":[
        {
            "category":"Organizations",
            "subcategory":"Religious Organization",
            "type":"Services"
        }
    ],
    "sg:phone":"+1 574 223 5804",
    "sg:postcode":"46975",
    "sg:province":"IN",
    "sg:tags":[
        "church"
    ],
    "sg:website":"www.rtcol.com/~jdillinger",
    "wof:name":"Church Of Christ",
    "wof:placetype":"venue"
},
  "geometry": {"coordinates":[-86.215581,41.069466],"type":"Point"}
}