{
  "type": "Feature",
  "properties": {
    "iso:country":"US",
    "sg:address":"3300 W 3rd St",
    "sg:city":"Bloomington",
    "sg:classifiers":[
        {
            "category":"Restaurant",
            "type":"Food & Drink"
        }
    ],
    "sg:menulink":"http://www.allmenus.com/in/van-buren/159602-arbys/menu/",
    "sg:phone":"+1 812 334 1657",
    "sg:postcode":"47404",
    "sg:province":"IN",
    "sg:tags":[
        "sandwich",
        "salad",
        "burger",
        "soup",
        "american",
        "wrap"
    ],
    "wof:name":"Arby's",
    "wof:placetype":"venue"
},
  "geometry": {"coordinates":[-86.576356,39.164697],"type":"Point"}
}