{
  "type": "Feature",
  "properties": {
    "addr:full":"455 Roxbury Rd Valparaiso IN 46385",
    "addr:housenumber":"455",
    "addr:postcode":"46385",
    "addr:street":"Roxbury Rd",
    "iso:country":"US",
    "sg:address":"455 Roxbury Rd",
    "sg:city":"Valparaiso",
    "sg:classifiers":[
        {
            "category":"Professional",
            "subcategory":"Business Services",
            "type":"Services"
        }
    ],
    "sg:phone":"+1 219 548 3296",
    "sg:postcode":"46385",
    "sg:province":"IN",
    "wof:name":"Hoosier Teleprompter Co",
    "wof:placetype":"venue"
},
  "geometry": {"coordinates":[-87.152731,41.458482],"type":"Point"}
}