{
  "type": "Feature",
  "properties": {
    "iso:country":"US",
    "sg:address":"1015 W Oakdale Dr",
    "sg:city":"Fort Wayne",
    "sg:classifiers":[
        {
            "category":"Professional",
            "subcategory":"Computer Services",
            "type":"Services"
        }
    ],
    "sg:phone":"+1 260 456 9353",
    "sg:postcode":"46807",
    "sg:province":"IN",
    "sg:tags":[
        "prepackaged",
        "software"
    ],
    "wof:name":"Wallyware",
    "wof:placetype":"venue"
},
  "geometry": {"coordinates":[-85.150515,41.051982],"type":"Point"}
}