{
  "type": "Feature",
  "properties": {
    "iso:country":"US",
    "sg:address":"7504 Broadview Dr",
    "sg:city":"Indianapolis",
    "sg:classifiers":[
        {
            "category":"Professional",
            "subcategory":"Employment Agencies",
            "type":"Services"
        }
    ],
    "sg:phone":"+1 317 885 4426",
    "sg:postcode":"46227",
    "sg:province":"IN",
    "sg:tags":[
        "truck",
        "driver"
    ],
    "wof:name":"Expedite Recruiters LLC",
    "wof:placetype":"venue"
},
  "geometry": {"coordinates":[-86.106957,39.658929],"type":"Point"}
}