{
  "type": "Feature",
  "properties": {
    "iso:country":"US",
    "sg:address":"1426 W 29th St",
    "sg:city":"Indianapolis",
    "sg:classifiers":[
        {
            "category":"Social Services",
            "type":"Services"
        }
    ],
    "sg:phone":"+1 317 612 6804",
    "sg:postcode":"46208",
    "sg:province":"IN",
    "sg:tags":[
        "organization",
        "welfare"
    ],
    "wof:name":"Pace/Oar",
    "wof:placetype":"venue"
},
  "geometry": {"coordinates":[-86.19085099999999,39.808236],"type":"Point"}
}