{
  "type": "Feature",
  "properties": {
    "addr:full":"3613 S 18th St Lafayette IN 47909",
    "addr:housenumber":"3613",
    "addr:postcode":"47909",
    "addr:street":"S 18Th St",
    "iso:country":"US",
    "sg:address":"3613 S 18th St",
    "sg:city":"Lafayette",
    "sg:classifiers":[
        {
            "category":"Insurance",
            "subcategory":"Insurance Agent",
            "type":"Services"
        }
    ],
    "sg:phone":"+1 765 471 0660",
    "sg:postcode":"47909",
    "sg:province":"IN",
    "wof:name":"Teder Insurance",
    "wof:placetype":"venue"
},
  "geometry": {"coordinates":[-86.875848,40.365556],"type":"Point"}
}