{
  "type": "Feature",
  "properties": {
    "addr:full":"8242 Pickford Dr Indianapolis IN 46227",
    "addr:housenumber":"8242",
    "addr:postcode":"46227",
    "addr:street":"Pickford Dr",
    "iso:country":"US",
    "sg:address":"8242 Pickford Dr",
    "sg:city":"Indianapolis",
    "sg:classifiers":[
        {
            "category":"Building & Trades",
            "subcategory":"Plumbing",
            "type":"Services"
        }
    ],
    "sg:phone":"+1 317 881 2296",
    "sg:postcode":"46227",
    "sg:province":"IN",
    "sg:tags":[
        "plumbing",
        "contractor"
    ],
    "wof:name":"D W Bond Plumbing",
    "wof:placetype":"venue"
},
  "geometry": {"coordinates":[-86.112601,39.646764],"type":"Point"}
}