{
  "type": "Feature",
  "properties": {
    "iso:country":"US",
    "sg:address":"2843 Denison St",
    "sg:city":"Indianapolis",
    "sg:classifiers":[
        {
            "category":"Building & Trades",
            "subcategory":"Construction",
            "type":"Services"
        }
    ],
    "sg:phone":"+1 317 248 1054",
    "sg:postcode":"46241",
    "sg:province":"IN",
    "sg:tags":[
        "house"
    ],
    "wof:name":"Rodneys Home Repair",
    "wof:placetype":"venue"
},
  "geometry": {"coordinates":[-86.238362,39.723167],"type":"Point"}
}