{
  "type": "Feature",
  "properties": {
    "iso:country":"US",
    "sg:address":"310 Walnut St",
    "sg:city":"Lawrenceburg",
    "sg:classifiers":[
        {
            "category":"Wholesale",
            "subcategory":"Durable Goods & Equipment",
            "type":"Manufacturing & Wholesale Goods"
        }
    ],
    "sg:phone":"+1 812 537 4333",
    "sg:postcode":"47025",
    "sg:province":"IN",
    "sg:tags":[
        "importer"
    ],
    "wof:name":"Z Imports Of Sumeria",
    "wof:placetype":"venue"
},
  "geometry": {"coordinates":[-84.850891,39.095207],"type":"Point"}
}