{
  "type": "Feature",
  "properties": {
    "iso:country":"US",
    "sg:address":"1229 N Bluff Rd",
    "sg:city":"Greenwood",
    "sg:classifiers":[
        {
            "category":"Food & Beverages",
            "subcategory":"Groceries & Convenience Stores",
            "type":"Retail Goods"
        }
    ],
    "sg:phone":"+1 317 881 6601",
    "sg:postcode":"46142",
    "sg:province":"IN",
    "wof:name":"Big Foot Food Store",
    "wof:placetype":"venue"
},
  "geometry": {"coordinates":[-86.204615,39.634121],"type":"Point"}
}