{
  "type": "Feature",
  "properties": {
    "addr:full":"8271 S 100 E Fairmount IN 46928",
    "addr:housenumber":"8271;100 e",
    "addr:postcode":"46928",
    "addr:street":"S",
    "iso:country":"US",
    "sg:address":"8271 S 100 E",
    "sg:city":"Fairmount",
    "sg:classifiers":[
        {
            "category":"Farming",
            "subcategory":"Farm",
            "type":"Manufacturing & Wholesale Goods"
        }
    ],
    "sg:phone":"+1 765 948 5307",
    "sg:postcode":"46928",
    "sg:province":"IN",
    "wof:name":"Kelsay Farm",
    "wof:placetype":"venue"
},
  "geometry": {"coordinates":[-85.654053,40.427748],"type":"Point"}
}