{
  "type": "Feature",
  "properties": {
    "iso:country":"US",
    "sg:address":"1908 Unruh Ct",
    "sg:city":"New Albany",
    "sg:classifiers":[
        {
            "category":"Insurance",
            "subcategory":"Insurance Agent",
            "type":"Services"
        }
    ],
    "sg:phone":"+1 812 945 1665",
    "sg:postcode":"47150",
    "sg:province":"IN",
    "wof:name":"Auto-Owners Insurance Co",
    "wof:placetype":"venue"
},
  "geometry": {"coordinates":[-85.81692700000001,38.324008],"type":"Point"}
}