{
  "type": "Feature",
  "properties": {
    "addr:full":"601 S Lake St Gary IN 46403",
    "addr:housenumber":"601",
    "addr:postcode":"46403",
    "addr:street":"S Lake St Gary",
    "iso:country":"US",
    "sg:address":"601 S Lake St",
    "sg:city":"Gary",
    "sg:classifiers":[
        {
            "category":"Shopping",
            "type":"Retail Goods"
        }
    ],
    "sg:phone":"+1 219 938 0281",
    "sg:postcode":"46403",
    "sg:province":"IN",
    "sg:tags":[
        "enforcement",
        "law",
        "supply"
    ],
    "wof:name":"Community Oriented Police",
    "wof:placetype":"venue"
},
  "geometry": {"coordinates":[-87.26716999999999,41.599779],"type":"Point"}
}