{
  "type": "Feature",
  "properties": {
    "iso:country":"US",
    "sg:address":"445 E 206th St",
    "sg:city":"Sheridan",
    "sg:classifiers":[
        {
            "category":"Organizations",
            "subcategory":"Religious Organization",
            "type":"Services"
        }
    ],
    "sg:phone":"+1 317 758 5698",
    "sg:postcode":"46069",
    "sg:province":"IN",
    "wof:name":"Hortonville Meeting Church",
    "wof:placetype":"venue"
},
  "geometry": {"coordinates":[-86.149951,40.086028],"type":"Point"}
}