{
  "type": "Feature",
  "properties": {
    "addr:full":"203 E Main St Delphi IN 46923",
    "addr:housenumber":"203",
    "addr:postcode":"46923",
    "addr:street":"E Main St",
    "iso:country":"US",
    "sg:address":"203 E Main St",
    "sg:city":"Delphi",
    "sg:classifiers":[
        {
            "category":"Autos & Motor Vehicles",
            "subcategory":"Automobile Sales",
            "type":"Retail Goods"
        }
    ],
    "sg:phone":"+1 765 564 6444",
    "sg:postcode":"46923",
    "sg:province":"IN",
    "sg:tags":[
        "car",
        "dealer"
    ],
    "wof:name":"Mc Carty Motors",
    "wof:placetype":"venue"
},
  "geometry": {"coordinates":[-86.67240099999999,40.58681],"type":"Point"}
}