{
  "type": "Feature",
  "properties": {
    "iso:country":"US",
    "sg:address":"711 E Thompson Rd",
    "sg:city":"Indianapolis",
    "sg:classifiers":[
        {
            "category":"Bars & Pubs",
            "type":"Food & Drink"
        }
    ],
    "sg:phone":"+1 317 783 4646",
    "sg:postcode":"46227",
    "sg:province":"IN",
    "wof:name":"Carson Pub",
    "wof:placetype":"venue"
},
  "geometry": {"coordinates":[-86.144086,39.693325],"type":"Point"}
}