{
  "type": "Feature",
  "properties": {
    "iso:country":"US",
    "sg:address":"378 S Mountain Rd",
    "sg:city":"Hillsboro",
    "sg:classifiers":[
        {
            "category":"Building & Trades",
            "subcategory":"Cleaning & Sanitation",
            "type":"Services"
        }
    ],
    "sg:phone":"+1 765 234 2570",
    "sg:postcode":"47949",
    "sg:province":"IN",
    "sg:tags":[
        "fireplace",
        "chimney"
    ],
    "wof:name":"Sugar Creek Chimney Sweep",
    "wof:placetype":"venue"
},
  "geometry": {"coordinates":[-87.092026,40.110986],"type":"Point"}
}