{
  "type": "Feature",
  "properties": {
    "iso:country":"US",
    "sg:address":"508 Marion Ave",
    "sg:city":"Arcadia",
    "sg:classifiers":[
        {
            "category":"Government",
            "subcategory":"Fire Station",
            "type":"Public Place"
        }
    ],
    "sg:phone":"+1 317 984 3443",
    "sg:postcode":"46030",
    "sg:province":"IN",
    "sg:tags":[
        "department"
    ],
    "wof:name":"Jackson Township Fire Dept",
    "wof:placetype":"venue"
},
  "geometry": {"coordinates":[-86.01656,40.17224],"type":"Point"}
}