{
  "type": "Feature",
  "properties": {
    "iso:country":"US",
    "sg:address":"11901 Covington Rd",
    "sg:city":"Fort Wayne",
    "sg:classifiers":[
        {
            "category":"Real Estate",
            "subcategory":"Real Estate Agent",
            "type":"Services"
        }
    ],
    "sg:phone":"+1 260 625 5840",
    "sg:postcode":"46814",
    "sg:province":"IN",
    "wof:name":"George Huber",
    "wof:placetype":"venue"
},
  "geometry": {"coordinates":[-85.300373,41.059434],"type":"Point"}
}