{
  "type": "Feature",
  "properties": {
    "iso:country":"US",
    "sg:address":"12220 N Meridian St",
    "sg:city":"Carmel",
    "sg:classifiers":[
        {
            "category":"Professional",
            "subcategory":"Engineering",
            "type":"Services"
        },
        {
            "category":"Professional",
            "subcategory":"Management & Consulting",
            "type":"Services"
        }
    ],
    "sg:phone":"+1 317 569 8880",
    "sg:postcode":"46032",
    "sg:province":"IN",
    "sg:tags":[
        "consultant",
        "ecological",
        "engineer",
        "environmental"
    ],
    "wof:name":"Haley & Aldrich",
    "wof:placetype":"venue"
},
  "geometry": {"coordinates":[-86.158379,39.966438],"type":"Point"}
}