{
  "type": "Feature",
  "properties": {
    "iso:country":"US",
    "sg:address":"130 S Main St",
    "sg:city":"Kendallville",
    "sg:classifiers":[
        {
            "category":"Professional",
            "subcategory":"Accounting & Tax Preparation",
            "type":"Services"
        }
    ],
    "sg:phone":"+1 260 347 0144",
    "sg:postcode":"46755",
    "sg:province":"IN",
    "sg:tags":[
        "return",
        "filing"
    ],
    "wof:name":"Dick's Tax Svc",
    "wof:placetype":"venue"
},
  "geometry": {"coordinates":[-85.265738,41.44351],"type":"Point"}
}