{
  "type": "Feature",
  "properties": {
    "iso:country":"US",
    "sg:address":"10291 N Murphy Rd",
    "sg:city":"Brazil",
    "sg:classifiers":[
        {
            "category":"Building & Trades",
            "subcategory":"Plumbing",
            "type":"Services"
        }
    ],
    "sg:phone":"+1 812 443 3031",
    "sg:postcode":"47834",
    "sg:province":"IN",
    "sg:tags":[
        "conditioning",
        "air",
        "system",
        "contractor"
    ],
    "wof:name":"Brazil Heating & Electric Co",
    "wof:placetype":"venue"
},
  "geometry": {"coordinates":[-87.108036,39.53781],"type":"Point"}
}