{
  "type": "Feature",
  "properties": {
    "iso:country":"US",
    "sg:address":"1309 Donnybrook Dr",
    "sg:city":"Carmel",
    "sg:classifiers":[
        {
            "category":"Professional",
            "subcategory":"Management & Consulting",
            "type":"Services"
        }
    ],
    "sg:phone":"+1 317 575 1858",
    "sg:postcode":"46032",
    "sg:province":"IN",
    "sg:tags":[
        "business"
    ],
    "wof:name":"McConnell Terri Mary Kay",
    "wof:placetype":"venue"
},
  "geometry": {"coordinates":[-86.135119,39.953279],"type":"Point"}
}