{
  "type": "Feature",
  "properties": {
    "iso:country":"US",
    "sg:address":"1192 A St NE",
    "sg:city":"Linton",
    "sg:classifiers":[
        {
            "category":"Autos & Motor Vehicles",
            "subcategory":"Motorcycle Sales",
            "type":"Retail Goods"
        }
    ],
    "sg:phone":"+1 812 847 4588",
    "sg:postcode":"47441",
    "sg:province":"IN",
    "sg:tags":[
        "scooter"
    ],
    "wof:name":"Brothers Custom Cycle",
    "wof:placetype":"venue"
},
  "geometry": {"coordinates":[-87.153796,39.036645],"type":"Point"}
}