{
  "type": "Feature",
  "properties": {
    "iso:country":"US",
    "sg:address":"1301 Johnson St",
    "sg:city":"Elkhart",
    "sg:classifiers":[
        {
            "category":"Insurance",
            "subcategory":"Insurance Agent",
            "type":"Services"
        }
    ],
    "sg:phone":"+1 574 264 7634",
    "sg:postcode":"46514",
    "sg:province":"IN",
    "wof:name":"Perry Uselman Insurance",
    "wof:placetype":"venue"
},
  "geometry": {"coordinates":[-85.966101,41.701225],"type":"Point"}
}