{
  "type": "Feature",
  "properties": {
    "iso:country":"US",
    "sg:address":"2553 W Hillside Dr",
    "sg:city":"Greenfield",
    "sg:classifiers":[
        {
            "category":"Building & Trades",
            "subcategory":"Construction",
            "type":"Services"
        }
    ],
    "sg:phone":"+1 317 462 8406",
    "sg:postcode":"46140",
    "sg:province":"IN",
    "sg:tags":[
        "general",
        "contractor"
    ],
    "wof:name":"Chas O Wells Cement Contractor",
    "wof:placetype":"venue"
},
  "geometry": {"coordinates":[-85.851898,39.775967],"type":"Point"}
}