{
  "type": "Feature",
  "properties": {
    "iso:country":"US",
    "sg:address":"3845 E 82nd St",
    "sg:city":"Indianapolis",
    "sg:classifiers":[
        {
            "category":"Retail",
            "subcategory":"Repair Shop",
            "type":"Services"
        }
    ],
    "sg:phone":"+1 317 849 6839",
    "sg:postcode":"46240",
    "sg:province":"IN",
    "sg:tags":[
        "upholsterer"
    ],
    "wof:name":"Market Pointe Interiors",
    "wof:placetype":"venue"
},
  "geometry": {"coordinates":[-86.104021,39.909875],"type":"Point"}
}