{
  "type": "Feature",
  "properties": {
    "iso:country":"US",
    "sg:address":"30814 Oakbrook Dr",
    "sg:city":"Granger",
    "sg:classifiers":[
        {
            "category":"Building & Trades",
            "subcategory":"Cleaning & Sanitation",
            "type":"Services"
        }
    ],
    "sg:phone":"+1 574 596 4676",
    "sg:postcode":"46530",
    "sg:province":"IN",
    "sg:tags":[
        "ventilating",
        "system"
    ],
    "wof:name":"A-1 Duct Cleaning",
    "wof:placetype":"venue"
},
  "geometry": {"coordinates":[-86.05933,41.719916],"type":"Point"}
}