{
  "type": "Feature",
  "properties": {
    "addr:full":"2 N 9th St Noblesville IN 46060",
    "addr:housenumber":"2",
    "addr:postcode":"46060",
    "addr:street":"N 9Th St",
    "iso:country":"US",
    "sg:address":"2 N 9th St",
    "sg:city":"Noblesville",
    "sg:classifiers":[
        {
            "category":"Real Estate",
            "subcategory":"Real Estate Services",
            "type":"Services"
        }
    ],
    "sg:phone":"+1 317 773 0587",
    "sg:postcode":"46060",
    "sg:province":"IN",
    "sg:tags":[
        "company",
        "title"
    ],
    "wof:name":"Title Search Svc",
    "wof:placetype":"venue"
},
  "geometry": {"coordinates":[-86.01349399999999,40.04654],"type":"Point"}
}