{
  "type": "Feature",
  "properties": {
    "iso:country":"US",
    "sg:address":"111 Library Ln",
    "sg:city":"Valparaiso",
    "sg:classifiers":[
        {
            "category":"Shopping",
            "subcategory":"Catalog Store",
            "type":"Retail Goods"
        }
    ],
    "sg:phone":"+1 219 464 4499",
    "sg:postcode":"46383",
    "sg:province":"IN",
    "sg:tags":[
        "book"
    ],
    "wof:name":"Business First Books",
    "wof:placetype":"venue"
},
  "geometry": {"coordinates":[-87.058679,41.468877],"type":"Point"}
}