{
  "type": "Feature",
  "properties": {
    "addr:full":"1011 N Meridian St Marion IN 46952",
    "addr:housenumber":"1011",
    "addr:postcode":"46952",
    "addr:street":"N Meridian St",
    "iso:country":"US",
    "sg:address":"1011 N Meridian St",
    "sg:city":"Marion",
    "sg:classifiers":[
        {
            "category":"Bars & Pubs",
            "type":"Food & Drink"
        }
    ],
    "sg:phone":"+1 765 662 0753",
    "sg:postcode":"46952",
    "sg:province":"IN",
    "wof:name":"Christopher's",
    "wof:placetype":"venue"
},
  "geometry": {"coordinates":[-85.655339,40.573065],"type":"Point"}
}