{
  "type": "Feature",
  "properties": {
    "iso:country":"US",
    "sg:address":"132 N Main St",
    "sg:city":"Monticello",
    "sg:classifiers":[
        {
            "category":"Communications",
            "subcategory":"Radio Station",
            "type":"Services"
        }
    ],
    "sg:phone":"+1 574 583 8121",
    "sg:postcode":"47960",
    "sg:province":"IN",
    "sg:tags":[
        "company",
        "broadcasting"
    ],
    "sg:website":"www.wmrsradio.com",
    "wof:name":"WMRS",
    "wof:placetype":"venue"
},
  "geometry": {"coordinates":[-86.76199699999999,40.745133],"type":"Point"}
}