{
  "type": "Feature",
  "properties": {
    "iso:country":"US",
    "sg:address":"301 W Main St",
    "sg:city":"Muncie",
    "sg:classifiers":[
        {
            "category":"Professional",
            "subcategory":"Lawyer & Legal Services",
            "type":"Services"
        }
    ],
    "sg:phone":"+1 765 282 2274",
    "sg:postcode":"47305",
    "sg:province":"IN",
    "sg:tags":[
        "attorney"
    ],
    "wof:name":"Alan K Wilson",
    "wof:placetype":"venue"
},
  "geometry": {"coordinates":[-85.38987899999999,40.193732],"type":"Point"}
}