{
  "type": "Feature",
  "properties": {
    "addr:full":"202 N Howard St Oxford IN 47971",
    "addr:housenumber":"202",
    "addr:postcode":"47971",
    "addr:street":"N Howard St",
    "iso:country":"US",
    "sg:address":"202 N Howard St",
    "sg:city":"Oxford",
    "sg:classifiers":[
        {
            "category":"Restaurant",
            "type":"Food & Drink"
        }
    ],
    "sg:phone":"+1 765 385 5355",
    "sg:postcode":"47971",
    "sg:province":"IN",
    "wof:name":"Pizza King",
    "wof:placetype":"venue"
},
  "geometry": {"coordinates":[-87.249088,40.521913],"type":"Point"}
}