{
  "type": "Feature",
  "properties": {
    "addr:full":"120 E 8th St Anderson IN 46016",
    "addr:housenumber":"120",
    "addr:postcode":"46016",
    "addr:street":"E 8Th St",
    "iso:country":"US",
    "sg:address":"120 E 8th St",
    "sg:city":"Anderson",
    "sg:classifiers":[
        {
            "category":"Government",
            "subcategory":"Office",
            "type":"Public Place"
        }
    ],
    "sg:phone":"+1 765 648 6050",
    "sg:postcode":"46016",
    "sg:province":"IN",
    "sg:tags":[
        "village"
    ],
    "wof:name":"Anderson Information Systems",
    "wof:placetype":"venue"
},
  "geometry": {"coordinates":[-85.677086,40.107985],"type":"Point"}
}