{
  "type": "Feature",
  "properties": {
    "iso:country":"US",
    "sg:address":"120 N Main St",
    "sg:city":"Columbia City",
    "sg:classifiers":[
        {
            "category":"Food & Beverages",
            "subcategory":"Specialty",
            "type":"Retail Goods"
        }
    ],
    "sg:phone":"+1 260 248 4111",
    "sg:postcode":"46725",
    "sg:province":"IN",
    "sg:tags":[
        "tea",
        "coffee"
    ],
    "wof:name":"Brew Ha",
    "wof:placetype":"venue"
},
  "geometry": {"coordinates":[-85.48833,41.157911],"type":"Point"}
}