{
  "type": "Feature",
  "properties": {
    "iso:country":"US",
    "sg:address":"3635 State Rd 38 E",
    "sg:city":"Lafayette",
    "sg:classifiers":[
        {
            "category":"Building & Trades",
            "subcategory":"Construction",
            "type":"Services"
        }
    ],
    "sg:phone":"+1 765 447 4109",
    "sg:postcode":"47905",
    "sg:province":"IN",
    "sg:tags":[
        "designer",
        "dealer",
        "pool",
        "swimming"
    ],
    "wof:name":"Aquazone Inc",
    "wof:placetype":"venue"
},
  "geometry": {"coordinates":[-86.848124,40.393925],"type":"Point"}
}