{
  "type": "Feature",
  "properties": {
    "iso:country":"US",
    "sg:address":"619 N Pennsylvania St",
    "sg:city":"Indianapolis",
    "sg:classifiers":[
        {
            "category":"Real Estate",
            "subcategory":"Real Estate Agent",
            "type":"Services"
        }
    ],
    "sg:phone":"+1 317 687 2747",
    "sg:postcode":"46204",
    "sg:province":"IN",
    "sg:tags":[
        "appraiser"
    ],
    "wof:name":"Mitchell Appraisals Inc",
    "wof:placetype":"venue"
},
  "geometry": {"coordinates":[-86.155861,39.77581],"type":"Point"}
}