{
  "type": "Feature",
  "properties": {
    "iso:country":"US",
    "sg:address":"305 US Hwy 27 S",
    "sg:city":"Berne",
    "sg:classifiers":[
        {
            "category":"Health Services",
            "subcategory":"Optometrist",
            "type":"Services"
        }
    ],
    "sg:phone":"+1 260 589 2020",
    "sg:postcode":"46711",
    "sg:province":"IN",
    "wof:name":"Lehman & Bixler Optometrists",
    "wof:placetype":"venue"
},
  "geometry": {"coordinates":[-84.956063,40.655783],"type":"Point"}
}