{
  "type": "Feature",
  "properties": {
    "addr:full":"2804 Mount Vernon Ave Evansville IN 47712",
    "addr:housenumber":"2804",
    "addr:postcode":"47712",
    "addr:street":"Mount Vernon Ave",
    "iso:country":"US",
    "sg:address":"2804 Mount Vernon Ave",
    "sg:city":"Evansville",
    "sg:classifiers":[
        {
            "category":"Shopping",
            "subcategory":"Tobacco",
            "type":"Retail Goods"
        }
    ],
    "sg:phone":"+1 812 962 0469",
    "sg:postcode":"47712",
    "sg:province":"IN",
    "sg:tags":[
        "cigarette",
        "cigar",
        "dealer"
    ],
    "wof:name":"Express Smokes",
    "wof:placetype":"venue"
},
  "geometry": {"coordinates":[-87.609588,37.983222],"type":"Point"}
}