{
  "type": "Feature",
  "properties": {
    "iso:country":"US",
    "sg:address":"126 S 3rd St",
    "sg:city":"Lafayette",
    "sg:classifiers":[
        {
            "category":"Organizations",
            "subcategory":"Non-profit Organization",
            "type":"Services"
        }
    ],
    "sg:phone":"+1 765 428 8800",
    "sg:postcode":"47901",
    "sg:province":"IN",
    "sg:tags":[
        "information",
        "alcoholism",
        "treatment"
    ],
    "wof:name":"Rebecca Sullivan",
    "wof:placetype":"venue"
},
  "geometry": {"coordinates":[-86.894244,40.416422],"type":"Point"}
}