{
  "type": "Feature",
  "properties": {
    "iso:country":"US",
    "sg:address":"101 N East St",
    "sg:city":"Crown Point",
    "sg:classifiers":[
        {
            "category":"Government",
            "subcategory":"Office",
            "type":"Public Place"
        }
    ],
    "sg:phone":"+1 219 662 3290",
    "sg:postcode":"46307",
    "sg:province":"IN",
    "sg:tags":[
        "village"
    ],
    "sg:website":"www.crownpoint.in.gov",
    "wof:name":"Crown Point Special Events Ofc",
    "wof:placetype":"venue"
},
  "geometry": {"coordinates":[-87.363182,41.419084],"type":"Point"}
}