{
  "type": "Feature",
  "properties": {
    "addr:full":"2200 N Wayne St Angola IN 46703",
    "addr:housenumber":"2200",
    "addr:postcode":"46703",
    "addr:street":"N Wayne St",
    "iso:country":"US",
    "sg:address":"2200 N Wayne St",
    "sg:city":"Angola",
    "sg:classifiers":[
        {
            "category":"Banks & Credit Unions",
            "subcategory":"Bank",
            "type":"Services"
        }
    ],
    "sg:phone":"+1 260 665 3114",
    "sg:postcode":"46703",
    "sg:province":"IN",
    "sg:tags":[
        "financing"
    ],
    "wof:name":"American General Finance Inc",
    "wof:placetype":"venue"
},
  "geometry": {"coordinates":[-84.99953499999999,41.656017],"type":"Point"}
}