{
  "type": "Feature",
  "properties": {
    "iso:country":"US",
    "sg:address":"9642 Apple Tree Ln",
    "sg:city":"Indianapolis",
    "sg:phone":"+1 317 890 9086",
    "sg:postcode":"46235",
    "sg:province":"IN",
    "wof:name":"Road Runner Road Service",
    "wof:placetype":"venue"
},
  "geometry": {"coordinates":[-85.99734599999999,39.845181],"type":"Point"}
}