{
  "type": "Feature",
  "properties": {
    "iso:country":"US",
    "sg:address":"216 W Broadway St",
    "sg:city":"Fortville",
    "sg:classifiers":[
        {
            "category":"Retail",
            "subcategory":"Veterinary Services",
            "type":"Services"
        }
    ],
    "sg:phone":"+1 317 485 6090",
    "sg:postcode":"46040",
    "sg:province":"IN",
    "sg:tags":[
        "veterinarian"
    ],
    "wof:name":"Fortville Veterinary Clinic",
    "wof:placetype":"venue"
},
  "geometry": {"coordinates":[-85.848817,39.930815],"type":"Point"}
}