{
  "type": "Feature",
  "properties": {
    "iso:country":"US",
    "sg:address":"8526 Bay Colony Dr",
    "sg:city":"Indianapolis",
    "sg:classifiers":[
        {
            "category":"Sports & Exercise",
            "subcategory":"Race Track",
            "type":"Entertainment"
        }
    ],
    "sg:phone":"+1 317 298 7035",
    "sg:postcode":"46234",
    "sg:province":"IN",
    "wof:name":"Robbie Buhl Racing Inc",
    "wof:placetype":"venue"
},
  "geometry": {"coordinates":[-86.31534499999999,39.850101],"type":"Point"}
}