{
  "type": "Feature",
  "properties": {
    "iso:country":"US",
    "sg:address":"1400 25th St",
    "sg:city":"Columbus",
    "sg:classifiers":[
        {
            "category":"Education",
            "subcategory":"School",
            "type":"Public Place"
        }
    ],
    "sg:phone":"+1 812 376 4431",
    "sg:postcode":"47201",
    "sg:province":"IN",
    "wof:name":"Columbus North High School",
    "wof:placetype":"venue"
},
  "geometry": {"coordinates":[-85.909734,39.222974],"type":"Point"}
}