{
  "type": "Feature",
  "properties": {
    "addr:full":"14327 US Hwy 20 Middlebury IN 46540",
    "addr:housenumber":"14327",
    "addr:postcode":"46540",
    "addr:street":"Us Hwy 20",
    "iso:country":"US",
    "sg:address":"14327 US Hwy 20",
    "sg:city":"Middlebury",
    "sg:classifiers":[
        {
            "category":"Building & Trades",
            "subcategory":"Landscaping Services",
            "type":"Services"
        }
    ],
    "sg:phone":"+1 574 825 8688",
    "sg:postcode":"46540",
    "sg:province":"IN",
    "sg:tags":[
        "tree"
    ],
    "wof:name":"Michiana Tree Movers",
    "wof:placetype":"venue"
},
  "geometry": {"coordinates":[-85.741106,41.668156],"type":"Point"}
}