{
  "type": "Feature",
  "properties": {
    "addr:full":"1207 S State Rd 57 Washington IN 47501",
    "addr:housenumber":"1207;57",
    "addr:postcode":"47501",
    "addr:street":"S State Rd",
    "iso:country":"US",
    "sg:address":"1207 S State Rd 57",
    "sg:city":"Washington",
    "sg:classifiers":[
        {
            "category":"Restaurant",
            "type":"Food & Drink"
        }
    ],
    "sg:phone":"+1 812 254 7152",
    "sg:postcode":"47501",
    "sg:province":"IN",
    "wof:name":"Mi Pueblo Mexican Restaurant",
    "wof:placetype":"venue"
},
  "geometry": {"coordinates":[-87.173536,38.645766],"type":"Point"}
}