{
  "type": "Feature",
  "properties": {
    "iso:country":"US",
    "sg:address":"14 E Main St",
    "sg:city":"Flora",
    "sg:classifiers":[
        {
            "category":"Manufacturing",
            "subcategory":"Printing",
            "type":"Manufacturing & Wholesale Goods"
        }
    ],
    "sg:phone":"+1 574 967 4135",
    "sg:postcode":"46929",
    "sg:province":"IN",
    "sg:tags":[
        "newspaper"
    ],
    "wof:name":"Carroll County Comet",
    "wof:placetype":"venue"
},
  "geometry": {"coordinates":[-86.523684,40.548183],"type":"Point"}
}