{
  "type": "Feature",
  "properties": {
    "addr:full":"110 E Main St Washington IN 47501",
    "addr:housenumber":"110",
    "addr:postcode":"47501",
    "addr:street":"E Main St",
    "iso:country":"US",
    "sg:address":"110 E Main St",
    "sg:city":"Washington",
    "sg:classifiers":[
        {
            "category":"Insurance",
            "subcategory":"Insurance Agent",
            "type":"Services"
        }
    ],
    "sg:phone":"+1 812 254 5565",
    "sg:postcode":"47501",
    "sg:province":"IN",
    "wof:name":"State Farm Insurance",
    "wof:placetype":"venue"
},
  "geometry": {"coordinates":[-87.174363,38.657005],"type":"Point"}
}