{
  "type": "Feature",
  "properties": {
    "iso:country":"US",
    "sg:address":"1156 E Co Rd 800 N",
    "sg:city":"Pittsboro",
    "sg:classifiers":[
        {
            "category":"Professional",
            "subcategory":"Advertising",
            "type":"Services"
        }
    ],
    "sg:phone":"+1 317 892 4900",
    "sg:postcode":"46149",
    "sg:province":"IN",
    "wof:name":"Indiana Outdoor Advertising",
    "wof:placetype":"venue"
},
  "geometry": {"coordinates":[-86.50430299999999,39.879108],"type":"Point"}
}