{
  "type": "Feature",
  "properties": {
    "iso:country":"US",
    "sg:address":"2020 Fairfield Ave",
    "sg:city":"Fort Wayne",
    "sg:classifiers":[
        {
            "category":"Home & Garden",
            "subcategory":"Furniture",
            "type":"Retail Goods"
        }
    ],
    "sg:phone":"+1 260 744 1572",
    "sg:postcode":"46802",
    "sg:province":"IN",
    "wof:name":"Joe's Furniture",
    "wof:placetype":"venue"
},
  "geometry": {"coordinates":[-85.145368,41.067099],"type":"Point"}
}