{
  "type": "Feature",
  "properties": {
    "iso:country":"US",
    "sg:address":"400 S 5th St",
    "sg:city":"Richmond",
    "sg:classifiers":[
        {
            "category":"Retail",
            "subcategory":"Self-service Laundry",
            "type":"Services"
        }
    ],
    "sg:phone":"+1 765 935 4345",
    "sg:postcode":"47374",
    "sg:province":"IN",
    "wof:name":"Coin-A-Matic",
    "wof:placetype":"venue"
},
  "geometry": {"coordinates":[-84.895955,39.823429],"type":"Point"}
}