{
  "type": "Feature",
  "properties": {
    "iso:country":"US",
    "sg:address":"8021 Durban Dr",
    "sg:city":"Fort Wayne",
    "sg:classifiers":[
        {
            "category":"Recreation",
            "type":"Entertainment"
        }
    ],
    "sg:phone":"+1 260 747 0324",
    "sg:postcode":"46819",
    "sg:province":"IN",
    "sg:tags":[
        "parks"
    ],
    "wof:name":"Avalon Summer Sports Club",
    "wof:placetype":"venue"
},
  "geometry": {"coordinates":[-85.159578,41.011397],"type":"Point"}
}