{
  "type": "Feature",
  "properties": {
    "iso:country":"US",
    "sg:address":"8039 Burch Park Dr",
    "sg:city":"Evansville",
    "sg:classifiers":[
        {
            "category":"Manufacturing",
            "subcategory":"Tools & Machinery",
            "type":"Manufacturing & Wholesale Goods"
        }
    ],
    "sg:phone":"+1 812 867 2494",
    "sg:postcode":"47725",
    "sg:province":"IN",
    "sg:tags":[
        "die",
        "maker"
    ],
    "wof:name":"Triplet Tool & Die Co",
    "wof:placetype":"venue"
},
  "geometry": {"coordinates":[-87.53768100000001,38.052931],"type":"Point"}
}