{
  "type": "Feature",
  "properties": {
    "iso:country":"US",
    "sg:address":"3204 Lower Huntington Rd",
    "sg:city":"Fort Wayne",
    "sg:classifiers":[
        {
            "category":"Building & Trades",
            "subcategory":"Construction",
            "type":"Services"
        }
    ],
    "sg:phone":"+1 260 747 7570",
    "sg:postcode":"46809",
    "sg:province":"IN",
    "sg:tags":[
        "product",
        "asphalt"
    ],
    "wof:name":"Bunn Inc",
    "wof:placetype":"venue"
},
  "geometry": {"coordinates":[-85.180262,41.018619],"type":"Point"}
}