{
  "type": "Feature",
  "properties": {
    "addr:full":"935 E Hanna Ave Indianapolis IN 46227",
    "addr:housenumber":"935",
    "addr:postcode":"46227",
    "addr:street":"E Hanna Ave",
    "iso:country":"US",
    "sg:address":"935 E Hanna Ave",
    "sg:city":"Indianapolis",
    "sg:classifiers":[
        {
            "category":"Shopping",
            "subcategory":"Shoes",
            "type":"Retail Goods"
        }
    ],
    "sg:phone":"+1 317 783 2442",
    "sg:postcode":"46227",
    "sg:province":"IN",
    "wof:name":"Red Wing Shoe Store",
    "wof:placetype":"venue"
},
  "geometry": {"coordinates":[-86.147907,39.707861],"type":"Point"}
}