{
  "type": "Feature",
  "properties": {
    "addr:full":"1002 Wishard Blvd Indianapolis IN 46202",
    "addr:housenumber":"1002",
    "addr:postcode":"46202",
    "addr:street":"Wishard Blvd",
    "iso:country":"US",
    "sg:address":"1002 Wishard Blvd",
    "sg:city":"Indianapolis",
    "sg:classifiers":[
        {
            "category":"Health Services",
            "subcategory":"Doctor",
            "type":"Services"
        }
    ],
    "sg:phone":"+1 317 692 2363",
    "sg:postcode":"46202",
    "sg:province":"IN",
    "sg:tags":[
        "physician",
        "surgeon"
    ],
    "sg:website":"www.iumg.com",
    "wof:name":"Pediatrics Clinical Practice",
    "wof:placetype":"venue"
},
  "geometry": {"coordinates":[-86.174927,39.778751],"type":"Point"}
}