{
  "type": "Feature",
  "properties": {
    "addr:full":"401 E Walnut St Owensville IN 47665",
    "addr:housenumber":"401",
    "addr:postcode":"47665",
    "addr:street":"E Walnut St",
    "iso:country":"US",
    "sg:address":"401 E Walnut St",
    "sg:city":"Owensville",
    "sg:classifiers":[
        {
            "category":"Restaurant",
            "type":"Food & Drink"
        }
    ],
    "sg:phone":"+1 812 724 2199",
    "sg:postcode":"47665",
    "sg:province":"IN",
    "wof:name":"Winner's Circle Pizza & Pasta",
    "wof:placetype":"venue"
},
  "geometry": {"coordinates":[-87.687353,38.269377],"type":"Point"}
}