{
  "type": "Feature",
  "properties": {
    "iso:country":"US",
    "sg:address":"7763 E 4th St",
    "sg:city":"Attica",
    "sg:classifiers":[
        {
            "category":"Organizations",
            "subcategory":"Religious Organization",
            "type":"Services"
        }
    ],
    "sg:phone":"+1 765 762 2992",
    "sg:postcode":"47918",
    "sg:province":"IN",
    "wof:name":"Riverview United Methodist",
    "wof:placetype":"venue"
},
  "geometry": {"coordinates":[-87.17229,40.338164],"type":"Point"}
}