{
  "type": "Feature",
  "properties": {
    "iso:country":"US",
    "sg:address":"5012 E 62nd St",
    "sg:city":"Indianapolis",
    "sg:classifiers":[
        {
            "category":"Wholesale",
            "subcategory":"Fruits & Vegetables",
            "type":"Manufacturing & Wholesale Goods"
        }
    ],
    "sg:phone":"+1 317 252 4900",
    "sg:postcode":"46220",
    "sg:province":"IN",
    "wof:name":"Tom Lange Co Inc",
    "wof:placetype":"venue"
},
  "geometry": {"coordinates":[-86.085123,39.86874],"type":"Point"}
}