{
  "type": "Feature",
  "properties": {
    "iso:country":"US",
    "sg:address":"1700 N Ewing St",
    "sg:city":"Seymour",
    "sg:classifiers":[
        {
            "category":"Education",
            "subcategory":"School",
            "type":"Public Place"
        }
    ],
    "sg:phone":"+1 812 522 5621",
    "sg:postcode":"47274",
    "sg:province":"IN",
    "wof:name":"Redding Elementary School",
    "wof:placetype":"venue"
},
  "geometry": {"coordinates":[-85.890523,38.974986],"type":"Point"}
}