{
  "type": "Feature",
  "properties": {
    "iso:country":"US",
    "sg:address":"953 N Co Rd 735 W",
    "sg:city":"Greensburg",
    "sg:classifiers":[
        {
            "category":"Organizations",
            "subcategory":"Non-profit Organization",
            "type":"Services"
        }
    ],
    "sg:phone":"+1 812 663 2445",
    "sg:postcode":"47240",
    "sg:province":"IN",
    "sg:tags":[
        "action",
        "agency",
        "community"
    ],
    "wof:name":"Milford Town Hall",
    "wof:placetype":"venue"
},
  "geometry": {"coordinates":[-85.618649,39.349962],"type":"Point"}
}