{
  "type": "Feature",
  "properties": {
    "iso:country":"US",
    "sg:address":"29 N Monroe St",
    "sg:city":"Williamsport",
    "sg:classifiers":[
        {
            "category":"Government",
            "subcategory":"Office",
            "type":"Public Place"
        }
    ],
    "sg:phone":"+1 765 762 3257",
    "sg:postcode":"47993",
    "sg:province":"IN",
    "sg:tags":[
        "city"
    ],
    "wof:name":"Williamsport Town Hall",
    "wof:placetype":"venue"
},
  "geometry": {"coordinates":[-87.293877,40.287125],"type":"Point"}
}