{
  "type": "Feature",
  "properties": {
    "addr:full":"2 NW 18th St Richmond IN 47374",
    "addr:housenumber":"2",
    "addr:postcode":"47374",
    "addr:street":"Nw 18Th St",
    "iso:country":"US",
    "sg:address":"2 NW 18th St",
    "sg:city":"Richmond",
    "sg:classifiers":[
        {
            "category":"Banks & Credit Unions",
            "subcategory":"Bank",
            "type":"Services"
        }
    ],
    "sg:phone":"+1 765 935 4831",
    "sg:postcode":"47374",
    "sg:province":"IN",
    "wof:name":"Bank One",
    "wof:placetype":"venue"
},
  "geometry": {"coordinates":[-84.926935,39.830267],"type":"Point"}
}