{
  "type": "Feature",
  "properties": {
    "iso:country":"US",
    "sg:address":"30013 US Hwy 20",
    "sg:city":"Elkhart",
    "sg:classifiers":[
        {
            "category":"Shopping",
            "subcategory":"Bicycles & Sporting Goods",
            "type":"Retail Goods"
        }
    ],
    "sg:phone":"+1 574 296 2881",
    "sg:postcode":"46514",
    "sg:province":"IN",
    "sg:tags":[
        "equipment",
        "golf",
        "supply"
    ],
    "wof:name":"Nick's Golf Ctr",
    "wof:placetype":"venue"
},
  "geometry": {"coordinates":[-86.045953,41.688773],"type":"Point"}
}