{
  "type": "Feature",
  "properties": {
    "iso:country":"US",
    "sg:address":"107 Water St",
    "sg:city":"Plymouth",
    "sg:classifiers":[
        {
            "category":"Retail",
            "subcategory":"Repair Shop",
            "type":"Services"
        }
    ],
    "sg:phone":"+1 574 936 4265",
    "sg:postcode":"46563",
    "sg:province":"IN",
    "sg:tags":[
        "instrument",
        "musical"
    ],
    "wof:name":"J R Music Svc",
    "wof:placetype":"venue"
},
  "geometry": {"coordinates":[-86.307979,41.34086],"type":"Point"}
}