{
  "type": "Feature",
  "properties": {
    "iso:country":"US",
    "sg:address":"102 W Lincoln Ave",
    "sg:city":"Goshen",
    "sg:classifiers":[
        {
            "category":"Professional",
            "subcategory":"Management & Consulting",
            "type":"Services"
        }
    ],
    "sg:phone":"+1 574 535 1002",
    "sg:postcode":"46526",
    "sg:province":"IN",
    "sg:tags":[
        "development",
        "economic",
        "agency"
    ],
    "wof:name":"Economic Development Corp",
    "wof:placetype":"venue"
},
  "geometry": {"coordinates":[-85.83530500000001,41.586356],"type":"Point"}
}