{
  "type": "Feature",
  "properties": {
    "iso:country":"US",
    "sg:address":"4100 S Co Rd 50 E",
    "sg:city":"Clay City",
    "sg:classifiers":[
        {
            "category":"Retail",
            "subcategory":"Veterinary Services",
            "type":"Services"
        }
    ],
    "sg:phone":"+1 812 939 2748",
    "sg:postcode":"47841",
    "sg:province":"IN",
    "sg:tags":[
        "veterinarian"
    ],
    "wof:name":"Tucker Veterinary Clinic",
    "wof:placetype":"venue"
},
  "geometry": {"coordinates":[-87.100675,39.327041],"type":"Point"}
}