{
  "type": "Feature",
  "properties": {
    "iso:country":"US",
    "sg:address":"2619 E Robby Dr",
    "sg:city":"Warsaw",
    "sg:classifiers":[
        {
            "category":"Professional",
            "subcategory":"Accounting & Tax Preparation",
            "type":"Services"
        }
    ],
    "sg:phone":"+1 574 269 4539",
    "sg:postcode":"46580",
    "sg:province":"IN",
    "sg:tags":[
        "return"
    ],
    "wof:name":"Ed Christner Income Tax Svc",
    "wof:placetype":"venue"
},
  "geometry": {"coordinates":[-85.792832,41.22137],"type":"Point"}
}