{
  "type": "Feature",
  "properties": {
    "addr:full":"1030 N Berwick Ave Indianapolis IN 46222",
    "addr:housenumber":"1030",
    "addr:postcode":"46222",
    "addr:street":"N Berwick Ave",
    "iso:country":"US",
    "sg:address":"1030 N Berwick Ave",
    "sg:city":"Indianapolis",
    "sg:classifiers":[
        {
            "category":"Shopping",
            "subcategory":"Gifts & Souvenirs",
            "type":"Retail Goods"
        }
    ],
    "sg:phone":"+1 317 264 8643",
    "sg:postcode":"46222",
    "sg:province":"IN",
    "wof:name":"Avon",
    "wof:placetype":"venue"
},
  "geometry": {"coordinates":[-86.218524,39.781752],"type":"Point"}
}