{
  "type": "Feature",
  "properties": {
    "iso:country":"US",
    "sg:address":"15580 Herriman Blvd",
    "sg:city":"Noblesville",
    "sg:classifiers":[
        {
            "category":"Home & Garden",
            "subcategory":"Home Furnishings",
            "type":"Retail Goods"
        }
    ],
    "sg:phone":"+1 317 770 6020",
    "sg:postcode":"46060",
    "sg:province":"IN",
    "sg:tags":[
        "fireplace"
    ],
    "wof:name":"Indiana Fireplace Systems",
    "wof:placetype":"venue"
},
  "geometry": {"coordinates":[-86.00422,40.015157],"type":"Point"}
}