{
  "type": "Feature",
  "properties": {
    "iso:country":"US",
    "sg:address":"19035 Hand Rd",
    "sg:city":"Huntertown",
    "sg:classifiers":[
        {
            "category":"Building & Trades",
            "subcategory":"Construction",
            "type":"Services"
        }
    ],
    "sg:phone":"+1 260 637 8249",
    "sg:postcode":"46748",
    "sg:province":"IN",
    "sg:tags":[
        "house"
    ],
    "wof:name":"McClurg Construction Inc",
    "wof:placetype":"venue"
},
  "geometry": {"coordinates":[-85.211356,41.258875],"type":"Point"}
}