{
  "type": "Feature",
  "properties": {
    "iso:country":"US",
    "sg:address":"204 E Broadway St",
    "sg:city":"Loogootee",
    "sg:classifiers":[
        {
            "category":"Retail",
            "subcategory":"Auto Repair",
            "type":"Services"
        }
    ],
    "sg:phone":"+1 812 295 3209",
    "sg:postcode":"47553",
    "sg:province":"IN",
    "sg:tags":[
        "repairing",
        "automobile"
    ],
    "wof:name":"Muffler Menders Auto Repair",
    "wof:placetype":"venue"
},
  "geometry": {"coordinates":[-86.910872,38.676226],"type":"Point"}
}