{
  "type": "Feature",
  "properties": {
    "iso:country":"US",
    "sg:address":"14425 Leo Rd",
    "sg:city":"Leo",
    "sg:classifiers":[
        {
            "category":"Insurance",
            "subcategory":"Insurance Agent",
            "type":"Services"
        }
    ],
    "sg:phone":"+1 260 627 0172",
    "sg:postcode":"46765",
    "sg:province":"IN",
    "wof:name":"State Farm Insurance",
    "wof:placetype":"venue"
},
  "geometry": {"coordinates":[-85.01504300000001,41.217453],"type":"Point"}
}