{
  "type": "Feature",
  "properties": {
    "iso:country":"US",
    "sg:address":"1300 N Pennsylvania St",
    "sg:city":"Indianapolis",
    "sg:classifiers":[
        {
            "category":"Professional",
            "subcategory":"Computer Services",
            "type":"Services"
        }
    ],
    "sg:phone":"+1 317 822 8230",
    "sg:postcode":"46202",
    "sg:province":"IN",
    "sg:website":"www.dbisp.net",
    "wof:name":"D B Group",
    "wof:placetype":"venue"
},
  "geometry": {"coordinates":[-86.15577999999999,39.785742],"type":"Point"}
}