{
  "type": "Feature",
  "properties": {
    "addr:full":"8449 Sand Point Way Indianapolis IN 46240",
    "addr:housenumber":"8449",
    "addr:postcode":"46240",
    "addr:street":"Sand Point Way",
    "iso:country":"US",
    "sg:address":"8449 Sand Point Way",
    "sg:city":"Indianapolis",
    "sg:phone":"+1 317 251 6853",
    "sg:postcode":"46240",
    "sg:province":"IN",
    "sg:tags":[
        "fixture",
        "store"
    ],
    "wof:name":"Indianapolis Store Fixtures Co",
    "wof:placetype":"venue"
},
  "geometry": {"coordinates":[-86.112078,39.910608],"type":"Point"}
}