{
  "type": "Feature",
  "properties": {
    "iso:country":"US",
    "sg:address":"65 State Rd 5",
    "sg:city":"Shipshewana",
    "sg:classifiers":[
        {
            "category":"Retail",
            "subcategory":"Auto Repair",
            "type":"Services"
        }
    ],
    "sg:phone":"+1 260 768 3282",
    "sg:postcode":"46565",
    "sg:province":"IN",
    "sg:tags":[
        "parts",
        "electrical"
    ],
    "wof:name":"Better Bilt Strter Alternators",
    "wof:placetype":"venue"
},
  "geometry": {"coordinates":[-85.579804,41.633756],"type":"Point"}
}