{
  "type": "Feature",
  "properties": {
    "addr:full":"604 E 2nd St Bloomington IN 47401",
    "addr:housenumber":"604",
    "addr:postcode":"47401",
    "addr:street":"E 2Nd St",
    "iso:country":"US",
    "sg:address":"604 E 2nd St",
    "sg:city":"Bloomington",
    "sg:classifiers":[
        {
            "category":"Manufacturing",
            "subcategory":"Printing",
            "type":"Manufacturing & Wholesale Goods"
        }
    ],
    "sg:phone":"+1 812 332 3006",
    "sg:postcode":"47401",
    "sg:province":"IN",
    "sg:tags":[
        "screen",
        "advertising",
        "specialty"
    ],
    "wof:name":"Image Boxers",
    "wof:placetype":"venue"
},
  "geometry": {"coordinates":[-86.52596,39.161263],"type":"Point"}
}