{
  "type": "Feature",
  "properties": {
    "iso:country":"US",
    "sg:address":"1912 W 23rd Ave",
    "sg:city":"Gary",
    "sg:classifiers":[
        {
            "category":"Education",
            "subcategory":"School",
            "type":"Public Place"
        }
    ],
    "sg:phone":"+1 219 977 2116",
    "sg:postcode":"46404",
    "sg:province":"IN",
    "wof:name":"Benjamin Banneker Elem School",
    "wof:placetype":"venue"
},
  "geometry": {"coordinates":[-87.360267,41.577022],"type":"Point"}
}