{
  "type": "Feature",
  "properties": {
    "iso:country":"US",
    "sg:address":"222 E Ohio St",
    "sg:city":"Indianapolis",
    "sg:classifiers":[
        {
            "category":"Insurance",
            "subcategory":"Insurance Agent",
            "type":"Services"
        }
    ],
    "sg:phone":"+1 317 580 5900",
    "sg:postcode":"46204",
    "sg:province":"IN",
    "wof:name":"Indianapolis Twisters",
    "wof:placetype":"venue"
},
  "geometry": {"coordinates":[-86.152567,39.769714],"type":"Point"}
}