{
  "type": "Feature",
  "properties": {
    "iso:country":"US",
    "sg:address":"2569 W Co Rd 300 N",
    "sg:city":"Connersville",
    "sg:classifiers":[
        {
            "category":"Professional",
            "subcategory":"Computer Services",
            "type":"Services"
        }
    ],
    "sg:phone":"+1 765 825 6499",
    "sg:postcode":"47331",
    "sg:province":"IN",
    "sg:tags":[
        "related"
    ],
    "wof:name":"Davis Material Control Inc",
    "wof:placetype":"venue"
},
  "geometry": {"coordinates":[-85.187516,39.686574],"type":"Point"}
}