{
  "type": "Feature",
  "properties": {
    "iso:country":"US",
    "sg:address":"5106 Pollack Ave",
    "sg:city":"Evansville",
    "sg:classifiers":[
        {
            "category":"Building & Trades",
            "subcategory":"Construction",
            "type":"Services"
        }
    ],
    "sg:phone":"+1 812 476 7077",
    "sg:postcode":"47715",
    "sg:province":"IN",
    "sg:tags":[
        "house"
    ],
    "wof:name":"Ohio Valley Home Imp",
    "wof:placetype":"venue"
},
  "geometry": {"coordinates":[-87.489059,37.947859],"type":"Point"}
}