{
  "type": "Feature",
  "properties": {
    "iso:country":"US",
    "sg:address":"1413 E Naomi St",
    "sg:city":"Indianapolis",
    "sg:classifiers":[
        {
            "category":"Recreation",
            "subcategory":"Arcade",
            "type":"Entertainment"
        }
    ],
    "sg:phone":"+1 317 784 2693",
    "sg:postcode":"46203",
    "sg:province":"IN",
    "sg:tags":[
        "amusement",
        "devices"
    ],
    "wof:name":"Boyd Music Co",
    "wof:placetype":"venue"
},
  "geometry": {"coordinates":[-86.135059,39.742493],"type":"Point"}
}