{
  "type": "Feature",
  "properties": {
    "iso:country":"US",
    "sg:address":"4729 S US Hwy 41",
    "sg:city":"Terre Haute",
    "sg:classifiers":[
        {
            "category":"Banks & Credit Unions",
            "subcategory":"Bank",
            "type":"Services"
        }
    ],
    "sg:phone":"+1 812 244 5200",
    "sg:postcode":"47802",
    "sg:province":"IN",
    "wof:name":"Terre Haute Savings Bank",
    "wof:placetype":"venue"
},
  "geometry": {"coordinates":[-87.413825,39.41192],"type":"Point"}
}