{
  "type": "Feature",
  "properties": {
    "iso:country":"US",
    "sg:address":"1415 N Wayne St",
    "sg:city":"Angola",
    "sg:classifiers":[
        {
            "category":"Restaurant",
            "type":"Food & Drink"
        }
    ],
    "sg:menulink":"http://www.allmenus.com/in/angola/207979-taco-bell/menu/",
    "sg:phone":"+1 260 665 6565",
    "sg:postcode":"46703",
    "sg:province":"IN",
    "sg:tags":[
        "mexican"
    ],
    "wof:name":"Taco Bell",
    "wof:placetype":"venue"
},
  "geometry": {"coordinates":[-84.99954099999999,41.653552],"type":"Point"}
}