{
  "type": "Feature",
  "properties": {
    "iso:country":"US",
    "sg:address":"18 N State St",
    "sg:city":"Greenfield",
    "sg:classifiers":[
        {
            "category":"Home & Garden",
            "subcategory":"Household Appliances",
            "type":"Retail Goods"
        }
    ],
    "sg:phone":"+1 317 467 1230",
    "sg:postcode":"46140",
    "sg:province":"IN",
    "sg:tags":[
        "repair",
        "electrical"
    ],
    "wof:name":"Sweeper Shop",
    "wof:placetype":"venue"
},
  "geometry": {"coordinates":[-85.769453,39.785994],"type":"Point"}
}