{
  "type": "Feature",
  "properties": {
    "iso:country":"US",
    "sg:address":"1558 W US Hwy 36",
    "sg:city":"Bainbridge",
    "sg:classifiers":[
        {
            "category":"Government",
            "subcategory":"Office",
            "type":"Public Place"
        }
    ],
    "sg:phone":"+1 765 522 2911",
    "sg:postcode":"46105",
    "sg:province":"IN",
    "sg:tags":[
        "state",
        "program"
    ],
    "wof:name":"Transportation Dept",
    "wof:placetype":"venue"
},
  "geometry": {"coordinates":[-86.857517,39.762013],"type":"Point"}
}