{
  "type": "Feature",
  "properties": {
    "addr:full":"7627 Iron Horse Ln Indianapolis IN 46256",
    "addr:housenumber":"7627",
    "addr:postcode":"46256",
    "addr:street":"Iron Horse Ln",
    "iso:country":"US",
    "sg:address":"7627 Iron Horse Ln",
    "sg:city":"Indianapolis",
    "sg:classifiers":[
        {
            "category":"Freight",
            "type":"Transportation"
        }
    ],
    "sg:phone":"+1 317 842 7752",
    "sg:postcode":"46256",
    "sg:province":"IN",
    "sg:tags":[
        "hauling",
        "trucking"
    ],
    "wof:name":"Gray One Transportation LLC",
    "wof:placetype":"venue"
},
  "geometry": {"coordinates":[-86.033907,39.887592],"type":"Point"}
}