{
  "type": "Feature",
  "properties": {
    "iso:country":"US",
    "sg:address":"1024 Shelby St",
    "sg:city":"Indianapolis",
    "sg:classifiers":[
        {
            "category":"Wholesale",
            "subcategory":"Construction Materials",
            "type":"Manufacturing & Wholesale Goods"
        }
    ],
    "sg:phone":"+1 317 356 3644",
    "sg:postcode":"46203",
    "sg:province":"IN",
    "sg:tags":[
        "fence"
    ],
    "wof:name":"Duke Fence Co Inc",
    "wof:placetype":"venue"
},
  "geometry": {"coordinates":[-86.139859,39.752478],"type":"Point"}
}