{
  "type": "Feature",
  "properties": {
    "addr:full":"204 N Walnut St Brazil IN 47834",
    "addr:housenumber":"204",
    "addr:postcode":"47834",
    "addr:street":"N Walnut St",
    "iso:country":"US",
    "sg:address":"204 N Walnut St",
    "sg:city":"Brazil",
    "sg:classifiers":[
        {
            "category":"Education",
            "subcategory":"Library",
            "type":"Public Place"
        }
    ],
    "sg:phone":"+1 812 448 1981",
    "sg:postcode":"47834",
    "sg:province":"IN",
    "sg:website":"www.brazil.lib.in.us",
    "wof:name":"Brazil Public Library",
    "wof:placetype":"venue"
},
  "geometry": {"coordinates":[-87.128066,39.524476],"type":"Point"}
}