{
  "type": "Feature",
  "properties": {
    "addr:full":"806 W 9th St Rushville IN 46173",
    "addr:housenumber":"806",
    "addr:postcode":"46173",
    "addr:street":"W 9Th St",
    "iso:country":"US",
    "sg:address":"806 W 9th St",
    "sg:city":"Rushville",
    "sg:classifiers":[
        {
            "category":"Organizations",
            "subcategory":"Religious Organization",
            "type":"Services"
        }
    ],
    "sg:phone":"+1 765 932 4867",
    "sg:postcode":"46173",
    "sg:province":"IN",
    "wof:name":"Rushville Parsonage",
    "wof:placetype":"venue"
},
  "geometry": {"coordinates":[-85.455958,39.616154],"type":"Point"}
}