{
  "type": "Feature",
  "properties": {
    "iso:country":"US",
    "sg:address":"880 US Hwy 31 S",
    "sg:city":"Greenwood",
    "sg:classifiers":[
        {
            "category":"Food & Beverages",
            "subcategory":"Groceries & Convenience Stores",
            "type":"Retail Goods"
        }
    ],
    "sg:phone":"+1 317 865 7227",
    "sg:postcode":"46143",
    "sg:province":"IN",
    "sg:tags":[
        "grocer",
        "supermarket"
    ],
    "wof:name":"Marsh Supermarket 43",
    "wof:placetype":"venue"
},
  "geometry": {"coordinates":[-86.107207,39.604755],"type":"Point"}
}