{
  "type": "Feature",
  "properties": {
    "iso:country":"US",
    "sg:address":"2000 E 116th St",
    "sg:city":"Carmel",
    "sg:classifiers":[
        {
            "category":"Health Services",
            "subcategory":"Doctor",
            "type":"Services"
        }
    ],
    "sg:phone":"+1 317 844 6284",
    "sg:postcode":"46032",
    "sg:province":"IN",
    "sg:tags":[
        "dentist"
    ],
    "wof:name":"Carmel Orthodontics",
    "wof:placetype":"venue"
},
  "geometry": {"coordinates":[-86.118416,39.956657],"type":"Point"}
}