{
  "type": "Feature",
  "properties": {
    "iso:country":"US",
    "sg:address":"3395 Putnam St",
    "sg:city":"West Lafayette",
    "sg:classifiers":[
        {
            "category":"Farming",
            "subcategory":"Farm",
            "type":"Manufacturing & Wholesale Goods"
        }
    ],
    "sg:phone":"+1 765 497 9751",
    "sg:postcode":"47906",
    "sg:province":"IN",
    "sg:tags":[
        "crop",
        "general"
    ],
    "wof:name":"J&K Dodt Farm LLC",
    "wof:placetype":"venue"
},
  "geometry": {"coordinates":[-86.910852,40.466345],"type":"Point"}
}