{
  "type": "Feature",
  "properties": {
    "iso:country":"US",
    "sg:address":"2500 E Bellefontaine Rd",
    "sg:city":"Hamilton",
    "sg:classifiers":[
        {
            "category":"Health Services",
            "subcategory":"Doctor",
            "type":"Services"
        }
    ],
    "sg:phone":"+1 260 488 2211",
    "sg:postcode":"46742",
    "sg:province":"IN",
    "sg:tags":[
        "physician",
        "surgeon"
    ],
    "wof:name":"Teresa Smith MD",
    "wof:placetype":"venue"
},
  "geometry": {"coordinates":[-84.944491,41.545782],"type":"Point"}
}