{
  "type": "Feature",
  "properties": {
    "addr:full":"9702 E Washington St Indianapolis IN 46229",
    "addr:housenumber":"9702",
    "addr:postcode":"46229",
    "addr:street":"E Washington St",
    "iso:country":"US",
    "sg:address":"9702 E Washington St",
    "sg:city":"Indianapolis",
    "sg:classifiers":[
        {
            "category":"Restaurant",
            "type":"Food & Drink"
        }
    ],
    "sg:menulink":"http://www.allmenus.com/in/warren/98238-qdoba/menu/",
    "sg:phone":"+1 317 890 8070",
    "sg:postcode":"46229",
    "sg:province":"IN",
    "sg:tags":[
        "mexican"
    ],
    "wof:name":"Qdoba",
    "wof:placetype":"venue"
},
  "geometry": {"coordinates":[-85.99329,39.775421],"type":"Point"}
}