{
  "type": "Feature",
  "properties": {
    "iso:country":"US",
    "sg:address":"104 S Harrison St",
    "sg:city":"Alexandria",
    "sg:classifiers":[
        {
            "category":"Real Estate",
            "subcategory":"Real Estate Agent",
            "type":"Services"
        }
    ],
    "sg:phone":"+1 765 724 2937",
    "sg:postcode":"46001",
    "sg:province":"IN",
    "wof:name":"Priority Realty Inc",
    "wof:placetype":"venue"
},
  "geometry": {"coordinates":[-85.674352,40.262602],"type":"Point"}
}