{
  "type": "Feature",
  "properties": {
    "iso:country":"US",
    "sg:address":"1242 Summer Ridge Ln",
    "sg:city":"Brownsburg",
    "sg:classifiers":[
        {
            "category":"Banks & Credit Unions",
            "subcategory":"Bank",
            "type":"Services"
        }
    ],
    "sg:phone":"+1 317 408 4606",
    "sg:postcode":"46112",
    "sg:province":"IN",
    "sg:tags":[
        "mortgage"
    ],
    "wof:name":"AG Harris Closing Associates",
    "wof:placetype":"venue"
},
  "geometry": {"coordinates":[-86.376552,39.861995],"type":"Point"}
}