{
  "type": "Feature",
  "properties": {
    "iso:country":"US",
    "sg:address":"187 Greenwood",
    "sg:city":"Jeffersonville",
    "sg:classifiers":[
        {
            "category":"Government",
            "subcategory":"Office",
            "type":"Public Place"
        }
    ],
    "sg:phone":"+1 812 283 8875",
    "sg:postcode":"47130",
    "sg:province":"IN",
    "sg:tags":[
        "village"
    ],
    "wof:name":"Greenwood Community Building",
    "wof:placetype":"venue"
},
  "geometry": {"coordinates":[-85.746605,38.289696],"type":"Point"}
}