{
  "type": "Feature",
  "properties": {
    "iso:country":"US",
    "sg:address":"1120 S 15th St",
    "sg:city":"Vincennes",
    "sg:classifiers":[
        {
            "category":"Health Services",
            "subcategory":"Health Practitioner",
            "type":"Services"
        }
    ],
    "sg:phone":"+1 812 882 3146",
    "sg:postcode":"47591",
    "sg:province":"IN",
    "sg:tags":[
        "therapist",
        "physical"
    ],
    "wof:name":"Schneider Physical Therapy",
    "wof:placetype":"venue"
},
  "geometry": {"coordinates":[-87.53207,38.662111],"type":"Point"}
}