{
  "type": "Feature",
  "properties": {
    "iso:country":"US",
    "sg:address":"1315 W Main St",
    "sg:city":"Fort Wayne",
    "sg:classifiers":[
        {
            "category":"Building & Trades",
            "subcategory":"Construction",
            "type":"Services"
        }
    ],
    "sg:phone":"+1 260 426 2513",
    "sg:postcode":"46808",
    "sg:province":"IN",
    "sg:tags":[
        "product",
        "asphalt"
    ],
    "wof:name":"Top KOTE Asphalt Svc",
    "wof:placetype":"venue"
},
  "geometry": {"coordinates":[-85.159389,41.078556],"type":"Point"}
}