{
  "type": "Feature",
  "properties": {
    "iso:country":"US",
    "sg:address":"5559 N 500 W",
    "sg:city":"Mc Cordsville",
    "sg:classifiers":[
        {
            "category":"Home & Garden",
            "subcategory":"Garden Supply",
            "type":"Retail Goods"
        }
    ],
    "sg:phone":"+1 317 335 3333",
    "sg:postcode":"46055",
    "sg:province":"IN",
    "sg:tags":[
        "bulb",
        "seed"
    ],
    "wof:name":"Steyer Seeds",
    "wof:placetype":"venue"
},
  "geometry": {"coordinates":[-85.897719,39.864135],"type":"Point"}
}