{
  "type": "Feature",
  "properties": {
    "iso:country":"US",
    "sg:address":"104 N Main St",
    "sg:city":"Wanatah",
    "sg:classifiers":[
        {
            "category":"Government",
            "subcategory":"Office",
            "type":"Public Place"
        }
    ],
    "sg:phone":"+1 219 733 2340",
    "sg:postcode":"46390",
    "sg:province":"IN",
    "sg:tags":[
        "city"
    ],
    "wof:name":"Wanatah Town Hall",
    "wof:placetype":"venue"
},
  "geometry": {"coordinates":[-86.897667,41.430047],"type":"Point"}
}