{
  "type": "Feature",
  "properties": {
    "iso:country":"US",
    "sg:address":"470 S Mitthoeffer Rd",
    "sg:city":"Indianapolis",
    "sg:classifiers":[
        {
            "category":"Manufacturing",
            "subcategory":"Tools & Machinery",
            "type":"Manufacturing & Wholesale Goods"
        },
        {
            "category":"Manufacturing",
            "subcategory":"Metals",
            "type":"Manufacturing & Wholesale Goods"
        },
        {
            "category":"Manufacturing",
            "subcategory":"Building Materials",
            "type":"Manufacturing & Wholesale Goods"
        }
    ],
    "sg:phone":"+1 317 899 2203",
    "sg:postcode":"46229",
    "sg:province":"IN",
    "sg:tags":[
        "sheet",
        "work",
        "machine",
        "work-manufacturers",
        "fabricator",
        "manufacturer"
    ],
    "sg:website":"http://www.estesdm.com",
    "wof:name":"Estes Design And Manufacturing Inc",
    "wof:placetype":"venue"
},
  "geometry": {"coordinates":[-85.99012999999999,39.76317],"type":"Point"}
}