{
  "type": "Feature",
  "properties": {
    "iso:country":"US",
    "sg:address":"29156 Co Rd 146",
    "sg:city":"Nappanee",
    "sg:classifiers":[
        {
            "category":"Farming",
            "subcategory":"Dairy Farm",
            "type":"Manufacturing & Wholesale Goods"
        }
    ],
    "sg:phone":"+1 574 862 4051",
    "sg:postcode":"46550",
    "sg:province":"IN",
    "wof:name":"Bradley Metzger",
    "wof:placetype":"venue"
},
  "geometry": {"coordinates":[-86.025849,41.49157],"type":"Point"}
}