{
  "type": "Feature",
  "properties": {
    "iso:country":"US",
    "sg:address":"302 W Main St",
    "sg:city":"North Manchester",
    "sg:classifiers":[
        {
            "category":"Health Services",
            "subcategory":"Chiropractor",
            "type":"Services"
        }
    ],
    "sg:phone":"+1 260 982 4646",
    "sg:postcode":"46962",
    "sg:province":"IN",
    "wof:name":"Manchester Chiropractic Ctr",
    "wof:placetype":"venue"
},
  "geometry": {"coordinates":[-85.77382,40.999071],"type":"Point"}
}