{
  "type": "Feature",
  "properties": {
    "iso:country":"US",
    "sg:address":"190 N Union St",
    "sg:city":"Russiaville",
    "sg:classifiers":[
        {
            "category":"Professional",
            "subcategory":"Accounting & Tax Preparation",
            "type":"Services"
        }
    ],
    "sg:phone":"+1 765 883 8507",
    "sg:postcode":"46979",
    "sg:province":"IN",
    "sg:tags":[
        "return",
        "filing"
    ],
    "wof:name":"Western Tax",
    "wof:placetype":"venue"
},
  "geometry": {"coordinates":[-86.271305,40.418041],"type":"Point"}
}