{
  "type": "Feature",
  "properties": {
    "addr:full":"428 Pearl St New Albany IN 47150",
    "addr:housenumber":"428",
    "addr:postcode":"47150",
    "addr:street":"Pearl St",
    "iso:country":"US",
    "sg:address":"428 Pearl St",
    "sg:city":"New Albany",
    "sg:classifiers":[
        {
            "category":"Professional",
            "subcategory":"Business Services",
            "type":"Services"
        }
    ],
    "sg:phone":"+1 812 945 8660",
    "sg:postcode":"47150",
    "sg:province":"IN",
    "sg:tags":[
        "appraiser"
    ],
    "sg:website":"www.royappraisal.com",
    "wof:name":"Roy Appraisal",
    "wof:placetype":"venue"
},
  "geometry": {"coordinates":[-85.82338,38.286839],"type":"Point"}
}