{
  "type": "Feature",
  "properties": {
    "addr:full":"1350 W McKay Rd Shelbyville IN 46176",
    "addr:housenumber":"1350",
    "addr:postcode":"46176",
    "addr:street":"W Mckay Rd",
    "iso:country":"US",
    "sg:address":"1350 W McKay Rd",
    "sg:city":"Shelbyville",
    "sg:classifiers":[
        {
            "category":"Government",
            "subcategory":"Fire Station",
            "type":"Public Place"
        }
    ],
    "sg:phone":"+1 317 392 5125",
    "sg:postcode":"46176",
    "sg:province":"IN",
    "sg:tags":[
        "protection"
    ],
    "wof:name":"Shelbyvlle Cy Fire Dept Stn 3",
    "wof:placetype":"venue"
},
  "geometry": {"coordinates":[-85.798593,39.504702],"type":"Point"}
}