{
  "type": "Feature",
  "properties": {
    "iso:country":"US",
    "sg:address":"1105 E Ridge Rd",
    "sg:city":"Griffith",
    "sg:classifiers":[
        {
            "category":"Restaurant",
            "type":"Food & Drink"
        }
    ],
    "sg:phone":"+1 219 923 7170",
    "sg:postcode":"46319",
    "sg:province":"IN",
    "sg:tags":[
        "eating"
    ],
    "wof:name":"Pagoda Inn",
    "wof:placetype":"venue"
},
  "geometry": {"coordinates":[-87.41312,41.549501],"type":"Point"}
}