{
  "type": "Feature",
  "properties": {
    "iso:country":"US",
    "sg:address":"1 S Commercial St",
    "sg:city":"Worthington",
    "sg:classifiers":[
        {
            "category":"Shopping",
            "subcategory":"Used Merchandise",
            "type":"Retail Goods"
        }
    ],
    "sg:phone":"+1 812 875 3775",
    "sg:postcode":"47471",
    "sg:province":"IN",
    "wof:name":"Log Cabin Treasures",
    "wof:placetype":"venue"
},
  "geometry": {"coordinates":[-86.975893,39.119007],"type":"Point"}
}