{
  "type": "Feature",
  "properties": {
    "iso:country":"US",
    "sg:address":"2739 S Saint Anthony Rd W",
    "sg:city":"Huntingburg",
    "sg:classifiers":[
        {
            "category":"Manufacturing",
            "subcategory":"Lumber",
            "type":"Manufacturing & Wholesale Goods"
        }
    ],
    "sg:phone":"+1 812 326 2053",
    "sg:postcode":"47542",
    "sg:province":"IN",
    "sg:tags":[
        "planing",
        "mills",
        "sawmill"
    ],
    "wof:name":"Southern Indiana Hardwood Dry",
    "wof:placetype":"venue"
},
  "geometry": {"coordinates":[-86.858343,38.339429],"type":"Point"}
}