{
  "type": "Feature",
  "properties": {
    "addr:full":"1620 Rembrandt St Indianapolis IN 46202",
    "addr:housenumber":"1620",
    "addr:postcode":"46202",
    "addr:street":"Rembrandt St",
    "iso:country":"US",
    "sg:address":"1620 Rembrandt St",
    "sg:city":"Indianapolis",
    "sg:classifiers":[
        {
            "category":"Manufacturing",
            "subcategory":"Tools & Machinery",
            "type":"Manufacturing & Wholesale Goods"
        }
    ],
    "sg:phone":"+1 317 231 2215",
    "sg:postcode":"46202",
    "sg:province":"IN",
    "sg:tags":[
        "equipment",
        "supplies-wholesale",
        "electric",
        "manufacturer"
    ],
    "wof:name":"Consolidated Electrical Distributors-Economy Electrical Supply",
    "wof:placetype":"venue"
},
  "geometry": {"coordinates":[-86.181361,39.788946],"type":"Point"}
}