{
  "type": "Feature",
  "properties": {
    "iso:country":"US",
    "sg:address":"3111 Madison Ave",
    "sg:city":"Anderson",
    "sg:classifiers":[
        {
            "category":"Shopping",
            "type":"Retail Goods"
        }
    ],
    "sg:phone":"+1 765 683 9920",
    "sg:postcode":"46016",
    "sg:province":"IN",
    "sg:tags":[
        "product",
        "wood"
    ],
    "sg:website":"www.trucutinc.com",
    "wof:name":"Tru-Cut Inc",
    "wof:placetype":"venue"
},
  "geometry": {"coordinates":[-85.692018,40.086162],"type":"Point"}
}