{
  "type": "Feature",
  "properties": {
    "iso:country":"US",
    "sg:address":"66301 Gumwood Rd",
    "sg:city":"Bremen",
    "sg:classifiers":[
        {
            "category":"Professional",
            "subcategory":"Business Services",
            "type":"Services"
        }
    ],
    "sg:phone":"+1 574 633 4842",
    "sg:postcode":"46506",
    "sg:province":"IN",
    "wof:name":"My Fathers House",
    "wof:placetype":"venue"
},
  "geometry": {"coordinates":[-86.176389,41.532445],"type":"Point"}
}