{
  "type": "Feature",
  "properties": {
    "iso:country":"US",
    "sg:address":"5196 Plum Creek Rd",
    "sg:city":"Nashville",
    "sg:classifiers":[
        {
            "category":"Retail",
            "subcategory":"Repair Shop",
            "type":"Services"
        }
    ],
    "sg:phone":"+1 812 988 6020",
    "sg:postcode":"47448",
    "sg:province":"IN",
    "sg:tags":[
        "refrigerator",
        "freezer"
    ],
    "wof:name":"Nevins Refrigeration Htg & AC",
    "wof:placetype":"venue"
},
  "geometry": {"coordinates":[-86.335491,39.24944],"type":"Point"}
}