{
  "type": "Feature",
  "properties": {
    "iso:country":"US",
    "sg:address":"834 State St",
    "sg:city":"New Albany",
    "sg:classifiers":[
        {
            "category":"Retail",
            "subcategory":"Repair Shop",
            "type":"Services"
        }
    ],
    "sg:phone":"+1 812 944 7571",
    "sg:postcode":"47150",
    "sg:province":"IN",
    "sg:tags":[
        "television",
        "radio"
    ],
    "wof:name":"Collins TV VCR Repair",
    "wof:placetype":"venue"
},
  "geometry": {"coordinates":[-85.827202,38.291958],"type":"Point"}
}