{
  "type": "Feature",
  "properties": {
    "addr:full":"252 State Rd 67 Switz City IN 47471",
    "addr:housenumber":"252;67",
    "addr:postcode":"47471",
    "addr:street":"State Rd",
    "iso:country":"US",
    "sg:address":"252 State Rd 67",
    "sg:city":"Switz City",
    "sg:classifiers":[
        {
            "category":"Retail",
            "subcategory":"Auto Repair",
            "type":"Services"
        }
    ],
    "sg:phone":"+1 812 659 1490",
    "sg:postcode":"47471",
    "sg:province":"IN",
    "sg:tags":[
        "truck"
    ],
    "wof:name":"Gibco Motor Express Inc",
    "wof:placetype":"venue"
},
  "geometry": {"coordinates":[-86.978183,39.116539],"type":"Point"}
}