{
  "type": "Feature",
  "properties": {
    "iso:country":"US",
    "sg:address":"1452 W 800 N",
    "sg:city":"Shelbyville",
    "sg:phone":"+1 317 835 4312",
    "sg:postcode":"46176",
    "sg:province":"IN",
    "sg:tags":[
        "farm",
        "grain",
        "cash"
    ],
    "wof:name":"Nigh Farms",
    "wof:placetype":"venue"
},
  "geometry": {"coordinates":[-85.808829,39.640246],"type":"Point"}
}