{
  "type": "Feature",
  "properties": {
    "addr:full":"110 S Francke Rd Henryville IN 47126",
    "addr:housenumber":"110",
    "addr:postcode":"47126",
    "addr:street":"S Francke Rd",
    "iso:country":"US",
    "sg:address":"110 S Francke Rd",
    "sg:city":"Henryville",
    "sg:classifiers":[
        {
            "category":"Organizations",
            "subcategory":"Religious Organization",
            "type":"Services"
        }
    ],
    "sg:phone":"+1 812 294 1431",
    "sg:postcode":"47126",
    "sg:province":"IN",
    "sg:tags":[
        "church"
    ],
    "wof:name":"First Baptist Church",
    "wof:placetype":"venue"
},
  "geometry": {"coordinates":[-85.77314,38.540031],"type":"Point"}
}