{
  "type": "Feature",
  "properties": {
    "iso:country":"US",
    "sg:address":"2969 Burr St",
    "sg:city":"Gary",
    "sg:classifiers":[
        {
            "category":"Freight",
            "type":"Transportation"
        }
    ],
    "sg:phone":"+1 219 989 8024",
    "sg:postcode":"46406",
    "sg:province":"IN",
    "sg:tags":[
        "commercial",
        "storage"
    ],
    "wof:name":"Burr Street Self Storage",
    "wof:placetype":"venue"
},
  "geometry": {"coordinates":[-87.403372,41.565599],"type":"Point"}
}