{
  "type": "Feature",
  "properties": {
    "iso:country":"US",
    "sg:address":"1305 Baywood Dr",
    "sg:city":"New Haven",
    "sg:classifiers":[
        {
            "category":"Shopping",
            "subcategory":"Hobbies, Toys, & Games",
            "type":"Retail Goods"
        }
    ],
    "sg:phone":"+1 260 749 1897",
    "sg:postcode":"46774",
    "sg:province":"IN",
    "sg:tags":[
        "equipment",
        "ceramic",
        "supply"
    ],
    "wof:name":"Lavonne's Ceramics",
    "wof:placetype":"venue"
},
  "geometry": {"coordinates":[-85.037838,41.062104],"type":"Point"}
}