{
  "type": "Feature",
  "properties": {
    "iso:country":"US",
    "sg:address":"6781 US Hwy 36",
    "sg:city":"Avon",
    "sg:classifiers":[
        {
            "category":"Government",
            "subcategory":"Office",
            "type":"Public Place"
        }
    ],
    "sg:phone":"+1 317 272 6261",
    "sg:postcode":"46122",
    "sg:province":"IN",
    "sg:tags":[
        "city",
        "taxation"
    ],
    "wof:name":"Township Assessor",
    "wof:placetype":"venue"
},
  "geometry": {"coordinates":[-86.634804,39.760594],"type":"Point"}
}