{
  "type": "Feature",
  "properties": {
    "iso:country":"US",
    "sg:address":"10643 State Rd 160",
    "sg:city":"Salem",
    "sg:classifiers":[
        {
            "category":"Manufacturing",
            "subcategory":"Lumber",
            "type":"Manufacturing & Wholesale Goods"
        }
    ],
    "sg:phone":"+1 812 967 2442",
    "sg:postcode":"47167",
    "sg:province":"IN",
    "sg:tags":[
        "logging"
    ],
    "wof:name":"Roger Lanham Logging",
    "wof:placetype":"venue"
},
  "geometry": {"coordinates":[-85.908828,38.579043],"type":"Point"}
}