{
  "type": "Feature",
  "properties": {
    "iso:country":"US",
    "sg:address":"1475 Summer St",
    "sg:city":"Hammond",
    "sg:classifiers":[
        {
            "category":"Retail",
            "subcategory":"Laundry & Dry Cleaning",
            "type":"Services"
        }
    ],
    "sg:phone":"+1 219 932 8600",
    "sg:postcode":"46320",
    "sg:province":"IN",
    "wof:name":"Mickey's Linen",
    "wof:placetype":"venue"
},
  "geometry": {"coordinates":[-87.49374,41.607321],"type":"Point"}
}