{
  "type": "Feature",
  "properties": {
    "iso:country":"US",
    "sg:address":"4608 Buckingham Ct",
    "sg:city":"Carmel",
    "sg:classifiers":[
        {
            "category":"Manufacturing",
            "subcategory":"Jewelry",
            "type":"Manufacturing & Wholesale Goods"
        }
    ],
    "sg:phone":"+1 317 844 8109",
    "sg:postcode":"46033",
    "sg:province":"IN",
    "sg:tags":[
        "precious",
        "metal",
        "mfg"
    ],
    "wof:name":"For What Its Worth Inc",
    "wof:placetype":"venue"
},
  "geometry": {"coordinates":[-86.092717,39.962202],"type":"Point"}
}