{
  "type": "Feature",
  "properties": {
    "iso:country":"US",
    "sg:address":"4241 Hogue Rd",
    "sg:city":"Evansville",
    "sg:classifiers":[
        {
            "category":"Building & Trades",
            "subcategory":"Construction",
            "type":"Services"
        }
    ],
    "sg:phone":"+1 812 423 4286",
    "sg:postcode":"47712",
    "sg:province":"IN",
    "sg:tags":[
        "insulation",
        "heat",
        "contractor"
    ],
    "wof:name":"Ohio Valley Insulation Co Inc",
    "wof:placetype":"venue"
},
  "geometry": {"coordinates":[-87.627427,37.981101],"type":"Point"}
}