{
  "type": "Feature",
  "properties": {
    "iso:country":"US",
    "sg:address":"1314 Crest Ct",
    "sg:city":"Plainfield",
    "sg:classifiers":[
        {
            "category":"Farming",
            "subcategory":"Farm",
            "type":"Manufacturing & Wholesale Goods"
        }
    ],
    "sg:phone":"+1 317 839 2646",
    "sg:postcode":"46168",
    "sg:province":"IN",
    "sg:tags":[
        "crop",
        "general"
    ],
    "wof:name":"David Sinders",
    "wof:placetype":"venue"
},
  "geometry": {"coordinates":[-86.387706,39.686237],"type":"Point"}
}