{
  "type": "Feature",
  "properties": {
    "iso:country":"US",
    "sg:address":"4895 State Rd 252",
    "sg:city":"Martinsville",
    "sg:classifiers":[
        {
            "category":"Wholesale",
            "subcategory":"Auto Parts",
            "type":"Manufacturing & Wholesale Goods"
        }
    ],
    "sg:phone":"+1 765 342 4841",
    "sg:postcode":"46151",
    "sg:province":"IN",
    "sg:tags":[
        "used"
    ],
    "wof:name":"Powell Auto Parts",
    "wof:placetype":"venue"
},
  "geometry": {"coordinates":[-86.33471400000001,39.403921],"type":"Point"}
}