{
  "type": "Feature",
  "properties": {
    "iso:country":"US",
    "sg:address":"10 Highland Ave",
    "sg:city":"Franklin",
    "sg:classifiers":[
        {
            "category":"Wholesale",
            "subcategory":"Electrical",
            "type":"Manufacturing & Wholesale Goods"
        }
    ],
    "sg:phone":"+1 317 736 0440",
    "sg:postcode":"46131",
    "sg:province":"IN",
    "sg:tags":[
        "elements",
        "electric",
        "heating"
    ],
    "wof:name":"Process Heat & Controls Inc",
    "wof:placetype":"venue"
},
  "geometry": {"coordinates":[-86.060168,39.491025],"type":"Point"}
}