{
  "type": "Feature",
  "properties": {
    "iso:country":"US",
    "sg:address":"108 E Franklin St",
    "sg:city":"Winchester",
    "sg:classifiers":[
        {
            "category":"Real Estate",
            "subcategory":"Real Estate Agent",
            "type":"Services"
        }
    ],
    "sg:phone":"+1 765 584 3495",
    "sg:postcode":"47394",
    "sg:province":"IN",
    "wof:name":"Helms Realty",
    "wof:placetype":"venue"
},
  "geometry": {"coordinates":[-84.979863,40.171579],"type":"Point"}
}