{
  "type": "Feature",
  "properties": {
    "addr:full":"4943 W US Hwy 40 Greenfield IN 46140",
    "addr:housenumber":"4943",
    "addr:postcode":"46140",
    "addr:street":"W Us Hwy 40",
    "iso:country":"US",
    "sg:address":"4943 W US Hwy 40",
    "sg:city":"Greenfield",
    "sg:classifiers":[
        {
            "category":"Freight",
            "type":"Transportation"
        }
    ],
    "sg:phone":"+1 317 894 7738",
    "sg:postcode":"46140",
    "sg:province":"IN",
    "sg:tags":[
        "commercial",
        "storage"
    ],
    "wof:name":"Gem Self Storage LLC",
    "wof:placetype":"venue"
},
  "geometry": {"coordinates":[-85.893321,39.779475],"type":"Point"}
}