{
  "type": "Feature",
  "properties": {
    "iso:country":"US",
    "sg:address":"911 Indianapolis Ave",
    "sg:city":"Lebanon",
    "sg:classifiers":[
        {
            "category":"Home & Garden",
            "subcategory":"Carpets & Floor Coverings",
            "type":"Retail Goods"
        }
    ],
    "sg:phone":"+1 765 482 5440",
    "sg:postcode":"46052",
    "sg:province":"IN",
    "sg:tags":[
        "dealer",
        "rug"
    ],
    "wof:name":"Hawks Custom Floors",
    "wof:placetype":"venue"
},
  "geometry": {"coordinates":[-86.45801400000001,40.039986],"type":"Point"}
}