{
  "type": "Feature",
  "properties": {
    "iso:country":"US",
    "sg:address":"4257 W Delap Rd",
    "sg:city":"Ellettsville",
    "sg:classifiers":[
        {
            "category":"Building & Trades",
            "subcategory":"Landscaping Services",
            "type":"Services"
        }
    ],
    "sg:phone":"+1 812 876 5296",
    "sg:postcode":"47429",
    "sg:province":"IN",
    "sg:tags":[
        "tree"
    ],
    "wof:name":"A Turf 'n Tree MD",
    "wof:placetype":"venue"
},
  "geometry": {"coordinates":[-86.591658,39.254158],"type":"Point"}
}