{
  "type": "Feature",
  "properties": {
    "iso:country":"US",
    "sg:address":"500 S Grandstaff Dr",
    "sg:city":"Auburn",
    "sg:classifiers":[
        {
            "category":"Home & Garden",
            "subcategory":"Carpets & Floor Coverings",
            "type":"Retail Goods"
        }
    ],
    "sg:phone":"+1 260 925 3016",
    "sg:postcode":"46706",
    "sg:province":"IN",
    "sg:tags":[
        "dealer",
        "rug"
    ],
    "wof:name":"West Floor Coverings Shop Inc",
    "wof:placetype":"venue"
},
  "geometry": {"coordinates":[-85.071415,41.363271],"type":"Point"}
}