{
  "type": "Feature",
  "properties": {
    "iso:country":"US",
    "sg:address":"3602 Lafayette Rd",
    "sg:city":"Indianapolis",
    "sg:classifiers":[
        {
            "category":"Food & Beverages",
            "subcategory":"Liquor & Beverages",
            "type":"Retail Goods"
        }
    ],
    "sg:phone":"+1 317 293 3661",
    "sg:postcode":"46222",
    "sg:province":"IN",
    "wof:name":"Quick Stop Liquors",
    "wof:placetype":"venue"
},
  "geometry": {"coordinates":[-86.23236799999999,39.821104],"type":"Point"}
}