{
  "type": "Feature",
  "properties": {
    "addr:full":"4255 Sharp Ln Columbus IN 47201",
    "addr:housenumber":"4255",
    "addr:postcode":"47201",
    "addr:street":"Sharp Ln",
    "iso:country":"US",
    "sg:address":"4255 Sharp Ln",
    "sg:city":"Columbus",
    "sg:classifiers":[
        {
            "category":"Building & Trades",
            "subcategory":"Construction",
            "type":"Services"
        }
    ],
    "sg:phone":"+1 812 378 9670",
    "sg:postcode":"47201",
    "sg:province":"IN",
    "sg:tags":[
        "general",
        "contractor"
    ],
    "wof:name":"Carriage Builders Inc",
    "wof:placetype":"venue"
},
  "geometry": {"coordinates":[-85.969729,39.189906],"type":"Point"}
}