{
  "type": "Feature",
  "properties": {
    "iso:country":"US",
    "sg:address":"101 Madison St",
    "sg:city":"Decatur",
    "sg:classifiers":[
        {
            "category":"Organizations",
            "subcategory":"Community Association",
            "type":"Services"
        }
    ],
    "sg:phone":"+1 260 724 3705",
    "sg:postcode":"46733",
    "sg:province":"IN",
    "sg:tags":[
        "military"
    ],
    "wof:name":"American Legion",
    "wof:placetype":"venue"
},
  "geometry": {"coordinates":[-84.922833,40.830225],"type":"Point"}
}