{
  "type": "Feature",
  "properties": {
    "iso:country":"US",
    "sg:address":"8360 N 200 W",
    "sg:city":"Decatur",
    "sg:classifiers":[
        {
            "category":"Personal",
            "subcategory":"Beauty Salon",
            "type":"Services"
        }
    ],
    "sg:phone":"+1 260 724 9799",
    "sg:postcode":"46733",
    "sg:province":"IN",
    "wof:name":"Creative Scissors Inc",
    "wof:placetype":"venue"
},
  "geometry": {"coordinates":[-84.976468,40.866927],"type":"Point"}
}