{
  "type": "Feature",
  "properties": {
    "iso:country":"US",
    "sg:address":"219 E Sycamore St",
    "sg:city":"Kokomo",
    "sg:classifiers":[
        {
            "category":"Government",
            "subcategory":"Office",
            "type":"Public Place"
        }
    ],
    "sg:phone":"+1 765 456 7544",
    "sg:postcode":"46901",
    "sg:province":"IN",
    "sg:tags":[
        "village"
    ],
    "wof:name":"Kokomo Traffic Systems",
    "wof:placetype":"venue"
},
  "geometry": {"coordinates":[-86.128928,40.486409],"type":"Point"}
}