{
  "type": "Feature",
  "properties": {
    "addr:full":"1636 Slate Run Rd New Albany IN 47150",
    "addr:housenumber":"1636",
    "addr:postcode":"47150",
    "addr:street":"Slate Run Rd",
    "iso:country":"US",
    "sg:address":"1636 Slate Run Rd",
    "sg:city":"New Albany",
    "sg:classifiers":[
        {
            "category":"Professional",
            "subcategory":"Accounting & Tax Preparation",
            "type":"Services"
        }
    ],
    "sg:phone":"+1 812 944 3619",
    "sg:postcode":"47150",
    "sg:province":"IN",
    "sg:tags":[
        "return"
    ],
    "wof:name":"Buehner Tax Service",
    "wof:placetype":"venue"
},
  "geometry": {"coordinates":[-85.800946,38.319829],"type":"Point"}
}