{
  "type": "Feature",
  "properties": {
    "iso:country":"US",
    "sg:address":"1230 Dr Martin Luther King St",
    "sg:city":"Indianapolis",
    "sg:classifiers":[
        {
            "category":"Shopping",
            "subcategory":"Clothing, Apparel, & Fashions",
            "type":"Retail Goods"
        }
    ],
    "sg:phone":"+1 317 631 4938",
    "sg:postcode":"46202",
    "sg:province":"IN",
    "wof:name":"Auntie's Fashions",
    "wof:placetype":"venue"
},
  "geometry": {"coordinates":[-86.168448,39.784589],"type":"Point"}
}