{
  "type": "Feature",
  "properties": {
    "iso:country":"US",
    "sg:address":"7868 Allison Ave",
    "sg:city":"Indianapolis",
    "sg:classifiers":[
        {
            "category":"Banks & Credit Unions",
            "subcategory":"Financial Services",
            "type":"Services"
        }
    ],
    "sg:phone":"+1 317 876 0815",
    "sg:postcode":"46268",
    "sg:province":"IN",
    "sg:tags":[
        "company",
        "holding"
    ],
    "wof:name":"World Wide Technology Holding",
    "wof:placetype":"venue"
},
  "geometry": {"coordinates":[-86.250138,39.894791],"type":"Point"}
}