{
  "type": "Feature",
  "properties": {
    "iso:country":"US",
    "sg:address":"14501 Lincoln Hwy",
    "sg:city":"Plymouth",
    "sg:classifiers":[
        {
            "category":"Building & Trades",
            "subcategory":"Construction",
            "type":"Services"
        }
    ],
    "sg:phone":"+1 574 935 5456",
    "sg:postcode":"46563",
    "sg:province":"IN",
    "sg:tags":[
        "excavating",
        "contractor"
    ],
    "wof:name":"Stone Excavating",
    "wof:placetype":"venue"
},
  "geometry": {"coordinates":[-86.345892,41.34697],"type":"Point"}
}