{
  "type": "Feature",
  "properties": {
    "iso:country":"US",
    "sg:address":"912 N Morton St",
    "sg:city":"Franklin",
    "sg:classifiers":[
        {
            "category":"Banks & Credit Unions",
            "subcategory":"Bank",
            "type":"Services"
        }
    ],
    "sg:phone":"+1 317 736 8035",
    "sg:postcode":"46131",
    "sg:province":"IN",
    "sg:tags":[
        "cashing",
        "check"
    ],
    "wof:name":"Chek' N Go Of Indiana",
    "wof:placetype":"venue"
},
  "geometry": {"coordinates":[-86.064285,39.488975],"type":"Point"}
}