{
  "type": "Feature",
  "properties": {
    "iso:country":"US",
    "sg:address":"300 Garwood Rd",
    "sg:city":"Richmond",
    "sg:classifiers":[
        {
            "category":"Farming",
            "subcategory":"Livestock Farm",
            "type":"Manufacturing & Wholesale Goods"
        }
    ],
    "sg:phone":"+1 765 962 6365",
    "sg:postcode":"47374",
    "sg:province":"IN",
    "sg:tags":[
        "feedlot",
        "field",
        "crop",
        "beef",
        "cattle"
    ],
    "wof:name":"Robert Bowen",
    "wof:placetype":"venue"
},
  "geometry": {"coordinates":[-84.84225,39.824273],"type":"Point"}
}