{
  "type": "Feature",
  "properties": {
    "iso:country":"US",
    "sg:address":"102 Main St",
    "sg:city":"Vincennes",
    "sg:classifiers":[
        {
            "category":"Home & Garden",
            "subcategory":"Home Furnishings",
            "type":"Retail Goods"
        }
    ],
    "sg:phone":"+1 812 882 1543",
    "sg:postcode":"47591",
    "sg:province":"IN",
    "sg:tags":[
        "bathroom",
        "fixture",
        "accessory"
    ],
    "wof:name":"Wabash Plumbing Inc",
    "wof:placetype":"venue"
},
  "geometry": {"coordinates":[-87.532857,38.680662],"type":"Point"}
}