{
  "type": "Feature",
  "properties": {
    "addr:full":"102 Birchwood Dr Lebanon IN 46052",
    "addr:housenumber":"102",
    "addr:postcode":"46052",
    "addr:street":"Birchwood Dr",
    "iso:country":"US",
    "sg:address":"102 Birchwood Dr",
    "sg:city":"Lebanon",
    "sg:classifiers":[
        {
            "category":"Real Estate",
            "subcategory":"Real Estate Agent",
            "type":"Services"
        }
    ],
    "sg:phone":"+1 765 483 4622",
    "sg:postcode":"46052",
    "sg:province":"IN",
    "sg:website":"www.carpentergmac.com",
    "wof:name":"Carpenter Gmac Real Estate",
    "wof:placetype":"venue"
},
  "geometry": {"coordinates":[-86.47056000000001,40.035296],"type":"Point"}
}