{
  "type": "Feature",
  "properties": {
    "iso:country":"US",
    "sg:address":"711 North St",
    "sg:city":"Syracuse",
    "sg:classifiers":[
        {
            "category":"Building & Trades",
            "subcategory":"Construction",
            "type":"Services"
        }
    ],
    "sg:phone":"+1 574 457 2451",
    "sg:postcode":"46567",
    "sg:province":"IN",
    "sg:tags":[
        "hanging",
        "contractor"
    ],
    "wof:name":"Wawasee Lake Services",
    "wof:placetype":"venue"
},
  "geometry": {"coordinates":[-85.756299,41.426201],"type":"Point"}
}