{
  "type": "Feature",
  "properties": {
    "iso:country":"US",
    "sg:address":"1229 S 8th St",
    "sg:city":"Richmond",
    "sg:classifiers":[
        {
            "category":"Retail",
            "subcategory":"Repair Shop",
            "type":"Services"
        }
    ],
    "sg:phone":"+1 765 962 6487",
    "sg:postcode":"47374",
    "sg:province":"IN",
    "sg:tags":[
        "boat"
    ],
    "wof:name":"Richmond Marine Outlet",
    "wof:placetype":"venue"
},
  "geometry": {"coordinates":[-84.891689,39.813893],"type":"Point"}
}