{
  "type": "Feature",
  "properties": {
    "iso:country":"US",
    "sg:address":"6240 Grand Blvd",
    "sg:city":"Hobart",
    "sg:classifiers":[
        {
            "category":"Organizations",
            "subcategory":"Religious Organization",
            "type":"Services"
        }
    ],
    "sg:phone":"+1 219 942 0836",
    "sg:postcode":"46342",
    "sg:province":"IN",
    "wof:name":"Grace Evang Lutheran Church",
    "wof:placetype":"venue"
},
  "geometry": {"coordinates":[-87.258848,41.506356],"type":"Point"}
}