{
  "type": "Feature",
  "properties": {
    "iso:country":"US",
    "sg:address":"1916 N 850 E",
    "sg:city":"Pierceton",
    "sg:classifiers":[
        {
            "category":"Autos & Motor Vehicles",
            "subcategory":"Recreational Vehicle Sales",
            "type":"Retail Goods"
        }
    ],
    "sg:phone":"+1 574 594 3003",
    "sg:postcode":"46562",
    "sg:province":"IN",
    "wof:name":"Hide Away Rv",
    "wof:placetype":"venue"
},
  "geometry": {"coordinates":[-85.677348,41.264529],"type":"Point"}
}