{
  "type": "Feature",
  "properties": {
    "iso:country":"US",
    "sg:address":"2915 E State Rd 44",
    "sg:city":"Shelbyville",
    "sg:classifiers":[
        {
            "category":"Insurance",
            "subcategory":"Insurance Agent",
            "type":"Services"
        }
    ],
    "sg:phone":"+1 317 392 2501",
    "sg:postcode":"46176",
    "sg:province":"IN",
    "wof:name":"Pilkington North America Inc",
    "wof:placetype":"venue"
},
  "geometry": {"coordinates":[-85.73050499999999,39.528627],"type":"Point"}
}