{
  "type": "Feature",
  "properties": {
    "iso:country":"US",
    "sg:address":"17901 River Ave",
    "sg:city":"Noblesville",
    "sg:classifiers":[
        {
            "category":"Restaurant",
            "type":"Food & Drink"
        }
    ],
    "sg:phone":"+1 317 770 1839",
    "sg:postcode":"46062",
    "sg:province":"IN",
    "sg:tags":[
        "pizza"
    ],
    "wof:name":"Ageno's Coal Fired Pizza",
    "wof:placetype":"venue"
},
  "geometry": {"coordinates":[-86.02812400000001,40.047066],"type":"Point"}
}