{
  "type": "Feature",
  "properties": {
    "addr:full":"2001 Engle St Huntington IN 46750",
    "addr:housenumber":"2001",
    "addr:postcode":"46750",
    "addr:street":"Engle St",
    "iso:country":"US",
    "sg:address":"2001 Engle St",
    "sg:city":"Huntington",
    "sg:classifiers":[
        {
            "category":"Organizations",
            "subcategory":"Religious Organization",
            "type":"Services"
        }
    ],
    "sg:phone":"+1 260 356 0870",
    "sg:postcode":"46750",
    "sg:province":"IN",
    "sg:tags":[
        "church"
    ],
    "wof:name":"New Hope United Brethren Chr",
    "wof:placetype":"venue"
},
  "geometry": {"coordinates":[-85.497264,40.860898],"type":"Point"}
}