{
  "type": "Feature",
  "properties": {
    "iso:country":"US",
    "sg:address":"1714 N Leland Ave",
    "sg:city":"Indianapolis",
    "sg:classifiers":[
        {
            "category":"Social Services",
            "subcategory":"Child Care",
            "type":"Services"
        }
    ],
    "sg:phone":"+1 317 357 4086",
    "sg:postcode":"46218",
    "sg:province":"IN",
    "sg:tags":[
        "day"
    ],
    "wof:name":"Caring Cuddle Child Care",
    "wof:placetype":"venue"
},
  "geometry": {"coordinates":[-86.081754,39.791253],"type":"Point"}
}