{
  "type": "Feature",
  "properties": {
    "iso:country":"US",
    "sg:address":"908 N Franklin Rd",
    "sg:city":"Indianapolis",
    "sg:classifiers":[
        {
            "category":"Professional",
            "subcategory":"Secretarial Services",
            "type":"Services"
        }
    ],
    "sg:phone":"+1 317 356 4644",
    "sg:postcode":"46219",
    "sg:province":"IN",
    "sg:tags":[
        "reporting",
        "court"
    ],
    "wof:name":"Charles L Wise",
    "wof:placetype":"venue"
},
  "geometry": {"coordinates":[-86.026355,39.779347],"type":"Point"}
}