{
  "type": "Feature",
  "properties": {
    "iso:country":"US",
    "sg:address":"197 W State St",
    "sg:city":"East Brunswick",
    "sg:classifiers":[
        {
            "category":"Professional",
            "type":"Services"
        }
    ],
    "sg:phone":"+1 732 214 2660",
    "sg:postcode":"47834",
    "sg:province":"IN",
    "sg:tags":[
        "establishment"
    ],
    "wof:name":"Lets Go Trade",
    "wof:placetype":"venue"
},
  "geometry": {"coordinates":[-87.129763,39.523863],"type":"Point"}
}