{
  "type": "Feature",
  "properties": {
    "iso:country":"US",
    "sg:address":"6800 S 300 W",
    "sg:city":"North Judson",
    "sg:classifiers":[
        {
            "category":"Manufacturing",
            "subcategory":"Wood Products",
            "type":"Manufacturing & Wholesale Goods"
        }
    ],
    "sg:phone":"+1 574 896 2766",
    "sg:postcode":"46366",
    "sg:province":"IN",
    "sg:tags":[
        "pallet",
        "skid"
    ],
    "wof:name":"C E Kersting & Sons",
    "wof:placetype":"venue"
},
  "geometry": {"coordinates":[-86.756269,41.203687],"type":"Point"}
}