{
  "type": "Feature",
  "properties": {
    "addr:full":"612 Station Dr Carmel IN 46032",
    "addr:housenumber":"612",
    "addr:postcode":"46032",
    "addr:street":"Station Dr",
    "iso:country":"US",
    "sg:address":"612 Station Dr",
    "sg:city":"Carmel",
    "sg:classifiers":[
        {
            "category":"Shopping",
            "subcategory":"Computers & Home Electronics",
            "type":"Retail Goods"
        }
    ],
    "sg:phone":"+1 317 580 1922",
    "sg:postcode":"46032",
    "sg:province":"IN",
    "sg:website":"www.digitechcustom.net",
    "wof:name":"Digitech Custom Audio & Video",
    "wof:placetype":"venue"
},
  "geometry": {"coordinates":[-86.11640199999999,39.960499],"type":"Point"}
}