{
  "type": "Feature",
  "properties": {
    "iso:country":"US",
    "sg:address":"8190 S 900 W",
    "sg:city":"San Pierre",
    "sg:classifiers":[
        {
            "category":"Social Services",
            "subcategory":"Child Care",
            "type":"Services"
        }
    ],
    "sg:phone":"+1 219 828 3600",
    "sg:postcode":"46374",
    "sg:province":"IN",
    "wof:name":"Cribs To Crayons Child Care 2",
    "wof:placetype":"venue"
},
  "geometry": {"coordinates":[-86.871968,41.18396],"type":"Point"}
}