{
  "type": "Feature",
  "properties": {
    "iso:country":"US",
    "sg:address":"3120 S Madison St",
    "sg:city":"Muncie",
    "sg:classifiers":[
        {
            "category":"Shopping",
            "subcategory":"Clothing, Apparel, & Fashions",
            "type":"Retail Goods"
        }
    ],
    "sg:phone":"+1 765 282 8112",
    "sg:postcode":"47302",
    "sg:province":"IN",
    "sg:tags":[
        "furnishing"
    ],
    "wof:name":"Carl's Department Store",
    "wof:placetype":"venue"
},
  "geometry": {"coordinates":[-85.381587,40.165439],"type":"Point"}
}