{
  "type": "Feature",
  "properties": {
    "addr:full":"340 S 1st St Zionsville IN 46077",
    "addr:housenumber":"340",
    "addr:postcode":"46077",
    "addr:street":"S 1St St",
    "iso:country":"US",
    "sg:address":"340 S 1st St",
    "sg:city":"Zionsville",
    "sg:classifiers":[
        {
            "category":"Restaurant",
            "type":"Food & Drink"
        }
    ],
    "sg:phone":"+1 317 873 3751",
    "sg:postcode":"46077",
    "sg:province":"IN",
    "sg:tags":[
        "parlor",
        "ice",
        "cream"
    ],
    "sg:website":"http://www.dairyqueen.com",
    "wof:name":"Dairy Queen",
    "wof:placetype":"venue"
},
  "geometry": {"coordinates":[-86.261782,39.948915],"type":"Point"}
}