{
  "type": "Feature",
  "properties": {
    "addr:full":"510 W Adams St Plymouth IN 46563",
    "addr:housenumber":"510",
    "addr:postcode":"46563",
    "addr:street":"W Adams St",
    "iso:country":"US",
    "sg:address":"510 W Adams St",
    "sg:city":"Plymouth",
    "sg:classifiers":[
        {
            "category":"Wholesale",
            "subcategory":"Farm Supplies",
            "type":"Manufacturing & Wholesale Goods"
        }
    ],
    "sg:phone":"+1 574 936 3107",
    "sg:postcode":"46563",
    "sg:province":"IN",
    "sg:tags":[
        "fertilizer"
    ],
    "wof:name":"Fulton Marshall Farm Co-Op",
    "wof:placetype":"venue"
},
  "geometry": {"coordinates":[-86.314318,41.342358],"type":"Point"}
}