{
  "type": "Feature",
  "properties": {
    "iso:country":"US",
    "sg:address":"309 E Lincolnway",
    "sg:city":"Valparaiso",
    "sg:classifiers":[
        {
            "category":"Organizations",
            "subcategory":"Religious Organization",
            "type":"Services"
        }
    ],
    "sg:phone":"+1 219 465 6900",
    "sg:postcode":"46383",
    "sg:province":"IN",
    "wof:name":"Intervrsity Christn Fellowship",
    "wof:placetype":"venue"
},
  "geometry": {"coordinates":[-87.056301,41.467869],"type":"Point"}
}