{
  "type": "Feature",
  "properties": {
    "addr:full":"1400 Ortman Ln Lafayette IN 47909",
    "addr:housenumber":"1400",
    "addr:postcode":"47909",
    "addr:street":"Ortman Ln",
    "iso:country":"US",
    "sg:address":"1400 Ortman Ln",
    "sg:city":"Lafayette",
    "sg:classifiers":[
        {
            "category":"Organizations",
            "subcategory":"Religious Organization",
            "type":"Services"
        }
    ],
    "sg:phone":"+1 765 474 2445",
    "sg:postcode":"47909",
    "sg:province":"IN",
    "sg:tags":[
        "church"
    ],
    "wof:name":"Crestview United Brethren Chr",
    "wof:placetype":"venue"
},
  "geometry": {"coordinates":[-86.876029,40.374451],"type":"Point"}
}