{
  "type": "Feature",
  "properties": {
    "iso:country":"US",
    "sg:address":"651 Brookview Dr",
    "sg:city":"Greenwood",
    "sg:classifiers":[
        {
            "category":"Professional",
            "type":"Services"
        }
    ],
    "sg:phone":"+1 317 859 7362",
    "sg:postcode":"46142",
    "sg:province":"IN",
    "wof:name":"Pamela Harris Pt Inc",
    "wof:placetype":"venue"
},
  "geometry": {"coordinates":[-86.13363,39.621604],"type":"Point"}
}