{
  "type": "Feature",
  "properties": {
    "iso:country":"US",
    "sg:address":"3201 Middlebury St",
    "sg:city":"Elkhart",
    "sg:classifiers":[
        {
            "category":"Retail",
            "subcategory":"Auto Repair",
            "type":"Services"
        }
    ],
    "sg:phone":"+1 574 293 8933",
    "sg:postcode":"46516",
    "sg:province":"IN",
    "sg:tags":[
        "repairing",
        "automobile"
    ],
    "wof:name":"Culp's Auto Clinic Inc",
    "wof:placetype":"venue"
},
  "geometry": {"coordinates":[-85.917179,41.681379],"type":"Point"}
}