{
  "type": "Feature",
  "properties": {
    "addr:full":"23695 Ramble Wood Ln Elkhart IN 46516",
    "addr:postcode":"23695;46516",
    "addr:street":"Ramble Wood Ln",
    "iso:country":"US",
    "sg:address":"23695 Ramble Wood Ln",
    "sg:city":"Elkhart",
    "sg:classifiers":[
        {
            "category":"Health Services",
            "subcategory":"Health Practitioner",
            "type":"Services"
        }
    ],
    "sg:phone":"+1 574 294 1117",
    "sg:postcode":"46516",
    "sg:province":"IN",
    "sg:tags":[
        "paramedical"
    ],
    "wof:name":"Michiana Medex Inc",
    "wof:placetype":"venue"
},
  "geometry": {"coordinates":[-85.921363,41.670693],"type":"Point"}
}