{
  "type": "Feature",
  "properties": {
    "iso:country":"US",
    "sg:address":"359 N Jackson St",
    "sg:city":"Frankfort",
    "sg:classifiers":[
        {
            "category":"Manufacturing",
            "subcategory":"Petroleum Products",
            "type":"Manufacturing & Wholesale Goods"
        }
    ],
    "sg:phone":"+1 765 654 5311",
    "sg:postcode":"46041",
    "sg:province":"IN",
    "wof:name":"Tri County Petroleum",
    "wof:placetype":"venue"
},
  "geometry": {"coordinates":[-86.510638,40.28304],"type":"Point"}
}