{
  "type": "Feature",
  "properties": {
    "iso:country":"US",
    "sg:address":"1117 E Main St",
    "sg:city":"Greensburg",
    "sg:classifiers":[
        {
            "category":"Restaurant",
            "type":"Food & Drink"
        }
    ],
    "sg:phone":"+1 812 663 5240",
    "sg:postcode":"47240",
    "sg:province":"IN",
    "sg:tags":[
        "caterer"
    ],
    "wof:name":"Doris' Sugar Shack",
    "wof:placetype":"venue"
},
  "geometry": {"coordinates":[-85.467082,39.336459],"type":"Point"}
}