{
  "type": "Feature",
  "properties": {
    "iso:country":"US",
    "sg:address":"400 N High St",
    "sg:city":"Muncie",
    "sg:classifiers":[
        {
            "category":"Banks & Credit Unions",
            "subcategory":"Bank",
            "type":"Services"
        }
    ],
    "sg:phone":"+1 765 289 5626",
    "sg:postcode":"47305",
    "sg:province":"IN",
    "sg:tags":[
        "loan",
        "real estate"
    ],
    "wof:name":"Choice Mortgage Funding",
    "wof:placetype":"venue"
},
  "geometry": {"coordinates":[-85.387695,40.196164],"type":"Point"}
}