{
  "type": "Feature",
  "properties": {
    "iso:country":"US",
    "sg:address":"335 E Meridian St",
    "sg:city":"Atlanta",
    "sg:classifiers":[
        {
            "category":"Professional",
            "subcategory":"Management & Consulting",
            "type":"Services"
        }
    ],
    "sg:phone":"+1 765 292 2266",
    "sg:postcode":"46031",
    "sg:province":"IN",
    "wof:name":"Shepard & Associates",
    "wof:placetype":"venue"
},
  "geometry": {"coordinates":[-86.022893,40.217328],"type":"Point"}
}