{
  "type": "Feature",
  "properties": {
    "iso:country":"US",
    "sg:address":"311 N Morris St",
    "sg:city":"Farmland",
    "sg:classifiers":[
        {
            "category":"Retail",
            "subcategory":"Auto Repair",
            "type":"Services"
        }
    ],
    "sg:phone":"+1 765 468 6915",
    "sg:postcode":"47340",
    "sg:province":"IN",
    "sg:tags":[
        "repairing",
        "automobile"
    ],
    "wof:name":"Newton Auto & Radiator Svc",
    "wof:placetype":"venue"
},
  "geometry": {"coordinates":[-85.125031,40.192927],"type":"Point"}
}