{
  "type": "Feature",
  "properties": {
    "addr:full":"6729 Cobden Ln Indianapolis IN 46254",
    "addr:housenumber":"6729",
    "addr:postcode":"46254",
    "addr:street":"Cobden Ln",
    "iso:country":"US",
    "sg:address":"6729 Cobden Ln",
    "sg:city":"Indianapolis",
    "sg:classifiers":[
        {
            "category":"Building & Trades",
            "subcategory":"Pest Control",
            "type":"Services"
        }
    ],
    "sg:phone":"+1 317 329 8099",
    "sg:postcode":"46254",
    "sg:province":"IN",
    "wof:name":"Advance Termite & Pest Control",
    "wof:placetype":"venue"
},
  "geometry": {"coordinates":[-86.278447,39.832734],"type":"Point"}
}