{
  "type": "Feature",
  "properties": {
    "iso:country":"US",
    "sg:address":"53468 Ada Dr",
    "sg:city":"Elkhart",
    "sg:classifiers":[
        {
            "category":"Manufacturing",
            "subcategory":"Metals",
            "type":"Manufacturing & Wholesale Goods"
        }
    ],
    "sg:phone":"+1 574 264 9504",
    "sg:postcode":"46514",
    "sg:province":"IN",
    "sg:tags":[
        "stamping"
    ],
    "sg:website":"www.voyagerinc.net",
    "wof:name":"Voyager Inc",
    "wof:placetype":"venue"
},
  "geometry": {"coordinates":[-85.922728,41.718385],"type":"Point"}
}