{
  "type": "Feature",
  "properties": {
    "addr:full":"3669 Broadway Gary IN 46409",
    "addr:housenumber":"3669",
    "addr:postcode":"46409",
    "addr:street":"Broadway",
    "iso:country":"US",
    "sg:address":"3669 Broadway",
    "sg:city":"Gary",
    "sg:classifiers":[
        {
            "category":"Coffee & Tea",
            "type":"Food & Drink"
        },
        {
            "category":"Restaurant",
            "type":"Food & Drink"
        }
    ],
    "sg:phone":"+1 219 887 1745",
    "sg:postcode":"46409",
    "sg:province":"IN",
    "sg:tags":[
        "espresso"
    ],
    "wof:name":"Ohana Cafe",
    "wof:placetype":"venue"
},
  "geometry": {"coordinates":[-87.336507,41.551815],"type":"Point"}
}