{
  "type": "Feature",
  "properties": {
    "iso:country":"US",
    "sg:address":"1159 E Diamond Ave",
    "sg:city":"Evansville",
    "sg:classifiers":[
        {
            "category":"Wholesale",
            "subcategory":"Electrical",
            "type":"Manufacturing & Wholesale Goods"
        }
    ],
    "sg:phone":"+1 812 423 4257",
    "sg:postcode":"47711",
    "sg:province":"IN",
    "sg:tags":[
        "equipment",
        "electric",
        "supply"
    ],
    "wof:name":"Tri-State Lighting & Supply Co",
    "wof:placetype":"venue"
},
  "geometry": {"coordinates":[-87.54656199999999,37.999099],"type":"Point"}
}