{
  "type": "Feature",
  "properties": {
    "iso:country":"US",
    "sg:address":"1970 E Stop 13 Rd",
    "sg:city":"Indianapolis",
    "sg:classifiers":[
        {
            "category":"Personal",
            "subcategory":"Beauty Salon",
            "type":"Services"
        }
    ],
    "sg:phone":"+1 317 865 3392",
    "sg:postcode":"46227",
    "sg:province":"IN",
    "sg:tags":[
        "manicuring"
    ],
    "wof:name":"My Nails II",
    "wof:placetype":"venue"
},
  "geometry": {"coordinates":[-86.126062,39.638621],"type":"Point"}
}