{
  "type": "Feature",
  "properties": {
    "addr:full":"8996 S 500 W Wabash IN 46992",
    "addr:housenumber":"8996;500",
    "addr:postcode":"46992",
    "addr:street":"S;W Wabash",
    "iso:country":"US",
    "sg:address":"8996 S 500 W",
    "sg:city":"Wabash",
    "sg:classifiers":[
        {
            "category":"Organizations",
            "subcategory":"Religious Organization",
            "type":"Services"
        }
    ],
    "sg:phone":"+1 260 563 3910",
    "sg:postcode":"46992",
    "sg:province":"IN",
    "sg:tags":[
        "church"
    ],
    "wof:name":"College Corner Brethren Church",
    "wof:placetype":"venue"
},
  "geometry": {"coordinates":[-85.885109,40.694242],"type":"Point"}
}