{
  "type": "Feature",
  "properties": {
    "iso:country":"US",
    "sg:address":"68047 Co Rd 13",
    "sg:city":"Nappanee",
    "sg:classifiers":[
        {
            "category":"Building & Trades",
            "subcategory":"Construction",
            "type":"Services"
        }
    ],
    "sg:phone":"+1 574 831 2282",
    "sg:postcode":"46550",
    "sg:province":"IN",
    "sg:tags":[
        "carpentry",
        "contractor"
    ],
    "wof:name":"Lb Customs",
    "wof:placetype":"venue"
},
  "geometry": {"coordinates":[-85.924675,41.507709],"type":"Point"}
}