{
  "type": "Feature",
  "properties": {
    "addr:full":"2929 N 7th St Terre Haute IN 47804",
    "addr:housenumber":"2929",
    "addr:postcode":"47804",
    "addr:street":"N 7Th St",
    "iso:country":"US",
    "sg:address":"2929 N 7th St",
    "sg:city":"Terre Haute",
    "sg:classifiers":[
        {
            "category":"Organizations",
            "subcategory":"Religious Organization",
            "type":"Services"
        }
    ],
    "sg:phone":"+1 812 466 7241",
    "sg:postcode":"47804",
    "sg:province":"IN",
    "sg:tags":[
        "church"
    ],
    "sg:website":"www.thfirst.org",
    "wof:name":"First Assembly Of God",
    "wof:placetype":"venue"
},
  "geometry": {"coordinates":[-87.40723800000001,39.502971],"type":"Point"}
}