{
  "type": "Feature",
  "properties": {
    "addr:full":"7961 Calumet Ave Munster IN 46321",
    "addr:housenumber":"7961",
    "addr:postcode":"46321",
    "addr:street":"Calumet Ave",
    "iso:country":"US",
    "sg:address":"7961 Calumet Ave",
    "sg:city":"Munster",
    "sg:classifiers":[
        {
            "category":"Shopping",
            "subcategory":"Beauty & Cosmetics",
            "type":"Retail Goods"
        }
    ],
    "sg:phone":"+1 219 513 0405",
    "sg:postcode":"46321",
    "sg:province":"IN",
    "sg:tags":[
        "supply"
    ],
    "sg:website":"www.sallybeauty.com",
    "wof:name":"Sally Beauty Supply",
    "wof:placetype":"venue"
},
  "geometry": {"coordinates":[-87.508771,41.568388],"type":"Point"}
}