{
  "type": "Feature",
  "properties": {
    "iso:country":"US",
    "sg:address":"109 E Main St",
    "sg:city":"Warsaw",
    "sg:classifiers":[
        {
            "category":"Government",
            "subcategory":"Fire Station",
            "type":"Public Place"
        }
    ],
    "sg:phone":"+1 574 372 9501",
    "sg:postcode":"46580",
    "sg:province":"IN",
    "sg:tags":[
        "department"
    ],
    "wof:name":"Warsaw Fire Dept",
    "wof:placetype":"venue"
},
  "geometry": {"coordinates":[-85.856595,41.239165],"type":"Point"}
}