{
  "type": "Feature",
  "properties": {
    "iso:country":"US",
    "sg:address":"2345 Ripley St",
    "sg:city":"Lake Station",
    "sg:classifiers":[
        {
            "category":"Home & Garden",
            "subcategory":"Carpets & Floor Coverings",
            "type":"Retail Goods"
        }
    ],
    "sg:phone":"+1 219 962 5500",
    "sg:postcode":"46405",
    "sg:province":"IN",
    "sg:tags":[
        "material"
    ],
    "wof:name":"Carpet-Cuts Inc",
    "wof:placetype":"venue"
},
  "geometry": {"coordinates":[-87.239955,41.574954],"type":"Point"}
}