{
  "type": "Feature",
  "properties": {
    "iso:country":"US",
    "sg:address":"1913 N Michigan St",
    "sg:city":"Plymouth",
    "sg:classifiers":[
        {
            "category":"Professional",
            "subcategory":"Accounting & Tax Preparation",
            "type":"Services"
        }
    ],
    "sg:phone":"+1 574 935 0300",
    "sg:postcode":"46563",
    "sg:province":"IN",
    "sg:tags":[
        "return",
        "filing"
    ],
    "wof:name":"Jackson Hewitt Tax Svc",
    "wof:placetype":"venue"
},
  "geometry": {"coordinates":[-86.31160300000001,41.358805],"type":"Point"}
}