{
  "type": "Feature",
  "properties": {
    "iso:country":"US",
    "sg:address":"844 Surrey Hill Ct",
    "sg:city":"Greenwood",
    "sg:classifiers":[
        {
            "category":"Health Services",
            "subcategory":"Clinic",
            "type":"Services"
        }
    ],
    "sg:phone":"+1 317 888 4141",
    "sg:postcode":"46142",
    "sg:province":"IN",
    "sg:tags":[
        "specialty",
        "outpatient"
    ],
    "wof:name":"Wellness Center For Women Inc",
    "wof:placetype":"venue"
},
  "geometry": {"coordinates":[-86.127925,39.611045],"type":"Point"}
}