{
  "type": "Feature",
  "properties": {
    "iso:country":"US",
    "sg:address":"12 S Jefferson St",
    "sg:city":"Nashville",
    "sg:classifiers":[
        {
            "category":"Professional",
            "subcategory":"Lawyer & Legal Services",
            "type":"Services"
        }
    ],
    "sg:phone":"+1 812 988 0314",
    "sg:postcode":"47448",
    "sg:province":"IN",
    "sg:tags":[
        "attorney"
    ],
    "wof:name":"Thomas M Barr & Assoc",
    "wof:placetype":"venue"
},
  "geometry": {"coordinates":[-86.248217,39.207157],"type":"Point"}
}