{
  "type": "Feature",
  "properties": {
    "iso:country":"US",
    "sg:address":"1101 English Ave",
    "sg:city":"Indianapolis",
    "sg:classifiers":[
        {
            "category":"Bars & Pubs",
            "type":"Food & Drink"
        }
    ],
    "sg:phone":"+1 317 261 1218",
    "sg:postcode":"46203",
    "sg:province":"IN",
    "wof:name":"Ironworkers Corner Bar",
    "wof:placetype":"venue"
},
  "geometry": {"coordinates":[-86.136854,39.759659],"type":"Point"}
}