{
  "type": "Feature",
  "properties": {
    "iso:country":"US",
    "sg:address":"2925 S Co Rd 500 E",
    "sg:city":"Dupont",
    "sg:classifiers":[
        {
            "category":"Farming",
            "subcategory":"Farm",
            "type":"Manufacturing & Wholesale Goods"
        }
    ],
    "sg:phone":"+1 812 873 6557",
    "sg:postcode":"47231",
    "sg:province":"IN",
    "wof:name":"Mark Erler Farms",
    "wof:placetype":"venue"
},
  "geometry": {"coordinates":[-85.520422,38.942154],"type":"Point"}
}