{
  "type": "Feature",
  "properties": {
    "iso:country":"US",
    "sg:address":"1 E Chicago Ave",
    "sg:city":"East Chicago",
    "sg:classifiers":[
        {
            "category":"Recreation",
            "subcategory":"Arcade",
            "type":"Entertainment"
        }
    ],
    "sg:phone":"+1 219 391 7777",
    "sg:postcode":"46312",
    "sg:province":"IN",
    "sg:tags":[
        "casino"
    ],
    "wof:name":"Showboat Mardi Gras Casino",
    "wof:placetype":"venue"
},
  "geometry": {"coordinates":[-87.47001299999999,41.629324],"type":"Point"}
}