{
  "type": "Feature",
  "properties": {
    "iso:country":"US",
    "sg:address":"120 W 3rd St",
    "sg:city":"Winchester",
    "sg:classifiers":[
        {
            "category":"Retail",
            "subcategory":"Repair Shop",
            "type":"Services"
        },
        {
            "category":"Social Services",
            "type":"Services"
        }
    ],
    "sg:phone":"+1 765 546 0116",
    "sg:postcode":"47394",
    "sg:province":"IN",
    "sg:tags":[
        "information",
        "abuse",
        "treatment",
        "center"
    ],
    "wof:name":"Living Life Clean LLC",
    "wof:placetype":"venue"
},
  "geometry": {"coordinates":[-84.98165400000001,40.176519],"type":"Point"}
}