{
  "type": "Feature",
  "properties": {
    "iso:country":"US",
    "sg:address":"421 E 23rd St",
    "sg:city":"Anderson",
    "sg:classifiers":[
        {
            "category":"Bars & Pubs",
            "type":"Food & Drink"
        }
    ],
    "sg:phone":"+1 765 644 2323",
    "sg:postcode":"46016",
    "sg:province":"IN",
    "wof:name":"South Park Cafe",
    "wof:placetype":"venue"
},
  "geometry": {"coordinates":[-85.674063,40.093435],"type":"Point"}
}