{
  "type": "Feature",
  "properties": {
    "iso:country":"US",
    "sg:address":"7816 Ashton Pl",
    "sg:city":"Fishers",
    "sg:classifiers":[
        {
            "category":"Professional",
            "type":"Services"
        }
    ],
    "sg:phone":"+1 317 849 3210",
    "sg:postcode":"46038",
    "sg:province":"IN",
    "wof:name":"Superior Searches Inc",
    "wof:placetype":"venue"
},
  "geometry": {"coordinates":[-86.025192,39.961468],"type":"Point"}
}