{
  "type": "Feature",
  "properties": {
    "iso:country":"US",
    "sg:address":"2758 E 300 S",
    "sg:city":"Franklin",
    "sg:phone":"+1 317 738 2650",
    "sg:postcode":"46131",
    "sg:province":"IN",
    "sg:tags":[
        "farm",
        "corn",
        "beef",
        "feedlot",
        "cattle"
    ],
    "wof:name":"Hugh Dunn",
    "wof:placetype":"venue"
},
  "geometry": {"coordinates":[-86.059653,39.433599],"type":"Point"}
}