{
  "type": "Feature",
  "properties": {
    "iso:country":"US",
    "sg:address":"2634 167th St",
    "sg:city":"Hammond",
    "sg:classifiers":[
        {
            "category":"Wholesale",
            "subcategory":"Hardware",
            "type":"Manufacturing & Wholesale Goods"
        }
    ],
    "sg:phone":"+1 219 845 4006",
    "sg:postcode":"46323",
    "sg:province":"IN",
    "sg:tags":[
        "equipment",
        "heating",
        "system"
    ],
    "wof:name":"Mikson's Heating & AC",
    "wof:placetype":"venue"
},
  "geometry": {"coordinates":[-87.464104,41.591886],"type":"Point"}
}