{
  "type": "Feature",
  "properties": {
    "iso:country":"US",
    "sg:address":"216 W High St",
    "sg:city":"Elkhart",
    "sg:classifiers":[
        {
            "category":"Professional",
            "subcategory":"Lawyer & Legal Services",
            "type":"Services"
        }
    ],
    "sg:phone":"+1 574 293 6525",
    "sg:postcode":"46516",
    "sg:province":"IN",
    "sg:tags":[
        "attorney"
    ],
    "wof:name":"Lee F Mellinger Law Office",
    "wof:placetype":"venue"
},
  "geometry": {"coordinates":[-85.97514,41.684568],"type":"Point"}
}