{
  "type": "Feature",
  "properties": {
    "iso:country":"US",
    "sg:address":"1515 Gostlin St",
    "sg:city":"Hammond",
    "sg:classifiers":[
        {
            "category":"Freight",
            "type":"Transportation"
        }
    ],
    "sg:phone":"+1 219 933 7429",
    "sg:postcode":"46327",
    "sg:province":"IN",
    "sg:tags":[
        "delivery",
        "package"
    ],
    "wof:name":"Fedex",
    "wof:placetype":"venue"
},
  "geometry": {"coordinates":[-87.49724399999999,41.632205],"type":"Point"}
}