{
  "type": "Feature",
  "properties": {
    "addr:full":"2301 W Lexington Ave Elkhart IN 46514",
    "addr:housenumber":"2301",
    "addr:postcode":"46514",
    "addr:street":"W Lexington Ave",
    "iso:country":"US",
    "sg:address":"2301 W Lexington Ave",
    "sg:city":"Elkhart",
    "sg:classifiers":[
        {
            "category":"Real Estate",
            "subcategory":"Real Estate Operator",
            "type":"Services"
        }
    ],
    "sg:phone":"+1 574 293 9321",
    "sg:postcode":"46514",
    "sg:province":"IN",
    "sg:tags":[
        "apartment"
    ],
    "wof:name":"Lexington Square Apartments",
    "wof:placetype":"venue"
},
  "geometry": {"coordinates":[-86.005161,41.683097],"type":"Point"}
}