{
  "type": "Feature",
  "properties": {
    "iso:country":"US",
    "sg:address":"10116 Coldwater Rd",
    "sg:city":"Fort Wayne",
    "sg:classifiers":[
        {
            "category":"Insurance",
            "subcategory":"Insurance Agent",
            "type":"Services"
        }
    ],
    "sg:phone":"+1 260 489 3500",
    "sg:postcode":"46825",
    "sg:province":"IN",
    "wof:name":"Bodenhafer Insurance",
    "wof:placetype":"venue"
},
  "geometry": {"coordinates":[-85.130945,41.175302],"type":"Point"}
}