{
  "type": "Feature",
  "properties": {
    "iso:country":"US",
    "sg:address":"526 Belvedere Dr",
    "sg:city":"Kokomo",
    "sg:classifiers":[
        {
            "category":"Wholesale",
            "subcategory":"Electrical",
            "type":"Manufacturing & Wholesale Goods"
        }
    ],
    "sg:phone":"+1 765 452 2811",
    "sg:postcode":"46901",
    "sg:province":"IN",
    "sg:tags":[
        "communication",
        "radio",
        "system"
    ],
    "wof:name":"Integrity Communications",
    "wof:placetype":"venue"
},
  "geometry": {"coordinates":[-86.10639,40.48261],"type":"Point"}
}