{
  "type": "Feature",
  "properties": {
    "addr:full":"1810 Redwood Ln Lafayette IN 47905",
    "addr:housenumber":"1810",
    "addr:postcode":"47905",
    "addr:street":"Redwood Ln",
    "iso:country":"US",
    "sg:address":"1810 Redwood Ln",
    "sg:city":"Lafayette",
    "sg:classifiers":[
        {
            "category":"Real Estate",
            "subcategory":"Real Estate Operator",
            "type":"Services"
        }
    ],
    "sg:phone":"+1 765 420 7900",
    "sg:postcode":"47905",
    "sg:province":"IN",
    "sg:tags":[
        "apartment"
    ],
    "wof:name":"Burk Management Inc",
    "wof:placetype":"venue"
},
  "geometry": {"coordinates":[-86.851,40.435572],"type":"Point"}
}