{
  "type": "Feature",
  "properties": {
    "iso:country":"US",
    "sg:address":"1627 Park Castle Way",
    "sg:city":"Indianapolis",
    "sg:classifiers":[
        {
            "category":"Communications",
            "subcategory":"Film & Video Production",
            "type":"Services"
        }
    ],
    "sg:phone":"+1 317 891 8081",
    "sg:postcode":"46229",
    "sg:province":"IN",
    "sg:tags":[
        "motion",
        "picture"
    ],
    "sg:website":"www.mycreationshop.com",
    "wof:name":"Graves Video Productions",
    "wof:placetype":"venue"
},
  "geometry": {"coordinates":[-85.986361,39.79077],"type":"Point"}
}