{
  "type": "Feature",
  "properties": {
    "iso:country":"US",
    "sg:address":"2901 Langston Dr",
    "sg:city":"Evansville",
    "sg:classifiers":[
        {
            "category":"Building & Trades",
            "subcategory":"Construction",
            "type":"Services"
        }
    ],
    "sg:phone":"+1 812 457 6153",
    "sg:postcode":"47725",
    "sg:province":"IN",
    "sg:tags":[
        "home",
        "builder"
    ],
    "wof:name":"Brian Stevens Homes",
    "wof:placetype":"venue"
},
  "geometry": {"coordinates":[-87.51325799999999,38.094448],"type":"Point"}
}