{
  "type": "Feature",
  "properties": {
    "addr:full":"1633 E 1000 S Keystone IN 46759",
    "addr:housenumber":"1633",
    "addr:postcode":"46759",
    "addr:street":"E 1000 S Keystone",
    "iso:country":"US",
    "sg:address":"1633 E 1000 S",
    "sg:city":"Keystone",
    "sg:classifiers":[
        {
            "category":"Building & Trades",
            "subcategory":"Construction",
            "type":"Services"
        }
    ],
    "sg:phone":"+1 260 346 2680",
    "sg:postcode":"46759",
    "sg:province":"IN",
    "sg:tags":[
        "excavation",
        "contractor"
    ],
    "wof:name":"Jarrod Hahn Excavating",
    "wof:placetype":"venue"
},
  "geometry": {"coordinates":[-85.19895,40.596604],"type":"Point"}
}