{
  "type": "Feature",
  "properties": {
    "iso:country":"US",
    "sg:address":"2497 State St",
    "sg:city":"Lafayette",
    "sg:classifiers":[
        {
            "category":"Organizations",
            "subcategory":"Religious Organization",
            "type":"Services"
        }
    ],
    "sg:phone":"+1 765 471 8305",
    "sg:postcode":"47905",
    "sg:province":"IN",
    "wof:name":"Abundant Love Outreach Church",
    "wof:placetype":"venue"
},
  "geometry": {"coordinates":[-86.868452,40.400713],"type":"Point"}
}