{
  "type": "Feature",
  "properties": {
    "addr:full":"7072 Emblem Dr Indianapolis IN 46237",
    "addr:postcode":"7072;46237",
    "addr:street":"Emblem Dr",
    "iso:country":"US",
    "sg:address":"7072 Emblem Dr",
    "sg:city":"Indianapolis",
    "sg:classifiers":[
        {
            "category":"Retail",
            "subcategory":"Auto Repair",
            "type":"Services"
        }
    ],
    "sg:phone":"+1 317 882 4180",
    "sg:postcode":"46237",
    "sg:province":"IN",
    "sg:tags":[
        "automobile",
        "lubrication"
    ],
    "wof:name":"Jiffy Lube",
    "wof:placetype":"venue"
},
  "geometry": {"coordinates":[-86.081596,39.664647],"type":"Point"}
}