{
  "type": "Feature",
  "properties": {
    "iso:country":"US",
    "sg:address":"1910 S State Ave",
    "sg:city":"Indianapolis",
    "sg:classifiers":[
        {
            "category":"Professional",
            "subcategory":"Testing Lab",
            "type":"Services"
        }
    ],
    "sg:phone":"+1 317 788 9930",
    "sg:postcode":"46203",
    "sg:province":"IN",
    "sg:tags":[
        "chemist"
    ],
    "wof:name":"World Wide Chemicals",
    "wof:placetype":"venue"
},
  "geometry": {"coordinates":[-86.130422,39.741638],"type":"Point"}
}