{
  "type": "Feature",
  "properties": {
    "iso:country":"US",
    "sg:address":"2530 Sandcrest Blvd",
    "sg:city":"Columbus",
    "sg:classifiers":[
        {
            "category":"Health Services",
            "subcategory":"Hospital",
            "type":"Services"
        }
    ],
    "sg:phone":"+1 812 372 3177",
    "sg:postcode":"47203",
    "sg:province":"IN",
    "sg:tags":[
        "mental"
    ],
    "wof:name":"Association Of Personal & Fmly",
    "wof:placetype":"venue"
},
  "geometry": {"coordinates":[-85.878412,39.224341],"type":"Point"}
}