{
  "type": "Feature",
  "properties": {
    "iso:country":"US",
    "sg:address":"56848 Ferrettie Ct",
    "sg:city":"Mishawaka",
    "sg:classifiers":[
        {
            "category":"Building & Trades",
            "subcategory":"Plumbing",
            "type":"Services"
        }
    ],
    "sg:phone":"+1 574 259 7847",
    "sg:postcode":"46545",
    "sg:province":"IN",
    "sg:tags":[
        "conditioning",
        "air",
        "system",
        "contractor"
    ],
    "sg:website":"www.bwheatingandcooling.com",
    "wof:name":"B W Heating & Cooling Inc",
    "wof:placetype":"venue"
},
  "geometry": {"coordinates":[-86.13126699999999,41.670349],"type":"Point"}
}