{
  "type": "Feature",
  "properties": {
    "iso:country":"US",
    "sg:address":"1101 S Whitney Rd",
    "sg:city":"Muncie",
    "sg:classifiers":[
        {
            "category":"Building & Trades",
            "subcategory":"Plumbing",
            "type":"Services"
        }
    ],
    "sg:phone":"+1 765 747 6074",
    "sg:postcode":"47302",
    "sg:province":"IN",
    "sg:tags":[
        "plumbing",
        "contractor"
    ],
    "wof:name":"Needler's Master Plumbing",
    "wof:placetype":"venue"
},
  "geometry": {"coordinates":[-85.292333,40.178039],"type":"Point"}
}