{
  "type": "Feature",
  "properties": {
    "iso:country":"US",
    "sg:address":"5200 E 600 N",
    "sg:city":"Greenfield",
    "sg:classifiers":[
        {
            "category":"Farming",
            "subcategory":"Farm",
            "type":"Manufacturing & Wholesale Goods"
        }
    ],
    "sg:phone":"+1 317 326 2589",
    "sg:postcode":"46140",
    "sg:province":"IN",
    "sg:tags":[
        "industrial",
        "general",
        "crop",
        "supply"
    ],
    "wof:name":"Mohr R & S Family Farms Inc",
    "wof:placetype":"venue"
},
  "geometry": {"coordinates":[-85.694945,39.872643],"type":"Point"}
}