{
  "type": "Feature",
  "properties": {
    "iso:country":"US",
    "sg:address":"1133 N Sugar Bend Run",
    "sg:city":"Greenfield",
    "sg:classifiers":[
        {
            "category":"Shopping",
            "subcategory":"Used Merchandise",
            "type":"Retail Goods"
        }
    ],
    "sg:phone":"+1 317 326 2754",
    "sg:postcode":"46140",
    "sg:province":"IN",
    "wof:name":"Robinsrarebookscom",
    "wof:placetype":"venue"
},
  "geometry": {"coordinates":[-85.851403,39.801291],"type":"Point"}
}