{
  "type": "Feature",
  "properties": {
    "iso:country":"US",
    "sg:address":"7322 White Oak Ave",
    "sg:city":"Hammond",
    "sg:classifiers":[
        {
            "category":"Freight",
            "type":"Transportation"
        }
    ],
    "sg:phone":"+1 219 989 0747",
    "sg:postcode":"46324",
    "sg:province":"IN",
    "sg:tags":[
        "trucking"
    ],
    "wof:name":"Collins Trucking",
    "wof:placetype":"venue"
},
  "geometry": {"coordinates":[-87.490522,41.581174],"type":"Point"}
}