{
  "type": "Feature",
  "properties": {
    "iso:country":"US",
    "sg:address":"1203 N Co Rd 730 E",
    "sg:city":"Michigantown",
    "sg:classifiers":[
        {
            "category":"Building & Trades",
            "subcategory":"Construction",
            "type":"Services"
        }
    ],
    "sg:phone":"+1 765 249 5188",
    "sg:postcode":"46057",
    "sg:province":"IN",
    "sg:tags":[
        "designer",
        "dealer",
        "pool",
        "swimming"
    ],
    "wof:name":"L & M Svc",
    "wof:placetype":"venue"
},
  "geometry": {"coordinates":[-86.372578,40.302416],"type":"Point"}
}