{
  "type": "Feature",
  "properties": {
    "iso:country":"US",
    "sg:address":"8711 Old State Rd 60",
    "sg:city":"Sellersburg",
    "sg:classifiers":[
        {
            "category":"Building & Trades",
            "subcategory":"Construction",
            "type":"Services"
        }
    ],
    "sg:phone":"+1 812 246 9638",
    "sg:postcode":"47172",
    "sg:province":"IN",
    "sg:tags":[
        "concrete",
        "contractor"
    ],
    "wof:name":"Hecker Construction",
    "wof:placetype":"venue"
},
  "geometry": {"coordinates":[-85.769169,38.385561],"type":"Point"}
}