{
  "type": "Feature",
  "properties": {
    "iso:country":"US",
    "sg:address":"1301 Willow St",
    "sg:city":"Vincennes",
    "sg:classifiers":[
        {
            "category":"Wholesale",
            "subcategory":"Electrical",
            "type":"Manufacturing & Wholesale Goods"
        }
    ],
    "sg:phone":"+1 812 882 2938",
    "sg:postcode":"47591",
    "sg:province":"IN",
    "sg:tags":[
        "equipment",
        "electric",
        "supply"
    ],
    "sg:website":"www.kirbyrisk.com",
    "wof:name":"Kirby Risk Electrical Supply",
    "wof:placetype":"venue"
},
  "geometry": {"coordinates":[-87.533458,38.664698],"type":"Point"}
}