{
  "type": "Feature",
  "properties": {
    "addr:full":"11 W Leota Rd Scottsburg IN 47170",
    "addr:housenumber":"11",
    "addr:postcode":"47170",
    "addr:street":"W Leota Rd",
    "iso:country":"US",
    "sg:address":"11 W Leota Rd",
    "sg:city":"Scottsburg",
    "sg:classifiers":[
        {
            "category":"Organizations",
            "subcategory":"Religious Organization",
            "type":"Services"
        }
    ],
    "sg:phone":"+1 812 752 3943",
    "sg:postcode":"47170",
    "sg:province":"IN",
    "sg:tags":[
        "church"
    ],
    "wof:name":"Vienna Baptist",
    "wof:placetype":"venue"
},
  "geometry": {"coordinates":[-85.77486399999999,38.648882],"type":"Point"}
}