{
  "type": "Feature",
  "properties": {
    "iso:country":"US",
    "sg:address":"8164 Robin Hill Dr",
    "sg:city":"Newburgh",
    "sg:classifiers":[
        {
            "category":"Health Services",
            "subcategory":"Doctor",
            "type":"Services"
        }
    ],
    "sg:phone":"+1 812 853 8700",
    "sg:postcode":"47630",
    "sg:province":"IN",
    "sg:tags":[
        "dentist"
    ],
    "wof:name":"Gerald D Enlow DDS",
    "wof:placetype":"venue"
},
  "geometry": {"coordinates":[-87.398392,37.96023],"type":"Point"}
}