{
  "type": "Feature",
  "properties": {
    "iso:country":"US",
    "sg:address":"5515 W 38th St",
    "sg:city":"Indianapolis",
    "sg:classifiers":[
        {
            "category":"Restaurant",
            "type":"Food & Drink"
        }
    ],
    "sg:menulink":"http://www.allmenus.com/in/speedway/13970-olive-garden-italian-restaurant/menu/",
    "sg:phone":"+1 317 293 4725",
    "sg:postcode":"46254",
    "sg:province":"IN",
    "sg:tags":[
        "italian"
    ],
    "wof:name":"Olive Garden Italian Restaurant",
    "wof:placetype":"venue"
},
  "geometry": {"coordinates":[-86.257212,39.823105],"type":"Point"}
}