{
  "type": "Feature",
  "properties": {
    "iso:country":"US",
    "sg:address":"2174 E 54th St",
    "sg:city":"Indianapolis",
    "sg:classifiers":[
        {
            "category":"Professional",
            "subcategory":"Art Services",
            "type":"Services"
        }
    ],
    "sg:phone":"+1 317 255 2820",
    "sg:postcode":"46220",
    "sg:province":"IN",
    "sg:tags":[
        "photographer"
    ],
    "wof:name":"Passport Photo",
    "wof:placetype":"venue"
},
  "geometry": {"coordinates":[-86.123102,39.851379],"type":"Point"}
}