{
  "type": "Feature",
  "properties": {
    "iso:country":"US",
    "sg:address":"323 Conrad Harcourt Way",
    "sg:city":"Rushville",
    "sg:classifiers":[
        {
            "category":"Health Services",
            "subcategory":"Doctor",
            "type":"Services"
        }
    ],
    "sg:phone":"+1 765 938 2045",
    "sg:postcode":"46173",
    "sg:province":"IN",
    "sg:tags":[
        "physician",
        "surgeon"
    ],
    "wof:name":"Jetmore Bawa & Hirons",
    "wof:placetype":"venue"
},
  "geometry": {"coordinates":[-85.440928,39.623204],"type":"Point"}
}