{
  "type": "Feature",
  "properties": {
    "addr:full":"2198 Southlake Mall Merrillville IN 46410",
    "addr:housenumber":"2198",
    "addr:postcode":"46410",
    "addr:street":"Southlake Mall",
    "iso:country":"US",
    "sg:address":"2198 Southlake Mall",
    "sg:city":"Merrillville",
    "sg:classifiers":[
        {
            "category":"Shopping",
            "subcategory":"Clothing, Apparel, & Fashions",
            "type":"Retail Goods"
        },
        {
            "category":"Shopping",
            "subcategory":"Bicycles & Sporting Goods",
            "type":"Retail Goods"
        }
    ],
    "sg:phone":"+1 219 769 1525",
    "sg:postcode":"46410",
    "sg:province":"IN",
    "sg:tags":[
        "apparel",
        "racing",
        "merchandise",
        "sportswear"
    ],
    "wof:name":"All Stars Inc",
    "wof:placetype":"venue"
},
  "geometry": {"coordinates":[-87.309967,41.470451],"type":"Point"}
}