{
  "type": "Feature",
  "properties": {
    "iso:country":"US",
    "sg:address":"1751 Thornapple Cir",
    "sg:city":"Valparaiso",
    "sg:classifiers":[
        {
            "category":"Health Services",
            "subcategory":"Doctor",
            "type":"Services"
        }
    ],
    "sg:phone":"+1 219 464 1141",
    "sg:postcode":"46385",
    "sg:province":"IN",
    "sg:tags":[
        "dentist"
    ],
    "wof:name":"Heritage Dental",
    "wof:placetype":"venue"
},
  "geometry": {"coordinates":[-87.080351,41.459727],"type":"Point"}
}