{
  "type": "Feature",
  "properties": {
    "iso:country":"US",
    "sg:address":"1266 Bell Rd",
    "sg:city":"Chandler",
    "sg:classifiers":[
        {
            "category":"Manufacturing",
            "subcategory":"Motor Vehicles & Parts",
            "type":"Manufacturing & Wholesale Goods"
        }
    ],
    "sg:phone":"+1 812 925 3176",
    "sg:postcode":"47610",
    "sg:province":"IN",
    "sg:tags":[
        "body",
        "car"
    ],
    "wof:name":"Bc Sales",
    "wof:placetype":"venue"
},
  "geometry": {"coordinates":[-87.404595,38.015031],"type":"Point"}
}