{
  "type": "Feature",
  "properties": {
    "addr:full":"2203 N State St Greenfield IN 46140",
    "addr:housenumber":"2203",
    "addr:postcode":"46140",
    "addr:street":"N State St",
    "iso:country":"US",
    "sg:address":"2203 N State St",
    "sg:city":"Greenfield",
    "sg:classifiers":[
        {
            "category":"Restaurant",
            "type":"Food & Drink"
        }
    ],
    "sg:phone":"+1 317 462 5272",
    "sg:postcode":"46140",
    "sg:province":"IN",
    "wof:name":"El Rodeo Mexican Restaurant",
    "wof:placetype":"venue"
},
  "geometry": {"coordinates":[-85.769711,39.816099],"type":"Point"}
}