{
  "type": "Feature",
  "properties": {
    "iso:country":"US",
    "sg:address":"2155 Liberty Church Rd",
    "sg:city":"Martinsville",
    "sg:classifiers":[
        {
            "category":"Wholesale",
            "subcategory":"Farm Supplies",
            "type":"Manufacturing & Wholesale Goods"
        }
    ],
    "sg:phone":"+1 765 342 3079",
    "sg:postcode":"46151",
    "sg:province":"IN",
    "sg:tags":[
        "grain"
    ],
    "wof:name":"Maxwell Farm Svc",
    "wof:placetype":"venue"
},
  "geometry": {"coordinates":[-86.47056000000001,39.374433],"type":"Point"}
}