{
  "type": "Feature",
  "properties": {
    "iso:country":"US",
    "sg:address":"3826 Main St",
    "sg:city":"East Chicago",
    "sg:classifiers":[
        {
            "category":"Professional",
            "subcategory":"Lawyer & Legal Services",
            "type":"Services"
        }
    ],
    "sg:phone":"+1 219 378 1111",
    "sg:postcode":"46312",
    "sg:province":"IN",
    "wof:name":"Corinth Bishop Atty",
    "wof:placetype":"venue"
},
  "geometry": {"coordinates":[-87.445023,41.643042],"type":"Point"}
}