{
  "type": "Feature",
  "properties": {
    "iso:country":"US",
    "sg:address":"4707 W Western Ave",
    "sg:city":"South Bend",
    "sg:classifiers":[
        {
            "category":"Autos & Motor Vehicles",
            "subcategory":"Automobile Sales",
            "type":"Retail Goods"
        }
    ],
    "sg:phone":"+1 574 234 9031",
    "sg:postcode":"46619",
    "sg:province":"IN",
    "sg:tags":[
        "truck"
    ],
    "wof:name":"Whiteford Ford Trucks",
    "wof:placetype":"venue"
},
  "geometry": {"coordinates":[-86.31383700000001,41.671986],"type":"Point"}
}