{
  "type": "Feature",
  "properties": {
    "iso:country":"US",
    "sg:address":"2488 Getz Rd",
    "sg:city":"Fort Wayne",
    "sg:classifiers":[
        {
            "category":"Recreation",
            "type":"Entertainment"
        }
    ],
    "sg:phone":"+1 260 459 6665",
    "sg:postcode":"46804",
    "sg:province":"IN",
    "sg:tags":[
        "parlor",
        "billiard"
    ],
    "wof:name":"Mick's Rec Room",
    "wof:placetype":"venue"
},
  "geometry": {"coordinates":[-85.219428,41.061328],"type":"Point"}
}