{
  "type": "Feature",
  "properties": {
    "iso:country":"US",
    "sg:address":"11525 Lantern Rd",
    "sg:city":"Fishers",
    "sg:classifiers":[
        {
            "category":"Personal",
            "subcategory":"Beauty Salon",
            "type":"Services"
        }
    ],
    "sg:phone":"+1 317 570 1865",
    "sg:postcode":"46038",
    "sg:province":"IN",
    "wof:name":"All About Me",
    "wof:placetype":"venue"
},
  "geometry": {"coordinates":[-86.013847,39.95442],"type":"Point"}
}