{
  "type": "Feature",
  "properties": {
    "iso:country":"US",
    "sg:address":"1611 E Markland Ave",
    "sg:city":"Kokomo",
    "sg:classifiers":[
        {
            "category":"Banks & Credit Unions",
            "subcategory":"Bank",
            "type":"Services"
        }
    ],
    "sg:phone":"+1 765 457 8321",
    "sg:postcode":"46901",
    "sg:province":"IN",
    "sg:tags":[
        "financing"
    ],
    "wof:name":"American General Finance Inc",
    "wof:placetype":"venue"
},
  "geometry": {"coordinates":[-86.111535,40.476577],"type":"Point"}
}