{
  "type": "Feature",
  "properties": {
    "iso:country":"US",
    "sg:address":"4498 N 1st Ave",
    "sg:city":"Evansville",
    "sg:classifiers":[
        {
            "category":"Health Services",
            "subcategory":"Doctor",
            "type":"Services"
        }
    ],
    "sg:phone":"+1 812 436 7280",
    "sg:postcode":"47710",
    "sg:province":"IN",
    "sg:tags":[
        "physician",
        "surgeon"
    ],
    "wof:name":"Deaconess Primary Care-Seniors",
    "wof:placetype":"venue"
},
  "geometry": {"coordinates":[-87.574076,38.020901],"type":"Point"}
}