{
  "type": "Feature",
  "properties": {
    "iso:country":"US",
    "sg:address":"4627 W Richland Plz",
    "sg:city":"Bloomington",
    "sg:classifiers":[
        {
            "category":"Professional",
            "subcategory":"Lawyer & Legal Services",
            "type":"Services"
        }
    ],
    "sg:phone":"+1 812 876 2770",
    "sg:postcode":"47404",
    "sg:province":"IN",
    "sg:tags":[
        "attorney"
    ],
    "wof:name":"P Mason Clark",
    "wof:placetype":"venue"
},
  "geometry": {"coordinates":[-86.593082,39.21471],"type":"Point"}
}