{
  "type": "Feature",
  "properties": {
    "addr:full":"8325 White Oak Ave Munster IN 46321",
    "addr:housenumber":"8325",
    "addr:postcode":"46321",
    "addr:street":"White Oak Ave",
    "iso:country":"US",
    "sg:address":"8325 White Oak Ave",
    "sg:city":"Munster",
    "sg:classifiers":[
        {
            "category":"Shopping",
            "type":"Retail Goods"
        }
    ],
    "sg:phone":"+1 219 838 7314",
    "sg:postcode":"46321",
    "sg:province":"IN",
    "sg:tags":[
        "cosmetic",
        "perfume"
    ],
    "wof:name":"Mary Kay Cosmetics",
    "wof:placetype":"venue"
},
  "geometry": {"coordinates":[-87.49043899999999,41.559874],"type":"Point"}
}