{
  "type": "Feature",
  "properties": {
    "iso:country":"US",
    "sg:address":"2809 W Co Rd 240 NW",
    "sg:city":"Greensburg",
    "sg:classifiers":[
        {
            "category":"Farming",
            "subcategory":"Farm",
            "type":"Manufacturing & Wholesale Goods"
        }
    ],
    "sg:phone":"+1 812 663 5557",
    "sg:postcode":"47240",
    "sg:province":"IN",
    "wof:name":"B G Reiger Farms",
    "wof:placetype":"venue"
},
  "geometry": {"coordinates":[-85.524212,39.352592],"type":"Point"}
}