{
  "type": "Feature",
  "properties": {
    "addr:full":"1405 N Baldwin Ave Marion IN 46952",
    "addr:housenumber":"1405",
    "addr:postcode":"46952",
    "addr:street":"N Baldwin Ave",
    "iso:country":"US",
    "sg:address":"1405 N Baldwin Ave",
    "sg:city":"Marion",
    "sg:classifiers":[
        {
            "category":"Health Services",
            "subcategory":"Doctor",
            "type":"Services"
        }
    ],
    "sg:phone":"+1 765 671 7140",
    "sg:postcode":"46952",
    "sg:province":"IN",
    "sg:tags":[
        "physician",
        "surgeon"
    ],
    "wof:name":"Marion Family Practice",
    "wof:placetype":"venue"
},
  "geometry": {"coordinates":[-85.673922,40.575205],"type":"Point"}
}