{
  "type": "Feature",
  "properties": {
    "iso:country":"US",
    "sg:address":"757 N 200 E",
    "sg:city":"Huntington",
    "sg:classifiers":[
        {
            "category":"Manufacturing",
            "subcategory":"Signs",
            "type":"Manufacturing & Wholesale Goods"
        }
    ],
    "sg:phone":"+1 260 758 2258",
    "sg:postcode":"46750",
    "sg:province":"IN",
    "wof:name":"J & M Signs-Plastics",
    "wof:placetype":"venue"
},
  "geometry": {"coordinates":[-85.412493,40.843746],"type":"Point"}
}