{
  "type": "Feature",
  "properties": {
    "iso:country":"US",
    "sg:address":"7037 Stones River Dr",
    "sg:city":"Indianapolis",
    "sg:classifiers":[
        {
            "category":"Building & Trades",
            "subcategory":"Construction",
            "type":"Services"
        }
    ],
    "sg:phone":"+1 317 862 6800",
    "sg:postcode":"46259",
    "sg:province":"IN",
    "sg:tags":[
        "home",
        "builder"
    ],
    "sg:website":"www.princetonhomesonline.com",
    "wof:name":"Princeton Lakes",
    "wof:placetype":"venue"
},
  "geometry": {"coordinates":[-86.028291,39.665372],"type":"Point"}
}