{
  "type": "Feature",
  "properties": {
    "iso:country":"US",
    "sg:address":"8811 W Adaline St",
    "sg:city":"Yorktown",
    "sg:classifiers":[
        {
            "category":"Building & Trades",
            "subcategory":"Plumbing",
            "type":"Services"
        }
    ],
    "sg:phone":"+1 765 284 5995",
    "sg:postcode":"47396",
    "sg:province":"IN",
    "sg:tags":[
        "plumbing",
        "contractor"
    ],
    "wof:name":"Don Harman Sewer & Septic",
    "wof:placetype":"venue"
},
  "geometry": {"coordinates":[-85.489702,40.174542],"type":"Point"}
}