{
  "type": "Feature",
  "properties": {
    "iso:country":"US",
    "sg:address":"5725 E 77th St",
    "sg:city":"Indianapolis",
    "sg:classifiers":[
        {
            "category":"Professional",
            "subcategory":"Accounting & Tax Preparation",
            "type":"Services"
        }
    ],
    "sg:phone":"+1 317 842 0279",
    "sg:postcode":"46250",
    "sg:province":"IN",
    "wof:name":"Manuel W Kent CPA",
    "wof:placetype":"venue"
},
  "geometry": {"coordinates":[-86.07026399999999,39.894181],"type":"Point"}
}