{
  "type": "Feature",
  "properties": {
    "iso:country":"US",
    "sg:address":"4701 Rockville Rd",
    "sg:city":"Indianapolis",
    "sg:classifiers":[
        {
            "category":"Sports & Exercise",
            "subcategory":"Race Track",
            "type":"Entertainment"
        }
    ],
    "sg:phone":"+1 317 244 1000",
    "sg:postcode":"46222",
    "sg:province":"IN",
    "sg:tags":[
        "equipment",
        "supply"
    ],
    "sg:website":"www.goodridge.net",
    "wof:name":"Goodridge USA Inc",
    "wof:placetype":"venue"
},
  "geometry": {"coordinates":[-86.239674,39.764517],"type":"Point"}
}