{
  "type": "Feature",
  "properties": {
    "iso:country":"US",
    "sg:address":"664 E Illinois St",
    "sg:city":"Evansville",
    "sg:classifiers":[
        {
            "category":"Bars & Pubs",
            "type":"Food & Drink"
        }
    ],
    "sg:phone":"+1 812 423 0828",
    "sg:postcode":"47711",
    "sg:province":"IN",
    "wof:name":"Sidetrack Tavern",
    "wof:placetype":"venue"
},
  "geometry": {"coordinates":[-87.554367,37.979067],"type":"Point"}
}