{
  "type": "Feature",
  "properties": {
    "iso:country":"US",
    "sg:address":"2215 S Madison St",
    "sg:city":"Muncie",
    "sg:classifiers":[
        {
            "category":"Freight",
            "type":"Transportation"
        }
    ],
    "sg:phone":"+1 765 286 0766",
    "sg:postcode":"47302",
    "sg:province":"IN",
    "sg:tags":[
        "commercial",
        "storage"
    ],
    "wof:name":"Paul Davis Mini Warehouses",
    "wof:placetype":"venue"
},
  "geometry": {"coordinates":[-85.381725,40.174523],"type":"Point"}
}