{
  "type": "Feature",
  "properties": {
    "iso:country":"US",
    "sg:address":"1558 E Co Rd 800 N",
    "sg:city":"Orleans",
    "sg:classifiers":[
        {
            "category":"Retail",
            "subcategory":"Repair Shop",
            "type":"Services"
        }
    ],
    "sg:phone":"+1 812 865 3335",
    "sg:postcode":"47452",
    "sg:province":"IN",
    "sg:tags":[
        "scooter",
        "motorcycle",
        "motor"
    ],
    "wof:name":"K & R Cycles",
    "wof:placetype":"venue"
},
  "geometry": {"coordinates":[-86.438082,38.6708],"type":"Point"}
}