{
  "type": "Feature",
  "properties": {
    "iso:country":"US",
    "sg:address":"602 W McCarty St",
    "sg:city":"Indianapolis",
    "sg:classifiers":[
        {
            "category":"Building & Trades",
            "subcategory":"Electrical",
            "type":"Services"
        }
    ],
    "sg:phone":"+1 317 231 2363",
    "sg:postcode":"46225",
    "sg:province":"IN",
    "sg:tags":[
        "electrical",
        "contractor"
    ],
    "wof:name":"Scherer Industrial Group",
    "wof:placetype":"venue"
},
  "geometry": {"coordinates":[-86.16985699999999,39.756731],"type":"Point"}
}