{
  "type": "Feature",
  "properties": {
    "iso:country":"US",
    "sg:address":"5883 Beau Jardin Dr",
    "sg:city":"Indianapolis",
    "sg:classifiers":[
        {
            "category":"Professional",
            "type":"Services"
        }
    ],
    "sg:phone":"+1 317 781 9347",
    "sg:postcode":"46237",
    "sg:province":"IN",
    "sg:tags":[
        "establishment"
    ],
    "wof:name":"Lucent Technologies",
    "wof:placetype":"venue"
},
  "geometry": {"coordinates":[-86.065663,39.691327],"type":"Point"}
}