{
  "type": "Feature",
  "properties": {
    "iso:country":"US",
    "sg:address":"660 Co Rd 15",
    "sg:city":"Elkhart",
    "sg:classifiers":[
        {
            "category":"Professional",
            "subcategory":"Art Services",
            "type":"Services"
        }
    ],
    "sg:phone":"+1 574 522 4005",
    "sg:postcode":"46516",
    "sg:province":"IN",
    "sg:tags":[
        "graphic"
    ],
    "wof:name":"Falcon Enterprises",
    "wof:placetype":"venue"
},
  "geometry": {"coordinates":[-85.90739499999999,41.688418],"type":"Point"}
}