{
  "type": "Feature",
  "properties": {
    "addr:full":"3606 W Co Rd 300 S Greensburg IN 47240",
    "addr:housenumber":"3606",
    "addr:postcode":"47240",
    "addr:street":"W Co Rd 300 S",
    "iso:country":"US",
    "sg:address":"3606 W Co Rd 300 S",
    "sg:city":"Greensburg",
    "sg:phone":"+1 812 663 3429",
    "sg:postcode":"47240",
    "sg:province":"IN",
    "sg:tags":[
        "wheat",
        "farm",
        "corn",
        "crop",
        "field",
        "soybean"
    ],
    "wof:name":"Fred Clark",
    "wof:placetype":"venue"
},
  "geometry": {"coordinates":[-85.549234,39.291921],"type":"Point"}
}