{
  "type": "Feature",
  "properties": {
    "iso:country":"US",
    "sg:address":"419 E Kirkwood Ave",
    "sg:city":"Bloomington",
    "sg:classifiers":[
        {
            "category":"Deli",
            "type":"Food & Drink"
        },
        {
            "category":"Food & Beverages",
            "subcategory":"Bakery",
            "type":"Retail Goods"
        }
    ],
    "sg:phone":"+1 812 336 5300",
    "sg:postcode":"47408",
    "sg:province":"IN",
    "sg:tags":[
        "sandwich"
    ],
    "sg:website":"www.bloomingfoods.coop",
    "wof:name":"Bloomingfoods Market and Deli",
    "wof:placetype":"venue"
},
  "geometry": {"coordinates":[-86.529494,39.166672],"type":"Point"}
}