{
  "type": "Feature",
  "properties": {
    "iso:country":"US",
    "sg:address":"1106 James Ave",
    "sg:city":"Bedford",
    "sg:classifiers":[
        {
            "category":"Banks & Credit Unions",
            "subcategory":"Bank",
            "type":"Services"
        }
    ],
    "sg:phone":"+1 812 278 8790",
    "sg:postcode":"47421",
    "sg:province":"IN",
    "sg:tags":[
        "cashing",
        "check"
    ],
    "wof:name":"Advance America",
    "wof:placetype":"venue"
},
  "geometry": {"coordinates":[-86.518272,38.867165],"type":"Point"}
}