{
  "type": "Feature",
  "properties": {
    "iso:country":"US",
    "sg:address":"325 S Oak St",
    "sg:city":"Winchester",
    "sg:classifiers":[
        {
            "category":"Education",
            "subcategory":"Special Training",
            "type":"Public Place"
        }
    ],
    "sg:phone":"+1 765 584 5440",
    "sg:postcode":"47394",
    "sg:province":"IN",
    "sg:tags":[
        "program"
    ],
    "wof:name":"River Valley Resources",
    "wof:placetype":"venue"
},
  "geometry": {"coordinates":[-84.973356,40.170105],"type":"Point"}
}