{
  "type": "Feature",
  "properties": {
    "iso:country":"US",
    "sg:address":"1015 E Mechanic St",
    "sg:city":"Brazil",
    "sg:classifiers":[
        {
            "category":"Manufacturing",
            "subcategory":"Tools & Machinery",
            "type":"Manufacturing & Wholesale Goods"
        }
    ],
    "sg:phone":"+1 812 446 6141",
    "sg:postcode":"47834",
    "sg:province":"IN",
    "sg:tags":[
        "machine",
        "shop"
    ],
    "sg:website":"www.morrismfg.com",
    "wof:name":"Morris Mfg & Sales Corp",
    "wof:placetype":"venue"
},
  "geometry": {"coordinates":[-87.112863,39.52349],"type":"Point"}
}