{
  "type": "Feature",
  "properties": {
    "iso:country":"US",
    "sg:address":"10438 W 800 S",
    "sg:city":"Westville",
    "sg:classifiers":[
        {
            "category":"Professional",
            "type":"Services"
        }
    ],
    "sg:phone":"+1 219 733 2684",
    "sg:postcode":"46391",
    "sg:province":"IN",
    "wof:name":"Herrold Custom Svc",
    "wof:placetype":"venue"
},
  "geometry": {"coordinates":[-86.901362,41.49195],"type":"Point"}
}