{
  "type": "Feature",
  "properties": {
    "iso:country":"US",
    "sg:address":"213 E Ohio St",
    "sg:city":"Bluffton",
    "sg:classifiers":[
        {
            "category":"Insurance",
            "subcategory":"Insurance Agent",
            "type":"Services"
        }
    ],
    "sg:phone":"+1 260 824 2580",
    "sg:postcode":"46714",
    "sg:province":"IN",
    "wof:name":"Lockwood Insurance & Financial",
    "wof:placetype":"venue"
},
  "geometry": {"coordinates":[-85.16904100000001,40.733492],"type":"Point"}
}