{
  "type": "Feature",
  "properties": {
    "iso:country":"US",
    "sg:address":"5373 S 700 W",
    "sg:city":"Pendleton",
    "sg:classifiers":[
        {
            "category":"Farming",
            "subcategory":"Farm",
            "type":"Manufacturing & Wholesale Goods"
        }
    ],
    "sg:phone":"+1 765 534 4461",
    "sg:postcode":"46064",
    "sg:province":"IN",
    "sg:tags":[
        "crop",
        "general"
    ],
    "wof:name":"Scott Family Farms Inc",
    "wof:placetype":"venue"
},
  "geometry": {"coordinates":[-85.805494,40.017262],"type":"Point"}
}