{
  "type": "Feature",
  "properties": {
    "iso:country":"US",
    "sg:address":"244 Shepherd Ct",
    "sg:city":"Greenfield",
    "sg:classifiers":[
        {
            "category":"Professional",
            "subcategory":"Computer Services",
            "type":"Services"
        }
    ],
    "sg:phone":"+1 317 462 2400",
    "sg:postcode":"46140",
    "sg:province":"IN",
    "sg:tags":[
        "engine",
        "search",
        "internet"
    ],
    "sg:website":"www.greenfieldin.biz",
    "wof:name":"GREENFIELDIN.BIZ",
    "wof:placetype":"venue"
},
  "geometry": {"coordinates":[-85.762671,39.768662],"type":"Point"}
}