{
  "type": "Feature",
  "properties": {
    "iso:country":"US",
    "sg:address":"17 E Lincolnway",
    "sg:city":"Valparaiso",
    "sg:classifiers":[
        {
            "category":"Food & Beverages",
            "subcategory":"Candy",
            "type":"Retail Goods"
        }
    ],
    "sg:phone":"+1 219 477 5924",
    "sg:postcode":"46383",
    "sg:province":"IN",
    "sg:tags":[
        "confectionery"
    ],
    "wof:name":"Chocolate Indulgence",
    "wof:placetype":"venue"
},
  "geometry": {"coordinates":[-87.059882,41.467894],"type":"Point"}
}