{
  "type": "Feature",
  "properties": {
    "iso:country":"US",
    "sg:address":"1607 Scatterfield Rd",
    "sg:city":"Anderson",
    "sg:classifiers":[
        {
            "category":"Education",
            "subcategory":"Special Training",
            "type":"Public Place"
        }
    ],
    "sg:phone":"+1 765 643 1211",
    "sg:postcode":"46016",
    "sg:province":"IN",
    "sg:tags":[
        "tutoring"
    ],
    "wof:name":"Sylvan Learning Ctr",
    "wof:placetype":"venue"
},
  "geometry": {"coordinates":[-85.652793,40.10078],"type":"Point"}
}