{
  "type": "Feature",
  "properties": {
    "iso:country":"US",
    "sg:address":"6548 Old Vincennes Rd",
    "sg:city":"Floyds Knobs",
    "sg:classifiers":[
        {
            "category":"Home & Garden",
            "subcategory":"Home Furnishings",
            "type":"Retail Goods"
        }
    ],
    "sg:phone":"+1 812 923 8660",
    "sg:postcode":"47119",
    "sg:province":"IN",
    "wof:name":"Bobbi Ceramics Barn",
    "wof:placetype":"venue"
},
  "geometry": {"coordinates":[-85.9297,38.33367],"type":"Point"}
}