{
  "type": "Feature",
  "properties": {
    "addr:full":"1919 S Walnut St Bloomington IN 47401",
    "addr:housenumber":"1919",
    "addr:postcode":"47401",
    "addr:street":"S Walnut St",
    "iso:country":"US",
    "sg:address":"1919 S Walnut St",
    "sg:city":"Bloomington",
    "sg:phone":"+1 812 334 3637",
    "sg:postcode":"47401",
    "sg:province":"IN",
    "sg:website":"http://www.mcdonalds.com",
    "wof:name":"McDonald's",
    "wof:placetype":"venue"
},
  "geometry": {"coordinates":[-86.53203600000001,39.144892],"type":"Point"}
}