{
  "type": "Feature",
  "properties": {
    "iso:country":"US",
    "sg:address":"8121 Center Run Dr",
    "sg:city":"Indianapolis",
    "sg:classifiers":[
        {
            "category":"Health Services",
            "subcategory":"Doctor",
            "type":"Services"
        }
    ],
    "sg:phone":"+1 317 849 9304",
    "sg:postcode":"46250",
    "sg:province":"IN",
    "sg:tags":[
        "clinic"
    ],
    "wof:name":"Planned Parenthood",
    "wof:placetype":"venue"
},
  "geometry": {"coordinates":[-86.057852,39.904246],"type":"Point"}
}