{
  "type": "Feature",
  "properties": {
    "iso:country":"US",
    "sg:address":"559 N Green River Rd",
    "sg:city":"Evansville",
    "sg:classifiers":[
        {
            "category":"Restaurant",
            "type":"Food & Drink"
        }
    ],
    "sg:menulink":"http://www.allmenus.com/in/knight/64259-chuck-e-cheeses/menu/",
    "sg:phone":"+1 812 473 0004",
    "sg:postcode":"47715",
    "sg:province":"IN",
    "sg:tags":[
        "american",
        "pizza"
    ],
    "wof:name":"Chuck E. Cheese's",
    "wof:placetype":"venue"
},
  "geometry": {"coordinates":[-87.492591,37.982005],"type":"Point"}
}