{
  "type": "Feature",
  "properties": {
    "addr:full":"517 Broadway Chesterton IN 46304",
    "addr:housenumber":"517",
    "addr:postcode":"46304",
    "addr:street":"Broadway",
    "iso:country":"US",
    "sg:address":"517 Broadway",
    "sg:city":"Chesterton",
    "sg:classifiers":[
        {
            "category":"Government",
            "subcategory":"Office",
            "type":"Public Place"
        }
    ],
    "sg:phone":"+1 219 926 3194",
    "sg:postcode":"46304",
    "sg:province":"IN",
    "wof:name":"Porter County Coroner's Office",
    "wof:placetype":"venue"
},
  "geometry": {"coordinates":[-87.058848,41.611245],"type":"Point"}
}