{
  "type": "Feature",
  "properties": {
    "iso:country":"US",
    "sg:address":"7040 Forest Ave",
    "sg:city":"Hammond",
    "sg:classifiers":[
        {
            "category":"Real Estate",
            "subcategory":"Architect",
            "type":"Services"
        }
    ],
    "sg:phone":"+1 219 931 4117",
    "sg:postcode":"46324",
    "sg:province":"IN",
    "wof:name":"Paul E Taylor Aia",
    "wof:placetype":"venue"
},
  "geometry": {"coordinates":[-87.523804,41.5854],"type":"Point"}
}