{
  "type": "Feature",
  "properties": {
    "addr:full":"571 S Burr St Lowell IN 46356",
    "addr:housenumber":"571",
    "addr:postcode":"46356",
    "addr:street":"S Burr St",
    "iso:country":"US",
    "sg:address":"571 S Burr St",
    "sg:city":"Lowell",
    "sg:classifiers":[
        {
            "category":"Real Estate",
            "subcategory":"Real Estate Operator",
            "type":"Services"
        }
    ],
    "sg:phone":"+1 219 696 1177",
    "sg:postcode":"46356",
    "sg:province":"IN",
    "sg:tags":[
        "apartment"
    ],
    "wof:name":"The Oaks Ix Apartments",
    "wof:placetype":"venue"
},
  "geometry": {"coordinates":[-87.40085999999999,41.282198],"type":"Point"}
}