{
  "type": "Feature",
  "properties": {
    "iso:country":"US",
    "sg:address":"1935 Hillside Dr",
    "sg:city":"Franklin",
    "sg:classifiers":[
        {
            "category":"Professional",
            "subcategory":"Management & Consulting",
            "type":"Services"
        }
    ],
    "sg:phone":"+1 317 738 4121",
    "sg:postcode":"46131",
    "sg:province":"IN",
    "wof:name":"Triple Impact LLC",
    "wof:placetype":"venue"
},
  "geometry": {"coordinates":[-86.023854,39.491885],"type":"Point"}
}