{
  "type": "Feature",
  "properties": {
    "iso:country":"US",
    "sg:address":"401 W Co Rd 200 N",
    "sg:city":"Osgood",
    "sg:classifiers":[
        {
            "category":"Organizations",
            "subcategory":"Religious Organization",
            "type":"Services"
        }
    ],
    "sg:phone":"+1 812 689 4758",
    "sg:postcode":"47037",
    "sg:province":"IN",
    "sg:tags":[
        "church"
    ],
    "wof:name":"Rodney Wesleyan Church",
    "wof:placetype":"venue"
},
  "geometry": {"coordinates":[-85.269955,39.103452],"type":"Point"}
}