{
  "type": "Feature",
  "properties": {
    "iso:country":"US",
    "sg:address":"7415 Dobson St",
    "sg:city":"Indianapolis",
    "sg:classifiers":[
        {
            "category":"Building & Trades",
            "subcategory":"Plumbing",
            "type":"Services"
        }
    ],
    "sg:phone":"+1 317 291 6769",
    "sg:postcode":"46268",
    "sg:province":"IN",
    "sg:tags":[
        "conditioning",
        "air",
        "system",
        "contractor"
    ],
    "wof:name":"Circle City Heating & Air Cond",
    "wof:placetype":"venue"
},
  "geometry": {"coordinates":[-86.238558,39.885793],"type":"Point"}
}