{
  "type": "Feature",
  "properties": {
    "addr:full":"801 Court St Evansville IN 47708",
    "addr:housenumber":"801",
    "addr:postcode":"47708",
    "addr:street":"Court St",
    "iso:country":"US",
    "sg:address":"801 Court St",
    "sg:city":"Evansville",
    "sg:classifiers":[
        {
            "category":"Organizations",
            "subcategory":"Community Association",
            "type":"Services"
        }
    ],
    "sg:phone":"+1 812 422 7373",
    "sg:postcode":"47708",
    "sg:province":"IN",
    "sg:tags":[
        "fraternal"
    ],
    "wof:name":"Fraternal Order Of Police",
    "wof:placetype":"venue"
},
  "geometry": {"coordinates":[-87.567954,37.976689],"type":"Point"}
}