{
  "type": "Feature",
  "properties": {
    "addr:full":"47 S Meridian St Indianapolis IN 46204",
    "addr:housenumber":"47",
    "addr:postcode":"46204",
    "addr:street":"S Meridian St",
    "iso:country":"US",
    "sg:address":"47 S Meridian St",
    "sg:city":"Indianapolis",
    "sg:classifiers":[
        {
            "category":"Real Estate",
            "subcategory":"Architect",
            "type":"Services"
        }
    ],
    "sg:phone":"+1 317 636 7469",
    "sg:postcode":"46204",
    "sg:province":"IN",
    "sg:website":"www.urscorp.com",
    "wof:name":"URS Corp",
    "wof:placetype":"venue"
},
  "geometry": {"coordinates":[-86.158118,39.766338],"type":"Point"}
}