{
  "type": "Feature",
  "properties": {
    "iso:country":"US",
    "sg:address":"395 W Gates Rd",
    "sg:city":"Columbia City",
    "sg:classifiers":[
        {
            "category":"Insurance",
            "subcategory":"Insurance Agent",
            "type":"Services"
        }
    ],
    "sg:phone":"+1 260 244 6354",
    "sg:postcode":"46725",
    "sg:province":"IN",
    "wof:name":"Mary Louise Strouse Insurance",
    "wof:placetype":"venue"
},
  "geometry": {"coordinates":[-85.499315,41.163708],"type":"Point"}
}