{
  "type": "Feature",
  "properties": {
    "iso:country":"US",
    "sg:address":"4541 E State Rd 10",
    "sg:city":"Demotte",
    "sg:classifiers":[
        {
            "category":"Utilities",
            "subcategory":"Fuel Oil & Lpg",
            "type":"Services"
        }
    ],
    "sg:phone":"+1 219 345 3412",
    "sg:postcode":"46310",
    "sg:province":"IN",
    "wof:name":"Boezeman Oil Co Inc",
    "wof:placetype":"venue"
},
  "geometry": {"coordinates":[-87.303848,41.144588],"type":"Point"}
}