{
  "type": "Feature",
  "properties": {
    "addr:full":"5412 N 700 E Montpelier IN 47359",
    "addr:housenumber":"5412",
    "addr:postcode":"47359",
    "addr:street":"N 700 E",
    "iso:country":"US",
    "sg:address":"5412 N 700 E",
    "sg:city":"Montpelier",
    "sg:classifiers":[
        {
            "category":"Retail",
            "subcategory":"Auto Repair",
            "type":"Services"
        }
    ],
    "sg:phone":"+1 765 728 5856",
    "sg:postcode":"47359",
    "sg:province":"IN",
    "sg:tags":[
        "body",
        "repairing",
        "automobile",
        "dent",
        "removal",
        "painting"
    ],
    "wof:name":"Feltts Fleet Vehicle Restoring",
    "wof:placetype":"venue"
},
  "geometry": {"coordinates":[-85.24009700000001,40.528785],"type":"Point"}
}