{
  "type": "Feature",
  "properties": {
    "iso:country":"US",
    "sg:address":"4049 Plum Creek Rd",
    "sg:city":"Nashville",
    "sg:classifiers":[
        {
            "category":"Manufacturing",
            "subcategory":"Lumber",
            "type":"Manufacturing & Wholesale Goods"
        }
    ],
    "sg:phone":"+1 812 988 6896",
    "sg:postcode":"47448",
    "sg:province":"IN",
    "sg:tags":[
        "product",
        "forest",
        "gathering"
    ],
    "wof:name":"Needmore Bamboo Co",
    "wof:placetype":"venue"
},
  "geometry": {"coordinates":[-86.308191,39.244876],"type":"Point"}
}