{
  "type": "Feature",
  "properties": {
    "addr:full":"687 E 50 N Flora IN 46929",
    "addr:housenumber":"687;50 n",
    "addr:postcode":"46929",
    "addr:street":"E;Flora In",
    "iso:country":"US",
    "sg:address":"687 E 50 N",
    "sg:city":"Flora",
    "sg:classifiers":[
        {
            "category":"Organizations",
            "subcategory":"Religious Organization",
            "type":"Services"
        }
    ],
    "sg:phone":"+1 574 967 3018",
    "sg:postcode":"46929",
    "sg:province":"IN",
    "sg:tags":[
        "church"
    ],
    "wof:name":"Jubilee Fellowship",
    "wof:placetype":"venue"
},
  "geometry": {"coordinates":[-86.50941899999999,40.554281],"type":"Point"}
}