{
  "type": "Feature",
  "properties": {
    "iso:country":"US",
    "sg:address":"310 Blacketor Dr",
    "sg:city":"Rochester",
    "sg:classifiers":[
        {
            "category":"Building & Trades",
            "subcategory":"Construction",
            "type":"Services"
        }
    ],
    "sg:phone":"+1 574 223 4644",
    "sg:postcode":"46975",
    "sg:province":"IN",
    "sg:tags":[
        "paving",
        "contractor"
    ],
    "sg:website":"www.ebpaving.com",
    "wof:name":"E & B Paving Inc",
    "wof:placetype":"venue"
},
  "geometry": {"coordinates":[-86.199257,41.073391],"type":"Point"}
}