{
  "type": "Feature",
  "properties": {
    "iso:country":"US",
    "sg:address":"4929 New Haven Ave",
    "sg:city":"Fort Wayne",
    "sg:classifiers":[
        {
            "category":"Wholesale",
            "subcategory":"Metals & Minerals",
            "type":"Manufacturing & Wholesale Goods"
        }
    ],
    "sg:phone":"+1 260 432 3524",
    "sg:postcode":"46803",
    "sg:province":"IN",
    "sg:tags":[
        "steel",
        "warehouse"
    ],
    "sg:website":"www.alro.com",
    "wof:name":"Alro Steel Corp",
    "wof:placetype":"venue"
},
  "geometry": {"coordinates":[-85.075249,41.06909],"type":"Point"}
}