{
  "type": "Feature",
  "properties": {
    "addr:full":"115 Columbia Dr Winona Lake IN 46590",
    "addr:housenumber":"115",
    "addr:postcode":"46590",
    "addr:street":"Columbia Dr",
    "iso:country":"US",
    "sg:address":"115 Columbia Dr",
    "sg:city":"Winona Lake",
    "sg:classifiers":[
        {
            "category":"Building & Trades",
            "subcategory":"Construction",
            "type":"Services"
        }
    ],
    "sg:phone":"+1 574 269 7956",
    "sg:postcode":"46590",
    "sg:province":"IN",
    "sg:tags":[
        "home",
        "improvement"
    ],
    "wof:name":"Mike Deck Construction",
    "wof:placetype":"venue"
},
  "geometry": {"coordinates":[-85.82042300000001,41.22122],"type":"Point"}
}