{
  "type": "Feature",
  "properties": {
    "iso:country":"US",
    "sg:address":"2834 45th St",
    "sg:city":"Highland",
    "sg:classifiers":[
        {
            "category":"Professional",
            "subcategory":"Lawyer & Legal Services",
            "type":"Services"
        }
    ],
    "sg:phone":"+1 219 924 4740",
    "sg:postcode":"46322",
    "sg:province":"IN",
    "sg:tags":[
        "attorney"
    ],
    "wof:name":"Skozen & Misner",
    "wof:placetype":"venue"
},
  "geometry": {"coordinates":[-87.46072700000001,41.537402],"type":"Point"}
}