{
  "type": "Feature",
  "properties": {
    "iso:country":"US",
    "sg:address":"8625 Maple View Dr",
    "sg:city":"Indianapolis",
    "sg:classifiers":[
        {
            "category":"Organizations",
            "subcategory":"Community Association",
            "type":"Services"
        }
    ],
    "sg:phone":"+1 317 885 8684",
    "sg:postcode":"46217",
    "sg:province":"IN",
    "wof:name":"Delta Theta Tau Sorority",
    "wof:placetype":"venue"
},
  "geometry": {"coordinates":[-86.174725,39.640251],"type":"Point"}
}