{
  "type": "Feature",
  "properties": {
    "addr:full":"1140 N State Rd 135 Greenwood IN 46142",
    "addr:housenumber":"1140;135",
    "addr:postcode":"46142",
    "addr:street":"N State Rd",
    "iso:country":"US",
    "sg:address":"1140 N State Rd 135",
    "sg:city":"Greenwood",
    "sg:classifiers":[
        {
            "category":"Retail",
            "subcategory":"Repair Shop",
            "type":"Services"
        }
    ],
    "sg:phone":"+1 317 888 5010",
    "sg:postcode":"46142",
    "sg:province":"IN",
    "wof:name":"Frame Connection Co",
    "wof:placetype":"venue"
},
  "geometry": {"coordinates":[-86.158461,39.632887],"type":"Point"}
}