{
  "type": "Feature",
  "properties": {
    "iso:country":"US",
    "sg:address":"4624 E 10th St",
    "sg:city":"Indianapolis",
    "sg:classifiers":[
        {
            "category":"Shopping",
            "subcategory":"Gifts & Souvenirs",
            "type":"Retail Goods"
        }
    ],
    "sg:phone":"+1 317 353 2359",
    "sg:postcode":"46201",
    "sg:province":"IN",
    "sg:tags":[
        "novelty"
    ],
    "wof:name":"Dr Feel Good",
    "wof:placetype":"venue"
},
  "geometry": {"coordinates":[-86.090748,39.781547],"type":"Point"}
}