{
  "type": "Feature",
  "properties": {
    "iso:country":"US",
    "sg:address":"454 Raven Cir",
    "sg:city":"Brownsburg",
    "sg:classifiers":[
        {
            "category":"Building & Trades",
            "subcategory":"Construction",
            "type":"Services"
        }
    ],
    "sg:phone":"+1 317 852 6900",
    "sg:postcode":"46112",
    "sg:province":"IN",
    "sg:tags":[
        "home",
        "builder"
    ],
    "wof:name":"Pulte Homes Corp",
    "wof:placetype":"venue"
},
  "geometry": {"coordinates":[-86.423648,39.84494],"type":"Point"}
}