{
  "type": "Feature",
  "properties": {
    "iso:country":"US",
    "sg:address":"1521 E McKinley Ave",
    "sg:city":"Mishawaka",
    "sg:classifiers":[
        {
            "category":"Retail",
            "subcategory":"Car Wash",
            "type":"Services"
        }
    ],
    "sg:phone":"+1 574 258 5353",
    "sg:postcode":"46545",
    "sg:province":"IN",
    "sg:tags":[
        "automobile",
        "detail",
        "clean"
    ],
    "wof:name":"Headers Car Care",
    "wof:placetype":"venue"
},
  "geometry": {"coordinates":[-86.16079000000001,41.680246],"type":"Point"}
}