{
  "type": "Feature",
  "properties": {
    "addr:full":"12450 Plymouth Goshen Trl Plymouth IN 46563",
    "addr:housenumber":"12450",
    "addr:postcode":"46563",
    "addr:street":"Goshen Trl",
    "iso:country":"US",
    "sg:address":"12450 Plymouth Goshen Trl",
    "sg:city":"Plymouth",
    "sg:classifiers":[
        {
            "category":"Organizations",
            "subcategory":"Religious Organization",
            "type":"Services"
        }
    ],
    "sg:phone":"+1 574 936 5877",
    "sg:postcode":"46563",
    "sg:province":"IN",
    "sg:tags":[
        "church"
    ],
    "wof:name":"United Pentecostal Church",
    "wof:placetype":"venue"
},
  "geometry": {"coordinates":[-86.29841399999999,41.359583],"type":"Point"}
}