{
  "type": "Feature",
  "properties": {
    "iso:country":"US",
    "sg:address":"3251 S State Rd 135",
    "sg:city":"Greenwood",
    "sg:classifiers":[
        {
            "category":"Farming",
            "subcategory":"Farm",
            "type":"Manufacturing & Wholesale Goods"
        }
    ],
    "sg:phone":"+1 317 535 5121",
    "sg:postcode":"46143",
    "sg:province":"IN",
    "wof:name":"Honey Creek Farms",
    "wof:placetype":"venue"
},
  "geometry": {"coordinates":[-86.158855,39.562129],"type":"Point"}
}