{
  "type": "Feature",
  "properties": {
    "addr:full":"1300 N Main St Rushville IN 46173",
    "addr:housenumber":"1300",
    "addr:postcode":"46173",
    "addr:street":"N Main St",
    "iso:country":"US",
    "sg:address":"1300 N Main St",
    "sg:city":"Rushville",
    "sg:classifiers":[
        {
            "category":"Professional",
            "subcategory":"Management & Consulting",
            "type":"Services"
        }
    ],
    "sg:phone":"+1 765 932 5921",
    "sg:postcode":"46173",
    "sg:province":"IN",
    "sg:tags":[
        "consultant",
        "energy",
        "conservation"
    ],
    "wof:name":"River Valley Resources",
    "wof:placetype":"venue"
},
  "geometry": {"coordinates":[-85.444772,39.622167],"type":"Point"}
}