{
  "type": "Feature",
  "properties": {
    "iso:country":"US",
    "sg:address":"5601 S Winthrop Ct",
    "sg:city":"Terre Haute",
    "sg:classifiers":[
        {
            "category":"Real Estate",
            "subcategory":"Real Estate Operator",
            "type":"Services"
        }
    ],
    "sg:phone":"+1 812 299 5731",
    "sg:postcode":"47802",
    "sg:province":"IN",
    "sg:tags":[
        "apartment"
    ],
    "wof:name":"Winthrop Court Apartments",
    "wof:placetype":"venue"
},
  "geometry": {"coordinates":[-87.395864,39.398557],"type":"Point"}
}