{
  "type": "Feature",
  "properties": {
    "addr:full":"602 Roosevelt Rd Walkerton IN 46574",
    "addr:housenumber":"602",
    "addr:postcode":"46574",
    "addr:street":"Roosevelt Rd",
    "iso:country":"US",
    "sg:address":"602 Roosevelt Rd",
    "sg:city":"Walkerton",
    "sg:classifiers":[
        {
            "category":"Shopping",
            "subcategory":"Tobacco",
            "type":"Retail Goods"
        }
    ],
    "sg:phone":"+1 574 586 7261",
    "sg:postcode":"46574",
    "sg:province":"IN",
    "sg:tags":[
        "cigarette",
        "cigar",
        "dealer"
    ],
    "wof:name":"Tobacco Shop",
    "wof:placetype":"venue"
},
  "geometry": {"coordinates":[-86.483273,41.46677],"type":"Point"}
}