{
  "type": "Feature",
  "properties": {
    "iso:country":"US",
    "sg:address":"503 N Rogers St",
    "sg:city":"Bloomington",
    "sg:classifiers":[
        {
            "category":"Wholesale",
            "subcategory":"Scrap",
            "type":"Manufacturing & Wholesale Goods"
        }
    ],
    "sg:phone":"+1 812 336 6884",
    "sg:postcode":"47404",
    "sg:province":"IN",
    "sg:tags":[
        "metal",
        "iron"
    ],
    "wof:name":"Bloomington Iron & Metal Inc",
    "wof:placetype":"venue"
},
  "geometry": {"coordinates":[-86.538528,39.171382],"type":"Point"}
}