{
  "type": "Feature",
  "properties": {
    "iso:country":"US",
    "sg:address":"911 S Adams St",
    "sg:city":"Marion",
    "sg:classifiers":[
        {
            "category":"Local Transit",
            "type":"Transportation"
        }
    ],
    "sg:phone":"+1 765 664 0706",
    "sg:postcode":"46953",
    "sg:province":"IN",
    "sg:tags":[
        "ambulance"
    ],
    "wof:name":"Quality Care Ambulance Inc",
    "wof:placetype":"venue"
},
  "geometry": {"coordinates":[-85.65848200000001,40.552054],"type":"Point"}
}