{
  "type": "Feature",
  "properties": {
    "iso:country":"US",
    "sg:address":"320 Winchester St",
    "sg:city":"Decatur",
    "sg:classifiers":[
        {
            "category":"Personal",
            "subcategory":"Beauty Salon",
            "type":"Services"
        }
    ],
    "sg:phone":"+1 260 724 2527",
    "sg:postcode":"46733",
    "sg:province":"IN",
    "sg:tags":[
        "shop"
    ],
    "wof:name":"Deanna's Styling Salon",
    "wof:placetype":"venue"
},
  "geometry": {"coordinates":[-84.923512,40.827128],"type":"Point"}
}