{
  "type": "Feature",
  "properties": {
    "iso:country":"US",
    "sg:address":"750 S Kentucky Ave",
    "sg:city":"Evansville",
    "sg:classifiers":[
        {
            "category":"Shopping",
            "subcategory":"Florist",
            "type":"Retail Goods"
        }
    ],
    "sg:phone":"+1 812 423 3191",
    "sg:postcode":"47714",
    "sg:province":"IN",
    "sg:website":"www.theflowershop.com",
    "wof:name":"Flower Shop Inc",
    "wof:placetype":"venue"
},
  "geometry": {"coordinates":[-87.547716,37.966536],"type":"Point"}
}