{
  "type": "Feature",
  "properties": {
    "iso:country":"US",
    "sg:address":"107 E Washington St",
    "sg:city":"Plymouth",
    "sg:classifiers":[
        {
            "category":"Organizations",
            "subcategory":"Religious Organization",
            "type":"Services"
        }
    ],
    "sg:phone":"+1 574 936 8929",
    "sg:postcode":"46563",
    "sg:province":"IN",
    "wof:name":"Gideons International",
    "wof:placetype":"venue"
},
  "geometry": {"coordinates":[-86.308094,41.341908],"type":"Point"}
}