{
  "type": "Feature",
  "properties": {
    "iso:country":"US",
    "sg:address":"4365 N 1400 W",
    "sg:city":"Medaryville",
    "sg:classifiers":[
        {
            "category":"Retail",
            "subcategory":"Auto Repair",
            "type":"Services"
        }
    ],
    "sg:phone":"+1 219 843 6925",
    "sg:postcode":"47957",
    "sg:province":"IN",
    "sg:tags":[
        "wrecker"
    ],
    "wof:name":"P & B Salvage",
    "wof:placetype":"venue"
},
  "geometry": {"coordinates":[-86.872214,41.119053],"type":"Point"}
}