{
  "type": "Feature",
  "properties": {
    "iso:country":"US",
    "sg:address":"2920 S Lafountain St",
    "sg:city":"Kokomo",
    "sg:classifiers":[
        {
            "category":"Professional",
            "subcategory":"Accounting & Tax Preparation",
            "type":"Services"
        }
    ],
    "sg:phone":"+1 765 455 1777",
    "sg:postcode":"46902",
    "sg:province":"IN",
    "sg:tags":[
        "accountant"
    ],
    "wof:name":"Bergman Coon & Renbarger",
    "wof:placetype":"venue"
},
  "geometry": {"coordinates":[-86.126986,40.454619],"type":"Point"}
}