{
  "type": "Feature",
  "properties": {
    "iso:country":"US",
    "sg:address":"117 S Nappanee St",
    "sg:city":"Elkhart",
    "sg:classifiers":[
        {
            "category":"Health Services",
            "subcategory":"Doctor",
            "type":"Services"
        }
    ],
    "sg:phone":"+1 574 295 7342",
    "sg:postcode":"46514",
    "sg:province":"IN",
    "sg:tags":[
        "dentist"
    ],
    "wof:name":"Endodontic Services Inc",
    "wof:placetype":"venue"
},
  "geometry": {"coordinates":[-86.003471,41.683988],"type":"Point"}
}