{
  "type": "Feature",
  "properties": {
    "addr:full":"26330 Ernest Rd Arcadia IN 46030",
    "addr:housenumber":"26330",
    "addr:postcode":"46030",
    "addr:street":"Ernest Rd",
    "iso:country":"US",
    "sg:address":"26330 Ernest Rd",
    "sg:city":"Arcadia",
    "sg:classifiers":[
        {
            "category":"Retail",
            "subcategory":"Portrait Studio",
            "type":"Services"
        }
    ],
    "sg:phone":"+1 317 984 3504",
    "sg:postcode":"46030",
    "sg:province":"IN",
    "sg:tags":[
        "photo"
    ],
    "wof:name":"Memory Lane Portraits",
    "wof:placetype":"venue"
},
  "geometry": {"coordinates":[-86.052266,40.172329],"type":"Point"}
}