{
  "type": "Feature",
  "properties": {
    "iso:country":"US",
    "sg:address":"2423 Fairfield Ave",
    "sg:city":"Fort Wayne",
    "sg:classifiers":[
        {
            "category":"Social Services",
            "type":"Services"
        }
    ],
    "sg:phone":"+1 260 745 9431",
    "sg:postcode":"46807",
    "sg:province":"IN",
    "sg:tags":[
        "organization",
        "welfare"
    ],
    "sg:website":"www.whitington.org",
    "wof:name":"Whitington Inc",
    "wof:placetype":"venue"
},
  "geometry": {"coordinates":[-85.145026,41.062135],"type":"Point"}
}