{
  "type": "Feature",
  "properties": {
    "iso:country":"US",
    "sg:address":"2430 E Main St",
    "sg:city":"Plainfield",
    "sg:classifiers":[
        {
            "category":"Real Estate",
            "subcategory":"Real Estate Agent",
            "type":"Services"
        }
    ],
    "sg:phone":"+1 317 839 8786",
    "sg:postcode":"46168",
    "sg:province":"IN",
    "sg:tags":[
        "buyer",
        "broker"
    ],
    "wof:name":"Crager Bartels Real Estate",
    "wof:placetype":"venue"
},
  "geometry": {"coordinates":[-86.364931,39.714922],"type":"Point"}
}