{
  "type": "Feature",
  "properties": {
    "iso:country":"US",
    "sg:address":"1196 Lazio Ct",
    "sg:city":"Greenwood",
    "sg:classifiers":[
        {
            "category":"Insurance",
            "subcategory":"Hazard Insurance",
            "type":"Services"
        },
        {
            "category":"Insurance",
            "subcategory":"Health Insurance",
            "type":"Services"
        }
    ],
    "sg:phone":"+1 317 885 9745",
    "sg:postcode":"46143",
    "sg:province":"IN",
    "sg:tags":[
        "employee",
        "benefit",
        "commercial",
        "business"
    ],
    "wof:name":"Circle City Group Financial",
    "wof:placetype":"venue"
},
  "geometry": {"coordinates":[-86.140648,39.598059],"type":"Point"}
}