{
  "type": "Feature",
  "properties": {
    "iso:country":"US",
    "sg:address":"3613 N Broadway Ave",
    "sg:city":"Muncie",
    "sg:classifiers":[
        {
            "category":"Banks & Credit Unions",
            "subcategory":"Bank",
            "type":"Services"
        }
    ],
    "sg:phone":"+1 765 747 2817",
    "sg:postcode":"47303",
    "sg:province":"IN",
    "wof:name":"Mutual Federal Savings Bank",
    "wof:placetype":"venue"
},
  "geometry": {"coordinates":[-85.370757,40.223269],"type":"Point"}
}