{
  "type": "Feature",
  "properties": {
    "addr:full":"1300 N 3rd St Logansport IN 46947",
    "addr:housenumber":"1300",
    "addr:postcode":"46947",
    "addr:street":"N 3Rd St",
    "iso:country":"US",
    "sg:address":"1300 N 3rd St",
    "sg:city":"Logansport",
    "sg:classifiers":[
        {
            "category":"Education",
            "subcategory":"School",
            "type":"Public Place"
        }
    ],
    "sg:phone":"+1 574 753 3797",
    "sg:postcode":"46947",
    "sg:province":"IN",
    "wof:name":"Columbia Middle School",
    "wof:placetype":"venue"
},
  "geometry": {"coordinates":[-86.372158,40.762614],"type":"Point"}
}