{
  "type": "Feature",
  "properties": {
    "iso:country":"US",
    "sg:address":"2312 Eisenhower Dr N",
    "sg:city":"Goshen",
    "sg:classifiers":[
        {
            "category":"Shopping",
            "subcategory":"Computers & Home Electronics",
            "type":"Retail Goods"
        }
    ],
    "sg:phone":"+1 574 533 0571",
    "sg:postcode":"46526",
    "sg:province":"IN",
    "sg:tags":[
        "software"
    ],
    "sg:website":"www.hertzler.com",
    "wof:name":"Hertzler Systems Inc",
    "wof:placetype":"venue"
},
  "geometry": {"coordinates":[-85.797528,41.557389],"type":"Point"}
}