{
  "type": "Feature",
  "properties": {
    "iso:country":"US",
    "sg:address":"5765 Coopers Hawk Dr",
    "sg:city":"Carmel",
    "sg:classifiers":[
        {
            "category":"Professional",
            "subcategory":"Management & Consulting",
            "type":"Services"
        }
    ],
    "sg:phone":"+1 317 575 8119",
    "sg:postcode":"46033",
    "sg:province":"IN",
    "sg:tags":[
        "business"
    ],
    "wof:name":"H3 Consulting & Coaching LLC",
    "wof:placetype":"venue"
},
  "geometry": {"coordinates":[-86.078413,39.982895],"type":"Point"}
}