{
  "type": "Feature",
  "properties": {
    "iso:country":"US",
    "sg:address":"5707 W Minnesota St",
    "sg:city":"Indianapolis",
    "sg:classifiers":[
        {
            "category":"Manufacturing",
            "subcategory":"Tools & Machinery",
            "type":"Manufacturing & Wholesale Goods"
        }
    ],
    "sg:phone":"+1 317 484 3745",
    "sg:postcode":"46241",
    "sg:province":"IN",
    "sg:tags":[
        "farm",
        "equipment"
    ],
    "sg:website":"www.sepinc.com",
    "wof:name":"Separators Inc",
    "wof:placetype":"venue"
},
  "geometry": {"coordinates":[-86.258332,39.742942],"type":"Point"}
}