{
  "type": "Feature",
  "properties": {
    "addr:full":"1309 N Meridian St Portland IN 47371",
    "addr:housenumber":"1309",
    "addr:postcode":"47371",
    "addr:street":"N Meridian St",
    "iso:country":"US",
    "sg:address":"1309 N Meridian St",
    "sg:city":"Portland",
    "sg:classifiers":[
        {
            "category":"Health Services",
            "subcategory":"Health Practitioner",
            "type":"Services"
        }
    ],
    "sg:phone":"+1 260 726 6828",
    "sg:postcode":"47371",
    "sg:province":"IN",
    "sg:tags":[
        "therapist",
        "physical"
    ],
    "wof:name":"Adams Physical Therapy Svc Inc",
    "wof:placetype":"venue"
},
  "geometry": {"coordinates":[-84.978094,40.445772],"type":"Point"}
}