{
  "type": "Feature",
  "properties": {
    "iso:country":"US",
    "sg:address":"931 Spy Run Rd",
    "sg:city":"Indianapolis",
    "sg:classifiers":[
        {
            "category":"Real Estate",
            "subcategory":"Real Estate Operator",
            "type":"Services"
        }
    ],
    "sg:phone":"+1 317 894 7376",
    "sg:postcode":"46229",
    "sg:province":"IN",
    "sg:tags":[
        "apartment"
    ],
    "wof:name":"Cumberland Manor Apartments",
    "wof:placetype":"venue"
},
  "geometry": {"coordinates":[-85.955893,39.782113],"type":"Point"}
}