{
  "type": "Feature",
  "properties": {
    "iso:country":"US",
    "sg:address":"7835 W 350 N",
    "sg:city":"Shipshewana",
    "sg:classifiers":[
        {
            "category":"Building & Trades",
            "subcategory":"Equipment Rental",
            "type":"Services"
        }
    ],
    "sg:phone":"+1 260 768 4955",
    "sg:postcode":"46565",
    "sg:province":"IN",
    "sg:tags":[
        "repair"
    ],
    "wof:name":"Ms Service",
    "wof:placetype":"venue"
},
  "geometry": {"coordinates":[-85.577235,41.691754],"type":"Point"}
}