{
  "type": "Feature",
  "properties": {
    "iso:country":"US",
    "sg:address":"10233 N Co Rd 300 E",
    "sg:city":"Seymour",
    "sg:classifiers":[
        {
            "category":"Freight",
            "type":"Transportation"
        }
    ],
    "sg:phone":"+1 812 523 6908",
    "sg:postcode":"47274",
    "sg:province":"IN",
    "sg:tags":[
        "trucking"
    ],
    "wof:name":"Wischmeier Trucking Inc",
    "wof:placetype":"venue"
},
  "geometry": {"coordinates":[-85.98354,39.029225],"type":"Point"}
}