{
  "type": "Feature",
  "properties": {
    "addr:full":"1101 Eisenhower Dr N Goshen IN 46526",
    "addr:housenumber":"1101",
    "addr:postcode":"46526",
    "addr:street":"Eisenhower Dr N",
    "iso:country":"US",
    "sg:address":"1101 Eisenhower Dr N",
    "sg:city":"Goshen",
    "sg:classifiers":[
        {
            "category":"Manufacturing",
            "subcategory":"Buildings",
            "type":"Manufacturing & Wholesale Goods"
        }
    ],
    "sg:phone":"+1 574 533 0431",
    "sg:postcode":"46526",
    "sg:province":"IN",
    "sg:tags":[
        "prefab"
    ],
    "sg:website":"www.libertyhomesinc.com",
    "wof:name":"Liberty Homes Inc",
    "wof:placetype":"venue"
},
  "geometry": {"coordinates":[-85.819023,41.557488],"type":"Point"}
}