{
  "type": "Feature",
  "properties": {
    "iso:country":"US",
    "sg:address":"6835 Guion Rd",
    "sg:city":"Indianapolis",
    "sg:classifiers":[
        {
            "category":"Autos & Motor Vehicles",
            "subcategory":"Automobile Sales",
            "type":"Retail Goods"
        }
    ],
    "sg:phone":"+1 317 299 5100",
    "sg:postcode":"46268",
    "sg:province":"IN",
    "sg:tags":[
        "performance",
        "race",
        "dealer"
    ],
    "sg:website":"www.fernandezracing.net",
    "wof:name":"Fernandez Racing",
    "wof:placetype":"venue"
},
  "geometry": {"coordinates":[-86.231491,39.881925],"type":"Point"}
}