{
  "type": "Feature",
  "properties": {
    "iso:country":"US",
    "sg:address":"1600 N Meridian St",
    "sg:city":"Portland",
    "sg:classifiers":[
        {
            "category":"Shopping",
            "subcategory":"Department Store",
            "type":"Retail Goods"
        }
    ],
    "sg:phone":"+1 260 726 3682",
    "sg:postcode":"47371",
    "sg:province":"IN",
    "wof:name":"Wal-Mart",
    "wof:placetype":"venue"
},
  "geometry": {"coordinates":[-84.978275,40.447704],"type":"Point"}
}