{
  "type": "Feature",
  "properties": {
    "iso:country":"US",
    "sg:address":"7390 Carson School Rd",
    "sg:city":"Mt Vernon",
    "sg:classifiers":[
        {
            "category":"Freight",
            "type":"Transportation"
        }
    ],
    "sg:phone":"+1 812 985 9519",
    "sg:postcode":"47620",
    "sg:province":"IN",
    "wof:name":"Shipping Post",
    "wof:placetype":"venue"
},
  "geometry": {"coordinates":[-87.741613,37.937195],"type":"Point"}
}