{
  "type": "Feature",
  "properties": {
    "iso:country":"US",
    "sg:address":"1000 E Spring St",
    "sg:city":"New Albany",
    "sg:classifiers":[
        {
            "category":"Health Services",
            "subcategory":"Doctor",
            "type":"Services"
        }
    ],
    "sg:phone":"+1 812 941 1701",
    "sg:postcode":"47150",
    "sg:province":"IN",
    "sg:tags":[
        "clinic"
    ],
    "wof:name":"Family Health Ctr-Floyd County",
    "wof:placetype":"venue"
},
  "geometry": {"coordinates":[-85.812918,38.289505],"type":"Point"}
}