{
  "type": "Feature",
  "properties": {
    "addr:full":"7826 E Ridge Rd Hobart IN 46342",
    "addr:housenumber":"7826",
    "addr:postcode":"46342",
    "addr:street":"E Ridge Rd",
    "iso:country":"US",
    "sg:address":"7826 E Ridge Rd",
    "sg:city":"Hobart",
    "sg:classifiers":[
        {
            "category":"Food & Beverages",
            "subcategory":"Specialty",
            "type":"Retail Goods"
        }
    ],
    "sg:phone":"+1 219 962 4468",
    "sg:postcode":"46342",
    "sg:province":"IN",
    "sg:tags":[
        "herb",
        "health",
        "diet"
    ],
    "sg:website":"http://www.gnc.com",
    "wof:name":"GNC",
    "wof:placetype":"venue"
},
  "geometry": {"coordinates":[-87.240559,41.55072],"type":"Point"}
}