{
  "type": "Feature",
  "properties": {
    "iso:country":"US",
    "sg:address":"605 W Eichel Ave",
    "sg:city":"Evansville",
    "sg:classifiers":[
        {
            "category":"Manufacturing",
            "subcategory":"Chemicals & Compounds",
            "type":"Manufacturing & Wholesale Goods"
        }
    ],
    "sg:phone":"+1 812 401 2178",
    "sg:postcode":"47710",
    "sg:province":"IN",
    "sg:tags":[
        "plastic"
    ],
    "wof:name":"Lucent Polymers",
    "wof:placetype":"venue"
},
  "geometry": {"coordinates":[-87.573559,37.991351],"type":"Point"}
}