{
  "type": "Feature",
  "properties": {
    "iso:country":"US",
    "sg:address":"233 S Pete Ellis Dr",
    "sg:city":"Bloomington",
    "sg:classifiers":[
        {
            "category":"Recreation",
            "type":"Entertainment"
        }
    ],
    "sg:phone":"+1 812 339 3276",
    "sg:postcode":"47408",
    "sg:province":"IN",
    "sg:tags":[
        "range",
        "baseball",
        "batting"
    ],
    "wof:name":"Putt Putt Golf & Games",
    "wof:placetype":"venue"
},
  "geometry": {"coordinates":[-86.494843,39.166008],"type":"Point"}
}