{
  "type": "Feature",
  "properties": {
    "iso:country":"US",
    "sg:address":"10 N Center St",
    "sg:city":"Flora",
    "sg:classifiers":[
        {
            "category":"Government",
            "subcategory":"Police Station",
            "type":"Public Place"
        }
    ],
    "sg:phone":"+1 574 967 4457",
    "sg:postcode":"46929",
    "sg:province":"IN",
    "sg:tags":[
        "department"
    ],
    "wof:name":"Flora Police Dept",
    "wof:placetype":"venue"
},
  "geometry": {"coordinates":[-86.523841,40.54856],"type":"Point"}
}