{
  "type": "Feature",
  "properties": {
    "iso:country":"US",
    "sg:address":"8788 Ruffian Ln",
    "sg:city":"Newburgh",
    "sg:classifiers":[
        {
            "category":"Insurance",
            "subcategory":"Insurance Agent",
            "type":"Services"
        }
    ],
    "sg:phone":"+1 812 858 3544",
    "sg:postcode":"47630",
    "sg:province":"IN",
    "wof:name":"Brown & Brown Insurance",
    "wof:placetype":"venue"
},
  "geometry": {"coordinates":[-87.410819,37.975684],"type":"Point"}
}