{
  "type": "Feature",
  "properties": {
    "iso:country":"US",
    "sg:address":"1375 State Rd 1",
    "sg:city":"Cambridge City",
    "sg:classifiers":[
        {
            "category":"Food & Beverages",
            "subcategory":"Groceries & Convenience Stores",
            "type":"Retail Goods"
        }
    ],
    "sg:phone":"+1 260 478 3797",
    "sg:postcode":"47327",
    "sg:province":"IN",
    "wof:name":"Marsh",
    "wof:placetype":"venue"
},
  "geometry": {"coordinates":[-85.144449,39.846859],"type":"Point"}
}