{
  "type": "Feature",
  "properties": {
    "iso:country":"US",
    "sg:address":"7141 Michigan Rd",
    "sg:city":"Indianapolis",
    "sg:classifiers":[
        {
            "category":"Health Services",
            "subcategory":"Dentist",
            "type":"Services"
        }
    ],
    "sg:phone":"+1 317 297 7900",
    "sg:postcode":"46268",
    "sg:province":"IN",
    "sg:tags":[
        "product",
        "dentists-cosmetic",
        "dental",
        "dentistry",
        "dentists-pediatric",
        "clinic",
        "whitening",
        "teeth"
    ],
    "sg:website":"http://www.augustadentalindianapolis.com",
    "wof:name":"Augusta Dental Office PC",
    "wof:placetype":"venue"
},
  "geometry": {"coordinates":[-86.20925699999999,39.883693],"type":"Point"}
}