{
  "type": "Feature",
  "properties": {
    "addr:full":"10202 E Washington St Indianapolis IN 46229",
    "addr:housenumber":"10202",
    "addr:postcode":"46229",
    "addr:street":"E Washington St",
    "iso:country":"US",
    "sg:address":"10202 E Washington St",
    "sg:city":"Indianapolis",
    "sg:phone":"+1 317 890 6202",
    "sg:postcode":"46229",
    "sg:province":"IN",
    "wof:name":"3 Sisters Accessories Corp",
    "wof:placetype":"venue"
},
  "geometry": {"coordinates":[-85.987402,39.775095],"type":"Point"}
}