{
  "type": "Feature",
  "properties": {
    "iso:country":"US",
    "sg:address":"201 N Line St",
    "sg:city":"Columbia City",
    "sg:classifiers":[
        {
            "category":"Social Services",
            "type":"Services"
        }
    ],
    "sg:phone":"+1 260 244 0057",
    "sg:postcode":"46725",
    "sg:province":"IN",
    "sg:tags":[
        "counselor",
        "marriage",
        "family"
    ],
    "wof:name":"Family Support Svc",
    "wof:placetype":"venue"
},
  "geometry": {"coordinates":[-85.49132,41.159205],"type":"Point"}
}