{
  "type": "Feature",
  "properties": {
    "addr:full":"215 W Franklin St Winchester IN 47394",
    "addr:housenumber":"215",
    "addr:postcode":"47394",
    "addr:street":"W Franklin St",
    "iso:country":"US",
    "sg:address":"215 W Franklin St",
    "sg:city":"Winchester",
    "sg:classifiers":[
        {
            "category":"Utilities",
            "subcategory":"Natural Gas",
            "type":"Services"
        }
    ],
    "sg:phone":"+1 765 584 5501",
    "sg:postcode":"47394",
    "sg:province":"IN",
    "sg:tags":[
        "transmission",
        "distribution"
    ],
    "wof:name":"Ohio Valley Gas Corp",
    "wof:placetype":"venue"
},
  "geometry": {"coordinates":[-84.98309,40.171554],"type":"Point"}
}