{
  "type": "Feature",
  "properties": {
    "iso:country":"US",
    "sg:address":"2403 E Wallen Rd",
    "sg:city":"Fort Wayne",
    "sg:classifiers":[
        {
            "category":"Retail",
            "subcategory":"Funeral Services",
            "type":"Services"
        }
    ],
    "sg:phone":"+1 260 490 4060",
    "sg:postcode":"46825",
    "sg:province":"IN",
    "sg:tags":[
        "director"
    ],
    "wof:name":"Advantage Funeral & Cremation",
    "wof:placetype":"venue"
},
  "geometry": {"coordinates":[-85.112334,41.164311],"type":"Point"}
}