{
  "type": "Feature",
  "properties": {
    "iso:country":"US",
    "sg:address":"805 East St",
    "sg:city":"Michigantown",
    "sg:classifiers":[
        {
            "category":"Manufacturing",
            "subcategory":"Chemicals & Compounds",
            "type":"Manufacturing & Wholesale Goods"
        }
    ],
    "sg:phone":"+1 765 249 2233",
    "sg:postcode":"46057",
    "sg:province":"IN",
    "sg:tags":[
        "fertilizer"
    ],
    "wof:name":"Frontier Co-Op Inc",
    "wof:placetype":"venue"
},
  "geometry": {"coordinates":[-86.39038,40.331223],"type":"Point"}
}