{
  "type": "Feature",
  "properties": {
    "iso:country":"US",
    "sg:address":"8144 Robin Hill Dr",
    "sg:city":"Newburgh",
    "sg:classifiers":[
        {
            "category":"Building & Trades",
            "subcategory":"Landscaping Services",
            "type":"Services"
        }
    ],
    "sg:phone":"+1 812 853 3955",
    "sg:postcode":"47630",
    "sg:province":"IN",
    "sg:tags":[
        "landscape",
        "contractor"
    ],
    "wof:name":"Suburban Landscape Nursery",
    "wof:placetype":"venue"
},
  "geometry": {"coordinates":[-87.39745499999999,37.960166],"type":"Point"}
}