{
  "type": "Feature",
  "properties": {
    "iso:country":"US",
    "sg:address":"3701 S Western Ave",
    "sg:city":"Marion",
    "sg:classifiers":[
        {
            "category":"Food & Beverages",
            "subcategory":"Liquor & Beverages",
            "type":"Retail Goods"
        }
    ],
    "sg:phone":"+1 765 674 7250",
    "sg:postcode":"46953",
    "sg:province":"IN",
    "wof:name":"Save-On Liquor",
    "wof:placetype":"venue"
},
  "geometry": {"coordinates":[-85.67350999999999,40.52454],"type":"Point"}
}