{
  "type": "Feature",
  "properties": {
    "iso:country":"US",
    "sg:address":"4961 Woodcreek Dr",
    "sg:city":"Carmel",
    "sg:classifiers":[
        {
            "category":"Professional",
            "subcategory":"Business Services",
            "type":"Services"
        }
    ],
    "sg:phone":"+1 317 844 2120",
    "sg:postcode":"46033",
    "sg:province":"IN",
    "wof:name":"Care Giver Promotions",
    "wof:placetype":"venue"
},
  "geometry": {"coordinates":[-86.08586200000001,39.949932],"type":"Point"}
}