{
  "type": "Feature",
  "properties": {
    "iso:country":"US",
    "sg:address":"4007 S Western Ave",
    "sg:city":"Marion",
    "sg:classifiers":[
        {
            "category":"Insurance",
            "subcategory":"Insurance Agent",
            "type":"Services"
        }
    ],
    "sg:phone":"+1 765 674 6788",
    "sg:postcode":"46953",
    "sg:province":"IN",
    "wof:name":"Allstate Insurance",
    "wof:placetype":"venue"
},
  "geometry": {"coordinates":[-85.673312,40.519982],"type":"Point"}
}