{
  "type": "Feature",
  "properties": {
    "iso:country":"US",
    "sg:address":"7471 W Olson Rd",
    "sg:city":"Leiters Ford",
    "sg:classifiers":[
        {
            "category":"Retail",
            "subcategory":"Repair Shop",
            "type":"Services"
        }
    ],
    "sg:phone":"+1 574 542 4334",
    "sg:postcode":"46975",
    "sg:province":"IN",
    "sg:tags":[
        "farm",
        "equipment",
        "parts"
    ],
    "wof:name":"Hawk's Garage",
    "wof:placetype":"venue"
},
  "geometry": {"coordinates":[-86.38539400000001,41.122258],"type":"Point"}
}