{
  "type": "Feature",
  "properties": {
    "iso:country":"US",
    "sg:address":"603 E Lincolnway",
    "sg:city":"Laporte",
    "sg:classifiers":[
        {
            "category":"Shopping",
            "subcategory":"Department Store",
            "type":"Retail Goods"
        }
    ],
    "sg:phone":"+1 219 324 4878",
    "sg:postcode":"46350",
    "sg:province":"IN",
    "sg:tags":[
        "shop"
    ],
    "wof:name":"Dollar General",
    "wof:placetype":"venue"
},
  "geometry": {"coordinates":[-86.706597,41.618021],"type":"Point"}
}