{
  "type": "Feature",
  "properties": {
    "addr:full":"3990 Georgetown Rd Indianapolis IN 46254",
    "addr:housenumber":"3990",
    "addr:postcode":"46254",
    "addr:street":"Georgetown Rd",
    "iso:country":"US",
    "sg:address":"3990 Georgetown Rd",
    "sg:city":"Indianapolis",
    "sg:classifiers":[
        {
            "category":"Retail",
            "subcategory":"Auto Rental",
            "type":"Services"
        }
    ],
    "sg:phone":"+1 317 328 2784",
    "sg:postcode":"46254",
    "sg:province":"IN",
    "sg:tags":[
        "renting",
        "automobile"
    ],
    "wof:name":"Hertz Rent A Car",
    "wof:placetype":"venue"
},
  "geometry": {"coordinates":[-86.240432,39.827451],"type":"Point"}
}