{
  "type": "Feature",
  "properties": {
    "addr:full":"2708 E Michigan St Indianapolis IN 46201",
    "addr:housenumber":"2708",
    "addr:postcode":"46201",
    "addr:street":"E Michigan St",
    "iso:country":"US",
    "sg:address":"2708 E Michigan St",
    "sg:city":"Indianapolis",
    "sg:classifiers":[
        {
            "category":"Government",
            "subcategory":"Fire Station",
            "type":"Public Place"
        }
    ],
    "sg:phone":"+1 317 631 2304",
    "sg:postcode":"46201",
    "sg:province":"IN",
    "sg:tags":[
        "equipment",
        "extinguisher",
        "supply",
        "protection",
        "consultant"
    ],
    "sg:website":"http://www.jdifire.com",
    "wof:name":"Jacob-Dietz Inc",
    "wof:placetype":"venue"
},
  "geometry": {"coordinates":[-86.117645,39.774441],"type":"Point"}
}