{
  "type": "Feature",
  "properties": {
    "iso:country":"US",
    "sg:address":"103 Franklin St",
    "sg:city":"Valparaiso",
    "sg:classifiers":[
        {
            "category":"Organizations",
            "subcategory":"Religious Organization",
            "type":"Services"
        }
    ],
    "sg:phone":"+1 219 465 1661",
    "sg:postcode":"46383",
    "sg:province":"IN",
    "sg:tags":[
        "church"
    ],
    "sg:website":"www.valpofumc.org",
    "wof:name":"First United Methodist Church",
    "wof:placetype":"venue"
},
  "geometry": {"coordinates":[-87.059769,41.46884],"type":"Point"}
}