{
  "type": "Feature",
  "properties": {
    "iso:country":"US",
    "sg:address":"122 W Main St",
    "sg:city":"Hartford City",
    "sg:classifiers":[
        {
            "category":"Personal",
            "type":"Services"
        }
    ],
    "sg:phone":"+1 765 348 2806",
    "sg:postcode":"47348",
    "sg:province":"IN",
    "sg:tags":[
        "miscellaneous"
    ],
    "wof:name":"Sunshine Palace",
    "wof:placetype":"venue"
},
  "geometry": {"coordinates":[-85.367803,40.452217],"type":"Point"}
}