{
  "type": "Feature",
  "properties": {
    "iso:country":"US",
    "sg:address":"2311 Crescent Ave",
    "sg:city":"Fort Wayne",
    "sg:classifiers":[
        {
            "category":"Retail",
            "subcategory":"Auto Repair",
            "type":"Services"
        }
    ],
    "sg:phone":"+1 260 482 7711",
    "sg:postcode":"46805",
    "sg:province":"IN",
    "sg:tags":[
        "repairing",
        "automobile"
    ],
    "wof:name":"Summit City Car Care",
    "wof:placetype":"venue"
},
  "geometry": {"coordinates":[-85.12323499999999,41.097629],"type":"Point"}
}