{
  "type": "Feature",
  "properties": {
    "iso:country":"US",
    "sg:address":"51628 State Rd 19",
    "sg:city":"Elkhart",
    "sg:classifiers":[
        {
            "category":"Personal",
            "subcategory":"Beauty Salon",
            "type":"Services"
        }
    ],
    "sg:phone":"+1 574 264 3640",
    "sg:postcode":"46514",
    "sg:province":"IN",
    "wof:name":"Lakeland Beauty Salon",
    "wof:placetype":"venue"
},
  "geometry": {"coordinates":[-85.97444,41.745748],"type":"Point"}
}