{
  "type": "Feature",
  "properties": {
    "iso:country":"US",
    "sg:address":"135 W Jefferson St",
    "sg:city":"Shelburn",
    "sg:classifiers":[
        {
            "category":"Organizations",
            "subcategory":"Religious Organization",
            "type":"Services"
        }
    ],
    "sg:phone":"+1 812 397 2655",
    "sg:postcode":"47879",
    "sg:province":"IN",
    "sg:tags":[
        "church"
    ],
    "wof:name":"First Christian Church",
    "wof:placetype":"venue"
},
  "geometry": {"coordinates":[-87.395287,39.180838],"type":"Point"}
}