{
  "type": "Feature",
  "properties": {
    "iso:country":"US",
    "sg:address":"202 E Vine St",
    "sg:city":"Fort Branch",
    "sg:classifiers":[
        {
            "category":"Organizations",
            "subcategory":"Religious Organization",
            "type":"Services"
        }
    ],
    "sg:phone":"+1 812 753 4380",
    "sg:postcode":"47648",
    "sg:province":"IN",
    "wof:name":"Fort Branch Wesleyan",
    "wof:placetype":"venue"
},
  "geometry": {"coordinates":[-87.57715899999999,38.248397],"type":"Point"}
}