{
  "type": "Feature",
  "properties": {
    "addr:full":"1015 S Peru St Cicero IN 46034",
    "addr:housenumber":"1015",
    "addr:postcode":"46034",
    "addr:street":"S Peru St",
    "iso:country":"US",
    "sg:address":"1015 S Peru St",
    "sg:city":"Cicero",
    "sg:classifiers":[
        {
            "category":"Restaurant",
            "type":"Food & Drink"
        }
    ],
    "sg:menulink":"http://www.allmenus.com/in/jackson/186285-mcdonalds/menu/",
    "sg:postcode":"46034",
    "sg:province":"IN",
    "sg:tags":[
        "burger",
        "american"
    ],
    "wof:name":"McDonald's",
    "wof:placetype":"venue"
},
  "geometry": {"coordinates":[-86.01286500000001,40.123116],"type":"Point"}
}