{
  "type": "Feature",
  "properties": {
    "iso:country":"US",
    "sg:address":"600 Hulman St",
    "sg:city":"Terre Haute",
    "sg:classifiers":[
        {
            "category":"Organizations",
            "subcategory":"Religious Organization",
            "type":"Services"
        }
    ],
    "sg:phone":"+1 812 232 1857",
    "sg:postcode":"47802",
    "sg:province":"IN",
    "sg:tags":[
        "church"
    ],
    "wof:name":"Hulman Street Assembly Of God",
    "wof:placetype":"venue"
},
  "geometry": {"coordinates":[-87.40911699999999,39.448264],"type":"Point"}
}