{
  "type": "Feature",
  "properties": {
    "addr:full":"3663 Milkhouse Ln Mooresville IN 46158",
    "addr:housenumber":"3663",
    "addr:postcode":"46158",
    "addr:street":"Milkhouse Ln",
    "iso:country":"US",
    "sg:address":"3663 Milkhouse Ln",
    "sg:city":"Mooresville",
    "sg:classifiers":[
        {
            "category":"Real Estate",
            "subcategory":"Developer",
            "type":"Services"
        }
    ],
    "sg:phone":"+1 317 831 3200",
    "sg:postcode":"46158",
    "sg:province":"IN",
    "sg:tags":[
        "company",
        "land"
    ],
    "wof:name":"Shae Co Inc",
    "wof:placetype":"venue"
},
  "geometry": {"coordinates":[-86.353696,39.591897],"type":"Point"}
}