{
  "type": "Feature",
  "properties": {
    "addr:full":"9112 E 36th St Indianapolis IN 46235",
    "addr:housenumber":"9112",
    "addr:postcode":"46235",
    "addr:street":"E 36Th St",
    "iso:country":"US",
    "sg:address":"9112 E 36th St",
    "sg:city":"Indianapolis",
    "sg:classifiers":[
        {
            "category":"Retail",
            "subcategory":"Auto Repair",
            "type":"Services"
        }
    ],
    "sg:phone":"+1 317 895 6030",
    "sg:postcode":"46235",
    "sg:province":"IN",
    "sg:tags":[
        "wrecker"
    ],
    "wof:name":"S & R Towing",
    "wof:placetype":"venue"
},
  "geometry": {"coordinates":[-86.005815,39.822121],"type":"Point"}
}