{
  "type": "Feature",
  "properties": {
    "iso:country":"US",
    "sg:address":"324 S 25th St",
    "sg:city":"Terre Haute",
    "sg:classifiers":[
        {
            "category":"Real Estate",
            "subcategory":"Real Estate Agent",
            "type":"Services"
        }
    ],
    "sg:phone":"+1 812 234 8899",
    "sg:postcode":"47803",
    "sg:province":"IN",
    "sg:tags":[
        "management"
    ],
    "wof:name":"Ragle & Co Inc",
    "wof:placetype":"venue"
},
  "geometry": {"coordinates":[-87.378788,39.463914],"type":"Point"}
}