{
  "type": "Feature",
  "properties": {
    "addr:full":"625 17th St Logansport IN 46947",
    "addr:housenumber":"625",
    "addr:postcode":"46947",
    "addr:street":"17Th St",
    "iso:country":"US",
    "sg:address":"625 17th St",
    "sg:city":"Logansport",
    "sg:classifiers":[
        {
            "category":"Shopping",
            "subcategory":"Florist",
            "type":"Retail Goods"
        }
    ],
    "sg:phone":"+1 574 722 1155",
    "sg:postcode":"46947",
    "sg:province":"IN",
    "wof:name":"Warner's Greenhouse",
    "wof:placetype":"venue"
},
  "geometry": {"coordinates":[-86.346884,40.753473],"type":"Point"}
}