{
  "type": "Feature",
  "properties": {
    "iso:country":"US",
    "sg:address":"111 Magnolia Dr",
    "sg:city":"Anderson",
    "sg:classifiers":[
        {
            "category":"Shopping",
            "subcategory":"Used Merchandise",
            "type":"Retail Goods"
        }
    ],
    "sg:phone":"+1 765 644 0454",
    "sg:postcode":"46012",
    "sg:province":"IN",
    "wof:name":"Ginnys Good & Old",
    "wof:placetype":"venue"
},
  "geometry": {"coordinates":[-85.67426500000001,40.170176],"type":"Point"}
}