{
  "type": "Feature",
  "properties": {
    "iso:country":"US",
    "sg:address":"7623 Oakdale Ave",
    "sg:city":"Hammond",
    "sg:classifiers":[
        {
            "category":"Real Estate",
            "subcategory":"Architect",
            "type":"Services"
        }
    ],
    "sg:phone":"+1 219 937 0999",
    "sg:postcode":"46324",
    "sg:province":"IN",
    "wof:name":"Masterson Szafasz & Shaw",
    "wof:placetype":"venue"
},
  "geometry": {"coordinates":[-87.50369999999999,41.574902],"type":"Point"}
}