{
  "type": "Feature",
  "properties": {
    "addr:full":"29 Carnaby Dr Brownsburg IN 46112",
    "addr:housenumber":"29",
    "addr:postcode":"46112",
    "addr:street":"Carnaby Dr",
    "iso:country":"US",
    "sg:address":"29 Carnaby Dr",
    "sg:city":"Brownsburg",
    "sg:classifiers":[
        {
            "category":"Building & Trades",
            "subcategory":"Construction",
            "type":"Services"
        }
    ],
    "sg:phone":"+1 317 852 8409",
    "sg:postcode":"46112",
    "sg:province":"IN",
    "sg:tags":[
        "house",
        "builder",
        "home"
    ],
    "wof:name":"Masterpiece Homes LLC",
    "wof:placetype":"venue"
},
  "geometry": {"coordinates":[-86.403131,39.852184],"type":"Point"}
}