{
  "type": "Feature",
  "properties": {
    "iso:country":"US",
    "sg:address":"2409 Locust Ln",
    "sg:city":"Richmond",
    "sg:classifiers":[
        {
            "category":"Building & Trades",
            "subcategory":"Electrical",
            "type":"Services"
        }
    ],
    "sg:phone":"+1 765 965 2665",
    "sg:postcode":"47374",
    "sg:province":"IN",
    "sg:tags":[
        "electric",
        "contractor"
    ],
    "wof:name":"Clayton Electric",
    "wof:placetype":"venue"
},
  "geometry": {"coordinates":[-84.869131,39.820646],"type":"Point"}
}