{
  "type": "Feature",
  "properties": {
    "iso:country":"US",
    "sg:address":"310 SE 5th St",
    "sg:city":"Washington",
    "sg:classifiers":[
        {
            "category":"Cinema",
            "subcategory":"Movie Rental",
            "type":"Entertainment"
        }
    ],
    "sg:phone":"+1 812 254 3010",
    "sg:postcode":"47501",
    "sg:province":"IN",
    "sg:tags":[
        "leasing",
        "video",
        "disc",
        "tape"
    ],
    "wof:name":"Family Video Movie Club",
    "wof:placetype":"venue"
},
  "geometry": {"coordinates":[-87.170136,38.654617],"type":"Point"}
}