{
  "type": "Feature",
  "properties": {
    "iso:country":"US",
    "sg:address":"131 S Harbour Dr",
    "sg:city":"Noblesville",
    "sg:classifiers":[
        {
            "category":"Professional",
            "subcategory":"Business Services",
            "type":"Services"
        }
    ],
    "sg:phone":"+1 317 776 3928",
    "sg:postcode":"46062",
    "sg:province":"IN",
    "sg:tags":[
        "plant",
        "design",
        "maintenance"
    ],
    "wof:name":"Paradise Plantscapes Inc",
    "wof:placetype":"venue"
},
  "geometry": {"coordinates":[-86.048954,40.062785],"type":"Point"}
}