{
  "type": "Feature",
  "properties": {
    "iso:country":"US",
    "sg:address":"1312 E Chicago Ave",
    "sg:city":"East Chicago",
    "sg:classifiers":[
        {
            "category":"Autos & Motor Vehicles",
            "subcategory":"Fuel & Gas Station",
            "type":"Retail Goods"
        }
    ],
    "sg:phone":"+1 219 378 1955",
    "sg:postcode":"46312",
    "sg:province":"IN",
    "sg:tags":[
        "oil"
    ],
    "wof:name":"Chicago Avenue Super Duper",
    "wof:placetype":"venue"
},
  "geometry": {"coordinates":[-87.454554,41.62922],"type":"Point"}
}