{
  "type": "Feature",
  "properties": {
    "addr:full":"1100 Regina Ln NW Corydon IN 47112",
    "addr:housenumber":"1100",
    "addr:postcode":"47112",
    "addr:street":"Regina Ln Nw",
    "iso:country":"US",
    "sg:address":"1100 Regina Ln NW",
    "sg:city":"Corydon",
    "sg:classifiers":[
        {
            "category":"Wholesale",
            "subcategory":"Auto Parts",
            "type":"Manufacturing & Wholesale Goods"
        }
    ],
    "sg:phone":"+1 812 738 8324",
    "sg:postcode":"47112",
    "sg:province":"IN",
    "sg:tags":[
        "repair",
        "product",
        "tire"
    ],
    "wof:name":"Stouts Tech Supply Inc",
    "wof:placetype":"venue"
},
  "geometry": {"coordinates":[-86.143629,38.228636],"type":"Point"}
}