{
  "type": "Feature",
  "properties": {
    "iso:country":"US",
    "sg:address":"740 E Main St",
    "sg:city":"Brownsburg",
    "sg:classifiers":[
        {
            "category":"Retail",
            "subcategory":"Laundry & Dry Cleaning",
            "type":"Services"
        }
    ],
    "sg:phone":"+1 317 852 4277",
    "sg:postcode":"46112",
    "sg:province":"IN",
    "sg:tags":[
        "cleaners"
    ],
    "wof:name":"Modern Cleaners",
    "wof:placetype":"venue"
},
  "geometry": {"coordinates":[-86.387201,39.840292],"type":"Point"}
}