{
  "type": "Feature",
  "properties": {
    "iso:country":"US",
    "sg:address":"335 S Meridian St",
    "sg:city":"Greenwood",
    "sg:classifiers":[
        {
            "category":"Organizations",
            "subcategory":"Religious Organization",
            "type":"Services"
        }
    ],
    "sg:phone":"+1 317 888 2861",
    "sg:postcode":"46143",
    "sg:province":"IN",
    "sg:tags":[
        "church"
    ],
    "wof:name":"Our Lady Of The Greenwood",
    "wof:placetype":"venue"
},
  "geometry": {"coordinates":[-86.106224,39.6069],"type":"Point"}
}