{
  "type": "Feature",
  "properties": {
    "iso:country":"US",
    "sg:address":"41 S Park Blvd",
    "sg:city":"Greenwood",
    "sg:classifiers":[
        {
            "category":"Banks & Credit Unions",
            "subcategory":"Bank",
            "type":"Services"
        }
    ],
    "sg:phone":"+1 317 865 0836",
    "sg:postcode":"46143",
    "sg:province":"IN",
    "sg:tags":[
        "loan",
        "real estate"
    ],
    "sg:website":"www.ameritrustmortgage.net",
    "wof:name":"Ameritrust Mortgage Svc",
    "wof:placetype":"venue"
},
  "geometry": {"coordinates":[-86.078122,39.616539],"type":"Point"}
}