{
  "type": "Feature",
  "properties": {
    "iso:country":"US",
    "sg:address":"3204 E 300 S",
    "sg:city":"Hillsboro",
    "sg:classifiers":[
        {
            "category":"Travel",
            "subcategory":"Campground",
            "type":"Entertainment"
        }
    ],
    "sg:phone":"+1 765 234 7286",
    "sg:postcode":"47949",
    "sg:province":"IN",
    "wof:name":"Charlarose Lake & Campground",
    "wof:placetype":"venue"
},
  "geometry": {"coordinates":[-87.096678,40.082795],"type":"Point"}
}