{
  "type": "Feature",
  "properties": {
    "iso:country":"US",
    "sg:address":"5040 Allisonville Rd",
    "sg:city":"Indianapolis",
    "sg:classifiers":[
        {
            "category":"Professional",
            "subcategory":"Management & Consulting",
            "type":"Services"
        }
    ],
    "sg:phone":"+1 317 289 8763",
    "sg:postcode":"46205",
    "sg:province":"IN",
    "sg:tags":[
        "telecommunication"
    ],
    "wof:name":"Xl Communications Inc",
    "wof:placetype":"venue"
},
  "geometry": {"coordinates":[-86.11162299999999,39.846689],"type":"Point"}
}