{
  "type": "Feature",
  "properties": {
    "iso:country":"US",
    "sg:address":"1002 Oak Dr",
    "sg:city":"Richmond",
    "sg:classifiers":[
        {
            "category":"Health Services",
            "subcategory":"Doctor",
            "type":"Services"
        }
    ],
    "sg:phone":"+1 765 966 7602",
    "sg:postcode":"47374",
    "sg:province":"IN",
    "sg:tags":[
        "dentist"
    ],
    "wof:name":"Jack J Reynolds DDS",
    "wof:placetype":"venue"
},
  "geometry": {"coordinates":[-84.886456,39.846977],"type":"Point"}
}