{
  "type": "Feature",
  "properties": {
    "iso:country":"US",
    "sg:address":"3408 E Jackson St",
    "sg:city":"Muncie",
    "sg:classifiers":[
        {
            "category":"Retail",
            "subcategory":"Auto Repair",
            "type":"Services"
        }
    ],
    "sg:phone":"+1 765 289 3493",
    "sg:postcode":"47303",
    "sg:province":"IN",
    "sg:tags":[
        "repairing",
        "automobile"
    ],
    "wof:name":"Armstrong Auto Electric Svc",
    "wof:placetype":"venue"
},
  "geometry": {"coordinates":[-85.34620700000001,40.193046],"type":"Point"}
}