{
  "type": "Feature",
  "properties": {
    "addr:full":"229 S East St Crown Point IN 46307",
    "addr:housenumber":"229",
    "addr:postcode":"46307",
    "addr:street":"S East St",
    "iso:country":"US",
    "sg:address":"229 S East St",
    "sg:city":"Crown Point",
    "sg:classifiers":[
        {
            "category":"Retail",
            "subcategory":"Laundry & Dry Cleaning",
            "type":"Services"
        }
    ],
    "sg:phone":"+1 219 663 9876",
    "sg:postcode":"46307",
    "sg:province":"IN",
    "sg:tags":[
        "cleaners"
    ],
    "wof:name":"Gards Laundry & Dry Cleaning",
    "wof:placetype":"venue"
},
  "geometry": {"coordinates":[-87.36327300000001,41.415297],"type":"Point"}
}