{
  "type": "Feature",
  "properties": {
    "iso:country":"US",
    "sg:address":"5318 Blue Ridge Rd",
    "sg:city":"Charlestown",
    "sg:classifiers":[
        {
            "category":"Organizations",
            "subcategory":"Community Association",
            "type":"Services"
        }
    ],
    "sg:phone":"+1 812 967 2837",
    "sg:postcode":"47111",
    "sg:province":"IN",
    "sg:tags":[
        "club"
    ],
    "wof:name":"Equine Rescue League",
    "wof:placetype":"venue"
},
  "geometry": {"coordinates":[-85.519282,38.495215],"type":"Point"}
}