{
  "type": "Feature",
  "properties": {
    "iso:country":"US",
    "sg:address":"501 W Railroad Ave",
    "sg:city":"Syracuse",
    "sg:classifiers":[
        {
            "category":"Manufacturing",
            "subcategory":"Motor Vehicles & Parts",
            "type":"Manufacturing & Wholesale Goods"
        }
    ],
    "sg:phone":"+1 574 457 4422",
    "sg:postcode":"46567",
    "sg:province":"IN",
    "sg:tags":[
        "axle"
    ],
    "wof:name":"Dana Corp",
    "wof:placetype":"venue"
},
  "geometry": {"coordinates":[-85.752889,41.421906],"type":"Point"}
}