{
  "type": "Feature",
  "properties": {
    "iso:country":"US",
    "sg:address":"5349 Brooks Bnd",
    "sg:city":"Greenwood",
    "sg:classifiers":[
        {
            "category":"Banks & Credit Unions",
            "subcategory":"Investment Brokerage",
            "type":"Services"
        },
        {
            "category":"Insurance",
            "subcategory":"Hazard Insurance",
            "type":"Services"
        }
    ],
    "sg:phone":"+1 317 422 2046",
    "sg:postcode":"46143",
    "sg:province":"IN",
    "sg:tags":[
        "commercial",
        "agent",
        "business",
        "resume"
    ],
    "wof:name":"Fisk Insurance Services",
    "wof:placetype":"venue"
},
  "geometry": {"coordinates":[-86.203512,39.565355],"type":"Point"}
}