{
  "type": "Feature",
  "properties": {
    "iso:country":"US",
    "sg:address":"6765 Harrison Trl NE",
    "sg:city":"Georgetown",
    "sg:classifiers":[
        {
            "category":"Building & Trades",
            "subcategory":"Construction",
            "type":"Services"
        }
    ],
    "sg:phone":"+1 812 951 2574",
    "sg:postcode":"47122",
    "sg:province":"IN",
    "sg:tags":[
        "hanging",
        "contractor"
    ],
    "wof:name":"Tim Spaney",
    "wof:placetype":"venue"
},
  "geometry": {"coordinates":[-86.003879,38.298413],"type":"Point"}
}