{
  "type": "Feature",
  "properties": {
    "addr:full":"10202 E Washington St 887A Indianapolis IN 46229",
    "addr:housenumber":"10202;887a",
    "addr:postcode":"46229",
    "addr:street":"E Washington St",
    "iso:country":"US",
    "sg:address":"10202 E Washington St 887A",
    "sg:city":"Indianapolis",
    "sg:classifiers":[
        {
            "category":"Manufacturing",
            "subcategory":"Apparel",
            "type":"Manufacturing & Wholesale Goods"
        }
    ],
    "sg:phone":"+1 317 808 2901",
    "sg:postcode":"46229",
    "sg:province":"IN",
    "sg:tags":[
        "clothing-men's-wholesale",
        "manufacturer"
    ],
    "wof:name":"Bermo Enterprises",
    "wof:placetype":"venue"
},
  "geometry": {"coordinates":[-85.987402,39.775095],"type":"Point"}
}