{
  "type": "Feature",
  "properties": {
    "addr:full":"8446 W Base Rd Arlington IN 46104",
    "addr:housenumber":"8446",
    "addr:postcode":"46104",
    "addr:street":"W Base Rd",
    "iso:country":"US",
    "sg:address":"8446 W Base Rd",
    "sg:city":"Arlington",
    "sg:classifiers":[
        {
            "category":"Wholesale",
            "subcategory":"Hardware",
            "type":"Manufacturing & Wholesale Goods"
        }
    ],
    "sg:phone":"+1 765 663 2420",
    "sg:postcode":"46104",
    "sg:province":"IN",
    "sg:tags":[
        "refrigeration"
    ],
    "wof:name":"Rains Refrigeration",
    "wof:placetype":"venue"
},
  "geometry": {"coordinates":[-85.60519499999999,39.611159],"type":"Point"}
}