{
  "type": "Feature",
  "properties": {
    "iso:country":"US",
    "sg:address":"56935 Elk Ct",
    "sg:city":"Elkhart",
    "sg:classifiers":[
        {
            "category":"Wholesale",
            "subcategory":"Machinery & Supplies",
            "type":"Manufacturing & Wholesale Goods"
        }
    ],
    "sg:phone":"+1 574 389 0909",
    "sg:postcode":"46516",
    "sg:province":"IN",
    "sg:tags":[
        "compressor",
        "gas"
    ],
    "wof:name":"Brehob Air Compressor Div",
    "wof:placetype":"venue"
},
  "geometry": {"coordinates":[-86.036077,41.669667],"type":"Point"}
}