{
  "type": "Feature",
  "properties": {
    "iso:country":"US",
    "sg:address":"1200 N Benjamin St",
    "sg:city":"Rushville",
    "sg:classifiers":[
        {
            "category":"Real Estate",
            "subcategory":"Real Estate Operator",
            "type":"Services"
        }
    ],
    "sg:phone":"+1 765 932 4389",
    "sg:postcode":"46173",
    "sg:province":"IN",
    "sg:tags":[
        "building",
        "apartment"
    ],
    "wof:name":"East Park Apts",
    "wof:placetype":"venue"
},
  "geometry": {"coordinates":[-85.435035,39.619585],"type":"Point"}
}