{
  "type": "Feature",
  "properties": {
    "iso:country":"US",
    "sg:address":"912 Main St",
    "sg:city":"Vincennes",
    "sg:classifiers":[
        {
            "category":"Professional",
            "subcategory":"Credit Reporting & Collection",
            "type":"Services"
        }
    ],
    "sg:phone":"+1 812 882 0909",
    "sg:postcode":"47591",
    "sg:province":"IN",
    "sg:tags":[
        "agency"
    ],
    "wof:name":"KNOX Accounts Svc",
    "wof:placetype":"venue"
},
  "geometry": {"coordinates":[-87.526919,38.674464],"type":"Point"}
}