{
  "type": "Feature",
  "properties": {
    "addr:full":"1042 Golfview Dr Ste A Carmel IN 46032",
    "addr:housenumber":"1042",
    "addr:postcode":"46032",
    "addr:street":"Golfview Dr Ste A Carmel",
    "iso:country":"US",
    "sg:address":"1042 Golfview Dr Ste A",
    "sg:city":"Carmel",
    "sg:classifiers":[
        {
            "category":"Real Estate",
            "subcategory":"Real Estate Operator",
            "type":"Services"
        },
        {
            "category":"Sports & Exercise",
            "subcategory":"Golf",
            "type":"Entertainment"
        }
    ],
    "sg:phone":"+1 317 844 3112",
    "sg:postcode":"46032",
    "sg:province":"IN",
    "sg:tags":[
        "apartment"
    ],
    "wof:name":"Mohawk Hills Golf Course",
    "wof:placetype":"venue"
},
  "geometry": {"coordinates":[-86.116302,39.967499],"type":"Point"}
}