{
  "type": "Feature",
  "properties": {
    "iso:country":"US",
    "sg:address":"5011 Kessler Blvd East Dr",
    "sg:city":"Indianapolis",
    "sg:classifiers":[
        {
            "category":"Social Services",
            "subcategory":"Adult Care",
            "type":"Services"
        }
    ],
    "sg:phone":"+1 317 251 1300",
    "sg:postcode":"46220",
    "sg:province":"IN",
    "sg:tags":[
        "home",
        "residential"
    ],
    "wof:name":"Sunrise Assisted Living-Fall",
    "wof:placetype":"venue"
},
  "geometry": {"coordinates":[-86.085145,39.857141],"type":"Point"}
}