{
  "type": "Feature",
  "properties": {
    "iso:country":"US",
    "sg:address":"4100 E Indiana St",
    "sg:city":"St Anthony",
    "sg:classifiers":[
        {
            "category":"Organizations",
            "subcategory":"Religious Organization",
            "type":"Services"
        }
    ],
    "sg:phone":"+1 812 326 2421",
    "sg:postcode":"47575",
    "sg:province":"IN",
    "sg:tags":[
        "church"
    ],
    "wof:name":"St Anthony Catholic Church",
    "wof:placetype":"venue"
},
  "geometry": {"coordinates":[-86.82752000000001,38.315986],"type":"Point"}
}