{
  "type": "Feature",
  "properties": {
    "iso:country":"US",
    "sg:address":"157 York Cir",
    "sg:city":"Valparaiso",
    "sg:classifiers":[
        {
            "category":"Building & Trades",
            "subcategory":"Construction",
            "type":"Services"
        }
    ],
    "sg:phone":"+1 219 477 5403",
    "sg:postcode":"46385",
    "sg:province":"IN",
    "sg:tags":[
        "house"
    ],
    "wof:name":"Lagneau Construction Inc",
    "wof:placetype":"venue"
},
  "geometry": {"coordinates":[-87.160135,41.458112],"type":"Point"}
}