{
  "type": "Feature",
  "properties": {
    "iso:country":"US",
    "sg:address":"5265 Hohman Ave",
    "sg:city":"Hammond",
    "sg:classifiers":[
        {
            "category":"Autos & Motor Vehicles",
            "subcategory":"Automobile Sales",
            "type":"Retail Goods"
        }
    ],
    "sg:phone":"+1 219 937 9660",
    "sg:postcode":"46320",
    "sg:province":"IN",
    "sg:tags":[
        "car",
        "dealer"
    ],
    "wof:name":"Hammond Luxury Motors",
    "wof:placetype":"venue"
},
  "geometry": {"coordinates":[-87.521958,41.616989],"type":"Point"}
}