{
  "type": "Feature",
  "properties": {
    "iso:country":"US",
    "sg:address":"234 S 8th St",
    "sg:city":"Richmond",
    "sg:classifiers":[
        {
            "category":"Shopping",
            "subcategory":"Clothing, Apparel, & Fashions",
            "type":"Retail Goods"
        }
    ],
    "sg:phone":"+1 765 966 7146",
    "sg:postcode":"47374",
    "sg:province":"IN",
    "wof:name":"Clothes Closet",
    "wof:placetype":"venue"
},
  "geometry": {"coordinates":[-84.891705,39.824815],"type":"Point"}
}