{
  "type": "Feature",
  "properties": {
    "iso:country":"US",
    "sg:address":"7600 W Reeves Rd",
    "sg:city":"Bloomington",
    "sg:classifiers":[
        {
            "category":"Education",
            "subcategory":"School",
            "type":"Public Place"
        }
    ],
    "sg:phone":"+1 812 876 2219",
    "sg:postcode":"47404",
    "sg:province":"IN",
    "sg:website":"www.rbbcsc.k12.in.us",
    "wof:name":"Ellettsville Elementary School",
    "wof:placetype":"venue"
},
  "geometry": {"coordinates":[-86.640718,39.23128],"type":"Point"}
}