{
  "type": "Feature",
  "properties": {
    "iso:country":"US",
    "sg:address":"2503 Eisenhower Ave",
    "sg:city":"Valparaiso",
    "sg:classifiers":[
        {
            "category":"Professional",
            "subcategory":"Engineering",
            "type":"Services"
        }
    ],
    "sg:phone":"+1 219 464 0460",
    "sg:postcode":"46383",
    "sg:province":"IN",
    "sg:tags":[
        "engineer"
    ],
    "sg:website":"www.amerecoeng.com",
    "wof:name":"Amereco Inc",
    "wof:placetype":"venue"
},
  "geometry": {"coordinates":[-87.02938,41.487842],"type":"Point"}
}