{
  "type": "Feature",
  "properties": {
    "addr:full":"512 Wind Cir S Evansville IN 47711",
    "addr:housenumber":"512",
    "addr:postcode":"47711",
    "addr:street":"Wind Cir S",
    "iso:country":"US",
    "sg:address":"512 Wind Cir S",
    "sg:city":"Evansville",
    "sg:classifiers":[
        {
            "category":"Education",
            "subcategory":"Dance Studio",
            "type":"Public Place"
        }
    ],
    "sg:phone":"+1 812 867 1055",
    "sg:postcode":"47711",
    "sg:province":"IN",
    "wof:name":"Jackson Shannon",
    "wof:placetype":"venue"
},
  "geometry": {"coordinates":[-87.56683,38.060116],"type":"Point"}
}