{
  "type": "Feature",
  "properties": {
    "iso:country":"US",
    "sg:address":"10070 Palmaire Pl",
    "sg:city":"Noblesville",
    "sg:classifiers":[
        {
            "category":"Communications",
            "subcategory":"Film & Video Production",
            "type":"Services"
        }
    ],
    "sg:phone":"+1 317 913 3838",
    "sg:postcode":"46038",
    "sg:province":"IN",
    "sg:tags":[
        "motion",
        "picture"
    ],
    "wof:name":"Scotspots",
    "wof:placetype":"venue"
},
  "geometry": {"coordinates":[-85.991829,39.992379],"type":"Point"}
}