{
  "type": "Feature",
  "properties": {
    "iso:country":"US",
    "sg:address":"705 N Meridian St",
    "sg:city":"Portland",
    "sg:classifiers":[
        {
            "category":"Shopping",
            "subcategory":"Department Store",
            "type":"Retail Goods"
        }
    ],
    "sg:phone":"+1 260 726 8347",
    "sg:postcode":"47371",
    "sg:province":"IN",
    "sg:tags":[
        "shop"
    ],
    "wof:name":"Family Dollar Store",
    "wof:placetype":"venue"
},
  "geometry": {"coordinates":[-84.977981,40.44052],"type":"Point"}
}