{
  "type": "Feature",
  "properties": {
    "iso:country":"US",
    "sg:address":"496 W Plaza Dr",
    "sg:city":"Columbia City",
    "sg:classifiers":[
        {
            "category":"Banks & Credit Unions",
            "subcategory":"Bank",
            "type":"Services"
        }
    ],
    "sg:phone":"+1 260 248 4564",
    "sg:postcode":"46725",
    "sg:province":"IN",
    "sg:website":"www.threeriversfcu.com",
    "wof:name":"Three Rivers Federal CU",
    "wof:placetype":"venue"
},
  "geometry": {"coordinates":[-85.491665,41.17008],"type":"Point"}
}