{
  "type": "Feature",
  "properties": {
    "iso:country":"US",
    "sg:address":"531 E Market St",
    "sg:city":"Indianapolis",
    "sg:classifiers":[
        {
            "category":"Organizations",
            "subcategory":"Labor Organization",
            "type":"Services"
        }
    ],
    "sg:phone":"+1 317 632 9780",
    "sg:postcode":"46204",
    "sg:province":"IN",
    "wof:name":"Carpenters Local 60",
    "wof:placetype":"venue"
},
  "geometry": {"coordinates":[-86.147272,39.76824],"type":"Point"}
}