{
  "type": "Feature",
  "properties": {
    "iso:country":"US",
    "sg:address":"216 W Market St",
    "sg:city":"Warsaw",
    "sg:classifiers":[
        {
            "category":"Communications",
            "subcategory":"Radio Station",
            "type":"Services"
        }
    ],
    "sg:phone":"+1 574 267 2230",
    "sg:postcode":"46580",
    "sg:province":"IN",
    "sg:tags":[
        "company",
        "broadcasting"
    ],
    "wof:name":"107.3-1480",
    "wof:placetype":"venue"
},
  "geometry": {"coordinates":[-85.85912500000001,41.23718],"type":"Point"}
}