{
  "type": "Feature",
  "properties": {
    "iso:country":"US",
    "sg:address":"1927 E 52nd St",
    "sg:city":"Indianapolis",
    "sg:classifiers":[
        {
            "category":"Shopping",
            "subcategory":"Clothing, Apparel, & Fashions",
            "type":"Retail Goods"
        }
    ],
    "sg:phone":"+1 317 251 7314",
    "sg:postcode":"46205",
    "sg:province":"IN",
    "sg:tags":[
        "alteration"
    ],
    "wof:name":"Graham Sewing Svc",
    "wof:placetype":"venue"
},
  "geometry": {"coordinates":[-86.126885,39.847553],"type":"Point"}
}