{
  "type": "Feature",
  "properties": {
    "iso:country":"US",
    "sg:address":"1595 Harrison Plz",
    "sg:city":"Bluffton",
    "sg:classifiers":[
        {
            "category":"Restaurant",
            "type":"Food & Drink"
        }
    ],
    "sg:phone":"+1 260 824 1111",
    "sg:postcode":"46714",
    "sg:province":"IN",
    "wof:name":"Taste Of China",
    "wof:placetype":"venue"
},
  "geometry": {"coordinates":[-85.16668,40.720971],"type":"Point"}
}