{
  "type": "Feature",
  "properties": {
    "iso:country":"US",
    "sg:address":"1700 Rozella Rd",
    "sg:city":"Warsaw",
    "sg:classifiers":[
        {
            "category":"Sports & Exercise",
            "subcategory":"Golf",
            "type":"Entertainment"
        }
    ],
    "sg:phone":"+1 574 269 9582",
    "sg:postcode":"46580",
    "sg:province":"IN",
    "sg:website":"www.rozellaford.com",
    "wof:name":"Rozella Ford Golf Course",
    "wof:placetype":"venue"
},
  "geometry": {"coordinates":[-85.87890299999999,41.219205],"type":"Point"}
}