{
  "type": "Feature",
  "properties": {
    "iso:country":"US",
    "sg:address":"5431 E 600 N",
    "sg:city":"Roselawn",
    "sg:classifiers":[
        {
            "category":"Farming",
            "subcategory":"Dairy Farm",
            "type":"Manufacturing & Wholesale Goods"
        }
    ],
    "sg:phone":"+1 219 345 7824",
    "sg:postcode":"46392",
    "sg:province":"IN",
    "wof:name":"Fair Oaks Dairy Farm",
    "wof:placetype":"venue"
},
  "geometry": {"coordinates":[-86.972889,41.099931],"type":"Point"}
}