{
  "type": "Feature",
  "properties": {
    "iso:country":"US",
    "sg:address":"9010 Corporation Dr",
    "sg:city":"Indianapolis",
    "sg:classifiers":[
        {
            "category":"Professional",
            "type":"Services"
        }
    ],
    "sg:phone":"+1 317 842 1200",
    "sg:postcode":"46256",
    "sg:province":"IN",
    "sg:tags":[
        "establishment"
    ],
    "wof:name":"Barclay-Holland Inc",
    "wof:placetype":"venue"
},
  "geometry": {"coordinates":[-86.033054,39.926896],"type":"Point"}
}