{
  "type": "Feature",
  "properties": {
    "iso:country":"US",
    "sg:address":"116 N Market St",
    "sg:city":"Winamac",
    "sg:classifiers":[
        {
            "category":"Personal",
            "subcategory":"Beauty Salon",
            "type":"Services"
        }
    ],
    "sg:phone":"+1 574 946 6412",
    "sg:postcode":"46996",
    "sg:province":"IN",
    "wof:name":"Headlines",
    "wof:placetype":"venue"
},
  "geometry": {"coordinates":[-86.604412,41.051723],"type":"Point"}
}