{
  "type": "Feature",
  "properties": {
    "iso:country":"US",
    "sg:address":"219 S Bluff St",
    "sg:city":"Monticello",
    "sg:classifiers":[
        {
            "category":"Building & Trades",
            "subcategory":"Construction",
            "type":"Services"
        }
    ],
    "sg:phone":"+1 574 583 4830",
    "sg:postcode":"47960",
    "sg:province":"IN",
    "sg:tags":[
        "concrete",
        "contractor"
    ],
    "wof:name":"D & W Contractors Inc",
    "wof:placetype":"venue"
},
  "geometry": {"coordinates":[-86.760295,40.743516],"type":"Point"}
}