{
  "type": "Feature",
  "properties": {
    "iso:country":"US",
    "sg:address":"10884 Co Rd W 150 S",
    "sg:city":"Russiaville",
    "sg:classifiers":[
        {
            "category":"Building & Trades",
            "subcategory":"Construction",
            "type":"Services"
        }
    ],
    "sg:phone":"+1 765 883 7266",
    "sg:postcode":"46979",
    "sg:province":"IN",
    "sg:tags":[
        "roofing",
        "contractor"
    ],
    "wof:name":"Hanson Construction",
    "wof:placetype":"venue"
},
  "geometry": {"coordinates":[-86.343689,40.453588],"type":"Point"}
}