{
  "type": "Feature",
  "properties": {
    "addr:full":"4351 W Morris St Indianapolis IN 46241",
    "addr:housenumber":"4351",
    "addr:postcode":"46241",
    "addr:street":"W Morris St",
    "iso:country":"US",
    "sg:address":"4351 W Morris St",
    "sg:city":"Indianapolis",
    "sg:classifiers":[
        {
            "category":"Building & Trades",
            "subcategory":"Construction",
            "type":"Services"
        }
    ],
    "sg:phone":"+1 317 248 1344",
    "sg:postcode":"46241",
    "sg:province":"IN",
    "sg:tags":[
        "sealcoating",
        "asphalt",
        "paving"
    ],
    "sg:website":"http://www.henry.com",
    "wof:name":"Monsey Bakor",
    "wof:placetype":"venue"
},
  "geometry": {"coordinates":[-86.23278500000001,39.749619],"type":"Point"}
}