{
  "type": "Feature",
  "properties": {
    "iso:country":"US",
    "sg:address":"512 Ridge Rd",
    "sg:city":"Munster",
    "sg:classifiers":[
        {
            "category":"Health Services",
            "subcategory":"Doctor",
            "type":"Services"
        }
    ],
    "sg:phone":"+1 219 836 9400",
    "sg:postcode":"46321",
    "sg:province":"IN",
    "sg:tags":[
        "physician",
        "surgeon"
    ],
    "wof:name":"Medical Clinics Of America",
    "wof:placetype":"venue"
},
  "geometry": {"coordinates":[-87.514777,41.562017],"type":"Point"}
}