{
  "type": "Feature",
  "properties": {
    "addr:full":"209 E Mill St Fortville IN 46040",
    "addr:housenumber":"209",
    "addr:postcode":"46040",
    "addr:street":"E Mill St",
    "iso:country":"US",
    "sg:address":"209 E Mill St",
    "sg:city":"Fortville",
    "sg:classifiers":[
        {
            "category":"Autos & Motor Vehicles",
            "subcategory":"Auto Supplies",
            "type":"Retail Goods"
        }
    ],
    "sg:phone":"+1 317 485 6330",
    "sg:postcode":"46040",
    "sg:province":"IN",
    "sg:tags":[
        "tire"
    ],
    "wof:name":"Fortville Tire Ctr Inc",
    "wof:placetype":"venue"
},
  "geometry": {"coordinates":[-85.84708000000001,39.93379],"type":"Point"}
}