{
  "type": "Feature",
  "properties": {
    "addr:full":"1600 E Tipton St Seymour IN 47274",
    "addr:housenumber":"1600",
    "addr:postcode":"47274",
    "addr:street":"E Tipton St",
    "iso:country":"US",
    "sg:address":"1600 E Tipton St",
    "sg:city":"Seymour",
    "sg:classifiers":[
        {
            "category":"Restaurant",
            "type":"Food & Drink"
        }
    ],
    "sg:phone":"+1 812 522 1012",
    "sg:postcode":"47274",
    "sg:province":"IN",
    "sg:tags":[
        "parlor",
        "ice",
        "cream"
    ],
    "wof:name":"TCBY",
    "wof:placetype":"venue"
},
  "geometry": {"coordinates":[-85.861543,38.958096],"type":"Point"}
}