{
  "type": "Feature",
  "properties": {
    "addr:full":"2313 W Columbia St Evansville IN 47712",
    "addr:housenumber":"2313",
    "addr:postcode":"47712",
    "addr:street":"W Columbia St",
    "iso:country":"US",
    "sg:address":"2313 W Columbia St",
    "sg:city":"Evansville",
    "sg:classifiers":[
        {
            "category":"Freight",
            "type":"Transportation"
        }
    ],
    "sg:phone":"+1 812 303 3142",
    "sg:postcode":"47712",
    "sg:province":"IN",
    "wof:name":"Blm Transportation",
    "wof:placetype":"venue"
},
  "geometry": {"coordinates":[-87.600317,37.985223],"type":"Point"}
}