{
  "type": "Feature",
  "properties": {
    "iso:country":"US",
    "sg:address":"6646 W 600 N",
    "sg:city":"Mc Cordsville",
    "sg:classifiers":[
        {
            "category":"Building & Trades",
            "subcategory":"Construction",
            "type":"Services"
        }
    ],
    "sg:phone":"+1 317 335 9842",
    "sg:postcode":"46055",
    "sg:province":"IN",
    "sg:tags":[
        "house"
    ],
    "wof:name":"Geryak Construction Mike",
    "wof:placetype":"venue"
},
  "geometry": {"coordinates":[-85.93141,39.869984],"type":"Point"}
}