{
  "type": "Feature",
  "properties": {
    "addr:full":"593 Westfield Rd Noblesville IN 46060",
    "addr:housenumber":"593",
    "addr:postcode":"46060",
    "addr:street":"Westfield Rd",
    "iso:country":"US",
    "sg:address":"593 Westfield Rd",
    "sg:city":"Noblesville",
    "sg:classifiers":[
        {
            "category":"Education",
            "subcategory":"Kindergarten",
            "type":"Public Place"
        }
    ],
    "sg:phone":"+1 317 776 9916",
    "sg:postcode":"46060",
    "sg:province":"IN",
    "sg:tags":[
        "school",
        "driving"
    ],
    "wof:name":"A A Indiana Driving School",
    "wof:placetype":"venue"
},
  "geometry": {"coordinates":[-86.026802,40.046902],"type":"Point"}
}