{
  "type": "Feature",
  "properties": {
    "iso:country":"US",
    "sg:address":"704 North St",
    "sg:city":"Logansport",
    "sg:classifiers":[
        {
            "category":"Shopping",
            "subcategory":"Bicycles & Sporting Goods",
            "type":"Retail Goods"
        }
    ],
    "sg:phone":"+1 574 753 9473",
    "sg:postcode":"46947",
    "sg:province":"IN",
    "sg:tags":[
        "bait",
        "fishing"
    ],
    "wof:name":"Peattie's Bait & Tackle",
    "wof:placetype":"venue"
},
  "geometry": {"coordinates":[-86.360557,40.756176],"type":"Point"}
}