{
  "type": "Feature",
  "properties": {
    "iso:country":"US",
    "sg:address":"3585 W State Road 46",
    "sg:city":"Bloomington",
    "sg:classifiers":[
        {
            "category":"Autos & Motor Vehicles",
            "subcategory":"Fuel & Gas Station",
            "type":"Retail Goods"
        }
    ],
    "sg:phone":"+1 812 336 3893",
    "sg:postcode":"47404",
    "sg:province":"IN",
    "sg:website":"www.speedway.com",
    "wof:name":"Speedway Petroleum Corp",
    "wof:placetype":"venue"
},
  "geometry": {"coordinates":[-86.57497600000001,39.199484],"type":"Point"}
}