{
  "type": "Feature",
  "properties": {
    "iso:country":"US",
    "sg:address":"21 Catalpa Ave",
    "sg:city":"Lawrenceburg",
    "sg:classifiers":[
        {
            "category":"Freight",
            "type":"Transportation"
        }
    ],
    "sg:phone":"+1 812 537 3915",
    "sg:postcode":"47025",
    "sg:province":"IN",
    "sg:tags":[
        "operator",
        "local",
        "trucking"
    ],
    "wof:name":"CWC Cartage",
    "wof:placetype":"venue"
},
  "geometry": {"coordinates":[-84.856143,39.119219],"type":"Point"}
}