{
  "type": "Feature",
  "properties": {
    "iso:country":"US",
    "sg:address":"852 E 300 S",
    "sg:city":"Franklin",
    "sg:phone":"+1 317 736 4081",
    "sg:postcode":"46131",
    "sg:province":"IN",
    "sg:tags":[
        "farm",
        "corn",
        "soybean"
    ],
    "wof:name":"William Canary",
    "wof:placetype":"venue"
},
  "geometry": {"coordinates":[-86.087001,39.433109],"type":"Point"}
}