{
  "type": "Feature",
  "properties": {
    "iso:country":"US",
    "sg:address":"1124 W 53rd St",
    "sg:city":"Anderson",
    "sg:classifiers":[
        {
            "category":"Manufacturing",
            "subcategory":"Tools & Machinery",
            "type":"Manufacturing & Wholesale Goods"
        }
    ],
    "sg:phone":"+1 765 644 2821",
    "sg:postcode":"46013",
    "sg:province":"IN",
    "sg:tags":[
        "industry",
        "special"
    ],
    "sg:website":"www.perfecto.com",
    "wof:name":"Perfecto Tool & Engineering Co",
    "wof:placetype":"venue"
},
  "geometry": {"coordinates":[-85.694136,40.061657],"type":"Point"}
}