{
  "type": "Feature",
  "properties": {
    "iso:country":"US",
    "sg:address":"6109 Cambridge Way",
    "sg:city":"Plainfield",
    "sg:classifiers":[
        {
            "category":"Restaurant",
            "type":"Food & Drink"
        }
    ],
    "sg:phone":"+1 317 838 5641",
    "sg:postcode":"46168",
    "sg:province":"IN",
    "wof:name":"Indy Mix America Mxcn Rstrnt",
    "wof:placetype":"venue"
},
  "geometry": {"coordinates":[-86.367632,39.671149],"type":"Point"}
}