{
  "type": "Feature",
  "properties": {
    "iso:country":"US",
    "sg:address":"2313 Lammermoor Cir",
    "sg:city":"Indianapolis",
    "sg:classifiers":[
        {
            "category":"Professional",
            "subcategory":"Business Services",
            "type":"Services"
        }
    ],
    "sg:phone":"+1 317 241 2757",
    "sg:postcode":"46214",
    "sg:province":"IN",
    "sg:tags":[
        "consultant",
        "coach"
    ],
    "wof:name":"Justice Legal Nurse Consulting",
    "wof:placetype":"venue"
},
  "geometry": {"coordinates":[-86.30419000000001,39.79747],"type":"Point"}
}