{
  "type": "Feature",
  "properties": {
    "iso:country":"US",
    "sg:address":"4230 Lake Ave",
    "sg:city":"Fort Wayne",
    "sg:classifiers":[
        {
            "category":"Building & Trades",
            "subcategory":"Construction",
            "type":"Services"
        }
    ],
    "sg:phone":"+1 260 420 4888",
    "sg:postcode":"46815",
    "sg:province":"IN",
    "sg:tags":[
        "home",
        "improvement"
    ],
    "wof:name":"Home Depot",
    "wof:placetype":"venue"
},
  "geometry": {"coordinates":[-85.086471,41.090465],"type":"Point"}
}