{
  "type": "Feature",
  "properties": {
    "iso:country":"US",
    "sg:address":"609 E Dupont Rd",
    "sg:city":"Fort Wayne",
    "sg:classifiers":[
        {
            "category":"Cinema",
            "subcategory":"Movie Rental",
            "type":"Entertainment"
        }
    ],
    "sg:phone":"+1 260 637 4144",
    "sg:postcode":"46825",
    "sg:province":"IN",
    "sg:tags":[
        "leasing",
        "video",
        "disc",
        "tape"
    ],
    "wof:name":"Hollywood Video",
    "wof:placetype":"venue"
},
  "geometry": {"coordinates":[-85.13420600000001,41.178235],"type":"Point"}
}