{
  "type": "Feature",
  "properties": {
    "iso:country":"US",
    "sg:address":"7847 Prairie View Dr",
    "sg:city":"Indianapolis",
    "sg:classifiers":[
        {
            "category":"Shopping",
            "subcategory":"Tobacco",
            "type":"Retail Goods"
        }
    ],
    "sg:phone":"+1 317 570 9822",
    "sg:postcode":"46256",
    "sg:province":"IN",
    "sg:tags":[
        "cigarette",
        "cigar",
        "dealer"
    ],
    "wof:name":"Us Tobacco",
    "wof:placetype":"venue"
},
  "geometry": {"coordinates":[-86.005349,39.896991],"type":"Point"}
}