{
  "type": "Feature",
  "properties": {
    "iso:country":"US",
    "sg:address":"930 Prospect St",
    "sg:city":"Indianapolis",
    "sg:classifiers":[
        {
            "category":"Professional",
            "subcategory":"Business Services",
            "type":"Services"
        }
    ],
    "sg:phone":"+1 317 423 1100",
    "sg:postcode":"46203",
    "sg:province":"IN",
    "sg:tags":[
        "merchandising"
    ],
    "wof:name":"Lyte Merchandise Inc",
    "wof:placetype":"venue"
},
  "geometry": {"coordinates":[-86.141917,39.752321],"type":"Point"}
}