{
  "type": "Feature",
  "properties": {
    "iso:country":"US",
    "sg:address":"2422 Lincolnway E",
    "sg:city":"Goshen",
    "sg:classifiers":[
        {
            "category":"Utilities",
            "subcategory":"Fuel Oil & Lpg",
            "type":"Services"
        }
    ],
    "sg:phone":"+1 574 533 4181",
    "sg:postcode":"46526",
    "sg:province":"IN",
    "sg:tags":[
        "propane",
        "gas"
    ],
    "sg:website":"www.amerigas.com",
    "wof:name":"Ameri Gas Inc",
    "wof:placetype":"venue"
},
  "geometry": {"coordinates":[-85.797669,41.562179],"type":"Point"}
}