{
  "type": "Feature",
  "properties": {
    "iso:country":"US",
    "sg:address":"1605 W Water St",
    "sg:city":"Hartford City",
    "sg:classifiers":[
        {
            "category":"Organizations",
            "subcategory":"Community Association",
            "type":"Services"
        }
    ],
    "sg:phone":"+1 765 348 0700",
    "sg:postcode":"47348",
    "sg:province":"IN",
    "sg:tags":[
        "club"
    ],
    "wof:name":"Blackford Golf Club",
    "wof:placetype":"venue"
},
  "geometry": {"coordinates":[-85.387543,40.450479],"type":"Point"}
}