{
  "type": "Feature",
  "properties": {
    "iso:country":"US",
    "sg:address":"2029 Villa Dr",
    "sg:city":"Fort Wayne",
    "sg:classifiers":[
        {
            "category":"Personal",
            "type":"Services"
        }
    ],
    "sg:phone":"+1 260 747 5605",
    "sg:postcode":"46819",
    "sg:province":"IN",
    "wof:name":"Maximum Styling Salon Inc",
    "wof:placetype":"venue"
},
  "geometry": {"coordinates":[-85.168527,41.000677],"type":"Point"}
}