{
  "type": "Feature",
  "properties": {
    "iso:country":"US",
    "sg:address":"6426 E 82nd St",
    "sg:city":"Indianapolis",
    "sg:classifiers":[
        {
            "category":"Restaurant",
            "type":"Food & Drink"
        }
    ],
    "sg:menulink":"http://www.allmenus.com/in/lawrence/8825-hooters/menu/",
    "sg:phone":"+1 317 577 1477",
    "sg:postcode":"46250",
    "sg:province":"IN",
    "sg:tags":[
        "american",
        "wing"
    ],
    "wof:name":"Hooters",
    "wof:placetype":"venue"
},
  "geometry": {"coordinates":[-86.05653,39.905324],"type":"Point"}
}