{
  "type": "Feature",
  "properties": {
    "iso:country":"US",
    "sg:address":"15080 Wicker Ave",
    "sg:city":"Cedar Lake",
    "sg:classifiers":[
        {
            "category":"Wholesale",
            "subcategory":"Construction Materials",
            "type":"Manufacturing & Wholesale Goods"
        }
    ],
    "sg:phone":"+1 219 696 7646",
    "sg:postcode":"46303",
    "sg:province":"IN",
    "sg:tags":[
        "fence"
    ],
    "wof:name":"FFC Fencing Co",
    "wof:placetype":"venue"
},
  "geometry": {"coordinates":[-87.47002999999999,41.345027],"type":"Point"}
}