{
  "type": "Feature",
  "properties": {
    "iso:country":"US",
    "sg:address":"719 Jefferson St",
    "sg:city":"Alexandria",
    "sg:classifiers":[
        {
            "category":"Retail",
            "subcategory":"Animal Services",
            "type":"Services"
        }
    ],
    "sg:phone":"+1 765 724 4187",
    "sg:postcode":"46001",
    "sg:province":"IN",
    "sg:tags":[
        "pet",
        "grooming",
        "washing"
    ],
    "wof:name":"Groovy Grooming",
    "wof:placetype":"venue"
},
  "geometry": {"coordinates":[-85.684963,40.264716],"type":"Point"}
}