{
  "type": "Feature",
  "properties": {
    "addr:full":"9901 Allisonville Rd Fishers IN 46038",
    "addr:housenumber":"9901",
    "addr:postcode":"46038",
    "addr:street":"Allisonville Rd",
    "iso:country":"US",
    "sg:address":"9901 Allisonville Rd",
    "sg:city":"Fishers",
    "sg:classifiers":[
        {
            "category":"Professional",
            "subcategory":"Printing & Photocopies",
            "type":"Services"
        }
    ],
    "sg:phone":"+1 317 598 0661",
    "sg:postcode":"46038",
    "sg:province":"IN",
    "sg:tags":[
        "blueprinting",
        "art",
        "supply"
    ],
    "sg:website":"www.easternengineering.com",
    "wof:name":"Eastern Engineering Supply Inc",
    "wof:placetype":"venue"
},
  "geometry": {"coordinates":[-86.059898,39.931801],"type":"Point"}
}