{
  "type": "Feature",
  "properties": {
    "iso:country":"US",
    "sg:address":"735 E Spear Rd",
    "sg:city":"Columbia City",
    "sg:classifiers":[
        {
            "category":"Professional",
            "type":"Services"
        }
    ],
    "sg:phone":"+1 260 691 3289",
    "sg:postcode":"46725",
    "sg:province":"IN",
    "wof:name":"Lakeside Embroidery",
    "wof:placetype":"venue"
},
  "geometry": {"coordinates":[-85.477818,41.256258],"type":"Point"}
}