{
  "type": "Feature",
  "properties": {
    "iso:country":"US",
    "sg:address":"3510 John Hinkle Pl",
    "sg:city":"Bloomington",
    "sg:classifiers":[
        {
            "category":"Building & Trades",
            "subcategory":"Construction",
            "type":"Services"
        }
    ],
    "sg:phone":"+1 812 339 2860",
    "sg:postcode":"47408",
    "sg:province":"IN",
    "sg:tags":[
        "elevator"
    ],
    "wof:name":"Otis Elevator",
    "wof:placetype":"venue"
},
  "geometry": {"coordinates":[-86.49093499999999,39.170962],"type":"Point"}
}