{
  "type": "Feature",
  "properties": {
    "iso:country":"US",
    "sg:address":"220 NW Lincoln Ave",
    "sg:city":"Portland",
    "sg:classifiers":[
        {
            "category":"Shopping",
            "subcategory":"Department Store",
            "type":"Retail Goods"
        }
    ],
    "sg:phone":"+1 260 726 3996",
    "sg:postcode":"47371",
    "sg:province":"IN",
    "sg:tags":[
        "shop"
    ],
    "wof:name":"Dollar General",
    "wof:placetype":"venue"
},
  "geometry": {"coordinates":[-84.979645,40.446769],"type":"Point"}
}