{
  "type": "Feature",
  "properties": {
    "iso:country":"US",
    "sg:address":"2129 N Oak Rd",
    "sg:city":"Plymouth",
    "sg:classifiers":[
        {
            "category":"Building & Trades",
            "subcategory":"Construction",
            "type":"Services"
        }
    ],
    "sg:phone":"+1 574 936 6979",
    "sg:postcode":"46563",
    "sg:province":"IN",
    "sg:tags":[
        "general",
        "contractor"
    ],
    "wof:name":"Denaut Construction Co Inc",
    "wof:placetype":"venue"
},
  "geometry": {"coordinates":[-86.328874,41.359293],"type":"Point"}
}