{
  "type": "Feature",
  "properties": {
    "iso:country":"US",
    "sg:address":"2314 W Franklin St",
    "sg:city":"Evansville",
    "sg:classifiers":[
        {
            "category":"Shopping",
            "subcategory":"Bicycles & Sporting Goods",
            "type":"Retail Goods"
        }
    ],
    "sg:phone":"+1 812 428 0028",
    "sg:postcode":"47712",
    "sg:province":"IN",
    "wof:name":"Billiard Shop",
    "wof:placetype":"venue"
},
  "geometry": {"coordinates":[-87.600358,37.980454],"type":"Point"}
}