{
  "type": "Feature",
  "properties": {
    "addr:full":"3019 W Hill Lake Rd Claypool IN 46510",
    "addr:housenumber":"3019",
    "addr:postcode":"46510",
    "addr:street":"W Hill Lake Rd",
    "iso:country":"US",
    "sg:address":"3019 W Hill Lake Rd",
    "sg:city":"Claypool",
    "sg:classifiers":[
        {
            "category":"Building & Trades",
            "subcategory":"Plumbing",
            "type":"Services"
        }
    ],
    "sg:phone":"+1 574 566 2908",
    "sg:postcode":"46510",
    "sg:province":"IN",
    "sg:tags":[
        "plumbing",
        "contractor"
    ],
    "wof:name":"Surface Plumbing & Heating Svc",
    "wof:placetype":"venue"
},
  "geometry": {"coordinates":[-85.89300799999999,41.110342],"type":"Point"}
}