{
  "type": "Feature",
  "properties": {
    "addr:full":"2270 Wampler Rd Martinsville IN 46151",
    "addr:housenumber":"2270",
    "addr:postcode":"46151",
    "addr:street":"Wampler Rd",
    "iso:country":"US",
    "sg:address":"2270 Wampler Rd",
    "sg:city":"Martinsville",
    "sg:classifiers":[
        {
            "category":"Building & Trades",
            "subcategory":"Construction",
            "type":"Services"
        }
    ],
    "sg:phone":"+1 765 342 3877",
    "sg:postcode":"46151",
    "sg:province":"IN",
    "sg:tags":[
        "residence",
        "general",
        "family",
        "contractor"
    ],
    "wof:name":"Wampler Construction",
    "wof:placetype":"venue"
},
  "geometry": {"coordinates":[-86.307007,39.45317],"type":"Point"}
}