{
  "type": "Feature",
  "properties": {
    "iso:country":"US",
    "sg:address":"9409 Illinois Rd",
    "sg:city":"Fort Wayne",
    "sg:classifiers":[
        {
            "category":"Social Services",
            "subcategory":"Child Care",
            "type":"Services"
        }
    ],
    "sg:phone":"+1 260 432 7186",
    "sg:postcode":"46804",
    "sg:province":"IN",
    "sg:tags":[
        "kindergarten",
        "academic",
        "school"
    ],
    "wof:name":"Coventry School Early Learning",
    "wof:placetype":"venue"
},
  "geometry": {"coordinates":[-85.26575699999999,41.074091],"type":"Point"}
}