{
  "type": "Feature",
  "properties": {
    "addr:full":"2503 Sears St Valparaiso IN 46383",
    "addr:housenumber":"2503",
    "addr:postcode":"46383",
    "addr:street":"Sears St",
    "iso:country":"US",
    "sg:address":"2503 Sears St",
    "sg:city":"Valparaiso",
    "sg:classifiers":[
        {
            "category":"Social Services",
            "type":"Services"
        }
    ],
    "sg:phone":"+1 219 464 7971",
    "sg:postcode":"46383",
    "sg:province":"IN",
    "wof:name":"Greyhound Guardians Inc",
    "wof:placetype":"venue"
},
  "geometry": {"coordinates":[-87.064339,41.49089],"type":"Point"}
}