{
  "type": "Feature",
  "properties": {
    "iso:country":"US",
    "sg:address":"5694 N Co Rd 10 E",
    "sg:city":"Greensburg",
    "sg:classifiers":[
        {
            "category":"Professional",
            "subcategory":"Accounting & Tax Preparation",
            "type":"Services"
        }
    ],
    "sg:phone":"+1 812 663 0095",
    "sg:postcode":"47240",
    "sg:province":"IN",
    "sg:tags":[
        "return"
    ],
    "wof:name":"H & H Tax Service",
    "wof:placetype":"venue"
},
  "geometry": {"coordinates":[-85.478179,39.420224],"type":"Point"}
}