{
  "type": "Feature",
  "properties": {
    "iso:country":"US",
    "sg:address":"12707 Spencerville Rd",
    "sg:city":"Harlan",
    "sg:classifiers":[
        {
            "category":"Building & Trades",
            "subcategory":"Construction",
            "type":"Services"
        }
    ],
    "sg:phone":"+1 260 657 5154",
    "sg:postcode":"46741",
    "sg:province":"IN",
    "sg:tags":[
        "maker",
        "cabinet"
    ],
    "sg:website":"www.harlancabinets.com",
    "wof:name":"Harlan Cabinets",
    "wof:placetype":"venue"
},
  "geometry": {"coordinates":[-84.91997499999999,41.203381],"type":"Point"}
}