{
  "type": "Feature",
  "properties": {
    "addr:full":"2406 N Richard Dr Shelbyville IN 46176",
    "addr:housenumber":"2406",
    "addr:postcode":"46176",
    "addr:street":"N Richard Dr",
    "iso:country":"US",
    "sg:address":"2406 N Richard Dr",
    "sg:city":"Shelbyville",
    "sg:classifiers":[
        {
            "category":"Manufacturing",
            "subcategory":"Furniture",
            "type":"Manufacturing & Wholesale Goods"
        }
    ],
    "sg:phone":"+1 317 398 9580",
    "sg:postcode":"46176",
    "sg:province":"IN",
    "sg:tags":[
        "mfg"
    ],
    "wof:name":"Inlow Foundation Inc",
    "wof:placetype":"venue"
},
  "geometry": {"coordinates":[-85.779915,39.567194],"type":"Point"}
}