{
  "type": "Feature",
  "properties": {
    "addr:full":"7064 W Timber Dr New Palestine IN 46163",
    "addr:housenumber":"7064",
    "addr:postcode":"dr;46163",
    "addr:street":"W Timber",
    "iso:country":"US",
    "sg:address":"7064 W Timber Dr",
    "sg:city":"New Palestine",
    "sg:classifiers":[
        {
            "category":"Professional",
            "type":"Services"
        }
    ],
    "sg:phone":"+1 317 861 8884",
    "sg:postcode":"46163",
    "sg:province":"IN",
    "wof:name":"Indiana Turtle Care Inc",
    "wof:placetype":"venue"
},
  "geometry": {"coordinates":[-85.936509,39.720262],"type":"Point"}
}