{
  "type": "Feature",
  "properties": {
    "iso:country":"US",
    "sg:address":"4426 W 25th Ave",
    "sg:city":"Gary",
    "sg:classifiers":[
        {
            "category":"Retail",
            "subcategory":"Repair Shop",
            "type":"Services"
        }
    ],
    "sg:phone":"+1 219 977 9883",
    "sg:postcode":"46404",
    "sg:province":"IN",
    "sg:tags":[
        "plumbing",
        "drain",
        "cleaning",
        "sewer"
    ],
    "wof:name":"D & B Sewer Drain & Plumbing",
    "wof:placetype":"venue"
},
  "geometry": {"coordinates":[-87.392229,41.573464],"type":"Point"}
}