{
  "type": "Feature",
  "properties": {
    "iso:country":"US",
    "sg:address":"2843 S Holt Rd",
    "sg:city":"Indianapolis",
    "sg:classifiers":[
        {
            "category":"Banks & Credit Unions",
            "subcategory":"Bank",
            "type":"Services"
        }
    ],
    "sg:phone":"+1 317 243 1663",
    "sg:postcode":"46241",
    "sg:province":"IN",
    "sg:tags":[
        "financing"
    ],
    "wof:name":"ITC Acceptance Co",
    "wof:placetype":"venue"
},
  "geometry": {"coordinates":[-86.225099,39.723543],"type":"Point"}
}