{
  "type": "Feature",
  "properties": {
    "iso:country":"US",
    "sg:address":"2205 S Old Decker Rd",
    "sg:city":"Vincennes",
    "sg:classifiers":[
        {
            "category":"Manufacturing",
            "subcategory":"Tools & Machinery",
            "type":"Manufacturing & Wholesale Goods"
        }
    ],
    "sg:phone":"+1 812 886 5500",
    "sg:postcode":"47591",
    "sg:province":"IN",
    "sg:tags":[
        "farm",
        "equipment"
    ],
    "sg:website":"www.rileyequipment.com",
    "wof:name":"Riley Equipment Inc",
    "wof:placetype":"venue"
},
  "geometry": {"coordinates":[-87.527551,38.64826],"type":"Point"}
}