{
  "type": "Feature",
  "properties": {
    "addr:full":"3125 Homestead Hills Run Fort Wayne IN 46804",
    "addr:housenumber":"3125",
    "addr:postcode":"46804",
    "addr:street":"Homestead Hills Run",
    "iso:country":"US",
    "sg:address":"3125 Homestead Hills Run",
    "sg:city":"Fort Wayne",
    "sg:classifiers":[
        {
            "category":"Restaurant",
            "type":"Food & Drink"
        }
    ],
    "sg:phone":"+1 260 436 6691",
    "sg:postcode":"46804",
    "sg:province":"IN",
    "sg:tags":[
        "eating"
    ],
    "wof:name":"Skyline Cafe LLC",
    "wof:placetype":"venue"
},
  "geometry": {"coordinates":[-85.283503,41.055878],"type":"Point"}
}