{
  "type": "Feature",
  "properties": {
    "iso:country":"US",
    "sg:address":"2400 W Co Rd 500 S",
    "sg:city":"Muncie",
    "sg:classifiers":[
        {
            "category":"Building & Trades",
            "subcategory":"Plumbing",
            "type":"Services"
        }
    ],
    "sg:phone":"+1 765 286 8890",
    "sg:postcode":"47302",
    "sg:province":"IN",
    "sg:tags":[
        "conditioning",
        "air",
        "system",
        "contractor"
    ],
    "wof:name":"Cooper Consulting & Property",
    "wof:placetype":"venue"
},
  "geometry": {"coordinates":[-85.412346,40.120185],"type":"Point"}
}