{
  "type": "Feature",
  "properties": {
    "iso:country":"US",
    "sg:address":"1425 Oliver Rd",
    "sg:city":"Wadesville",
    "sg:classifiers":[
        {
            "category":"Organizations",
            "subcategory":"Religious Organization",
            "type":"Services"
        }
    ],
    "sg:phone":"+1 812 783 2337",
    "sg:postcode":"47638",
    "sg:province":"IN",
    "wof:name":"Mount Zion Gen Baptst Church",
    "wof:placetype":"venue"
},
  "geometry": {"coordinates":[-87.837286,38.055889],"type":"Point"}
}