{
  "type": "Feature",
  "properties": {
    "iso:country":"US",
    "sg:address":"6447 W Jefferson Blvd",
    "sg:city":"Fort Wayne",
    "sg:classifiers":[
        {
            "category":"Retail",
            "subcategory":"Photofinishing",
            "type":"Services"
        }
    ],
    "sg:phone":"+1 260 432 7767",
    "sg:postcode":"46804",
    "sg:province":"IN",
    "sg:tags":[
        "photo",
        "finishing"
    ],
    "wof:name":"Stellhorn",
    "wof:placetype":"venue"
},
  "geometry": {"coordinates":[-85.224382,41.056193],"type":"Point"}
}