{
  "type": "Feature",
  "properties": {
    "addr:full":"740 E 52nd St Indianapolis IN 46205",
    "addr:housenumber":"740",
    "addr:postcode":"46205",
    "addr:street":"E 52Nd St",
    "iso:country":"US",
    "sg:address":"740 E 52nd St",
    "sg:city":"Indianapolis",
    "sg:classifiers":[
        {
            "category":"Professional",
            "subcategory":"Accounting & Tax Preparation",
            "type":"Services"
        },
        {
            "category":"Professional",
            "type":"Services"
        }
    ],
    "sg:phone":"+1 317 251 9101",
    "sg:postcode":"46205",
    "sg:province":"IN",
    "sg:tags":[
        "data",
        "processing",
        "payroll",
        "bookkeeping"
    ],
    "sg:website":"http://www.cdadata.com",
    "wof:name":"Church Data Associates",
    "wof:placetype":"venue"
},
  "geometry": {"coordinates":[-86.145195,39.846921],"type":"Point"}
}