{
  "type": "Feature",
  "properties": {
    "addr:full":"2935 Wedgewood Dr Columbus IN 47203",
    "addr:housenumber":"2935",
    "addr:postcode":"47203",
    "addr:street":"Wedgewood Dr",
    "iso:country":"US",
    "sg:address":"2935 Wedgewood Dr",
    "sg:city":"Columbus",
    "sg:classifiers":[
        {
            "category":"Organizations",
            "subcategory":"Community Association",
            "type":"Services"
        }
    ],
    "sg:phone":"+1 812 372 8570",
    "sg:postcode":"47203",
    "sg:province":"IN",
    "wof:name":"Sertoma International",
    "wof:placetype":"venue"
},
  "geometry": {"coordinates":[-85.862582,39.227508],"type":"Point"}
}