{
  "type": "Feature",
  "properties": {
    "addr:full":"15600 Pear Rd Plymouth IN 46563",
    "addr:housenumber":"15600",
    "addr:postcode":"46563",
    "addr:street":"Pear Rd",
    "iso:country":"US",
    "sg:address":"15600 Pear Rd",
    "sg:city":"Plymouth",
    "sg:classifiers":[
        {
            "category":"Real Estate",
            "subcategory":"Real Estate Operator",
            "type":"Services"
        }
    ],
    "sg:phone":"+1 574 936 7875",
    "sg:postcode":"46563",
    "sg:province":"IN",
    "sg:tags":[
        "property",
        "lessor"
    ],
    "wof:name":"Steve Ringer",
    "wof:placetype":"venue"
},
  "geometry": {"coordinates":[-86.357069,41.250755],"type":"Point"}
}