{
  "type": "Feature",
  "properties": {
    "iso:country":"US",
    "sg:address":"1092 3rd Ave SW",
    "sg:city":"Carmel",
    "sg:classifiers":[
        {
            "category":"Manufacturing",
            "subcategory":"Metals",
            "type":"Manufacturing & Wholesale Goods"
        }
    ],
    "sg:phone":"+1 317 574 9009",
    "sg:postcode":"46032",
    "sg:province":"IN",
    "sg:tags":[
        "treating",
        "heat"
    ],
    "sg:website":"www.kauffmanproducts.com",
    "wof:name":"Kauffman Products Inc",
    "wof:placetype":"venue"
},
  "geometry": {"coordinates":[-86.131035,39.964168],"type":"Point"}
}