{
  "type": "Feature",
  "properties": {
    "iso:country":"US",
    "sg:address":"2900 Campbell St",
    "sg:city":"Valparaiso",
    "sg:classifiers":[
        {
            "category":"Home & Garden",
            "subcategory":"Garden Supply",
            "type":"Retail Goods"
        }
    ],
    "sg:phone":"+1 219 462 4055",
    "sg:postcode":"46385",
    "sg:province":"IN",
    "sg:tags":[
        "landscaping",
        "equipment"
    ],
    "wof:name":"Clifford Stone & Material Co",
    "wof:placetype":"venue"
},
  "geometry": {"coordinates":[-87.065853,41.493179],"type":"Point"}
}