{
  "type": "Feature",
  "properties": {
    "iso:country":"US",
    "sg:address":"2800 E Wabash St",
    "sg:city":"Frankfort",
    "sg:classifiers":[
        {
            "category":"Sports & Exercise",
            "subcategory":"Bowling",
            "type":"Entertainment"
        }
    ],
    "sg:phone":"+1 765 654 7193",
    "sg:postcode":"46041",
    "sg:province":"IN",
    "sg:tags":[
        "center"
    ],
    "wof:name":"Classic Lanes",
    "wof:placetype":"venue"
},
  "geometry": {"coordinates":[-86.47245599999999,40.278833],"type":"Point"}
}