{
  "type": "Feature",
  "properties": {
    "iso:country":"US",
    "sg:address":"2710 E 250 N",
    "sg:city":"Bluffton",
    "sg:classifiers":[
        {
            "category":"Retail",
            "subcategory":"Auto Repair",
            "type":"Services"
        }
    ],
    "sg:phone":"+1 260 824 3271",
    "sg:postcode":"46714",
    "sg:province":"IN",
    "sg:tags":[
        "general"
    ],
    "wof:name":"Garretts Marathon Service Stn",
    "wof:placetype":"venue"
},
  "geometry": {"coordinates":[-85.166618,40.778679],"type":"Point"}
}