{
  "type": "Feature",
  "properties": {
    "iso:country":"US",
    "sg:address":"6326 Rucker Rd",
    "sg:city":"Indianapolis",
    "sg:classifiers":[
        {
            "category":"Real Estate",
            "subcategory":"Real Estate Agent",
            "type":"Services"
        }
    ],
    "sg:phone":"+1 317 253 4800",
    "sg:postcode":"46220",
    "sg:province":"IN",
    "wof:name":"R L Young Co",
    "wof:placetype":"venue"
},
  "geometry": {"coordinates":[-86.079346,39.868726],"type":"Point"}
}