{
  "type": "Feature",
  "properties": {
    "iso:country":"US",
    "sg:address":"2704 W Wilden Ave",
    "sg:city":"Goshen",
    "sg:classifiers":[
        {
            "category":"Professional",
            "subcategory":"Engineering",
            "type":"Services"
        }
    ],
    "sg:phone":"+1 574 537 1300",
    "sg:postcode":"46528",
    "sg:province":"IN",
    "sg:tags":[
        "engineer"
    ],
    "wof:name":"Kevin M Finn",
    "wof:placetype":"venue"
},
  "geometry": {"coordinates":[-85.867778,41.603609],"type":"Point"}
}