{
  "type": "Feature",
  "properties": {
    "addr:full":"9111 Louisiana St Merrillville IN 46410",
    "addr:housenumber":"9111",
    "addr:postcode":"46410",
    "addr:street":"Louisiana St",
    "iso:country":"US",
    "sg:address":"9111 Louisiana St",
    "sg:city":"Merrillville",
    "sg:classifiers":[
        {
            "category":"Building & Trades",
            "subcategory":"Electrical",
            "type":"Services"
        }
    ],
    "sg:phone":"+1 219 769 6007",
    "sg:postcode":"46410",
    "sg:province":"IN",
    "sg:tags":[
        "electric",
        "contractor"
    ],
    "wof:name":"Sweeny Electric Co Inc",
    "wof:placetype":"venue"
},
  "geometry": {"coordinates":[-87.31950000000001,41.451825],"type":"Point"}
}