{
  "type": "Feature",
  "properties": {
    "iso:country":"US",
    "sg:address":"2113 State Rd 329",
    "sg:city":"Logansport",
    "sg:classifiers":[
        {
            "category":"Shopping",
            "subcategory":"Bicycles & Sporting Goods",
            "type":"Retail Goods"
        }
    ],
    "sg:phone":"+1 574 722 3206",
    "sg:postcode":"46947",
    "sg:province":"IN",
    "sg:tags":[
        "equipment",
        "outdoor",
        "accessory"
    ],
    "wof:name":"Great Outdoors",
    "wof:placetype":"venue"
},
  "geometry": {"coordinates":[-86.375515,40.733737],"type":"Point"}
}