{
  "type": "Feature",
  "properties": {
    "iso:country":"US",
    "sg:address":"412 6th St",
    "sg:city":"Columbus",
    "sg:classifiers":[
        {
            "category":"Insurance",
            "subcategory":"Hazard Insurance",
            "type":"Services"
        }
    ],
    "sg:phone":"+1 812 378 0714",
    "sg:postcode":"47201",
    "sg:province":"IN",
    "sg:tags":[
        "employee",
        "benefit",
        "compensation",
        "plan"
    ],
    "wof:name":"Gateway Medical Resource",
    "wof:placetype":"venue"
},
  "geometry": {"coordinates":[-85.919975,39.204404],"type":"Point"}
}