{
  "type": "Feature",
  "properties": {
    "iso:country":"US",
    "sg:address":"2390 Elkhart Rd",
    "sg:city":"Goshen",
    "sg:classifiers":[
        {
            "category":"Building & Trades",
            "subcategory":"Construction",
            "type":"Services"
        }
    ],
    "sg:phone":"+1 574 533 2157",
    "sg:postcode":"46526",
    "sg:province":"IN",
    "sg:tags":[
        "downspouts",
        "gutter"
    ],
    "wof:name":"Rainflow Of Michiana Gutters",
    "wof:placetype":"venue"
},
  "geometry": {"coordinates":[-85.87004399999999,41.603364],"type":"Point"}
}