{
  "type": "Feature",
  "properties": {
    "iso:country":"US",
    "sg:address":"216 NW 10th St",
    "sg:city":"Evansville",
    "sg:classifiers":[
        {
            "category":"Wholesale",
            "subcategory":"Machinery & Supplies",
            "type":"Manufacturing & Wholesale Goods"
        }
    ],
    "sg:phone":"+1 812 422 4191",
    "sg:postcode":"47708",
    "sg:province":"IN",
    "sg:tags":[
        "janitor"
    ],
    "wof:name":"Kor-X-All Co",
    "wof:placetype":"venue"
},
  "geometry": {"coordinates":[-87.566591,37.976371],"type":"Point"}
}