{
  "type": "Feature",
  "properties": {
    "iso:country":"US",
    "sg:address":"1800 N Stonelake Dr",
    "sg:city":"Bloomington",
    "sg:classifiers":[
        {
            "category":"Organizations",
            "subcategory":"Non-profit Organization",
            "type":"Services"
        }
    ],
    "sg:phone":"+1 812 339 2203",
    "sg:postcode":"47404",
    "sg:province":"IN",
    "sg:website":"www.ait.net",
    "wof:name":"Agency For Instructional Tech",
    "wof:placetype":"venue"
},
  "geometry": {"coordinates":[-86.544583,39.187176],"type":"Point"}
}