{
  "type": "Feature",
  "properties": {
    "iso:country":"US",
    "sg:address":"1600 E Main St",
    "sg:city":"Richmond",
    "sg:classifiers":[
        {
            "category":"Restaurant",
            "type":"Food & Drink"
        }
    ],
    "sg:phone":"+1 765 962 7041",
    "sg:postcode":"47374",
    "sg:province":"IN",
    "wof:name":"Main Street Diner",
    "wof:placetype":"venue"
},
  "geometry": {"coordinates":[-84.879453,39.829696],"type":"Point"}
}