{
  "type": "Feature",
  "properties": {
    "addr:full":"6825 Parkdale Pl Indianapolis IN 46254",
    "addr:housenumber":"6825",
    "addr:postcode":"46254",
    "addr:street":"Parkdale Pl",
    "iso:country":"US",
    "sg:address":"6825 Parkdale Pl",
    "sg:city":"Indianapolis",
    "sg:classifiers":[
        {
            "category":"Professional",
            "subcategory":"Engineering",
            "type":"Services"
        }
    ],
    "sg:phone":"+1 317 293 5930",
    "sg:postcode":"46254",
    "sg:province":"IN",
    "sg:tags":[
        "engineer"
    ],
    "wof:name":"Competitive Edge Tech Inc",
    "wof:placetype":"venue"
},
  "geometry": {"coordinates":[-86.28282400000001,39.826137],"type":"Point"}
}