{
  "type": "Feature",
  "properties": {
    "addr:full":"2852 N Hillcrest Dr Seymour IN 47274",
    "addr:housenumber":"2852",
    "addr:postcode":"47274",
    "addr:street":"N Hillcrest Dr",
    "iso:country":"US",
    "sg:address":"2852 N Hillcrest Dr",
    "sg:city":"Seymour",
    "sg:classifiers":[
        {
            "category":"Retail",
            "subcategory":"Laundry & Dry Cleaning",
            "type":"Services"
        }
    ],
    "sg:phone":"+1 812 524 2405",
    "sg:postcode":"47274",
    "sg:province":"IN",
    "wof:name":"Clean Right",
    "wof:placetype":"venue"
},
  "geometry": {"coordinates":[-85.88607399999999,38.924601],"type":"Point"}
}