{
  "type": "Feature",
  "properties": {
    "addr:full":"418 N College Ave Bloomington IN 47404",
    "addr:housenumber":"418",
    "addr:postcode":"47404",
    "addr:street":"N College Ave",
    "iso:country":"US",
    "sg:address":"418 N College Ave",
    "sg:city":"Bloomington",
    "sg:classifiers":[
        {
            "category":"Food & Beverages",
            "subcategory":"Liquor & Beverages",
            "type":"Retail Goods"
        }
    ],
    "sg:phone":"+1 812 335 4609",
    "sg:postcode":"47404",
    "sg:province":"IN",
    "sg:tags":[
        "beer",
        "spirit",
        "wine"
    ],
    "sg:website":"www.bigredliquors.com",
    "wof:name":"Big Red Liquors",
    "wof:placetype":"venue"
},
  "geometry": {"coordinates":[-86.534661,39.169673],"type":"Point"}
}