{
  "type": "Feature",
  "properties": {
    "iso:country":"US",
    "sg:address":"7307 Stones River Dr",
    "sg:city":"Indianapolis",
    "sg:classifiers":[
        {
            "category":"Professional",
            "subcategory":"Engineering",
            "type":"Services"
        }
    ],
    "sg:phone":"+1 317 862 8174",
    "sg:postcode":"46259",
    "sg:province":"IN",
    "sg:tags":[
        "engineer",
        "mechanical"
    ],
    "wof:name":"Manek Corp",
    "wof:placetype":"venue"
},
  "geometry": {"coordinates":[-86.029579,39.661471],"type":"Point"}
}