{
  "type": "Feature",
  "properties": {
    "iso:country":"US",
    "sg:address":"3405 Godsey Rd",
    "sg:city":"Martinsville",
    "sg:classifiers":[
        {
            "category":"Home & Garden",
            "subcategory":"Building Materials",
            "type":"Retail Goods"
        }
    ],
    "sg:phone":"+1 765 342 5372",
    "sg:postcode":"46151",
    "sg:province":"IN",
    "sg:tags":[
        "door"
    ],
    "wof:name":"Gary E Martin & Sons",
    "wof:placetype":"venue"
},
  "geometry": {"coordinates":[-86.493183,39.373361],"type":"Point"}
}