{
  "type": "Feature",
  "properties": {
    "iso:country":"US",
    "sg:address":"311 E 1st St",
    "sg:city":"Ferdinand",
    "sg:classifiers":[
        {
            "category":"Health Services",
            "subcategory":"Nursing And Care Facility",
            "type":"Services"
        }
    ],
    "sg:phone":"+1 812 367 2299",
    "sg:postcode":"47532",
    "sg:province":"IN",
    "sg:tags":[
        "home",
        "convalescent"
    ],
    "wof:name":"Scenic Hills Care Ctr",
    "wof:placetype":"venue"
},
  "geometry": {"coordinates":[-86.86130900000001,38.216751],"type":"Point"}
}