{
  "type": "Feature",
  "properties": {
    "iso:country":"US",
    "sg:address":"202 Main St",
    "sg:city":"Vincennes",
    "sg:classifiers":[
        {
            "category":"Shopping",
            "subcategory":"Gifts & Souvenirs",
            "type":"Retail Goods"
        }
    ],
    "sg:phone":"+1 812 886 8805",
    "sg:postcode":"47591",
    "sg:province":"IN",
    "sg:tags":[
        "collectible"
    ],
    "wof:name":"Old Gimbel Corner Antiques",
    "wof:placetype":"venue"
},
  "geometry": {"coordinates":[-87.532296,38.679938],"type":"Point"}
}