{
  "type": "Feature",
  "properties": {
    "iso:country":"US",
    "sg:address":"7768 Moller Rd",
    "sg:city":"Indianapolis",
    "sg:classifiers":[
        {
            "category":"Wholesale",
            "subcategory":"Electrical",
            "type":"Manufacturing & Wholesale Goods"
        }
    ],
    "sg:phone":"+1 317 876 3008",
    "sg:postcode":"46268",
    "sg:province":"IN",
    "sg:tags":[
        "supply",
        "sign"
    ],
    "wof:name":"Ameriban Inc",
    "wof:placetype":"venue"
},
  "geometry": {"coordinates":[-86.256269,39.893425],"type":"Point"}
}