{
  "type": "Feature",
  "properties": {
    "addr:full":"909 N Wheeling Ave Muncie IN 47303",
    "addr:housenumber":"909",
    "addr:postcode":"47303",
    "addr:street":"N Wheeling Ave",
    "iso:country":"US",
    "sg:address":"909 N Wheeling Ave",
    "sg:city":"Muncie",
    "sg:classifiers":[
        {
            "category":"Restaurant",
            "type":"Food & Drink"
        }
    ],
    "sg:phone":"+1 765 287 0909",
    "sg:postcode":"47303",
    "sg:province":"IN",
    "wof:name":"909 Grill",
    "wof:placetype":"venue"
},
  "geometry": {"coordinates":[-85.39279500000001,40.20188],"type":"Point"}
}