{
  "type": "Feature",
  "properties": {
    "iso:country":"US",
    "sg:address":"7964 Cardinal Cove E",
    "sg:city":"Indianapolis",
    "sg:classifiers":[
        {
            "category":"Professional",
            "type":"Services"
        }
    ],
    "sg:phone":"+1 317 577 2586",
    "sg:postcode":"46256",
    "sg:province":"IN",
    "wof:name":"Touba Housecleaning Service",
    "wof:placetype":"venue"
},
  "geometry": {"coordinates":[-86.029072,39.899005],"type":"Point"}
}