{
  "type": "Feature",
  "properties": {
    "iso:country":"US",
    "sg:address":"3677 W State Rte 62",
    "sg:city":"Boonville",
    "sg:classifiers":[
        {
            "category":"Autos & Motor Vehicles",
            "subcategory":"Automobile Sales",
            "type":"Retail Goods"
        }
    ],
    "sg:phone":"+1 812 897 1310",
    "sg:postcode":"47601",
    "sg:province":"IN",
    "sg:tags":[
        "car",
        "dealer"
    ],
    "wof:name":"Hometown Auto Sales",
    "wof:placetype":"venue"
},
  "geometry": {"coordinates":[-87.31397,38.048269],"type":"Point"}
}