{
  "type": "Feature",
  "properties": {
    "addr:full":"4133 Ridgeway Dr Indianapolis IN 46221",
    "addr:housenumber":"4133",
    "addr:postcode":"46221",
    "addr:street":"Ridgeway Dr",
    "iso:country":"US",
    "sg:address":"4133 Ridgeway Dr",
    "sg:city":"Indianapolis",
    "sg:classifiers":[
        {
            "category":"Manufacturing",
            "subcategory":"Printing",
            "type":"Manufacturing & Wholesale Goods"
        }
    ],
    "sg:phone":"+1 317 248 0715",
    "sg:postcode":"46221",
    "sg:province":"IN",
    "sg:tags":[
        "publisher"
    ],
    "wof:name":"R & R Endeavors Inc",
    "wof:placetype":"venue"
},
  "geometry": {"coordinates":[-86.23241899999999,39.698428],"type":"Point"}
}