{
  "type": "Feature",
  "properties": {
    "iso:country":"US",
    "sg:address":"216 Blue Ridge Rd",
    "sg:city":"Indianapolis",
    "sg:classifiers":[
        {
            "category":"Food & Beverages",
            "subcategory":"Groceries & Convenience Stores",
            "type":"Retail Goods"
        }
    ],
    "sg:phone":"+1 317 283 2210",
    "sg:postcode":"46208",
    "sg:province":"IN",
    "wof:name":"Genesis Enterprise Mgt Co",
    "wof:placetype":"venue"
},
  "geometry": {"coordinates":[-86.162392,39.837604],"type":"Point"}
}