{
  "type": "Feature",
  "properties": {
    "iso:country":"US",
    "sg:address":"1205 E New York St",
    "sg:city":"Indianapolis",
    "sg:classifiers":[
        {
            "category":"Organizations",
            "subcategory":"Religious Organization",
            "type":"Services"
        }
    ],
    "sg:phone":"+1 317 955 0358",
    "sg:postcode":"46202",
    "sg:province":"IN",
    "sg:tags":[
        "church"
    ],
    "sg:website":"www.hopeinternationalministries.com",
    "wof:name":"Hope International Ministries",
    "wof:placetype":"venue"
},
  "geometry": {"coordinates":[-86.13534300000001,39.771293],"type":"Point"}
}