{
  "type": "Feature",
  "properties": {
    "iso:country":"US",
    "sg:address":"305 S Green St",
    "sg:city":"Cambridge City",
    "sg:classifiers":[
        {
            "category":"Manufacturing",
            "subcategory":"Retail Goods",
            "type":"Manufacturing & Wholesale Goods"
        }
    ],
    "sg:phone":"+1 765 478 3742",
    "sg:postcode":"47327",
    "sg:province":"IN",
    "sg:tags":[
        "burial",
        "casket"
    ],
    "wof:name":"Cambridge City Casket Inc",
    "wof:placetype":"venue"
},
  "geometry": {"coordinates":[-85.173338,39.809728],"type":"Point"}
}