{
  "type": "Feature",
  "properties": {
    "iso:country":"US",
    "sg:address":"6324 N 125 W",
    "sg:city":"Whiteland",
    "sg:classifiers":[
        {
            "category":"Professional",
            "subcategory":"Management & Consulting",
            "type":"Services"
        }
    ],
    "sg:phone":"+1 317 535 4077",
    "sg:postcode":"46184",
    "sg:province":"IN",
    "sg:tags":[
        "farm"
    ],
    "wof:name":"Mathena Farm",
    "wof:placetype":"venue"
},
  "geometry": {"coordinates":[-86.12546,39.568021],"type":"Point"}
}