{
  "type": "Feature",
  "properties": {
    "addr:full":"1402 Lincolnway Laporte IN 46350",
    "addr:housenumber":"1402",
    "addr:postcode":"46350",
    "addr:street":"Lincolnway Laporte",
    "iso:country":"US",
    "sg:address":"1402 Lincolnway",
    "sg:city":"Laporte",
    "sg:classifiers":[
        {
            "category":"Shopping",
            "subcategory":"Jewelry",
            "type":"Retail Goods"
        }
    ],
    "sg:phone":"+1 219 326 7664",
    "sg:postcode":"46350",
    "sg:province":"IN",
    "sg:tags":[
        "jeweler"
    ],
    "wof:name":"Maple City Jewelers",
    "wof:placetype":"venue"
},
  "geometry": {"coordinates":[-86.727011,41.608149],"type":"Point"}
}