{
  "type": "Feature",
  "properties": {
    "iso:country":"US",
    "sg:address":"1 NW 5th St",
    "sg:city":"Richmond",
    "sg:classifiers":[
        {
            "category":"Personal",
            "subcategory":"Beauty Salon",
            "type":"Services"
        }
    ],
    "sg:phone":"+1 765 966 7376",
    "sg:postcode":"47374",
    "sg:province":"IN",
    "wof:name":"Hair Bazaar",
    "wof:placetype":"venue"
},
  "geometry": {"coordinates":[-84.908006,39.830086],"type":"Point"}
}