{
  "type": "Feature",
  "properties": {
    "iso:country":"US",
    "sg:address":"2334 E County Line Rd",
    "sg:city":"Indianapolis",
    "sg:classifiers":[
        {
            "category":"Banks & Credit Unions",
            "subcategory":"Bank",
            "type":"Services"
        }
    ],
    "sg:phone":"+1 317 881 8045",
    "sg:postcode":"46227",
    "sg:province":"IN",
    "sg:tags":[
        "loan",
        "saving"
    ],
    "sg:website":"http://citizens-banking.com",
    "wof:name":"Citizens Bank",
    "wof:placetype":"venue"
},
  "geometry": {"coordinates":[-86.121075,39.635553],"type":"Point"}
}