{
  "type": "Feature",
  "properties": {
    "iso:country":"US",
    "sg:address":"5018 Old Mill Rd",
    "sg:city":"Fort Wayne",
    "sg:classifiers":[
        {
            "category":"Wholesale",
            "subcategory":"Non-durable Goods",
            "type":"Manufacturing & Wholesale Goods"
        }
    ],
    "sg:phone":"+1 260 744 1493",
    "sg:postcode":"46807",
    "sg:province":"IN",
    "sg:tags":[
        "sales"
    ],
    "wof:name":"Ron Nelson",
    "wof:placetype":"venue"
},
  "geometry": {"coordinates":[-85.150374,41.035157],"type":"Point"}
}