{
  "type": "Feature",
  "properties": {
    "iso:country":"US",
    "sg:address":"550 Union St",
    "sg:city":"Mishawaka",
    "sg:classifiers":[
        {
            "category":"Real Estate",
            "subcategory":"Architect",
            "type":"Services"
        }
    ],
    "sg:phone":"+1 574 259 9976",
    "sg:postcode":"46544",
    "sg:province":"IN",
    "wof:name":"Troyer Group Inc",
    "wof:placetype":"venue"
},
  "geometry": {"coordinates":[-86.177007,41.657502],"type":"Point"}
}