{
  "type": "Feature",
  "properties": {
    "iso:country":"US",
    "sg:address":"807 E Canal St",
    "sg:city":"Winona Lake",
    "sg:classifiers":[
        {
            "category":"Shopping",
            "type":"Retail Goods"
        }
    ],
    "sg:phone":"+1 574 269 2997",
    "sg:postcode":"46590",
    "sg:province":"IN",
    "sg:tags":[
        "merchandise"
    ],
    "wof:name":"Blue Heron Artworks",
    "wof:placetype":"venue"
},
  "geometry": {"coordinates":[-85.82264,41.227051],"type":"Point"}
}