{
  "type": "Feature",
  "properties": {
    "iso:country":"US",
    "sg:address":"8555 Cedar Place Dr",
    "sg:city":"Indianapolis",
    "sg:classifiers":[
        {
            "category":"Professional",
            "subcategory":"Advertising",
            "type":"Services"
        }
    ],
    "sg:phone":"+1 317 251 6744",
    "sg:postcode":"46240",
    "sg:province":"IN",
    "sg:tags":[
        "counselor"
    ],
    "sg:website":"www.rarebirdinc.com",
    "wof:name":"Rare Bird Inc",
    "wof:placetype":"venue"
},
  "geometry": {"coordinates":[-86.144003,39.911682],"type":"Point"}
}