{
  "type": "Feature",
  "properties": {
    "iso:country":"US",
    "sg:address":"720 N Marr Rd",
    "sg:city":"Columbus",
    "sg:classifiers":[
        {
            "category":"Organizations",
            "subcategory":"Non-profit Organization",
            "type":"Services"
        }
    ],
    "sg:phone":"+1 812 314 3600",
    "sg:postcode":"47201",
    "sg:province":"IN",
    "sg:tags":[
        "info",
        "addiction",
        "abuse",
        "treatment",
        "drug"
    ],
    "wof:name":"Recovery Associates",
    "wof:placetype":"venue"
},
  "geometry": {"coordinates":[-85.885301,39.20629],"type":"Point"}
}