{
  "type": "Feature",
  "properties": {
    "addr:full":"1099 Marci Ln Georgetown IN 47122",
    "addr:housenumber":"1099",
    "addr:postcode":"47122",
    "addr:street":"Marci Ln",
    "iso:country":"US",
    "sg:address":"1099 Marci Ln",
    "sg:city":"Georgetown",
    "sg:classifiers":[
        {
            "category":"Social Services",
            "subcategory":"Child Care",
            "type":"Services"
        }
    ],
    "sg:phone":"+1 812 951 3215",
    "sg:postcode":"47122",
    "sg:province":"IN",
    "wof:name":"Rainbow's End Child Care",
    "wof:placetype":"venue"
},
  "geometry": {"coordinates":[-85.963531,38.29618],"type":"Point"}
}