{
  "type": "Feature",
  "properties": {
    "iso:country":"US",
    "sg:address":"1617 S Weinbach Ave",
    "sg:city":"Evansville",
    "sg:classifiers":[
        {
            "category":"Restaurant",
            "type":"Food & Drink"
        }
    ],
    "sg:phone":"+1 812 473 0677",
    "sg:postcode":"47714",
    "sg:province":"IN",
    "sg:tags":[
        "parlor",
        "ice",
        "cream"
    ],
    "wof:name":"Rivertown Ice Cream",
    "wof:placetype":"venue"
},
  "geometry": {"coordinates":[-87.529833,37.954814],"type":"Point"}
}