{
  "type": "Feature",
  "properties": {
    "iso:country":"US",
    "sg:address":"1313 N State St",
    "sg:city":"Greenfield",
    "sg:classifiers":[
        {
            "category":"Autos & Motor Vehicles",
            "subcategory":"Fuel & Gas Station",
            "type":"Retail Goods"
        }
    ],
    "sg:phone":"+1 317 462 8773",
    "sg:postcode":"46140",
    "sg:province":"IN",
    "sg:tags":[
        "oil"
    ],
    "wof:name":"Swifty Service Station",
    "wof:placetype":"venue"
},
  "geometry": {"coordinates":[-85.76956,39.804097],"type":"Point"}
}