{
  "type": "Feature",
  "properties": {
    "iso:country":"US",
    "sg:address":"10433 Starboard Way",
    "sg:city":"Indianapolis",
    "sg:classifiers":[
        {
            "category":"Home & Garden",
            "subcategory":"Household Appliances",
            "type":"Retail Goods"
        },
        {
            "category":"Wholesale",
            "subcategory":"Construction Materials",
            "type":"Manufacturing & Wholesale Goods"
        },
        {
            "category":"Home & Garden",
            "subcategory":"Building Materials",
            "type":"Retail Goods"
        },
        {
            "category":"Utilities",
            "type":"Services"
        }
    ],
    "sg:phone":"+1 317 578 3000",
    "sg:postcode":"46256",
    "sg:province":"IN",
    "sg:tags":[
        "systems-wholesale",
        "units-manufacturers",
        "dishwashing",
        "heating",
        "system",
        "machine",
        "equipment",
        "distributor"
    ],
    "wof:name":"B & B Air One",
    "wof:placetype":"venue"
},
  "geometry": {"coordinates":[-85.983334,39.914659],"type":"Point"}
}