{
  "type": "Feature",
  "properties": {
    "iso:country":"US",
    "sg:address":"1233 S Rockport Rd",
    "sg:city":"Boonville",
    "sg:classifiers":[
        {
            "category":"Building & Trades",
            "subcategory":"Construction",
            "type":"Services"
        }
    ],
    "sg:phone":"+1 812 897 4257",
    "sg:postcode":"47601",
    "sg:province":"IN",
    "sg:tags":[
        "excavating",
        "contractor"
    ],
    "wof:name":"Phil Baxter Landscaping",
    "wof:placetype":"venue"
},
  "geometry": {"coordinates":[-87.217892,38.00429],"type":"Point"}
}