{
  "type": "Feature",
  "properties": {
    "iso:country":"US",
    "sg:address":"2404 National Rd W",
    "sg:city":"Richmond",
    "sg:classifiers":[
        {
            "category":"Restaurant",
            "type":"Food & Drink"
        }
    ],
    "sg:phone":"+1 765 939 7683",
    "sg:postcode":"47374",
    "sg:province":"IN",
    "wof:name":"Elrodeo Mexican Restaurant",
    "wof:placetype":"venue"
},
  "geometry": {"coordinates":[-84.934031,39.823958],"type":"Point"}
}