{
  "type": "Feature",
  "properties": {
    "iso:country":"US",
    "sg:address":"703 N 500 E",
    "sg:city":"La Porte",
    "sg:classifiers":[
        {
            "category":"Organizations",
            "subcategory":"Religious Organization",
            "type":"Services"
        }
    ],
    "sg:phone":"+1 219 369 9224",
    "sg:postcode":"46350",
    "sg:province":"IN",
    "wof:name":"Liberty Ministries",
    "wof:placetype":"venue"
},
  "geometry": {"coordinates":[-86.601849,41.61754],"type":"Point"}
}