{
  "type": "Feature",
  "properties": {
    "iso:country":"US",
    "sg:address":"18687 Pribble Rd",
    "sg:city":"Lawrenceburg",
    "sg:classifiers":[
        {
            "category":"Organizations",
            "subcategory":"Religious Organization",
            "type":"Services"
        }
    ],
    "sg:phone":"+1 812 537 2272",
    "sg:postcode":"47025",
    "sg:province":"IN",
    "sg:tags":[
        "church"
    ],
    "wof:name":"Trinity Christian Ctr",
    "wof:placetype":"venue"
},
  "geometry": {"coordinates":[-84.888479,39.142138],"type":"Point"}
}