{
  "type": "Feature",
  "properties": {
    "addr:full":"316 S 15th St Vincennes IN 47591",
    "addr:housenumber":"316",
    "addr:postcode":"47591",
    "addr:street":"S 15Th St",
    "iso:country":"US",
    "sg:address":"316 S 15th St",
    "sg:city":"Vincennes",
    "sg:classifiers":[
        {
            "category":"Wholesale",
            "subcategory":"Toys & Hobbies",
            "type":"Manufacturing & Wholesale Goods"
        }
    ],
    "sg:phone":"+1 812 885 9009",
    "sg:postcode":"47591",
    "sg:province":"IN",
    "sg:tags":[
        "wholesaler"
    ],
    "wof:name":"B K Wholesale",
    "wof:placetype":"venue"
},
  "geometry": {"coordinates":[-87.523979,38.667104],"type":"Point"}
}