{
  "type": "Feature",
  "properties": {
    "iso:country":"US",
    "sg:address":"807 Goshen Ave",
    "sg:city":"Elkhart",
    "sg:classifiers":[
        {
            "category":"Personal",
            "subcategory":"Barber",
            "type":"Services"
        }
    ],
    "sg:phone":"+1 574 294 2263",
    "sg:postcode":"46516",
    "sg:province":"IN",
    "wof:name":"Kent's Barber Shop",
    "wof:placetype":"venue"
},
  "geometry": {"coordinates":[-85.947684,41.680677],"type":"Point"}
}