{
  "type": "Feature",
  "properties": {
    "iso:country":"US",
    "sg:address":"8414 Kennedy Ave",
    "sg:city":"Highland",
    "sg:classifiers":[
        {
            "category":"Personal",
            "subcategory":"Beauty Salon",
            "type":"Services"
        }
    ],
    "sg:phone":"+1 219 923 9568",
    "sg:postcode":"46322",
    "sg:province":"IN",
    "wof:name":"Michael & Co",
    "wof:placetype":"venue"
},
  "geometry": {"coordinates":[-87.461727,41.560637],"type":"Point"}
}