{
  "type": "Feature",
  "properties": {
    "iso:country":"US",
    "sg:address":"2409 W Lincoln Hwy",
    "sg:city":"Merrillville",
    "sg:classifiers":[
        {
            "category":"Building & Trades",
            "subcategory":"Construction",
            "type":"Services"
        }
    ],
    "sg:phone":"+1 219 769 1720",
    "sg:postcode":"46410",
    "sg:province":"IN",
    "sg:tags":[
        "designer",
        "dealer",
        "pool",
        "swimming"
    ],
    "sg:website":"www.poolarama.com",
    "wof:name":"Pool-A-Rama",
    "wof:placetype":"venue"
},
  "geometry": {"coordinates":[-87.36507,41.471043],"type":"Point"}
}