{
  "type": "Feature",
  "properties": {
    "iso:country":"US",
    "sg:address":"25 W High St",
    "sg:city":"Lawrenceburg",
    "sg:classifiers":[
        {
            "category":"Insurance",
            "subcategory":"Insurance Agent",
            "type":"Services"
        }
    ],
    "sg:phone":"+1 812 537 0264",
    "sg:postcode":"47025",
    "sg:province":"IN",
    "wof:name":"Seitz Insurance Inc",
    "wof:placetype":"venue"
},
  "geometry": {"coordinates":[-84.847889,39.09245],"type":"Point"}
}