{
  "type": "Feature",
  "properties": {
    "iso:country":"US",
    "sg:address":"3201 E Center St Exd",
    "sg:city":"Warsaw",
    "sg:classifiers":[
        {
            "category":"Organizations",
            "subcategory":"Religious Organization",
            "type":"Services"
        }
    ],
    "sg:phone":"+1 574 268 1919",
    "sg:postcode":"46582",
    "sg:province":"IN",
    "sg:tags":[
        "church"
    ],
    "wof:name":"Warsaw Dist Ofc United Meth Ch",
    "wof:placetype":"venue"
},
  "geometry": {"coordinates":[-85.814037,41.238596],"type":"Point"}
}