{
  "type": "Feature",
  "properties": {
    "iso:country":"US",
    "sg:address":"4703 Ohara Dr",
    "sg:city":"Evansville",
    "sg:classifiers":[
        {
            "category":"Manufacturing",
            "subcategory":"Metals",
            "type":"Manufacturing & Wholesale Goods"
        }
    ],
    "sg:phone":"+1 812 425 1561",
    "sg:postcode":"47711",
    "sg:province":"IN",
    "sg:tags":[
        "stamping"
    ],
    "sg:website":"www.mastermfg.com",
    "wof:name":"Master Manufacturing Co",
    "wof:placetype":"venue"
},
  "geometry": {"coordinates":[-87.521556,38.023146],"type":"Point"}
}