{
  "type": "Feature",
  "properties": {
    "iso:country":"US",
    "sg:address":"52225 Eagle Chase Dr",
    "sg:city":"Granger",
    "sg:classifiers":[
        {
            "category":"Building & Trades",
            "subcategory":"Plumbing",
            "type":"Services"
        }
    ],
    "sg:phone":"+1 574 234 4511",
    "sg:postcode":"46530",
    "sg:province":"IN",
    "sg:tags":[
        "contractor"
    ],
    "wof:name":"Sticklers Plumbing",
    "wof:placetype":"venue"
},
  "geometry": {"coordinates":[-86.141408,41.735513],"type":"Point"}
}