{
  "type": "Feature",
  "properties": {
    "addr:full":"112 S Orchard St Kendallville IN 46755",
    "addr:housenumber":"112",
    "addr:postcode":"46755",
    "addr:street":"S Orchard St",
    "iso:country":"US",
    "sg:address":"112 S Orchard St",
    "sg:city":"Kendallville",
    "sg:classifiers":[
        {
            "category":"Education",
            "subcategory":"School",
            "type":"Public Place"
        }
    ],
    "sg:phone":"+1 260 347 5236",
    "sg:postcode":"46755",
    "sg:province":"IN",
    "wof:name":"Northeast Indiana Special Ed",
    "wof:placetype":"venue"
},
  "geometry": {"coordinates":[-85.267225,41.443544],"type":"Point"}
}