{
  "type": "Feature",
  "properties": {
    "iso:country":"US",
    "sg:address":"7026 E 49 N",
    "sg:city":"Flora",
    "sg:classifiers":[
        {
            "category":"Farming",
            "subcategory":"Farm",
            "type":"Manufacturing & Wholesale Goods"
        }
    ],
    "sg:phone":"+1 574 859 2583",
    "sg:postcode":"46929",
    "sg:province":"IN",
    "sg:tags":[
        "crop",
        "general"
    ],
    "wof:name":"Bradley I Hayden",
    "wof:placetype":"venue"
},
  "geometry": {"coordinates":[-86.391711,40.553296],"type":"Point"}
}