{
  "type": "Feature",
  "properties": {
    "iso:country":"US",
    "sg:address":"3038 S Lafountain St",
    "sg:city":"Kokomo",
    "sg:classifiers":[
        {
            "category":"Professional",
            "type":"Services"
        }
    ],
    "sg:phone":"+1 765 864 1663",
    "sg:postcode":"46902",
    "sg:province":"IN",
    "sg:tags":[
        "establishment"
    ],
    "wof:name":"SBA Towers Inc",
    "wof:placetype":"venue"
},
  "geometry": {"coordinates":[-86.126993,40.453311],"type":"Point"}
}