{
  "type": "Feature",
  "properties": {
    "iso:country":"US",
    "sg:address":"1918 E Wayne St",
    "sg:city":"Fort Wayne",
    "sg:classifiers":[
        {
            "category":"Manufacturing",
            "subcategory":"Metals",
            "type":"Manufacturing & Wholesale Goods"
        }
    ],
    "sg:phone":"+1 260 422 6518",
    "sg:postcode":"46803",
    "sg:province":"IN",
    "sg:tags":[
        "machine",
        "screw",
        "product"
    ],
    "sg:website":"www.precisemfginc.com",
    "wof:name":"Precise Manufacturing Inc",
    "wof:placetype":"venue"
},
  "geometry": {"coordinates":[-85.109989,41.080261],"type":"Point"}
}