{
  "type": "Feature",
  "properties": {
    "iso:country":"US",
    "sg:address":"701 School St",
    "sg:city":"Culver",
    "sg:classifiers":[
        {
            "category":"Education",
            "subcategory":"School",
            "type":"Public Place"
        }
    ],
    "sg:phone":"+1 574 842 3391",
    "sg:postcode":"46511",
    "sg:province":"IN",
    "sg:website":"www.culver.k12.in.us",
    "wof:name":"Culver Community Highschool",
    "wof:placetype":"venue"
},
  "geometry": {"coordinates":[-86.424174,41.22311],"type":"Point"}
}