{
  "type": "Feature",
  "properties": {
    "iso:country":"US",
    "sg:address":"58560 Quince Rd",
    "sg:city":"South Bend",
    "sg:classifiers":[
        {
            "category":"Building & Trades",
            "subcategory":"Construction",
            "type":"Services"
        }
    ],
    "sg:phone":"+1 574 272 6655",
    "sg:postcode":"46619",
    "sg:province":"IN",
    "sg:tags":[
        "water",
        "well",
        "drilling"
    ],
    "wof:name":"Repairing & Drilling",
    "wof:placetype":"venue"
},
  "geometry": {"coordinates":[-86.380393,41.635382],"type":"Point"}
}