{
  "type": "Feature",
  "properties": {
    "addr:full":"11627 Fox Rd Indianapolis IN 46236",
    "addr:housenumber":"11627",
    "addr:postcode":"46236",
    "addr:street":"Fox Rd",
    "iso:country":"US",
    "sg:address":"11627 Fox Rd",
    "sg:city":"Indianapolis",
    "sg:classifiers":[
        {
            "category":"Shopping",
            "subcategory":"Pharmacy",
            "type":"Retail Goods"
        }
    ],
    "sg:phone":"+1 317 823 0824",
    "sg:postcode":"46236",
    "sg:province":"IN",
    "wof:name":"Osco Drug",
    "wof:placetype":"venue"
},
  "geometry": {"coordinates":[-85.960684,39.90205],"type":"Point"}
}