{
  "type": "Feature",
  "properties": {
    "iso:country":"US",
    "sg:address":"3300 Liverpool Rd",
    "sg:city":"Lake Station",
    "sg:classifiers":[
        {
            "category":"Freight",
            "type":"Transportation"
        }
    ],
    "sg:phone":"+1 219 962 9729",
    "sg:postcode":"46405",
    "sg:province":"IN",
    "sg:tags":[
        "trucking"
    ],
    "wof:name":"Gary East Trucking",
    "wof:placetype":"venue"
},
  "geometry": {"coordinates":[-87.292058,41.561577],"type":"Point"}
}