{
  "type": "Feature",
  "properties": {
    "addr:full":"319 E 4th St Huntingburg IN 47542",
    "addr:housenumber":"319",
    "addr:postcode":"47542",
    "addr:street":"E 4Th St",
    "iso:country":"US",
    "sg:address":"319 E 4th St",
    "sg:city":"Huntingburg",
    "sg:classifiers":[
        {
            "category":"Manufacturing",
            "subcategory":"Printing",
            "type":"Manufacturing & Wholesale Goods"
        }
    ],
    "sg:phone":"+1 812 683 4416",
    "sg:postcode":"47542",
    "sg:province":"IN",
    "sg:tags":[
        "commercial"
    ],
    "wof:name":"Cecil's Printing & Office Supl",
    "wof:placetype":"venue"
},
  "geometry": {"coordinates":[-86.95691600000001,38.295993],"type":"Point"}
}