{
  "type": "Feature",
  "properties": {
    "addr:full":"18255 S Bend Ave South Bend IN 46637",
    "addr:housenumber":"18255",
    "addr:postcode":"46637",
    "addr:street":"S Bend Ave",
    "iso:country":"US",
    "sg:address":"18255 S Bend Ave",
    "sg:city":"South Bend",
    "sg:classifiers":[
        {
            "category":"Autos & Motor Vehicles",
            "subcategory":"Auto Supplies",
            "type":"Retail Goods"
        }
    ],
    "sg:phone":"+1 574 272 4884",
    "sg:postcode":"46637",
    "sg:province":"IN",
    "sg:tags":[
        "tire"
    ],
    "wof:name":"Zolman Tire Inc",
    "wof:placetype":"venue"
},
  "geometry": {"coordinates":[-86.218339,41.699185],"type":"Point"}
}