{
  "type": "Feature",
  "properties": {
    "addr:full":"325 S Oak St Winchester IN 47394",
    "addr:housenumber":"325",
    "addr:postcode":"47394",
    "addr:street":"S Oak St",
    "iso:country":"US",
    "sg:address":"325 S Oak St",
    "sg:city":"Winchester",
    "sg:classifiers":[
        {
            "category":"Health Services",
            "subcategory":"Hospital",
            "type":"Services"
        }
    ],
    "sg:phone":"+1 765 584 9001",
    "sg:postcode":"47394",
    "sg:province":"IN",
    "wof:name":"Randolph County Hospital",
    "wof:placetype":"venue"
},
  "geometry": {"coordinates":[-84.973356,40.170105],"type":"Point"}
}