{
  "type": "Feature",
  "properties": {
    "addr:full":"2370 E 116th St Carmel IN 46032",
    "addr:housenumber":"2370",
    "addr:postcode":"46032",
    "addr:street":"E 116Th St",
    "iso:country":"US",
    "sg:address":"2370 E 116th St",
    "sg:city":"Carmel",
    "sg:classifiers":[
        {
            "category":"Restaurant",
            "type":"Food & Drink"
        }
    ],
    "sg:phone":"+1 317 846 4412",
    "sg:postcode":"46032",
    "sg:province":"IN",
    "sg:website":"www.wendys.com",
    "wof:name":"Wendy's",
    "wof:placetype":"venue"
},
  "geometry": {"coordinates":[-86.115898,39.956501],"type":"Point"}
}