{
  "type": "Feature",
  "properties": {
    "addr:full":"2755 Teal Rd Lafayette IN 47909",
    "addr:housenumber":"2755",
    "addr:postcode":"47909",
    "addr:street":"Teal Rd",
    "iso:country":"US",
    "sg:address":"2755 Teal Rd",
    "sg:city":"Lafayette",
    "sg:classifiers":[
        {
            "category":"Social Services",
            "subcategory":"Child Care",
            "type":"Services"
        }
    ],
    "sg:phone":"+1 765 474 3663",
    "sg:postcode":"47909",
    "sg:province":"IN",
    "wof:name":"Kinder Care Learning Ctr",
    "wof:placetype":"venue"
},
  "geometry": {"coordinates":[-86.86206,40.395521],"type":"Point"}
}