{
  "type": "Feature",
  "properties": {
    "addr:full":"350 S Oakland Ave Nappanee IN 46550",
    "addr:housenumber":"350",
    "addr:postcode":"46550",
    "addr:street":"S Oakland Ave",
    "iso:country":"US",
    "sg:address":"350 S Oakland Ave",
    "sg:city":"Nappanee",
    "sg:classifiers":[
        {
            "category":"Retail",
            "subcategory":"Auto Repair",
            "type":"Services"
        }
    ],
    "sg:phone":"+1 574 773 2435",
    "sg:postcode":"46550",
    "sg:province":"IN",
    "sg:tags":[
        "repairing",
        "automobile"
    ],
    "wof:name":"Nappanee Auto Repair",
    "wof:placetype":"venue"
},
  "geometry": {"coordinates":[-85.982259,41.440144],"type":"Point"}
}