{
  "type": "Feature",
  "properties": {
    "iso:country":"US",
    "sg:address":"100 Shawnee Dr",
    "sg:city":"Bedford",
    "sg:classifiers":[
        {
            "category":"Real Estate",
            "subcategory":"Real Estate Agent",
            "type":"Services"
        }
    ],
    "sg:phone":"+1 812 275 8314",
    "sg:postcode":"47421",
    "sg:province":"IN",
    "sg:tags":[
        "finding",
        "apartment",
        "rental"
    ],
    "wof:name":"Shawnee Apartments",
    "wof:placetype":"venue"
},
  "geometry": {"coordinates":[-86.508707,38.847528],"type":"Point"}
}