{
  "type": "Feature",
  "properties": {
    "iso:country":"US",
    "sg:address":"153 W 300 S",
    "sg:city":"Crawfordsville",
    "sg:classifiers":[
        {
            "category":"Organizations",
            "subcategory":"Religious Organization",
            "type":"Services"
        }
    ],
    "sg:phone":"+1 765 361 9812",
    "sg:postcode":"47933",
    "sg:province":"IN",
    "sg:tags":[
        "church"
    ],
    "wof:name":"Southside Church Of Christ",
    "wof:placetype":"venue"
},
  "geometry": {"coordinates":[-86.906733,39.99591],"type":"Point"}
}