{
  "type": "Feature",
  "properties": {
    "iso:country":"US",
    "sg:address":"513 Randle St",
    "sg:city":"Valparaiso",
    "sg:classifiers":[
        {
            "category":"Shopping",
            "subcategory":"Used Merchandise",
            "type":"Retail Goods"
        }
    ],
    "sg:phone":"+1 219 476 7308",
    "sg:postcode":"46383",
    "sg:province":"IN",
    "sg:tags":[
        "shop",
        "consignment"
    ],
    "wof:name":"Kids Place",
    "wof:placetype":"venue"
},
  "geometry": {"coordinates":[-87.05515800000001,41.482319],"type":"Point"}
}