{
  "type": "Feature",
  "properties": {
    "addr:full":"200 Dekko Dr Avilla IN 46710",
    "addr:housenumber":"200",
    "addr:postcode":"avilla;46710",
    "addr:street":"Dekko Dr",
    "iso:country":"US",
    "sg:address":"200 Dekko Dr",
    "sg:city":"Avilla",
    "sg:classifiers":[
        {
            "category":"Wholesale",
            "subcategory":"Durable Goods & Equipment",
            "type":"Manufacturing & Wholesale Goods"
        }
    ],
    "sg:phone":"+1 260 897 3459",
    "sg:postcode":"46710",
    "sg:province":"IN",
    "sg:tags":[
        "representative",
        "manufacturer"
    ],
    "sg:website":"www.dekko.com",
    "wof:name":"Pent Assemblies Avilla",
    "wof:placetype":"venue"
},
  "geometry": {"coordinates":[-85.222336,41.368024],"type":"Point"}
}