{
  "type": "Feature",
  "properties": {
    "iso:country":"US",
    "sg:address":"2300 Middlebury St",
    "sg:city":"Elkhart",
    "sg:classifiers":[
        {
            "category":"Professional",
            "subcategory":"Advertising",
            "type":"Services"
        }
    ],
    "sg:phone":"+1 574 295 7820",
    "sg:postcode":"46516",
    "sg:province":"IN",
    "sg:website":"www.tl.com",
    "wof:name":"T L Enterprises Inc",
    "wof:placetype":"venue"
},
  "geometry": {"coordinates":[-85.92262,41.681438],"type":"Point"}
}