{
  "type": "Feature",
  "properties": {
    "addr:full":"980 Joliet St Dyer IN 46311",
    "addr:housenumber":"980",
    "addr:postcode":"46311",
    "addr:street":"Joliet St",
    "iso:country":"US",
    "sg:address":"980 Joliet St",
    "sg:city":"Dyer",
    "sg:classifiers":[
        {
            "category":"Restaurant",
            "type":"Food & Drink"
        }
    ],
    "sg:menulink":"http://www.allmenus.com/in/st-john/124717-quiznos-sub/menu/",
    "sg:phone":"+1 219 322 1465",
    "sg:postcode":"46311",
    "sg:province":"IN",
    "sg:tags":[
        "wrap",
        "american",
        "sandwich"
    ],
    "wof:name":"Quiznos Sub",
    "wof:placetype":"venue"
},
  "geometry": {"coordinates":[-87.50349199999999,41.492258],"type":"Point"}
}