{
  "type": "Feature",
  "properties": {
    "iso:country":"US",
    "sg:address":"400 W 7th St",
    "sg:city":"North Manchester",
    "sg:classifiers":[
        {
            "category":"Organizations",
            "subcategory":"Non-profit Organization",
            "type":"Services"
        }
    ],
    "sg:phone":"+1 260 982 8616",
    "sg:postcode":"46962",
    "sg:province":"IN",
    "sg:website":"www.peabodyrc.com",
    "wof:name":"Peabody Retirement Community",
    "wof:placetype":"venue"
},
  "geometry": {"coordinates":[-85.773653,41.005606],"type":"Point"}
}