{
  "type": "Feature",
  "properties": {
    "iso:country":"US",
    "sg:address":"1853 E Ludlow Ave",
    "sg:city":"Indianapolis",
    "sg:classifiers":[
        {
            "category":"Manufacturing",
            "subcategory":"Rubber & Plastics",
            "type":"Manufacturing & Wholesale Goods"
        }
    ],
    "sg:phone":"+1 317 639 0224",
    "sg:postcode":"46201",
    "sg:province":"IN",
    "sg:tags":[
        "product"
    ],
    "wof:name":"Atco Rubber Products",
    "wof:placetype":"venue"
},
  "geometry": {"coordinates":[-86.124925,39.790976],"type":"Point"}
}