{
  "type": "Feature",
  "properties": {
    "iso:country":"US",
    "sg:address":"16849 Co Rd 38",
    "sg:city":"Goshen",
    "sg:classifiers":[
        {
            "category":"Manufacturing",
            "subcategory":"Metals",
            "type":"Manufacturing & Wholesale Goods"
        }
    ],
    "sg:phone":"+1 574 533 2180",
    "sg:postcode":"46526",
    "sg:province":"IN",
    "sg:tags":[
        "stamping"
    ],
    "wof:name":"Continental Stamping",
    "wof:placetype":"venue"
},
  "geometry": {"coordinates":[-85.787122,41.551916],"type":"Point"}
}