{
  "type": "Feature",
  "properties": {
    "iso:country":"US",
    "sg:address":"2940 Taylor Rd",
    "sg:city":"Columbus",
    "sg:classifiers":[
        {
            "category":"Professional",
            "subcategory":"Business Services",
            "type":"Services"
        }
    ],
    "sg:phone":"+1 812 372 9239",
    "sg:postcode":"47203",
    "sg:province":"IN",
    "wof:name":"Carr Laminating Service",
    "wof:placetype":"venue"
},
  "geometry": {"coordinates":[-85.876078,39.227889],"type":"Point"}
}