{
  "type": "Feature",
  "properties": {
    "iso:country":"US",
    "sg:address":"24 E 14th St",
    "sg:city":"Indianapolis",
    "sg:classifiers":[
        {
            "category":"Retail",
            "subcategory":"Repair Shop",
            "type":"Services"
        }
    ],
    "sg:phone":"+1 317 634 2845",
    "sg:postcode":"46202",
    "sg:province":"IN",
    "sg:tags":[
        "bicycle"
    ],
    "wof:name":"Bicycle Mechanica",
    "wof:placetype":"venue"
},
  "geometry": {"coordinates":[-86.156791,39.785807],"type":"Point"}
}