{
  "type": "Feature",
  "properties": {
    "iso:country":"US",
    "sg:address":"7787 US Hwy 31 S",
    "sg:city":"Indianapolis",
    "sg:classifiers":[
        {
            "category":"Banks & Credit Unions",
            "subcategory":"Bank",
            "type":"Services"
        }
    ],
    "sg:phone":"+1 317 888 8887",
    "sg:postcode":"46227",
    "sg:province":"IN",
    "sg:tags":[
        "financing"
    ],
    "wof:name":"Wells Fargo Financial Accptnce",
    "wof:placetype":"venue"
},
  "geometry": {"coordinates":[-86.141589,39.657445],"type":"Point"}
}