{
  "type": "Feature",
  "properties": {
    "iso:country":"US",
    "sg:address":"6436 Central Ave",
    "sg:city":"Portage",
    "sg:classifiers":[
        {
            "category":"Retail",
            "subcategory":"Auto Repair",
            "type":"Services"
        }
    ],
    "sg:phone":"+1 219 763 1782",
    "sg:postcode":"46368",
    "sg:province":"IN",
    "sg:tags":[
        "repairing",
        "automobile"
    ],
    "wof:name":"Reeders Auto Svc Ctr",
    "wof:placetype":"venue"
},
  "geometry": {"coordinates":[-87.166215,41.575991],"type":"Point"}
}