{
  "type": "Feature",
  "properties": {
    "addr:full":"1401 E 5th St Connersville IN 47331",
    "addr:housenumber":"1401",
    "addr:postcode":"47331",
    "addr:street":"E 5Th St",
    "iso:country":"US",
    "sg:address":"1401 E 5th St",
    "sg:city":"Connersville",
    "sg:classifiers":[
        {
            "category":"Personal",
            "subcategory":"Beauty Salon",
            "type":"Services"
        }
    ],
    "sg:phone":"+1 765 825 6192",
    "sg:postcode":"47331",
    "sg:province":"IN",
    "wof:name":"Reflections",
    "wof:placetype":"venue"
},
  "geometry": {"coordinates":[-85.117496,39.639139],"type":"Point"}
}