{
  "type": "Feature",
  "properties": {
    "iso:country":"US",
    "sg:address":"350 S Mitthoeffer Rd",
    "sg:city":"Indianapolis",
    "sg:classifiers":[
        {
            "category":"Manufacturing",
            "subcategory":"Metals",
            "type":"Manufacturing & Wholesale Goods"
        }
    ],
    "sg:phone":"+1 317 897 1410",
    "sg:postcode":"46229",
    "sg:province":"IN",
    "sg:tags":[
        "door"
    ],
    "wof:name":"Custom Stainless Fabricators",
    "wof:placetype":"venue"
},
  "geometry": {"coordinates":[-85.990269,39.765681],"type":"Point"}
}