{
  "type": "Feature",
  "properties": {
    "iso:country":"US",
    "sg:address":"183 Superior Blvd",
    "sg:city":"Warsaw",
    "sg:classifiers":[
        {
            "category":"Professional",
            "subcategory":"Advertising",
            "type":"Services"
        }
    ],
    "sg:phone":"+1 574 267 6002",
    "sg:postcode":"46516",
    "sg:province":"IN",
    "wof:name":"Savage International",
    "wof:placetype":"venue"
},
  "geometry": {"coordinates":[-85.930201,41.692122],"type":"Point"}
}