{
  "type": "Feature",
  "properties": {
    "addr:full":"5585 Georgetown Rd Indianapolis IN 46254",
    "addr:housenumber":"5585",
    "addr:postcode":"46254",
    "addr:street":"Georgetown Rd",
    "iso:country":"US",
    "sg:address":"5585 Georgetown Rd",
    "sg:city":"Indianapolis",
    "sg:classifiers":[
        {
            "category":"Autos & Motor Vehicles",
            "subcategory":"Fuel & Gas Station",
            "type":"Retail Goods"
        }
    ],
    "sg:phone":"+1 317 293 9132",
    "sg:postcode":"46254",
    "sg:province":"IN",
    "sg:tags":[
        "oil"
    ],
    "sg:website":"www.bp.com",
    "wof:name":"BP",
    "wof:placetype":"venue"
},
  "geometry": {"coordinates":[-86.240208,39.85183],"type":"Point"}
}