{
  "type": "Feature",
  "properties": {
    "iso:country":"US",
    "sg:address":"1939 N Carver St",
    "sg:city":"Greensburg",
    "sg:classifiers":[
        {
            "category":"Government",
            "subcategory":"Office",
            "type":"Public Place"
        }
    ],
    "sg:phone":"+1 812 663 8830",
    "sg:postcode":"47240",
    "sg:province":"IN",
    "wof:name":"US Human Svc",
    "wof:placetype":"venue"
},
  "geometry": {"coordinates":[-85.49164399999999,39.355294],"type":"Point"}
}