{
  "type": "Feature",
  "properties": {
    "iso:country":"US",
    "sg:address":"6045 US Hwy 35",
    "sg:city":"Williamsburg",
    "sg:classifiers":[
        {
            "category":"Farming",
            "subcategory":"Livestock Farm",
            "type":"Manufacturing & Wholesale Goods"
        }
    ],
    "sg:phone":"+1 765 935 0179",
    "sg:postcode":"47393",
    "sg:province":"IN",
    "sg:tags":[
        "equine"
    ],
    "wof:name":"River View Farms",
    "wof:placetype":"venue"
},
  "geometry": {"coordinates":[-84.952713,39.911191],"type":"Point"}
}