{
  "type": "Feature",
  "properties": {
    "addr:full":"1221 E 37th Ave Gary IN 46409",
    "addr:housenumber":"1221",
    "addr:postcode":"46409",
    "addr:street":"E 37Th Ave",
    "iso:country":"US",
    "sg:address":"1221 E 37th Ave",
    "sg:city":"Gary",
    "sg:classifiers":[
        {
            "category":"Organizations",
            "subcategory":"Labor Organization",
            "type":"Services"
        }
    ],
    "sg:phone":"+1 219 887 0591",
    "sg:postcode":"46409",
    "sg:province":"IN",
    "sg:website":"http://www.uswa.org",
    "wof:name":"United Steelworkers of America",
    "wof:placetype":"venue"
},
  "geometry": {"coordinates":[-87.321736,41.551144],"type":"Point"}
}