{
  "type": "Feature",
  "properties": {
    "iso:country":"US",
    "sg:address":"8005 Englewood Rd",
    "sg:city":"Indianapolis",
    "sg:classifiers":[
        {
            "category":"Manufacturing",
            "subcategory":"Food",
            "type":"Manufacturing & Wholesale Goods"
        }
    ],
    "sg:phone":"+1 317 466 7994",
    "sg:postcode":"46240",
    "sg:province":"IN",
    "sg:tags":[
        "malt",
        "beverage",
        "mfg"
    ],
    "wof:name":"Trouble Brewing Co Inc",
    "wof:placetype":"venue"
},
  "geometry": {"coordinates":[-86.132402,39.90285],"type":"Point"}
}