{
  "type": "Feature",
  "properties": {
    "iso:country":"US",
    "sg:address":"5142 E 65th St",
    "sg:city":"Indianapolis",
    "sg:classifiers":[
        {
            "category":"Wholesale",
            "subcategory":"Machinery & Supplies",
            "type":"Manufacturing & Wholesale Goods"
        }
    ],
    "sg:phone":"+1 317 842 7888",
    "sg:postcode":"46220",
    "sg:province":"IN",
    "sg:tags":[
        "valve"
    ],
    "sg:website":"www.airsystemsengineering.com",
    "wof:name":"Air Systems Engineering Inc",
    "wof:placetype":"venue"
},
  "geometry": {"coordinates":[-86.080175,39.876068],"type":"Point"}
}