{
  "type": "Feature",
  "properties": {
    "iso:country":"US",
    "sg:address":"285 Seminary St",
    "sg:city":"Roanoke",
    "sg:classifiers":[
        {
            "category":"Organizations",
            "subcategory":"Religious Organization",
            "type":"Services"
        }
    ],
    "sg:phone":"+1 260 672 3167",
    "sg:postcode":"46783",
    "sg:province":"IN",
    "sg:tags":[
        "church"
    ],
    "wof:name":"Roanoke United Methodist Chr",
    "wof:placetype":"venue"
},
  "geometry": {"coordinates":[-85.375309,40.963142],"type":"Point"}
}