{
  "type": "Feature",
  "properties": {
    "addr:full":"6620 Parkdale Pl Indianapolis IN 46254",
    "addr:housenumber":"6620",
    "addr:postcode":"46254",
    "addr:street":"Parkdale Pl",
    "iso:country":"US",
    "sg:address":"6620 Parkdale Pl",
    "sg:city":"Indianapolis",
    "sg:classifiers":[
        {
            "category":"Professional",
            "subcategory":"Computer Services",
            "type":"Services"
        }
    ],
    "sg:phone":"+1 317 299 0213",
    "sg:postcode":"46254",
    "sg:province":"IN",
    "sg:tags":[
        "repair"
    ],
    "wof:name":"Decisionone",
    "wof:placetype":"venue"
},
  "geometry": {"coordinates":[-86.27853899999999,39.825672],"type":"Point"}
}