{
  "type": "Feature",
  "properties": {
    "iso:country":"US",
    "sg:address":"9984 Olcott Ave",
    "sg:city":"Saint John",
    "sg:classifiers":[
        {
            "category":"Professional",
            "subcategory":"Business Services",
            "type":"Services"
        }
    ],
    "sg:phone":"+1 219 365 1013",
    "sg:postcode":"46373",
    "sg:province":"IN",
    "sg:tags":[
        "carrier",
        "insurance"
    ],
    "wof:name":"Chicago Mutual",
    "wof:placetype":"venue"
},
  "geometry": {"coordinates":[-87.479908,41.437318],"type":"Point"}
}