{
  "type": "Feature",
  "properties": {
    "iso:country":"US",
    "sg:address":"1702 Oxford St",
    "sg:city":"Fort Wayne",
    "sg:classifiers":[
        {
            "category":"Building & Trades",
            "subcategory":"Landscaping Services",
            "type":"Services"
        }
    ],
    "sg:phone":"+1 260 740 9033",
    "sg:postcode":"46806",
    "sg:province":"IN",
    "wof:name":"Green Gold Lawn Service",
    "wof:placetype":"venue"
},
  "geometry": {"coordinates":[-85.113676,41.053525],"type":"Point"}
}