{
  "type": "Feature",
  "properties": {
    "iso:country":"US",
    "sg:address":"4701 N Old State Rd 3",
    "sg:city":"Muncie",
    "sg:classifiers":[
        {
            "category":"Building & Trades",
            "subcategory":"Construction",
            "type":"Services"
        }
    ],
    "sg:phone":"+1 765 289 5184",
    "sg:postcode":"47303",
    "sg:province":"IN",
    "sg:tags":[
        "paving",
        "contractor"
    ],
    "wof:name":"Asphalt Maintenance Inc",
    "wof:placetype":"venue"
},
  "geometry": {"coordinates":[-85.368042,40.228329],"type":"Point"}
}