{
  "type": "Feature",
  "properties": {
    "iso:country":"US",
    "sg:address":"1358 E Sawmill Rd",
    "sg:city":"Kingman",
    "sg:classifiers":[
        {
            "category":"Retail",
            "subcategory":"Auto Repair",
            "type":"Services"
        }
    ],
    "sg:phone":"+1 765 397 3840",
    "sg:postcode":"47952",
    "sg:province":"IN",
    "sg:tags":[
        "repairing",
        "automobile"
    ],
    "wof:name":"J C Yater Garage",
    "wof:placetype":"venue"
},
  "geometry": {"coordinates":[-87.20102300000001,39.956721],"type":"Point"}
}