{
  "type": "Feature",
  "properties": {
    "iso:country":"US",
    "sg:address":"320 W 13th St",
    "sg:city":"Jeffersonville",
    "sg:classifiers":[
        {
            "category":"Health Services",
            "subcategory":"Doctor",
            "type":"Services"
        }
    ],
    "sg:phone":"+1 812 280 9800",
    "sg:postcode":"47130",
    "sg:province":"IN",
    "sg:tags":[
        "physician",
        "surgeon"
    ],
    "wof:name":"Tri County Gastroenterology",
    "wof:placetype":"venue"
},
  "geometry": {"coordinates":[-85.750097,38.283169],"type":"Point"}
}