{
  "type": "Feature",
  "properties": {
    "iso:country":"US",
    "sg:address":"221 N John F Kennedy Ave",
    "sg:city":"Loogootee",
    "sg:classifiers":[
        {
            "category":"Professional",
            "subcategory":"Accounting & Tax Preparation",
            "type":"Services"
        }
    ],
    "sg:phone":"+1 812 295 4849",
    "sg:postcode":"47553",
    "sg:province":"IN",
    "sg:tags":[
        "accountant"
    ],
    "wof:name":"Robert D Toy CPA",
    "wof:placetype":"venue"
},
  "geometry": {"coordinates":[-86.914496,38.677139],"type":"Point"}
}