{
  "type": "Feature",
  "properties": {
    "addr:full":"1400 E Monroe Dam Rd Bloomington IN 47401",
    "addr:housenumber":"1400",
    "addr:postcode":"47401",
    "addr:street":"E Monroe Dam Rd",
    "iso:country":"US",
    "sg:address":"1400 E Monroe Dam Rd",
    "sg:city":"Bloomington",
    "sg:classifiers":[
        {
            "category":"Autos & Motor Vehicles",
            "subcategory":"Boat Sales",
            "type":"Retail Goods"
        }
    ],
    "sg:phone":"+1 812 824 8221",
    "sg:postcode":"47401",
    "sg:province":"IN",
    "sg:tags":[
        "dealer",
        "sales"
    ],
    "wof:name":"Boathaven",
    "wof:placetype":"venue"
},
  "geometry": {"coordinates":[-86.513677,39.006862],"type":"Point"}
}