{
  "type": "Feature",
  "properties": {
    "iso:country":"US",
    "sg:address":"306 6th St",
    "sg:city":"Oolitic",
    "sg:classifiers":[
        {
            "category":"Professional",
            "subcategory":"Secretarial Services",
            "type":"Services"
        }
    ],
    "sg:phone":"+1 812 275 0522",
    "sg:postcode":"47451",
    "sg:province":"IN",
    "sg:tags":[
        "reporting"
    ],
    "wof:name":"Joy Easton",
    "wof:placetype":"venue"
},
  "geometry": {"coordinates":[-86.526301,38.895902],"type":"Point"}
}