{
  "type": "Feature",
  "properties": {
    "iso:country":"US",
    "sg:address":"850 Lincoln Way W",
    "sg:city":"Osceola",
    "sg:classifiers":[
        {
            "category":"Government",
            "subcategory":"Police Station",
            "type":"Public Place"
        }
    ],
    "sg:phone":"+1 574 674 8685",
    "sg:postcode":"46561",
    "sg:province":"IN",
    "sg:tags":[
        "department"
    ],
    "wof:name":"Osceola Police Dept",
    "wof:placetype":"venue"
},
  "geometry": {"coordinates":[-86.079841,41.66334],"type":"Point"}
}