{
  "type": "Feature",
  "properties": {
    "iso:country":"US",
    "sg:address":"5709 Park Plaza Ct",
    "sg:city":"Indianapolis",
    "sg:classifiers":[
        {
            "category":"Building & Trades",
            "subcategory":"Cleaning & Sanitation",
            "type":"Services"
        }
    ],
    "sg:phone":"+1 317 845 0556",
    "sg:postcode":"46220",
    "sg:province":"IN",
    "sg:tags":[
        "house"
    ],
    "wof:name":"Merry Maids Inc",
    "wof:placetype":"venue"
},
  "geometry": {"coordinates":[-86.073071,39.879364],"type":"Point"}
}