{
  "type": "Feature",
  "properties": {
    "iso:country":"US",
    "sg:address":"9410 N County Line Rd",
    "sg:city":"Gosport",
    "sg:classifiers":[
        {
            "category":"Building & Trades",
            "subcategory":"Construction",
            "type":"Services"
        }
    ],
    "sg:phone":"+1 812 876 7538",
    "sg:postcode":"47433",
    "sg:province":"IN",
    "sg:tags":[
        "excavating",
        "contractor"
    ],
    "wof:name":"Mike Anderson Excavating",
    "wof:placetype":"venue"
},
  "geometry": {"coordinates":[-86.68553799999999,39.317029],"type":"Point"}
}