{
  "type": "Feature",
  "properties": {
    "addr:full":"53179 County Kerry Dr Granger IN 46530",
    "addr:housenumber":"53179",
    "addr:postcode":"46530",
    "addr:street":"County Kerry Dr",
    "iso:country":"US",
    "sg:address":"53179 County Kerry Dr",
    "sg:city":"Granger",
    "sg:classifiers":[
        {
            "category":"Banks & Credit Unions",
            "subcategory":"Bank",
            "type":"Services"
        }
    ],
    "sg:phone":"+1 574 247 0519",
    "sg:postcode":"46530",
    "sg:province":"IN",
    "wof:name":"US Bank",
    "wof:placetype":"venue"
},
  "geometry": {"coordinates":[-86.149624,41.721158],"type":"Point"}
}