{
  "type": "Feature",
  "properties": {
    "iso:country":"US",
    "sg:address":"6640 E 500 S",
    "sg:city":"Wolcottville",
    "sg:classifiers":[
        {
            "category":"Home & Garden",
            "subcategory":"Garden Supply",
            "type":"Retail Goods"
        }
    ],
    "sg:phone":"+1 260 351 3775",
    "sg:postcode":"46795",
    "sg:province":"IN",
    "sg:tags":[
        "nurseryman"
    ],
    "wof:name":"Juniper Hill Nursery",
    "wof:placetype":"venue"
},
  "geometry": {"coordinates":[-85.298145,41.570319],"type":"Point"}
}