{
  "type": "Feature",
  "properties": {
    "iso:country":"US",
    "sg:address":"10 Wildwood Ct",
    "sg:city":"Brownsburg",
    "sg:classifiers":[
        {
            "category":"Building & Trades",
            "subcategory":"Construction",
            "type":"Services"
        }
    ],
    "sg:phone":"+1 317 852 0788",
    "sg:postcode":"46112",
    "sg:province":"IN",
    "sg:tags":[
        "painter"
    ],
    "wof:name":"Byasee Paint & Trim Inc",
    "wof:placetype":"venue"
},
  "geometry": {"coordinates":[-86.38590600000001,39.826694],"type":"Point"}
}