{
  "type": "Feature",
  "properties": {
    "iso:country":"US",
    "sg:address":"1 S Washington St",
    "sg:city":"Danville",
    "sg:classifiers":[
        {
            "category":"Professional",
            "subcategory":"Lawyer & Legal Services",
            "type":"Services"
        }
    ],
    "sg:phone":"+1 317 745 4408",
    "sg:postcode":"46122",
    "sg:province":"IN",
    "sg:tags":[
        "attorney"
    ],
    "wof:name":"Kendall Wood Lowry & Kessinger",
    "wof:placetype":"venue"
},
  "geometry": {"coordinates":[-86.523904,39.760757],"type":"Point"}
}