{
  "type": "Feature",
  "properties": {
    "iso:country":"US",
    "sg:address":"7630 S 700 W",
    "sg:city":"Topeka",
    "sg:classifiers":[
        {
            "category":"Retail",
            "subcategory":"Repair Shop",
            "type":"Services"
        }
    ],
    "sg:phone":"+1 260 593 2804",
    "sg:postcode":"46571",
    "sg:province":"IN",
    "sg:tags":[
        "refrigeration"
    ],
    "wof:name":"Kurtz Repair Service Inc",
    "wof:placetype":"venue"
},
  "geometry": {"coordinates":[-85.55855699999999,41.530082],"type":"Point"}
}