{
  "type": "Feature",
  "properties": {
    "iso:country":"US",
    "sg:address":"105 W State St",
    "sg:city":"Ashley",
    "sg:classifiers":[
        {
            "category":"Food & Beverages",
            "subcategory":"Liquor & Beverages",
            "type":"Retail Goods"
        }
    ],
    "sg:phone":"+1 260 587 9400",
    "sg:postcode":"46705",
    "sg:province":"IN",
    "wof:name":"Bottle Shop",
    "wof:placetype":"venue"
},
  "geometry": {"coordinates":[-85.066906,41.527016],"type":"Point"}
}