{
  "type": "Feature",
  "properties": {
    "iso:country":"US",
    "sg:address":"3750 Roosevelt St",
    "sg:city":"Gary",
    "sg:classifiers":[
        {
            "category":"Retail",
            "subcategory":"Repair Shop",
            "type":"Services"
        }
    ],
    "sg:phone":"+1 219 884 6097",
    "sg:postcode":"46408",
    "sg:province":"IN",
    "sg:tags":[
        "equipment",
        "industrial"
    ],
    "wof:name":"Pro Pump Inc",
    "wof:placetype":"venue"
},
  "geometry": {"coordinates":[-87.363181,41.551017],"type":"Point"}
}