{
  "type": "Feature",
  "properties": {
    "iso:country":"US",
    "sg:address":"510 Foote St",
    "sg:city":"Crown Point",
    "sg:classifiers":[
        {
            "category":"Building & Trades",
            "subcategory":"Cleaning & Sanitation",
            "type":"Services"
        }
    ],
    "sg:phone":"+1 219 662 7838",
    "sg:postcode":"46307",
    "sg:province":"IN",
    "sg:tags":[
        "carpet"
    ],
    "sg:website":"www.mastercleanselect.com",
    "wof:name":"Master Clean",
    "wof:placetype":"venue"
},
  "geometry": {"coordinates":[-87.359386,41.426757],"type":"Point"}
}