{
  "type": "Feature",
  "properties": {
    "iso:country":"US",
    "sg:address":"116 E Pearl St",
    "sg:city":"Greens Fork",
    "sg:classifiers":[
        {
            "category":"Organizations",
            "subcategory":"Religious Organization",
            "type":"Services"
        }
    ],
    "sg:phone":"+1 765 886 5030",
    "sg:postcode":"47345",
    "sg:province":"IN",
    "sg:tags":[
        "church"
    ],
    "wof:name":"Greensfork Christian Church",
    "wof:placetype":"venue"
},
  "geometry": {"coordinates":[-85.042728,39.892848],"type":"Point"}
}