{
  "type": "Feature",
  "properties": {
    "iso:country":"US",
    "sg:address":"6020 E 82nd St Ste 1406",
    "sg:city":"Indianapolis",
    "sg:classifiers":[
        {
            "category":"Restaurant",
            "type":"Food & Drink"
        }
    ],
    "sg:phone":"+1 317 915 1338",
    "sg:postcode":"46250",
    "sg:province":"IN",
    "sg:tags":[
        "japanese"
    ],
    "wof:name":"Yuki Japanese Restaruant",
    "wof:placetype":"venue"
},
  "geometry": {"coordinates":[-86.061677,39.907886],"type":"Point"}
}