{
  "type": "Feature",
  "properties": {
    "iso:country":"US",
    "sg:address":"100 Industrial Dr",
    "sg:city":"Lawrenceburg",
    "sg:classifiers":[
        {
            "category":"Retail",
            "subcategory":"Auto Repair",
            "type":"Services"
        }
    ],
    "sg:phone":"+1 812 537 2744",
    "sg:postcode":"47025",
    "sg:province":"IN",
    "sg:tags":[
        "repairing",
        "automobile"
    ],
    "wof:name":"CARTECH",
    "wof:placetype":"venue"
},
  "geometry": {"coordinates":[-84.87407899999999,39.107589],"type":"Point"}
}