{
  "type": "Feature",
  "properties": {
    "iso:country":"US",
    "sg:address":"22790 Falcon Ct",
    "sg:city":"Goshen",
    "sg:classifiers":[
        {
            "category":"Home & Garden",
            "subcategory":"Home Furnishings",
            "type":"Retail Goods"
        }
    ],
    "sg:phone":"+1 574 875 6162",
    "sg:postcode":"46528",
    "sg:province":"IN",
    "sg:tags":[
        "venetian",
        "blind"
    ],
    "wof:name":"Rainbow Shades By Jane",
    "wof:placetype":"venue"
},
  "geometry": {"coordinates":[-85.904014,41.660942],"type":"Point"}
}