{
  "type": "Feature",
  "properties": {
    "iso:country":"US",
    "sg:address":"654 E Diamond Ave",
    "sg:city":"Evansville",
    "sg:classifiers":[
        {
            "category":"Shopping",
            "subcategory":"Books",
            "type":"Retail Goods"
        }
    ],
    "sg:phone":"+1 812 423 6952",
    "sg:postcode":"47711",
    "sg:province":"IN",
    "sg:tags":[
        "comic"
    ],
    "wof:name":"Comic's Unlimited",
    "wof:placetype":"venue"
},
  "geometry": {"coordinates":[-87.554326,37.999578],"type":"Point"}
}