{
  "type": "Feature",
  "properties": {
    "addr:full":"4335 Calumet Ave Hammond IN 46320",
    "addr:housenumber":"4335",
    "addr:postcode":"46320",
    "addr:street":"Calumet Ave",
    "iso:country":"US",
    "sg:address":"4335 Calumet Ave",
    "sg:city":"Hammond",
    "sg:classifiers":[
        {
            "category":"Retail",
            "subcategory":"Auto Rental",
            "type":"Services"
        }
    ],
    "sg:phone":"+1 219 931 5444",
    "sg:postcode":"46320",
    "sg:province":"IN",
    "sg:tags":[
        "renting",
        "truck",
        "leasing"
    ],
    "wof:name":"Allard Rental Corp",
    "wof:placetype":"venue"
},
  "geometry": {"coordinates":[-87.508662,41.634412],"type":"Point"}
}