{
  "type": "Feature",
  "properties": {
    "addr:full":"1002 E Center St Warsaw IN 46580",
    "addr:housenumber":"1002",
    "addr:postcode":"46580",
    "addr:street":"E Center St",
    "iso:country":"US",
    "sg:address":"1002 E Center St",
    "sg:city":"Warsaw",
    "sg:classifiers":[
        {
            "category":"Retail",
            "subcategory":"Photofinishing",
            "type":"Services"
        }
    ],
    "sg:phone":"+1 574 267 5400",
    "sg:postcode":"46580",
    "sg:province":"IN",
    "sg:tags":[
        "photo",
        "finishing"
    ],
    "sg:website":"www.blossers.com",
    "wof:name":"Blosser's 30 Min Photo",
    "wof:placetype":"venue"
},
  "geometry": {"coordinates":[-85.842882,41.237972],"type":"Point"}
}