{
  "type": "Feature",
  "properties": {
    "iso:country":"US",
    "sg:address":"148 S 1st Ave",
    "sg:city":"Beech Grove",
    "sg:classifiers":[
        {
            "category":"Autos & Motor Vehicles",
            "subcategory":"Auto Supplies",
            "type":"Retail Goods"
        }
    ],
    "sg:phone":"+1 317 786 2790",
    "sg:postcode":"46107",
    "sg:province":"IN",
    "wof:name":"Macs Off Road Inc",
    "wof:placetype":"venue"
},
  "geometry": {"coordinates":[-86.082444,39.721008],"type":"Point"}
}