{
  "type": "Feature",
  "properties": {
    "iso:country":"US",
    "sg:address":"425 W 56th Ave",
    "sg:city":"Merrillville",
    "sg:classifiers":[
        {
            "category":"Shopping",
            "subcategory":"Clothing, Apparel, & Fashions",
            "type":"Retail Goods"
        }
    ],
    "sg:phone":"+1 219 884 1787",
    "sg:postcode":"46410",
    "sg:province":"IN",
    "sg:tags":[
        "apparel",
        "women's"
    ],
    "wof:name":"Custom Made Fashions By Mimi",
    "wof:placetype":"venue"
},
  "geometry": {"coordinates":[-87.34108500000001,41.516335],"type":"Point"}
}