{
  "type": "Feature",
  "properties": {
    "iso:country":"US",
    "sg:address":"10 W Main St",
    "sg:city":"Greenfield",
    "sg:classifiers":[
        {
            "category":"Home & Garden",
            "subcategory":"Hardware",
            "type":"Retail Goods"
        }
    ],
    "sg:phone":"+1 317 462 2375",
    "sg:postcode":"46140",
    "sg:province":"IN",
    "wof:name":"Pickett Hardware Co",
    "wof:placetype":"venue"
},
  "geometry": {"coordinates":[-85.76938699999999,39.785287],"type":"Point"}
}