{
  "type": "Feature",
  "properties": {
    "iso:country":"US",
    "sg:address":"7225 Riley Ct",
    "sg:city":"Indianapolis",
    "sg:classifiers":[
        {
            "category":"Wholesale",
            "subcategory":"Machinery & Supplies",
            "type":"Manufacturing & Wholesale Goods"
        }
    ],
    "sg:phone":"+1 317 594 9141",
    "sg:postcode":"46250",
    "sg:province":"IN",
    "sg:tags":[
        "fire",
        "equipment",
        "fighting"
    ],
    "wof:name":"Isap Corp",
    "wof:placetype":"venue"
},
  "geometry": {"coordinates":[-86.086985,39.887052],"type":"Point"}
}