{
  "type": "Feature",
  "properties": {
    "iso:country":"US",
    "sg:address":"14220 Union St",
    "sg:city":"Hebron",
    "sg:classifiers":[
        {
            "category":"Professional",
            "subcategory":"Computer Services",
            "type":"Services"
        }
    ],
    "sg:phone":"+1 219 996 6573",
    "sg:postcode":"46341",
    "sg:province":"IN",
    "sg:tags":[
        "datum"
    ],
    "wof:name":"Netdisney",
    "wof:placetype":"venue"
},
  "geometry": {"coordinates":[-87.229485,41.35766],"type":"Point"}
}