{
  "type": "Feature",
  "properties": {
    "iso:country":"US",
    "sg:address":"4933 E 16th St",
    "sg:city":"Indianapolis",
    "sg:classifiers":[
        {
            "category":"Food & Beverages",
            "subcategory":"Liquor & Beverages",
            "type":"Retail Goods"
        }
    ],
    "sg:phone":"+1 317 353 0646",
    "sg:postcode":"46201",
    "sg:province":"IN",
    "wof:name":"Payless Liquors",
    "wof:placetype":"venue"
},
  "geometry": {"coordinates":[-86.085795,39.788791],"type":"Point"}
}