{
  "type": "Feature",
  "properties": {
    "iso:country":"US",
    "sg:address":"5699 Coventry Ln",
    "sg:city":"Fort Wayne",
    "sg:classifiers":[
        {
            "category":"Education",
            "subcategory":"Vocational School",
            "type":"Public Place"
        }
    ],
    "sg:phone":"+1 260 459 4500",
    "sg:postcode":"46804",
    "sg:province":"IN",
    "sg:tags":[
        "secretarial"
    ],
    "sg:website":"www.ibcfortwayne.edu",
    "wof:name":"International Business College",
    "wof:placetype":"venue"
},
  "geometry": {"coordinates":[-85.256443,41.036265],"type":"Point"}
}