{
  "type": "Feature",
  "properties": {
    "iso:country":"US",
    "sg:address":"2517 W 1250 N",
    "sg:city":"Milford",
    "sg:classifiers":[
        {
            "category":"Farming",
            "subcategory":"Farm",
            "type":"Manufacturing & Wholesale Goods"
        }
    ],
    "sg:phone":"+1 574 658 3343",
    "sg:postcode":"46542",
    "sg:province":"IN",
    "wof:name":"Mil-View Farm",
    "wof:placetype":"venue"
},
  "geometry": {"coordinates":[-85.896931,41.412858],"type":"Point"}
}