{
  "type": "Feature",
  "properties": {
    "iso:country":"US",
    "sg:address":"2162 N Mitthoeffer Rd",
    "sg:city":"Indianapolis",
    "sg:classifiers":[
        {
            "category":"Manufacturing",
            "subcategory":"Tobacco Products",
            "type":"Manufacturing & Wholesale Goods"
        },
        {
            "category":"Wholesale",
            "subcategory":"Tobacco Products",
            "type":"Manufacturing & Wholesale Goods"
        }
    ],
    "sg:phone":"+1 317 890 8820",
    "sg:postcode":"46229",
    "sg:province":"IN",
    "sg:tags":[
        "cigar",
        "tobacco-wholesale",
        "cigarette",
        "warehouse",
        "manufacturer"
    ],
    "wof:name":"Tobacco Cash Warehouse",
    "wof:placetype":"venue"
},
  "geometry": {"coordinates":[-85.990555,39.798401],"type":"Point"}
}