{
  "type": "Feature",
  "properties": {
    "iso:country":"US",
    "sg:address":"522 Ashland St",
    "sg:city":"Brownstown",
    "sg:phone":"+1 812 358 2960",
    "sg:postcode":"47220",
    "sg:province":"IN",
    "sg:tags":[
        "farm",
        "corn",
        "wheat",
        "soybean"
    ],
    "wof:name":"Ray Meahl",
    "wof:placetype":"venue"
},
  "geometry": {"coordinates":[-86.05260800000001,38.876029],"type":"Point"}
}