{
  "type": "Feature",
  "properties": {
    "iso:country":"US",
    "sg:address":"2070 Indianapolis Blvd",
    "sg:city":"Whiting",
    "sg:classifiers":[
        {
            "category":"Restaurant",
            "type":"Food & Drink"
        }
    ],
    "sg:phone":"+1 219 659 0452",
    "sg:postcode":"46394",
    "sg:province":"IN",
    "sg:tags":[
        "pizza"
    ],
    "sg:website":"www.littlecaesars.com",
    "wof:name":"Little Caesar's Pizza",
    "wof:placetype":"venue"
},
  "geometry": {"coordinates":[-87.49569700000001,41.6759],"type":"Point"}
}