{
  "type": "Feature",
  "properties": {
    "iso:country":"US",
    "sg:address":"502 National Ave",
    "sg:city":"Indianapolis",
    "sg:classifiers":[
        {
            "category":"Farming",
            "subcategory":"Nursery",
            "type":"Manufacturing & Wholesale Goods"
        }
    ],
    "sg:phone":"+1 317 786 1528",
    "sg:postcode":"46227",
    "sg:province":"IN",
    "sg:tags":[
        "greenhouse"
    ],
    "wof:name":"Heidenreich Greenhouses",
    "wof:placetype":"venue"
},
  "geometry": {"coordinates":[-86.145298,39.711719],"type":"Point"}
}