{
  "type": "Feature",
  "properties": {
    "iso:country":"US",
    "sg:address":"580 Main St",
    "sg:city":"Lawrenceburg",
    "sg:classifiers":[
        {
            "category":"Social Services",
            "subcategory":"Adult Care",
            "type":"Services"
        }
    ],
    "sg:phone":"+1 812 537 2441",
    "sg:postcode":"47025",
    "sg:province":"IN",
    "sg:tags":[
        "home",
        "group"
    ],
    "wof:name":"VOCA Corp Of Indiana",
    "wof:placetype":"venue"
},
  "geometry": {"coordinates":[-84.859493,39.098768],"type":"Point"}
}