{
  "type": "Feature",
  "properties": {
    "iso:country":"US",
    "sg:address":"6382 S 50 E",
    "sg:city":"Wabash",
    "sg:classifiers":[
        {
            "category":"Organizations",
            "subcategory":"Religious Organization",
            "type":"Services"
        }
    ],
    "sg:phone":"+1 219 866 0679",
    "sg:postcode":"46992",
    "sg:province":"IN",
    "sg:tags":[
        "church"
    ],
    "wof:name":"Plainfield Christian Church",
    "wof:placetype":"venue"
},
  "geometry": {"coordinates":[-85.782781,40.733281],"type":"Point"}
}