{
  "type": "Feature",
  "properties": {
    "addr:full":"321 W Oregon St Evansville IN 47710",
    "addr:housenumber":"321",
    "addr:postcode":"47710",
    "addr:street":"W Oregon St",
    "iso:country":"US",
    "sg:address":"321 W Oregon St",
    "sg:city":"Evansville",
    "sg:classifiers":[
        {
            "category":"Recreation",
            "type":"Entertainment"
        },
        {
            "category":"Organizations",
            "subcategory":"Community Association",
            "type":"Services"
        }
    ],
    "sg:phone":"+1 812 422 1819",
    "sg:postcode":"47710",
    "sg:province":"IN",
    "sg:tags":[
        "club",
        "membership"
    ],
    "wof:name":"Evansville Athletic Club Inc",
    "wof:placetype":"venue"
},
  "geometry": {"coordinates":[-87.56943800000001,37.986685],"type":"Point"}
}