{
  "type": "Feature",
  "properties": {
    "iso:country":"US",
    "sg:address":"101 W Kirkwood Ave Ste 119",
    "sg:city":"Bloomington",
    "sg:classifiers":[
        {
            "category":"Health Services",
            "subcategory":"Optometrist",
            "type":"Services"
        },
        {
            "category":"Shopping",
            "subcategory":"Optician",
            "type":"Retail Goods"
        }
    ],
    "sg:phone":"+1 812 331 9082",
    "sg:postcode":"47404",
    "sg:province":"IN",
    "sg:tags":[
        "eyewear"
    ],
    "sg:website":"www.optiks.com",
    "wof:name":"Optiks",
    "wof:placetype":"venue"
},
  "geometry": {"coordinates":[-86.533672,39.166577],"type":"Point"}
}