{
  "type": "Feature",
  "properties": {
    "iso:country":"US",
    "sg:address":"8001 E Fenway Dr",
    "sg:city":"Terre Haute",
    "sg:classifiers":[
        {
            "category":"Building & Trades",
            "subcategory":"Construction",
            "type":"Services"
        }
    ],
    "sg:phone":"+1 812 894 3264",
    "sg:postcode":"47802",
    "sg:province":"IN",
    "sg:tags":[
        "farm",
        "contractor",
        "labor"
    ],
    "wof:name":"Mark Larison Contracting",
    "wof:placetype":"venue"
},
  "geometry": {"coordinates":[-87.294582,39.404856],"type":"Point"}
}