{
  "type": "Feature",
  "properties": {
    "addr:full":"349 W 100 S Valparaiso IN 46385",
    "addr:housenumber":"349",
    "addr:postcode":"46385",
    "addr:street":"W 100 S",
    "iso:country":"US",
    "sg:address":"349 W 100 S",
    "sg:city":"Valparaiso",
    "sg:classifiers":[
        {
            "category":"Farming",
            "subcategory":"Livestock Farm",
            "type":"Manufacturing & Wholesale Goods"
        }
    ],
    "sg:phone":"+1 219 462 7002",
    "sg:postcode":"46385",
    "sg:province":"IN",
    "sg:tags":[
        "ranch"
    ],
    "wof:name":"Outcast Ranch",
    "wof:placetype":"venue"
},
  "geometry": {"coordinates":[-87.123999,41.420438],"type":"Point"}
}