{
  "type": "Feature",
  "properties": {
    "iso:country":"US",
    "sg:address":"3101 Broadway St",
    "sg:city":"Fort Wayne",
    "sg:classifiers":[
        {
            "category":"Personal",
            "subcategory":"Barber",
            "type":"Services"
        }
    ],
    "sg:phone":"+1 260 456 0425",
    "sg:postcode":"46807",
    "sg:province":"IN",
    "wof:name":"Riley's Barber Shop",
    "wof:placetype":"venue"
},
  "geometry": {"coordinates":[-85.154654,41.056048],"type":"Point"}
}