{
  "type": "Feature",
  "properties": {
    "iso:country":"US",
    "sg:address":"4901 W McGalliard Rd",
    "sg:city":"Muncie",
    "sg:classifiers":[
        {
            "category":"Autos & Motor Vehicles",
            "subcategory":"Automobile Sales",
            "type":"Retail Goods"
        }
    ],
    "sg:phone":"+1 765 282 5955",
    "sg:postcode":"47304",
    "sg:province":"IN",
    "sg:tags":[
        "car",
        "dealer"
    ],
    "wof:name":"Victory Honda Of Muncie",
    "wof:placetype":"venue"
},
  "geometry": {"coordinates":[-85.442681,40.218367],"type":"Point"}
}