{
  "type": "Feature",
  "properties": {
    "iso:country":"US",
    "sg:address":"101 Utility Dr",
    "sg:city":"Hebron",
    "sg:classifiers":[
        {
            "category":"Government",
            "subcategory":"Office",
            "type":"Public Place"
        }
    ],
    "sg:phone":"+1 219 996 5950",
    "sg:postcode":"46341",
    "sg:province":"IN",
    "sg:tags":[
        "village"
    ],
    "wof:name":"Hebron Sewage Treatment Plant",
    "wof:placetype":"venue"
},
  "geometry": {"coordinates":[-87.191159,41.316435],"type":"Point"}
}