{
  "type": "Feature",
  "properties": {
    "iso:country":"US",
    "sg:address":"8917 Dune Creek Cove",
    "sg:city":"Fort Wayne",
    "sg:classifiers":[
        {
            "category":"Building & Trades",
            "subcategory":"Construction",
            "type":"Services"
        }
    ],
    "sg:phone":"+1 260 485 2617",
    "sg:postcode":"46835",
    "sg:province":"IN",
    "sg:tags":[
        "contractor"
    ],
    "wof:name":"Stripe-N-Seal Inc",
    "wof:placetype":"venue"
},
  "geometry": {"coordinates":[-85.02979999999999,41.138124],"type":"Point"}
}