{
  "type": "Feature",
  "properties": {
    "iso:country":"US",
    "sg:address":"20 E Center St",
    "sg:city":"Lawrenceburg",
    "sg:classifiers":[
        {
            "category":"Home & Garden",
            "subcategory":"Carpets & Floor Coverings",
            "type":"Retail Goods"
        }
    ],
    "sg:phone":"+1 812 537 0619",
    "sg:postcode":"47025",
    "sg:province":"IN",
    "sg:tags":[
        "material"
    ],
    "sg:website":"www.homefurniture.bz",
    "wof:name":"Home Furniture",
    "wof:placetype":"venue"
},
  "geometry": {"coordinates":[-84.849236,39.094356],"type":"Point"}
}