{
  "type": "Feature",
  "properties": {
    "iso:country":"US",
    "sg:address":"2 W Main St",
    "sg:city":"Gosport",
    "sg:classifiers":[
        {
            "category":"Organizations",
            "subcategory":"Religious Organization",
            "type":"Services"
        }
    ],
    "sg:phone":"+1 812 879 4316",
    "sg:postcode":"47433",
    "sg:province":"IN",
    "sg:tags":[
        "church"
    ],
    "wof:name":"Gosport Baptist Church",
    "wof:placetype":"venue"
},
  "geometry": {"coordinates":[-86.668516,39.348894],"type":"Point"}
}