{
  "type": "Feature",
  "properties": {
    "iso:country":"US",
    "sg:address":"1834 E Summer St",
    "sg:city":"Hammond",
    "sg:classifiers":[
        {
            "category":"Building & Trades",
            "subcategory":"Construction",
            "type":"Services"
        }
    ],
    "sg:phone":"+1 219 932 5036",
    "sg:postcode":"46320",
    "sg:province":"IN",
    "sg:tags":[
        "contractor"
    ],
    "wof:name":"Morrison Construction Company",
    "wof:placetype":"venue"
},
  "geometry": {"coordinates":[-87.486397,41.603199],"type":"Point"}
}