{
  "type": "Feature",
  "properties": {
    "iso:country":"US",
    "sg:address":"153 Bethel Ave",
    "sg:city":"Beech Grove",
    "sg:classifiers":[
        {
            "category":"Building & Trades",
            "subcategory":"Plumbing",
            "type":"Services"
        }
    ],
    "sg:phone":"+1 317 787 5625",
    "sg:postcode":"46107",
    "sg:province":"IN",
    "sg:tags":[
        "heating",
        "contractor"
    ],
    "wof:name":"Gene Ray Heating & Cooling",
    "wof:placetype":"venue"
},
  "geometry": {"coordinates":[-86.083253,39.724414],"type":"Point"}
}