{
  "type": "Feature",
  "properties": {
    "iso:country":"US",
    "sg:address":"113 W 700 N",
    "sg:city":"Crawfordsville",
    "sg:classifiers":[
        {
            "category":"Home & Garden",
            "subcategory":"Garden Supply",
            "type":"Retail Goods"
        }
    ],
    "sg:phone":"+1 765 339 7393",
    "sg:postcode":"47978",
    "sg:province":"IN",
    "sg:tags":[
        "tree",
        "christmas"
    ],
    "wof:name":"Layton's Christmas Tree Farm",
    "wof:placetype":"venue"
},
  "geometry": {"coordinates":[-87.047823,41.114697],"type":"Point"}
}