{
  "type": "Feature",
  "properties": {
    "iso:country":"US",
    "sg:address":"2324 Sagamore Pkwy S",
    "sg:city":"Lafayette",
    "sg:classifiers":[
        {
            "category":"Shopping",
            "subcategory":"Hobbies, Toys, & Games",
            "type":"Retail Goods"
        }
    ],
    "sg:phone":"+1 765 474 4425",
    "sg:postcode":"47905",
    "sg:province":"IN",
    "wof:name":"Toys R Us",
    "wof:placetype":"venue"
},
  "geometry": {"coordinates":[-86.855069,40.393476],"type":"Point"}
}