{
  "type": "Feature",
  "properties": {
    "iso:country":"US",
    "sg:address":"1320 Lowell Ct",
    "sg:city":"Clarksville",
    "sg:classifiers":[
        {
            "category":"Farming",
            "subcategory":"Farm",
            "type":"Manufacturing & Wholesale Goods"
        }
    ],
    "sg:phone":"+1 812 949 1065",
    "sg:postcode":"47129",
    "sg:province":"IN",
    "sg:tags":[
        "crop",
        "general"
    ],
    "wof:name":"Lila M Dering Family Farms LLC",
    "wof:placetype":"venue"
},
  "geometry": {"coordinates":[-85.77326600000001,38.319215],"type":"Point"}
}