{
  "type": "Feature",
  "properties": {
    "iso:country":"US",
    "sg:address":"958 E Chestnut St",
    "sg:city":"Jeffersonville",
    "sg:classifiers":[
        {
            "category":"Organizations",
            "subcategory":"Labor Organization",
            "type":"Services"
        }
    ],
    "sg:phone":"+1 812 282 2212",
    "sg:postcode":"47130",
    "sg:province":"IN",
    "wof:name":"International Chemical Workers",
    "wof:placetype":"venue"
},
  "geometry": {"coordinates":[-85.728926,38.27739],"type":"Point"}
}