{
  "type": "Feature",
  "properties": {
    "iso:country":"US",
    "sg:address":"2838 45th St",
    "sg:city":"Highland",
    "sg:classifiers":[
        {
            "category":"Health Services",
            "subcategory":"Doctor",
            "type":"Services"
        }
    ],
    "sg:phone":"+1 219 922 7945",
    "sg:postcode":"46322",
    "sg:province":"IN",
    "sg:tags":[
        "dentist"
    ],
    "wof:name":"Laura G Fletes DDS",
    "wof:placetype":"venue"
},
  "geometry": {"coordinates":[-87.460765,41.537402],"type":"Point"}
}