{
  "type": "Feature",
  "properties": {
    "iso:country":"US",
    "sg:address":"125 W Grant St",
    "sg:city":"Decatur",
    "sg:classifiers":[
        {
            "category":"Wholesale",
            "subcategory":"Electrical",
            "type":"Manufacturing & Wholesale Goods"
        }
    ],
    "sg:phone":"+1 260 724 8874",
    "sg:postcode":"46733",
    "sg:province":"IN",
    "sg:tags":[
        "harness",
        "wire"
    ],
    "wof:name":"Tri Tec Systems Inc",
    "wof:placetype":"venue"
},
  "geometry": {"coordinates":[-84.91904,40.821407],"type":"Point"}
}