{
  "type": "Feature",
  "properties": {
    "iso:country":"US",
    "sg:address":"2319 Fair Oaks Dr Apt B",
    "sg:city":"Indianapolis",
    "sg:classifiers":[
        {
            "category":"Bakery",
            "type":"Food & Drink"
        }
    ],
    "sg:phone":"+1 317 248 0307",
    "sg:postcode":"46224",
    "sg:province":"IN",
    "wof:name":"Raul Morales Bakery",
    "wof:placetype":"venue"
},
  "geometry": {"coordinates":[-86.253355,39.797589],"type":"Point"}
}