{
  "type": "Feature",
  "properties": {
    "iso:country":"US",
    "sg:address":"7001 Pendleton Pike",
    "sg:city":"Indianapolis",
    "sg:classifiers":[
        {
            "category":"Retail",
            "subcategory":"Auto Repair",
            "type":"Services"
        }
    ],
    "sg:phone":"+1 317 542 7615",
    "sg:postcode":"46226",
    "sg:province":"IN",
    "sg:tags":[
        "repairing",
        "automobile"
    ],
    "wof:name":"Sincere Auto Care",
    "wof:placetype":"venue"
},
  "geometry": {"coordinates":[-86.04454,39.827968],"type":"Point"}
}