{
  "type": "Feature",
  "properties": {
    "addr:full":"1045 N Senate Ave Indianapolis IN 46202",
    "addr:housenumber":"1045",
    "addr:postcode":"46202",
    "addr:street":"N Senate Ave",
    "iso:country":"US",
    "sg:address":"1045 N Senate Ave",
    "sg:city":"Indianapolis",
    "sg:classifiers":[
        {
            "category":"Bars & Pubs",
            "type":"Food & Drink"
        }
    ],
    "sg:phone":"+1 317 637 2680",
    "sg:postcode":"46202",
    "sg:province":"IN",
    "wof:name":"Loading Dock",
    "wof:placetype":"venue"
},
  "geometry": {"coordinates":[-86.16298999999999,39.781028],"type":"Point"}
}