{
  "type": "Feature",
  "properties": {
    "iso:country":"US",
    "sg:address":"3140 W Co Rd 900 N",
    "sg:city":"Brazil",
    "sg:classifiers":[
        {
            "category":"Building & Trades",
            "subcategory":"Construction",
            "type":"Services"
        }
    ],
    "sg:phone":"+1 812 443 2081",
    "sg:postcode":"47834",
    "sg:province":"IN",
    "sg:tags":[
        "residential",
        "nonresidential"
    ],
    "wof:name":"Weddle Construction",
    "wof:placetype":"venue"
},
  "geometry": {"coordinates":[-87.16580500000001,39.51904],"type":"Point"}
}