{
  "type": "Feature",
  "properties": {
    "iso:country":"US",
    "sg:address":"10110 Brooks School Rd",
    "sg:city":"Fishers",
    "sg:classifiers":[
        {
            "category":"Restaurant",
            "type":"Food & Drink"
        }
    ],
    "sg:phone":"+1 317 598 9663",
    "sg:postcode":"46037",
    "sg:province":"IN",
    "sg:tags":[
        "shop",
        "coffee"
    ],
    "wof:name":"Mama Bear's",
    "wof:placetype":"venue"
},
  "geometry": {"coordinates":[-85.947585,39.934746],"type":"Point"}
}