{
  "type": "Feature",
  "properties": {
    "addr:full":"2993 Weatherstone Dr Carmel IN 46032",
    "addr:housenumber":"2993",
    "addr:postcode":"46032",
    "addr:street":"Weatherstone Dr",
    "iso:country":"US",
    "sg:address":"2993 Weatherstone Dr",
    "sg:city":"Carmel",
    "sg:classifiers":[
        {
            "category":"Banks & Credit Unions",
            "subcategory":"Bank",
            "type":"Services"
        }
    ],
    "sg:phone":"+1 317 587 0495",
    "sg:postcode":"46032",
    "sg:province":"IN",
    "sg:tags":[
        "loan",
        "real estate"
    ],
    "wof:name":"First Equity Funding",
    "wof:placetype":"venue"
},
  "geometry": {"coordinates":[-86.11283899999999,39.935045],"type":"Point"}
}