{
  "type": "Feature",
  "properties": {
    "addr:full":"6161 E 75th St Indianapolis IN 46250",
    "addr:housenumber":"6161",
    "addr:postcode":"46250",
    "addr:street":"E 75Th St",
    "iso:country":"US",
    "sg:address":"6161 E 75th St",
    "sg:city":"Indianapolis",
    "sg:classifiers":[
        {
            "category":"Wholesale",
            "subcategory":"Machinery & Supplies",
            "type":"Manufacturing & Wholesale Goods"
        }
    ],
    "sg:phone":"+1 317 567 2488",
    "sg:postcode":"46250",
    "sg:province":"IN",
    "sg:tags":[
        "industrial",
        "equipment",
        "used",
        "machinery-new",
        "supplies-wholesale"
    ],
    "wof:name":"Stanley Works",
    "wof:placetype":"venue"
},
  "geometry": {"coordinates":[-86.06166,39.890646],"type":"Point"}
}