{
  "type": "Feature",
  "properties": {
    "iso:country":"US",
    "sg:address":"902 Norwood Dr",
    "sg:city":"North Manchester",
    "sg:classifiers":[
        {
            "category":"Retail",
            "subcategory":"Animal Services",
            "type":"Services"
        }
    ],
    "sg:phone":"+1 260 982 7696",
    "sg:postcode":"46962",
    "sg:province":"IN",
    "wof:name":"Whisker Sitters",
    "wof:placetype":"venue"
},
  "geometry": {"coordinates":[-85.760164,41.01951],"type":"Point"}
}