{
  "type": "Feature",
  "properties": {
    "iso:country":"US",
    "sg:address":"207 W Union St",
    "sg:city":"Liberty",
    "sg:classifiers":[
        {
            "category":"Restaurant",
            "type":"Food & Drink"
        }
    ],
    "sg:phone":"+1 765 458 6890",
    "sg:postcode":"47353",
    "sg:province":"IN",
    "wof:name":"J's Restaurant",
    "wof:placetype":"venue"
},
  "geometry": {"coordinates":[-84.934463,39.63553],"type":"Point"}
}