{
  "type": "Feature",
  "properties": {
    "iso:country":"US",
    "sg:address":"3901 Irish Hills Dr",
    "sg:city":"South Bend",
    "sg:classifiers":[
        {
            "category":"Retail",
            "subcategory":"Repair Shop",
            "type":"Services"
        }
    ],
    "sg:phone":"+1 574 210 3799",
    "sg:postcode":"46614",
    "sg:province":"IN",
    "sg:tags":[
        "merchandise"
    ],
    "wof:name":"Michiana Door Company",
    "wof:placetype":"venue"
},
  "geometry": {"coordinates":[-86.210295,41.629528],"type":"Point"}
}