{
  "type": "Feature",
  "properties": {
    "iso:country":"US",
    "sg:address":"717 S East St",
    "sg:city":"Indianapolis",
    "sg:classifiers":[
        {
            "category":"Professional",
            "subcategory":"Lawyer & Legal Services",
            "type":"Services"
        }
    ],
    "sg:phone":"+1 317 632 5633",
    "sg:postcode":"46225",
    "sg:province":"IN",
    "sg:tags":[
        "attorney"
    ],
    "wof:name":"Austin & Jones",
    "wof:placetype":"venue"
},
  "geometry": {"coordinates":[-86.149526,39.756733],"type":"Point"}
}