{
  "type": "Feature",
  "properties": {
    "iso:country":"US",
    "sg:address":"6309 N Co Rd 500 E",
    "sg:city":"Muncie",
    "sg:classifiers":[
        {
            "category":"Organizations",
            "subcategory":"Religious Organization",
            "type":"Services"
        }
    ],
    "sg:phone":"+1 765 284 8062",
    "sg:postcode":"47303",
    "sg:province":"IN",
    "sg:tags":[
        "church"
    ],
    "wof:name":"De Soto United Methodist Chr",
    "wof:placetype":"venue"
},
  "geometry": {"coordinates":[-85.293309,40.248453],"type":"Point"}
}