{
  "type": "Feature",
  "properties": {
    "addr:full":"118 E Palmer St Indianapolis IN 46225",
    "addr:housenumber":"118",
    "addr:postcode":"46225",
    "addr:street":"E Palmer St",
    "iso:country":"US",
    "sg:address":"118 E Palmer St",
    "sg:city":"Indianapolis",
    "sg:classifiers":[
        {
            "category":"Bars & Pubs",
            "type":"Food & Drink"
        }
    ],
    "sg:phone":"+1 317 632 5199",
    "sg:postcode":"46225",
    "sg:province":"IN",
    "wof:name":"Vollrath Tavern",
    "wof:placetype":"venue"
},
  "geometry": {"coordinates":[-86.157444,39.746069],"type":"Point"}
}