{
  "type": "Feature",
  "properties": {
    "iso:country":"US",
    "sg:address":"54541 Co Rd 19",
    "sg:city":"Bristol",
    "sg:classifiers":[
        {
            "category":"Banks & Credit Unions",
            "subcategory":"Investment Brokerage",
            "type":"Services"
        },
        {
            "category":"Professional",
            "subcategory":"Management & Consulting",
            "type":"Services"
        }
    ],
    "sg:phone":"+1 574 848 9770",
    "sg:postcode":"46507",
    "sg:province":"IN",
    "sg:tags":[
        "personal",
        "advisory",
        "financial"
    ],
    "wof:name":"Fifth Street Financial Service",
    "wof:placetype":"venue"
},
  "geometry": {"coordinates":[-85.870587,41.700204],"type":"Point"}
}