{
  "type": "Feature",
  "properties": {
    "iso:country":"US",
    "sg:address":"1354 S Wallick Rd",
    "sg:city":"Peru",
    "sg:classifiers":[
        {
            "category":"Personal",
            "type":"Services"
        }
    ],
    "sg:phone":"+1 765 472 3227",
    "sg:postcode":"46970",
    "sg:province":"IN",
    "wof:name":"Exotic Tans",
    "wof:placetype":"venue"
},
  "geometry": {"coordinates":[-86.097909,40.736798],"type":"Point"}
}