{
  "type": "Feature",
  "properties": {
    "iso:country":"US",
    "sg:address":"900 Old Plank Rd",
    "sg:city":"Rockport",
    "sg:classifiers":[
        {
            "category":"Government",
            "subcategory":"Office",
            "type":"Public Place"
        }
    ],
    "sg:phone":"+1 812 649 9111",
    "sg:postcode":"47601",
    "sg:province":"IN",
    "sg:tags":[
        "county",
        "resource"
    ],
    "wof:name":"Spencer County Public Welfare",
    "wof:placetype":"venue"
},
  "geometry": {"coordinates":[-87.369914,38.016307],"type":"Point"}
}