{
  "type": "Feature",
  "properties": {
    "iso:country":"US",
    "sg:address":"1002 Wishard Blvd",
    "sg:city":"Indianapolis",
    "sg:classifiers":[
        {
            "category":"Health Services",
            "subcategory":"Doctor",
            "type":"Services"
        }
    ],
    "sg:phone":"+1 317 266 2902",
    "sg:postcode":"46202",
    "sg:province":"IN",
    "sg:tags":[
        "physician",
        "surgeon"
    ],
    "wof:name":"Rita Bair MD",
    "wof:placetype":"venue"
},
  "geometry": {"coordinates":[-86.174927,39.778751],"type":"Point"}
}