{
  "type": "Feature",
  "properties": {
    "iso:country":"US",
    "sg:address":"3104 S Lafountain St",
    "sg:city":"Kokomo",
    "sg:classifiers":[
        {
            "category":"Education",
            "subcategory":"Dance Studio",
            "type":"Public Place"
        }
    ],
    "sg:phone":"+1 765 453 1956",
    "sg:postcode":"46902",
    "sg:province":"IN",
    "sg:tags":[
        "instruction",
        "dancing"
    ],
    "wof:name":"Kristie Wright School Of Dance",
    "wof:placetype":"venue"
},
  "geometry": {"coordinates":[-86.12699,40.451099],"type":"Point"}
}