{
  "type": "Feature",
  "properties": {
    "addr:full":"3101 Broadway Gary IN 46409",
    "addr:housenumber":"3101",
    "addr:postcode":"46409",
    "addr:street":"Broadway",
    "iso:country":"US",
    "sg:address":"3101 Broadway",
    "sg:city":"Gary",
    "sg:classifiers":[
        {
            "category":"Organizations",
            "subcategory":"Non-profit Organization",
            "type":"Services"
        }
    ],
    "sg:phone":"+1 219 887 9621",
    "sg:postcode":"46409",
    "sg:province":"IN",
    "wof:name":"Urban League Of Northwest In",
    "wof:placetype":"venue"
},
  "geometry": {"coordinates":[-87.33662699999999,41.558517],"type":"Point"}
}