{
  "type": "Feature",
  "properties": {
    "iso:country":"US",
    "sg:address":"2101 Virginia St",
    "sg:city":"Gary",
    "sg:classifiers":[
        {
            "category":"Food & Beverages",
            "subcategory":"Groceries & Convenience Stores",
            "type":"Retail Goods"
        }
    ],
    "sg:phone":"+1 219 886 2211",
    "sg:postcode":"46407",
    "sg:province":"IN",
    "sg:tags":[
        "grocer"
    ],
    "wof:name":"Sam's Food",
    "wof:placetype":"venue"
},
  "geometry": {"coordinates":[-87.329603,41.579857],"type":"Point"}
}