{
  "type": "Feature",
  "properties": {
    "iso:country":"US",
    "sg:address":"600 E 6th St",
    "sg:city":"Huntingburg",
    "sg:classifiers":[
        {
            "category":"Wholesale",
            "subcategory":"Hardware",
            "type":"Manufacturing & Wholesale Goods"
        }
    ],
    "sg:phone":"+1 812 683 0800",
    "sg:postcode":"47542",
    "sg:province":"IN",
    "sg:tags":[
        "fastener"
    ],
    "wof:name":"S L Wylucki Constr Fasteners",
    "wof:placetype":"venue"
},
  "geometry": {"coordinates":[-86.951648,38.29891],"type":"Point"}
}