{
  "type": "Feature",
  "properties": {
    "iso:country":"US",
    "sg:address":"1409 N Fares Ave",
    "sg:city":"Evansville",
    "sg:classifiers":[
        {
            "category":"Professional",
            "type":"Services"
        }
    ],
    "sg:phone":"+1 812 554 0029",
    "sg:postcode":"47711",
    "sg:province":"IN",
    "sg:tags":[
        "establishment"
    ],
    "wof:name":"Lacy Ladies",
    "wof:placetype":"venue"
},
  "geometry": {"coordinates":[-87.542832,37.990974],"type":"Point"}
}