{
  "type": "Feature",
  "properties": {
    "addr:full":"801 E Market St Logansport IN 46947",
    "addr:housenumber":"801",
    "addr:postcode":"46947",
    "addr:street":"E Market St",
    "iso:country":"US",
    "sg:address":"801 E Market St",
    "sg:city":"Logansport",
    "sg:classifiers":[
        {
            "category":"Autos & Motor Vehicles",
            "subcategory":"Auto Supplies",
            "type":"Retail Goods"
        }
    ],
    "sg:phone":"+1 574 722 6666",
    "sg:postcode":"46947",
    "sg:province":"IN",
    "sg:tags":[
        "automobile",
        "parts"
    ],
    "wof:name":"NAPA Auto Parts",
    "wof:placetype":"venue"
},
  "geometry": {"coordinates":[-86.35836399999999,40.754086],"type":"Point"}
}