{
  "type": "Feature",
  "properties": {
    "addr:full":"1503 Columbia Ave Indianapolis IN 46202",
    "addr:housenumber":"1503",
    "addr:postcode":"46202",
    "addr:street":"Columbia Ave",
    "iso:country":"US",
    "sg:address":"1503 Columbia Ave",
    "sg:city":"Indianapolis",
    "sg:classifiers":[
        {
            "category":"Retail",
            "subcategory":"Funeral Services",
            "type":"Services"
        }
    ],
    "sg:phone":"+1 317 955 1193",
    "sg:postcode":"46202",
    "sg:province":"IN",
    "sg:tags":[
        "director"
    ],
    "wof:name":"Ellis Mortuary",
    "wof:placetype":"venue"
},
  "geometry": {"coordinates":[-86.13691900000001,39.788477],"type":"Point"}
}