{
  "type": "Feature",
  "properties": {
    "iso:country":"US",
    "sg:address":"2612 E Morgan Ave",
    "sg:city":"Evansville",
    "sg:classifiers":[
        {
            "category":"Education",
            "subcategory":"Dance Studio",
            "type":"Public Place"
        }
    ],
    "sg:phone":"+1 812 473 6003",
    "sg:postcode":"47711",
    "sg:province":"IN",
    "sg:tags":[
        "instruction",
        "dancing"
    ],
    "wof:name":"Dance Crafters-School-Ballroom",
    "wof:placetype":"venue"
},
  "geometry": {"coordinates":[-87.517009,37.99162],"type":"Point"}
}