{
  "type": "Feature",
  "properties": {
    "iso:country":"US",
    "sg:address":"10832 Paulding Rd",
    "sg:city":"New Haven",
    "sg:classifiers":[
        {
            "category":"Building & Trades",
            "subcategory":"Construction",
            "type":"Services"
        }
    ],
    "sg:phone":"+1 260 749 0800",
    "sg:postcode":"46774",
    "sg:province":"IN",
    "sg:tags":[
        "roofing",
        "contractor"
    ],
    "wof:name":"Bailey Construction",
    "wof:placetype":"venue"
},
  "geometry": {"coordinates":[-84.995242,41.034211],"type":"Point"}
}