{
  "type": "Feature",
  "properties": {
    "iso:country":"US",
    "sg:address":"775 Heuser St NE",
    "sg:city":"Palmyra",
    "sg:classifiers":[
        {
            "category":"Home & Garden",
            "subcategory":"Garden Supply",
            "type":"Retail Goods"
        }
    ],
    "sg:phone":"+1 812 364 6642",
    "sg:postcode":"47164",
    "sg:province":"IN",
    "sg:tags":[
        "water"
    ],
    "wof:name":"Custom Aquatics",
    "wof:placetype":"venue"
},
  "geometry": {"coordinates":[-86.109551,38.404247],"type":"Point"}
}