{
  "type": "Feature",
  "properties": {
    "iso:country":"US",
    "sg:address":"223 E Mcgalliard Rd",
    "sg:city":"Muncie",
    "sg:classifiers":[
        {
            "category":"Restaurant",
            "type":"Food & Drink"
        }
    ],
    "sg:menulink":"http://www.allmenus.com/in/muncie/174208-wendys/menu/",
    "sg:phone":"+1 765 284 3996",
    "sg:postcode":"47303",
    "sg:province":"IN",
    "sg:tags":[
        "burger",
        "american",
        "soup"
    ],
    "wof:name":"Wendy's",
    "wof:placetype":"venue"
},
  "geometry": {"coordinates":[-85.38525199999999,40.219001],"type":"Point"}
}