{
  "type": "Feature",
  "properties": {
    "iso:country":"US",
    "sg:address":"7195 E State Rd 14",
    "sg:city":"Columbia City",
    "sg:classifiers":[
        {
            "category":"Home & Garden",
            "subcategory":"Garden Supply",
            "type":"Retail Goods"
        }
    ],
    "sg:phone":"+1 260 749 1012",
    "sg:postcode":"46725",
    "sg:province":"IN",
    "sg:tags":[
        "nurseryman"
    ],
    "wof:name":"Saxton Group Inc",
    "wof:placetype":"venue"
},
  "geometry": {"coordinates":[-85.349064,41.07857],"type":"Point"}
}