{
  "type": "Feature",
  "properties": {
    "addr:full":"34 N Monroe St Williamsport IN 47993",
    "addr:housenumber":"34",
    "addr:postcode":"47993",
    "addr:street":"N Monroe St",
    "iso:country":"US",
    "sg:address":"34 N Monroe St",
    "sg:city":"Williamsport",
    "sg:classifiers":[
        {
            "category":"Insurance",
            "subcategory":"Insurance Agent",
            "type":"Services"
        }
    ],
    "sg:phone":"+1 765 762 2359",
    "sg:postcode":"47993",
    "sg:province":"IN",
    "wof:name":"Warren Agency Inc",
    "wof:placetype":"venue"
},
  "geometry": {"coordinates":[-87.29389999999999,40.286774],"type":"Point"}
}