{
  "type": "Feature",
  "properties": {
    "iso:country":"US",
    "sg:address":"505 S 21st St",
    "sg:city":"New Castle",
    "sg:classifiers":[
        {
            "category":"Personal",
            "subcategory":"Beauty Salon",
            "type":"Services"
        }
    ],
    "sg:phone":"+1 765 521 3000",
    "sg:postcode":"47362",
    "sg:province":"IN",
    "wof:name":"Bolden's Hair Ctr",
    "wof:placetype":"venue"
},
  "geometry": {"coordinates":[-85.359346,39.927481],"type":"Point"}
}