{
  "type": "Feature",
  "properties": {
    "iso:country":"US",
    "sg:address":"20380 Co Rd 14",
    "sg:city":"Bristol",
    "sg:classifiers":[
        {
            "category":"Professional",
            "type":"Services"
        }
    ],
    "sg:phone":"+1 574 294 4065",
    "sg:postcode":"46507",
    "sg:province":"IN",
    "wof:name":"Drive Capital Inc",
    "wof:placetype":"venue"
},
  "geometry": {"coordinates":[-85.855416,41.68161],"type":"Point"}
}