{
  "type": "Feature",
  "properties": {
    "iso:country":"US",
    "sg:address":"9473 N Co Rd 250 E",
    "sg:city":"Springport",
    "sg:classifiers":[
        {
            "category":"Shopping",
            "subcategory":"Computers & Home Electronics",
            "type":"Retail Goods"
        }
    ],
    "sg:phone":"+1 765 741 8369",
    "sg:postcode":"47386",
    "sg:province":"IN",
    "wof:name":"J Tech Computers",
    "wof:placetype":"venue"
},
  "geometry": {"coordinates":[-85.33763399999999,40.069882],"type":"Point"}
}