{
  "type": "Feature",
  "properties": {
    "iso:country":"US",
    "sg:address":"605 N Bell Ave",
    "sg:city":"Evansville",
    "sg:classifiers":[
        {
            "category":"Shopping",
            "subcategory":"Musical Instruments",
            "type":"Retail Goods"
        }
    ],
    "sg:phone":"+1 812 425 0374",
    "sg:postcode":"47712",
    "sg:province":"IN",
    "wof:name":"Pro Audio Svc",
    "wof:placetype":"venue"
},
  "geometry": {"coordinates":[-87.602656,37.984251],"type":"Point"}
}