{
  "type": "Feature",
  "properties": {
    "iso:country":"US",
    "sg:address":"9746 Lantern Rd",
    "sg:city":"Fishers",
    "sg:classifiers":[
        {
            "category":"Professional",
            "type":"Services"
        }
    ],
    "sg:phone":"+1 317 621 1300",
    "sg:postcode":"46037",
    "sg:province":"IN",
    "sg:tags":[
        "establishment"
    ],
    "wof:name":"Olio Rd Family Care",
    "wof:placetype":"venue"
},
  "geometry": {"coordinates":[-86.013711,39.928191],"type":"Point"}
}