{
  "type": "Feature",
  "properties": {
    "iso:country":"US",
    "sg:address":"298 N Boatman Rd",
    "sg:city":"Scottsburg",
    "sg:classifiers":[
        {
            "category":"Building & Trades",
            "subcategory":"Construction",
            "type":"Services"
        }
    ],
    "sg:phone":"+1 812 752 4865",
    "sg:postcode":"47170",
    "sg:province":"IN",
    "sg:tags":[
        "house"
    ],
    "wof:name":"Travis Lakins Constructio",
    "wof:placetype":"venue"
},
  "geometry": {"coordinates":[-85.813144,38.696568],"type":"Point"}
}