{
  "type": "Feature",
  "properties": {
    "iso:country":"US",
    "sg:address":"140 E Washington St",
    "sg:city":"Orleans",
    "sg:classifiers":[
        {
            "category":"Restaurant",
            "type":"Food & Drink"
        }
    ],
    "sg:phone":"+1 812 865 4100",
    "sg:postcode":"47452",
    "sg:province":"IN",
    "wof:name":"Hot Diggity Dog",
    "wof:placetype":"venue"
},
  "geometry": {"coordinates":[-86.452242,38.661701],"type":"Point"}
}