{
  "type": "Feature",
  "properties": {
    "iso:country":"US",
    "sg:address":"1339 W State Rd 2",
    "sg:city":"Laporte",
    "sg:classifiers":[
        {
            "category":"Health Services",
            "subcategory":"Doctor",
            "type":"Services"
        }
    ],
    "sg:phone":"+1 219 324 6112",
    "sg:postcode":"46350",
    "sg:province":"IN",
    "sg:tags":[
        "dentist"
    ],
    "wof:name":"Mark J Mihalo DDS",
    "wof:placetype":"venue"
},
  "geometry": {"coordinates":[-86.734372,41.600802],"type":"Point"}
}