{
  "type": "Feature",
  "properties": {
    "iso:country":"US",
    "sg:address":"16 Plz North Shopping Center",
    "sg:city":"Terre Haute",
    "sg:classifiers":[
        {
            "category":"Professional",
            "subcategory":"Management & Consulting",
            "type":"Services"
        }
    ],
    "sg:phone":"+1 812 261 1026",
    "sg:postcode":"47804",
    "sg:province":"IN",
    "sg:tags":[
        "logistics"
    ],
    "wof:name":"Dadc-M & B Logistics",
    "wof:placetype":"venue"
},
  "geometry": {"coordinates":[-87.387545,39.507023],"type":"Point"}
}