{
  "type": "Feature",
  "properties": {
    "iso:country":"US",
    "sg:address":"1065 Wissman Rd",
    "sg:city":"Georgetown",
    "sg:classifiers":[
        {
            "category":"Professional",
            "subcategory":"Business Services",
            "type":"Services"
        }
    ],
    "sg:phone":"+1 812 951 3529",
    "sg:postcode":"47122",
    "sg:province":"IN",
    "wof:name":"PSI Iota Xi",
    "wof:placetype":"venue"
},
  "geometry": {"coordinates":[-85.975585,38.291532],"type":"Point"}
}