{
  "type": "Feature",
  "properties": {
    "iso:country":"US",
    "sg:address":"1501 Keller St",
    "sg:city":"Evansville",
    "sg:classifiers":[
        {
            "category":"Manufacturing",
            "subcategory":"Metals",
            "type":"Manufacturing & Wholesale Goods"
        }
    ],
    "sg:phone":"+1 812 428 6624",
    "sg:postcode":"47710",
    "sg:province":"IN",
    "sg:tags":[
        "steel"
    ],
    "wof:name":"Structural Fabricators Inc",
    "wof:placetype":"venue"
},
  "geometry": {"coordinates":[-87.58636,37.996519],"type":"Point"}
}