{
  "type": "Feature",
  "properties": {
    "addr:full":"4220 Edison Lakes Pkwy Mishawaka IN 46545",
    "addr:housenumber":"4220",
    "addr:postcode":"46545",
    "addr:street":"Edison Lakes Pkwy",
    "iso:country":"US",
    "sg:address":"4220 Edison Lakes Pkwy",
    "sg:city":"Mishawaka",
    "sg:classifiers":[
        {
            "category":"Insurance",
            "subcategory":"Insurance Agent",
            "type":"Services"
        }
    ],
    "sg:phone":"+1 574 243 0710",
    "sg:postcode":"46545",
    "sg:province":"IN",
    "wof:name":"Westfield Companies",
    "wof:placetype":"venue"
},
  "geometry": {"coordinates":[-86.17613,41.698836],"type":"Point"}
}