{
  "type": "Feature",
  "properties": {
    "iso:country":"US",
    "sg:address":"2200 N Heidelbach Ave",
    "sg:city":"Evansville",
    "sg:classifiers":[
        {
            "category":"Building & Trades",
            "subcategory":"Plumbing",
            "type":"Services"
        }
    ],
    "sg:phone":"+1 812 424 0958",
    "sg:postcode":"47711",
    "sg:province":"IN",
    "sg:tags":[
        "plumbing",
        "contractor"
    ],
    "wof:name":"Clyde's Plumbing Svc",
    "wof:placetype":"venue"
},
  "geometry": {"coordinates":[-87.560803,37.998557],"type":"Point"}
}