{
  "type": "Feature",
  "properties": {
    "iso:country":"US",
    "sg:address":"3302 Stonegate Dr",
    "sg:city":"New Castle",
    "sg:classifiers":[
        {
            "category":"Real Estate",
            "subcategory":"Real Estate Operator",
            "type":"Services"
        }
    ],
    "sg:phone":"+1 765 529 2464",
    "sg:postcode":"47362",
    "sg:province":"IN",
    "sg:tags":[
        "apartment"
    ],
    "wof:name":"Stonegate Village",
    "wof:placetype":"venue"
},
  "geometry": {"coordinates":[-85.359114,39.900022],"type":"Point"}
}