{
  "type": "Feature",
  "properties": {
    "iso:country":"US",
    "sg:address":"2222 Bluff Rd",
    "sg:city":"Indianapolis",
    "sg:classifiers":[
        {
            "category":"Freight",
            "type":"Transportation"
        }
    ],
    "sg:phone":"+1 317 783 5416",
    "sg:postcode":"46225",
    "sg:province":"IN",
    "sg:tags":[
        "trucking"
    ],
    "wof:name":"George E Ellis Inc",
    "wof:placetype":"venue"
},
  "geometry": {"coordinates":[-86.164089,39.734975],"type":"Point"}
}