{
  "type": "Feature",
  "properties": {
    "iso:country":"US",
    "sg:address":"115 E Spring St",
    "sg:city":"New Albany",
    "sg:classifiers":[
        {
            "category":"Professional",
            "subcategory":"Lawyer & Legal Services",
            "type":"Services"
        }
    ],
    "sg:phone":"+1 812 945 5606",
    "sg:postcode":"47150",
    "sg:province":"IN",
    "sg:tags":[
        "attorney"
    ],
    "wof:name":"Gary D Allen",
    "wof:placetype":"venue"
},
  "geometry": {"coordinates":[-85.823584,38.285889],"type":"Point"}
}