{
  "type": "Feature",
  "properties": {
    "iso:country":"US",
    "sg:address":"410 N 13th St",
    "sg:city":"Lafayette",
    "sg:classifiers":[
        {
            "category":"Building & Trades",
            "subcategory":"Construction",
            "type":"Services"
        }
    ],
    "sg:phone":"+1 765 742 2612",
    "sg:postcode":"47904",
    "sg:province":"IN",
    "sg:tags":[
        "roofing",
        "contractor"
    ],
    "wof:name":"Schafer Roofing Co",
    "wof:placetype":"venue"
},
  "geometry": {"coordinates":[-86.883184,40.421789],"type":"Point"}
}