{
  "type": "Feature",
  "properties": {
    "iso:country":"US",
    "sg:address":"10100 Harrison Rd",
    "sg:city":"Osceola",
    "sg:classifiers":[
        {
            "category":"Building & Trades",
            "subcategory":"Construction",
            "type":"Services"
        }
    ],
    "sg:phone":"+1 574 674 8746",
    "sg:postcode":"46561",
    "sg:province":"IN",
    "sg:tags":[
        "water",
        "well",
        "drilling"
    ],
    "wof:name":"Taber's Pump & Well Svc Inc",
    "wof:placetype":"venue"
},
  "geometry": {"coordinates":[-86.061195,41.650651],"type":"Point"}
}