{
  "type": "Feature",
  "properties": {
    "iso:country":"US",
    "sg:address":"1474 Industrial Dr",
    "sg:city":"Lafayette",
    "sg:classifiers":[
        {
            "category":"Wholesale",
            "subcategory":"Hardware",
            "type":"Manufacturing & Wholesale Goods"
        }
    ],
    "sg:phone":"+1 765 448 6858",
    "sg:postcode":"47905",
    "sg:province":"IN",
    "sg:tags":[
        "plumbing",
        "fixture",
        "supply"
    ],
    "wof:name":"L Robbins & Assoc",
    "wof:placetype":"venue"
},
  "geometry": {"coordinates":[-86.851493,40.403138],"type":"Point"}
}