{
  "type": "Feature",
  "properties": {
    "iso:country":"US",
    "sg:address":"1100 Prairie Ave",
    "sg:city":"South Bend",
    "sg:classifiers":[
        {
            "category":"Wholesale",
            "subcategory":"Metals & Minerals",
            "type":"Manufacturing & Wholesale Goods"
        }
    ],
    "sg:phone":"+1 574 282 2323",
    "sg:postcode":"46601",
    "sg:province":"IN",
    "sg:tags":[
        "pipe"
    ],
    "wof:name":"Underground Pipes & Valves",
    "wof:placetype":"venue"
},
  "geometry": {"coordinates":[-86.262736,41.661546],"type":"Point"}
}