{
  "type": "Feature",
  "properties": {
    "iso:country":"US",
    "sg:address":"525 N 4th St",
    "sg:city":"Vincennes",
    "sg:classifiers":[
        {
            "category":"Government",
            "subcategory":"Office",
            "type":"Public Place"
        }
    ],
    "sg:phone":"+1 812 882 1353",
    "sg:postcode":"47591",
    "sg:province":"IN",
    "sg:tags":[
        "village"
    ],
    "wof:name":"Vincennes Neighborhood Fclts",
    "wof:placetype":"venue"
},
  "geometry": {"coordinates":[-87.525628,38.681512],"type":"Point"}
}