{
  "type": "Feature",
  "properties": {
    "iso:country":"US",
    "sg:address":"1512 Tipton Ln",
    "sg:city":"Columbus",
    "sg:classifiers":[
        {
            "category":"Professional",
            "subcategory":"Business Services",
            "type":"Services"
        }
    ],
    "sg:phone":"+1 812 376 6364",
    "sg:postcode":"47201",
    "sg:province":"IN",
    "sg:tags":[
        "paper"
    ],
    "wof:name":"Speedy Shred",
    "wof:placetype":"venue"
},
  "geometry": {"coordinates":[-85.908112,39.229793],"type":"Point"}
}