{
  "type": "Feature",
  "properties": {
    "iso:country":"US",
    "sg:address":"7372 Deerfield Dr",
    "sg:city":"Greenfield",
    "sg:classifiers":[
        {
            "category":"Building & Trades",
            "subcategory":"Plumbing",
            "type":"Services"
        }
    ],
    "sg:phone":"+1 317 891 8997",
    "sg:postcode":"46140",
    "sg:province":"IN",
    "sg:tags":[
        "contractor"
    ],
    "wof:name":"J B Enterprises",
    "wof:placetype":"venue"
},
  "geometry": {"coordinates":[-85.943465,39.825332],"type":"Point"}
}