{
  "type": "Feature",
  "properties": {
    "iso:country":"US",
    "sg:address":"2709 Winch St",
    "sg:city":"Fort Wayne",
    "sg:classifiers":[
        {
            "category":"Retail",
            "subcategory":"Repair Shop",
            "type":"Services"
        }
    ],
    "sg:phone":"+1 260 422 4072",
    "sg:postcode":"46803",
    "sg:province":"IN",
    "wof:name":"K & W Cleaning Inc",
    "wof:placetype":"venue"
},
  "geometry": {"coordinates":[-85.10191500000001,41.074906],"type":"Point"}
}