{
  "type": "Feature",
  "properties": {
    "iso:country":"US",
    "sg:address":"66 N Van Buren St",
    "sg:city":"Nashville",
    "sg:classifiers":[
        {
            "category":"Home & Garden",
            "subcategory":"Furniture",
            "type":"Retail Goods"
        }
    ],
    "sg:phone":"+1 812 988 6855",
    "sg:postcode":"47448",
    "sg:province":"IN",
    "sg:website":"www.thealleyshop.com",
    "wof:name":"Alley Shoppe",
    "wof:placetype":"venue"
},
  "geometry": {"coordinates":[-86.246869,39.207972],"type":"Point"}
}