{
  "type": "Feature",
  "properties": {
    "iso:country":"US",
    "sg:address":"62 S Sycamore St",
    "sg:city":"Spencer",
    "sg:classifiers":[
        {
            "category":"Manufacturing",
            "subcategory":"Metals",
            "type":"Manufacturing & Wholesale Goods"
        }
    ],
    "sg:phone":"+1 812 829 6575",
    "sg:postcode":"47460",
    "sg:province":"IN",
    "sg:tags":[
        "fabricator",
        "sheet"
    ],
    "wof:name":"Jeffers & Sons Sheet Metal",
    "wof:placetype":"venue"
},
  "geometry": {"coordinates":[-86.76648299999999,39.286161],"type":"Point"}
}