{
  "type": "Feature",
  "properties": {
    "iso:country":"US",
    "sg:address":"1200 Sheffield Ave",
    "sg:city":"Dyer",
    "sg:classifiers":[
        {
            "category":"Shopping",
            "subcategory":"Department Store",
            "type":"Retail Goods"
        }
    ],
    "sg:phone":"+1 219 865 1913",
    "sg:postcode":"46311",
    "sg:province":"IN",
    "sg:tags":[
        "shop"
    ],
    "wof:name":"Dollar Central",
    "wof:placetype":"venue"
},
  "geometry": {"coordinates":[-87.51877399999999,41.508148],"type":"Point"}
}