{
  "type": "Feature",
  "properties": {
    "iso:country":"US",
    "sg:address":"6839 W Isanogel Rd",
    "sg:city":"Muncie",
    "sg:classifiers":[
        {
            "category":"Farming",
            "subcategory":"Livestock Farm",
            "type":"Manufacturing & Wholesale Goods"
        }
    ],
    "sg:phone":"+1 765 288 3558",
    "sg:postcode":"47304",
    "sg:province":"IN",
    "sg:tags":[
        "equine",
        "animal"
    ],
    "wof:name":"Raintree Morgans",
    "wof:placetype":"venue"
},
  "geometry": {"coordinates":[-85.466107,40.20025],"type":"Point"}
}