{
  "type": "Feature",
  "properties": {
    "addr:full":"800 Saint Marys Dr Evansville IN 47714",
    "addr:housenumber":"800",
    "addr:postcode":"47714",
    "addr:street":"Saint Marys Dr",
    "iso:country":"US",
    "sg:address":"800 Saint Marys Dr",
    "sg:city":"Evansville",
    "sg:classifiers":[
        {
            "category":"Professional",
            "subcategory":"Research",
            "type":"Services"
        }
    ],
    "sg:phone":"+1 812 474 6530",
    "sg:postcode":"47714",
    "sg:province":"IN",
    "sg:tags":[
        "medical"
    ],
    "wof:name":"West Pharmaceutical Svc",
    "wof:placetype":"venue"
},
  "geometry": {"coordinates":[-87.50297,37.965052],"type":"Point"}
}