{
  "type": "Feature",
  "properties": {
    "iso:country":"US",
    "sg:address":"200 W Maple St",
    "sg:city":"Cayuga",
    "sg:phone":"+1 765 492 3660",
    "sg:postcode":"47928",
    "sg:province":"IN",
    "sg:tags":[
        "equipment",
        "station"
    ],
    "sg:website":"www.fabstar.com",
    "wof:name":"Fabstar",
    "wof:placetype":"venue"
},
  "geometry": {"coordinates":[-87.46291600000001,39.945513],"type":"Point"}
}