{
  "type": "Feature",
  "properties": {
    "iso:country":"US",
    "sg:address":"2524 E National Hwy",
    "sg:city":"Washington",
    "sg:classifiers":[
        {
            "category":"Government",
            "subcategory":"Office",
            "type":"Public Place"
        }
    ],
    "sg:phone":"+1 812 254 4780",
    "sg:postcode":"47501",
    "sg:province":"IN",
    "wof:name":"Daviess County Agriculture",
    "wof:placetype":"venue"
},
  "geometry": {"coordinates":[-87.13167300000001,38.655311],"type":"Point"}
}