{
  "type": "Feature",
  "properties": {
    "addr:full":"770 Andico Rd Plainfield IN 46168",
    "addr:housenumber":"770",
    "addr:postcode":"46168",
    "addr:street":"Andico Rd",
    "iso:country":"US",
    "sg:address":"770 Andico Rd",
    "sg:city":"Plainfield",
    "sg:classifiers":[
        {
            "category":"Manufacturing",
            "subcategory":"Rubber & Plastics",
            "type":"Manufacturing & Wholesale Goods"
        }
    ],
    "sg:phone":"+1 317 837 1101",
    "sg:postcode":"46168",
    "sg:province":"IN",
    "sg:tags":[
        "plastics-vacuum",
        "plastics-fabricating",
        "plastics-molders",
        "pressure",
        "forming-manufacturers",
        "finishing",
        "decorating"
    ],
    "sg:website":"http://www.integrityrotational.com",
    "wof:name":"Integrity Rotational Molding",
    "wof:placetype":"venue"
},
  "geometry": {"coordinates":[-86.391521,39.713959],"type":"Point"}
}