{
  "type": "Feature",
  "properties": {
    "addr:full":"190 Twin Springs Ct Carmel IN 46033",
    "addr:housenumber":"190",
    "addr:postcode":"46033",
    "addr:street":"Twin Springs Ct",
    "iso:country":"US",
    "sg:address":"190 Twin Springs Ct",
    "sg:city":"Carmel",
    "sg:classifiers":[
        {
            "category":"Professional",
            "type":"Services"
        }
    ],
    "sg:phone":"+1 317 844 9754",
    "sg:postcode":"46033",
    "sg:province":"IN",
    "wof:name":"Royal River Co Inc",
    "wof:placetype":"venue"
},
  "geometry": {"coordinates":[-86.100604,39.955606],"type":"Point"}
}