{
  "type": "Feature",
  "properties": {
    "iso:country":"US",
    "sg:address":"155 S Calumet Rd",
    "sg:city":"Chesterton",
    "sg:classifiers":[
        {
            "category":"Insurance",
            "subcategory":"Insurance Agent",
            "type":"Services"
        }
    ],
    "sg:phone":"+1 219 926 8681",
    "sg:postcode":"46304",
    "sg:province":"IN",
    "sg:website":"www.antoninsurance.com",
    "wof:name":"Anton Insurance Inc",
    "wof:placetype":"venue"
},
  "geometry": {"coordinates":[-87.052075,41.610183],"type":"Point"}
}