{
  "type": "Feature",
  "properties": {
    "iso:country":"US",
    "sg:address":"615 W 64th St",
    "sg:city":"Indianapolis",
    "sg:classifiers":[
        {
            "category":"Education",
            "subcategory":"School",
            "type":"Public Place"
        }
    ],
    "sg:phone":"+1 317 255 1631",
    "sg:postcode":"46260",
    "sg:province":"IN",
    "wof:name":"Indiana Japanese Language Schl",
    "wof:placetype":"venue"
},
  "geometry": {"coordinates":[-86.174033,39.871916],"type":"Point"}
}