{
  "type": "Feature",
  "properties": {
    "iso:country":"US",
    "sg:address":"5144 Hunter Rd",
    "sg:city":"Newburgh",
    "sg:classifiers":[
        {
            "category":"Building & Trades",
            "subcategory":"Construction",
            "type":"Services"
        }
    ],
    "sg:phone":"+1 812 455 5336",
    "sg:postcode":"47601",
    "sg:province":"IN",
    "sg:tags":[
        "excavating",
        "contractor"
    ],
    "wof:name":"Ryan's Excavating",
    "wof:placetype":"venue"
},
  "geometry": {"coordinates":[-87.33926099999999,38.019702],"type":"Point"}
}