{
  "type": "Feature",
  "properties": {
    "iso:country":"US",
    "sg:address":"2950 Covert Ave",
    "sg:city":"Evansville",
    "sg:classifiers":[
        {
            "category":"Fast Food",
            "type":"Food & Drink"
        },
        {
            "category":"Restaurant",
            "type":"Food & Drink"
        }
    ],
    "sg:phone":"+1 812 473 1122",
    "sg:postcode":"47714",
    "sg:province":"IN",
    "sg:tags":[
        "italian",
        "pizza"
    ],
    "wof:name":"Una Pizza Covert",
    "wof:placetype":"venue"
},
  "geometry": {"coordinates":[-87.513611,37.955098],"type":"Point"}
}