{
  "type": "Feature",
  "properties": {
    "iso:country":"US",
    "sg:address":"105 W Liberty St",
    "sg:city":"North Liberty",
    "sg:classifiers":[
        {
            "category":"Education",
            "subcategory":"Library",
            "type":"Public Place"
        }
    ],
    "sg:phone":"+1 574 656 3664",
    "sg:postcode":"46554",
    "sg:province":"IN",
    "wof:name":"North Liberty Library",
    "wof:placetype":"venue"
},
  "geometry": {"coordinates":[-86.428087,41.529535],"type":"Point"}
}