{
  "type": "Feature",
  "properties": {
    "iso:country":"US",
    "sg:address":"1404 119th St",
    "sg:city":"Whiting",
    "sg:classifiers":[
        {
            "category":"Professional",
            "subcategory":"Research",
            "type":"Services"
        }
    ],
    "sg:phone":"+1 219 473 0600",
    "sg:postcode":"46394",
    "sg:province":"IN",
    "sg:tags":[
        "environmental",
        "ecological"
    ],
    "sg:website":"www.keter.com",
    "wof:name":"Keter Consultants Inc",
    "wof:placetype":"venue"
},
  "geometry": {"coordinates":[-87.494628,41.679304],"type":"Point"}
}