{
  "type": "Feature",
  "properties": {
    "iso:country":"US",
    "sg:address":"14638 Michigan Rd",
    "sg:city":"Argos",
    "sg:classifiers":[
        {
            "category":"Building & Trades",
            "subcategory":"Plumbing",
            "type":"Services"
        }
    ],
    "sg:phone":"+1 574 892 5119",
    "sg:postcode":"46501",
    "sg:province":"IN",
    "sg:tags":[
        "heating",
        "contractor"
    ],
    "wof:name":"Thacker A/C-Ref-Heating Inc",
    "wof:placetype":"venue"
},
  "geometry": {"coordinates":[-86.258284,41.26445],"type":"Point"}
}