{
  "type": "Feature",
  "properties": {
    "addr:full":"353 Gentlemen Pl Cloverdale IN 46120",
    "addr:housenumber":"353",
    "addr:postcode":"46120",
    "addr:street":"Gentlemen Pl",
    "iso:country":"US",
    "sg:address":"353 Gentlemen Pl",
    "sg:city":"Cloverdale",
    "sg:classifiers":[
        {
            "category":"Building & Trades",
            "subcategory":"Construction",
            "type":"Services"
        }
    ],
    "sg:phone":"+1 765 795 4967",
    "sg:postcode":"46120",
    "sg:province":"IN",
    "sg:tags":[
        "carpentry",
        "contractor"
    ],
    "wof:name":"Rogers & Lockwood Inc",
    "wof:placetype":"venue"
},
  "geometry": {"coordinates":[-86.814216,39.520475],"type":"Point"}
}