{
  "type": "Feature",
  "properties": {
    "iso:country":"US",
    "sg:address":"2115 E 3rd St",
    "sg:city":"Bloomington",
    "sg:classifiers":[
        {
            "category":"Social Services",
            "type":"Services"
        }
    ],
    "sg:phone":"+1 812 339 6362",
    "sg:postcode":"47401",
    "sg:province":"IN",
    "sg:tags":[
        "counselor",
        "marriage",
        "family"
    ],
    "wof:name":"Judy L Malschick",
    "wof:placetype":"venue"
},
  "geometry": {"coordinates":[-86.50843,39.164336],"type":"Point"}
}