{
  "type": "Feature",
  "properties": {
    "iso:country":"US",
    "sg:address":"1859 Harrison Blvd",
    "sg:city":"Valparaiso",
    "sg:classifiers":[
        {
            "category":"Shopping",
            "subcategory":"Clothing, Apparel, & Fashions",
            "type":"Retail Goods"
        }
    ],
    "sg:phone":"+1 219 531 5474",
    "sg:postcode":"46385",
    "sg:province":"IN",
    "wof:name":"St Paul Clothing Ctr",
    "wof:placetype":"venue"
},
  "geometry": {"coordinates":[-87.083322,41.484582],"type":"Point"}
}