{
  "type": "Feature",
  "properties": {
    "iso:country":"US",
    "sg:address":"6550 Guion Rd",
    "sg:city":"Indianapolis",
    "sg:classifiers":[
        {
            "category":"Shopping",
            "subcategory":"Stationery & Office Supplies",
            "type":"Retail Goods"
        }
    ],
    "sg:phone":"+1 317 284 0070",
    "sg:postcode":"46254",
    "sg:province":"IN",
    "wof:name":"Semaphore Investigations",
    "wof:placetype":"venue"
},
  "geometry": {"coordinates":[-86.231623,39.872656],"type":"Point"}
}