{
  "type": "Feature",
  "properties": {
    "iso:country":"US",
    "sg:address":"5700 N 50 W",
    "sg:city":"West Lafayette",
    "sg:classifiers":[
        {
            "category":"Education",
            "subcategory":"School",
            "type":"Public Place"
        }
    ],
    "sg:phone":"+1 765 463 2237",
    "sg:postcode":"47906",
    "sg:province":"IN",
    "wof:name":"Burnett Creek Elementary Schl",
    "wof:placetype":"venue"
},
  "geometry": {"coordinates":[-86.915983,40.500535],"type":"Point"}
}