{
  "type": "Feature",
  "properties": {
    "iso:country":"US",
    "sg:address":"1141 N Salem Rd",
    "sg:city":"Decatur",
    "sg:classifiers":[
        {
            "category":"Real Estate",
            "subcategory":"Real Estate Operator",
            "type":"Services"
        }
    ],
    "sg:phone":"+1 260 592 7558",
    "sg:postcode":"46733",
    "sg:province":"IN",
    "sg:tags":[
        "property",
        "lessor"
    ],
    "wof:name":"Don Riley",
    "wof:placetype":"venue"
},
  "geometry": {"coordinates":[-84.86058,40.765769],"type":"Point"}
}