{
  "type": "Feature",
  "properties": {
    "iso:country":"US",
    "sg:address":"1604 Cottage Ave",
    "sg:city":"Columbus",
    "sg:classifiers":[
        {
            "category":"Building & Trades",
            "subcategory":"Construction",
            "type":"Services"
        }
    ],
    "sg:phone":"+1 812 372 3791",
    "sg:postcode":"47201",
    "sg:province":"IN",
    "sg:tags":[
        "general",
        "contractor"
    ],
    "wof:name":"Repp & Mundt Inc",
    "wof:placetype":"venue"
},
  "geometry": {"coordinates":[-85.905457,39.215034],"type":"Point"}
}