{
  "type": "Feature",
  "properties": {
    "iso:country":"US",
    "sg:address":"8643 Louisiana Pl",
    "sg:city":"Merrillville",
    "sg:classifiers":[
        {
            "category":"Wholesale",
            "subcategory":"Non-durable Goods",
            "type":"Manufacturing & Wholesale Goods"
        }
    ],
    "sg:phone":"+1 219 738 2398",
    "sg:postcode":"46410",
    "sg:province":"IN",
    "sg:tags":[
        "advertising"
    ],
    "wof:name":"First Impressions",
    "wof:placetype":"venue"
},
  "geometry": {"coordinates":[-87.31992700000001,41.460871],"type":"Point"}
}