{
  "type": "Feature",
  "properties": {
    "iso:country":"US",
    "sg:address":"19 Hillcrest Cir",
    "sg:city":"Bedford",
    "sg:classifiers":[
        {
            "category":"Restaurant",
            "type":"Food & Drink"
        }
    ],
    "sg:phone":"+1 812 277 8977",
    "sg:postcode":"47421",
    "sg:province":"IN",
    "wof:name":"Churb's Cafe",
    "wof:placetype":"venue"
},
  "geometry": {"coordinates":[-86.505913,38.831959],"type":"Point"}
}