{
  "type": "Feature",
  "properties": {
    "iso:country":"US",
    "sg:address":"7616 Posey Ln",
    "sg:city":"Lafayette",
    "sg:classifiers":[
        {
            "category":"Wholesale",
            "subcategory":"Electrical",
            "type":"Manufacturing & Wholesale Goods"
        }
    ],
    "sg:phone":"+1 765 296 9500",
    "sg:postcode":"47905",
    "sg:province":"IN",
    "sg:tags":[
        "communication",
        "radio",
        "system"
    ],
    "sg:website":"www.acdc.net",
    "wof:name":"Advanced Communication Inc",
    "wof:placetype":"venue"
},
  "geometry": {"coordinates":[-86.760553,40.412378],"type":"Point"}
}