{
  "type": "Feature",
  "properties": {
    "iso:country":"US",
    "sg:address":"1359 Canterbury Ct",
    "sg:city":"Dyer",
    "sg:classifiers":[
        {
            "category":"Retail",
            "subcategory":"Repair Shop",
            "type":"Services"
        }
    ],
    "sg:phone":"+1 219 865 0436",
    "sg:postcode":"46311",
    "sg:province":"IN",
    "sg:tags":[
        "equipment",
        "electrical",
        "system",
        "telephone"
    ],
    "wof:name":"Suburban Wire Inc",
    "wof:placetype":"venue"
},
  "geometry": {"coordinates":[-87.497388,41.479722],"type":"Point"}
}