{
  "type": "Feature",
  "properties": {
    "iso:country":"US",
    "sg:address":"4410 Pembroke Ln",
    "sg:city":"Fort Wayne",
    "sg:classifiers":[
        {
            "category":"Manufacturing",
            "subcategory":"Apparel",
            "type":"Manufacturing & Wholesale Goods"
        }
    ],
    "sg:phone":"+1 260 744 5447",
    "sg:postcode":"46807",
    "sg:province":"IN",
    "sg:tags":[
        "mfg",
        "accessory"
    ],
    "wof:name":"Latida",
    "wof:placetype":"venue"
},
  "geometry": {"coordinates":[-85.15006,41.044169],"type":"Point"}
}