{
  "type": "Feature",
  "properties": {
    "addr:full":"7100 W 15th Ave Gary IN 46406",
    "addr:housenumber":"7100",
    "addr:postcode":"46406",
    "addr:street":"W 15Th Ave",
    "iso:country":"US",
    "sg:address":"7100 W 15th Ave",
    "sg:city":"Gary",
    "sg:classifiers":[
        {
            "category":"Wholesale",
            "subcategory":"Auto Parts",
            "type":"Manufacturing & Wholesale Goods"
        }
    ],
    "sg:phone":"+1 219 944 3233",
    "sg:postcode":"46406",
    "sg:province":"IN",
    "sg:tags":[
        "automobile",
        "rebuilt"
    ],
    "wof:name":"Rick's Auto Salvage",
    "wof:placetype":"venue"
},
  "geometry": {"coordinates":[-87.422978,41.588063],"type":"Point"}
}