{
  "type": "Feature",
  "properties": {
    "iso:country":"US",
    "sg:address":"478 N 1100 E",
    "sg:city":"Zionsville",
    "sg:classifiers":[
        {
            "category":"Building & Trades",
            "subcategory":"Construction",
            "type":"Services"
        }
    ],
    "sg:phone":"+1 317 769 4777",
    "sg:postcode":"46077",
    "sg:province":"IN",
    "sg:tags":[
        "underground",
        "wire",
        "laying",
        "cable"
    ],
    "wof:name":"Telecom Placement Inc",
    "wof:placetype":"venue"
},
  "geometry": {"coordinates":[-86.260511,40.047785],"type":"Point"}
}