{
  "type": "Feature",
  "properties": {
    "addr:full":"11760 NE Executive Dr Edinburgh IN 46124",
    "addr:housenumber":"11760",
    "addr:postcode":"46124",
    "addr:street":"Ne Executive Dr",
    "iso:country":"US",
    "sg:address":"11760 NE Executive Dr",
    "sg:city":"Edinburgh",
    "sg:classifiers":[
        {
            "category":"Shopping",
            "subcategory":"Books",
            "type":"Retail Goods"
        }
    ],
    "sg:phone":"+1 812 526 9860",
    "sg:postcode":"46124",
    "sg:province":"IN",
    "sg:tags":[
        "dealer"
    ],
    "wof:name":"Bible Factory Outlet",
    "wof:placetype":"venue"
},
  "geometry": {"coordinates":[-85.96196,39.312179],"type":"Point"}
}