{
  "type": "Feature",
  "properties": {
    "iso:country":"US",
    "sg:address":"1804 N Wheeling Ave",
    "sg:city":"Muncie",
    "sg:classifiers":[
        {
            "category":"Social Services",
            "type":"Services"
        }
    ],
    "sg:phone":"+1 765 289 1631",
    "sg:postcode":"47303",
    "sg:province":"IN",
    "sg:tags":[
        "counselor",
        "marriage",
        "family"
    ],
    "wof:name":"Christian Counseling Svc",
    "wof:placetype":"venue"
},
  "geometry": {"coordinates":[-85.397363,40.209785],"type":"Point"}
}