{
  "type": "Feature",
  "properties": {
    "iso:country":"US",
    "sg:address":"701 W Jefferson Blvd",
    "sg:city":"Mishawaka",
    "sg:classifiers":[
        {
            "category":"Building & Trades",
            "subcategory":"Construction",
            "type":"Services"
        }
    ],
    "sg:phone":"+1 574 254 0018",
    "sg:postcode":"46545",
    "sg:province":"IN",
    "sg:tags":[
        "home",
        "builder"
    ],
    "wof:name":"Wagner Homes",
    "wof:placetype":"venue"
},
  "geometry": {"coordinates":[-86.19188800000001,41.673035],"type":"Point"}
}