{
  "type": "Feature",
  "properties": {
    "iso:country":"US",
    "sg:address":"301 W 40th Ave",
    "sg:city":"Gary",
    "sg:classifiers":[
        {
            "category":"Retail",
            "subcategory":"Auto Repair",
            "type":"Services"
        }
    ],
    "sg:phone":"+1 219 884 7884",
    "sg:postcode":"46408",
    "sg:province":"IN",
    "sg:tags":[
        "body",
        "automobile",
        "painting"
    ],
    "wof:name":"Rich's Body Shop",
    "wof:placetype":"venue"
},
  "geometry": {"coordinates":[-87.341239,41.54586],"type":"Point"}
}