{
  "type": "Feature",
  "properties": {
    "iso:country":"US",
    "sg:address":"2300 W Main St",
    "sg:city":"Richmond",
    "sg:classifiers":[
        {
            "category":"Social Services",
            "type":"Services"
        }
    ],
    "sg:phone":"+1 765 935 3116",
    "sg:postcode":"47374",
    "sg:province":"IN",
    "sg:tags":[
        "counselor",
        "marriage",
        "family"
    ],
    "wof:name":"Lutheran Counseling Ctr",
    "wof:placetype":"venue"
},
  "geometry": {"coordinates":[-84.931793,39.829308],"type":"Point"}
}