{
  "type": "Feature",
  "properties": {
    "iso:country":"US",
    "sg:address":"1165 S Creasy Ln",
    "sg:city":"Lafayette",
    "sg:classifiers":[
        {
            "category":"Shopping",
            "type":"Retail Goods"
        }
    ],
    "sg:phone":"+1 765 448 6434",
    "sg:postcode":"47905",
    "sg:province":"IN",
    "sg:tags":[
        "church",
        "supply"
    ],
    "sg:website":"www.carpentersson.com",
    "wof:name":"Carpenter's Son",
    "wof:placetype":"venue"
},
  "geometry": {"coordinates":[-86.838461,40.39348],"type":"Point"}
}