{
  "type": "Feature",
  "properties": {
    "iso:country":"US",
    "sg:address":"12400 N Co Rd 900 W",
    "sg:city":"Gaston",
    "sg:classifiers":[
        {
            "category":"Farming",
            "subcategory":"Farm",
            "type":"Manufacturing & Wholesale Goods"
        }
    ],
    "sg:phone":"+1 765 358 3745",
    "sg:postcode":"47342",
    "sg:province":"IN",
    "sg:tags":[
        "crop",
        "general"
    ],
    "wof:name":"Robert Dewees",
    "wof:placetype":"venue"
},
  "geometry": {"coordinates":[-85.557912,40.298029],"type":"Point"}
}