{
  "type": "Feature",
  "properties": {
    "iso:country":"US",
    "sg:address":"1930 Broadway",
    "sg:city":"Fort Wayne",
    "sg:classifiers":[
        {
            "category":"Shopping",
            "subcategory":"Used Merchandise",
            "type":"Retail Goods"
        }
    ],
    "sg:phone":"+1 260 426 6722",
    "sg:postcode":"46802",
    "sg:province":"IN",
    "sg:tags":[
        "pawnbroker"
    ],
    "wof:name":"Broadway Loan Co",
    "wof:placetype":"venue"
},
  "geometry": {"coordinates":[-85.152245,41.068023],"type":"Point"}
}