{
  "type": "Feature",
  "properties": {
    "iso:country":"US",
    "sg:address":"205 Tilden Ave",
    "sg:city":"Michigan City",
    "sg:classifiers":[
        {
            "category":"Home & Garden",
            "subcategory":"Furniture",
            "type":"Retail Goods"
        }
    ],
    "sg:phone":"+1 219 878 9914",
    "sg:postcode":"46360",
    "sg:province":"IN",
    "sg:tags":[
        "equipment",
        "kitchen",
        "cabinet"
    ],
    "wof:name":"A A Custom Cabinets & Counter",
    "wof:placetype":"venue"
},
  "geometry": {"coordinates":[-86.886729,41.702398],"type":"Point"}
}