{
  "type": "Feature",
  "properties": {
    "iso:country":"US",
    "sg:address":"224 E Commercial Ave",
    "sg:city":"Lowell",
    "sg:classifiers":[
        {
            "category":"Retail",
            "subcategory":"Portrait Studio",
            "type":"Services"
        }
    ],
    "sg:phone":"+1 219 696 6768",
    "sg:postcode":"46356",
    "sg:province":"IN",
    "sg:tags":[
        "photographer"
    ],
    "wof:name":"Hefner Photography",
    "wof:placetype":"venue"
},
  "geometry": {"coordinates":[-87.421179,41.291288],"type":"Point"}
}