{
  "type": "Feature",
  "properties": {
    "iso:country":"US",
    "sg:address":"2303 Thorndale Ct",
    "sg:city":"Elkhart",
    "sg:classifiers":[
        {
            "category":"Organizations",
            "subcategory":"Community Association",
            "type":"Services"
        }
    ],
    "sg:phone":"+1 574 293 7476",
    "sg:postcode":"46517",
    "sg:province":"IN",
    "wof:name":"Delta Theta Tau Sorority",
    "wof:placetype":"venue"
},
  "geometry": {"coordinates":[-85.967788,41.664671],"type":"Point"}
}