{
  "type": "Feature",
  "properties": {
    "addr:full":"984 Logan St Noblesville IN 46060",
    "addr:housenumber":"984",
    "addr:postcode":"46060",
    "addr:street":"Logan St",
    "iso:country":"US",
    "sg:address":"984 Logan St",
    "sg:city":"Noblesville",
    "sg:classifiers":[
        {
            "category":"Professional",
            "subcategory":"Business Services",
            "type":"Services"
        }
    ],
    "sg:phone":"+1 317 776 3115",
    "sg:postcode":"46060",
    "sg:province":"IN",
    "sg:tags":[
        "interior",
        "consultant",
        "design",
        "decorator"
    ],
    "wof:name":"Signature Decor",
    "wof:placetype":"venue"
},
  "geometry": {"coordinates":[-86.012674,40.04663],"type":"Point"}
}