{
  "type": "Feature",
  "properties": {
    "addr:full":"1135 Broadway Fort Wayne IN 46802",
    "addr:housenumber":"1135",
    "addr:postcode":"46802",
    "addr:street":"Broadway",
    "iso:country":"US",
    "sg:address":"1135 Broadway",
    "sg:city":"Fort Wayne",
    "sg:classifiers":[
        {
            "category":"Shopping",
            "subcategory":"Used Merchandise",
            "type":"Retail Goods"
        }
    ],
    "sg:phone":"+1 260 426 5423",
    "sg:postcode":"46802",
    "sg:province":"IN",
    "wof:name":"Lemaster Antique",
    "wof:placetype":"venue"
},
  "geometry": {"coordinates":[-85.147756,41.073883],"type":"Point"}
}