{
  "type": "Feature",
  "properties": {
    "iso:country":"US",
    "sg:address":"375 W Cleveland Rd",
    "sg:city":"Granger",
    "sg:classifiers":[
        {
            "category":"Real Estate",
            "subcategory":"Developer",
            "type":"Services"
        }
    ],
    "sg:phone":"+1 574 272 6971",
    "sg:postcode":"46530",
    "sg:province":"IN",
    "sg:tags":[
        "cemetery"
    ],
    "wof:name":"St Joseph Valley Memorial Park",
    "wof:placetype":"venue"
},
  "geometry": {"coordinates":[-86.18543099999999,41.723904],"type":"Point"}
}