{
  "type": "Feature",
  "properties": {
    "addr:full":"50571 State Rd 13 Middlebury IN 46540",
    "addr:housenumber":"50571;13",
    "addr:postcode":"46540",
    "addr:street":"State Rd",
    "iso:country":"US",
    "sg:address":"50571 State Rd 13",
    "sg:city":"Middlebury",
    "sg:classifiers":[
        {
            "category":"Shopping",
            "type":"Retail Goods"
        }
    ],
    "sg:phone":"+1 574 825 9607",
    "sg:postcode":"46540",
    "sg:province":"IN",
    "sg:tags":[
        "equipment",
        "irrigation",
        "system"
    ],
    "sg:website":"www.maisco.net",
    "wof:name":"MAISCO",
    "wof:placetype":"venue"
},
  "geometry": {"coordinates":[-85.67776499999999,41.758269],"type":"Point"}
}