{
  "type": "Feature",
  "properties": {
    "iso:country":"US",
    "sg:address":"732 S Allen Chapel Rd",
    "sg:city":"Kendallville",
    "sg:classifiers":[
        {
            "category":"Museum",
            "type":"Entertainment"
        }
    ],
    "sg:phone":"+1 260 347 2334",
    "sg:postcode":"46755",
    "sg:province":"IN",
    "sg:website":"www.midamericawindmillmuseum.com",
    "wof:name":"Mid-America Windmill Museum",
    "wof:placetype":"venue"
},
  "geometry": {"coordinates":[-85.232214,41.435458],"type":"Point"}
}