{
  "type": "Feature",
  "properties": {
    "iso:country":"US",
    "sg:address":"3390 Elizabeth St",
    "sg:city":"Columbus",
    "sg:classifiers":[
        {
            "category":"Professional",
            "subcategory":"Art Services",
            "type":"Services"
        }
    ],
    "sg:phone":"+1 812 372 8220",
    "sg:postcode":"47203",
    "sg:province":"IN",
    "sg:tags":[
        "commercial",
        "design"
    ],
    "wof:name":"Graphic Resources",
    "wof:placetype":"venue"
},
  "geometry": {"coordinates":[-85.85899000000001,39.236341],"type":"Point"}
}