{
  "type": "Feature",
  "properties": {
    "iso:country":"US",
    "sg:address":"2000 Roosevelt Rd",
    "sg:city":"Valparaiso",
    "sg:classifiers":[
        {
            "category":"Health Services",
            "subcategory":"Doctor",
            "type":"Services"
        }
    ],
    "sg:phone":"+1 219 462 6500",
    "sg:postcode":"46383",
    "sg:province":"IN",
    "sg:tags":[
        "physician",
        "surgeon"
    ],
    "wof:name":"Neurological & Spinal Surgery",
    "wof:placetype":"venue"
},
  "geometry": {"coordinates":[-87.046468,41.48609],"type":"Point"}
}