{
  "type": "Feature",
  "properties": {
    "addr:full":"313 Montclair Ct Evansville IN 47715",
    "addr:housenumber":"313",
    "addr:postcode":"47715",
    "addr:street":"Montclair Ct",
    "iso:country":"US",
    "sg:address":"313 Montclair Ct",
    "sg:city":"Evansville",
    "sg:classifiers":[
        {
            "category":"Personal",
            "type":"Services"
        }
    ],
    "sg:phone":"+1 812 471 3705",
    "sg:postcode":"47715",
    "sg:province":"IN",
    "wof:name":"Escape With Karen",
    "wof:placetype":"venue"
},
  "geometry": {"coordinates":[-87.483293,37.972834],"type":"Point"}
}