{
  "type": "Feature",
  "properties": {
    "iso:country":"US",
    "sg:address":"100 Broadway St",
    "sg:city":"Oaktown",
    "sg:classifiers":[
        {
            "category":"Government",
            "subcategory":"Office",
            "type":"Public Place"
        }
    ],
    "sg:phone":"+1 812 745 3360",
    "sg:postcode":"47561",
    "sg:province":"IN",
    "sg:tags":[
        "city"
    ],
    "wof:name":"Oaktown Town Hall",
    "wof:placetype":"venue"
},
  "geometry": {"coordinates":[-87.441071,38.871247],"type":"Point"}
}