{
  "type": "Feature",
  "properties": {
    "iso:country":"US",
    "sg:address":"7345 Camby Rd",
    "sg:city":"Camby",
    "sg:classifiers":[
        {
            "category":"Wholesale",
            "subcategory":"Office Equipment",
            "type":"Manufacturing & Wholesale Goods"
        }
    ],
    "sg:phone":"+1 317 856 3223",
    "sg:postcode":"46113",
    "sg:province":"IN",
    "sg:tags":[
        "register",
        "cash",
        "supply"
    ],
    "wof:name":"You Call We Install Inc",
    "wof:placetype":"venue"
},
  "geometry": {"coordinates":[-86.289661,39.661952],"type":"Point"}
}