{
  "type": "Feature",
  "properties": {
    "iso:country":"US",
    "sg:address":"413 Silver St",
    "sg:city":"New Albany",
    "sg:classifiers":[
        {
            "category":"Organizations",
            "subcategory":"Religious Organization",
            "type":"Services"
        }
    ],
    "sg:phone":"+1 812 948 1331",
    "sg:postcode":"47150",
    "sg:province":"IN",
    "sg:tags":[
        "church"
    ],
    "sg:website":"www.silverstreetumc.com",
    "wof:name":"Silver St United Methodist Chr",
    "wof:placetype":"venue"
},
  "geometry": {"coordinates":[-85.800878,38.297501],"type":"Point"}
}