{
  "type": "Feature",
  "properties": {
    "iso:country":"US",
    "sg:address":"4665 N Starnes Rd",
    "sg:city":"Bloomington",
    "sg:classifiers":[
        {
            "category":"Building & Trades",
            "subcategory":"Construction",
            "type":"Services"
        }
    ],
    "sg:phone":"+1 812 876 4995",
    "sg:postcode":"47404",
    "sg:province":"IN",
    "sg:tags":[
        "general",
        "contractor"
    ],
    "wof:name":"Underwood Construction Inc",
    "wof:placetype":"venue"
},
  "geometry": {"coordinates":[-86.658966,39.229146],"type":"Point"}
}