{
  "type": "Feature",
  "properties": {
    "iso:country":"US",
    "sg:address":"518 Garland Ave",
    "sg:city":"Columbia City",
    "sg:classifiers":[
        {
            "category":"Real Estate",
            "subcategory":"Real Estate Agent",
            "type":"Services"
        }
    ],
    "sg:phone":"+1 260 625 3765",
    "sg:postcode":"46725",
    "sg:province":"IN",
    "sg:tags":[
        "sales"
    ],
    "sg:website":"www.orizonrealestate.com",
    "wof:name":"Orizon Real Estate Inc",
    "wof:placetype":"venue"
},
  "geometry": {"coordinates":[-85.48533,41.166621],"type":"Point"}
}