{
  "type": "Feature",
  "properties": {
    "iso:country":"US",
    "sg:address":"6100 N Keystone Ave",
    "sg:city":"Indianapolis",
    "sg:classifiers":[
        {
            "category":"Education",
            "subcategory":"Special Training",
            "type":"Public Place"
        }
    ],
    "sg:phone":"+1 317 465 1835",
    "sg:postcode":"46220",
    "sg:province":"IN",
    "sg:tags":[
        "self",
        "motivational",
        "improvement"
    ],
    "sg:website":"www.qmgroup.net",
    "wof:name":"Quintessential Management",
    "wof:placetype":"venue"
},
  "geometry": {"coordinates":[-86.122304,39.866857],"type":"Point"}
}