{
  "type": "Feature",
  "properties": {
    "iso:country":"US",
    "sg:address":"3824 E Co Rd 625 N",
    "sg:city":"Orleans",
    "sg:classifiers":[
        {
            "category":"Retail",
            "subcategory":"Repair Shop",
            "type":"Services"
        }
    ],
    "sg:phone":"+1 812 865 3298",
    "sg:postcode":"47452",
    "sg:province":"IN",
    "sg:tags":[
        "welding"
    ],
    "wof:name":"Williams Welding Svc",
    "wof:placetype":"venue"
},
  "geometry": {"coordinates":[-86.387632,38.648186],"type":"Point"}
}