{
  "type": "Feature",
  "properties": {
    "iso:country":"US",
    "sg:address":"6922 Hillsdale Ct",
    "sg:city":"Indianapolis",
    "sg:classifiers":[
        {
            "category":"Health Services",
            "subcategory":"Health Practitioner",
            "type":"Services"
        }
    ],
    "sg:phone":"+1 317 621 7820",
    "sg:postcode":"46250",
    "sg:province":"IN",
    "sg:tags":[
        "therapist",
        "physical"
    ],
    "wof:name":"Rehab & Sports Medicine",
    "wof:placetype":"venue"
},
  "geometry": {"coordinates":[-86.04840299999999,39.896242],"type":"Point"}
}