{
  "type": "Feature",
  "properties": {
    "iso:country":"US",
    "sg:address":"176 S Main St",
    "sg:city":"Zionsville",
    "sg:classifiers":[
        {
            "category":"Professional",
            "type":"Services"
        }
    ],
    "sg:phone":"+1 317 873 3482",
    "sg:postcode":"46077",
    "sg:province":"IN",
    "sg:tags":[
        "establishment"
    ],
    "wof:name":"Spiral Staircase",
    "wof:placetype":"venue"
},
  "geometry": {"coordinates":[-86.26168800000001,39.950547],"type":"Point"}
}