{
  "type": "Feature",
  "properties": {
    "addr:full":"6068 N Keystone Ave Indianapolis IN 46220",
    "addr:housenumber":"6068",
    "addr:postcode":"46220",
    "addr:street":"N Keystone Ave",
    "iso:country":"US",
    "sg:address":"6068 N Keystone Ave",
    "sg:city":"Indianapolis",
    "sg:classifiers":[
        {
            "category":"Health Services",
            "subcategory":"Doctor",
            "type":"Services"
        }
    ],
    "sg:phone":"+1 317 257 7198",
    "sg:postcode":"46220",
    "sg:province":"IN",
    "sg:tags":[
        "dentist"
    ],
    "wof:name":"Family Dentistry",
    "wof:placetype":"venue"
},
  "geometry": {"coordinates":[-86.12230700000001,39.867546],"type":"Point"}
}