{
  "type": "Feature",
  "properties": {
    "iso:country":"US",
    "sg:address":"300 Michigan St",
    "sg:city":"Walkerton",
    "sg:classifiers":[
        {
            "category":"Education",
            "subcategory":"Library",
            "type":"Public Place"
        }
    ],
    "sg:phone":"+1 574 586 2933",
    "sg:postcode":"46574",
    "sg:province":"IN",
    "wof:name":"Walkerton Public Library",
    "wof:placetype":"venue"
},
  "geometry": {"coordinates":[-86.482725,41.467237],"type":"Point"}
}