{
  "type": "Feature",
  "properties": {
    "iso:country":"US",
    "sg:address":"630 Kimmell Rd",
    "sg:city":"Vincennes",
    "sg:classifiers":[
        {
            "category":"Restaurant",
            "type":"Food & Drink"
        }
    ],
    "sg:phone":"+1 812 882 5115",
    "sg:postcode":"47591",
    "sg:province":"IN",
    "wof:name":"Charlies Smorgasbord",
    "wof:placetype":"venue"
},
  "geometry": {"coordinates":[-87.495882,38.667963],"type":"Point"}
}