{
  "type": "Feature",
  "properties": {
    "iso:country":"US",
    "sg:address":"1403 Stanley Dr",
    "sg:city":"Plymouth",
    "sg:classifiers":[
        {
            "category":"Manufacturing",
            "subcategory":"Metals",
            "type":"Manufacturing & Wholesale Goods"
        }
    ],
    "sg:phone":"+1 574 936 8876",
    "sg:postcode":"46563",
    "sg:province":"IN",
    "sg:tags":[
        "steel",
        "pipe",
        "tube"
    ],
    "sg:website":"www.whitleyproducts.com",
    "wof:name":"Whitley Products Inc",
    "wof:placetype":"venue"
},
  "geometry": {"coordinates":[-86.333713,41.354432],"type":"Point"}
}