{
  "type": "Feature",
  "properties": {
    "iso:country":"US",
    "sg:address":"1215 S Buttercup Dr",
    "sg:city":"New Palestine",
    "sg:classifiers":[
        {
            "category":"Professional",
            "subcategory":"Management & Consulting",
            "type":"Services"
        }
    ],
    "sg:phone":"+1 317 861 1157",
    "sg:postcode":"46163",
    "sg:province":"IN",
    "sg:tags":[
        "consultant",
        "printing"
    ],
    "wof:name":"USA Custom Printing",
    "wof:placetype":"venue"
},
  "geometry": {"coordinates":[-85.900004,39.76634],"type":"Point"}
}