{
  "type": "Feature",
  "properties": {
    "iso:country":"US",
    "sg:address":"7321 E Co Rd 800 N",
    "sg:city":"Frankfort",
    "sg:phone":"+1 765 249 2730",
    "sg:postcode":"46041",
    "sg:province":"IN",
    "sg:tags":[
        "farm",
        "corn"
    ],
    "wof:name":"Willard Stahl",
    "wof:placetype":"venue"
},
  "geometry": {"coordinates":[-86.371887,40.402716],"type":"Point"}
}