{
  "type": "Feature",
  "properties": {
    "iso:country":"US",
    "sg:address":"1384 E Co Rd 400 S",
    "sg:city":"Logansport",
    "sg:classifiers":[
        {
            "category":"Farming",
            "subcategory":"Farm",
            "type":"Manufacturing & Wholesale Goods"
        }
    ],
    "sg:phone":"+1 574 722 4232",
    "sg:postcode":"46947",
    "sg:province":"IN",
    "wof:name":"R D Slusser Farms Inc",
    "wof:placetype":"venue"
},
  "geometry": {"coordinates":[-86.34789600000001,40.707172],"type":"Point"}
}