{
  "type": "Feature",
  "properties": {
    "iso:country":"US",
    "sg:address":"3133 W Jonestown Rd",
    "sg:city":"Clinton",
    "sg:classifiers":[
        {
            "category":"Building & Trades",
            "subcategory":"Equipment Rental",
            "type":"Services"
        }
    ],
    "sg:phone":"+1 765 832 8033",
    "sg:postcode":"47842",
    "sg:province":"IN",
    "wof:name":"Wabash Distributing",
    "wof:placetype":"venue"
},
  "geometry": {"coordinates":[-87.524146,39.708928],"type":"Point"}
}