{
  "type": "Feature",
  "properties": {
    "iso:country":"US",
    "sg:address":"2635 Wabash Ave",
    "sg:city":"Vincennes",
    "sg:classifiers":[
        {
            "category":"Personal",
            "subcategory":"Beauty Salon",
            "type":"Services"
        }
    ],
    "sg:phone":"+1 812 882 7224",
    "sg:postcode":"47591",
    "sg:province":"IN",
    "sg:tags":[
        "shop"
    ],
    "wof:name":"Brenda's Beauty Boutique",
    "wof:placetype":"venue"
},
  "geometry": {"coordinates":[-87.49556800000001,38.668178],"type":"Point"}
}