{
  "type": "Feature",
  "properties": {
    "iso:country":"US",
    "sg:address":"2001 State Rd 1",
    "sg:city":"Cambridge City",
    "sg:classifiers":[
        {
            "category":"Food & Beverages",
            "subcategory":"Dairy",
            "type":"Retail Goods"
        }
    ],
    "sg:phone":"+1 765 478 5847",
    "sg:postcode":"47327",
    "sg:province":"IN",
    "sg:tags":[
        "cheese"
    ],
    "wof:name":"Amish Cheese Shop",
    "wof:placetype":"venue"
},
  "geometry": {"coordinates":[-85.154978,39.802616],"type":"Point"}
}