{
  "type": "Feature",
  "properties": {
    "iso:country":"US",
    "sg:address":"7765 E Washington St",
    "sg:city":"Indianapolis",
    "sg:classifiers":[
        {
            "category":"Professional",
            "subcategory":"Employment Agencies",
            "type":"Services"
        }
    ],
    "sg:phone":"+1 317 359 8367",
    "sg:postcode":"46219",
    "sg:province":"IN",
    "sg:tags":[
        "opportunity"
    ],
    "sg:website":"www.westaff.com",
    "wof:name":"Westaff",
    "wof:placetype":"venue"
},
  "geometry": {"coordinates":[-86.029516,39.772805],"type":"Point"}
}