{
  "type": "Feature",
  "properties": {
    "iso:country":"US",
    "sg:address":"903 Spring St",
    "sg:city":"Jeffersonville",
    "sg:classifiers":[
        {
            "category":"Real Estate",
            "subcategory":"Architect",
            "type":"Services"
        }
    ],
    "sg:phone":"+1 812 282 3700",
    "sg:postcode":"47130",
    "sg:province":"IN",
    "sg:website":"www.theestopinalgroup.com",
    "wof:name":"Estopinal Group Inc",
    "wof:placetype":"venue"
},
  "geometry": {"coordinates":[-85.745388,38.27821],"type":"Point"}
}