{
  "type": "Feature",
  "properties": {
    "addr:full":"120 Crossroads Dr Whiteland IN 46184",
    "addr:housenumber":"120",
    "addr:postcode":"46184",
    "addr:street":"Crossroads Dr",
    "iso:country":"US",
    "sg:address":"120 Crossroads Dr",
    "sg:city":"Whiteland",
    "sg:classifiers":[
        {
            "category":"Building & Trades",
            "subcategory":"Landscaping Services",
            "type":"Services"
        }
    ],
    "sg:phone":"+1 317 535 1002",
    "sg:postcode":"46184",
    "sg:province":"IN",
    "sg:tags":[
        "lawn",
        "maintenance",
        "grounds"
    ],
    "wof:name":"Certified Lawn Care",
    "wof:placetype":"venue"
},
  "geometry": {"coordinates":[-86.095432,39.576924],"type":"Point"}
}