{
  "type": "Feature",
  "properties": {
    "iso:country":"US",
    "sg:address":"7646 N 700 W",
    "sg:city":"Fairland",
    "sg:classifiers":[
        {
            "category":"Building & Trades",
            "subcategory":"Electrical",
            "type":"Services"
        }
    ],
    "sg:phone":"+1 317 835 8580",
    "sg:postcode":"46126",
    "sg:province":"IN",
    "sg:tags":[
        "electric",
        "contractor"
    ],
    "wof:name":"F C Electricial",
    "wof:placetype":"venue"
},
  "geometry": {"coordinates":[-85.914321,39.632169],"type":"Point"}
}