{
  "type": "Feature",
  "properties": {
    "addr:full":"11681 Brooks School Rd Fishers IN 46037",
    "addr:housenumber":"11681",
    "addr:postcode":"46037",
    "addr:street":"Brooks School Rd",
    "iso:country":"US",
    "sg:address":"11681 Brooks School Rd",
    "sg:city":"Fishers",
    "sg:classifiers":[
        {
            "category":"Cinema",
            "subcategory":"Movie Rental",
            "type":"Entertainment"
        }
    ],
    "sg:phone":"+1 317 598 0856",
    "sg:postcode":"46037",
    "sg:province":"IN",
    "sg:tags":[
        "leasing",
        "video",
        "disc",
        "tape"
    ],
    "sg:website":"www.blockbuster.com",
    "wof:name":"Blockbuster Video",
    "wof:placetype":"venue"
},
  "geometry": {"coordinates":[-85.94218100000001,39.958757],"type":"Point"}
}