{
  "type": "Feature",
  "properties": {
    "addr:full":"150 S Olive St South Bend IN 46619",
    "addr:housenumber":"150",
    "addr:postcode":"46619",
    "addr:street":"S Olive St",
    "iso:country":"US",
    "sg:address":"150 S Olive St",
    "sg:city":"South Bend",
    "sg:classifiers":[
        {
            "category":"Government",
            "subcategory":"Post Office",
            "type":"Public Place"
        }
    ],
    "sg:phone":"+1 574 282 8515",
    "sg:postcode":"46619",
    "sg:province":"IN",
    "wof:name":"US Post Office",
    "wof:placetype":"venue"
},
  "geometry": {"coordinates":[-86.28330200000001,41.675681],"type":"Point"}
}