{
  "type": "Feature",
  "properties": {
    "iso:country":"US",
    "sg:address":"113 Vernon St",
    "sg:city":"North Vernon",
    "sg:classifiers":[
        {
            "category":"Social Services",
            "subcategory":"Child Care",
            "type":"Services"
        }
    ],
    "sg:phone":"+1 812 346 6790",
    "sg:postcode":"47265",
    "sg:province":"IN",
    "wof:name":"House Of Great Care",
    "wof:placetype":"venue"
},
  "geometry": {"coordinates":[-85.622976,39.002822],"type":"Point"}
}