{
  "type": "Feature",
  "properties": {
    "iso:country":"US",
    "sg:address":"3 Pinetree Rd",
    "sg:city":"Garrett",
    "sg:classifiers":[
        {
            "category":"Manufacturing",
            "subcategory":"Motor Vehicles & Parts",
            "type":"Manufacturing & Wholesale Goods"
        }
    ],
    "sg:phone":"+1 260 637 6638",
    "sg:postcode":"46738",
    "sg:province":"IN",
    "sg:tags":[
        "truck",
        "trailer",
        "mfg"
    ],
    "wof:name":"Grossman Enterprises",
    "wof:placetype":"venue"
},
  "geometry": {"coordinates":[-85.129289,41.285442],"type":"Point"}
}