{
  "type": "Feature",
  "properties": {
    "iso:country":"US",
    "sg:address":"9609 Leesburg Rd",
    "sg:city":"Fort Wayne",
    "sg:classifiers":[
        {
            "category":"Professional",
            "type":"Services"
        }
    ],
    "sg:phone":"+1 260 625 3525",
    "sg:postcode":"46818",
    "sg:province":"IN",
    "wof:name":"Kreigh Blasi Incorporated",
    "wof:placetype":"venue"
},
  "geometry": {"coordinates":[-85.284548,41.125363],"type":"Point"}
}