{
  "type": "Feature",
  "properties": {
    "iso:country":"US",
    "sg:address":"10942 Sheephead Ct",
    "sg:city":"Demotte",
    "sg:classifiers":[
        {
            "category":"Personal",
            "subcategory":"Beauty Salon",
            "type":"Services"
        }
    ],
    "sg:phone":"+1 219 987 5755",
    "sg:postcode":"46310",
    "sg:province":"IN",
    "sg:tags":[
        "shop"
    ],
    "wof:name":"Maxey KUT",
    "wof:placetype":"venue"
},
  "geometry": {"coordinates":[-87.263628,41.172272],"type":"Point"}
}