{
  "type": "Feature",
  "properties": {
    "iso:country":"US",
    "sg:address":"119 E Main St",
    "sg:city":"Hillsboro",
    "sg:classifiers":[
        {
            "category":"Personal",
            "subcategory":"Beauty Salon",
            "type":"Services"
        }
    ],
    "sg:phone":"+1 765 798 2607",
    "sg:postcode":"47949",
    "sg:province":"IN",
    "wof:name":"Carlson's Hair Care Ctr",
    "wof:placetype":"venue"
},
  "geometry": {"coordinates":[-87.159022,40.106581],"type":"Point"}
}