{
  "type": "Feature",
  "properties": {
    "iso:country":"US",
    "sg:address":"1830 Ohio St",
    "sg:city":"Evansville",
    "sg:classifiers":[
        {
            "category":"Freight",
            "type":"Transportation"
        }
    ],
    "sg:phone":"+1 812 425 7152",
    "sg:postcode":"47712",
    "sg:province":"IN",
    "sg:tags":[
        "warehouse",
        "self",
        "storage"
    ],
    "wof:name":"Port Of Evansville",
    "wof:placetype":"venue"
},
  "geometry": {"coordinates":[-87.59369100000001,37.976771],"type":"Point"}
}