{
  "type": "Feature",
  "properties": {
    "iso:country":"US",
    "sg:address":"2845 Guilford St",
    "sg:city":"Huntington",
    "sg:classifiers":[
        {
            "category":"Banks & Credit Unions",
            "subcategory":"Bank",
            "type":"Services"
        }
    ],
    "sg:phone":"+1 260 355 0406",
    "sg:postcode":"46750",
    "sg:province":"IN",
    "wof:name":"Huntington Community Banking",
    "wof:placetype":"venue"
},
  "geometry": {"coordinates":[-85.508202,40.903586],"type":"Point"}
}