{
  "type": "Feature",
  "properties": {
    "iso:country":"US",
    "sg:address":"1001 W Culver Rd",
    "sg:city":"Knox",
    "sg:classifiers":[
        {
            "category":"Home & Garden",
            "subcategory":"Building Materials",
            "type":"Retail Goods"
        }
    ],
    "sg:phone":"+1 574 772 2955",
    "sg:postcode":"46534",
    "sg:province":"IN",
    "sg:tags":[
        "windows"
    ],
    "wof:name":"Rockwell Window Co Inc",
    "wof:placetype":"venue"
},
  "geometry": {"coordinates":[-86.638301,41.288155],"type":"Point"}
}