{
  "type": "Feature",
  "properties": {
    "addr:full":"227 Main St Evansville IN 47708",
    "addr:housenumber":"227",
    "addr:postcode":"47708",
    "addr:street":"Main St",
    "iso:country":"US",
    "sg:address":"227 Main St",
    "sg:city":"Evansville",
    "sg:classifiers":[
        {
            "category":"Professional",
            "type":"Services"
        }
    ],
    "sg:phone":"+1 812 464 9638",
    "sg:postcode":"47708",
    "sg:province":"IN",
    "wof:name":"Deaf Services",
    "wof:placetype":"venue"
},
  "geometry": {"coordinates":[-87.572428,37.970805],"type":"Point"}
}