{
  "type": "Feature",
  "properties": {
    "iso:country":"US",
    "sg:address":"202 Nancy Dr",
    "sg:city":"Kokomo",
    "sg:classifiers":[
        {
            "category":"Building & Trades",
            "subcategory":"Construction",
            "type":"Services"
        }
    ],
    "sg:phone":"+1 765 452 6482",
    "sg:postcode":"46901",
    "sg:province":"IN",
    "sg:tags":[
        "house"
    ],
    "wof:name":"Dumoulin Construction",
    "wof:placetype":"venue"
},
  "geometry": {"coordinates":[-86.126773,40.553834],"type":"Point"}
}