{
  "type": "Feature",
  "properties": {
    "iso:country":"US",
    "sg:address":"7620 Old Trails Rd",
    "sg:city":"Indianapolis",
    "sg:classifiers":[
        {
            "category":"Manufacturing",
            "subcategory":"Toys & Sporting Goods",
            "type":"Manufacturing & Wholesale Goods"
        },
        {
            "category":"Utilities",
            "subcategory":"Natural Gas",
            "type":"Services"
        }
    ],
    "sg:phone":"+1 317 359 2264",
    "sg:postcode":"46219",
    "sg:province":"IN",
    "sg:tags":[
        "fireworks-wholesale",
        "firework",
        "manufacturer"
    ],
    "wof:name":"Big Fireworks.Com",
    "wof:placetype":"venue"
},
  "geometry": {"coordinates":[-86.034002,39.771313],"type":"Point"}
}