{
  "type": "Feature",
  "properties": {
    "iso:country":"US",
    "sg:address":"2623 Camino Ct",
    "sg:city":"Fort Wayne",
    "sg:classifiers":[
        {
            "category":"Manufacturing",
            "subcategory":"Printing",
            "type":"Manufacturing & Wholesale Goods"
        }
    ],
    "sg:phone":"+1 260 482 2720",
    "sg:postcode":"46808",
    "sg:province":"IN",
    "sg:tags":[
        "commercial"
    ],
    "wof:name":"Excell Color Graphics Inc",
    "wof:placetype":"venue"
},
  "geometry": {"coordinates":[-85.182149,41.109559],"type":"Point"}
}