{
  "type": "Feature",
  "properties": {
    "iso:country":"US",
    "sg:address":"6381 Central Ave",
    "sg:city":"Portage",
    "sg:classifiers":[
        {
            "category":"Food & Beverages",
            "subcategory":"Groceries & Convenience Stores",
            "type":"Retail Goods"
        }
    ],
    "sg:phone":"+1 219 763 4197",
    "sg:postcode":"46368",
    "sg:province":"IN",
    "sg:website":"www.mcrshortstop.com",
    "wof:name":"Short Stop",
    "wof:placetype":"venue"
},
  "geometry": {"coordinates":[-87.17301,41.57582],"type":"Point"}
}