{
  "type": "Feature",
  "properties": {
    "addr:full":"331 N 4th St Lafayette IN 47901",
    "addr:housenumber":"331",
    "addr:postcode":"47901",
    "addr:street":"N 4Th St",
    "iso:country":"US",
    "sg:address":"331 N 4th St",
    "sg:city":"Lafayette",
    "sg:classifiers":[
        {
            "category":"Travel",
            "subcategory":"Travel Agent",
            "type":"Entertainment"
        }
    ],
    "sg:phone":"+1 765 423 1697",
    "sg:postcode":"47901",
    "sg:province":"IN",
    "sg:tags":[
        "ticket",
        "agency",
        "airline"
    ],
    "wof:name":"AAA Hoosier Motor Club",
    "wof:placetype":"venue"
},
  "geometry": {"coordinates":[-86.893016,40.420656],"type":"Point"}
}