{
  "type": "Feature",
  "properties": {
    "iso:country":"US",
    "sg:address":"1345 W Southport Rd",
    "sg:city":"Indianapolis",
    "sg:classifiers":[
        {
            "category":"Personal",
            "subcategory":"Nail Salon",
            "type":"Services"
        }
    ],
    "sg:phone":"+1 317 865 8856",
    "sg:postcode":"46217",
    "sg:province":"IN",
    "wof:name":"Tammy Nails",
    "wof:placetype":"venue"
},
  "geometry": {"coordinates":[-86.183438,39.663833],"type":"Point"}
}