{
  "type": "Feature",
  "properties": {
    "iso:country":"US",
    "sg:address":"336 US Hwy 30 W",
    "sg:city":"New Haven",
    "sg:classifiers":[
        {
            "category":"Restaurant",
            "type":"Food & Drink"
        }
    ],
    "sg:phone":"+1 260 749 8262",
    "sg:postcode":"46774",
    "sg:province":"IN",
    "wof:name":"Arby's",
    "wof:placetype":"venue"
},
  "geometry": {"coordinates":[-85.033373,41.0689],"type":"Point"}
}