{
  "type": "Feature",
  "properties": {
    "addr:full":"2125 Glenview Dr Evansville IN 47720",
    "addr:housenumber":"2125",
    "addr:postcode":"47720",
    "addr:street":"Glenview Dr",
    "iso:country":"US",
    "sg:address":"2125 Glenview Dr",
    "sg:city":"Evansville",
    "sg:classifiers":[
        {
            "category":"Professional",
            "subcategory":"Research",
            "type":"Services"
        }
    ],
    "sg:phone":"+1 812 421 1744",
    "sg:postcode":"47720",
    "sg:province":"IN",
    "sg:tags":[
        "environmental",
        "ecological"
    ],
    "wof:name":"Summit Environmental Svc Inc",
    "wof:placetype":"venue"
},
  "geometry": {"coordinates":[-87.59599799999999,38.017494],"type":"Point"}
}