{
  "type": "Feature",
  "properties": {
    "iso:country":"US",
    "sg:address":"7679 State Rd 13",
    "sg:city":"Pendleton",
    "sg:classifiers":[
        {
            "category":"Organizations",
            "subcategory":"Religious Organization",
            "type":"Services"
        }
    ],
    "sg:phone":"+1 317 485 5051",
    "sg:postcode":"46064",
    "sg:province":"IN",
    "wof:name":"Beech Grove Church Brethren",
    "wof:placetype":"venue"
},
  "geometry": {"coordinates":[-85.84307099999999,39.992411],"type":"Point"}
}