{
  "type": "Feature",
  "properties": {
    "iso:country":"US",
    "sg:address":"1500 Jefferson St",
    "sg:city":"Mt Vernon",
    "sg:classifiers":[
        {
            "category":"Real Estate",
            "subcategory":"Real Estate Agent",
            "type":"Services"
        }
    ],
    "sg:phone":"+1 812 838 6356",
    "sg:postcode":"47620",
    "sg:province":"IN",
    "sg:tags":[
        "authorities",
        "housing"
    ],
    "wof:name":"Housing Authority",
    "wof:placetype":"venue"
},
  "geometry": {"coordinates":[-87.899975,37.944109],"type":"Point"}
}