{
  "type": "Feature",
  "properties": {
    "iso:country":"US",
    "sg:address":"116 W Carmel Dr",
    "sg:city":"Carmel",
    "sg:classifiers":[
        {
            "category":"Wholesale",
            "subcategory":"Durable Goods & Equipment",
            "type":"Manufacturing & Wholesale Goods"
        }
    ],
    "sg:phone":"+1 317 819 0391",
    "sg:postcode":"46032",
    "sg:province":"IN",
    "sg:tags":[
        "magnet",
        "magnetic",
        "devices"
    ],
    "wof:name":"Polaris Rare Earth Materials",
    "wof:placetype":"venue"
},
  "geometry": {"coordinates":[-86.128207,39.96146],"type":"Point"}
}