{
  "type": "Feature",
  "properties": {
    "iso:country":"US",
    "sg:address":"7001 W Washington St",
    "sg:city":"Indianapolis",
    "sg:classifiers":[
        {
            "category":"Home & Garden",
            "subcategory":"Household Appliances",
            "type":"Retail Goods"
        },
        {
            "category":"Retail",
            "subcategory":"Repair Shop",
            "type":"Services"
        }
    ],
    "sg:phone":"+1 317 839 6372",
    "sg:postcode":"46241",
    "sg:province":"IN",
    "sg:tags":[
        "major",
        "dishwashing",
        "refinishing",
        "appliances-small",
        "machine",
        "small"
    ],
    "wof:name":"Ribble's Appliance Service",
    "wof:placetype":"venue"
},
  "geometry": {"coordinates":[-86.284271,39.742359],"type":"Point"}
}