{
  "type": "Feature",
  "properties": {
    "addr:full":"519 Main St Jasper IN 47546",
    "addr:housenumber":"519",
    "addr:postcode":"47546",
    "addr:street":"Main St",
    "iso:country":"US",
    "sg:address":"519 Main St",
    "sg:city":"Jasper",
    "sg:classifiers":[
        {
            "category":"Shopping",
            "subcategory":"Clothing, Apparel, & Fashions",
            "type":"Retail Goods"
        }
    ],
    "sg:phone":"+1 812 482 4990",
    "sg:postcode":"47546",
    "sg:province":"IN",
    "sg:tags":[
        "shop",
        "bridal"
    ],
    "wof:name":"Bridal Boutique",
    "wof:placetype":"venue"
},
  "geometry": {"coordinates":[-86.930891,38.391049],"type":"Point"}
}