{
  "type": "Feature",
  "properties": {
    "addr:full":"3819 Claremont Ave Evansville IN 47712",
    "addr:housenumber":"3819",
    "addr:postcode":"47712",
    "addr:street":"Claremont Ave",
    "iso:country":"US",
    "sg:address":"3819 Claremont Ave",
    "sg:city":"Evansville",
    "sg:classifiers":[
        {
            "category":"Shopping",
            "subcategory":"Bicycles & Sporting Goods",
            "type":"Retail Goods"
        }
    ],
    "sg:phone":"+1 812 423 2238",
    "sg:postcode":"47712",
    "sg:province":"IN",
    "sg:tags":[
        "bait",
        "fishing"
    ],
    "wof:name":"University Bait & Taxidermy",
    "wof:placetype":"venue"
},
  "geometry": {"coordinates":[-87.624002,37.971627],"type":"Point"}
}