{
  "type": "Feature",
  "properties": {
    "iso:country":"US",
    "sg:address":"1215 E Spring St",
    "sg:city":"Bluffton",
    "sg:classifiers":[
        {
            "category":"Professional",
            "subcategory":"Research",
            "type":"Services"
        }
    ],
    "sg:phone":"+1 260 824 5066",
    "sg:postcode":"46714",
    "sg:province":"IN",
    "wof:name":"C & I Research & Development",
    "wof:placetype":"venue"
},
  "geometry": {"coordinates":[-85.156737,40.728347],"type":"Point"}
}