{
  "type": "Feature",
  "properties": {
    "addr:full":"8477 Fishers Center Dr Fishers IN 46038",
    "addr:housenumber":"8477",
    "addr:postcode":"46038",
    "addr:street":"Fishers Center Dr",
    "iso:country":"US",
    "sg:address":"8477 Fishers Center Dr",
    "sg:city":"Fishers",
    "sg:classifiers":[
        {
            "category":"Banks & Credit Unions",
            "subcategory":"Financial Services",
            "type":"Services"
        }
    ],
    "sg:phone":"+1 317 813 1600",
    "sg:postcode":"46038",
    "sg:province":"IN",
    "sg:tags":[
        "card",
        "card-merchant"
    ],
    "wof:name":"Advopay",
    "wof:placetype":"venue"
},
  "geometry": {"coordinates":[-86.01864399999999,39.955986],"type":"Point"}
}