{
  "type": "Feature",
  "properties": {
    "iso:country":"US",
    "sg:address":"969 N Shadeland Ave",
    "sg:city":"Indianapolis",
    "sg:classifiers":[
        {
            "category":"Utilities",
            "subcategory":"Mobile Phone",
            "type":"Services"
        }
    ],
    "sg:phone":"+1 317 359 6999",
    "sg:postcode":"46219",
    "sg:province":"IN",
    "sg:tags":[
        "equipment",
        "paging",
        "signaling",
        "system"
    ],
    "wof:name":"Mastercom Materpage",
    "wof:placetype":"venue"
},
  "geometry": {"coordinates":[-86.045321,39.779447],"type":"Point"}
}