{
  "type": "Feature",
  "properties": {
    "iso:country":"US",
    "sg:address":"12811 Co Rd 2",
    "sg:city":"Middlebury",
    "sg:classifiers":[
        {
            "category":"Retail",
            "subcategory":"Repair Shop",
            "type":"Services"
        }
    ],
    "sg:phone":"+1 574 825 0464",
    "sg:postcode":"46540",
    "sg:province":"IN",
    "sg:tags":[
        "taxidermist"
    ],
    "wof:name":"Wildlife Wonders Taxidermy",
    "wof:placetype":"venue"
},
  "geometry": {"coordinates":[-85.718309,41.751075],"type":"Point"}
}