{
  "type": "Feature",
  "properties": {
    "iso:country":"US",
    "sg:address":"1855 Cragmont St",
    "sg:city":"Madison",
    "sg:classifiers":[
        {
            "category":"Retail",
            "subcategory":"Auto Repair",
            "type":"Services"
        }
    ],
    "sg:phone":"+1 812 574 3000",
    "sg:postcode":"47250",
    "sg:province":"IN",
    "sg:tags":[
        "repairing",
        "automobile"
    ],
    "wof:name":"D & D Automotive",
    "wof:placetype":"venue"
},
  "geometry": {"coordinates":[-85.396566,38.763368],"type":"Point"}
}