{
  "type": "Feature",
  "properties": {
    "addr:full":"201 N Jefferson St Huntington IN 46750",
    "addr:housenumber":"201",
    "addr:postcode":"46750",
    "addr:street":"N Jefferson",
    "iso:country":"US",
    "sg:address":"201 N Jefferson St",
    "sg:city":"Huntington",
    "sg:classifiers":[
        {
            "category":"Government",
            "subcategory":"Office",
            "type":"Public Place"
        }
    ],
    "sg:phone":"+1 260 358 4850",
    "sg:postcode":"46750",
    "sg:province":"IN",
    "wof:name":"Small Claims Div",
    "wof:placetype":"venue"
},
  "geometry": {"coordinates":[-85.49422199999999,40.881159],"type":"Point"}
}