{
  "type": "Feature",
  "properties": {
    "iso:country":"US",
    "sg:address":"1117 Calumet Ave",
    "sg:city":"Valparaiso",
    "sg:classifiers":[
        {
            "category":"Home & Garden",
            "subcategory":"Household Appliances",
            "type":"Retail Goods"
        }
    ],
    "sg:phone":"+1 219 462 6113",
    "sg:postcode":"46383",
    "sg:province":"IN",
    "wof:name":"Sun Appliance & Electronics",
    "wof:placetype":"venue"
},
  "geometry": {"coordinates":[-87.055356,41.47841],"type":"Point"}
}