{
  "type": "Feature",
  "properties": {
    "iso:country":"US",
    "sg:address":"3504 Stellhorn Rd",
    "sg:city":"Fort Wayne",
    "sg:classifiers":[
        {
            "category":"Food & Beverages",
            "subcategory":"Specialty",
            "type":"Retail Goods"
        }
    ],
    "sg:phone":"+1 260 485 2673",
    "sg:postcode":"46815",
    "sg:province":"IN",
    "sg:tags":[
        "herb"
    ],
    "wof:name":"Bob Black's Herbs & Vitamins",
    "wof:placetype":"venue"
},
  "geometry": {"coordinates":[-85.098517,41.119243],"type":"Point"}
}