{
  "type": "Feature",
  "properties": {
    "addr:full":"1400 E Pugh Dr Terre Haute IN 47802",
    "addr:housenumber":"1400",
    "addr:postcode":"47802",
    "addr:street":"E Pugh Dr",
    "iso:country":"US",
    "sg:address":"1400 E Pugh Dr",
    "sg:city":"Terre Haute",
    "sg:classifiers":[
        {
            "category":"Real Estate",
            "subcategory":"Real Estate Agent",
            "type":"Services"
        }
    ],
    "sg:phone":"+1 812 242 9393",
    "sg:postcode":"47802",
    "sg:province":"IN",
    "wof:name":"Assist 2 Sell",
    "wof:placetype":"venue"
},
  "geometry": {"coordinates":[-87.39807500000001,39.432304],"type":"Point"}
}