{
  "type": "Feature",
  "properties": {
    "iso:country":"US",
    "sg:address":"109 W Huntington St",
    "sg:city":"Montpelier",
    "sg:classifiers":[
        {
            "category":"Real Estate",
            "subcategory":"Real Estate Agent",
            "type":"Services"
        }
    ],
    "sg:phone":"+1 765 728 2246",
    "sg:postcode":"47359",
    "sg:province":"IN",
    "wof:name":"Neff Realty",
    "wof:placetype":"venue"
},
  "geometry": {"coordinates":[-85.279106,40.554539],"type":"Point"}
}