{
  "type": "Feature",
  "properties": {
    "iso:country":"US",
    "sg:address":"3983 State Rd 38 E",
    "sg:city":"Lafayette",
    "sg:classifiers":[
        {
            "category":"Food & Beverages",
            "subcategory":"Groceries & Convenience Stores",
            "type":"Retail Goods"
        }
    ],
    "sg:phone":"+1 765 446 9202",
    "sg:postcode":"47905",
    "sg:province":"IN",
    "wof:name":"Family Express Corp",
    "wof:placetype":"venue"
},
  "geometry": {"coordinates":[-86.831594,40.385404],"type":"Point"}
}