{
  "type": "Feature",
  "properties": {
    "iso:country":"US",
    "sg:address":"511 N Memorial Dr",
    "sg:city":"New Castle",
    "sg:classifiers":[
        {
            "category":"Home & Garden",
            "subcategory":"Furniture",
            "type":"Retail Goods"
        }
    ],
    "sg:phone":"+1 765 529 1848",
    "sg:postcode":"47362",
    "sg:province":"IN",
    "wof:name":"Dennis Kinser's Furniture",
    "wof:placetype":"venue"
},
  "geometry": {"coordinates":[-85.383833,39.937135],"type":"Point"}
}