{
  "type": "Feature",
  "properties": {
    "iso:country":"US",
    "sg:address":"411 S Huntington St",
    "sg:city":"Syracuse",
    "sg:classifiers":[
        {
            "category":"Banks & Credit Unions",
            "subcategory":"Bank",
            "type":"Services"
        }
    ],
    "sg:phone":"+1 574 457 4471",
    "sg:postcode":"46567",
    "sg:province":"IN",
    "wof:name":"Farmers State Bank",
    "wof:placetype":"venue"
},
  "geometry": {"coordinates":[-85.747674,41.418875],"type":"Point"}
}