{
  "type": "Feature",
  "properties": {
    "iso:country":"US",
    "sg:address":"3219 Washington Ave",
    "sg:city":"Evansville",
    "sg:classifiers":[
        {
            "category":"Organizations",
            "subcategory":"Religious Organization",
            "type":"Services"
        }
    ],
    "sg:phone":"+1 812 474 0494",
    "sg:postcode":"47714",
    "sg:province":"IN",
    "wof:name":"Rev James Mercer",
    "wof:placetype":"venue"
},
  "geometry": {"coordinates":[-87.509713,37.962366],"type":"Point"}
}