{
  "type": "Feature",
  "properties": {
    "addr:full":"3839 Central Ave Indianapolis IN 46205",
    "addr:housenumber":"3839",
    "addr:postcode":"46205",
    "addr:street":"Central Ave",
    "iso:country":"US",
    "sg:address":"3839 Central Ave",
    "sg:city":"Indianapolis",
    "sg:classifiers":[
        {
            "category":"Retail",
            "subcategory":"Repair Shop",
            "type":"Services"
        }
    ],
    "sg:phone":"+1 317 698 9682",
    "sg:postcode":"46205",
    "sg:province":"IN",
    "sg:tags":[
        "lock",
        "locksmith"
    ],
    "wof:name":"Cats 24 Hour Unlock Svc",
    "wof:placetype":"venue"
},
  "geometry": {"coordinates":[-86.14970700000001,39.826108],"type":"Point"}
}