{
  "type": "Feature",
  "properties": {
    "iso:country":"US",
    "sg:address":"2182 N Illinois St",
    "sg:city":"Indianapolis",
    "sg:classifiers":[
        {
            "category":"Food & Beverages",
            "subcategory":"Liquor & Beverages",
            "type":"Retail Goods"
        }
    ],
    "sg:phone":"+1 317 923 7750",
    "sg:postcode":"46202",
    "sg:province":"IN",
    "wof:name":"Hoot Package Liquor Str",
    "wof:placetype":"venue"
},
  "geometry": {"coordinates":[-86.15920699999999,39.79651],"type":"Point"}
}