{
  "type": "Feature",
  "properties": {
    "iso:country":"US",
    "sg:address":"3031 W 79th St",
    "sg:city":"Indianapolis",
    "sg:classifiers":[
        {
            "category":"Education",
            "subcategory":"College",
            "type":"Public Place"
        },
        {
            "category":"Education",
            "subcategory":"Special Training",
            "type":"Public Place"
        }
    ],
    "sg:phone":"+1 317 802 9599",
    "sg:postcode":"46268",
    "sg:province":"IN",
    "sg:tags":[
        "aircraft",
        "flight",
        "airlines-training",
        "school"
    ],
    "wof:name":"Crew Training International",
    "wof:placetype":"venue"
},
  "geometry": {"coordinates":[-86.21095800000001,39.897213],"type":"Point"}
}