{
  "type": "Feature",
  "properties": {
    "iso:country":"US",
    "sg:address":"5500 Emerson Way",
    "sg:city":"Indianapolis",
    "sg:classifiers":[
        {
            "category":"Restaurant",
            "type":"Food & Drink"
        }
    ],
    "sg:phone":"+1 317 251 5108",
    "sg:postcode":"46226",
    "sg:province":"IN",
    "sg:website":"www.hilltopnorth.com",
    "wof:name":"Hilltop North",
    "wof:placetype":"venue"
},
  "geometry": {"coordinates":[-86.086805,39.854614],"type":"Point"}
}