{
  "type": "Feature",
  "properties": {
    "iso:country":"US",
    "sg:address":"740 N US Hwy 35",
    "sg:city":"Knox",
    "sg:classifiers":[
        {
            "category":"Home & Garden",
            "subcategory":"Garden Supply",
            "type":"Retail Goods"
        },
        {
            "category":"Utilities",
            "type":"Services"
        }
    ],
    "sg:phone":"+1 574 772 3211",
    "sg:postcode":"46534",
    "sg:province":"IN",
    "sg:tags":[
        "sanitary",
        "nurseryman"
    ],
    "wof:name":"Ledbetter's Nursery",
    "wof:placetype":"venue"
},
  "geometry": {"coordinates":[-86.620638,41.315234],"type":"Point"}
}