{
  "type": "Feature",
  "properties": {
    "iso:country":"US",
    "sg:address":"13403 Darmstadt Rd",
    "sg:city":"Evansville",
    "sg:classifiers":[
        {
            "category":"Freight",
            "type":"Transportation"
        }
    ],
    "sg:phone":"+1 812 868 0725",
    "sg:postcode":"47725",
    "sg:province":"IN",
    "sg:tags":[
        "consultant"
    ],
    "wof:name":"Navtax Inc",
    "wof:placetype":"venue"
},
  "geometry": {"coordinates":[-87.57817900000001,38.101646],"type":"Point"}
}