{
  "type": "Feature",
  "properties": {
    "iso:country":"US",
    "sg:address":"1821 E Market St",
    "sg:city":"Warsaw",
    "sg:classifiers":[
        {
            "category":"Restaurant",
            "type":"Food & Drink"
        }
    ],
    "sg:phone":"+1 574 269 9050",
    "sg:postcode":"46580",
    "sg:province":"IN",
    "wof:name":"Cozy Cottage Restaurant",
    "wof:placetype":"venue"
},
  "geometry": {"coordinates":[-85.833005,41.237117],"type":"Point"}
}