{
  "type": "Feature",
  "properties": {
    "iso:country":"US",
    "sg:address":"9235 Crawfordsville Rd",
    "sg:city":"Indianapolis",
    "sg:classifiers":[
        {
            "category":"Personal",
            "subcategory":"Beauty Salon",
            "type":"Services"
        }
    ],
    "sg:phone":"+1 317 216 9923",
    "sg:postcode":"46234",
    "sg:province":"IN",
    "wof:name":"Edy's Barber & Beauty",
    "wof:placetype":"venue"
},
  "geometry": {"coordinates":[-86.327184,39.817662],"type":"Point"}
}