{
  "type": "Feature",
  "properties": {
    "iso:country":"US",
    "sg:address":"1106 Ruddell Dr",
    "sg:city":"Kokomo",
    "sg:classifiers":[
        {
            "category":"Building & Trades",
            "subcategory":"Construction",
            "type":"Services"
        }
    ],
    "sg:phone":"+1 765 459 8325",
    "sg:postcode":"46901",
    "sg:province":"IN",
    "sg:tags":[
        "hanging",
        "contractor"
    ],
    "wof:name":"Sears Painting Bill",
    "wof:placetype":"venue"
},
  "geometry": {"coordinates":[-86.151497,40.497476],"type":"Point"}
}