{
  "type": "Feature",
  "properties": {
    "addr:full":"16767 Clover Rd Noblesville IN 46060",
    "addr:housenumber":"16767",
    "addr:postcode":"46060",
    "addr:street":"Clover Rd",
    "iso:country":"US",
    "sg:address":"16767 Clover Rd",
    "sg:city":"Noblesville",
    "sg:classifiers":[
        {
            "category":"Personal",
            "subcategory":"Beauty Salon",
            "type":"Services"
        }
    ],
    "sg:phone":"+1 317 773 4606",
    "sg:postcode":"46060",
    "sg:province":"IN",
    "wof:name":"Great Clips",
    "wof:placetype":"venue"
},
  "geometry": {"coordinates":[-85.99803,40.037088],"type":"Point"}
}