{
  "type": "Feature",
  "properties": {
    "iso:country":"US",
    "sg:address":"2615 Wilson Ave",
    "sg:city":"Madison",
    "sg:classifiers":[
        {
            "category":"Health Services",
            "subcategory":"Chiropractor",
            "type":"Services"
        }
    ],
    "sg:phone":"+1 812 265 5369",
    "sg:postcode":"47250",
    "sg:province":"IN",
    "wof:name":"Tipton Chiropractic Ctr",
    "wof:placetype":"venue"
},
  "geometry": {"coordinates":[-85.405954,38.774539],"type":"Point"}
}