{
  "type": "Feature",
  "properties": {
    "addr:full":"4436 E Alquina Rd Connersville IN 47331",
    "addr:housenumber":"4436",
    "addr:postcode":"47331",
    "addr:street":"E Alquina Rd",
    "iso:country":"US",
    "sg:address":"4436 E Alquina Rd",
    "sg:city":"Connersville",
    "sg:classifiers":[
        {
            "category":"Organizations",
            "subcategory":"Religious Organization",
            "type":"Services"
        }
    ],
    "sg:phone":"+1 765 825 2458",
    "sg:postcode":"47331",
    "sg:province":"IN",
    "wof:name":"Alquina United Methdst Church",
    "wof:placetype":"venue"
},
  "geometry": {"coordinates":[-85.055509,39.613186],"type":"Point"}
}