{
  "type": "Feature",
  "properties": {
    "addr:full":"5015 Greenfield Dr Fort Wayne IN 46835",
    "addr:housenumber":"5015",
    "addr:postcode":"46835",
    "addr:street":"Greenfield Dr",
    "iso:country":"US",
    "sg:address":"5015 Greenfield Dr",
    "sg:city":"Fort Wayne",
    "sg:classifiers":[
        {
            "category":"Retail",
            "subcategory":"Repair Shop",
            "type":"Services"
        }
    ],
    "sg:phone":"+1 260 485 5048",
    "sg:postcode":"46835",
    "sg:province":"IN",
    "sg:tags":[
        "leather",
        "good"
    ],
    "wof:name":"Dr Vinyl Of South Ft Wayne",
    "wof:placetype":"venue"
},
  "geometry": {"coordinates":[-85.078227,41.137576],"type":"Point"}
}