{
  "type": "Feature",
  "properties": {
    "addr:full":"2354 N US Hwy 35 Laporte IN 46350",
    "addr:housenumber":"2354",
    "addr:postcode":"46350",
    "addr:street":"N Us Hwy 35",
    "iso:country":"US",
    "sg:address":"2354 N US Hwy 35",
    "sg:city":"Laporte",
    "sg:classifiers":[
        {
            "category":"Government",
            "subcategory":"Office",
            "type":"Public Place"
        }
    ],
    "sg:phone":"+1 219 326 0014",
    "sg:postcode":"46350",
    "sg:province":"IN",
    "sg:tags":[
        "county",
        "program"
    ],
    "sg:website":"www.solidwastedistrict.com",
    "wof:name":"Solid Waste District",
    "wof:placetype":"venue"
},
  "geometry": {"coordinates":[-86.763384,41.654653],"type":"Point"}
}