{
  "type": "Feature",
  "properties": {
    "addr:full":"9982 W 1200 S Brookston IN 47923",
    "addr:housenumber":"9982",
    "addr:postcode":"47923",
    "addr:street":"W 1200 S Brookston",
    "iso:country":"US",
    "sg:address":"9982 W 1200 S",
    "sg:city":"Brookston",
    "sg:phone":"+1 765 583 2848",
    "sg:postcode":"47923",
    "sg:province":"IN",
    "sg:tags":[
        "farm",
        "corn",
        "soybean"
    ],
    "wof:name":"Lehe John",
    "wof:placetype":"venue"
},
  "geometry": {"coordinates":[-87.056119,40.577189],"type":"Point"}
}