{
  "type": "Feature",
  "properties": {
    "iso:country":"US",
    "sg:address":"1225 Ransdell Ct",
    "sg:city":"Lebanon",
    "sg:classifiers":[
        {
            "category":"Building & Trades",
            "subcategory":"Plumbing",
            "type":"Services"
        }
    ],
    "sg:phone":"+1 765 482 1111",
    "sg:postcode":"46052",
    "sg:province":"IN",
    "sg:tags":[
        "heating",
        "contractor"
    ],
    "wof:name":"Ridgway Heating & Cooling Inc",
    "wof:placetype":"venue"
},
  "geometry": {"coordinates":[-86.481637,40.042735],"type":"Point"}
}