{
  "type": "Feature",
  "properties": {
    "iso:country":"US",
    "sg:address":"202 Main St",
    "sg:city":"Beech Grove",
    "sg:classifiers":[
        {
            "category":"Government",
            "subcategory":"Post Office",
            "type":"Public Place"
        }
    ],
    "sg:phone":"+1 317 000 1111",
    "sg:postcode":"46107",
    "sg:province":"IN",
    "wof:name":"US Post Office",
    "wof:placetype":"venue"
},
  "geometry": {"coordinates":[-86.084992,39.721828],"type":"Point"}
}