{
  "type": "Feature",
  "properties": {
    "addr:full":"617 Massachusetts Ave Indianapolis IN 46204",
    "addr:housenumber":"617",
    "addr:postcode":"46204",
    "addr:street":"Massachusetts Ave",
    "iso:country":"US",
    "sg:address":"617 Massachusetts Ave",
    "sg:city":"Indianapolis",
    "sg:classifiers":[
        {
            "category":"Shopping",
            "type":"Retail Goods"
        }
    ],
    "sg:phone":"+1 317 822 8455",
    "sg:postcode":"46204",
    "sg:province":"IN",
    "sg:tags":[
        "art",
        "gallery",
        "dealer"
    ],
    "wof:name":"Barry Franklin Gallery",
    "wof:placetype":"venue"
},
  "geometry": {"coordinates":[-86.148295,39.775402],"type":"Point"}
}