{
  "type": "Feature",
  "properties": {
    "iso:country":"US",
    "sg:address":"3807 Lafayette Rd",
    "sg:city":"Indianapolis",
    "sg:classifiers":[
        {
            "category":"Shopping",
            "subcategory":"Hobbies, Toys, & Games",
            "type":"Retail Goods"
        },
        {
            "category":"Recreation",
            "subcategory":"Fishing",
            "type":"Entertainment"
        },
        {
            "category":"Recreation",
            "subcategory":"Gun Range",
            "type":"Entertainment"
        }
    ],
    "sg:phone":"+1 317 297 4242",
    "sg:postcode":"46254",
    "sg:province":"IN",
    "sg:tags":[
        "ammunition",
        "bait",
        "instruction",
        "marksmanship",
        "gunsmith",
        "safety",
        "rifle",
        "pistol"
    ],
    "sg:website":"http://www.donsguns.com",
    "wof:name":"Don's Guns & Galleries Inc",
    "wof:placetype":"venue"
},
  "geometry": {"coordinates":[-86.234987,39.824199],"type":"Point"}
}