{
  "type": "Feature",
  "properties": {
    "addr:full":"107 Maples Trailer Park West Lafayette IN 47906",
    "addr:housenumber":"107",
    "addr:postcode":"47906",
    "addr:street":"Maples Trailer Park West",
    "iso:country":"US",
    "sg:address":"107 Maples Trailer Park",
    "sg:city":"West Lafayette",
    "sg:classifiers":[
        {
            "category":"Shopping",
            "subcategory":"Hobbies, Toys, & Games",
            "type":"Retail Goods"
        }
    ],
    "sg:phone":"+1 765 497 4518",
    "sg:postcode":"47906",
    "sg:province":"IN",
    "sg:tags":[
        "magician",
        "supply"
    ],
    "wof:name":"Ron London",
    "wof:placetype":"venue"
},
  "geometry": {"coordinates":[-86.951836,40.468553],"type":"Point"}
}