{
  "type": "Feature",
  "properties": {
    "addr:full":"5801 Plainview Dr Evansville IN 47720",
    "addr:housenumber":"5801",
    "addr:postcode":"47720",
    "addr:street":"Plainview Dr",
    "iso:country":"US",
    "sg:address":"5801 Plainview Dr",
    "sg:city":"Evansville",
    "sg:classifiers":[
        {
            "category":"Building & Trades",
            "subcategory":"Plumbing",
            "type":"Services"
        }
    ],
    "sg:phone":"+1 812 963 3357",
    "sg:postcode":"47720",
    "sg:province":"IN",
    "sg:tags":[
        "contractor"
    ],
    "wof:name":"Wingerts Plumbing Service",
    "wof:placetype":"venue"
},
  "geometry": {"coordinates":[-87.64397200000001,38.054871],"type":"Point"}
}