{
  "type": "Feature",
  "properties": {
    "iso:country":"US",
    "sg:address":"1803 N College Ave",
    "sg:city":"Bloomington",
    "sg:classifiers":[
        {
            "category":"Restaurant",
            "type":"Food & Drink"
        }
    ],
    "sg:phone":"+1 812 332 4838",
    "sg:postcode":"47404",
    "sg:province":"IN",
    "wof:name":"Huse Food Group Inc",
    "wof:placetype":"venue"
},
  "geometry": {"coordinates":[-86.534768,39.18037],"type":"Point"}
}