{
  "type": "Feature",
  "properties": {
    "addr:full":"413 W Water St Hartford City IN 47348",
    "addr:housenumber":"413",
    "addr:postcode":"47348",
    "addr:street":"W Water St",
    "iso:country":"US",
    "sg:address":"413 W Water St",
    "sg:city":"Hartford City",
    "sg:classifiers":[
        {
            "category":"Professional",
            "subcategory":"Business Services",
            "type":"Services"
        }
    ],
    "sg:phone":"+1 765 348 2587",
    "sg:postcode":"47348",
    "sg:province":"IN",
    "sg:tags":[
        "water",
        "treatment"
    ],
    "wof:name":"Ecowater Systems",
    "wof:placetype":"venue"
},
  "geometry": {"coordinates":[-85.37170500000001,40.45032],"type":"Point"}
}