{
  "type": "Feature",
  "properties": {
    "iso:country":"US",
    "sg:address":"1001 E 24th St",
    "sg:city":"Marion",
    "sg:classifiers":[
        {
            "category":"Home & Garden",
            "subcategory":"Furniture",
            "type":"Retail Goods"
        }
    ],
    "sg:phone":"+1 765 664 3938",
    "sg:postcode":"46953",
    "sg:province":"IN",
    "sg:tags":[
        "cabinet"
    ],
    "wof:name":"Mid West Cabinet Solutions Inc",
    "wof:placetype":"venue"
},
  "geometry": {"coordinates":[-85.647261,40.539315],"type":"Point"}
}