{
  "type": "Feature",
  "properties": {
    "iso:country":"US",
    "sg:address":"422 High St",
    "sg:city":"Logansport",
    "sg:classifiers":[
        {
            "category":"Professional",
            "subcategory":"Accounting & Tax Preparation",
            "type":"Services"
        }
    ],
    "sg:phone":"+1 574 753 7387",
    "sg:postcode":"46947",
    "sg:province":"IN",
    "sg:tags":[
        "return",
        "filing"
    ],
    "wof:name":"H & R Block Tax Svc",
    "wof:placetype":"venue"
},
  "geometry": {"coordinates":[-86.365377,40.75652],"type":"Point"}
}