{
  "type": "Feature",
  "properties": {
    "iso:country":"US",
    "sg:address":"230 W 3rd St",
    "sg:city":"Rushville",
    "sg:classifiers":[
        {
            "category":"Government",
            "subcategory":"Post Office",
            "type":"Public Place"
        }
    ],
    "sg:phone":"+1 765 932 3139",
    "sg:postcode":"46173",
    "sg:province":"IN",
    "sg:tags":[
        "postal",
        "us"
    ],
    "wof:name":"US Post Office",
    "wof:placetype":"venue"
},
  "geometry": {"coordinates":[-85.446692,39.609381],"type":"Point"}
}