{
  "type": "Feature",
  "properties": {
    "iso:country":"US",
    "sg:address":"4730 S Scatterfield Rd",
    "sg:city":"Anderson",
    "sg:classifiers":[
        {
            "category":"Bakery",
            "type":"Food & Drink"
        }
    ],
    "sg:menulink":"http://www.allmenus.com/in/anderson/102980-panera-bread/menu/",
    "sg:phone":"+1 765 622 9115",
    "sg:postcode":"46013",
    "sg:province":"IN",
    "sg:tags":[
        "american",
        "sandwich",
        "pastry"
    ],
    "wof:name":"Panera Bread",
    "wof:placetype":"venue"
},
  "geometry": {"coordinates":[-85.65263400000001,40.065378],"type":"Point"}
}