{
  "type": "Feature",
  "properties": {
    "addr:full":"2 N Meridian St Indianapolis IN 46204",
    "addr:housenumber":"2",
    "addr:postcode":"46204",
    "addr:street":"N Meridian St",
    "iso:country":"US",
    "sg:address":"2 N Meridian St",
    "sg:city":"Indianapolis",
    "sg:classifiers":[
        {
            "category":"Banks & Credit Unions",
            "subcategory":"Bank",
            "type":"Services"
        }
    ],
    "sg:phone":"+1 317 634 0916",
    "sg:postcode":"46204",
    "sg:province":"IN",
    "wof:name":"Flagstar Bank",
    "wof:placetype":"venue"
},
  "geometry": {"coordinates":[-86.15807599999999,39.767595],"type":"Point"}
}