{
  "type": "Feature",
  "properties": {
    "iso:country":"US",
    "sg:address":"19 NW 4th St",
    "sg:city":"Evansville",
    "sg:classifiers":[
        {
            "category":"Real Estate",
            "subcategory":"Real Estate Services",
            "type":"Services"
        }
    ],
    "sg:phone":"+1 812 468 8485",
    "sg:postcode":"47708",
    "sg:province":"IN",
    "sg:tags":[
        "company",
        "title"
    ],
    "wof:name":"Total Title Svc LLC",
    "wof:placetype":"venue"
},
  "geometry": {"coordinates":[-87.57161499999999,37.972296],"type":"Point"}
}