{
  "type": "Feature",
  "properties": {
    "iso:country":"US",
    "sg:address":"9379 Mount Tabor Ct",
    "sg:city":"Aurora",
    "sg:classifiers":[
        {
            "category":"Professional",
            "subcategory":"Computer Services",
            "type":"Services"
        }
    ],
    "sg:phone":"+1 812 926 1828",
    "sg:postcode":"47001",
    "sg:province":"IN",
    "sg:tags":[
        "consultant",
        "designer"
    ],
    "wof:name":"Neusys Inc",
    "wof:placetype":"venue"
},
  "geometry": {"coordinates":[-84.993092,39.025803],"type":"Point"}
}