{
  "type": "Feature",
  "properties": {
    "addr:full":"7405 Westfield Blvd Indianapolis IN 46240",
    "addr:housenumber":"7405",
    "addr:postcode":"46240",
    "addr:street":"Westfield Blvd",
    "iso:country":"US",
    "sg:address":"7405 Westfield Blvd",
    "sg:city":"Indianapolis",
    "sg:classifiers":[
        {
            "category":"Wholesale",
            "subcategory":"Medical Equipment & Supplies",
            "type":"Manufacturing & Wholesale Goods"
        },
        {
            "category":"Shopping",
            "subcategory":"Pharmacy",
            "type":"Retail Goods"
        },
        {
            "category":"Health Services",
            "subcategory":"Dentist",
            "type":"Services"
        }
    ],
    "sg:phone":"+1 317 202 9381",
    "sg:postcode":"46240",
    "sg:province":"IN",
    "sg:tags":[
        "home",
        "dental",
        "care"
    ],
    "wof:name":"National Laser Technology Inc",
    "wof:placetype":"venue"
},
  "geometry": {"coordinates":[-86.14022900000001,39.88902],"type":"Point"}
}