{
  "type": "Feature",
  "properties": {
    "iso:country":"US",
    "sg:address":"6389 State Rd 234 E",
    "sg:city":"Ladoga",
    "sg:classifiers":[
        {
            "category":"Professional",
            "type":"Services"
        }
    ],
    "sg:phone":"+1 765 942 0530",
    "sg:postcode":"47954",
    "sg:province":"IN",
    "wof:name":"Actis Building Inc",
    "wof:placetype":"venue"
},
  "geometry": {"coordinates":[-86.784255,39.915634],"type":"Point"}
}