{
  "type": "Feature",
  "properties": {
    "addr:full":"211 Circle St Terre Haute IN 47803",
    "addr:housenumber":"211",
    "addr:postcode":"47803",
    "addr:street":"Circle St",
    "iso:country":"US",
    "sg:address":"211 Circle St",
    "sg:city":"Terre Haute",
    "sg:classifiers":[
        {
            "category":"Professional",
            "subcategory":"Management & Consulting",
            "type":"Services"
        }
    ],
    "sg:phone":"+1 812 877 3105",
    "sg:postcode":"47803",
    "sg:province":"IN",
    "sg:tags":[
        "development",
        "project",
        "for",
        "community"
    ],
    "wof:name":"C J Stewart Group Inc",
    "wof:placetype":"venue"
},
  "geometry": {"coordinates":[-87.339771,39.471507],"type":"Point"}
}