{
  "type": "Feature",
  "properties": {
    "iso:country":"US",
    "sg:address":"6136 E Co Rd 700 S",
    "sg:city":"Plainfield",
    "sg:classifiers":[
        {
            "category":"Building & Trades",
            "subcategory":"Construction",
            "type":"Services"
        }
    ],
    "sg:phone":"+1 317 837 8252",
    "sg:postcode":"46168",
    "sg:province":"IN",
    "sg:tags":[
        "general",
        "contractor"
    ],
    "wof:name":"Construction Kemps",
    "wof:placetype":"venue"
},
  "geometry": {"coordinates":[-86.41503400000001,39.660816],"type":"Point"}
}