{
  "type": "Feature",
  "properties": {
    "iso:country":"US",
    "sg:address":"1739 N 4th St",
    "sg:city":"Terre Haute",
    "sg:classifiers":[
        {
            "category":"Health Services",
            "subcategory":"Doctor",
            "type":"Services"
        }
    ],
    "sg:phone":"+1 812 242 3600",
    "sg:postcode":"47804",
    "sg:province":"IN",
    "sg:tags":[
        "physician",
        "surgeon"
    ],
    "wof:name":"A P & S CLINIC LLC",
    "wof:placetype":"venue"
},
  "geometry": {"coordinates":[-87.412755,39.486148],"type":"Point"}
}