{
  "type": "Feature",
  "properties": {
    "iso:country":"US",
    "sg:address":"15210 S 300 W",
    "sg:city":"Columbus",
    "sg:phone":"+1 812 342 6859",
    "sg:postcode":"47201",
    "sg:province":"IN",
    "sg:tags":[
        "farm",
        "corn"
    ],
    "wof:name":"Greg Meyer",
    "wof:placetype":"venue"
},
  "geometry": {"coordinates":[-85.96583699999999,39.065005],"type":"Point"}
}