{
  "type": "Feature",
  "properties": {
    "iso:country":"US",
    "sg:address":"5830 US Hwy 6",
    "sg:city":"Portage",
    "sg:classifiers":[
        {
            "category":"Wholesale",
            "subcategory":"Construction Materials",
            "type":"Manufacturing & Wholesale Goods"
        }
    ],
    "sg:phone":"+1 219 764 0755",
    "sg:postcode":"46368",
    "sg:province":"IN",
    "sg:tags":[
        "fence"
    ],
    "wof:name":"Fetzer Fence",
    "wof:placetype":"venue"
},
  "geometry": {"coordinates":[-87.18818899999999,41.550587],"type":"Point"}
}