{
  "type": "Feature",
  "properties": {
    "iso:country":"US",
    "sg:address":"2815 Foreman Dr",
    "sg:city":"Warsaw",
    "sg:classifiers":[
        {
            "category":"Airline",
            "type":"Transportation"
        }
    ],
    "sg:phone":"+1 574 267 3038",
    "sg:postcode":"46582",
    "sg:province":"IN",
    "sg:tags":[
        "company"
    ],
    "wof:name":"Image Air Inc",
    "wof:placetype":"venue"
},
  "geometry": {"coordinates":[-85.835485,41.275447],"type":"Point"}
}