{
  "type": "Feature",
  "properties": {
    "iso:country":"US",
    "sg:address":"9444 Hadway Dr",
    "sg:city":"Indianapolis",
    "sg:classifiers":[
        {
            "category":"Health Services",
            "subcategory":"Clinic",
            "type":"Services"
        }
    ],
    "sg:phone":"+1 317 578 7960",
    "sg:postcode":"46256",
    "sg:province":"IN",
    "wof:name":"Health Resources Inc",
    "wof:placetype":"venue"
},
  "geometry": {"coordinates":[-86.016813,39.925079],"type":"Point"}
}