{
  "type": "Feature",
  "properties": {
    "iso:country":"US",
    "sg:address":"4602 Pumpkin Vine Dr",
    "sg:city":"Kokomo",
    "sg:classifiers":[
        {
            "category":"Personal",
            "subcategory":"Beauty Salon",
            "type":"Services"
        }
    ],
    "sg:phone":"+1 765 457 4478",
    "sg:postcode":"46902",
    "sg:province":"IN",
    "wof:name":"Little Candle-Opera-Candle",
    "wof:placetype":"venue"
},
  "geometry": {"coordinates":[-86.060425,40.465552],"type":"Point"}
}