{
  "type": "Feature",
  "properties": {
    "iso:country":"US",
    "sg:address":"4196 Mueller Rd",
    "sg:city":"Cedar Grove",
    "sg:classifiers":[
        {
            "category":"Farming",
            "subcategory":"Farm",
            "type":"Manufacturing & Wholesale Goods"
        }
    ],
    "sg:phone":"+1 765 647 4092",
    "sg:postcode":"47016",
    "sg:province":"IN",
    "sg:tags":[
        "crop",
        "general"
    ],
    "wof:name":"Ralph Frey",
    "wof:placetype":"venue"
},
  "geometry": {"coordinates":[-84.883057,39.354654],"type":"Point"}
}