{
  "type": "Feature",
  "properties": {
    "iso:country":"US",
    "sg:address":"1546 E Daisy Ln",
    "sg:city":"Salem",
    "sg:classifiers":[
        {
            "category":"Building & Trades",
            "subcategory":"Construction",
            "type":"Services"
        }
    ],
    "sg:phone":"+1 812 883 5921",
    "sg:postcode":"47167",
    "sg:province":"IN",
    "sg:tags":[
        "general",
        "contractor"
    ],
    "wof:name":"Babbitt Construction Inc",
    "wof:placetype":"venue"
},
  "geometry": {"coordinates":[-86.077521,38.521824],"type":"Point"}
}