{
  "type": "Feature",
  "properties": {
    "iso:country":"US",
    "sg:address":"706 Shannon Dr",
    "sg:city":"Chesterton",
    "sg:classifiers":[
        {
            "category":"Wholesale",
            "subcategory":"Office Equipment",
            "type":"Manufacturing & Wholesale Goods"
        }
    ],
    "sg:phone":"+1 219 926 3156",
    "sg:postcode":"46304",
    "sg:province":"IN",
    "wof:name":"Dunes Office Equipment",
    "wof:placetype":"venue"
},
  "geometry": {"coordinates":[-87.06111799999999,41.601383],"type":"Point"}
}