{
  "type": "Feature",
  "properties": {
    "iso:country":"US",
    "sg:address":"938 Knowles St",
    "sg:city":"Clinton",
    "sg:classifiers":[
        {
            "category":"Place Of Worship",
            "type":"Public Place"
        }
    ],
    "sg:phone":"+1 765 832 6457",
    "sg:postcode":"47842",
    "sg:province":"IN",
    "sg:tags":[
        "church"
    ],
    "wof:name":"Diana M Church",
    "wof:placetype":"venue"
},
  "geometry": {"coordinates":[-87.40900499999999,39.66597],"type":"Point"}
}