{
  "type": "Feature",
  "properties": {
    "iso:country":"US",
    "sg:address":"4669 Purdue Rd",
    "sg:city":"Vincennes",
    "sg:phone":"+1 812 886 9661",
    "sg:postcode":"47591",
    "sg:province":"IN",
    "sg:tags":[
        "agricultural",
        "product"
    ],
    "wof:name":"Southwest Purdue Ag Ctr",
    "wof:placetype":"venue"
},
  "geometry": {"coordinates":[-87.483609,38.739064],"type":"Point"}
}