{
  "type": "Feature",
  "properties": {
    "iso:country":"US",
    "sg:address":"2967 Willowcreek Rd",
    "sg:city":"Portage",
    "sg:classifiers":[
        {
            "category":"Social Services",
            "type":"Services"
        }
    ],
    "sg:phone":"+1 219 762 1177",
    "sg:postcode":"46368",
    "sg:province":"IN",
    "sg:tags":[
        "organization",
        "welfare"
    ],
    "wof:name":"Catholic Family Svc",
    "wof:placetype":"venue"
},
  "geometry": {"coordinates":[-87.18277,41.565815],"type":"Point"}
}