{
  "type": "Feature",
  "properties": {
    "addr:full":"1305 Eugene St Indianapolis IN 46208",
    "addr:housenumber":"1305",
    "addr:postcode":"46208",
    "addr:street":"Eugene St",
    "iso:country":"US",
    "sg:address":"1305 Eugene St",
    "sg:city":"Indianapolis",
    "sg:classifiers":[
        {
            "category":"Personal",
            "subcategory":"Beauty Salon",
            "type":"Services"
        }
    ],
    "sg:phone":"+1 317 925 5471",
    "sg:postcode":"46208",
    "sg:province":"IN",
    "sg:tags":[
        "manicuring"
    ],
    "wof:name":"Jamika's Pedicure",
    "wof:placetype":"venue"
},
  "geometry": {"coordinates":[-86.18577500000001,39.809042],"type":"Point"}
}