{
  "type": "Feature",
  "properties": {
    "iso:country":"US",
    "sg:address":"2 S 3rd St",
    "sg:city":"Flora",
    "sg:classifiers":[
        {
            "category":"Education",
            "subcategory":"School",
            "type":"Public Place"
        }
    ],
    "sg:phone":"+1 574 967 4113",
    "sg:postcode":"46929",
    "sg:province":"IN",
    "wof:name":"Carroll Superintendent's Ofc",
    "wof:placetype":"venue"
},
  "geometry": {"coordinates":[-86.515268,40.548047],"type":"Point"}
}