{
  "type": "Feature",
  "properties": {
    "addr:full":"3810 S Post Rd Indianapolis IN 46239",
    "addr:housenumber":"3810",
    "addr:postcode":"46239",
    "addr:street":"S Post Rd",
    "iso:country":"US",
    "sg:address":"3810 S Post Rd",
    "sg:city":"Indianapolis",
    "sg:classifiers":[
        {
            "category":"Restaurant",
            "type":"Food & Drink"
        }
    ],
    "sg:menulink":"http://www.allmenus.com/in/wanamaker/174127-wendys/menu/",
    "sg:phone":"+1 317 862 6547",
    "sg:postcode":"46239",
    "sg:province":"IN",
    "sg:tags":[
        "burger",
        "american",
        "soup"
    ],
    "wof:name":"Wendy's",
    "wof:placetype":"venue"
},
  "geometry": {"coordinates":[-86.008948,39.713099],"type":"Point"}
}