{
  "type": "Feature",
  "properties": {
    "iso:country":"US",
    "sg:address":"647 E Main St",
    "sg:city":"Danville",
    "sg:classifiers":[
        {
            "category":"Autos & Motor Vehicles",
            "subcategory":"Auto Supplies",
            "type":"Retail Goods"
        }
    ],
    "sg:phone":"+1 317 718 1145",
    "sg:postcode":"46122",
    "sg:province":"IN",
    "sg:tags":[
        "automobile",
        "parts"
    ],
    "wof:name":"Advance Auto Parts Inc",
    "wof:placetype":"venue"
},
  "geometry": {"coordinates":[-86.514415,39.760103],"type":"Point"}
}