{
  "type": "Feature",
  "properties": {
    "iso:country":"US",
    "sg:address":"4165 E Allison Rd",
    "sg:city":"Camby",
    "sg:classifiers":[
        {
            "category":"Retail",
            "subcategory":"Funeral Services",
            "type":"Services"
        }
    ],
    "sg:phone":"+1 317 831 0200",
    "sg:postcode":"46113",
    "sg:province":"IN",
    "sg:tags":[
        "director"
    ],
    "sg:website":"www.jonesfamilymortuary.com",
    "wof:name":"Jones Family Mortuary",
    "wof:placetype":"venue"
},
  "geometry": {"coordinates":[-86.32658600000001,39.624811],"type":"Point"}
}