{
  "type": "Feature",
  "properties": {
    "iso:country":"US",
    "sg:address":"1130 E Creighton Ave",
    "sg:city":"Fort Wayne",
    "sg:classifiers":[
        {
            "category":"Retail",
            "subcategory":"Auto Repair",
            "type":"Services"
        }
    ],
    "sg:phone":"+1 260 745 0707",
    "sg:postcode":"46803",
    "sg:province":"IN",
    "sg:tags":[
        "automotive"
    ],
    "wof:name":"Gary McKee",
    "wof:placetype":"venue"
},
  "geometry": {"coordinates":[-85.12218,41.064737],"type":"Point"}
}