{
  "type": "Feature",
  "properties": {
    "addr:full":"1234 State Rd 2 Laporte IN 46350",
    "addr:housenumber":"1234",
    "addr:postcode":"46350",
    "addr:street":"State Rd 2",
    "iso:country":"US",
    "sg:address":"1234 State Rd 2",
    "sg:city":"Laporte",
    "sg:classifiers":[
        {
            "category":"Food & Beverages",
            "subcategory":"Groceries & Convenience Stores",
            "type":"Retail Goods"
        }
    ],
    "sg:phone":"+1 219 000 1111",
    "sg:postcode":"46350",
    "sg:province":"IN",
    "sg:tags":[
        "grocer"
    ],
    "wof:name":"Aldi",
    "wof:placetype":"venue"
},
  "geometry": {"coordinates":[-86.732896,41.600937],"type":"Point"}
}