{
  "type": "Feature",
  "properties": {
    "addr:full":"8571 E Old Maple Ave Terre Haute IN 47803",
    "addr:housenumber":"8571",
    "addr:postcode":"47803",
    "addr:street":"E Old Maple Ave",
    "iso:country":"US",
    "sg:address":"8571 E Old Maple Ave",
    "sg:city":"Terre Haute",
    "sg:classifiers":[
        {
            "category":"Real Estate",
            "subcategory":"Real Estate Operator",
            "type":"Services"
        }
    ],
    "sg:phone":"+1 812 877 9357",
    "sg:postcode":"47803",
    "sg:province":"IN",
    "sg:tags":[
        "apartment"
    ],
    "wof:name":"Maplewood Apartments",
    "wof:placetype":"venue"
},
  "geometry": {"coordinates":[-87.281351,39.49158],"type":"Point"}
}