{
  "type": "Feature",
  "properties": {
    "addr:full":"101 N Jefferson St Mooreland IN 47360",
    "addr:housenumber":"101",
    "addr:postcode":"47360",
    "addr:street":"N Jefferson St",
    "iso:country":"US",
    "sg:address":"101 N Jefferson St",
    "sg:city":"Mooreland",
    "sg:classifiers":[
        {
            "category":"Organizations",
            "subcategory":"Religious Organization",
            "type":"Services"
        }
    ],
    "sg:phone":"+1 765 766 5656",
    "sg:postcode":"47360",
    "sg:province":"IN",
    "sg:tags":[
        "church"
    ],
    "wof:name":"Mooreland Friends Meeting",
    "wof:placetype":"venue"
},
  "geometry": {"coordinates":[-85.252403,39.998324],"type":"Point"}
}