{
  "type": "Feature",
  "properties": {
    "iso:country":"US",
    "sg:address":"3298 W 246th St",
    "sg:city":"Sheridan",
    "sg:classifiers":[
        {
            "category":"Organizations",
            "subcategory":"Religious Organization",
            "type":"Services"
        }
    ],
    "sg:phone":"+1 317 758 1619",
    "sg:postcode":"46069",
    "sg:province":"IN",
    "wof:name":"V J Stover Rev",
    "wof:placetype":"venue"
},
  "geometry": {"coordinates":[-86.214182,40.14438],"type":"Point"}
}