{
  "type": "Feature",
  "properties": {
    "iso:country":"US",
    "sg:address":"5008 Washington St",
    "sg:city":"Westpoint",
    "sg:classifiers":[
        {
            "category":"Building & Trades",
            "subcategory":"Construction",
            "type":"Services"
        }
    ],
    "sg:phone":"+1 765 572 2550",
    "sg:postcode":"47992",
    "sg:province":"IN",
    "sg:tags":[
        "excavating",
        "contractor"
    ],
    "wof:name":"Cheesman Inc",
    "wof:placetype":"venue"
},
  "geometry": {"coordinates":[-87.042961,40.344895],"type":"Point"}
}