{
  "type": "Feature",
  "properties": {
    "iso:country":"US",
    "sg:address":"65 Airport Pkwy",
    "sg:city":"Greenwood",
    "sg:classifiers":[
        {
            "category":"Banks & Credit Unions",
            "subcategory":"Investment Brokerage",
            "type":"Services"
        }
    ],
    "sg:phone":"+1 317 881 2220",
    "sg:postcode":"46143",
    "sg:province":"IN",
    "sg:tags":[
        "stock",
        "bond"
    ],
    "sg:website":"www.agedwards.com",
    "wof:name":"A G Edwards & Sons Inc",
    "wof:placetype":"venue"
},
  "geometry": {"coordinates":[-86.089832,39.617373],"type":"Point"}
}