{
  "type": "Feature",
  "properties": {
    "iso:country":"US",
    "sg:address":"98 N Lovers Ln",
    "sg:city":"Franklin",
    "sg:classifiers":[
        {
            "category":"Restaurant",
            "type":"Food & Drink"
        }
    ],
    "sg:menulink":"http://www.allmenus.com/in/needham/140727-waffle-house/menu/",
    "sg:phone":"+1 770 455 3447",
    "sg:postcode":"46131",
    "sg:province":"IN",
    "sg:tags":[
        "american"
    ],
    "wof:name":"Waffle House",
    "wof:placetype":"venue"
},
  "geometry": {"coordinates":[-86.01726499999999,39.481715],"type":"Point"}
}