{
  "type": "Feature",
  "properties": {
    "iso:country":"US",
    "sg:address":"2922 Marrett Dr",
    "sg:city":"Mishawaka",
    "sg:classifiers":[
        {
            "category":"Social Services",
            "subcategory":"Child Care",
            "type":"Services"
        }
    ],
    "sg:phone":"+1 574 255 5810",
    "sg:postcode":"46544",
    "sg:province":"IN",
    "sg:tags":[
        "day"
    ],
    "wof:name":"Little Sweethearts Daycare",
    "wof:placetype":"venue"
},
  "geometry": {"coordinates":[-86.131894,41.650114],"type":"Point"}
}