{
  "type": "Feature",
  "properties": {
    "iso:country":"US",
    "sg:address":"1806 W Winona Ave",
    "sg:city":"Warsaw",
    "sg:classifiers":[
        {
            "category":"Wholesale",
            "subcategory":"Auto Parts",
            "type":"Manufacturing & Wholesale Goods"
        }
    ],
    "sg:phone":"+1 574 267 8086",
    "sg:postcode":"46580",
    "sg:province":"IN",
    "sg:tags":[
        "automobile",
        "rebuilt"
    ],
    "wof:name":"Mike Gill Auto & Truck Parts",
    "wof:placetype":"venue"
},
  "geometry": {"coordinates":[-85.882762,41.233697],"type":"Point"}
}