{
  "type": "Feature",
  "properties": {
    "iso:country":"US",
    "sg:address":"654 N Jefferson St",
    "sg:city":"Muncie",
    "sg:classifiers":[
        {
            "category":"Organizations",
            "subcategory":"Religious Organization",
            "type":"Services"
        }
    ],
    "sg:phone":"+1 765 284 1783",
    "sg:postcode":"47305",
    "sg:province":"IN",
    "sg:tags":[
        "church"
    ],
    "wof:name":"Christ Temple Ministries",
    "wof:placetype":"venue"
},
  "geometry": {"coordinates":[-85.38405,40.198755],"type":"Point"}
}