{
  "type": "Feature",
  "properties": {
    "iso:country":"US",
    "sg:address":"3111 Eastbrook Blvd",
    "sg:city":"Jeffersonville",
    "sg:classifiers":[
        {
            "category":"Building & Trades",
            "subcategory":"Cleaning & Sanitation",
            "type":"Services"
        }
    ],
    "sg:phone":"+1 812 285 9038",
    "sg:postcode":"47130",
    "sg:province":"IN",
    "sg:tags":[
        "janitor"
    ],
    "wof:name":"Tobin's Cleaning Svc",
    "wof:placetype":"venue"
},
  "geometry": {"coordinates":[-85.715839,38.331629],"type":"Point"}
}