{
  "type": "Feature",
  "properties": {
    "addr:full":"13936 Hoagland Rd Monroeville IN 46773",
    "addr:housenumber":"13936",
    "addr:postcode":"46773",
    "addr:street":"Hoagland Rd",
    "iso:country":"US",
    "sg:address":"13936 Hoagland Rd",
    "sg:city":"Monroeville",
    "sg:phone":"+1 260 639 6120",
    "sg:postcode":"46773",
    "sg:province":"IN",
    "sg:tags":[
        "farm",
        "corn",
        "wheat",
        "soybean"
    ],
    "wof:name":"Genth Deveta",
    "wof:placetype":"venue"
},
  "geometry": {"coordinates":[-84.957048,40.948843],"type":"Point"}
}