{
  "type": "Feature",
  "properties": {
    "iso:country":"US",
    "sg:address":"12465 Keeley Ct",
    "sg:city":"Fishers",
    "sg:classifiers":[
        {
            "category":"Building & Trades",
            "subcategory":"Construction",
            "type":"Services"
        }
    ],
    "sg:phone":"+1 317 570 3699",
    "sg:postcode":"46038",
    "sg:province":"IN",
    "sg:tags":[
        "house"
    ],
    "wof:name":"Garrison Builders Incorporated",
    "wof:placetype":"venue"
},
  "geometry": {"coordinates":[-86.00561399999999,39.967933],"type":"Point"}
}