{
  "type": "Feature",
  "properties": {
    "iso:country":"US",
    "sg:address":"2903 W 3rd St",
    "sg:city":"Bloomington",
    "sg:classifiers":[
        {
            "category":"Home & Garden",
            "subcategory":"Carpets & Floor Coverings",
            "type":"Retail Goods"
        }
    ],
    "sg:phone":"+1 812 332 6555",
    "sg:postcode":"47404",
    "sg:province":"IN",
    "sg:tags":[
        "carpeting"
    ],
    "wof:name":"Bounds and Mc Pike Carpet",
    "wof:placetype":"venue"
},
  "geometry": {"coordinates":[-86.570702,39.164398],"type":"Point"}
}