{
  "type": "Feature",
  "properties": {
    "iso:country":"US",
    "sg:address":"111 S Main St",
    "sg:city":"Salem",
    "sg:classifiers":[
        {
            "category":"Insurance",
            "subcategory":"Insurance Agent",
            "type":"Services"
        }
    ],
    "sg:phone":"+1 812 883 2806",
    "sg:postcode":"47167",
    "sg:province":"IN",
    "wof:name":"Nale Insurance",
    "wof:placetype":"venue"
},
  "geometry": {"coordinates":[-86.100829,38.605192],"type":"Point"}
}