{
  "type": "Feature",
  "properties": {
    "iso:country":"US",
    "sg:address":"1615 W Edgewood Ave",
    "sg:city":"Indianapolis",
    "sg:classifiers":[
        {
            "category":"Retail",
            "subcategory":"Auto Repair",
            "type":"Services"
        }
    ],
    "sg:phone":"+1 317 784 9224",
    "sg:postcode":"46217",
    "sg:province":"IN",
    "sg:tags":[
        "repairing",
        "automobile"
    ],
    "wof:name":"Virgil's Garage",
    "wof:placetype":"venue"
},
  "geometry": {"coordinates":[-86.191434,39.678304],"type":"Point"}
}