{
  "type": "Feature",
  "properties": {
    "iso:country":"US",
    "sg:address":"52080 Barrington Pl",
    "sg:city":"Granger",
    "sg:classifiers":[
        {
            "category":"Professional",
            "subcategory":"Management & Consulting",
            "type":"Services"
        }
    ],
    "sg:phone":"+1 574 273 9515",
    "sg:postcode":"46530",
    "sg:province":"IN",
    "sg:tags":[
        "business"
    ],
    "wof:name":"Five Star Consulting",
    "wof:placetype":"venue"
},
  "geometry": {"coordinates":[-86.132655,41.738444],"type":"Point"}
}