{
  "type": "Feature",
  "properties": {
    "addr:full":"6501 Grape Rd Mishawaka IN 46545",
    "addr:housenumber":"6501",
    "addr:postcode":"46545",
    "addr:street":"Grape Rd",
    "iso:country":"US",
    "sg:address":"6501 Grape Rd",
    "sg:city":"Mishawaka",
    "sg:classifiers":[
        {
            "category":"Retail",
            "subcategory":"Portrait Studio",
            "type":"Services"
        }
    ],
    "sg:phone":"+1 574 277 5638",
    "sg:postcode":"46545",
    "sg:province":"IN",
    "sg:tags":[
        "photographer"
    ],
    "wof:name":"J C Penney Portrait Studio",
    "wof:placetype":"venue"
},
  "geometry": {"coordinates":[-86.187781,41.716898],"type":"Point"}
}