{
  "type": "Feature",
  "properties": {
    "iso:country":"US",
    "sg:address":"6525 S Indianapolis Blvd",
    "sg:city":"Hammond",
    "sg:classifiers":[
        {
            "category":"Restaurant",
            "type":"Food & Drink"
        }
    ],
    "sg:phone":"+1 219 844 5951",
    "sg:postcode":"46320",
    "sg:province":"IN",
    "wof:name":"New Petros Restaurant",
    "wof:placetype":"venue"
},
  "geometry": {"coordinates":[-87.480797,41.5951],"type":"Point"}
}