{
  "type": "Feature",
  "properties": {
    "iso:country":"US",
    "sg:address":"1014 E Garfield Dr",
    "sg:city":"Indianapolis",
    "sg:classifiers":[
        {
            "category":"Organizations",
            "subcategory":"Religious Organization",
            "type":"Services"
        }
    ],
    "sg:phone":"+1 317 784 8810",
    "sg:postcode":"46203",
    "sg:province":"IN",
    "sg:tags":[
        "church"
    ],
    "wof:name":"Faith Temple Church Inc",
    "wof:placetype":"venue"
},
  "geometry": {"coordinates":[-86.139953,39.733787],"type":"Point"}
}