{
  "type": "Feature",
  "properties": {
    "iso:country":"US",
    "sg:address":"24 W 6th St",
    "sg:city":"Anderson",
    "sg:classifiers":[
        {
            "category":"Retail",
            "subcategory":"Auto Repair",
            "type":"Services"
        }
    ],
    "sg:phone":"+1 765 643 8897",
    "sg:postcode":"46016",
    "sg:province":"IN",
    "sg:tags":[
        "body",
        "automobile",
        "painting"
    ],
    "wof:name":"Bob Brown Auto Body",
    "wof:placetype":"venue"
},
  "geometry": {"coordinates":[-85.680316,40.109944],"type":"Point"}
}