{
  "type": "Feature",
  "properties": {
    "iso:country":"US",
    "sg:address":"9685 S State Rd 55",
    "sg:city":"Brook",
    "sg:classifiers":[
        {
            "category":"Wholesale",
            "subcategory":"Poultry",
            "type":"Manufacturing & Wholesale Goods"
        }
    ],
    "sg:phone":"+1 219 275 8131",
    "sg:postcode":"47922",
    "sg:province":"IN",
    "sg:tags":[
        "eggs"
    ],
    "wof:name":"Newton County Egg Farm",
    "wof:placetype":"venue"
},
  "geometry": {"coordinates":[-87.295693,40.91438],"type":"Point"}
}