{
  "type": "Feature",
  "properties": {
    "iso:country":"US",
    "sg:address":"4001 E 21st St",
    "sg:city":"Indianapolis",
    "sg:classifiers":[
        {
            "category":"Government",
            "subcategory":"Office",
            "type":"Public Place"
        }
    ],
    "sg:phone":"+1 317 221 7440",
    "sg:postcode":"46218",
    "sg:province":"IN",
    "sg:website":"www.hhcorp.org",
    "wof:name":"Marion County Mosquito Control",
    "wof:placetype":"venue"
},
  "geometry": {"coordinates":[-86.097546,39.796129],"type":"Point"}
}