{
  "type": "Feature",
  "properties": {
    "iso:country":"US",
    "sg:address":"617 Main St",
    "sg:city":"Jasper",
    "sg:classifiers":[
        {
            "category":"Restaurant",
            "type":"Food & Drink"
        }
    ],
    "sg:phone":"+1 812 634 9931",
    "sg:postcode":"47546",
    "sg:province":"IN",
    "wof:name":"Katie's Corner",
    "wof:placetype":"venue"
},
  "geometry": {"coordinates":[-86.930878,38.392127],"type":"Point"}
}