{
  "type": "Feature",
  "properties": {
    "iso:country":"US",
    "sg:address":"1726 Co Rd 28",
    "sg:city":"Auburn",
    "sg:classifiers":[
        {
            "category":"Travel",
            "subcategory":"Hotels & Motels",
            "type":"Entertainment"
        }
    ],
    "sg:phone":"+1 260 281 2298",
    "sg:postcode":"46706",
    "sg:province":"IN",
    "sg:tags":[
        "operation"
    ],
    "wof:name":"Hilltop Country Inn",
    "wof:placetype":"venue"
},
  "geometry": {"coordinates":[-85.100188,41.425256],"type":"Point"}
}