{
  "type": "Feature",
  "properties": {
    "iso:country":"US",
    "sg:address":"602 S College Ave",
    "sg:city":"Greencastle",
    "sg:classifiers":[
        {
            "category":"Education",
            "subcategory":"College",
            "type":"Public Place"
        }
    ],
    "sg:phone":"+1 765 658 4800",
    "sg:postcode":"46135",
    "sg:province":"IN",
    "sg:tags":[
        "science",
        "center",
        "math"
    ],
    "wof:name":"Julian Science & Math Center",
    "wof:placetype":"venue"
},
  "geometry": {"coordinates":[-86.862614,39.639039],"type":"Point"}
}