{
  "type": "Feature",
  "properties": {
    "addr:full":"625 N Mill St Hartford City IN 47348",
    "addr:housenumber":"625",
    "addr:postcode":"47348",
    "addr:street":"N Mill St",
    "iso:country":"US",
    "sg:address":"625 N Mill St",
    "sg:city":"Hartford City",
    "sg:classifiers":[
        {
            "category":"Organizations",
            "subcategory":"Community Association",
            "type":"Services"
        }
    ],
    "sg:phone":"+1 765 348 4281",
    "sg:postcode":"47348",
    "sg:province":"IN",
    "wof:name":"Blackford County Girl Scout",
    "wof:placetype":"venue"
},
  "geometry": {"coordinates":[-85.360721,40.455704],"type":"Point"}
}