{
  "type": "Feature",
  "properties": {
    "iso:country":"US",
    "sg:address":"393 E US Hwy 30",
    "sg:city":"Valparaiso",
    "sg:classifiers":[
        {
            "category":"Autos & Motor Vehicles",
            "subcategory":"Motorcycle Sales",
            "type":"Retail Goods"
        }
    ],
    "sg:phone":"+1 219 477 4700",
    "sg:postcode":"46383",
    "sg:province":"IN",
    "sg:tags":[
        "scooter"
    ],
    "sg:website":"www.buckspowersports.com",
    "wof:name":"Buck's Power Sports",
    "wof:placetype":"venue"
},
  "geometry": {"coordinates":[-86.98927999999999,41.443583],"type":"Point"}
}