{
  "type": "Feature",
  "properties": {
    "addr:full":"7626 E 88th Pl Indianapolis IN 46256",
    "addr:housenumber":"7626",
    "addr:postcode":"46256",
    "addr:street":"E 88Th Pl",
    "iso:country":"US",
    "sg:address":"7626 E 88th Pl",
    "sg:city":"Indianapolis",
    "sg:classifiers":[
        {
            "category":"Retail",
            "subcategory":"Auto Repair",
            "type":"Services"
        }
    ],
    "sg:phone":"+1 317 845 3095",
    "sg:postcode":"46256",
    "sg:province":"IN",
    "sg:tags":[
        "body",
        "automobile",
        "painting",
        "repairing"
    ],
    "sg:website":"http://www.church-brothers.com",
    "wof:name":"Church Brothers",
    "wof:placetype":"venue"
},
  "geometry": {"coordinates":[-86.03426,39.916801],"type":"Point"}
}