{
  "type": "Feature",
  "properties": {
    "iso:country":"US",
    "sg:address":"1321 N Mitchner Ave",
    "sg:city":"Indianapolis",
    "sg:classifiers":[
        {
            "category":"Arts & Performance",
            "subcategory":"Theater",
            "type":"Entertainment"
        }
    ],
    "sg:phone":"+1 317 357 1654",
    "sg:postcode":"46219",
    "sg:province":"IN",
    "sg:tags":[
        "group"
    ],
    "wof:name":"Northwinds Big Dance Band",
    "wof:placetype":"venue"
},
  "geometry": {"coordinates":[-86.034881,39.785175],"type":"Point"}
}