{
  "type": "Feature",
  "properties": {
    "iso:country":"US",
    "sg:address":"4943 Rosebud Ln",
    "sg:city":"Newburgh",
    "sg:classifiers":[
        {
            "category":"Personal",
            "subcategory":"Beauty Salon",
            "type":"Services"
        }
    ],
    "sg:phone":"+1 812 473 1033",
    "sg:postcode":"47630",
    "sg:province":"IN",
    "sg:tags":[
        "shop"
    ],
    "wof:name":"Electrlysis Prmnt Csmtc Clinic",
    "wof:placetype":"venue"
},
  "geometry": {"coordinates":[-87.44962200000001,37.961389],"type":"Point"}
}