{
  "type": "Feature",
  "properties": {
    "iso:country":"US",
    "sg:address":"1202 E 38th St",
    "sg:city":"Indianapolis",
    "sg:classifiers":[
        {
            "category":"Home & Garden",
            "subcategory":"Furniture",
            "type":"Retail Goods"
        }
    ],
    "sg:phone":"+1 317 924 9106",
    "sg:postcode":"46205",
    "sg:province":"IN",
    "wof:name":"John KIRK Furniture",
    "wof:placetype":"venue"
},
  "geometry": {"coordinates":[-86.13463400000001,39.825544],"type":"Point"}
}