{
  "type": "Feature",
  "properties": {
    "iso:country":"US",
    "sg:address":"820 E Main St",
    "sg:city":"Brownsburg",
    "sg:classifiers":[
        {
            "category":"Food & Beverages",
            "subcategory":"Bakery",
            "type":"Retail Goods"
        }
    ],
    "sg:phone":"+1 317 852 7451",
    "sg:postcode":"46112",
    "sg:province":"IN",
    "sg:tags":[
        "baker"
    ],
    "wof:name":"Hilligoss Bakery",
    "wof:placetype":"venue"
},
  "geometry": {"coordinates":[-86.385195,39.839515],"type":"Point"}
}