{
  "type": "Feature",
  "properties": {
    "addr:full":"1309 E 86th St Indianapolis IN 46240",
    "addr:housenumber":"1309",
    "addr:postcode":"46240",
    "addr:street":"E 86Th St",
    "iso:country":"US",
    "sg:address":"1309 E 86th St",
    "sg:city":"Indianapolis",
    "sg:classifiers":[
        {
            "category":"Cinema",
            "subcategory":"Movie Rental",
            "type":"Entertainment"
        }
    ],
    "sg:phone":"+1 317 253 4143",
    "sg:postcode":"46240",
    "sg:province":"IN",
    "sg:tags":[
        "leasing",
        "video",
        "disc",
        "tape"
    ],
    "wof:name":"Blockbuster Video",
    "wof:placetype":"venue"
},
  "geometry": {"coordinates":[-86.136382,39.912442],"type":"Point"}
}