{
  "type": "Feature",
  "properties": {
    "iso:country":"US",
    "sg:address":"229 1st St NE",
    "sg:city":"Carmel",
    "sg:classifiers":[
        {
            "category":"Wholesale",
            "subcategory":"Durable Goods & Equipment",
            "type":"Manufacturing & Wholesale Goods"
        }
    ],
    "sg:phone":"+1 317 571 9947",
    "sg:postcode":"46032",
    "sg:province":"IN",
    "sg:tags":[
        "representative",
        "manufacturer"
    ],
    "wof:name":"Restronics Midwest Inc",
    "wof:placetype":"venue"
},
  "geometry": {"coordinates":[-86.125253,39.979211],"type":"Point"}
}