{
  "type": "Feature",
  "properties": {
    "addr:full":"1305 Veterans Pkwy Clarksville IN 47129",
    "addr:housenumber":"1305",
    "addr:postcode":"47129",
    "addr:street":"Veterans Pkwy",
    "iso:country":"US",
    "sg:address":"1305 Veterans Pkwy",
    "sg:city":"Clarksville",
    "sg:classifiers":[
        {
            "category":"Deli",
            "type":"Food & Drink"
        }
    ],
    "sg:menulink":"http://www.allmenus.com/in/jeffersonville/93009-mcalisters-deli/menu/",
    "sg:phone":"+1 812 282 3354",
    "sg:postcode":"47129",
    "sg:province":"IN",
    "sg:tags":[
        "wrap",
        "american",
        "sandwich"
    ],
    "wof:name":"Mcalister's Deli",
    "wof:placetype":"venue"
},
  "geometry": {"coordinates":[-85.759749,38.328891],"type":"Point"}
}