{
  "type": "Feature",
  "properties": {
    "iso:country":"US",
    "sg:address":"1004 W Main St",
    "sg:city":"Mitchell",
    "sg:classifiers":[
        {
            "category":"Social Services",
            "subcategory":"Child Care",
            "type":"Services"
        }
    ],
    "sg:phone":"+1 812 849 0560",
    "sg:postcode":"47446",
    "sg:province":"IN",
    "sg:tags":[
        "kindergarten",
        "academic",
        "school"
    ],
    "wof:name":"Little Lights Pre School",
    "wof:placetype":"venue"
},
  "geometry": {"coordinates":[-86.47698099999999,38.731843],"type":"Point"}
}