{
  "type": "Feature",
  "properties": {
    "addr:full":"301 Armory Rd Monticello IN 47960",
    "addr:housenumber":"301",
    "addr:postcode":"47960",
    "addr:street":"Armory Rd",
    "iso:country":"US",
    "sg:address":"301 Armory Rd",
    "sg:city":"Monticello",
    "sg:classifiers":[
        {
            "category":"Wholesale",
            "subcategory":"Machinery & Supplies",
            "type":"Manufacturing & Wholesale Goods"
        }
    ],
    "sg:phone":"+1 574 583 4145",
    "sg:postcode":"47960",
    "sg:province":"IN",
    "sg:tags":[
        "construction",
        "general"
    ],
    "wof:name":"Steven Hooker",
    "wof:placetype":"venue"
},
  "geometry": {"coordinates":[-86.75870999999999,40.732971],"type":"Point"}
}