{
  "type": "Feature",
  "properties": {
    "iso:country":"US",
    "sg:address":"3001 N 8th St",
    "sg:city":"Terre Haute",
    "sg:classifiers":[
        {
            "category":"Shopping",
            "subcategory":"Discount & Variety Stores",
            "type":"Retail Goods"
        }
    ],
    "sg:phone":"+1 812 466 4964",
    "sg:postcode":"47804",
    "sg:province":"IN",
    "sg:tags":[
        "merchandise",
        "general"
    ],
    "wof:name":"Acanthus Leaf Supply Co",
    "wof:placetype":"venue"
},
  "geometry": {"coordinates":[-87.405951,39.505631],"type":"Point"}
}