{
  "type": "Feature",
  "properties": {
    "iso:country":"US",
    "sg:address":"1302 N Butler Ave",
    "sg:city":"Indianapolis",
    "sg:classifiers":[
        {
            "category":"Manufacturing",
            "subcategory":"Printing",
            "type":"Manufacturing & Wholesale Goods"
        }
    ],
    "sg:phone":"+1 317 352 1367",
    "sg:postcode":"46219",
    "sg:province":"IN",
    "sg:tags":[
        "multimedia"
    ],
    "wof:name":"Nielsen Media",
    "wof:placetype":"venue"
},
  "geometry": {"coordinates":[-86.080975,39.788851],"type":"Point"}
}