{
  "type": "Feature",
  "properties": {
    "iso:country":"US",
    "sg:address":"15280 Herriman Blvd",
    "sg:city":"Noblesville",
    "sg:classifiers":[
        {
            "category":"Professional",
            "type":"Services"
        }
    ],
    "sg:phone":"+1 317 877 4688",
    "sg:postcode":"46060",
    "sg:province":"IN",
    "wof:name":"Herriman Products Co",
    "wof:placetype":"venue"
},
  "geometry": {"coordinates":[-86.004956,40.012275],"type":"Point"}
}