{
  "type": "Feature",
  "properties": {
    "addr:full":"1066 Kehoe Ln Jeffersonville IN 47130",
    "addr:housenumber":"1066",
    "addr:postcode":"47130",
    "addr:street":"Kehoe Ln",
    "iso:country":"US",
    "sg:address":"1066 Kehoe Ln",
    "sg:city":"Jeffersonville",
    "sg:classifiers":[
        {
            "category":"Restaurant",
            "type":"Food & Drink"
        }
    ],
    "sg:phone":"+1 812 282 8286",
    "sg:postcode":"47130",
    "sg:province":"IN",
    "sg:tags":[
        "pizza"
    ],
    "wof:name":"Pizza King",
    "wof:placetype":"venue"
},
  "geometry": {"coordinates":[-85.721237,38.300159],"type":"Point"}
}