{
  "type": "Feature",
  "properties": {
    "iso:country":"US",
    "sg:address":"2989 Industrial Blvd",
    "sg:city":"Crawfordsville",
    "sg:classifiers":[
        {
            "category":"Autos & Motor Vehicles",
            "subcategory":"Automobile Sales",
            "type":"Retail Goods"
        }
    ],
    "sg:phone":"+1 765 364 0828",
    "sg:postcode":"47933",
    "sg:province":"IN",
    "sg:tags":[
        "truck"
    ],
    "wof:name":"Allen Truck Sales",
    "wof:placetype":"venue"
},
  "geometry": {"coordinates":[-86.91032800000001,40.079231],"type":"Point"}
}