{
  "type": "Feature",
  "properties": {
    "iso:country":"US",
    "sg:address":"7780 S US Hwy 41",
    "sg:city":"Terre Haute",
    "sg:classifiers":[
        {
            "category":"Organizations",
            "subcategory":"Religious Organization",
            "type":"Services"
        }
    ],
    "sg:phone":"+1 812 299 5450",
    "sg:postcode":"47802",
    "sg:province":"IN",
    "sg:tags":[
        "church"
    ],
    "sg:website":"www.agapechristianchurch.com",
    "wof:name":"Agape Christian Church",
    "wof:placetype":"venue"
},
  "geometry": {"coordinates":[-87.389988,39.373711],"type":"Point"}
}