{
  "type": "Feature",
  "properties": {
    "iso:country":"US",
    "sg:address":"20 E Columbia St",
    "sg:city":"Logansport",
    "sg:classifiers":[
        {
            "category":"Education",
            "subcategory":"School",
            "type":"Public Place"
        }
    ],
    "sg:phone":"+1 574 753 3432",
    "sg:postcode":"46947",
    "sg:province":"IN",
    "sg:website":"www.lcsc.k12.in.us",
    "wof:name":"Columbia Elementary School",
    "wof:placetype":"venue"
},
  "geometry": {"coordinates":[-86.371622,40.762181],"type":"Point"}
}