{
  "type": "Feature",
  "properties": {
    "iso:country":"US",
    "sg:address":"1134 Leininger Dr",
    "sg:city":"Tipton",
    "sg:phone":"+1 765 675 7648",
    "sg:postcode":"46072",
    "sg:province":"IN",
    "sg:tags":[
        "farm",
        "corn",
        "soybean"
    ],
    "wof:name":"Bruce Schulenburg",
    "wof:placetype":"venue"
},
  "geometry": {"coordinates":[-86.069018,40.274339],"type":"Point"}
}