{
  "type": "Feature",
  "properties": {
    "iso:country":"US",
    "sg:address":"216 Vernon St",
    "sg:city":"North Vernon",
    "sg:classifiers":[
        {
            "category":"Retail",
            "subcategory":"Repair Shop",
            "type":"Services"
        }
    ],
    "sg:phone":"+1 812 346 6167",
    "sg:postcode":"47265",
    "sg:province":"IN",
    "sg:tags":[
        "antique",
        "refinishing",
        "restoring",
        "furniture"
    ],
    "wof:name":"Heirlooms Reborn",
    "wof:placetype":"venue"
},
  "geometry": {"coordinates":[-85.6222,39.003248],"type":"Point"}
}