{
  "type": "Feature",
  "properties": {
    "iso:country":"US",
    "sg:address":"135 N 1650 W",
    "sg:city":"Medaryville",
    "sg:classifiers":[
        {
            "category":"Building & Trades",
            "subcategory":"Landscaping Services",
            "type":"Services"
        }
    ],
    "sg:phone":"+1 219 843 7421",
    "sg:postcode":"47957",
    "sg:province":"IN",
    "wof:name":"Leroys Tree Service",
    "wof:placetype":"venue"
},
  "geometry": {"coordinates":[-86.92070099999999,41.06216],"type":"Point"}
}