{
  "type": "Feature",
  "properties": {
    "iso:country":"US",
    "sg:address":"6350 W 37th St",
    "sg:city":"Indianapolis",
    "sg:classifiers":[
        {
            "category":"Retail",
            "subcategory":"Repair Shop",
            "type":"Services"
        }
    ],
    "sg:phone":"+1 317 280 1901",
    "sg:postcode":"46224",
    "sg:province":"IN",
    "sg:tags":[
        "appliance"
    ],
    "wof:name":"Perez Appliance Repair & Sales",
    "wof:placetype":"venue"
},
  "geometry": {"coordinates":[-86.273088,39.821559],"type":"Point"}
}