{
  "type": "Feature",
  "properties": {
    "addr:full":"1816 E Wheeler St Kokomo IN 46902",
    "addr:housenumber":"1816",
    "addr:postcode":"46902",
    "addr:street":"E Wheeler St",
    "iso:country":"US",
    "sg:address":"1816 E Wheeler St",
    "sg:city":"Kokomo",
    "sg:classifiers":[
        {
            "category":"Shopping",
            "subcategory":"Gifts & Souvenirs",
            "type":"Retail Goods"
        }
    ],
    "sg:phone":"+1 765 457 5068",
    "sg:postcode":"46902",
    "sg:province":"IN",
    "sg:tags":[
        "shop"
    ],
    "wof:name":"Ceramic Cat",
    "wof:placetype":"venue"
},
  "geometry": {"coordinates":[-86.10957399999999,40.467176],"type":"Point"}
}