{
  "type": "Feature",
  "properties": {
    "iso:country":"US",
    "sg:address":"4716 Jennys Rd",
    "sg:city":"Indianapolis",
    "sg:classifiers":[
        {
            "category":"Professional",
            "subcategory":"Management & Consulting",
            "type":"Services"
        }
    ],
    "sg:phone":"+1 317 299 4033",
    "sg:postcode":"46228",
    "sg:province":"IN",
    "sg:tags":[
        "business"
    ],
    "wof:name":"Business Performance Assoc",
    "wof:placetype":"venue"
},
  "geometry": {"coordinates":[-86.207797,39.840445],"type":"Point"}
}