{
  "type": "Feature",
  "properties": {
    "iso:country":"US",
    "sg:address":"4841 W Old Vernal Pike",
    "sg:city":"Bloomington",
    "sg:classifiers":[
        {
            "category":"Wholesale",
            "subcategory":"Auto Parts",
            "type":"Manufacturing & Wholesale Goods"
        }
    ],
    "sg:phone":"+1 812 330 8831",
    "sg:postcode":"47404",
    "sg:province":"IN",
    "sg:tags":[
        "tire"
    ],
    "wof:name":"Ben Tire Distributors",
    "wof:placetype":"venue"
},
  "geometry": {"coordinates":[-86.60654100000001,39.18661],"type":"Point"}
}