{
  "type": "Feature",
  "properties": {
    "iso:country":"US",
    "sg:address":"509 NE E St",
    "sg:city":"Linton",
    "sg:classifiers":[
        {
            "category":"Retail",
            "subcategory":"Auto Repair",
            "type":"Services"
        }
    ],
    "sg:phone":"+1 812 847 4861",
    "sg:postcode":"47441",
    "sg:province":"IN",
    "sg:tags":[
        "repairing",
        "automobile"
    ],
    "wof:name":"Pletch's Major Muffler Shop",
    "wof:placetype":"venue"
},
  "geometry": {"coordinates":[-87.16055,39.038472],"type":"Point"}
}