{
  "type": "Feature",
  "properties": {
    "iso:country":"US",
    "sg:address":"319 N Walnut St",
    "sg:city":"Bloomington",
    "sg:classifiers":[
        {
            "category":"Real Estate",
            "subcategory":"Real Estate Agent",
            "type":"Services"
        }
    ],
    "sg:phone":"+1 812 330 1671",
    "sg:postcode":"47404",
    "sg:province":"IN",
    "wof:name":"Property Fire Adjusters",
    "wof:placetype":"venue"
},
  "geometry": {"coordinates":[-86.533656,39.169319],"type":"Point"}
}