{
  "type": "Feature",
  "properties": {
    "iso:country":"US",
    "sg:address":"106 S Main St",
    "sg:city":"Sidney",
    "sg:classifiers":[
        {
            "category":"Manufacturing",
            "subcategory":"Metals",
            "type":"Manufacturing & Wholesale Goods"
        }
    ],
    "sg:phone":"+1 260 839 5100",
    "sg:postcode":"46562",
    "sg:province":"IN",
    "sg:tags":[
        "polishing"
    ],
    "wof:name":"Perfection Polishing",
    "wof:placetype":"venue"
},
  "geometry": {"coordinates":[-85.743489,41.105314],"type":"Point"}
}