{
  "type": "Feature",
  "properties": {
    "iso:country":"US",
    "sg:address":"3735 S Airport Rd",
    "sg:city":"Logansport",
    "sg:classifiers":[
        {
            "category":"Airport",
            "type":"Transportation"
        }
    ],
    "sg:phone":"+1 574 732 1124",
    "sg:postcode":"46947",
    "sg:province":"IN",
    "wof:name":"Logansport Municipal Airport",
    "wof:placetype":"venue"
},
  "geometry": {"coordinates":[-86.377667,40.709924],"type":"Point"}
}