{
  "type": "Feature",
  "properties": {
    "iso:country":"US",
    "sg:address":"515 Sutton Dr",
    "sg:city":"Fort Wayne",
    "sg:classifiers":[
        {
            "category":"Retail",
            "subcategory":"Repair Shop",
            "type":"Services"
        }
    ],
    "sg:phone":"+1 260 435 1575",
    "sg:postcode":"46804",
    "sg:province":"IN",
    "sg:tags":[
        "scooter",
        "motorcycle",
        "motor"
    ],
    "wof:name":"Sams Cycle Repair",
    "wof:placetype":"venue"
},
  "geometry": {"coordinates":[-85.213354,41.076845],"type":"Point"}
}