{
  "type": "Feature",
  "properties": {
    "addr:full":"3664 E 1100 N Alexandria IN 46001",
    "addr:housenumber":"3664",
    "addr:postcode":"46001",
    "addr:street":"E 1100 N",
    "iso:country":"US",
    "sg:address":"3664 E 1100 N",
    "sg:city":"Alexandria",
    "sg:classifiers":[
        {
            "category":"Building & Trades",
            "subcategory":"Construction",
            "type":"Services"
        }
    ],
    "sg:phone":"+1 765 724 4672",
    "sg:postcode":"46001",
    "sg:province":"IN",
    "sg:tags":[
        "excavating",
        "contractor"
    ],
    "wof:name":"Cannell Excavating",
    "wof:placetype":"venue"
},
  "geometry": {"coordinates":[-85.602002,40.262682],"type":"Point"}
}