{
  "type": "Feature",
  "properties": {
    "iso:country":"US",
    "sg:address":"716 W Morgan St",
    "sg:city":"Spencer",
    "sg:classifiers":[
        {
            "category":"Home & Garden",
            "subcategory":"Furniture",
            "type":"Retail Goods"
        }
    ],
    "sg:phone":"+1 812 829 8881",
    "sg:postcode":"47460",
    "sg:province":"IN",
    "wof:name":"Byers Home Furnishings",
    "wof:placetype":"venue"
},
  "geometry": {"coordinates":[-86.77015,39.287069],"type":"Point"}
}