{
  "type": "Feature",
  "properties": {
    "addr:full":"8142 S State Rd 66 Leavenworth IN 47137",
    "addr:housenumber":"8142;66",
    "addr:postcode":"47137",
    "addr:street":"S State Rd",
    "iso:country":"US",
    "sg:address":"8142 S State Rd 66",
    "sg:city":"Leavenworth",
    "sg:classifiers":[
        {
            "category":"Insurance",
            "subcategory":"Insurance Agent",
            "type":"Services"
        }
    ],
    "sg:phone":"+1 812 739 4343",
    "sg:postcode":"47137",
    "sg:province":"IN",
    "wof:name":"Steve Breeden Insurance",
    "wof:placetype":"venue"
},
  "geometry": {"coordinates":[-86.36896900000001,38.220579],"type":"Point"}
}