{
  "type": "Feature",
  "properties": {
    "iso:country":"US",
    "sg:address":"2801 N Walnut St",
    "sg:city":"Bloomington",
    "sg:classifiers":[
        {
            "category":"Insurance",
            "subcategory":"Insurance Agent",
            "type":"Services"
        }
    ],
    "sg:phone":"+1 812 332 9215",
    "sg:postcode":"47404",
    "sg:province":"IN",
    "wof:name":"Don's Insurance",
    "wof:placetype":"venue"
},
  "geometry": {"coordinates":[-86.533242,39.192879],"type":"Point"}
}