{
  "type": "Feature",
  "properties": {
    "iso:country":"US",
    "sg:address":"450 Erie Ave",
    "sg:city":"Connersville",
    "sg:classifiers":[
        {
            "category":"Health Services",
            "subcategory":"Hospital",
            "type":"Services"
        }
    ],
    "sg:phone":"+1 765 827 7890",
    "sg:postcode":"47331",
    "sg:province":"IN",
    "sg:tags":[
        "mental"
    ],
    "wof:name":"Whitewater Valley Care Pvln",
    "wof:placetype":"venue"
},
  "geometry": {"coordinates":[-85.12493499999999,39.678996],"type":"Point"}
}