{
  "type": "Feature",
  "properties": {
    "iso:country":"US",
    "sg:address":"5825 Sunnyside Rd",
    "sg:city":"Indianapolis",
    "sg:classifiers":[
        {
            "category":"Shopping",
            "subcategory":"Department Store",
            "type":"Retail Goods"
        }
    ],
    "sg:phone":"+1 317 823 8930",
    "sg:postcode":"46235",
    "sg:province":"IN",
    "sg:website":"http://www.kohls.com",
    "wof:name":"Kohl's",
    "wof:placetype":"venue"
},
  "geometry": {"coordinates":[-85.97273800000001,39.862642],"type":"Point"}
}