{
  "type": "Feature",
  "properties": {
    "iso:country":"US",
    "sg:address":"1915 E 350 S",
    "sg:city":"Knox",
    "sg:classifiers":[
        {
            "category":"Wholesale",
            "subcategory":"Auto Parts",
            "type":"Manufacturing & Wholesale Goods"
        }
    ],
    "sg:phone":"+1 219 828 3800",
    "sg:postcode":"46534",
    "sg:province":"IN",
    "sg:tags":[
        "department",
        "used",
        "store"
    ],
    "wof:name":"San Pierre Auto Inc",
    "wof:placetype":"venue"
},
  "geometry": {"coordinates":[-86.661362,41.251115],"type":"Point"}
}