{
  "type": "Feature",
  "properties": {
    "iso:country":"US",
    "sg:address":"3313 Imperial Pkwy",
    "sg:city":"Lafayette",
    "sg:classifiers":[
        {
            "category":"Building & Trades",
            "subcategory":"Construction",
            "type":"Services"
        }
    ],
    "sg:phone":"+1 765 474 5471",
    "sg:postcode":"47909",
    "sg:province":"IN",
    "sg:tags":[
        "general",
        "contractor"
    ],
    "wof:name":"Mid-States General Contracting",
    "wof:placetype":"venue"
},
  "geometry": {"coordinates":[-86.848948,40.380464],"type":"Point"}
}