{
  "type": "Feature",
  "properties": {
    "addr:full":"20428 Salt Fork Rd Lawrenceburg IN 47025",
    "addr:postcode":"20428;47025",
    "addr:street":"Fork Rd",
    "iso:country":"US",
    "sg:address":"20428 Salt Fork Rd",
    "sg:city":"Lawrenceburg",
    "sg:classifiers":[
        {
            "category":"Building & Trades",
            "subcategory":"Construction",
            "type":"Services"
        }
    ],
    "sg:phone":"+1 812 537 9101",
    "sg:postcode":"47025",
    "sg:province":"IN",
    "sg:tags":[
        "demolition",
        "contractor"
    ],
    "wof:name":"ABS",
    "wof:placetype":"venue"
},
  "geometry": {"coordinates":[-84.87007199999999,39.17935],"type":"Point"}
}