{
  "type": "Feature",
  "properties": {
    "iso:country":"US",
    "sg:address":"6700 E Devonald Ave",
    "sg:city":"Terre Haute",
    "sg:classifiers":[
        {
            "category":"Personal",
            "subcategory":"Beauty Salon",
            "type":"Services"
        }
    ],
    "sg:phone":"+1 812 478 5430",
    "sg:postcode":"47805",
    "sg:province":"IN",
    "wof:name":"Craft & Curl",
    "wof:placetype":"venue"
},
  "geometry": {"coordinates":[-87.30470699999999,39.542812],"type":"Point"}
}