{
  "type": "Feature",
  "properties": {
    "addr:full":"26 Park Ave Logansport IN 46947",
    "addr:housenumber":"26",
    "addr:postcode":"46947",
    "addr:street":"Park Ave",
    "iso:country":"US",
    "sg:address":"26 Park Ave",
    "sg:city":"Logansport",
    "sg:classifiers":[
        {
            "category":"Retail",
            "subcategory":"Auto Repair",
            "type":"Services"
        }
    ],
    "sg:phone":"+1 574 722 5915",
    "sg:postcode":"46947",
    "sg:province":"IN",
    "sg:tags":[
        "transmission"
    ],
    "wof:name":"Dishon Transmission Service",
    "wof:placetype":"venue"
},
  "geometry": {"coordinates":[-86.383206,40.747258],"type":"Point"}
}