{
  "type": "Feature",
  "properties": {
    "iso:country":"US",
    "sg:address":"905 Crabapple Ln",
    "sg:city":"Valparaiso",
    "sg:classifiers":[
        {
            "category":"Professional",
            "subcategory":"Business Services",
            "type":"Services"
        }
    ],
    "sg:phone":"+1 219 531 5656",
    "sg:postcode":"46383",
    "sg:province":"IN",
    "wof:name":"Charrock Inc",
    "wof:placetype":"venue"
},
  "geometry": {"coordinates":[-87.01896,41.553531],"type":"Point"}
}