{
  "type": "Feature",
  "properties": {
    "iso:country":"US",
    "sg:address":"1100 E 5th St",
    "sg:city":"Anderson",
    "sg:classifiers":[
        {
            "category":"Professional",
            "subcategory":"Business Services",
            "type":"Services"
        }
    ],
    "sg:phone":"+1 765 649 6708",
    "sg:postcode":"46012",
    "sg:province":"IN",
    "wof:name":"Heberling Enterprises Inc",
    "wof:placetype":"venue"
},
  "geometry": {"coordinates":[-85.664825,40.111157],"type":"Point"}
}