{
  "type": "Feature",
  "properties": {
    "iso:country":"US",
    "sg:address":"2002 S Calhoun St",
    "sg:city":"Fort Wayne",
    "sg:classifiers":[
        {
            "category":"Personal",
            "subcategory":"Beauty Salon",
            "type":"Services"
        }
    ],
    "sg:phone":"+1 260 456 1930",
    "sg:postcode":"46802",
    "sg:province":"IN",
    "wof:name":"Expo Hair & Nails",
    "wof:placetype":"venue"
},
  "geometry": {"coordinates":[-85.138143,41.066347],"type":"Point"}
}