{
  "type": "Feature",
  "properties": {
    "addr:full":"125 Cooper St Loogootee IN 47553",
    "addr:housenumber":"125",
    "addr:postcode":"47553",
    "addr:street":"Cooper St",
    "iso:country":"US",
    "sg:address":"125 Cooper St",
    "sg:city":"Loogootee",
    "sg:classifiers":[
        {
            "category":"Government",
            "subcategory":"Office",
            "type":"Public Place"
        }
    ],
    "sg:phone":"+1 812 295 2550",
    "sg:postcode":"47553",
    "sg:province":"IN",
    "wof:name":"License BRANCHES/Bmv",
    "wof:placetype":"venue"
},
  "geometry": {"coordinates":[-86.913453,38.672867],"type":"Point"}
}