{
  "type": "Feature",
  "properties": {
    "iso:country":"US",
    "sg:address":"11796 Eden Estates Pl",
    "sg:city":"Carmel",
    "sg:classifiers":[
        {
            "category":"Real Estate",
            "subcategory":"Real Estate Agent",
            "type":"Services"
        },
        {
            "category":"Insurance",
            "subcategory":"Insurance Agent",
            "type":"Services"
        }
    ],
    "sg:phone":"+1 317 574 9884",
    "sg:postcode":"46033",
    "sg:province":"IN",
    "wof:name":"Carper Grove Investments LLC",
    "wof:placetype":"venue"
},
  "geometry": {"coordinates":[-86.106826,39.959255],"type":"Point"}
}