{
  "type": "Feature",
  "properties": {
    "iso:country":"US",
    "sg:address":"111 E Ludwig Rd",
    "sg:city":"Fort Wayne",
    "sg:classifiers":[
        {
            "category":"Organizations",
            "subcategory":"Religious Organization",
            "type":"Services"
        }
    ],
    "sg:phone":"+1 260 480 5757",
    "sg:postcode":"46825",
    "sg:province":"IN",
    "sg:tags":[
        "church"
    ],
    "wof:name":"Southwest Lutheran Church",
    "wof:placetype":"venue"
},
  "geometry": {"coordinates":[-85.139222,41.140095],"type":"Point"}
}