{
  "type": "Feature",
  "properties": {
    "iso:country":"US",
    "sg:address":"4511 Stellhorn Rd",
    "sg:city":"Fort Wayne",
    "sg:classifiers":[
        {
            "category":"Social Services",
            "subcategory":"Child Care",
            "type":"Services"
        }
    ],
    "sg:phone":"+1 260 969 1320",
    "sg:postcode":"46815",
    "sg:province":"IN",
    "wof:name":"Sabrina's Little Angels",
    "wof:placetype":"venue"
},
  "geometry": {"coordinates":[-85.08791,41.119585],"type":"Point"}
}