{
  "type": "Feature",
  "properties": {
    "iso:country":"US",
    "sg:address":"9425 E 30th St",
    "sg:city":"Indianapolis",
    "sg:classifiers":[
        {
            "category":"Social Services",
            "subcategory":"Child Care",
            "type":"Services"
        }
    ],
    "sg:phone":"+1 317 897 9888",
    "sg:postcode":"46229",
    "sg:province":"IN",
    "wof:name":"Alternative Learning Ctr",
    "wof:placetype":"venue"
},
  "geometry": {"coordinates":[-86.008968,39.811291],"type":"Point"}
}