{
  "type": "Feature",
  "properties": {
    "iso:country":"US",
    "sg:address":"906 N 6th St",
    "sg:city":"Terre Haute",
    "sg:classifiers":[
        {
            "category":"Health Services",
            "subcategory":"Doctor",
            "type":"Services"
        }
    ],
    "sg:phone":"+1 812 232 8677",
    "sg:postcode":"47807",
    "sg:province":"IN",
    "sg:tags":[
        "dentist"
    ],
    "wof:name":"Fred H Isaacs DDS",
    "wof:placetype":"venue"
},
  "geometry": {"coordinates":[-87.410651,39.477961],"type":"Point"}
}