{
  "type": "Feature",
  "properties": {
    "iso:country":"US",
    "sg:address":"405 S Huntington St",
    "sg:city":"Gary",
    "sg:classifiers":[
        {
            "category":"Real Estate",
            "subcategory":"Real Estate Operator",
            "type":"Services"
        }
    ],
    "sg:phone":"+1 219 938 4068",
    "sg:postcode":"46403",
    "sg:province":"IN",
    "sg:tags":[
        "apartment"
    ],
    "wof:name":"Windsor Square Apartments",
    "wof:placetype":"venue"
},
  "geometry": {"coordinates":[-87.262955,41.603144],"type":"Point"}
}