{
  "type": "Feature",
  "properties": {
    "iso:country":"US",
    "sg:address":"700 S Memorial Dr",
    "sg:city":"New Castle",
    "sg:classifiers":[
        {
            "category":"Insurance",
            "subcategory":"Insurance Agent",
            "type":"Services"
        }
    ],
    "sg:phone":"+1 765 593 0327",
    "sg:postcode":"47362",
    "sg:province":"IN",
    "wof:name":"Primerica Financial Svc",
    "wof:placetype":"venue"
},
  "geometry": {"coordinates":[-85.381855,39.925261],"type":"Point"}
}