{
  "type": "Feature",
  "properties": {
    "iso:country":"US",
    "sg:address":"5497 S 100 W",
    "sg:city":"Morocco",
    "sg:phone":"+1 219 285 2457",
    "sg:postcode":"47963",
    "sg:province":"IN",
    "sg:tags":[
        "farm",
        "corn"
    ],
    "wof:name":"Daniel Baird",
    "wof:placetype":"venue"
},
  "geometry": {"coordinates":[-87.41186500000001,40.918685],"type":"Point"}
}