{
  "type": "Feature",
  "properties": {
    "iso:country":"US",
    "sg:address":"1124 W Warwick Rd",
    "sg:city":"Muncie",
    "sg:classifiers":[
        {
            "category":"Professional",
            "subcategory":"Computer Services",
            "type":"Services"
        }
    ],
    "sg:phone":"+1 765 286 1725",
    "sg:postcode":"47304",
    "sg:province":"IN",
    "sg:tags":[
        "programing",
        "custom"
    ],
    "wof:name":"Thomas Shafer Svc",
    "wof:placetype":"venue"
},
  "geometry": {"coordinates":[-85.410876,40.204216],"type":"Point"}
}