{
  "type": "Feature",
  "properties": {
    "iso:country":"US",
    "sg:address":"7935 Ainsworth Rd",
    "sg:city":"Hobart",
    "sg:classifiers":[
        {
            "category":"Freight",
            "type":"Transportation"
        }
    ],
    "sg:phone":"+1 219 947 2228",
    "sg:postcode":"46342",
    "sg:province":"IN",
    "wof:name":"M J Howland",
    "wof:placetype":"venue"
},
  "geometry": {"coordinates":[-87.241868,41.490279],"type":"Point"}
}