{
  "type": "Feature",
  "properties": {
    "iso:country":"US",
    "sg:address":"462 N Independence St",
    "sg:city":"Tipton",
    "sg:classifiers":[
        {
            "category":"Building & Trades",
            "subcategory":"Construction",
            "type":"Services"
        }
    ],
    "sg:phone":"+1 765 675 4743",
    "sg:postcode":"46072",
    "sg:province":"IN",
    "sg:tags":[
        "carpentry",
        "contractor"
    ],
    "wof:name":"Plake Carpentry",
    "wof:placetype":"venue"
},
  "geometry": {"coordinates":[-86.039721,40.28835],"type":"Point"}
}