{
  "type": "Feature",
  "properties": {
    "iso:country":"US",
    "sg:address":"1202 Rossville Ave",
    "sg:city":"Frankfort",
    "sg:classifiers":[
        {
            "category":"Autos & Motor Vehicles",
            "subcategory":"Automobile Sales",
            "type":"Retail Goods"
        }
    ],
    "sg:phone":"+1 765 659 3983",
    "sg:postcode":"46041",
    "sg:province":"IN",
    "sg:tags":[
        "car",
        "dealer"
    ],
    "wof:name":"Frankfort Auto Sales",
    "wof:placetype":"venue"
},
  "geometry": {"coordinates":[-86.52156,40.290925],"type":"Point"}
}