{
  "type": "Feature",
  "properties": {
    "iso:country":"US",
    "sg:address":"4281 Park Ave",
    "sg:city":"Lake Station",
    "sg:classifiers":[
        {
            "category":"Recreation",
            "type":"Entertainment"
        }
    ],
    "sg:phone":"+1 219 962 6713",
    "sg:postcode":"46405",
    "sg:province":"IN",
    "sg:tags":[
        "stable"
    ],
    "wof:name":"Classic Memories",
    "wof:placetype":"venue"
},
  "geometry": {"coordinates":[-87.28670099999999,41.562295],"type":"Point"}
}