{
  "type": "Feature",
  "properties": {
    "iso:country":"US",
    "sg:address":"5008 State Rd 25 S",
    "sg:city":"Westpoint",
    "sg:classifiers":[
        {
            "category":"Retail",
            "subcategory":"Auto Repair",
            "type":"Services"
        }
    ],
    "sg:phone":"+1 765 572 2437",
    "sg:postcode":"47992",
    "sg:province":"IN",
    "sg:tags":[
        "body",
        "automobile",
        "painting"
    ],
    "wof:name":"Martin's Body & Paint",
    "wof:placetype":"venue"
},
  "geometry": {"coordinates":[-87.046271,40.343781],"type":"Point"}
}