{
  "type": "Feature",
  "properties": {
    "iso:country":"US",
    "sg:address":"2925 S Washington St",
    "sg:city":"Kokomo",
    "sg:classifiers":[
        {
            "category":"Food & Beverages",
            "subcategory":"Specialty",
            "type":"Retail Goods"
        }
    ],
    "sg:phone":"+1 765 864 9521",
    "sg:postcode":"46902",
    "sg:province":"IN",
    "sg:tags":[
        "health",
        "diet"
    ],
    "wof:name":"GNC",
    "wof:placetype":"venue"
},
  "geometry": {"coordinates":[-86.128373,40.453002],"type":"Point"}
}