{
  "type": "Feature",
  "properties": {
    "iso:country":"US",
    "sg:address":"550 W Walnut St",
    "sg:city":"Frankfort",
    "sg:classifiers":[
        {
            "category":"Personal",
            "subcategory":"Beauty Salon",
            "type":"Services"
        }
    ],
    "sg:phone":"+1 765 654 5155",
    "sg:postcode":"46041",
    "sg:province":"IN",
    "wof:name":"Edge",
    "wof:placetype":"venue"
},
  "geometry": {"coordinates":[-86.519052,40.279688],"type":"Point"}
}