{
  "type": "Feature",
  "properties": {
    "iso:country":"US",
    "sg:address":"4617 E 10th Ave",
    "sg:city":"Gary",
    "sg:classifiers":[
        {
            "category":"Social Services",
            "subcategory":"Child Care",
            "type":"Services"
        }
    ],
    "sg:phone":"+1 219 938 8062",
    "sg:postcode":"46403",
    "sg:province":"IN",
    "wof:name":"Hattie's Day Care & Pre School",
    "wof:placetype":"venue"
},
  "geometry": {"coordinates":[-87.280099,41.593943],"type":"Point"}
}