{
  "type": "Feature",
  "properties": {
    "addr:full":"205 Shaffer Rd Warsaw IN 46580",
    "addr:housenumber":"205",
    "addr:postcode":"46580",
    "addr:street":"Shaffer Rd",
    "iso:country":"US",
    "sg:address":"205 Shaffer Rd",
    "sg:city":"Warsaw",
    "sg:classifiers":[
        {
            "category":"Personal",
            "subcategory":"Beauty Salon",
            "type":"Services"
        }
    ],
    "sg:phone":"+1 574 267 6018",
    "sg:postcode":"46580",
    "sg:province":"IN",
    "wof:name":"Hair Designs",
    "wof:placetype":"venue"
},
  "geometry": {"coordinates":[-85.85880299999999,41.224866],"type":"Point"}
}