{
  "type": "Feature",
  "properties": {
    "addr:full":"667 E 38th St Indianapolis IN 46205",
    "addr:housenumber":"667",
    "addr:postcode":"46205",
    "addr:street":"E 38Th St",
    "iso:country":"US",
    "sg:address":"667 E 38th St",
    "sg:city":"Indianapolis",
    "sg:classifiers":[
        {
            "category":"Professional",
            "subcategory":"Employment Agencies",
            "type":"Services"
        }
    ],
    "sg:phone":"+1 317 926 7734",
    "sg:postcode":"46205",
    "sg:province":"IN",
    "sg:tags":[
        "opportunity"
    ],
    "wof:name":"On Demand Staffing",
    "wof:placetype":"venue"
},
  "geometry": {"coordinates":[-86.145353,39.824989],"type":"Point"}
}