{
  "type": "Feature",
  "properties": {
    "iso:country":"US",
    "sg:address":"306 Virginia Ct",
    "sg:city":"New Albany",
    "sg:classifiers":[
        {
            "category":"Wholesale",
            "subcategory":"Jewelry",
            "type":"Manufacturing & Wholesale Goods"
        }
    ],
    "sg:phone":"+1 812 948 9037",
    "sg:postcode":"47150",
    "sg:province":"IN",
    "sg:tags":[
        "stone"
    ],
    "wof:name":"Rachel & Co Inc",
    "wof:placetype":"venue"
},
  "geometry": {"coordinates":[-85.835151,38.297552],"type":"Point"}
}