{
  "type": "Feature",
  "properties": {
    "iso:country":"US",
    "sg:address":"663 N 36th St",
    "sg:city":"Lafayette",
    "sg:classifiers":[
        {
            "category":"Building & Trades",
            "subcategory":"Plumbing",
            "type":"Services"
        }
    ],
    "sg:phone":"+1 765 448 3405",
    "sg:postcode":"47905",
    "sg:province":"IN",
    "sg:tags":[
        "mechanical",
        "contractor"
    ],
    "wof:name":"D A Dodd Mechanical",
    "wof:placetype":"venue"
},
  "geometry": {"coordinates":[-86.850849,40.423909],"type":"Point"}
}