{
  "type": "Feature",
  "properties": {
    "iso:country":"US",
    "sg:address":"11057 Allisonville Rd # 308",
    "sg:city":"Fishers",
    "sg:classifiers":[
        {
            "category":"Professional",
            "subcategory":"Engineering",
            "type":"Services"
        }
    ],
    "sg:phone":"+1 317 842 2177",
    "sg:postcode":"46038",
    "sg:province":"IN",
    "sg:tags":[
        "engineer",
        "integration",
        "system"
    ],
    "wof:name":"Clingman Technology Consulting",
    "wof:placetype":"venue"
},
  "geometry": {"coordinates":[-86.042919,39.948813],"type":"Point"}
}