{
  "type": "Feature",
  "properties": {
    "iso:country":"US",
    "sg:address":"2521 S 25th St",
    "sg:city":"Terre Haute",
    "sg:classifiers":[
        {
            "category":"Utilities",
            "subcategory":"Cable",
            "type":"Services"
        }
    ],
    "sg:phone":"+1 812 235 4849",
    "sg:postcode":"47802",
    "sg:province":"IN",
    "sg:tags":[
        "television"
    ],
    "wof:name":"Direct TV Sales & Svc",
    "wof:placetype":"venue"
},
  "geometry": {"coordinates":[-87.37883100000001,39.43951],"type":"Point"}
}