{
  "type": "Feature",
  "properties": {
    "iso:country":"US",
    "sg:address":"749 W State Road 42",
    "sg:city":"Mooresville",
    "sg:classifiers":[
        {
            "category":"Home & Garden",
            "subcategory":"Garden Supply",
            "type":"Retail Goods"
        },
        {
            "category":"Home & Garden",
            "subcategory":"Building Materials",
            "type":"Retail Goods"
        },
        {
            "category":"Utilities",
            "subcategory":"Natural Gas",
            "type":"Services"
        }
    ],
    "sg:phone":"+1 317 996 2826",
    "sg:postcode":"46158",
    "sg:province":"IN",
    "sg:tags":[
        "stone",
        "landscaping",
        "wall",
        "mulch",
        "topsoil",
        "equipment",
        "retaining"
    ],
    "sg:website":"http://www.greendellmulch.com",
    "wof:name":"Greendell Mulch & Mix",
    "wof:placetype":"venue"
},
  "geometry": {"coordinates":[-86.440242,39.593057],"type":"Point"}
}