{
  "type": "Feature",
  "properties": {
    "iso:country":"US",
    "sg:address":"65 Commercial Rd",
    "sg:city":"Huntington",
    "sg:classifiers":[
        {
            "category":"Restaurant",
            "type":"Food & Drink"
        }
    ],
    "sg:phone":"+1 260 359 0508",
    "sg:postcode":"46750",
    "sg:province":"IN",
    "wof:name":"Country Post Inn",
    "wof:placetype":"venue"
},
  "geometry": {"coordinates":[-85.525331,40.889961],"type":"Point"}
}