{
  "type": "Feature",
  "properties": {
    "iso:country":"US",
    "sg:address":"6702 Chipmunk Dr",
    "sg:city":"Nineveh",
    "sg:classifiers":[
        {
            "category":"Professional",
            "subcategory":"Management & Consulting",
            "type":"Services"
        }
    ],
    "sg:phone":"+1 317 933 2618",
    "sg:postcode":"46164",
    "sg:province":"IN",
    "wof:name":"Minkrn",
    "wof:placetype":"venue"
},
  "geometry": {"coordinates":[-86.12832299999999,39.312163],"type":"Point"}
}