{
  "type": "Feature",
  "properties": {
    "iso:country":"US",
    "sg:address":"951 W 250 N",
    "sg:city":"Winchester",
    "sg:classifiers":[
        {
            "category":"Retail",
            "subcategory":"Auto Repair",
            "type":"Services"
        }
    ],
    "sg:phone":"+1 765 584 6963",
    "sg:postcode":"47394",
    "sg:province":"IN",
    "sg:tags":[
        "wrecker"
    ],
    "wof:name":"Van Note Wrecker Svc",
    "wof:placetype":"venue"
},
  "geometry": {"coordinates":[-84.99313600000001,40.201123],"type":"Point"}
}