{
  "type": "Feature",
  "properties": {
    "iso:country":"US",
    "sg:address":"3500 S Lafountain St",
    "sg:city":"Kokomo",
    "sg:classifiers":[
        {
            "category":"Health Services",
            "subcategory":"Nursing And Care Facility",
            "type":"Services"
        }
    ],
    "sg:phone":"+1 765 453 8471",
    "sg:postcode":"46902",
    "sg:province":"IN",
    "sg:tags":[
        "home",
        "convalescent"
    ],
    "sg:website":"www.howardcommunity.org",
    "wof:name":"Extended Care Unit",
    "wof:placetype":"venue"
},
  "geometry": {"coordinates":[-86.127015,40.446594],"type":"Point"}
}