{
  "type": "Feature",
  "properties": {
    "addr:full":"6251 Coffman Rd Indianapolis IN 46268",
    "addr:housenumber":"6251",
    "addr:postcode":"46268",
    "addr:street":"Coffman Rd",
    "iso:country":"US",
    "sg:address":"6251 Coffman Rd",
    "sg:city":"Indianapolis",
    "sg:classifiers":[
        {
            "category":"Freight",
            "type":"Transportation"
        }
    ],
    "sg:phone":"+1 317 295 8355",
    "sg:postcode":"46268",
    "sg:province":"IN",
    "sg:tags":[
        "mover"
    ],
    "wof:name":"Anytime Inc",
    "wof:placetype":"venue"
},
  "geometry": {"coordinates":[-86.240877,39.871087],"type":"Point"}
}