{
  "type": "Feature",
  "properties": {
    "iso:country":"US",
    "sg:address":"1525 E Vera Dr",
    "sg:city":"Bloomington",
    "sg:classifiers":[
        {
            "category":"Professional",
            "subcategory":"Business Services",
            "type":"Services"
        }
    ],
    "sg:phone":"+1 812 824 6842",
    "sg:postcode":"47401",
    "sg:province":"IN",
    "wof:name":"Coyote Group LLC",
    "wof:placetype":"venue"
},
  "geometry": {"coordinates":[-86.512536,39.096126],"type":"Point"}
}