{
  "type": "Feature",
  "properties": {
    "iso:country":"US",
    "sg:address":"219 W 550 N",
    "sg:city":"Valparaiso",
    "sg:classifiers":[
        {
            "category":"Building & Trades",
            "subcategory":"Plumbing",
            "type":"Services"
        }
    ],
    "sg:phone":"+1 219 759 1712",
    "sg:postcode":"46385",
    "sg:province":"IN",
    "sg:tags":[
        "heating",
        "contractor"
    ],
    "wof:name":"L & N Heating & Cooling Inc",
    "wof:placetype":"venue"
},
  "geometry": {"coordinates":[-87.109302,41.514383],"type":"Point"}
}