{
  "type": "Feature",
  "properties": {
    "addr:full":"1009 E Poplar St Terre Haute IN 47807",
    "addr:housenumber":"1009",
    "addr:postcode":"47807",
    "addr:street":"E Poplar St",
    "iso:country":"US",
    "sg:address":"1009 E Poplar St",
    "sg:city":"Terre Haute",
    "sg:classifiers":[
        {
            "category":"Wholesale",
            "subcategory":"Hardware",
            "type":"Manufacturing & Wholesale Goods"
        }
    ],
    "sg:phone":"+1 812 232 6000",
    "sg:postcode":"47807",
    "sg:province":"IN",
    "sg:tags":[
        "fastener"
    ],
    "wof:name":"Fastenal Co",
    "wof:placetype":"venue"
},
  "geometry": {"coordinates":[-87.401814,39.462853],"type":"Point"}
}