{
  "type": "Feature",
  "properties": {
    "iso:country":"US",
    "sg:address":"222 W 4th St",
    "sg:city":"Michigan City",
    "sg:classifiers":[
        {
            "category":"Professional",
            "subcategory":"Advertising",
            "type":"Services"
        }
    ],
    "sg:phone":"+1 219 874 3807",
    "sg:postcode":"46360",
    "sg:province":"IN",
    "wof:name":"Winski Advertising",
    "wof:placetype":"venue"
},
  "geometry": {"coordinates":[-86.904951,41.717551],"type":"Point"}
}