{
  "type": "Feature",
  "properties": {
    "iso:country":"US",
    "sg:address":"4353 State Rd 3",
    "sg:city":"Hartford City",
    "sg:classifiers":[
        {
            "category":"Organizations",
            "subcategory":"Religious Organization",
            "type":"Services"
        }
    ],
    "sg:phone":"+1 765 348 4346",
    "sg:postcode":"47348",
    "sg:province":"IN",
    "sg:tags":[
        "church"
    ],
    "wof:name":"Mount Carmel United Methodist",
    "wof:placetype":"venue"
},
  "geometry": {"coordinates":[-85.369573,40.387625],"type":"Point"}
}