{
  "type": "Feature",
  "properties": {
    "iso:country":"US",
    "sg:address":"18 W Main St",
    "sg:city":"Greenfield",
    "sg:classifiers":[
        {
            "category":"Professional",
            "subcategory":"Accounting & Tax Preparation",
            "type":"Services"
        }
    ],
    "sg:phone":"+1 317 462 7178",
    "sg:postcode":"46140",
    "sg:province":"IN",
    "sg:tags":[
        "return",
        "filing"
    ],
    "wof:name":"Haines-Prigg Accounting & Tax",
    "wof:placetype":"venue"
},
  "geometry": {"coordinates":[-85.76945600000001,39.785283],"type":"Point"}
}