{
  "type": "Feature",
  "properties": {
    "addr:full":"3629 Hwy 135 NE Corydon IN 47112",
    "addr:housenumber":"3629",
    "addr:postcode":"47112",
    "addr:street":"Hwy 135 Ne",
    "iso:country":"US",
    "sg:address":"3629 Hwy 135 NE",
    "sg:city":"Corydon",
    "sg:classifiers":[
        {
            "category":"Shopping",
            "subcategory":"Gifts & Souvenirs",
            "type":"Retail Goods"
        }
    ],
    "sg:phone":"+1 812 738 1270",
    "sg:postcode":"47112",
    "sg:province":"IN",
    "sg:tags":[
        "shop"
    ],
    "wof:name":"Sandy's Gift Shoppe",
    "wof:placetype":"venue"
},
  "geometry": {"coordinates":[-86.119399,38.25886],"type":"Point"}
}