{
  "type": "Feature",
  "properties": {
    "iso:country":"US",
    "sg:address":"1338 E Co Rd 1100 N",
    "sg:city":"Batesville",
    "sg:classifiers":[
        {
            "category":"Wholesale",
            "subcategory":"Construction Materials",
            "type":"Manufacturing & Wholesale Goods"
        }
    ],
    "sg:phone":"+1 812 934 4474",
    "sg:postcode":"47006",
    "sg:province":"IN",
    "sg:tags":[
        "fence"
    ],
    "wof:name":"Grazing Systems Supply",
    "wof:placetype":"venue"
},
  "geometry": {"coordinates":[-85.232676,39.233734],"type":"Point"}
}