{
  "type": "Feature",
  "properties": {
    "iso:country":"US",
    "sg:address":"600 E Votaw St",
    "sg:city":"Portland",
    "sg:classifiers":[
        {
            "category":"Manufacturing",
            "subcategory":"Building Materials",
            "type":"Manufacturing & Wholesale Goods"
        }
    ],
    "sg:phone":"+1 260 726 9357",
    "sg:postcode":"47371",
    "sg:province":"IN",
    "sg:tags":[
        "cabinet"
    ],
    "sg:website":"www.pennvillecabinetry.com",
    "wof:name":"Pennville Custom Cabinetry",
    "wof:placetype":"venue"
},
  "geometry": {"coordinates":[-84.969651,40.439671],"type":"Point"}
}