{
  "type": "Feature",
  "properties": {
    "iso:country":"US",
    "sg:address":"330 N College Ave",
    "sg:city":"Indianapolis",
    "sg:classifiers":[
        {
            "category":"Professional",
            "subcategory":"Engineering",
            "type":"Services"
        }
    ],
    "sg:phone":"+1 317 685 6600",
    "sg:postcode":"46202",
    "sg:province":"IN",
    "sg:tags":[
        "engineer"
    ],
    "sg:website":"www.keramida.com",
    "wof:name":"Keramida Environmental Inc",
    "wof:placetype":"venue"
},
  "geometry": {"coordinates":[-86.145538,39.772105],"type":"Point"}
}