{
  "type": "Feature",
  "properties": {
    "iso:country":"US",
    "sg:address":"2690 US Hwy 31 S",
    "sg:city":"Greenwood",
    "sg:classifiers":[
        {
            "category":"Home & Garden",
            "subcategory":"Garden Supply",
            "type":"Retail Goods"
        }
    ],
    "sg:phone":"+1 317 535 4757",
    "sg:postcode":"46143",
    "sg:province":"IN",
    "sg:tags":[
        "repair",
        "lawn",
        "mower"
    ],
    "wof:name":"Nichols Outdoor Power Equip Co",
    "wof:placetype":"venue"
},
  "geometry": {"coordinates":[-86.098402,39.579319],"type":"Point"}
}