{
  "type": "Feature",
  "properties": {
    "iso:country":"US",
    "sg:address":"3904 Fern St",
    "sg:city":"East Chicago",
    "sg:classifiers":[
        {
            "category":"Professional",
            "subcategory":"Engineering",
            "type":"Services"
        }
    ],
    "sg:phone":"+1 219 397 1528",
    "sg:postcode":"46312",
    "sg:province":"IN",
    "sg:tags":[
        "engineer"
    ],
    "wof:name":"VIP Consulting Svc Inc",
    "wof:placetype":"venue"
},
  "geometry": {"coordinates":[-87.43662399999999,41.64071],"type":"Point"}
}