{
  "type": "Feature",
  "properties": {
    "iso:country":"US",
    "sg:address":"1680 S 700 E",
    "sg:city":"Marion",
    "sg:classifiers":[
        {
            "category":"Banks & Credit Unions",
            "subcategory":"Financial Services",
            "type":"Services"
        }
    ],
    "sg:phone":"+1 765 662 8923",
    "sg:postcode":"46953",
    "sg:province":"IN",
    "sg:tags":[
        "investor"
    ],
    "wof:name":"Ronald Soards",
    "wof:placetype":"venue"
},
  "geometry": {"coordinates":[-85.541132,40.528898],"type":"Point"}
}