{
  "type": "Feature",
  "properties": {
    "addr:full":"2024 Redfern Dr Indianapolis IN 46227",
    "addr:housenumber":"2024",
    "addr:postcode":"46227",
    "addr:street":"Redfern Dr",
    "iso:country":"US",
    "sg:address":"2024 Redfern Dr",
    "sg:city":"Indianapolis",
    "sg:classifiers":[
        {
            "category":"Professional",
            "subcategory":"Secretarial Services",
            "type":"Services"
        }
    ],
    "sg:phone":"+1 317 783 4717",
    "sg:postcode":"46227",
    "sg:province":"IN",
    "sg:tags":[
        "reporting"
    ],
    "wof:name":"Southside Trnscrption Svcs Inc",
    "wof:placetype":"venue"
},
  "geometry": {"coordinates":[-86.122474,39.700644],"type":"Point"}
}