{
  "type": "Feature",
  "properties": {
    "iso:country":"US",
    "sg:address":"1300 W Pike St",
    "sg:city":"Goshen",
    "sg:classifiers":[
        {
            "category":"Sports & Exercise",
            "subcategory":"Bowling",
            "type":"Entertainment"
        }
    ],
    "sg:phone":"+1 574 533 8564",
    "sg:postcode":"46526",
    "sg:province":"IN",
    "sg:tags":[
        "center"
    ],
    "sg:website":"www.maplecitybowl.com",
    "wof:name":"Maple City Bowl",
    "wof:placetype":"venue"
},
  "geometry": {"coordinates":[-85.853725,41.589003],"type":"Point"}
}