{
  "type": "Feature",
  "properties": {
    "iso:country":"US",
    "sg:address":"3517 W Washington St",
    "sg:city":"South Bend",
    "sg:classifiers":[
        {
            "category":"Organizations",
            "subcategory":"Religious Organization",
            "type":"Services"
        }
    ],
    "sg:phone":"+1 574 288 7703",
    "sg:postcode":"46619",
    "sg:province":"IN",
    "sg:tags":[
        "church"
    ],
    "wof:name":"Israel Spiritual Church",
    "wof:placetype":"venue"
},
  "geometry": {"coordinates":[-86.297764,41.675636],"type":"Point"}
}