{
  "type": "Feature",
  "properties": {
    "iso:country":"US",
    "sg:address":"15 Franklin St",
    "sg:city":"Valparaiso",
    "sg:classifiers":[
        {
            "category":"Real Estate",
            "subcategory":"Real Estate Agent",
            "type":"Services"
        }
    ],
    "sg:phone":"+1 219 531 6910",
    "sg:postcode":"46383",
    "sg:province":"IN",
    "sg:tags":[
        "management"
    ],
    "wof:name":"Reason Bell Property Mgmt",
    "wof:placetype":"venue"
},
  "geometry": {"coordinates":[-87.059798,41.468105],"type":"Point"}
}