{
  "type": "Feature",
  "properties": {
    "iso:country":"US",
    "sg:address":"2011 Southern Hills Dr",
    "sg:city":"Borden",
    "sg:classifiers":[
        {
            "category":"Professional",
            "subcategory":"Management & Consulting",
            "type":"Services"
        }
    ],
    "sg:phone":"+1 812 248 0277",
    "sg:postcode":"47106",
    "sg:province":"IN",
    "sg:tags":[
        "construction"
    ],
    "wof:name":"Williams Construction",
    "wof:placetype":"venue"
},
  "geometry": {"coordinates":[-85.856257,38.434884],"type":"Point"}
}