{
  "type": "Feature",
  "properties": {
    "iso:country":"US",
    "sg:address":"2020 N Lincoln St",
    "sg:city":"Greensburg",
    "sg:classifiers":[
        {
            "category":"Autos & Motor Vehicles",
            "subcategory":"Fuel & Gas Station",
            "type":"Retail Goods"
        }
    ],
    "sg:phone":"+1 812 663 4229",
    "sg:postcode":"47240",
    "sg:province":"IN",
    "sg:tags":[
        "oil"
    ],
    "wof:name":"Interstate Shell",
    "wof:placetype":"venue"
},
  "geometry": {"coordinates":[-85.479752,39.353474],"type":"Point"}
}