{
  "type": "Feature",
  "properties": {
    "iso:country":"US",
    "sg:address":"25 N Railroad St",
    "sg:city":"Shelburn",
    "sg:classifiers":[
        {
            "category":"Government",
            "subcategory":"Office",
            "type":"Public Place"
        }
    ],
    "sg:phone":"+1 812 397 5953",
    "sg:postcode":"47879",
    "sg:province":"IN",
    "sg:tags":[
        "village"
    ],
    "wof:name":"Shelburn Sewage Plant",
    "wof:placetype":"venue"
},
  "geometry": {"coordinates":[-87.393377,39.178649],"type":"Point"}
}