{
  "type": "Feature",
  "properties": {
    "addr:full":"1503 N Baldwin Ave Marion IN 46952",
    "addr:housenumber":"1503",
    "addr:postcode":"46952",
    "addr:street":"N Baldwin Ave",
    "iso:country":"US",
    "sg:address":"1503 N Baldwin Ave",
    "sg:city":"Marion",
    "sg:classifiers":[
        {
            "category":"Food & Beverages",
            "subcategory":"Groceries & Convenience Stores",
            "type":"Retail Goods"
        }
    ],
    "sg:phone":"+1 765 662 6100",
    "sg:postcode":"46952",
    "sg:province":"IN",
    "wof:name":"Village Pantry",
    "wof:placetype":"venue"
},
  "geometry": {"coordinates":[-85.66557,40.58154],"type":"Point"}
}