{
  "type": "Feature",
  "properties": {
    "iso:country":"US",
    "sg:address":"301 S Scott St",
    "sg:city":"Warsaw",
    "sg:classifiers":[
        {
            "category":"Shopping",
            "type":"Retail Goods"
        }
    ],
    "sg:phone":"+1 574 267 1426",
    "sg:postcode":"46580",
    "sg:province":"IN",
    "sg:tags":[
        "trophy",
        "medal",
        "award"
    ],
    "wof:name":"Acey's Trophies & Awards",
    "wof:placetype":"venue"
},
  "geometry": {"coordinates":[-85.842922,41.236094],"type":"Point"}
}