{
  "type": "Feature",
  "properties": {
    "iso:country":"US",
    "sg:address":"1025 E Barachel Ln",
    "sg:city":"Greensburg",
    "sg:classifiers":[
        {
            "category":"Professional",
            "subcategory":"Employment Agencies",
            "type":"Services"
        }
    ],
    "sg:phone":"+1 812 662 6975",
    "sg:postcode":"47240",
    "sg:province":"IN",
    "sg:tags":[
        "opportunity"
    ],
    "wof:name":"Malone Staffing-Gecom",
    "wof:placetype":"venue"
},
  "geometry": {"coordinates":[-85.47035200000001,39.351513],"type":"Point"}
}