{
  "type": "Feature",
  "properties": {
    "iso:country":"US",
    "sg:address":"6237 E 25th St",
    "sg:city":"Indianapolis",
    "sg:classifiers":[
        {
            "category":"Building & Trades",
            "subcategory":"Construction",
            "type":"Services"
        }
    ],
    "sg:phone":"+1 317 357 4341",
    "sg:postcode":"46219",
    "sg:province":"IN",
    "sg:tags":[
        "general",
        "contractor"
    ],
    "wof:name":"D & S Roofing & Construction",
    "wof:placetype":"venue"
},
  "geometry": {"coordinates":[-86.057063,39.80358],"type":"Point"}
}