{
  "type": "Feature",
  "properties": {
    "iso:country":"US",
    "sg:address":"1109 Rossville Ave",
    "sg:city":"Frankfort",
    "sg:classifiers":[
        {
            "category":"Shopping",
            "subcategory":"Bicycles & Sporting Goods",
            "type":"Retail Goods"
        }
    ],
    "sg:phone":"+1 765 654 4544",
    "sg:postcode":"46041",
    "sg:province":"IN",
    "wof:name":"U-Sav",
    "wof:placetype":"venue"
},
  "geometry": {"coordinates":[-86.521023,40.290482],"type":"Point"}
}