{
  "type": "Feature",
  "properties": {
    "iso:country":"US",
    "sg:address":"7880 Broadway",
    "sg:city":"Merrillville",
    "sg:classifiers":[
        {
            "category":"Banks & Credit Unions",
            "subcategory":"Bank",
            "type":"Services"
        }
    ],
    "sg:phone":"+1 219 769 7090",
    "sg:postcode":"46410",
    "sg:province":"IN",
    "sg:tags":[
        "loan",
        "real estate"
    ],
    "wof:name":"Trustcorp Mortgage Co",
    "wof:placetype":"venue"
},
  "geometry": {"coordinates":[-87.33607,41.479262],"type":"Point"}
}