{
  "type": "Feature",
  "properties": {
    "iso:country":"US",
    "sg:address":"7960 W 125 S",
    "sg:city":"Laporte",
    "sg:classifiers":[
        {
            "category":"Farming",
            "subcategory":"Farm",
            "type":"Manufacturing & Wholesale Goods"
        }
    ],
    "sg:phone":"+1 219 326 8633",
    "sg:postcode":"46350",
    "sg:province":"IN",
    "sg:tags":[
        "crop",
        "general"
    ],
    "wof:name":"M & W Farms Inc",
    "wof:placetype":"venue"
},
  "geometry": {"coordinates":[-86.851874,41.58519],"type":"Point"}
}