{
  "type": "Feature",
  "properties": {
    "addr:full":"13266 N 300 W Milford IN 46542",
    "addr:housenumber":"13266",
    "addr:postcode":"46542",
    "addr:street":"N 300 W",
    "iso:country":"US",
    "sg:address":"13266 N 300 W",
    "sg:city":"Milford",
    "sg:classifiers":[
        {
            "category":"Farming",
            "subcategory":"Livestock Farm",
            "type":"Manufacturing & Wholesale Goods"
        }
    ],
    "sg:phone":"+1 574 658 4890",
    "sg:postcode":"46542",
    "sg:province":"IN",
    "sg:tags":[
        "hog",
        "or",
        "feedlot"
    ],
    "wof:name":"Hubert Krull",
    "wof:placetype":"venue"
},
  "geometry": {"coordinates":[-85.905331,41.416198],"type":"Point"}
}