{
  "type": "Feature",
  "properties": {
    "iso:country":"US",
    "sg:address":"726 Pawnee Dr",
    "sg:city":"Carmel",
    "sg:classifiers":[
        {
            "category":"Communications",
            "subcategory":"Film & Video Production",
            "type":"Services"
        }
    ],
    "sg:phone":"+1 317 846 2551",
    "sg:postcode":"46032",
    "sg:province":"IN",
    "sg:tags":[
        "motion"
    ],
    "wof:name":"Diehl Productions",
    "wof:placetype":"venue"
},
  "geometry": {"coordinates":[-86.125144,39.969398],"type":"Point"}
}