{
  "type": "Feature",
  "properties": {
    "iso:country":"US",
    "sg:address":"3029 E 10th St",
    "sg:city":"Indianapolis",
    "sg:classifiers":[
        {
            "category":"Food & Beverages",
            "subcategory":"Liquor & Beverages",
            "type":"Retail Goods"
        }
    ],
    "sg:phone":"+1 317 321 9019",
    "sg:postcode":"46201",
    "sg:province":"IN",
    "wof:name":"DPT Corp",
    "wof:placetype":"venue"
},
  "geometry": {"coordinates":[-86.113982,39.781276],"type":"Point"}
}