{
  "type": "Feature",
  "properties": {
    "iso:country":"US",
    "sg:address":"850 Maple St",
    "sg:city":"Middletown",
    "sg:classifiers":[
        {
            "category":"Professional",
            "subcategory":"Lawyer & Legal Services",
            "type":"Services"
        }
    ],
    "sg:phone":"+1 765 354 2177",
    "sg:postcode":"47356",
    "sg:province":"IN",
    "sg:tags":[
        "attorney"
    ],
    "wof:name":"Kreegar & Mc Cord",
    "wof:placetype":"venue"
},
  "geometry": {"coordinates":[-85.538483,40.060517],"type":"Point"}
}