{
  "type": "Feature",
  "properties": {
    "iso:country":"US",
    "sg:address":"2075 Rush Pl",
    "sg:city":"Lake Station",
    "sg:classifiers":[
        {
            "category":"Social Services",
            "subcategory":"Child Care",
            "type":"Services"
        }
    ],
    "sg:phone":"+1 219 962 4857",
    "sg:postcode":"46405",
    "sg:province":"IN",
    "sg:tags":[
        "kindergarten",
        "academic",
        "school"
    ],
    "wof:name":"Liberty Baptist Academy",
    "wof:placetype":"venue"
},
  "geometry": {"coordinates":[-87.238206,41.578069],"type":"Point"}
}