{
  "type": "Feature",
  "properties": {
    "iso:country":"US",
    "sg:address":"544 W 30th St",
    "sg:city":"Connersville",
    "sg:classifiers":[
        {
            "category":"Government",
            "subcategory":"Office",
            "type":"Public Place"
        }
    ],
    "sg:phone":"+1 765 825 2261",
    "sg:postcode":"47331",
    "sg:province":"IN",
    "sg:tags":[
        "state",
        "program"
    ],
    "sg:website":"www.in.gov",
    "wof:name":"Auto License Branch",
    "wof:placetype":"venue"
},
  "geometry": {"coordinates":[-85.135538,39.671717],"type":"Point"}
}