{
  "type": "Feature",
  "properties": {
    "iso:country":"US",
    "sg:address":"1080 E 500 S",
    "sg:city":"Pleasant Lake",
    "sg:classifiers":[
        {
            "category":"Wholesale",
            "subcategory":"Scrap",
            "type":"Manufacturing & Wholesale Goods"
        }
    ],
    "sg:phone":"+1 260 475 5056",
    "sg:postcode":"46779",
    "sg:province":"IN",
    "sg:tags":[
        "metal",
        "iron"
    ],
    "wof:name":"Jackson & Co",
    "wof:placetype":"venue"
},
  "geometry": {"coordinates":[-84.952805,41.572943],"type":"Point"}
}