{
  "type": "Feature",
  "properties": {
    "iso:country":"US",
    "sg:address":"19 E Main St",
    "sg:city":"Logansport",
    "sg:classifiers":[
        {
            "category":"Organizations",
            "subcategory":"Religious Organization",
            "type":"Services"
        }
    ],
    "sg:phone":"+1 574 753 3488",
    "sg:postcode":"46947",
    "sg:province":"IN",
    "sg:tags":[
        "church"
    ],
    "wof:name":"Main Street United Methodist",
    "wof:placetype":"venue"
},
  "geometry": {"coordinates":[-86.367294,40.746234],"type":"Point"}
}