{
  "type": "Feature",
  "properties": {
    "iso:country":"US",
    "sg:address":"1925 Borneman Ave",
    "sg:city":"Elkhart",
    "sg:classifiers":[
        {
            "category":"Shopping",
            "type":"Retail Goods"
        }
    ],
    "sg:phone":"+1 574 293 3123",
    "sg:postcode":"46517",
    "sg:province":"IN",
    "sg:tags":[
        "equipment",
        "telephone",
        "supply"
    ],
    "sg:website":"www.acs-phone.com",
    "wof:name":"Advanced Communications Systs",
    "wof:placetype":"venue"
},
  "geometry": {"coordinates":[-86.000662,41.664168],"type":"Point"}
}