{
  "type": "Feature",
  "properties": {
    "iso:country":"US",
    "sg:address":"8315 Timberlake Ln",
    "sg:city":"Mt Vernon",
    "sg:classifiers":[
        {
            "category":"Retail",
            "subcategory":"Portrait Studio",
            "type":"Services"
        }
    ],
    "sg:phone":"+1 812 985 9844",
    "sg:postcode":"47620",
    "sg:province":"IN",
    "sg:tags":[
        "photographer"
    ],
    "wof:name":"Dewig Photography",
    "wof:placetype":"venue"
},
  "geometry": {"coordinates":[-87.76621299999999,37.967994],"type":"Point"}
}