{
  "type": "Feature",
  "properties": {
    "addr:full":"4566 Maplecrest Rd Fort Wayne IN 46835",
    "addr:housenumber":"4566",
    "addr:postcode":"46835",
    "addr:street":"Maplecrest Rd",
    "iso:country":"US",
    "sg:address":"4566 Maplecrest Rd",
    "sg:city":"Fort Wayne",
    "sg:classifiers":[
        {
            "category":"Cinema",
            "subcategory":"Movie Rental",
            "type":"Entertainment"
        }
    ],
    "sg:phone":"+1 260 486 4979",
    "sg:postcode":"46835",
    "sg:province":"IN",
    "sg:tags":[
        "leasing",
        "video",
        "disc",
        "tape"
    ],
    "sg:website":"www.blockbuster.com",
    "wof:name":"Blockbuster Video",
    "wof:placetype":"venue"
},
  "geometry": {"coordinates":[-85.06165799999999,41.122537],"type":"Point"}
}