{
  "type": "Feature",
  "properties": {
    "iso:country":"US",
    "sg:address":"8611 Meadowood Dr",
    "sg:city":"Newburgh",
    "sg:classifiers":[
        {
            "category":"Real Estate",
            "subcategory":"Real Estate Operator",
            "type":"Services"
        }
    ],
    "sg:phone":"+1 812 853 3220",
    "sg:postcode":"47630",
    "sg:province":"IN",
    "sg:tags":[
        "apartment"
    ],
    "wof:name":"Meadowood Apartments",
    "wof:placetype":"venue"
},
  "geometry": {"coordinates":[-87.39830000000001,37.963699],"type":"Point"}
}