{
  "type": "Feature",
  "properties": {
    "iso:country":"US",
    "sg:address":"3233 Covington Rd",
    "sg:city":"Fort Wayne",
    "sg:classifiers":[
        {
            "category":"Wholesale",
            "subcategory":"Machinery & Supplies",
            "type":"Manufacturing & Wholesale Goods"
        }
    ],
    "sg:phone":"+1 260 432 3013",
    "sg:postcode":"46802",
    "sg:province":"IN",
    "sg:tags":[
        "equipment",
        "material",
        "handling"
    ],
    "wof:name":"Mansfield Materials Handling",
    "wof:placetype":"venue"
},
  "geometry": {"coordinates":[-85.182343,41.0601],"type":"Point"}
}