{
  "type": "Feature",
  "properties": {
    "iso:country":"US",
    "sg:address":"4525 S 500 E",
    "sg:city":"Hartford City",
    "sg:classifiers":[
        {
            "category":"Restaurant",
            "type":"Food & Drink"
        }
    ],
    "sg:phone":"+1 765 768 6731",
    "sg:postcode":"47348",
    "sg:province":"IN",
    "sg:tags":[
        "eating"
    ],
    "wof:name":"Val Gene Shop",
    "wof:placetype":"venue"
},
  "geometry": {"coordinates":[-85.277467,40.384654],"type":"Point"}
}