{
  "type": "Feature",
  "properties": {
    "iso:country":"US",
    "sg:address":"34 N Delaware St",
    "sg:city":"Indianapolis",
    "sg:classifiers":[
        {
            "category":"Restaurant",
            "type":"Food & Drink"
        }
    ],
    "sg:phone":"+1 317 634 7116",
    "sg:postcode":"46204",
    "sg:province":"IN",
    "wof:name":"Best Yet Restaurant",
    "wof:placetype":"venue"
},
  "geometry": {"coordinates":[-86.15453100000001,39.767201],"type":"Point"}
}