{
  "type": "Feature",
  "properties": {
    "iso:country":"US",
    "sg:address":"8306 Crestwood Ave",
    "sg:city":"Munster",
    "sg:classifiers":[
        {
            "category":"Building & Trades",
            "subcategory":"Landscaping Services",
            "type":"Services"
        }
    ],
    "sg:phone":"+1 219 838 8814",
    "sg:postcode":"46321",
    "sg:province":"IN",
    "sg:tags":[
        "lawn",
        "maintenance",
        "grounds"
    ],
    "wof:name":"Ciesars Growing Concern I",
    "wof:placetype":"venue"
},
  "geometry": {"coordinates":[-87.482656,41.560622],"type":"Point"}
}