{
  "type": "Feature",
  "properties": {
    "addr:full":"767 N Warman Ave Indianapolis IN 46222",
    "addr:housenumber":"767",
    "addr:postcode":"46222",
    "addr:street":"N Warman Ave",
    "iso:country":"US",
    "sg:address":"767 N Warman Ave",
    "sg:city":"Indianapolis",
    "sg:classifiers":[
        {
            "category":"Shopping",
            "subcategory":"Crafts & Fabrics",
            "type":"Retail Goods"
        }
    ],
    "sg:phone":"+1 317 634 1760",
    "sg:postcode":"46222",
    "sg:province":"IN",
    "sg:tags":[
        "shop"
    ],
    "wof:name":"Sharon's Fabric",
    "wof:placetype":"venue"
},
  "geometry": {"coordinates":[-86.206328,39.777964],"type":"Point"}
}