{
  "type": "Feature",
  "properties": {
    "iso:country":"US",
    "sg:address":"505 W Jefferson St",
    "sg:city":"Plymouth",
    "sg:classifiers":[
        {
            "category":"Wholesale",
            "subcategory":"Groceries",
            "type":"Manufacturing & Wholesale Goods"
        }
    ],
    "sg:phone":"+1 574 935 9855",
    "sg:postcode":"46563",
    "sg:province":"IN",
    "sg:tags":[
        "food",
        "product",
        "mexican"
    ],
    "wof:name":"Barreras Mexican Store",
    "wof:placetype":"venue"
},
  "geometry": {"coordinates":[-86.314097,41.343112],"type":"Point"}
}