{
  "type": "Feature",
  "properties": {
    "iso:country":"US",
    "sg:address":"504 N Jackson St",
    "sg:city":"St Paul",
    "sg:classifiers":[
        {
            "category":"Building & Trades",
            "subcategory":"Cleaning & Sanitation",
            "type":"Services"
        }
    ],
    "sg:phone":"+1 765 525 6300",
    "sg:postcode":"47272",
    "sg:province":"IN",
    "sg:tags":[
        "janitor"
    ],
    "wof:name":"Tony's Carpet Cleaning",
    "wof:placetype":"venue"
},
  "geometry": {"coordinates":[-85.625348,39.429871],"type":"Point"}
}