{
  "type": "Feature",
  "properties": {
    "iso:country":"US",
    "sg:address":"1928 S A St",
    "sg:city":"Jasper",
    "sg:classifiers":[
        {
            "category":"Building & Trades",
            "subcategory":"Construction",
            "type":"Services"
        }
    ],
    "sg:phone":"+1 812 634 1834",
    "sg:postcode":"47546",
    "sg:province":"IN",
    "sg:tags":[
        "excavating",
        "contractor"
    ],
    "wof:name":"Little Si's Construction",
    "wof:placetype":"venue"
},
  "geometry": {"coordinates":[-86.900075,38.364683],"type":"Point"}
}