{
  "type": "Feature",
  "properties": {
    "addr:full":"3423 Newton St Jasper IN 47546",
    "addr:housenumber":"3423",
    "addr:postcode":"47546",
    "addr:street":"Newton St",
    "iso:country":"US",
    "sg:address":"3423 Newton St",
    "sg:city":"Jasper",
    "sg:classifiers":[
        {
            "category":"Insurance",
            "subcategory":"Insurance Agent",
            "type":"Services"
        }
    ],
    "sg:phone":"+1 812 482 3113",
    "sg:postcode":"47546",
    "sg:province":"IN",
    "wof:name":"Robert G Buchta Insurance",
    "wof:placetype":"venue"
},
  "geometry": {"coordinates":[-86.937979,38.420239],"type":"Point"}
}