{
  "type": "Feature",
  "properties": {
    "iso:country":"US",
    "sg:address":"2130 S West St",
    "sg:city":"Yorktown",
    "sg:classifiers":[
        {
            "category":"Insurance",
            "subcategory":"Insurance Agent",
            "type":"Services"
        }
    ],
    "sg:phone":"+1 765 759 5000",
    "sg:postcode":"47396",
    "sg:province":"IN",
    "wof:name":"Integrity Advisors Inc",
    "wof:placetype":"venue"
},
  "geometry": {"coordinates":[-85.49950699999999,40.172307],"type":"Point"}
}