{
  "type": "Feature",
  "properties": {
    "iso:country":"US",
    "sg:address":"8634 E 700 N",
    "sg:city":"Monticello",
    "sg:classifiers":[
        {
            "category":"Professional",
            "subcategory":"Computer Services",
            "type":"Services"
        }
    ],
    "sg:phone":"+1 574 278 2381",
    "sg:postcode":"47960",
    "sg:province":"IN",
    "sg:tags":[
        "consultant",
        "designer"
    ],
    "sg:website":"www.cetinc1.com",
    "wof:name":"Creative Electronic Tech Inc",
    "wof:placetype":"venue"
},
  "geometry": {"coordinates":[-86.703868,40.854395],"type":"Point"}
}