{
  "type": "Feature",
  "properties": {
    "iso:country":"US",
    "sg:address":"7930 E Washington St",
    "sg:city":"Indianapolis",
    "sg:classifiers":[
        {
            "category":"Ice Cream",
            "type":"Food & Drink"
        }
    ],
    "sg:menulink":"http://www.allmenus.com/in/warren/92531-steak-n-shake/menu/",
    "sg:phone":"+1 317 359 1102",
    "sg:postcode":"46219",
    "sg:province":"IN",
    "sg:tags":[
        "american"
    ],
    "wof:name":"Steak 'n Shake",
    "wof:placetype":"venue"
},
  "geometry": {"coordinates":[-86.02643,39.773121],"type":"Point"}
}