{
  "type": "Feature",
  "properties": {
    "addr:full":"6434 N College Ave Indianapolis IN 46220",
    "addr:housenumber":"6434",
    "addr:postcode":"46220",
    "addr:street":"N College Ave",
    "iso:country":"US",
    "sg:address":"6434 N College Ave",
    "sg:city":"Indianapolis",
    "sg:classifiers":[
        {
            "category":"Banks & Credit Unions",
            "subcategory":"Investment Brokerage",
            "type":"Services"
        }
    ],
    "sg:phone":"+1 317 257 7588",
    "sg:postcode":"46220",
    "sg:province":"IN",
    "sg:tags":[
        "stock",
        "bond"
    ],
    "wof:name":"Edward Jones Co",
    "wof:placetype":"venue"
},
  "geometry": {"coordinates":[-86.146304,39.87265],"type":"Point"}
}