{
  "type": "Feature",
  "properties": {
    "iso:country":"US",
    "sg:address":"2291 N Oak Rd",
    "sg:city":"Plymouth",
    "sg:classifiers":[
        {
            "category":"Shopping",
            "subcategory":"Computers & Home Electronics",
            "type":"Retail Goods"
        }
    ],
    "sg:phone":"+1 574 936 6685",
    "sg:postcode":"46563",
    "sg:province":"IN",
    "sg:tags":[
        "game",
        "video"
    ],
    "wof:name":"Game Stop Corp",
    "wof:placetype":"venue"
},
  "geometry": {"coordinates":[-86.32898299999999,41.361995],"type":"Point"}
}