{
  "type": "Feature",
  "properties": {
    "iso:country":"US",
    "sg:address":"67180 Co Rd 31",
    "sg:city":"Goshen",
    "sg:classifiers":[
        {
            "category":"Building & Trades",
            "subcategory":"Landscaping Services",
            "type":"Services"
        }
    ],
    "sg:phone":"+1 574 642 5188",
    "sg:postcode":"46528",
    "sg:province":"IN",
    "wof:name":"Herschberger Lawn Care",
    "wof:placetype":"venue"
},
  "geometry": {"coordinates":[-85.770086,41.520392],"type":"Point"}
}