{
  "type": "Feature",
  "properties": {
    "iso:country":"US",
    "sg:address":"2345 Hart St",
    "sg:city":"Vincennes",
    "sg:classifiers":[
        {
            "category":"Shopping",
            "subcategory":"Computers & Home Electronics",
            "type":"Retail Goods"
        }
    ],
    "sg:phone":"+1 812 886 9543",
    "sg:postcode":"47591",
    "sg:province":"IN",
    "sg:tags":[
        "high",
        "fidelity",
        "stereophonic"
    ],
    "wof:name":"Risley's Audio & Video",
    "wof:placetype":"venue"
},
  "geometry": {"coordinates":[-87.506998,38.658724],"type":"Point"}
}