{
  "type": "Feature",
  "properties": {
    "addr:full":"5225 E Washington St Indianapolis IN 46219",
    "addr:housenumber":"5225",
    "addr:postcode":"46219",
    "addr:street":"E Washington St",
    "iso:country":"US",
    "sg:address":"5225 E Washington St",
    "sg:city":"Indianapolis",
    "sg:classifiers":[
        {
            "category":"Restaurant",
            "type":"Food & Drink"
        }
    ],
    "sg:phone":"+1 317 353 3000",
    "sg:postcode":"46219",
    "sg:province":"IN",
    "sg:tags":[
        "pizza"
    ],
    "wof:name":"Taylor Made Pizza II",
    "wof:placetype":"venue"
},
  "geometry": {"coordinates":[-86.081755,39.770147],"type":"Point"}
}