{
  "type": "Feature",
  "properties": {
    "iso:country":"US",
    "sg:address":"611 Deming St",
    "sg:city":"Terre Haute",
    "sg:classifiers":[
        {
            "category":"Real Estate",
            "subcategory":"Architect",
            "type":"Services"
        }
    ],
    "sg:phone":"+1 812 232 5256",
    "sg:postcode":"47807",
    "sg:province":"IN",
    "wof:name":"Sanders & Assoc Inc",
    "wof:placetype":"venue"
},
  "geometry": {"coordinates":[-87.409665,39.458591],"type":"Point"}
}