{
  "type": "Feature",
  "properties": {
    "addr:full":"3115 S Walnut Street Pike Bloomington IN 47401",
    "addr:housenumber":"3115",
    "addr:postcode":"47401",
    "addr:street":"S Walnut Street Pike",
    "iso:country":"US",
    "sg:address":"3115 S Walnut Street Pike",
    "sg:city":"Bloomington",
    "sg:classifiers":[
        {
            "category":"Autos & Motor Vehicles",
            "subcategory":"Automobile Sales",
            "type":"Retail Goods"
        }
    ],
    "sg:phone":"+1 812 339 1161",
    "sg:postcode":"47401",
    "sg:province":"IN",
    "sg:tags":[
        "car",
        "dealer"
    ],
    "wof:name":"Royal Mazda",
    "wof:placetype":"venue"
},
  "geometry": {"coordinates":[-86.52672200000001,39.128839],"type":"Point"}
}