{
  "type": "Feature",
  "properties": {
    "iso:country":"US",
    "sg:address":"20 Center Dr",
    "sg:city":"Crawfordsville",
    "sg:classifiers":[
        {
            "category":"Building & Trades",
            "subcategory":"Construction",
            "type":"Services"
        }
    ],
    "sg:phone":"+1 765 362 1564",
    "sg:postcode":"47933",
    "sg:province":"IN",
    "wof:name":"Roach Construction",
    "wof:placetype":"venue"
},
  "geometry": {"coordinates":[-86.88685,40.022417],"type":"Point"}
}