{
  "type": "Feature",
  "properties": {
    "iso:country":"US",
    "sg:address":"2709 Enterprise Dr",
    "sg:city":"Anderson",
    "sg:classifiers":[
        {
            "category":"Manufacturing",
            "subcategory":"Tools & Machinery",
            "type":"Manufacturing & Wholesale Goods"
        }
    ],
    "sg:phone":"+1 765 778 4080",
    "sg:postcode":"46013",
    "sg:province":"IN",
    "sg:tags":[
        "register",
        "cash",
        "supply"
    ],
    "sg:website":"www.midwestpos.com",
    "wof:name":"Midwest POS Solutions",
    "wof:placetype":"venue"
},
  "geometry": {"coordinates":[-85.726268,40.037763],"type":"Point"}
}