{
  "type": "Feature",
  "properties": {
    "iso:country":"US",
    "sg:address":"120 N Range Line Rd",
    "sg:city":"Carmel",
    "sg:classifiers":[
        {
            "category":"Wholesale",
            "subcategory":"Durable Goods & Equipment",
            "type":"Manufacturing & Wholesale Goods"
        }
    ],
    "sg:phone":"+1 317 846 6104",
    "sg:postcode":"46032",
    "sg:province":"IN",
    "sg:tags":[
        "representative",
        "manufacturer"
    ],
    "wof:name":"Sweco Inc",
    "wof:placetype":"venue"
},
  "geometry": {"coordinates":[-86.127133,39.979436],"type":"Point"}
}