{
  "type": "Feature",
  "properties": {
    "iso:country":"US",
    "sg:address":"8001 E Old Fort Harrison Ave",
    "sg:city":"Terre Haute",
    "sg:classifiers":[
        {
            "category":"Professional",
            "subcategory":"Business Services",
            "type":"Services"
        }
    ],
    "sg:phone":"+1 812 877 3383",
    "sg:postcode":"47803",
    "sg:province":"IN",
    "sg:tags":[
        "interior",
        "consultant",
        "design",
        "decorator"
    ],
    "wof:name":"Linda's Interiors Inc",
    "wof:placetype":"venue"
},
  "geometry": {"coordinates":[-87.292089,39.506078],"type":"Point"}
}