{
  "type": "Feature",
  "properties": {
    "iso:country":"US",
    "sg:address":"901 Oak Hill Rd",
    "sg:city":"Evansville",
    "sg:classifiers":[
        {
            "category":"Building & Trades",
            "subcategory":"Construction",
            "type":"Services"
        }
    ],
    "sg:phone":"+1 812 471 5814",
    "sg:postcode":"47711",
    "sg:province":"IN",
    "sg:tags":[
        "general",
        "contractor"
    ],
    "wof:name":"Tradesman Contractors",
    "wof:placetype":"venue"
},
  "geometry": {"coordinates":[-87.53037999999999,37.987809],"type":"Point"}
}