{
  "type": "Feature",
  "properties": {
    "iso:country":"US",
    "sg:address":"8243 Kennedy Ave",
    "sg:city":"Highland",
    "sg:classifiers":[
        {
            "category":"Food & Beverages",
            "subcategory":"Groceries & Convenience Stores",
            "type":"Retail Goods"
        }
    ],
    "sg:phone":"+1 219 923 1685",
    "sg:postcode":"46322",
    "sg:province":"IN",
    "wof:name":"Lucky 7",
    "wof:placetype":"venue"
},
  "geometry": {"coordinates":[-87.461578,41.563097],"type":"Point"}
}