{
  "type": "Feature",
  "properties": {
    "addr:full":"6103 Clearview Dr Carmel IN 46033",
    "addr:housenumber":"6103",
    "addr:postcode":"46033",
    "addr:street":"Clearview Dr",
    "iso:country":"US",
    "sg:address":"6103 Clearview Dr",
    "sg:city":"Carmel",
    "sg:classifiers":[
        {
            "category":"Building & Trades",
            "subcategory":"Locksmith",
            "type":"Services"
        }
    ],
    "sg:phone":"+1 317 682 9096",
    "sg:postcode":"46033",
    "sg:province":"IN",
    "sg:tags":[
        "key"
    ],
    "wof:name":"A Emergency Locksmith",
    "wof:placetype":"venue"
},
  "geometry": {"coordinates":[-86.065099,39.965419],"type":"Point"}
}