{
  "type": "Feature",
  "properties": {
    "addr:full":"231 W 10th St Anderson IN 46016",
    "addr:housenumber":"231",
    "addr:postcode":"46016",
    "addr:street":"W 10Th St",
    "iso:country":"US",
    "sg:address":"231 W 10th St",
    "sg:city":"Anderson",
    "sg:classifiers":[
        {
            "category":"Organizations",
            "subcategory":"Religious Organization",
            "type":"Services"
        }
    ],
    "sg:phone":"+1 765 643 4827",
    "sg:postcode":"46016",
    "sg:province":"IN",
    "sg:tags":[
        "church"
    ],
    "wof:name":"Central Community Chapel",
    "wof:placetype":"venue"
},
  "geometry": {"coordinates":[-85.683018,40.106011],"type":"Point"}
}