{
  "type": "Feature",
  "properties": {
    "iso:country":"US",
    "sg:address":"9668 N Smokey Row Rd",
    "sg:city":"Mooresville",
    "sg:classifiers":[
        {
            "category":"Professional",
            "type":"Services"
        }
    ],
    "sg:phone":"+1 317 834 2789",
    "sg:postcode":"46158",
    "sg:province":"IN",
    "sg:tags":[
        "establishment"
    ],
    "wof:name":"Prairie Aggregates",
    "wof:placetype":"venue"
},
  "geometry": {"coordinates":[-86.269759,39.586674],"type":"Point"}
}