{
  "type": "Feature",
  "properties": {
    "iso:country":"US",
    "sg:address":"618 N Washington St",
    "sg:city":"Delphi",
    "sg:classifiers":[
        {
            "category":"Education",
            "subcategory":"School",
            "type":"Public Place"
        }
    ],
    "sg:phone":"+1 765 564 3992",
    "sg:postcode":"46923",
    "sg:province":"IN",
    "wof:name":"Genesis Program",
    "wof:placetype":"venue"
},
  "geometry": {"coordinates":[-86.677727,40.591611],"type":"Point"}
}