{
  "type": "Feature",
  "properties": {
    "iso:country":"US",
    "sg:address":"503 E Beaver St",
    "sg:city":"Morocco",
    "sg:classifiers":[
        {
            "category":"Organizations",
            "subcategory":"Religious Organization",
            "type":"Services"
        }
    ],
    "sg:phone":"+1 219 285 2791",
    "sg:postcode":"47963",
    "sg:province":"IN",
    "wof:name":"Cornoer Assembly of God",
    "wof:placetype":"venue"
},
  "geometry": {"coordinates":[-87.447692,40.947926],"type":"Point"}
}