{
  "type": "Feature",
  "properties": {
    "addr:full":"8021 W 1100 N Ambia IN 47917",
    "addr:housenumber":"8021",
    "addr:postcode":"47917",
    "addr:street":"W 1100 N",
    "iso:country":"US",
    "sg:address":"8021 W 1100 N",
    "sg:city":"Ambia",
    "sg:phone":"+1 765 869 5680",
    "sg:postcode":"47917",
    "sg:province":"IN",
    "sg:tags":[
        "farm",
        "corn",
        "soybean"
    ],
    "wof:name":"Carl Foster",
    "wof:placetype":"venue"
},
  "geometry": {"coordinates":[-87.474007,40.47673],"type":"Point"}
}