{
  "type": "Feature",
  "properties": {
    "iso:country":"US",
    "sg:address":"3759 S 500 E",
    "sg:city":"Columbia City",
    "sg:classifiers":[
        {
            "category":"Freight",
            "type":"Transportation"
        }
    ],
    "sg:phone":"+1 260 248 2085",
    "sg:postcode":"46725",
    "sg:province":"IN",
    "sg:tags":[
        "operator",
        "local",
        "trucking"
    ],
    "wof:name":"CC Trucking",
    "wof:placetype":"venue"
},
  "geometry": {"coordinates":[-85.395432,41.107288],"type":"Point"}
}