{
  "type": "Feature",
  "properties": {
    "iso:country":"US",
    "sg:address":"2153 W Ryman Dr",
    "sg:city":"Terre Haute",
    "sg:classifiers":[
        {
            "category":"Retail",
            "subcategory":"Auto Repair",
            "type":"Services"
        }
    ],
    "sg:phone":"+1 812 231 0051",
    "sg:postcode":"47802",
    "sg:province":"IN",
    "sg:tags":[
        "body",
        "automobile",
        "painting"
    ],
    "wof:name":"Davis Drive Collision Repair",
    "wof:placetype":"venue"
},
  "geometry": {"coordinates":[-87.446146,39.390381],"type":"Point"}
}