{
  "type": "Feature",
  "properties": {
    "iso:country":"US",
    "sg:address":"1155 W McClain St",
    "sg:city":"Scottsburg",
    "sg:classifiers":[
        {
            "category":"Organizations",
            "subcategory":"Religious Organization",
            "type":"Services"
        }
    ],
    "sg:phone":"+1 812 752 6664",
    "sg:postcode":"47170",
    "sg:province":"IN",
    "sg:tags":[
        "church"
    ],
    "wof:name":"Seventh-Day Adventist Church",
    "wof:placetype":"venue"
},
  "geometry": {"coordinates":[-85.783703,38.685505],"type":"Point"}
}