{
  "type": "Feature",
  "properties": {
    "iso:country":"US",
    "sg:address":"1124 Silver Hills Ln",
    "sg:city":"New Albany",
    "sg:classifiers":[
        {
            "category":"Government",
            "subcategory":"Office",
            "type":"Public Place"
        }
    ],
    "sg:phone":"+1 812 949 2394",
    "sg:postcode":"47150",
    "sg:province":"IN",
    "sg:tags":[
        "village"
    ],
    "wof:name":"City Of New Albany",
    "wof:placetype":"venue"
},
  "geometry": {"coordinates":[-85.838835,38.282852],"type":"Point"}
}