{
  "type": "Feature",
  "properties": {
    "iso:country":"US",
    "sg:address":"9365 Counselors Row",
    "sg:city":"Indianapolis",
    "sg:classifiers":[
        {
            "category":"Professional",
            "subcategory":"Business Services",
            "type":"Services"
        }
    ],
    "sg:phone":"+1 317 805 3975",
    "sg:postcode":"46240",
    "sg:province":"IN",
    "sg:tags":[
        "interior",
        "consultant",
        "design",
        "decorator"
    ],
    "sg:website":"www.maregattiinteriors.com",
    "wof:name":"Maregatti Interiors",
    "wof:placetype":"venue"
},
  "geometry": {"coordinates":[-86.104352,39.923927],"type":"Point"}
}