{
  "type": "Feature",
  "properties": {
    "addr:full":"1955 E Wabash St Frankfort IN 46041",
    "addr:housenumber":"1955",
    "addr:postcode":"46041",
    "addr:street":"E Wabash St",
    "iso:country":"US",
    "sg:address":"1955 E Wabash St",
    "sg:city":"Frankfort",
    "sg:classifiers":[
        {
            "category":"Shopping",
            "subcategory":"Tobacco",
            "type":"Retail Goods"
        }
    ],
    "sg:phone":"+1 765 654 0469",
    "sg:postcode":"46041",
    "sg:province":"IN",
    "sg:tags":[
        "cigarette",
        "cigar",
        "dealer"
    ],
    "wof:name":"Low Bob's Discount Tobacco",
    "wof:placetype":"venue"
},
  "geometry": {"coordinates":[-86.49036,40.278861],"type":"Point"}
}