{
  "type": "Feature",
  "properties": {
    "iso:country":"US",
    "sg:address":"105 E Ohio St",
    "sg:city":"Indianapolis",
    "sg:classifiers":[
        {
            "category":"Shopping",
            "subcategory":"Pharmacy",
            "type":"Retail Goods"
        }
    ],
    "sg:phone":"+1 317 636 5577",
    "sg:postcode":"46204",
    "sg:province":"IN",
    "wof:name":"CVS Pharmacy",
    "wof:placetype":"venue"
},
  "geometry": {"coordinates":[-86.155275,39.769853],"type":"Point"}
}