{
  "type": "Feature",
  "properties": {
    "iso:country":"US",
    "sg:address":"800 Zahn St",
    "sg:city":"Huntington",
    "sg:classifiers":[
        {
            "category":"Government",
            "subcategory":"Office",
            "type":"Public Place"
        }
    ],
    "sg:phone":"+1 260 356 0518",
    "sg:postcode":"46750",
    "sg:province":"IN",
    "sg:tags":[
        "state",
        "security"
    ],
    "wof:name":"National Guard Recruiter",
    "wof:placetype":"venue"
},
  "geometry": {"coordinates":[-85.50579399999999,40.882166],"type":"Point"}
}