{
  "type": "Feature",
  "properties": {
    "iso:country":"US",
    "sg:address":"7996 E State Rd 4",
    "sg:city":"Walkerton",
    "sg:classifiers":[
        {
            "category":"Food & Beverages",
            "subcategory":"Groceries & Convenience Stores",
            "type":"Retail Goods"
        }
    ],
    "sg:phone":"+1 219 369 1306",
    "sg:postcode":"46574",
    "sg:province":"IN",
    "sg:tags":[
        "grocer"
    ],
    "wof:name":"Fish Lake Market",
    "wof:placetype":"venue"
},
  "geometry": {"coordinates":[-86.544352,41.564763],"type":"Point"}
}