{
  "type": "Feature",
  "properties": {
    "iso:country":"US",
    "sg:address":"10625 E Seelyville Ave",
    "sg:city":"Brazil",
    "sg:classifiers":[
        {
            "category":"Recreation",
            "type":"Entertainment"
        }
    ],
    "sg:phone":"+1 812 877 2911",
    "sg:postcode":"47834",
    "sg:province":"IN",
    "sg:tags":[
        "club",
        "membership"
    ],
    "wof:name":"Outdoor Recreation Club Inc",
    "wof:placetype":"venue"
},
  "geometry": {"coordinates":[-87.25666200000001,39.484222],"type":"Point"}
}