{
  "type": "Feature",
  "properties": {
    "addr:full":"6468 Harrison Ct Merrillville IN 46410",
    "addr:housenumber":"6468",
    "addr:postcode":"46410",
    "addr:street":"Harrison Ct",
    "iso:country":"US",
    "sg:address":"6468 Harrison Ct",
    "sg:city":"Merrillville",
    "sg:classifiers":[
        {
            "category":"Real Estate",
            "subcategory":"Real Estate Agent",
            "type":"Services"
        }
    ],
    "sg:phone":"+1 219 769 7175",
    "sg:postcode":"46410",
    "sg:province":"IN",
    "sg:tags":[
        "property",
        "rental"
    ],
    "wof:name":"D A D A Harris Co",
    "wof:placetype":"venue"
},
  "geometry": {"coordinates":[-87.344883,41.500285],"type":"Point"}
}