{
  "type": "Feature",
  "properties": {
    "iso:country":"US",
    "sg:address":"1399 E 500 S",
    "sg:city":"Churubusco",
    "sg:classifiers":[
        {
            "category":"Professional",
            "type":"Services"
        }
    ],
    "sg:phone":"+1 260 693 0076",
    "sg:postcode":"46723",
    "sg:province":"IN",
    "sg:tags":[
        "establishment"
    ],
    "wof:name":"Consolidated Co Inc",
    "wof:placetype":"venue"
},
  "geometry": {"coordinates":[-85.39712,41.279537],"type":"Point"}
}