{
  "type": "Feature",
  "properties": {
    "iso:country":"US",
    "sg:address":"5474 W 200 N",
    "sg:city":"Rensselaer",
    "sg:classifiers":[
        {
            "category":"Organizations",
            "subcategory":"Religious Organization",
            "type":"Services"
        }
    ],
    "sg:phone":"+1 219 866 3933",
    "sg:postcode":"47978",
    "sg:province":"IN",
    "sg:tags":[
        "church"
    ],
    "wof:name":"Brushwood United Methodist Chr",
    "wof:placetype":"venue"
},
  "geometry": {"coordinates":[-87.15129,41.041563],"type":"Point"}
}