{
  "type": "Feature",
  "properties": {
    "addr:full":"545 Dallas St Gary IN 46406",
    "addr:housenumber":"545",
    "addr:postcode":"46406",
    "addr:street":"Dallas St Gary",
    "iso:country":"US",
    "sg:address":"545 Dallas St",
    "sg:city":"Gary",
    "sg:classifiers":[
        {
            "category":"Social Services",
            "subcategory":"Child Care",
            "type":"Services"
        }
    ],
    "sg:phone":"+1 219 944 7494",
    "sg:postcode":"46406",
    "sg:province":"IN",
    "wof:name":"Davis Home Day Care",
    "wof:placetype":"venue"
},
  "geometry": {"coordinates":[-87.409462,41.600316],"type":"Point"}
}