{
  "type": "Feature",
  "properties": {
    "iso:country":"US",
    "sg:address":"99 E 86th Ave",
    "sg:city":"Merrillville",
    "sg:classifiers":[
        {
            "category":"Health Services",
            "subcategory":"Doctor",
            "type":"Services"
        }
    ],
    "sg:phone":"+1 219 736 8800",
    "sg:postcode":"46410",
    "sg:province":"IN",
    "sg:tags":[
        "physician",
        "reconstructive",
        "surgeons",
        "plastic",
        "otorhinolaryngology",
        "nose",
        "throat",
        "surgeon",
        "ear"
    ],
    "sg:website":"http://carepointe.net",
    "wof:name":"CarePointe Ear Nose Throat & Sinus Centers",
    "wof:placetype":"venue"
},
  "geometry": {"coordinates":[-87.334397,41.461945],"type":"Point"}
}