{
  "type": "Feature",
  "properties": {
    "iso:country":"US",
    "sg:address":"499 E St",
    "sg:city":"Kouts",
    "sg:classifiers":[
        {
            "category":"Building & Trades",
            "subcategory":"Construction",
            "type":"Services"
        }
    ],
    "sg:phone":"+1 219 929 7651",
    "sg:postcode":"46350",
    "sg:province":"IN",
    "sg:tags":[
        "house"
    ],
    "wof:name":"Bills Excavating Builders",
    "wof:placetype":"venue"
},
  "geometry": {"coordinates":[-86.724155,41.602942],"type":"Point"}
}