{
  "type": "Feature",
  "properties": {
    "iso:country":"US",
    "sg:address":"2311 Spy Run Ave",
    "sg:city":"Fort Wayne",
    "sg:classifiers":[
        {
            "category":"Wholesale",
            "subcategory":"Machinery & Supplies",
            "type":"Manufacturing & Wholesale Goods"
        }
    ],
    "sg:phone":"+1 260 471 3037",
    "sg:postcode":"46805",
    "sg:province":"IN",
    "sg:tags":[
        "equipment",
        "establishment"
    ],
    "wof:name":"Nail Expression",
    "wof:placetype":"venue"
},
  "geometry": {"coordinates":[-85.136901,41.096101],"type":"Point"}
}