{
  "type": "Feature",
  "properties": {
    "iso:country":"US",
    "sg:address":"609 Dubois St",
    "sg:city":"Vincennes",
    "sg:classifiers":[
        {
            "category":"Health Services",
            "subcategory":"Optometrist",
            "type":"Services"
        }
    ],
    "sg:phone":"+1 812 882 8500",
    "sg:postcode":"47591",
    "sg:province":"IN",
    "wof:name":"Family Vision",
    "wof:placetype":"venue"
},
  "geometry": {"coordinates":[-87.532707,38.674789],"type":"Point"}
}