{
  "type": "Feature",
  "properties": {
    "iso:country":"US",
    "sg:address":"2040 Raible Ave",
    "sg:city":"Anderson",
    "sg:phone":"+1 765 643 5026",
    "sg:postcode":"46011",
    "sg:province":"IN",
    "sg:tags":[
        "oil"
    ],
    "wof:name":"Don Hartman Oil Co",
    "wof:placetype":"venue"
},
  "geometry": {"coordinates":[-85.711007,40.095612],"type":"Point"}
}