{
  "type": "Feature",
  "properties": {
    "iso:country":"US",
    "sg:address":"285 Morton Ave",
    "sg:city":"Martinsville",
    "sg:classifiers":[
        {
            "category":"Food & Beverages",
            "subcategory":"Groceries & Convenience Stores",
            "type":"Retail Goods"
        }
    ],
    "sg:phone":"+1 765 342 5736",
    "sg:postcode":"46151",
    "sg:province":"IN",
    "sg:tags":[
        "grocer"
    ],
    "wof:name":"Marsh Supermarket",
    "wof:placetype":"venue"
},
  "geometry": {"coordinates":[-86.429109,39.418951],"type":"Point"}
}