{
  "type": "Feature",
  "properties": {
    "addr:full":"650 N Girls School Rd Indianapolis IN 46214",
    "addr:housenumber":"650",
    "addr:postcode":"46214",
    "addr:street":"N Girls School Rd",
    "iso:country":"US",
    "sg:address":"650 N Girls School Rd",
    "sg:city":"Indianapolis",
    "sg:classifiers":[
        {
            "category":"Professional",
            "subcategory":"Accounting & Tax Preparation",
            "type":"Services"
        }
    ],
    "sg:phone":"+1 317 209 0813",
    "sg:postcode":"46214",
    "sg:province":"IN",
    "sg:tags":[
        "accountant"
    ],
    "wof:name":"Ronald L Hooper CPA",
    "wof:placetype":"venue"
},
  "geometry": {"coordinates":[-86.289258,39.77586],"type":"Point"}
}