{
  "type": "Feature",
  "properties": {
    "iso:country":"US",
    "sg:address":"1700 S Indiana Ave",
    "sg:city":"Auburn",
    "sg:classifiers":[
        {
            "category":"Manufacturing",
            "subcategory":"Metals",
            "type":"Manufacturing & Wholesale Goods"
        }
    ],
    "sg:phone":"+1 260 925 2588",
    "sg:postcode":"46706",
    "sg:province":"IN",
    "sg:tags":[
        "industrial",
        "valve"
    ],
    "wof:name":"SCP Inc",
    "wof:placetype":"venue"
},
  "geometry": {"coordinates":[-85.061458,41.354324],"type":"Point"}
}