{
  "type": "Feature",
  "properties": {
    "iso:country":"US",
    "sg:address":"3037 Goshen Rd",
    "sg:city":"Fort Wayne",
    "sg:classifiers":[
        {
            "category":"Shopping",
            "type":"Retail Goods"
        }
    ],
    "sg:phone":"+1 260 484 3741",
    "sg:postcode":"46808",
    "sg:province":"IN",
    "sg:tags":[
        "merchandise"
    ],
    "wof:name":"Mechanics CB Shop",
    "wof:placetype":"venue"
},
  "geometry": {"coordinates":[-85.178397,41.114807],"type":"Point"}
}