{
  "type": "Feature",
  "properties": {
    "iso:country":"US",
    "sg:address":"971 W US Hwy 40",
    "sg:city":"Greenfield",
    "sg:classifiers":[
        {
            "category":"Organizations",
            "subcategory":"Religious Organization",
            "type":"Services"
        }
    ],
    "sg:phone":"+1 317 462 9398",
    "sg:postcode":"46140",
    "sg:province":"IN",
    "sg:tags":[
        "church"
    ],
    "wof:name":"First Assembly Of God",
    "wof:placetype":"venue"
},
  "geometry": {"coordinates":[-85.820138,39.782684],"type":"Point"}
}