{
  "type": "Feature",
  "properties": {
    "iso:country":"US",
    "sg:address":"595 N Troy Ave",
    "sg:city":"Marion",
    "sg:classifiers":[
        {
            "category":"Manufacturing",
            "subcategory":"Signs",
            "type":"Manufacturing & Wholesale Goods"
        },
        {
            "category":"Professional",
            "subcategory":"Business Services",
            "type":"Services"
        }
    ],
    "sg:phone":"+1 765 384 5301",
    "sg:postcode":"46952",
    "sg:province":"IN",
    "sg:tags":[
        "specialty",
        "mfg"
    ],
    "wof:name":"Dougherty Sign Studio",
    "wof:placetype":"venue"
},
  "geometry": {"coordinates":[-85.712482,40.562336],"type":"Point"}
}