{
  "type": "Feature",
  "properties": {
    "iso:country":"US",
    "sg:address":"3940 W Delta Dr",
    "sg:city":"Marion",
    "sg:classifiers":[
        {
            "category":"Real Estate",
            "subcategory":"Real Estate Operator",
            "type":"Services"
        }
    ],
    "sg:phone":"+1 765 674 3662",
    "sg:postcode":"46952",
    "sg:province":"IN",
    "sg:tags":[
        "apartment"
    ],
    "wof:name":"Colonial Crest Apartments",
    "wof:placetype":"venue"
},
  "geometry": {"coordinates":[-85.748376,40.568922],"type":"Point"}
}