{
  "type": "Feature",
  "properties": {
    "iso:country":"US",
    "sg:address":"400 E Jefferson St",
    "sg:city":"Franklin",
    "sg:classifiers":[
        {
            "category":"Autos & Motor Vehicles",
            "subcategory":"Fuel & Gas Station",
            "type":"Retail Goods"
        }
    ],
    "sg:phone":"+1 317 346 6577",
    "sg:postcode":"46131",
    "sg:province":"IN",
    "sg:tags":[
        "oil"
    ],
    "wof:name":"Clark Gas Station",
    "wof:placetype":"venue"
},
  "geometry": {"coordinates":[-86.0493,39.48082],"type":"Point"}
}