{
  "type": "Feature",
  "properties": {
    "iso:country":"US",
    "sg:address":"4158 Meadows Dr",
    "sg:city":"Indianapolis",
    "sg:classifiers":[
        {
            "category":"Social Services",
            "subcategory":"Child Care",
            "type":"Services"
        }
    ],
    "sg:phone":"+1 317 377 1045",
    "sg:postcode":"46205",
    "sg:province":"IN",
    "wof:name":"Tony Child Care",
    "wof:placetype":"venue"
},
  "geometry": {"coordinates":[-86.109282,39.832507],"type":"Point"}
}