{
  "type": "Feature",
  "properties": {
    "iso:country":"US",
    "sg:address":"3809 E 82nd St",
    "sg:city":"Indianapolis",
    "sg:classifiers":[
        {
            "category":"Shopping",
            "subcategory":"Jewelry",
            "type":"Retail Goods"
        },
        {
            "category":"Manufacturing",
            "subcategory":"Jewelry",
            "type":"Manufacturing & Wholesale Goods"
        },
        {
            "category":"Retail",
            "subcategory":"Repair Shop",
            "type":"Services"
        }
    ],
    "sg:phone":"+1 317 577 7070",
    "sg:postcode":"46240",
    "sg:province":"IN",
    "sg:tags":[
        "repairing",
        "designer",
        "watch",
        "appraiser",
        "jeweler"
    ],
    "wof:name":"Hofmeister Personal Jewelers",
    "wof:placetype":"venue"
},
  "geometry": {"coordinates":[-86.101303,39.908798],"type":"Point"}
}