{
  "type": "Feature",
  "properties": {
    "addr:full":"723 3rd Ave Jasper IN 47546",
    "addr:housenumber":"723",
    "addr:postcode":"47546",
    "addr:street":"3Rd Ave",
    "iso:country":"US",
    "sg:address":"723 3rd Ave",
    "sg:city":"Jasper",
    "sg:classifiers":[
        {
            "category":"Retail",
            "subcategory":"Portrait Studio",
            "type":"Services"
        }
    ],
    "sg:phone":"+1 812 634 7448",
    "sg:postcode":"47546",
    "sg:province":"IN",
    "sg:tags":[
        "photographer"
    ],
    "wof:name":"Olan Mills Portrait Studio",
    "wof:placetype":"venue"
},
  "geometry": {"coordinates":[-86.916888,38.378655],"type":"Point"}
}