{
  "type": "Feature",
  "properties": {
    "iso:country":"US",
    "sg:address":"211 W 2nd North St",
    "sg:city":"Versailles",
    "sg:classifiers":[
        {
            "category":"Retail",
            "subcategory":"Animal Services",
            "type":"Services"
        }
    ],
    "sg:phone":"+1 812 689 4257",
    "sg:postcode":"47042",
    "sg:province":"IN",
    "sg:tags":[
        "pet",
        "grooming",
        "washing"
    ],
    "wof:name":"Lila's Love On A Leash Dog",
    "wof:placetype":"venue"
},
  "geometry": {"coordinates":[-85.25321,39.073448],"type":"Point"}
}