{
  "type": "Feature",
  "properties": {
    "iso:country":"US",
    "sg:address":"425 E Jefferson St",
    "sg:city":"Tipton",
    "sg:classifiers":[
        {
            "category":"Food & Beverages",
            "subcategory":"Specialty",
            "type":"Retail Goods"
        }
    ],
    "sg:phone":"+1 765 675 9440",
    "sg:postcode":"46072",
    "sg:province":"IN",
    "sg:tags":[
        "tea",
        "coffee"
    ],
    "wof:name":"Jefferson Street Coffee Co",
    "wof:placetype":"venue"
},
  "geometry": {"coordinates":[-86.036716,40.282358],"type":"Point"}
}