{
  "type": "Feature",
  "properties": {
    "iso:country":"US",
    "sg:address":"505 Fulton St",
    "sg:city":"Berne",
    "sg:classifiers":[
        {
            "category":"Manufacturing",
            "subcategory":"Wood Products",
            "type":"Manufacturing & Wholesale Goods"
        }
    ],
    "sg:phone":"+1 260 589 2388",
    "sg:postcode":"46711",
    "sg:province":"IN",
    "sg:tags":[
        "mfg"
    ],
    "wof:name":"Decatur Industries",
    "wof:placetype":"venue"
},
  "geometry": {"coordinates":[-84.950541,40.654012],"type":"Point"}
}