{
  "type": "Feature",
  "properties": {
    "iso:country":"US",
    "sg:address":"727 Fulton St",
    "sg:city":"Fort Wayne",
    "sg:classifiers":[
        {
            "category":"Real Estate",
            "subcategory":"Real Estate Operator",
            "type":"Services"
        }
    ],
    "sg:phone":"+1 260 420 8700",
    "sg:postcode":"46802",
    "sg:province":"IN",
    "sg:tags":[
        "apartment"
    ],
    "wof:name":"Midtowne Realty Inc",
    "wof:placetype":"venue"
},
  "geometry": {"coordinates":[-85.14731500000001,41.07837],"type":"Point"}
}