{
  "type": "Feature",
  "properties": {
    "iso:country":"US",
    "sg:address":"925 W Hancock Rd",
    "sg:city":"Scottsburg",
    "sg:classifiers":[
        {
            "category":"Farming",
            "subcategory":"Livestock Farm",
            "type":"Manufacturing & Wholesale Goods"
        }
    ],
    "sg:phone":"+1 812 754 1566",
    "sg:postcode":"47170",
    "sg:province":"IN",
    "sg:tags":[
        "equine"
    ],
    "wof:name":"Rosehill Xtc Farm",
    "wof:placetype":"venue"
},
  "geometry": {"coordinates":[-85.791988,38.64856],"type":"Point"}
}