{
  "type": "Feature",
  "properties": {
    "iso:country":"US",
    "sg:address":"2420 Knollridge Dr",
    "sg:city":"Fort Wayne",
    "sg:classifiers":[
        {
            "category":"Real Estate",
            "subcategory":"Real Estate Agent",
            "type":"Services"
        }
    ],
    "sg:phone":"+1 260 493 4222",
    "sg:postcode":"46815",
    "sg:province":"IN",
    "wof:name":"David Augustyniak Real Estate",
    "wof:placetype":"venue"
},
  "geometry": {"coordinates":[-85.052178,41.101487],"type":"Point"}
}