{
  "type": "Feature",
  "properties": {
    "iso:country":"US",
    "sg:address":"2700 S Main St",
    "sg:city":"South Bend",
    "sg:classifiers":[
        {
            "category":"Home & Garden",
            "subcategory":"Household Appliances",
            "type":"Retail Goods"
        }
    ],
    "sg:phone":"+1 574 291 6000",
    "sg:postcode":"46614",
    "sg:province":"IN",
    "sg:website":"www.bobmillers.com",
    "wof:name":"Bob Miller's Appliance Sales",
    "wof:placetype":"venue"
},
  "geometry": {"coordinates":[-86.25125,41.645945],"type":"Point"}
}