{
  "type": "Feature",
  "properties": {
    "iso:country":"US",
    "sg:address":"8135 Pendleton Pike",
    "sg:city":"Indianapolis",
    "sg:classifiers":[
        {
            "category":"Restaurant",
            "type":"Food & Drink"
        }
    ],
    "sg:phone":"+1 317 898 5455",
    "sg:postcode":"46226",
    "sg:province":"IN",
    "sg:website":"www.mclcafe.com",
    "wof:name":"MCL Cafeteria",
    "wof:placetype":"venue"
},
  "geometry": {"coordinates":[-86.022803,39.838291],"type":"Point"}
}