{
  "type": "Feature",
  "properties": {
    "addr:full":"3902 W 86th St Indianapolis IN 46268",
    "addr:housenumber":"3902",
    "addr:postcode":"46268",
    "addr:street":"W 86Th St",
    "iso:country":"US",
    "sg:address":"3902 W 86th St",
    "sg:city":"Indianapolis",
    "sg:classifiers":[
        {
            "category":"Personal",
            "subcategory":"Beauty Salon",
            "type":"Services"
        }
    ],
    "sg:phone":"+1 317 872 5756",
    "sg:postcode":"46268",
    "sg:province":"IN",
    "wof:name":"Rose-Dore Salon",
    "wof:placetype":"venue"
},
  "geometry": {"coordinates":[-86.22763999999999,39.911704],"type":"Point"}
}