{
  "type": "Feature",
  "properties": {
    "iso:country":"US",
    "sg:address":"120 Round Tree Ct",
    "sg:city":"Ellettsville",
    "sg:classifiers":[
        {
            "category":"Home & Garden",
            "subcategory":"Household Appliances",
            "type":"Retail Goods"
        }
    ],
    "sg:phone":"+1 812 829 1126",
    "sg:postcode":"47429",
    "sg:province":"IN",
    "sg:tags":[
        "cleaners",
        "vacuum"
    ],
    "wof:name":"Tri-State Kirby",
    "wof:placetype":"venue"
},
  "geometry": {"coordinates":[-86.634687,39.240323],"type":"Point"}
}