{
  "type": "Feature",
  "properties": {
    "iso:country":"US",
    "sg:address":"7301 Maplecrest Rd",
    "sg:city":"Fort Wayne",
    "sg:classifiers":[
        {
            "category":"Food & Beverages",
            "subcategory":"Groceries & Convenience Stores",
            "type":"Retail Goods"
        }
    ],
    "sg:phone":"+1 260 486 4050",
    "sg:postcode":"46835",
    "sg:province":"IN",
    "sg:tags":[
        "grocer"
    ],
    "wof:name":"Marsh Supermarket",
    "wof:placetype":"venue"
},
  "geometry": {"coordinates":[-85.063023,41.147733],"type":"Point"}
}