{
  "type": "Feature",
  "properties": {
    "iso:country":"US",
    "sg:address":"4720 E Morgan Ave",
    "sg:city":"Evansville",
    "sg:classifiers":[
        {
            "category":"Autos & Motor Vehicles",
            "subcategory":"Automobile Sales",
            "type":"Retail Goods"
        }
    ],
    "sg:phone":"+1 812 962 1250",
    "sg:postcode":"47715",
    "sg:province":"IN",
    "sg:tags":[
        "car",
        "dealer"
    ],
    "wof:name":"Morgan Autos Of Evansville",
    "wof:placetype":"venue"
},
  "geometry": {"coordinates":[-87.494814,37.991301],"type":"Point"}
}