{
  "type": "Feature",
  "properties": {
    "iso:country":"US",
    "sg:address":"6949 Kennedy Ave Ste E",
    "sg:city":"Hammond",
    "sg:classifiers":[
        {
            "category":"Shopping",
            "subcategory":"Pharmacy",
            "type":"Retail Goods"
        }
    ],
    "sg:phone":"+1 219 972 0992",
    "sg:postcode":"46323",
    "sg:province":"IN",
    "sg:tags":[
        "drugstore"
    ],
    "sg:website":"www.vytospharmacy.com",
    "wof:name":"Vyto's Pharmacy",
    "wof:placetype":"venue"
},
  "geometry": {"coordinates":[-87.46144700000001,41.587472],"type":"Point"}
}