{
  "type": "Feature",
  "properties": {
    "addr:full":"700 W Riverside Dr Jeffersonville IN 47130",
    "addr:housenumber":"700",
    "addr:postcode":"47130",
    "addr:street":"W Riverside Dr",
    "iso:country":"US",
    "sg:address":"700 W Riverside Dr",
    "sg:city":"Jeffersonville",
    "sg:classifiers":[
        {
            "category":"Travel",
            "subcategory":"Hotels & Motels",
            "type":"Entertainment"
        },
        {
            "category":"Retail",
            "subcategory":"Event Space",
            "type":"Services"
        }
    ],
    "sg:phone":"+1 800 537 3612",
    "sg:postcode":"47130",
    "sg:province":"IN",
    "sg:tags":[
        "facility",
        "banquet",
        "planning",
        "reception",
        "meeting",
        "hall"
    ],
    "sg:website":"http://www.ramada.com",
    "wof:name":"Ramada Inn",
    "wof:placetype":"venue"
},
  "geometry": {"coordinates":[-85.74733000000001,38.268261],"type":"Point"}
}