{
  "type": "Feature",
  "properties": {
    "iso:country":"US",
    "sg:address":"1080 W 200 S",
    "sg:city":"Warsaw",
    "sg:classifiers":[
        {
            "category":"Manufacturing",
            "subcategory":"Glass & Minerals",
            "type":"Manufacturing & Wholesale Goods"
        }
    ],
    "sg:phone":"+1 574 269 2722",
    "sg:postcode":"46580",
    "sg:province":"IN",
    "sg:tags":[
        "product",
        "mfg"
    ],
    "wof:name":"Cyrstal Shadows",
    "wof:placetype":"venue"
},
  "geometry": {"coordinates":[-85.85375999999999,41.205135],"type":"Point"}
}