{
  "type": "Feature",
  "properties": {
    "addr:full":"333 N Main St Middlebury IN 46540",
    "addr:housenumber":"333",
    "addr:postcode":"46540",
    "addr:street":"N Main St",
    "iso:country":"US",
    "sg:address":"333 N Main St",
    "sg:city":"Middlebury",
    "sg:classifiers":[
        {
            "category":"Retail",
            "subcategory":"Car Wash",
            "type":"Services"
        }
    ],
    "sg:phone":"+1 574 825 2078",
    "sg:postcode":"46540",
    "sg:province":"IN",
    "sg:tags":[
        "automobile",
        "detail",
        "clean"
    ],
    "wof:name":"Dynamic Auto Detailing Svc",
    "wof:placetype":"venue"
},
  "geometry": {"coordinates":[-85.705242,41.679259],"type":"Point"}
}