{
  "type": "Feature",
  "properties": {
    "iso:country":"US",
    "sg:address":"328 N Kingston Rd",
    "sg:city":"Plymouth",
    "sg:classifiers":[
        {
            "category":"Shopping",
            "subcategory":"Department Store",
            "type":"Retail Goods"
        }
    ],
    "sg:phone":"+1 574 941 2131",
    "sg:postcode":"46563",
    "sg:province":"IN",
    "sg:tags":[
        "shop"
    ],
    "wof:name":"Dollar General",
    "wof:placetype":"venue"
},
  "geometry": {"coordinates":[-86.296161,41.343569],"type":"Point"}
}