{
  "type": "Feature",
  "properties": {
    "addr:full":"5916 Grape Rd Mishawaka IN 46545",
    "addr:housenumber":"5916",
    "addr:postcode":"46545",
    "addr:street":"Grape Rd",
    "iso:country":"US",
    "sg:address":"5916 Grape Rd",
    "sg:city":"Mishawaka",
    "sg:classifiers":[
        {
            "category":"Shopping",
            "subcategory":"Used Merchandise",
            "type":"Retail Goods"
        }
    ],
    "sg:phone":"+1 574 243 9100",
    "sg:postcode":"46545",
    "sg:province":"IN",
    "sg:tags":[
        "clothing"
    ],
    "wof:name":"Plato's Closet",
    "wof:placetype":"venue"
},
  "geometry": {"coordinates":[-86.18749,41.715924],"type":"Point"}
}