{
  "type": "Feature",
  "properties": {
    "addr:full":"4150 Lafayette Rd Indianapolis IN 46254",
    "addr:housenumber":"4150",
    "addr:postcode":"46254",
    "iso:country":"US",
    "sg:address":"4150 Lafayette Rd",
    "sg:city":"Indianapolis",
    "sg:classifiers":[
        {
            "category":"Health Services",
            "subcategory":"Optometrist",
            "type":"Services"
        }
    ],
    "sg:phone":"+1 317 280 0114",
    "sg:postcode":"46254",
    "sg:province":"IN",
    "wof:name":"Eye Works",
    "wof:placetype":"venue"
},
  "geometry": {"coordinates":[-86.24216800000001,39.831064],"type":"Point"}
}