{
  "type": "Feature",
  "properties": {
    "addr:full":"200 Ct Park Logansport IN 46947",
    "addr:postcode":"46947",
    "addr:street":"200 Ct Park",
    "iso:country":"US",
    "sg:address":"200 Ct Park",
    "sg:city":"Logansport",
    "sg:classifiers":[
        {
            "category":"Government",
            "subcategory":"Office",
            "type":"Public Place"
        }
    ],
    "sg:phone":"+1 574 753 7830",
    "sg:postcode":"46947",
    "sg:province":"IN",
    "wof:name":"Cass County Small Claims Div",
    "wof:placetype":"venue"
},
  "geometry": {"coordinates":[-86.367526,40.754337],"type":"Point"}
}