{
  "type": "Feature",
  "properties": {
    "iso:country":"US",
    "sg:address":"1503 High St",
    "sg:city":"Decatur",
    "sg:classifiers":[
        {
            "category":"Real Estate",
            "subcategory":"Developer",
            "type":"Services"
        }
    ],
    "sg:phone":"+1 260 724 2273",
    "sg:postcode":"46733",
    "sg:province":"IN",
    "sg:tags":[
        "cemetery"
    ],
    "wof:name":"St Joseph Catholic Cemetery",
    "wof:placetype":"venue"
},
  "geometry": {"coordinates":[-84.918308,40.812753],"type":"Point"}
}