{
  "type": "Feature",
  "properties": {
    "addr:full":"13630 Bass Rd Fort Wayne IN 46818",
    "addr:housenumber":"13630",
    "addr:postcode":"46818",
    "addr:street":"Bass Rd",
    "iso:country":"US",
    "sg:address":"13630 Bass Rd",
    "sg:city":"Fort Wayne",
    "sg:classifiers":[
        {
            "category":"Personal",
            "subcategory":"Beauty Salon",
            "type":"Services"
        }
    ],
    "sg:phone":"+1 260 625 6500",
    "sg:postcode":"46818",
    "sg:province":"IN",
    "wof:name":"House Of Windsor Hair & Nail",
    "wof:placetype":"venue"
},
  "geometry": {"coordinates":[-85.31230100000001,41.089685],"type":"Point"}
}