{
  "type": "Feature",
  "properties": {
    "addr:full":"2020 E Winona Ave Warsaw IN 46580",
    "addr:housenumber":"2020 e",
    "addr:postcode":"46580",
    "addr:street":"Winona Ave",
    "iso:country":"US",
    "sg:address":"2020 E Winona Ave",
    "sg:city":"Warsaw",
    "sg:classifiers":[
        {
            "category":"Retail",
            "subcategory":"Laundry & Dry Cleaning",
            "type":"Services"
        }
    ],
    "sg:phone":"+1 574 267 6022",
    "sg:postcode":"46580",
    "sg:province":"IN",
    "sg:tags":[
        "cleaners"
    ],
    "wof:name":"Peerlees Cleaners",
    "wof:placetype":"venue"
},
  "geometry": {"coordinates":[-85.830979,41.23398],"type":"Point"}
}