{
  "type": "Feature",
  "properties": {
    "iso:country":"US",
    "sg:address":"3 E Main St",
    "sg:city":"Washington",
    "sg:classifiers":[
        {
            "category":"Organizations",
            "subcategory":"Community Association",
            "type":"Services"
        }
    ],
    "sg:phone":"+1 812 254 3361",
    "sg:postcode":"47501",
    "sg:province":"IN",
    "sg:tags":[
        "club"
    ],
    "wof:name":"Veterans Of Foreign Wars",
    "wof:placetype":"venue"
},
  "geometry": {"coordinates":[-87.17547399999999,38.656849],"type":"Point"}
}