{
  "type": "Feature",
  "properties": {
    "iso:country":"US",
    "sg:address":"1716 S Michigan St",
    "sg:city":"South Bend",
    "sg:classifiers":[
        {
            "category":"Insurance",
            "subcategory":"Insurance Agent",
            "type":"Services"
        }
    ],
    "sg:phone":"+1 574 280 3991",
    "sg:postcode":"46613",
    "sg:province":"IN",
    "wof:name":"Midwest Insurance Svc",
    "wof:placetype":"venue"
},
  "geometry": {"coordinates":[-86.249785,41.655915],"type":"Point"}
}