{
  "type": "Feature",
  "properties": {
    "iso:country":"US",
    "sg:address":"6938 E State Rd 218",
    "sg:city":"Camden",
    "sg:classifiers":[
        {
            "category":"Manufacturing",
            "subcategory":"Printing",
            "type":"Manufacturing & Wholesale Goods"
        }
    ],
    "sg:phone":"+1 574 859 2141",
    "sg:postcode":"46917",
    "sg:province":"IN",
    "sg:tags":[
        "commercial"
    ],
    "wof:name":"Lesh Advertising",
    "wof:placetype":"venue"
},
  "geometry": {"coordinates":[-86.392589,40.609716],"type":"Point"}
}