{
  "type": "Feature",
  "properties": {
    "iso:country":"US",
    "sg:address":"406 Morton Ln",
    "sg:city":"Ossian",
    "sg:classifiers":[
        {
            "category":"Farming",
            "subcategory":"Farm",
            "type":"Manufacturing & Wholesale Goods"
        }
    ],
    "sg:phone":"+1 260 622 4559",
    "sg:postcode":"46777",
    "sg:province":"IN",
    "sg:tags":[
        "crop",
        "general"
    ],
    "wof:name":"Heckber Farms Inc",
    "wof:placetype":"venue"
},
  "geometry": {"coordinates":[-85.16333,40.884168],"type":"Point"}
}