{
  "type": "Feature",
  "properties": {
    "iso:country":"US",
    "sg:address":"221 S Main St",
    "sg:city":"Liberty",
    "sg:classifiers":[
        {
            "category":"Home & Garden",
            "subcategory":"Building Materials",
            "type":"Retail Goods"
        }
    ],
    "sg:phone":"+1 765 458 5111",
    "sg:postcode":"47353",
    "sg:province":"IN",
    "sg:tags":[
        "center"
    ],
    "sg:website":"www.miles-richmond.com",
    "wof:name":"Miles-Richmond Inc",
    "wof:placetype":"venue"
},
  "geometry": {"coordinates":[-84.93094,39.631862],"type":"Point"}
}