{
  "type": "Feature",
  "properties": {
    "iso:country":"US",
    "sg:address":"343 SW 4th St",
    "sg:city":"Richmond",
    "sg:classifiers":[
        {
            "category":"Building & Trades",
            "subcategory":"Electrical",
            "type":"Services"
        }
    ],
    "sg:phone":"+1 765 962 5378",
    "sg:postcode":"47374",
    "sg:province":"IN",
    "sg:tags":[
        "electrical",
        "contractor"
    ],
    "wof:name":"Discount Electric Service Inc",
    "wof:placetype":"venue"
},
  "geometry": {"coordinates":[-84.907122,39.824602],"type":"Point"}
}