{
  "type": "Feature",
  "properties": {
    "iso:country":"US",
    "sg:address":"701 Wohlert St",
    "sg:city":"Angola",
    "sg:classifiers":[
        {
            "category":"Retail",
            "subcategory":"Repair Shop",
            "type":"Services"
        }
    ],
    "sg:phone":"+1 260 665 3999",
    "sg:postcode":"46703",
    "sg:province":"IN",
    "sg:tags":[
        "equipment",
        "welding"
    ],
    "wof:name":"Mc Coy's Welding",
    "wof:placetype":"venue"
},
  "geometry": {"coordinates":[-85.004317,41.644349],"type":"Point"}
}