{
  "type": "Feature",
  "properties": {
    "iso:country":"US",
    "sg:address":"10224 US Hwy 36",
    "sg:city":"Avon",
    "sg:classifiers":[
        {
            "category":"Restaurant",
            "type":"Food & Drink"
        }
    ],
    "sg:phone":"+1 317 271 7225",
    "sg:postcode":"46123",
    "sg:province":"IN",
    "sg:tags":[
        "drinking",
        "eating"
    ],
    "wof:name":"Cazuela's Mexican Restaurant",
    "wof:placetype":"venue"
},
  "geometry": {"coordinates":[-86.343498,39.763856],"type":"Point"}
}