{
  "type": "Feature",
  "properties": {
    "iso:country":"US",
    "sg:address":"136 S 9th St",
    "sg:city":"Noblesville",
    "sg:classifiers":[
        {
            "category":"Professional",
            "subcategory":"Advertising",
            "type":"Services"
        }
    ],
    "sg:phone":"+1 317 776 0676",
    "sg:postcode":"46060",
    "sg:province":"IN",
    "sg:tags":[
        "book",
        "agency",
        "publishing"
    ],
    "wof:name":"Buttermilk Ridge Publishing",
    "wof:placetype":"venue"
},
  "geometry": {"coordinates":[-86.013413,40.044327],"type":"Point"}
}