{
  "type": "Feature",
  "properties": {
    "iso:country":"US",
    "sg:address":"7148 Creekside Ln",
    "sg:city":"Indianapolis",
    "sg:classifiers":[
        {
            "category":"Health Services",
            "subcategory":"Nursing And Care Facility",
            "type":"Services"
        }
    ],
    "sg:phone":"+1 317 913 1895",
    "sg:postcode":"46250",
    "sg:province":"IN",
    "sg:tags":[
        "consultant",
        "hygiene",
        "industrial"
    ],
    "wof:name":"Cih Services",
    "wof:placetype":"venue"
},
  "geometry": {"coordinates":[-86.053523,39.884358],"type":"Point"}
}