{
  "type": "Feature",
  "properties": {
    "iso:country":"US",
    "sg:address":"5419 Carrollton Ave",
    "sg:city":"Indianapolis",
    "sg:classifiers":[
        {
            "category":"Travel",
            "subcategory":"Hotels & Motels",
            "type":"Entertainment"
        },
        {
            "category":"Travel",
            "subcategory":"Bed & Breakfast",
            "type":"Entertainment"
        }
    ],
    "sg:phone":"+1 317 894 8839",
    "sg:postcode":"46220",
    "sg:province":"IN",
    "sg:tags":[
        "inn",
        "lodging"
    ],
    "wof:name":"Ahlbrands Inn",
    "wof:placetype":"venue"
},
  "geometry": {"coordinates":[-86.14417400000001,39.85137],"type":"Point"}
}