{
  "type": "Feature",
  "properties": {
    "iso:country":"US",
    "sg:address":"3524 N 1st Ave",
    "sg:city":"Evansville",
    "sg:classifiers":[
        {
            "category":"Health Services",
            "subcategory":"Doctor",
            "type":"Services"
        }
    ],
    "sg:phone":"+1 812 422 6886",
    "sg:postcode":"47710",
    "sg:province":"IN",
    "sg:tags":[
        "physician",
        "surgeon"
    ],
    "wof:name":"Jennifer Stone MD",
    "wof:placetype":"venue"
},
  "geometry": {"coordinates":[-87.574239,38.013142],"type":"Point"}
}