{
  "type": "Feature",
  "properties": {
    "iso:country":"US",
    "sg:address":"110 W Central Way",
    "sg:city":"Pendleton",
    "sg:classifiers":[
        {
            "category":"Organizations",
            "subcategory":"Religious Organization",
            "type":"Services"
        }
    ],
    "sg:phone":"+1 765 778 7107",
    "sg:postcode":"46064",
    "sg:province":"IN",
    "wof:name":"New Faith Fellowship Inc",
    "wof:placetype":"venue"
},
  "geometry": {"coordinates":[-85.736852,40.003434],"type":"Point"}
}