{
  "type": "Feature",
  "properties": {
    "addr:full":"2410 Executive Dr Indianapolis IN 46241",
    "addr:housenumber":"2410",
    "addr:postcode":"46241",
    "addr:street":"Executive Dr",
    "iso:country":"US",
    "sg:address":"2410 Executive Dr",
    "sg:city":"Indianapolis",
    "sg:classifiers":[
        {
            "category":"Manufacturing",
            "subcategory":"Rubber & Plastics",
            "type":"Manufacturing & Wholesale Goods"
        }
    ],
    "sg:phone":"+1 317 241 1111",
    "sg:postcode":"46241",
    "sg:province":"IN",
    "sg:website":"www.spcmfg.com",
    "wof:name":"Specialty Manufacturers Co",
    "wof:placetype":"venue"
},
  "geometry": {"coordinates":[-86.25629600000001,39.731098],"type":"Point"}
}