{
  "type": "Feature",
  "properties": {
    "iso:country":"US",
    "sg:address":"5769 Co Rd 425 S",
    "sg:city":"Trafalgar",
    "sg:phone":"+1 317 878 5774",
    "sg:postcode":"46181",
    "sg:province":"IN",
    "sg:tags":[
        "wheat",
        "beef",
        "farm",
        "corn",
        "crop",
        "field",
        "soybean"
    ],
    "wof:name":"Bradley Farms",
    "wof:placetype":"venue"
},
  "geometry": {"coordinates":[-86.21205,39.411805],"type":"Point"}
}