{
  "type": "Feature",
  "properties": {
    "addr:full":"1020 S Palmer Ave Bloomington IN 47401",
    "addr:housenumber":"1020",
    "addr:postcode":"47401",
    "addr:street":"S Palmer Ave",
    "iso:country":"US",
    "sg:address":"1020 S Palmer Ave",
    "sg:city":"Bloomington",
    "sg:classifiers":[
        {
            "category":"Professional",
            "subcategory":"Management & Consulting",
            "type":"Services"
        }
    ],
    "sg:phone":"+1 812 323 8483",
    "sg:postcode":"47401",
    "sg:province":"IN",
    "sg:tags":[
        "business"
    ],
    "wof:name":"Meridian Consulting Svcs",
    "wof:placetype":"venue"
},
  "geometry": {"coordinates":[-86.529234,39.154457],"type":"Point"}
}