{
  "type": "Feature",
  "properties": {
    "iso:country":"US",
    "sg:address":"219 SW 18th St",
    "sg:city":"Richmond",
    "sg:classifiers":[
        {
            "category":"Personal",
            "subcategory":"Beauty Salon",
            "type":"Services"
        }
    ],
    "sg:phone":"+1 765 962 4788",
    "sg:postcode":"47374",
    "sg:province":"IN",
    "wof:name":"Brenda's Beauty Salon",
    "wof:placetype":"venue"
},
  "geometry": {"coordinates":[-84.926943,39.825936],"type":"Point"}
}