{
  "type": "Feature",
  "properties": {
    "iso:country":"US",
    "sg:address":"110 Main St",
    "sg:city":"Brookville",
    "sg:classifiers":[
        {
            "category":"Wholesale",
            "subcategory":"Farm Supplies",
            "type":"Manufacturing & Wholesale Goods"
        }
    ],
    "sg:phone":"+1 765 647 4154",
    "sg:postcode":"47012",
    "sg:province":"IN",
    "wof:name":"Ag One Co-Op",
    "wof:placetype":"venue"
},
  "geometry": {"coordinates":[-85.012771,39.415002],"type":"Point"}
}