{
  "type": "Feature",
  "properties": {
    "iso:country":"US",
    "sg:address":"416 E Washington St",
    "sg:city":"Alexandria",
    "sg:classifiers":[
        {
            "category":"Professional",
            "subcategory":"Business Services",
            "type":"Services"
        }
    ],
    "sg:phone":"+1 765 724 1099",
    "sg:postcode":"46001",
    "sg:province":"IN",
    "wof:name":"Adams Agency",
    "wof:placetype":"venue"
},
  "geometry": {"coordinates":[-85.670267,40.263299],"type":"Point"}
}