{
  "type": "Feature",
  "properties": {
    "addr:full":"5055 W 700 S Geneva IN 46740",
    "addr:housenumber":"5055",
    "addr:postcode":"46740",
    "addr:street":"W 700 S",
    "iso:country":"US",
    "sg:address":"5055 W 700 S",
    "sg:city":"Geneva",
    "sg:classifiers":[
        {
            "category":"Building & Trades",
            "subcategory":"Plumbing",
            "type":"Services"
        }
    ],
    "sg:phone":"+1 260 334 5496",
    "sg:postcode":"46740",
    "sg:province":"IN",
    "sg:tags":[
        "plumbing",
        "contractor"
    ],
    "wof:name":"Linn Grove Hardware",
    "wof:placetype":"venue"
},
  "geometry": {"coordinates":[-85.032718,40.64312],"type":"Point"}
}