{
  "type": "Feature",
  "properties": {
    "iso:country":"US",
    "sg:address":"1701 Indianapolis Rd",
    "sg:city":"Greencastle",
    "sg:classifiers":[
        {
            "category":"Banks & Credit Unions",
            "subcategory":"Investment Brokerage",
            "type":"Services"
        }
    ],
    "sg:phone":"+1 765 653 4888",
    "sg:postcode":"46135",
    "sg:province":"IN",
    "sg:tags":[
        "advisory",
        "financial"
    ],
    "wof:name":"American Equipment Financing",
    "wof:placetype":"venue"
},
  "geometry": {"coordinates":[-86.82076000000001,39.646255],"type":"Point"}
}