{
  "type": "Feature",
  "properties": {
    "iso:country":"US",
    "sg:address":"761 Indian Boundary Rd",
    "sg:city":"Chesterton",
    "sg:classifiers":[
        {
            "category":"Ice Cream",
            "type":"Food & Drink"
        }
    ],
    "sg:menulink":"http://www.allmenus.com/in/westchester/184790-cold-stone-creamery/menu/",
    "sg:phone":"+1 219 983 9549",
    "sg:postcode":"46304",
    "sg:province":"IN",
    "sg:tags":[
        "smoothy",
        "juice",
        "american"
    ],
    "wof:name":"Cold Stone Creamery",
    "wof:placetype":"venue"
},
  "geometry": {"coordinates":[-87.039529,41.61691],"type":"Point"}
}