{
  "type": "Feature",
  "properties": {
    "iso:country":"US",
    "sg:address":"599 Industrial Dr",
    "sg:city":"Carmel",
    "sg:classifiers":[
        {
            "category":"Professional",
            "subcategory":"Computer Services",
            "type":"Services"
        }
    ],
    "sg:phone":"+1 317 815 0341",
    "sg:postcode":"46032",
    "sg:province":"IN",
    "sg:tags":[
        "credit",
        "card"
    ],
    "wof:name":"Immediate Payment Solutions",
    "wof:placetype":"venue"
},
  "geometry": {"coordinates":[-86.131188,39.974751],"type":"Point"}
}