{
  "type": "Feature",
  "properties": {
    "addr:full":"844 169th St Hammond IN 46324",
    "addr:housenumber":"844",
    "addr:postcode":"46324",
    "addr:street":"169Th St",
    "iso:country":"US",
    "sg:address":"844 169th St",
    "sg:city":"Hammond",
    "sg:classifiers":[
        {
            "category":"Communications",
            "subcategory":"Television Station",
            "type":"Services"
        }
    ],
    "sg:phone":"+1 219 852 4700",
    "sg:postcode":"46324",
    "sg:province":"IN",
    "sg:tags":[
        "broadcast",
        "satellite",
        "representative",
        "cable"
    ],
    "sg:website":"http://www.comcast.com",
    "wof:name":"Comcast",
    "wof:placetype":"venue"
},
  "geometry": {"coordinates":[-87.508561,41.588264],"type":"Point"}
}