{
  "type": "Feature",
  "properties": {
    "iso:country":"US",
    "sg:address":"120 N Ash St",
    "sg:city":"Tipton",
    "sg:classifiers":[
        {
            "category":"Insurance",
            "subcategory":"Insurance Agent",
            "type":"Services"
        }
    ],
    "sg:phone":"+1 765 675 7423",
    "sg:postcode":"46072",
    "sg:province":"IN",
    "wof:name":"Farm Bureau Insurance",
    "wof:placetype":"venue"
},
  "geometry": {"coordinates":[-86.031758,40.282802],"type":"Point"}
}