{
  "type": "Feature",
  "properties": {
    "iso:country":"US",
    "sg:address":"817 W 4th St",
    "sg:city":"Mt Vernon",
    "sg:classifiers":[
        {
            "category":"Manufacturing",
            "subcategory":"Chemicals & Compounds",
            "type":"Manufacturing & Wholesale Goods"
        }
    ],
    "sg:phone":"+1 812 838 4468",
    "sg:postcode":"47620",
    "sg:province":"IN",
    "sg:tags":[
        "fertilizer",
        "mixing",
        "only"
    ],
    "sg:website":"www.poseynet.com",
    "wof:name":"Posey County Farm Bureau Co",
    "wof:placetype":"venue"
},
  "geometry": {"coordinates":[-87.904439,37.92996],"type":"Point"}
}