{
  "type": "Feature",
  "properties": {
    "iso:country":"US",
    "sg:address":"17911 Hurshtown Rd",
    "sg:city":"Grabill",
    "sg:classifiers":[
        {
            "category":"Retail",
            "subcategory":"Repair Shop",
            "type":"Services"
        }
    ],
    "sg:phone":"+1 260 657 5486",
    "sg:postcode":"46741",
    "sg:province":"IN",
    "wof:name":"Michael A Dawson",
    "wof:placetype":"venue"
},
  "geometry": {"coordinates":[-84.91636,41.239692],"type":"Point"}
}