{
  "type": "Feature",
  "properties": {
    "iso:country":"US",
    "sg:address":"9940 Express Dr",
    "sg:city":"Highland",
    "sg:classifiers":[
        {
            "category":"Wholesale",
            "subcategory":"Hardware",
            "type":"Manufacturing & Wholesale Goods"
        }
    ],
    "sg:phone":"+1 219 922 0705",
    "sg:postcode":"46322",
    "sg:province":"IN",
    "sg:tags":[
        "nut",
        "bolt"
    ],
    "wof:name":"Mighty Mill Supply",
    "wof:placetype":"venue"
},
  "geometry": {"coordinates":[-87.46986699999999,41.534971],"type":"Point"}
}