{
  "type": "Feature",
  "properties": {
    "addr:full":"2725 Enterprise Dr Anderson IN 46013",
    "addr:housenumber":"2725",
    "addr:postcode":"46013",
    "addr:street":"Enterprise Dr",
    "iso:country":"US",
    "sg:address":"2725 Enterprise Dr",
    "sg:city":"Anderson",
    "sg:classifiers":[
        {
            "category":"Social Services",
            "subcategory":"Child Care",
            "type":"Services"
        }
    ],
    "sg:phone":"+1 765 778 9142",
    "sg:postcode":"46013",
    "sg:province":"IN",
    "wof:name":"Tree Climbers Child Dev Ctr",
    "wof:placetype":"venue"
},
  "geometry": {"coordinates":[-85.726859,40.037623],"type":"Point"}
}