{
  "type": "Feature",
  "properties": {
    "addr:full":"3591 N Briarwood Ln Muncie IN 47304",
    "addr:housenumber":"3591",
    "addr:postcode":"47304",
    "addr:street":"N Briarwood Ln",
    "iso:country":"US",
    "sg:address":"3591 N Briarwood Ln",
    "sg:city":"Muncie",
    "sg:classifiers":[
        {
            "category":"Insurance",
            "subcategory":"Insurance Agent",
            "type":"Services"
        }
    ],
    "sg:phone":"+1 765 289 1113",
    "sg:postcode":"47304",
    "sg:province":"IN",
    "wof:name":"Comprehensive Financial Svc",
    "wof:placetype":"venue"
},
  "geometry": {"coordinates":[-85.42838,40.221136],"type":"Point"}
}