{
  "type": "Feature",
  "properties": {
    "addr:full":"51567 State Rd 19 Elkhart IN 46514",
    "addr:housenumber":"51567;19",
    "addr:postcode":"46514",
    "addr:street":"State Rd",
    "iso:country":"US",
    "sg:address":"51567 State Rd 19",
    "sg:city":"Elkhart",
    "sg:classifiers":[
        {
            "category":"Personal",
            "subcategory":"Beauty Salon",
            "type":"Services"
        }
    ],
    "sg:phone":"+1 574 264 3533",
    "sg:postcode":"46514",
    "sg:province":"IN",
    "wof:name":"Classic Cuts Hair Salon",
    "wof:placetype":"venue"
},
  "geometry": {"coordinates":[-85.974476,41.745214],"type":"Point"}
}