{
  "type": "Feature",
  "properties": {
    "iso:country":"US",
    "sg:address":"5149 Avian Way",
    "sg:city":"Carmel",
    "sg:classifiers":[
        {
            "category":"Professional",
            "subcategory":"Lawyer & Legal Services",
            "type":"Services"
        }
    ],
    "sg:phone":"+1 317 844 9984",
    "sg:postcode":"46033",
    "sg:province":"IN",
    "wof:name":"Paralegal Assoc Inc",
    "wof:placetype":"venue"
},
  "geometry": {"coordinates":[-86.076568,39.987618],"type":"Point"}
}