{
  "type": "Feature",
  "properties": {
    "addr:full":"1 N Broadway Peru IN 46970",
    "addr:housenumber":"1",
    "addr:postcode":"46970",
    "addr:street":"N Broadway",
    "iso:country":"US",
    "sg:address":"1 N Broadway",
    "sg:city":"Peru",
    "sg:classifiers":[
        {
            "category":"Organizations",
            "subcategory":"Community Association",
            "type":"Services"
        }
    ],
    "sg:phone":"+1 765 473 7544",
    "sg:postcode":"46970",
    "sg:province":"IN",
    "sg:tags":[
        "fraternal"
    ],
    "wof:name":"Masonic Lodge",
    "wof:placetype":"venue"
},
  "geometry": {"coordinates":[-86.06973600000001,40.754591],"type":"Point"}
}