{
  "type": "Feature",
  "properties": {
    "iso:country":"US",
    "sg:address":"13200 Old Meridian St",
    "sg:city":"Carmel",
    "sg:classifiers":[
        {
            "category":"Education",
            "subcategory":"School",
            "type":"Public Place"
        }
    ],
    "sg:phone":"+1 317 815 6887",
    "sg:postcode":"46032",
    "sg:province":"IN",
    "wof:name":"Walnut Grove Christian School",
    "wof:placetype":"venue"
},
  "geometry": {"coordinates":[-86.14324999999999,39.980908],"type":"Point"}
}