{
  "type": "Feature",
  "properties": {
    "iso:country":"US",
    "sg:address":"5891 Broadway",
    "sg:city":"Merrillville",
    "sg:classifiers":[
        {
            "category":"Restaurant",
            "type":"Food & Drink"
        }
    ],
    "sg:phone":"+1 219 884 1835",
    "sg:postcode":"46410",
    "sg:province":"IN",
    "wof:name":"P J's Grill",
    "wof:placetype":"venue"
},
  "geometry": {"coordinates":[-87.336006,41.510267],"type":"Point"}
}