{
  "type": "Feature",
  "properties": {
    "iso:country":"US",
    "sg:address":"322 N Bennett St",
    "sg:city":"Muncie",
    "sg:classifiers":[
        {
            "category":"Building & Trades",
            "subcategory":"Construction",
            "type":"Services"
        }
    ],
    "sg:phone":"+1 765 282 2201",
    "sg:postcode":"47303",
    "sg:province":"IN",
    "sg:tags":[
        "concrete",
        "contractor"
    ],
    "wof:name":"Its Frog",
    "wof:placetype":"venue"
},
  "geometry": {"coordinates":[-85.345008,40.196541],"type":"Point"}
}