{
  "type": "Feature",
  "properties": {
    "iso:country":"US",
    "sg:address":"302 S 21st St",
    "sg:city":"Chesterton",
    "sg:classifiers":[
        {
            "category":"Communications",
            "subcategory":"Film & Video Production",
            "type":"Services"
        }
    ],
    "sg:phone":"+1 219 926 8918",
    "sg:postcode":"46304",
    "sg:province":"IN",
    "sg:tags":[
        "motion"
    ],
    "wof:name":"Mesa West Productions",
    "wof:placetype":"venue"
},
  "geometry": {"coordinates":[-87.079244,41.608949],"type":"Point"}
}