{
  "type": "Feature",
  "properties": {
    "iso:country":"US",
    "sg:address":"18157 State Road 23",
    "sg:city":"South Bend",
    "sg:classifiers":[
        {
            "category":"Restaurant",
            "type":"Food & Drink"
        }
    ],
    "sg:menulink":"http://www.allmenus.com/in/georgetown/79521-pizza-hut/menu/",
    "sg:phone":"+1 574 273 9944",
    "sg:postcode":"46637",
    "sg:province":"IN",
    "sg:tags":[
        "american",
        "pizza"
    ],
    "wof:name":"Pizza Hut",
    "wof:placetype":"venue"
},
  "geometry": {"coordinates":[-86.217817,41.699261],"type":"Point"}
}