{
  "type": "Feature",
  "properties": {
    "iso:country":"US",
    "sg:address":"211 E York St",
    "sg:city":"Rockville",
    "sg:classifiers":[
        {
            "category":"Health Services",
            "subcategory":"Chiropractor",
            "type":"Services"
        }
    ],
    "sg:phone":"+1 765 569 3129",
    "sg:postcode":"47872",
    "sg:province":"IN",
    "wof:name":"Mc Vay Family Chiropractic",
    "wof:placetype":"venue"
},
  "geometry": {"coordinates":[-87.226283,39.76349],"type":"Point"}
}