{
  "type": "Feature",
  "properties": {
    "addr:full":"1215 E Carter St Kokomo IN 46901",
    "addr:housenumber":"1215",
    "addr:postcode":"46901",
    "addr:street":"E Carter St",
    "iso:country":"US",
    "sg:address":"1215 E Carter St",
    "sg:city":"Kokomo",
    "sg:classifiers":[
        {
            "category":"Retail",
            "subcategory":"Car Wash",
            "type":"Services"
        }
    ],
    "sg:phone":"+1 765 854 0803",
    "sg:postcode":"46901",
    "sg:province":"IN",
    "sg:tags":[
        "automobile",
        "detail",
        "clean"
    ],
    "wof:name":"Stan's Detailing",
    "wof:placetype":"venue"
},
  "geometry": {"coordinates":[-86.114677,40.483792],"type":"Point"}
}