{
  "type": "Feature",
  "properties": {
    "iso:country":"US",
    "sg:address":"961 Lafayette Ave",
    "sg:city":"Terre Haute",
    "sg:classifiers":[
        {
            "category":"Education",
            "subcategory":"Library",
            "type":"Public Place"
        }
    ],
    "sg:phone":"+1 812 462 4354",
    "sg:postcode":"47804",
    "sg:province":"IN",
    "wof:name":"Instructional Materials Ctr",
    "wof:placetype":"venue"
},
  "geometry": {"coordinates":[-87.402815,39.486337],"type":"Point"}
}