{
  "type": "Feature",
  "properties": {
    "addr:full":"2412 State Rd 46 E Nashville IN 47448",
    "addr:housenumber":"2412;46 e",
    "addr:postcode":"47448",
    "addr:street":"State Rd",
    "iso:country":"US",
    "sg:address":"2412 State Rd 46 E",
    "sg:city":"Nashville",
    "sg:classifiers":[
        {
            "category":"Autos & Motor Vehicles",
            "subcategory":"Auto Supplies",
            "type":"Retail Goods"
        }
    ],
    "sg:phone":"+1 812 988 7472",
    "sg:postcode":"47448",
    "sg:province":"IN",
    "sg:tags":[
        "automobile",
        "parts"
    ],
    "wof:name":"NAPA Auto Parts",
    "wof:placetype":"venue"
},
  "geometry": {"coordinates":[-86.173715,39.18953],"type":"Point"}
}