{
  "type": "Feature",
  "properties": {
    "addr:full":"336 E Troy Ave Indianapolis IN 46225",
    "addr:housenumber":"336",
    "addr:postcode":"46225",
    "addr:street":"E Troy Ave",
    "iso:country":"US",
    "sg:address":"336 E Troy Ave",
    "sg:city":"Indianapolis",
    "sg:classifiers":[
        {
            "category":"Personal",
            "subcategory":"Barber",
            "type":"Services"
        }
    ],
    "sg:phone":"+1 317 782 0452",
    "sg:postcode":"46225",
    "sg:province":"IN",
    "sg:tags":[
        "shop"
    ],
    "wof:name":"Style Quarters",
    "wof:placetype":"venue"
},
  "geometry": {"coordinates":[-86.15114,39.722648],"type":"Point"}
}