{
  "type": "Feature",
  "properties": {
    "iso:country":"US",
    "sg:address":"105 W 1st St",
    "sg:city":"Jasper",
    "sg:classifiers":[
        {
            "category":"Retail",
            "subcategory":"Auto Repair",
            "type":"Services"
        }
    ],
    "sg:phone":"+1 812 482 5900",
    "sg:postcode":"47546",
    "sg:province":"IN",
    "sg:tags":[
        "body",
        "automobile",
        "painting"
    ],
    "wof:name":"P J's Auto Inc",
    "wof:placetype":"venue"
},
  "geometry": {"coordinates":[-86.930889,38.386508],"type":"Point"}
}