{
  "type": "Feature",
  "properties": {
    "addr:full":"349 Walnut St Lawrenceburg IN 47025",
    "addr:housenumber":"349",
    "addr:postcode":"47025",
    "addr:street":"Walnut St",
    "iso:country":"US",
    "sg:address":"349 Walnut St",
    "sg:city":"Lawrenceburg",
    "sg:classifiers":[
        {
            "category":"Wholesale",
            "subcategory":"Machinery & Supplies",
            "type":"Manufacturing & Wholesale Goods"
        }
    ],
    "sg:phone":"+1 812 539 4814",
    "sg:postcode":"47025",
    "sg:province":"IN",
    "sg:tags":[
        "pump"
    ],
    "wof:name":"Corporate Equipment Co",
    "wof:placetype":"venue"
},
  "geometry": {"coordinates":[-84.85055800000001,39.094681],"type":"Point"}
}