{
  "type": "Feature",
  "properties": {
    "iso:country":"US",
    "sg:address":"28875 Co Rd 20",
    "sg:city":"Elkhart",
    "sg:classifiers":[
        {
            "category":"Retail",
            "subcategory":"Auto Rental",
            "type":"Services"
        }
    ],
    "sg:phone":"+1 574 389 1528",
    "sg:postcode":"46517",
    "sg:province":"IN",
    "sg:tags":[
        "renting",
        "leasing",
        "trailer"
    ],
    "wof:name":"Tip-Transport Intl Pool",
    "wof:placetype":"venue"
},
  "geometry": {"coordinates":[-86.02104799999999,41.658226],"type":"Point"}
}