{
  "type": "Feature",
  "properties": {
    "addr:full":"9500 US Hwy 36 Avon IN 46123",
    "addr:housenumber":"9500",
    "addr:postcode":"46123",
    "addr:street":"Us Hwy 36",
    "iso:country":"US",
    "sg:address":"9500 US Hwy 36",
    "sg:city":"Avon",
    "sg:classifiers":[
        {
            "category":"Shopping",
            "subcategory":"Department Store",
            "type":"Retail Goods"
        }
    ],
    "sg:phone":"+1 317 209 0857",
    "sg:postcode":"46123",
    "sg:province":"IN",
    "wof:name":"Wal-Mart Supercenter",
    "wof:placetype":"venue"
},
  "geometry": {"coordinates":[-86.348252,39.763773],"type":"Point"}
}