{
  "type": "Feature",
  "properties": {
    "iso:country":"US",
    "sg:address":"112 E Walnut St",
    "sg:city":"Bluffton",
    "sg:classifiers":[
        {
            "category":"Shopping",
            "subcategory":"Computers & Home Electronics",
            "type":"Retail Goods"
        }
    ],
    "sg:phone":"+1 260 824 7529",
    "sg:postcode":"46714",
    "sg:province":"IN",
    "sg:tags":[
        "game",
        "video"
    ],
    "wof:name":"Gamer's Domain",
    "wof:placetype":"venue"
},
  "geometry": {"coordinates":[-85.170284,40.739132],"type":"Point"}
}