{
  "type": "Feature",
  "properties": {
    "addr:full":"24606 State Line Rd Lawrenceburg IN 47025",
    "addr:housenumber":"24606",
    "addr:postcode":"47025",
    "addr:street":"State Line Rd",
    "iso:country":"US",
    "sg:address":"24606 State Line Rd",
    "sg:city":"Lawrenceburg",
    "sg:classifiers":[
        {
            "category":"Building & Trades",
            "subcategory":"Landscaping Services",
            "type":"Services"
        }
    ],
    "sg:phone":"+1 812 637 3717",
    "sg:postcode":"47025",
    "sg:province":"IN",
    "sg:tags":[
        "landscape",
        "contractor"
    ],
    "wof:name":"Bright Four Seasons Lndscpng",
    "wof:placetype":"venue"
},
  "geometry": {"coordinates":[-84.860809,39.227505],"type":"Point"}
}