{
  "type": "Feature",
  "properties": {
    "iso:country":"US",
    "sg:address":"1007 W Brown St",
    "sg:city":"Seymour",
    "sg:classifiers":[
        {
            "category":"Government",
            "subcategory":"Office",
            "type":"Public Place"
        }
    ],
    "sg:phone":"+1 812 523 8688",
    "sg:postcode":"47274",
    "sg:province":"IN",
    "sg:tags":[
        "county"
    ],
    "wof:name":"Literacy Jackson County Cltn",
    "wof:placetype":"venue"
},
  "geometry": {"coordinates":[-85.898805,38.954391],"type":"Point"}
}