{
  "type": "Feature",
  "properties": {
    "iso:country":"US",
    "sg:address":"104 E Kirkwood Ave",
    "sg:city":"Bloomington",
    "sg:classifiers":[
        {
            "category":"Shopping",
            "subcategory":"Gifts & Souvenirs",
            "type":"Retail Goods"
        }
    ],
    "sg:phone":"+1 812 333 1055",
    "sg:postcode":"47408",
    "sg:province":"IN",
    "sg:tags":[
        "shop"
    ],
    "wof:name":"Emporium-Earthly Goods/Treasur",
    "wof:placetype":"venue"
},
  "geometry": {"coordinates":[-86.532388,39.166497],"type":"Point"}
}