{
  "type": "Feature",
  "properties": {
    "iso:country":"US",
    "sg:address":"111 Hendron Hills Dr",
    "sg:city":"Vincennes",
    "sg:classifiers":[
        {
            "category":"Professional",
            "subcategory":"Business Services",
            "type":"Services"
        }
    ],
    "sg:phone":"+1 812 886 4541",
    "sg:postcode":"47591",
    "sg:province":"IN",
    "wof:name":"Gislason Limited Partnership",
    "wof:placetype":"venue"
},
  "geometry": {"coordinates":[-87.493449,38.686345],"type":"Point"}
}