{
  "type": "Feature",
  "properties": {
    "iso:country":"US",
    "sg:address":"4815 N 400 W",
    "sg:city":"Decatur",
    "sg:classifiers":[
        {
            "category":"Freight",
            "type":"Transportation"
        }
    ],
    "sg:phone":"+1 260 565 3592",
    "sg:postcode":"46733",
    "sg:province":"IN",
    "sg:tags":[
        "grain",
        "elevator"
    ],
    "wof:name":"Peterson Grain Co",
    "wof:placetype":"venue"
},
  "geometry": {"coordinates":[-85.014692,40.815723],"type":"Point"}
}