{
  "type": "Feature",
  "properties": {
    "iso:country":"US",
    "sg:address":"80 W 79th Ave",
    "sg:city":"Merrillville",
    "sg:classifiers":[
        {
            "category":"Sports & Exercise",
            "subcategory":"Gym",
            "type":"Entertainment"
        }
    ],
    "sg:phone":"+1 219 756 2878",
    "sg:postcode":"46410",
    "sg:province":"IN",
    "sg:tags":[
        "club",
        "health",
        "studio",
        "gymnasium"
    ],
    "sg:website":"www.curvesinternational.com",
    "wof:name":"Curves For Women",
    "wof:placetype":"venue"
},
  "geometry": {"coordinates":[-87.3456,41.475434],"type":"Point"}
}