{
  "type": "Feature",
  "properties": {
    "iso:country":"US",
    "sg:address":"812 Scatterfield Rd",
    "sg:city":"Anderson",
    "sg:classifiers":[
        {
            "category":"Shopping",
            "type":"Retail Goods"
        }
    ],
    "sg:phone":"+1 765 649 5757",
    "sg:postcode":"46012",
    "sg:province":"IN",
    "sg:tags":[
        "art",
        "gallery",
        "dealer"
    ],
    "wof:name":"Grande Junction Galleria",
    "wof:placetype":"venue"
},
  "geometry": {"coordinates":[-85.652637,40.107056],"type":"Point"}
}