{
  "type": "Feature",
  "properties": {
    "iso:country":"US",
    "sg:address":"4172 Scotland Rd",
    "sg:city":"Kirklin",
    "sg:classifiers":[
        {
            "category":"Building & Trades",
            "subcategory":"Plumbing",
            "type":"Services"
        }
    ],
    "sg:phone":"+1 765 325 2715",
    "sg:postcode":"46050",
    "sg:province":"IN",
    "sg:tags":[
        "conditioning",
        "air",
        "system",
        "contractor"
    ],
    "wof:name":"G M Walker & Sons",
    "wof:placetype":"venue"
},
  "geometry": {"coordinates":[-86.43088299999999,40.184317],"type":"Point"}
}