{
  "type": "Feature",
  "properties": {
    "iso:country":"US",
    "sg:address":"7499 W US Hwy 136",
    "sg:city":"Covington",
    "sg:phone":"+1 765 793 7185",
    "sg:postcode":"47932",
    "sg:province":"IN",
    "sg:tags":[
        "farm",
        "corn"
    ],
    "wof:name":"Wayne Spiening",
    "wof:placetype":"venue"
},
  "geometry": {"coordinates":[-87.459169,40.141829],"type":"Point"}
}