{
  "type": "Feature",
  "properties": {
    "iso:country":"US",
    "sg:address":"1248 E Main St",
    "sg:city":"Attica",
    "sg:classifiers":[
        {
            "category":"Retail",
            "subcategory":"Portrait Studio",
            "type":"Services"
        }
    ],
    "sg:phone":"+1 765 762 1744",
    "sg:postcode":"47918",
    "sg:province":"IN",
    "sg:tags":[
        "photographer"
    ],
    "wof:name":"Classic Photography",
    "wof:placetype":"venue"
},
  "geometry": {"coordinates":[-87.234863,40.286151],"type":"Point"}
}