{
  "type": "Feature",
  "properties": {
    "addr:full":"313 Church St Vincennes IN 47591",
    "addr:housenumber":"313",
    "addr:postcode":"47591",
    "addr:street":"Church St",
    "iso:country":"US",
    "sg:address":"313 Church St",
    "sg:city":"Vincennes",
    "sg:classifiers":[
        {
            "category":"Retail",
            "subcategory":"Funeral Services",
            "type":"Services"
        }
    ],
    "sg:phone":"+1 812 882 6896",
    "sg:postcode":"47591",
    "sg:province":"IN",
    "sg:tags":[
        "director"
    ],
    "wof:name":"Fredrick & Son Funeral Home",
    "wof:placetype":"venue"
},
  "geometry": {"coordinates":[-87.533198,38.678061],"type":"Point"}
}