{
  "type": "Feature",
  "properties": {
    "iso:country":"US",
    "sg:address":"18 State Road 32 E",
    "sg:city":"Westfield",
    "sg:classifiers":[
        {
            "category":"Retail",
            "subcategory":"Auto Repair",
            "type":"Services"
        }
    ],
    "sg:phone":"+1 317 896 2464",
    "sg:postcode":"46074",
    "sg:province":"IN",
    "sg:tags":[
        "body",
        "shop"
    ],
    "sg:website":"www.thetinranch.com",
    "wof:name":"Tin Ranch the",
    "wof:placetype":"venue"
},
  "geometry": {"coordinates":[-86.153099,40.0425],"type":"Point"}
}