{
  "type": "Feature",
  "properties": {
    "iso:country":"US",
    "sg:address":"318 W Pearl St",
    "sg:city":"Union City",
    "sg:classifiers":[
        {
            "category":"Organizations",
            "subcategory":"Professional Association",
            "type":"Services"
        }
    ],
    "sg:phone":"+1 765 964 6449",
    "sg:postcode":"47390",
    "sg:province":"OH",
    "wof:name":"Local 494",
    "wof:placetype":"venue"
},
  "geometry": {"coordinates":[-84.808528,40.198771],"type":"Point"}
}