{
  "type": "Feature",
  "properties": {
    "iso:country":"US",
    "sg:address":"728 Maple St",
    "sg:city":"Tipton",
    "sg:classifiers":[
        {
            "category":"Professional",
            "subcategory":"Computer Services",
            "type":"Services"
        }
    ],
    "sg:phone":"+1 765 675 4381",
    "sg:postcode":"46072",
    "sg:province":"IN",
    "sg:tags":[
        "related"
    ],
    "wof:name":"Don Douglas",
    "wof:placetype":"venue"
},
  "geometry": {"coordinates":[-86.034426,40.292486],"type":"Point"}
}