{
  "type": "Feature",
  "properties": {
    "iso:country":"US",
    "sg:address":"5816 Brentwood Ct",
    "sg:city":"Evansville",
    "sg:classifiers":[
        {
            "category":"Organizations",
            "subcategory":"Religious Organization",
            "type":"Services"
        }
    ],
    "sg:phone":"+1 812 473 9116",
    "sg:postcode":"47715",
    "sg:province":"IN",
    "sg:tags":[
        "clergy"
    ],
    "wof:name":"Connie Baltzell Jr",
    "wof:placetype":"venue"
},
  "geometry": {"coordinates":[-87.47927,37.975943],"type":"Point"}
}