{
  "type": "Feature",
  "properties": {
    "iso:country":"US",
    "sg:address":"43 Lockerbie Dr",
    "sg:city":"Valparaiso",
    "sg:classifiers":[
        {
            "category":"Banks & Credit Unions",
            "subcategory":"Investment Brokerage",
            "type":"Services"
        }
    ],
    "sg:phone":"+1 219 476 9094",
    "sg:postcode":"46385",
    "sg:province":"IN",
    "sg:tags":[
        "advisory",
        "financial"
    ],
    "wof:name":"Lincoln Financial Group",
    "wof:placetype":"venue"
},
  "geometry": {"coordinates":[-87.12129899999999,41.440926],"type":"Point"}
}