{
  "type": "Feature",
  "properties": {
    "addr:full":"6155 Massachusetts Ave Indianapolis IN 46226",
    "addr:housenumber":"6155",
    "addr:postcode":"46226",
    "addr:street":"Massachusetts Ave",
    "iso:country":"US",
    "sg:address":"6155 Massachusetts Ave",
    "sg:city":"Indianapolis",
    "sg:classifiers":[
        {
            "category":"Building & Trades",
            "subcategory":"Construction",
            "type":"Services"
        }
    ],
    "sg:phone":"+1 317 541 1871",
    "sg:postcode":"46226",
    "sg:province":"IN",
    "sg:tags":[
        "carpentry",
        "contractor"
    ],
    "wof:name":"No It All",
    "wof:placetype":"venue"
},
  "geometry": {"coordinates":[-86.057086,39.821615],"type":"Point"}
}