{
  "type": "Feature",
  "properties": {
    "iso:country":"US",
    "sg:address":"6480 Manchester Dr",
    "sg:city":"Fishers",
    "sg:classifiers":[
        {
            "category":"Building & Trades",
            "subcategory":"Construction",
            "type":"Services"
        }
    ],
    "sg:phone":"+1 317 577 1822",
    "sg:postcode":"46038",
    "sg:province":"IN",
    "sg:tags":[
        "contractor"
    ],
    "wof:name":"Schwartz Enterprises",
    "wof:placetype":"venue"
},
  "geometry": {"coordinates":[-86.056425,39.947254],"type":"Point"}
}