{
  "type": "Feature",
  "properties": {
    "iso:country":"US",
    "sg:address":"320 S Lynhurst Dr",
    "sg:city":"Indianapolis",
    "sg:classifiers":[
        {
            "category":"Building & Trades",
            "subcategory":"Construction",
            "type":"Services"
        }
    ],
    "sg:phone":"+1 317 247 8129",
    "sg:postcode":"46241",
    "sg:province":"IN",
    "sg:tags":[
        "roofing",
        "contractor"
    ],
    "wof:name":"Four Seasons Roofing & Constr",
    "wof:placetype":"venue"
},
  "geometry": {"coordinates":[-86.25025599999999,39.761005],"type":"Point"}
}