{
  "type": "Feature",
  "properties": {
    "iso:country":"US",
    "sg:address":"2525 Sandcrest Blvd",
    "sg:city":"Columbus",
    "sg:classifiers":[
        {
            "category":"Health Services",
            "subcategory":"Doctor",
            "type":"Services"
        }
    ],
    "sg:phone":"+1 812 372 6165",
    "sg:postcode":"47203",
    "sg:province":"IN",
    "sg:tags":[
        "dentist"
    ],
    "wof:name":"Sandcrest Dental Health Assoc",
    "wof:placetype":"venue"
},
  "geometry": {"coordinates":[-85.878262,39.22442],"type":"Point"}
}