{
  "type": "Feature",
  "properties": {
    "iso:country":"US",
    "sg:address":"382 Melton Rd",
    "sg:city":"Chesterton",
    "sg:classifiers":[
        {
            "category":"Professional",
            "type":"Services"
        }
    ],
    "sg:phone":"+1 219 787 9308",
    "sg:postcode":"46304",
    "sg:province":"IN",
    "wof:name":"Lees Transfer Service",
    "wof:placetype":"venue"
},
  "geometry": {"coordinates":[-87.13696,41.600095],"type":"Point"}
}