{
  "type": "Feature",
  "properties": {
    "iso:country":"US",
    "sg:address":"7906 Meadow Bend Dr",
    "sg:city":"Indianapolis",
    "sg:classifiers":[
        {
            "category":"Building & Trades",
            "subcategory":"Construction",
            "type":"Services"
        }
    ],
    "sg:phone":"+1 317 835 7010",
    "sg:postcode":"46259",
    "sg:province":"IN",
    "sg:tags":[
        "home",
        "improvement"
    ],
    "wof:name":"Ken Clonch Home Improvements",
    "wof:placetype":"venue"
},
  "geometry": {"coordinates":[-86.027234,39.652509],"type":"Point"}
}