{
  "type": "Feature",
  "properties": {
    "iso:country":"US",
    "sg:address":"235 E Water St",
    "sg:city":"Berne",
    "sg:classifiers":[
        {
            "category":"Wholesale",
            "subcategory":"Hardware",
            "type":"Manufacturing & Wholesale Goods"
        }
    ],
    "sg:phone":"+1 260 589 8454",
    "sg:postcode":"46711",
    "sg:province":"IN",
    "sg:tags":[
        "equipment",
        "heating",
        "system"
    ],
    "wof:name":"Prairie Supply Co",
    "wof:placetype":"venue"
},
  "geometry": {"coordinates":[-84.947716,40.658928],"type":"Point"}
}