{
  "type": "Feature",
  "properties": {
    "iso:country":"US",
    "sg:address":"7202 N Shadeland Ave",
    "sg:city":"Indianapolis",
    "sg:classifiers":[
        {
            "category":"Professional",
            "subcategory":"Lawyer & Legal Services",
            "type":"Services"
        }
    ],
    "sg:phone":"+1 317 578 1630",
    "sg:postcode":"46250",
    "sg:province":"IN",
    "sg:tags":[
        "attorney"
    ],
    "wof:name":"Hocker & Assoc Inc",
    "wof:placetype":"venue"
},
  "geometry": {"coordinates":[-86.046176,39.885852],"type":"Point"}
}