{
  "type": "Feature",
  "properties": {
    "iso:country":"US",
    "sg:address":"380 Maple St",
    "sg:city":"Monrovia",
    "sg:classifiers":[
        {
            "category":"Wholesale",
            "subcategory":"Construction Materials",
            "type":"Manufacturing & Wholesale Goods"
        }
    ],
    "sg:phone":"+1 317 996 2103",
    "sg:postcode":"46157",
    "sg:province":"IN",
    "sg:tags":[
        "concrete",
        "form"
    ],
    "wof:name":"Scepter Steel Inc",
    "wof:placetype":"venue"
},
  "geometry": {"coordinates":[-86.482614,39.582359],"type":"Point"}
}