{
  "type": "Feature",
  "properties": {
    "addr:full":"823 Massachusetts Ave Indianapolis IN 46204",
    "addr:housenumber":"823",
    "addr:postcode":"46204",
    "addr:street":"Massachusetts Ave",
    "iso:country":"US",
    "sg:address":"823 Massachusetts Ave",
    "sg:city":"Indianapolis",
    "sg:classifiers":[
        {
            "category":"Manufacturing",
            "subcategory":"Musical Instruments",
            "type":"Manufacturing & Wholesale Goods"
        }
    ],
    "sg:phone":"+1 317 637 5222",
    "sg:postcode":"46204",
    "sg:province":"IN",
    "sg:tags":[
        "organs"
    ],
    "sg:website":"www.gouldingandwood.com",
    "wof:name":"Goulding & Wood Pipe Organs",
    "wof:placetype":"venue"
},
  "geometry": {"coordinates":[-86.145245,39.777628],"type":"Point"}
}