{
  "type": "Feature",
  "properties": {
    "iso:country":"US",
    "sg:address":"21315 Campbell Rd",
    "sg:city":"Spencerville",
    "sg:phone":"+1 260 238 4294",
    "sg:postcode":"46788",
    "sg:province":"IN",
    "sg:tags":[
        "farm",
        "corn",
        "soybean"
    ],
    "wof:name":"James Hoeppner",
    "wof:placetype":"venue"
},
  "geometry": {"coordinates":[-84.875274,41.255001],"type":"Point"}
}