{
  "type": "Feature",
  "properties": {
    "iso:country":"US",
    "sg:address":"2594 Endress Pl",
    "sg:city":"Greenwood",
    "sg:classifiers":[
        {
            "category":"Manufacturing",
            "subcategory":"Tools & Machinery",
            "type":"Manufacturing & Wholesale Goods"
        }
    ],
    "sg:phone":"+1 317 535 7156",
    "sg:postcode":"46143",
    "sg:province":"IN",
    "sg:tags":[
        "machine",
        "shop"
    ],
    "wof:name":"Greenwood Models Inc",
    "wof:placetype":"venue"
},
  "geometry": {"coordinates":[-86.091305,39.581352],"type":"Point"}
}