{
  "type": "Feature",
  "properties": {
    "iso:country":"US",
    "sg:address":"8633 Brookville Rd",
    "sg:city":"Indianapolis",
    "sg:classifiers":[
        {
            "category":"Manufacturing",
            "subcategory":"Apparel",
            "type":"Manufacturing & Wholesale Goods"
        }
    ],
    "sg:phone":"+1 317 357 8671",
    "sg:postcode":"46239",
    "sg:province":"IN",
    "sg:tags":[
        "flag",
        "banner"
    ],
    "wof:name":"Curry Enterprises",
    "wof:placetype":"venue"
},
  "geometry": {"coordinates":[-86.018786,39.748453],"type":"Point"}
}