{
  "type": "Feature",
  "properties": {
    "iso:country":"US",
    "sg:address":"725 E Parr Rd",
    "sg:city":"Berne",
    "sg:classifiers":[
        {
            "category":"Freight",
            "type":"Transportation"
        }
    ],
    "sg:phone":"+1 260 589 3485",
    "sg:postcode":"46711",
    "sg:province":"IN",
    "sg:tags":[
        "warehouse"
    ],
    "wof:name":"Lear Corporation",
    "wof:placetype":"venue"
},
  "geometry": {"coordinates":[-84.945436,40.665365],"type":"Point"}
}