{
  "type": "Feature",
  "properties": {
    "iso:country":"US",
    "sg:address":"55 S State Ave",
    "sg:city":"Indianapolis",
    "sg:classifiers":[
        {
            "category":"Wholesale",
            "subcategory":"Electrical",
            "type":"Manufacturing & Wholesale Goods"
        }
    ],
    "sg:phone":"+1 317 916 8995",
    "sg:postcode":"46201",
    "sg:province":"IN",
    "sg:tags":[
        "equipment",
        "electronic",
        "supply"
    ],
    "wof:name":"E & F Electronics",
    "wof:placetype":"venue"
},
  "geometry": {"coordinates":[-86.130536,39.765141],"type":"Point"}
}