{
  "type": "Feature",
  "properties": {
    "iso:country":"US",
    "sg:address":"30 W Washington St",
    "sg:city":"Sullivan",
    "sg:classifiers":[
        {
            "category":"Bars & Pubs",
            "type":"Food & Drink"
        }
    ],
    "sg:phone":"+1 812 268 9071",
    "sg:postcode":"47882",
    "sg:province":"IN",
    "wof:name":"Runt's Lounge",
    "wof:placetype":"venue"
},
  "geometry": {"coordinates":[-87.408017,39.095494],"type":"Point"}
}