{
  "type": "Feature",
  "properties": {
    "iso:country":"US",
    "sg:address":"4331 Clark Ave",
    "sg:city":"Hammond",
    "sg:classifiers":[
        {
            "category":"Building & Trades",
            "subcategory":"Construction",
            "type":"Services"
        }
    ],
    "sg:phone":"+1 219 931 5579",
    "sg:postcode":"46327",
    "sg:province":"IN",
    "sg:tags":[
        "hanging",
        "contractor"
    ],
    "wof:name":"Pasternak Painting & Deco",
    "wof:placetype":"venue"
},
  "geometry": {"coordinates":[-87.52372200000001,41.633047],"type":"Point"}
}