{
  "type": "Feature",
  "properties": {
    "iso:country":"US",
    "sg:address":"714 US Hwy 31 N",
    "sg:city":"Greenwood",
    "sg:classifiers":[
        {
            "category":"Utilities",
            "subcategory":"Mobile Phone",
            "type":"Services"
        }
    ],
    "sg:phone":"+1 317 884 2720",
    "sg:postcode":"46142",
    "sg:province":"IN",
    "sg:tags":[
        "telephone",
        "cellular"
    ],
    "wof:name":"Sprint PCS",
    "wof:placetype":"venue"
},
  "geometry": {"coordinates":[-86.11891199999999,39.62445],"type":"Point"}
}