{
  "type": "Feature",
  "properties": {
    "iso:country":"US",
    "sg:address":"3769 N Co Rd 225 W",
    "sg:city":"Seymour",
    "sg:classifiers":[
        {
            "category":"Real Estate",
            "subcategory":"Real Estate Operator",
            "type":"Services"
        }
    ],
    "sg:phone":"+1 812 358 2025",
    "sg:postcode":"47274",
    "sg:province":"IN",
    "sg:tags":[
        "property",
        "lessor"
    ],
    "wof:name":"William Murray",
    "wof:placetype":"venue"
},
  "geometry": {"coordinates":[-86.080796,38.930463],"type":"Point"}
}