{
  "type": "Feature",
  "properties": {
    "iso:country":"US",
    "sg:address":"8425 Keystone Xing",
    "sg:city":"Indianapolis",
    "sg:classifiers":[
        {
            "category":"Insurance",
            "subcategory":"Insurance Agent",
            "type":"Services"
        }
    ],
    "sg:phone":"+1 317 251 2801",
    "sg:postcode":"46240",
    "sg:province":"IN",
    "wof:name":"Rogers Benefit Group",
    "wof:placetype":"venue"
},
  "geometry": {"coordinates":[-86.11451700000001,39.910141],"type":"Point"}
}