{
  "type": "Feature",
  "properties": {
    "iso:country":"US",
    "sg:address":"2224 Compton Ave",
    "sg:city":"Elkhart",
    "sg:classifiers":[
        {
            "category":"Organizations",
            "subcategory":"Religious Organization",
            "type":"Services"
        }
    ],
    "sg:phone":"+1 574 522 8413",
    "sg:postcode":"46517",
    "sg:province":"IN",
    "sg:tags":[
        "church"
    ],
    "sg:website":"www.kingdom-seal.com",
    "wof:name":"Kingdom Seal Ministries Inc",
    "wof:placetype":"venue"
},
  "geometry": {"coordinates":[-85.97247900000001,41.664962],"type":"Point"}
}