{
  "type": "Feature",
  "properties": {
    "iso:country":"US",
    "sg:address":"627 S 350 E",
    "sg:city":"Flora",
    "sg:classifiers":[
        {
            "category":"Farming",
            "subcategory":"Farm",
            "type":"Manufacturing & Wholesale Goods"
        }
    ],
    "sg:phone":"+1 574 967 4768",
    "sg:postcode":"46929",
    "sg:province":"IN",
    "sg:tags":[
        "crop",
        "general"
    ],
    "wof:name":"Agri Aspects Inc",
    "wof:placetype":"venue"
},
  "geometry": {"coordinates":[-86.45837299999999,40.537773],"type":"Point"}
}