{
  "type": "Feature",
  "properties": {
    "iso:country":"US",
    "sg:address":"1505 S Washington St",
    "sg:city":"Crawfordsville",
    "sg:classifiers":[
        {
            "category":"Food & Beverages",
            "subcategory":"Liquor & Beverages",
            "type":"Retail Goods"
        }
    ],
    "sg:phone":"+1 765 362 3605",
    "sg:postcode":"47933",
    "sg:province":"IN",
    "wof:name":"Southside Liquor Store",
    "wof:placetype":"venue"
},
  "geometry": {"coordinates":[-86.901554,40.026641],"type":"Point"}
}