{
  "type": "Feature",
  "properties": {
    "iso:country":"US",
    "sg:address":"1114 E 46th St",
    "sg:city":"Indianapolis",
    "sg:classifiers":[
        {
            "category":"Building & Trades",
            "subcategory":"Construction",
            "type":"Services"
        }
    ],
    "sg:phone":"+1 317 254 4411",
    "sg:postcode":"46205",
    "sg:province":"IN",
    "sg:tags":[
        "wallcoverings-installation",
        "wallpaper",
        "painting",
        "contractor"
    ],
    "wof:name":"Byb Painting",
    "wof:placetype":"venue"
},
  "geometry": {"coordinates":[-86.139297,39.83992],"type":"Point"}
}