{
  "type": "Feature",
  "properties": {
    "iso:country":"US",
    "sg:address":"105 S Glick St",
    "sg:city":"Mulberry",
    "sg:classifiers":[
        {
            "category":"Restaurant",
            "type":"Food & Drink"
        }
    ],
    "sg:phone":"+1 765 296 3288",
    "sg:postcode":"46058",
    "sg:province":"IN",
    "wof:name":"Mulberry Corner Restaurant",
    "wof:placetype":"venue"
},
  "geometry": {"coordinates":[-86.66628,40.34461],"type":"Point"}
}