{
  "type": "Feature",
  "properties": {
    "iso:country":"US",
    "sg:address":"259 Southmoor Rd",
    "sg:city":"Hammond",
    "sg:classifiers":[
        {
            "category":"Building & Trades",
            "subcategory":"Cleaning & Sanitation",
            "type":"Services"
        }
    ],
    "sg:phone":"+1 219 937 4641",
    "sg:postcode":"46324",
    "sg:province":"IN",
    "sg:tags":[
        "janitor"
    ],
    "wof:name":"Exxon Building Maintenance",
    "wof:placetype":"venue"
},
  "geometry": {"coordinates":[-87.518815,41.576975],"type":"Point"}
}