{
  "type": "Feature",
  "properties": {
    "iso:country":"US",
    "sg:address":"1804 Conner St",
    "sg:city":"Noblesville",
    "sg:classifiers":[
        {
            "category":"Health Services",
            "subcategory":"Chiropractor",
            "type":"Services"
        }
    ],
    "sg:phone":"+1 317 774 8780",
    "sg:postcode":"46060",
    "sg:province":"IN",
    "wof:name":"Athlete's Chiropractric",
    "wof:placetype":"venue"
},
  "geometry": {"coordinates":[-86.001739,40.045682],"type":"Point"}
}