{
  "type": "Feature",
  "properties": {
    "iso:country":"US",
    "sg:address":"475 Austin Ln",
    "sg:city":"Greenwood",
    "sg:classifiers":[
        {
            "category":"Building & Trades",
            "subcategory":"Construction",
            "type":"Services"
        }
    ],
    "sg:phone":"+1 317 535 8215",
    "sg:postcode":"46142",
    "sg:province":"IN",
    "sg:tags":[
        "general",
        "contractor"
    ],
    "wof:name":"Renfro Construction Inc",
    "wof:placetype":"venue"
},
  "geometry": {"coordinates":[-86.118657,39.609339],"type":"Point"}
}