{
  "type": "Feature",
  "properties": {
    "iso:country":"US",
    "sg:address":"8448 E Co Rd 1100 N",
    "sg:city":"Sunman",
    "sg:classifiers":[
        {
            "category":"Building & Trades",
            "subcategory":"Construction",
            "type":"Services"
        }
    ],
    "sg:phone":"+1 812 623 1525",
    "sg:postcode":"47041",
    "sg:province":"IN",
    "sg:tags":[
        "contractor"
    ],
    "wof:name":"Roberts C Wldg Trck Hvy Equip",
    "wof:placetype":"venue"
},
  "geometry": {"coordinates":[-85.106492,39.236959],"type":"Point"}
}