{
  "type": "Feature",
  "properties": {
    "addr:full":"2707 E Main St Plainfield IN 46168",
    "addr:housenumber":"2707",
    "addr:postcode":"46168",
    "addr:street":"E Main St",
    "iso:country":"US",
    "sg:address":"2707 E Main St",
    "sg:city":"Plainfield",
    "sg:classifiers":[
        {
            "category":"Wholesale",
            "subcategory":"Medical Equipment & Supplies",
            "type":"Manufacturing & Wholesale Goods"
        },
        {
            "category":"Home & Garden",
            "subcategory":"Building Materials",
            "type":"Retail Goods"
        },
        {
            "category":"Professional",
            "subcategory":"Printing & Photocopies",
            "type":"Services"
        },
        {
            "category":"Manufacturing",
            "subcategory":"Building Materials",
            "type":"Manufacturing & Wholesale Goods"
        }
    ],
    "sg:phone":"+1 317 839 3050",
    "sg:postcode":"46168",
    "sg:province":"IN",
    "sg:tags":[
        "loading",
        "door",
        "garage",
        "accessory",
        "dock",
        "window",
        "opener",
        "doors",
        "gate",
        "frames",
        "door-overhead",
        "type"
    ],
    "sg:website":"http://www.prodoorindy.com",
    "wof:name":"Professional Garage Door Systems Inc",
    "wof:placetype":"venue"
},
  "geometry": {"coordinates":[-86.35298,39.719466],"type":"Point"}
}