{
  "type": "Feature",
  "properties": {
    "iso:country":"US",
    "sg:address":"1501 Sanders Dr",
    "sg:city":"Auburn",
    "sg:classifiers":[
        {
            "category":"Shopping",
            "subcategory":"Gifts & Souvenirs",
            "type":"Retail Goods"
        }
    ],
    "sg:phone":"+1 260 925 3250",
    "sg:postcode":"46706",
    "sg:province":"IN",
    "wof:name":"Between Rafters",
    "wof:placetype":"venue"
},
  "geometry": {"coordinates":[-85.034722,41.360612],"type":"Point"}
}