{
  "type": "Feature",
  "properties": {
    "iso:country":"US",
    "sg:address":"620 Hayden St",
    "sg:city":"Fort Wayne",
    "sg:classifiers":[
        {
            "category":"Building & Trades",
            "subcategory":"Electrical",
            "type":"Services"
        }
    ],
    "sg:phone":"+1 260 467 1336",
    "sg:postcode":"46802",
    "sg:province":"IN",
    "wof:name":"LHR Cable",
    "wof:placetype":"venue"
},
  "geometry": {"coordinates":[-85.128671,41.072213],"type":"Point"}
}