{
  "type": "Feature",
  "properties": {
    "iso:country":"US",
    "sg:address":"1209 Baker Ave",
    "sg:city":"Evansville",
    "sg:classifiers":[
        {
            "category":"Restaurant",
            "type":"Food & Drink"
        }
    ],
    "sg:phone":"+1 812 424 2250",
    "sg:postcode":"47710",
    "sg:province":"IN",
    "sg:tags":[
        "eating"
    ],
    "wof:name":"Serenity House Coffee Shop",
    "wof:placetype":"venue"
},
  "geometry": {"coordinates":[-87.56556,37.9893],"type":"Point"}
}