{
  "type": "Feature",
  "properties": {
    "iso:country":"US",
    "sg:address":"3875 N Newton St",
    "sg:city":"Jasper",
    "sg:classifiers":[
        {
            "category":"Utilities",
            "subcategory":"Mobile Phone",
            "type":"Services"
        }
    ],
    "sg:phone":"+1 812 482 4112",
    "sg:postcode":"47546",
    "sg:province":"IN",
    "sg:tags":[
        "telephone",
        "cellular"
    ],
    "wof:name":"Cingular Wireless",
    "wof:placetype":"venue"
},
  "geometry": {"coordinates":[-86.938017,38.425948],"type":"Point"}
}