{
  "type": "Feature",
  "properties": {
    "addr:full":"1507 S State Rd 57 Washington IN 47501",
    "addr:housenumber":"1507;57",
    "addr:postcode":"47501",
    "addr:street":"S State Rd",
    "iso:country":"US",
    "sg:address":"1507 S State Rd 57",
    "sg:city":"Washington",
    "sg:classifiers":[
        {
            "category":"Retail",
            "subcategory":"Auto Repair",
            "type":"Services"
        }
    ],
    "sg:phone":"+1 812 254 3086",
    "sg:postcode":"47501",
    "sg:province":"IN",
    "sg:tags":[
        "body",
        "automobile",
        "painting"
    ],
    "wof:name":"Auto Clinic",
    "wof:placetype":"venue"
},
  "geometry": {"coordinates":[-87.175952,38.64275],"type":"Point"}
}