{
  "type": "Feature",
  "properties": {
    "iso:country":"US",
    "sg:address":"305 Pinehurst Ct E",
    "sg:city":"Valparaiso",
    "sg:classifiers":[
        {
            "category":"Professional",
            "type":"Services"
        }
    ],
    "sg:phone":"+1 219 531 5438",
    "sg:postcode":"46383",
    "sg:province":"IN",
    "sg:tags":[
        "establishment"
    ],
    "wof:name":"Soil Solutions",
    "wof:placetype":"venue"
},
  "geometry": {"coordinates":[-87.004683,41.433265],"type":"Point"}
}