{
  "type": "Feature",
  "properties": {
    "iso:country":"US",
    "sg:address":"51548 Creekside Dr",
    "sg:city":"Granger",
    "sg:classifiers":[
        {
            "category":"Wholesale",
            "subcategory":"Chemicals & Plastics",
            "type":"Manufacturing & Wholesale Goods"
        }
    ],
    "sg:phone":"+1 574 674 6368",
    "sg:postcode":"46530",
    "sg:province":"IN",
    "wof:name":"Chemcentral Corporation",
    "wof:placetype":"venue"
},
  "geometry": {"coordinates":[-86.068024,41.745336],"type":"Point"}
}