{
  "type": "Feature",
  "properties": {
    "iso:country":"US",
    "sg:address":"8388 Lincoln Ave",
    "sg:city":"Evansville",
    "sg:classifiers":[
        {
            "category":"Personal",
            "type":"Services"
        }
    ],
    "sg:phone":"+1 812 858 1903",
    "sg:postcode":"47715",
    "sg:province":"IN",
    "sg:tags":[
        "therapist",
        "massage"
    ],
    "wof:name":"Linda Flota-Hall",
    "wof:placetype":"venue"
},
  "geometry": {"coordinates":[-87.452625,37.969465],"type":"Point"}
}