{
  "type": "Feature",
  "properties": {
    "iso:country":"US",
    "sg:address":"1808 Indianapolis Rd",
    "sg:city":"Crawfordsville",
    "sg:classifiers":[
        {
            "category":"Autos & Motor Vehicles",
            "subcategory":"Fuel & Gas Station",
            "type":"Retail Goods"
        },
        {
            "category":"Food & Beverages",
            "subcategory":"Groceries & Convenience Stores",
            "type":"Retail Goods"
        }
    ],
    "sg:phone":"+1 765 362 3440",
    "sg:postcode":"47933",
    "sg:province":"IN",
    "wof:name":"Marathon Food Mart",
    "wof:placetype":"venue"
},
  "geometry": {"coordinates":[-86.87146,40.039536],"type":"Point"}
}