{
  "type": "Feature",
  "properties": {
    "iso:country":"US",
    "sg:address":"5714 W 750 S",
    "sg:city":"Hanover",
    "sg:classifiers":[
        {
            "category":"Insurance",
            "subcategory":"Hazard Insurance",
            "type":"Services"
        }
    ],
    "sg:phone":"+1 812 866 4355",
    "sg:postcode":"47243",
    "sg:province":"IN",
    "sg:tags":[
        "carrier"
    ],
    "wof:name":"Odell Insurance",
    "wof:placetype":"venue"
},
  "geometry": {"coordinates":[-85.49141299999999,38.628462],"type":"Point"}
}