{
  "type": "Feature",
  "properties": {
    "iso:country":"US",
    "sg:address":"16214 Mount St",
    "sg:city":"Lowell",
    "sg:classifiers":[
        {
            "category":"Building & Trades",
            "subcategory":"Landscaping Services",
            "type":"Services"
        }
    ],
    "sg:phone":"+1 219 696 9712",
    "sg:postcode":"46356",
    "sg:province":"IN",
    "sg:tags":[
        "tree"
    ],
    "wof:name":"Judy's Tree Svc",
    "wof:placetype":"venue"
},
  "geometry": {"coordinates":[-87.397012,41.322425],"type":"Point"}
}