{
  "type": "Feature",
  "properties": {
    "addr:full":"3321 16th St Bedford IN 47421",
    "addr:housenumber":"3321",
    "addr:postcode":"47421",
    "addr:street":"16Th St",
    "iso:country":"US",
    "sg:address":"3321 16th St",
    "sg:city":"Bedford",
    "sg:classifiers":[
        {
            "category":"Restaurant",
            "type":"Food & Drink"
        }
    ],
    "sg:menulink":"http://www.allmenus.com/in/shawswick/42073-bob-evans/menu/",
    "sg:phone":"+1 812 275 8368",
    "sg:postcode":"47421",
    "sg:province":"IN",
    "sg:tags":[
        "american"
    ],
    "wof:name":"Bob Evans",
    "wof:placetype":"venue"
},
  "geometry": {"coordinates":[-86.516081,38.860939],"type":"Point"}
}