{
  "type": "Feature",
  "properties": {
    "iso:country":"US",
    "sg:address":"201 N Main St",
    "sg:city":"Churubusco",
    "sg:classifiers":[
        {
            "category":"Shopping",
            "subcategory":"Florist",
            "type":"Retail Goods"
        }
    ],
    "sg:phone":"+1 260 693 2741",
    "sg:postcode":"46723",
    "sg:province":"IN",
    "wof:name":"Floral Creations By Diana",
    "wof:placetype":"venue"
},
  "geometry": {"coordinates":[-85.32055699999999,41.232209],"type":"Point"}
}