{
  "type": "Feature",
  "properties": {
    "iso:country":"US",
    "sg:address":"8921 Southpointe Dr",
    "sg:city":"Indianapolis",
    "sg:classifiers":[
        {
            "category":"Health Services",
            "subcategory":"Health Practitioner",
            "type":"Services"
        }
    ],
    "sg:phone":"+1 317 881 1718",
    "sg:postcode":"46227",
    "sg:province":"IN",
    "sg:tags":[
        "therapist",
        "physical"
    ],
    "wof:name":"A Step Ahead Pediatric Therapy",
    "wof:placetype":"venue"
},
  "geometry": {"coordinates":[-86.137846,39.636618],"type":"Point"}
}