{
  "type": "Feature",
  "properties": {
    "iso:country":"US",
    "sg:address":"936 W 3rd St",
    "sg:city":"Rushville",
    "sg:classifiers":[
        {
            "category":"Retail",
            "subcategory":"Repair Shop",
            "type":"Services"
        }
    ],
    "sg:phone":"+1 765 932 5792",
    "sg:postcode":"46173",
    "sg:province":"IN",
    "sg:tags":[
        "television",
        "radio"
    ],
    "wof:name":"Al's TV Svc",
    "wof:placetype":"venue"
},
  "geometry": {"coordinates":[-85.459464,39.611278],"type":"Point"}
}