{
  "type": "Feature",
  "properties": {
    "addr:full":"600 N Indiana St Greencastle IN 46135",
    "addr:housenumber":"600",
    "addr:postcode":"46135",
    "addr:street":"N Indiana St",
    "iso:country":"US",
    "sg:address":"600 N Indiana St",
    "sg:city":"Greencastle",
    "sg:classifiers":[
        {
            "category":"Building & Trades",
            "subcategory":"Plumbing",
            "type":"Services"
        }
    ],
    "sg:phone":"+1 765 653 2961",
    "sg:postcode":"46135",
    "sg:province":"IN",
    "sg:tags":[
        "septic"
    ],
    "wof:name":"Baker's Septic Svc",
    "wof:placetype":"venue"
},
  "geometry": {"coordinates":[-86.864548,39.649367],"type":"Point"}
}