{
  "type": "Feature",
  "properties": {
    "iso:country":"US",
    "sg:address":"24 Washington St",
    "sg:city":"Valparaiso",
    "sg:classifiers":[
        {
            "category":"Restaurant",
            "type":"Food & Drink"
        }
    ],
    "sg:phone":"+1 219 476 0099",
    "sg:postcode":"46383",
    "sg:province":"IN",
    "wof:name":"Cafe Paradiso",
    "wof:placetype":"venue"
},
  "geometry": {"coordinates":[-87.061027,41.467038],"type":"Point"}
}