{
  "type": "Feature",
  "properties": {
    "iso:country":"US",
    "sg:address":"389 Gradle Dr",
    "sg:city":"Carmel",
    "sg:classifiers":[
        {
            "category":"Building & Trades",
            "subcategory":"Construction",
            "type":"Services"
        }
    ],
    "sg:phone":"+1 317 846 4876",
    "sg:postcode":"46032",
    "sg:province":"IN",
    "sg:tags":[
        "contractor"
    ],
    "wof:name":"Sollenberger Construction Co",
    "wof:placetype":"venue"
},
  "geometry": {"coordinates":[-86.133499,39.966599],"type":"Point"}
}