{
  "type": "Feature",
  "properties": {
    "iso:country":"US",
    "sg:address":"10924 N 506 E",
    "sg:city":"Demotte",
    "sg:classifiers":[
        {
            "category":"Building & Trades",
            "subcategory":"Construction",
            "type":"Services"
        }
    ],
    "sg:phone":"+1 219 345 5620",
    "sg:postcode":"46310",
    "sg:province":"IN",
    "sg:tags":[
        "contractor"
    ],
    "wof:name":"Tip-Top Remodeling",
    "wof:placetype":"venue"
},
  "geometry": {"coordinates":[-87.294215,41.158422],"type":"Point"}
}