{
  "type": "Feature",
  "properties": {
    "addr:full":"300 Windy Hill Dr Lafayette IN 47905",
    "addr:housenumber":"300",
    "addr:postcode":"47905",
    "addr:street":"Windy Hill Dr",
    "iso:country":"US",
    "sg:address":"300 Windy Hill Dr",
    "sg:city":"Lafayette",
    "sg:classifiers":[
        {
            "category":"Health Services",
            "subcategory":"Nursing And Care Facility",
            "type":"Services"
        }
    ],
    "sg:phone":"+1 765 477 7791",
    "sg:postcode":"47905",
    "sg:province":"IN",
    "sg:tags":[
        "home",
        "convalescent"
    ],
    "wof:name":"Regency Place Of Lafayette",
    "wof:placetype":"venue"
},
  "geometry": {"coordinates":[-86.901037,40.395234],"type":"Point"}
}