{
  "type": "Feature",
  "properties": {
    "iso:country":"US",
    "sg:address":"1163 Wernsing Rd",
    "sg:city":"Jasper",
    "sg:classifiers":[
        {
            "category":"Restaurant",
            "type":"Food & Drink"
        }
    ],
    "sg:phone":"+1 812 634 7030",
    "sg:postcode":"47546",
    "sg:province":"IN",
    "wof:name":"Mac-A-Doo's",
    "wof:placetype":"venue"
},
  "geometry": {"coordinates":[-86.942474,38.372648],"type":"Point"}
}