{
  "type": "Feature",
  "properties": {
    "iso:country":"US",
    "sg:address":"6431 S East St",
    "sg:city":"Indianapolis",
    "sg:classifiers":[
        {
            "category":"Health Services",
            "subcategory":"Clinic",
            "type":"Services"
        }
    ],
    "sg:phone":"+1 317 788 0300",
    "sg:postcode":"46227",
    "sg:province":"IN",
    "sg:tags":[
        "home"
    ],
    "sg:website":"www.vistacare.com",
    "wof:name":"Vistacare",
    "wof:placetype":"venue"
},
  "geometry": {"coordinates":[-86.149129,39.673743],"type":"Point"}
}