{
  "type": "Feature",
  "properties": {
    "iso:country":"US",
    "sg:address":"6878 Trailside Ave",
    "sg:city":"Portage",
    "sg:classifiers":[
        {
            "category":"Professional",
            "subcategory":"Accounting & Tax Preparation",
            "type":"Services"
        }
    ],
    "sg:phone":"+1 219 763 9073",
    "sg:postcode":"46368",
    "sg:province":"IN",
    "sg:tags":[
        "accountant"
    ],
    "wof:name":"Kristine Gerike CPA",
    "wof:placetype":"venue"
},
  "geometry": {"coordinates":[-87.151881,41.577625],"type":"Point"}
}