{
  "type": "Feature",
  "properties": {
    "addr:full":"315 S Tekoppel Ave Evansville IN 47712",
    "addr:housenumber":"315",
    "addr:postcode":"47712",
    "addr:street":"S Tekoppel Ave",
    "iso:country":"US",
    "sg:address":"315 S Tekoppel Ave",
    "sg:city":"Evansville",
    "sg:classifiers":[
        {
            "category":"Wholesale",
            "subcategory":"Machinery & Supplies",
            "type":"Manufacturing & Wholesale Goods"
        }
    ],
    "sg:phone":"+1 812 421 2486",
    "sg:postcode":"47712",
    "sg:province":"IN",
    "sg:tags":[
        "contractor"
    ],
    "sg:website":"www.hydraserve.com",
    "wof:name":"Hydraserve Inc",
    "wof:placetype":"venue"
},
  "geometry": {"coordinates":[-87.619117,37.973004],"type":"Point"}
}