{
  "type": "Feature",
  "properties": {
    "iso:country":"US",
    "sg:address":"414 E South St",
    "sg:city":"Liberty",
    "sg:classifiers":[
        {
            "category":"Organizations",
            "subcategory":"Religious Organization",
            "type":"Services"
        }
    ],
    "sg:phone":"+1 765 458 6539",
    "sg:postcode":"47353",
    "sg:province":"IN",
    "sg:tags":[
        "church"
    ],
    "wof:name":"Liberty Baptist Church",
    "wof:placetype":"venue"
},
  "geometry": {"coordinates":[-84.922805,39.63257],"type":"Point"}
}