{
  "type": "Feature",
  "properties": {
    "iso:country":"US",
    "sg:address":"500 Commerce Dr",
    "sg:city":"Lakeville",
    "sg:classifiers":[
        {
            "category":"Wholesale",
            "subcategory":"Machinery & Supplies",
            "type":"Manufacturing & Wholesale Goods"
        }
    ],
    "sg:phone":"+1 574 784 8560",
    "sg:postcode":"46536",
    "sg:province":"IN",
    "sg:tags":[
        "equipment",
        "irrigation",
        "system"
    ],
    "wof:name":"Irrigation Solutions",
    "wof:placetype":"venue"
},
  "geometry": {"coordinates":[-86.276071,41.528805],"type":"Point"}
}