{
  "type": "Feature",
  "properties": {
    "iso:country":"US",
    "sg:address":"444 W Baker St",
    "sg:city":"Fort Wayne",
    "sg:classifiers":[
        {
            "category":"Retail",
            "subcategory":"Repair Shop",
            "type":"Services"
        }
    ],
    "sg:phone":"+1 260 424 2093",
    "sg:postcode":"46802",
    "sg:province":"IN",
    "wof:name":"Wood Shack",
    "wof:placetype":"venue"
},
  "geometry": {"coordinates":[-85.144787,41.072398],"type":"Point"}
}