{
  "type": "Feature",
  "properties": {
    "iso:country":"US",
    "sg:address":"9824 E Raymond St",
    "sg:city":"Indianapolis",
    "sg:classifiers":[
        {
            "category":"Manufacturing",
            "subcategory":"Glass & Minerals",
            "type":"Manufacturing & Wholesale Goods"
        }
    ],
    "sg:phone":"+1 317 862 3991",
    "sg:postcode":"46239",
    "sg:province":"IN",
    "sg:tags":[
        "cut",
        "mfg"
    ],
    "wof:name":"Five Star Marble",
    "wof:placetype":"venue"
},
  "geometry": {"coordinates":[-85.994484,39.740454],"type":"Point"}
}