{
  "type": "Feature",
  "properties": {
    "iso:country":"US",
    "sg:address":"3716 N Wheeling Ave",
    "sg:city":"Muncie",
    "sg:classifiers":[
        {
            "category":"Shopping",
            "type":"Retail Goods"
        }
    ],
    "sg:phone":"+1 765 747 4131",
    "sg:postcode":"47304",
    "sg:province":"IN",
    "sg:tags":[
        "hearing",
        "equipment",
        "supply",
        "impaired"
    ],
    "wof:name":"Wilson's Hearing Aid Ctr",
    "wof:placetype":"venue"
},
  "geometry": {"coordinates":[-85.405683,40.224319],"type":"Point"}
}