{
  "type": "Feature",
  "properties": {
    "iso:country":"US",
    "sg:address":"4447 E Co Rd 1200 N",
    "sg:city":"Lamar",
    "sg:classifiers":[
        {
            "category":"Farming",
            "subcategory":"Farm",
            "type":"Manufacturing & Wholesale Goods"
        }
    ],
    "sg:phone":"+1 812 529 8317",
    "sg:postcode":"47550",
    "sg:province":"IN",
    "wof:name":"Rambling Acres Farms",
    "wof:placetype":"venue"
},
  "geometry": {"coordinates":[-86.971605,38.060733],"type":"Point"}
}