{
  "type": "Feature",
  "properties": {
    "iso:country":"US",
    "sg:address":"1201 Northside Blvd",
    "sg:city":"South Bend",
    "sg:classifiers":[
        {
            "category":"Social Services",
            "type":"Services"
        }
    ],
    "sg:phone":"+1 574 233 3486",
    "sg:postcode":"46615",
    "sg:province":"IN",
    "sg:tags":[
        "organization",
        "welfare"
    ],
    "wof:name":"Home Management Resources",
    "wof:placetype":"venue"
},
  "geometry": {"coordinates":[-86.233977,41.664413],"type":"Point"}
}