{
  "type": "Feature",
  "properties": {
    "iso:country":"US",
    "sg:address":"6171 W 400 N",
    "sg:city":"Greenfield",
    "sg:classifiers":[
        {
            "category":"Building & Trades",
            "subcategory":"Electrical",
            "type":"Services"
        }
    ],
    "sg:phone":"+1 317 894 1105",
    "sg:postcode":"46140",
    "sg:province":"IN",
    "sg:tags":[
        "electric",
        "contractor"
    ],
    "wof:name":"Power Electric",
    "wof:placetype":"venue"
},
  "geometry": {"coordinates":[-85.918033,39.841447],"type":"Point"}
}