{
  "type": "Feature",
  "properties": {
    "iso:country":"US",
    "sg:address":"1355 Sagamore Pkwy N",
    "sg:city":"Lafayette",
    "sg:classifiers":[
        {
            "category":"Shopping",
            "subcategory":"Bicycles & Sporting Goods",
            "type":"Retail Goods"
        }
    ],
    "sg:phone":"+1 765 449 1400",
    "sg:postcode":"47904",
    "sg:province":"IN",
    "sg:tags":[
        "equipment",
        "golf",
        "supply"
    ],
    "wof:name":"Pro Golf Discount",
    "wof:placetype":"venue"
},
  "geometry": {"coordinates":[-86.858423,40.427995],"type":"Point"}
}