{
  "type": "Feature",
  "properties": {
    "iso:country":"US",
    "sg:address":"215 N 15th St",
    "sg:city":"Vincennes",
    "sg:classifiers":[
        {
            "category":"Professional",
            "type":"Services"
        }
    ],
    "sg:phone":"+1 812 882 0072",
    "sg:postcode":"47591",
    "sg:province":"IN",
    "sg:tags":[
        "establishment"
    ],
    "wof:name":"R D Van Eaton Inc",
    "wof:placetype":"venue"
},
  "geometry": {"coordinates":[-87.518758,38.670357],"type":"Point"}
}