{
  "type": "Feature",
  "properties": {
    "iso:country":"US",
    "sg:address":"3939 W 300 N",
    "sg:city":"Decatur",
    "sg:classifiers":[
        {
            "category":"Building & Trades",
            "subcategory":"Plumbing",
            "type":"Services"
        }
    ],
    "sg:phone":"+1 260 547 4410",
    "sg:postcode":"46733",
    "sg:province":"IN",
    "sg:tags":[
        "contractor"
    ],
    "wof:name":"Mikes Heating AC",
    "wof:placetype":"venue"
},
  "geometry": {"coordinates":[-85.013667,40.787414],"type":"Point"}
}