{
  "type": "Feature",
  "properties": {
    "iso:country":"US",
    "sg:address":"2724 Washington Ave",
    "sg:city":"Vincennes",
    "sg:classifiers":[
        {
            "category":"Building & Trades",
            "subcategory":"Construction",
            "type":"Services"
        }
    ],
    "sg:phone":"+1 812 882 2260",
    "sg:postcode":"47591",
    "sg:province":"IN",
    "sg:tags":[
        "general",
        "contractor"
    ],
    "wof:name":"Wolfe Construction Co",
    "wof:placetype":"venue"
},
  "geometry": {"coordinates":[-87.50002499999999,38.684735],"type":"Point"}
}