{
  "type": "Feature",
  "properties": {
    "iso:country":"US",
    "sg:address":"136 S Main St",
    "sg:city":"Goshen",
    "sg:classifiers":[
        {
            "category":"Restaurant",
            "type":"Food & Drink"
        }
    ],
    "sg:phone":"+1 574 533 5990",
    "sg:postcode":"46526",
    "sg:province":"IN",
    "sg:website":"www.theelectricbrew.com",
    "wof:name":"Electric Brew",
    "wof:placetype":"venue"
},
  "geometry": {"coordinates":[-85.83449,41.58574],"type":"Point"}
}