{
  "type": "Feature",
  "properties": {
    "addr:full":"4802 Charlestown Rd New Albany IN 47150",
    "addr:housenumber":"4802",
    "addr:postcode":"47150",
    "addr:street":"Charlestown Rd",
    "iso:country":"US",
    "sg:address":"4802 Charlestown Rd",
    "sg:city":"New Albany",
    "sg:classifiers":[
        {
            "category":"Social Services",
            "subcategory":"Child Care",
            "type":"Services"
        }
    ],
    "sg:phone":"+1 812 941 9999",
    "sg:postcode":"47150",
    "sg:province":"IN",
    "wof:name":"Kids Club",
    "wof:placetype":"venue"
},
  "geometry": {"coordinates":[-85.78182099999999,38.362653],"type":"Point"}
}