{
  "type": "Feature",
  "properties": {
    "iso:country":"US",
    "sg:address":"4391 Village Pkwy Cir E",
    "sg:city":"Indianapolis",
    "sg:classifiers":[
        {
            "category":"Shopping",
            "subcategory":"News",
            "type":"Retail Goods"
        }
    ],
    "sg:phone":"+1 317 293 2307",
    "sg:postcode":"46254",
    "sg:province":"IN",
    "wof:name":"Distributor Service Inc",
    "wof:placetype":"venue"
},
  "geometry": {"coordinates":[-86.287303,39.834508],"type":"Point"}
}