{
  "type": "Feature",
  "properties": {
    "iso:country":"US",
    "sg:address":"1815 Foyt Dr",
    "sg:city":"Indianapolis",
    "sg:classifiers":[
        {
            "category":"Real Estate",
            "subcategory":"Real Estate Operator",
            "type":"Services"
        }
    ],
    "sg:phone":"+1 317 243 0189",
    "sg:postcode":"46224",
    "sg:province":"IN",
    "sg:tags":[
        "apartment"
    ],
    "wof:name":"Stanford Court",
    "wof:placetype":"venue"
},
  "geometry": {"coordinates":[-86.268446,39.791747],"type":"Point"}
}