{
  "type": "Feature",
  "properties": {
    "iso:country":"US",
    "sg:address":"1200 S Alvord Blvd",
    "sg:city":"Evansville",
    "sg:classifiers":[
        {
            "category":"Building & Trades",
            "subcategory":"Construction",
            "type":"Services"
        }
    ],
    "sg:phone":"+1 812 476 8167",
    "sg:postcode":"47714",
    "sg:province":"IN",
    "sg:tags":[
        "hanging",
        "contractor"
    ],
    "wof:name":"James LS Painting",
    "wof:placetype":"venue"
},
  "geometry": {"coordinates":[-87.524811,37.960203],"type":"Point"}
}