{
  "type": "Feature",
  "properties": {
    "iso:country":"US",
    "sg:address":"100 NW 2nd St",
    "sg:city":"Evansville",
    "sg:classifiers":[
        {
            "category":"Professional",
            "subcategory":"Research",
            "type":"Services"
        }
    ],
    "sg:phone":"+1 812 422 1699",
    "sg:postcode":"47708",
    "sg:province":"IN",
    "sg:tags":[
        "foundation",
        "philanthropic"
    ],
    "sg:website":"www.pefevansville.org",
    "wof:name":"Public Education Foundation",
    "wof:placetype":"venue"
},
  "geometry": {"coordinates":[-87.574632,37.972133],"type":"Point"}
}