{
  "type": "Feature",
  "properties": {
    "addr:full":"1209 Reckeweg Rd Fort Wayne IN 46804",
    "addr:housenumber":"1209",
    "addr:postcode":"46804",
    "addr:street":"Reckeweg Rd",
    "iso:country":"US",
    "sg:address":"1209 Reckeweg Rd",
    "sg:city":"Fort Wayne",
    "sg:classifiers":[
        {
            "category":"Banks & Credit Unions",
            "subcategory":"Bank",
            "type":"Services"
        }
    ],
    "sg:phone":"+1 260 432 3433",
    "sg:postcode":"46804",
    "sg:province":"IN",
    "sg:tags":[
        "state"
    ],
    "wof:name":"Public Service Credit Union",
    "wof:placetype":"venue"
},
  "geometry": {"coordinates":[-85.205343,41.072591],"type":"Point"}
}