{
  "type": "Feature",
  "properties": {
    "iso:country":"US",
    "sg:address":"3901 Fir St",
    "sg:city":"East Chicago",
    "sg:classifiers":[
        {
            "category":"Organizations",
            "subcategory":"Non-profit Organization",
            "type":"Services"
        }
    ],
    "sg:phone":"+1 219 397 5803",
    "sg:postcode":"46312",
    "sg:province":"IN",
    "sg:tags":[
        "service/non-profit",
        "community"
    ],
    "sg:website":"www.catholiccharitiesusa.org",
    "wof:name":"Catholic Charities Diocese of Gary",
    "wof:placetype":"venue"
},
  "geometry": {"coordinates":[-87.448402,41.642399],"type":"Point"}
}