{
  "type": "Feature",
  "properties": {
    "iso:country":"US",
    "sg:address":"12734 Hamilton Crossing Blvd",
    "sg:city":"Carmel",
    "sg:classifiers":[
        {
            "category":"Education",
            "subcategory":"Special Training",
            "type":"Public Place"
        }
    ],
    "sg:phone":"+1 317 819 1200",
    "sg:postcode":"46032",
    "sg:province":"IN",
    "sg:tags":[
        "program"
    ],
    "wof:name":"General Physics Corp",
    "wof:placetype":"venue"
},
  "geometry": {"coordinates":[-86.160253,39.976089],"type":"Point"}
}