{
  "type": "Feature",
  "properties": {
    "iso:country":"US",
    "sg:address":"41 Wildcat Ct",
    "sg:city":"Jasper",
    "sg:classifiers":[
        {
            "category":"Shopping",
            "subcategory":"Catalog Store",
            "type":"Retail Goods"
        }
    ],
    "sg:phone":"+1 812 482 9725",
    "sg:postcode":"47546",
    "sg:province":"IN",
    "sg:tags":[
        "mail",
        "house"
    ],
    "wof:name":"Jasper Direct",
    "wof:placetype":"venue"
},
  "geometry": {"coordinates":[-86.911218,38.382538],"type":"Point"}
}