{
  "type": "Feature",
  "properties": {
    "addr:full":"420 Poplar Rd Indianapolis IN 46219",
    "addr:housenumber":"420",
    "addr:postcode":"46219",
    "addr:street":"Poplar Rd",
    "iso:country":"US",
    "sg:address":"420 Poplar Rd",
    "sg:city":"Indianapolis",
    "sg:classifiers":[
        {
            "category":"Retail",
            "subcategory":"Repair Shop",
            "type":"Services"
        }
    ],
    "sg:phone":"+1 317 353 9278",
    "sg:postcode":"46219",
    "sg:province":"IN",
    "wof:name":"Beckers Residential Repair",
    "wof:placetype":"venue"
},
  "geometry": {"coordinates":[-86.080592,39.774829],"type":"Point"}
}