{
  "type": "Feature",
  "properties": {
    "iso:country":"US",
    "sg:address":"6873 E South Barbee Dr",
    "sg:city":"Pierceton",
    "sg:classifiers":[
        {
            "category":"Building & Trades",
            "subcategory":"Plumbing",
            "type":"Services"
        }
    ],
    "sg:phone":"+1 574 594 3488",
    "sg:postcode":"46562",
    "sg:province":"IN",
    "sg:tags":[
        "plumbing",
        "contractor"
    ],
    "wof:name":"Water Works Plumbing & Elec",
    "wof:placetype":"venue"
},
  "geometry": {"coordinates":[-85.711824,41.279322],"type":"Point"}
}