{
  "type": "Feature",
  "properties": {
    "iso:country":"US",
    "sg:address":"3374 W Co Rd 950 N",
    "sg:city":"Brazil",
    "sg:classifiers":[
        {
            "category":"Government",
            "subcategory":"Fire Station",
            "type":"Public Place"
        }
    ],
    "sg:phone":"+1 812 446 2425",
    "sg:postcode":"47834",
    "sg:province":"IN",
    "sg:tags":[
        "department"
    ],
    "wof:name":"Dick Johnson Twp Fire Dept",
    "wof:placetype":"venue"
},
  "geometry": {"coordinates":[-87.16664,39.526386],"type":"Point"}
}