{
  "type": "Feature",
  "properties": {
    "iso:country":"US",
    "sg:address":"309 Ferry St",
    "sg:city":"Vevay",
    "sg:classifiers":[
        {
            "category":"Utilities",
            "subcategory":"Natural Gas",
            "type":"Services"
        }
    ],
    "sg:phone":"+1 812 427 3332",
    "sg:postcode":"47043",
    "sg:province":"IN",
    "sg:tags":[
        "company"
    ],
    "wof:name":"Switzerland County Natural Gas",
    "wof:placetype":"venue"
},
  "geometry": {"coordinates":[-85.067602,38.748038],"type":"Point"}
}