{
  "type": "Feature",
  "properties": {
    "iso:country":"US",
    "sg:address":"350 Jackson St",
    "sg:city":"Gary",
    "sg:classifiers":[
        {
            "category":"Recreation",
            "type":"Entertainment"
        }
    ],
    "sg:phone":"+1 219 882 2527",
    "sg:postcode":"46402",
    "sg:province":"IN",
    "sg:tags":[
        "parks"
    ],
    "wof:name":"Jackson Park Pavilion",
    "wof:placetype":"venue"
},
  "geometry": {"coordinates":[-87.344673,41.604733],"type":"Point"}
}