{
  "type": "Feature",
  "properties": {
    "addr:full":"5272 S Hohman Ave Hammond IN 46320",
    "addr:housenumber":"5272",
    "addr:postcode":"46320",
    "addr:street":"S Hohman Ave",
    "iso:country":"US",
    "sg:address":"5272 S Hohman Ave",
    "sg:city":"Hammond",
    "sg:classifiers":[
        {
            "category":"Professional",
            "subcategory":"Lawyer & Legal Services",
            "type":"Services"
        }
    ],
    "sg:phone":"+1 219 937 0500",
    "sg:postcode":"46320",
    "sg:province":"IN",
    "wof:name":"O'connor Wm J Lwyr",
    "wof:placetype":"venue"
},
  "geometry": {"coordinates":[-87.52220199999999,41.617001],"type":"Point"}
}