{
  "type": "Feature",
  "properties": {
    "iso:country":"US",
    "sg:address":"5840 Brookville Rd",
    "sg:city":"Indianapolis",
    "sg:classifiers":[
        {
            "category":"Autos & Motor Vehicles",
            "subcategory":"Automobile Sales",
            "type":"Retail Goods"
        }
    ],
    "sg:phone":"+1 317 356 9604",
    "sg:postcode":"46219",
    "sg:province":"IN",
    "sg:tags":[
        "car",
        "dealer"
    ],
    "wof:name":"Comstock Sales & Svc",
    "wof:placetype":"venue"
},
  "geometry": {"coordinates":[-86.067066,39.758719],"type":"Point"}
}