{
  "type": "Feature",
  "properties": {
    "iso:country":"US",
    "sg:address":"9121 Wicker Ave",
    "sg:city":"St John",
    "sg:classifiers":[
        {
            "category":"Professional",
            "subcategory":"Business Services",
            "type":"Services"
        }
    ],
    "sg:phone":"+1 219 365 8927",
    "sg:postcode":"46373",
    "sg:province":"IN",
    "sg:tags":[
        "drafting"
    ],
    "wof:name":"Leon Fisher & Assoc",
    "wof:placetype":"venue"
},
  "geometry": {"coordinates":[-87.470156,41.453956],"type":"Point"}
}