{
  "type": "Feature",
  "properties": {
    "iso:country":"US",
    "sg:address":"102 Clarendon Dr",
    "sg:city":"Noblesville",
    "sg:classifiers":[
        {
            "category":"Wholesale",
            "subcategory":"Stationery",
            "type":"Manufacturing & Wholesale Goods"
        },
        {
            "category":"Manufacturing",
            "subcategory":"Printing",
            "type":"Manufacturing & Wholesale Goods"
        }
    ],
    "sg:phone":"+1 317 877 9140",
    "sg:postcode":"46062",
    "sg:province":"IN",
    "sg:tags":[
        "printer",
        "supply"
    ],
    "wof:name":"Indiana Business Forms Inc",
    "wof:placetype":"venue"
},
  "geometry": {"coordinates":[-86.045154,40.090083],"type":"Point"}
}