{
  "type": "Feature",
  "properties": {
    "addr:full":"13300 Main St Grabill IN 46741",
    "addr:housenumber":"13300",
    "addr:postcode":"46741",
    "addr:street":"Main St",
    "iso:country":"US",
    "sg:address":"13300 Main St",
    "sg:city":"Grabill",
    "sg:classifiers":[
        {
            "category":"Shopping",
            "subcategory":"Discount & Variety Stores",
            "type":"Retail Goods"
        }
    ],
    "sg:phone":"+1 260 627 5107",
    "sg:postcode":"46741",
    "sg:province":"IN",
    "sg:tags":[
        "merchandise",
        "general"
    ],
    "wof:name":"Farmers Daughter",
    "wof:placetype":"venue"
},
  "geometry": {"coordinates":[-84.96735700000001,41.208535],"type":"Point"}
}