{
  "type": "Feature",
  "properties": {
    "iso:country":"US",
    "sg:address":"1470 W 400 N",
    "sg:city":"Shelbyville",
    "sg:classifiers":[
        {
            "category":"Freight",
            "type":"Transportation"
        }
    ],
    "sg:phone":"+1 317 398 0941",
    "sg:postcode":"46176",
    "sg:province":"IN",
    "sg:tags":[
        "commercial",
        "storage"
    ],
    "wof:name":"Atlas Cold Storage",
    "wof:placetype":"venue"
},
  "geometry": {"coordinates":[-85.810988,39.584099],"type":"Point"}
}