{
  "type": "Feature",
  "properties": {
    "iso:country":"US",
    "sg:address":"430 Meadowview Ln",
    "sg:city":"Greenwood",
    "sg:classifiers":[
        {
            "category":"Building & Trades",
            "subcategory":"Construction",
            "type":"Services"
        }
    ],
    "sg:phone":"+1 317 887 0868",
    "sg:postcode":"46142",
    "sg:province":"IN",
    "sg:tags":[
        "general",
        "contractor"
    ],
    "sg:website":"www.matrixconstructioninc.us",
    "wof:name":"Matrix Construction Inc",
    "wof:placetype":"venue"
},
  "geometry": {"coordinates":[-86.139027,39.619837],"type":"Point"}
}