{
  "type": "Feature",
  "properties": {
    "iso:country":"US",
    "sg:address":"922 W 27th St",
    "sg:city":"Indianapolis",
    "sg:classifiers":[
        {
            "category":"Real Estate",
            "subcategory":"Real Estate Agent",
            "type":"Services"
        }
    ],
    "sg:phone":"+1 317 926 4599",
    "sg:postcode":"46208",
    "sg:province":"IN",
    "wof:name":"Spaulding Realty",
    "wof:placetype":"venue"
},
  "geometry": {"coordinates":[-86.177677,39.805621],"type":"Point"}
}