{
  "type": "Feature",
  "properties": {
    "iso:country":"US",
    "sg:address":"3324 S Co Rd 325 W",
    "sg:city":"Logansport",
    "sg:classifiers":[
        {
            "category":"Manufacturing",
            "subcategory":"Food",
            "type":"Manufacturing & Wholesale Goods"
        }
    ],
    "sg:phone":"+1 574 722 2626",
    "sg:postcode":"46947",
    "sg:province":"IN",
    "sg:tags":[
        "oil",
        "mills",
        "soybean"
    ],
    "wof:name":"Andersons Clymers Terminal",
    "wof:placetype":"venue"
},
  "geometry": {"coordinates":[-86.434336,40.71651],"type":"Point"}
}