{
  "type": "Feature",
  "properties": {
    "iso:country":"US",
    "sg:address":"703 Lincolnway E",
    "sg:city":"Goshen",
    "sg:classifiers":[
        {
            "category":"Autos & Motor Vehicles",
            "subcategory":"Automobile Sales",
            "type":"Retail Goods"
        }
    ],
    "sg:phone":"+1 574 534 6390",
    "sg:postcode":"46526",
    "sg:province":"IN",
    "sg:tags":[
        "car",
        "dealer"
    ],
    "wof:name":"South Main Auto",
    "wof:placetype":"venue"
},
  "geometry": {"coordinates":[-85.818793,41.578248],"type":"Point"}
}