{
  "type": "Feature",
  "properties": {
    "iso:country":"US",
    "sg:address":"1440 W Center St",
    "sg:city":"Warsaw",
    "sg:classifiers":[
        {
            "category":"Freight",
            "type":"Transportation"
        }
    ],
    "sg:phone":"+1 574 268 2105",
    "sg:postcode":"46580",
    "sg:province":"IN",
    "sg:tags":[
        "storage"
    ],
    "wof:name":"Hmt Inc",
    "wof:placetype":"venue"
},
  "geometry": {"coordinates":[-85.874939,41.239088],"type":"Point"}
}