{
  "type": "Feature",
  "properties": {
    "addr:full":"6331 E 30th St Indianapolis IN 46219",
    "addr:housenumber":"6331",
    "addr:postcode":"46219",
    "addr:street":"E 30Th St",
    "iso:country":"US",
    "sg:address":"6331 E 30th St",
    "sg:city":"Indianapolis",
    "sg:classifiers":[
        {
            "category":"Retail",
            "subcategory":"Laundry & Dry Cleaning",
            "type":"Services"
        }
    ],
    "sg:phone":"+1 317 547 3613",
    "sg:postcode":"46219",
    "sg:province":"IN",
    "sg:tags":[
        "cleaners"
    ],
    "wof:name":"Sander's Cleaners & Laundry",
    "wof:placetype":"venue"
},
  "geometry": {"coordinates":[-86.058725,39.810936],"type":"Point"}
}