{
  "type": "Feature",
  "properties": {
    "iso:country":"US",
    "sg:address":"4765 W State Rd 46",
    "sg:city":"Greensburg",
    "sg:classifiers":[
        {
            "category":"Building & Trades",
            "subcategory":"Construction",
            "type":"Services"
        }
    ],
    "sg:phone":"+1 812 663 8650",
    "sg:postcode":"47240",
    "sg:province":"IN",
    "sg:tags":[
        "drainage",
        "contractor"
    ],
    "wof:name":"Heger Drainage",
    "wof:placetype":"venue"
},
  "geometry": {"coordinates":[-85.571813,39.309454],"type":"Point"}
}