{
  "type": "Feature",
  "properties": {
    "iso:country":"US",
    "sg:address":"33987 Gordon Rd",
    "sg:city":"New Carlisle",
    "sg:classifiers":[
        {
            "category":"Farming",
            "subcategory":"Livestock Farm",
            "type":"Manufacturing & Wholesale Goods"
        }
    ],
    "sg:phone":"+1 574 654 3477",
    "sg:postcode":"46552",
    "sg:province":"IN",
    "sg:tags":[
        "beef",
        "feedlot",
        "cattle"
    ],
    "wof:name":"Robert Melady",
    "wof:placetype":"venue"
},
  "geometry": {"coordinates":[-86.522041,41.657661],"type":"Point"}
}