{
  "type": "Feature",
  "properties": {
    "addr:full":"1501 S Meridian St Indianapolis IN 46225",
    "addr:housenumber":"1501",
    "addr:postcode":"46225",
    "addr:street":"S Meridian St",
    "iso:country":"US",
    "sg:address":"1501 S Meridian St",
    "sg:city":"Indianapolis",
    "sg:classifiers":[
        {
            "category":"Organizations",
            "subcategory":"Non-profit Organization",
            "type":"Services"
        }
    ],
    "sg:phone":"+1 317 632 8944",
    "sg:postcode":"46225",
    "sg:province":"IN",
    "wof:name":"Villa At Sacred Heart",
    "wof:placetype":"venue"
},
  "geometry": {"coordinates":[-86.15903400000001,39.747423],"type":"Point"}
}