{
  "type": "Feature",
  "properties": {
    "iso:country":"US",
    "sg:address":"1018 Woodward Ave",
    "sg:city":"New Castle",
    "sg:classifiers":[
        {
            "category":"Home & Garden",
            "subcategory":"Building Materials",
            "type":"Retail Goods"
        }
    ],
    "sg:phone":"+1 765 529 8455",
    "sg:postcode":"47362",
    "sg:province":"IN",
    "sg:tags":[
        "glass",
        "window",
        "plate"
    ],
    "wof:name":"Henry County Glass & Mirror",
    "wof:placetype":"venue"
},
  "geometry": {"coordinates":[-85.37283,39.936044],"type":"Point"}
}