{
  "type": "Feature",
  "properties": {
    "iso:country":"US",
    "sg:address":"4945 Tod Ave",
    "sg:city":"East Chicago",
    "sg:classifiers":[
        {
            "category":"Organizations",
            "subcategory":"Religious Organization",
            "type":"Services"
        }
    ],
    "sg:phone":"+1 219 398 4702",
    "sg:postcode":"46312",
    "sg:province":"IN",
    "sg:tags":[
        "clergy"
    ],
    "wof:name":"Ossie Bewley",
    "wof:placetype":"venue"
},
  "geometry": {"coordinates":[-87.477942,41.62391],"type":"Point"}
}