{
  "type": "Feature",
  "properties": {
    "iso:country":"US",
    "sg:address":"12881 E Co Rd 350 N",
    "sg:city":"Albany",
    "sg:classifiers":[
        {
            "category":"Farming",
            "subcategory":"Farm",
            "type":"Manufacturing & Wholesale Goods"
        }
    ],
    "sg:phone":"+1 765 789 4753",
    "sg:postcode":"47320",
    "sg:province":"IN",
    "wof:name":"Catalpa Grove Farms Inc",
    "wof:placetype":"venue"
},
  "geometry": {"coordinates":[-85.245234,40.241682],"type":"Point"}
}