{
  "type": "Feature",
  "properties": {
    "addr:full":"104 E Main St Petersburg IN 47567",
    "addr:housenumber":"104",
    "addr:postcode":"47567",
    "addr:street":"E Main St",
    "iso:country":"US",
    "sg:address":"104 E Main St",
    "sg:city":"Petersburg",
    "sg:classifiers":[
        {
            "category":"Ice Cream",
            "type":"Food & Drink"
        }
    ],
    "sg:menulink":"http://www.allmenus.com/in/petersburg/161551-dairy-queen/menu/",
    "sg:phone":"+1 812 354 1722",
    "sg:postcode":"47567",
    "sg:province":"IN",
    "sg:tags":[
        "burger",
        "american"
    ],
    "wof:name":"Dairy Queen",
    "wof:placetype":"venue"
},
  "geometry": {"coordinates":[-87.28458999999999,38.488224],"type":"Point"}
}