{
  "type": "Feature",
  "properties": {
    "iso:country":"US",
    "sg:address":"7821 US Hwy 31 S",
    "sg:city":"Indianapolis",
    "sg:classifiers":[
        {
            "category":"Personal",
            "subcategory":"Beauty Salon",
            "type":"Services"
        }
    ],
    "sg:phone":"+1 317 888 4508",
    "sg:postcode":"46227",
    "sg:province":"IN",
    "sg:tags":[
        "manicuring"
    ],
    "wof:name":"Wonder Nails",
    "wof:placetype":"venue"
},
  "geometry": {"coordinates":[-86.138276,39.651938],"type":"Point"}
}