{
  "type": "Feature",
  "properties": {
    "iso:country":"US",
    "sg:address":"5066 State Route 261",
    "sg:city":"Newburgh",
    "sg:classifiers":[
        {
            "category":"Restaurant",
            "type":"Food & Drink"
        }
    ],
    "sg:phone":"+1 812 853 2680",
    "sg:postcode":"47630",
    "sg:province":"IN",
    "sg:tags":[
        "chinese"
    ],
    "wof:name":"Golden Buddha Chinese Restaurant",
    "wof:placetype":"venue"
},
  "geometry": {"coordinates":[-87.399399,37.961399],"type":"Point"}
}