{
  "type": "Feature",
  "properties": {
    "iso:country":"US",
    "sg:address":"512 W Market St",
    "sg:city":"Bluffton",
    "sg:classifiers":[
        {
            "category":"Social Services",
            "type":"Services"
        }
    ],
    "sg:phone":"+1 260 824 1351",
    "sg:postcode":"46714",
    "sg:province":"IN",
    "sg:tags":[
        "organization",
        "welfare"
    ],
    "wof:name":"Bi County Svc",
    "wof:placetype":"venue"
},
  "geometry": {"coordinates":[-85.177351,40.739744],"type":"Point"}
}