{
  "type": "Feature",
  "properties": {
    "iso:country":"US",
    "sg:address":"3024 W Shoaff Rd",
    "sg:city":"Huntertown",
    "sg:phone":"+1 260 637 3919",
    "sg:postcode":"46748",
    "sg:province":"IN",
    "sg:tags":[
        "farm",
        "corn"
    ],
    "wof:name":"Joseph Malcolm",
    "wof:placetype":"venue"
},
  "geometry": {"coordinates":[-85.19128600000001,41.235782],"type":"Point"}
}