{
  "type": "Feature",
  "properties": {
    "iso:country":"US",
    "sg:address":"8312 E Lake View Dr",
    "sg:city":"Syracuse",
    "sg:classifiers":[
        {
            "category":"Building & Trades",
            "subcategory":"Construction",
            "type":"Services"
        }
    ],
    "sg:phone":"+1 574 457 2523",
    "sg:postcode":"46567",
    "sg:province":"IN",
    "sg:tags":[
        "house"
    ],
    "wof:name":"Sylvester Home Improvment",
    "wof:placetype":"venue"
},
  "geometry": {"coordinates":[-85.688145,41.379721],"type":"Point"}
}