{
  "type": "Feature",
  "properties": {
    "iso:country":"US",
    "sg:address":"9115 Indiana Pl",
    "sg:city":"Merrillville",
    "sg:classifiers":[
        {
            "category":"Professional",
            "subcategory":"Accounting & Tax Preparation",
            "type":"Services"
        }
    ],
    "sg:phone":"+1 219 756 9619",
    "sg:postcode":"46410",
    "sg:province":"IN",
    "sg:tags":[
        "return",
        "filing"
    ],
    "wof:name":"Ken Oliver",
    "wof:placetype":"venue"
},
  "geometry": {"coordinates":[-87.316588,41.449568],"type":"Point"}
}