{
  "type": "Feature",
  "properties": {
    "iso:country":"US",
    "sg:address":"6769 E 350 S",
    "sg:city":"Kewanna",
    "sg:classifiers":[
        {
            "category":"Wholesale",
            "subcategory":"Farm Supplies",
            "type":"Manufacturing & Wholesale Goods"
        }
    ],
    "sg:phone":"+1 574 946 6687",
    "sg:postcode":"46939",
    "sg:province":"IN",
    "wof:name":"Agmarket",
    "wof:placetype":"venue"
},
  "geometry": {"coordinates":[-86.472418,41.004181],"type":"Point"}
}