{
  "type": "Feature",
  "properties": {
    "iso:country":"US",
    "sg:address":"1118 N Ireland St",
    "sg:city":"Greensburg",
    "sg:classifiers":[
        {
            "category":"Building & Trades",
            "subcategory":"Construction",
            "type":"Services"
        }
    ],
    "sg:phone":"+1 812 662 7508",
    "sg:postcode":"47240",
    "sg:province":"IN",
    "sg:tags":[
        "roofing",
        "contractor"
    ],
    "wof:name":"L & W Brothers Roofing & Remod",
    "wof:placetype":"venue"
},
  "geometry": {"coordinates":[-85.488759,39.348037],"type":"Point"}
}