{
  "type": "Feature",
  "properties": {
    "addr:full":"431 E Carmel Dr Carmel IN 46032",
    "addr:housenumber":"431",
    "addr:postcode":"46032",
    "addr:street":"E Carmel Dr",
    "iso:country":"US",
    "sg:address":"431 E Carmel Dr",
    "sg:city":"Carmel",
    "sg:classifiers":[
        {
            "category":"Retail",
            "subcategory":"Car Wash",
            "type":"Services"
        }
    ],
    "sg:phone":"+1 317 844 4664",
    "sg:postcode":"46032",
    "sg:province":"IN",
    "wof:name":"Ultimate Car Wash",
    "wof:placetype":"venue"
},
  "geometry": {"coordinates":[-86.11900300000001,39.962101],"type":"Point"}
}