{
  "type": "Feature",
  "properties": {
    "addr:full":"931 Seward St New Haven IN 46774",
    "addr:housenumber":"931",
    "addr:postcode":"46774",
    "addr:street":"Seward St",
    "iso:country":"US",
    "sg:address":"931 Seward St",
    "sg:city":"New Haven",
    "sg:classifiers":[
        {
            "category":"Professional",
            "type":"Services"
        }
    ],
    "sg:phone":"+1 260 749 8435",
    "sg:postcode":"46774",
    "sg:province":"IN",
    "wof:name":"Oars Inc",
    "wof:placetype":"venue"
},
  "geometry": {"coordinates":[-85.01683,41.076567],"type":"Point"}
}