{
  "type": "Feature",
  "properties": {
    "addr:full":"103 E Gibson St Haubstadt IN 47639",
    "addr:housenumber":"103",
    "addr:postcode":"47639",
    "addr:street":"E Gibson St",
    "iso:country":"US",
    "sg:address":"103 E Gibson St",
    "sg:city":"Haubstadt",
    "sg:classifiers":[
        {
            "category":"Restaurant",
            "type":"Food & Drink"
        }
    ],
    "sg:phone":"+1 812 768 6131",
    "sg:postcode":"47639",
    "sg:province":"IN",
    "wof:name":"Carriage Inn",
    "wof:placetype":"venue"
},
  "geometry": {"coordinates":[-87.574206,38.205182],"type":"Point"}
}