{
  "type": "Feature",
  "properties": {
    "iso:country":"US",
    "sg:address":"703 W National Hwy",
    "sg:city":"Washington",
    "sg:classifiers":[
        {
            "category":"Home & Garden",
            "subcategory":"Building Materials",
            "type":"Retail Goods"
        }
    ],
    "sg:phone":"+1 812 254 1105",
    "sg:postcode":"47501",
    "sg:province":"IN",
    "sg:tags":[
        "glass",
        "window",
        "plate"
    ],
    "wof:name":"Glass Specialty Systems",
    "wof:placetype":"venue"
},
  "geometry": {"coordinates":[-87.182858,38.652562],"type":"Point"}
}