{
  "type": "Feature",
  "properties": {
    "addr:full":"781 E Main St Westfield IN 46074",
    "addr:housenumber":"781",
    "addr:postcode":"46074",
    "addr:street":"E Main St",
    "iso:country":"US",
    "sg:address":"781 E Main St",
    "sg:city":"Westfield",
    "sg:classifiers":[
        {
            "category":"Bars & Pubs",
            "type":"Food & Drink"
        }
    ],
    "sg:phone":"+1 317 867 3500",
    "sg:postcode":"46074",
    "sg:province":"IN",
    "wof:name":"Bucky's Grill and Pub",
    "wof:placetype":"venue"
},
  "geometry": {"coordinates":[-86.11786499999999,40.042743],"type":"Point"}
}