{
  "type": "Feature",
  "properties": {
    "iso:country":"US",
    "sg:address":"5627 W 38th St",
    "sg:city":"Indianapolis",
    "sg:classifiers":[
        {
            "category":"Personal",
            "subcategory":"Beauty Salon",
            "type":"Services"
        }
    ],
    "sg:phone":"+1 317 328 1794",
    "sg:postcode":"46254",
    "sg:province":"IN",
    "sg:tags":[
        "manicuring"
    ],
    "wof:name":"Hot Nails",
    "wof:placetype":"venue"
},
  "geometry": {"coordinates":[-86.258224,39.823712],"type":"Point"}
}