{
  "type": "Feature",
  "properties": {
    "iso:country":"US",
    "sg:address":"2244 Profit Dr",
    "sg:city":"Indianapolis",
    "sg:classifiers":[
        {
            "category":"Wholesale",
            "subcategory":"Durable Goods & Equipment",
            "type":"Manufacturing & Wholesale Goods"
        }
    ],
    "sg:phone":"+1 317 240 0005",
    "sg:postcode":"46241",
    "sg:province":"IN",
    "sg:tags":[
        "importer"
    ],
    "wof:name":"Regency International",
    "wof:placetype":"venue"
},
  "geometry": {"coordinates":[-86.25744,39.735151],"type":"Point"}
}