{
  "type": "Feature",
  "properties": {
    "iso:country":"US",
    "sg:address":"110 N Main St",
    "sg:city":"Summitville",
    "sg:classifiers":[
        {
            "category":"Food & Beverages",
            "subcategory":"Groceries & Convenience Stores",
            "type":"Retail Goods"
        }
    ],
    "sg:phone":"+1 765 536 2085",
    "sg:postcode":"46070",
    "sg:province":"IN",
    "wof:name":"Big Foot Food Store",
    "wof:placetype":"venue"
},
  "geometry": {"coordinates":[-85.64436000000001,40.339063],"type":"Point"}
}