{
  "type": "Feature",
  "properties": {
    "iso:country":"US",
    "sg:address":"11403 Valley Dr",
    "sg:city":"Saint John",
    "sg:classifiers":[
        {
            "category":"Manufacturing",
            "subcategory":"Tools & Machinery",
            "type":"Manufacturing & Wholesale Goods"
        }
    ],
    "sg:phone":"+1 219 365 9550",
    "sg:postcode":"46373",
    "sg:province":"IN",
    "sg:tags":[
        "repair"
    ],
    "wof:name":"K A R E Tools",
    "wof:placetype":"venue"
},
  "geometry": {"coordinates":[-87.47265,41.436489],"type":"Point"}
}