{
  "type": "Feature",
  "properties": {
    "iso:country":"US",
    "sg:address":"2770 N 9th Street Rd",
    "sg:city":"Lafayette",
    "sg:classifiers":[
        {
            "category":"Utilities",
            "subcategory":"Refuse",
            "type":"Services"
        }
    ],
    "sg:phone":"+1 765 429 5616",
    "sg:postcode":"47904",
    "sg:province":"IN",
    "sg:tags":[
        "garbage",
        "collection"
    ],
    "wof:name":"Waste Management Inc",
    "wof:placetype":"venue"
},
  "geometry": {"coordinates":[-86.877431,40.450547],"type":"Point"}
}