{
  "type": "Feature",
  "properties": {
    "iso:country":"US",
    "sg:address":"3437 Lafayette Rd",
    "sg:city":"Indianapolis",
    "sg:classifiers":[
        {
            "category":"Autos & Motor Vehicles",
            "subcategory":"Fuel & Gas Station",
            "type":"Retail Goods"
        }
    ],
    "sg:phone":"+1 317 293 3228",
    "sg:postcode":"46222",
    "sg:province":"IN",
    "sg:tags":[
        "oil"
    ],
    "wof:name":"Speedway",
    "wof:placetype":"venue"
},
  "geometry": {"coordinates":[-86.22852399999999,39.817564],"type":"Point"}
}