{
  "type": "Feature",
  "properties": {
    "iso:country":"US",
    "sg:address":"2975 Old State Rd 55 N",
    "sg:city":"Crawfordsville",
    "sg:phone":"+1 765 362 4208",
    "sg:postcode":"47994",
    "sg:province":"IN",
    "sg:tags":[
        "farm",
        "corn",
        "soybean"
    ],
    "wof:name":"Phil Campbell Farms",
    "wof:placetype":"venue"
},
  "geometry": {"coordinates":[-86.96248799999999,40.081704],"type":"Point"}
}