{
  "type": "Feature",
  "properties": {
    "iso:country":"US",
    "sg:address":"229 Farabee Dr N",
    "sg:city":"Lafayette",
    "sg:classifiers":[
        {
            "category":"Home & Garden",
            "subcategory":"Carpets & Floor Coverings",
            "type":"Retail Goods"
        }
    ],
    "sg:phone":"+1 765 448 3330",
    "sg:postcode":"47905",
    "sg:province":"IN",
    "sg:tags":[
        "dealer",
        "rug"
    ],
    "wof:name":"Creative Floor Coverings",
    "wof:placetype":"venue"
},
  "geometry": {"coordinates":[-86.85208799999999,40.418395],"type":"Point"}
}