{
  "type": "Feature",
  "properties": {
    "iso:country":"US",
    "sg:address":"3798 State Rd 10",
    "sg:city":"Wheatfield",
    "sg:classifiers":[
        {
            "category":"Restaurant",
            "type":"Food & Drink"
        }
    ],
    "sg:phone":"+1 219 956 4523",
    "sg:postcode":"46392",
    "sg:province":"IN",
    "wof:name":"Valley Pizza",
    "wof:placetype":"venue"
},
  "geometry": {"coordinates":[-86.984281,41.186752],"type":"Point"}
}