{
  "type": "Feature",
  "properties": {
    "iso:country":"US",
    "sg:address":"5530 E 650 S",
    "sg:city":"Whitestown",
    "sg:classifiers":[
        {
            "category":"Shopping",
            "type":"Retail Goods"
        }
    ],
    "sg:phone":"+1 317 769 3345",
    "sg:postcode":"46075",
    "sg:province":"IN",
    "sg:tags":[
        "equipment",
        "irrigation",
        "system"
    ],
    "wof:name":"Indianapolis Irrigation Co",
    "wof:placetype":"venue"
},
  "geometry": {"coordinates":[-86.360278,39.946064],"type":"Point"}
}