{
  "type": "Feature",
  "properties": {
    "iso:country":"US",
    "sg:address":"11067 Sandpiper St",
    "sg:city":"Demotte",
    "sg:classifiers":[
        {
            "category":"Professional",
            "subcategory":"Advertising",
            "type":"Services"
        }
    ],
    "sg:phone":"+1 219 987 6565",
    "sg:postcode":"46310",
    "sg:province":"IN",
    "sg:tags":[
        "agency"
    ],
    "wof:name":"Advertising & Design By Shari",
    "wof:placetype":"venue"
},
  "geometry": {"coordinates":[-87.22603599999999,41.180361],"type":"Point"}
}