{
  "type": "Feature",
  "properties": {
    "iso:country":"US",
    "sg:address":"2900 State Rd 250",
    "sg:city":"Brownstown",
    "sg:classifiers":[
        {
            "category":"Restaurant",
            "type":"Food & Drink"
        }
    ],
    "sg:phone":"+1 812 358 4517",
    "sg:postcode":"47220",
    "sg:province":"IN",
    "sg:tags":[
        "eating"
    ],
    "wof:name":"Culinary Blessings LLC",
    "wof:placetype":"venue"
},
  "geometry": {"coordinates":[-85.986268,38.852509],"type":"Point"}
}