{
  "type": "Feature",
  "properties": {
    "iso:country":"US",
    "sg:address":"618 N Central Ave",
    "sg:city":"Connersville",
    "sg:classifiers":[
        {
            "category":"Professional",
            "subcategory":"Computer Services",
            "type":"Services"
        }
    ],
    "sg:phone":"+1 765 827 4848",
    "sg:postcode":"47331",
    "sg:province":"IN",
    "sg:tags":[
        "consultant"
    ],
    "sg:website":"www.cnz.com",
    "wof:name":"Citadel Network",
    "wof:placetype":"venue"
},
  "geometry": {"coordinates":[-85.13829800000001,39.642614],"type":"Point"}
}