{
  "type": "Feature",
  "properties": {
    "iso:country":"US",
    "sg:address":"24 Portage Pl",
    "sg:city":"Jeffersonville",
    "sg:classifiers":[
        {
            "category":"Insurance",
            "subcategory":"Insurance Agent",
            "type":"Services"
        }
    ],
    "sg:phone":"+1 812 948 5188",
    "sg:postcode":"47130",
    "sg:province":"IN",
    "wof:name":"Joe Olson & Assoc",
    "wof:placetype":"venue"
},
  "geometry": {"coordinates":[-85.675093,38.308968],"type":"Point"}
}