{
  "type": "Feature",
  "properties": {
    "iso:country":"US",
    "sg:address":"64 N US Hwy 231",
    "sg:city":"Greencastle",
    "sg:classifiers":[
        {
            "category":"Manufacturing",
            "subcategory":"Lumber",
            "type":"Manufacturing & Wholesale Goods"
        }
    ],
    "sg:phone":"+1 765 653 6615",
    "sg:postcode":"46135",
    "sg:province":"IN",
    "sg:tags":[
        "government"
    ],
    "wof:name":"Natural Rsrc Dept-Forestry Div",
    "wof:placetype":"venue"
},
  "geometry": {"coordinates":[-86.870086,39.664756],"type":"Point"}
}