{
  "type": "Feature",
  "properties": {
    "iso:country":"US",
    "sg:address":"104 N Lutz St",
    "sg:city":"Kentland",
    "sg:classifiers":[
        {
            "category":"Building & Trades",
            "subcategory":"Construction",
            "type":"Services"
        }
    ],
    "sg:phone":"+1 219 474 6542",
    "sg:postcode":"47951",
    "sg:province":"IN",
    "sg:tags":[
        "bridge",
        "builder"
    ],
    "wof:name":"Wirtz-Yates Inc",
    "wof:placetype":"venue"
},
  "geometry": {"coordinates":[-87.466174,40.770363],"type":"Point"}
}