{
  "type": "Feature",
  "properties": {
    "iso:country":"US",
    "sg:address":"6830 US Hwy 24",
    "sg:city":"Logansport",
    "sg:classifiers":[
        {
            "category":"Sports & Exercise",
            "subcategory":"Race Track",
            "type":"Entertainment"
        }
    ],
    "sg:phone":"+1 574 753 6922",
    "sg:postcode":"46947",
    "sg:province":"IN",
    "wof:name":"U S 24 Speedway",
    "wof:placetype":"venue"
},
  "geometry": {"coordinates":[-86.502379,40.764395],"type":"Point"}
}