{
  "type": "Feature",
  "properties": {
    "iso:country":"US",
    "sg:address":"1626 E Crothersville Rd",
    "sg:city":"Austin",
    "sg:classifiers":[
        {
            "category":"Retail",
            "subcategory":"Laundry & Dry Cleaning",
            "type":"Services"
        }
    ],
    "sg:phone":"+1 812 794 3897",
    "sg:postcode":"47102",
    "sg:province":"IN",
    "wof:name":"Spicers Noah Von Schrader CPT",
    "wof:placetype":"venue"
},
  "geometry": {"coordinates":[-85.75125,38.786765],"type":"Point"}
}