{
  "type": "Feature",
  "properties": {
    "iso:country":"US",
    "sg:address":"980 Padre Ln",
    "sg:city":"Greenwood",
    "sg:classifiers":[
        {
            "category":"Professional",
            "subcategory":"Secretarial Services",
            "type":"Services"
        }
    ],
    "sg:phone":"+1 317 883 2139",
    "sg:postcode":"46143",
    "sg:province":"IN",
    "sg:tags":[
        "reporting",
        "court"
    ],
    "wof:name":"Margaret S Dodd",
    "wof:placetype":"venue"
},
  "geometry": {"coordinates":[-86.08329000000001,39.606097],"type":"Point"}
}