{
  "type": "Feature",
  "properties": {
    "iso:country":"US",
    "sg:address":"2665 N Co Rd 850 W",
    "sg:city":"Shipshewana",
    "sg:classifiers":[
        {
            "category":"Manufacturing",
            "subcategory":"Chemicals & Compounds",
            "type":"Manufacturing & Wholesale Goods"
        }
    ],
    "sg:phone":"+1 260 768 4513",
    "sg:postcode":"46565",
    "sg:province":"IN",
    "sg:tags":[
        "fertilizer",
        "mixing",
        "only"
    ],
    "wof:name":"Edd's Supplies Inc",
    "wof:placetype":"venue"
},
  "geometry": {"coordinates":[-85.590392,41.679023],"type":"Point"}
}