{
  "type": "Feature",
  "properties": {
    "iso:country":"US",
    "sg:address":"16 W 5th St",
    "sg:city":"Brookville",
    "sg:classifiers":[
        {
            "category":"Social Services",
            "type":"Services"
        }
    ],
    "sg:phone":"+1 765 647 2853",
    "sg:postcode":"47012",
    "sg:province":"IN",
    "wof:name":"Franklin County Red Cross",
    "wof:placetype":"venue"
},
  "geometry": {"coordinates":[-85.013447,39.419737],"type":"Point"}
}