{
  "type": "Feature",
  "properties": {
    "iso:country":"US",
    "sg:address":"12232 Hancock St",
    "sg:city":"Carmel",
    "sg:classifiers":[
        {
            "category":"Arts & Performance",
            "subcategory":"Art Gallery",
            "type":"Entertainment"
        },
        {
            "category":"Shopping",
            "subcategory":"Antiques",
            "type":"Retail Goods"
        }
    ],
    "sg:phone":"+1 317 844 7253",
    "sg:postcode":"46032",
    "sg:province":"IN",
    "wof:name":"Jackson & Wickliff Auctioneers Inc",
    "wof:placetype":"venue"
},
  "geometry": {"coordinates":[-86.148903,39.965801],"type":"Point"}
}