{
  "type": "Feature",
  "properties": {
    "addr:full":"1405 Newton St Jasper IN 47546",
    "addr:housenumber":"1405",
    "addr:postcode":"47546",
    "addr:street":"Newton St",
    "iso:country":"US",
    "sg:address":"1405 Newton St",
    "sg:city":"Jasper",
    "sg:classifiers":[
        {
            "category":"Banks & Credit Unions",
            "subcategory":"Investment Brokerage",
            "type":"Services"
        }
    ],
    "sg:phone":"+1 812 634 2883",
    "sg:postcode":"47546",
    "sg:province":"IN",
    "sg:tags":[
        "consultant",
        "planning",
        "financial"
    ],
    "wof:name":"Heidorn Financial Ctr",
    "wof:placetype":"venue"
},
  "geometry": {"coordinates":[-86.931887,38.400163],"type":"Point"}
}