{
  "type": "Feature",
  "properties": {
    "iso:country":"US",
    "sg:address":"591 E Water St",
    "sg:city":"Pendleton",
    "sg:classifiers":[
        {
            "category":"Recreation",
            "type":"Entertainment"
        }
    ],
    "sg:phone":"+1 765 778 4411",
    "sg:postcode":"46064",
    "sg:province":"IN",
    "sg:tags":[
        "pool",
        "swimming"
    ],
    "wof:name":"Brown Pool",
    "wof:placetype":"venue"
},
  "geometry": {"coordinates":[-85.737575,40.003827],"type":"Point"}
}