{
  "type": "Feature",
  "properties": {
    "iso:country":"US",
    "sg:address":"7001 Jackson St",
    "sg:city":"Indianapolis",
    "sg:classifiers":[
        {
            "category":"Building & Trades",
            "subcategory":"Plumbing",
            "type":"Services"
        }
    ],
    "sg:phone":"+1 317 841 7024",
    "sg:postcode":"46241",
    "sg:province":"IN",
    "sg:tags":[
        "plumbing",
        "contractor"
    ],
    "wof:name":"K L Price Plumbing",
    "wof:placetype":"venue"
},
  "geometry": {"coordinates":[-86.285679,39.761243],"type":"Point"}
}