{
  "type": "Feature",
  "properties": {
    "addr:full":"7820 Eagle Crest Blvd Evansville IN 47715",
    "addr:housenumber":"7820",
    "addr:postcode":"47715",
    "addr:street":"Eagle Crest Blvd",
    "iso:country":"US",
    "sg:address":"7820 Eagle Crest Blvd",
    "sg:city":"Evansville",
    "sg:classifiers":[
        {
            "category":"Insurance",
            "subcategory":"Insurance Agent",
            "type":"Services"
        }
    ],
    "sg:phone":"+1 812 477 9966",
    "sg:postcode":"47715",
    "sg:province":"IN",
    "wof:name":"AAA Insurance",
    "wof:placetype":"venue"
},
  "geometry": {"coordinates":[-87.459766,37.975675],"type":"Point"}
}