{
  "type": "Feature",
  "properties": {
    "iso:country":"US",
    "sg:address":"1527 N Gardner St",
    "sg:city":"Scottsburg",
    "sg:classifiers":[
        {
            "category":"Autos & Motor Vehicles",
            "subcategory":"Automobile Sales",
            "type":"Retail Goods"
        }
    ],
    "sg:phone":"+1 812 752 4693",
    "sg:postcode":"47170",
    "sg:province":"IN",
    "sg:tags":[
        "car",
        "dealer"
    ],
    "wof:name":"Stevens Spellman Auto Corp",
    "wof:placetype":"venue"
},
  "geometry": {"coordinates":[-85.78264799999999,38.723038],"type":"Point"}
}