{
  "type": "Feature",
  "properties": {
    "iso:country":"US",
    "sg:address":"421 Chestnut St",
    "sg:city":"Evansville",
    "sg:classifiers":[
        {
            "category":"Banks & Credit Unions",
            "subcategory":"Financial Services",
            "type":"Services"
        }
    ],
    "sg:phone":"+1 812 426 6686",
    "sg:postcode":"47713",
    "sg:province":"IN",
    "sg:tags":[
        "company",
        "holding"
    ],
    "wof:name":"Us Healthcare Holdings",
    "wof:placetype":"venue"
},
  "geometry": {"coordinates":[-87.569573,37.968648],"type":"Point"}
}