{
  "type": "Feature",
  "properties": {
    "addr:full":"2312 N 23rd St Lafayette IN 47904",
    "addr:housenumber":"2312",
    "addr:postcode":"47904",
    "addr:street":"N 23Rd St",
    "iso:country":"US",
    "sg:address":"2312 N 23rd St",
    "sg:city":"Lafayette",
    "sg:classifiers":[
        {
            "category":"Building & Trades",
            "subcategory":"Construction",
            "type":"Services"
        }
    ],
    "sg:phone":"+1 765 742 5311",
    "sg:postcode":"47904",
    "sg:province":"IN",
    "sg:tags":[
        "company"
    ],
    "wof:name":"K & S Construction",
    "wof:placetype":"venue"
},
  "geometry": {"coordinates":[-86.87091700000001,40.441017],"type":"Point"}
}