{
  "type": "Feature",
  "properties": {
    "iso:country":"US",
    "sg:address":"7760 E 37th Ave",
    "sg:city":"Hobart",
    "sg:classifiers":[
        {
            "category":"Food & Beverages",
            "subcategory":"Groceries & Convenience Stores",
            "type":"Retail Goods"
        }
    ],
    "sg:phone":"+1 219 962 5551",
    "sg:postcode":"46342",
    "sg:province":"IN",
    "sg:tags":[
        "grocer"
    ],
    "wof:name":"Strack & Van Til Mega Mart",
    "wof:placetype":"venue"
},
  "geometry": {"coordinates":[-87.24821,41.550798],"type":"Point"}
}