{
  "type": "Feature",
  "properties": {
    "iso:country":"US",
    "sg:address":"817 S Green River Rd",
    "sg:city":"Evansville",
    "sg:classifiers":[
        {
            "category":"Shopping",
            "subcategory":"Clothing, Apparel, & Fashions",
            "type":"Retail Goods"
        }
    ],
    "sg:phone":"+1 812 473 2640",
    "sg:postcode":"47715",
    "sg:province":"IN",
    "sg:tags":[
        "designer"
    ],
    "wof:name":"Harvey Jake's Fashion",
    "wof:placetype":"venue"
},
  "geometry": {"coordinates":[-87.49275799999999,37.962524],"type":"Point"}
}