{
  "type": "Feature",
  "properties": {
    "iso:country":"US",
    "sg:address":"3123 S 500 W",
    "sg:city":"New Palestine",
    "sg:classifiers":[
        {
            "category":"Organizations",
            "subcategory":"Religious Organization",
            "type":"Services"
        }
    ],
    "sg:phone":"+1 317 861 5407",
    "sg:postcode":"46163",
    "sg:province":"IN",
    "sg:tags":[
        "church"
    ],
    "wof:name":"Community Christian Church",
    "wof:placetype":"venue"
},
  "geometry": {"coordinates":[-85.895538,39.739906],"type":"Point"}
}