{
  "type": "Feature",
  "properties": {
    "iso:country":"US",
    "sg:address":"1439 Industrial Dr N",
    "sg:city":"Lagrange",
    "sg:classifiers":[
        {
            "category":"Manufacturing",
            "subcategory":"Rubber & Plastics",
            "type":"Manufacturing & Wholesale Goods"
        }
    ],
    "sg:phone":"+1 260 463 7100",
    "sg:postcode":"46761",
    "sg:province":"IN",
    "wof:name":"Master Quality Finishing",
    "wof:placetype":"venue"
},
  "geometry": {"coordinates":[-85.418885,41.658256],"type":"Point"}
}