{
  "type": "Feature",
  "properties": {
    "iso:country":"US",
    "sg:address":"2121 25th St",
    "sg:city":"Columbus",
    "sg:classifiers":[
        {
            "category":"Banks & Credit Unions",
            "subcategory":"Investment Brokerage",
            "type":"Services"
        }
    ],
    "sg:phone":"+1 812 546 5000",
    "sg:postcode":"47201",
    "sg:province":"IN",
    "sg:tags":[
        "consultant",
        "planning",
        "financial"
    ],
    "wof:name":"Synergy Group Inc",
    "wof:placetype":"venue"
},
  "geometry": {"coordinates":[-85.901478,39.222948],"type":"Point"}
}