{
  "type": "Feature",
  "properties": {
    "addr:full":"2948 State Rd 62 Jeffersonville IN 47130",
    "addr:housenumber":"2948;62",
    "addr:postcode":"47130",
    "addr:street":"State Rd",
    "iso:country":"US",
    "sg:address":"2948 State Rd 62",
    "sg:city":"Jeffersonville",
    "sg:classifiers":[
        {
            "category":"Professional",
            "subcategory":"Accounting & Tax Preparation",
            "type":"Services"
        }
    ],
    "sg:phone":"+1 812 280 9395",
    "sg:postcode":"47130",
    "sg:province":"IN",
    "sg:tags":[
        "return",
        "filing"
    ],
    "wof:name":"Jackson Hewitt Tax Service",
    "wof:placetype":"venue"
},
  "geometry": {"coordinates":[-85.71320900000001,38.321689],"type":"Point"}
}