{
  "type": "Feature",
  "properties": {
    "iso:country":"US",
    "sg:address":"3100 N Detroit St",
    "sg:city":"Warsaw",
    "sg:classifiers":[
        {
            "category":"Manufacturing",
            "subcategory":"Electronics",
            "type":"Manufacturing & Wholesale Goods"
        }
    ],
    "sg:phone":"+1 574 267 8101",
    "sg:postcode":"46582",
    "sg:province":"IN",
    "sg:tags":[
        "equipment",
        "household"
    ],
    "sg:website":"www.da-lite.com",
    "wof:name":"Da-Lite Screen Co",
    "wof:placetype":"venue"
},
  "geometry": {"coordinates":[-85.853358,41.284662],"type":"Point"}
}