{
  "type": "Feature",
  "properties": {
    "iso:country":"US",
    "sg:address":"7930 Cherrybark Ct",
    "sg:city":"Indianapolis",
    "sg:classifiers":[
        {
            "category":"Professional",
            "subcategory":"Business Services",
            "type":"Services"
        }
    ],
    "sg:phone":"+1 317 823 5784",
    "sg:postcode":"46236",
    "sg:province":"IN",
    "wof:name":"DMJ Services",
    "wof:placetype":"venue"
},
  "geometry": {"coordinates":[-85.948488,39.899335],"type":"Point"}
}