{
  "type": "Feature",
  "properties": {
    "iso:country":"US",
    "sg:address":"3726 Ridge Rd",
    "sg:city":"Highland",
    "sg:classifiers":[
        {
            "category":"Retail",
            "subcategory":"Portrait Studio",
            "type":"Services"
        }
    ],
    "sg:phone":"+1 219 923 5990",
    "sg:postcode":"46322",
    "sg:province":"IN",
    "sg:tags":[
        "photo"
    ],
    "wof:name":"Photographers Unlimited",
    "wof:placetype":"venue"
},
  "geometry": {"coordinates":[-87.43795900000001,41.552029],"type":"Point"}
}