{
  "type": "Feature",
  "properties": {
    "iso:country":"US",
    "sg:address":"111 W Main St",
    "sg:city":"Carmel",
    "sg:classifiers":[
        {
            "category":"Restaurant",
            "type":"Food & Drink"
        }
    ],
    "sg:phone":"+1 317 848 4488",
    "sg:postcode":"46032",
    "sg:province":"IN",
    "sg:tags":[
        "pizza"
    ],
    "sg:website":"www.bazbeaux.com",
    "wof:name":"Bazbeaux Pizza",
    "wof:placetype":"venue"
},
  "geometry": {"coordinates":[-86.128782,39.977888],"type":"Point"}
}