{
  "type": "Feature",
  "properties": {
    "iso:country":"US",
    "sg:address":"6612 Belle Isle Pl",
    "sg:city":"Fort Wayne",
    "sg:classifiers":[
        {
            "category":"Retail",
            "subcategory":"Laundry & Dry Cleaning",
            "type":"Services"
        }
    ],
    "sg:phone":"+1 260 486 8611",
    "sg:postcode":"46835",
    "sg:province":"IN",
    "sg:tags":[
        "cleaners"
    ],
    "wof:name":"Pressed 4 Time",
    "wof:placetype":"venue"
},
  "geometry": {"coordinates":[-85.060615,41.15635],"type":"Point"}
}