{
  "type": "Feature",
  "properties": {
    "iso:country":"US",
    "sg:address":"10287 Sheffield Ct",
    "sg:city":"Newburgh",
    "sg:classifiers":[
        {
            "category":"Sports & Exercise",
            "subcategory":"Race Track",
            "type":"Entertainment"
        }
    ],
    "sg:phone":"+1 812 858 9824",
    "sg:postcode":"47630",
    "sg:province":"IN",
    "sg:tags":[
        "operation",
        "racing",
        "or"
    ],
    "wof:name":"Dejong Merritt Jr",
    "wof:placetype":"venue"
},
  "geometry": {"coordinates":[-87.438119,37.968784],"type":"Point"}
}