{
  "type": "Feature",
  "properties": {
    "iso:country":"US",
    "sg:address":"6650 Telecom Dr",
    "sg:city":"Indianapolis",
    "sg:classifiers":[
        {
            "category":"Professional",
            "subcategory":"Lawyer & Legal Services",
            "type":"Services"
        }
    ],
    "sg:phone":"+1 317 616 3675",
    "sg:postcode":"46278",
    "sg:province":"IN",
    "sg:tags":[
        "attorney"
    ],
    "wof:name":"Rowdy Williams Law Office",
    "wof:placetype":"venue"
},
  "geometry": {"coordinates":[-86.269698,39.875735],"type":"Point"}
}