{
  "type": "Feature",
  "properties": {
    "iso:country":"US",
    "sg:address":"809 S Co Rd 200 W",
    "sg:city":"Greensburg",
    "sg:classifiers":[
        {
            "category":"Recreation",
            "type":"Entertainment"
        }
    ],
    "sg:phone":"+1 812 663 5988",
    "sg:postcode":"47240",
    "sg:province":"IN",
    "sg:tags":[
        "pool",
        "swimming"
    ],
    "wof:name":"Allen Memorial Pool",
    "wof:placetype":"venue"
},
  "geometry": {"coordinates":[-85.51827400000001,39.326169],"type":"Point"}
}