{
  "type": "Feature",
  "properties": {
    "iso:country":"US",
    "sg:address":"1690 S Co Rd 225 E",
    "sg:city":"Danville",
    "sg:classifiers":[
        {
            "category":"Retail",
            "subcategory":"Repair Shop",
            "type":"Services"
        }
    ],
    "sg:phone":"+1 317 745 0204",
    "sg:postcode":"46122",
    "sg:province":"IN",
    "sg:tags":[
        "related"
    ],
    "wof:name":"Danville Truck Repair Ctr",
    "wof:placetype":"venue"
},
  "geometry": {"coordinates":[-86.481499,39.738107],"type":"Point"}
}