{
  "type": "Feature",
  "properties": {
    "addr:full":"709 Stafford Rd Plainfield IN 46168",
    "addr:housenumber":"709",
    "addr:postcode":"46168",
    "addr:street":"Stafford Rd",
    "iso:country":"US",
    "sg:address":"709 Stafford Rd",
    "sg:city":"Plainfield",
    "sg:classifiers":[
        {
            "category":"Education",
            "subcategory":"School",
            "type":"Public Place"
        }
    ],
    "sg:phone":"+1 317 839 7711",
    "sg:postcode":"46168",
    "sg:province":"IN",
    "sg:website":"www.plainfield.k12.in.us",
    "wof:name":"Plainfield High School",
    "wof:placetype":"venue"
},
  "geometry": {"coordinates":[-86.395607,39.69673],"type":"Point"}
}