{
  "type": "Feature",
  "properties": {
    "iso:country":"US",
    "sg:address":"13935 Huseman St",
    "sg:city":"Cedar Lake",
    "sg:classifiers":[
        {
            "category":"Autos & Motor Vehicles",
            "subcategory":"Boat Sales",
            "type":"Retail Goods"
        }
    ],
    "sg:phone":"+1 219 776 4014",
    "sg:postcode":"46303",
    "sg:province":"IN",
    "sg:tags":[
        "dealer",
        "sales"
    ],
    "wof:name":"Lake Front Maintenance",
    "wof:placetype":"venue"
},
  "geometry": {"coordinates":[-87.436943,41.365451],"type":"Point"}
}