{
  "type": "Feature",
  "properties": {
    "addr:full":"3249 E Co Rd 700 N Sunman IN 47041",
    "addr:housenumber":"3249;700",
    "addr:postcode":"47041",
    "addr:street":"E Co Rd;N",
    "iso:country":"US",
    "sg:address":"3249 E Co Rd 700 N",
    "sg:city":"Sunman",
    "sg:classifiers":[
        {
            "category":"Farming",
            "subcategory":"Farm",
            "type":"Manufacturing & Wholesale Goods"
        }
    ],
    "sg:phone":"+1 812 852 4424",
    "sg:postcode":"47041",
    "sg:province":"IN",
    "wof:name":"Crum Farms",
    "wof:placetype":"venue"
},
  "geometry": {"coordinates":[-85.205659,39.17698],"type":"Point"}
}