{
  "type": "Feature",
  "properties": {
    "iso:country":"US",
    "sg:address":"3180 W 250 N",
    "sg:city":"West Lafayette",
    "sg:classifiers":[
        {
            "category":"Manufacturing",
            "subcategory":"Rubber & Plastics",
            "type":"Manufacturing & Wholesale Goods"
        }
    ],
    "sg:phone":"+1 765 463 1011",
    "sg:postcode":"47906",
    "sg:province":"IN",
    "sg:tags":[
        "product"
    ],
    "sg:website":"www.treepro.com",
    "wof:name":"Tree Pro",
    "wof:placetype":"venue"
},
  "geometry": {"coordinates":[-86.96969300000001,40.452945],"type":"Point"}
}