{
  "type": "Feature",
  "properties": {
    "iso:country":"US",
    "sg:address":"12324 W 175 N",
    "sg:city":"Deputy",
    "sg:classifiers":[
        {
            "category":"Building & Trades",
            "subcategory":"Plumbing",
            "type":"Services"
        }
    ],
    "sg:phone":"+1 812 866 8070",
    "sg:postcode":"47230",
    "sg:province":"IN",
    "sg:tags":[
        "conditioning",
        "air",
        "system",
        "contractor"
    ],
    "wof:name":"American Heating & Cooling",
    "wof:placetype":"venue"
},
  "geometry": {"coordinates":[-85.61888500000001,38.76277],"type":"Point"}
}