{
  "type": "Feature",
  "properties": {
    "iso:country":"US",
    "sg:address":"5206 N College Ave",
    "sg:city":"Indianapolis",
    "sg:classifiers":[
        {
            "category":"Shopping",
            "subcategory":"Florist",
            "type":"Retail Goods"
        }
    ],
    "sg:phone":"+1 317 920 8030",
    "sg:postcode":"46220",
    "sg:province":"IN",
    "wof:name":"Keith Little Fine Florals",
    "wof:placetype":"venue"
},
  "geometry": {"coordinates":[-86.14585099999999,39.847774],"type":"Point"}
}