{
  "type": "Feature",
  "properties": {
    "iso:country":"US",
    "sg:address":"919 Millbrook Ln",
    "sg:city":"Kokomo",
    "sg:classifiers":[
        {
            "category":"Government",
            "subcategory":"Office",
            "type":"Public Place"
        }
    ],
    "sg:phone":"+1 765 456 7561",
    "sg:postcode":"46901",
    "sg:province":"IN",
    "sg:tags":[
        "village"
    ],
    "wof:name":"Kokomo Central Garage",
    "wof:placetype":"venue"
},
  "geometry": {"coordinates":[-86.151106,40.476613],"type":"Point"}
}