{
  "type": "Feature",
  "properties": {
    "addr:full":"10288 W State Route 66 Newburgh IN 47630",
    "addr:housenumber":"10288",
    "addr:postcode":"47630",
    "addr:street":"W State Route 66",
    "iso:country":"US",
    "sg:address":"10288 W State Route 66",
    "sg:city":"Newburgh",
    "sg:classifiers":[
        {
            "category":"Health Services",
            "subcategory":"Doctor",
            "type":"Services"
        }
    ],
    "sg:phone":"+1 812 853 5864",
    "sg:postcode":"47630",
    "sg:province":"IN",
    "sg:website":"www.thelungcentre.com",
    "wof:name":"Lung Centre the",
    "wof:placetype":"venue"
},
  "geometry": {"coordinates":[-87.43626500000001,37.976997],"type":"Point"}
}