{
  "type": "Feature",
  "properties": {
    "iso:country":"US",
    "sg:address":"10084 Cedar Ridge Dr",
    "sg:city":"Carmel",
    "sg:classifiers":[
        {
            "category":"Health Services",
            "subcategory":"Doctor",
            "type":"Services"
        }
    ],
    "sg:phone":"+1 317 848 7897",
    "sg:postcode":"46032",
    "sg:province":"IN",
    "sg:tags":[
        "surgeon",
        "oral"
    ],
    "wof:name":"Gradeless Michael R DDS",
    "wof:placetype":"venue"
},
  "geometry": {"coordinates":[-86.177696,39.933498],"type":"Point"}
}