{
  "type": "Feature",
  "properties": {
    "iso:country":"US",
    "sg:address":"910 W Kathy's Way",
    "sg:city":"Greensburg",
    "sg:classifiers":[
        {
            "category":"Autos & Motor Vehicles",
            "subcategory":"Automobile Sales",
            "type":"Retail Goods"
        }
    ],
    "sg:phone":"+1 812 663 1002",
    "sg:postcode":"47240",
    "sg:province":"IN",
    "sg:tags":[
        "car",
        "dealer"
    ],
    "wof:name":"J & M Auto Sales & Svc Inc",
    "wof:placetype":"venue"
},
  "geometry": {"coordinates":[-85.499973,39.344358],"type":"Point"}
}