{
  "type": "Feature",
  "properties": {
    "iso:country":"US",
    "sg:address":"922 Meridian St",
    "sg:city":"Anderson",
    "sg:classifiers":[
        {
            "category":"Professional",
            "subcategory":"Credit Reporting & Collection",
            "type":"Services"
        }
    ],
    "sg:phone":"+1 765 649 4650",
    "sg:postcode":"46016",
    "sg:province":"IN",
    "sg:tags":[
        "agency"
    ],
    "wof:name":"Collection Specialists Inc",
    "wof:placetype":"venue"
},
  "geometry": {"coordinates":[-85.679135,40.106312],"type":"Point"}
}