{
  "type": "Feature",
  "properties": {
    "iso:country":"US",
    "sg:address":"3451 W 126th St",
    "sg:city":"Carmel",
    "sg:classifiers":[
        {
            "category":"Social Services",
            "type":"Services"
        }
    ],
    "sg:phone":"+1 317 733 9807",
    "sg:postcode":"46032",
    "sg:province":"IN",
    "sg:tags":[
        "youth",
        "organization",
        "center"
    ],
    "wof:name":"Carmel Dads' Club",
    "wof:placetype":"venue"
},
  "geometry": {"coordinates":[-86.218972,39.969922],"type":"Point"}
}