{
  "type": "Feature",
  "properties": {
    "addr:full":"145 S Nappanee St Elkhart IN 46514",
    "addr:housenumber":"145",
    "addr:postcode":"46514",
    "addr:street":"S Nappanee St",
    "iso:country":"US",
    "sg:address":"145 S Nappanee St",
    "sg:city":"Elkhart",
    "sg:classifiers":[
        {
            "category":"Health Services",
            "subcategory":"Podiatrist",
            "type":"Services"
        }
    ],
    "sg:phone":"+1 574 522 3668",
    "sg:postcode":"46514",
    "sg:province":"IN",
    "wof:name":"Foot Surgeons & Podiatry Spec",
    "wof:placetype":"venue"
},
  "geometry": {"coordinates":[-86.003472,41.684247],"type":"Point"}
}