{
  "type": "Feature",
  "properties": {
    "addr:full":"18761 Co Rd 40 Goshen IN 46526",
    "addr:housenumber":"18761;40",
    "addr:postcode":"46526",
    "addr:street":"Co Rd",
    "iso:country":"US",
    "sg:address":"18761 Co Rd 40",
    "sg:city":"Goshen",
    "sg:classifiers":[
        {
            "category":"Health Services",
            "subcategory":"Clinic",
            "type":"Services"
        }
    ],
    "sg:phone":"+1 574 534 2213",
    "sg:postcode":"46526",
    "sg:province":"IN",
    "sg:tags":[
        "alternative",
        "care"
    ],
    "wof:name":"Focus On Health",
    "wof:placetype":"venue"
},
  "geometry": {"coordinates":[-85.82114900000001,41.537047],"type":"Point"}
}