{
  "type": "Feature",
  "properties": {
    "iso:country":"US",
    "sg:address":"1017 N Drexel Ave",
    "sg:city":"Indianapolis",
    "sg:classifiers":[
        {
            "category":"Building & Trades",
            "subcategory":"Construction",
            "type":"Services"
        }
    ],
    "sg:phone":"+1 317 359 2794",
    "sg:postcode":"46201",
    "sg:province":"IN",
    "sg:tags":[
        "downspouts",
        "gutter"
    ],
    "wof:name":"Lord's Custom Gutters Inc",
    "wof:placetype":"venue"
},
  "geometry": {"coordinates":[-86.091585,39.78231],"type":"Point"}
}