{
  "type": "Feature",
  "properties": {
    "iso:country":"US",
    "sg:address":"325 J St",
    "sg:city":"Laporte",
    "sg:classifiers":[
        {
            "category":"Shopping",
            "subcategory":"Computers & Home Electronics",
            "type":"Retail Goods"
        }
    ],
    "sg:phone":"+1 219 326 7779",
    "sg:postcode":"46350",
    "sg:province":"IN",
    "sg:tags":[
        "equipment",
        "dealer"
    ],
    "sg:website":"www.wje.net",
    "wof:name":"Computech Systems",
    "wof:placetype":"venue"
},
  "geometry": {"coordinates":[-86.730172,41.60457],"type":"Point"}
}