{
  "type": "Feature",
  "properties": {
    "iso:country":"US",
    "sg:address":"468 Main St",
    "sg:city":"Brookville",
    "sg:classifiers":[
        {
            "category":"Cinema",
            "subcategory":"Movie Rental",
            "type":"Entertainment"
        }
    ],
    "sg:phone":"+1 765 647 3371",
    "sg:postcode":"47012",
    "sg:province":"IN",
    "sg:tags":[
        "leasing",
        "video",
        "disc",
        "tape"
    ],
    "wof:name":"George's Family Video",
    "wof:placetype":"venue"
},
  "geometry": {"coordinates":[-85.01288099999999,39.419442],"type":"Point"}
}