{
  "type": "Feature",
  "properties": {
    "addr:full":"1302 13th St Bedford IN 47421",
    "addr:housenumber":"1302",
    "addr:postcode":"47421",
    "addr:street":"13Th St",
    "iso:country":"US",
    "sg:address":"1302 13th St",
    "sg:city":"Bedford",
    "sg:classifiers":[
        {
            "category":"Organizations",
            "subcategory":"Religious Organization",
            "type":"Services"
        }
    ],
    "sg:phone":"+1 812 275 2369",
    "sg:postcode":"47421",
    "sg:province":"IN",
    "sg:tags":[
        "church"
    ],
    "wof:name":"Landmark Missionary Baptist",
    "wof:placetype":"venue"
},
  "geometry": {"coordinates":[-86.490036,38.864426],"type":"Point"}
}