{
  "type": "Feature",
  "properties": {
    "addr:full":"2316 Grant Line Rd New Albany IN 47150",
    "addr:housenumber":"2316",
    "addr:postcode":"47150",
    "addr:street":"Grant Line Rd",
    "iso:country":"US",
    "sg:address":"2316 Grant Line Rd",
    "sg:city":"New Albany",
    "sg:classifiers":[
        {
            "category":"Retail",
            "subcategory":"Auto Repair",
            "type":"Services"
        }
    ],
    "sg:phone":"+1 812 945 2162",
    "sg:postcode":"47150",
    "sg:province":"IN",
    "sg:tags":[
        "repairing",
        "automobile"
    ],
    "wof:name":"Clemons Auto Svc",
    "wof:placetype":"venue"
},
  "geometry": {"coordinates":[-85.82083299999999,38.309173],"type":"Point"}
}