{
  "type": "Feature",
  "properties": {
    "addr:full":"7089 N Chicago Rd New Carlisle IN 46552",
    "addr:housenumber":"7089",
    "addr:postcode":"46552",
    "addr:street":"N Chicago Rd",
    "iso:country":"US",
    "sg:address":"7089 N Chicago Rd",
    "sg:city":"New Carlisle",
    "sg:classifiers":[
        {
            "category":"Restaurant",
            "type":"Food & Drink"
        }
    ],
    "sg:phone":"+1 574 654 3260",
    "sg:postcode":"46552",
    "sg:province":"IN",
    "wof:name":"Whistlestop Cafe",
    "wof:placetype":"venue"
},
  "geometry": {"coordinates":[-86.537699,41.709361],"type":"Point"}
}