{
  "type": "Feature",
  "properties": {
    "iso:country":"US",
    "sg:address":"100 Williamsburg Dr",
    "sg:city":"Evansville",
    "sg:classifiers":[
        {
            "category":"Real Estate",
            "subcategory":"Real Estate Operator",
            "type":"Services"
        }
    ],
    "sg:phone":"+1 812 479 0917",
    "sg:postcode":"47715",
    "sg:province":"IN",
    "sg:tags":[
        "apartment"
    ],
    "wof:name":"Williamsburg On The Lake",
    "wof:placetype":"venue"
},
  "geometry": {"coordinates":[-87.474876,37.974495],"type":"Point"}
}