{
  "type": "Feature",
  "properties": {
    "addr:full":"1901 3rd Ave Terre Haute IN 47807",
    "addr:housenumber":"1901",
    "addr:postcode":"47807",
    "addr:street":"3Rd Ave",
    "iso:country":"US",
    "sg:address":"1901 3rd Ave",
    "sg:city":"Terre Haute",
    "sg:classifiers":[
        {
            "category":"Retail",
            "subcategory":"Auto Repair",
            "type":"Services"
        }
    ],
    "sg:phone":"+1 812 235 7000",
    "sg:postcode":"47807",
    "sg:province":"IN",
    "sg:tags":[
        "repairing",
        "automobile"
    ],
    "wof:name":"Auto Doctor",
    "wof:placetype":"venue"
},
  "geometry": {"coordinates":[-87.387214,39.480237],"type":"Point"}
}