{
  "type": "Feature",
  "properties": {
    "iso:country":"US",
    "sg:address":"2372 E Main St",
    "sg:city":"Plainfield",
    "sg:classifiers":[
        {
            "category":"Personal",
            "subcategory":"Beauty Salon",
            "type":"Services"
        }
    ],
    "sg:phone":"+1 317 839 8319",
    "sg:postcode":"46168",
    "sg:province":"IN",
    "sg:tags":[
        "shop"
    ],
    "wof:name":"Hair Designs By Brian Patrick",
    "wof:placetype":"venue"
},
  "geometry": {"coordinates":[-86.370281,39.712833],"type":"Point"}
}