{
  "type": "Feature",
  "properties": {
    "iso:country":"US",
    "sg:address":"2550 N 6th St",
    "sg:city":"Terre Haute",
    "sg:classifiers":[
        {
            "category":"Building & Trades",
            "subcategory":"Construction",
            "type":"Services"
        }
    ],
    "sg:phone":"+1 812 208 3296",
    "sg:postcode":"47804",
    "sg:province":"IN",
    "sg:tags":[
        "demolition",
        "contractor"
    ],
    "wof:name":"Ace Demolition",
    "wof:placetype":"venue"
},
  "geometry": {"coordinates":[-87.410757,39.49933],"type":"Point"}
}