{
  "type": "Feature",
  "properties": {
    "iso:country":"US",
    "sg:address":"9516 W 500 N",
    "sg:city":"Delphi",
    "sg:classifiers":[
        {
            "category":"Freight",
            "type":"Transportation"
        }
    ],
    "sg:phone":"+1 765 564 6222",
    "sg:postcode":"46923",
    "sg:province":"IN",
    "sg:tags":[
        "trucking"
    ],
    "wof:name":"Kennedy Enterprises",
    "wof:placetype":"venue"
},
  "geometry": {"coordinates":[-86.714433,40.61956],"type":"Point"}
}