{
  "type": "Feature",
  "properties": {
    "addr:full":"1906 W 1000 N Knightstown IN 46148",
    "addr:housenumber":"1906",
    "addr:postcode":"46148",
    "addr:street":"W 1000 N",
    "iso:country":"US",
    "sg:address":"1906 W 1000 N",
    "sg:city":"Knightstown",
    "sg:classifiers":[
        {
            "category":"Building & Trades",
            "subcategory":"Construction",
            "type":"Services"
        }
    ],
    "sg:phone":"+1 765 345 2843",
    "sg:postcode":"46148",
    "sg:province":"IN",
    "sg:tags":[
        "house"
    ],
    "wof:name":"Robert Neal",
    "wof:placetype":"venue"
},
  "geometry": {"coordinates":[-85.47927900000001,39.7578],"type":"Point"}
}