{
  "type": "Feature",
  "properties": {
    "iso:country":"US",
    "sg:address":"2091 E 1400 N",
    "sg:city":"Syracuse",
    "sg:classifiers":[
        {
            "category":"Farming",
            "subcategory":"Farm",
            "type":"Manufacturing & Wholesale Goods"
        }
    ],
    "sg:phone":"+1 574 658 4321",
    "sg:postcode":"46567",
    "sg:province":"IN",
    "wof:name":"Sands Farms",
    "wof:placetype":"venue"
},
  "geometry": {"coordinates":[-85.810874,41.4349],"type":"Point"}
}