{
  "type": "Feature",
  "properties": {
    "addr:full":"107 E Main St Greensburg IN 47240",
    "addr:housenumber":"107",
    "addr:postcode":"47240",
    "addr:street":"E Main St",
    "iso:country":"US",
    "sg:address":"107 E Main St",
    "sg:city":"Greensburg",
    "sg:classifiers":[
        {
            "category":"Shopping",
            "subcategory":"Jewelry",
            "type":"Retail Goods"
        }
    ],
    "sg:phone":"+1 812 663 2144",
    "sg:postcode":"47240",
    "sg:province":"IN",
    "sg:tags":[
        "jeweler"
    ],
    "wof:name":"Stephenson Jewelry",
    "wof:placetype":"venue"
},
  "geometry": {"coordinates":[-85.484145,39.336493],"type":"Point"}
}