{
  "type": "Feature",
  "properties": {
    "iso:country":"US",
    "sg:address":"3835 S 800 W",
    "sg:city":"Tipton",
    "sg:classifiers":[
        {
            "category":"Arts & Performance",
            "subcategory":"Theater",
            "type":"Entertainment"
        }
    ],
    "sg:phone":"+1 765 963 3988",
    "sg:postcode":"46072",
    "sg:province":"IN",
    "sg:tags":[
        "musician"
    ],
    "wof:name":"Eternals Inc",
    "wof:placetype":"venue"
},
  "geometry": {"coordinates":[-86.16554600000001,40.247915],"type":"Point"}
}