{
  "type": "Feature",
  "properties": {
    "addr:full":"1108 W Main St Madison IN 47250",
    "addr:housenumber":"1108",
    "addr:postcode":"47250",
    "addr:street":"W Main St",
    "iso:country":"US",
    "sg:address":"1108 W Main St",
    "sg:city":"Madison",
    "sg:classifiers":[
        {
            "category":"Building & Trades",
            "subcategory":"Construction",
            "type":"Services"
        }
    ],
    "sg:phone":"+1 812 265 6861",
    "sg:postcode":"47250",
    "sg:province":"IN",
    "sg:tags":[
        "contractor"
    ],
    "wof:name":"Madison Iron Works",
    "wof:placetype":"venue"
},
  "geometry": {"coordinates":[-85.40150199999999,38.740351],"type":"Point"}
}