{
  "type": "Feature",
  "properties": {
    "addr:full":"105 N Main St Bicknell IN 47512",
    "addr:housenumber":"105",
    "addr:postcode":"47512",
    "addr:street":"N Main St",
    "iso:country":"US",
    "sg:address":"105 N Main St",
    "sg:city":"Bicknell",
    "sg:classifiers":[
        {
            "category":"Restaurant",
            "type":"Food & Drink"
        }
    ],
    "sg:phone":"+1 812 735 0048",
    "sg:postcode":"47512",
    "sg:province":"IN",
    "wof:name":"Little Town Pizza",
    "wof:placetype":"venue"
},
  "geometry": {"coordinates":[-87.30730699999999,38.773335],"type":"Point"}
}