{
  "type": "Feature",
  "properties": {
    "addr:full":"5620 Coventry Ln Fort Wayne IN 46804",
    "addr:housenumber":"5620",
    "addr:postcode":"46804",
    "addr:street":"Coventry Ln",
    "iso:country":"US",
    "sg:address":"5620 Coventry Ln",
    "sg:city":"Fort Wayne",
    "sg:classifiers":[
        {
            "category":"Professional",
            "subcategory":"Engineering",
            "type":"Services"
        }
    ],
    "sg:phone":"+1 260 435 1414",
    "sg:postcode":"46804",
    "sg:province":"IN",
    "sg:tags":[
        "engineer"
    ],
    "wof:name":"Gove Associates Inc",
    "wof:placetype":"venue"
},
  "geometry": {"coordinates":[-85.25781000000001,41.036037],"type":"Point"}
}