{
  "type": "Feature",
  "properties": {
    "iso:country":"US",
    "sg:address":"630 Eastern Blvd",
    "sg:city":"Clarksville",
    "sg:classifiers":[
        {
            "category":"Health Services",
            "subcategory":"Doctor",
            "type":"Services"
        }
    ],
    "sg:phone":"+1 812 288 6068",
    "sg:postcode":"47129",
    "sg:province":"IN",
    "sg:tags":[
        "physician",
        "surgeon"
    ],
    "wof:name":"Rukhsana I Rahman MD",
    "wof:placetype":"venue"
},
  "geometry": {"coordinates":[-85.762023,38.299502],"type":"Point"}
}