{
  "type": "Feature",
  "properties": {
    "iso:country":"US",
    "sg:address":"728 S Morgantown Rd",
    "sg:city":"Greenwood",
    "sg:classifiers":[
        {
            "category":"Building & Trades",
            "subcategory":"Plumbing",
            "type":"Services"
        }
    ],
    "sg:phone":"+1 317 881 0418",
    "sg:postcode":"46143",
    "sg:province":"IN",
    "sg:tags":[
        "heating",
        "contractor"
    ],
    "wof:name":"Phelps Heating & Air Cond",
    "wof:placetype":"venue"
},
  "geometry": {"coordinates":[-86.197292,39.604485],"type":"Point"}
}