{
  "type": "Feature",
  "properties": {
    "iso:country":"US",
    "sg:address":"9229 Delegates Row",
    "sg:city":"Indianapolis",
    "sg:classifiers":[
        {
            "category":"Professional",
            "subcategory":"Lawyer & Legal Services",
            "type":"Services"
        }
    ],
    "sg:phone":"+1 317 848 1000",
    "sg:postcode":"46240",
    "sg:province":"IN",
    "sg:tags":[
        "attorney"
    ],
    "wof:name":"Safrin & Assoc",
    "wof:placetype":"venue"
},
  "geometry": {"coordinates":[-86.099103,39.921649],"type":"Point"}
}