{
  "type": "Feature",
  "properties": {
    "iso:country":"US",
    "sg:address":"1024 Main St",
    "sg:city":"Rochester",
    "sg:classifiers":[
        {
            "category":"Wholesale",
            "subcategory":"Electrical",
            "type":"Manufacturing & Wholesale Goods"
        }
    ],
    "sg:phone":"+1 574 223 3938",
    "sg:postcode":"46975",
    "sg:province":"IN",
    "sg:tags":[
        "operated",
        "telephone",
        "card"
    ],
    "wof:name":"Telaleasing Enterprises Inc",
    "wof:placetype":"venue"
},
  "geometry": {"coordinates":[-86.216257,41.063598],"type":"Point"}
}