{
  "type": "Feature",
  "properties": {
    "iso:country":"US",
    "sg:address":"111 N Buckeye St",
    "sg:city":"Osgood",
    "sg:classifiers":[
        {
            "category":"Shopping",
            "subcategory":"Pharmacy",
            "type":"Retail Goods"
        }
    ],
    "sg:phone":"+1 812 689 4748",
    "sg:postcode":"47037",
    "sg:province":"IN",
    "wof:name":"G A Triplett & Son",
    "wof:placetype":"venue"
},
  "geometry": {"coordinates":[-85.29167,39.129674],"type":"Point"}
}