{
  "type": "Feature",
  "properties": {
    "iso:country":"US",
    "sg:address":"6937 Daneby Cir",
    "sg:city":"Indianapolis",
    "sg:classifiers":[
        {
            "category":"Social Services",
            "subcategory":"Child Care",
            "type":"Services"
        }
    ],
    "sg:phone":"+1 317 845 5267",
    "sg:postcode":"46220",
    "sg:province":"IN",
    "sg:tags":[
        "day"
    ],
    "wof:name":"Carolyn Mueller",
    "wof:placetype":"venue"
},
  "geometry": {"coordinates":[-86.056228,39.881618],"type":"Point"}
}