{
  "type": "Feature",
  "properties": {
    "addr:full":"6910 Lakeknoll Dr Indianapolis IN 46220",
    "addr:housenumber":"6910",
    "addr:postcode":"46220",
    "addr:street":"Lakeknoll Dr",
    "iso:country":"US",
    "sg:address":"6910 Lakeknoll Dr",
    "sg:city":"Indianapolis",
    "sg:classifiers":[
        {
            "category":"Wholesale",
            "subcategory":"Durable Goods & Equipment",
            "type":"Manufacturing & Wholesale Goods"
        }
    ],
    "sg:phone":"+1 317 596 8050",
    "sg:postcode":"46220",
    "sg:province":"IN",
    "wof:name":"Advance Tanning Supply",
    "wof:placetype":"venue"
},
  "geometry": {"coordinates":[-86.065718,39.881803],"type":"Point"}
}