{
  "type": "Feature",
  "properties": {
    "iso:country":"US",
    "sg:address":"902 W New York St",
    "sg:city":"Indianapolis",
    "sg:classifiers":[
        {
            "category":"Travel",
            "subcategory":"Hotels & Motels",
            "type":"Entertainment"
        },
        {
            "category":"Retail",
            "subcategory":"Event Space",
            "type":"Services"
        },
        {
            "category":"Conference Center",
            "type":"Public Place"
        }
    ],
    "sg:phone":"+1 317 269 9000",
    "sg:postcode":"46202",
    "sg:province":"IN",
    "sg:tags":[
        "facility",
        "wedding",
        "hall",
        "location",
        "reception",
        "convention",
        "banquet"
    ],
    "wof:name":"University Place Conference Center & Hotel At IUPUI",
    "wof:placetype":"venue"
},
  "geometry": {"coordinates":[-86.174367,39.771703],"type":"Point"}
}