{
  "type": "Feature",
  "properties": {
    "iso:country":"US",
    "sg:address":"2341 Dieffenbach Rd",
    "sg:city":"Evansville",
    "sg:classifiers":[
        {
            "category":"Building & Trades",
            "subcategory":"Construction",
            "type":"Services"
        }
    ],
    "sg:phone":"+1 812 423 7230",
    "sg:postcode":"47720",
    "sg:province":"IN",
    "sg:tags":[
        "house"
    ],
    "wof:name":"Jdh Building & REM",
    "wof:placetype":"venue"
},
  "geometry": {"coordinates":[-87.65252099999999,38.00182],"type":"Point"}
}