{
  "type": "Feature",
  "properties": {
    "iso:country":"US",
    "sg:address":"2430 Volkman Rd",
    "sg:city":"Evansville",
    "sg:classifiers":[
        {
            "category":"Building & Trades",
            "subcategory":"Construction",
            "type":"Services"
        }
    ],
    "sg:phone":"+1 812 867 2211",
    "sg:postcode":"47725",
    "sg:province":"IN",
    "sg:tags":[
        "house"
    ],
    "wof:name":"Mooneys Remodeling",
    "wof:placetype":"venue"
},
  "geometry": {"coordinates":[-87.512986,38.144185],"type":"Point"}
}