{
  "type": "Feature",
  "properties": {
    "addr:full":"4705 W 71st St Indianapolis IN 46268",
    "addr:housenumber":"4705",
    "addr:postcode":"46268",
    "addr:street":"W 71St St",
    "iso:country":"US",
    "sg:address":"4705 W 71st St",
    "sg:city":"Indianapolis",
    "sg:classifiers":[
        {
            "category":"Insurance",
            "subcategory":"Insurance Agent",
            "type":"Services"
        },
        {
            "category":"Insurance",
            "subcategory":"Hazard Insurance",
            "type":"Services"
        },
        {
            "category":"Insurance",
            "subcategory":"Title Insurance",
            "type":"Services"
        },
        {
            "category":"Insurance",
            "subcategory":"Life Insurance",
            "type":"Services"
        }
    ],
    "sg:phone":"+1 317 290 9200",
    "sg:postcode":"46268",
    "sg:province":"IN",
    "sg:tags":[
        "business",
        "auto",
        "commercial",
        "homeowner",
        "motorcycle",
        "renter"
    ],
    "wof:name":"Allstate Insurance Company - Donald Oldham",
    "wof:placetype":"venue"
},
  "geometry": {"coordinates":[-86.240094,39.882351],"type":"Point"}
}