{
  "type": "Feature",
  "properties": {
    "iso:country":"US",
    "sg:address":"30309 Britt Ave",
    "sg:city":"Elkhart",
    "sg:classifiers":[
        {
            "category":"Professional",
            "subcategory":"Management & Consulting",
            "type":"Services"
        }
    ],
    "sg:phone":"+1 574 674 9698",
    "sg:postcode":"46514",
    "sg:province":"IN",
    "sg:tags":[
        "business"
    ],
    "wof:name":"Pamela Peacock",
    "wof:placetype":"venue"
},
  "geometry": {"coordinates":[-86.050239,41.68659],"type":"Point"}
}