{
  "type": "Feature",
  "properties": {
    "iso:country":"US",
    "sg:address":"3837 S Lafountain St",
    "sg:city":"Kokomo",
    "sg:classifiers":[
        {
            "category":"Personal",
            "subcategory":"Beauty Salon",
            "type":"Services"
        }
    ],
    "sg:phone":"+1 765 453 4800",
    "sg:postcode":"46902",
    "sg:province":"IN",
    "wof:name":"New Catalina",
    "wof:placetype":"venue"
},
  "geometry": {"coordinates":[-86.12718700000001,40.443046],"type":"Point"}
}