{
  "type": "Feature",
  "properties": {
    "iso:country":"US",
    "sg:address":"105 N Division St",
    "sg:city":"Cayuga",
    "sg:classifiers":[
        {
            "category":"Autos & Motor Vehicles",
            "subcategory":"Automobile Sales",
            "type":"Retail Goods"
        }
    ],
    "sg:phone":"+1 765 492 3313",
    "sg:postcode":"47928",
    "sg:province":"IN",
    "sg:tags":[
        "car",
        "dealer"
    ],
    "sg:website":"www.clarkchevy.com",
    "wof:name":"Clark Chevrolet Sales Inc",
    "wof:placetype":"venue"
},
  "geometry": {"coordinates":[-87.461341,39.950401],"type":"Point"}
}