{
  "type": "Feature",
  "properties": {
    "iso:country":"US",
    "sg:address":"1643 Beech Dr",
    "sg:city":"Crown Point",
    "sg:classifiers":[
        {
            "category":"Building & Trades",
            "subcategory":"Construction",
            "type":"Services"
        }
    ],
    "sg:phone":"+1 219 661 9939",
    "sg:postcode":"46307",
    "sg:province":"IN",
    "sg:tags":[
        "concrete",
        "contractor"
    ],
    "wof:name":"Concepts In Concrete",
    "wof:placetype":"venue"
},
  "geometry": {"coordinates":[-87.34234600000001,41.418644],"type":"Point"}
}