{
  "type": "Feature",
  "properties": {
    "iso:country":"US",
    "sg:address":"106 S Main St",
    "sg:city":"Otterbein",
    "sg:classifiers":[
        {
            "category":"Recreation",
            "type":"Entertainment"
        }
    ],
    "sg:phone":"+1 765 583 4997",
    "sg:postcode":"47970",
    "sg:province":"IN",
    "sg:tags":[
        "ticket"
    ],
    "wof:name":"T One Tickets",
    "wof:placetype":"venue"
},
  "geometry": {"coordinates":[-87.096241,40.488455],"type":"Point"}
}