{
  "type": "Feature",
  "properties": {
    "iso:country":"US",
    "sg:address":"926 W 17th St",
    "sg:city":"Bloomington",
    "sg:classifiers":[
        {
            "category":"Retail",
            "subcategory":"Repair Shop",
            "type":"Services"
        }
    ],
    "sg:phone":"+1 812 332 1682",
    "sg:postcode":"47404",
    "sg:province":"IN",
    "sg:tags":[
        "equipment"
    ],
    "wof:name":"Gooldy & Sons Inc",
    "wof:placetype":"venue"
},
  "geometry": {"coordinates":[-86.546661,39.179119],"type":"Point"}
}