{
  "type": "Feature",
  "properties": {
    "addr:full":"101 W Ohio St Indianapolis IN 46204",
    "addr:housenumber":"101",
    "addr:postcode":"46204",
    "addr:street":"W Ohio St",
    "iso:country":"US",
    "sg:address":"101 W Ohio St",
    "sg:city":"Indianapolis",
    "sg:classifiers":[
        {
            "category":"Manufacturing",
            "subcategory":"Buildings",
            "type":"Manufacturing & Wholesale Goods"
        },
        {
            "category":"Building & Trades",
            "subcategory":"Construction",
            "type":"Services"
        }
    ],
    "sg:phone":"+1 317 951 1500",
    "sg:postcode":"46204",
    "sg:province":"IN",
    "sg:tags":[
        "management",
        "builder",
        "contractor",
        "industrial",
        "contractors-commercial",
        "home"
    ],
    "wof:name":"Ketra Construction",
    "wof:placetype":"venue"
},
  "geometry": {"coordinates":[-86.15979799999999,39.769951],"type":"Point"}
}