{
  "type": "Feature",
  "properties": {
    "iso:country":"US",
    "sg:address":"1198 S 450 E",
    "sg:city":"Shelbyville",
    "sg:phone":"+1 317 398 6080",
    "sg:postcode":"46176",
    "sg:province":"IN",
    "sg:tags":[
        "farm",
        "corn",
        "soybean"
    ],
    "wof:name":"Walter Schwegman",
    "wof:placetype":"venue"
},
  "geometry": {"coordinates":[-85.694052,39.507963],"type":"Point"}
}