{
  "type": "Feature",
  "properties": {
    "iso:country":"US",
    "sg:address":"9587 Pekin Rd",
    "sg:city":"Greenville",
    "sg:classifiers":[
        {
            "category":"Professional",
            "type":"Services"
        }
    ],
    "sg:phone":"+1 812 923 7767",
    "sg:postcode":"47124",
    "sg:province":"IN",
    "wof:name":"Con National Services",
    "wof:placetype":"venue"
},
  "geometry": {"coordinates":[-85.989272,38.407702],"type":"Point"}
}