{
  "type": "Feature",
  "properties": {
    "iso:country":"US",
    "sg:address":"5271 Eastwick Dr",
    "sg:city":"Fort Wayne",
    "sg:classifiers":[
        {
            "category":"Real Estate",
            "subcategory":"Real Estate Operator",
            "type":"Services"
        }
    ],
    "sg:phone":"+1 260 483 6651",
    "sg:postcode":"46815",
    "sg:province":"IN",
    "sg:tags":[
        "apartment"
    ],
    "wof:name":"Summit Ridge Apartments",
    "wof:placetype":"venue"
},
  "geometry": {"coordinates":[-85.07421100000001,41.101096],"type":"Point"}
}