{
  "type": "Feature",
  "properties": {
    "iso:country":"US",
    "sg:address":"1114 S Brady St",
    "sg:city":"Attica",
    "sg:classifiers":[
        {
            "category":"Real Estate",
            "subcategory":"Real Estate Agent",
            "type":"Services"
        }
    ],
    "sg:phone":"+1 765 764 4685",
    "sg:postcode":"47918",
    "sg:province":"IN",
    "wof:name":"Baldwin Real Estate & Tax Svc",
    "wof:placetype":"venue"
},
  "geometry": {"coordinates":[-87.252929,40.282442],"type":"Point"}
}