{
  "type": "Feature",
  "properties": {
    "iso:country":"US",
    "sg:address":"2353 Winthrop Ave",
    "sg:city":"Indianapolis",
    "sg:classifiers":[
        {
            "category":"Organizations",
            "subcategory":"Non-profit Organization",
            "type":"Services"
        }
    ],
    "sg:phone":"+1 317 925 0087",
    "sg:postcode":"46205",
    "sg:province":"IN",
    "sg:tags":[
        "social"
    ],
    "wof:name":"Community Empowerment",
    "wof:placetype":"venue"
},
  "geometry": {"coordinates":[-86.140629,39.800328],"type":"Point"}
}