{
  "type": "Feature",
  "properties": {
    "iso:country":"US",
    "sg:address":"20 W 37th Ave",
    "sg:city":"Hobart",
    "sg:classifiers":[
        {
            "category":"Organizations",
            "subcategory":"Professional Association",
            "type":"Services"
        }
    ],
    "sg:phone":"+1 219 962 5728",
    "sg:postcode":"46342",
    "sg:province":"IN",
    "wof:name":"Hobart Eagles FOE 2498",
    "wof:placetype":"venue"
},
  "geometry": {"coordinates":[-87.277563,41.551067],"type":"Point"}
}