{
  "type": "Feature",
  "properties": {
    "iso:country":"US",
    "sg:address":"515 N Railroad St E",
    "sg:city":"Monticello",
    "sg:classifiers":[
        {
            "category":"Building & Trades",
            "subcategory":"Construction",
            "type":"Services"
        }
    ],
    "sg:phone":"+1 574 583 7033",
    "sg:postcode":"47960",
    "sg:province":"IN",
    "sg:tags":[
        "marking",
        "maintenance",
        "parking"
    ],
    "wof:name":"Street Dept Garage",
    "wof:placetype":"venue"
},
  "geometry": {"coordinates":[-86.764566,40.751001],"type":"Point"}
}