{
  "type": "Feature",
  "properties": {
    "iso:country":"US",
    "sg:address":"1515 E Tipton St",
    "sg:city":"Seymour",
    "sg:classifiers":[
        {
            "category":"Restaurant",
            "type":"Food & Drink"
        }
    ],
    "sg:menulink":"http://www.allmenus.com/in/jackson/119971-subway/menu/",
    "sg:phone":"+1 812 523 8106",
    "sg:postcode":"47274",
    "sg:province":"IN",
    "sg:tags":[
        "american",
        "sandwich"
    ],
    "wof:name":"Subway",
    "wof:placetype":"venue"
},
  "geometry": {"coordinates":[-85.866736,38.958126],"type":"Point"}
}