{
  "type": "Feature",
  "properties": {
    "iso:country":"US",
    "sg:address":"18638 Big Cynthiana Rd",
    "sg:city":"Haubstadt",
    "sg:classifiers":[
        {
            "category":"Retail",
            "subcategory":"Repair Shop",
            "type":"Services"
        }
    ],
    "sg:phone":"+1 812 963 6686",
    "sg:postcode":"47639",
    "sg:province":"IN",
    "wof:name":"Gentrys Repair",
    "wof:placetype":"venue"
},
  "geometry": {"coordinates":[-87.67154,38.148769],"type":"Point"}
}