{
  "type": "Feature",
  "properties": {
    "iso:country":"US",
    "sg:address":"311 W Madison St",
    "sg:city":"Goshen",
    "sg:classifiers":[
        {
            "category":"Government",
            "subcategory":"Office",
            "type":"Public Place"
        }
    ],
    "sg:phone":"+1 574 533 9857",
    "sg:postcode":"46526",
    "sg:province":"IN",
    "sg:tags":[
        "village"
    ],
    "wof:name":"Goshen Ordinance Administrator",
    "wof:placetype":"venue"
},
  "geometry": {"coordinates":[-85.836956,41.582407],"type":"Point"}
}