{
  "type": "Feature",
  "properties": {
    "iso:country":"US",
    "sg:address":"105 S Front St",
    "sg:city":"Henryville",
    "sg:classifiers":[
        {
            "category":"Insurance",
            "subcategory":"Insurance Agent",
            "type":"Services"
        }
    ],
    "sg:phone":"+1 812 294 1338",
    "sg:postcode":"47126",
    "sg:province":"IN",
    "wof:name":"Tom Murphy Insurance Inc",
    "wof:placetype":"venue"
},
  "geometry": {"coordinates":[-85.766333,38.54088],"type":"Point"}
}