{
  "type": "Feature",
  "properties": {
    "iso:country":"US",
    "sg:address":"2202 Fair Oaks Dr",
    "sg:city":"Indianapolis",
    "sg:classifiers":[
        {
            "category":"Real Estate",
            "subcategory":"Real Estate Operator",
            "type":"Services"
        }
    ],
    "sg:phone":"+1 317 241 9341",
    "sg:postcode":"46224",
    "sg:province":"IN",
    "sg:tags":[
        "apartment"
    ],
    "sg:website":"www.apartments.com",
    "wof:name":"Coppertree Apartments",
    "wof:placetype":"venue"
},
  "geometry": {"coordinates":[-86.253416,39.796912],"type":"Point"}
}