{
  "type": "Feature",
  "properties": {
    "addr:full":"4053 W Joliet Rd Laporte IN 46350",
    "addr:housenumber":"4053",
    "addr:postcode":"46350",
    "addr:street":"W Joliet Rd",
    "iso:country":"US",
    "sg:address":"4053 W Joliet Rd",
    "sg:city":"Laporte",
    "sg:classifiers":[
        {
            "category":"Building & Trades",
            "subcategory":"Construction",
            "type":"Services"
        }
    ],
    "sg:phone":"+1 219 324 9310",
    "sg:postcode":"46350",
    "sg:province":"IN",
    "sg:tags":[
        "dry wall",
        "contractor"
    ],
    "wof:name":"K's Drywall",
    "wof:placetype":"venue"
},
  "geometry": {"coordinates":[-86.78089300000001,41.572139],"type":"Point"}
}