{
  "type": "Feature",
  "properties": {
    "iso:country":"US",
    "sg:address":"3516 N 650 E",
    "sg:city":"Rochester",
    "sg:classifiers":[
        {
            "category":"Organizations",
            "subcategory":"Religious Organization",
            "type":"Services"
        }
    ],
    "sg:phone":"+1 574 223 6267",
    "sg:postcode":"46975",
    "sg:province":"IN",
    "wof:name":"Bethlehem Baptist Church",
    "wof:placetype":"venue"
},
  "geometry": {"coordinates":[-86.122298,41.101901],"type":"Point"}
}