{
  "type": "Feature",
  "properties": {
    "iso:country":"US",
    "sg:address":"3754 US Hwy 231 N",
    "sg:city":"Crawfordsville",
    "sg:classifiers":[
        {
            "category":"Home & Garden",
            "subcategory":"Garden Supply",
            "type":"Retail Goods"
        }
    ],
    "sg:phone":"+1 765 362 6300",
    "sg:postcode":"47933",
    "sg:province":"IN",
    "sg:tags":[
        "nurseryman"
    ],
    "wof:name":"Evergreen Nursery & Landscape",
    "wof:placetype":"venue"
},
  "geometry": {"coordinates":[-86.904004,40.095435],"type":"Point"}
}