{
  "type": "Feature",
  "properties": {
    "addr:full":"643 Ironwood Dr Lowell IN 46356",
    "addr:housenumber":"643",
    "addr:postcode":"46356",
    "addr:street":"Ironwood Dr",
    "iso:country":"US",
    "sg:address":"643 Ironwood Dr",
    "sg:city":"Lowell",
    "sg:classifiers":[
        {
            "category":"Professional",
            "subcategory":"Computer Services",
            "type":"Services"
        }
    ],
    "sg:phone":"+1 219 696 9362",
    "sg:postcode":"46356",
    "sg:province":"IN",
    "wof:name":"Anything Inc",
    "wof:placetype":"venue"
},
  "geometry": {"coordinates":[-87.40859500000001,41.280122],"type":"Point"}
}