{
  "type": "Feature",
  "properties": {
    "iso:country":"US",
    "sg:address":"641 Cleveland St",
    "sg:city":"Tipton",
    "sg:classifiers":[
        {
            "category":"Manufacturing",
            "subcategory":"Tools & Machinery",
            "type":"Manufacturing & Wholesale Goods"
        }
    ],
    "sg:phone":"+1 765 675 8841",
    "sg:postcode":"46072",
    "sg:province":"IN",
    "sg:tags":[
        "turbine"
    ],
    "wof:name":"Acra-Line Products Inc",
    "wof:placetype":"venue"
},
  "geometry": {"coordinates":[-86.034181,40.291455],"type":"Point"}
}