{
  "type": "Feature",
  "properties": {
    "iso:country":"US",
    "sg:address":"2100 National Rd W",
    "sg:city":"Richmond",
    "sg:classifiers":[
        {
            "category":"Wholesale",
            "subcategory":"Farm Supplies",
            "type":"Manufacturing & Wholesale Goods"
        }
    ],
    "sg:phone":"+1 765 966 7785",
    "sg:postcode":"47374",
    "sg:province":"IN",
    "wof:name":"Orscheln Farm & Home",
    "wof:placetype":"venue"
},
  "geometry": {"coordinates":[-84.930814,39.824283],"type":"Point"}
}