{
  "type": "Feature",
  "properties": {
    "iso:country":"US",
    "sg:address":"3715 Columbus Ave",
    "sg:city":"Anderson",
    "sg:classifiers":[
        {
            "category":"Social Services",
            "subcategory":"Child Care",
            "type":"Services"
        }
    ],
    "sg:phone":"+1 765 642 8647",
    "sg:postcode":"46013",
    "sg:province":"IN",
    "wof:name":"Apple Critters Child Care",
    "wof:placetype":"venue"
},
  "geometry": {"coordinates":[-85.667055,40.076612],"type":"Point"}
}