{
  "type": "Feature",
  "properties": {
    "iso:country":"US",
    "sg:address":"225 N 2nd St",
    "sg:city":"Vincennes",
    "sg:classifiers":[
        {
            "category":"Health Services",
            "subcategory":"Doctor",
            "type":"Services"
        }
    ],
    "sg:phone":"+1 812 882 2660",
    "sg:postcode":"47591",
    "sg:province":"IN",
    "sg:tags":[
        "physician",
        "surgeon"
    ],
    "wof:name":"Donald L Snider Inc",
    "wof:placetype":"venue"
},
  "geometry": {"coordinates":[-87.529748,38.681229],"type":"Point"}
}