{
  "type": "Feature",
  "properties": {
    "iso:country":"US",
    "sg:address":"248 12th St",
    "sg:city":"Tell City",
    "sg:classifiers":[
        {
            "category":"Autos & Motor Vehicles",
            "subcategory":"Automobile Sales",
            "type":"Retail Goods"
        }
    ],
    "sg:phone":"+1 812 547 0084",
    "sg:postcode":"47586",
    "sg:province":"IN",
    "sg:tags":[
        "car",
        "dealer"
    ],
    "wof:name":"Auto Solutions",
    "wof:placetype":"venue"
},
  "geometry": {"coordinates":[-86.764498,37.944636],"type":"Point"}
}