{
  "type": "Feature",
  "properties": {
    "addr:full":"3010 S Main St Liberty Center IN 46766",
    "addr:housenumber":"3010",
    "addr:postcode":"46766",
    "addr:street":"S Main St",
    "iso:country":"US",
    "sg:address":"3010 S Main St",
    "sg:city":"Liberty Center",
    "sg:classifiers":[
        {
            "category":"Government",
            "subcategory":"Post Office",
            "type":"Public Place"
        }
    ],
    "sg:phone":"+1 260 694 6500",
    "sg:postcode":"46766",
    "sg:province":"IN",
    "wof:name":"US Post Office",
    "wof:placetype":"venue"
},
  "geometry": {"coordinates":[-85.279141,40.69747],"type":"Point"}
}