{
  "type": "Feature",
  "properties": {
    "iso:country":"US",
    "sg:address":"431 Pine Lake Ave",
    "sg:city":"Laporte",
    "sg:classifiers":[
        {
            "category":"Shopping",
            "subcategory":"Clothing, Apparel, & Fashions",
            "type":"Retail Goods"
        }
    ],
    "sg:phone":"+1 219 362 4321",
    "sg:postcode":"46350",
    "sg:province":"IN",
    "sg:tags":[
        "theatrical",
        "costume"
    ],
    "sg:website":"www.deathstudios.com",
    "wof:name":"Death Studios",
    "wof:placetype":"venue"
},
  "geometry": {"coordinates":[-86.738016,41.621235],"type":"Point"}
}