{
  "type": "Feature",
  "properties": {
    "addr:full":"288 W Northwood Ave Jasper IN 47546",
    "addr:housenumber":"288",
    "addr:postcode":"47546",
    "addr:street":"W Northwood Ave",
    "iso:country":"US",
    "sg:address":"288 W Northwood Ave",
    "sg:city":"Jasper",
    "sg:classifiers":[
        {
            "category":"Health Services",
            "subcategory":"Doctor",
            "type":"Services"
        }
    ],
    "sg:phone":"+1 812 482 1855",
    "sg:postcode":"47546",
    "sg:province":"IN",
    "sg:tags":[
        "dentist"
    ],
    "wof:name":"Wilson & Wilson",
    "wof:placetype":"venue"
},
  "geometry": {"coordinates":[-86.94069,38.416086],"type":"Point"}
}