{
  "type": "Feature",
  "properties": {
    "iso:country":"US",
    "sg:address":"8045 Windham Lake Dr",
    "sg:city":"Indianapolis",
    "sg:classifiers":[
        {
            "category":"Personal",
            "subcategory":"Beauty Salon",
            "type":"Services"
        }
    ],
    "sg:phone":"+1 317 280 4639",
    "sg:postcode":"46214",
    "sg:province":"IN",
    "sg:tags":[
        "shop"
    ],
    "wof:name":"Indy Cuts Hair Salon",
    "wof:placetype":"venue"
},
  "geometry": {"coordinates":[-86.30261,39.815129],"type":"Point"}
}