{
  "type": "Feature",
  "properties": {
    "iso:country":"US",
    "sg:address":"1531 W Lake St",
    "sg:city":"Warsaw",
    "sg:classifiers":[
        {
            "category":"Autos & Motor Vehicles",
            "subcategory":"Automobile Sales",
            "type":"Retail Goods"
        }
    ],
    "sg:phone":"+1 574 269 5640",
    "sg:postcode":"46580",
    "sg:province":"IN",
    "sg:tags":[
        "car",
        "dealer"
    ],
    "wof:name":"Center Motor Sales",
    "wof:placetype":"venue"
},
  "geometry": {"coordinates":[-85.879696,41.248193],"type":"Point"}
}