{
  "type": "Feature",
  "properties": {
    "iso:country":"US",
    "sg:address":"1108 E Main St",
    "sg:city":"Griffith",
    "sg:classifiers":[
        {
            "category":"Wholesale",
            "subcategory":"Auto Parts",
            "type":"Manufacturing & Wholesale Goods"
        }
    ],
    "sg:phone":"+1 219 922 3694",
    "sg:postcode":"46319",
    "sg:province":"IN",
    "sg:tags":[
        "equipment",
        "truck"
    ],
    "wof:name":"Wachowski & Sons",
    "wof:placetype":"venue"
},
  "geometry": {"coordinates":[-87.413213,41.522718],"type":"Point"}
}