{
  "type": "Feature",
  "properties": {
    "iso:country":"US",
    "sg:address":"2219 Northway Dr",
    "sg:city":"Fort Wayne",
    "sg:classifiers":[
        {
            "category":"Building & Trades",
            "subcategory":"Construction",
            "type":"Services"
        }
    ],
    "sg:phone":"+1 260 637 6630",
    "sg:postcode":"46845",
    "sg:province":"IN",
    "sg:tags":[
        "tile",
        "dealer",
        "contractor"
    ],
    "wof:name":"Dave Kieffer Tile Inc",
    "wof:placetype":"venue"
},
  "geometry": {"coordinates":[-85.104325,41.185198],"type":"Point"}
}