{
  "type": "Feature",
  "properties": {
    "iso:country":"US",
    "sg:address":"1806 Mayflower Pl",
    "sg:city":"Goshen",
    "sg:classifiers":[
        {
            "category":"Health Services",
            "subcategory":"Doctor",
            "type":"Services"
        }
    ],
    "sg:phone":"+1 574 535 2620",
    "sg:postcode":"46526",
    "sg:province":"IN",
    "sg:tags":[
        "physician",
        "surgeon"
    ],
    "wof:name":"Goshen General Ctr Sleep Study",
    "wof:placetype":"venue"
},
  "geometry": {"coordinates":[-85.832251,41.562474],"type":"Point"}
}