{
  "type": "Feature",
  "properties": {
    "addr:full":"521 Green Blvd Aurora IN 47001",
    "addr:housenumber":"521",
    "addr:postcode":"47001",
    "addr:street":"Green Blvd",
    "iso:country":"US",
    "sg:address":"521 Green Blvd",
    "sg:city":"Aurora",
    "sg:classifiers":[
        {
            "category":"Real Estate",
            "subcategory":"Real Estate Agent",
            "type":"Services"
        }
    ],
    "sg:phone":"+1 812 926 9995",
    "sg:postcode":"47001",
    "sg:province":"IN",
    "wof:name":"Help U Sell",
    "wof:placetype":"venue"
},
  "geometry": {"coordinates":[-84.89710599999999,39.06293],"type":"Point"}
}