{
  "type": "Feature",
  "properties": {
    "iso:country":"US",
    "sg:address":"49 E 3rd St",
    "sg:city":"Peru",
    "sg:classifiers":[
        {
            "category":"Restaurant",
            "type":"Food & Drink"
        }
    ],
    "sg:phone":"+1 765 473 5989",
    "sg:postcode":"46970",
    "sg:province":"IN",
    "sg:tags":[
        "eating"
    ],
    "wof:name":"Bills Grill",
    "wof:placetype":"venue"
},
  "geometry": {"coordinates":[-86.068422,40.752863],"type":"Point"}
}