{
  "type": "Feature",
  "properties": {
    "iso:country":"US",
    "sg:address":"302 N Walnut Street",
    "sg:city":"Bloomington",
    "sg:classifiers":[
        {
            "category":"Bakery",
            "type":"Food & Drink"
        }
    ],
    "sg:phone":"+1 812 339 7771",
    "sg:postcode":"47404",
    "sg:province":"IN",
    "sg:website":"www.insomniacookies.com",
    "wof:name":"Insomnia Cookies",
    "wof:placetype":"venue"
},
  "geometry": {"coordinates":[-86.533599,39.168568],"type":"Point"}
}