{
  "type": "Feature",
  "properties": {
    "iso:country":"US",
    "sg:address":"1870 E 106th St",
    "sg:city":"Carmel",
    "sg:classifiers":[
        {
            "category":"Professional",
            "subcategory":"Art Services",
            "type":"Services"
        }
    ],
    "sg:phone":"+1 317 844 4433",
    "sg:postcode":"46032",
    "sg:province":"IN",
    "sg:tags":[
        "commercial",
        "design"
    ],
    "wof:name":"Willy April Goodman Inc",
    "wof:placetype":"venue"
},
  "geometry": {"coordinates":[-86.125936,39.941629],"type":"Point"}
}