{
  "type": "Feature",
  "properties": {
    "iso:country":"US",
    "sg:address":"4730 E 71st St",
    "sg:city":"Indianapolis",
    "sg:classifiers":[
        {
            "category":"Professional",
            "type":"Services"
        }
    ],
    "sg:phone":"+1 317 290 7867",
    "sg:postcode":"46220",
    "sg:province":"IN",
    "sg:tags":[
        "establishment"
    ],
    "wof:name":"Indy Runners",
    "wof:placetype":"venue"
},
  "geometry": {"coordinates":[-86.09228299999999,39.883271],"type":"Point"}
}