{
  "type": "Feature",
  "properties": {
    "iso:country":"US",
    "sg:address":"1341 S Jackson St",
    "sg:city":"Auburn",
    "sg:classifiers":[
        {
            "category":"Organizations",
            "subcategory":"Religious Organization",
            "type":"Services"
        }
    ],
    "sg:phone":"+1 260 925 0848",
    "sg:postcode":"46706",
    "sg:province":"IN",
    "sg:tags":[
        "church"
    ],
    "wof:name":"Cornerstone World Outreach",
    "wof:placetype":"venue"
},
  "geometry": {"coordinates":[-85.05690800000001,41.358835],"type":"Point"}
}