{
  "type": "Feature",
  "properties": {
    "iso:country":"US",
    "sg:address":"905 W Gump Rd",
    "sg:city":"Fort Wayne",
    "sg:classifiers":[
        {
            "category":"Retail",
            "subcategory":"Veterinary Services",
            "type":"Services"
        }
    ],
    "sg:phone":"+1 260 637 5932",
    "sg:postcode":"46745",
    "sg:province":"IN",
    "sg:tags":[
        "veterinarian"
    ],
    "wof:name":"Veterinary Services",
    "wof:placetype":"venue"
},
  "geometry": {"coordinates":[-85.154874,41.224734],"type":"Point"}
}