{
  "type": "Feature",
  "properties": {
    "iso:country":"US",
    "sg:address":"149 N 36th St",
    "sg:city":"Terre Haute",
    "sg:classifiers":[
        {
            "category":"Building & Trades",
            "subcategory":"Construction",
            "type":"Services"
        }
    ],
    "sg:phone":"+1 812 877 3158",
    "sg:postcode":"47803",
    "sg:province":"IN",
    "sg:tags":[
        "concrete",
        "contractor"
    ],
    "wof:name":"A-1 Akers Contracting",
    "wof:placetype":"venue"
},
  "geometry": {"coordinates":[-87.362483,39.475743],"type":"Point"}
}