{
  "type": "Feature",
  "properties": {
    "iso:country":"US",
    "sg:address":"7259 S State Rd 39",
    "sg:city":"Frankfort",
    "sg:phone":"+1 765 325 2941",
    "sg:postcode":"46041",
    "sg:province":"IN",
    "sg:tags":[
        "farm",
        "corn"
    ],
    "wof:name":"Randy Golden",
    "wof:placetype":"venue"
},
  "geometry": {"coordinates":[-86.48743399999999,40.18082],"type":"Point"}
}