{
  "type": "Feature",
  "properties": {
    "iso:country":"US",
    "sg:address":"2129 Massachusetts Ave",
    "sg:city":"Indianapolis",
    "sg:classifiers":[
        {
            "category":"Wholesale",
            "subcategory":"Medical Equipment & Supplies",
            "type":"Manufacturing & Wholesale Goods"
        }
    ],
    "sg:phone":"+1 317 632 1790",
    "sg:postcode":"46218",
    "sg:province":"IN",
    "sg:tags":[
        "physician",
        "surgeon"
    ],
    "wof:name":"Advacare Systems",
    "wof:placetype":"venue"
},
  "geometry": {"coordinates":[-86.120233,39.791925],"type":"Point"}
}