{
  "type": "Feature",
  "properties": {
    "addr:full":"8400 W State Route 66 Newburgh IN 47630",
    "addr:housenumber":"8400",
    "addr:postcode":"47630",
    "addr:street":"W State Route 66",
    "iso:country":"US",
    "sg:address":"8400 W State Route 66",
    "sg:city":"Newburgh",
    "sg:classifiers":[
        {
            "category":"Autos & Motor Vehicles",
            "subcategory":"Automobile Sales",
            "type":"Retail Goods"
        }
    ],
    "sg:phone":"+1 812 858 1148",
    "sg:postcode":"47630",
    "sg:province":"IN",
    "sg:tags":[
        "car"
    ],
    "sg:website":"www.enterprise.com",
    "wof:name":"Enterprise Rent-A-Car",
    "wof:placetype":"venue"
},
  "geometry": {"coordinates":[-87.402394,37.976739],"type":"Point"}
}