{
  "type": "Feature",
  "properties": {
    "iso:country":"US",
    "sg:address":"2606 E 350 S",
    "sg:city":"Lafayette",
    "sg:classifiers":[
        {
            "category":"Health Services",
            "subcategory":"Health Practitioner",
            "type":"Services"
        }
    ],
    "sg:phone":"+1 765 474 4544",
    "sg:postcode":"47909",
    "sg:province":"IN",
    "sg:tags":[
        "audiologists"
    ],
    "wof:name":"Knecht Audiology",
    "wof:placetype":"venue"
},
  "geometry": {"coordinates":[-86.856173,40.3673],"type":"Point"}
}