{
  "type": "Feature",
  "properties": {
    "iso:country":"US",
    "sg:address":"305 W Washington St",
    "sg:city":"Indianapolis",
    "sg:classifiers":[
        {
            "category":"Restaurant",
            "type":"Food & Drink"
        }
    ],
    "sg:menulink":"http://www.allmenus.com/in/indianapolis/81762-subway/menu/",
    "sg:phone":"+1 317 267 9960",
    "sg:postcode":"46204",
    "sg:province":"IN",
    "sg:tags":[
        "american",
        "sandwich"
    ],
    "wof:name":"Subway",
    "wof:placetype":"venue"
},
  "geometry": {"coordinates":[-86.163624,39.767206],"type":"Point"}
}