{
  "type": "Feature",
  "properties": {
    "addr:full":"437 N Halleck St Demotte IN 46310",
    "addr:housenumber":"437",
    "addr:postcode":"46310",
    "addr:street":"N Halleck St",
    "iso:country":"US",
    "sg:address":"437 N Halleck St",
    "sg:city":"Demotte",
    "sg:classifiers":[
        {
            "category":"Shopping",
            "subcategory":"Used Merchandise",
            "type":"Retail Goods"
        }
    ],
    "sg:phone":"+1 219 987 6145",
    "sg:postcode":"46310",
    "sg:province":"IN",
    "sg:tags":[
        "shop",
        "thrift"
    ],
    "wof:name":"Second Time Around",
    "wof:placetype":"venue"
},
  "geometry": {"coordinates":[-87.198729,41.205396],"type":"Point"}
}