{
  "type": "Feature",
  "properties": {
    "iso:country":"US",
    "sg:address":"7920 Spring Mill Rd",
    "sg:city":"Indianapolis",
    "sg:classifiers":[
        {
            "category":"Professional",
            "subcategory":"Business Services",
            "type":"Services"
        }
    ],
    "sg:phone":"+1 317 257 2406",
    "sg:postcode":"46260",
    "sg:province":"IN",
    "wof:name":"S R 7",
    "wof:placetype":"venue"
},
  "geometry": {"coordinates":[-86.164976,39.898627],"type":"Point"}
}