{
  "type": "Feature",
  "properties": {
    "iso:country":"US",
    "sg:address":"2916 S Anthony Blvd",
    "sg:city":"Fort Wayne",
    "sg:classifiers":[
        {
            "category":"Organizations",
            "subcategory":"Religious Organization",
            "type":"Services"
        }
    ],
    "sg:phone":"+1 260 745 9233",
    "sg:postcode":"46806",
    "sg:province":"IN",
    "sg:tags":[
        "church"
    ],
    "wof:name":"Faith Tabernacle Chr Upper Rm",
    "wof:placetype":"venue"
},
  "geometry": {"coordinates":[-85.11389800000001,41.057863],"type":"Point"}
}