{
  "type": "Feature",
  "properties": {
    "iso:country":"US",
    "sg:address":"5864 W 71st St",
    "sg:city":"Indianapolis",
    "sg:classifiers":[
        {
            "category":"Wholesale",
            "subcategory":"Machinery & Supplies",
            "type":"Manufacturing & Wholesale Goods"
        }
    ],
    "sg:phone":"+1 317 387 8686",
    "sg:postcode":"46278",
    "sg:province":"IN",
    "sg:tags":[
        "equipment",
        "industrial"
    ],
    "wof:name":"S & K Air Power",
    "wof:placetype":"venue"
},
  "geometry": {"coordinates":[-86.265289,39.881694],"type":"Point"}
}