{
  "type": "Feature",
  "properties": {
    "iso:country":"US",
    "sg:address":"1005 E 500 S",
    "sg:city":"Cutler",
    "sg:classifiers":[
        {
            "category":"Building & Trades",
            "subcategory":"Construction",
            "type":"Services"
        }
    ],
    "sg:phone":"+1 765 268 2148",
    "sg:postcode":"46920",
    "sg:province":"IN",
    "sg:tags":[
        "excavating",
        "contractor"
    ],
    "wof:name":"Ronald L Carman",
    "wof:placetype":"venue"
},
  "geometry": {"coordinates":[-86.506086,40.474741],"type":"Point"}
}