{
  "type": "Feature",
  "properties": {
    "iso:country":"US",
    "sg:address":"8484 W Washington St",
    "sg:city":"Indianapolis",
    "sg:classifiers":[
        {
            "category":"Wholesale",
            "subcategory":"Machinery & Supplies",
            "type":"Manufacturing & Wholesale Goods"
        }
    ],
    "sg:phone":"+1 317 227 8720",
    "sg:postcode":"46231",
    "sg:province":"IN",
    "sg:tags":[
        "equipment",
        "printing"
    ],
    "wof:name":"American Pro-Tech Inc",
    "wof:placetype":"venue"
},
  "geometry": {"coordinates":[-86.309926,39.734679],"type":"Point"}
}