{
  "type": "Feature",
  "properties": {
    "iso:country":"US",
    "sg:address":"2506 Willowbrook Pkwy",
    "sg:city":"Indianapolis",
    "sg:classifiers":[
        {
            "category":"Health Services",
            "subcategory":"Hospital",
            "type":"Services"
        }
    ],
    "sg:phone":"+1 317 251 0005",
    "sg:postcode":"46205",
    "sg:province":"IN",
    "sg:tags":[
        "mental"
    ],
    "sg:website":"www.mcmha.org",
    "wof:name":"Marion County Mental Health",
    "wof:placetype":"venue"
},
  "geometry": {"coordinates":[-86.11927,39.842424],"type":"Point"}
}