{
  "type": "Feature",
  "properties": {
    "addr:full":"100 E Main St Fort Wayne IN 46802",
    "addr:housenumber":"100",
    "addr:postcode":"46802",
    "addr:street":"E Main St",
    "iso:country":"US",
    "sg:address":"100 E Main St",
    "sg:city":"Fort Wayne",
    "sg:classifiers":[
        {
            "category":"Government",
            "subcategory":"Office",
            "type":"Public Place"
        }
    ],
    "sg:phone":"+1 260 427 1210",
    "sg:postcode":"46802",
    "sg:province":"IN",
    "sg:tags":[
        "village"
    ],
    "wof:name":"Fort Wayne Communications",
    "wof:placetype":"venue"
},
  "geometry": {"coordinates":[-85.138307,41.080529],"type":"Point"}
}