{
  "type": "Feature",
  "properties": {
    "iso:country":"US",
    "sg:address":"21 S Main St",
    "sg:city":"Fortville",
    "sg:classifiers":[
        {
            "category":"Restaurant",
            "type":"Food & Drink"
        }
    ],
    "sg:phone":"+1 317 485 7988",
    "sg:postcode":"46040",
    "sg:province":"IN",
    "wof:name":"Chinese Restaurant",
    "wof:placetype":"venue"
},
  "geometry": {"coordinates":[-85.849612,39.933926],"type":"Point"}
}