{
  "type": "Feature",
  "properties": {
    "iso:country":"US",
    "sg:address":"7715 US Hwy 136 W",
    "sg:city":"Waynetown",
    "sg:classifiers":[
        {
            "category":"Shopping",
            "subcategory":"Bicycles & Sporting Goods",
            "type":"Retail Goods"
        }
    ],
    "sg:phone":"+1 765 234 1322",
    "sg:postcode":"47990",
    "sg:province":"IN",
    "sg:tags":[
        "equipment",
        "archery",
        "supply"
    ],
    "wof:name":"Outback Archery",
    "wof:placetype":"venue"
},
  "geometry": {"coordinates":[-86.909164,40.042771],"type":"Point"}
}