{
  "type": "Feature",
  "properties": {
    "iso:country":"US",
    "sg:address":"112 N 7th St",
    "sg:city":"Vincennes",
    "sg:classifiers":[
        {
            "category":"Professional",
            "subcategory":"Lawyer & Legal Services",
            "type":"Services"
        }
    ],
    "sg:phone":"+1 812 886 9970",
    "sg:postcode":"47591",
    "sg:province":"IN",
    "sg:tags":[
        "attorney"
    ],
    "wof:name":"Sommer Barnard",
    "wof:placetype":"venue"
},
  "geometry": {"coordinates":[-87.526858,38.677141],"type":"Point"}
}