{
  "type": "Feature",
  "properties": {
    "iso:country":"US",
    "sg:address":"408 S Walnut St",
    "sg:city":"Crawfordsville",
    "sg:classifiers":[
        {
            "category":"Real Estate",
            "subcategory":"Real Estate Operator",
            "type":"Services"
        }
    ],
    "sg:phone":"+1 765 362 4642",
    "sg:postcode":"47933",
    "sg:province":"IN",
    "sg:tags":[
        "apartment"
    ],
    "wof:name":"Campus View Apartments",
    "wof:placetype":"venue"
},
  "geometry": {"coordinates":[-86.902838,40.038191],"type":"Point"}
}