{
  "type": "Feature",
  "properties": {
    "iso:country":"US",
    "sg:address":"400 S Main St",
    "sg:city":"Sheridan",
    "sg:classifiers":[
        {
            "category":"Professional",
            "subcategory":"Advertising",
            "type":"Services"
        }
    ],
    "sg:phone":"+1 317 758 7920",
    "sg:postcode":"46069",
    "sg:province":"IN",
    "sg:tags":[
        "mailing",
        "shipping"
    ],
    "wof:name":"Main Street Power Mail",
    "wof:placetype":"venue"
},
  "geometry": {"coordinates":[-86.22062699999999,40.135262],"type":"Point"}
}