{
  "type": "Feature",
  "properties": {
    "iso:country":"US",
    "sg:address":"36 N 5th St",
    "sg:city":"Vincennes",
    "sg:classifiers":[
        {
            "category":"Professional",
            "subcategory":"Lawyer & Legal Services",
            "type":"Services"
        }
    ],
    "sg:phone":"+1 812 886 9230",
    "sg:postcode":"47591",
    "sg:province":"IN",
    "sg:tags":[
        "attorney"
    ],
    "wof:name":"Feavel Law Offices",
    "wof:placetype":"venue"
},
  "geometry": {"coordinates":[-87.529509,38.677954],"type":"Point"}
}