{
  "type": "Feature",
  "properties": {
    "iso:country":"US",
    "sg:address":"1319 W Mishawaka Ave",
    "sg:city":"South Bend",
    "sg:classifiers":[
        {
            "category":"Home & Garden",
            "subcategory":"Hardware",
            "type":"Retail Goods"
        }
    ],
    "sg:phone":"+1 574 288 5025",
    "sg:postcode":"46615",
    "sg:province":"IN",
    "wof:name":"Builders Store Inc",
    "wof:placetype":"venue"
},
  "geometry": {"coordinates":[-86.229682,41.665918],"type":"Point"}
}