{
  "type": "Feature",
  "properties": {
    "iso:country":"US",
    "sg:address":"2525 S McCullough Pl",
    "sg:city":"West Terre Haute",
    "sg:classifiers":[
        {
            "category":"Building & Trades",
            "subcategory":"Construction",
            "type":"Services"
        }
    ],
    "sg:phone":"+1 812 533 2245",
    "sg:postcode":"47885",
    "sg:province":"IN",
    "sg:tags":[
        "concrete",
        "contractor"
    ],
    "wof:name":"R & M Concrete Inc",
    "wof:placetype":"venue"
},
  "geometry": {"coordinates":[-87.48397,39.435528],"type":"Point"}
}