{
  "type": "Feature",
  "properties": {
    "iso:country":"US",
    "sg:address":"208 Water St",
    "sg:city":"Plymouth",
    "sg:classifiers":[
        {
            "category":"Shopping",
            "subcategory":"Beauty & Cosmetics",
            "type":"Retail Goods"
        }
    ],
    "sg:phone":"+1 574 936 6838",
    "sg:postcode":"46563",
    "sg:province":"IN",
    "sg:tags":[
        "merchandise"
    ],
    "wof:name":"Merle Norman Cosmetics",
    "wof:placetype":"venue"
},
  "geometry": {"coordinates":[-86.307946,41.341771],"type":"Point"}
}