{
  "type": "Feature",
  "properties": {
    "iso:country":"US",
    "sg:address":"104 NW 4th St",
    "sg:city":"Paoli",
    "sg:classifiers":[
        {
            "category":"Retail",
            "subcategory":"Auto Repair",
            "type":"Services"
        }
    ],
    "sg:phone":"+1 812 723 5254",
    "sg:postcode":"47454",
    "sg:province":"IN",
    "sg:tags":[
        "repairing",
        "automobile",
        "general"
    ],
    "wof:name":"G & E Auto Repair",
    "wof:placetype":"venue"
},
  "geometry": {"coordinates":[-86.473663,38.557162],"type":"Point"}
}