{
  "type": "Feature",
  "properties": {
    "addr:full":"1010 W Dewey St Bremen IN 46506",
    "addr:housenumber":"1010",
    "addr:postcode":"46506",
    "addr:street":"W Dewey St",
    "iso:country":"US",
    "sg:address":"1010 W Dewey St",
    "sg:city":"Bremen",
    "sg:classifiers":[
        {
            "category":"Manufacturing",
            "subcategory":"Metals",
            "type":"Manufacturing & Wholesale Goods"
        }
    ],
    "sg:phone":"+1 574 546 3298",
    "sg:postcode":"46506",
    "sg:province":"IN",
    "sg:tags":[
        "plumbing",
        "fixture",
        "supply"
    ],
    "sg:website":"www.maax.com",
    "wof:name":"Maax Midwest",
    "wof:placetype":"venue"
},
  "geometry": {"coordinates":[-86.160482,41.45053],"type":"Point"}
}