{
  "type": "Feature",
  "properties": {
    "iso:country":"US",
    "sg:address":"18 N Main St",
    "sg:city":"Bloomingdale",
    "sg:classifiers":[
        {
            "category":"Manufacturing",
            "subcategory":"Tools & Machinery",
            "type":"Manufacturing & Wholesale Goods"
        }
    ],
    "sg:phone":"+1 765 498 2294",
    "sg:postcode":"47882",
    "sg:province":"IN",
    "sg:tags":[
        "mold",
        "special"
    ],
    "wof:name":"Ark Tool & Engineering",
    "wof:placetype":"venue"
},
  "geometry": {"coordinates":[-87.40710199999999,39.09625],"type":"Point"}
}