{
  "type": "Feature",
  "properties": {
    "iso:country":"US",
    "sg:address":"13469 S Trueblood Pl",
    "sg:city":"Terre Haute",
    "sg:classifiers":[
        {
            "category":"Shopping",
            "subcategory":"News",
            "type":"Retail Goods"
        }
    ],
    "sg:phone":"+1 812 898 2678",
    "sg:postcode":"47802",
    "sg:province":"IN",
    "sg:tags":[
        "magazine"
    ],
    "sg:website":"www.animalfindersguide.com",
    "wof:name":"Animal Finders Guide",
    "wof:placetype":"venue"
},
  "geometry": {"coordinates":[-87.460494,39.302478],"type":"Point"}
}