{
  "type": "Feature",
  "properties": {
    "addr:full":"3447 E Crystal Ave Terre Haute IN 47805",
    "addr:housenumber":"3447",
    "addr:postcode":"47805",
    "addr:street":"E Crystal Ave",
    "iso:country":"US",
    "sg:address":"3447 E Crystal Ave",
    "sg:city":"Terre Haute",
    "sg:classifiers":[
        {
            "category":"Professional",
            "subcategory":"Management & Consulting",
            "type":"Services"
        }
    ],
    "sg:phone":"+1 812 466 1300",
    "sg:postcode":"47805",
    "sg:province":"IN",
    "sg:tags":[
        "business"
    ],
    "wof:name":"Express Communications",
    "wof:placetype":"venue"
},
  "geometry": {"coordinates":[-87.36547299999999,39.542422],"type":"Point"}
}