{
  "type": "Feature",
  "properties": {
    "iso:country":"US",
    "sg:address":"1021 J St",
    "sg:city":"Bedford",
    "sg:classifiers":[
        {
            "category":"Organizations",
            "subcategory":"Community Association",
            "type":"Services"
        }
    ],
    "sg:phone":"+1 812 275 5504",
    "sg:postcode":"47421",
    "sg:province":"IN",
    "sg:tags":[
        "club"
    ],
    "wof:name":"Hideaway Lounge",
    "wof:placetype":"venue"
},
  "geometry": {"coordinates":[-86.48422100000001,38.86666],"type":"Point"}
}