{
  "type": "Feature",
  "properties": {
    "iso:country":"US",
    "sg:address":"330 Preston Dr",
    "sg:city":"South Bend",
    "sg:classifiers":[
        {
            "category":"Building & Trades",
            "subcategory":"Construction",
            "type":"Services"
        }
    ],
    "sg:phone":"+1 574 233 8060",
    "sg:postcode":"46615",
    "sg:province":"IN",
    "sg:tags":[
        "contractor"
    ],
    "wof:name":"Keith Donihue Svc",
    "wof:placetype":"venue"
},
  "geometry": {"coordinates":[-86.201453,41.681715],"type":"Point"}
}