{
  "type": "Feature",
  "properties": {
    "iso:country":"US",
    "sg:address":"970 W Main St",
    "sg:city":"Boonville",
    "sg:classifiers":[
        {
            "category":"Shopping",
            "type":"Retail Goods"
        }
    ],
    "sg:phone":"+1 812 897 9042",
    "sg:postcode":"47601",
    "sg:province":"IN",
    "sg:tags":[
        "merchandise"
    ],
    "wof:name":"Advanced Cellular Inc",
    "wof:placetype":"venue"
},
  "geometry": {"coordinates":[-87.288206,38.048026],"type":"Point"}
}