{
  "type": "Feature",
  "properties": {
    "iso:country":"US",
    "sg:address":"7820 Innovation Blvd",
    "sg:city":"Indianapolis",
    "sg:classifiers":[
        {
            "category":"Professional",
            "subcategory":"Computer Services",
            "type":"Services"
        }
    ],
    "sg:phone":"+1 317 610 8800",
    "sg:postcode":"46278",
    "sg:province":"IN",
    "sg:tags":[
        "information",
        "recovery",
        "processing",
        "system",
        "equipment",
        "data",
        "retrieval"
    ],
    "sg:website":"http://www.digitalinsight.com",
    "wof:name":"Digital Insight Corporation",
    "wof:placetype":"venue"
},
  "geometry": {"coordinates":[-86.26712000000001,39.893219],"type":"Point"}
}