{
  "type": "Feature",
  "properties": {
    "iso:country":"US",
    "sg:address":"4050 N 25th St",
    "sg:city":"Terre Haute",
    "sg:classifiers":[
        {
            "category":"Shopping",
            "subcategory":"Discount & Variety Stores",
            "type":"Retail Goods"
        }
    ],
    "sg:phone":"+1 812 466 5520",
    "sg:postcode":"47805",
    "sg:province":"IN",
    "sg:tags":[
        "department"
    ],
    "wof:name":"Dollar General",
    "wof:placetype":"venue"
},
  "geometry": {"coordinates":[-87.37927000000001,39.515599],"type":"Point"}
}