{
  "type": "Feature",
  "properties": {
    "iso:country":"US",
    "sg:address":"109 N Superior St",
    "sg:city":"Angola",
    "sg:classifiers":[
        {
            "category":"Restaurant",
            "type":"Food & Drink"
        }
    ],
    "sg:phone":"+1 260 665 9053",
    "sg:postcode":"46703",
    "sg:province":"IN",
    "wof:name":"Village Kitchen",
    "wof:placetype":"venue"
},
  "geometry": {"coordinates":[-85.002901,41.635588],"type":"Point"}
}