{
  "type": "Feature",
  "properties": {
    "addr:full":"500 Industrial Park Dr Loogootee IN 47553",
    "addr:housenumber":"500",
    "addr:postcode":"47553",
    "addr:street":"Industrial Park Dr",
    "iso:country":"US",
    "sg:address":"500 Industrial Park Dr",
    "sg:city":"Loogootee",
    "sg:classifiers":[
        {
            "category":"Wholesale",
            "subcategory":"Scrap",
            "type":"Manufacturing & Wholesale Goods"
        }
    ],
    "sg:phone":"+1 812 295 4142",
    "sg:postcode":"47553",
    "sg:province":"IN",
    "sg:tags":[
        "recycling",
        "center"
    ],
    "wof:name":"Martin County Recycling Ctr",
    "wof:placetype":"venue"
},
  "geometry": {"coordinates":[-86.902372,38.681106],"type":"Point"}
}