{
  "type": "Feature",
  "properties": {
    "iso:country":"US",
    "sg:address":"7732 Shannon Lakes Way",
    "sg:city":"Indianapolis",
    "sg:classifiers":[
        {
            "category":"Building & Trades",
            "subcategory":"Landscaping Services",
            "type":"Services"
        }
    ],
    "sg:phone":"+1 317 859 1700",
    "sg:postcode":"46217",
    "sg:province":"IN",
    "wof:name":"Pluntz Lawncare Service",
    "wof:placetype":"venue"
},
  "geometry": {"coordinates":[-86.18291000000001,39.651466],"type":"Point"}
}