{
  "type": "Feature",
  "properties": {
    "iso:country":"US",
    "sg:address":"212 Beechmont Dr",
    "sg:city":"Carmel",
    "sg:classifiers":[
        {
            "category":"Health Services",
            "subcategory":"Chiropractor",
            "type":"Services"
        }
    ],
    "sg:phone":"+1 317 846 2202",
    "sg:postcode":"46032",
    "sg:province":"IN",
    "wof:name":"Ralph K Crawford DC",
    "wof:placetype":"venue"
},
  "geometry": {"coordinates":[-86.116968,39.981109],"type":"Point"}
}