{
  "type": "Feature",
  "properties": {
    "iso:country":"US",
    "sg:address":"808 Madison St",
    "sg:city":"Laporte",
    "sg:classifiers":[
        {
            "category":"Banks & Credit Unions",
            "subcategory":"Bank",
            "type":"Services"
        }
    ],
    "sg:phone":"+1 219 324 7975",
    "sg:postcode":"46350",
    "sg:province":"IN",
    "sg:tags":[
        "loan"
    ],
    "wof:name":"Vintage Financial Inc",
    "wof:placetype":"venue"
},
  "geometry": {"coordinates":[-86.722697,41.609293],"type":"Point"}
}