{
  "type": "Feature",
  "properties": {
    "iso:country":"US",
    "sg:address":"151 Oak St",
    "sg:city":"Terre Haute",
    "sg:classifiers":[
        {
            "category":"Government",
            "subcategory":"Office",
            "type":"Public Place"
        }
    ],
    "sg:phone":"+1 812 462 3365",
    "sg:postcode":"47807",
    "sg:province":"IN",
    "wof:name":"Vigo County Building Inspctn",
    "wof:placetype":"venue"
},
  "geometry": {"coordinates":[-87.414628,39.461319],"type":"Point"}
}