{
  "type": "Feature",
  "properties": {
    "iso:country":"US",
    "sg:address":"1424 E Lincolnway",
    "sg:city":"Laporte",
    "sg:classifiers":[
        {
            "category":"Banks & Credit Unions",
            "subcategory":"Bank",
            "type":"Services"
        }
    ],
    "sg:phone":"+1 219 325 3316",
    "sg:postcode":"46350",
    "sg:province":"IN",
    "sg:tags":[
        "cashing",
        "check"
    ],
    "wof:name":"Check 'n Go",
    "wof:placetype":"venue"
},
  "geometry": {"coordinates":[-86.690539,41.624896],"type":"Point"}
}