{
  "type": "Feature",
  "properties": {
    "iso:country":"US",
    "sg:address":"4601 National Rd E",
    "sg:city":"Richmond",
    "sg:classifiers":[
        {
            "category":"Cinema",
            "subcategory":"Movie Rental",
            "type":"Entertainment"
        }
    ],
    "sg:phone":"+1 765 939 9546",
    "sg:postcode":"47374",
    "sg:province":"IN",
    "sg:tags":[
        "leasing",
        "video",
        "disc",
        "tape"
    ],
    "wof:name":"Hastings Books Music Video",
    "wof:placetype":"venue"
},
  "geometry": {"coordinates":[-84.826616,39.832572],"type":"Point"}
}