{
  "type": "Feature",
  "properties": {
    "iso:country":"US",
    "sg:address":"2920 E 96th St",
    "sg:city":"Indianapolis",
    "sg:classifiers":[
        {
            "category":"Real Estate",
            "subcategory":"Real Estate Services",
            "type":"Services"
        },
        {
            "category":"Building & Trades",
            "subcategory":"Construction",
            "type":"Services"
        }
    ],
    "sg:phone":"+1 317 846 4001",
    "sg:postcode":"46240",
    "sg:province":"IN",
    "sg:tags":[
        "management",
        "property",
        "contractor"
    ],
    "wof:name":"Paragus Property Management Company",
    "wof:placetype":"venue"
},
  "geometry": {"coordinates":[-86.115601,39.9268],"type":"Point"}
}