{
  "type": "Feature",
  "properties": {
    "iso:country":"US",
    "sg:address":"610 N 1st St",
    "sg:city":"Pierceton",
    "sg:classifiers":[
        {
            "category":"Shopping",
            "subcategory":"Gifts & Souvenirs",
            "type":"Retail Goods"
        }
    ],
    "sg:phone":"+1 574 594 5454",
    "sg:postcode":"46562",
    "sg:province":"IN",
    "sg:tags":[
        "collectible"
    ],
    "wof:name":"Turn One Racing Collectibles",
    "wof:placetype":"venue"
},
  "geometry": {"coordinates":[-85.78860899999999,41.31829],"type":"Point"}
}