{
  "type": "Feature",
  "properties": {
    "iso:country":"US",
    "sg:address":"6181 W Holland Rd NE",
    "sg:city":"Holland",
    "sg:classifiers":[
        {
            "category":"Professional",
            "type":"Services"
        }
    ],
    "sg:phone":"+1 812 536 2529",
    "sg:postcode":"47541",
    "sg:province":"IN",
    "wof:name":"Irvin Blemker",
    "wof:placetype":"venue"
},
  "geometry": {"coordinates":[-87.021579,38.251651],"type":"Point"}
}