{
  "type": "Feature",
  "properties": {
    "iso:country":"US",
    "sg:address":"211 N Walnut St",
    "sg:city":"Bloomington",
    "sg:classifiers":[
        {
            "category":"Restaurant",
            "type":"Food & Drink"
        }
    ],
    "sg:menulink":"http://www.allmenus.com/in/bloomington/247568-greeks-pizzeria/menu/",
    "sg:phone":"+1 812 323 0044",
    "sg:postcode":"47404",
    "sg:province":"IN",
    "sg:tags":[
        "pasta",
        "american",
        "sandwich",
        "pizza"
    ],
    "wof:name":"Greek's Pizzeria",
    "wof:placetype":"venue"
},
  "geometry": {"coordinates":[-86.533631,39.167682],"type":"Point"}
}