{
  "type": "Feature",
  "properties": {
    "iso:country":"US",
    "sg:address":"315 W Franklin St",
    "sg:city":"Evansville",
    "sg:classifiers":[
        {
            "category":"Wholesale",
            "subcategory":"Auto Parts",
            "type":"Manufacturing & Wholesale Goods"
        }
    ],
    "sg:phone":"+1 812 425 7057",
    "sg:postcode":"47710",
    "sg:province":"IN",
    "sg:tags":[
        "body",
        "automobile",
        "shop"
    ],
    "wof:name":"Performance Refinish Supl Inc",
    "wof:placetype":"venue"
},
  "geometry": {"coordinates":[-87.569525,37.98031],"type":"Point"}
}