{
  "type": "Feature",
  "properties": {
    "iso:country":"US",
    "sg:address":"2600 S Madison St",
    "sg:city":"Muncie",
    "sg:classifiers":[
        {
            "category":"Personal",
            "subcategory":"Beauty Salon",
            "type":"Services"
        }
    ],
    "sg:phone":"+1 765 281 0525",
    "sg:postcode":"47302",
    "sg:province":"IN",
    "wof:name":"Shaggy & Sheek Beauty Salon",
    "wof:placetype":"venue"
},
  "geometry": {"coordinates":[-85.381653,40.170307],"type":"Point"}
}