{
  "type": "Feature",
  "properties": {
    "iso:country":"US",
    "sg:address":"914 E Tipton St",
    "sg:city":"Seymour",
    "sg:classifiers":[
        {
            "category":"Insurance",
            "subcategory":"Insurance Agent",
            "type":"Services"
        },
        {
            "category":"Insurance",
            "subcategory":"Hazard Insurance",
            "type":"Services"
        },
        {
            "category":"Insurance",
            "subcategory":"Title Insurance",
            "type":"Services"
        },
        {
            "category":"Insurance",
            "subcategory":"Life Insurance",
            "type":"Services"
        }
    ],
    "sg:phone":"+1 812 522 7300",
    "sg:postcode":"47274",
    "sg:province":"IN",
    "sg:tags":[
        "business",
        "auto",
        "commercial",
        "homeowner",
        "motorcycle",
        "renter"
    ],
    "wof:name":"Allstate Insurance Company - Tim Schrink",
    "wof:placetype":"venue"
},
  "geometry": {"coordinates":[-85.875958,38.958143],"type":"Point"}
}