{
  "type": "Feature",
  "properties": {
    "addr:full":"2575 S State Rd 9 Lagrange IN 46761",
    "addr:housenumber":"2575",
    "addr:postcode":"46761",
    "addr:street":"S State Rd 9 Lagrange",
    "iso:country":"US",
    "sg:address":"2575 S State Rd 9",
    "sg:city":"Lagrange",
    "sg:classifiers":[
        {
            "category":"Insurance",
            "subcategory":"Insurance Agent",
            "type":"Services"
        }
    ],
    "sg:phone":"+1 260 463 2881",
    "sg:postcode":"46761",
    "sg:province":"IN",
    "sg:website":"www.howelagrangegmac.com",
    "wof:name":"Howe-Lagrange Agency Inc",
    "wof:placetype":"venue"
},
  "geometry": {"coordinates":[-85.39967300000001,41.604212],"type":"Point"}
}