{
  "type": "Feature",
  "properties": {
    "iso:country":"US",
    "sg:address":"4730 Speedway Dr",
    "sg:city":"Fort Wayne",
    "sg:classifiers":[
        {
            "category":"Wholesale",
            "subcategory":"Hardware",
            "type":"Manufacturing & Wholesale Goods"
        }
    ],
    "sg:phone":"+1 260 484 5958",
    "sg:postcode":"46825",
    "sg:province":"IN",
    "sg:tags":[
        "tool"
    ],
    "wof:name":"D & B Sales",
    "wof:placetype":"venue"
},
  "geometry": {"coordinates":[-85.142521,41.12283],"type":"Point"}
}