{
  "type": "Feature",
  "properties": {
    "addr:full":"7033 Lesta Ct Indianapolis IN 46217",
    "addr:postcode":"7033;46217",
    "addr:street":"Lesta Ct",
    "iso:country":"US",
    "sg:address":"7033 Lesta Ct",
    "sg:city":"Indianapolis",
    "sg:classifiers":[
        {
            "category":"Shopping",
            "subcategory":"Party Supplies",
            "type":"Retail Goods"
        }
    ],
    "sg:phone":"+1 317 881 6679",
    "sg:postcode":"46217",
    "sg:province":"IN",
    "sg:tags":[
        "decoration",
        "rental"
    ],
    "wof:name":"Bell Express",
    "wof:placetype":"venue"
},
  "geometry": {"coordinates":[-86.189977,39.662828],"type":"Point"}
}