{
  "type": "Feature",
  "properties": {
    "addr:full":"5450 Coldwater Rd Fort Wayne IN 46825",
    "addr:housenumber":"5450",
    "addr:postcode":"46825",
    "addr:street":"Coldwater Rd",
    "iso:country":"US",
    "sg:address":"5450 Coldwater Rd",
    "sg:city":"Fort Wayne",
    "sg:classifiers":[
        {
            "category":"Banks & Credit Unions",
            "subcategory":"Bank",
            "type":"Services"
        }
    ],
    "sg:phone":"+1 260 482 7872",
    "sg:postcode":"46825",
    "sg:province":"IN",
    "sg:tags":[
        "cashing",
        "check"
    ],
    "wof:name":"Allied Cash Advance Indiana",
    "wof:placetype":"venue"
},
  "geometry": {"coordinates":[-85.135786,41.129901],"type":"Point"}
}