{
  "type": "Feature",
  "properties": {
    "iso:country":"US",
    "sg:address":"4740 E 10th St",
    "sg:city":"Indianapolis",
    "sg:classifiers":[
        {
            "category":"Personal",
            "subcategory":"Barber",
            "type":"Services"
        }
    ],
    "sg:phone":"+1 317 359 2053",
    "sg:postcode":"46201",
    "sg:province":"IN",
    "wof:name":"Ideal Barber Shop",
    "wof:placetype":"venue"
},
  "geometry": {"coordinates":[-86.08940200000001,39.781555],"type":"Point"}
}