{
  "type": "Feature",
  "properties": {
    "iso:country":"US",
    "sg:address":"3522 Grape Rd",
    "sg:city":"Mishawaka",
    "sg:classifiers":[
        {
            "category":"Shopping",
            "subcategory":"Shoes",
            "type":"Retail Goods"
        }
    ],
    "sg:phone":"+1 574 257 7867",
    "sg:postcode":"46545",
    "sg:province":"IN",
    "wof:name":"Metro Run & Walk",
    "wof:placetype":"venue"
},
  "geometry": {"coordinates":[-86.187235,41.693716],"type":"Point"}
}