{
  "type": "Feature",
  "properties": {
    "iso:country":"US",
    "sg:address":"8 E National Ave",
    "sg:city":"Brazil",
    "sg:classifiers":[
        {
            "category":"Arts & Performance",
            "subcategory":"Theater",
            "type":"Entertainment"
        },
        {
            "category":"Cinema",
            "subcategory":"Movie Theater",
            "type":"Entertainment"
        }
    ],
    "sg:phone":"+1 812 442 1059",
    "sg:postcode":"47834",
    "sg:province":"IN",
    "sg:tags":[
        "motion",
        "picture"
    ],
    "wof:name":"Community Theatre of Clay Co",
    "wof:placetype":"venue"
},
  "geometry": {"coordinates":[-87.127145,39.523259],"type":"Point"}
}