{
  "type": "Feature",
  "properties": {
    "iso:country":"US",
    "sg:address":"1245 Governors Ln",
    "sg:city":"Zionsville",
    "sg:classifiers":[
        {
            "category":"Banks & Credit Unions",
            "subcategory":"Bank",
            "type":"Services"
        }
    ],
    "sg:phone":"+1 317 873 9462",
    "sg:postcode":"46077",
    "sg:province":"IN",
    "sg:tags":[
        "mortgage"
    ],
    "wof:name":"Alpine Mortgage Services LLC",
    "wof:placetype":"venue"
},
  "geometry": {"coordinates":[-86.281037,39.969344],"type":"Point"}
}