{
  "type": "Feature",
  "properties": {
    "addr:full":"5360 Clem Rd Portage IN 46368",
    "addr:postcode":"5360;46368",
    "addr:street":"Clem Rd",
    "iso:country":"US",
    "sg:address":"5360 Clem Rd",
    "sg:city":"Portage",
    "sg:classifiers":[
        {
            "category":"Place Of Worship",
            "subcategory":"Church",
            "type":"Public Place"
        },
        {
            "category":"Place Of Worship",
            "type":"Public Place"
        }
    ],
    "sg:phone":"+1 219 762 7179",
    "sg:postcode":"46368",
    "sg:province":"IN",
    "sg:tags":[
        "nazarene",
        "churches-church",
        "churches-nazarene"
    ],
    "wof:name":"Grace Church Of The Nazarene Inc",
    "wof:placetype":"venue"
},
  "geometry": {"coordinates":[-87.208868,41.587221],"type":"Point"}
}