{
  "type": "Feature",
  "properties": {
    "iso:country":"US",
    "sg:address":"301 E Sherry Ln",
    "sg:city":"Wolcott",
    "sg:phone":"+1 219 279 2658",
    "sg:postcode":"47995",
    "sg:province":"IN",
    "sg:tags":[
        "farm",
        "grain",
        "cash",
        "soybean"
    ],
    "wof:name":"Lawrence E Klink Farms Inc",
    "wof:placetype":"venue"
},
  "geometry": {"coordinates":[-87.037964,40.764757],"type":"Point"}
}