{
  "type": "Feature",
  "properties": {
    "iso:country":"US",
    "sg:address":"3904 N Locust St",
    "sg:city":"Muncie",
    "sg:classifiers":[
        {
            "category":"Retail",
            "subcategory":"Repair Shop",
            "type":"Services"
        }
    ],
    "sg:phone":"+1 765 289 6015",
    "sg:postcode":"47304",
    "sg:province":"IN",
    "wof:name":"Creative Framing",
    "wof:placetype":"venue"
},
  "geometry": {"coordinates":[-85.39809700000001,40.226061],"type":"Point"}
}