{
  "type": "Feature",
  "properties": {
    "iso:country":"US",
    "sg:address":"112 E Kirkwood Ave",
    "sg:city":"Bloomington",
    "sg:classifiers":[
        {
            "category":"Food & Beverages",
            "subcategory":"Candy",
            "type":"Retail Goods"
        },
        {
            "category":"Food & Beverages",
            "subcategory":"Chocolate",
            "type":"Retail Goods"
        }
    ],
    "sg:phone":"+1 812 334 8460",
    "sg:postcode":"47408",
    "sg:province":"IN",
    "sg:tags":[
        "shop",
        "dessert",
        "chocolatiers"
    ],
    "sg:website":"www.bluboychocolates.com",
    "wof:name":"BLU Boy Chocolate Cafe and Cakery",
    "wof:placetype":"venue"
},
  "geometry": {"coordinates":[-86.533461,39.166579],"type":"Point"}
}