{
  "type": "Feature",
  "properties": {
    "iso:country":"US",
    "sg:address":"7353 Company Dr",
    "sg:city":"Indianapolis",
    "sg:classifiers":[
        {
            "category":"Professional",
            "subcategory":"Management & Consulting",
            "type":"Services"
        }
    ],
    "sg:phone":"+1 317 865 9338",
    "sg:postcode":"46237",
    "sg:province":"IN",
    "sg:tags":[
        "logistics"
    ],
    "wof:name":"Ryder Integrated Logistics Inc",
    "wof:placetype":"venue"
},
  "geometry": {"coordinates":[-86.079615,39.659564],"type":"Point"}
}