{
  "type": "Feature",
  "properties": {
    "iso:country":"US",
    "sg:address":"7317 Mikesell Dr",
    "sg:city":"Indianapolis",
    "sg:classifiers":[
        {
            "category":"Professional",
            "subcategory":"Business Services",
            "type":"Services"
        }
    ],
    "sg:phone":"+1 317 253 7435",
    "sg:postcode":"46260",
    "sg:province":"IN",
    "wof:name":"JM Bell & Associates",
    "wof:placetype":"venue"
},
  "geometry": {"coordinates":[-86.18981700000001,39.889214],"type":"Point"}
}