{
  "type": "Feature",
  "properties": {
    "addr:full":"3415 English Ave Indianapolis IN 46201",
    "addr:housenumber":"3415",
    "addr:postcode":"46201",
    "addr:street":"English Ave",
    "iso:country":"US",
    "sg:address":"3415 English Ave",
    "sg:city":"Indianapolis",
    "sg:classifiers":[
        {
            "category":"Shopping",
            "subcategory":"Department Store",
            "type":"Retail Goods"
        }
    ],
    "sg:phone":"+1 317 635 2743",
    "sg:postcode":"46201",
    "sg:province":"IN",
    "sg:tags":[
        "shop"
    ],
    "sg:website":"www.biglots.com",
    "wof:name":"Big Lots",
    "wof:placetype":"venue"
},
  "geometry": {"coordinates":[-86.108059,39.759867],"type":"Point"}
}