{
  "type": "Feature",
  "properties": {
    "addr:full":"2413 N Meridian St Indianapolis IN 46208",
    "addr:housenumber":"2413",
    "addr:postcode":"46208",
    "addr:street":"N Meridian St",
    "iso:country":"US",
    "sg:address":"2413 N Meridian St",
    "sg:city":"Indianapolis",
    "sg:classifiers":[
        {
            "category":"Organizations",
            "subcategory":"Non-profit Organization",
            "type":"Services"
        },
        {
            "category":"Social Services",
            "type":"Services"
        }
    ],
    "sg:phone":"+1 317 926 9177",
    "sg:postcode":"46208",
    "sg:province":"IN",
    "sg:tags":[
        "alternative",
        "abortion"
    ],
    "wof:name":"Centrl In Crisis Pregnancy Ctr",
    "wof:placetype":"venue"
},
  "geometry": {"coordinates":[-86.156584,39.802465],"type":"Point"}
}