{
  "type": "Feature",
  "properties": {
    "iso:country":"US",
    "sg:address":"7925 N Clinton St",
    "sg:city":"Fort Wayne",
    "sg:classifiers":[
        {
            "category":"Manufacturing",
            "subcategory":"Tools & Machinery",
            "type":"Manufacturing & Wholesale Goods"
        }
    ],
    "sg:phone":"+1 260 482 9211",
    "sg:postcode":"46825",
    "sg:province":"IN",
    "sg:tags":[
        "plastic"
    ],
    "sg:website":"www.plasticservices.com",
    "wof:name":"Plastic Services & Equipment",
    "wof:placetype":"venue"
},
  "geometry": {"coordinates":[-85.109104,41.154569],"type":"Point"}
}