{
  "type": "Feature",
  "properties": {
    "iso:country":"US",
    "sg:address":"6046 E 21st St",
    "sg:city":"Indianapolis",
    "sg:classifiers":[
        {
            "category":"Real Estate",
            "subcategory":"Real Estate Operator",
            "type":"Services"
        }
    ],
    "sg:phone":"+1 317 353 0300",
    "sg:postcode":"46219",
    "sg:province":"IN",
    "sg:tags":[
        "apartment"
    ],
    "wof:name":"DSI Properties",
    "wof:placetype":"venue"
},
  "geometry": {"coordinates":[-86.061446,39.796403],"type":"Point"}
}