{
  "type": "Feature",
  "properties": {
    "iso:country":"US",
    "sg:address":"121 Shadowlawn Dr",
    "sg:city":"Fishers",
    "sg:classifiers":[
        {
            "category":"Building & Trades",
            "subcategory":"Construction",
            "type":"Services"
        }
    ],
    "sg:phone":"+1 317 842 5342",
    "sg:postcode":"46038",
    "sg:province":"IN",
    "sg:tags":[
        "contractor"
    ],
    "sg:website":"www.midstateserectors.com",
    "wof:name":"Mid-States Erectors Inc",
    "wof:placetype":"venue"
},
  "geometry": {"coordinates":[-86.044197,39.9519],"type":"Point"}
}