{
  "type": "Feature",
  "properties": {
    "iso:country":"US",
    "sg:address":"10908 Rockville Rd",
    "sg:city":"Avon",
    "sg:classifiers":[
        {
            "category":"Autos & Motor Vehicles",
            "subcategory":"Fuel & Gas Station",
            "type":"Retail Goods"
        }
    ],
    "sg:phone":"+1 317 271 8278",
    "sg:postcode":"46123",
    "sg:province":"IN",
    "sg:tags":[
        "oil"
    ],
    "wof:name":"Speedway",
    "wof:placetype":"venue"
},
  "geometry": {"coordinates":[-86.329115,39.763834],"type":"Point"}
}