{
  "type": "Feature",
  "properties": {
    "iso:country":"US",
    "sg:address":"3541 Brehob Rd",
    "sg:city":"Indianapolis",
    "sg:classifiers":[
        {
            "category":"Building & Trades",
            "subcategory":"Construction",
            "type":"Services"
        }
    ],
    "sg:phone":"+1 317 784 1857",
    "sg:postcode":"46217",
    "sg:province":"IN",
    "sg:tags":[
        "paving",
        "contractor"
    ],
    "wof:name":"Paving Plus Co",
    "wof:placetype":"venue"
},
  "geometry": {"coordinates":[-86.165544,39.708232],"type":"Point"}
}