{
  "type": "Feature",
  "properties": {
    "addr:full":"2302 E Michigan Blvd Michigan City IN 46360",
    "addr:housenumber":"2302",
    "addr:postcode":"46360",
    "addr:street":"E Michigan Blvd",
    "iso:country":"US",
    "sg:address":"2302 E Michigan Blvd",
    "sg:city":"Michigan City",
    "sg:classifiers":[
        {
            "category":"Manufacturing",
            "subcategory":"Electronics",
            "type":"Manufacturing & Wholesale Goods"
        }
    ],
    "sg:phone":"+1 219 879 3381",
    "sg:postcode":"46360",
    "sg:province":"IN",
    "sg:tags":[
        "equipment",
        "electronic",
        "supply"
    ],
    "wof:name":"Infonics Inc",
    "wof:placetype":"venue"
},
  "geometry": {"coordinates":[-86.870769,41.709002],"type":"Point"}
}