{
  "type": "Feature",
  "properties": {
    "iso:country":"US",
    "sg:address":"531 S 10th St",
    "sg:city":"Mitchell",
    "sg:classifiers":[
        {
            "category":"Building & Trades",
            "subcategory":"Plumbing",
            "type":"Services"
        }
    ],
    "sg:phone":"+1 812 849 2944",
    "sg:postcode":"47446",
    "sg:province":"IN",
    "sg:tags":[
        "air",
        "heating",
        "conditioning",
        "contractor"
    ],
    "wof:name":"Woolston Heating & Cooling",
    "wof:placetype":"venue"
},
  "geometry": {"coordinates":[-86.47612,38.725961],"type":"Point"}
}