{
  "type": "Feature",
  "properties": {
    "iso:country":"US",
    "sg:address":"4424 Vogel Rd",
    "sg:city":"Evansville",
    "sg:classifiers":[
        {
            "category":"Organizations",
            "subcategory":"Professional Association",
            "type":"Services"
        }
    ],
    "sg:phone":"+1 812 962 2202",
    "sg:postcode":"47715",
    "sg:province":"IN",
    "sg:website":"www.komenevansville.org",
    "wof:name":"Susan G Komen Breast Cancer",
    "wof:placetype":"venue"
},
  "geometry": {"coordinates":[-87.499438,37.987784],"type":"Point"}
}