{
  "type": "Feature",
  "properties": {
    "addr:full":"5925 Kingsley Drive Indianapolis IN 46220",
    "addr:housenumber":"5925",
    "addr:postcode":"46220",
    "addr:street":"Kingsley Drive",
    "iso:country":"US",
    "sg:address":"5925 Kingsley Drive",
    "sg:city":"Indianapolis",
    "sg:classifiers":[
        {
            "category":"Professional",
            "subcategory":"Computer Services",
            "type":"Services"
        }
    ],
    "sg:phone":"+1 478 227 4868",
    "sg:postcode":"46220",
    "sg:province":"IN",
    "sg:tags":[
        "dating",
        "science-of-dating",
        "being-social",
        "having-relationships",
        "social-life"
    ],
    "sg:website":"http://misspivot.com",
    "wof:name":"Miss Pivot",
    "wof:placetype":"venue"
},
  "geometry": {"coordinates":[-86.130489,39.86358],"type":"Point"}
}