{
  "type": "Feature",
  "properties": {
    "iso:country":"US",
    "sg:address":"1027 S Bend Ave",
    "sg:city":"South Bend",
    "sg:classifiers":[
        {
            "category":"Shopping",
            "subcategory":"Books",
            "type":"Retail Goods"
        }
    ],
    "sg:phone":"+1 574 232 8444",
    "sg:postcode":"46617",
    "sg:province":"IN",
    "sg:tags":[
        "dealer"
    ],
    "wof:name":"Erasmus Books",
    "wof:placetype":"venue"
},
  "geometry": {"coordinates":[-86.235544,41.687352],"type":"Point"}
}