{
  "type": "Feature",
  "properties": {
    "iso:country":"US",
    "sg:address":"66625 Co Rd 15",
    "sg:city":"Goshen",
    "sg:phone":"+1 574 831 4860",
    "sg:postcode":"46526",
    "sg:province":"IN",
    "sg:tags":[
        "farm",
        "grain",
        "cash"
    ],
    "wof:name":"Robert W Ramer",
    "wof:placetype":"venue"
},
  "geometry": {"coordinates":[-85.905265,41.527815],"type":"Point"}
}