{
  "type": "Feature",
  "properties": {
    "iso:country":"US",
    "sg:address":"3463 Eden Way Pl",
    "sg:city":"Carmel",
    "sg:classifiers":[
        {
            "category":"Professional",
            "subcategory":"Business Services",
            "type":"Services"
        }
    ],
    "sg:phone":"+1 317 575 9629",
    "sg:postcode":"46033",
    "sg:province":"IN",
    "wof:name":"Otto Dennis & Associates Inc",
    "wof:placetype":"venue"
},
  "geometry": {"coordinates":[-86.108462,39.966602],"type":"Point"}
}