{
  "type": "Feature",
  "properties": {
    "iso:country":"US",
    "sg:address":"18967 Jefferson Ln",
    "sg:city":"Goshen",
    "sg:classifiers":[
        {
            "category":"Building & Trades",
            "subcategory":"Construction",
            "type":"Services"
        }
    ],
    "sg:phone":"+1 574 642 4424",
    "sg:postcode":"46528",
    "sg:province":"IN",
    "sg:tags":[
        "excavation",
        "contractor"
    ],
    "wof:name":"P&L Backhoe Service",
    "wof:placetype":"venue"
},
  "geometry": {"coordinates":[-85.827313,41.636237],"type":"Point"}
}