{
  "type": "Feature",
  "properties": {
    "iso:country":"US",
    "sg:address":"6558 E Urmeyville Rd",
    "sg:city":"Franklin",
    "sg:classifiers":[
        {
            "category":"Social Services",
            "subcategory":"Child Care",
            "type":"Services"
        }
    ],
    "sg:phone":"+1 317 850 5019",
    "sg:postcode":"46131",
    "sg:province":"IN",
    "sg:tags":[
        "day"
    ],
    "wof:name":"Stepping Stone Stables",
    "wof:placetype":"venue"
},
  "geometry": {"coordinates":[-85.985024,39.519796],"type":"Point"}
}