{
  "type": "Feature",
  "properties": {
    "iso:country":"US",
    "sg:address":"5875 Castle Creek Parkway North Dr",
    "sg:city":"Indianapolis",
    "sg:classifiers":[
        {
            "category":"Health Services",
            "subcategory":"Clinic",
            "type":"Services"
        }
    ],
    "sg:phone":"+1 317 845 7357",
    "sg:postcode":"46250",
    "sg:province":"IN",
    "wof:name":"Graystone Healthcare",
    "wof:placetype":"venue"
},
  "geometry": {"coordinates":[-86.070308,39.915617],"type":"Point"}
}