{
  "type": "Feature",
  "properties": {
    "addr:full":"2703 Drexel Ave Fort Wayne IN 46806",
    "addr:housenumber":"2703",
    "addr:postcode":"46806",
    "addr:street":"Drexel Ave",
    "iso:country":"US",
    "sg:address":"2703 Drexel Ave",
    "sg:city":"Fort Wayne",
    "sg:classifiers":[
        {
            "category":"Personal",
            "subcategory":"Beauty Salon",
            "type":"Services"
        }
    ],
    "sg:phone":"+1 260 456 0207",
    "sg:postcode":"46806",
    "sg:province":"IN",
    "wof:name":"Kamaru's Hair Salon",
    "wof:placetype":"venue"
},
  "geometry": {"coordinates":[-85.101207,41.055958],"type":"Point"}
}