{
  "type": "Feature",
  "properties": {
    "iso:country":"US",
    "sg:address":"3607 E Raymond St",
    "sg:city":"Indianapolis",
    "sg:classifiers":[
        {
            "category":"Autos & Motor Vehicles",
            "subcategory":"Auto Supplies",
            "type":"Retail Goods"
        }
    ],
    "sg:phone":"+1 317 786 2086",
    "sg:postcode":"46203",
    "sg:province":"IN",
    "sg:tags":[
        "automobile",
        "parts"
    ],
    "wof:name":"Autozone",
    "wof:placetype":"venue"
},
  "geometry": {"coordinates":[-86.107553,39.73781],"type":"Point"}
}