{
  "type": "Feature",
  "properties": {
    "iso:country":"US",
    "sg:address":"1406 W Oak St",
    "sg:city":"Union City",
    "sg:classifiers":[
        {
            "category":"Building & Trades",
            "subcategory":"Construction",
            "type":"Services"
        }
    ],
    "sg:phone":"+1 765 964 4900",
    "sg:postcode":"47390",
    "sg:province":"IN",
    "sg:tags":[
        "general",
        "contractor"
    ],
    "wof:name":"Creative Woodworking",
    "wof:placetype":"venue"
},
  "geometry": {"coordinates":[-84.823646,40.198613],"type":"Point"}
}