{
  "type": "Feature",
  "properties": {
    "iso:country":"US",
    "sg:address":"144 W 22nd St",
    "sg:city":"Indianapolis",
    "sg:classifiers":[
        {
            "category":"Health Services",
            "subcategory":"Doctor",
            "type":"Services"
        }
    ],
    "sg:phone":"+1 765 683 3180",
    "sg:postcode":"46202",
    "sg:province":"IN",
    "sg:tags":[
        "physician",
        "surgeon"
    ],
    "wof:name":"Family Physicians Of Anderson",
    "wof:placetype":"venue"
},
  "geometry": {"coordinates":[-86.161231,39.797358],"type":"Point"}
}