{
  "type": "Feature",
  "properties": {
    "iso:country":"US",
    "sg:address":"9760 Lantern Rd",
    "sg:city":"Fishers",
    "sg:classifiers":[
        {
            "category":"Health Services",
            "subcategory":"Optometrist",
            "type":"Services"
        }
    ],
    "sg:phone":"+1 317 577 9200",
    "sg:postcode":"46037",
    "sg:province":"IN",
    "wof:name":"Sweet-Obenauf Eye Care",
    "wof:placetype":"venue"
},
  "geometry": {"coordinates":[-86.013717,39.930337],"type":"Point"}
}