{
  "type": "Feature",
  "properties": {
    "iso:country":"US",
    "sg:address":"2980 W Sycamore St",
    "sg:city":"Kokomo",
    "sg:classifiers":[
        {
            "category":"Retail",
            "subcategory":"Auto Rental",
            "type":"Services"
        }
    ],
    "sg:phone":"+1 765 452 2054",
    "sg:postcode":"46901",
    "sg:province":"IN",
    "sg:tags":[
        "renting",
        "truck",
        "leasing"
    ],
    "wof:name":"Budget Truck Rental",
    "wof:placetype":"venue"
},
  "geometry": {"coordinates":[-86.183922,40.487644],"type":"Point"}
}