{
  "type": "Feature",
  "properties": {
    "iso:country":"US",
    "sg:address":"44 N Van Buren St",
    "sg:city":"Nashville",
    "sg:classifiers":[
        {
            "category":"Shopping",
            "subcategory":"Stationery & Office Supplies",
            "type":"Retail Goods"
        }
    ],
    "sg:phone":"+1 812 988 9820",
    "sg:postcode":"47448",
    "sg:province":"IN",
    "sg:tags":[
        "album",
        "scrapbook"
    ],
    "wof:name":"Scrap Book Boutique",
    "wof:placetype":"venue"
},
  "geometry": {"coordinates":[-86.24687,39.208096],"type":"Point"}
}