{
  "type": "Feature",
  "properties": {
    "addr:full":"18491 Co Rd 146 New Paris IN 46553",
    "addr:housenumber":"18491;146",
    "addr:postcode":"in 46553",
    "addr:street":"Co Rd",
    "iso:country":"US",
    "sg:address":"18491 Co Rd 146",
    "sg:city":"New Paris",
    "sg:classifiers":[
        {
            "category":"Professional",
            "subcategory":"Management & Consulting",
            "type":"Services"
        }
    ],
    "sg:phone":"+1 574 831 5880",
    "sg:postcode":"46553",
    "sg:province":"IN",
    "sg:tags":[
        "consultant"
    ],
    "wof:name":"Riley Trading",
    "wof:placetype":"venue"
},
  "geometry": {"coordinates":[-85.818601,41.486111],"type":"Point"}
}