{
  "type": "Feature",
  "properties": {
    "iso:country":"US",
    "sg:address":"23611 River Lake Ct",
    "sg:city":"Elkhart",
    "sg:classifiers":[
        {
            "category":"Real Estate",
            "subcategory":"Real Estate Operator",
            "type":"Services"
        }
    ],
    "sg:phone":"+1 574 875 3973",
    "sg:postcode":"46516",
    "sg:province":"IN",
    "sg:tags":[
        "building",
        "apartment"
    ],
    "wof:name":"Jon R Danforth",
    "wof:placetype":"venue"
},
  "geometry": {"coordinates":[-85.917118,41.652973],"type":"Point"}
}