{
  "type": "Feature",
  "properties": {
    "addr:full":"7651 Newcastle Rd Lafayette IN 47905",
    "addr:housenumber":"7651",
    "addr:postcode":"47905",
    "addr:street":"Newcastle Rd",
    "iso:country":"US",
    "sg:address":"7651 Newcastle Rd",
    "sg:city":"Lafayette",
    "sg:classifiers":[
        {
            "category":"Government",
            "subcategory":"Office",
            "type":"Public Place"
        }
    ],
    "sg:phone":"+1 765 296 8064",
    "sg:postcode":"47905",
    "sg:province":"IN",
    "sg:tags":[
        "village"
    ],
    "wof:name":"Sheffield Township Trustee",
    "wof:placetype":"venue"
},
  "geometry": {"coordinates":[-86.733085,40.308506],"type":"Point"}
}