{
  "type": "Feature",
  "properties": {
    "iso:country":"US",
    "sg:address":"6508 W 200 N",
    "sg:city":"Rensselaer",
    "sg:classifiers":[
        {
            "category":"Freight",
            "type":"Transportation"
        }
    ],
    "sg:phone":"+1 219 866 8514",
    "sg:postcode":"47978",
    "sg:province":"IN",
    "sg:tags":[
        "operator",
        "trucking"
    ],
    "wof:name":"Kosta Trucking Inc",
    "wof:placetype":"venue"
},
  "geometry": {"coordinates":[-87.180299,41.04179],"type":"Point"}
}