{
  "type": "Feature",
  "properties": {
    "addr:full":"700 W Riverside Dr Jeffersonville IN 47130",
    "addr:housenumber":"700",
    "addr:postcode":"47130",
    "addr:street":"W Riverside Dr",
    "iso:country":"US",
    "sg:address":"700 W Riverside Dr",
    "sg:city":"Jeffersonville",
    "sg:classifiers":[
        {
            "category":"Restaurant",
            "type":"Food & Drink"
        }
    ],
    "sg:phone":"+1 812 280 0032",
    "sg:postcode":"47130",
    "sg:province":"IN",
    "wof:name":"Ernesto's Mex Mex Grill",
    "wof:placetype":"venue"
},
  "geometry": {"coordinates":[-85.748935,38.268544],"type":"Point"}
}