{
  "type": "Feature",
  "properties": {
    "iso:country":"US",
    "sg:address":"6485 E 249th St",
    "sg:city":"Cicero",
    "sg:classifiers":[
        {
            "category":"Retail",
            "subcategory":"Repair Shop",
            "type":"Services"
        }
    ],
    "sg:phone":"+1 317 984 5520",
    "sg:postcode":"46034",
    "sg:province":"IN",
    "wof:name":"Shull Forge Repairs",
    "wof:placetype":"venue"
},
  "geometry": {"coordinates":[-86.057548,40.150223],"type":"Point"}
}