{
  "type": "Feature",
  "properties": {
    "iso:country":"US",
    "sg:address":"2410 Grant Blvd",
    "sg:city":"Lebanon",
    "sg:classifiers":[
        {
            "category":"Professional",
            "subcategory":"Business Services",
            "type":"Services"
        }
    ],
    "sg:phone":"+1 765 482 0483",
    "sg:postcode":"46052",
    "sg:province":"IN",
    "wof:name":"Morton Group LLC",
    "wof:placetype":"venue"
},
  "geometry": {"coordinates":[-86.460291,40.075514],"type":"Point"}
}