{
  "type": "Feature",
  "properties": {
    "iso:country":"US",
    "sg:address":"5424 E 1050 S",
    "sg:city":"La Fontaine",
    "sg:classifiers":[
        {
            "category":"Building & Trades",
            "subcategory":"Construction",
            "type":"Services"
        }
    ],
    "sg:phone":"+1 765 981 2455",
    "sg:postcode":"46940",
    "sg:province":"IN",
    "sg:tags":[
        "concrete",
        "contractor"
    ],
    "wof:name":"CAT Excavating & Constr Inc",
    "wof:placetype":"venue"
},
  "geometry": {"coordinates":[-85.681901,40.674658],"type":"Point"}
}