{
  "type": "Feature",
  "properties": {
    "iso:country":"US",
    "sg:address":"6929 Antietam Ct",
    "sg:city":"Indianapolis",
    "sg:classifiers":[
        {
            "category":"Shopping",
            "subcategory":"Bicycles & Sporting Goods",
            "type":"Retail Goods"
        }
    ],
    "sg:phone":"+1 317 291 0398",
    "sg:postcode":"46278",
    "sg:province":"IN",
    "wof:name":"Lee Sport Chase Authentic",
    "wof:placetype":"venue"
},
  "geometry": {"coordinates":[-86.286682,39.879956],"type":"Point"}
}