{
  "type": "Feature",
  "properties": {
    "addr:full":"1415 N Main St Mishawaka IN 46545",
    "addr:housenumber":"1415",
    "addr:postcode":"46545",
    "addr:street":"N Main St",
    "iso:country":"US",
    "sg:address":"1415 N Main St",
    "sg:city":"Mishawaka",
    "sg:classifiers":[
        {
            "category":"Real Estate",
            "subcategory":"Developer",
            "type":"Services"
        }
    ],
    "sg:phone":"+1 574 255 2523",
    "sg:postcode":"46545",
    "sg:province":"IN",
    "sg:tags":[
        "cemetery"
    ],
    "wof:name":"Fairview Cemetery",
    "wof:placetype":"venue"
},
  "geometry": {"coordinates":[-86.181437,41.673042],"type":"Point"}
}