{
  "type": "Feature",
  "properties": {
    "iso:country":"US",
    "sg:address":"930 W State Rd 62",
    "sg:city":"Leavenworth",
    "sg:classifiers":[
        {
            "category":"Travel",
            "subcategory":"Hotels & Motels",
            "type":"Entertainment"
        }
    ],
    "sg:phone":"+1 812 739 2120",
    "sg:postcode":"47137",
    "sg:province":"IN",
    "sg:tags":[
        "breakfast",
        "accommodation",
        "bed"
    ],
    "wof:name":"Leavenworth Inn",
    "wof:placetype":"venue"
},
  "geometry": {"coordinates":[-86.353082,38.205484],"type":"Point"}
}