{
  "type": "Feature",
  "properties": {
    "iso:country":"US",
    "sg:address":"2434 N State Rd 39",
    "sg:city":"Laporte",
    "sg:classifiers":[
        {
            "category":"Banks & Credit Unions",
            "subcategory":"Bank",
            "type":"Services"
        }
    ],
    "sg:phone":"+1 219 326 8470",
    "sg:postcode":"46350",
    "sg:province":"IN",
    "sg:tags":[
        "loan",
        "real estate"
    ],
    "wof:name":"Mid America Mortgage Corp",
    "wof:placetype":"venue"
},
  "geometry": {"coordinates":[-86.73837399999999,41.639248],"type":"Point"}
}