{
  "type": "Feature",
  "properties": {
    "iso:country":"US",
    "sg:address":"3800 Wabash Ave",
    "sg:city":"Terre Haute",
    "sg:classifiers":[
        {
            "category":"Autos & Motor Vehicles",
            "subcategory":"Automobile Sales",
            "type":"Retail Goods"
        }
    ],
    "sg:phone":"+1 812 232 7582",
    "sg:postcode":"47803",
    "sg:province":"IN",
    "sg:tags":[
        "car",
        "dealer"
    ],
    "wof:name":"Lakes Car & Cycle Ctr",
    "wof:placetype":"venue"
},
  "geometry": {"coordinates":[-87.359499,39.474036],"type":"Point"}
}