{
  "type": "Feature",
  "properties": {
    "iso:country":"US",
    "sg:address":"12307 Greenbriar Blvd",
    "sg:city":"Sellersburg",
    "sg:classifiers":[
        {
            "category":"Shopping",
            "subcategory":"Clothing, Apparel, & Fashions",
            "type":"Retail Goods"
        }
    ],
    "sg:phone":"+1 812 248 7023",
    "sg:postcode":"47172",
    "sg:province":"IN",
    "sg:tags":[
        "apparel",
        "racing",
        "sportswear",
        "merchandise"
    ],
    "wof:name":"Bluegrass Sportswear",
    "wof:placetype":"venue"
},
  "geometry": {"coordinates":[-85.79756399999999,38.435244],"type":"Point"}
}