{
  "type": "Feature",
  "properties": {
    "iso:country":"US",
    "sg:address":"1815 N Meridian St",
    "sg:city":"Indianapolis",
    "sg:classifiers":[
        {
            "category":"Real Estate",
            "subcategory":"Real Estate Agent",
            "type":"Services"
        }
    ],
    "sg:phone":"+1 317 923 8191",
    "sg:postcode":"46202",
    "sg:province":"IN",
    "wof:name":"Lifetime Properties",
    "wof:placetype":"venue"
},
  "geometry": {"coordinates":[-86.157231,39.791233],"type":"Point"}
}