{
  "type": "Feature",
  "properties": {
    "iso:country":"US",
    "sg:address":"1231 Fairfield Ave",
    "sg:city":"Fort Wayne",
    "sg:classifiers":[
        {
            "category":"Retail",
            "subcategory":"Auto Repair",
            "type":"Services"
        }
    ],
    "sg:phone":"+1 260 424 8386",
    "sg:postcode":"46802",
    "sg:province":"IN",
    "sg:tags":[
        "repairing",
        "automobile"
    ],
    "wof:name":"JTM Auto Svc",
    "wof:placetype":"venue"
},
  "geometry": {"coordinates":[-85.145143,41.074553],"type":"Point"}
}