{
  "type": "Feature",
  "properties": {
    "addr:full":"2834 Villa Ave Indianapolis IN 46203",
    "addr:housenumber":"2834",
    "addr:postcode":"46203",
    "addr:street":"Villa Ave",
    "iso:country":"US",
    "sg:address":"2834 Villa Ave",
    "sg:city":"Indianapolis",
    "sg:classifiers":[
        {
            "category":"Building & Trades",
            "subcategory":"Construction",
            "type":"Services"
        }
    ],
    "sg:phone":"+1 317 784 9409",
    "sg:postcode":"46203",
    "sg:province":"IN",
    "sg:tags":[
        "painting"
    ],
    "wof:name":"S & C Painting Inc",
    "wof:placetype":"venue"
},
  "geometry": {"coordinates":[-86.124658,39.725701],"type":"Point"}
}