{
  "type": "Feature",
  "properties": {
    "iso:country":"US",
    "sg:address":"303 E Hefron St",
    "sg:city":"Washington",
    "sg:classifiers":[
        {
            "category":"Government",
            "subcategory":"Office",
            "type":"Public Place"
        }
    ],
    "sg:phone":"+1 812 254 8666",
    "sg:postcode":"47501",
    "sg:province":"IN",
    "sg:tags":[
        "county",
        "program",
        "health"
    ],
    "wof:name":"Health Dept",
    "wof:placetype":"venue"
},
  "geometry": {"coordinates":[-87.17233899999999,38.659502],"type":"Point"}
}