{
  "type": "Feature",
  "properties": {
    "addr:full":"940 Indianapolis Rd Greencastle IN 46135",
    "addr:housenumber":"940",
    "addr:postcode":"46135",
    "addr:street":"Indianapolis Rd",
    "iso:country":"US",
    "sg:address":"940 Indianapolis Rd",
    "sg:city":"Greencastle",
    "sg:classifiers":[
        {
            "category":"Restaurant",
            "type":"Food & Drink"
        }
    ],
    "sg:menulink":"http://www.allmenus.com/in/greencastle/186366-mcdonalds/menu/",
    "sg:postcode":"46135",
    "sg:province":"IN",
    "sg:tags":[
        "burger",
        "american"
    ],
    "wof:name":"McDonald's",
    "wof:placetype":"venue"
},
  "geometry": {"coordinates":[-86.84571200000001,39.64507],"type":"Point"}
}