{
  "type": "Feature",
  "properties": {
    "iso:country":"US",
    "sg:address":"5454 Broadway",
    "sg:city":"Merrillville",
    "sg:classifiers":[
        {
            "category":"Health Services",
            "subcategory":"Doctor",
            "type":"Services"
        }
    ],
    "sg:phone":"+1 219 884 2600",
    "sg:postcode":"46410",
    "sg:province":"IN",
    "sg:tags":[
        "physician",
        "surgeon"
    ],
    "wof:name":"Broadway Emergency-Family Med",
    "wof:placetype":"venue"
},
  "geometry": {"coordinates":[-87.33622699999999,41.519326],"type":"Point"}
}