{
  "type": "Feature",
  "properties": {
    "addr:full":"4351 Lafayette Rd Indianapolis IN 46254",
    "addr:housenumber":"4351",
    "addr:postcode":"46254",
    "iso:country":"US",
    "sg:address":"4351 Lafayette Rd",
    "sg:city":"Indianapolis",
    "sg:classifiers":[
        {
            "category":"Restaurant",
            "type":"Food & Drink"
        }
    ],
    "sg:menulink":"http://www.allmenus.com/in/pike/81797-subway/menu/",
    "sg:phone":"+1 317 293 9400",
    "sg:postcode":"46254",
    "sg:province":"IN",
    "sg:tags":[
        "american",
        "sandwich"
    ],
    "wof:name":"Subway",
    "wof:placetype":"venue"
},
  "geometry": {"coordinates":[-86.24426800000001,39.833565],"type":"Point"}
}