{
  "type": "Feature",
  "properties": {
    "iso:country":"US",
    "sg:address":"2103 Wayne Dr",
    "sg:city":"Greenfield",
    "sg:classifiers":[
        {
            "category":"Professional",
            "subcategory":"Computer Services",
            "type":"Services"
        }
    ],
    "sg:phone":"+1 317 326 2243",
    "sg:postcode":"46140",
    "sg:province":"IN",
    "sg:tags":[
        "repair"
    ],
    "wof:name":"Programs At Work Inc",
    "wof:placetype":"venue"
},
  "geometry": {"coordinates":[-85.844421,39.789583],"type":"Point"}
}