{
  "type": "Feature",
  "properties": {
    "iso:country":"US",
    "sg:address":"71 E Jefferson St",
    "sg:city":"Franklin",
    "sg:classifiers":[
        {
            "category":"Banks & Credit Unions",
            "subcategory":"Investment Brokerage",
            "type":"Services"
        }
    ],
    "sg:phone":"+1 317 736 4070",
    "sg:postcode":"46131",
    "sg:province":"IN",
    "sg:tags":[
        "stock",
        "bond"
    ],
    "wof:name":"Edward Jones Co",
    "wof:placetype":"venue"
},
  "geometry": {"coordinates":[-86.054096,39.480518],"type":"Point"}
}