{
  "type": "Feature",
  "properties": {
    "iso:country":"US",
    "sg:address":"220 E 7th St",
    "sg:city":"Auburn",
    "sg:classifiers":[
        {
            "category":"Utilities",
            "subcategory":"Natural Gas",
            "type":"Services"
        }
    ],
    "sg:phone":"+1 260 925 2700",
    "sg:postcode":"46706",
    "sg:province":"IN",
    "sg:tags":[
        "company"
    ],
    "sg:website":"www.niflco.com",
    "wof:name":"Northern Indiana Fuel & Light",
    "wof:placetype":"venue"
},
  "geometry": {"coordinates":[-85.053585,41.367036],"type":"Point"}
}