{
  "type": "Feature",
  "properties": {
    "iso:country":"US",
    "sg:address":"17602 Stockbridge Ln",
    "sg:city":"Granger",
    "sg:classifiers":[
        {
            "category":"Professional",
            "subcategory":"Business Services",
            "type":"Services"
        }
    ],
    "sg:phone":"+1 574 272 8022",
    "sg:postcode":"46530",
    "sg:province":"IN",
    "wof:name":"Design Concepts",
    "wof:placetype":"venue"
},
  "geometry": {"coordinates":[-86.209648,41.743491],"type":"Point"}
}