{
  "type": "Feature",
  "properties": {
    "iso:country":"US",
    "sg:address":"610 N Sherman Dr",
    "sg:city":"Indianapolis",
    "sg:classifiers":[
        {
            "category":"Professional",
            "subcategory":"Advertising",
            "type":"Services"
        }
    ],
    "sg:phone":"+1 317 536 2415",
    "sg:postcode":"46201",
    "sg:province":"IN",
    "sg:tags":[
        "advertising-telephone",
        "fax",
        "telemarketing"
    ],
    "wof:name":"Agi International, Inc.",
    "wof:placetype":"venue"
},
  "geometry": {"coordinates":[-86.10221900000001,39.775234],"type":"Point"}
}