{
  "type": "Feature",
  "properties": {
    "iso:country":"US",
    "sg:address":"106 N Walnut St",
    "sg:city":"Bloomington",
    "sg:classifiers":[
        {
            "category":"Professional",
            "type":"Services"
        }
    ],
    "sg:phone":"+1 812 333 2282",
    "sg:postcode":"47404",
    "sg:province":"IN",
    "sg:tags":[
        "establishment"
    ],
    "wof:name":"Cave Group",
    "wof:placetype":"venue"
},
  "geometry": {"coordinates":[-86.53353300000001,39.16749],"type":"Point"}
}