{
  "type": "Feature",
  "properties": {
    "iso:country":"US",
    "sg:address":"454 State Rd 161",
    "sg:city":"Rockport",
    "sg:classifiers":[
        {
            "category":"Autos & Motor Vehicles",
            "subcategory":"Auto Supplies",
            "type":"Retail Goods"
        }
    ],
    "sg:phone":"+1 812 649 4724",
    "sg:postcode":"47635",
    "sg:province":"IN",
    "sg:tags":[
        "automobile",
        "parts"
    ],
    "sg:website":"www.gipeautomotive.com",
    "wof:name":"Gipe Automotive",
    "wof:placetype":"venue"
},
  "geometry": {"coordinates":[-87.109559,37.894992],"type":"Point"}
}