{
  "type": "Feature",
  "properties": {
    "iso:country":"US",
    "sg:address":"5466 Featheringill Rd",
    "sg:city":"New Albany",
    "sg:classifiers":[
        {
            "category":"Organizations",
            "subcategory":"Religious Organization",
            "type":"Services"
        }
    ],
    "sg:phone":"+1 812 923 3757",
    "sg:postcode":"47124",
    "sg:province":"IN",
    "sg:tags":[
        "church"
    ],
    "wof:name":"Church Of Christ",
    "wof:placetype":"venue"
},
  "geometry": {"coordinates":[-85.94753900000001,38.347638],"type":"Point"}
}