{
  "type": "Feature",
  "properties": {
    "iso:country":"US",
    "sg:address":"1255 S Commerce Dr",
    "sg:city":"Seymour",
    "sg:classifiers":[
        {
            "category":"Freight",
            "type":"Transportation"
        }
    ],
    "sg:phone":"+1 812 524 0258",
    "sg:postcode":"47274",
    "sg:province":"IN",
    "sg:tags":[
        "operator",
        "trucking"
    ],
    "wof:name":"A P L Logistics Whse MGT Svcs",
    "wof:placetype":"venue"
},
  "geometry": {"coordinates":[-85.84275599999999,38.94541],"type":"Point"}
}