{
  "type": "Feature",
  "properties": {
    "iso:country":"US",
    "sg:address":"203 Illinois Ave",
    "sg:city":"Michigan City",
    "sg:classifiers":[
        {
            "category":"Organizations",
            "subcategory":"Religious Organization",
            "type":"Services"
        }
    ],
    "sg:phone":"+1 219 879 5068",
    "sg:postcode":"46360",
    "sg:province":"IN",
    "wof:name":"Franciscan Friars",
    "wof:placetype":"venue"
},
  "geometry": {"coordinates":[-86.889521,41.731401],"type":"Point"}
}