{
  "type": "Feature",
  "properties": {
    "iso:country":"US",
    "sg:address":"10001 Express Dr",
    "sg:city":"Highland",
    "sg:classifiers":[
        {
            "category":"Manufacturing",
            "subcategory":"Tools & Machinery",
            "type":"Manufacturing & Wholesale Goods"
        }
    ],
    "sg:phone":"+1 219 924 3616",
    "sg:postcode":"46322",
    "sg:province":"IN",
    "sg:tags":[
        "construction"
    ],
    "sg:website":"www.siebsales.com",
    "wof:name":"Sieb Sales & Engineering Inc",
    "wof:placetype":"venue"
},
  "geometry": {"coordinates":[-87.468389,41.53215],"type":"Point"}
}