{
  "type": "Feature",
  "properties": {
    "iso:country":"US",
    "sg:address":"332 W US Hwy 30",
    "sg:city":"Valparaiso",
    "sg:classifiers":[
        {
            "category":"Home & Garden",
            "subcategory":"Furniture",
            "type":"Retail Goods"
        }
    ],
    "sg:phone":"+1 219 464 4000",
    "sg:postcode":"46385",
    "sg:province":"IN",
    "sg:tags":[
        "cabinet"
    ],
    "wof:name":"Kitchen Encounters Etc Inc",
    "wof:placetype":"venue"
},
  "geometry": {"coordinates":[-87.118592,41.464966],"type":"Point"}
}