{
  "type": "Feature",
  "properties": {
    "iso:country":"US",
    "sg:address":"110 E Creighton Ave",
    "sg:city":"Fort Wayne",
    "sg:classifiers":[
        {
            "category":"Shopping",
            "subcategory":"Pharmacy",
            "type":"Retail Goods"
        }
    ],
    "sg:phone":"+1 260 456 1153",
    "sg:postcode":"46803",
    "sg:province":"IN",
    "wof:name":"Walgreens",
    "wof:placetype":"venue"
},
  "geometry": {"coordinates":[-85.13654699999999,41.064191],"type":"Point"}
}