{
  "type": "Feature",
  "properties": {
    "iso:country":"US",
    "sg:address":"139 Stoney Creek Ovlk",
    "sg:city":"Noblesville",
    "sg:classifiers":[
        {
            "category":"Wholesale",
            "subcategory":"Electrical",
            "type":"Manufacturing & Wholesale Goods"
        }
    ],
    "sg:phone":"+1 317 770 7202",
    "sg:postcode":"46060",
    "sg:province":"IN",
    "sg:tags":[
        "equipment"
    ],
    "wof:name":"A B B Inc",
    "wof:placetype":"venue"
},
  "geometry": {"coordinates":[-86.007043,40.025658],"type":"Point"}
}