{
  "type": "Feature",
  "properties": {
    "addr:full":"1600 E State Rd 44 Shelbyville IN 46176",
    "addr:housenumber":"1600;44",
    "addr:postcode":"46176",
    "addr:street":"E State Rd",
    "iso:country":"US",
    "sg:address":"1600 E State Rd 44",
    "sg:city":"Shelbyville",
    "sg:classifiers":[
        {
            "category":"Health Services",
            "subcategory":"Doctor",
            "type":"Services"
        }
    ],
    "sg:phone":"+1 317 398 0717",
    "sg:postcode":"46176",
    "sg:province":"IN",
    "sg:tags":[
        "clinic"
    ],
    "wof:name":"Planned Parenthood",
    "wof:placetype":"venue"
},
  "geometry": {"coordinates":[-85.75626800000001,39.520047],"type":"Point"}
}