{
  "type": "Feature",
  "properties": {
    "iso:country":"US",
    "sg:address":"465 Bielby Rd",
    "sg:city":"Lawrenceburg",
    "sg:classifiers":[
        {
            "category":"Health Services",
            "subcategory":"Hospital",
            "type":"Services"
        }
    ],
    "sg:phone":"+1 812 537 5542",
    "sg:postcode":"47025",
    "sg:province":"IN",
    "sg:tags":[
        "medical",
        "center"
    ],
    "wof:name":"Summit Medical Group",
    "wof:placetype":"venue"
},
  "geometry": {"coordinates":[-84.883947,39.11832],"type":"Point"}
}