{
  "type": "Feature",
  "properties": {
    "iso:country":"US",
    "sg:address":"3300 W Kilgore Ave",
    "sg:city":"Muncie",
    "sg:classifiers":[
        {
            "category":"Autos & Motor Vehicles",
            "subcategory":"Automobile Sales",
            "type":"Retail Goods"
        }
    ],
    "sg:phone":"+1 765 286 4100",
    "sg:postcode":"47304",
    "sg:province":"IN",
    "sg:tags":[
        "used"
    ],
    "wof:name":"Vintage Wheels Of America Inc",
    "wof:placetype":"venue"
},
  "geometry": {"coordinates":[-85.428909,40.18109],"type":"Point"}
}