{
  "type": "Feature",
  "properties": {
    "addr:full":"1905 S Walnut St Bloomington IN 47401",
    "addr:housenumber":"1905",
    "addr:postcode":"47401",
    "addr:street":"S Walnut St",
    "iso:country":"US",
    "sg:address":"1905 S Walnut St",
    "sg:city":"Bloomington",
    "sg:classifiers":[
        {
            "category":"Restaurant",
            "type":"Food & Drink"
        }
    ],
    "sg:phone":"+1 812 336 0000",
    "sg:postcode":"47401",
    "sg:province":"IN",
    "wof:name":"Pizza Queen",
    "wof:placetype":"venue"
},
  "geometry": {"coordinates":[-86.531835,39.14439],"type":"Point"}
}