{
  "type": "Feature",
  "properties": {
    "iso:country":"US",
    "sg:address":"4800 W Smith Valley Rd",
    "sg:city":"Greenwood",
    "sg:classifiers":[
        {
            "category":"Insurance",
            "subcategory":"Insurance Agent",
            "type":"Services"
        }
    ],
    "sg:phone":"+1 317 883 1000",
    "sg:postcode":"46142",
    "sg:province":"IN",
    "wof:name":"Allstate Insurance",
    "wof:placetype":"venue"
},
  "geometry": {"coordinates":[-86.19479699999999,39.605159],"type":"Point"}
}