{
  "type": "Feature",
  "properties": {
    "iso:country":"US",
    "sg:address":"3838 N Illinois St",
    "sg:city":"Indianapolis",
    "sg:classifiers":[
        {
            "category":"Retail",
            "subcategory":"Repair Shop",
            "type":"Services"
        }
    ],
    "sg:phone":"+1 317 362 9274",
    "sg:postcode":"46208",
    "sg:province":"IN",
    "sg:tags":[
        "leather",
        "good"
    ],
    "wof:name":"Kim's Alteration Leather",
    "wof:placetype":"venue"
},
  "geometry": {"coordinates":[-86.159282,39.825307],"type":"Point"}
}