{
  "type": "Feature",
  "properties": {
    "iso:country":"US",
    "sg:address":"2220 E Columbus Dr",
    "sg:city":"East Chicago",
    "sg:classifiers":[
        {
            "category":"Autos & Motor Vehicles",
            "subcategory":"Fuel & Gas Station",
            "type":"Retail Goods"
        }
    ],
    "sg:phone":"+1 219 397 9198",
    "sg:postcode":"46312",
    "sg:province":"IN",
    "wof:name":"Mobile Columbus",
    "wof:placetype":"venue"
},
  "geometry": {"coordinates":[-87.44465099999999,41.639067],"type":"Point"}
}