{
  "type": "Feature",
  "properties": {
    "iso:country":"US",
    "sg:address":"4105 N Green River Rd",
    "sg:city":"Evansville",
    "sg:classifiers":[
        {
            "category":"Organizations",
            "subcategory":"Religious Organization",
            "type":"Services"
        }
    ],
    "sg:phone":"+1 812 471 2813",
    "sg:postcode":"47715",
    "sg:province":"IN",
    "sg:tags":[
        "church"
    ],
    "wof:name":"Word Of His Grace Fellowship",
    "wof:placetype":"venue"
},
  "geometry": {"coordinates":[-87.492156,38.013723],"type":"Point"}
}