{
  "type": "Feature",
  "properties": {
    "iso:country":"US",
    "sg:address":"205 S Walnut St",
    "sg:city":"Bloomington",
    "sg:classifiers":[
        {
            "category":"Social Services",
            "type":"Services"
        }
    ],
    "sg:phone":"+1 812 323 8230",
    "sg:postcode":"47404",
    "sg:province":"IN",
    "sg:tags":[
        "counselor",
        "marriage",
        "family"
    ],
    "wof:name":"Inner Resources Counseling",
    "wof:placetype":"venue"
},
  "geometry": {"coordinates":[-86.533552,39.164638],"type":"Point"}
}