{
  "type": "Feature",
  "properties": {
    "iso:country":"US",
    "sg:address":"201 E Wescott St",
    "sg:city":"Liberty",
    "sg:classifiers":[
        {
            "category":"Professional",
            "subcategory":"Business Services",
            "type":"Services"
        }
    ],
    "sg:phone":"+1 765 458 7533",
    "sg:postcode":"47353",
    "sg:province":"IN",
    "wof:name":"J Paul Ventures",
    "wof:placetype":"venue"
},
  "geometry": {"coordinates":[-84.923909,39.63822],"type":"Point"}
}