{
  "type": "Feature",
  "properties": {
    "iso:country":"US",
    "sg:address":"2150 N Talbott St",
    "sg:city":"Indianapolis",
    "sg:classifiers":[
        {
            "category":"Real Estate",
            "subcategory":"Real Estate Services",
            "type":"Services"
        }
    ],
    "sg:phone":"+1 317 925 2360",
    "sg:postcode":"46202",
    "sg:province":"IN",
    "sg:tags":[
        "company",
        "title"
    ],
    "wof:name":"Sterling Title Agency Inc",
    "wof:placetype":"venue"
},
  "geometry": {"coordinates":[-86.15507,39.796545],"type":"Point"}
}