{
  "type": "Feature",
  "properties": {
    "addr:full":"800 MacArthur Blvd Ste 31 Munster IN 46321",
    "addr:housenumber":"800",
    "addr:postcode":"46321",
    "addr:street":"Macarthur Blvd Ste 31",
    "iso:country":"US",
    "sg:address":"800 MacArthur Blvd Ste 31",
    "sg:city":"Munster",
    "sg:classifiers":[
        {
            "category":"Health Services",
            "subcategory":"Doctor",
            "type":"Services"
        },
        {
            "category":"Shopping",
            "subcategory":"Pharmacy",
            "type":"Retail Goods"
        }
    ],
    "sg:phone":"+1 219 836 9950",
    "sg:postcode":"46321",
    "sg:province":"IN",
    "sg:tags":[
        "drugstore"
    ],
    "wof:name":"Excel Health Care",
    "wof:placetype":"venue"
},
  "geometry": {"coordinates":[-87.508988,41.549943],"type":"Point"}
}