{
  "type": "Feature",
  "properties": {
    "addr:full":"8470 Allison Pointe Blvd Indianapolis IN 46250",
    "addr:housenumber":"8470",
    "addr:postcode":"46250",
    "addr:street":"Allison Pointe Blvd",
    "iso:country":"US",
    "sg:address":"8470 Allison Pointe Blvd",
    "sg:city":"Indianapolis",
    "sg:classifiers":[
        {
            "category":"Professional",
            "subcategory":"Lawyer & Legal Services",
            "type":"Services"
        }
    ],
    "sg:phone":"+1 317 638 5291",
    "sg:postcode":"46250",
    "sg:province":"IN",
    "sg:tags":[
        "personal",
        "injury"
    ],
    "wof:name":"Lowe & Webster Atty & Counseling",
    "wof:placetype":"venue"
},
  "geometry": {"coordinates":[-86.083421,39.910091],"type":"Point"}
}