{
  "type": "Feature",
  "properties": {
    "iso:country":"US",
    "sg:address":"4604 Callahan St",
    "sg:city":"Indianapolis",
    "sg:classifiers":[
        {
            "category":"Personal",
            "subcategory":"Nail Salon",
            "type":"Services"
        }
    ],
    "sg:phone":"+1 317 440 2675",
    "sg:postcode":"46239",
    "sg:province":"IN",
    "wof:name":"Hammer And Nail Inc",
    "wof:placetype":"venue"
},
  "geometry": {"coordinates":[-86.00594100000001,39.701701],"type":"Point"}
}