{
  "type": "Feature",
  "properties": {
    "iso:country":"US",
    "sg:address":"213 W Jasper St",
    "sg:city":"Goodland",
    "sg:classifiers":[
        {
            "category":"Organizations",
            "subcategory":"Religious Organization",
            "type":"Services"
        }
    ],
    "sg:phone":"+1 219 297 3556",
    "sg:postcode":"47948",
    "sg:province":"IN",
    "sg:tags":[
        "church"
    ],
    "wof:name":"Trinity Lutheran Church Inc",
    "wof:placetype":"venue"
},
  "geometry": {"coordinates":[-87.299115,40.76553],"type":"Point"}
}