{
  "type": "Feature",
  "properties": {
    "iso:country":"US",
    "sg:address":"4748 Calumet Ave",
    "sg:city":"Hammond",
    "sg:classifiers":[
        {
            "category":"Restaurant",
            "type":"Food & Drink"
        }
    ],
    "sg:phone":"+1 219 937 1041",
    "sg:postcode":"46327",
    "sg:province":"IN",
    "wof:name":"Bob's Shrimp",
    "wof:placetype":"venue"
},
  "geometry": {"coordinates":[-87.508822,41.627699],"type":"Point"}
}