{
  "type": "Feature",
  "properties": {
    "iso:country":"US",
    "sg:address":"2432 Kelly Pl",
    "sg:city":"Dyer",
    "sg:classifiers":[
        {
            "category":"Retail",
            "subcategory":"Veterinary Services",
            "type":"Services"
        }
    ],
    "sg:phone":"+1 219 865 3193",
    "sg:postcode":"46311",
    "sg:province":"IN",
    "sg:tags":[
        "specialty"
    ],
    "wof:name":"Larry W Booher Dvm",
    "wof:placetype":"venue"
},
  "geometry": {"coordinates":[-87.493972,41.486806],"type":"Point"}
}