{
  "type": "Feature",
  "properties": {
    "iso:country":"US",
    "sg:address":"307 N Central Ave",
    "sg:city":"Milton",
    "sg:classifiers":[
        {
            "category":"Government",
            "subcategory":"Post Office",
            "type":"Public Place"
        }
    ],
    "sg:phone":"+1 765 478 3777",
    "sg:postcode":"47357",
    "sg:province":"IN",
    "wof:name":"US Post Office",
    "wof:placetype":"venue"
},
  "geometry": {"coordinates":[-85.155343,39.78977],"type":"Point"}
}