{
  "type": "Feature",
  "properties": {
    "iso:country":"US",
    "sg:address":"10501 W 181st Ave",
    "sg:city":"Lowell",
    "sg:classifiers":[
        {
            "category":"Retail",
            "subcategory":"Auto Repair",
            "type":"Services"
        }
    ],
    "sg:phone":"+1 219 696 4869",
    "sg:postcode":"46356",
    "sg:province":"IN",
    "sg:tags":[
        "wrecker"
    ],
    "wof:name":"Wesley's 24 Hour Towing",
    "wof:placetype":"venue"
},
  "geometry": {"coordinates":[-87.459138,41.289989],"type":"Point"}
}