{
  "type": "Feature",
  "properties": {
    "iso:country":"US",
    "sg:address":"524 Main St",
    "sg:city":"Evansville",
    "sg:classifiers":[
        {
            "category":"Restaurant",
            "type":"Food & Drink"
        }
    ],
    "sg:phone":"+1 812 424 4121",
    "sg:postcode":"47708",
    "sg:province":"IN",
    "wof:name":"Blimpie Subs & Salads",
    "wof:placetype":"venue"
},
  "geometry": {"coordinates":[-87.569215,37.972604],"type":"Point"}
}