{
  "type": "Feature",
  "properties": {
    "iso:country":"US",
    "sg:address":"105 S Grant Ave",
    "sg:city":"Fowler",
    "sg:classifiers":[
        {
            "category":"Professional",
            "subcategory":"Lawyer & Legal Services",
            "type":"Services"
        }
    ],
    "sg:phone":"+1 765 884 1840",
    "sg:postcode":"47944",
    "sg:province":"IN",
    "sg:tags":[
        "attorney"
    ],
    "wof:name":"Dumas Weist & Mahnesmith",
    "wof:placetype":"venue"
},
  "geometry": {"coordinates":[-87.31479400000001,40.617674],"type":"Point"}
}