{
  "type": "Feature",
  "properties": {
    "addr:full":"215 E National Ave Brazil IN 47834",
    "addr:housenumber":"215",
    "addr:postcode":"47834",
    "addr:street":"E National Ave",
    "iso:country":"US",
    "sg:address":"215 E National Ave",
    "sg:city":"Brazil",
    "sg:classifiers":[
        {
            "category":"Local Transit",
            "type":"Transportation"
        }
    ],
    "sg:phone":"+1 812 446 1441",
    "sg:postcode":"47834",
    "sg:province":"IN",
    "sg:tags":[
        "limousine"
    ],
    "wof:name":"Luxury Limousine Svc",
    "wof:placetype":"venue"
},
  "geometry": {"coordinates":[-87.125134,39.523662],"type":"Point"}
}