{
  "type": "Feature",
  "properties": {
    "addr:full":"1500 Osolo Rd Elkhart IN 46514",
    "addr:housenumber":"1500",
    "addr:postcode":"46514",
    "addr:street":"Osolo Rd",
    "iso:country":"US",
    "sg:address":"1500 Osolo Rd",
    "sg:city":"Elkhart",
    "sg:classifiers":[
        {
            "category":"Restaurant",
            "type":"Food & Drink"
        }
    ],
    "sg:phone":"+1 574 266 8088",
    "sg:postcode":"46514",
    "sg:province":"IN",
    "wof:name":"E-L-Camino-Real",
    "wof:placetype":"venue"
},
  "geometry": {"coordinates":[-85.94669399999999,41.703264],"type":"Point"}
}