{
  "type": "Feature",
  "properties": {
    "iso:country":"US",
    "sg:address":"619 W 10th St",
    "sg:city":"Jonesboro",
    "sg:classifiers":[
        {
            "category":"Professional",
            "subcategory":"Engineering",
            "type":"Services"
        }
    ],
    "sg:phone":"+1 765 677 9152",
    "sg:postcode":"46938",
    "sg:province":"IN",
    "wof:name":"Daniel Jones",
    "wof:placetype":"venue"
},
  "geometry": {"coordinates":[-85.637344,40.476135],"type":"Point"}
}