{
  "type": "Feature",
  "properties": {
    "addr:full":"6925 Bloomfield Dr E Indianapolis IN 46259",
    "addr:housenumber":"6925",
    "addr:postcode":"46259",
    "addr:street":"Bloomfield Dr E",
    "iso:country":"US",
    "sg:address":"6925 Bloomfield Dr E",
    "sg:city":"Indianapolis",
    "sg:classifiers":[
        {
            "category":"Building & Trades",
            "subcategory":"Cleaning & Sanitation",
            "type":"Services"
        }
    ],
    "sg:phone":"+1 317 862 1787",
    "sg:postcode":"46259",
    "sg:province":"IN",
    "sg:tags":[
        "janitor"
    ],
    "wof:name":"Smith Cleaning Svc",
    "wof:placetype":"venue"
},
  "geometry": {"coordinates":[-85.96247700000001,39.667606],"type":"Point"}
}