{
  "type": "Feature",
  "properties": {
    "iso:country":"US",
    "sg:address":"5985 E 1015 N",
    "sg:city":"Demotte",
    "sg:classifiers":[
        {
            "category":"Health Services",
            "subcategory":"Doctor",
            "type":"Services"
        }
    ],
    "sg:phone":"+1 219 345 4843",
    "sg:postcode":"46310",
    "sg:province":"IN",
    "sg:tags":[
        "physician",
        "clinic",
        "surgeon"
    ],
    "wof:name":"Lake Holiday Health Ctr",
    "wof:placetype":"venue"
},
  "geometry": {"coordinates":[-87.276095,41.146737],"type":"Point"}
}