{
  "type": "Feature",
  "properties": {
    "iso:country":"US",
    "sg:address":"221 N Madison St",
    "sg:city":"Muncie",
    "sg:classifiers":[
        {
            "category":"Retail",
            "subcategory":"Repair Shop",
            "type":"Services"
        }
    ],
    "sg:phone":"+1 765 288 7271",
    "sg:postcode":"47305",
    "sg:province":"IN",
    "sg:tags":[
        "lock",
        "locksmith"
    ],
    "wof:name":"Jones Locksmiths",
    "wof:placetype":"venue"
},
  "geometry": {"coordinates":[-85.381769,40.195156],"type":"Point"}
}