{
  "type": "Feature",
  "properties": {
    "iso:country":"US",
    "sg:address":"3960 Wallace Pkwy",
    "sg:city":"Gary",
    "sg:classifiers":[
        {
            "category":"Manufacturing",
            "subcategory":"Signs",
            "type":"Manufacturing & Wholesale Goods"
        }
    ],
    "sg:phone":"+1 219 980 1733",
    "sg:postcode":"46408",
    "sg:province":"IN",
    "wof:name":"A-1 Neon",
    "wof:placetype":"venue"
},
  "geometry": {"coordinates":[-87.383062,41.546622],"type":"Point"}
}