{
  "type": "Feature",
  "properties": {
    "iso:country":"US",
    "sg:address":"113 N Jackson St",
    "sg:city":"Huntingburg",
    "sg:classifiers":[
        {
            "category":"Education",
            "subcategory":"School",
            "type":"Public Place"
        }
    ],
    "sg:phone":"+1 812 683 3971",
    "sg:postcode":"47542",
    "sg:province":"IN",
    "wof:name":"Southwest Dubois Cnty Schl",
    "wof:placetype":"venue"
},
  "geometry": {"coordinates":[-86.95377499999999,38.292668],"type":"Point"}
}