{
  "type": "Feature",
  "properties": {
    "iso:country":"US",
    "sg:address":"100 E Main St",
    "sg:city":"Atlanta",
    "sg:classifiers":[
        {
            "category":"Travel",
            "subcategory":"Hotels & Motels",
            "type":"Entertainment"
        }
    ],
    "sg:phone":"+1 765 292 2600",
    "sg:postcode":"46031",
    "sg:province":"IN",
    "sg:tags":[
        "breakfast",
        "accommodation",
        "bed"
    ],
    "wof:name":"Walton House Bed & Breakfast",
    "wof:placetype":"venue"
},
  "geometry": {"coordinates":[-86.025628,40.216072],"type":"Point"}
}