{
  "type": "Feature",
  "properties": {
    "iso:country":"US",
    "sg:address":"814 E McGalliard Rd",
    "sg:city":"Muncie",
    "sg:classifiers":[
        {
            "category":"Autos & Motor Vehicles",
            "subcategory":"Auto Supplies",
            "type":"Retail Goods"
        }
    ],
    "sg:phone":"+1 765 747 0910",
    "sg:postcode":"47303",
    "sg:province":"IN",
    "sg:tags":[
        "automobile",
        "alarm"
    ],
    "wof:name":"Great Sounds Inc",
    "wof:placetype":"venue"
},
  "geometry": {"coordinates":[-85.375491,40.219106],"type":"Point"}
}