{
  "type": "Feature",
  "properties": {
    "iso:country":"US",
    "sg:address":"1571 E 85th Ave",
    "sg:city":"Merrillville",
    "sg:classifiers":[
        {
            "category":"Government",
            "subcategory":"Court House",
            "type":"Public Place"
        }
    ],
    "sg:phone":"+1 219 681 7000",
    "sg:postcode":"46410",
    "sg:province":"IN",
    "sg:tags":[
        "federal"
    ],
    "wof:name":"US District Court Clerk",
    "wof:placetype":"venue"
},
  "geometry": {"coordinates":[-87.317225,41.463208],"type":"Point"}
}