{
  "type": "Feature",
  "properties": {
    "iso:country":"US",
    "sg:address":"956 Beechwood Ave",
    "sg:city":"Middletown",
    "sg:classifiers":[
        {
            "category":"Banks & Credit Unions",
            "subcategory":"Bank",
            "type":"Services"
        }
    ],
    "sg:phone":"+1 765 354 2275",
    "sg:postcode":"47356",
    "sg:province":"IN",
    "wof:name":"Ameriana Bank & Trust",
    "wof:placetype":"venue"
},
  "geometry": {"coordinates":[-85.538659,40.061308],"type":"Point"}
}