{
  "type": "Feature",
  "properties": {
    "iso:country":"US",
    "sg:address":"110 W 78th Ave",
    "sg:city":"Merrillville",
    "sg:classifiers":[
        {
            "category":"Insurance",
            "subcategory":"Insurance Agent",
            "type":"Services"
        }
    ],
    "sg:phone":"+1 219 736 2303",
    "sg:postcode":"46410",
    "sg:province":"IN",
    "wof:name":"Consolidated Inc Insurance",
    "wof:placetype":"venue"
},
  "geometry": {"coordinates":[-87.34150699999999,41.476112],"type":"Point"}
}