{
  "type": "Feature",
  "properties": {
    "iso:country":"US",
    "sg:address":"792 Broadway",
    "sg:city":"Gary",
    "sg:classifiers":[
        {
            "category":"Banks & Credit Unions",
            "subcategory":"Bank",
            "type":"Services"
        }
    ],
    "sg:phone":"+1 219 882 7898",
    "sg:postcode":"46402",
    "sg:province":"IN",
    "sg:tags":[
        "currency",
        "exchange"
    ],
    "wof:name":"Currency Exchange",
    "wof:placetype":"venue"
},
  "geometry": {"coordinates":[-87.3372,41.598277],"type":"Point"}
}