{
  "type": "Feature",
  "properties": {
    "iso:country":"US",
    "sg:address":"620 H St",
    "sg:city":"Bedford",
    "sg:classifiers":[
        {
            "category":"Mining & Drilling",
            "type":"Manufacturing & Wholesale Goods"
        }
    ],
    "sg:phone":"+1 812 277 1793",
    "sg:postcode":"47421",
    "sg:province":"IN",
    "sg:tags":[
        "quarry"
    ],
    "wof:name":"Aggregate Manufacturing Intl",
    "wof:placetype":"venue"
},
  "geometry": {"coordinates":[-86.481556,38.87287],"type":"Point"}
}