{
  "type": "Feature",
  "properties": {
    "iso:country":"US",
    "sg:address":"1414 H St",
    "sg:city":"Bedford",
    "sg:classifiers":[
        {
            "category":"Real Estate",
            "subcategory":"Real Estate Agent",
            "type":"Services"
        }
    ],
    "sg:phone":"+1 812 275 5247",
    "sg:postcode":"47421",
    "sg:province":"IN",
    "sg:tags":[
        "management"
    ],
    "wof:name":"S & S Management LLC",
    "wof:placetype":"venue"
},
  "geometry": {"coordinates":[-86.481125,38.86313],"type":"Point"}
}