{
  "type": "Feature",
  "properties": {
    "iso:country":"US",
    "sg:address":"45 W Carey St",
    "sg:city":"Knightstown",
    "sg:classifiers":[
        {
            "category":"Home & Garden",
            "subcategory":"Building Materials",
            "type":"Retail Goods"
        }
    ],
    "sg:phone":"+1 765 345 5181",
    "sg:postcode":"46148",
    "sg:province":"IN",
    "sg:tags":[
        "lumber"
    ],
    "wof:name":"Tweedy Lumber Do-It Ctr",
    "wof:placetype":"venue"
},
  "geometry": {"coordinates":[-85.528144,39.798263],"type":"Point"}
}