{
  "type": "Feature",
  "properties": {
    "iso:country":"US",
    "sg:address":"812 S Washington St",
    "sg:city":"Swayzee",
    "sg:classifiers":[
        {
            "category":"Shopping",
            "subcategory":"Tobacco",
            "type":"Retail Goods"
        }
    ],
    "sg:phone":"+1 765 922 7087",
    "sg:postcode":"46986",
    "sg:province":"IN",
    "sg:tags":[
        "cigarette",
        "cigar",
        "dealer"
    ],
    "wof:name":"Low Bobs Disc Tobacco Co",
    "wof:placetype":"venue"
},
  "geometry": {"coordinates":[-85.825508,40.500996],"type":"Point"}
}