{
  "type": "Feature",
  "properties": {
    "iso:country":"US",
    "sg:address":"10511 W Appaloosa Rd",
    "sg:city":"Stilesville",
    "sg:classifiers":[
        {
            "category":"Wholesale",
            "subcategory":"Home Furnishings",
            "type":"Manufacturing & Wholesale Goods"
        }
    ],
    "sg:phone":"+1 317 996 3359",
    "sg:postcode":"46180",
    "sg:province":"IN",
    "sg:tags":[
        "mat",
        "matting"
    ],
    "wof:name":"Step Ahead Mat Svc",
    "wof:placetype":"venue"
},
  "geometry": {"coordinates":[-86.627748,39.586592],"type":"Point"}
}