{
  "type": "Feature",
  "properties": {
    "iso:country":"US",
    "sg:address":"2545 Lafayette Rd",
    "sg:city":"Indianapolis",
    "sg:classifiers":[
        {
            "category":"Autos & Motor Vehicles",
            "subcategory":"Automobile Sales",
            "type":"Retail Goods"
        }
    ],
    "sg:phone":"+1 317 924 5666",
    "sg:postcode":"46222",
    "sg:province":"IN",
    "sg:tags":[
        "car",
        "dealer"
    ],
    "wof:name":"Ali's Auto Sales",
    "wof:placetype":"venue"
},
  "geometry": {"coordinates":[-86.21346,39.802516],"type":"Point"}
}