{
  "type": "Feature",
  "properties": {
    "iso:country":"US",
    "sg:address":"4310 Guion Rd",
    "sg:city":"Indianapolis",
    "sg:classifiers":[
        {
            "category":"Wholesale",
            "subcategory":"Durable Goods & Equipment",
            "type":"Manufacturing & Wholesale Goods"
        }
    ],
    "sg:phone":"+1 317 293 5700",
    "sg:postcode":"46254",
    "sg:province":"IN",
    "sg:tags":[
        "representative",
        "manufacturer"
    ],
    "wof:name":"Thermonet USA",
    "wof:placetype":"venue"
},
  "geometry": {"coordinates":[-86.226907,39.834056],"type":"Point"}
}