{
  "type": "Feature",
  "properties": {
    "iso:country":"US",
    "sg:address":"3038 S Western Ave",
    "sg:city":"Marion",
    "sg:classifiers":[
        {
            "category":"Restaurant",
            "type":"Food & Drink"
        }
    ],
    "sg:phone":"+1 765 651 0668",
    "sg:postcode":"46953",
    "sg:province":"IN",
    "wof:name":"Lo-Y-Lo Chinese Restaurant",
    "wof:placetype":"venue"
},
  "geometry": {"coordinates":[-85.673801,40.533103],"type":"Point"}
}