{
  "type": "Feature",
  "properties": {
    "iso:country":"US",
    "sg:address":"423 Washington St",
    "sg:city":"Columbus",
    "sg:classifiers":[
        {
            "category":"Shopping",
            "type":"Retail Goods"
        }
    ],
    "sg:phone":"+1 812 372 4233",
    "sg:postcode":"47201",
    "sg:province":"IN",
    "sg:tags":[
        "art",
        "gallery",
        "dealer"
    ],
    "wof:name":"Gallery 423",
    "wof:placetype":"venue"
},
  "geometry": {"coordinates":[-85.921031,39.203259],"type":"Point"}
}