{
  "type": "Feature",
  "properties": {
    "addr:full":"2420 Lincoln St Highland IN 46322",
    "addr:housenumber":"2420",
    "addr:postcode":"46322",
    "addr:street":"Lincoln St",
    "iso:country":"US",
    "sg:address":"2420 Lincoln St",
    "sg:city":"Highland",
    "sg:classifiers":[
        {
            "category":"Organizations",
            "subcategory":"Religious Organization",
            "type":"Services"
        }
    ],
    "sg:phone":"+1 219 838 6986",
    "sg:postcode":"46322",
    "sg:province":"IN",
    "sg:tags":[
        "church"
    ],
    "wof:name":"First Church Of Christ",
    "wof:placetype":"venue"
},
  "geometry": {"coordinates":[-87.47021700000001,41.551993],"type":"Point"}
}