{
  "type": "Feature",
  "properties": {
    "iso:country":"US",
    "sg:address":"7722 Inverness Dr",
    "sg:city":"Indianapolis",
    "sg:classifiers":[
        {
            "category":"Building & Trades",
            "subcategory":"Plumbing",
            "type":"Services"
        }
    ],
    "sg:phone":"+1 317 881 1400",
    "sg:postcode":"46237",
    "sg:province":"IN",
    "sg:tags":[
        "plumbing",
        "contractor"
    ],
    "wof:name":"Eagle Sewer & Drain Svc",
    "wof:placetype":"venue"
},
  "geometry": {"coordinates":[-86.04837499999999,39.654668],"type":"Point"}
}