{
  "type": "Feature",
  "properties": {
    "iso:country":"US",
    "sg:address":"802 Ernest St",
    "sg:city":"Auburn",
    "sg:classifiers":[
        {
            "category":"Wholesale",
            "subcategory":"Auto Parts",
            "type":"Manufacturing & Wholesale Goods"
        }
    ],
    "sg:phone":"+1 260 927 1725",
    "sg:postcode":"46706",
    "sg:province":"IN",
    "sg:tags":[
        "used"
    ],
    "wof:name":"Micks Hy Preformance",
    "wof:placetype":"venue"
},
  "geometry": {"coordinates":[-85.07338300000001,41.372899],"type":"Point"}
}