{
  "type": "Feature",
  "properties": {
    "iso:country":"US",
    "sg:address":"1123 N 9th St",
    "sg:city":"Lafayette",
    "sg:classifiers":[
        {
            "category":"Building & Trades",
            "subcategory":"Cleaning & Sanitation",
            "type":"Services"
        }
    ],
    "sg:phone":"+1 765 742 5326",
    "sg:postcode":"47904",
    "sg:province":"IN",
    "wof:name":"Revalee Development Group",
    "wof:placetype":"venue"
},
  "geometry": {"coordinates":[-86.886961,40.428586],"type":"Point"}
}