{
  "type": "Feature",
  "properties": {
    "iso:country":"US",
    "sg:address":"9025 Seabreeze Cir",
    "sg:city":"Indianapolis",
    "sg:classifiers":[
        {
            "category":"Organizations",
            "subcategory":"Religious Organization",
            "type":"Services"
        }
    ],
    "sg:phone":"+1 317 849 0866",
    "sg:postcode":"46256",
    "sg:province":"IN",
    "wof:name":"Dr Russell Blowers",
    "wof:placetype":"venue"
},
  "geometry": {"coordinates":[-85.98936399999999,39.919084],"type":"Point"}
}