{
  "type": "Feature",
  "properties": {
    "iso:country":"US",
    "sg:address":"1020 W 5th Ave",
    "sg:city":"Gary",
    "sg:classifiers":[
        {
            "category":"Building & Trades",
            "subcategory":"Electrical",
            "type":"Services"
        }
    ],
    "sg:phone":"+1 219 881 0024",
    "sg:postcode":"46402",
    "sg:province":"IN",
    "sg:tags":[
        "electric",
        "contractor"
    ],
    "wof:name":"D & J Electrical Specialties",
    "wof:placetype":"venue"
},
  "geometry": {"coordinates":[-87.350723,41.602082],"type":"Point"}
}