{
  "type": "Feature",
  "properties": {
    "iso:country":"US",
    "sg:address":"8801 E Milner Ave",
    "sg:city":"Terre Haute",
    "sg:classifiers":[
        {
            "category":"Professional",
            "subcategory":"Business Services",
            "type":"Services"
        }
    ],
    "sg:phone":"+1 812 877 1531",
    "sg:postcode":"47803",
    "sg:province":"IN",
    "wof:name":"Plumbers Stm Fitters Local 157",
    "wof:placetype":"venue"
},
  "geometry": {"coordinates":[-87.27361000000001,39.477083],"type":"Point"}
}