{
  "type": "Feature",
  "properties": {
    "iso:country":"US",
    "sg:address":"6875 Corydon Junction Rd NE",
    "sg:city":"New Salisbury",
    "sg:classifiers":[
        {
            "category":"Organizations",
            "subcategory":"Religious Organization",
            "type":"Services"
        }
    ],
    "sg:phone":"+1 812 366 3803",
    "sg:postcode":"47161",
    "sg:province":"IN",
    "sg:tags":[
        "church"
    ],
    "wof:name":"New Salisbury Full Gospel Chr",
    "wof:placetype":"venue"
},
  "geometry": {"coordinates":[-86.10178500000001,38.300588],"type":"Point"}
}