{
  "type": "Feature",
  "properties": {
    "iso:country":"US",
    "sg:address":"8860 W 750 N",
    "sg:city":"Shipshewana",
    "sg:classifiers":[
        {
            "category":"Manufacturing",
            "subcategory":"Metals",
            "type":"Manufacturing & Wholesale Goods"
        }
    ],
    "sg:phone":"+1 260 768 4415",
    "sg:postcode":"46565",
    "sg:province":"IN",
    "sg:tags":[
        "fabricated",
        "structural"
    ],
    "wof:name":"Smith Welding",
    "wof:placetype":"venue"
},
  "geometry": {"coordinates":[-85.599272,41.748392],"type":"Point"}
}