{
  "type": "Feature",
  "properties": {
    "iso:country":"US",
    "sg:address":"404 E 2nd St",
    "sg:city":"Seymour",
    "sg:classifiers":[
        {
            "category":"Shopping",
            "subcategory":"Jewelry",
            "type":"Retail Goods"
        }
    ],
    "sg:phone":"+1 812 522 3228",
    "sg:postcode":"47274",
    "sg:province":"IN",
    "sg:tags":[
        "jeweler"
    ],
    "wof:name":"Ellis Jewelers Inc",
    "wof:placetype":"venue"
},
  "geometry": {"coordinates":[-85.884328,38.960431],"type":"Point"}
}