{
  "type": "Feature",
  "properties": {
    "iso:country":"US",
    "sg:address":"541 Ada St",
    "sg:city":"Francesville",
    "sg:classifiers":[
        {
            "category":"Personal",
            "subcategory":"Beauty Salon",
            "type":"Services"
        }
    ],
    "sg:phone":"+1 219 567 2117",
    "sg:postcode":"47946",
    "sg:province":"IN",
    "wof:name":"New Attitudes Styling",
    "wof:placetype":"venue"
},
  "geometry": {"coordinates":[-86.876853,40.988562],"type":"Point"}
}