{
  "type": "Feature",
  "properties": {
    "iso:country":"US",
    "sg:address":"620 E Diamond Ave",
    "sg:city":"Evansville",
    "sg:classifiers":[
        {
            "category":"Home & Garden",
            "subcategory":"Carpets & Floor Coverings",
            "type":"Retail Goods"
        }
    ],
    "sg:phone":"+1 812 479 8829",
    "sg:postcode":"47711",
    "sg:province":"IN",
    "sg:tags":[
        "dealer",
        "rug"
    ],
    "wof:name":"Carpet One Floortiles",
    "wof:placetype":"venue"
},
  "geometry": {"coordinates":[-87.553996,37.999569],"type":"Point"}
}