{
  "type": "Feature",
  "properties": {
    "addr:full":"8145 S Strain Ridge Rd Bloomington IN 47401",
    "addr:housenumber":"8145",
    "addr:postcode":"47401",
    "addr:street":"S Strain Ridge Rd",
    "iso:country":"US",
    "sg:address":"8145 S Strain Ridge Rd",
    "sg:city":"Bloomington",
    "sg:classifiers":[
        {
            "category":"Building & Trades",
            "subcategory":"Plumbing",
            "type":"Services"
        }
    ],
    "sg:phone":"+1 812 824 6947",
    "sg:postcode":"47401",
    "sg:province":"IN",
    "sg:tags":[
        "tank",
        "septic"
    ],
    "wof:name":"Brownie's Septic Svc",
    "wof:placetype":"venue"
},
  "geometry": {"coordinates":[-86.50787200000001,39.055127],"type":"Point"}
}