{
  "type": "Feature",
  "properties": {
    "iso:country":"US",
    "sg:address":"711 Green Rd",
    "sg:city":"Madison",
    "sg:classifiers":[
        {
            "category":"Professional",
            "subcategory":"Management & Consulting",
            "type":"Services"
        }
    ],
    "sg:phone":"+1 812 265 3536",
    "sg:postcode":"47250",
    "sg:province":"IN",
    "sg:tags":[
        "consultant",
        "restoration",
        "historical"
    ],
    "wof:name":"Historic Site Restoration Dept",
    "wof:placetype":"venue"
},
  "geometry": {"coordinates":[-85.40008400000001,38.761603],"type":"Point"}
}