{
  "type": "Feature",
  "properties": {
    "iso:country":"US",
    "sg:address":"54 N Main St",
    "sg:city":"Frankfort",
    "sg:classifiers":[
        {
            "category":"Shopping",
            "subcategory":"Jewelry",
            "type":"Retail Goods"
        }
    ],
    "sg:phone":"+1 765 654 4511",
    "sg:postcode":"46041",
    "sg:province":"IN",
    "sg:tags":[
        "jeweler"
    ],
    "wof:name":"Dan Caddell Jeweler",
    "wof:placetype":"venue"
},
  "geometry": {"coordinates":[-86.512024,40.281097],"type":"Point"}
}