{
  "type": "Feature",
  "properties": {
    "addr:full":"410 W 19th St Auburn IN 46706",
    "addr:housenumber":"410",
    "addr:postcode":"46706",
    "addr:street":"W 19Th St",
    "iso:country":"US",
    "sg:address":"410 W 19th St",
    "sg:city":"Auburn",
    "sg:classifiers":[
        {
            "category":"Building & Trades",
            "subcategory":"Landscaping Services",
            "type":"Services"
        }
    ],
    "sg:phone":"+1 260 570 6646",
    "sg:postcode":"46706",
    "sg:province":"IN",
    "sg:tags":[
        "landscape"
    ],
    "wof:name":"Smokeys Perennial Landscape",
    "wof:placetype":"venue"
},
  "geometry": {"coordinates":[-85.062192,41.360332],"type":"Point"}
}