{
  "type": "Feature",
  "properties": {
    "iso:country":"US",
    "sg:address":"151 N Van Buren St",
    "sg:city":"Nashville",
    "sg:classifiers":[
        {
            "category":"Recreation",
            "type":"Entertainment"
        }
    ],
    "sg:phone":"+1 812 988 8775",
    "sg:postcode":"47448",
    "sg:province":"IN",
    "sg:tags":[
        "psychic",
        "medium"
    ],
    "wof:name":"Norma Reigle Palm Reader",
    "wof:placetype":"venue"
},
  "geometry": {"coordinates":[-86.246862,39.2075],"type":"Point"}
}