{
  "type": "Feature",
  "properties": {
    "iso:country":"US",
    "sg:address":"119 E Center St",
    "sg:city":"Warsaw",
    "sg:classifiers":[
        {
            "category":"Organizations",
            "subcategory":"Non-profit Organization",
            "type":"Services"
        }
    ],
    "sg:phone":"+1 574 269 9446",
    "sg:postcode":"46580",
    "sg:province":"IN",
    "wof:name":"F I Saemann Foundation",
    "wof:placetype":"venue"
},
  "geometry": {"coordinates":[-85.856461,41.238169],"type":"Point"}
}