{
  "type": "Feature",
  "properties": {
    "addr:full":"13190 Hazel Dell Pkwy Carmel IN 46033",
    "addr:housenumber":"13190",
    "addr:postcode":"46033",
    "addr:street":"Hazel Dell Pkwy",
    "iso:country":"US",
    "sg:address":"13190 Hazel Dell Pkwy",
    "sg:city":"Carmel",
    "sg:classifiers":[
        {
            "category":"Personal",
            "subcategory":"Nail Salon",
            "type":"Services"
        }
    ],
    "sg:phone":"+1 317 575 8580",
    "sg:postcode":"46033",
    "sg:province":"IN",
    "wof:name":"Luxe Nails",
    "wof:placetype":"venue"
},
  "geometry": {"coordinates":[-86.070668,39.980521],"type":"Point"}
}