{
  "type": "Feature",
  "properties": {
    "iso:country":"US",
    "sg:address":"127 W 8th St",
    "sg:city":"Auburn",
    "sg:classifiers":[
        {
            "category":"Shopping",
            "subcategory":"Gifts & Souvenirs",
            "type":"Retail Goods"
        }
    ],
    "sg:phone":"+1 260 925 5483",
    "sg:postcode":"46706",
    "sg:province":"IN",
    "sg:tags":[
        "shop"
    ],
    "wof:name":"Dauenhauer Glass Co Inc",
    "wof:placetype":"venue"
},
  "geometry": {"coordinates":[-85.056773,41.366286],"type":"Point"}
}