{
  "type": "Feature",
  "properties": {
    "iso:country":"US",
    "sg:address":"915 Kasting Rd",
    "sg:city":"Seymour",
    "sg:classifiers":[
        {
            "category":"Organizations",
            "subcategory":"Religious Organization",
            "type":"Services"
        }
    ],
    "sg:phone":"+1 812 523 3335",
    "sg:postcode":"47274",
    "sg:province":"IN",
    "sg:tags":[
        "church"
    ],
    "wof:name":"Seymour Christian Church",
    "wof:placetype":"venue"
},
  "geometry": {"coordinates":[-85.899403,38.945529],"type":"Point"}
}