{
  "type": "Feature",
  "properties": {
    "iso:country":"US",
    "sg:address":"53132 Co Rd 43",
    "sg:city":"Middlebury",
    "sg:classifiers":[
        {
            "category":"Building & Trades",
            "subcategory":"Construction",
            "type":"Services"
        }
    ],
    "sg:phone":"+1 574 825 4337",
    "sg:postcode":"46540",
    "sg:province":"IN",
    "sg:tags":[
        "painter"
    ],
    "wof:name":"Stoltzfus Quality Painting Inc",
    "wof:placetype":"venue"
},
  "geometry": {"coordinates":[-85.67425,41.724056],"type":"Point"}
}