{
  "type": "Feature",
  "properties": {
    "iso:country":"US",
    "sg:address":"1012 Hartford Cir",
    "sg:city":"Lawrenceburg",
    "sg:classifiers":[
        {
            "category":"Building & Trades",
            "subcategory":"Construction",
            "type":"Services"
        }
    ],
    "sg:phone":"+1 513 564 8103",
    "sg:postcode":"47025",
    "sg:province":"IN",
    "sg:tags":[
        "house"
    ],
    "wof:name":"Cw Contruction",
    "wof:placetype":"venue"
},
  "geometry": {"coordinates":[-84.83898,39.148717],"type":"Point"}
}