{
  "type": "Feature",
  "properties": {
    "iso:country":"US",
    "sg:address":"23845 Chris Ln",
    "sg:city":"Lawrenceburg",
    "sg:classifiers":[
        {
            "category":"Building & Trades",
            "subcategory":"Construction",
            "type":"Services"
        }
    ],
    "sg:phone":"+1 812 637 1605",
    "sg:postcode":"47025",
    "sg:province":"IN",
    "sg:tags":[
        "paving",
        "contractor"
    ],
    "wof:name":"Southwest Paving",
    "wof:placetype":"venue"
},
  "geometry": {"coordinates":[-84.857811,39.216683],"type":"Point"}
}