{
  "type": "Feature",
  "properties": {
    "iso:country":"US",
    "sg:address":"817 Millbrook Ln",
    "sg:city":"Kokomo",
    "sg:classifiers":[
        {
            "category":"Building & Trades",
            "subcategory":"Plumbing",
            "type":"Services"
        }
    ],
    "sg:phone":"+1 765 457 1527",
    "sg:postcode":"46901",
    "sg:province":"IN",
    "sg:tags":[
        "mechanical",
        "contractor"
    ],
    "wof:name":"BMD Contractors Inc",
    "wof:placetype":"venue"
},
  "geometry": {"coordinates":[-86.152031,40.477749],"type":"Point"}
}