{
  "type": "Feature",
  "properties": {
    "iso:country":"US",
    "sg:address":"4805 W Chesterfield Dr",
    "sg:city":"Indianapolis",
    "sg:classifiers":[
        {
            "category":"Organizations",
            "subcategory":"Religious Organization",
            "type":"Services"
        }
    ],
    "sg:phone":"+1 317 787 4948",
    "sg:postcode":"46227",
    "sg:province":"IN",
    "wof:name":"Hobson Wm J 2d Rev",
    "wof:placetype":"venue"
},
  "geometry": {"coordinates":[-86.146911,39.696081],"type":"Point"}
}