{
  "type": "Feature",
  "properties": {
    "iso:country":"US",
    "sg:address":"103 S Prairie St",
    "sg:city":"Brookston",
    "sg:classifiers":[
        {
            "category":"Banks & Credit Unions",
            "subcategory":"Bank",
            "type":"Services"
        }
    ],
    "sg:phone":"+1 765 563 6400",
    "sg:postcode":"47923",
    "sg:province":"IN",
    "wof:name":"Lafayette Bank & Trust Co",
    "wof:placetype":"venue"
},
  "geometry": {"coordinates":[-86.868684,40.604659],"type":"Point"}
}