{
  "type": "Feature",
  "properties": {
    "iso:country":"US",
    "sg:address":"1733 Mount Gilead Rd",
    "sg:city":"Boonville",
    "sg:classifiers":[
        {
            "category":"Building & Trades",
            "subcategory":"Pest Control",
            "type":"Services"
        }
    ],
    "sg:phone":"+1 812 897 4008",
    "sg:postcode":"47601",
    "sg:province":"IN",
    "wof:name":"Daves Exterminating Co",
    "wof:placetype":"venue"
},
  "geometry": {"coordinates":[-87.274468,38.010924],"type":"Point"}
}