{
  "type": "Feature",
  "properties": {
    "iso:country":"US",
    "sg:address":"2111 W Alto Rd",
    "sg:city":"Kokomo",
    "sg:classifiers":[
        {
            "category":"Manufacturing",
            "subcategory":"Printing",
            "type":"Manufacturing & Wholesale Goods"
        }
    ],
    "sg:phone":"+1 765 453 6161",
    "sg:postcode":"46902",
    "sg:province":"IN",
    "sg:tags":[
        "commercial"
    ],
    "sg:website":"www.hpsprayercards.com",
    "wof:name":"Howard Print Shop",
    "wof:placetype":"venue"
},
  "geometry": {"coordinates":[-86.167203,40.439972],"type":"Point"}
}