{
  "type": "Feature",
  "properties": {
    "iso:country":"US",
    "sg:address":"495 W McKee St",
    "sg:city":"Greensburg",
    "sg:classifiers":[
        {
            "category":"Manufacturing",
            "subcategory":"Tools & Machinery",
            "type":"Manufacturing & Wholesale Goods"
        }
    ],
    "sg:phone":"+1 812 663 3213",
    "sg:postcode":"47240",
    "sg:province":"IN",
    "sg:tags":[
        "equipment",
        "infrared"
    ],
    "sg:website":"www.blasdel.net",
    "wof:name":"Blasdel Enterprises Inc",
    "wof:placetype":"venue"
},
  "geometry": {"coordinates":[-85.49143599999999,39.33466],"type":"Point"}
}