{
  "type": "Feature",
  "properties": {
    "iso:country":"US",
    "sg:address":"6816 Wilmington Pike",
    "sg:city":"Aurora",
    "sg:classifiers":[
        {
            "category":"Building & Trades",
            "subcategory":"Construction",
            "type":"Services"
        }
    ],
    "sg:phone":"+1 812 926 9622",
    "sg:postcode":"47001",
    "sg:province":"IN",
    "sg:tags":[
        "roofing",
        "contractor"
    ],
    "wof:name":"Brown Roofing Co",
    "wof:placetype":"venue"
},
  "geometry": {"coordinates":[-84.944294,39.062202],"type":"Point"}
}