{
  "type": "Feature",
  "properties": {
    "iso:country":"US",
    "sg:address":"3616 W 3rd St",
    "sg:city":"Bloomington",
    "sg:classifiers":[
        {
            "category":"Restaurant",
            "type":"Food & Drink"
        }
    ],
    "sg:phone":"+1 812 323 1108",
    "sg:postcode":"47404",
    "sg:province":"IN",
    "wof:name":"Great Taste Buffet",
    "wof:placetype":"venue"
},
  "geometry": {"coordinates":[-86.5802,39.1647],"type":"Point"}
}