{
  "type": "Feature",
  "properties": {
    "iso:country":"US",
    "sg:address":"4204 N College Ave",
    "sg:city":"Indianapolis",
    "sg:classifiers":[
        {
            "category":"Building & Trades",
            "subcategory":"Construction",
            "type":"Services"
        }
    ],
    "sg:phone":"+1 317 920 0598",
    "sg:postcode":"46205",
    "sg:province":"IN",
    "sg:tags":[
        "elevator"
    ],
    "wof:name":"Elevator Building",
    "wof:placetype":"venue"
},
  "geometry": {"coordinates":[-86.145225,39.835901],"type":"Point"}
}