{
  "type": "Feature",
  "properties": {
    "iso:country":"US",
    "sg:address":"100 Michigan St",
    "sg:city":"Winamac",
    "sg:classifiers":[
        {
            "category":"Wholesale",
            "subcategory":"Beer",
            "type":"Manufacturing & Wholesale Goods"
        }
    ],
    "sg:phone":"+1 574 946 6666",
    "sg:postcode":"46989",
    "sg:province":"IN",
    "sg:tags":[
        "ale"
    ],
    "wof:name":"Tippecanoe Beverages Inc",
    "wof:placetype":"venue"
},
  "geometry": {"coordinates":[-85.495186,40.472569],"type":"Point"}
}