{
  "type": "Feature",
  "properties": {
    "iso:country":"US",
    "sg:address":"7940 Calumet Ave",
    "sg:city":"Munster",
    "sg:classifiers":[
        {
            "category":"Autos & Motor Vehicles",
            "subcategory":"Automobile Sales",
            "type":"Retail Goods"
        }
    ],
    "sg:phone":"+1 219 836 2163",
    "sg:postcode":"46321",
    "sg:province":"IN",
    "sg:tags":[
        "truck"
    ],
    "wof:name":"Anderson Motors Inc",
    "wof:placetype":"venue"
},
  "geometry": {"coordinates":[-87.50910399999999,41.567249],"type":"Point"}
}