{
  "type": "Feature",
  "properties": {
    "iso:country":"US",
    "sg:address":"351 Gasoline Aly",
    "sg:city":"Indianapolis",
    "sg:classifiers":[
        {
            "category":"Autos & Motor Vehicles",
            "subcategory":"Automobile Sales",
            "type":"Retail Goods"
        }
    ],
    "sg:phone":"+1 317 486 1132",
    "sg:postcode":"46222",
    "sg:province":"IN",
    "sg:tags":[
        "performance",
        "race",
        "dealer"
    ],
    "wof:name":"Lewis Racing",
    "wof:placetype":"venue"
},
  "geometry": {"coordinates":[-86.234921,39.769173],"type":"Point"}
}