{
  "type": "Feature",
  "properties": {
    "iso:country":"US",
    "sg:address":"351 S Post Rd",
    "sg:city":"Indianapolis",
    "sg:classifiers":[
        {
            "category":"Professional",
            "subcategory":"Printing & Photocopies",
            "type":"Services"
        },
        {
            "category":"Shopping Center",
            "type":"Public Place"
        }
    ],
    "sg:phone":"+1 317 898 6688",
    "sg:postcode":"46219",
    "sg:province":"IN",
    "sg:tags":[
        "card",
        "printers-business"
    ],
    "wof:name":"Business Cards Tomorrow",
    "wof:placetype":"venue"
},
  "geometry": {"coordinates":[-86.009033,39.76524],"type":"Point"}
}