{
  "type": "Feature",
  "properties": {
    "iso:country":"US",
    "sg:address":"11360 Royal Ct",
    "sg:city":"Carmel",
    "sg:classifiers":[
        {
            "category":"Professional",
            "subcategory":"Advertising",
            "type":"Services"
        }
    ],
    "sg:phone":"+1 317 848 6214",
    "sg:postcode":"46032",
    "sg:province":"IN",
    "wof:name":"Cg Parkin Communications Inc",
    "wof:placetype":"venue"
},
  "geometry": {"coordinates":[-86.198643,39.949629],"type":"Point"}
}