{
  "type": "Feature",
  "properties": {
    "iso:country":"US",
    "sg:address":"8182 N 150 E",
    "sg:city":"Rushville",
    "sg:classifiers":[
        {
            "category":"Farming",
            "subcategory":"Farm",
            "type":"Manufacturing & Wholesale Goods"
        }
    ],
    "sg:phone":"+1 765 645 5289",
    "sg:postcode":"46173",
    "sg:province":"IN",
    "sg:tags":[
        "crop",
        "general"
    ],
    "wof:name":"Kenneth Brashaber",
    "wof:placetype":"venue"
},
  "geometry": {"coordinates":[-85.415496,39.737115],"type":"Point"}
}