{
  "type": "Feature",
  "properties": {
    "addr:full":"2001 E 62nd St Ste C Indianapolis IN 46220",
    "addr:housenumber":"2001",
    "addr:postcode":"46220",
    "addr:street":"E 62Nd St Ste C",
    "iso:country":"US",
    "sg:address":"2001 E 62nd St Ste C",
    "sg:city":"Indianapolis",
    "sg:classifiers":[
        {
            "category":"Personal",
            "subcategory":"Nail Salon",
            "type":"Services"
        }
    ],
    "sg:phone":"+1 317 475 9633",
    "sg:postcode":"46220",
    "sg:province":"IN",
    "wof:name":"Style Nail",
    "wof:placetype":"venue"
},
  "geometry": {"coordinates":[-86.12690000000001,39.868649],"type":"Point"}
}