{
  "type": "Feature",
  "properties": {
    "iso:country":"US",
    "sg:address":"501 Madison Ave",
    "sg:city":"Indianapolis",
    "sg:classifiers":[
        {
            "category":"Professional",
            "type":"Services"
        }
    ],
    "sg:phone":"+1 317 396 1000",
    "sg:postcode":"46225",
    "sg:province":"IN",
    "sg:tags":[
        "establishment"
    ],
    "wof:name":"Malichi International Inc",
    "wof:placetype":"venue"
},
  "geometry": {"coordinates":[-86.157529,39.759536],"type":"Point"}
}