{
  "type": "Feature",
  "properties": {
    "iso:country":"US",
    "sg:address":"557 Renz Ave",
    "sg:city":"Sellersburg",
    "sg:classifiers":[
        {
            "category":"Communications",
            "subcategory":"Radio Station",
            "type":"Services"
        }
    ],
    "sg:phone":"+1 812 248 0541",
    "sg:postcode":"47172",
    "sg:province":"IN",
    "sg:tags":[
        "company",
        "broadcasting"
    ],
    "wof:name":"WMPI Radio Station",
    "wof:placetype":"venue"
},
  "geometry": {"coordinates":[-85.753402,38.408585],"type":"Point"}
}