{
  "type": "Feature",
  "properties": {
    "iso:country":"US",
    "sg:address":"10022 Co Rd 10",
    "sg:city":"Middlebury",
    "sg:classifiers":[
        {
            "category":"Freight",
            "type":"Transportation"
        }
    ],
    "sg:phone":"+1 574 825 9241",
    "sg:postcode":"46540",
    "sg:province":"IN",
    "sg:tags":[
        "operator",
        "trucking"
    ],
    "wof:name":"Ed Baer",
    "wof:placetype":"venue"
},
  "geometry": {"coordinates":[-85.659058,41.703926],"type":"Point"}
}