{
  "type": "Feature",
  "properties": {
    "iso:country":"US",
    "sg:address":"3301 E 10th St",
    "sg:city":"Indianapolis",
    "sg:classifiers":[
        {
            "category":"Shopping",
            "type":"Retail Goods"
        }
    ],
    "sg:phone":"+1 317 351 1900",
    "sg:postcode":"46201",
    "sg:province":"IN",
    "sg:tags":[
        "coin",
        "dealer",
        "supply"
    ],
    "wof:name":"Universe Gold & Silver",
    "wof:placetype":"venue"
},
  "geometry": {"coordinates":[-86.10878599999999,39.781299],"type":"Point"}
}