{
  "type": "Feature",
  "properties": {
    "iso:country":"US",
    "sg:address":"741 S N St",
    "sg:city":"Richmond",
    "sg:classifiers":[
        {
            "category":"Retail",
            "subcategory":"Car Wash",
            "type":"Services"
        }
    ],
    "sg:phone":"+1 765 966 8331",
    "sg:postcode":"47374",
    "sg:province":"IN",
    "sg:tags":[
        "carwash"
    ],
    "wof:name":"Beauty Restored Auto Detail",
    "wof:placetype":"venue"
},
  "geometry": {"coordinates":[-84.894378,39.811535],"type":"Point"}
}