{
  "type": "Feature",
  "properties": {
    "iso:country":"US",
    "sg:address":"1522 Main St",
    "sg:city":"Anderson",
    "sg:classifiers":[
        {
            "category":"Shopping",
            "type":"Retail Goods"
        }
    ],
    "sg:phone":"+1 765 641 1534",
    "sg:postcode":"46016",
    "sg:province":"IN",
    "sg:tags":[
        "trophy",
        "medal",
        "award"
    ],
    "sg:website":"www.ramtrophies.com",
    "wof:name":"Ram Trophies & Awards",
    "wof:placetype":"venue"
},
  "geometry": {"coordinates":[-85.67806899999999,40.101312],"type":"Point"}
}