{
  "type": "Feature",
  "properties": {
    "iso:country":"US",
    "sg:address":"1575 Pleasant St",
    "sg:city":"Noblesville",
    "sg:classifiers":[
        {
            "category":"Building & Trades",
            "subcategory":"Construction",
            "type":"Services"
        }
    ],
    "sg:phone":"+1 317 776 6348",
    "sg:postcode":"46060",
    "sg:province":"IN",
    "sg:tags":[
        "marking",
        "maintenance",
        "parking"
    ],
    "sg:website":"www.cityofnoblesville.org",
    "wof:name":"Noblesville Street Dept",
    "wof:placetype":"venue"
},
  "geometry": {"coordinates":[-86.000823,40.03916],"type":"Point"}
}