{
  "type": "Feature",
  "properties": {
    "iso:country":"US",
    "sg:address":"8802 Madison Ave",
    "sg:city":"Indianapolis",
    "sg:classifiers":[
        {
            "category":"Wholesale",
            "subcategory":"Durable Goods & Equipment",
            "type":"Manufacturing & Wholesale Goods"
        }
    ],
    "sg:phone":"+1 317 865 1281",
    "sg:postcode":"46227",
    "sg:province":"IN",
    "sg:tags":[
        "representative",
        "manufacturer"
    ],
    "wof:name":"Donley Distribution",
    "wof:placetype":"venue"
},
  "geometry": {"coordinates":[-86.118021,39.63813],"type":"Point"}
}