{
  "type": "Feature",
  "properties": {
    "addr:full":"2816 Mitchell Rd Bedford IN 47421",
    "addr:housenumber":"2816",
    "addr:postcode":"47421",
    "addr:street":"Mitchell Rd",
    "iso:country":"US",
    "sg:address":"2816 Mitchell Rd",
    "sg:city":"Bedford",
    "sg:classifiers":[
        {
            "category":"Travel",
            "subcategory":"Hotels & Motels",
            "type":"Entertainment"
        }
    ],
    "sg:phone":"+1 812 275 7515",
    "sg:postcode":"47421",
    "sg:province":"IN",
    "wof:name":"Budget Inn Of Bedford",
    "wof:placetype":"venue"
},
  "geometry": {"coordinates":[-86.547196,38.86857],"type":"Point"}
}