{
  "type": "Feature",
  "properties": {
    "iso:country":"US",
    "sg:address":"6401 Westhaven Dr",
    "sg:city":"Indianapolis",
    "sg:classifiers":[
        {
            "category":"Wholesale",
            "subcategory":"Machinery & Supplies",
            "type":"Manufacturing & Wholesale Goods"
        }
    ],
    "sg:phone":"+1 317 290 0944",
    "sg:postcode":"46254",
    "sg:province":"IN",
    "sg:tags":[
        "audiometer"
    ],
    "wof:name":"Gordon N Stowe & Assoc",
    "wof:placetype":"venue"
},
  "geometry": {"coordinates":[-86.272554,39.826989],"type":"Point"}
}