{
  "type": "Feature",
  "properties": {
    "iso:country":"US",
    "sg:address":"865 Crown Ct",
    "sg:city":"Crown Point",
    "sg:classifiers":[
        {
            "category":"Utilities",
            "subcategory":"Refuse",
            "type":"Services"
        }
    ],
    "sg:phone":"+1 219 662 8254",
    "sg:postcode":"46307",
    "sg:province":"IN",
    "sg:tags":[
        "garbage",
        "collection"
    ],
    "wof:name":"Allied Waste Industries",
    "wof:placetype":"venue"
},
  "geometry": {"coordinates":[-87.353126,41.431126],"type":"Point"}
}