{
  "type": "Feature",
  "properties": {
    "iso:country":"US",
    "sg:address":"327 Ley Rd",
    "sg:city":"Fort Wayne",
    "sg:classifiers":[
        {
            "category":"Manufacturing",
            "subcategory":"Tools & Machinery",
            "type":"Manufacturing & Wholesale Goods"
        }
    ],
    "sg:phone":"+1 260 483 4282",
    "sg:postcode":"46825",
    "sg:province":"IN",
    "sg:tags":[
        "die",
        "maker"
    ],
    "sg:website":"www.midwest-tool.com",
    "wof:name":"Midwest Tool & Die Corp",
    "wof:placetype":"venue"
},
  "geometry": {"coordinates":[-85.14720800000001,41.125224],"type":"Point"}
}