{
  "type": "Feature",
  "properties": {
    "addr:full":"1318 Ohio St Terre Haute IN 47807",
    "addr:housenumber":"1318",
    "addr:postcode":"47807",
    "addr:street":"Ohio St",
    "iso:country":"US",
    "sg:address":"1318 Ohio St",
    "sg:city":"Terre Haute",
    "sg:classifiers":[
        {
            "category":"Professional",
            "subcategory":"Advertising",
            "type":"Services"
        }
    ],
    "sg:phone":"+1 812 238 0606",
    "sg:postcode":"47807",
    "sg:province":"IN",
    "sg:tags":[
        "guide"
    ],
    "wof:name":"Mc Leod USA Yellow Book",
    "wof:placetype":"venue"
},
  "geometry": {"coordinates":[-87.396586,39.46554],"type":"Point"}
}