{
  "type": "Feature",
  "properties": {
    "iso:country":"US",
    "sg:address":"1240 S Jefferson St",
    "sg:city":"Huntington",
    "sg:classifiers":[
        {
            "category":"Banks & Credit Unions",
            "subcategory":"Bank",
            "type":"Services"
        }
    ],
    "sg:phone":"+1 260 356 5633",
    "sg:postcode":"46750",
    "sg:province":"IN",
    "wof:name":"First Federal Savings Bank",
    "wof:placetype":"venue"
},
  "geometry": {"coordinates":[-85.484368,40.871542],"type":"Point"}
}