{
  "type": "Feature",
  "properties": {
    "iso:country":"US",
    "sg:address":"2001 Troy Ave",
    "sg:city":"New Castle",
    "sg:classifiers":[
        {
            "category":"Manufacturing",
            "subcategory":"Rubber & Plastics",
            "type":"Manufacturing & Wholesale Goods"
        }
    ],
    "sg:phone":"+1 765 529 7001",
    "sg:postcode":"47362",
    "sg:province":"IN",
    "sg:tags":[
        "lining",
        "brake"
    ],
    "sg:website":"www.hibbingfriction.com",
    "wof:name":"Hibbing International Friction",
    "wof:placetype":"venue"
},
  "geometry": {"coordinates":[-85.347657,39.913055],"type":"Point"}
}