{
  "type": "Feature",
  "properties": {
    "addr:full":"3400 State Rd 28 Muncie IN 47303",
    "addr:housenumber":"3400;28",
    "addr:postcode":"47303",
    "addr:street":"State Rd",
    "iso:country":"US",
    "sg:address":"3400 State Rd 28",
    "sg:city":"Muncie",
    "sg:classifiers":[
        {
            "category":"Education",
            "subcategory":"School",
            "type":"Public Place"
        }
    ],
    "sg:phone":"+1 765 288 5597",
    "sg:postcode":"47303",
    "sg:province":"IN",
    "sg:website":"www.delcomschools.org",
    "wof:name":"Delta High School",
    "wof:placetype":"venue"
},
  "geometry": {"coordinates":[-85.42543000000001,40.277229],"type":"Point"}
}