{
  "type": "Feature",
  "properties": {
    "iso:country":"US",
    "sg:address":"7300 Lantern Rd",
    "sg:city":"Indianapolis",
    "sg:classifiers":[
        {
            "category":"Social Services",
            "subcategory":"Child Care",
            "type":"Services"
        }
    ],
    "sg:phone":"+1 317 849 2794",
    "sg:postcode":"46256",
    "sg:province":"IN",
    "sg:tags":[
        "kindergarten",
        "academic",
        "school"
    ],
    "wof:name":"Geist Orchard Co-Op Preschool",
    "wof:placetype":"venue"
},
  "geometry": {"coordinates":[-86.013921,39.889232],"type":"Point"}
}