{
  "type": "Feature",
  "properties": {
    "iso:country":"US",
    "sg:address":"9681 N 180 E",
    "sg:city":"North Manchester",
    "sg:classifiers":[
        {
            "category":"Building & Trades",
            "subcategory":"Construction",
            "type":"Services"
        }
    ],
    "sg:phone":"+1 260 982 1271",
    "sg:postcode":"46962",
    "sg:province":"IN",
    "sg:tags":[
        "house"
    ],
    "wof:name":"Brunk Construction",
    "wof:placetype":"venue"
},
  "geometry": {"coordinates":[-85.76294,40.967297],"type":"Point"}
}