{
  "type": "Feature",
  "properties": {
    "iso:country":"US",
    "sg:address":"704 Chestnut Dr",
    "sg:city":"Gas City",
    "sg:classifiers":[
        {
            "category":"Freight",
            "type":"Transportation"
        }
    ],
    "sg:phone":"+1 765 674 1529",
    "sg:postcode":"46933",
    "sg:province":"IN",
    "wof:name":"K & J Transportation",
    "wof:placetype":"venue"
},
  "geometry": {"coordinates":[-85.605062,40.493334],"type":"Point"}
}