{
  "type": "Feature",
  "properties": {
    "iso:country":"US",
    "sg:address":"6051 Industrial Hwy",
    "sg:city":"Gary",
    "sg:classifiers":[
        {
            "category":"Government",
            "subcategory":"Fire Station",
            "type":"Public Place"
        }
    ],
    "sg:phone":"+1 219 949 9034",
    "sg:postcode":"46406",
    "sg:province":"IN",
    "sg:tags":[
        "department"
    ],
    "wof:name":"Garyregional Airport Fire Dept",
    "wof:placetype":"venue"
},
  "geometry": {"coordinates":[-87.40031,41.614474],"type":"Point"}
}