{
  "type": "Feature",
  "properties": {
    "iso:country":"US",
    "sg:address":"57738 Oakside Ave",
    "sg:city":"Mishawaka",
    "sg:classifiers":[
        {
            "category":"Building & Trades",
            "subcategory":"Construction",
            "type":"Services"
        }
    ],
    "sg:phone":"+1 574 259 5000",
    "sg:postcode":"46544",
    "sg:province":"IN",
    "sg:tags":[
        "downspouts",
        "gutter"
    ],
    "wof:name":"Weathertite Seamless Gutters",
    "wof:placetype":"venue"
},
  "geometry": {"coordinates":[-86.122001,41.656265],"type":"Point"}
}