{
  "type": "Feature",
  "properties": {
    "iso:country":"US",
    "sg:address":"253 America Pl",
    "sg:city":"Jeffersonville",
    "sg:classifiers":[
        {
            "category":"Shopping",
            "subcategory":"Shoes",
            "type":"Retail Goods"
        }
    ],
    "sg:phone":"+1 812 288 7659",
    "sg:postcode":"47130",
    "sg:province":"IN",
    "sg:website":"www.actonenterprises.com",
    "wof:name":"Acton Enterprises Inc",
    "wof:placetype":"venue"
},
  "geometry": {"coordinates":[-85.736811,38.288229],"type":"Point"}
}