{
  "type": "Feature",
  "properties": {
    "addr:full":"1723 la Porte Ave Whiting IN 46394",
    "addr:housenumber":"1723",
    "addr:postcode":"46394",
    "addr:street":"La Porte Ave",
    "iso:country":"US",
    "sg:address":"1723 la Porte Ave",
    "sg:city":"Whiting",
    "sg:classifiers":[
        {
            "category":"Education",
            "subcategory":"School",
            "type":"Public Place"
        }
    ],
    "sg:phone":"+1 219 659 1088",
    "sg:postcode":"46394",
    "sg:province":"IN",
    "wof:name":"Sacred Heart School",
    "wof:placetype":"venue"
},
  "geometry": {"coordinates":[-87.24859499999999,41.521777],"type":"Point"}
}