{
  "type": "Feature",
  "properties": {
    "iso:country":"US",
    "sg:address":"2823 Brentwood Ct",
    "sg:city":"Richmond",
    "sg:classifiers":[
        {
            "category":"Professional",
            "subcategory":"Engineering",
            "type":"Services"
        }
    ],
    "sg:phone":"+1 765 966 5755",
    "sg:postcode":"47374",
    "sg:province":"IN",
    "wof:name":"Warehouse Mgt Systm Consulting",
    "wof:placetype":"venue"
},
  "geometry": {"coordinates":[-84.86376,39.818359],"type":"Point"}
}