{
  "type": "Feature",
  "properties": {
    "iso:country":"US",
    "sg:address":"3435 E State Rd 28",
    "sg:city":"Tipton",
    "sg:classifiers":[
        {
            "category":"Restaurant",
            "type":"Food & Drink"
        }
    ],
    "sg:phone":"+1 765 675 9965",
    "sg:postcode":"46072",
    "sg:province":"IN",
    "wof:name":"Feed Mill Restaurant",
    "wof:placetype":"venue"
},
  "geometry": {"coordinates":[-85.949807,40.285157],"type":"Point"}
}