{
  "type": "Feature",
  "properties": {
    "addr:full":"4149 N Hartstrait Rd Bloomington IN 47404",
    "addr:housenumber":"4149",
    "addr:postcode":"47404",
    "addr:street":"N Hartstrait Rd",
    "iso:country":"US",
    "sg:address":"4149 N Hartstrait Rd",
    "sg:city":"Bloomington",
    "sg:classifiers":[
        {
            "category":"Building & Trades",
            "subcategory":"Construction",
            "type":"Services"
        }
    ],
    "sg:phone":"+1 812 876 1363",
    "sg:postcode":"47404",
    "sg:province":"IN",
    "sg:tags":[
        "contractor"
    ],
    "wof:name":"Dawley Construction",
    "wof:placetype":"venue"
},
  "geometry": {"coordinates":[-86.611504,39.212299],"type":"Point"}
}