{
  "type": "Feature",
  "properties": {
    "iso:country":"US",
    "sg:address":"206 W Mill St",
    "sg:city":"Attica",
    "sg:classifiers":[
        {
            "category":"Retail",
            "subcategory":"Auto Repair",
            "type":"Services"
        }
    ],
    "sg:phone":"+1 765 762 6726",
    "sg:postcode":"47918",
    "sg:province":"IN",
    "sg:tags":[
        "repairing",
        "automobile"
    ],
    "wof:name":"Synesael Inc Garage",
    "wof:placetype":"venue"
},
  "geometry": {"coordinates":[-87.25116,40.294328],"type":"Point"}
}