{
  "type": "Feature",
  "properties": {
    "addr:full":"1307 W 3rd St Bloomington IN 47404",
    "addr:housenumber":"1307",
    "addr:postcode":"47404",
    "addr:street":"W 3Rd St",
    "iso:country":"US",
    "sg:address":"1307 W 3rd St",
    "sg:city":"Bloomington",
    "sg:classifiers":[
        {
            "category":"Food & Beverages",
            "subcategory":"Groceries & Convenience Stores",
            "type":"Retail Goods"
        }
    ],
    "sg:phone":"+1 812 331 9576",
    "sg:postcode":"47404",
    "sg:province":"IN",
    "wof:name":"Village Pantry",
    "wof:placetype":"venue"
},
  "geometry": {"coordinates":[-86.547569,39.16427],"type":"Point"}
}