{
  "type": "Feature",
  "properties": {
    "iso:country":"US",
    "sg:address":"5804 W State Rd 46",
    "sg:city":"Bloomington",
    "sg:classifiers":[
        {
            "category":"Home & Garden",
            "subcategory":"Home Furnishings",
            "type":"Retail Goods"
        }
    ],
    "sg:phone":"+1 812 876 1340",
    "sg:postcode":"47404",
    "sg:province":"IN",
    "sg:tags":[
        "fireplace"
    ],
    "wof:name":"Economy Fireplace",
    "wof:placetype":"venue"
},
  "geometry": {"coordinates":[-86.61284000000001,39.225327],"type":"Point"}
}