{
  "type": "Feature",
  "properties": {
    "iso:country":"US",
    "sg:address":"208 W Catherine St",
    "sg:city":"Milford",
    "sg:classifiers":[
        {
            "category":"Organizations",
            "subcategory":"Religious Organization",
            "type":"Services"
        }
    ],
    "sg:phone":"+1 574 658 4814",
    "sg:postcode":"46542",
    "sg:province":"IN",
    "sg:tags":[
        "church"
    ],
    "wof:name":"Milford United Methodist Chr",
    "wof:placetype":"venue"
},
  "geometry": {"coordinates":[-85.848928,41.409717],"type":"Point"}
}