{
  "type": "Feature",
  "properties": {
    "iso:country":"US",
    "sg:address":"2109 W 57th St",
    "sg:city":"Hobart",
    "sg:classifiers":[
        {
            "category":"Social Services",
            "subcategory":"Child Care",
            "type":"Services"
        }
    ],
    "sg:phone":"+1 219 942 9410",
    "sg:postcode":"46342",
    "sg:province":"IN",
    "sg:tags":[
        "kindergarten",
        "academic",
        "school"
    ],
    "wof:name":"Montessori Academy In The Oaks",
    "wof:placetype":"venue"
},
  "geometry": {"coordinates":[-87.313147,41.514481],"type":"Point"}
}