{
  "type": "Feature",
  "properties": {
    "addr:full":"4010 S Anthony Blvd Fort Wayne IN 46806",
    "addr:housenumber":"4010",
    "addr:postcode":"46806",
    "addr:street":"S Anthony Blvd",
    "iso:country":"US",
    "sg:address":"4010 S Anthony Blvd",
    "sg:city":"Fort Wayne",
    "sg:classifiers":[
        {
            "category":"Retail",
            "subcategory":"Auto Repair",
            "type":"Services"
        }
    ],
    "sg:phone":"+1 260 456 2957",
    "sg:postcode":"46806",
    "sg:province":"IN",
    "sg:tags":[
        "repairing",
        "automobile"
    ],
    "wof:name":"Dutch's Auto Repair",
    "wof:placetype":"venue"
},
  "geometry": {"coordinates":[-85.113489,41.049111],"type":"Point"}
}