{
  "type": "Feature",
  "properties": {
    "iso:country":"US",
    "sg:address":"5907 W Co Rd 375 S",
    "sg:city":"French Lick",
    "sg:classifiers":[
        {
            "category":"Building & Trades",
            "subcategory":"Construction",
            "type":"Services"
        }
    ],
    "sg:phone":"+1 812 936 7711",
    "sg:postcode":"47432",
    "sg:province":"IN",
    "sg:tags":[
        "general",
        "contractor"
    ],
    "wof:name":"Ashby Construction",
    "wof:placetype":"venue"
},
  "geometry": {"coordinates":[-86.567456,38.501289],"type":"Point"}
}