{
  "type": "Feature",
  "properties": {
    "addr:full":"1320 Washington St Rochester IN 46975",
    "addr:housenumber":"1320",
    "addr:postcode":"46975",
    "addr:street":"Washington St",
    "iso:country":"US",
    "sg:address":"1320 Washington St",
    "sg:city":"Rochester",
    "sg:classifiers":[
        {
            "category":"Organizations",
            "subcategory":"Religious Organization",
            "type":"Services"
        }
    ],
    "sg:phone":"+1 574 223 4193",
    "sg:postcode":"46975",
    "sg:province":"IN",
    "sg:tags":[
        "church"
    ],
    "sg:website":"www.riverviewcommunitychurch.org",
    "wof:name":"Riverview Community Chr-Ofc",
    "wof:placetype":"venue"
},
  "geometry": {"coordinates":[-86.200137,41.058542],"type":"Point"}
}