{
  "type": "Feature",
  "properties": {
    "addr:full":"405 E South St South Bend IN 46601",
    "addr:housenumber":"405 e",
    "addr:postcode":"46601",
    "addr:street":"South St",
    "iso:country":"US",
    "sg:address":"405 E South St",
    "sg:city":"South Bend",
    "sg:classifiers":[
        {
            "category":"Building & Trades",
            "subcategory":"Construction",
            "type":"Services"
        }
    ],
    "sg:phone":"+1 574 299 1908",
    "sg:postcode":"46601",
    "sg:province":"IN",
    "sg:tags":[
        "repairing",
        "remodeling",
        "contractor"
    ],
    "wof:name":"Gean Remodeling & Construction",
    "wof:placetype":"venue"
},
  "geometry": {"coordinates":[-86.24521900000001,41.669531],"type":"Point"}
}