{
  "type": "Feature",
  "properties": {
    "addr:full":"705 N 6th St Monticello IN 47960",
    "addr:housenumber":"705",
    "addr:postcode":"47960",
    "addr:street":"N 6Th St",
    "iso:country":"US",
    "sg:address":"705 N 6th St",
    "sg:city":"Monticello",
    "sg:classifiers":[
        {
            "category":"Manufacturing",
            "subcategory":"Tools & Machinery",
            "type":"Manufacturing & Wholesale Goods"
        }
    ],
    "sg:phone":"+1 574 583 9171",
    "sg:postcode":"47960",
    "sg:province":"IN",
    "sg:tags":[
        "bearing",
        "ball",
        "roller"
    ],
    "wof:name":"Emerson Power Transmission",
    "wof:placetype":"venue"
},
  "geometry": {"coordinates":[-86.77514499999999,40.754024],"type":"Point"}
}