{
  "type": "Feature",
  "properties": {
    "iso:country":"US",
    "sg:address":"1478 W 86th St",
    "sg:city":"Indianapolis",
    "sg:classifiers":[
        {
            "category":"Shopping",
            "subcategory":"Clothing, Apparel, & Fashions",
            "type":"Retail Goods"
        }
    ],
    "sg:phone":"+1 317 872 9494",
    "sg:postcode":"46260",
    "sg:province":"IN",
    "wof:name":"Collection 94",
    "wof:placetype":"venue"
},
  "geometry": {"coordinates":[-86.187526,39.912245],"type":"Point"}
}