{
  "type": "Feature",
  "properties": {
    "iso:country":"US",
    "sg:address":"103 State St",
    "sg:city":"Newburgh",
    "sg:classifiers":[
        {
            "category":"Shopping",
            "subcategory":"Used Merchandise",
            "type":"Retail Goods"
        }
    ],
    "sg:phone":"+1 812 858 9544",
    "sg:postcode":"47630",
    "sg:province":"IN",
    "sg:tags":[
        "antique"
    ],
    "wof:name":"Country Gentleman Antiques",
    "wof:placetype":"venue"
},
  "geometry": {"coordinates":[-87.405035,37.944593],"type":"Point"}
}