{
  "type": "Feature",
  "properties": {
    "iso:country":"US",
    "sg:address":"525 N Church St",
    "sg:city":"Austin",
    "sg:classifiers":[
        {
            "category":"Organizations",
            "subcategory":"Religious Organization",
            "type":"Services"
        }
    ],
    "sg:phone":"+1 812 794 3152",
    "sg:postcode":"47102",
    "sg:province":"IN",
    "wof:name":"Austin Wesleyan Parsonage",
    "wof:placetype":"venue"
},
  "geometry": {"coordinates":[-85.80403,38.74838],"type":"Point"}
}