{
  "type": "Feature",
  "properties": {
    "iso:country":"US",
    "sg:address":"3940 Winding Way",
    "sg:city":"Indianapolis",
    "sg:classifiers":[
        {
            "category":"Retail",
            "subcategory":"Auto Repair",
            "type":"Services"
        }
    ],
    "sg:phone":"+1 317 253 4853",
    "sg:postcode":"46220",
    "sg:province":"IN",
    "wof:name":"Gogreen Conversions Inc.",
    "wof:placetype":"venue"
},
  "geometry": {"coordinates":[-86.10005200000001,39.857861],"type":"Point"}
}