{
  "type": "Feature",
  "properties": {
    "iso:country":"US",
    "sg:address":"1100 Bloomingdale Dr",
    "sg:city":"Bristol",
    "sg:classifiers":[
        {
            "category":"Manufacturing",
            "subcategory":"Rubber & Plastics",
            "type":"Manufacturing & Wholesale Goods"
        }
    ],
    "sg:phone":"+1 574 848 0925",
    "sg:postcode":"46507",
    "sg:province":"IN",
    "wof:name":"B D Custom Manufacturing",
    "wof:placetype":"venue"
},
  "geometry": {"coordinates":[-85.815177,41.711913],"type":"Point"}
}