{
  "type": "Feature",
  "properties": {
    "iso:country":"US",
    "sg:address":"405 E Main St",
    "sg:city":"Greenwood",
    "sg:classifiers":[
        {
            "category":"Home & Garden",
            "subcategory":"Furniture",
            "type":"Retail Goods"
        }
    ],
    "sg:phone":"+1 317 859 6336",
    "sg:postcode":"46143",
    "sg:province":"IN",
    "sg:tags":[
        "cabinet"
    ],
    "wof:name":"The Corner Cabinet",
    "wof:placetype":"venue"
},
  "geometry": {"coordinates":[-86.100227,39.613861],"type":"Point"}
}