{
  "type": "Feature",
  "properties": {
    "iso:country":"US",
    "sg:address":"4040 S Meridian St",
    "sg:city":"Indianapolis",
    "sg:classifiers":[
        {
            "category":"Professional",
            "subcategory":"Lawyer & Legal Services",
            "type":"Services"
        }
    ],
    "sg:phone":"+1 317 783 2500",
    "sg:postcode":"46217",
    "sg:province":"IN",
    "sg:tags":[
        "attorney"
    ],
    "wof:name":"Steve Willsey Law Office",
    "wof:placetype":"venue"
},
  "geometry": {"coordinates":[-86.15825,39.703074],"type":"Point"}
}