{
  "type": "Feature",
  "properties": {
    "iso:country":"US",
    "sg:address":"1101 N Baldwin Ave",
    "sg:city":"Marion",
    "sg:classifiers":[
        {
            "category":"Autos & Motor Vehicles",
            "subcategory":"Automobile Sales",
            "type":"Retail Goods"
        }
    ],
    "sg:phone":"+1 765 662 3831",
    "sg:postcode":"46952",
    "sg:province":"IN",
    "sg:tags":[
        "car",
        "dealer"
    ],
    "sg:website":"www.matthewsbuick.com",
    "wof:name":"Matthews Buick-Pontiac-Olds",
    "wof:placetype":"venue"
},
  "geometry": {"coordinates":[-85.675961,40.570743],"type":"Point"}
}