{
  "type": "Feature",
  "properties": {
    "iso:country":"US",
    "sg:address":"1700 Grant St",
    "sg:city":"Gary",
    "sg:classifiers":[
        {
            "category":"Bars & Pubs",
            "type":"Food & Drink"
        }
    ],
    "sg:phone":"+1 219 944 7780",
    "sg:postcode":"46404",
    "sg:province":"IN",
    "sg:tags":[
        "club",
        "night"
    ],
    "wof:name":"Satches Inc",
    "wof:placetype":"venue"
},
  "geometry": {"coordinates":[-87.35630399999999,41.58557],"type":"Point"}
}