{
  "type": "Feature",
  "properties": {
    "iso:country":"US",
    "sg:address":"1498 Upper Schooner Rd",
    "sg:city":"Nashville",
    "sg:classifiers":[
        {
            "category":"Professional",
            "subcategory":"Management & Consulting",
            "type":"Services"
        }
    ],
    "sg:phone":"+1 812 988 6442",
    "sg:postcode":"47448",
    "sg:province":"IN",
    "wof:name":"Sanjo Management Corp",
    "wof:placetype":"venue"
},
  "geometry": {"coordinates":[-86.275855,39.158045],"type":"Point"}
}