{
  "type": "Feature",
  "properties": {
    "iso:country":"US",
    "sg:address":"2014 Kulp Ave",
    "sg:city":"Elkhart",
    "sg:classifiers":[
        {
            "category":"Arts & Performance",
            "subcategory":"Theater",
            "type":"Entertainment"
        }
    ],
    "sg:phone":"+1 574 522 1854",
    "sg:postcode":"46517",
    "sg:province":"IN",
    "sg:tags":[
        "live",
        "music"
    ],
    "wof:name":"HITS To Go Disc Jockey & Krk",
    "wof:placetype":"venue"
},
  "geometry": {"coordinates":[-85.937844,41.646921],"type":"Point"}
}