{
  "type": "Feature",
  "properties": {
    "iso:country":"US",
    "sg:address":"3220 W 25th St",
    "sg:city":"Anderson",
    "sg:classifiers":[
        {
            "category":"Manufacturing",
            "subcategory":"Metals",
            "type":"Manufacturing & Wholesale Goods"
        }
    ],
    "sg:phone":"+1 765 642 2464",
    "sg:postcode":"46011",
    "sg:province":"IN",
    "sg:tags":[
        "coating"
    ],
    "wof:name":"Natural Coating Systems",
    "wof:placetype":"venue"
},
  "geometry": {"coordinates":[-85.726531,40.090574],"type":"Point"}
}