{
  "type": "Feature",
  "properties": {
    "iso:country":"US",
    "sg:address":"2000 Liberty Dr",
    "sg:city":"Bloomington",
    "sg:classifiers":[
        {
            "category":"Manufacturing",
            "subcategory":"Metals",
            "type":"Manufacturing & Wholesale Goods"
        }
    ],
    "sg:phone":"+1 812 334 8839",
    "sg:postcode":"47403",
    "sg:province":"IN",
    "sg:tags":[
        "product",
        "wire",
        "fabricated"
    ],
    "wof:name":"Schulte Corp",
    "wof:placetype":"venue"
},
  "geometry": {"coordinates":[-86.577565,39.146428],"type":"Point"}
}