{
  "type": "Feature",
  "properties": {
    "iso:country":"US",
    "sg:address":"20804 S 1100 W",
    "sg:city":"La Crosse",
    "sg:classifiers":[
        {
            "category":"Farming",
            "subcategory":"Farm",
            "type":"Manufacturing & Wholesale Goods"
        }
    ],
    "sg:phone":"+1 219 754 2680",
    "sg:postcode":"46348",
    "sg:province":"IN",
    "sg:tags":[
        "crop",
        "general"
    ],
    "wof:name":"Knapp Farms Inc",
    "wof:placetype":"venue"
},
  "geometry": {"coordinates":[-86.910751,41.30568],"type":"Point"}
}