{
  "type": "Feature",
  "properties": {
    "iso:country":"US",
    "sg:address":"1825 Stout Field Ter",
    "sg:city":"Indianapolis",
    "sg:classifiers":[
        {
            "category":"Freight",
            "type":"Transportation"
        }
    ],
    "sg:phone":"+1 317 484 1767",
    "sg:postcode":"46241",
    "sg:province":"IN",
    "sg:tags":[
        "warehouse",
        "public"
    ],
    "wof:name":"Interstate Warehousing",
    "wof:placetype":"venue"
},
  "geometry": {"coordinates":[-86.232519,39.741398],"type":"Point"}
}