{
  "type": "Feature",
  "properties": {
    "addr:full":"5410 S State Rd 9 Columbia City IN 46725",
    "addr:housenumber":"5410",
    "addr:postcode":"46725",
    "addr:street":"S State Rd 9",
    "iso:country":"US",
    "sg:address":"5410 S State Rd 9",
    "sg:city":"Columbia City",
    "sg:classifiers":[
        {
            "category":"Building & Trades",
            "subcategory":"Landscaping Services",
            "type":"Services"
        }
    ],
    "sg:phone":"+1 260 248 2700",
    "sg:postcode":"46725",
    "sg:province":"IN",
    "sg:tags":[
        "lawn",
        "maintenance",
        "grounds"
    ],
    "wof:name":"J B Lawn Svc & Nursery Inc",
    "wof:placetype":"venue"
},
  "geometry": {"coordinates":[-85.47020000000001,41.082312],"type":"Point"}
}