{
  "type": "Feature",
  "properties": {
    "iso:country":"US",
    "sg:address":"2399 E 98th St",
    "sg:city":"Indianapolis",
    "sg:classifiers":[
        {
            "category":"Shopping",
            "subcategory":"Crafts & Fabrics",
            "type":"Retail Goods"
        }
    ],
    "sg:phone":"+1 317 514 3783",
    "sg:postcode":"46280",
    "sg:province":"IN",
    "sg:tags":[
        "sewing"
    ],
    "wof:name":"Define Design",
    "wof:placetype":"venue"
},
  "geometry": {"coordinates":[-86.11644,39.930923],"type":"Point"}
}