{
  "type": "Feature",
  "properties": {
    "addr:full":"9382 Whispering Trce Brownsburg IN 46112",
    "addr:housenumber":"9382",
    "addr:postcode":"46112",
    "addr:street":"Whispering Trce",
    "iso:country":"US",
    "sg:address":"9382 Whispering Trce",
    "sg:city":"Brownsburg",
    "sg:classifiers":[
        {
            "category":"Personal",
            "subcategory":"Beauty Salon",
            "type":"Services"
        }
    ],
    "sg:phone":"+1 317 852 0319",
    "sg:postcode":"46112",
    "sg:province":"IN",
    "sg:tags":[
        "cosmetologist"
    ],
    "wof:name":"Jennifer Lynn Moser",
    "wof:placetype":"venue"
},
  "geometry": {"coordinates":[-86.38399200000001,39.835507],"type":"Point"}
}