{
  "type": "Feature",
  "properties": {
    "iso:country":"US",
    "sg:address":"530 US Hwy 31 S",
    "sg:city":"Greenwood",
    "sg:classifiers":[
        {
            "category":"Banks & Credit Unions",
            "subcategory":"Bank",
            "type":"Services"
        }
    ],
    "sg:phone":"+1 317 881 0862",
    "sg:postcode":"46142",
    "sg:province":"IN",
    "sg:tags":[
        "loan",
        "real estate"
    ],
    "wof:name":"Superior Mortgage Svc",
    "wof:placetype":"venue"
},
  "geometry": {"coordinates":[-86.110796,39.607956],"type":"Point"}
}