{
  "type": "Feature",
  "properties": {
    "iso:country":"US",
    "sg:address":"4306 Lake Ave",
    "sg:city":"Fort Wayne",
    "sg:classifiers":[
        {
            "category":"Health Services",
            "subcategory":"Doctor",
            "type":"Services"
        }
    ],
    "sg:phone":"+1 260 422 1906",
    "sg:postcode":"46815",
    "sg:province":"IN",
    "sg:tags":[
        "physician",
        "surgeon"
    ],
    "wof:name":"Quorum",
    "wof:placetype":"venue"
},
  "geometry": {"coordinates":[-85.084708,41.090449],"type":"Point"}
}