{
  "type": "Feature",
  "properties": {
    "iso:country":"US",
    "sg:address":"11073 N Risley Rd",
    "sg:city":"Oaktown",
    "sg:classifiers":[
        {
            "category":"Professional",
            "type":"Services"
        }
    ],
    "sg:phone":"+1 812 745 2408",
    "sg:postcode":"47561",
    "sg:province":"IN",
    "wof:name":"Rob Robbins",
    "wof:placetype":"venue"
},
  "geometry": {"coordinates":[-87.392382,38.833549],"type":"Point"}
}