{
  "type": "Feature",
  "properties": {
    "iso:country":"US",
    "sg:address":"519 Oxford St",
    "sg:city":"Fort Wayne",
    "sg:classifiers":[
        {
            "category":"Social Services",
            "type":"Services"
        }
    ],
    "sg:phone":"+1 260 456 6917",
    "sg:postcode":"46806",
    "sg:province":"IN",
    "sg:tags":[
        "organization",
        "welfare"
    ],
    "wof:name":"TEAM III Inc",
    "wof:placetype":"venue"
},
  "geometry": {"coordinates":[-85.129275,41.053481],"type":"Point"}
}