{
  "type": "Feature",
  "properties": {
    "iso:country":"US",
    "sg:address":"740 N 10th St",
    "sg:city":"Decatur",
    "sg:classifiers":[
        {
            "category":"Retail",
            "subcategory":"Repair Shop",
            "type":"Services"
        }
    ],
    "sg:phone":"+1 260 728 2940",
    "sg:postcode":"46733",
    "sg:province":"IN",
    "wof:name":"A & M Upholstery Inc",
    "wof:placetype":"venue"
},
  "geometry": {"coordinates":[-84.934413,40.837807],"type":"Point"}
}