{
  "type": "Feature",
  "properties": {
    "iso:country":"US",
    "sg:address":"25 Vernon St",
    "sg:city":"North Vernon",
    "sg:classifiers":[
        {
            "category":"Retail",
            "subcategory":"Auto Repair",
            "type":"Services"
        }
    ],
    "sg:phone":"+1 812 346 6905",
    "sg:postcode":"47265",
    "sg:province":"IN",
    "sg:tags":[
        "repairing",
        "automobile"
    ],
    "wof:name":"Ron's Auto Svc",
    "wof:placetype":"venue"
},
  "geometry": {"coordinates":[-85.62409,39.001984],"type":"Point"}
}