{
  "type": "Feature",
  "properties": {
    "iso:country":"US",
    "sg:address":"1041 Walnut St",
    "sg:city":"Madison",
    "sg:classifiers":[
        {
            "category":"Organizations",
            "subcategory":"Community Association",
            "type":"Services"
        }
    ],
    "sg:phone":"+1 812 265 2707",
    "sg:postcode":"47250",
    "sg:province":"IN",
    "sg:tags":[
        "club"
    ],
    "wof:name":"Jefferson County Goodwill",
    "wof:placetype":"venue"
},
  "geometry": {"coordinates":[-85.375894,38.742249],"type":"Point"}
}