{
  "type": "Feature",
  "properties": {
    "addr:full":"11444 Lake Stonebridge Ln Fishers IN 46037",
    "addr:housenumber":"11444",
    "addr:postcode":"46037",
    "addr:street":"Lake Stonebridge Ln",
    "iso:country":"US",
    "sg:address":"11444 Lake Stonebridge Ln",
    "sg:city":"Fishers",
    "sg:classifiers":[
        {
            "category":"Organizations",
            "subcategory":"Professional Association",
            "type":"Services"
        }
    ],
    "sg:phone":"+1 317 849 5651",
    "sg:postcode":"46037",
    "sg:province":"IN",
    "sg:tags":[
        "business",
        "trade"
    ],
    "wof:name":"Jewel Among Jewels Adoption",
    "wof:placetype":"venue"
},
  "geometry": {"coordinates":[-85.974323,39.954128],"type":"Point"}
}