{
  "type": "Feature",
  "properties": {
    "addr:full":"2310 Parkdale Dr Richmond IN 47374",
    "addr:housenumber":"2310",
    "addr:postcode":"47374",
    "addr:street":"Parkdale Dr",
    "iso:country":"US",
    "sg:address":"2310 Parkdale Dr",
    "sg:city":"Richmond",
    "sg:classifiers":[
        {
            "category":"Professional",
            "type":"Services"
        }
    ],
    "sg:phone":"+1 765 966 1229",
    "sg:postcode":"47374",
    "sg:province":"IN",
    "sg:tags":[
        "establishment"
    ],
    "wof:name":"Jack Doyle & Assoc",
    "wof:placetype":"venue"
},
  "geometry": {"coordinates":[-84.88188100000001,39.861193],"type":"Point"}
}