{
  "type": "Feature",
  "properties": {
    "iso:country":"US",
    "sg:address":"4214 Lincoln Way E",
    "sg:city":"Mishawaka",
    "sg:classifiers":[
        {
            "category":"Autos & Motor Vehicles",
            "subcategory":"Automobile Sales",
            "type":"Retail Goods"
        }
    ],
    "sg:phone":"+1 574 288 7720",
    "sg:postcode":"46544",
    "sg:province":"IN",
    "sg:tags":[
        "used"
    ],
    "wof:name":"Credit Auto Mart",
    "wof:placetype":"venue"
},
  "geometry": {"coordinates":[-86.112295,41.663377],"type":"Point"}
}