{
  "type": "Feature",
  "properties": {
    "iso:country":"US",
    "sg:address":"2244 W US Hwy 40",
    "sg:city":"Greenfield",
    "sg:classifiers":[
        {
            "category":"Shopping",
            "subcategory":"Used Merchandise",
            "type":"Retail Goods"
        }
    ],
    "sg:phone":"+1 317 467 4744",
    "sg:postcode":"46140",
    "sg:province":"IN",
    "sg:tags":[
        "antique"
    ],
    "wof:name":"Sugar Creek Antique Mall",
    "wof:placetype":"venue"
},
  "geometry": {"coordinates":[-85.84438900000001,39.781768],"type":"Point"}
}