{
  "type": "Feature",
  "properties": {
    "iso:country":"US",
    "sg:address":"2800 State Rd 261",
    "sg:city":"Newburgh",
    "sg:classifiers":[
        {
            "category":"Education",
            "subcategory":"School",
            "type":"Public Place"
        }
    ],
    "sg:phone":"+1 812 853 7347",
    "sg:postcode":"47630",
    "sg:province":"IN",
    "wof:name":"Castle Junior High School",
    "wof:placetype":"venue"
},
  "geometry": {"coordinates":[-87.379432,37.995178],"type":"Point"}
}