{
  "type": "Feature",
  "properties": {
    "iso:country":"US",
    "sg:address":"51050 Bittersweet Rd",
    "sg:city":"Granger",
    "sg:classifiers":[
        {
            "category":"Personal",
            "type":"Services"
        }
    ],
    "sg:phone":"+1 574 272 2222",
    "sg:postcode":"46530",
    "sg:province":"IN",
    "sg:tags":[
        "training",
        "health",
        "supply"
    ],
    "wof:name":"Fit Stop Inc",
    "wof:placetype":"venue"
},
  "geometry": {"coordinates":[-86.110921,41.752655],"type":"Point"}
}