{
  "type": "Feature",
  "properties": {
    "iso:country":"US",
    "sg:address":"1111 W 156th St",
    "sg:city":"Westfield",
    "sg:classifiers":[
        {
            "category":"Banks & Credit Unions",
            "subcategory":"Investment Brokerage",
            "type":"Services"
        }
    ],
    "sg:phone":"+1 317 896 9310",
    "sg:postcode":"46074",
    "sg:province":"IN",
    "sg:tags":[
        "merger",
        "acquisition"
    ],
    "wof:name":"Premier Acquisitions",
    "wof:placetype":"venue"
},
  "geometry": {"coordinates":[-86.175574,40.013711],"type":"Point"}
}