{
  "type": "Feature",
  "properties": {
    "addr:full":"2761 N 1275 W Delphi IN 46923",
    "addr:housenumber":"2761",
    "addr:postcode":"46923",
    "addr:street":"N 1275 W",
    "iso:country":"US",
    "sg:address":"2761 N 1275 W",
    "sg:city":"Delphi",
    "sg:classifiers":[
        {
            "category":"Autos & Motor Vehicles",
            "subcategory":"Boat Sales",
            "type":"Retail Goods"
        }
    ],
    "sg:phone":"+1 765 564 6806",
    "sg:postcode":"46923",
    "sg:province":"IN",
    "sg:tags":[
        "canoe"
    ],
    "wof:name":"Hodges Canoe Trips",
    "wof:placetype":"venue"
},
  "geometry": {"coordinates":[-86.769217,40.593271],"type":"Point"}
}