{
  "type": "Feature",
  "properties": {
    "iso:country":"US",
    "sg:address":"8803 Madison Ave",
    "sg:city":"Indianapolis",
    "sg:classifiers":[
        {
            "category":"Personal",
            "subcategory":"Beauty Salon",
            "type":"Services"
        }
    ],
    "sg:phone":"+1 317 888 0740",
    "sg:postcode":"46227",
    "sg:province":"IN",
    "wof:name":"Crestwood Beauty Salon",
    "wof:placetype":"venue"
},
  "geometry": {"coordinates":[-86.118027,39.638154],"type":"Point"}
}