{
  "type": "Feature",
  "properties": {
    "addr:full":"102 W Main St Petersburg IN 47567",
    "addr:housenumber":"102",
    "addr:postcode":"47567",
    "addr:street":"W Main St",
    "iso:country":"US",
    "sg:address":"102 W Main St",
    "sg:city":"Petersburg",
    "sg:classifiers":[
        {
            "category":"Restaurant",
            "type":"Food & Drink"
        }
    ],
    "sg:phone":"+1 812 354 3739",
    "sg:postcode":"47567",
    "sg:province":"IN",
    "wof:name":"Huck's Convenient Food Store",
    "wof:placetype":"venue"
},
  "geometry": {"coordinates":[-87.28684699999999,38.486402],"type":"Point"}
}