{
  "type": "Feature",
  "properties": {
    "iso:country":"US",
    "sg:address":"221 N Franklin St",
    "sg:city":"Greensburg",
    "sg:classifiers":[
        {
            "category":"Real Estate",
            "subcategory":"Real Estate Services",
            "type":"Services"
        }
    ],
    "sg:phone":"+1 812 663 2190",
    "sg:postcode":"47240",
    "sg:province":"IN",
    "wof:name":"Ford Abstract Corp",
    "wof:placetype":"venue"
},
  "geometry": {"coordinates":[-85.482869,39.338584],"type":"Point"}
}