{
  "type": "Feature",
  "properties": {
    "addr:full":"7246 W 200 S Swayzee IN 46986",
    "addr:housenumber":"7246",
    "addr:postcode":"46986",
    "addr:street":"W 200 S Swayzee",
    "iso:country":"US",
    "sg:address":"7246 W 200 S",
    "sg:city":"Swayzee",
    "sg:classifiers":[
        {
            "category":"Food & Beverages",
            "subcategory":"Specialty",
            "type":"Retail Goods"
        }
    ],
    "sg:phone":"+1 765 922 4854",
    "sg:postcode":"46986",
    "sg:province":"IN",
    "sg:tags":[
        "water",
        "bulk",
        "company"
    ],
    "wof:name":"Prime Water Care",
    "wof:placetype":"venue"
},
  "geometry": {"coordinates":[-85.810917,40.522954],"type":"Point"}
}