{
  "type": "Feature",
  "properties": {
    "iso:country":"US",
    "sg:address":"2339 Eisenhower Dr N",
    "sg:city":"Goshen",
    "sg:classifiers":[
        {
            "category":"Organizations",
            "subcategory":"Religious Organization",
            "type":"Services"
        }
    ],
    "sg:phone":"+1 574 534 4477",
    "sg:postcode":"46526",
    "sg:province":"IN",
    "sg:tags":[
        "church"
    ],
    "wof:name":"Church Of Jesus Christ Of Lds",
    "wof:placetype":"venue"
},
  "geometry": {"coordinates":[-85.801433,41.557082],"type":"Point"}
}