{
  "type": "Feature",
  "properties": {
    "iso:country":"US",
    "sg:address":"810 Orchard Ln",
    "sg:city":"Greenwood",
    "sg:classifiers":[
        {
            "category":"Professional",
            "subcategory":"Business Services",
            "type":"Services"
        }
    ],
    "sg:phone":"+1 317 888 1221",
    "sg:postcode":"46142",
    "sg:province":"IN",
    "wof:name":"Wilkins Patrick M Rl Est",
    "wof:placetype":"venue"
},
  "geometry": {"coordinates":[-86.123267,39.608081],"type":"Point"}
}