{
  "type": "Feature",
  "properties": {
    "iso:country":"US",
    "sg:address":"112 Three Rivers E",
    "sg:city":"Fort Wayne",
    "sg:classifiers":[
        {
            "category":"Banks & Credit Unions",
            "subcategory":"Investment Brokerage",
            "type":"Services"
        }
    ],
    "sg:phone":"+1 260 469 9000",
    "sg:postcode":"46802",
    "sg:province":"IN",
    "sg:tags":[
        "consultant",
        "planning",
        "financial"
    ],
    "wof:name":"American Express Financial Adv",
    "wof:placetype":"venue"
},
  "geometry": {"coordinates":[-85.13386300000001,41.082521],"type":"Point"}
}