{
  "type": "Feature",
  "properties": {
    "iso:country":"US",
    "sg:address":"101 E 9th St",
    "sg:city":"Auburn",
    "sg:classifiers":[
        {
            "category":"Professional",
            "subcategory":"Lawyer & Legal Services",
            "type":"Services"
        }
    ],
    "sg:phone":"+1 260 925 4514",
    "sg:postcode":"46706",
    "sg:province":"IN",
    "sg:tags":[
        "attorney"
    ],
    "wof:name":"Grimm & Grimm",
    "wof:placetype":"venue"
},
  "geometry": {"coordinates":[-85.05456700000001,41.365867],"type":"Point"}
}