{
  "type": "Feature",
  "properties": {
    "iso:country":"US",
    "sg:address":"802 Linlawn Dr",
    "sg:city":"Wabash",
    "sg:classifiers":[
        {
            "category":"Professional",
            "subcategory":"Computer Services",
            "type":"Services"
        }
    ],
    "sg:phone":"+1 260 563 3608",
    "sg:postcode":"46992",
    "sg:province":"IN",
    "sg:tags":[
        "consultant",
        "designer"
    ],
    "wof:name":"Sargent Computer Svc",
    "wof:placetype":"venue"
},
  "geometry": {"coordinates":[-85.83437499999999,40.781405],"type":"Point"}
}