{
  "type": "Feature",
  "properties": {
    "iso:country":"US",
    "sg:address":"600 Iwo St",
    "sg:city":"Auburn",
    "sg:phone":"+1 260 925 1206",
    "sg:postcode":"46706",
    "sg:province":"IN",
    "sg:tags":[
        "farm",
        "soybean"
    ],
    "wof:name":"ZB Farming Inc",
    "wof:placetype":"venue"
},
  "geometry": {"coordinates":[-85.04411899999999,41.358724],"type":"Point"}
}