{
  "type": "Feature",
  "properties": {
    "addr:full":"8208 Kennedy Ave Highland IN 46322",
    "addr:housenumber":"8208",
    "addr:postcode":"46322",
    "addr:street":"Kennedy Ave",
    "iso:country":"US",
    "sg:address":"8208 Kennedy Ave",
    "sg:city":"Highland",
    "sg:classifiers":[
        {
            "category":"Home & Garden",
            "subcategory":"Building Materials",
            "type":"Retail Goods"
        },
        {
            "category":"Building & Trades",
            "subcategory":"Construction",
            "type":"Services"
        }
    ],
    "sg:phone":"+1 219 923 5782",
    "sg:postcode":"46322",
    "sg:province":"IN",
    "sg:tags":[
        "roofing",
        "bathroom",
        "window",
        "contractor",
        "siding",
        "planning",
        "remodeling",
        "kitchen"
    ],
    "sg:website":"http://hobsonscottremodeling.com",
    "wof:name":"Hobson & Scott Remodeling Inc",
    "wof:placetype":"venue"
},
  "geometry": {"coordinates":[-87.46162200000001,41.56435],"type":"Point"}
}