{
  "type": "Feature",
  "properties": {
    "iso:country":"US",
    "sg:address":"12400 N Meridian St Suite 170",
    "sg:city":"Carmel",
    "sg:classifiers":[
        {
            "category":"Social Services",
            "type":"Services"
        },
        {
            "category":"Education",
            "subcategory":"Special Training",
            "type":"Public Place"
        },
        {
            "category":"Personal",
            "subcategory":"Adult",
            "type":"Services"
        }
    ],
    "sg:phone":"+1 317 218 5111",
    "sg:postcode":"46032",
    "sg:province":"IN",
    "sg:tags":[
        "consulting",
        "coaching-business",
        "educational",
        "geriatric"
    ],
    "sg:website":"http://www.AlzCareGroup.com",
    "wof:name":"Alzheimer's Care Group",
    "wof:placetype":"venue"
},
  "geometry": {"coordinates":[-86.158841,39.970794],"type":"Point"}
}