{
  "type": "Feature",
  "properties": {
    "addr:full":"2275 Leith Ct Indianapolis IN 46214",
    "addr:housenumber":"2275",
    "addr:postcode":"46214",
    "addr:street":"Leith Ct",
    "iso:country":"US",
    "sg:address":"2275 Leith Ct",
    "sg:city":"Indianapolis",
    "sg:classifiers":[
        {
            "category":"Arts & Performance",
            "subcategory":"Theater",
            "type":"Entertainment"
        }
    ],
    "sg:phone":"+1 317 248 8978",
    "sg:postcode":"46214",
    "sg:province":"IN",
    "sg:tags":[
        "live",
        "music"
    ],
    "wof:name":"Koffee's DJ Svc",
    "wof:placetype":"venue"
},
  "geometry": {"coordinates":[-86.300932,39.797211],"type":"Point"}
}