{
  "type": "Feature",
  "properties": {
    "iso:country":"US",
    "sg:address":"5492 N Vine School Rd",
    "sg:city":"Attica",
    "sg:classifiers":[
        {
            "category":"Farming",
            "subcategory":"Livestock Farm",
            "type":"Manufacturing & Wholesale Goods"
        }
    ],
    "sg:phone":"+1 765 572 2226",
    "sg:postcode":"47918",
    "sg:province":"IN",
    "sg:tags":[
        "beef",
        "feedlot",
        "cattle"
    ],
    "wof:name":"Carmen Wolfe",
    "wof:placetype":"venue"
},
  "geometry": {"coordinates":[-87.135271,40.323022],"type":"Point"}
}