{
  "type": "Feature",
  "properties": {
    "iso:country":"US",
    "sg:address":"1402 Wabash Ave",
    "sg:city":"Terre Haute",
    "sg:classifiers":[
        {
            "category":"Personal",
            "subcategory":"Beauty Salon",
            "type":"Services"
        }
    ],
    "sg:phone":"+1 812 234 4405",
    "sg:postcode":"47807",
    "sg:province":"IN",
    "wof:name":"Gary's Hair Designers",
    "wof:placetype":"venue"
},
  "geometry": {"coordinates":[-87.393745,39.468495],"type":"Point"}
}