{
  "type": "Feature",
  "properties": {
    "addr:full":"2830 Condit St Highland IN 46322",
    "addr:housenumber":"2830",
    "addr:postcode":"46322",
    "addr:street":"Condit St",
    "iso:country":"US",
    "sg:address":"2830 Condit St",
    "sg:city":"Highland",
    "sg:classifiers":[
        {
            "category":"Personal",
            "type":"Services"
        }
    ],
    "sg:phone":"+1 219 923 7025",
    "sg:postcode":"46322",
    "sg:province":"IN",
    "sg:tags":[
        "mover"
    ],
    "wof:name":"C & D Mini Moving",
    "wof:placetype":"venue"
},
  "geometry": {"coordinates":[-87.46076499999999,41.5564],"type":"Point"}
}