{
  "type": "Feature",
  "properties": {
    "iso:country":"US",
    "sg:address":"1421 McKinley Ave",
    "sg:city":"Vincennes",
    "sg:classifiers":[
        {
            "category":"Building & Trades",
            "subcategory":"Construction",
            "type":"Services"
        }
    ],
    "sg:phone":"+1 812 882 9794",
    "sg:postcode":"47591",
    "sg:province":"IN",
    "sg:tags":[
        "residential"
    ],
    "wof:name":"Welton Construction Joe",
    "wof:placetype":"venue"
},
  "geometry": {"coordinates":[-87.506154,38.678898],"type":"Point"}
}