{
  "type": "Feature",
  "properties": {
    "addr:full":"940 W 16th St Indianapolis IN 46202",
    "addr:housenumber":"940",
    "addr:postcode":"46202",
    "addr:street":"W 16Th St",
    "iso:country":"US",
    "sg:address":"940 W 16th St",
    "sg:city":"Indianapolis",
    "sg:classifiers":[
        {
            "category":"Autos & Motor Vehicles",
            "subcategory":"Automobile Sales",
            "type":"Retail Goods"
        },
        {
            "category":"Wholesale",
            "subcategory":"Scrap",
            "type":"Manufacturing & Wholesale Goods"
        },
        {
            "category":"Autos & Motor Vehicles",
            "subcategory":"Auto Supplies",
            "type":"Retail Goods"
        },
        {
            "category":"Retail",
            "subcategory":"Storage",
            "type":"Services"
        }
    ],
    "sg:phone":"+1 317 925 2277",
    "sg:postcode":"46202",
    "sg:province":"IN",
    "sg:tags":[
        "junk",
        "part",
        "supplies-used",
        "rebuilt",
        "salvage"
    ],
    "sg:website":"http://www.indypicapart.com",
    "wof:name":"Pic-A-Part",
    "wof:placetype":"venue"
},
  "geometry": {"coordinates":[-86.177677,39.788714],"type":"Point"}
}