{
  "type": "Feature",
  "properties": {
    "iso:country":"US",
    "sg:address":"403 Wabash Rd",
    "sg:city":"North Manchester",
    "sg:classifiers":[
        {
            "category":"Manufacturing",
            "subcategory":"Metals",
            "type":"Manufacturing & Wholesale Goods"
        }
    ],
    "sg:phone":"+1 260 982 2191",
    "sg:postcode":"46962",
    "sg:province":"IN",
    "sg:tags":[
        "foundry"
    ],
    "wof:name":"Machester Metals LLC",
    "wof:placetype":"venue"
},
  "geometry": {"coordinates":[-85.781326,40.995362],"type":"Point"}
}