{
  "type": "Feature",
  "properties": {
    "iso:country":"US",
    "sg:address":"4202 Majestic Ln",
    "sg:city":"Indianapolis",
    "sg:classifiers":[
        {
            "category":"Recreation",
            "type":"Entertainment"
        }
    ],
    "sg:phone":"+1 317 297 6006",
    "sg:postcode":"46254",
    "sg:province":"IN",
    "sg:tags":[
        "boxing",
        "instruction"
    ],
    "wof:name":"Bad Boys Boxing",
    "wof:placetype":"venue"
},
  "geometry": {"coordinates":[-86.274283,39.833412],"type":"Point"}
}