{
  "type": "Feature",
  "properties": {
    "iso:country":"US",
    "sg:address":"2514 Highland Rd",
    "sg:city":"Anderson",
    "sg:classifiers":[
        {
            "category":"Wholesale",
            "subcategory":"Drugs",
            "type":"Manufacturing & Wholesale Goods"
        }
    ],
    "sg:phone":"+1 765 642 1639",
    "sg:postcode":"46012",
    "sg:province":"IN",
    "wof:name":"Glaxo Smith Kline",
    "wof:placetype":"venue"
},
  "geometry": {"coordinates":[-85.64768100000001,40.134087],"type":"Point"}
}