{
  "type": "Feature",
  "properties": {
    "iso:country":"US",
    "sg:address":"8444 E Washington St",
    "sg:city":"Indianapolis",
    "sg:classifiers":[
        {
            "category":"Professional",
            "type":"Services"
        }
    ],
    "sg:phone":"+1 317 869 0111",
    "sg:postcode":"46219",
    "sg:province":"IN",
    "sg:tags":[
        "establishment"
    ],
    "wof:name":"Shearer Co Inc",
    "wof:placetype":"venue"
},
  "geometry": {"coordinates":[-86.018567,39.773523],"type":"Point"}
}