{
  "type": "Feature",
  "properties": {
    "iso:country":"US",
    "sg:address":"16 S Westside Dr",
    "sg:city":"New Palestine",
    "sg:classifiers":[
        {
            "category":"Home & Garden",
            "subcategory":"Building Materials",
            "type":"Retail Goods"
        }
    ],
    "sg:phone":"+1 317 861 6305",
    "sg:postcode":"46163",
    "sg:province":"IN",
    "sg:tags":[
        "dry wall"
    ],
    "wof:name":"New Palestine Drywall Supply",
    "wof:placetype":"venue"
},
  "geometry": {"coordinates":[-85.898578,39.721188],"type":"Point"}
}