{
  "type": "Feature",
  "properties": {
    "iso:country":"US",
    "sg:address":"8911 Telephone Rd",
    "sg:city":"Chandler",
    "sg:classifiers":[
        {
            "category":"Personal",
            "subcategory":"Beauty Salon",
            "type":"Services"
        }
    ],
    "sg:phone":"+1 812 858 0035",
    "sg:postcode":"47610",
    "sg:province":"IN",
    "wof:name":"Beth's Styling & Tanning Salon",
    "wof:placetype":"venue"
},
  "geometry": {"coordinates":[-87.411545,38.005525],"type":"Point"}
}