{
  "type": "Feature",
  "properties": {
    "iso:country":"US",
    "sg:address":"912 Main St",
    "sg:city":"Elwood",
    "sg:classifiers":[
        {
            "category":"Home & Garden",
            "subcategory":"Hardware",
            "type":"Retail Goods"
        }
    ],
    "sg:phone":"+1 765 552 2723",
    "sg:postcode":"46036",
    "sg:province":"IN",
    "wof:name":"Genes Softwater",
    "wof:placetype":"venue"
},
  "geometry": {"coordinates":[-85.850154,40.277028],"type":"Point"}
}