{
  "type": "Feature",
  "properties": {
    "iso:country":"US",
    "sg:address":"307 Sagamore Pkwy W",
    "sg:city":"West Lafayette",
    "sg:classifiers":[
        {
            "category":"Restaurant",
            "type":"Food & Drink"
        }
    ],
    "sg:menulink":"http://www.allmenus.com/in/wabash/237597-pizza-king/menu/",
    "sg:phone":"+1 765 463 5581",
    "sg:postcode":"47906",
    "sg:province":"IN",
    "sg:tags":[
        "american",
        "pizza"
    ],
    "wof:name":"Pizza King",
    "wof:placetype":"venue"
},
  "geometry": {"coordinates":[-86.90896600000001,40.452779],"type":"Point"}
}