{
  "type": "Feature",
  "properties": {
    "iso:country":"US",
    "sg:address":"8 N Washington St",
    "sg:city":"Worthington",
    "sg:classifiers":[
        {
            "category":"Social Services",
            "type":"Services"
        }
    ],
    "sg:phone":"+1 812 875 2525",
    "sg:postcode":"47471",
    "sg:province":"IN",
    "wof:name":"Worthington Senior Citizens",
    "wof:placetype":"venue"
},
  "geometry": {"coordinates":[-86.97645900000001,39.118954],"type":"Point"}
}