{
  "type": "Feature",
  "properties": {
    "iso:country":"US",
    "sg:address":"104 E Lincoln St",
    "sg:city":"Nappanee",
    "sg:classifiers":[
        {
            "category":"Home & Garden",
            "subcategory":"Carpets & Floor Coverings",
            "type":"Retail Goods"
        }
    ],
    "sg:phone":"+1 574 773 7001",
    "sg:postcode":"46550",
    "sg:province":"IN",
    "sg:tags":[
        "dealer",
        "rug"
    ],
    "wof:name":"Graber's Carpet Studio",
    "wof:placetype":"venue"
},
  "geometry": {"coordinates":[-86.001256,41.441742],"type":"Point"}
}