{
  "type": "Feature",
  "properties": {
    "iso:country":"US",
    "sg:address":"2750 E Chicago Ave",
    "sg:city":"East Chicago",
    "sg:classifiers":[
        {
            "category":"Organizations",
            "subcategory":"Religious Organization",
            "type":"Services"
        }
    ],
    "sg:phone":"+1 219 397 8306",
    "sg:postcode":"46312",
    "sg:province":"IN",
    "sg:tags":[
        "clergy"
    ],
    "wof:name":"Milton Reed",
    "wof:placetype":"venue"
},
  "geometry": {"coordinates":[-87.442095,41.62907],"type":"Point"}
}