{
  "type": "Feature",
  "properties": {
    "iso:country":"US",
    "sg:address":"1121 W Morgan St",
    "sg:city":"Kokomo",
    "sg:classifiers":[
        {
            "category":"Retail",
            "subcategory":"Repair Shop",
            "type":"Services"
        }
    ],
    "sg:phone":"+1 765 457 7202",
    "sg:postcode":"46901",
    "sg:province":"IN",
    "sg:tags":[
        "furniture"
    ],
    "wof:name":"Strip Shop",
    "wof:placetype":"venue"
},
  "geometry": {"coordinates":[-86.142606,40.505205],"type":"Point"}
}