{
  "type": "Feature",
  "properties": {
    "iso:country":"US",
    "sg:address":"122 N Michigan St",
    "sg:city":"Argos",
    "sg:classifiers":[
        {
            "category":"Building & Trades",
            "subcategory":"Construction",
            "type":"Services"
        }
    ],
    "sg:phone":"+1 574 892 5063",
    "sg:postcode":"46501",
    "sg:province":"IN",
    "sg:tags":[
        "general",
        "contractor"
    ],
    "wof:name":"Easterday Construction Co",
    "wof:placetype":"venue"
},
  "geometry": {"coordinates":[-86.245501,41.237832],"type":"Point"}
}