{
  "type": "Feature",
  "properties": {
    "iso:country":"US",
    "sg:address":"1316 Cincinnati St",
    "sg:city":"Lafayette",
    "sg:classifiers":[
        {
            "category":"Building & Trades",
            "subcategory":"Construction",
            "type":"Services"
        }
    ],
    "sg:phone":"+1 765 423 1830",
    "sg:postcode":"47904",
    "sg:province":"IN",
    "sg:tags":[
        "general",
        "contractor"
    ],
    "wof:name":"Runyan Construction",
    "wof:placetype":"venue"
},
  "geometry": {"coordinates":[-86.882316,40.422813],"type":"Point"}
}