{
  "type": "Feature",
  "properties": {
    "iso:country":"US",
    "sg:address":"15031 E Tillman Rd",
    "sg:city":"Fort Wayne",
    "sg:classifiers":[
        {
            "category":"Building & Trades",
            "subcategory":"Construction",
            "type":"Services"
        }
    ],
    "sg:phone":"+1 260 493 4672",
    "sg:postcode":"46816",
    "sg:province":"IN",
    "sg:tags":[
        "home",
        "improvement"
    ],
    "wof:name":"D A Home Improvements",
    "wof:placetype":"venue"
},
  "geometry": {"coordinates":[-84.94603499999999,41.02125],"type":"Point"}
}