{
  "type": "Feature",
  "properties": {
    "iso:country":"US",
    "sg:address":"2011 Beckin Dr",
    "sg:city":"Floyds Knobs",
    "sg:classifiers":[
        {
            "category":"Building & Trades",
            "subcategory":"Construction",
            "type":"Services"
        }
    ],
    "sg:phone":"+1 812 945 2030",
    "sg:postcode":"47119",
    "sg:province":"IN",
    "sg:tags":[
        "painting",
        "contractor"
    ],
    "wof:name":"W E Colin Company",
    "wof:placetype":"venue"
},
  "geometry": {"coordinates":[-85.848992,38.376399],"type":"Point"}
}