{
  "type": "Feature",
  "properties": {
    "iso:country":"US",
    "sg:address":"750 N Main St",
    "sg:city":"Crown Point",
    "sg:classifiers":[
        {
            "category":"Personal",
            "subcategory":"Nail Salon",
            "type":"Services"
        }
    ],
    "sg:phone":"+1 219 662 9960",
    "sg:postcode":"46307",
    "sg:province":"IN",
    "wof:name":"Sirens Full Service Salon",
    "wof:placetype":"venue"
},
  "geometry": {"coordinates":[-87.364304,41.426601],"type":"Point"}
}