{
  "type": "Feature",
  "properties": {
    "iso:country":"US",
    "sg:address":"205 W Main St",
    "sg:city":"Monrovia",
    "sg:classifiers":[
        {
            "category":"Shopping",
            "type":"Retail Goods"
        }
    ],
    "sg:phone":"+1 317 996 2700",
    "sg:postcode":"46157",
    "sg:province":"IN",
    "sg:tags":[
        "coin",
        "dealer",
        "supply"
    ],
    "wof:name":"Monrovia Antique & Coin",
    "wof:placetype":"venue"
},
  "geometry": {"coordinates":[-86.483062,39.578779],"type":"Point"}
}