{
  "type": "Feature",
  "properties": {
    "iso:country":"US",
    "sg:address":"2294 S Old Decker Rd",
    "sg:city":"Vincennes",
    "sg:classifiers":[
        {
            "category":"Wholesale",
            "subcategory":"Hardware",
            "type":"Manufacturing & Wholesale Goods"
        }
    ],
    "sg:phone":"+1 812 882 3470",
    "sg:postcode":"47591",
    "sg:province":"IN",
    "sg:tags":[
        "plumbing",
        "fixture",
        "supply"
    ],
    "wof:name":"O'Donnell Supply Corp",
    "wof:placetype":"venue"
},
  "geometry": {"coordinates":[-87.527551,38.64826],"type":"Point"}
}