{
  "type": "Feature",
  "properties": {
    "iso:country":"US",
    "sg:address":"360 N 400 W",
    "sg:city":"Marion",
    "sg:classifiers":[
        {
            "category":"Retail",
            "subcategory":"Auto Repair",
            "type":"Services"
        }
    ],
    "sg:phone":"+1 765 384 7793",
    "sg:postcode":"46953",
    "sg:province":"IN",
    "sg:tags":[
        "repairing",
        "automobile"
    ],
    "wof:name":"Elliott Automotive & Constr",
    "wof:placetype":"venue"
},
  "geometry": {"coordinates":[-85.749936,40.564044],"type":"Point"}
}