{
  "type": "Feature",
  "properties": {
    "addr:full":"1514 W Mishawaka Ave South Bend IN 46615",
    "addr:housenumber":"1514",
    "addr:postcode":"46615",
    "addr:street":"W Mishawaka Ave",
    "iso:country":"US",
    "sg:address":"1514 W Mishawaka Ave",
    "sg:city":"South Bend",
    "sg:classifiers":[
        {
            "category":"Home & Garden",
            "subcategory":"Carpets & Floor Coverings",
            "type":"Retail Goods"
        }
    ],
    "sg:phone":"+1 574 287 7148",
    "sg:postcode":"46615",
    "sg:province":"IN",
    "sg:tags":[
        "dealer",
        "rug"
    ],
    "wof:name":"Carpet Service Outlet",
    "wof:placetype":"venue"
},
  "geometry": {"coordinates":[-86.224493,41.665734],"type":"Point"}
}