{
  "type": "Feature",
  "properties": {
    "iso:country":"US",
    "sg:address":"2544 Lauren Ln",
    "sg:city":"Kokomo",
    "sg:classifiers":[
        {
            "category":"Professional",
            "subcategory":"Management & Consulting",
            "type":"Services"
        }
    ],
    "sg:phone":"+1 765 457 4575",
    "sg:postcode":"46901",
    "sg:province":"IN",
    "sg:tags":[
        "forum",
        "pt",
        "cruiser",
        "for",
        "discussion",
        "chrysler",
        "owner"
    ],
    "wof:name":"Pt Enthusiasts",
    "wof:placetype":"venue"
},
  "geometry": {"coordinates":[-86.167509,40.482203],"type":"Point"}
}