{
  "type": "Feature",
  "properties": {
    "iso:country":"US",
    "sg:address":"703 Hendricks St",
    "sg:city":"Berne",
    "sg:classifiers":[
        {
            "category":"Professional",
            "subcategory":"Business Services",
            "type":"Services"
        }
    ],
    "sg:phone":"+1 260 589 8690",
    "sg:postcode":"46711",
    "sg:province":"IN",
    "wof:name":"Scott Editing & Design In",
    "wof:placetype":"venue"
},
  "geometry": {"coordinates":[-84.951149,40.651715],"type":"Point"}
}