{
  "type": "Feature",
  "properties": {
    "iso:country":"US",
    "sg:address":"11191 Governors Ln",
    "sg:city":"Fishers",
    "sg:classifiers":[
        {
            "category":"Building & Trades",
            "subcategory":"Construction",
            "type":"Services"
        }
    ],
    "sg:phone":"+1 317 849 9888",
    "sg:postcode":"46037",
    "sg:province":"IN",
    "sg:tags":[
        "general",
        "contractor"
    ],
    "wof:name":"D & D Construction & Mntnc",
    "wof:placetype":"venue"
},
  "geometry": {"coordinates":[-85.966285,39.940073],"type":"Point"}
}