{
  "type": "Feature",
  "properties": {
    "iso:country":"US",
    "sg:address":"401 W Central Ave",
    "sg:city":"Lagrange",
    "sg:classifiers":[
        {
            "category":"Professional",
            "type":"Services"
        }
    ],
    "sg:phone":"+1 260 463 0127",
    "sg:postcode":"46761",
    "sg:province":"IN",
    "sg:tags":[
        "establishment"
    ],
    "wof:name":"K & M Systems",
    "wof:placetype":"venue"
},
  "geometry": {"coordinates":[-85.42484399999999,41.641377],"type":"Point"}
}