{
  "type": "Feature",
  "properties": {
    "iso:country":"US",
    "sg:address":"9715 Skipjack Cove",
    "sg:city":"Fort Wayne",
    "sg:classifiers":[
        {
            "category":"Real Estate",
            "subcategory":"Real Estate Agent",
            "type":"Services"
        }
    ],
    "sg:phone":"+1 260 485 3115",
    "sg:postcode":"46835",
    "sg:province":"IN",
    "sg:website":"www.heavenlyhome.com",
    "wof:name":"Duesler Realty House",
    "wof:placetype":"venue"
},
  "geometry": {"coordinates":[-85.01816700000001,41.136927],"type":"Point"}
}