{
  "type": "Feature",
  "properties": {
    "iso:country":"US",
    "sg:address":"413 N 11th St",
    "sg:city":"Lafayette",
    "sg:classifiers":[
        {
            "category":"Retail",
            "subcategory":"Repair Shop",
            "type":"Services"
        }
    ],
    "sg:phone":"+1 765 532 1079",
    "sg:postcode":"47904",
    "sg:province":"IN",
    "sg:tags":[
        "press",
        "printing"
    ],
    "wof:name":"James Cottome",
    "wof:placetype":"venue"
},
  "geometry": {"coordinates":[-86.884906,40.421717],"type":"Point"}
}