{
  "type": "Feature",
  "properties": {
    "iso:country":"US",
    "sg:address":"9975 E Jefferson St",
    "sg:city":"Otwell",
    "sg:classifiers":[
        {
            "category":"Government",
            "subcategory":"Fire Station",
            "type":"Public Place"
        }
    ],
    "sg:phone":"+1 812 354 3806",
    "sg:postcode":"47564",
    "sg:province":"IN",
    "sg:tags":[
        "department"
    ],
    "wof:name":"Jefferson Twp Vol Fire Dept",
    "wof:placetype":"venue"
},
  "geometry": {"coordinates":[-87.092361,38.455809],"type":"Point"}
}