{
  "type": "Feature",
  "properties": {
    "iso:country":"US",
    "sg:address":"1735 W 53rd St",
    "sg:city":"Anderson",
    "sg:classifiers":[
        {
            "category":"Manufacturing",
            "subcategory":"Tools & Machinery",
            "type":"Manufacturing & Wholesale Goods"
        }
    ],
    "sg:phone":"+1 765 643 6691",
    "sg:postcode":"46013",
    "sg:province":"IN",
    "sg:tags":[
        "machine"
    ],
    "sg:website":"www.ateinc.com",
    "wof:name":"Anderson Tool & Engineering",
    "wof:placetype":"venue"
},
  "geometry": {"coordinates":[-85.70648199999999,40.061361],"type":"Point"}
}