{
  "type": "Feature",
  "properties": {
    "iso:country":"US",
    "sg:address":"7245 Noel Rd",
    "sg:city":"Indianapolis",
    "sg:classifiers":[
        {
            "category":"Wholesale",
            "subcategory":"Durable Goods & Equipment",
            "type":"Manufacturing & Wholesale Goods"
        }
    ],
    "sg:phone":"+1 317 388 1111",
    "sg:postcode":"46278",
    "sg:province":"IN",
    "sg:tags":[
        "magnet",
        "magnetic",
        "devices"
    ],
    "sg:website":"www.promotionalproductsnow.com",
    "wof:name":"Wilco Specialty Advertising",
    "wof:placetype":"venue"
},
  "geometry": {"coordinates":[-86.292947,39.88844],"type":"Point"}
}