{
  "type": "Feature",
  "properties": {
    "iso:country":"US",
    "sg:address":"8416 Kennedy Ave",
    "sg:city":"Highland",
    "sg:classifiers":[
        {
            "category":"Personal",
            "subcategory":"Beauty Salon",
            "type":"Services"
        },
        {
            "category":"Personal",
            "subcategory":"Barber",
            "type":"Services"
        }
    ],
    "sg:phone":"+1 219 838 7862",
    "sg:postcode":"46322",
    "sg:province":"IN",
    "sg:tags":[
        "shop"
    ],
    "wof:name":"George's Gentlemen Shop",
    "wof:placetype":"venue"
},
  "geometry": {"coordinates":[-87.4618,41.5606],"type":"Point"}
}