{
  "type": "Feature",
  "properties": {
    "iso:country":"US",
    "sg:address":"1116 N 16th St",
    "sg:city":"Lafayette",
    "sg:classifiers":[
        {
            "category":"Health Services",
            "subcategory":"Doctor",
            "type":"Services"
        }
    ],
    "sg:phone":"+1 765 428 2500",
    "sg:postcode":"47904",
    "sg:province":"IN",
    "sg:tags":[
        "physician",
        "surgeon"
    ],
    "sg:website":"www.thecaregroup.com",
    "wof:name":"Care Group Lafayette",
    "wof:placetype":"venue"
},
  "geometry": {"coordinates":[-86.879657,40.429868],"type":"Point"}
}