{
  "type": "Feature",
  "properties": {
    "iso:country":"US",
    "sg:address":"4202 Melbourne Rd",
    "sg:city":"Indianapolis",
    "sg:classifiers":[
        {
            "category":"Professional",
            "subcategory":"Business Services",
            "type":"Services"
        }
    ],
    "sg:phone":"+1 317 791 0100",
    "sg:postcode":"46228",
    "sg:province":"IN",
    "sg:tags":[
        "holding"
    ],
    "wof:name":"Pbh Holdings, Inc.",
    "wof:placetype":"venue"
},
  "geometry": {"coordinates":[-86.220558,39.831628],"type":"Point"}
}