{
  "type": "Feature",
  "properties": {
    "iso:country":"US",
    "sg:address":"851 Marietta St",
    "sg:city":"South Bend",
    "sg:classifiers":[
        {
            "category":"Professional",
            "subcategory":"Business Services",
            "type":"Services"
        }
    ],
    "sg:phone":"+1 952 884 1111",
    "sg:postcode":"46601",
    "sg:province":"IN",
    "sg:tags":[
        "answering",
        "telephone"
    ],
    "wof:name":"A-Alpha",
    "wof:placetype":"venue"
},
  "geometry": {"coordinates":[-86.241082,41.666208],"type":"Point"}
}