{
  "type": "Feature",
  "properties": {
    "iso:country":"US",
    "sg:address":"502 Kesco Dr",
    "sg:city":"Bristol",
    "sg:classifiers":[
        {
            "category":"Manufacturing",
            "subcategory":"Furniture",
            "type":"Manufacturing & Wholesale Goods"
        }
    ],
    "sg:phone":"+1 574 848 5697",
    "sg:postcode":"46507",
    "sg:province":"IN",
    "wof:name":"Mission Woodworking",
    "wof:placetype":"venue"
},
  "geometry": {"coordinates":[-85.815463,41.716776],"type":"Point"}
}