{
  "type": "Feature",
  "properties": {
    "iso:country":"US",
    "sg:address":"4997 W State Rd 44",
    "sg:city":"Morgantown",
    "sg:classifiers":[
        {
            "category":"Retail",
            "subcategory":"Laundry & Dry Cleaning",
            "type":"Services"
        }
    ],
    "sg:phone":"+1 317 738 4881",
    "sg:postcode":"46160",
    "sg:province":"IN",
    "wof:name":"Franklin Launderette",
    "wof:placetype":"venue"
},
  "geometry": {"coordinates":[-86.195401,39.445939],"type":"Point"}
}