{
  "type": "Feature",
  "properties": {
    "iso:country":"US",
    "sg:address":"26262 Co Rd 40",
    "sg:city":"Goshen",
    "sg:classifiers":[
        {
            "category":"Building & Trades",
            "subcategory":"Construction",
            "type":"Services"
        }
    ],
    "sg:phone":"+1 574 862 2142",
    "sg:postcode":"46526",
    "sg:province":"IN",
    "sg:tags":[
        "general",
        "contractor"
    ],
    "sg:website":"www.martinbroscontracting.com",
    "wof:name":"Martin Brothers Contracting",
    "wof:placetype":"venue"
},
  "geometry": {"coordinates":[-85.967697,41.536332],"type":"Point"}
}