{
  "type": "Feature",
  "properties": {
    "iso:country":"US",
    "sg:address":"7016 Dubonnet Ct",
    "sg:city":"Indianapolis",
    "sg:classifiers":[
        {
            "category":"Banks & Credit Unions",
            "subcategory":"Investment Brokerage",
            "type":"Services"
        }
    ],
    "sg:phone":"+1 317 875 5263",
    "sg:postcode":"46278",
    "sg:province":"IN",
    "wof:name":"Universal Investment",
    "wof:placetype":"venue"
},
  "geometry": {"coordinates":[-86.286243,39.88963],"type":"Point"}
}