{
  "type": "Feature",
  "properties": {
    "iso:country":"US",
    "sg:address":"5668 Grape Rd",
    "sg:city":"Mishawaka",
    "sg:classifiers":[
        {
            "category":"Banks & Credit Unions",
            "subcategory":"Bank",
            "type":"Services"
        }
    ],
    "sg:phone":"+1 574 273 4880",
    "sg:postcode":"46545",
    "sg:province":"IN",
    "sg:tags":[
        "loan"
    ],
    "wof:name":"Household Finance",
    "wof:placetype":"venue"
},
  "geometry": {"coordinates":[-86.187546,41.711713],"type":"Point"}
}