{
  "type": "Feature",
  "properties": {
    "iso:country":"US",
    "sg:address":"510 E 5th St",
    "sg:city":"Connersville",
    "sg:classifiers":[
        {
            "category":"Shopping",
            "type":"Retail Goods"
        }
    ],
    "sg:phone":"+1 765 825 4478",
    "sg:postcode":"47331",
    "sg:province":"IN",
    "sg:tags":[
        "pet",
        "food",
        "supply"
    ],
    "wof:name":"Fayette Feed Farm & Pet Supply",
    "wof:placetype":"venue"
},
  "geometry": {"coordinates":[-85.132406,39.63956],"type":"Point"}
}