{
  "type": "Feature",
  "properties": {
    "addr:full":"115 W 8th St Anderson IN 46016",
    "addr:housenumber":"115",
    "addr:postcode":"46016",
    "addr:street":"W 8Th St",
    "iso:country":"US",
    "sg:address":"115 W 8th St",
    "sg:city":"Anderson",
    "sg:classifiers":[
        {
            "category":"Shopping",
            "subcategory":"Gifts & Souvenirs",
            "type":"Retail Goods"
        }
    ],
    "sg:phone":"+1 765 643 0028",
    "sg:postcode":"46016",
    "sg:province":"IN",
    "sg:tags":[
        "shop"
    ],
    "wof:name":"Moneyhun's Fine Gifts",
    "wof:placetype":"venue"
},
  "geometry": {"coordinates":[-85.68164400000001,40.107812],"type":"Point"}
}