{
  "type": "Feature",
  "properties": {
    "iso:country":"US",
    "sg:address":"1471 N New Jersey St",
    "sg:city":"Indianapolis",
    "sg:classifiers":[
        {
            "category":"Professional",
            "type":"Services"
        }
    ],
    "sg:phone":"+1 317 972 1812",
    "sg:postcode":"46202",
    "sg:province":"IN",
    "wof:name":"Financialfacts",
    "wof:placetype":"venue"
},
  "geometry": {"coordinates":[-86.150737,39.786084],"type":"Point"}
}