{
  "type": "Feature",
  "properties": {
    "iso:country":"US",
    "sg:address":"1507 W Monticello Rd",
    "sg:city":"Rochester",
    "sg:classifiers":[
        {
            "category":"Manufacturing",
            "subcategory":"Tools & Machinery",
            "type":"Manufacturing & Wholesale Goods"
        }
    ],
    "sg:phone":"+1 574 223 8962",
    "sg:postcode":"46975",
    "sg:province":"IN",
    "sg:tags":[
        "machine",
        "shop"
    ],
    "wof:name":"S S Performance & Machining",
    "wof:placetype":"venue"
},
  "geometry": {"coordinates":[-86.239995,41.085596],"type":"Point"}
}