{
  "type": "Feature",
  "properties": {
    "iso:country":"US",
    "sg:address":"101 N 6th St",
    "sg:city":"Kentland",
    "sg:classifiers":[
        {
            "category":"Insurance",
            "subcategory":"Insurance Agent",
            "type":"Services"
        }
    ],
    "sg:phone":"+1 219 474 5177",
    "sg:postcode":"47951",
    "sg:province":"IN",
    "wof:name":"Kindell Insurance Svc",
    "wof:placetype":"venue"
},
  "geometry": {"coordinates":[-87.439666,40.768916],"type":"Point"}
}