{
  "type": "Feature",
  "properties": {
    "iso:country":"US",
    "sg:address":"500 Shiloh Rd SW",
    "sg:city":"Corydon",
    "sg:classifiers":[
        {
            "category":"Organizations",
            "subcategory":"Religious Organization",
            "type":"Services"
        }
    ],
    "sg:phone":"+1 812 738 2516",
    "sg:postcode":"47112",
    "sg:province":"IN",
    "sg:tags":[
        "church"
    ],
    "wof:name":"Trinity Assembly Of God Church",
    "wof:placetype":"venue"
},
  "geometry": {"coordinates":[-86.137488,38.179416],"type":"Point"}
}