{
  "type": "Feature",
  "properties": {
    "iso:country":"US",
    "sg:address":"1020 E Chicago Ave",
    "sg:city":"East Chicago",
    "sg:classifiers":[
        {
            "category":"Personal",
            "subcategory":"Beauty Salon",
            "type":"Services"
        }
    ],
    "sg:phone":"+1 219 378 1272",
    "sg:postcode":"46312",
    "sg:province":"IN",
    "wof:name":"Lasting Impressions",
    "wof:placetype":"venue"
},
  "geometry": {"coordinates":[-87.458122,41.629262],"type":"Point"}
}