{
  "type": "Feature",
  "properties": {
    "addr:full":"217 E Main St Washington IN 47501",
    "addr:housenumber":"217",
    "addr:postcode":"47501",
    "addr:street":"E Main St",
    "iso:country":"US",
    "sg:address":"217 E Main St",
    "sg:city":"Washington",
    "sg:classifiers":[
        {
            "category":"Shopping",
            "subcategory":"Pharmacy",
            "type":"Retail Goods"
        }
    ],
    "sg:phone":"+1 812 254 5141",
    "sg:postcode":"47501",
    "sg:province":"IN",
    "wof:name":"Main Street Pharmacy",
    "wof:placetype":"venue"
},
  "geometry": {"coordinates":[-87.17324600000001,38.656862],"type":"Point"}
}