{
  "type": "Feature",
  "properties": {
    "addr:full":"301 W Maple St Jeffersonville IN 47130",
    "addr:housenumber":"301",
    "addr:postcode":"47130",
    "addr:street":"W Maple St",
    "iso:country":"US",
    "sg:address":"301 W Maple St",
    "sg:city":"Jeffersonville",
    "sg:classifiers":[
        {
            "category":"Travel",
            "subcategory":"Hotels & Motels",
            "type":"Entertainment"
        }
    ],
    "sg:phone":"+1 812 283 8696",
    "sg:postcode":"47130",
    "sg:province":"IN",
    "wof:name":"Alben Motel",
    "wof:placetype":"venue"
},
  "geometry": {"coordinates":[-85.74374299999999,38.271843],"type":"Point"}
}