{
  "type": "Feature",
  "properties": {
    "addr:full":"11703 N 700 W-57 Topeka IN 46571",
    "addr:housenumber":"11703;w-57",
    "addr:postcode":"46571",
    "addr:street":"N 700",
    "iso:country":"US",
    "sg:address":"11703 N 700 W-57",
    "sg:city":"Topeka",
    "sg:classifiers":[
        {
            "category":"Farming",
            "subcategory":"Farm",
            "type":"Manufacturing & Wholesale Goods"
        }
    ],
    "sg:phone":"+1 260 593 2083",
    "sg:postcode":"46571",
    "sg:province":"IN",
    "wof:name":"J D Farms",
    "wof:placetype":"venue"
},
  "geometry": {"coordinates":[-85.558271,41.524665],"type":"Point"}
}