{
  "type": "Feature",
  "properties": {
    "addr:full":"2039 Columbus Ave Anderson IN 46016",
    "addr:housenumber":"2039",
    "addr:postcode":"46016",
    "addr:street":"Columbus Ave",
    "iso:country":"US",
    "sg:address":"2039 Columbus Ave",
    "sg:city":"Anderson",
    "sg:classifiers":[
        {
            "category":"Retail",
            "subcategory":"Laundry & Dry Cleaning",
            "type":"Services"
        }
    ],
    "sg:phone":"+1 765 649 0000",
    "sg:postcode":"46016",
    "sg:province":"IN",
    "sg:tags":[
        "cleaners",
        "rug",
        "carpet"
    ],
    "wof:name":"Bob Keller's Carpet Cleaning",
    "wof:placetype":"venue"
},
  "geometry": {"coordinates":[-85.667145,40.095993],"type":"Point"}
}