{
  "type": "Feature",
  "properties": {
    "iso:country":"US",
    "sg:address":"3230 E 25th St",
    "sg:city":"Indianapolis",
    "sg:classifiers":[
        {
            "category":"Retail",
            "subcategory":"Repair Shop",
            "type":"Services"
        }
    ],
    "sg:phone":"+1 317 541 9267",
    "sg:postcode":"46218",
    "sg:province":"IN",
    "sg:tags":[
        "related"
    ],
    "wof:name":"Marion Repair Shop",
    "wof:placetype":"venue"
},
  "geometry": {"coordinates":[-86.11103,39.803469],"type":"Point"}
}