{
  "type": "Feature",
  "properties": {
    "iso:country":"US",
    "sg:address":"1230 Wabash Ave",
    "sg:city":"Terre Haute",
    "sg:classifiers":[
        {
            "category":"Building & Trades",
            "subcategory":"Plumbing",
            "type":"Services"
        }
    ],
    "sg:phone":"+1 812 234 4806",
    "sg:postcode":"47807",
    "sg:province":"IN",
    "sg:tags":[
        "heating",
        "contractor"
    ],
    "sg:website":"www.wadsworthfurnace.com",
    "wof:name":"Wadsworth Furnace Co",
    "wof:placetype":"venue"
},
  "geometry": {"coordinates":[-87.39816,39.46776],"type":"Point"}
}