{
  "type": "Feature",
  "properties": {
    "iso:country":"US",
    "sg:address":"6527 Madison Ave",
    "sg:city":"Hammond",
    "sg:classifiers":[
        {
            "category":"Social Services",
            "subcategory":"Child Care",
            "type":"Services"
        }
    ],
    "sg:phone":"+1 219 937 2310",
    "sg:postcode":"46324",
    "sg:province":"IN",
    "sg:tags":[
        "day"
    ],
    "wof:name":"Secrets Loving Care",
    "wof:placetype":"venue"
},
  "geometry": {"coordinates":[-87.511199,41.595037],"type":"Point"}
}