{
  "type": "Feature",
  "properties": {
    "iso:country":"US",
    "sg:address":"429 W Carmel Dr",
    "sg:city":"Carmel",
    "sg:classifiers":[
        {
            "category":"Retail",
            "subcategory":"Auto Repair",
            "type":"Services"
        }
    ],
    "sg:phone":"+1 317 571 0800",
    "sg:postcode":"46032",
    "sg:province":"IN",
    "wof:name":"Dierolf Autohaus",
    "wof:placetype":"venue"
},
  "geometry": {"coordinates":[-86.13449900000001,39.962299],"type":"Point"}
}