{
  "type": "Feature",
  "properties": {
    "iso:country":"US",
    "sg:address":"2826 US Hwy 231 S",
    "sg:city":"Lafayette",
    "sg:classifiers":[
        {
            "category":"Restaurant",
            "type":"Food & Drink"
        }
    ],
    "sg:phone":"+1 765 477 1100",
    "sg:postcode":"47909",
    "sg:province":"IN",
    "wof:name":"Domino's Pizza",
    "wof:placetype":"venue"
},
  "geometry": {"coordinates":[-86.917609,40.379217],"type":"Point"}
}