{
  "type": "Feature",
  "properties": {
    "iso:country":"US",
    "sg:address":"3805 W Southport Rd",
    "sg:city":"Indianapolis",
    "sg:classifiers":[
        {
            "category":"Building & Trades",
            "subcategory":"Construction",
            "type":"Services"
        }
    ],
    "sg:phone":"+1 317 887 9700",
    "sg:postcode":"46217",
    "sg:province":"IN",
    "sg:tags":[
        "contractor"
    ],
    "wof:name":"C W Siding",
    "wof:placetype":"venue"
},
  "geometry": {"coordinates":[-86.22712,39.663146],"type":"Point"}
}