{
  "type": "Feature",
  "properties": {
    "iso:country":"US",
    "sg:address":"307 S Newton St",
    "sg:city":"Goodland",
    "sg:classifiers":[
        {
            "category":"Real Estate",
            "subcategory":"Real Estate Agent",
            "type":"Services"
        }
    ],
    "sg:phone":"+1 219 297 3000",
    "sg:postcode":"47948",
    "sg:province":"IN",
    "wof:name":"Burton Farm & Home Realty",
    "wof:placetype":"venue"
},
  "geometry": {"coordinates":[-87.293455,40.763278],"type":"Point"}
}