{
  "type": "Feature",
  "properties": {
    "iso:country":"US",
    "sg:address":"20002 E Co Rd 640 N",
    "sg:city":"Hope",
    "sg:classifiers":[
        {
            "category":"Building & Trades",
            "subcategory":"Cleaning & Sanitation",
            "type":"Services"
        }
    ],
    "sg:phone":"+1 812 546 5044",
    "sg:postcode":"47246",
    "sg:province":"IN",
    "sg:tags":[
        "fireplace",
        "chimney"
    ],
    "wof:name":"Indiana Soot Busters Chimney",
    "wof:placetype":"venue"
},
  "geometry": {"coordinates":[-85.707202,39.293308],"type":"Point"}
}