{
  "type": "Feature",
  "properties": {
    "iso:country":"US",
    "sg:address":"11150 Millgrove Rd",
    "sg:city":"Quincy",
    "sg:classifiers":[
        {
            "category":"Recreation",
            "type":"Entertainment"
        }
    ],
    "sg:phone":"+1 765 795 6053",
    "sg:postcode":"47456",
    "sg:province":"IN",
    "sg:tags":[
        "archery",
        "range"
    ],
    "wof:name":"Nancy's Broken Arrow",
    "wof:placetype":"venue"
},
  "geometry": {"coordinates":[-86.762357,39.484348],"type":"Point"}
}