{
  "type": "Feature",
  "properties": {
    "iso:country":"US",
    "sg:address":"1340 W 86th St",
    "sg:city":"Indianapolis",
    "sg:classifiers":[
        {
            "category":"Autos & Motor Vehicles",
            "subcategory":"Fuel & Gas Station",
            "type":"Retail Goods"
        }
    ],
    "sg:phone":"+1 317 843 9555",
    "sg:postcode":"46260",
    "sg:province":"IN",
    "sg:website":"www.speedway.com",
    "wof:name":"Speedway Petroleum",
    "wof:placetype":"venue"
},
  "geometry": {"coordinates":[-86.183403,39.912399],"type":"Point"}
}