{
  "type": "Feature",
  "properties": {
    "iso:country":"US",
    "sg:address":"1311 S Heaton St",
    "sg:city":"Knox",
    "sg:classifiers":[
        {
            "category":"Professional",
            "subcategory":"Accounting & Tax Preparation",
            "type":"Services"
        }
    ],
    "sg:phone":"+1 574 772 2316",
    "sg:postcode":"46534",
    "sg:province":"IN",
    "sg:tags":[
        "return",
        "filing"
    ],
    "wof:name":"H & R Block Tax Svc",
    "wof:placetype":"venue"
},
  "geometry": {"coordinates":[-86.62058,41.285103],"type":"Point"}
}