{
  "type": "Feature",
  "properties": {
    "iso:country":"US",
    "sg:address":"56 E Main St",
    "sg:city":"Danville",
    "sg:classifiers":[
        {
            "category":"Organizations",
            "subcategory":"Non-profit Organization",
            "type":"Services"
        }
    ],
    "sg:phone":"+1 317 745 0310",
    "sg:postcode":"46122",
    "sg:province":"IN",
    "sg:tags":[
        "social"
    ],
    "wof:name":"Hendricks County Office",
    "wof:placetype":"venue"
},
  "geometry": {"coordinates":[-86.523393,39.76083],"type":"Point"}
}