{
  "type": "Feature",
  "properties": {
    "addr:full":"4703 Kessler Blvd East Dr Indianapolis IN 46220",
    "addr:housenumber":"4703",
    "addr:postcode":"46220",
    "addr:street":"Kessler Blvd East Dr",
    "iso:country":"US",
    "sg:address":"4703 Kessler Blvd East Dr",
    "sg:city":"Indianapolis",
    "sg:classifiers":[
        {
            "category":"Professional",
            "subcategory":"Employment Agencies",
            "type":"Services"
        }
    ],
    "sg:phone":"+1 317 466 7924",
    "sg:postcode":"46220",
    "sg:province":"IN",
    "wof:name":"Robbie L Flippin",
    "wof:placetype":"venue"
},
  "geometry": {"coordinates":[-86.091759,39.858059],"type":"Point"}
}