{
  "type": "Feature",
  "properties": {
    "iso:country":"US",
    "sg:address":"50 E 91st St Ste 210",
    "sg:city":"Indianapolis",
    "sg:classifiers":[
        {
            "category":"Real Estate",
            "subcategory":"Architect",
            "type":"Services"
        }
    ],
    "sg:phone":"+1 317 575 9755",
    "sg:postcode":"46240",
    "sg:province":"IN",
    "wof:name":"Weaver Gary Inc",
    "wof:placetype":"venue"
},
  "geometry": {"coordinates":[-86.15720399999999,39.919701],"type":"Point"}
}