{
  "type": "Feature",
  "properties": {
    "iso:country":"US",
    "sg:address":"56314 Co Rd 1",
    "sg:city":"Elkhart",
    "sg:classifiers":[
        {
            "category":"Professional",
            "subcategory":"Business Services",
            "type":"Services"
        }
    ],
    "sg:phone":"+1 574 522 3724",
    "sg:postcode":"46516",
    "sg:province":"IN",
    "wof:name":"Bernie Payne Auction Service",
    "wof:placetype":"venue"
},
  "geometry": {"coordinates":[-86.04201500000001,41.676642],"type":"Point"}
}