{
  "type": "Feature",
  "properties": {
    "iso:country":"US",
    "sg:address":"53 W Main St",
    "sg:city":"New Palestine",
    "sg:classifiers":[
        {
            "category":"Insurance",
            "subcategory":"Insurance Agent",
            "type":"Services"
        }
    ],
    "sg:phone":"+1 317 861 6861",
    "sg:postcode":"46163",
    "sg:province":"IN",
    "wof:name":"Smith Insurance",
    "wof:placetype":"venue"
},
  "geometry": {"coordinates":[-85.894898,39.722116],"type":"Point"}
}