{
  "type": "Feature",
  "properties": {
    "iso:country":"US",
    "sg:address":"4410 New Haven Ave",
    "sg:city":"Fort Wayne",
    "sg:classifiers":[
        {
            "category":"Retail",
            "subcategory":"Repair Shop",
            "type":"Services"
        }
    ],
    "sg:phone":"+1 260 424 9200",
    "sg:postcode":"46803",
    "sg:province":"IN",
    "sg:tags":[
        "welding"
    ],
    "wof:name":"Renegade Portable Welding",
    "wof:placetype":"venue"
},
  "geometry": {"coordinates":[-85.080393,41.06883],"type":"Point"}
}