{
  "type": "Feature",
  "properties": {
    "iso:country":"US",
    "sg:address":"6225 Knollton Rd",
    "sg:city":"Indianapolis",
    "sg:classifiers":[
        {
            "category":"Personal",
            "type":"Services"
        }
    ],
    "sg:phone":"+1 317 257 2435",
    "sg:postcode":"46260",
    "sg:province":"IN",
    "sg:tags":[
        "travel",
        "agent",
        "wedding"
    ],
    "wof:name":"Signature Vacations & Travel",
    "wof:placetype":"venue"
},
  "geometry": {"coordinates":[-86.198072,39.868956],"type":"Point"}
}