{
  "type": "Feature",
  "properties": {
    "iso:country":"US",
    "sg:address":"1109 E 234th St",
    "sg:city":"Sheridan",
    "sg:classifiers":[
        {
            "category":"Shopping",
            "subcategory":"Computers & Home Electronics",
            "type":"Retail Goods"
        }
    ],
    "sg:phone":"+1 317 758 5558",
    "sg:postcode":"46069",
    "sg:province":"IN",
    "sg:tags":[
        "radio",
        "television",
        "electronic",
        "store"
    ],
    "wof:name":"Indianapolis Satellite & Elec",
    "wof:placetype":"venue"
},
  "geometry": {"coordinates":[-86.13301,40.127213],"type":"Point"}
}