{
  "type": "Feature",
  "properties": {
    "addr:full":"219 E Perry St Bluffton IN 46714",
    "addr:housenumber":"219",
    "addr:postcode":"46714",
    "addr:street":"E Perry St",
    "iso:country":"US",
    "sg:address":"219 E Perry St",
    "sg:city":"Bluffton",
    "sg:classifiers":[
        {
            "category":"Building & Trades",
            "subcategory":"Plumbing",
            "type":"Services"
        }
    ],
    "sg:phone":"+1 260 824 0228",
    "sg:postcode":"46714",
    "sg:province":"IN",
    "sg:tags":[
        "conditioning",
        "air",
        "system",
        "contractor"
    ],
    "wof:name":"Moser & Son Heating Inc",
    "wof:placetype":"venue"
},
  "geometry": {"coordinates":[-85.16906299999999,40.740377],"type":"Point"}
}