{
  "type": "Feature",
  "properties": {
    "iso:country":"US",
    "sg:address":"8 Motif Blvd",
    "sg:city":"Brownsburg",
    "sg:classifiers":[
        {
            "category":"Health Services",
            "subcategory":"Dentist",
            "type":"Services"
        }
    ],
    "sg:phone":"+1 317 852 4593",
    "sg:postcode":"46112",
    "sg:province":"IN",
    "sg:tags":[
        "product",
        "dentists-cosmetic",
        "denture",
        "dental",
        "teeth",
        "clinic",
        "whitening",
        "dentistry",
        "implant",
        "dentists-prosthodontists",
        "dentists-implantology"
    ],
    "sg:website":"http://www.smilesbytodd.com",
    "wof:name":"Brownsburg Family Dental Care",
    "wof:placetype":"venue"
},
  "geometry": {"coordinates":[-86.39444899999999,39.852356],"type":"Point"}
}