{
  "type": "Feature",
  "properties": {
    "iso:country":"US",
    "sg:address":"312 N 4th St",
    "sg:city":"Lafayette",
    "sg:classifiers":[
        {
            "category":"Shopping",
            "subcategory":"Clothing, Apparel, & Fashions",
            "type":"Retail Goods"
        }
    ],
    "sg:phone":"+1 765 429 6672",
    "sg:postcode":"47901",
    "sg:province":"IN",
    "sg:tags":[
        "sportswear"
    ],
    "wof:name":"Cheer & Gear",
    "wof:placetype":"venue"
},
  "geometry": {"coordinates":[-86.893169,40.420819],"type":"Point"}
}