{
  "type": "Feature",
  "properties": {
    "addr:full":"1100 N Main St Crown Point IN 46307",
    "addr:housenumber":"1100",
    "addr:postcode":"46307",
    "addr:street":"N Main St",
    "iso:country":"US",
    "sg:address":"1100 N Main St",
    "sg:city":"Crown Point",
    "sg:classifiers":[
        {
            "category":"Banks & Credit Unions",
            "subcategory":"Bank",
            "type":"Services"
        }
    ],
    "sg:phone":"+1 219 226 2030",
    "sg:postcode":"46307",
    "sg:province":"IN",
    "wof:name":"Bank Calumet",
    "wof:placetype":"venue"
},
  "geometry": {"coordinates":[-87.364403,41.4314],"type":"Point"}
}