{
  "type": "Feature",
  "properties": {
    "iso:country":"US",
    "sg:address":"4805 N Wheeling Ave",
    "sg:city":"Muncie",
    "sg:classifiers":[
        {
            "category":"Sports & Exercise",
            "subcategory":"Bowling",
            "type":"Entertainment"
        }
    ],
    "sg:phone":"+1 765 286 9965",
    "sg:postcode":"47304",
    "sg:province":"IN",
    "sg:tags":[
        "center"
    ],
    "wof:name":"Cjs Pro Shop Inc",
    "wof:placetype":"venue"
},
  "geometry": {"coordinates":[-85.410778,40.232736],"type":"Point"}
}