{
  "type": "Feature",
  "properties": {
    "addr:full":"588 N Indiana Ave Crown Point IN 46307",
    "addr:housenumber":"588",
    "addr:postcode":"46307",
    "addr:street":"N Indiana Ave",
    "iso:country":"US",
    "sg:address":"588 N Indiana Ave",
    "sg:city":"Crown Point",
    "sg:classifiers":[
        {
            "category":"Retail",
            "subcategory":"Pet Boarding",
            "type":"Services"
        }
    ],
    "sg:phone":"+1 219 662 0333",
    "sg:postcode":"46307",
    "sg:province":"IN",
    "sg:tags":[
        "boarding/pet",
        "sitting"
    ],
    "wof:name":"Linda's Dog & Suds",
    "wof:placetype":"venue"
},
  "geometry": {"coordinates":[-87.35471699999999,41.424585],"type":"Point"}
}