{
  "type": "Feature",
  "properties": {
    "iso:country":"US",
    "sg:address":"6201 Constitution Dr",
    "sg:city":"Fort Wayne",
    "sg:classifiers":[
        {
            "category":"Social Services",
            "type":"Services"
        }
    ],
    "sg:phone":"+1 260 432 0696",
    "sg:postcode":"46804",
    "sg:province":"IN",
    "sg:tags":[
        "employee",
        "assistance",
        "program"
    ],
    "wof:name":"William C Weber & Assoc Inc",
    "wof:placetype":"venue"
},
  "geometry": {"coordinates":[-85.219807,41.067874],"type":"Point"}
}