{
  "type": "Feature",
  "properties": {
    "iso:country":"US",
    "sg:address":"1116 Dekalb St",
    "sg:city":"Hobart",
    "sg:classifiers":[
        {
            "category":"Freight",
            "type":"Transportation"
        }
    ],
    "sg:phone":"+1 219 947 1380",
    "sg:postcode":"46342",
    "sg:province":"IN",
    "sg:tags":[
        "operator",
        "local",
        "trucking"
    ],
    "wof:name":"D & D Trucking Inc",
    "wof:placetype":"venue"
},
  "geometry": {"coordinates":[-87.274493,41.519405],"type":"Point"}
}