{
  "type": "Feature",
  "properties": {
    "addr:full":"5267 Crestview Ave Indianapolis IN 46220",
    "addr:housenumber":"5267",
    "addr:postcode":"46220",
    "addr:street":"Crestview Ave",
    "iso:country":"US",
    "sg:address":"5267 Crestview Ave",
    "sg:city":"Indianapolis",
    "sg:classifiers":[
        {
            "category":"Professional",
            "subcategory":"Computer Services",
            "type":"Services"
        }
    ],
    "sg:phone":"+1 317 253 5567",
    "sg:postcode":"46220",
    "sg:province":"IN",
    "sg:tags":[
        "consulting",
        "database"
    ],
    "wof:name":"Soder Kai",
    "wof:placetype":"venue"
},
  "geometry": {"coordinates":[-86.137229,39.848271],"type":"Point"}
}