{
  "type": "Feature",
  "properties": {
    "iso:country":"US",
    "sg:address":"2323 Columbus Ave",
    "sg:city":"Anderson",
    "sg:classifiers":[
        {
            "category":"Education",
            "subcategory":"School",
            "type":"Public Place"
        }
    ],
    "sg:phone":"+1 765 644 7774",
    "sg:postcode":"46016",
    "sg:province":"IN",
    "sg:website":"www.libertyonline.org",
    "wof:name":"Liberty Christian High School",
    "wof:placetype":"venue"
},
  "geometry": {"coordinates":[-85.66709299999999,40.092642],"type":"Point"}
}