{
  "type": "Feature",
  "properties": {
    "iso:country":"US",
    "sg:address":"5542 Hickorywood Dr",
    "sg:city":"Indianapolis",
    "sg:classifiers":[
        {
            "category":"Wholesale",
            "subcategory":"Metals & Minerals",
            "type":"Manufacturing & Wholesale Goods"
        }
    ],
    "sg:phone":"+1 317 293 0538",
    "sg:postcode":"46224",
    "sg:province":"IN",
    "sg:tags":[
        "center"
    ],
    "wof:name":"Bede Sales Co",
    "wof:placetype":"venue"
},
  "geometry": {"coordinates":[-86.257454,39.806087],"type":"Point"}
}