{
  "type": "Feature",
  "properties": {
    "iso:country":"US",
    "sg:address":"1899 W Eble Rd",
    "sg:city":"Boonville",
    "sg:classifiers":[
        {
            "category":"Building & Trades",
            "subcategory":"Construction",
            "type":"Services"
        }
    ],
    "sg:phone":"+1 812 853 7560",
    "sg:postcode":"47601",
    "sg:province":"IN",
    "sg:tags":[
        "mobile",
        "home"
    ],
    "wof:name":"A J Construction Co",
    "wof:placetype":"venue"
},
  "geometry": {"coordinates":[-87.282665,37.953503],"type":"Point"}
}