{
  "type": "Feature",
  "properties": {
    "iso:country":"US",
    "sg:address":"4850 E 50 N",
    "sg:city":"Columbus",
    "sg:classifiers":[
        {
            "category":"Building & Trades",
            "subcategory":"Electrical",
            "type":"Services"
        }
    ],
    "sg:phone":"+1 812 372 9149",
    "sg:postcode":"47203",
    "sg:province":"IN",
    "sg:tags":[
        "electric",
        "contractor"
    ],
    "wof:name":"Growe Electric",
    "wof:placetype":"venue"
},
  "geometry": {"coordinates":[-85.870017,39.20892],"type":"Point"}
}