{
  "type": "Feature",
  "properties": {
    "addr:full":"515 Countrywood Dr Noblesville IN 46060",
    "addr:housenumber":"515",
    "addr:postcode":"46060",
    "addr:street":"Countrywood Dr",
    "iso:country":"US",
    "sg:address":"515 Countrywood Dr",
    "sg:city":"Noblesville",
    "sg:classifiers":[
        {
            "category":"Building & Trades",
            "subcategory":"Electrical",
            "type":"Services"
        }
    ],
    "sg:phone":"+1 317 773 5980",
    "sg:postcode":"46060",
    "sg:province":"IN",
    "sg:tags":[
        "security",
        "system"
    ],
    "wof:name":"Dynamark Security Center",
    "wof:placetype":"venue"
},
  "geometry": {"coordinates":[-85.95788400000001,40.088859],"type":"Point"}
}