{
  "type": "Feature",
  "properties": {
    "iso:country":"US",
    "sg:address":"1976 Broadway",
    "sg:city":"Gary",
    "sg:classifiers":[
        {
            "category":"Autos & Motor Vehicles",
            "subcategory":"Auto Supplies",
            "type":"Retail Goods"
        }
    ],
    "sg:phone":"+1 219 882 8473",
    "sg:postcode":"46407",
    "sg:province":"IN",
    "sg:tags":[
        "tire"
    ],
    "wof:name":"Tire Farm",
    "wof:placetype":"venue"
},
  "geometry": {"coordinates":[-87.337046,41.583613],"type":"Point"}
}