{
  "type": "Feature",
  "properties": {
    "iso:country":"US",
    "sg:address":"59328 Hollywood Blvd",
    "sg:city":"South Bend",
    "sg:classifiers":[
        {
            "category":"Organizations",
            "subcategory":"Religious Organization",
            "type":"Services"
        }
    ],
    "sg:phone":"+1 574 287 6329",
    "sg:postcode":"46614",
    "sg:province":"IN",
    "wof:name":"May Flower Apollistic Church",
    "wof:placetype":"venue"
},
  "geometry": {"coordinates":[-86.323814,41.628274],"type":"Point"}
}