{
  "type": "Feature",
  "properties": {
    "iso:country":"US",
    "sg:address":"117 Bond St",
    "sg:city":"Notre Dame",
    "sg:classifiers":[
        {
            "category":"Education",
            "subcategory":"Library",
            "type":"Public Place"
        }
    ],
    "sg:phone":"+1 574 631 6654",
    "sg:postcode":"46555",
    "sg:province":"IN",
    "wof:name":"Architecture Library",
    "wof:placetype":"venue"
},
  "geometry": {"coordinates":[-85.716192,41.316048],"type":"Point"}
}