{
  "type": "Feature",
  "properties": {
    "iso:country":"US",
    "sg:address":"2940 Dekalb St",
    "sg:city":"Lake Station",
    "sg:classifiers":[
        {
            "category":"Bars & Pubs",
            "type":"Food & Drink"
        }
    ],
    "sg:phone":"+1 219 962 1096",
    "sg:postcode":"46405",
    "sg:province":"IN",
    "wof:name":"Stetson's Pub",
    "wof:placetype":"venue"
},
  "geometry": {"coordinates":[-87.27484,41.564043],"type":"Point"}
}