{
  "type": "Feature",
  "properties": {
    "iso:country":"US",
    "sg:address":"110 S Meridian St",
    "sg:city":"Portland",
    "sg:classifiers":[
        {
            "category":"Home & Garden",
            "subcategory":"Building Materials",
            "type":"Retail Goods"
        }
    ],
    "sg:phone":"+1 260 726 7350",
    "sg:postcode":"47371",
    "sg:province":"IN",
    "sg:tags":[
        "glass",
        "window",
        "plate"
    ],
    "wof:name":"Glass Bonsai",
    "wof:placetype":"venue"
},
  "geometry": {"coordinates":[-84.977907,40.433255],"type":"Point"}
}