{
  "type": "Feature",
  "properties": {
    "iso:country":"US",
    "sg:address":"8212 N Halyard Way",
    "sg:city":"Indianapolis",
    "sg:classifiers":[
        {
            "category":"Real Estate",
            "subcategory":"Real Estate Agent",
            "type":"Services"
        }
    ],
    "sg:phone":"+1 317 894 6000",
    "sg:postcode":"46236",
    "sg:province":"IN",
    "wof:name":"Re/Max Advantage",
    "wof:placetype":"venue"
},
  "geometry": {"coordinates":[-85.974419,39.906365],"type":"Point"}
}