{
  "type": "Feature",
  "properties": {
    "iso:country":"US",
    "sg:address":"120 N Jefferson St",
    "sg:city":"Hartford City",
    "sg:classifiers":[
        {
            "category":"Government",
            "subcategory":"Office",
            "type":"Public Place"
        }
    ],
    "sg:phone":"+1 765 348 5067",
    "sg:postcode":"47348",
    "sg:province":"IN",
    "sg:tags":[
        "state"
    ],
    "wof:name":"Natural Resources Dept",
    "wof:placetype":"venue"
},
  "geometry": {"coordinates":[-85.367331,40.451955],"type":"Point"}
}