{
  "type": "Feature",
  "properties": {
    "addr:full":"4015 W 625 S Lebanon IN 46052",
    "addr:housenumber":"4015",
    "addr:postcode":"46052",
    "addr:street":"W 625 S",
    "iso:country":"US",
    "sg:address":"4015 W 625 S",
    "sg:city":"Lebanon",
    "sg:classifiers":[
        {
            "category":"Building & Trades",
            "subcategory":"Construction",
            "type":"Services"
        }
    ],
    "sg:phone":"+1 765 482 9546",
    "sg:postcode":"46052",
    "sg:province":"IN",
    "sg:tags":[
        "excavating",
        "contractor"
    ],
    "wof:name":"Hiland Excavating",
    "wof:placetype":"venue"
},
  "geometry": {"coordinates":[-86.54418800000001,39.948139],"type":"Point"}
}