{
  "type": "Feature",
  "properties": {
    "iso:country":"US",
    "sg:address":"1000 N Morton St",
    "sg:city":"Portland",
    "sg:classifiers":[
        {
            "category":"Manufacturing",
            "subcategory":"Tools & Machinery",
            "type":"Manufacturing & Wholesale Goods"
        }
    ],
    "sg:phone":"+1 260 726 9800",
    "sg:postcode":"47371",
    "sg:province":"IN",
    "sg:website":"www.wmmanufacturing.com",
    "wof:name":"W & M Mfg Inc",
    "wof:placetype":"venue"
},
  "geometry": {"coordinates":[-84.968548,40.442979],"type":"Point"}
}