{
  "type": "Feature",
  "properties": {
    "iso:country":"US",
    "sg:address":"2193 W 84th Pl",
    "sg:city":"Merrillville",
    "sg:classifiers":[
        {
            "category":"Building & Trades",
            "subcategory":"Construction",
            "type":"Services"
        }
    ],
    "sg:phone":"+1 219 769 3996",
    "sg:postcode":"46410",
    "sg:province":"IN",
    "sg:tags":[
        "sewer",
        "contractor"
    ],
    "wof:name":"Independence Hill Conservancy",
    "wof:placetype":"venue"
},
  "geometry": {"coordinates":[-87.3636,41.464181],"type":"Point"}
}