{
  "type": "Feature",
  "properties": {
    "iso:country":"US",
    "sg:address":"12177 Sparta Pike",
    "sg:city":"Moores Hill",
    "sg:classifiers":[
        {
            "category":"Organizations",
            "subcategory":"Religious Organization",
            "type":"Services"
        }
    ],
    "sg:phone":"+1 812 744 3434",
    "sg:postcode":"47032",
    "sg:province":"IN",
    "sg:tags":[
        "church"
    ],
    "wof:name":"Sparta Baptist Parsonage",
    "wof:placetype":"venue"
},
  "geometry": {"coordinates":[-85.045346,39.105192],"type":"Point"}
}