{
  "type": "Feature",
  "properties": {
    "iso:country":"US",
    "sg:address":"308 S Seminole Cir",
    "sg:city":"Fort Wayne",
    "sg:classifiers":[
        {
            "category":"Organizations",
            "subcategory":"Non-profit Organization",
            "type":"Services"
        }
    ],
    "sg:phone":"+1 260 745 9621",
    "sg:postcode":"46807",
    "sg:province":"IN",
    "sg:tags":[
        "fund",
        "counselor",
        "raising"
    ],
    "sg:website":"www.keyfour.com",
    "wof:name":"Key Four Inc",
    "wof:placetype":"venue"
},
  "geometry": {"coordinates":[-85.13946799999999,41.044331],"type":"Point"}
}