{
  "type": "Feature",
  "properties": {
    "iso:country":"US",
    "sg:address":"3531 W 46th St",
    "sg:city":"Indianapolis",
    "sg:classifiers":[
        {
            "category":"Real Estate",
            "subcategory":"Real Estate Agent",
            "type":"Services"
        }
    ],
    "sg:phone":"+1 317 291 7088",
    "sg:postcode":"46228",
    "sg:province":"IN",
    "wof:name":"Chuck Dugger Realty Co",
    "wof:placetype":"venue"
},
  "geometry": {"coordinates":[-86.220209,39.838907],"type":"Point"}
}