{
  "type": "Feature",
  "properties": {
    "iso:country":"US",
    "sg:address":"8251 Wicker Ave",
    "sg:city":"St John",
    "sg:classifiers":[
        {
            "category":"Banks & Credit Unions",
            "subcategory":"Bank",
            "type":"Services"
        }
    ],
    "sg:phone":"+1 219 365 1458",
    "sg:postcode":"46373",
    "sg:province":"IN",
    "sg:tags":[
        "financing"
    ],
    "wof:name":"American General Finance Inc",
    "wof:placetype":"venue"
},
  "geometry": {"coordinates":[-87.470315,41.467797],"type":"Point"}
}