{
  "type": "Feature",
  "properties": {
    "addr:full":"1571 N State St Greenfield IN 46140",
    "addr:housenumber":"1571",
    "addr:postcode":"46140",
    "addr:street":"N State St",
    "iso:country":"US",
    "sg:address":"1571 N State St",
    "sg:city":"Greenfield",
    "sg:classifiers":[
        {
            "category":"Shopping",
            "subcategory":"Computers & Home Electronics",
            "type":"Retail Goods"
        }
    ],
    "sg:phone":"+1 317 462 3575",
    "sg:postcode":"46140",
    "sg:province":"IN",
    "sg:tags":[
        "equipment",
        "electronic",
        "supply"
    ],
    "wof:name":"Radio Shack",
    "wof:placetype":"venue"
},
  "geometry": {"coordinates":[-85.769577,39.805118],"type":"Point"}
}