{
  "type": "Feature",
  "properties": {
    "addr:full":"597 Industrial Dr Carmel IN 46032",
    "addr:housenumber":"597",
    "addr:postcode":"46032",
    "addr:street":"Industrial Dr",
    "iso:country":"US",
    "sg:address":"597 Industrial Dr",
    "sg:city":"Carmel",
    "sg:classifiers":[
        {
            "category":"Banks & Credit Unions",
            "subcategory":"Investment Brokerage",
            "type":"Services"
        }
    ],
    "sg:phone":"+1 317 569 9711",
    "sg:postcode":"46032",
    "sg:province":"IN",
    "sg:tags":[
        "commodity"
    ],
    "wof:name":"North Star Asset Management",
    "wof:placetype":"venue"
},
  "geometry": {"coordinates":[-86.132104,39.974676],"type":"Point"}
}