{
  "type": "Feature",
  "properties": {
    "addr:full":"20151 Patterson St Lakeville IN 46536",
    "addr:housenumber":"20151",
    "addr:postcode":"46536",
    "addr:street":"Patterson St",
    "iso:country":"US",
    "sg:address":"20151 Patterson St",
    "sg:city":"Lakeville",
    "sg:phone":"+1 574 784 8941",
    "sg:postcode":"46536",
    "sg:province":"IN",
    "sg:tags":[
        "farm",
        "corn",
        "soybean"
    ],
    "wof:name":"Lanny Fuchs",
    "wof:placetype":"venue"
},
  "geometry": {"coordinates":[-86.265314,41.524599],"type":"Point"}
}