{
  "type": "Feature",
  "properties": {
    "iso:country":"US",
    "sg:address":"210 E Centennial Ave",
    "sg:city":"Muncie",
    "sg:classifiers":[
        {
            "category":"Wholesale",
            "subcategory":"Durable Goods & Equipment",
            "type":"Manufacturing & Wholesale Goods"
        }
    ],
    "sg:phone":"+1 765 288 5522",
    "sg:postcode":"47303",
    "sg:province":"IN",
    "sg:tags":[
        "representative",
        "manufacturer"
    ],
    "wof:name":"Mark I Industries Inc",
    "wof:placetype":"venue"
},
  "geometry": {"coordinates":[-85.385559,40.20885],"type":"Point"}
}