{
  "type": "Feature",
  "properties": {
    "iso:country":"US",
    "sg:address":"1123 S Bend Ave",
    "sg:city":"South Bend",
    "sg:classifiers":[
        {
            "category":"Education",
            "subcategory":"Special Training",
            "type":"Public Place"
        }
    ],
    "sg:phone":"+1 574 288 5749",
    "sg:postcode":"46617",
    "sg:province":"IN",
    "sg:tags":[
        "instruction",
        "music"
    ],
    "wof:name":"Nicksmusic",
    "wof:placetype":"venue"
},
  "geometry": {"coordinates":[-86.235203,41.687529],"type":"Point"}
}