{
  "type": "Feature",
  "properties": {
    "iso:country":"US",
    "sg:address":"2763 N 500 W",
    "sg:city":"Rochester",
    "sg:classifiers":[
        {
            "category":"Manufacturing",
            "subcategory":"Printing",
            "type":"Manufacturing & Wholesale Goods"
        }
    ],
    "sg:phone":"+1 574 223 7577",
    "sg:postcode":"46975",
    "sg:province":"IN",
    "sg:tags":[
        "periodical"
    ],
    "wof:name":"Maximum X Press",
    "wof:placetype":"venue"
},
  "geometry": {"coordinates":[-86.337807,41.099183],"type":"Point"}
}