{
  "type": "Feature",
  "properties": {
    "iso:country":"US",
    "sg:address":"15227 Herriman Blvd",
    "sg:city":"Noblesville",
    "sg:classifiers":[
        {
            "category":"Building & Trades",
            "subcategory":"Pest Control",
            "type":"Services"
        }
    ],
    "sg:phone":"+1 317 574 1936",
    "sg:postcode":"46060",
    "sg:province":"IN",
    "wof:name":"Baxter Pest Doctors",
    "wof:placetype":"venue"
},
  "geometry": {"coordinates":[-86.004885,40.012968],"type":"Point"}
}