{
  "type": "Feature",
  "properties": {
    "iso:country":"US",
    "sg:address":"4583 N State Rd 29",
    "sg:city":"Camden",
    "sg:classifiers":[
        {
            "category":"Food & Beverages",
            "subcategory":"Groceries & Convenience Stores",
            "type":"Retail Goods"
        }
    ],
    "sg:phone":"+1 574 859 3500",
    "sg:postcode":"46917",
    "sg:province":"IN",
    "wof:name":"Betty's Stop & Shop",
    "wof:placetype":"venue"
},
  "geometry": {"coordinates":[-86.391156,40.612342],"type":"Point"}
}