{
  "type": "Feature",
  "properties": {
    "iso:country":"US",
    "sg:address":"2121 Sagamore Pkwy S",
    "sg:city":"Lafayette",
    "sg:classifiers":[
        {
            "category":"Building & Trades",
            "subcategory":"Electrical",
            "type":"Services"
        }
    ],
    "sg:phone":"+1 765 446 8102",
    "sg:postcode":"47905",
    "sg:province":"IN",
    "sg:tags":[
        "installation"
    ],
    "wof:name":"Car Stereo Installations",
    "wof:placetype":"venue"
},
  "geometry": {"coordinates":[-86.856761,40.397224],"type":"Point"}
}