{
  "type": "Feature",
  "properties": {
    "iso:country":"US",
    "sg:address":"6246 E State Rd 45",
    "sg:city":"Bloomington",
    "sg:classifiers":[
        {
            "category":"Building & Trades",
            "subcategory":"Construction",
            "type":"Services"
        }
    ],
    "sg:phone":"+1 812 336 3608",
    "sg:postcode":"47408",
    "sg:province":"IN",
    "sg:tags":[
        "general",
        "contractor"
    ],
    "sg:website":"www.strausercci.com",
    "wof:name":"Strauser Construction",
    "wof:placetype":"venue"
},
  "geometry": {"coordinates":[-86.456147,39.214539],"type":"Point"}
}