{
  "type": "Feature",
  "properties": {
    "iso:country":"US",
    "sg:address":"258 E Market St",
    "sg:city":"Nappanee",
    "sg:classifiers":[
        {
            "category":"Government",
            "subcategory":"Office",
            "type":"Public Place"
        }
    ],
    "sg:phone":"+1 574 773 2424",
    "sg:postcode":"46550",
    "sg:province":"IN",
    "sg:tags":[
        "village"
    ],
    "wof:name":"Elder-Haus",
    "wof:placetype":"venue"
},
  "geometry": {"coordinates":[-85.999272,41.442716],"type":"Point"}
}