{
  "type": "Feature",
  "properties": {
    "iso:country":"US",
    "sg:address":"117 E Washington St",
    "sg:city":"Indianapolis",
    "sg:classifiers":[
        {
            "category":"Real Estate",
            "subcategory":"Real Estate Agent",
            "type":"Services"
        }
    ],
    "sg:phone":"+1 317 633 5555",
    "sg:postcode":"46204",
    "sg:province":"IN",
    "wof:name":"Freihofer Inc",
    "wof:placetype":"venue"
},
  "geometry": {"coordinates":[-86.155321,39.767021],"type":"Point"}
}