{
  "type": "Feature",
  "properties": {
    "iso:country":"US",
    "sg:address":"655 Perry Rd",
    "sg:city":"Plainfield",
    "sg:classifiers":[
        {
            "category":"Shopping",
            "subcategory":"Bicycles & Sporting Goods",
            "type":"Retail Goods"
        }
    ],
    "sg:phone":"+1 317 837 0200",
    "sg:postcode":"46168",
    "sg:province":"IN",
    "wof:name":"Dick's Sporting Goods Inc",
    "wof:placetype":"venue"
},
  "geometry": {"coordinates":[-86.355629,39.697045],"type":"Point"}
}