{
  "type": "Feature",
  "properties": {
    "iso:country":"US",
    "sg:address":"7945 W 900 N",
    "sg:city":"Huntington",
    "sg:classifiers":[
        {
            "category":"Retail",
            "subcategory":"Auto Repair",
            "type":"Services"
        }
    ],
    "sg:phone":"+1 260 344 3700",
    "sg:postcode":"46750",
    "sg:province":"IN",
    "sg:tags":[
        "wrecker"
    ],
    "wof:name":"Don Henline Towing",
    "wof:placetype":"venue"
},
  "geometry": {"coordinates":[-85.603421,40.959005],"type":"Point"}
}