{
  "type": "Feature",
  "properties": {
    "iso:country":"US",
    "sg:address":"281 E Main St",
    "sg:city":"Hanover",
    "sg:classifiers":[
        {
            "category":"Food & Beverages",
            "subcategory":"Groceries & Convenience Stores",
            "type":"Retail Goods"
        }
    ],
    "sg:phone":"+1 812 866 3287",
    "sg:postcode":"47243",
    "sg:province":"IN",
    "sg:tags":[
        "grocer"
    ],
    "wof:name":"Johnson Home Market",
    "wof:placetype":"venue"
},
  "geometry": {"coordinates":[-85.468175,38.713758],"type":"Point"}
}