{
  "type": "Feature",
  "properties": {
    "iso:country":"US",
    "sg:address":"227 W Jefferson Blvd",
    "sg:city":"South Bend",
    "sg:classifiers":[
        {
            "category":"Government",
            "subcategory":"Office",
            "type":"Public Place"
        }
    ],
    "sg:phone":"+1 574 674 8894",
    "sg:postcode":"46601",
    "sg:province":"IN",
    "sg:tags":[
        "village"
    ],
    "sg:website":"www.macog.com",
    "wof:name":"Michiana Area Council Of Govt",
    "wof:placetype":"venue"
},
  "geometry": {"coordinates":[-86.252444,41.675084],"type":"Point"}
}