{
  "type": "Feature",
  "properties": {
    "iso:country":"US",
    "sg:address":"1098 W 500 N",
    "sg:city":"Decatur",
    "sg:classifiers":[
        {
            "category":"Restaurant",
            "type":"Food & Drink"
        }
    ],
    "sg:phone":"+1 260 724 6062",
    "sg:postcode":"46733",
    "sg:province":"IN",
    "sg:tags":[
        "banquet",
        "rooms"
    ],
    "sg:website":"www.greygoosegolfclub.com",
    "wof:name":"Grey Goose Reception Hall",
    "wof:placetype":"venue"
},
  "geometry": {"coordinates":[-84.957616,40.817239],"type":"Point"}
}