{
  "type": "Feature",
  "properties": {
    "iso:country":"US",
    "sg:address":"406 Washington St",
    "sg:city":"Clay City",
    "sg:classifiers":[
        {
            "category":"Personal",
            "subcategory":"Beauty Salon",
            "type":"Services"
        }
    ],
    "sg:phone":"+1 812 939 2517",
    "sg:postcode":"47841",
    "sg:province":"IN",
    "sg:tags":[
        "shop"
    ],
    "wof:name":"Andis Beauty Shop",
    "wof:placetype":"venue"
},
  "geometry": {"coordinates":[-87.111495,39.280624],"type":"Point"}
}