{
  "type": "Feature",
  "properties": {
    "iso:country":"US",
    "sg:address":"4138 Niewoehner Rd",
    "sg:city":"Richmond",
    "sg:classifiers":[
        {
            "category":"Education",
            "subcategory":"School",
            "type":"Public Place"
        }
    ],
    "sg:phone":"+1 765 973 3431",
    "sg:postcode":"47374",
    "sg:province":"IN",
    "wof:name":"Paul C Garrison Elem School",
    "wof:placetype":"venue"
},
  "geometry": {"coordinates":[-84.852255,39.771218],"type":"Point"}
}