{
  "type": "Feature",
  "properties": {
    "iso:country":"US",
    "sg:address":"1600 W Bloomfield Rd",
    "sg:city":"Bloomington",
    "sg:classifiers":[
        {
            "category":"Professional",
            "subcategory":"Accounting & Tax Preparation",
            "type":"Services"
        }
    ],
    "sg:phone":"+1 812 336 8550",
    "sg:postcode":"47403",
    "sg:province":"IN",
    "sg:tags":[
        "accountant"
    ],
    "sg:website":"www.bkd.com",
    "wof:name":"Bkd LLP",
    "wof:placetype":"venue"
},
  "geometry": {"coordinates":[-86.561408,39.156133],"type":"Point"}
}