{
  "type": "Feature",
  "properties": {
    "iso:country":"US",
    "sg:address":"9427 E Washington St",
    "sg:city":"Indianapolis",
    "sg:classifiers":[
        {
            "category":"Travel",
            "subcategory":"Travel Agent",
            "type":"Entertainment"
        }
    ],
    "sg:phone":"+1 317 899 4477",
    "sg:postcode":"46229",
    "sg:province":"IN",
    "sg:tags":[
        "agency",
        "bureau"
    ],
    "wof:name":"Carefree Travel Agency",
    "wof:placetype":"venue"
},
  "geometry": {"coordinates":[-85.998938,39.774377],"type":"Point"}
}