{
  "type": "Feature",
  "properties": {
    "iso:country":"US",
    "sg:address":"422 S 5th St",
    "sg:city":"Logansport",
    "sg:classifiers":[
        {
            "category":"Retail",
            "subcategory":"Repair Shop",
            "type":"Services"
        }
    ],
    "sg:phone":"+1 574 753 0495",
    "sg:postcode":"46947",
    "sg:province":"IN",
    "sg:tags":[
        "welding"
    ],
    "wof:name":"Taurus Welding",
    "wof:placetype":"venue"
},
  "geometry": {"coordinates":[-86.363862,40.752413],"type":"Point"}
}