{
  "type": "Feature",
  "properties": {
    "addr:full":"15034 State Rd 17 Culver IN 46511",
    "addr:housenumber":"15034;17;in",
    "addr:postcode":"46511",
    "addr:street":"State Rd",
    "iso:country":"US",
    "sg:address":"15034 State Rd 17",
    "sg:city":"Culver",
    "sg:phone":"+1 574 842 2073",
    "sg:postcode":"46511",
    "sg:province":"IN",
    "sg:tags":[
        "farm",
        "grain",
        "cash"
    ],
    "wof:name":"Glenn Overmeyer",
    "wof:placetype":"venue"
},
  "geometry": {"coordinates":[-86.41487600000001,41.258608],"type":"Point"}
}