{
  "type": "Feature",
  "properties": {
    "iso:country":"US",
    "sg:address":"860 N Green St",
    "sg:city":"Brownsburg",
    "sg:classifiers":[
        {
            "category":"Home & Garden",
            "subcategory":"Furniture",
            "type":"Retail Goods"
        }
    ],
    "sg:phone":"+1 317 852 5180",
    "sg:postcode":"46112",
    "sg:province":"IN",
    "wof:name":"Wicker Works",
    "wof:placetype":"venue"
},
  "geometry": {"coordinates":[-86.39482,39.852163],"type":"Point"}
}