{
  "type": "Feature",
  "properties": {
    "iso:country":"US",
    "sg:address":"806 Jackson St",
    "sg:city":"Columbus",
    "sg:classifiers":[
        {
            "category":"Health Services",
            "subcategory":"Health Practitioner",
            "type":"Services"
        }
    ],
    "sg:phone":"+1 812 379 4033",
    "sg:postcode":"47201",
    "sg:province":"IN",
    "sg:tags":[
        "psychologist"
    ],
    "wof:name":"Personal Growth Assoc",
    "wof:placetype":"venue"
},
  "geometry": {"coordinates":[-85.922703,39.207333],"type":"Point"}
}