{
  "type": "Feature",
  "properties": {
    "iso:country":"US",
    "sg:address":"108 N Main St",
    "sg:city":"Crown Point",
    "sg:classifiers":[
        {
            "category":"Shopping",
            "subcategory":"Shoes",
            "type":"Retail Goods"
        }
    ],
    "sg:phone":"+1 219 663 0463",
    "sg:postcode":"46307",
    "sg:province":"IN",
    "sg:tags":[
        "store"
    ],
    "wof:name":"Barney's Shoes & Boots",
    "wof:placetype":"venue"
},
  "geometry": {"coordinates":[-87.364197,41.417999],"type":"Point"}
}