{
  "type": "Feature",
  "properties": {
    "iso:country":"US",
    "sg:address":"4001 Prospect St",
    "sg:city":"Indianapolis",
    "sg:classifiers":[
        {
            "category":"Shopping",
            "subcategory":"Stationery & Office Supplies",
            "type":"Retail Goods"
        }
    ],
    "sg:phone":"+1 317 357 3707",
    "sg:postcode":"46203",
    "sg:province":"IN",
    "sg:tags":[
        "packing",
        "room",
        "shipping",
        "materials-shipping"
    ],
    "sg:website":"http://www.starpackaging.net",
    "wof:name":"Star Packaging Company Inc",
    "wof:placetype":"venue"
},
  "geometry": {"coordinates":[-86.063031,39.753021],"type":"Point"}
}