{
  "type": "Feature",
  "properties": {
    "iso:country":"US",
    "sg:address":"6350 E 100 N",
    "sg:city":"Lagrange",
    "sg:classifiers":[
        {
            "category":"Building & Trades",
            "subcategory":"Construction",
            "type":"Services"
        }
    ],
    "sg:phone":"+1 260 463 7514",
    "sg:postcode":"46761",
    "sg:province":"IN",
    "sg:tags":[
        "water",
        "well",
        "drilling"
    ],
    "wof:name":"Sanderson Well Drilling",
    "wof:placetype":"venue"
},
  "geometry": {"coordinates":[-85.305043,41.65631],"type":"Point"}
}