{
  "type": "Feature",
  "properties": {
    "iso:country":"US",
    "sg:address":"4229 Franklin St",
    "sg:city":"Michigan City",
    "sg:classifiers":[
        {
            "category":"Banks & Credit Unions",
            "subcategory":"Bank",
            "type":"Services"
        }
    ],
    "sg:phone":"+1 219 872 5577",
    "sg:postcode":"46360",
    "sg:province":"IN",
    "sg:tags":[
        "financing"
    ],
    "wof:name":"American General Finance Inc",
    "wof:placetype":"venue"
},
  "geometry": {"coordinates":[-86.894031,41.678798],"type":"Point"}
}