{
  "type": "Feature",
  "properties": {
    "addr:full":"4999 Elm Swamp Rd Lebanon IN 46052",
    "addr:housenumber":"4999",
    "addr:postcode":"46052",
    "addr:street":"Elm Swamp Rd",
    "iso:country":"US",
    "sg:address":"4999 Elm Swamp Rd",
    "sg:city":"Lebanon",
    "sg:classifiers":[
        {
            "category":"Sports & Exercise",
            "subcategory":"Golf",
            "type":"Entertainment"
        }
    ],
    "sg:phone":"+1 765 482 4906",
    "sg:postcode":"46052",
    "sg:province":"IN",
    "sg:tags":[
        "course"
    ],
    "wof:name":"Fair-Way Golf Course",
    "wof:placetype":"venue"
},
  "geometry": {"coordinates":[-86.45501,40.10467],"type":"Point"}
}