{
  "type": "Feature",
  "properties": {
    "iso:country":"US",
    "sg:address":"8745 N 200 W",
    "sg:city":"North Manchester",
    "sg:classifiers":[
        {
            "category":"Professional",
            "type":"Services"
        }
    ],
    "sg:phone":"+1 260 982 1611",
    "sg:postcode":"46962",
    "sg:province":"IN",
    "sg:tags":[
        "establishment"
    ],
    "wof:name":"Strauss Family Partnership",
    "wof:placetype":"venue"
},
  "geometry": {"coordinates":[-85.832448,40.95333],"type":"Point"}
}