{
  "type": "Feature",
  "properties": {
    "addr:full":"5551 S Belmont Ave Indianapolis IN 46217",
    "addr:housenumber":"5551",
    "addr:postcode":"46217",
    "addr:street":"S Belmont Ave",
    "iso:country":"US",
    "sg:address":"5551 S Belmont Ave",
    "sg:city":"Indianapolis",
    "sg:classifiers":[
        {
            "category":"Building & Trades",
            "subcategory":"Construction",
            "type":"Services"
        }
    ],
    "sg:phone":"+1 317 781 6844",
    "sg:postcode":"46217",
    "sg:province":"IN",
    "sg:tags":[
        "handyman"
    ],
    "wof:name":"Honey Do Handyman Inc",
    "wof:placetype":"venue"
},
  "geometry": {"coordinates":[-86.196489,39.678961],"type":"Point"}
}