{
  "type": "Feature",
  "properties": {
    "addr:full":"412 Blue River Ct Columbia City IN 46725",
    "addr:housenumber":"412",
    "addr:postcode":"46725",
    "addr:street":"Blue River Ct",
    "iso:country":"US",
    "sg:address":"412 Blue River Ct",
    "sg:city":"Columbia City",
    "sg:classifiers":[
        {
            "category":"Home & Garden",
            "subcategory":"Carpets & Floor Coverings",
            "type":"Retail Goods"
        }
    ],
    "sg:phone":"+1 260 244 6992",
    "sg:postcode":"46725",
    "sg:province":"IN",
    "wof:name":"Columbia City Rock Carpet Inc",
    "wof:placetype":"venue"
},
  "geometry": {"coordinates":[-85.480388,41.167554],"type":"Point"}
}