{
  "type": "Feature",
  "properties": {
    "iso:country":"US",
    "sg:address":"2221 W Franklin St",
    "sg:city":"Evansville",
    "sg:classifiers":[
        {
            "category":"Professional",
            "subcategory":"Lawyer & Legal Services",
            "type":"Services"
        }
    ],
    "sg:phone":"+1 812 424 2991",
    "sg:postcode":"47712",
    "sg:province":"IN",
    "sg:tags":[
        "attorney"
    ],
    "wof:name":"Douglas Patterson Law Office",
    "wof:placetype":"venue"
},
  "geometry": {"coordinates":[-87.598635,37.980678],"type":"Point"}
}