{
  "type": "Feature",
  "properties": {
    "iso:country":"US",
    "sg:address":"7072 Warrickton Rd",
    "sg:city":"Chandler",
    "sg:classifiers":[
        {
            "category":"Building & Trades",
            "subcategory":"Electrical",
            "type":"Services"
        }
    ],
    "sg:phone":"+1 812 477 3222",
    "sg:postcode":"47610",
    "sg:province":"IN",
    "sg:tags":[
        "electric",
        "contractor"
    ],
    "wof:name":"Taylor Electric Htg & Cooling",
    "wof:placetype":"venue"
},
  "geometry": {"coordinates":[-87.38420600000001,38.067029],"type":"Point"}
}