{
  "type": "Feature",
  "properties": {
    "iso:country":"US",
    "sg:address":"2110 McCormick Pl",
    "sg:city":"West Lafayette",
    "sg:classifiers":[
        {
            "category":"Building & Trades",
            "subcategory":"Construction",
            "type":"Services"
        }
    ],
    "sg:phone":"+1 765 497 2947",
    "sg:postcode":"47906",
    "sg:province":"IN",
    "sg:tags":[
        "general",
        "contractor"
    ],
    "wof:name":"Highline Construction",
    "wof:placetype":"venue"
},
  "geometry": {"coordinates":[-86.943274,40.450557],"type":"Point"}
}