{
  "type": "Feature",
  "properties": {
    "iso:country":"US",
    "sg:address":"4714 Coldwater Rd",
    "sg:city":"Fort Wayne",
    "sg:classifiers":[
        {
            "category":"Shopping",
            "type":"Retail Goods"
        }
    ],
    "sg:phone":"+1 260 483 2930",
    "sg:postcode":"46825",
    "sg:province":"IN",
    "sg:tags":[
        "pet",
        "food",
        "supply"
    ],
    "wof:name":"Pet Supplies Plus",
    "wof:placetype":"venue"
},
  "geometry": {"coordinates":[-85.135398,41.122621],"type":"Point"}
}