{
  "type": "Feature",
  "properties": {
    "iso:country":"US",
    "sg:address":"6537 Taney Ct",
    "sg:city":"Merrillville",
    "sg:classifiers":[
        {
            "category":"Wholesale",
            "subcategory":"Electrical",
            "type":"Manufacturing & Wholesale Goods"
        }
    ],
    "sg:phone":"+1 219 938 5055",
    "sg:postcode":"46410",
    "sg:province":"IN",
    "sg:tags":[
        "coil"
    ],
    "wof:name":"Advanced Security Systems",
    "wof:placetype":"venue"
},
  "geometry": {"coordinates":[-87.371858,41.499598],"type":"Point"}
}