{
  "type": "Feature",
  "properties": {
    "iso:country":"US",
    "sg:address":"405 S Mount Zion Rd",
    "sg:city":"Lebanon",
    "sg:classifiers":[
        {
            "category":"Travel",
            "subcategory":"Hotels & Motels",
            "type":"Entertainment"
        }
    ],
    "sg:phone":"+1 765 482 9999",
    "sg:postcode":"46052",
    "sg:province":"IN",
    "wof:name":"Super 8 Motel",
    "wof:placetype":"venue"
},
  "geometry": {"coordinates":[-86.512254,40.024352],"type":"Point"}
}