{
  "type": "Feature",
  "properties": {
    "iso:country":"US",
    "sg:address":"14951 W Co Rd 700 S",
    "sg:city":"Daleville",
    "sg:classifiers":[
        {
            "category":"Real Estate",
            "subcategory":"Real Estate Operator",
            "type":"Services"
        }
    ],
    "sg:phone":"+1 765 378 7867",
    "sg:postcode":"47334",
    "sg:province":"IN",
    "sg:tags":[
        "property",
        "lessor"
    ],
    "wof:name":"Harry Wright",
    "wof:placetype":"venue"
},
  "geometry": {"coordinates":[-85.556252,40.091422],"type":"Point"}
}