{
  "type": "Feature",
  "properties": {
    "iso:country":"US",
    "sg:address":"6939 S Co Rd 650 W",
    "sg:city":"Reelsville",
    "sg:classifiers":[
        {
            "category":"Home & Garden",
            "subcategory":"Carpets & Floor Coverings",
            "type":"Retail Goods"
        }
    ],
    "sg:phone":"+1 765 672 8499",
    "sg:postcode":"46171",
    "sg:province":"IN",
    "sg:tags":[
        "dealer",
        "rug"
    ],
    "sg:website":"www.carpetsculptors.com",
    "wof:name":"Carpet Sculptors",
    "wof:placetype":"venue"
},
  "geometry": {"coordinates":[-86.96691800000001,39.563876],"type":"Point"}
}