{
  "type": "Feature",
  "properties": {
    "addr:full":"4310 Old Vincennes Rd Floyds Knobs IN 47119",
    "addr:housenumber":"4310",
    "addr:postcode":"in 47119",
    "addr:street":"Old Vincennes Rd",
    "iso:country":"US",
    "sg:address":"4310 Old Vincennes Rd",
    "sg:city":"Floyds Knobs",
    "sg:classifiers":[
        {
            "category":"Building & Trades",
            "subcategory":"Construction",
            "type":"Services"
        }
    ],
    "sg:phone":"+1 812 945 3775",
    "sg:postcode":"47119",
    "sg:province":"IN",
    "sg:tags":[
        "house"
    ],
    "wof:name":"Arthur Sonny Home Builder",
    "wof:placetype":"venue"
},
  "geometry": {"coordinates":[-85.887642,38.307167],"type":"Point"}
}