{
  "type": "Feature",
  "properties": {
    "iso:country":"US",
    "sg:address":"39 W Washington St",
    "sg:city":"Shelbyville",
    "sg:classifiers":[
        {
            "category":"Personal",
            "subcategory":"Beauty Salon",
            "type":"Services"
        }
    ],
    "sg:phone":"+1 317 392 7956",
    "sg:postcode":"46176",
    "sg:province":"IN",
    "wof:name":"Elite Expressions",
    "wof:placetype":"venue"
},
  "geometry": {"coordinates":[-85.779133,39.524368],"type":"Point"}
}