{
  "type": "Feature",
  "properties": {
    "iso:country":"US",
    "sg:address":"260 165th St",
    "sg:city":"Hammond",
    "sg:classifiers":[
        {
            "category":"Autos & Motor Vehicles",
            "subcategory":"Fuel & Gas Station",
            "type":"Retail Goods"
        }
    ],
    "sg:phone":"+1 219 933 1488",
    "sg:postcode":"46324",
    "sg:province":"IN",
    "sg:tags":[
        "oil"
    ],
    "wof:name":"Ridgeway III",
    "wof:placetype":"venue"
},
  "geometry": {"coordinates":[-87.519096,41.595402],"type":"Point"}
}