{
  "type": "Feature",
  "properties": {
    "iso:country":"US",
    "sg:address":"1927 E 62nd St",
    "sg:city":"Indianapolis",
    "sg:classifiers":[
        {
            "category":"Health Services",
            "subcategory":"Doctor",
            "type":"Services"
        }
    ],
    "sg:phone":"+1 317 257 9103",
    "sg:postcode":"46220",
    "sg:province":"IN",
    "sg:tags":[
        "dentist"
    ],
    "wof:name":"Martin & Martin",
    "wof:placetype":"venue"
},
  "geometry": {"coordinates":[-86.127253,39.868581],"type":"Point"}
}