{
  "type": "Feature",
  "properties": {
    "iso:country":"US",
    "sg:address":"8935 N Meridian St # 200",
    "sg:city":"Indianapolis",
    "sg:classifiers":[
        {
            "category":"Health Services",
            "subcategory":"Doctor",
            "type":"Services"
        }
    ],
    "sg:phone":"+1 317 575 2955",
    "sg:postcode":"46260",
    "sg:province":"IN",
    "sg:tags":[
        "physician",
        "surgeon",
        "kidneys",
        "surgeons",
        "nephrology"
    ],
    "wof:name":"Indiana Nephrology & Internal",
    "wof:placetype":"venue"
},
  "geometry": {"coordinates":[-86.157562,39.916938],"type":"Point"}
}