{
  "type": "Feature",
  "properties": {
    "iso:country":"US",
    "sg:address":"264 E Fleming Ave",
    "sg:city":"Fort Wayne",
    "sg:classifiers":[
        {
            "category":"Sports & Exercise",
            "subcategory":"Bowling",
            "type":"Entertainment"
        }
    ],
    "sg:phone":"+1 260 744 0842",
    "sg:postcode":"46806",
    "sg:province":"IN",
    "sg:tags":[
        "center"
    ],
    "wof:name":"In My Spare Time",
    "wof:placetype":"venue"
},
  "geometry": {"coordinates":[-85.13211099999999,41.041042],"type":"Point"}
}