{
  "type": "Feature",
  "properties": {
    "iso:country":"US",
    "sg:address":"9235 New Harmony Rd",
    "sg:city":"Martinsville",
    "sg:classifiers":[
        {
            "category":"Building & Trades",
            "subcategory":"Construction",
            "type":"Services"
        }
    ],
    "sg:phone":"+1 765 342 3991",
    "sg:postcode":"46151",
    "sg:province":"IN",
    "sg:tags":[
        "concrete",
        "contractor"
    ],
    "wof:name":"Behling Concrete",
    "wof:placetype":"venue"
},
  "geometry": {"coordinates":[-86.262075,39.507663],"type":"Point"}
}