{
  "type": "Feature",
  "properties": {
    "iso:country":"US",
    "sg:address":"202 W Market St",
    "sg:city":"Bluffton",
    "sg:classifiers":[
        {
            "category":"Shopping",
            "subcategory":"Hobbies, Toys, & Games",
            "type":"Retail Goods"
        }
    ],
    "sg:phone":"+1 260 824 5766",
    "sg:postcode":"46714",
    "sg:province":"IN",
    "wof:name":"Joyce",
    "wof:placetype":"venue"
},
  "geometry": {"coordinates":[-85.173996,40.739721],"type":"Point"}
}