{
  "type": "Feature",
  "properties": {
    "addr:full":"1634 E 80th Ave Merrillville IN 46410",
    "addr:housenumber":"1634",
    "addr:postcode":"46410",
    "addr:street":"E 80Th Ave",
    "iso:country":"US",
    "sg:address":"1634 E 80th Ave",
    "sg:city":"Merrillville",
    "sg:classifiers":[
        {
            "category":"Restaurant",
            "type":"Food & Drink"
        }
    ],
    "sg:menulink":"http://www.allmenus.com/in/ross/104363-old-country-buffet/menu/",
    "sg:phone":"+1 219 769 0968",
    "sg:postcode":"46410",
    "sg:province":"IN",
    "sg:tags":[
        "american"
    ],
    "wof:name":"Old Country Buffet",
    "wof:placetype":"venue"
},
  "geometry": {"coordinates":[-87.31591299999999,41.473621],"type":"Point"}
}