{
  "type": "Feature",
  "properties": {
    "iso:country":"US",
    "sg:address":"2581 Viehe Dr",
    "sg:city":"Evansville",
    "sg:classifiers":[
        {
            "category":"Wholesale",
            "subcategory":"Meat",
            "type":"Manufacturing & Wholesale Goods"
        }
    ],
    "sg:phone":"+1 812 867 6519",
    "sg:postcode":"47725",
    "sg:province":"IN",
    "wof:name":"Troyer Poultry Inc",
    "wof:placetype":"venue"
},
  "geometry": {"coordinates":[-87.52173500000001,38.070374],"type":"Point"}
}