{
  "type": "Feature",
  "properties": {
    "iso:country":"US",
    "sg:address":"1101 Wohlert St",
    "sg:city":"Angola",
    "sg:classifiers":[
        {
            "category":"Manufacturing",
            "subcategory":"Glass & Minerals",
            "type":"Manufacturing & Wholesale Goods"
        }
    ],
    "sg:phone":"+1 260 665 9457",
    "sg:postcode":"46703",
    "sg:province":"IN",
    "sg:tags":[
        "abrasive",
        "product"
    ],
    "wof:name":"Micromatic Textron",
    "wof:placetype":"venue"
},
  "geometry": {"coordinates":[-85.004406,41.64563],"type":"Point"}
}