{
  "type": "Feature",
  "properties": {
    "addr:full":"2001 S Main St New Castle IN 47362",
    "addr:housenumber":"2001",
    "addr:postcode":"47362",
    "addr:street":"S Main St",
    "iso:country":"US",
    "sg:address":"2001 S Main St",
    "sg:city":"New Castle",
    "sg:classifiers":[
        {
            "category":"Food & Beverages",
            "subcategory":"Bakery",
            "type":"Retail Goods"
        }
    ],
    "sg:phone":"+1 765 521 6855",
    "sg:postcode":"47362",
    "sg:province":"IN",
    "sg:tags":[
        "baker"
    ],
    "wof:name":"Baker Park Pool",
    "wof:placetype":"venue"
},
  "geometry": {"coordinates":[-85.370853,39.912573],"type":"Point"}
}