{
  "type": "Feature",
  "properties": {
    "iso:country":"US",
    "sg:address":"3741 W 100 S",
    "sg:city":"Wabash",
    "sg:classifiers":[
        {
            "category":"Organizations",
            "subcategory":"Religious Organization",
            "type":"Services"
        }
    ],
    "sg:phone":"+1 260 563 8000",
    "sg:postcode":"46992",
    "sg:province":"IN",
    "sg:tags":[
        "church"
    ],
    "wof:name":"Jehovah's Witnesses",
    "wof:placetype":"venue"
},
  "geometry": {"coordinates":[-85.863178,40.809762],"type":"Point"}
}