{
  "type": "Feature",
  "properties": {
    "iso:country":"US",
    "sg:address":"5120 Massachusetts Ave",
    "sg:city":"Indianapolis",
    "sg:classifiers":[
        {
            "category":"Building & Trades",
            "subcategory":"Construction",
            "type":"Services"
        }
    ],
    "sg:phone":"+1 317 542 1535",
    "sg:postcode":"46218",
    "sg:province":"IN",
    "wof:name":"World of Trades",
    "wof:placetype":"venue"
},
  "geometry": {"coordinates":[-86.082944,39.811127],"type":"Point"}
}