{
  "type": "Feature",
  "properties": {
    "iso:country":"US",
    "sg:address":"8290 E 96th St",
    "sg:city":"Fishers",
    "sg:classifiers":[
        {
            "category":"Shopping",
            "subcategory":"Shoes",
            "type":"Retail Goods"
        }
    ],
    "sg:phone":"+1 317 594 0735",
    "sg:postcode":"46037",
    "sg:province":"IN",
    "sg:tags":[
        "store"
    ],
    "sg:website":"www.payless.com",
    "wof:name":"Payless Shoes",
    "wof:placetype":"venue"
},
  "geometry": {"coordinates":[-86.022004,39.927428],"type":"Point"}
}