{
  "type": "Feature",
  "properties": {
    "iso:country":"US",
    "sg:address":"4415 Forest Manor Ave",
    "sg:city":"Indianapolis",
    "sg:classifiers":[
        {
            "category":"Education",
            "subcategory":"Vocational School",
            "type":"Public Place"
        }
    ],
    "sg:phone":"+1 317 545 7071",
    "sg:postcode":"46226",
    "sg:province":"IN",
    "sg:tags":[
        "technical",
        "trade"
    ],
    "wof:name":"AC/C Tech",
    "wof:placetype":"venue"
},
  "geometry": {"coordinates":[-86.100202,39.837401],"type":"Point"}
}