{
  "type": "Feature",
  "properties": {
    "iso:country":"US",
    "sg:address":"201 N Illinois St",
    "sg:city":"Indianapolis",
    "sg:classifiers":[
        {
            "category":"Professional",
            "subcategory":"Management & Consulting",
            "type":"Services"
        }
    ],
    "sg:phone":"+1 317 383 3783",
    "sg:postcode":"46204",
    "sg:province":"IN",
    "sg:tags":[
        "consultant",
        "business"
    ],
    "wof:name":"John E Bourquard",
    "wof:placetype":"venue"
},
  "geometry": {"coordinates":[-86.159671,39.771247],"type":"Point"}
}