{
  "type": "Feature",
  "properties": {
    "iso:country":"US",
    "sg:address":"4300 Becker Rd",
    "sg:city":"Woodburn",
    "sg:classifiers":[
        {
            "category":"Organizations",
            "subcategory":"Religious Organization",
            "type":"Services"
        }
    ],
    "sg:phone":"+1 260 632 5313",
    "sg:postcode":"46797",
    "sg:province":"IN",
    "sg:tags":[
        "church"
    ],
    "wof:name":"Woodburn United Methodist Chr",
    "wof:placetype":"venue"
},
  "geometry": {"coordinates":[-84.857552,41.124963],"type":"Point"}
}