{
  "type": "Feature",
  "properties": {
    "addr:full":"6586 Crosswinds Ct Avon IN 46123",
    "addr:housenumber":"6586",
    "addr:postcode":"46123",
    "addr:street":"Crosswinds Ct",
    "iso:country":"US",
    "sg:address":"6586 Crosswinds Ct",
    "sg:city":"Avon",
    "sg:classifiers":[
        {
            "category":"Wholesale",
            "subcategory":"Sporting Goods",
            "type":"Manufacturing & Wholesale Goods"
        }
    ],
    "sg:phone":"+1 317 839 7662",
    "sg:postcode":"46123",
    "sg:province":"IN",
    "wof:name":"Porter Athletic Equipment",
    "wof:placetype":"venue"
},
  "geometry": {"coordinates":[-86.408008,39.735114],"type":"Point"}
}