{
  "type": "Feature",
  "properties": {
    "iso:country":"US",
    "sg:address":"9521 Carriage Ln",
    "sg:city":"Fort Wayne",
    "sg:classifiers":[
        {
            "category":"Food & Beverages",
            "subcategory":"Specialty",
            "type":"Retail Goods"
        }
    ],
    "sg:phone":"+1 260 436 2843",
    "sg:postcode":"46804",
    "sg:province":"IN",
    "sg:tags":[
        "health",
        "diet"
    ],
    "wof:name":"Shaklee Distributor",
    "wof:placetype":"venue"
},
  "geometry": {"coordinates":[-85.266901,41.049106],"type":"Point"}
}