{
  "type": "Feature",
  "properties": {
    "iso:country":"US",
    "sg:address":"3730 Edison Lakes Pkwy",
    "sg:city":"Mishawaka",
    "sg:classifiers":[
        {
            "category":"Health Services",
            "subcategory":"Doctor",
            "type":"Services"
        }
    ],
    "sg:phone":"+1 574 243 1700",
    "sg:postcode":"46545",
    "sg:province":"IN",
    "sg:tags":[
        "physician",
        "surgeon"
    ],
    "wof:name":"Gabriele Eye Institute",
    "wof:placetype":"venue"
},
  "geometry": {"coordinates":[-86.180775,41.694785],"type":"Point"}
}