{
  "type": "Feature",
  "properties": {
    "iso:country":"US",
    "sg:address":"1015 Southampton Dr",
    "sg:city":"Decatur",
    "sg:classifiers":[
        {
            "category":"Autos & Motor Vehicles",
            "subcategory":"Automobile Sales",
            "type":"Retail Goods"
        }
    ],
    "sg:phone":"+1 260 724 8766",
    "sg:postcode":"46733",
    "sg:province":"IN",
    "sg:tags":[
        "car",
        "dealer"
    ],
    "wof:name":"Strickler Auto Sales",
    "wof:placetype":"venue"
},
  "geometry": {"coordinates":[-84.93933699999999,40.842978],"type":"Point"}
}