{
  "type": "Feature",
  "properties": {
    "iso:country":"US",
    "sg:address":"114 S Chestnut St",
    "sg:city":"Seymour",
    "sg:classifiers":[
        {
            "category":"Insurance",
            "subcategory":"Insurance Agent",
            "type":"Services"
        }
    ],
    "sg:phone":"+1 812 522 4315",
    "sg:postcode":"47274",
    "sg:province":"IN",
    "sg:website":"www.chastaininsurance.com",
    "wof:name":"CHASTAIN Insurance",
    "wof:placetype":"venue"
},
  "geometry": {"coordinates":[-85.890034,38.957919],"type":"Point"}
}