{
  "type": "Feature",
  "properties": {
    "iso:country":"US",
    "sg:address":"300 E Broadway St",
    "sg:city":"Logansport",
    "sg:classifiers":[
        {
            "category":"Professional",
            "subcategory":"Management & Consulting",
            "type":"Services"
        }
    ],
    "sg:phone":"+1 574 722 5988",
    "sg:postcode":"46947",
    "sg:province":"IN",
    "sg:tags":[
        "consultant",
        "business"
    ],
    "sg:website":"www.ledf.com",
    "wof:name":"Logansport Economic Dev Fndtn",
    "wof:placetype":"venue"
},
  "geometry": {"coordinates":[-86.36518,40.754138],"type":"Point"}
}