{
  "type": "Feature",
  "properties": {
    "iso:country":"US",
    "sg:address":"710 Krueger St",
    "sg:city":"Kendallville",
    "sg:classifiers":[
        {
            "category":"Banks & Credit Unions",
            "subcategory":"Investment Brokerage",
            "type":"Services"
        }
    ],
    "sg:phone":"+1 260 347 1281",
    "sg:postcode":"46755",
    "sg:province":"IN",
    "sg:tags":[
        "advisory",
        "financial"
    ],
    "wof:name":"AMI Investment Management",
    "wof:placetype":"venue"
},
  "geometry": {"coordinates":[-85.268747,41.452187],"type":"Point"}
}