{
  "type": "Feature",
  "properties": {
    "addr:full":"9175 Calumet Ave Munster IN 46321",
    "addr:housenumber":"9175",
    "addr:postcode":"46321",
    "addr:street":"Calumet Ave",
    "iso:country":"US",
    "sg:address":"9175 Calumet Ave",
    "sg:city":"Munster",
    "sg:classifiers":[
        {
            "category":"Banks & Credit Unions",
            "subcategory":"Bank",
            "type":"Services"
        }
    ],
    "sg:phone":"+1 219 836 2403",
    "sg:postcode":"46321",
    "sg:province":"IN",
    "wof:name":"National City",
    "wof:placetype":"venue"
},
  "geometry": {"coordinates":[-87.509201,41.547401],"type":"Point"}
}