{
  "type": "Feature",
  "properties": {
    "iso:country":"US",
    "sg:address":"1710 S State Rd 9",
    "sg:city":"Columbia City",
    "sg:classifiers":[
        {
            "category":"Education",
            "subcategory":"School",
            "type":"Public Place"
        }
    ],
    "sg:phone":"+1 260 244 3343",
    "sg:postcode":"46725",
    "sg:province":"IN",
    "wof:name":"Little Turtle Elementary Sch",
    "wof:placetype":"venue"
},
  "geometry": {"coordinates":[-85.481454,41.136232],"type":"Point"}
}