{
  "type": "Feature",
  "properties": {
    "iso:country":"US",
    "sg:address":"10059 E Washington St",
    "sg:city":"Indianapolis",
    "sg:classifiers":[
        {
            "category":"Professional",
            "subcategory":"Detective & Security Services",
            "type":"Services"
        }
    ],
    "sg:phone":"+1 317 895 7661",
    "sg:postcode":"46229",
    "sg:province":"IN",
    "wof:name":"Spy Shop",
    "wof:placetype":"venue"
},
  "geometry": {"coordinates":[-85.988201,39.774901],"type":"Point"}
}