{
  "type": "Feature",
  "properties": {
    "addr:full":"2265 N Bradbury Rd Attica IN 47918",
    "addr:housenumber":"2265",
    "addr:postcode":"47918",
    "addr:street":"N Bradbury Rd",
    "iso:country":"US",
    "sg:address":"2265 N Bradbury Rd",
    "sg:city":"Attica",
    "sg:classifiers":[
        {
            "category":"Professional",
            "subcategory":"Management & Consulting",
            "type":"Services"
        }
    ],
    "sg:phone":"+1 765 494 1162",
    "sg:postcode":"47918",
    "sg:province":"IN",
    "sg:tags":[
        "environmental",
        "engineering"
    ],
    "wof:name":"Bernard Engel",
    "wof:placetype":"venue"
},
  "geometry": {"coordinates":[-87.153277,40.354586],"type":"Point"}
}