{
  "type": "Feature",
  "properties": {
    "iso:country":"US",
    "sg:address":"28778 US Hwy 20",
    "sg:city":"Elkhart",
    "sg:classifiers":[
        {
            "category":"Professional",
            "type":"Services"
        }
    ],
    "sg:phone":"+1 574 522 7280",
    "sg:postcode":"46514",
    "sg:province":"IN",
    "sg:tags":[
        "establishment"
    ],
    "wof:name":"S & S Equipment Corp",
    "wof:placetype":"venue"
},
  "geometry": {"coordinates":[-86.02105,41.68686],"type":"Point"}
}