{
  "type": "Feature",
  "properties": {
    "iso:country":"US",
    "sg:address":"3960 Southeastern Ave",
    "sg:city":"Indianapolis",
    "sg:classifiers":[
        {
            "category":"Sports & Exercise",
            "subcategory":"Gym",
            "type":"Entertainment"
        }
    ],
    "sg:phone":"+1 317 352 8100",
    "sg:postcode":"46203",
    "sg:province":"IN",
    "sg:tags":[
        "club",
        "health",
        "studio",
        "gymnasium"
    ],
    "wof:name":"USF Inc",
    "wof:placetype":"venue"
},
  "geometry": {"coordinates":[-86.094318,39.750869],"type":"Point"}
}