{
  "type": "Feature",
  "properties": {
    "iso:country":"US",
    "sg:address":"300 N Randolph St",
    "sg:city":"Garrett",
    "sg:classifiers":[
        {
            "category":"Museum",
            "type":"Entertainment"
        }
    ],
    "sg:phone":"+1 260 357 5575",
    "sg:postcode":"46738",
    "sg:province":"IN",
    "wof:name":"Garrett Historical Museum",
    "wof:placetype":"venue"
},
  "geometry": {"coordinates":[-85.135679,41.353637],"type":"Point"}
}