{
  "type": "Feature",
  "properties": {
    "iso:country":"US",
    "sg:address":"954 W National Ave",
    "sg:city":"Brazil",
    "sg:classifiers":[
        {
            "category":"Retail",
            "subcategory":"Car Wash",
            "type":"Services"
        }
    ],
    "sg:phone":"+1 812 442 1727",
    "sg:postcode":"47834",
    "sg:province":"IN",
    "sg:tags":[
        "carwash",
        "automobile",
        "detail",
        "clean"
    ],
    "wof:name":"Bryant's Auto Detailing",
    "wof:placetype":"venue"
},
  "geometry": {"coordinates":[-87.13813,39.520506],"type":"Point"}
}