{
  "type": "Feature",
  "properties": {
    "iso:country":"US",
    "sg:address":"208 5th St",
    "sg:city":"Monroe City",
    "sg:classifiers":[
        {
            "category":"Personal",
            "subcategory":"Beauty Salon",
            "type":"Services"
        }
    ],
    "sg:phone":"+1 812 743 2551",
    "sg:postcode":"47557",
    "sg:province":"IN",
    "wof:name":"Maxine's Beauty Nook",
    "wof:placetype":"venue"
},
  "geometry": {"coordinates":[-87.354449,38.617771],"type":"Point"}
}