{
  "type": "Feature",
  "properties": {
    "iso:country":"US",
    "sg:address":"3702 N Shadeland Ave",
    "sg:city":"Indianapolis",
    "sg:classifiers":[
        {
            "category":"Building & Trades",
            "subcategory":"Construction",
            "type":"Services"
        }
    ],
    "sg:phone":"+1 317 321 1089",
    "sg:postcode":"46226",
    "sg:province":"IN",
    "sg:tags":[
        "excavating",
        "contractor"
    ],
    "wof:name":"Acme Sewer Co",
    "wof:placetype":"venue"
},
  "geometry": {"coordinates":[-86.045947,39.823909],"type":"Point"}
}