{
  "type": "Feature",
  "properties": {
    "addr:full":"807 S Reed Rd Kokomo IN 46901",
    "addr:housenumber":"807",
    "addr:postcode":"46901",
    "addr:street":"S Reed Rd",
    "iso:country":"US",
    "sg:address":"807 S Reed Rd",
    "sg:city":"Kokomo",
    "sg:classifiers":[
        {
            "category":"Restaurant",
            "type":"Food & Drink"
        }
    ],
    "sg:phone":"+1 765 457 0908",
    "sg:postcode":"46901",
    "sg:province":"IN",
    "wof:name":"Waffle House",
    "wof:placetype":"venue"
},
  "geometry": {"coordinates":[-86.107843,40.476687],"type":"Point"}
}