{
  "type": "Feature",
  "properties": {
    "iso:country":"US",
    "sg:address":"14606 W 109th Ave",
    "sg:city":"Dyer",
    "sg:classifiers":[
        {
            "category":"Freight",
            "type":"Transportation"
        }
    ],
    "sg:phone":"+1 219 365 3930",
    "sg:postcode":"46311",
    "sg:province":"IN",
    "sg:tags":[
        "operator",
        "trucking"
    ],
    "wof:name":"Devries Transport Inc",
    "wof:placetype":"venue"
},
  "geometry": {"coordinates":[-87.517131,41.42114],"type":"Point"}
}