{
  "type": "Feature",
  "properties": {
    "iso:country":"US",
    "sg:address":"12412 Turkel Dr",
    "sg:city":"Fishers",
    "sg:classifiers":[
        {
            "category":"Building & Trades",
            "subcategory":"Landscaping Services",
            "type":"Services"
        }
    ],
    "sg:phone":"+1 317 849 6307",
    "sg:postcode":"46038",
    "sg:province":"IN",
    "sg:tags":[
        "landscape"
    ],
    "wof:name":"Heinzman Night Lights Inc",
    "wof:placetype":"venue"
},
  "geometry": {"coordinates":[-86.01621,39.965817],"type":"Point"}
}