{
  "type": "Feature",
  "properties": {
    "iso:country":"US",
    "sg:address":"6023 E 26th St",
    "sg:city":"Indianapolis",
    "sg:classifiers":[
        {
            "category":"Manufacturing",
            "subcategory":"Printing",
            "type":"Manufacturing & Wholesale Goods"
        }
    ],
    "sg:phone":"+1 317 568 1340",
    "sg:postcode":"46219",
    "sg:province":"IN",
    "sg:tags":[
        "bookbinder"
    ],
    "wof:name":"Emerson Bookbinding Co",
    "wof:placetype":"venue"
},
  "geometry": {"coordinates":[-86.06036899999999,39.805425],"type":"Point"}
}