{
  "type": "Feature",
  "properties": {
    "iso:country":"US",
    "sg:address":"811 E 9th St",
    "sg:city":"Rochester",
    "sg:classifiers":[
        {
            "category":"Restaurant",
            "type":"Food & Drink"
        }
    ],
    "sg:phone":"+1 574 224 6262",
    "sg:postcode":"46975",
    "sg:province":"IN",
    "sg:tags":[
        "pizza"
    ],
    "wof:name":"Mama Suzetta's Pizza & Pasta",
    "wof:placetype":"venue"
},
  "geometry": {"coordinates":[-86.206184,41.06434],"type":"Point"}
}