{
  "type": "Feature",
  "properties": {
    "iso:country":"US",
    "sg:address":"12838 N 400 W",
    "sg:city":"Milford",
    "sg:classifiers":[
        {
            "category":"Farming",
            "subcategory":"Dairy Farm",
            "type":"Manufacturing & Wholesale Goods"
        }
    ],
    "sg:phone":"+1 574 658 9320",
    "sg:postcode":"46542",
    "sg:province":"IN",
    "wof:name":"Gingerich Dairy",
    "wof:placetype":"venue"
},
  "geometry": {"coordinates":[-85.924825,41.424546],"type":"Point"}
}