{
  "type": "Feature",
  "properties": {
    "iso:country":"US",
    "sg:address":"1749 E Industrial Dr",
    "sg:city":"Terre Haute",
    "sg:classifiers":[
        {
            "category":"Banks & Credit Unions",
            "subcategory":"Bank",
            "type":"Services"
        }
    ],
    "sg:phone":"+1 812 238 6730",
    "sg:postcode":"47802",
    "sg:province":"IN",
    "wof:name":"Terre Haute First National",
    "wof:placetype":"venue"
},
  "geometry": {"coordinates":[-87.39045,39.345548],"type":"Point"}
}