{
  "type": "Feature",
  "properties": {
    "iso:country":"US",
    "sg:address":"1015 Main St",
    "sg:city":"Evansville",
    "sg:classifiers":[
        {
            "category":"Mining & Drilling",
            "type":"Manufacturing & Wholesale Goods"
        }
    ],
    "sg:phone":"+1 812 421 4453",
    "sg:postcode":"47708",
    "sg:province":"IN",
    "sg:tags":[
        "oil",
        "well"
    ],
    "wof:name":"Hydrocarbon Investments Inc",
    "wof:placetype":"venue"
},
  "geometry": {"coordinates":[-87.564217,37.976473],"type":"Point"}
}