{
  "type": "Feature",
  "properties": {
    "iso:country":"US",
    "sg:address":"3009 E Cherry St",
    "sg:city":"Evansville",
    "sg:classifiers":[
        {
            "category":"Utilities",
            "subcategory":"Refuse",
            "type":"Services"
        }
    ],
    "sg:phone":"+1 812 479 0382",
    "sg:postcode":"47714",
    "sg:province":"IN",
    "sg:tags":[
        "garbage",
        "collection"
    ],
    "wof:name":"R & R Hauling",
    "wof:placetype":"venue"
},
  "geometry": {"coordinates":[-87.511063,37.971521],"type":"Point"}
}