{
  "type": "Feature",
  "properties": {
    "iso:country":"US",
    "sg:address":"7981 New Jersey Ave",
    "sg:city":"Hammond",
    "sg:classifiers":[
        {
            "category":"Professional",
            "subcategory":"Business Services",
            "type":"Services"
        }
    ],
    "sg:phone":"+1 219 845 0795",
    "sg:postcode":"46323",
    "sg:province":"IN",
    "sg:tags":[
        "heavy",
        "construction"
    ],
    "wof:name":"Cranemasters Inc",
    "wof:placetype":"venue"
},
  "geometry": {"coordinates":[-87.438673,41.572532],"type":"Point"}
}