{
  "type": "Feature",
  "properties": {
    "iso:country":"US",
    "sg:address":"9 N Dunn St",
    "sg:city":"Plainville",
    "sg:classifiers":[
        {
            "category":"Building & Trades",
            "subcategory":"Landscaping Services",
            "type":"Services"
        }
    ],
    "sg:phone":"+1 812 687 7494",
    "sg:postcode":"47523",
    "sg:province":"IN",
    "wof:name":"Clidienst Lawn Care",
    "wof:placetype":"venue"
},
  "geometry": {"coordinates":[-86.98397799999999,38.172115],"type":"Point"}
}