{
  "type": "Feature",
  "properties": {
    "addr:full":"3787 W US Hwy 52 New Palestine IN 46163",
    "addr:housenumber":"3787",
    "addr:postcode":"in 46163",
    "addr:street":"W Us Hwy 52",
    "iso:country":"US",
    "sg:address":"3787 W US Hwy 52",
    "sg:city":"New Palestine",
    "sg:classifiers":[
        {
            "category":"Farming",
            "subcategory":"Nursery",
            "type":"Manufacturing & Wholesale Goods"
        }
    ],
    "sg:phone":"+1 317 861 1979",
    "sg:postcode":"46163",
    "sg:province":"IN",
    "sg:tags":[
        "greenhouse"
    ],
    "wof:name":"Ash Perennial Farm",
    "wof:placetype":"venue"
},
  "geometry": {"coordinates":[-85.861419,39.714553],"type":"Point"}
}