{
  "type": "Feature",
  "properties": {
    "iso:country":"US",
    "sg:address":"2702 E Glendale Blvd",
    "sg:city":"Valparaiso",
    "sg:classifiers":[
        {
            "category":"Organizations",
            "subcategory":"Religious Organization",
            "type":"Services"
        }
    ],
    "sg:phone":"+1 219 462 2751",
    "sg:postcode":"46383",
    "sg:province":"IN",
    "sg:tags":[
        "church"
    ],
    "sg:website":"www.valponaz.org",
    "wof:name":"Valparaiso Nazarene Church",
    "wof:placetype":"venue"
},
  "geometry": {"coordinates":[-87.028553,41.485418],"type":"Point"}
}