{
  "type": "Feature",
  "properties": {
    "iso:country":"US",
    "sg:address":"204 S Union St",
    "sg:city":"Delphi",
    "sg:classifiers":[
        {
            "category":"Retail",
            "subcategory":"Auto Repair",
            "type":"Services"
        }
    ],
    "sg:phone":"+1 765 564 2381",
    "sg:postcode":"46923",
    "sg:province":"IN",
    "sg:tags":[
        "repairing",
        "automobile"
    ],
    "wof:name":"B & B Automotive Svc Ctr",
    "wof:placetype":"venue"
},
  "geometry": {"coordinates":[-86.672901,40.586495],"type":"Point"}
}