{
  "type": "Feature",
  "properties": {
    "iso:country":"US",
    "sg:address":"507 E Haub St",
    "sg:city":"Haubstadt",
    "sg:classifiers":[
        {
            "category":"Real Estate",
            "subcategory":"Surveying",
            "type":"Services"
        }
    ],
    "sg:phone":"+1 812 768 6279",
    "sg:postcode":"47639",
    "sg:province":"IN",
    "sg:tags":[
        "surveyor"
    ],
    "wof:name":"Lee Ls Hoffman Home & Bus",
    "wof:placetype":"venue"
},
  "geometry": {"coordinates":[-87.569855,38.203921],"type":"Point"}
}