{
  "type": "Feature",
  "properties": {
    "iso:country":"US",
    "sg:address":"826 S State St",
    "sg:city":"Greenfield",
    "sg:classifiers":[
        {
            "category":"Restaurant",
            "type":"Food & Drink"
        }
    ],
    "sg:phone":"+1 317 468 1048",
    "sg:postcode":"46140",
    "sg:province":"IN",
    "sg:tags":[
        "eating"
    ],
    "wof:name":"Cholula Mexican Restaurant",
    "wof:placetype":"venue"
},
  "geometry": {"coordinates":[-85.76729,39.775296],"type":"Point"}
}