{
  "type": "Feature",
  "properties": {
    "iso:country":"US",
    "sg:address":"3202 Queen St",
    "sg:city":"Fort Wayne",
    "sg:classifiers":[
        {
            "category":"Social Services",
            "subcategory":"Child Care",
            "type":"Services"
        }
    ],
    "sg:phone":"+1 260 745 0035",
    "sg:postcode":"46806",
    "sg:province":"IN",
    "sg:tags":[
        "day",
        "provider"
    ],
    "wof:name":"Tender Loving Care",
    "wof:placetype":"venue"
},
  "geometry": {"coordinates":[-85.106513,41.055494],"type":"Point"}
}