{
  "type": "Feature",
  "properties": {
    "iso:country":"US",
    "sg:address":"4410 W Washington St",
    "sg:city":"Indianapolis",
    "sg:classifiers":[
        {
            "category":"Insurance",
            "subcategory":"Insurance Agent",
            "type":"Services"
        }
    ],
    "sg:phone":"+1 317 270 7000",
    "sg:postcode":"46241",
    "sg:province":"IN",
    "wof:name":"Agencia De Seguros Latino",
    "wof:placetype":"venue"
},
  "geometry": {"coordinates":[-86.238277,39.756611],"type":"Point"}
}