{
  "type": "Feature",
  "properties": {
    "addr:full":"2652 W State Rd 2 Laporte IN 46350",
    "addr:housenumber":"2652",
    "addr:postcode":"46350",
    "addr:street":"W State Rd 2",
    "iso:country":"US",
    "sg:address":"2652 W State Rd 2",
    "sg:city":"Laporte",
    "sg:classifiers":[
        {
            "category":"Travel",
            "subcategory":"Hotels & Motels",
            "type":"Entertainment"
        }
    ],
    "sg:phone":"+1 219 362 2092",
    "sg:postcode":"46350",
    "sg:province":"IN",
    "wof:name":"Mayflower Motel",
    "wof:placetype":"venue"
},
  "geometry": {"coordinates":[-86.750462,41.591405],"type":"Point"}
}