{
  "type": "Feature",
  "properties": {
    "iso:country":"US",
    "sg:address":"2028 W Willowcreek Dr",
    "sg:city":"Paoli",
    "sg:classifiers":[
        {
            "category":"Organizations",
            "subcategory":"Religious Organization",
            "type":"Services"
        }
    ],
    "sg:phone":"+1 812 723 2971",
    "sg:postcode":"47454",
    "sg:province":"IN",
    "sg:tags":[
        "church"
    ],
    "wof:name":"Souls Harbor Assembly Of God",
    "wof:placetype":"venue"
},
  "geometry": {"coordinates":[-86.493388,38.557323],"type":"Point"}
}