{
  "type": "Feature",
  "properties": {
    "iso:country":"US",
    "sg:address":"510 W McKinley Ave",
    "sg:city":"Mishawaka",
    "sg:classifiers":[
        {
            "category":"Banks & Credit Unions",
            "subcategory":"Bank",
            "type":"Services"
        }
    ],
    "sg:phone":"+1 574 257 1300",
    "sg:postcode":"46545",
    "sg:province":"IN",
    "sg:tags":[
        "financing",
        "institution"
    ],
    "wof:name":"Heights Finance Corporation",
    "wof:placetype":"venue"
},
  "geometry": {"coordinates":[-86.18850399999999,41.680411],"type":"Point"}
}