{
  "type": "Feature",
  "properties": {
    "iso:country":"US",
    "sg:address":"252 Pineview Ln",
    "sg:city":"Valparaiso",
    "sg:classifiers":[
        {
            "category":"Professional",
            "subcategory":"Business Services",
            "type":"Services"
        }
    ],
    "sg:phone":"+1 219 462 6012",
    "sg:postcode":"46383",
    "sg:province":"IN",
    "wof:name":"Ulman Shelly Dctg Faux Pntg Co",
    "wof:placetype":"venue"
},
  "geometry": {"coordinates":[-87.064073,41.504179],"type":"Point"}
}