{
  "type": "Feature",
  "properties": {
    "iso:country":"US",
    "sg:address":"8152 Kennedy Ave",
    "sg:city":"Highland",
    "sg:classifiers":[
        {
            "category":"Professional",
            "subcategory":"Business Services",
            "type":"Services"
        }
    ],
    "sg:phone":"+1 219 923 1602",
    "sg:postcode":"46322",
    "sg:province":"IN",
    "sg:tags":[
        "appraiser"
    ],
    "wof:name":"Bochnowski Appraisal Co",
    "wof:placetype":"venue"
},
  "geometry": {"coordinates":[-87.461505,41.564705],"type":"Point"}
}