{
  "type": "Feature",
  "properties": {
    "iso:country":"US",
    "sg:address":"13981 State Rd 23",
    "sg:city":"Granger",
    "sg:classifiers":[
        {
            "category":"Government",
            "subcategory":"Office",
            "type":"Public Place"
        }
    ],
    "sg:phone":"+1 574 272 3874",
    "sg:postcode":"46530",
    "sg:province":"IN",
    "sg:tags":[
        "village"
    ],
    "wof:name":"Harris Twp Adm",
    "wof:placetype":"venue"
},
  "geometry": {"coordinates":[-86.136093,41.745523],"type":"Point"}
}