{
  "type": "Feature",
  "properties": {
    "iso:country":"US",
    "sg:address":"9291 S Big Springs Rd",
    "sg:city":"Pekin",
    "sg:classifiers":[
        {
            "category":"Organizations",
            "subcategory":"Religious Organization",
            "type":"Services"
        }
    ],
    "sg:phone":"+1 812 364 4373",
    "sg:postcode":"47165",
    "sg:province":"IN",
    "wof:name":"Word of Truth Ministries",
    "wof:placetype":"venue"
},
  "geometry": {"coordinates":[-86.11297,38.461273],"type":"Point"}
}