{
  "type": "Feature",
  "properties": {
    "iso:country":"US",
    "sg:address":"5112 State Rd 62",
    "sg:city":"Jeffersonville",
    "sg:classifiers":[
        {
            "category":"Banks & Credit Unions",
            "subcategory":"Bank",
            "type":"Services"
        }
    ],
    "sg:phone":"+1 812 285 4050",
    "sg:postcode":"47130",
    "sg:province":"IN",
    "wof:name":"Community Bank",
    "wof:placetype":"venue"
},
  "geometry": {"coordinates":[-85.70380299999999,38.351948],"type":"Point"}
}