{
  "type": "Feature",
  "properties": {
    "iso:country":"US",
    "sg:address":"74 W New York St",
    "sg:city":"Indianapolis",
    "sg:classifiers":[
        {
            "category":"Restaurant",
            "type":"Food & Drink"
        }
    ],
    "sg:phone":"+1 317 423 2373",
    "sg:postcode":"46204",
    "sg:province":"IN",
    "sg:tags":[
        "pizza",
        "italian"
    ],
    "wof:name":"Luca Pizza Di Roma",
    "wof:placetype":"venue"
},
  "geometry": {"coordinates":[-86.159283,39.771339],"type":"Point"}
}