{
  "type": "Feature",
  "properties": {
    "iso:country":"US",
    "sg:address":"2621 E 80th Ave",
    "sg:city":"Merrillville",
    "sg:classifiers":[
        {
            "category":"Shopping",
            "subcategory":"Optical Goods",
            "type":"Retail Goods"
        }
    ],
    "sg:phone":"+1 219 942 2726",
    "sg:postcode":"46410",
    "sg:province":"IN",
    "wof:name":"For Eyes Optical Co",
    "wof:placetype":"venue"
},
  "geometry": {"coordinates":[-87.308109,41.473558],"type":"Point"}
}