{
  "type": "Feature",
  "properties": {
    "iso:country":"US",
    "sg:address":"251 N State Rd 39",
    "sg:city":"Laporte",
    "sg:classifiers":[
        {
            "category":"Manufacturing",
            "subcategory":"Wood Products",
            "type":"Manufacturing & Wholesale Goods"
        }
    ],
    "sg:phone":"+1 219 324 7697",
    "sg:postcode":"46350",
    "sg:province":"IN",
    "sg:tags":[
        "box"
    ],
    "wof:name":"Industrial Lumber Products",
    "wof:placetype":"venue"
},
  "geometry": {"coordinates":[-86.733532,41.617349],"type":"Point"}
}