{
  "type": "Feature",
  "properties": {
    "iso:country":"US",
    "sg:address":"930 Logan St",
    "sg:city":"Noblesville",
    "sg:classifiers":[
        {
            "category":"Home & Garden",
            "subcategory":"Furniture",
            "type":"Retail Goods"
        }
    ],
    "sg:phone":"+1 317 770 8200",
    "sg:postcode":"46060",
    "sg:province":"IN",
    "sg:tags":[
        "furniture-wholesale",
        "manufacturer"
    ],
    "wof:name":"Amish Hertigage Furniture",
    "wof:placetype":"venue"
},
  "geometry": {"coordinates":[-86.013119,40.046549],"type":"Point"}
}