{
  "type": "Feature",
  "properties": {
    "addr:full":"1324 N Gavin St Muncie IN 47303",
    "addr:housenumber":"1324",
    "addr:postcode":"47303",
    "addr:street":"N Gavin St",
    "iso:country":"US",
    "sg:address":"1324 N Gavin St",
    "sg:city":"Muncie",
    "sg:classifiers":[
        {
            "category":"Organizations",
            "subcategory":"Community Association",
            "type":"Services"
        }
    ],
    "sg:phone":"+1 765 282 8636",
    "sg:postcode":"47303",
    "sg:province":"IN",
    "sg:tags":[
        "fraternal"
    ],
    "wof:name":"Debonair Club",
    "wof:placetype":"venue"
},
  "geometry": {"coordinates":[-85.363007,40.205222],"type":"Point"}
}