{
  "type": "Feature",
  "properties": {
    "iso:country":"US",
    "sg:address":"2869 W 450 N",
    "sg:city":"Rochester",
    "sg:classifiers":[
        {
            "category":"Farming",
            "subcategory":"Farm",
            "type":"Manufacturing & Wholesale Goods"
        }
    ],
    "sg:phone":"+1 574 223 2273",
    "sg:postcode":"46975",
    "sg:province":"IN",
    "wof:name":"Hiatt Garden Farms",
    "wof:placetype":"venue"
},
  "geometry": {"coordinates":[-86.296008,41.12027],"type":"Point"}
}