{
  "type": "Feature",
  "properties": {
    "iso:country":"US",
    "sg:address":"6355 College Corner Rd",
    "sg:city":"Centerville",
    "sg:classifiers":[
        {
            "category":"Professional",
            "subcategory":"Management & Consulting",
            "type":"Services"
        }
    ],
    "sg:phone":"+1 765 855 2296",
    "sg:postcode":"47330",
    "sg:province":"IN",
    "sg:tags":[
        "retail",
        "direct",
        "sales"
    ],
    "wof:name":"Kim Northington",
    "wof:placetype":"venue"
},
  "geometry": {"coordinates":[-84.99654200000001,39.830759],"type":"Point"}
}