{
  "type": "Feature",
  "properties": {
    "addr:full":"32 S Center St Flora IN 46929",
    "addr:housenumber":"32",
    "addr:postcode":"46929",
    "addr:street":"S Center St",
    "iso:country":"US",
    "sg:address":"32 S Center St",
    "sg:city":"Flora",
    "sg:classifiers":[
        {
            "category":"Home & Garden",
            "subcategory":"Furniture",
            "type":"Retail Goods"
        }
    ],
    "sg:phone":"+1 574 967 3600",
    "sg:postcode":"46929",
    "sg:province":"IN",
    "wof:name":"Eikenberry Furniture",
    "wof:placetype":"venue"
},
  "geometry": {"coordinates":[-86.523691,40.547802],"type":"Point"}
}