{
  "type": "Feature",
  "properties": {
    "iso:country":"US",
    "sg:address":"171 N 600 W",
    "sg:city":"Valparaiso",
    "sg:classifiers":[
        {
            "category":"Building & Trades",
            "subcategory":"Construction",
            "type":"Services"
        }
    ],
    "sg:phone":"+1 219 759 1934",
    "sg:postcode":"46385",
    "sg:province":"IN",
    "sg:tags":[
        "general",
        "contractor"
    ],
    "wof:name":"L Dusseau",
    "wof:placetype":"venue"
},
  "geometry": {"coordinates":[-87.181184,41.45901],"type":"Point"}
}