{
  "type": "Feature",
  "properties": {
    "iso:country":"US",
    "sg:address":"1814 Navaho Dr",
    "sg:city":"Ellettsville",
    "sg:classifiers":[
        {
            "category":"Real Estate",
            "subcategory":"Real Estate Agent",
            "type":"Services"
        }
    ],
    "sg:phone":"+1 812 876 3052",
    "sg:postcode":"47429",
    "sg:province":"IN",
    "wof:name":"Action Real Estate",
    "wof:placetype":"venue"
},
  "geometry": {"coordinates":[-86.629117,39.221668],"type":"Point"}
}