{
  "type": "Feature",
  "properties": {
    "addr:full":"850 College Ave Jasper IN 47546",
    "addr:housenumber":"850",
    "addr:postcode":"47546",
    "addr:street":"College Ave",
    "iso:country":"US",
    "sg:address":"850 College Ave",
    "sg:city":"Jasper",
    "sg:classifiers":[
        {
            "category":"Education",
            "subcategory":"College",
            "type":"Public Place"
        }
    ],
    "sg:phone":"+1 812 482 3030",
    "sg:postcode":"47546",
    "sg:province":"IN",
    "sg:tags":[
        "academic",
        "school"
    ],
    "wof:name":"Vincennes University",
    "wof:placetype":"venue"
},
  "geometry": {"coordinates":[-86.904878,38.373158],"type":"Point"}
}