{
  "type": "Feature",
  "properties": {
    "addr:full":"3580 25th St Columbus IN 47203",
    "addr:housenumber":"3580",
    "addr:postcode":"47203",
    "addr:street":"25Th St",
    "iso:country":"US",
    "sg:address":"3580 25th St",
    "sg:city":"Columbus",
    "sg:classifiers":[
        {
            "category":"Home & Garden",
            "subcategory":"Hardware",
            "type":"Retail Goods"
        }
    ],
    "sg:phone":"+1 812 418 0020",
    "sg:postcode":"47203",
    "sg:province":"IN",
    "wof:name":"G's Ace Hardware",
    "wof:placetype":"venue"
},
  "geometry": {"coordinates":[-85.882926,39.223398],"type":"Point"}
}