{
  "type": "Feature",
  "properties": {
    "iso:country":"US",
    "sg:address":"330 Main St",
    "sg:city":"Ferdinand",
    "sg:classifiers":[
        {
            "category":"Retail",
            "subcategory":"Auto Repair",
            "type":"Services"
        }
    ],
    "sg:phone":"+1 812 367 2851",
    "sg:postcode":"47532",
    "sg:province":"IN",
    "sg:tags":[
        "lettering",
        "truck"
    ],
    "wof:name":"Hank's Sign Co",
    "wof:placetype":"venue"
},
  "geometry": {"coordinates":[-86.863163,38.219911],"type":"Point"}
}