{
  "type": "Feature",
  "properties": {
    "iso:country":"US",
    "sg:address":"8465 Keystone Xing",
    "sg:city":"Indianapolis",
    "sg:classifiers":[
        {
            "category":"Social Services",
            "type":"Services"
        }
    ],
    "sg:phone":"+1 317 257 1505",
    "sg:postcode":"46240",
    "sg:province":"IN",
    "sg:tags":[
        "organization",
        "welfare"
    ],
    "wof:name":"Wellness Community Central In",
    "wof:placetype":"venue"
},
  "geometry": {"coordinates":[-86.115785,39.909641],"type":"Point"}
}