{
  "type": "Feature",
  "properties": {
    "iso:country":"US",
    "sg:address":"2728 W 71st St",
    "sg:city":"Indianapolis",
    "sg:classifiers":[
        {
            "category":"Restaurant",
            "type":"Food & Drink"
        }
    ],
    "sg:phone":"+1 317 334 0930",
    "sg:postcode":"46268",
    "sg:province":"IN",
    "sg:tags":[
        "seafood"
    ],
    "wof:name":"Fish N Wingz Plus",
    "wof:placetype":"venue"
},
  "geometry": {"coordinates":[-86.254738,39.881889],"type":"Point"}
}