{
  "type": "Feature",
  "properties": {
    "iso:country":"US",
    "sg:address":"1511 E Market St",
    "sg:city":"New Albany",
    "sg:classifiers":[
        {
            "category":"Social Services",
            "subcategory":"Child Care",
            "type":"Services"
        }
    ],
    "sg:phone":"+1 812 944 9270",
    "sg:postcode":"47150",
    "sg:province":"IN",
    "wof:name":"Little Adventures",
    "wof:placetype":"venue"
},
  "geometry": {"coordinates":[-85.80720599999999,38.28985],"type":"Point"}
}