{
  "type": "Feature",
  "properties": {
    "iso:country":"US",
    "sg:address":"12245 W 109th Ave",
    "sg:city":"Cedar Lake",
    "sg:classifiers":[
        {
            "category":"Social Services",
            "subcategory":"Child Care",
            "type":"Services"
        }
    ],
    "sg:phone":"+1 219 374 3611",
    "sg:postcode":"46303",
    "sg:province":"IN",
    "sg:tags":[
        "kindergarten",
        "academic",
        "school"
    ],
    "wof:name":"Geminus Headstart",
    "wof:placetype":"venue"
},
  "geometry": {"coordinates":[-87.488088,41.421124],"type":"Point"}
}