{
  "type": "Feature",
  "properties": {
    "iso:country":"US",
    "sg:address":"7174 Waldemar Dr",
    "sg:city":"Indianapolis",
    "sg:classifiers":[
        {
            "category":"Insurance",
            "subcategory":"Hazard Insurance",
            "type":"Services"
        }
    ],
    "sg:phone":"+1 317 295 9029",
    "sg:postcode":"46268",
    "sg:province":"IN",
    "sg:tags":[
        "fidelity",
        "bond"
    ],
    "wof:name":"Backstrom Mc Carley Berry & Co",
    "wof:placetype":"venue"
},
  "geometry": {"coordinates":[-86.253011,39.883281],"type":"Point"}
}