{
  "type": "Feature",
  "properties": {
    "iso:country":"US",
    "sg:address":"5915 Ellison Rd",
    "sg:city":"Fort Wayne",
    "sg:classifiers":[
        {
            "category":"Travel",
            "subcategory":"Hotels & Motels",
            "type":"Entertainment"
        }
    ],
    "sg:phone":"+1 260 459 1888",
    "sg:postcode":"46804",
    "sg:province":"IN",
    "wof:name":"Holiday Inn Express Fort Wayne",
    "wof:placetype":"venue"
},
  "geometry": {"coordinates":[-85.25544499999999,41.021718],"type":"Point"}
}