{
  "type": "Feature",
  "properties": {
    "iso:country":"US",
    "sg:address":"209 W 81st Ave",
    "sg:city":"Merrillville",
    "sg:classifiers":[
        {
            "category":"Shopping",
            "type":"Retail Goods"
        }
    ],
    "sg:phone":"+1 219 769 2381",
    "sg:postcode":"46410",
    "sg:province":"IN",
    "sg:tags":[
        "cards",
        "sport",
        "baseball",
        "memorabilia"
    ],
    "wof:name":"Collectables In K-Mart Plaza",
    "wof:placetype":"venue"
},
  "geometry": {"coordinates":[-87.338975,41.471012],"type":"Point"}
}