{
  "type": "Feature",
  "properties": {
    "iso:country":"US",
    "sg:address":"326 4th Ct W",
    "sg:city":"Carmel",
    "sg:classifiers":[
        {
            "category":"Real Estate",
            "subcategory":"Real Estate Services",
            "type":"Services"
        },
        {
            "category":"Real Estate",
            "subcategory":"Real Estate Agent",
            "type":"Services"
        }
    ],
    "sg:phone":"+1 317 846 8793",
    "sg:postcode":"46033",
    "sg:province":"IN",
    "sg:tags":[
        "buyer",
        "broker"
    ],
    "wof:name":"Barbara Coppinger",
    "wof:placetype":"venue"
},
  "geometry": {"coordinates":[-86.103078,39.98328],"type":"Point"}
}