{
  "type": "Feature",
  "properties": {
    "iso:country":"US",
    "sg:address":"6239 Allisonville Rd",
    "sg:city":"Indianapolis",
    "sg:classifiers":[
        {
            "category":"Personal",
            "type":"Services"
        }
    ],
    "sg:phone":"+1 317 255 5333",
    "sg:postcode":"46220",
    "sg:province":"IN",
    "wof:name":"McTans",
    "wof:placetype":"venue"
},
  "geometry": {"coordinates":[-86.09660700000001,39.868921],"type":"Point"}
}