{
  "type": "Feature",
  "properties": {
    "iso:country":"US",
    "sg:address":"2345 S 13th St",
    "sg:city":"Terre Haute",
    "sg:classifiers":[
        {
            "category":"Retail",
            "subcategory":"Auto Repair",
            "type":"Services"
        }
    ],
    "sg:phone":"+1 812 234 4448",
    "sg:postcode":"47802",
    "sg:province":"IN",
    "sg:tags":[
        "automobile",
        "co",
        "drive",
        "transporter"
    ],
    "sg:website":"www.ruan.com",
    "wof:name":"Ruan Transport Co",
    "wof:placetype":"venue"
},
  "geometry": {"coordinates":[-87.397703,39.441407],"type":"Point"}
}