{
  "type": "Feature",
  "properties": {
    "iso:country":"US",
    "sg:address":"820 W 17th St",
    "sg:city":"Bloomington",
    "sg:classifiers":[
        {
            "category":"Insurance",
            "subcategory":"Insurance Agent",
            "type":"Services"
        }
    ],
    "sg:phone":"+1 812 332 1408",
    "sg:postcode":"47404",
    "sg:province":"IN",
    "sg:tags":[
        "adjuster"
    ],
    "wof:name":"GAB Robins",
    "wof:placetype":"venue"
},
  "geometry": {"coordinates":[-86.54304,39.179102],"type":"Point"}
}