{
  "type": "Feature",
  "properties": {
    "iso:country":"US",
    "sg:address":"50 Commerce Dr",
    "sg:city":"Huntington",
    "sg:classifiers":[
        {
            "category":"Real Estate",
            "subcategory":"Architect",
            "type":"Services"
        }
    ],
    "sg:phone":"+1 260 356 5110",
    "sg:postcode":"46750",
    "sg:province":"IN",
    "wof:name":"Humbert & Assoc",
    "wof:placetype":"venue"
},
  "geometry": {"coordinates":[-85.519822,40.89317],"type":"Point"}
}