{
  "type": "Feature",
  "properties": {
    "iso:country":"US",
    "sg:address":"2949 E 950 N",
    "sg:city":"Attica",
    "sg:classifiers":[
        {
            "category":"Manufacturing",
            "subcategory":"Building Materials",
            "type":"Manufacturing & Wholesale Goods"
        }
    ],
    "sg:phone":"+1 765 585 0328",
    "sg:postcode":"47918",
    "sg:province":"IN",
    "sg:tags":[
        "mfg"
    ],
    "wof:name":"Swanson Woodworking",
    "wof:placetype":"venue"
},
  "geometry": {"coordinates":[-87.113291,40.265696],"type":"Point"}
}