{
  "type": "Feature",
  "properties": {
    "addr:full":"2775 Brentwood Dr Columbus IN 47203",
    "addr:housenumber":"2775",
    "addr:postcode":"47203",
    "addr:street":"Brentwood Dr",
    "iso:country":"US",
    "sg:address":"2775 Brentwood Dr",
    "sg:city":"Columbus",
    "sg:classifiers":[
        {
            "category":"Personal",
            "subcategory":"Massage",
            "type":"Services"
        },
        {
            "category":"Personal",
            "subcategory":"Beauty Salon",
            "type":"Services"
        },
        {
            "category":"Personal",
            "subcategory":"Nail Salon",
            "type":"Services"
        }
    ],
    "sg:phone":"+1 812 372 4080",
    "sg:postcode":"47203",
    "sg:province":"IN",
    "sg:tags":[
        "therapist"
    ],
    "sg:website":"http://www.cameoroomsalon.com",
    "wof:name":"Cameo Beauty Salon",
    "wof:placetype":"venue"
},
  "geometry": {"coordinates":[-85.895723,39.228402],"type":"Point"}
}