{
  "type": "Feature",
  "properties": {
    "iso:country":"US",
    "sg:address":"9004 Technology Dr",
    "sg:city":"Fishers",
    "sg:classifiers":[
        {
            "category":"Wholesale",
            "subcategory":"Electrical",
            "type":"Manufacturing & Wholesale Goods"
        }
    ],
    "sg:phone":"+1 317 849 8878",
    "sg:postcode":"46038",
    "sg:province":"IN",
    "sg:tags":[
        "control"
    ],
    "sg:website":"www.gwberkheimer.com",
    "wof:name":"G W Berkheimer Co",
    "wof:placetype":"venue"
},
  "geometry": {"coordinates":[-86.008475,39.961201],"type":"Point"}
}