{
  "type": "Feature",
  "properties": {
    "iso:country":"US",
    "sg:address":"2110 Belmar Ln",
    "sg:city":"Evansville",
    "sg:classifiers":[
        {
            "category":"Professional",
            "subcategory":"Employment Agencies",
            "type":"Services"
        }
    ],
    "sg:phone":"+1 812 428 2201",
    "sg:postcode":"47720",
    "sg:province":"IN",
    "sg:tags":[
        "help",
        "supply"
    ],
    "wof:name":"Jake H Oldham",
    "wof:placetype":"venue"
},
  "geometry": {"coordinates":[-87.58991899999999,38.033271],"type":"Point"}
}