{
  "type": "Feature",
  "properties": {
    "iso:country":"US",
    "sg:address":"2010 E 250 S",
    "sg:city":"Warsaw",
    "sg:classifiers":[
        {
            "category":"Personal",
            "subcategory":"Beauty Salon",
            "type":"Services"
        }
    ],
    "sg:phone":"+1 574 269 2014",
    "sg:postcode":"46580",
    "sg:province":"IN",
    "sg:tags":[
        "shop"
    ],
    "wof:name":"Gordy's Hair Studio",
    "wof:placetype":"venue"
},
  "geometry": {"coordinates":[-85.798875,41.198783],"type":"Point"}
}