{
  "type": "Feature",
  "properties": {
    "addr:full":"1431 Main St Hamilton IN 45013",
    "addr:housenumber":"1431",
    "addr:postcode":"45013",
    "addr:street":"Main St",
    "iso:country":"US",
    "sg:address":"1431 Main St",
    "sg:city":"Hamilton",
    "sg:classifiers":[
        {
            "category":"Food & Beverages",
            "subcategory":"Groceries & Convenience Stores",
            "type":"Retail Goods"
        }
    ],
    "sg:phone":"+1 513 000 1111",
    "sg:postcode":"45013",
    "sg:province":"IN",
    "sg:tags":[
        "grocer"
    ],
    "wof:name":"Aldi",
    "wof:placetype":"venue"
},
  "geometry": {"coordinates":[-84.59142300000001,39.421469],"type":"Point"}
}