{
  "type": "Feature",
  "properties": {
    "iso:country":"US",
    "sg:address":"1524 N Elm St",
    "sg:city":"Fairmount",
    "sg:classifiers":[
        {
            "category":"Real Estate",
            "subcategory":"Real Estate Operator",
            "type":"Services"
        }
    ],
    "sg:phone":"+1 765 948 3788",
    "sg:postcode":"46928",
    "sg:province":"IN",
    "sg:tags":[
        "mobile",
        "home",
        "community"
    ],
    "wof:name":"Elm Street Mobile Home Court",
    "wof:placetype":"venue"
},
  "geometry": {"coordinates":[-85.643883,40.429248],"type":"Point"}
}