{
  "type": "Feature",
  "properties": {
    "addr:full":"2121 Industrial Pk Rd Bloomington IN 47404",
    "addr:housenumber":"2121",
    "addr:postcode":"47404",
    "addr:street":"Industrial Pk Rd",
    "iso:country":"US",
    "sg:address":"2121 Industrial Pk Rd",
    "sg:city":"Bloomington",
    "sg:classifiers":[
        {
            "category":"Building & Trades",
            "subcategory":"Construction",
            "type":"Services"
        }
    ],
    "sg:phone":"+1 812 339 3344",
    "sg:postcode":"47404",
    "sg:province":"IN",
    "sg:tags":[
        "carpentry",
        "special",
        "contractor"
    ],
    "wof:name":"Cabinet Distributors Southe",
    "wof:placetype":"venue"
},
  "geometry": {"coordinates":[-86.57096900000001,39.174786],"type":"Point"}
}