{
  "type": "Feature",
  "properties": {
    "iso:country":"US",
    "sg:address":"114 E Co Rd 450 N",
    "sg:city":"Connersville",
    "sg:classifiers":[
        {
            "category":"Professional",
            "subcategory":"Art Services",
            "type":"Services"
        }
    ],
    "sg:phone":"+1 765 825 5490",
    "sg:postcode":"47331",
    "sg:province":"IN",
    "sg:tags":[
        "commercial",
        "design"
    ],
    "wof:name":"Double D Design",
    "wof:placetype":"venue"
},
  "geometry": {"coordinates":[-85.137495,39.708068],"type":"Point"}
}