{
  "type": "Feature",
  "properties": {
    "iso:country":"US",
    "sg:address":"13298 N Hogan Rd",
    "sg:city":"Aurora",
    "sg:classifiers":[
        {
            "category":"Organizations",
            "subcategory":"Religious Organization",
            "type":"Services"
        }
    ],
    "sg:phone":"+1 812 744 2662",
    "sg:postcode":"47001",
    "sg:province":"IN",
    "wof:name":"Hogan Hill Baptist Church",
    "wof:placetype":"venue"
},
  "geometry": {"coordinates":[-85.05148800000001,39.140507],"type":"Point"}
}