{
  "type": "Feature",
  "properties": {
    "iso:country":"US",
    "sg:address":"14895 Co Rd 200 E",
    "sg:city":"Clinton",
    "sg:classifiers":[
        {
            "category":"Organizations",
            "subcategory":"Religious Organization",
            "type":"Services"
        }
    ],
    "sg:phone":"+1 765 832 2608",
    "sg:postcode":"47842",
    "sg:province":"IN",
    "sg:tags":[
        "church"
    ],
    "wof:name":"Wayside United Meth Church",
    "wof:placetype":"venue"
},
  "geometry": {"coordinates":[-87.427297,39.666479],"type":"Point"}
}