{
  "type": "Feature",
  "properties": {
    "iso:country":"US",
    "sg:address":"2381 Pointe Pkwy",
    "sg:city":"Carmel",
    "sg:classifiers":[
        {
            "category":"Shopping",
            "subcategory":"Books",
            "type":"Retail Goods"
        }
    ],
    "sg:phone":"+1 317 843 0450",
    "sg:postcode":"46032",
    "sg:province":"IN",
    "sg:tags":[
        "dealer"
    ],
    "wof:name":"Borders Books & Music",
    "wof:placetype":"venue"
},
  "geometry": {"coordinates":[-86.118314,39.956179],"type":"Point"}
}