{
  "type": "Feature",
  "properties": {
    "iso:country":"US",
    "sg:address":"1916 Montgomery Ct",
    "sg:city":"Fort Wayne",
    "sg:classifiers":[
        {
            "category":"Professional",
            "type":"Services"
        }
    ],
    "sg:phone":"+1 260 493 1436",
    "sg:postcode":"46815",
    "sg:province":"IN",
    "sg:tags":[
        "establishment"
    ],
    "wof:name":"Taykowski TR",
    "wof:placetype":"venue"
},
  "geometry": {"coordinates":[-85.070242,41.09428],"type":"Point"}
}