{
  "type": "Feature",
  "properties": {
    "iso:country":"US",
    "sg:address":"5420 North College Ave Suite L6",
    "sg:city":"Indianapolis",
    "sg:classifiers":[
        {
            "category":"Professional",
            "subcategory":"Computer Services",
            "type":"Services"
        }
    ],
    "sg:phone":"+1 877 336 3453",
    "sg:postcode":"46032",
    "sg:province":"IN",
    "sg:tags":[
        "file-backup",
        "ftp",
        "ftp-server",
        "online-storage",
        "file-sharing",
        "internet-file-storage",
        "online-file-storage",
        "share-files-online",
        "file-upload"
    ],
    "sg:website":"http://www.smartfile.com",
    "wof:name":"SmartFile",
    "wof:placetype":"venue"
},
  "geometry": {"coordinates":[-86.12405200000001,39.935609],"type":"Point"}
}