{
  "type": "Feature",
  "properties": {
    "iso:country":"US",
    "sg:address":"655 N Calumet Ave",
    "sg:city":"Valparaiso",
    "sg:classifiers":[
        {
            "category":"Communications",
            "subcategory":"Radio Station",
            "type":"Services"
        }
    ],
    "sg:phone":"+1 219 462 0551",
    "sg:postcode":"46383",
    "sg:province":"IN",
    "sg:tags":[
        "company",
        "broadcasting"
    ],
    "wof:name":"Weigel Broadcasting Co",
    "wof:placetype":"venue"
},
  "geometry": {"coordinates":[-87.034139,41.525391],"type":"Point"}
}