{
  "type": "Feature",
  "properties": {
    "iso:country":"US",
    "sg:address":"6524 Ferguson St",
    "sg:city":"Indianapolis",
    "sg:classifiers":[
        {
            "category":"Building & Trades",
            "subcategory":"Equipment Rental",
            "type":"Services"
        }
    ],
    "sg:phone":"+1 317 251 4735",
    "sg:postcode":"46220",
    "sg:province":"IN",
    "sg:tags":[
        "leasing"
    ],
    "wof:name":"Northwestern Financial Corp",
    "wof:placetype":"venue"
},
  "geometry": {"coordinates":[-86.143663,39.875797],"type":"Point"}
}