{
  "type": "Feature",
  "properties": {
    "iso:country":"US",
    "sg:address":"116 E Stephenson St",
    "sg:city":"Marion",
    "sg:classifiers":[
        {
            "category":"Professional",
            "type":"Services"
        }
    ],
    "sg:phone":"+1 765 664 3897",
    "sg:postcode":"46952",
    "sg:province":"IN",
    "wof:name":"2245 Inc",
    "wof:placetype":"venue"
},
  "geometry": {"coordinates":[-85.655538,40.577228],"type":"Point"}
}