{
  "type": "Feature",
  "properties": {
    "iso:country":"US",
    "sg:address":"45 Vernon St",
    "sg:city":"North Vernon",
    "sg:classifiers":[
        {
            "category":"Retail",
            "subcategory":"Repair Shop",
            "type":"Services"
        }
    ],
    "sg:phone":"+1 812 346 6390",
    "sg:postcode":"47265",
    "sg:province":"IN",
    "sg:tags":[
        "jewelry"
    ],
    "wof:name":"Bobs Jewelry Store Inc",
    "wof:placetype":"venue"
},
  "geometry": {"coordinates":[-85.624258,39.001799],"type":"Point"}
}