{
  "type": "Feature",
  "properties": {
    "addr:full":"132 Lincoln Hwy W New Haven IN 46774",
    "addr:housenumber":"132",
    "addr:postcode":"46774",
    "addr:street":"Lincoln Hwy W;Haven",
    "iso:country":"US",
    "sg:address":"132 Lincoln Hwy W",
    "sg:city":"New Haven",
    "sg:classifiers":[
        {
            "category":"Insurance",
            "subcategory":"Insurance Agent",
            "type":"Services"
        }
    ],
    "sg:phone":"+1 260 493 6178",
    "sg:postcode":"46774",
    "sg:province":"IN",
    "wof:name":"Gentz Insurance",
    "wof:placetype":"venue"
},
  "geometry": {"coordinates":[-85.031425,41.070128],"type":"Point"}
}