{
  "type": "Feature",
  "properties": {
    "iso:country":"US",
    "sg:address":"3635 E Laughery Creek Rd",
    "sg:city":"Aurora",
    "sg:classifiers":[
        {
            "category":"Real Estate",
            "subcategory":"Developer",
            "type":"Services"
        }
    ],
    "sg:phone":"+1 812 926 1496",
    "sg:postcode":"47001",
    "sg:province":"IN",
    "sg:tags":[
        "cemetery"
    ],
    "wof:name":"Riverview Cemetery Ass'n",
    "wof:placetype":"venue"
},
  "geometry": {"coordinates":[-84.886553,39.029115],"type":"Point"}
}