{
  "type": "Feature",
  "properties": {
    "iso:country":"US",
    "sg:address":"4273 W 1050 N",
    "sg:city":"Macy",
    "sg:phone":"+1 574 382 3266",
    "sg:postcode":"46951",
    "sg:province":"IN",
    "sg:tags":[
        "farm",
        "corn",
        "soybean"
    ],
    "wof:name":"Willard Graham",
    "wof:placetype":"venue"
},
  "geometry": {"coordinates":[-86.154725,40.916875],"type":"Point"}
}