{
  "type": "Feature",
  "properties": {
    "iso:country":"US",
    "sg:address":"300 Washington St",
    "sg:city":"Albion",
    "sg:classifiers":[
        {
            "category":"Building & Trades",
            "subcategory":"Construction",
            "type":"Services"
        }
    ],
    "sg:phone":"+1 260 636 7757",
    "sg:postcode":"46701",
    "sg:province":"IN",
    "sg:tags":[
        "maker",
        "cabinet"
    ],
    "wof:name":"Orr Cabinetry",
    "wof:placetype":"venue"
},
  "geometry": {"coordinates":[-85.420366,41.392345],"type":"Point"}
}