{
  "type": "Feature",
  "properties": {
    "addr:full":"3220 W 16th St Indianapolis IN 46222",
    "addr:housenumber":"3220",
    "addr:postcode":"46222",
    "addr:street":"W 16Th St",
    "iso:country":"US",
    "sg:address":"3220 W 16th St",
    "sg:city":"Indianapolis",
    "sg:classifiers":[
        {
            "category":"Retail",
            "subcategory":"Auto Repair",
            "type":"Services"
        }
    ],
    "sg:phone":"+1 317 638 8845",
    "sg:postcode":"46222",
    "sg:province":"IN",
    "sg:tags":[
        "automotive",
        "carburetor"
    ],
    "wof:name":"Bob Orr Carburetor Service",
    "wof:placetype":"venue"
},
  "geometry": {"coordinates":[-86.21347299999999,39.78792],"type":"Point"}
}