{
  "type": "Feature",
  "properties": {
    "iso:country":"US",
    "sg:address":"620 Cumberland Ave",
    "sg:city":"West Lafayette",
    "sg:classifiers":[
        {
            "category":"Organizations",
            "subcategory":"Religious Organization",
            "type":"Services"
        }
    ],
    "sg:phone":"+1 765 463 3455",
    "sg:postcode":"47906",
    "sg:province":"IN",
    "sg:tags":[
        "synagogue"
    ],
    "wof:name":"Temple Israel",
    "wof:placetype":"venue"
},
  "geometry": {"coordinates":[-86.90903900000001,40.460644],"type":"Point"}
}