{
  "type": "Feature",
  "properties": {
    "iso:country":"US",
    "sg:address":"1800 Western Ave",
    "sg:city":"Bluffton",
    "sg:classifiers":[
        {
            "category":"Wholesale",
            "subcategory":"Farm Supplies",
            "type":"Manufacturing & Wholesale Goods"
        }
    ],
    "sg:phone":"+1 260 824 0079",
    "sg:postcode":"46714",
    "sg:province":"IN",
    "sg:tags":[
        "feed"
    ],
    "sg:website":"www.moreinfo.com",
    "wof:name":"Adm Alliance Nutrition",
    "wof:placetype":"venue"
},
  "geometry": {"coordinates":[-85.197188,40.731792],"type":"Point"}
}