{
  "type": "Feature",
  "properties": {
    "iso:country":"US",
    "sg:address":"11025 Timber Ln",
    "sg:city":"Carmel",
    "sg:classifiers":[
        {
            "category":"Insurance",
            "subcategory":"Insurance Agent",
            "type":"Services"
        },
        {
            "category":"Insurance",
            "subcategory":"Hazard Insurance",
            "type":"Services"
        }
    ],
    "sg:phone":"+1 317 844 6200",
    "sg:postcode":"46032",
    "sg:province":"IN",
    "sg:tags":[
        "consultant",
        "analyst"
    ],
    "wof:name":"Garry Eckard & Co Inc",
    "wof:placetype":"venue"
},
  "geometry": {"coordinates":[-86.11654,39.946827],"type":"Point"}
}