{
  "type": "Feature",
  "properties": {
    "iso:country":"US",
    "sg:address":"2850 Madison Ave",
    "sg:city":"Indianapolis",
    "sg:classifiers":[
        {
            "category":"Autos & Motor Vehicles",
            "subcategory":"Automobile Sales",
            "type":"Retail Goods"
        }
    ],
    "sg:phone":"+1 317 787 3474",
    "sg:postcode":"46225",
    "sg:province":"IN",
    "sg:tags":[
        "car",
        "dealer"
    ],
    "wof:name":"Perry Brothers Auto Sales",
    "wof:placetype":"venue"
},
  "geometry": {"coordinates":[-86.151465,39.72477],"type":"Point"}
}