{
  "type": "Feature",
  "properties": {
    "iso:country":"US",
    "sg:address":"117 E Market St",
    "sg:city":"Bluffton",
    "sg:classifiers":[
        {
            "category":"Wholesale",
            "subcategory":"Toys & Hobbies",
            "type":"Manufacturing & Wholesale Goods"
        }
    ],
    "sg:phone":"+1 260 827 0765",
    "sg:postcode":"46714",
    "sg:province":"IN",
    "sg:tags":[
        "model",
        "supply"
    ],
    "sg:website":"www.firstplacehobbies.com",
    "wof:name":"First Place Hobbies",
    "wof:placetype":"venue"
},
  "geometry": {"coordinates":[-85.171291,40.739851],"type":"Point"}
}