{
  "type": "Feature",
  "properties": {
    "iso:country":"US",
    "sg:address":"2320 Meyer Rd",
    "sg:city":"Fort Wayne",
    "sg:classifiers":[
        {
            "category":"Manufacturing",
            "subcategory":"Retail Goods",
            "type":"Manufacturing & Wholesale Goods"
        }
    ],
    "sg:phone":"+1 260 428 2650",
    "sg:postcode":"46803",
    "sg:province":"IN",
    "sg:tags":[
        "manufacturer"
    ],
    "wof:name":"Zemco Mfg Inc",
    "wof:placetype":"venue"
},
  "geometry": {"coordinates":[-85.077905,41.064721],"type":"Point"}
}