{
  "type": "Feature",
  "properties": {
    "iso:country":"US",
    "sg:address":"116 N Depot St",
    "sg:city":"Brazil",
    "sg:classifiers":[
        {
            "category":"Utilities",
            "subcategory":"Fuel Oil & Lpg",
            "type":"Services"
        }
    ],
    "sg:phone":"+1 812 448 8128",
    "sg:postcode":"47834",
    "sg:province":"IN",
    "sg:tags":[
        "coal",
        "coke"
    ],
    "wof:name":"City Coal Yard",
    "wof:placetype":"venue"
},
  "geometry": {"coordinates":[-87.13163,39.523244],"type":"Point"}
}