{
  "type": "Feature",
  "properties": {
    "addr:full":"3105 N Sherman Dr Indianapolis IN 46218",
    "addr:housenumber":"3105",
    "addr:postcode":"46218",
    "addr:street":"N Sherman Dr",
    "iso:country":"US",
    "sg:address":"3105 N Sherman Dr",
    "sg:city":"Indianapolis",
    "sg:classifiers":[
        {
            "category":"Retail",
            "subcategory":"Auto Repair",
            "type":"Services"
        }
    ],
    "sg:phone":"+1 317 536 1310",
    "sg:postcode":"46218",
    "sg:province":"IN",
    "sg:tags":[
        "repairing",
        "automobile"
    ],
    "wof:name":"Miller Auto & Towing",
    "wof:placetype":"venue"
},
  "geometry": {"coordinates":[-86.102525,39.813115],"type":"Point"}
}