{
  "type": "Feature",
  "properties": {
    "iso:country":"US",
    "sg:address":"3318 E Main St",
    "sg:city":"Richmond",
    "sg:classifiers":[
        {
            "category":"Banks & Credit Unions",
            "subcategory":"Bank",
            "type":"Services"
        }
    ],
    "sg:phone":"+1 765 966 4561",
    "sg:postcode":"47374",
    "sg:province":"IN",
    "sg:tags":[
        "financing"
    ],
    "wof:name":"Citi Financial",
    "wof:placetype":"venue"
},
  "geometry": {"coordinates":[-84.856281,39.830965],"type":"Point"}
}