{
  "type": "Feature",
  "properties": {
    "iso:country":"US",
    "sg:address":"2109 Calumet Ave",
    "sg:city":"Valparaiso",
    "sg:classifiers":[
        {
            "category":"Shopping",
            "subcategory":"Used Merchandise",
            "type":"Retail Goods"
        }
    ],
    "sg:phone":"+1 219 548 1314",
    "sg:postcode":"46383",
    "sg:province":"IN",
    "sg:tags":[
        "shop",
        "thrift"
    ],
    "sg:website":"www.goodwill.org",
    "wof:name":"Goodwill Industries",
    "wof:placetype":"venue"
},
  "geometry": {"coordinates":[-87.048744,41.48912],"type":"Point"}
}