{
  "type": "Feature",
  "properties": {
    "iso:country":"US",
    "sg:address":"1746 Willow St",
    "sg:city":"Vincennes",
    "sg:classifiers":[
        {
            "category":"Building & Trades",
            "subcategory":"Construction",
            "type":"Services"
        }
    ],
    "sg:phone":"+1 812 882 9127",
    "sg:postcode":"47591",
    "sg:province":"IN",
    "sg:tags":[
        "farm",
        "carpentry",
        "supply",
        "contractor"
    ],
    "wof:name":"Marlins Seats Carports Garages",
    "wof:placetype":"venue"
},
  "geometry": {"coordinates":[-87.530631,38.658365],"type":"Point"}
}