{
  "type": "Feature",
  "properties": {
    "iso:country":"US",
    "sg:address":"3401 N Green River Rd",
    "sg:city":"Evansville",
    "sg:classifiers":[
        {
            "category":"Shopping",
            "subcategory":"Computers & Home Electronics",
            "type":"Retail Goods"
        }
    ],
    "sg:phone":"+1 812 476 5013",
    "sg:postcode":"47715",
    "sg:province":"IN",
    "sg:tags":[
        "game",
        "video"
    ],
    "wof:name":"Mc Van's Video Games",
    "wof:placetype":"venue"
},
  "geometry": {"coordinates":[-87.492278,38.007006],"type":"Point"}
}