{
  "type": "Feature",
  "properties": {
    "addr:full":"12467 N 600 W Elwood IN 46036",
    "addr:housenumber":"12467",
    "addr:postcode":"46036",
    "addr:street":"N 600 W",
    "iso:country":"US",
    "sg:address":"12467 N 600 W",
    "sg:city":"Elwood",
    "sg:classifiers":[
        {
            "category":"Farming",
            "subcategory":"Livestock Farm",
            "type":"Manufacturing & Wholesale Goods"
        }
    ],
    "sg:phone":"+1 765 552 6315",
    "sg:postcode":"46036",
    "sg:province":"IN",
    "sg:tags":[
        "corn",
        "soybean"
    ],
    "wof:name":"Owen Murry",
    "wof:placetype":"venue"
},
  "geometry": {"coordinates":[-85.785714,40.279358],"type":"Point"}
}