{
  "type": "Feature",
  "properties": {
    "iso:country":"US",
    "sg:address":"501 E Lincoln Rd",
    "sg:city":"Kokomo",
    "sg:classifiers":[
        {
            "category":"Shopping",
            "subcategory":"Optical Goods",
            "type":"Retail Goods"
        }
    ],
    "sg:phone":"+1 765 455 1810",
    "sg:postcode":"46902",
    "sg:province":"IN",
    "wof:name":"Kokomo Optical Inc",
    "wof:placetype":"venue"
},
  "geometry": {"coordinates":[-86.12463700000001,40.455126],"type":"Point"}
}