{
  "type": "Feature",
  "properties": {
    "iso:country":"US",
    "sg:address":"58288 Co Rd 3",
    "sg:city":"Elkhart",
    "sg:classifiers":[
        {
            "category":"Manufacturing",
            "subcategory":"Metals",
            "type":"Manufacturing & Wholesale Goods"
        }
    ],
    "sg:phone":"+1 574 294 2800",
    "sg:postcode":"46517",
    "sg:province":"IN",
    "sg:tags":[
        "forming"
    ],
    "wof:name":"United Roll Forming Inc",
    "wof:placetype":"venue"
},
  "geometry": {"coordinates":[-86.022235,41.649979],"type":"Point"}
}