{
  "type": "Feature",
  "properties": {
    "iso:country":"US",
    "sg:address":"50 N Alabama St Ste E224",
    "sg:city":"Indianapolis",
    "sg:classifiers":[
        {
            "category":"Government",
            "subcategory":"Office",
            "type":"Public Place"
        }
    ],
    "sg:phone":"+1 317 327 3399",
    "sg:postcode":"46204",
    "sg:province":"IN",
    "sg:tags":[
        "township",
        "government-city",
        "village"
    ],
    "sg:website":"http://www.indybarkpark.org",
    "wof:name":"City Of Indianapolis",
    "wof:placetype":"venue"
},
  "geometry": {"coordinates":[-86.15263400000001,39.76738],"type":"Point"}
}