{
  "type": "Feature",
  "properties": {
    "addr:full":"215 W Bell St Lagrange IN 46761",
    "addr:housenumber":"215",
    "addr:postcode":"46761",
    "addr:street":"W Bell St",
    "iso:country":"US",
    "sg:address":"215 W Bell St",
    "sg:city":"Lagrange",
    "sg:classifiers":[
        {
            "category":"Social Services",
            "subcategory":"Child Care",
            "type":"Services"
        }
    ],
    "sg:phone":"+1 260 463 7008",
    "sg:postcode":"46761",
    "sg:province":"IN",
    "sg:tags":[
        "day"
    ],
    "wof:name":"Marsha Mapes",
    "wof:placetype":"venue"
},
  "geometry": {"coordinates":[-85.41915,41.637067],"type":"Point"}
}