{
  "type": "Feature",
  "properties": {
    "iso:country":"US",
    "sg:address":"101 N Main St",
    "sg:city":"Rosedale",
    "sg:classifiers":[
        {
            "category":"Autos & Motor Vehicles",
            "subcategory":"Fuel & Gas Station",
            "type":"Retail Goods"
        }
    ],
    "sg:phone":"+1 765 548 2713",
    "sg:postcode":"47874",
    "sg:province":"IN",
    "sg:tags":[
        "oil"
    ],
    "wof:name":"J T's Marathon",
    "wof:placetype":"venue"
},
  "geometry": {"coordinates":[-87.283119,39.623656],"type":"Point"}
}