{
  "type": "Feature",
  "properties": {
    "iso:country":"US",
    "sg:address":"212 E Washington Center Rd",
    "sg:city":"Fort Wayne",
    "sg:classifiers":[
        {
            "category":"Restaurant",
            "type":"Food & Drink"
        }
    ],
    "sg:phone":"+1 260 471 9669",
    "sg:postcode":"46825",
    "sg:province":"IN",
    "wof:name":"Oriental Seafood Buffet",
    "wof:placetype":"venue"
},
  "geometry": {"coordinates":[-85.136868,41.132634],"type":"Point"}
}