{
  "type": "Feature",
  "properties": {
    "iso:country":"US",
    "sg:address":"2224 E Winona Ave",
    "sg:city":"Warsaw",
    "sg:classifiers":[
        {
            "category":"Arts & Performance",
            "subcategory":"Theater",
            "type":"Entertainment"
        }
    ],
    "sg:phone":"+1 574 372 3390",
    "sg:postcode":"46580",
    "sg:province":"IN",
    "sg:tags":[
        "equipment",
        "theatrical",
        "supply"
    ],
    "wof:name":"Sereis Seating Intl",
    "wof:placetype":"venue"
},
  "geometry": {"coordinates":[-85.829203,41.233568],"type":"Point"}
}