{
  "type": "Feature",
  "properties": {
    "iso:country":"US",
    "sg:address":"7303 Broadway",
    "sg:city":"Merrillville",
    "sg:classifiers":[
        {
            "category":"Retail",
            "subcategory":"Animal Services",
            "type":"Services"
        }
    ],
    "sg:phone":"+1 219 736 6442",
    "sg:postcode":"46410",
    "sg:province":"IN",
    "sg:tags":[
        "pet",
        "grooming",
        "washing"
    ],
    "wof:name":"Canine Clipper",
    "wof:placetype":"venue"
},
  "geometry": {"coordinates":[-87.33594100000001,41.483985],"type":"Point"}
}