{
  "type": "Feature",
  "properties": {
    "addr:full":"1410 Production Rd Fort Wayne IN 46808",
    "addr:housenumber":"1410",
    "addr:postcode":"46808",
    "addr:street":"Production Rd",
    "iso:country":"US",
    "sg:address":"1410 Production Rd",
    "sg:city":"Fort Wayne",
    "sg:classifiers":[
        {
            "category":"Professional",
            "subcategory":"Business Services",
            "type":"Services"
        }
    ],
    "sg:phone":"+1 260 407 6483",
    "sg:postcode":"46808",
    "sg:province":"IN",
    "sg:tags":[
        "telecommunication"
    ],
    "wof:name":"Bbk Group  Inc",
    "wof:placetype":"venue"
},
  "geometry": {"coordinates":[-85.164631,41.12043],"type":"Point"}
}