{
  "type": "Feature",
  "properties": {
    "iso:country":"US",
    "sg:address":"1507 Grand Ave",
    "sg:city":"Washington",
    "sg:classifiers":[
        {
            "category":"Social Services",
            "subcategory":"Child Care",
            "type":"Services"
        }
    ],
    "sg:phone":"+1 812 254 7632",
    "sg:postcode":"47501",
    "sg:province":"IN",
    "wof:name":"Tenderheart Child Care Home",
    "wof:placetype":"venue"
},
  "geometry": {"coordinates":[-87.15757499999999,38.659429],"type":"Point"}
}