{
  "type": "Feature",
  "properties": {
    "iso:country":"US",
    "sg:address":"3115 Rexing Rd",
    "sg:city":"Wadesville",
    "sg:classifiers":[
        {
            "category":"Building & Trades",
            "subcategory":"Construction",
            "type":"Services"
        }
    ],
    "sg:phone":"+1 812 963 9143",
    "sg:postcode":"47638",
    "sg:province":"IN",
    "sg:tags":[
        "general",
        "contractor"
    ],
    "wof:name":"Tieken Construction Inc",
    "wof:placetype":"venue"
},
  "geometry": {"coordinates":[-87.711042,38.082546],"type":"Point"}
}