{
  "type": "Feature",
  "properties": {
    "iso:country":"US",
    "sg:address":"1902 W Ewing Ave",
    "sg:city":"South Bend",
    "sg:classifiers":[
        {
            "category":"Shopping",
            "subcategory":"Computers & Home Electronics",
            "type":"Retail Goods"
        }
    ],
    "sg:phone":"+1 574 287 1373",
    "sg:postcode":"46613",
    "sg:province":"IN",
    "sg:tags":[
        "equipment",
        "satellite",
        "system"
    ],
    "wof:name":"Digitek",
    "wof:placetype":"venue"
},
  "geometry": {"coordinates":[-86.277704,41.650241],"type":"Point"}
}