{
  "type": "Feature",
  "properties": {
    "iso:country":"US",
    "sg:address":"1401 S Holt Rd",
    "sg:city":"Indianapolis",
    "sg:classifiers":[
        {
            "category":"Real Estate",
            "subcategory":"Real Estate Agent",
            "type":"Services"
        }
    ],
    "sg:phone":"+1 317 481 8218",
    "sg:postcode":"46241",
    "sg:province":"IN",
    "sg:tags":[
        "agency",
        "rental"
    ],
    "wof:name":"Enterprise Rent-A-Truck",
    "wof:placetype":"venue"
},
  "geometry": {"coordinates":[-86.225168,39.745531],"type":"Point"}
}