{
  "type": "Feature",
  "properties": {
    "iso:country":"US",
    "sg:address":"3300 Lower Huntington Rd",
    "sg:city":"Fort Wayne",
    "sg:classifiers":[
        {
            "category":"Insurance",
            "subcategory":"Insurance Agent",
            "type":"Services"
        }
    ],
    "sg:phone":"+1 260 478 7000",
    "sg:postcode":"46809",
    "sg:province":"IN",
    "wof:name":"AFLAC",
    "wof:placetype":"venue"
},
  "geometry": {"coordinates":[-85.18127,41.018238],"type":"Point"}
}