{
  "type": "Feature",
  "properties": {
    "iso:country":"US",
    "sg:address":"1934 McDonald Ave",
    "sg:city":"New Albany",
    "sg:classifiers":[
        {
            "category":"Organizations",
            "subcategory":"Religious Organization",
            "type":"Services"
        }
    ],
    "sg:phone":"+1 812 945 7170",
    "sg:postcode":"47150",
    "sg:province":"IN",
    "wof:name":"Emmaus Road Church & Day Care",
    "wof:placetype":"venue"
},
  "geometry": {"coordinates":[-85.812004,38.310379],"type":"Point"}
}