{
  "type": "Feature",
  "properties": {
    "iso:country":"US",
    "sg:address":"10655 Jessup Blvd",
    "sg:city":"Indianapolis",
    "sg:classifiers":[
        {
            "category":"Building & Trades",
            "subcategory":"Construction",
            "type":"Services"
        }
    ],
    "sg:phone":"+1 317 848 7807",
    "sg:postcode":"46280",
    "sg:province":"IN",
    "sg:tags":[
        "contractor"
    ],
    "wof:name":"Craftsman Drywall",
    "wof:placetype":"venue"
},
  "geometry": {"coordinates":[-86.143677,39.941838],"type":"Point"}
}