{
  "type": "Feature",
  "properties": {
    "iso:country":"US",
    "sg:address":"1419 Shelby St",
    "sg:city":"Vincennes",
    "sg:classifiers":[
        {
            "category":"Social Services",
            "subcategory":"Job Training",
            "type":"Services"
        }
    ],
    "sg:phone":"+1 812 886 9578",
    "sg:postcode":"47591",
    "sg:province":"IN",
    "sg:tags":[
        "workshop"
    ],
    "wof:name":"Group Home 6",
    "wof:placetype":"venue"
},
  "geometry": {"coordinates":[-87.517039,38.67267],"type":"Point"}
}