{
  "type": "Feature",
  "properties": {
    "addr:full":"8230 Lakeshore Trail East Dr Indianapolis IN 46250",
    "addr:housenumber":"8230",
    "addr:postcode":"46250",
    "addr:street":"Lakeshore Trail East Dr",
    "iso:country":"US",
    "sg:address":"8230 Lakeshore Trail East Dr",
    "sg:city":"Indianapolis",
    "sg:classifiers":[
        {
            "category":"Recreation",
            "type":"Entertainment"
        },
        {
            "category":"Landmark",
            "subcategory":"Tourist Information",
            "type":"Public Place"
        }
    ],
    "sg:phone":"+1 518 260 6612",
    "sg:postcode":"46250",
    "sg:province":"IN",
    "sg:tags":[
        "active",
        "tour",
        "life"
    ],
    "sg:website":"www.indianapolisballoonflights.com",
    "wof:name":"SkyHigh Aerial Promotions LLC",
    "wof:placetype":"venue"
},
  "geometry": {"coordinates":[-86.085054,39.9063],"type":"Point"}
}