{
  "type": "Feature",
  "properties": {
    "iso:country":"US",
    "sg:address":"7035 E 96th St",
    "sg:city":"Indianapolis",
    "sg:classifiers":[
        {
            "category":"Shopping",
            "subcategory":"Department Store",
            "type":"Retail Goods"
        },
        {
            "category":"Home & Garden",
            "subcategory":"Household Appliances",
            "type":"Retail Goods"
        },
        {
            "category":"Building & Trades",
            "subcategory":"Cleaning & Sanitation",
            "type":"Services"
        },
        {
            "category":"Home & Garden",
            "subcategory":"Hardware",
            "type":"Retail Goods"
        },
        {
            "category":"Building & Trades",
            "subcategory":"Construction",
            "type":"Services"
        }
    ],
    "sg:phone":"+1 317 570 3910",
    "sg:postcode":"46250",
    "sg:province":"IN",
    "sg:tags":[
        "cleaner",
        "cleaners-household-dealers",
        "supply",
        "house",
        "system",
        "equipment",
        "vacuum",
        "janitor"
    ],
    "wof:name":"Cleary Vacuum",
    "wof:placetype":"venue"
},
  "geometry": {"coordinates":[-86.046038,39.927013],"type":"Point"}
}