{
  "type": "Feature",
  "properties": {
    "addr:full":"1805 Kingsley Dr Anderson IN 46011",
    "addr:housenumber":"1805",
    "addr:postcode":"46011",
    "addr:street":"Kingsley Dr",
    "iso:country":"US",
    "sg:address":"1805 Kingsley Dr",
    "sg:city":"Anderson",
    "sg:classifiers":[
        {
            "category":"Professional",
            "subcategory":"Management & Consulting",
            "type":"Services"
        }
    ],
    "sg:phone":"+1 765 643 1689",
    "sg:postcode":"46011",
    "sg:province":"IN",
    "wof:name":"Spencer P Margolin",
    "wof:placetype":"venue"
},
  "geometry": {"coordinates":[-85.702291,40.124161],"type":"Point"}
}