{
  "type": "Feature",
  "properties": {
    "iso:country":"US",
    "sg:address":"1805 Kingsley Dr",
    "sg:city":"Anderson",
    "sg:classifiers":[
        {
            "category":"Professional",
            "subcategory":"Management & Consulting",
            "type":"Services"
        }
    ],
    "sg:phone":"+1 765 643 1689",
    "sg:postcode":"46011",
    "sg:province":"IN",
    "wof:name":"Spencer P Margolin",
    "wof:placetype":"venue"
},
  "geometry": {"coordinates":[-85.702291,40.124161],"type":"Point"}
}