{
  "type": "Feature",
  "properties": {
    "iso:country":"US",
    "sg:address":"3900 E 96th St",
    "sg:city":"Indianapolis",
    "sg:classifiers":[
        {
            "category":"Autos & Motor Vehicles",
            "subcategory":"Automobile Sales",
            "type":"Retail Goods"
        },
        {
            "category":"Retail",
            "subcategory":"Auto Repair",
            "type":"Services"
        }
    ],
    "sg:phone":"+1 317 580 6800",
    "sg:postcode":"46240",
    "sg:province":"IN",
    "sg:tags":[
        "car",
        "used",
        "new"
    ],
    "sg:website":"http://indianapolis.citysearch.com/profile/external/3971929/indianapolis_in/world_wide_motors_inc_.html?publisher=yellowpages&reference_id=1&placement=ypwebsitemip",
    "wof:name":"World Wide Motors Inc",
    "wof:placetype":"venue"
},
  "geometry": {"coordinates":[-86.10549899999999,39.926899],"type":"Point"}
}