{
  "type": "Feature",
  "properties": {
    "iso:country":"US",
    "sg:address":"822 W 1st St",
    "sg:city":"Bloomington",
    "sg:classifiers":[
        {
            "category":"Health Services",
            "subcategory":"Doctor",
            "type":"Services"
        }
    ],
    "sg:phone":"+1 812 333 4327",
    "sg:postcode":"47403",
    "sg:province":"IN",
    "sg:tags":[
        "cardiologist"
    ],
    "wof:name":"Calli Louis J Jr MD",
    "wof:placetype":"venue"
},
  "geometry": {"coordinates":[-86.54249299999999,39.159457],"type":"Point"}
}