{
  "type": "Feature",
  "properties": {
    "iso:country":"US",
    "sg:address":"200 N 2nd St",
    "sg:city":"Lafayette",
    "sg:classifiers":[
        {
            "category":"Local Transit",
            "type":"Transportation"
        }
    ],
    "sg:phone":"+1 765 742 7925",
    "sg:postcode":"47901",
    "sg:province":"IN",
    "sg:tags":[
        "bus",
        "line"
    ],
    "wof:name":"Greyhound Package Express",
    "wof:placetype":"venue"
},
  "geometry": {"coordinates":[-86.89548499999999,40.42001],"type":"Point"}
}