{
  "type": "Feature",
  "properties": {
    "addr:full":"2400 Andrew Ave Laporte IN 46350",
    "addr:housenumber":"2400",
    "addr:postcode":"46350",
    "addr:street":"Andrew Ave",
    "iso:country":"US",
    "sg:address":"2400 Andrew Ave",
    "sg:city":"Laporte",
    "sg:classifiers":[
        {
            "category":"Real Estate",
            "subcategory":"Real Estate Operator",
            "type":"Services"
        }
    ],
    "sg:phone":"+1 219 362 6040",
    "sg:postcode":"46350",
    "sg:province":"IN",
    "sg:tags":[
        "apartment"
    ],
    "wof:name":"Commons",
    "wof:placetype":"venue"
},
  "geometry": {"coordinates":[-86.734145,41.583405],"type":"Point"}
}