{
  "type": "Feature",
  "properties": {
    "iso:country":"US",
    "sg:address":"2975 N Centennial St",
    "sg:city":"Indianapolis",
    "sg:classifiers":[
        {
            "category":"Personal",
            "subcategory":"Barber",
            "type":"Services"
        }
    ],
    "sg:phone":"+1 317 926 8763",
    "sg:postcode":"46222",
    "sg:province":"IN",
    "wof:name":"Hair Professionals",
    "wof:placetype":"venue"
},
  "geometry": {"coordinates":[-86.212366,39.809394],"type":"Point"}
}