{
  "type": "Feature",
  "properties": {
    "iso:country":"US",
    "sg:address":"10071 Front St",
    "sg:city":"Dillsboro",
    "sg:classifiers":[
        {
            "category":"Organizations",
            "subcategory":"Religious Organization",
            "type":"Services"
        }
    ],
    "sg:phone":"+1 812 432 5748",
    "sg:postcode":"47018",
    "sg:province":"IN",
    "sg:tags":[
        "church"
    ],
    "wof:name":"United Methodist Church",
    "wof:placetype":"venue"
},
  "geometry": {"coordinates":[-85.060817,39.018121],"type":"Point"}
}