{
  "type": "Feature",
  "properties": {
    "addr:full":"115 Parthenia Ave Brownsburg IN 46112",
    "addr:housenumber":"115",
    "addr:postcode":"46112",
    "addr:street":"Parthenia Ave",
    "iso:country":"US",
    "sg:address":"115 Parthenia Ave",
    "sg:city":"Brownsburg",
    "sg:classifiers":[
        {
            "category":"Building & Trades",
            "subcategory":"Construction",
            "type":"Services"
        }
    ],
    "sg:phone":"+1 317 852 4927",
    "sg:postcode":"46112",
    "sg:province":"IN",
    "sg:website":"www.blitzbuilders.com",
    "wof:name":"Blitz Builders Inc",
    "wof:placetype":"venue"
},
  "geometry": {"coordinates":[-86.39390899999999,39.845143],"type":"Point"}
}