{
  "type": "Feature",
  "properties": {
    "addr:full":"323 S Park St Michigan City IN 46360",
    "addr:housenumber":"323",
    "addr:postcode":"46360",
    "addr:street":"S Park St",
    "iso:country":"US",
    "sg:address":"323 S Park St",
    "sg:city":"Michigan City",
    "sg:classifiers":[
        {
            "category":"Real Estate",
            "subcategory":"Real Estate Agent",
            "type":"Services"
        }
    ],
    "sg:phone":"+1 219 872 8545",
    "sg:postcode":"46360",
    "sg:province":"IN",
    "wof:name":"Home Pro Real Estate Insp",
    "wof:placetype":"venue"
},
  "geometry": {"coordinates":[-86.89680300000001,41.690888],"type":"Point"}
}