{
  "type": "Feature",
  "properties": {
    "addr:full":"116 E Washington St Shelbyville IN 46176",
    "addr:housenumber":"116",
    "addr:postcode":"46176",
    "addr:street":"E Washington St",
    "iso:country":"US",
    "sg:address":"116 E Washington St",
    "sg:city":"Shelbyville",
    "sg:classifiers":[
        {
            "category":"Banks & Credit Unions",
            "subcategory":"Bank",
            "type":"Services"
        }
    ],
    "sg:phone":"+1 317 398 1300",
    "sg:postcode":"46176",
    "sg:province":"IN",
    "sg:tags":[
        "financing"
    ],
    "wof:name":"Personal Finance Co",
    "wof:placetype":"venue"
},
  "geometry": {"coordinates":[-85.774378,39.52451],"type":"Point"}
}