{
  "type": "Feature",
  "properties": {
    "iso:country":"US",
    "sg:address":"3454 US Hwy 6",
    "sg:city":"Waterloo",
    "sg:classifiers":[
        {
            "category":"Travel",
            "subcategory":"Hotels & Motels",
            "type":"Entertainment"
        }
    ],
    "sg:phone":"+1 260 837 2414",
    "sg:postcode":"46793",
    "sg:province":"IN",
    "wof:name":"Lighthouse Inn",
    "wof:placetype":"venue"
},
  "geometry": {"coordinates":[-85.03186,41.43533],"type":"Point"}
}