{
  "type": "Feature",
  "properties": {
    "addr:full":"104 Marks Rd Valparaiso IN 46383",
    "addr:housenumber":"104",
    "addr:postcode":"46383",
    "addr:street":"Marks Rd",
    "iso:country":"US",
    "sg:address":"104 Marks Rd",
    "sg:city":"Valparaiso",
    "sg:classifiers":[
        {
            "category":"Wholesale",
            "subcategory":"Electrical",
            "type":"Manufacturing & Wholesale Goods"
        }
    ],
    "sg:phone":"+1 219 464 3517",
    "sg:postcode":"46383",
    "sg:province":"IN",
    "sg:tags":[
        "equipment",
        "electric",
        "supply"
    ],
    "wof:name":"All-Phase Electric Supply Co",
    "wof:placetype":"venue"
},
  "geometry": {"coordinates":[-87.039169,41.469705],"type":"Point"}
}