{
  "type": "Feature",
  "properties": {
    "addr:full":"3740 E US Hwy 20 Rolling Prairie IN 46371",
    "addr:housenumber":"3740",
    "addr:postcode":"46371",
    "addr:street":"E Us Hwy 20",
    "iso:country":"US",
    "sg:address":"3740 E US Hwy 20",
    "sg:city":"Rolling Prairie",
    "sg:classifiers":[
        {
            "category":"Autos & Motor Vehicles",
            "subcategory":"Auto Supplies",
            "type":"Retail Goods"
        }
    ],
    "sg:phone":"+1 219 778 4414",
    "sg:postcode":"46371",
    "sg:province":"IN",
    "wof:name":"BJ Enterprise",
    "wof:placetype":"venue"
},
  "geometry": {"coordinates":[-86.62591500000001,41.672216],"type":"Point"}
}