{
  "type": "Feature",
  "properties": {
    "iso:country":"US",
    "sg:address":"1005 3rd St",
    "sg:city":"Osceola",
    "sg:classifiers":[
        {
            "category":"Professional",
            "subcategory":"Business Services",
            "type":"Services"
        }
    ],
    "sg:phone":"+1 574 266 7220",
    "sg:postcode":"46561",
    "sg:province":"IN",
    "sg:tags":[
        "paper",
        "lamination"
    ],
    "wof:name":"Clear Concepts",
    "wof:placetype":"venue"
},
  "geometry": {"coordinates":[-86.089093,41.660702],"type":"Point"}
}