{
  "type": "Feature",
  "properties": {
    "iso:country":"US",
    "sg:address":"720 State Rd 131",
    "sg:city":"Clarksville",
    "sg:classifiers":[
        {
            "category":"Building & Trades",
            "subcategory":"Construction",
            "type":"Services"
        }
    ],
    "sg:phone":"+1 812 288 9777",
    "sg:postcode":"47129",
    "sg:province":"IN",
    "sg:tags":[
        "designer",
        "dealer",
        "pool",
        "swimming"
    ],
    "sg:website":"www.backyardsuperstore.com",
    "wof:name":"Walnut Ridge Pool & Patio",
    "wof:placetype":"venue"
},
  "geometry": {"coordinates":[-85.76418,38.312649],"type":"Point"}
}