{
  "type": "Feature",
  "properties": {
    "addr:full":"3710 Lafayette Rd Indianapolis IN 46222",
    "addr:housenumber":"3710",
    "addr:postcode":"46222",
    "iso:country":"US",
    "sg:address":"3710 Lafayette Rd",
    "sg:city":"Indianapolis",
    "sg:classifiers":[
        {
            "category":"Personal",
            "subcategory":"Tattoo Parlor",
            "type":"Services"
        }
    ],
    "sg:phone":"+1 317 388 9679",
    "sg:postcode":"46222",
    "sg:province":"IN",
    "sg:tags":[
        "tattooing"
    ],
    "wof:name":"Needleworx",
    "wof:placetype":"venue"
},
  "geometry": {"coordinates":[-86.234831,39.823751],"type":"Point"}
}