{
  "type": "Feature",
  "properties": {
    "iso:country":"US",
    "sg:address":"101 E Washington St",
    "sg:city":"Greencastle",
    "sg:classifiers":[
        {
            "category":"Banks & Credit Unions",
            "subcategory":"Investment Brokerage",
            "type":"Services"
        }
    ],
    "sg:phone":"+1 765 653 2040",
    "sg:postcode":"46135",
    "sg:province":"IN",
    "sg:tags":[
        "stock",
        "bond"
    ],
    "wof:name":"Mid America",
    "wof:placetype":"venue"
},
  "geometry": {"coordinates":[-86.863486,39.644002],"type":"Point"}
}