{
  "type": "Feature",
  "properties": {
    "addr:full":"2811 N 6th St Vincennes IN 47591",
    "addr:housenumber":"2811",
    "addr:postcode":"47591",
    "addr:street":"N 6Th St",
    "iso:country":"US",
    "sg:address":"2811 N 6th St",
    "sg:city":"Vincennes",
    "sg:classifiers":[
        {
            "category":"Autos & Motor Vehicles",
            "subcategory":"Automobile Sales",
            "type":"Retail Goods"
        }
    ],
    "sg:phone":"+1 812 895 1111",
    "sg:postcode":"47591",
    "sg:province":"IN",
    "sg:tags":[
        "car",
        "dealer"
    ],
    "wof:name":"Vincenne's Autoplex",
    "wof:placetype":"venue"
},
  "geometry": {"coordinates":[-87.49695800000001,38.693038],"type":"Point"}
}