{
  "type": "Feature",
  "properties": {
    "addr:full":"4400 W 61st Ave Hobart IN 46342",
    "addr:housenumber":"4400",
    "addr:postcode":"46342",
    "addr:street":"W 61St Ave",
    "iso:country":"US",
    "sg:address":"4400 W 61st Ave",
    "sg:city":"Hobart",
    "sg:classifiers":[
        {
            "category":"Building & Trades",
            "subcategory":"Construction",
            "type":"Services"
        }
    ],
    "sg:phone":"+1 219 947 2470",
    "sg:postcode":"46342",
    "sg:province":"IN",
    "sg:tags":[
        "roofing",
        "contractor"
    ],
    "wof:name":"Maris & Son Roofing",
    "wof:placetype":"venue"
},
  "geometry": {"coordinates":[-87.311064,41.50736],"type":"Point"}
}