{
  "type": "Feature",
  "properties": {
    "iso:country":"US",
    "sg:address":"155 N Alabama St",
    "sg:city":"Indianapolis",
    "sg:classifiers":[
        {
            "category":"Insurance",
            "subcategory":"Hazard Insurance",
            "type":"Services"
        }
    ],
    "sg:phone":"+1 317 634 3127",
    "sg:postcode":"46204",
    "sg:province":"IN",
    "sg:tags":[
        "fidelity",
        "surety",
        "bond"
    ],
    "sg:website":"http://www.aaabailbondsinc.com",
    "wof:name":"AAA Bail Bonds Inc",
    "wof:placetype":"venue"
},
  "geometry": {"coordinates":[-86.152556,39.769158],"type":"Point"}
}