{
  "type": "Feature",
  "properties": {
    "iso:country":"US",
    "sg:address":"2354 N 300 W",
    "sg:city":"Bluffton",
    "sg:classifiers":[
        {
            "category":"Utilities",
            "subcategory":"Telephone",
            "type":"Services"
        }
    ],
    "sg:phone":"+1 260 694 6627",
    "sg:postcode":"46714",
    "sg:province":"IN",
    "sg:tags":[
        "telecommunication"
    ],
    "wof:name":"Verizon Communications",
    "wof:placetype":"venue"
},
  "geometry": {"coordinates":[-85.27998,40.783942],"type":"Point"}
}