{
  "type": "Feature",
  "properties": {
    "addr:full":"5480 S 150 W Fountaintown IN 46130",
    "addr:housenumber":"5480;150",
    "addr:postcode":"46130",
    "addr:street":"S;W",
    "iso:country":"US",
    "sg:address":"5480 S 150 W",
    "sg:city":"Fountaintown",
    "sg:classifiers":[
        {
            "category":"Building & Trades",
            "subcategory":"Construction",
            "type":"Services"
        }
    ],
    "sg:phone":"+1 317 861 5908",
    "sg:postcode":"46130",
    "sg:province":"IN",
    "sg:tags":[
        "residential"
    ],
    "wof:name":"All Type Home Repair",
    "wof:placetype":"venue"
},
  "geometry": {"coordinates":[-85.82849,39.705231],"type":"Point"}
}