{
  "type": "Feature",
  "properties": {
    "iso:country":"US",
    "sg:address":"710 Hanover St",
    "sg:city":"Fort Wayne",
    "sg:classifiers":[
        {
            "category":"Manufacturing",
            "subcategory":"Metals",
            "type":"Manufacturing & Wholesale Goods"
        }
    ],
    "sg:phone":"+1 260 422 4448",
    "sg:postcode":"46803",
    "sg:province":"IN",
    "sg:tags":[
        "steel"
    ],
    "wof:name":"Precision Fabrication Inc",
    "wof:placetype":"venue"
},
  "geometry": {"coordinates":[-85.118607,41.08116],"type":"Point"}
}