{
  "type": "Feature",
  "properties": {
    "addr:full":"3310 E 10th St Jeffersonville IN 47130",
    "addr:housenumber":"3310",
    "addr:postcode":"47130",
    "addr:street":"E 10Th St",
    "iso:country":"US",
    "sg:address":"3310 E 10th St",
    "sg:city":"Jeffersonville",
    "sg:classifiers":[
        {
            "category":"Restaurant",
            "type":"Food & Drink"
        }
    ],
    "sg:menulink":"http://www.allmenus.com/in/jeffersonville/90085-penn-station/menu/",
    "sg:phone":"+1 812 218 8400",
    "sg:postcode":"47130",
    "sg:province":"IN",
    "sg:tags":[
        "wrap",
        "american",
        "sandwich"
    ],
    "wof:name":"Penn Station",
    "wof:placetype":"venue"
},
  "geometry": {"coordinates":[-85.711446,38.32839],"type":"Point"}
}