{
  "type": "Feature",
  "properties": {
    "iso:country":"US",
    "sg:address":"1046 US Hwy 27 N",
    "sg:city":"Berne",
    "sg:classifiers":[
        {
            "category":"Professional",
            "subcategory":"Accounting & Tax Preparation",
            "type":"Services"
        }
    ],
    "sg:phone":"+1 260 589 2120",
    "sg:postcode":"46711",
    "sg:province":"IN",
    "sg:tags":[
        "accountant"
    ],
    "wof:name":"S & S Accounting Inc",
    "wof:placetype":"venue"
},
  "geometry": {"coordinates":[-84.955506,40.666346],"type":"Point"}
}