{
  "type": "Feature",
  "properties": {
    "iso:country":"US",
    "sg:address":"3288 N 600 W",
    "sg:city":"Greenfield",
    "sg:classifiers":[
        {
            "category":"Government",
            "subcategory":"Fire Station",
            "type":"Public Place"
        }
    ],
    "sg:phone":"+1 317 894 4564",
    "sg:postcode":"46140",
    "sg:province":"IN",
    "sg:tags":[
        "department"
    ],
    "wof:name":"Buck Creek Twp Fire Dept",
    "wof:placetype":"venue"
},
  "geometry": {"coordinates":[-85.915278,39.830816],"type":"Point"}
}