{
  "type": "Feature",
  "properties": {
    "iso:country":"US",
    "sg:address":"6886 Hwy 237",
    "sg:city":"Cannelton",
    "sg:classifiers":[
        {
            "category":"Building & Trades",
            "subcategory":"Equipment Rental",
            "type":"Services"
        }
    ],
    "sg:phone":"+1 812 547 0933",
    "sg:postcode":"47520",
    "sg:province":"IN",
    "sg:tags":[
        "leasing"
    ],
    "wof:name":"Twin Cities Equipment Rentals",
    "wof:placetype":"venue"
},
  "geometry": {"coordinates":[-86.74332699999999,37.919658],"type":"Point"}
}