{
  "type": "Feature",
  "properties": {
    "iso:country":"US",
    "sg:address":"1825 Meridian St",
    "sg:city":"Anderson",
    "sg:classifiers":[
        {
            "category":"Restaurant",
            "type":"Food & Drink"
        }
    ],
    "sg:phone":"+1 765 641 0234",
    "sg:postcode":"46016",
    "sg:province":"IN",
    "wof:name":"Pizza King",
    "wof:placetype":"venue"
},
  "geometry": {"coordinates":[-85.67921,40.097593],"type":"Point"}
}