{
  "type": "Feature",
  "properties": {
    "iso:country":"US",
    "sg:address":"1110 Edgewater Beach Rd",
    "sg:city":"Valparaiso",
    "sg:classifiers":[
        {
            "category":"Manufacturing",
            "subcategory":"Soap",
            "type":"Manufacturing & Wholesale Goods"
        }
    ],
    "sg:phone":"+1 219 476 1757",
    "sg:postcode":"46383",
    "sg:province":"IN",
    "sg:tags":[
        "detergent"
    ],
    "wof:name":"Edgewater Cottages",
    "wof:placetype":"venue"
},
  "geometry": {"coordinates":[-87.047144,41.516169],"type":"Point"}
}