{
  "type": "Feature",
  "properties": {
    "iso:country":"US",
    "sg:address":"3333 Fenbrook Ct",
    "sg:city":"Evansville",
    "sg:classifiers":[
        {
            "category":"Freight",
            "type":"Transportation"
        }
    ],
    "sg:phone":"+1 812 401 6190",
    "sg:postcode":"47725",
    "sg:province":"IN",
    "sg:tags":[
        "operator",
        "local",
        "trucking"
    ],
    "wof:name":"Jls Trucking Inc",
    "wof:placetype":"venue"
},
  "geometry": {"coordinates":[-87.508187,38.042917],"type":"Point"}
}