{
  "type": "Feature",
  "properties": {
    "iso:country":"US",
    "sg:address":"3616 Holmans Ln",
    "sg:city":"Jeffersonville",
    "sg:classifiers":[
        {
            "category":"Health Services",
            "subcategory":"Chiropractor",
            "type":"Services"
        }
    ],
    "sg:phone":"+1 812 288 4660",
    "sg:postcode":"47130",
    "sg:province":"IN",
    "wof:name":"Howard Chiropractic",
    "wof:placetype":"venue"
},
  "geometry": {"coordinates":[-85.722527,38.333261],"type":"Point"}
}