{
  "type": "Feature",
  "properties": {
    "addr:full":"5050 E Mojunkin St Columbia City IN 46725",
    "addr:housenumber":"5050",
    "addr:postcode":"46725",
    "addr:street":"E Mojunkin St",
    "iso:country":"US",
    "sg:address":"5050 E Mojunkin St",
    "sg:city":"Columbia City",
    "sg:classifiers":[
        {
            "category":"Government",
            "subcategory":"Fire Station",
            "type":"Public Place"
        }
    ],
    "sg:phone":"+1 260 000 1111",
    "sg:postcode":"46725",
    "sg:province":"IN",
    "sg:tags":[
        "department"
    ],
    "wof:name":"Union Twp Fire Dept",
    "wof:placetype":"venue"
},
  "geometry": {"coordinates":[-85.396976,41.128215],"type":"Point"}
}