{
  "type": "Feature",
  "properties": {
    "addr:full":"125 S Mill St Mishawaka IN 46544",
    "addr:housenumber":"125",
    "addr:postcode":"46544",
    "addr:street":"S Mill St",
    "iso:country":"US",
    "sg:address":"125 S Mill St",
    "sg:city":"Mishawaka",
    "sg:classifiers":[
        {
            "category":"Banks & Credit Unions",
            "subcategory":"Bank",
            "type":"Services"
        }
    ],
    "sg:phone":"+1 574 256 2361",
    "sg:postcode":"46544",
    "sg:province":"IN",
    "wof:name":"Notre Dame Federal CU",
    "wof:placetype":"venue"
},
  "geometry": {"coordinates":[-86.18207,41.660348],"type":"Point"}
}