{
  "type": "Feature",
  "properties": {
    "iso:country":"US",
    "sg:address":"207 E 3rd St",
    "sg:city":"Sheridan",
    "sg:classifiers":[
        {
            "category":"Organizations",
            "subcategory":"Religious Organization",
            "type":"Services"
        }
    ],
    "sg:phone":"+1 317 758 4239",
    "sg:postcode":"46069",
    "sg:province":"IN",
    "sg:tags":[
        "church"
    ],
    "wof:name":"Sheridan Wesleyan Church",
    "wof:placetype":"venue"
},
  "geometry": {"coordinates":[-86.219375,40.136244],"type":"Point"}
}