{
  "type": "Feature",
  "properties": {
    "iso:country":"US",
    "sg:address":"624 S Green River Rd",
    "sg:city":"Evansville",
    "sg:classifiers":[
        {
            "category":"Shopping",
            "subcategory":"Books",
            "type":"Retail Goods"
        }
    ],
    "sg:phone":"+1 812 475 1054",
    "sg:postcode":"47715",
    "sg:province":"IN",
    "wof:name":"Barnes & Noble",
    "wof:placetype":"venue"
},
  "geometry": {"coordinates":[-87.492586,37.968346],"type":"Point"}
}