{
  "type": "Feature",
  "properties": {
    "iso:country":"US",
    "sg:address":"7460 N Shadeland Ave",
    "sg:city":"Indianapolis",
    "sg:classifiers":[
        {
            "category":"Personal",
            "subcategory":"Barber",
            "type":"Services"
        }
    ],
    "sg:phone":"+1 317 813 0989",
    "sg:postcode":"46250",
    "sg:province":"IN",
    "wof:name":"Big League Barbers",
    "wof:placetype":"venue"
},
  "geometry": {"coordinates":[-86.046171,39.888505],"type":"Point"}
}