{
  "type": "Feature",
  "properties": {
    "iso:country":"US",
    "sg:address":"425 E Center Rd",
    "sg:city":"Kokomo",
    "sg:classifiers":[
        {
            "category":"Professional",
            "subcategory":"Business Services",
            "type":"Services"
        }
    ],
    "sg:phone":"+1 765 455 3775",
    "sg:postcode":"46902",
    "sg:province":"IN",
    "sg:tags":[
        "water",
        "treatment"
    ],
    "wof:name":"Hague Quality Water",
    "wof:placetype":"venue"
},
  "geometry": {"coordinates":[-86.126216,40.433363],"type":"Point"}
}