{
  "type": "Feature",
  "properties": {
    "iso:country":"US",
    "sg:address":"4700 N Post Rd",
    "sg:city":"Lawrence",
    "sg:classifiers":[
        {
            "category":"Recreation",
            "type":"Entertainment"
        }
    ],
    "sg:phone":"+1 317 895 7866",
    "sg:postcode":"46226",
    "sg:province":"IN",
    "sg:tags":[
        "center"
    ],
    "wof:name":"Post Road Recreation Ctr",
    "wof:placetype":"venue"
},
  "geometry": {"coordinates":[-86.010241,39.844463],"type":"Point"}
}