{
  "type": "Feature",
  "properties": {
    "iso:country":"US",
    "sg:address":"11050 Keeler Rd",
    "sg:city":"Brookville",
    "sg:classifiers":[
        {
            "category":"Government",
            "subcategory":"Office",
            "type":"Public Place"
        }
    ],
    "sg:phone":"+1 765 647 5835",
    "sg:postcode":"47012",
    "sg:province":"IN",
    "wof:name":"Conservation Officers",
    "wof:placetype":"venue"
},
  "geometry": {"coordinates":[-85.015035,39.450998],"type":"Point"}
}