{
  "type": "Feature",
  "properties": {
    "iso:country":"US",
    "sg:address":"4350 E 550 N",
    "sg:city":"Decatur",
    "sg:classifiers":[
        {
            "category":"Real Estate",
            "subcategory":"Surveying",
            "type":"Services"
        }
    ],
    "sg:phone":"+1 260 724 8787",
    "sg:postcode":"46733",
    "sg:province":"IN",
    "sg:tags":[
        "surveyor"
    ],
    "wof:name":"Wemhoff's Land Surveying",
    "wof:placetype":"venue"
},
  "geometry": {"coordinates":[-84.854829,40.82646],"type":"Point"}
}