{
  "type": "Feature",
  "properties": {
    "iso:country":"US",
    "sg:address":"2110 Carew St",
    "sg:city":"Fort Wayne",
    "sg:classifiers":[
        {
            "category":"Health Services",
            "subcategory":"Medical Lab",
            "type":"Services"
        }
    ],
    "sg:phone":"+1 260 483 9127",
    "sg:postcode":"46805",
    "sg:province":"IN",
    "sg:tags":[
        "x"
    ],
    "wof:name":"Fort Wayne Radiology Mri Ctr",
    "wof:placetype":"venue"
},
  "geometry": {"coordinates":[-85.108162,41.09697],"type":"Point"}
}