{
  "type": "Feature",
  "properties": {
    "addr:full":"2051 E Commercial Ave Lowell IN 46356",
    "addr:housenumber":"2051",
    "addr:postcode":"46356",
    "addr:street":"E Commercial Ave",
    "iso:country":"US",
    "sg:address":"2051 E Commercial Ave",
    "sg:city":"Lowell",
    "sg:classifiers":[
        {
            "category":"Education",
            "subcategory":"School",
            "type":"Public Place"
        }
    ],
    "sg:phone":"+1 219 696 7733",
    "sg:postcode":"46356",
    "sg:province":"IN",
    "sg:tags":[
        "high",
        "middle",
        "elementary"
    ],
    "wof:name":"Schools Public",
    "wof:placetype":"venue"
},
  "geometry": {"coordinates":[-87.391537,41.289935],"type":"Point"}
}