{
  "type": "Feature",
  "properties": {
    "iso:country":"US",
    "sg:address":"5005 Bluffton Rd",
    "sg:city":"Fort Wayne",
    "sg:classifiers":[
        {
            "category":"Banks & Credit Unions",
            "subcategory":"Bank",
            "type":"Services"
        }
    ],
    "sg:phone":"+1 260 747 2245",
    "sg:postcode":"46809",
    "sg:province":"IN",
    "wof:name":"Three Rivers Federal Credit",
    "wof:placetype":"venue"
},
  "geometry": {"coordinates":[-85.166551,41.038697],"type":"Point"}
}