{
  "type": "Feature",
  "properties": {
    "iso:country":"US",
    "sg:address":"3300 16th St",
    "sg:city":"Bedford",
    "sg:classifiers":[
        {
            "category":"Building & Trades",
            "subcategory":"Construction",
            "type":"Services"
        }
    ],
    "sg:phone":"+1 812 277 8159",
    "sg:postcode":"47421",
    "sg:province":"IN",
    "sg:tags":[
        "home",
        "improvement"
    ],
    "wof:name":"Lowe's",
    "wof:placetype":"venue"
},
  "geometry": {"coordinates":[-86.51732199999999,38.860957],"type":"Point"}
}