{
  "type": "Feature",
  "properties": {
    "iso:country":"US",
    "sg:address":"16908 Cable Trl",
    "sg:city":"Fort Wayne",
    "sg:classifiers":[
        {
            "category":"Communications",
            "subcategory":"Film & Video Production",
            "type":"Services"
        }
    ],
    "sg:phone":"+1 260 637 1713",
    "sg:postcode":"46845",
    "sg:province":"IN",
    "sg:tags":[
        "motion",
        "picture"
    ],
    "wof:name":"Jay Winans Freelance",
    "wof:placetype":"venue"
},
  "geometry": {"coordinates":[-85.12338099999999,41.240819],"type":"Point"}
}