{
  "type": "Feature",
  "properties": {
    "iso:country":"US",
    "sg:address":"421 Read St",
    "sg:city":"Evansville",
    "sg:classifiers":[
        {
            "category":"Bars & Pubs",
            "type":"Food & Drink"
        }
    ],
    "sg:phone":"+1 812 423 8040",
    "sg:postcode":"47710",
    "sg:province":"IN",
    "wof:name":"Fred's Bar & Grill",
    "wof:placetype":"venue"
},
  "geometry": {"coordinates":[-87.568362,37.981878],"type":"Point"}
}