{
  "type": "Feature",
  "properties": {
    "addr:full":"5111 E State Rd 45 Bloomington IN 47408",
    "addr:housenumber":"5111;45",
    "addr:postcode":"47408",
    "addr:street":"E State Rd",
    "iso:country":"US",
    "sg:address":"5111 E State Rd 45",
    "sg:city":"Bloomington",
    "sg:classifiers":[
        {
            "category":"Autos & Motor Vehicles",
            "subcategory":"Recreational Vehicle Sales",
            "type":"Retail Goods"
        }
    ],
    "sg:phone":"+1 812 332 7442",
    "sg:postcode":"47408",
    "sg:province":"IN",
    "sg:website":"www.alexanderscampersales.com",
    "wof:name":"Alexander's Camper Sales",
    "wof:placetype":"venue"
},
  "geometry": {"coordinates":[-86.46813299999999,39.187194],"type":"Point"}
}