{
  "type": "Feature",
  "properties": {
    "iso:country":"US",
    "sg:address":"2510 E Co Rd 1050 S",
    "sg:city":"Cloverdale",
    "sg:classifiers":[
        {
            "category":"Building & Trades",
            "subcategory":"Electrical",
            "type":"Services"
        }
    ],
    "sg:phone":"+1 765 795 4944",
    "sg:postcode":"46120",
    "sg:province":"IN",
    "sg:tags":[
        "electric",
        "contractor"
    ],
    "wof:name":"Haltom Electric Inc",
    "wof:placetype":"venue"
},
  "geometry": {"coordinates":[-86.807442,39.506504],"type":"Point"}
}