{
  "type": "Feature",
  "properties": {
    "iso:country":"US",
    "sg:address":"586 Fayette St",
    "sg:city":"Hammond",
    "sg:classifiers":[
        {
            "category":"Building & Trades",
            "subcategory":"Plumbing",
            "type":"Services"
        }
    ],
    "sg:phone":"+1 219 931 1073",
    "sg:postcode":"46320",
    "sg:province":"IN",
    "sg:tags":[
        "heating",
        "contractor"
    ],
    "wof:name":"Budd The Furnace Man & Sons",
    "wof:placetype":"venue"
},
  "geometry": {"coordinates":[-87.514806,41.615823],"type":"Point"}
}