{
  "type": "Feature",
  "properties": {
    "addr:full":"754 Barry Knoll St Danville IN 46122",
    "addr:housenumber":"754",
    "addr:postcode":"46122",
    "addr:street":"Barry Knoll St",
    "iso:country":"US",
    "sg:address":"754 Barry Knoll St",
    "sg:city":"Danville",
    "sg:classifiers":[
        {
            "category":"Real Estate",
            "subcategory":"Real Estate Agent",
            "type":"Services"
        }
    ],
    "sg:phone":"+1 317 745 2849",
    "sg:postcode":"46122",
    "sg:province":"IN",
    "wof:name":"Kristen Cooney",
    "wof:placetype":"venue"
},
  "geometry": {"coordinates":[-86.53222,39.753591],"type":"Point"}
}