{
  "type": "Feature",
  "properties": {
    "iso:country":"US",
    "sg:address":"617 State Rd 131",
    "sg:city":"Clarksville",
    "sg:classifiers":[
        {
            "category":"Food & Beverages",
            "subcategory":"Liquor & Beverages",
            "type":"Retail Goods"
        }
    ],
    "sg:phone":"+1 812 283 3988",
    "sg:postcode":"47129",
    "sg:province":"IN",
    "wof:name":"Keg",
    "wof:placetype":"venue"
},
  "geometry": {"coordinates":[-85.76687,38.31109],"type":"Point"}
}