{
  "type": "Feature",
  "properties": {
    "addr:full":"3287 N 300 E Huntington IN 46750",
    "addr:housenumber":"3287",
    "addr:postcode":"46750",
    "addr:street":"N 300 E Huntington",
    "iso:country":"US",
    "sg:address":"3287 N 300 E",
    "sg:city":"Huntington",
    "sg:classifiers":[
        {
            "category":"Professional",
            "type":"Services"
        }
    ],
    "sg:phone":"+1 260 758 3485",
    "sg:postcode":"46750",
    "sg:province":"IN",
    "wof:name":"Danron Inc",
    "wof:placetype":"venue"
},
  "geometry": {"coordinates":[-85.394014,40.876573],"type":"Point"}
}