{
  "type": "Feature",
  "properties": {
    "iso:country":"US",
    "sg:address":"8611 Legion Ln",
    "sg:city":"Indianapolis",
    "sg:classifiers":[
        {
            "category":"Wholesale",
            "subcategory":"Non-durable Goods",
            "type":"Manufacturing & Wholesale Goods"
        }
    ],
    "sg:phone":"+1 317 440 4409",
    "sg:postcode":"46231",
    "sg:province":"IN",
    "wof:name":"Skys Country Cottage",
    "wof:placetype":"venue"
},
  "geometry": {"coordinates":[-86.315332,39.753419],"type":"Point"}
}