{
  "type": "Feature",
  "properties": {
    "iso:country":"US",
    "sg:address":"6444 Venice Dr",
    "sg:city":"Newburgh",
    "sg:classifiers":[
        {
            "category":"Professional",
            "subcategory":"Management & Consulting",
            "type":"Services"
        }
    ],
    "sg:phone":"+1 812 858 3791",
    "sg:postcode":"47630",
    "sg:province":"IN",
    "sg:tags":[
        "business"
    ],
    "wof:name":"Global Packaging Resource",
    "wof:placetype":"venue"
},
  "geometry": {"coordinates":[-87.369037,38.001553],"type":"Point"}
}