{
  "type": "Feature",
  "properties": {
    "iso:country":"US",
    "sg:address":"9 N Jackson St",
    "sg:city":"Frankfort",
    "sg:classifiers":[
        {
            "category":"Education",
            "subcategory":"Special Training",
            "type":"Public Place"
        }
    ],
    "sg:phone":"+1 765 654 9505",
    "sg:postcode":"46041",
    "sg:province":"IN",
    "sg:tags":[
        "center"
    ],
    "wof:name":"Frankfort Adult Learning Ctr",
    "wof:placetype":"venue"
},
  "geometry": {"coordinates":[-86.510628,40.281548],"type":"Point"}
}