{
  "type": "Feature",
  "properties": {
    "addr:full":"1718 E Havens St Kokomo IN 46901",
    "addr:housenumber":"1718",
    "addr:postcode":"46901",
    "addr:street":"E Havens St",
    "iso:country":"US",
    "sg:address":"1718 E Havens St",
    "sg:city":"Kokomo",
    "sg:classifiers":[
        {
            "category":"Autos & Motor Vehicles",
            "subcategory":"Auto Supplies",
            "type":"Retail Goods"
        }
    ],
    "sg:phone":"+1 765 457 7274",
    "sg:postcode":"46901",
    "sg:province":"IN",
    "sg:tags":[
        "tire"
    ],
    "wof:name":"Fouts Tire Auto Svc",
    "wof:placetype":"venue"
},
  "geometry": {"coordinates":[-86.107933,40.495501],"type":"Point"}
}