{
  "type": "Feature",
  "properties": {
    "iso:country":"US",
    "sg:address":"714 Penn Dr",
    "sg:city":"Crawfordsville",
    "sg:classifiers":[
        {
            "category":"Social Services",
            "subcategory":"Job Training",
            "type":"Services"
        }
    ],
    "sg:phone":"+1 765 364 0500",
    "sg:postcode":"47933",
    "sg:province":"IN",
    "sg:tags":[
        "retardation",
        "disabled",
        "mental",
        "dev"
    ],
    "wof:name":"Pennhall",
    "wof:placetype":"venue"
},
  "geometry": {"coordinates":[-86.88591700000001,40.048243],"type":"Point"}
}