{
  "type": "Feature",
  "properties": {
    "iso:country":"US",
    "sg:address":"5560 Shelby St",
    "sg:city":"Indianapolis",
    "sg:classifiers":[
        {
            "category":"Organizations",
            "subcategory":"Religious Organization",
            "type":"Services"
        }
    ],
    "sg:phone":"+1 317 787 5595",
    "sg:postcode":"46227",
    "sg:province":"IN",
    "wof:name":"Tallwood Chapel Cmnty Chrch",
    "wof:placetype":"venue"
},
  "geometry": {"coordinates":[-86.13955,39.685798],"type":"Point"}
}