{
  "type": "Feature",
  "properties": {
    "iso:country":"US",
    "sg:address":"2508 Western Ave",
    "sg:city":"Connersville",
    "sg:classifiers":[
        {
            "category":"Autos & Motor Vehicles",
            "subcategory":"Auto Supplies",
            "type":"Retail Goods"
        }
    ],
    "sg:phone":"+1 765 825 6524",
    "sg:postcode":"47331",
    "sg:province":"IN",
    "sg:tags":[
        "battery"
    ],
    "wof:name":"NAPA Auto Parts",
    "wof:placetype":"venue"
},
  "geometry": {"coordinates":[-85.138609,39.666132],"type":"Point"}
}