{
  "type": "Feature",
  "properties": {
    "iso:country":"US",
    "sg:address":"5491 E Kings Rd",
    "sg:city":"Bloomington",
    "sg:classifiers":[
        {
            "category":"Manufacturing",
            "subcategory":"Printing",
            "type":"Manufacturing & Wholesale Goods"
        }
    ],
    "sg:phone":"+1 812 335 8422",
    "sg:postcode":"47408",
    "sg:province":"IN",
    "sg:tags":[
        "publisher"
    ],
    "wof:name":"Hold The Toast Press",
    "wof:placetype":"venue"
},
  "geometry": {"coordinates":[-86.455026,39.167247],"type":"Point"}
}