{
  "type": "Feature",
  "properties": {
    "iso:country":"US",
    "sg:address":"423 S 11th St",
    "sg:city":"New Castle",
    "sg:classifiers":[
        {
            "category":"Organizations",
            "subcategory":"Religious Organization",
            "type":"Services"
        }
    ],
    "sg:phone":"+1 765 529 8757",
    "sg:postcode":"47362",
    "sg:province":"IN",
    "sg:tags":[
        "church"
    ],
    "wof:name":"New Castle Church Of Christ",
    "wof:placetype":"venue"
},
  "geometry": {"coordinates":[-85.37307300000001,39.928607],"type":"Point"}
}