{
  "type": "Feature",
  "properties": {
    "iso:country":"US",
    "sg:address":"101 NW 1st St",
    "sg:city":"Evansville",
    "sg:classifiers":[
        {
            "category":"Personal",
            "subcategory":"Barber",
            "type":"Services"
        }
    ],
    "sg:phone":"+1 812 422 5263",
    "sg:postcode":"47708",
    "sg:province":"IN",
    "wof:name":"Old Post Office Barbers",
    "wof:placetype":"venue"
},
  "geometry": {"coordinates":[-87.575715,37.971584],"type":"Point"}
}