{
  "type": "Feature",
  "properties": {
    "iso:country":"US",
    "sg:address":"3333 N Franklin Rd",
    "sg:city":"Indianapolis",
    "sg:classifiers":[
        {
            "category":"Freight",
            "type":"Transportation"
        }
    ],
    "sg:phone":"+1 317 895 9506",
    "sg:postcode":"46226",
    "sg:province":"IN",
    "sg:tags":[
        "warehouse",
        "self",
        "storage"
    ],
    "wof:name":"Power Logistics",
    "wof:placetype":"venue"
},
  "geometry": {"coordinates":[-86.026769,39.818356],"type":"Point"}
}