{
  "type": "Feature",
  "properties": {
    "addr:full":"6287 N 600 W Lake Village IN 46349",
    "addr:housenumber":"6287",
    "addr:postcode":"46349",
    "addr:street":"N 600 W Lake Village",
    "iso:country":"US",
    "sg:address":"6287 N 600 W",
    "sg:city":"Lake Village",
    "sg:classifiers":[
        {
            "category":"Retail",
            "subcategory":"Repair Shop",
            "type":"Services"
        }
    ],
    "sg:phone":"+1 219 992 9746",
    "sg:postcode":"46349",
    "sg:province":"IN",
    "wof:name":"Site Rite Inc",
    "wof:placetype":"venue"
},
  "geometry": {"coordinates":[-87.50612099999999,41.087806],"type":"Point"}
}