{
  "type": "Feature",
  "properties": {
    "iso:country":"US",
    "sg:address":"121 W Plymouth St",
    "sg:city":"Bremen",
    "sg:classifiers":[
        {
            "category":"Government",
            "subcategory":"Office",
            "type":"Public Place"
        }
    ],
    "sg:phone":"+1 574 546 4823",
    "sg:postcode":"46506",
    "sg:province":"IN",
    "sg:tags":[
        "village"
    ],
    "wof:name":"German Township Trustee",
    "wof:placetype":"venue"
},
  "geometry": {"coordinates":[-86.147462,41.446607],"type":"Point"}
}