{
  "type": "Feature",
  "properties": {
    "iso:country":"US",
    "sg:address":"820 S Main St",
    "sg:city":"Princeton",
    "sg:classifiers":[
        {
            "category":"Autos & Motor Vehicles",
            "subcategory":"Automobile Sales",
            "type":"Retail Goods"
        }
    ],
    "sg:phone":"+1 812 386 8282",
    "sg:postcode":"47670",
    "sg:province":"IN",
    "sg:tags":[
        "car",
        "dealer"
    ],
    "wof:name":"Princeton Auto Parke",
    "wof:placetype":"venue"
},
  "geometry": {"coordinates":[-87.567601,38.347815],"type":"Point"}
}