{
  "type": "Feature",
  "properties": {
    "iso:country":"US",
    "sg:address":"8844 Indianapolis Blvd",
    "sg:city":"Highland",
    "sg:classifiers":[
        {
            "category":"Banks & Credit Unions",
            "subcategory":"Bank",
            "type":"Services"
        }
    ],
    "sg:phone":"+1 219 972 0100",
    "sg:postcode":"46373",
    "sg:province":"IN",
    "sg:tags":[
        "loan",
        "real estate"
    ],
    "wof:name":"Mortgage One",
    "wof:placetype":"venue"
},
  "geometry": {"coordinates":[-87.470406,41.460522],"type":"Point"}
}