{
  "type": "Feature",
  "properties": {
    "iso:country":"US",
    "sg:address":"749 W 450 N",
    "sg:city":"Rochester",
    "sg:classifiers":[
        {
            "category":"Personal",
            "subcategory":"Beauty Salon",
            "type":"Services"
        }
    ],
    "sg:phone":"+1 574 223 2036",
    "sg:postcode":"46975",
    "sg:province":"IN",
    "wof:name":"Joan Bowen Beauty Shop",
    "wof:placetype":"venue"
},
  "geometry": {"coordinates":[-86.25797900000001,41.120445],"type":"Point"}
}