{
  "type": "Feature",
  "properties": {
    "addr:full":"8500 Broadway Merrillville IN 46410",
    "addr:housenumber":"8500",
    "addr:postcode":"46410",
    "addr:street":"Broadway",
    "iso:country":"US",
    "sg:address":"8500 Broadway",
    "sg:city":"Merrillville",
    "sg:classifiers":[
        {
            "category":"Shopping",
            "type":"Retail Goods"
        }
    ],
    "sg:phone":"+1 219 924 7311",
    "sg:postcode":"46410",
    "sg:province":"IN",
    "sg:tags":[
        "hearing",
        "equipment",
        "supply",
        "impaired"
    ],
    "wof:name":"Dr Smith's Family Hearing Ctr",
    "wof:placetype":"venue"
},
  "geometry": {"coordinates":[-87.335972,41.463335],"type":"Point"}
}