{
  "type": "Feature",
  "properties": {
    "iso:country":"US",
    "sg:address":"5265 Hohman Ave",
    "sg:city":"Hammond",
    "sg:classifiers":[
        {
            "category":"Banks & Credit Unions",
            "subcategory":"Bank",
            "type":"Services"
        }
    ],
    "sg:phone":"+1 219 933 1913",
    "sg:postcode":"46320",
    "sg:province":"IN",
    "sg:tags":[
        "loan",
        "real estate"
    ],
    "wof:name":"LRT & Co",
    "wof:placetype":"venue"
},
  "geometry": {"coordinates":[-87.521958,41.616989],"type":"Point"}
}