{
  "type": "Feature",
  "properties": {
    "addr:full":"704 Joliet St Dyer IN 46311",
    "addr:housenumber":"704",
    "addr:postcode":"46311",
    "addr:street":"Joliet St",
    "iso:country":"US",
    "sg:address":"704 Joliet St",
    "sg:city":"Dyer",
    "sg:classifiers":[
        {
            "category":"Organizations",
            "subcategory":"Religious Organization",
            "type":"Services"
        }
    ],
    "sg:phone":"+1 219 865 6646",
    "sg:postcode":"46311",
    "sg:province":"IN",
    "sg:tags":[
        "church"
    ],
    "sg:website":"www.fccdyer.com",
    "wof:name":"First Christian Church Of Dyer",
    "wof:placetype":"venue"
},
  "geometry": {"coordinates":[-87.510086,41.492952],"type":"Point"}
}