{
  "type": "Feature",
  "properties": {
    "addr:full":"4537 N Franklin Rd Indianapolis IN 46226",
    "addr:housenumber":"4537",
    "addr:postcode":"46226",
    "addr:street":"N Franklin Rd",
    "iso:country":"US",
    "sg:address":"4537 N Franklin Rd",
    "sg:city":"Indianapolis",
    "sg:classifiers":[
        {
            "category":"Professional",
            "subcategory":"Engineering",
            "type":"Services"
        },
        {
            "category":"Home & Garden",
            "subcategory":"Building Materials",
            "type":"Retail Goods"
        },
        {
            "category":"Building & Trades",
            "subcategory":"Construction",
            "type":"Services"
        }
    ],
    "sg:phone":"+1 317 782 5917",
    "sg:postcode":"46226",
    "sg:province":"IN",
    "sg:tags":[
        "system",
        "specialty",
        "heating",
        "equipment",
        "contractor",
        "air conditioning"
    ],
    "sg:website":"http://find.trane.com/tcs-dealer-417744?utm_source=YP&utm_medium=banner&utm_campaign=TL",
    "wof:name":"Swift Air Mechanical, Inc.",
    "wof:placetype":"venue"
},
  "geometry": {"coordinates":[-86.027153,39.840365],"type":"Point"}
}