{
  "type": "Feature",
  "properties": {
    "iso:country":"US",
    "sg:address":"306 Napoleon St",
    "sg:city":"Valparaiso",
    "sg:classifiers":[
        {
            "category":"Professional",
            "subcategory":"Management & Consulting",
            "type":"Services"
        }
    ],
    "sg:phone":"+1 219 464 7858",
    "sg:postcode":"46383",
    "sg:province":"IN",
    "sg:tags":[
        "consultant",
        "business"
    ],
    "wof:name":"Manufacturing Technology",
    "wof:placetype":"venue"
},
  "geometry": {"coordinates":[-87.063413,41.471213],"type":"Point"}
}