{
  "type": "Feature",
  "properties": {
    "addr:full":"8159 S State Rd 9 Columbia City IN 46725",
    "addr:housenumber":"8159",
    "addr:postcode":"46725",
    "addr:street":"S State Rd 9",
    "iso:country":"US",
    "sg:address":"8159 S State Rd 9",
    "sg:city":"Columbia City",
    "sg:classifiers":[
        {
            "category":"Building & Trades",
            "subcategory":"Electrical",
            "type":"Services"
        }
    ],
    "sg:phone":"+1 260 396 2781",
    "sg:postcode":"46725",
    "sg:province":"IN",
    "sg:tags":[
        "electric",
        "contractor"
    ],
    "wof:name":"Faulkner Electric Svc",
    "wof:placetype":"venue"
},
  "geometry": {"coordinates":[-85.470536,41.04609],"type":"Point"}
}