{
  "type": "Feature",
  "properties": {
    "iso:country":"US",
    "sg:address":"8330 Naab Rd Ste 307",
    "sg:city":"Indianapolis",
    "sg:classifiers":[
        {
            "category":"Health Services",
            "subcategory":"Doctor",
            "type":"Services"
        }
    ],
    "sg:phone":"+1 317 872 0400",
    "sg:postcode":"46260",
    "sg:province":"IN",
    "wof:name":"Stein Mark H MD",
    "wof:placetype":"venue"
},
  "geometry": {"coordinates":[-86.198303,39.9077],"type":"Point"}
}