{
  "type": "Feature",
  "properties": {
    "iso:country":"US",
    "sg:address":"4833 State Route 261",
    "sg:city":"Newburgh",
    "sg:classifiers":[
        {
            "category":"Professional",
            "type":"Services"
        },
        {
            "category":"Restaurant",
            "type":"Food & Drink"
        }
    ],
    "sg:phone":"+1 812 490 8227",
    "sg:postcode":"47630",
    "sg:province":"IN",
    "sg:tags":[
        "barbeque",
        "caterer"
    ],
    "sg:website":"www.thebarbqshack.com",
    "wof:name":"Bar-B-Q Shack Stepto's",
    "wof:placetype":"venue"
},
  "geometry": {"coordinates":[-87.39832,37.964348],"type":"Point"}
}