{
  "type": "Feature",
  "properties": {
    "addr:full":"3038 S Co Rd 1050 W French Lick IN 47432",
    "addr:housenumber":"3038",
    "addr:postcode":"47432",
    "addr:street":"S Co Rd 1050 W French",
    "iso:country":"US",
    "sg:address":"3038 S Co Rd 1050 W",
    "sg:city":"French Lick",
    "sg:classifiers":[
        {
            "category":"Building & Trades",
            "subcategory":"Construction",
            "type":"Services"
        }
    ],
    "sg:phone":"+1 812 936 2486",
    "sg:postcode":"47432",
    "sg:province":"IN",
    "sg:tags":[
        "concrete",
        "contractor"
    ],
    "wof:name":"Norton Concrete Svc",
    "wof:placetype":"venue"
},
  "geometry": {"coordinates":[-86.657206,38.506597],"type":"Point"}
}