{
  "type": "Feature",
  "properties": {
    "addr:full":"1571 Vann Ave Evansville IN 47714",
    "addr:housenumber":"1571",
    "addr:postcode":"47714",
    "addr:street":"Vann Ave",
    "iso:country":"US",
    "sg:address":"1571 Vann Ave",
    "sg:city":"Evansville",
    "sg:classifiers":[
        {
            "category":"Autos & Motor Vehicles",
            "subcategory":"Automobile Sales",
            "type":"Retail Goods"
        }
    ],
    "sg:phone":"+1 812 474 0865",
    "sg:postcode":"47714",
    "sg:province":"IN",
    "sg:tags":[
        "car",
        "dealer"
    ],
    "wof:name":"Evansville Car Ctr",
    "wof:placetype":"venue"
},
  "geometry": {"coordinates":[-87.511325,37.955496],"type":"Point"}
}