{
  "type": "Feature",
  "properties": {
    "addr:full":"1750 E US Hwy 12 Michigan City IN 46360",
    "addr:housenumber":"1750",
    "addr:postcode":"46360",
    "addr:street":"E Us Hwy 12",
    "iso:country":"US",
    "sg:address":"1750 E US Hwy 12",
    "sg:city":"Michigan City",
    "sg:classifiers":[
        {
            "category":"Wholesale",
            "subcategory":"Chemicals & Plastics",
            "type":"Manufacturing & Wholesale Goods"
        }
    ],
    "sg:phone":"+1 219 873 0914",
    "sg:postcode":"46360",
    "sg:province":"IN",
    "sg:tags":[
        "plant"
    ],
    "wof:name":"United States Aluminate",
    "wof:placetype":"venue"
},
  "geometry": {"coordinates":[-86.883078,41.72318],"type":"Point"}
}