{
  "type": "Feature",
  "properties": {
    "addr:full":"328 N 2nd St Vincennes IN 47591",
    "addr:housenumber":"328",
    "addr:postcode":"47591",
    "addr:street":"N 2Nd St",
    "iso:country":"US",
    "sg:address":"328 N 2nd St",
    "sg:city":"Vincennes",
    "sg:classifiers":[
        {
            "category":"Health Services",
            "subcategory":"Doctor",
            "type":"Services"
        }
    ],
    "sg:phone":"+1 812 895 0557",
    "sg:postcode":"47591",
    "sg:province":"IN",
    "sg:tags":[
        "physician",
        "surgeon"
    ],
    "wof:name":"Allergy & Asthma",
    "wof:placetype":"venue"
},
  "geometry": {"coordinates":[-87.528919,38.68183],"type":"Point"}
}