{
  "type": "Feature",
  "properties": {
    "iso:country":"US",
    "sg:address":"3002 Wayne Trce",
    "sg:city":"Fort Wayne",
    "sg:classifiers":[
        {
            "category":"Personal",
            "subcategory":"Barber",
            "type":"Services"
        }
    ],
    "sg:phone":"+1 260 745 2345",
    "sg:postcode":"46806",
    "sg:province":"IN",
    "sg:tags":[
        "shop"
    ],
    "wof:name":"Chilcote's Barber & Style Shop",
    "wof:placetype":"venue"
},
  "geometry": {"coordinates":[-85.09742300000001,41.057504],"type":"Point"}
}