{
  "type": "Feature",
  "properties": {
    "iso:country":"US",
    "sg:address":"1634 S State Ave",
    "sg:city":"Indianapolis",
    "sg:classifiers":[
        {
            "category":"Food & Beverages",
            "subcategory":"Groceries & Convenience Stores",
            "type":"Retail Goods"
        }
    ],
    "sg:phone":"+1 317 783 3833",
    "sg:postcode":"46203",
    "sg:province":"IN",
    "wof:name":"Village Pantry",
    "wof:placetype":"venue"
},
  "geometry": {"coordinates":[-86.130619,39.74548],"type":"Point"}
}