{
  "type": "Feature",
  "properties": {
    "iso:country":"US",
    "sg:address":"1920 E Markland Ave",
    "sg:city":"Kokomo",
    "sg:classifiers":[
        {
            "category":"Personal",
            "subcategory":"Beauty Salon",
            "type":"Services"
        }
    ],
    "sg:phone":"+1 765 452 9609",
    "sg:postcode":"46901",
    "sg:province":"IN",
    "wof:name":"Smart Style Family Hair Salon",
    "wof:placetype":"venue"
},
  "geometry": {"coordinates":[-86.10534699999999,40.476766],"type":"Point"}
}