{
  "type": "Feature",
  "properties": {
    "iso:country":"US",
    "sg:address":"1514 S Walnut St",
    "sg:city":"Bloomington",
    "sg:classifiers":[
        {
            "category":"Insurance",
            "subcategory":"Insurance Agent",
            "type":"Services"
        }
    ],
    "sg:phone":"+1 812 332 5888",
    "sg:postcode":"47401",
    "sg:province":"IN",
    "wof:name":"Ragsdale Financial Group",
    "wof:placetype":"venue"
},
  "geometry": {"coordinates":[-86.533568,39.149866],"type":"Point"}
}