{
  "type": "Feature",
  "properties": {
    "addr:full":"6020 E 82nd St Ste 710 Indianapolis IN 46250",
    "addr:housenumber":"6020",
    "addr:postcode":"46250",
    "addr:street":"E 82Nd St Ste 710",
    "iso:country":"US",
    "sg:address":"6020 E 82nd St Ste 710",
    "sg:city":"Indianapolis",
    "sg:classifiers":[
        {
            "category":"Shopping",
            "subcategory":"Shoes",
            "type":"Retail Goods"
        }
    ],
    "sg:phone":"+1 317 845 0709",
    "sg:postcode":"46250",
    "sg:province":"IN",
    "sg:tags":[
        "store"
    ],
    "wof:name":"Payless Shoesource",
    "wof:placetype":"venue"
},
  "geometry": {"coordinates":[-86.061677,39.907886],"type":"Point"}
}