{
  "type": "Feature",
  "properties": {
    "iso:country":"US",
    "sg:address":"520 Elliott Ct",
    "sg:city":"Greentown",
    "sg:classifiers":[
        {
            "category":"Building & Trades",
            "subcategory":"Construction",
            "type":"Services"
        }
    ],
    "sg:phone":"+1 765 628 2839",
    "sg:postcode":"46936",
    "sg:province":"IN",
    "sg:tags":[
        "repairing",
        "remodeling",
        "contractor"
    ],
    "wof:name":"Hainlen Construction",
    "wof:placetype":"venue"
},
  "geometry": {"coordinates":[-85.959216,40.472259],"type":"Point"}
}