{
  "type": "Feature",
  "properties": {
    "iso:country":"US",
    "sg:address":"7712 US Hwy 36",
    "sg:city":"Avon",
    "sg:classifiers":[
        {
            "category":"Home & Garden",
            "subcategory":"Furniture",
            "type":"Retail Goods"
        }
    ],
    "sg:phone":"+1 317 272 0793",
    "sg:postcode":"46123",
    "sg:province":"IN",
    "sg:tags":[
        "mattress"
    ],
    "wof:name":"Mattress Gallery",
    "wof:placetype":"venue"
},
  "geometry": {"coordinates":[-86.39955399999999,39.762841],"type":"Point"}
}