{
  "type": "Feature",
  "properties": {
    "iso:country":"US",
    "sg:address":"7 Ridge Ave",
    "sg:city":"Greendale",
    "sg:classifiers":[
        {
            "category":"Organizations",
            "subcategory":"Labor Organization",
            "type":"Services"
        }
    ],
    "sg:phone":"+1 812 537 5798",
    "sg:postcode":"47025",
    "sg:province":"IN",
    "wof:name":"Local 13 Social Security Fund",
    "wof:placetype":"venue"
},
  "geometry": {"coordinates":[-84.862757,39.103961],"type":"Point"}
}