{
  "type": "Feature",
  "properties": {
    "iso:country":"US",
    "sg:address":"237 W 1050 S",
    "sg:city":"Silver Lake",
    "sg:classifiers":[
        {
            "category":"Farming",
            "subcategory":"Livestock Farm",
            "type":"Manufacturing & Wholesale Goods"
        }
    ],
    "sg:phone":"+1 260 352 2137",
    "sg:postcode":"46982",
    "sg:province":"IN",
    "sg:tags":[
        "feedlot",
        "hog",
        "corn",
        "or",
        "soybean"
    ],
    "wof:name":"Kerlin Farms",
    "wof:placetype":"venue"
},
  "geometry": {"coordinates":[-85.836989,41.079595],"type":"Point"}
}