{
  "type": "Feature",
  "properties": {
    "iso:country":"US",
    "sg:address":"5446 Co Rd 29",
    "sg:city":"Auburn",
    "sg:classifiers":[
        {
            "category":"Communications",
            "subcategory":"Radio Station",
            "type":"Services"
        }
    ],
    "sg:phone":"+1 260 925 4300",
    "sg:postcode":"46706",
    "sg:province":"IN",
    "sg:tags":[
        "company",
        "broadcasting"
    ],
    "wof:name":"WGLL",
    "wof:placetype":"venue"
},
  "geometry": {"coordinates":[-85.050754,41.333028],"type":"Point"}
}