{
  "type": "Feature",
  "properties": {
    "iso:country":"US",
    "sg:address":"133 W Market St Suite200",
    "sg:city":"Indianapolis",
    "sg:classifiers":[
        {
            "category":"Social Services",
            "type":"Services"
        },
        {
            "category":"Personal",
            "subcategory":"Adult",
            "type":"Services"
        }
    ],
    "sg:phone":"+1 317 622 1285",
    "sg:postcode":"46204",
    "sg:province":"IN",
    "sg:tags":[
        "family",
        "coaching-business",
        "individual",
        "marriage",
        "child",
        "counselor"
    ],
    "wof:name":"The Assist",
    "wof:placetype":"venue"
},
  "geometry": {"coordinates":[-86.16044100000001,39.768567],"type":"Point"}
}