{
  "type": "Feature",
  "properties": {
    "iso:country":"US",
    "sg:address":"1938 N Alton Ave",
    "sg:city":"Indianapolis",
    "sg:classifiers":[
        {
            "category":"Professional",
            "subcategory":"Advertising",
            "type":"Services"
        }
    ],
    "sg:phone":"+1 317 631 0652",
    "sg:postcode":"46222",
    "sg:province":"IN",
    "sg:tags":[
        "mailing",
        "shipping"
    ],
    "wof:name":"You Can Sell It & I'Ll Mail It",
    "wof:placetype":"venue"
},
  "geometry": {"coordinates":[-86.217299,39.792004],"type":"Point"}
}