{
  "type": "Feature",
  "properties": {
    "iso:country":"US",
    "sg:address":"3821-D East Barrington Drive",
    "sg:city":"Bloomington",
    "sg:classifiers":[
        {
            "category":"Real Estate",
            "subcategory":"Real Estate Services",
            "type":"Services"
        }
    ],
    "sg:phone":"+1 812 334 2270",
    "sg:postcode":"47408",
    "sg:province":"IN",
    "sg:website":"www.homeisthecrest.com",
    "wof:name":"The Crest on East 10th St Apartments",
    "wof:placetype":"venue"
},
  "geometry": {"coordinates":[-86.48893,39.172016],"type":"Point"}
}