{
  "type": "Feature",
  "properties": {
    "iso:country":"US",
    "sg:address":"5867 E Cummins Rd",
    "sg:city":"Montpelier",
    "sg:classifiers":[
        {
            "category":"Sports & Exercise",
            "subcategory":"Golf",
            "type":"Entertainment"
        }
    ],
    "sg:phone":"+1 765 728 5402",
    "sg:postcode":"47359",
    "sg:province":"IN",
    "sg:tags":[
        "course"
    ],
    "wof:name":"Bluewater Golf Course",
    "wof:placetype":"venue"
},
  "geometry": {"coordinates":[-85.261741,40.559635],"type":"Point"}
}