{
  "type": "Feature",
  "properties": {
    "iso:country":"US",
    "sg:address":"410 Main St",
    "sg:city":"Mt Vernon",
    "sg:classifiers":[
        {
            "category":"Building & Trades",
            "subcategory":"Equipment Rental",
            "type":"Services"
        }
    ],
    "sg:phone":"+1 812 838 2770",
    "sg:postcode":"47620",
    "sg:province":"IN",
    "sg:tags":[
        "player",
        "recorder",
        "video"
    ],
    "wof:name":"New Harmony Video",
    "wof:placetype":"venue"
},
  "geometry": {"coordinates":[-87.89572200000001,37.932561],"type":"Point"}
}