{
  "type": "Feature",
  "properties": {
    "addr:full":"1756 W 1050 S Miami IN 46959",
    "addr:housenumber":"1756",
    "addr:postcode":"46959",
    "addr:street":"W 1050 S",
    "iso:country":"US",
    "sg:address":"1756 W 1050 S",
    "sg:city":"Miami",
    "sg:classifiers":[
        {
            "category":"Restaurant",
            "type":"Food & Drink"
        }
    ],
    "sg:phone":"+1 765 689 7630",
    "sg:postcode":"46959",
    "sg:province":"IN",
    "wof:name":"County Line Restaurant",
    "wof:placetype":"venue"
},
  "geometry": {"coordinates":[-86.105046,40.614004],"type":"Point"}
}