{
  "type": "Feature",
  "properties": {
    "iso:country":"US",
    "sg:address":"15229 Herriman Blvd",
    "sg:city":"Noblesville",
    "sg:classifiers":[
        {
            "category":"Professional",
            "subcategory":"Employment Agencies",
            "type":"Services"
        }
    ],
    "sg:phone":"+1 317 773 4323",
    "sg:postcode":"46060",
    "sg:province":"IN",
    "sg:tags":[
        "help",
        "contractor"
    ],
    "sg:website":"www.mriweb.com",
    "wof:name":"Compu Search",
    "wof:placetype":"venue"
},
  "geometry": {"coordinates":[-86.004892,40.012944],"type":"Point"}
}