{
  "type": "Feature",
  "properties": {
    "iso:country":"US",
    "sg:address":"128 N Meridian St",
    "sg:city":"Greentown",
    "sg:classifiers":[
        {
            "category":"Restaurant",
            "type":"Food & Drink"
        }
    ],
    "sg:phone":"+1 765 628 2377",
    "sg:postcode":"46936",
    "sg:province":"IN",
    "wof:name":"Barton's Family Restaurant",
    "wof:placetype":"venue"
},
  "geometry": {"coordinates":[-85.96653,40.478196],"type":"Point"}
}