{
  "type": "Feature",
  "properties": {
    "addr:full":"200 4th St Logansport IN 46947",
    "addr:housenumber":"200",
    "addr:postcode":"46947",
    "addr:street":"4Th St",
    "iso:country":"US",
    "sg:address":"200 4th St",
    "sg:city":"Logansport",
    "sg:classifiers":[
        {
            "category":"Professional",
            "subcategory":"Lawyer & Legal Services",
            "type":"Services"
        }
    ],
    "sg:phone":"+1 574 722 4560",
    "sg:postcode":"46947",
    "sg:province":"IN",
    "sg:tags":[
        "attorney"
    ],
    "wof:name":"Hillis & Hillis",
    "wof:placetype":"venue"
},
  "geometry": {"coordinates":[-86.365911,40.754019],"type":"Point"}
}