{
  "type": "Feature",
  "properties": {
    "iso:country":"US",
    "sg:address":"64901 Co Rd 11",
    "sg:city":"Goshen",
    "sg:classifiers":[
        {
            "category":"Organizations",
            "subcategory":"Religious Organization",
            "type":"Services"
        }
    ],
    "sg:phone":"+1 574 862 2595",
    "sg:postcode":"46526",
    "sg:province":"IN",
    "sg:tags":[
        "church"
    ],
    "wof:name":"Yellow Creek Mennonite Church",
    "wof:placetype":"venue"
},
  "geometry": {"coordinates":[-85.944256,41.552535],"type":"Point"}
}