{
  "type": "Feature",
  "properties": {
    "iso:country":"US",
    "sg:address":"3907 Murvihill Rd",
    "sg:city":"Valparaiso",
    "sg:classifiers":[
        {
            "category":"Wholesale",
            "subcategory":"Machinery & Supplies",
            "type":"Manufacturing & Wholesale Goods"
        }
    ],
    "sg:phone":"+1 219 548 5711",
    "sg:postcode":"46383",
    "sg:province":"IN",
    "sg:tags":[
        "spraying",
        "equipment"
    ],
    "sg:website":"www.mcsupply.org",
    "wof:name":"M C Supply & Svc Co",
    "wof:placetype":"venue"
},
  "geometry": {"coordinates":[-87.010971,41.449065],"type":"Point"}
}