{
  "type": "Feature",
  "properties": {
    "iso:country":"US",
    "sg:address":"2501 E 3rd St",
    "sg:city":"Bloomington",
    "sg:classifiers":[
        {
            "category":"Health Services",
            "subcategory":"Health Practitioner",
            "type":"Services"
        },
        {
            "category":"Health Services",
            "subcategory":"Chiropractor",
            "type":"Services"
        }
    ],
    "sg:phone":"+1 812 332 6427",
    "sg:postcode":"47401",
    "sg:province":"IN",
    "sg:tags":[
        "acupuncture",
        "nutritionist"
    ],
    "wof:name":"Houze Norman J DC",
    "wof:placetype":"venue"
},
  "geometry": {"coordinates":[-86.502197,39.164299],"type":"Point"}
}