{
  "type": "Feature",
  "properties": {
    "iso:country":"US",
    "sg:address":"1030 James Ave",
    "sg:city":"Bedford",
    "sg:classifiers":[
        {
            "category":"Shopping",
            "type":"Retail Goods"
        }
    ],
    "sg:phone":"+1 812 279 6953",
    "sg:postcode":"47421",
    "sg:province":"IN",
    "sg:tags":[
        "telephone",
        "cellular"
    ],
    "wof:name":"Radio Shack",
    "wof:placetype":"venue"
},
  "geometry": {"coordinates":[-86.518805,38.866282],"type":"Point"}
}