{
  "type": "Feature",
  "properties": {
    "iso:country":"US",
    "sg:address":"56508 Elm Ridge Rd",
    "sg:city":"Elkhart",
    "sg:classifiers":[
        {
            "category":"Professional",
            "type":"Services"
        }
    ],
    "sg:phone":"+1 574 293 7953",
    "sg:postcode":"46516",
    "sg:province":"IN",
    "wof:name":"Wendy Mischke",
    "wof:placetype":"venue"
},
  "geometry": {"coordinates":[-86.009102,41.672875],"type":"Point"}
}