{
  "type": "Feature",
  "properties": {
    "iso:country":"US",
    "sg:address":"1070 W Jefferson St",
    "sg:city":"Franklin",
    "sg:classifiers":[
        {
            "category":"Health Services",
            "subcategory":"Nursing And Care Facility",
            "type":"Services"
        }
    ],
    "sg:phone":"+1 317 736 7185",
    "sg:postcode":"46131",
    "sg:province":"IN",
    "sg:tags":[
        "home",
        "retirement",
        "community"
    ],
    "wof:name":"Franklin United Methodist Home",
    "wof:placetype":"venue"
},
  "geometry": {"coordinates":[-86.071676,39.479784],"type":"Point"}
}