{
  "type": "Feature",
  "properties": {
    "iso:country":"US",
    "sg:address":"4377 W 96th St",
    "sg:city":"Indianapolis",
    "sg:classifiers":[
        {
            "category":"Farming",
            "subcategory":"Dairy Farm",
            "type":"Manufacturing & Wholesale Goods"
        }
    ],
    "sg:phone":"+1 317 334 9190",
    "sg:postcode":"46268",
    "sg:province":"IN",
    "wof:name":"Oberweis Dairy",
    "wof:placetype":"venue"
},
  "geometry": {"coordinates":[-86.23333700000001,39.926057],"type":"Point"}
}