{
  "type": "Feature",
  "properties": {
    "iso:country":"US",
    "sg:address":"6115 W Savin Dr",
    "sg:city":"Indianapolis",
    "sg:classifiers":[
        {
            "category":"Social Services",
            "subcategory":"Child Care",
            "type":"Services"
        }
    ],
    "sg:phone":"+1 317 299 8881",
    "sg:postcode":"46254",
    "sg:province":"IN",
    "wof:name":"Kids Unlimited",
    "wof:placetype":"venue"
},
  "geometry": {"coordinates":[-86.267512,39.858913],"type":"Point"}
}