{
  "type": "Feature",
  "properties": {
    "iso:country":"US",
    "sg:address":"1149 Thiel Dr",
    "sg:city":"Schererville",
    "sg:classifiers":[
        {
            "category":"Museum",
            "type":"Entertainment"
        }
    ],
    "sg:phone":"+1 219 381 5908",
    "sg:postcode":"46375",
    "sg:province":"IN",
    "wof:name":"Heritage Institute Of Arts And Technolog",
    "wof:placetype":"venue"
},
  "geometry": {"coordinates":[-87.478763,41.480723],"type":"Point"}
}