{
  "type": "Feature",
  "properties": {
    "iso:country":"US",
    "sg:address":"10860 W Baseline Rd",
    "sg:city":"Paragon",
    "sg:classifiers":[
        {
            "category":"Retail",
            "subcategory":"Auto Repair",
            "type":"Services"
        }
    ],
    "sg:phone":"+1 765 537 2448",
    "sg:postcode":"46166",
    "sg:province":"IN",
    "sg:tags":[
        "general"
    ],
    "wof:name":"McClures Service",
    "wof:placetype":"venue"
},
  "geometry": {"coordinates":[-86.622074,39.426643],"type":"Point"}
}