{
  "type": "Feature",
  "properties": {
    "iso:country":"US",
    "sg:address":"6120 Allisonville Rd",
    "sg:city":"Indianapolis",
    "sg:classifiers":[
        {
            "category":"Retail",
            "subcategory":"Veterinary Services",
            "type":"Services"
        }
    ],
    "sg:phone":"+1 317 255 6627",
    "sg:postcode":"46220",
    "sg:province":"IN",
    "sg:tags":[
        "hospital",
        "animal"
    ],
    "wof:name":"Eastwood Animal Clinic",
    "wof:placetype":"venue"
},
  "geometry": {"coordinates":[-86.097792,39.86715],"type":"Point"}
}