{
  "type": "Feature",
  "properties": {
    "iso:country":"US",
    "sg:address":"1328 Broadway",
    "sg:city":"Gary",
    "sg:classifiers":[
        {
            "category":"Retail",
            "subcategory":"Laundry & Dry Cleaning",
            "type":"Services"
        }
    ],
    "sg:phone":"+1 219 886 3624",
    "sg:postcode":"46407",
    "sg:province":"IN",
    "wof:name":"Broadway Coin Op Laundry",
    "wof:placetype":"venue"
},
  "geometry": {"coordinates":[-87.33713,41.589042],"type":"Point"}
}