{
  "type": "Feature",
  "properties": {
    "iso:country":"US",
    "sg:address":"1415 Directors Row",
    "sg:city":"Fort Wayne",
    "sg:classifiers":[
        {
            "category":"Insurance",
            "subcategory":"Insurance Agent",
            "type":"Services"
        }
    ],
    "sg:phone":"+1 260 484 8098",
    "sg:postcode":"46808",
    "sg:province":"IN",
    "wof:name":"Pennsylvania Life Insurance Co",
    "wof:placetype":"venue"
},
  "geometry": {"coordinates":[-85.164526,41.118603],"type":"Point"}
}