{
  "type": "Feature",
  "properties": {
    "iso:country":"US",
    "sg:address":"210 N Section St",
    "sg:city":"Sullivan",
    "sg:classifiers":[
        {
            "category":"Professional",
            "subcategory":"Computer Services",
            "type":"Services"
        }
    ],
    "sg:phone":"+1 812 268 5199",
    "sg:postcode":"47882",
    "sg:province":"IN",
    "sg:tags":[
        "internet"
    ],
    "wof:name":"Wireless Internet For Illiana",
    "wof:placetype":"venue"
},
  "geometry": {"coordinates":[-87.409579,39.099047],"type":"Point"}
}