{
  "type": "Feature",
  "properties": {
    "iso:country":"US",
    "sg:address":"1225 W Oak St",
    "sg:city":"Zionsville",
    "sg:classifiers":[
        {
            "category":"Food & Beverages",
            "subcategory":"Bakery",
            "type":"Retail Goods"
        }
    ],
    "sg:phone":"+1 317 873 4255",
    "sg:postcode":"46077",
    "sg:province":"IN",
    "sg:tags":[
        "bagel"
    ],
    "wof:name":"Big Dave's Deli",
    "wof:placetype":"venue"
},
  "geometry": {"coordinates":[-86.275824,39.950046],"type":"Point"}
}