{
  "type": "Feature",
  "properties": {
    "iso:country":"US",
    "sg:address":"920 Millis Ave",
    "sg:city":"Boonville",
    "sg:classifiers":[
        {
            "category":"Social Services",
            "type":"Services"
        }
    ],
    "sg:phone":"+1 812 897 4182",
    "sg:postcode":"47601",
    "sg:province":"IN",
    "sg:tags":[
        "organization",
        "welfare"
    ],
    "wof:name":"Wic",
    "wof:placetype":"venue"
},
  "geometry": {"coordinates":[-87.26562699999999,38.041553],"type":"Point"}
}