{
  "type": "Feature",
  "properties": {
    "iso:country":"US",
    "sg:address":"5915 Covington Rd",
    "sg:city":"Fort Wayne",
    "sg:classifiers":[
        {
            "category":"Manufacturing",
            "subcategory":"Textiles",
            "type":"Manufacturing & Wholesale Goods"
        }
    ],
    "sg:phone":"+1 260 432 6520",
    "sg:postcode":"46804",
    "sg:province":"IN",
    "sg:tags":[
        "material",
        "waterproofing"
    ],
    "wof:name":"Ream Steckbeck Paint Co",
    "wof:placetype":"venue"
},
  "geometry": {"coordinates":[-85.216328,41.059653],"type":"Point"}
}