{
  "type": "Feature",
  "properties": {
    "addr:full":"9373 N Mount Pleasant Rd Gosport IN 47433",
    "addr:housenumber":"9373",
    "addr:postcode":"47433",
    "addr:street":"N Mount Pleasant Rd",
    "iso:country":"US",
    "sg:address":"9373 N Mount Pleasant Rd",
    "sg:city":"Gosport",
    "sg:phone":"+1 812 876 7719",
    "sg:postcode":"47433",
    "sg:province":"IN",
    "sg:tags":[
        "farm",
        "field",
        "crop"
    ],
    "wof:name":"Lawson Stock Farm",
    "wof:placetype":"venue"
},
  "geometry": {"coordinates":[-86.578034,39.319623],"type":"Point"}
}