{
  "type": "Feature",
  "properties": {
    "iso:country":"US",
    "sg:address":"2128 N 300 E",
    "sg:city":"Camden",
    "sg:classifiers":[
        {
            "category":"Farming",
            "subcategory":"Farm",
            "type":"Manufacturing & Wholesale Goods"
        }
    ],
    "sg:phone":"+1 574 967 3450",
    "sg:postcode":"46917",
    "sg:province":"IN",
    "sg:tags":[
        "crop",
        "general"
    ],
    "wof:name":"Gene Yost",
    "wof:placetype":"venue"
},
  "geometry": {"coordinates":[-86.467948,40.5795],"type":"Point"}
}