{
  "type": "Feature",
  "properties": {
    "iso:country":"US",
    "sg:address":"11583 W Williams Rd",
    "sg:city":"Hardinsburg",
    "sg:classifiers":[
        {
            "category":"Building & Trades",
            "subcategory":"Construction",
            "type":"Services"
        }
    ],
    "sg:phone":"+1 812 755 5020",
    "sg:postcode":"47125",
    "sg:province":"IN",
    "sg:tags":[
        "excavation",
        "contractor"
    ],
    "wof:name":"Koehn Excavating",
    "wof:placetype":"venue"
},
  "geometry": {"coordinates":[-86.299874,38.506702],"type":"Point"}
}