{
  "type": "Feature",
  "properties": {
    "iso:country":"US",
    "sg:address":"800 W Jefferson St",
    "sg:city":"Franklin",
    "sg:classifiers":[
        {
            "category":"Real Estate",
            "subcategory":"Real Estate Agent",
            "type":"Services"
        }
    ],
    "sg:phone":"+1 317 736 8494",
    "sg:postcode":"46131",
    "sg:province":"IN",
    "wof:name":"Jim O'Brien Realty",
    "wof:placetype":"venue"
},
  "geometry": {"coordinates":[-86.06506899999999,39.48007],"type":"Point"}
}