{
  "type": "Feature",
  "properties": {
    "iso:country":"US",
    "sg:address":"6018 Battleview Dr",
    "sg:city":"West Lafayette",
    "sg:classifiers":[
        {
            "category":"Building & Trades",
            "subcategory":"Plumbing",
            "type":"Services"
        }
    ],
    "sg:phone":"+1 765 567 7041",
    "sg:postcode":"47906",
    "sg:province":"IN",
    "sg:tags":[
        "heating",
        "contractor"
    ],
    "wof:name":"Tommy D's Heating",
    "wof:placetype":"venue"
},
  "geometry": {"coordinates":[-86.858032,40.505162],"type":"Point"}
}