{
  "type": "Feature",
  "properties": {
    "addr:full":"1208 Lincoln Hwy E New Haven IN 46774",
    "addr:housenumber":"1208",
    "addr:postcode":"46774",
    "addr:street":"Lincoln Hwy E",
    "iso:country":"US",
    "sg:address":"1208 Lincoln Hwy E",
    "sg:city":"New Haven",
    "sg:classifiers":[
        {
            "category":"Real Estate",
            "subcategory":"Real Estate Agent",
            "type":"Services"
        }
    ],
    "sg:phone":"+1 260 493 6555",
    "sg:postcode":"46774",
    "sg:province":"IN",
    "sg:website":"www.21landmark.com",
    "wof:name":"Landmark",
    "wof:placetype":"venue"
},
  "geometry": {"coordinates":[-85.01254900000001,41.070263],"type":"Point"}
}