{
  "type": "Feature",
  "properties": {
    "iso:country":"US",
    "sg:address":"7803 Dutch Ct",
    "sg:city":"Avon",
    "sg:classifiers":[
        {
            "category":"Farming",
            "subcategory":"Farm",
            "type":"Manufacturing & Wholesale Goods"
        }
    ],
    "sg:phone":"+1 317 838 0961",
    "sg:postcode":"46123",
    "sg:province":"IN",
    "sg:tags":[
        "crop",
        "general"
    ],
    "wof:name":"E & E Farms Inc",
    "wof:placetype":"venue"
},
  "geometry": {"coordinates":[-86.38270199999999,39.738189],"type":"Point"}
}