{
  "type": "Feature",
  "properties": {
    "iso:country":"US",
    "sg:address":"5725 Coventry Ln",
    "sg:city":"Fort Wayne",
    "sg:classifiers":[
        {
            "category":"Shopping",
            "subcategory":"Pharmacy",
            "type":"Retail Goods"
        }
    ],
    "sg:phone":"+1 260 434 0497",
    "sg:postcode":"46804",
    "sg:province":"IN",
    "wof:name":"Keltsch Pharmacy",
    "wof:placetype":"venue"
},
  "geometry": {"coordinates":[-85.256026,41.036462],"type":"Point"}
}