{
  "type": "Feature",
  "properties": {
    "iso:country":"US",
    "sg:address":"338 S 20th St",
    "sg:city":"Terre Haute",
    "sg:classifiers":[
        {
            "category":"Building & Trades",
            "subcategory":"Plumbing",
            "type":"Services"
        }
    ],
    "sg:phone":"+1 812 235 3342",
    "sg:postcode":"47803",
    "sg:province":"IN",
    "sg:tags":[
        "conditioning",
        "air",
        "system",
        "contractor"
    ],
    "wof:name":"Watson Service Co",
    "wof:placetype":"venue"
},
  "geometry": {"coordinates":[-87.387036,39.463841],"type":"Point"}
}