{
  "type": "Feature",
  "properties": {
    "addr:full":"3008 Covert Ave Evansville IN 47714",
    "addr:housenumber":"3008",
    "addr:postcode":"47714",
    "addr:street":"Covert Ave",
    "iso:country":"US",
    "sg:address":"3008 Covert Ave",
    "sg:city":"Evansville",
    "sg:classifiers":[
        {
            "category":"Banks & Credit Unions",
            "subcategory":"Bank",
            "type":"Services"
        }
    ],
    "sg:phone":"+1 812 962 1330",
    "sg:postcode":"47714",
    "sg:province":"IN",
    "sg:tags":[
        "cashing",
        "check"
    ],
    "wof:name":"Casey's Check Advance",
    "wof:placetype":"venue"
},
  "geometry": {"coordinates":[-87.511312,37.955122],"type":"Point"}
}