{
  "type": "Feature",
  "properties": {
    "addr:full":"3022 Calumet Ave Valparaiso IN 46383",
    "addr:housenumber":"3022",
    "addr:postcode":"46383",
    "addr:street":"Calumet Ave",
    "iso:country":"US",
    "sg:address":"3022 Calumet Ave",
    "sg:city":"Valparaiso",
    "sg:classifiers":[
        {
            "category":"Restaurant",
            "type":"Food & Drink"
        }
    ],
    "sg:phone":"+1 219 464 9860",
    "sg:postcode":"46383",
    "sg:province":"IN",
    "wof:name":"Jade Garden",
    "wof:placetype":"venue"
},
  "geometry": {"coordinates":[-87.04508,41.494936],"type":"Point"}
}