{
  "type": "Feature",
  "properties": {
    "iso:country":"US",
    "sg:address":"4110 Grape Rd",
    "sg:city":"Mishawaka",
    "sg:classifiers":[
        {
            "category":"Home & Garden",
            "subcategory":"Furniture",
            "type":"Retail Goods"
        }
    ],
    "sg:phone":"+1 574 255 5722",
    "sg:postcode":"46545",
    "sg:province":"IN",
    "sg:website":"www.sofaselect.com",
    "wof:name":"Sofa Select",
    "wof:placetype":"venue"
},
  "geometry": {"coordinates":[-86.187327,41.698345],"type":"Point"}
}