{
  "type": "Feature",
  "properties": {
    "addr:full":"10865 Parrish St Saint John IN 46373",
    "addr:housenumber":"10865",
    "addr:postcode":"in 46373",
    "addr:street":"Parrish St",
    "iso:country":"US",
    "sg:address":"10865 Parrish St",
    "sg:city":"Saint John",
    "sg:classifiers":[
        {
            "category":"Banks & Credit Unions",
            "subcategory":"Bank",
            "type":"Services"
        },
        {
            "category":"Banks & Credit Unions",
            "subcategory":"Financial Services",
            "type":"Services"
        }
    ],
    "sg:phone":"+1 219 365 9100",
    "sg:postcode":"46373",
    "sg:province":"IN",
    "sg:tags":[
        "broker",
        "mortgage"
    ],
    "sg:website":"www.lakefederal.com",
    "wof:name":"Lake Federal Bank Fsb",
    "wof:placetype":"venue"
},
  "geometry": {"coordinates":[-87.450565,41.421789],"type":"Point"}
}