{
  "type": "Feature",
  "properties": {
    "iso:country":"US",
    "sg:address":"6500 Madison Ave",
    "sg:city":"Indianapolis",
    "sg:classifiers":[
        {
            "category":"Utilities",
            "subcategory":"Refuse",
            "type":"Services"
        }
    ],
    "sg:phone":"+1 765 649 7272",
    "sg:postcode":"46227",
    "sg:province":"IN",
    "sg:tags":[
        "garbage",
        "collection"
    ],
    "wof:name":"Madison Ave Transfer Station",
    "wof:placetype":"venue"
},
  "geometry": {"coordinates":[-86.129374,39.670957],"type":"Point"}
}