{
  "type": "Feature",
  "properties": {
    "addr:full":"916 Jones Rd Gas City IN 46933",
    "addr:housenumber":"916",
    "addr:postcode":"46933",
    "addr:street":"Jones Rd",
    "iso:country":"US",
    "sg:address":"916 Jones Rd",
    "sg:city":"Gas City",
    "sg:classifiers":[
        {
            "category":"Organizations",
            "subcategory":"Religious Organization",
            "type":"Services"
        }
    ],
    "sg:phone":"+1 765 674 9029",
    "sg:postcode":"46933",
    "sg:province":"IN",
    "sg:tags":[
        "church"
    ],
    "wof:name":"United Methodist Church",
    "wof:placetype":"venue"
},
  "geometry": {"coordinates":[-85.599402,40.487433],"type":"Point"}
}