{
  "type": "Feature",
  "properties": {
    "iso:country":"US",
    "sg:address":"206 N Michigan St",
    "sg:city":"Plymouth",
    "sg:classifiers":[
        {
            "category":"Shopping",
            "subcategory":"Jewelry",
            "type":"Retail Goods"
        }
    ],
    "sg:phone":"+1 574 936 1577",
    "sg:postcode":"46563",
    "sg:province":"IN",
    "sg:tags":[
        "jeweler"
    ],
    "wof:name":"Foley & Welker Jewelers",
    "wof:placetype":"venue"
},
  "geometry": {"coordinates":[-86.309218,41.341696],"type":"Point"}
}