{
  "type": "Feature",
  "properties": {
    "iso:country":"US",
    "sg:address":"2000 Brooklyn Ave",
    "sg:city":"Fort Wayne",
    "sg:classifiers":[
        {
            "category":"Restaurant",
            "type":"Food & Drink"
        }
    ],
    "sg:phone":"+1 260 432 5252",
    "sg:postcode":"46802",
    "sg:province":"IN",
    "sg:tags":[
        "eating"
    ],
    "wof:name":"Fidel Parra",
    "wof:placetype":"venue"
},
  "geometry": {"coordinates":[-85.16525799999999,41.066663],"type":"Point"}
}