{
  "type": "Feature",
  "properties": {
    "iso:country":"US",
    "sg:address":"29117 Co Rd 16",
    "sg:city":"Elkhart",
    "sg:classifiers":[
        {
            "category":"Shopping",
            "subcategory":"Discount & Variety Stores",
            "type":"Retail Goods"
        }
    ],
    "sg:phone":"+1 574 295 4268",
    "sg:postcode":"46516",
    "sg:province":"IN",
    "sg:tags":[
        "merchandise",
        "general"
    ],
    "wof:name":"Cheng USA Inc Sales Office",
    "wof:placetype":"venue"
},
  "geometry": {"coordinates":[-86.027268,41.676559],"type":"Point"}
}