{
  "type": "Feature",
  "properties": {
    "addr:full":"1219 S Park Ave Alexandria IN 46001",
    "addr:housenumber":"1219",
    "addr:postcode":"46001",
    "addr:street":"S Park Ave",
    "iso:country":"US",
    "sg:address":"1219 S Park Ave",
    "sg:city":"Alexandria",
    "sg:classifiers":[
        {
            "category":"Personal",
            "subcategory":"Beauty Salon",
            "type":"Services"
        }
    ],
    "sg:phone":"+1 765 724 2361",
    "sg:postcode":"46001",
    "sg:province":"IN",
    "wof:name":"Sally's Beauty Salon",
    "wof:placetype":"venue"
},
  "geometry": {"coordinates":[-85.67151800000001,40.258507],"type":"Point"}
}