{
  "type": "Feature",
  "properties": {
    "iso:country":"US",
    "sg:address":"779 Salisbury Rd S",
    "sg:city":"Richmond",
    "sg:classifiers":[
        {
            "category":"Organizations",
            "subcategory":"Religious Organization",
            "type":"Services"
        }
    ],
    "sg:phone":"+1 765 966 4518",
    "sg:postcode":"47374",
    "sg:province":"IN",
    "sg:tags":[
        "church"
    ],
    "wof:name":"Christian Covenant Church",
    "wof:placetype":"venue"
},
  "geometry": {"coordinates":[-84.941605,39.818459],"type":"Point"}
}