{
  "type": "Feature",
  "properties": {
    "iso:country":"US",
    "sg:address":"318 Main St",
    "sg:city":"Jeffersonville",
    "sg:classifiers":[
        {
            "category":"Building & Trades",
            "subcategory":"Construction",
            "type":"Services"
        }
    ],
    "sg:phone":"+1 812 280 7076",
    "sg:postcode":"47130",
    "sg:province":"IN",
    "sg:tags":[
        "plastering",
        "contractor"
    ],
    "wof:name":"E & S Quality Exteriors",
    "wof:placetype":"venue"
},
  "geometry": {"coordinates":[-85.723585,38.279818],"type":"Point"}
}