{
  "type": "Feature",
  "properties": {
    "addr:full":"8018 Castleway Dr Indianapolis IN 46250",
    "addr:housenumber":"8018",
    "addr:postcode":"46250",
    "addr:street":"Castleway Dr",
    "iso:country":"US",
    "sg:address":"8018 Castleway Dr",
    "sg:city":"Indianapolis",
    "sg:classifiers":[
        {
            "category":"Wholesale",
            "subcategory":"Computers",
            "type":"Manufacturing & Wholesale Goods"
        }
    ],
    "sg:phone":"+1 317 841 6000",
    "sg:postcode":"46250",
    "sg:province":"IN",
    "sg:tags":[
        "software"
    ],
    "wof:name":"Prosolv",
    "wof:placetype":"venue"
},
  "geometry": {"coordinates":[-86.05659199999999,39.899587],"type":"Point"}
}