{
  "type": "Feature",
  "properties": {
    "iso:country":"US",
    "sg:address":"2650 N State Rd 9",
    "sg:city":"Columbus",
    "sg:classifiers":[
        {
            "category":"Autos & Motor Vehicles",
            "subcategory":"Fuel & Gas Station",
            "type":"Retail Goods"
        }
    ],
    "sg:phone":"+1 812 546 5428",
    "sg:postcode":"47203",
    "sg:province":"IN",
    "sg:tags":[
        "oil"
    ],
    "wof:name":"Palia BP Marathon Gas Station",
    "wof:placetype":"venue"
},
  "geometry": {"coordinates":[-85.771854,39.225768],"type":"Point"}
}