{
  "type": "Feature",
  "properties": {
    "iso:country":"US",
    "sg:address":"225 Highland Ct",
    "sg:city":"Terre Haute",
    "sg:classifiers":[
        {
            "category":"Banks & Credit Unions",
            "subcategory":"Investment Brokerage",
            "type":"Services"
        }
    ],
    "sg:phone":"+1 812 299 9572",
    "sg:postcode":"47802",
    "sg:province":"IN",
    "sg:tags":[
        "advisory",
        "financial"
    ],
    "wof:name":"Honey Creek Financial",
    "wof:placetype":"venue"
},
  "geometry": {"coordinates":[-87.379643,39.387506],"type":"Point"}
}