{
  "type": "Feature",
  "properties": {
    "iso:country":"US",
    "sg:address":"3012 Callway Dr",
    "sg:city":"Jeffersonville",
    "sg:classifiers":[
        {
            "category":"Professional",
            "subcategory":"Computer Services",
            "type":"Services"
        }
    ],
    "sg:phone":"+1 812 282 9959",
    "sg:postcode":"47130",
    "sg:province":"IN",
    "sg:tags":[
        "datum"
    ],
    "wof:name":"Workathomecom",
    "wof:placetype":"venue"
},
  "geometry": {"coordinates":[-85.73692200000001,38.311062],"type":"Point"}
}