{
  "type": "Feature",
  "properties": {
    "iso:country":"US",
    "sg:address":"3310 Liverpool Rd",
    "sg:city":"Lake Station",
    "sg:classifiers":[
        {
            "category":"Autos & Motor Vehicles",
            "subcategory":"Automobile Sales",
            "type":"Retail Goods"
        }
    ],
    "sg:phone":"+1 219 962 5469",
    "sg:postcode":"46405",
    "sg:province":"IN",
    "sg:tags":[
        "car",
        "dealer"
    ],
    "wof:name":"Liverpool Auto Sales",
    "wof:placetype":"venue"
},
  "geometry": {"coordinates":[-87.29172699999999,41.561825],"type":"Point"}
}