{
  "type": "Feature",
  "properties": {
    "iso:country":"US",
    "sg:address":"41 W Main St",
    "sg:city":"Carmel",
    "sg:classifiers":[
        {
            "category":"Home & Garden",
            "subcategory":"Building Materials",
            "type":"Retail Goods"
        }
    ],
    "sg:phone":"+1 317 566 9240",
    "sg:postcode":"46032",
    "sg:province":"IN",
    "sg:tags":[
        "glass",
        "window",
        "plate"
    ],
    "wof:name":"Red Dot Glass Gallery",
    "wof:placetype":"venue"
},
  "geometry": {"coordinates":[-86.127484,39.978308],"type":"Point"}
}