{
  "type": "Feature",
  "properties": {
    "iso:country":"US",
    "sg:address":"4150 Lafayette Rd",
    "sg:city":"Indianapolis",
    "sg:classifiers":[
        {
            "category":"Home & Garden",
            "subcategory":"Furniture",
            "type":"Retail Goods"
        }
    ],
    "sg:phone":"+1 317 299 9830",
    "sg:postcode":"46254",
    "sg:province":"IN",
    "sg:tags":[
        "store"
    ],
    "wof:name":"Furniture Discounters Inc",
    "wof:placetype":"venue"
},
  "geometry": {"coordinates":[-86.24239300000001,39.83139],"type":"Point"}
}