{
  "type": "Feature",
  "properties": {
    "addr:full":"5159 Atherton South Dr Indianapolis IN 46219",
    "addr:housenumber":"5159",
    "addr:postcode":"46219",
    "addr:street":"Atherton South Dr",
    "iso:country":"US",
    "sg:address":"5159 Atherton South Dr",
    "sg:city":"Indianapolis",
    "sg:classifiers":[
        {
            "category":"Retail",
            "subcategory":"Portrait Studio",
            "type":"Services"
        }
    ],
    "sg:phone":"+1 317 356 0724",
    "sg:postcode":"46219",
    "sg:province":"IN",
    "sg:tags":[
        "photo"
    ],
    "wof:name":"Ron Silvers Photography",
    "wof:placetype":"venue"
},
  "geometry": {"coordinates":[-86.08123999999999,39.765111],"type":"Point"}
}