{
  "type": "Feature",
  "properties": {
    "iso:country":"US",
    "sg:address":"786 US Hwy 6",
    "sg:city":"Nappanee",
    "sg:classifiers":[
        {
            "category":"Professional",
            "subcategory":"Management & Consulting",
            "type":"Services"
        }
    ],
    "sg:phone":"+1 574 773 3144",
    "sg:postcode":"46550",
    "sg:province":"IN",
    "sg:tags":[
        "consultant",
        "business"
    ],
    "sg:website":"www.borkholder.com",
    "wof:name":"Borkholder Corp",
    "wof:placetype":"venue"
},
  "geometry": {"coordinates":[-86.009612,41.442755],"type":"Point"}
}