{
  "type": "Feature",
  "properties": {
    "iso:country":"US",
    "sg:address":"380 S Main St",
    "sg:city":"Linton",
    "sg:classifiers":[
        {
            "category":"Shopping",
            "subcategory":"Clothing, Apparel, & Fashions",
            "type":"Retail Goods"
        }
    ],
    "sg:phone":"+1 812 847 7085",
    "sg:postcode":"47441",
    "sg:province":"IN",
    "sg:tags":[
        "furnishing"
    ],
    "wof:name":"D & J's Outfitters",
    "wof:placetype":"venue"
},
  "geometry": {"coordinates":[-87.16636099999999,39.030207],"type":"Point"}
}