{
  "type": "Feature",
  "properties": {
    "addr:full":"411 Main St Tell City IN 47586",
    "addr:housenumber":"411",
    "addr:postcode":"47586",
    "addr:street":"Main St",
    "iso:country":"US",
    "sg:address":"411 Main St",
    "sg:city":"Tell City",
    "sg:classifiers":[
        {
            "category":"Home & Garden",
            "subcategory":"Carpets & Floor Coverings",
            "type":"Retail Goods"
        }
    ],
    "sg:phone":"+1 812 547 7991",
    "sg:postcode":"47586",
    "sg:province":"IN",
    "sg:tags":[
        "dealer",
        "rug"
    ],
    "wof:name":"Kessner Interiors",
    "wof:placetype":"venue"
},
  "geometry": {"coordinates":[-86.769891,37.947601],"type":"Point"}
}