{
  "type": "Feature",
  "properties": {
    "iso:country":"US",
    "sg:address":"6655 State Rd 227",
    "sg:city":"Richmond",
    "sg:classifiers":[
        {
            "category":"Building & Trades",
            "subcategory":"Construction",
            "type":"Services"
        }
    ],
    "sg:phone":"+1 765 847 2126",
    "sg:postcode":"47374",
    "sg:province":"IN",
    "sg:tags":[
        "excavating",
        "contractor"
    ],
    "wof:name":"Butler Excavating Inc",
    "wof:placetype":"venue"
},
  "geometry": {"coordinates":[-84.851822,39.725158],"type":"Point"}
}