{
  "type": "Feature",
  "properties": {
    "iso:country":"US",
    "sg:address":"2223 E 21st Ave",
    "sg:city":"Gary",
    "sg:classifiers":[
        {
            "category":"Organizations",
            "subcategory":"Religious Organization",
            "type":"Services"
        }
    ],
    "sg:phone":"+1 219 882 0590",
    "sg:postcode":"46407",
    "sg:province":"IN",
    "wof:name":"Christ Temple True Holiness",
    "wof:placetype":"venue"
},
  "geometry": {"coordinates":[-87.310383,41.580062],"type":"Point"}
}