{
  "type": "Feature",
  "properties": {
    "iso:country":"US",
    "sg:address":"8435 7b Rd",
    "sg:city":"Plymouth",
    "sg:classifiers":[
        {
            "category":"Freight",
            "type":"Transportation"
        }
    ],
    "sg:phone":"+1 574 936 2578",
    "sg:postcode":"46563",
    "sg:province":"IN",
    "sg:tags":[
        "trucking"
    ],
    "wof:name":"Quik X Transportation Inc",
    "wof:placetype":"venue"
},
  "geometry": {"coordinates":[-86.164799,41.369054],"type":"Point"}
}