{
  "type": "Feature",
  "properties": {
    "iso:country":"US",
    "sg:address":"110 E Charles St",
    "sg:city":"Muncie",
    "sg:classifiers":[
        {
            "category":"Banks & Credit Unions",
            "subcategory":"Investment Brokerage",
            "type":"Services"
        }
    ],
    "sg:phone":"+1 765 747 2811",
    "sg:postcode":"47305",
    "sg:province":"IN",
    "sg:tags":[
        "stock",
        "bond"
    ],
    "wof:name":"AIG Sunamerica",
    "wof:placetype":"venue"
},
  "geometry": {"coordinates":[-85.385558,40.191171],"type":"Point"}
}