{
  "type": "Feature",
  "properties": {
    "addr:full":"16150 Elmwood Ave Mishawaka IN 46544",
    "addr:housenumber":"16150",
    "addr:postcode":"46544",
    "addr:street":"Elmwood Ave",
    "iso:country":"US",
    "sg:address":"16150 Elmwood Ave",
    "sg:city":"Mishawaka",
    "sg:classifiers":[
        {
            "category":"Wholesale",
            "subcategory":"Machinery & Supplies",
            "type":"Manufacturing & Wholesale Goods"
        }
    ],
    "sg:phone":"+1 574 255 4902",
    "sg:postcode":"46544",
    "sg:province":"IN",
    "sg:tags":[
        "equipment",
        "industrial",
        "repair"
    ],
    "wof:name":"Automatronics Inc",
    "wof:placetype":"venue"
},
  "geometry": {"coordinates":[-86.179498,41.627749],"type":"Point"}
}