{
  "type": "Feature",
  "properties": {
    "addr:full":"1334 119th St Whiting IN 46394",
    "addr:housenumber":"1334",
    "addr:postcode":"46394",
    "addr:street":"119Th St",
    "iso:country":"US",
    "sg:address":"1334 119th St",
    "sg:city":"Whiting",
    "sg:classifiers":[
        {
            "category":"Building & Trades",
            "subcategory":"Construction",
            "type":"Services"
        }
    ],
    "sg:phone":"+1 219 659 2545",
    "sg:postcode":"46394",
    "sg:province":"IN",
    "sg:tags":[
        "interior",
        "design"
    ],
    "wof:name":"Drae Designs International",
    "wof:placetype":"venue"
},
  "geometry": {"coordinates":[-87.496279,41.679189],"type":"Point"}
}