{
  "type": "Feature",
  "properties": {
    "iso:country":"US",
    "sg:address":"132 S Nancy St",
    "sg:city":"Warren",
    "sg:classifiers":[
        {
            "category":"Recreation",
            "type":"Entertainment"
        }
    ],
    "sg:phone":"+1 260 375 3550",
    "sg:postcode":"46792",
    "sg:province":"IN",
    "sg:tags":[
        "hall",
        "auditorium"
    ],
    "wof:name":"Warren Community Ctr",
    "wof:placetype":"venue"
},
  "geometry": {"coordinates":[-85.425436,40.680852],"type":"Point"}
}