{
  "type": "Feature",
  "properties": {
    "addr:full":"1322 W 6th St Marion IN 46953",
    "addr:housenumber":"1322",
    "addr:postcode":"46953",
    "addr:street":"W 6Th St",
    "iso:country":"US",
    "sg:address":"1322 W 6th St",
    "sg:city":"Marion",
    "sg:classifiers":[
        {
            "category":"Personal",
            "subcategory":"Beauty Salon",
            "type":"Services"
        }
    ],
    "sg:phone":"+1 765 664 9120",
    "sg:postcode":"46953",
    "sg:province":"IN",
    "wof:name":"Tyson & Co Hair Salon",
    "wof:placetype":"venue"
},
  "geometry": {"coordinates":[-85.674904,40.556088],"type":"Point"}
}