{
  "type": "Feature",
  "properties": {
    "iso:country":"US",
    "sg:address":"411 W 1st St",
    "sg:city":"New Albany",
    "sg:classifiers":[
        {
            "category":"Real Estate",
            "subcategory":"Real Estate Services",
            "type":"Services"
        }
    ],
    "sg:phone":"+1 812 944 4931",
    "sg:postcode":"47150",
    "sg:province":"IN",
    "sg:tags":[
        "research"
    ],
    "wof:name":"Southern Indiana Abstract Co",
    "wof:placetype":"venue"
},
  "geometry": {"coordinates":[-85.825731,38.286304],"type":"Point"}
}