{
  "type": "Feature",
  "properties": {
    "iso:country":"US",
    "sg:address":"721 W National Ave",
    "sg:city":"West Terre Haute",
    "sg:classifiers":[
        {
            "category":"Real Estate",
            "subcategory":"Real Estate Operator",
            "type":"Services"
        }
    ],
    "sg:phone":"+1 812 232 2625",
    "sg:postcode":"47885",
    "sg:province":"IN",
    "sg:tags":[
        "apartment"
    ],
    "wof:name":"Allendale Estates",
    "wof:placetype":"venue"
},
  "geometry": {"coordinates":[-87.452044,39.464637],"type":"Point"}
}