{
  "type": "Feature",
  "properties": {
    "iso:country":"US",
    "sg:address":"1501 Green Rd",
    "sg:city":"Madison",
    "sg:classifiers":[
        {
            "category":"Recreation",
            "type":"Entertainment"
        }
    ],
    "sg:phone":"+1 812 273 8885",
    "sg:postcode":"47250",
    "sg:province":"IN",
    "sg:tags":[
        "parks"
    ],
    "wof:name":"Clifty Falls State Park",
    "wof:placetype":"venue"
},
  "geometry": {"coordinates":[-85.420388,38.76117],"type":"Point"}
}