{
  "type": "Feature",
  "properties": {
    "addr:full":"8179 E 21st St Indianapolis IN 46219",
    "addr:housenumber":"8179",
    "addr:postcode":"46219",
    "addr:street":"E 21St St",
    "iso:country":"US",
    "sg:address":"8179 E 21st St",
    "sg:city":"Indianapolis",
    "sg:classifiers":[
        {
            "category":"Wholesale",
            "subcategory":"Jewelry",
            "type":"Manufacturing & Wholesale Goods"
        },
        {
            "category":"Shopping",
            "subcategory":"Crafts & Fabrics",
            "type":"Retail Goods"
        }
    ],
    "sg:phone":"+1 317 899 2323",
    "sg:postcode":"46219",
    "sg:province":"IN",
    "sg:tags":[
        "art",
        "supply",
        "beads-wholesale",
        "bead",
        "manufacturer"
    ],
    "wof:name":"Taylor's Trinkets & Beads",
    "wof:placetype":"venue"
},
  "geometry": {"coordinates":[-86.023704,39.796568],"type":"Point"}
}