{
  "type": "Feature",
  "properties": {
    "iso:country":"US",
    "sg:address":"5906 S Wirick St",
    "sg:city":"Star City",
    "sg:classifiers":[
        {
            "category":"Freight",
            "type":"Transportation"
        }
    ],
    "sg:phone":"+1 574 595 7527",
    "sg:postcode":"46985",
    "sg:province":"IN",
    "sg:tags":[
        "operator",
        "local",
        "trucking"
    ],
    "wof:name":"Edmondson Trucking",
    "wof:placetype":"venue"
},
  "geometry": {"coordinates":[-86.557391,40.970566],"type":"Point"}
}