{
  "type": "Feature",
  "properties": {
    "iso:country":"US",
    "sg:address":"3806 Euclid Ave",
    "sg:city":"East Chicago",
    "sg:classifiers":[
        {
            "category":"Restaurant",
            "type":"Food & Drink"
        }
    ],
    "sg:phone":"+1 219 397 8226",
    "sg:postcode":"46312",
    "sg:province":"IN",
    "sg:tags":[
        "mexican"
    ],
    "wof:name":"Taco Delight",
    "wof:placetype":"venue"
},
  "geometry": {"coordinates":[-87.454697,41.644299],"type":"Point"}
}