{
  "type": "Feature",
  "properties": {
    "iso:country":"US",
    "sg:address":"8829 Welnetz Rd",
    "sg:city":"Michigan City",
    "sg:classifiers":[
        {
            "category":"Building & Trades",
            "subcategory":"Pest Control",
            "type":"Services"
        }
    ],
    "sg:phone":"+1 219 874 2813",
    "sg:postcode":"46360",
    "sg:province":"IN",
    "wof:name":"LA Rocco Pest Control Inc",
    "wof:placetype":"venue"
},
  "geometry": {"coordinates":[-86.87358399999999,41.691145],"type":"Point"}
}