{
  "type": "Feature",
  "properties": {
    "iso:country":"US",
    "sg:address":"202 Main St",
    "sg:city":"Michigantown",
    "sg:classifiers":[
        {
            "category":"Restaurant",
            "type":"Food & Drink"
        }
    ],
    "sg:phone":"+1 765 249 2053",
    "sg:postcode":"46057",
    "sg:province":"IN",
    "wof:name":"Sundae Parlor",
    "wof:placetype":"venue"
},
  "geometry": {"coordinates":[-86.39301,40.32531],"type":"Point"}
}