{
  "type": "Feature",
  "properties": {
    "addr:full":"5025 East 82nd Street Indianapolis IN 46250",
    "addr:housenumber":"5025",
    "addr:postcode":"46250",
    "addr:street":"East 82Nd Street",
    "iso:country":"US",
    "sg:address":"5025 East 82nd Street",
    "sg:city":"Indianapolis",
    "sg:classifiers":[
        {
            "category":"Personal",
            "subcategory":"Tanning Parlor",
            "type":"Services"
        }
    ],
    "sg:phone":"+1 317 842 7465",
    "sg:postcode":"46250",
    "sg:province":"IN",
    "wof:name":"Suntan City",
    "wof:placetype":"venue"
},
  "geometry": {"coordinates":[-86.085666,39.904371],"type":"Point"}
}