{
  "type": "Feature",
  "properties": {
    "iso:country":"US",
    "sg:address":"1315 N Beckford Pl",
    "sg:city":"Marion",
    "sg:classifiers":[
        {
            "category":"Real Estate",
            "subcategory":"Real Estate Operator",
            "type":"Services"
        }
    ],
    "sg:phone":"+1 765 664 4155",
    "sg:postcode":"46952",
    "sg:province":"IN",
    "sg:tags":[
        "apartment"
    ],
    "wof:name":"Beckford Place Apartments",
    "wof:placetype":"venue"
},
  "geometry": {"coordinates":[-85.67113999999999,40.579515],"type":"Point"}
}