{
  "type": "Feature",
  "properties": {
    "iso:country":"US",
    "sg:address":"2103 Franklin St",
    "sg:city":"Michigan City",
    "sg:classifiers":[
        {
            "category":"Insurance",
            "subcategory":"Insurance Agent",
            "type":"Services"
        }
    ],
    "sg:phone":"+1 219 872 0554",
    "sg:postcode":"46360",
    "sg:province":"IN",
    "wof:name":"Bob Murdock Insurance",
    "wof:placetype":"venue"
},
  "geometry": {"coordinates":[-86.895289,41.704053],"type":"Point"}
}