{
  "type": "Feature",
  "properties": {
    "iso:country":"US",
    "sg:address":"111 Crossroads Dr",
    "sg:city":"Whiteland",
    "sg:classifiers":[
        {
            "category":"Freight",
            "type":"Transportation"
        }
    ],
    "sg:phone":"+1 317 535 8730",
    "sg:postcode":"46184",
    "sg:province":"IN",
    "sg:tags":[
        "mover"
    ],
    "wof:name":"AAA Moving & Storage",
    "wof:placetype":"venue"
},
  "geometry": {"coordinates":[-86.095297,39.576779],"type":"Point"}
}