{
  "type": "Feature",
  "properties": {
    "iso:country":"US",
    "sg:address":"6529 Oxford Dr",
    "sg:city":"Zionsville",
    "sg:classifiers":[
        {
            "category":"Professional",
            "type":"Services"
        }
    ],
    "sg:phone":"+1 317 873 1040",
    "sg:postcode":"46077",
    "sg:province":"IN",
    "wof:name":"Rawson Property Service LLC",
    "wof:placetype":"venue"
},
  "geometry": {"coordinates":[-86.334948,39.946556],"type":"Point"}
}