{
  "type": "Feature",
  "properties": {
    "iso:country":"US",
    "sg:address":"3730 E Co Rd 500 S",
    "sg:city":"Dupont",
    "sg:classifiers":[
        {
            "category":"Autos & Motor Vehicles",
            "subcategory":"Motorcycle Sales",
            "type":"Retail Goods"
        }
    ],
    "sg:phone":"+1 812 873 6363",
    "sg:postcode":"47231",
    "sg:province":"IN",
    "sg:tags":[
        "all",
        "terrain"
    ],
    "sg:website":"www.dupontpolaris.com",
    "wof:name":"Du Pont Polaris Svc",
    "wof:placetype":"venue"
},
  "geometry": {"coordinates":[-85.540488,38.912175],"type":"Point"}
}