{
  "type": "Feature",
  "properties": {
    "iso:country":"US",
    "sg:address":"1425 W Main St",
    "sg:city":"Greensburg",
    "sg:classifiers":[
        {
            "category":"Manufacturing",
            "subcategory":"Metals",
            "type":"Manufacturing & Wholesale Goods"
        }
    ],
    "sg:phone":"+1 812 663 4433",
    "sg:postcode":"47240",
    "sg:province":"IN",
    "sg:tags":[
        "plumbing",
        "trim",
        "fitting",
        "fixture"
    ],
    "wof:name":"Delta Faucet Co",
    "wof:placetype":"venue"
},
  "geometry": {"coordinates":[-85.503974,39.336252],"type":"Point"}
}