{
  "type": "Feature",
  "properties": {
    "iso:country":"US",
    "sg:address":"110 Ridge Rd",
    "sg:city":"Munster",
    "sg:classifiers":[
        {
            "category":"Health Services",
            "subcategory":"Doctor",
            "type":"Services"
        }
    ],
    "sg:phone":"+1 219 836 0672",
    "sg:postcode":"46321",
    "sg:province":"IN",
    "wof:name":"Panares Rodrigo R MD",
    "wof:placetype":"venue"
},
  "geometry": {"coordinates":[-87.52330600000001,41.563199],"type":"Point"}
}