{
  "type": "Feature",
  "properties": {
    "iso:country":"US",
    "sg:address":"7201 Mississippi St",
    "sg:city":"Merrillville",
    "sg:classifiers":[
        {
            "category":"Building & Trades",
            "subcategory":"Construction",
            "type":"Services"
        }
    ],
    "sg:phone":"+1 219 947 2202",
    "sg:postcode":"46410",
    "sg:province":"IN",
    "sg:tags":[
        "general",
        "contractor"
    ],
    "wof:name":"JSK Construction",
    "wof:placetype":"venue"
},
  "geometry": {"coordinates":[-87.316461,41.490602],"type":"Point"}
}