{
  "type": "Feature",
  "properties": {
    "iso:country":"US",
    "sg:address":"1207 E Lincolnway",
    "sg:city":"Laporte",
    "sg:classifiers":[
        {
            "category":"Manufacturing",
            "subcategory":"Rubber & Plastics",
            "type":"Manufacturing & Wholesale Goods"
        }
    ],
    "sg:phone":"+1 219 324 6886",
    "sg:postcode":"46350",
    "sg:province":"IN",
    "wof:name":"American Renolit Corp LA Porte",
    "wof:placetype":"venue"
},
  "geometry": {"coordinates":[-86.695783,41.622702],"type":"Point"}
}