{
  "type": "Feature",
  "properties": {
    "iso:country":"US",
    "sg:address":"7102 Warrior Trl",
    "sg:city":"Indianapolis",
    "sg:classifiers":[
        {
            "category":"Shopping",
            "subcategory":"Discount & Variety Stores",
            "type":"Retail Goods"
        }
    ],
    "sg:phone":"+1 317 295 0827",
    "sg:postcode":"46260",
    "sg:province":"IN",
    "sg:tags":[
        "merchandise",
        "general"
    ],
    "wof:name":"Barges Moap Sales",
    "wof:placetype":"venue"
},
  "geometry": {"coordinates":[-86.19491,39.88329],"type":"Point"}
}