{
  "type": "Feature",
  "properties": {
    "iso:country":"US",
    "sg:address":"2532 Deer Creek Dr",
    "sg:city":"Anderson",
    "sg:classifiers":[
        {
            "category":"Professional",
            "type":"Services"
        }
    ],
    "sg:phone":"+1 765 644 8907",
    "sg:postcode":"46011",
    "sg:province":"IN",
    "sg:tags":[
        "establishment"
    ],
    "wof:name":"Mantha Inc",
    "wof:placetype":"venue"
},
  "geometry": {"coordinates":[-85.711657,40.125507],"type":"Point"}
}