{
  "type": "Feature",
  "properties": {
    "iso:country":"US",
    "sg:address":"269 Westridge Blvd",
    "sg:city":"Greenwood",
    "sg:classifiers":[
        {
            "category":"Professional",
            "type":"Services"
        }
    ],
    "sg:phone":"+1 317 865 3710",
    "sg:postcode":"46142",
    "sg:province":"IN",
    "sg:tags":[
        "establishment"
    ],
    "wof:name":"Emeritus",
    "wof:placetype":"venue"
},
  "geometry": {"coordinates":[-86.145915,39.617181],"type":"Point"}
}