{
  "type": "Feature",
  "properties": {
    "iso:country":"US",
    "sg:address":"5750 S Harding St",
    "sg:city":"Indianapolis",
    "sg:classifiers":[
        {
            "category":"Farming",
            "subcategory":"Dairy Farm",
            "type":"Manufacturing & Wholesale Goods"
        }
    ],
    "sg:phone":"+1 317 788 9374",
    "sg:postcode":"46217",
    "sg:province":"IN",
    "sg:website":"www.indyfarms.com",
    "wof:name":"Prairie Farms Dairy",
    "wof:placetype":"venue"
},
  "geometry": {"coordinates":[-86.187128,39.684957],"type":"Point"}
}