{
  "type": "Feature",
  "properties": {
    "iso:country":"US",
    "sg:address":"8613 Schreiber Dr",
    "sg:city":"Munster",
    "sg:classifiers":[
        {
            "category":"Wholesale",
            "subcategory":"Vending Machines",
            "type":"Manufacturing & Wholesale Goods"
        }
    ],
    "sg:phone":"+1 219 923 1014",
    "sg:postcode":"46321",
    "sg:province":"IN",
    "sg:tags":[
        "operator"
    ],
    "wof:name":"Charlies Vending Inc",
    "wof:placetype":"venue"
},
  "geometry": {"coordinates":[-87.497321,41.555969],"type":"Point"}
}