{
  "type": "Feature",
  "properties": {
    "iso:country":"US",
    "sg:address":"1111 N Lebanon St",
    "sg:city":"Lebanon",
    "sg:classifiers":[
        {
            "category":"Health Services",
            "subcategory":"Optometrist",
            "type":"Services"
        }
    ],
    "sg:phone":"+1 765 482 2066",
    "sg:postcode":"46052",
    "sg:province":"IN",
    "wof:name":"Robert E Kline OD",
    "wof:placetype":"venue"
},
  "geometry": {"coordinates":[-86.47057599999999,40.056598],"type":"Point"}
}