{
  "type": "Feature",
  "properties": {
    "addr:full":"2332 E 151st St Carmel IN 46033",
    "addr:housenumber":"2332",
    "addr:postcode":"46033",
    "addr:street":"E 151St St",
    "iso:country":"US",
    "sg:address":"2332 E 151st St",
    "sg:city":"Carmel",
    "sg:classifiers":[
        {
            "category":"Autos & Motor Vehicles",
            "subcategory":"Automobile Sales",
            "type":"Retail Goods"
        },
        {
            "category":"Wholesale",
            "subcategory":"Electrical",
            "type":"Manufacturing & Wholesale Goods"
        }
    ],
    "sg:phone":"+1 317 815 8828",
    "sg:postcode":"46033",
    "sg:province":"IN",
    "sg:tags":[
        "electric"
    ],
    "wof:name":"Crmel Classic Motors",
    "wof:placetype":"venue"
},
  "geometry": {"coordinates":[-86.118268,40.007609],"type":"Point"}
}