{
  "type": "Feature",
  "properties": {
    "iso:country":"US",
    "sg:address":"404 5th St",
    "sg:city":"Florence",
    "sg:classifiers":[
        {
            "category":"Government",
            "subcategory":"Post Office",
            "type":"Public Place"
        }
    ],
    "sg:phone":"+1 812 594 2830",
    "sg:postcode":"47020",
    "sg:province":"IN",
    "wof:name":"US Post Office",
    "wof:placetype":"venue"
},
  "geometry": {"coordinates":[-84.924938,38.785022],"type":"Point"}
}