{
  "type": "Feature",
  "properties": {
    "iso:country":"US",
    "sg:address":"406 S Meridian St",
    "sg:city":"Winchester",
    "sg:classifiers":[
        {
            "category":"Manufacturing",
            "subcategory":"Printing",
            "type":"Manufacturing & Wholesale Goods"
        }
    ],
    "sg:phone":"+1 765 584 7575",
    "sg:postcode":"47394",
    "sg:province":"IN",
    "sg:tags":[
        "commercial"
    ],
    "wof:name":"H & S Printing Svc",
    "wof:placetype":"venue"
},
  "geometry": {"coordinates":[-84.982531,40.169241],"type":"Point"}
}