{
  "type": "Feature",
  "properties": {
    "iso:country":"US",
    "sg:address":"3035 S Meridian St Ste A",
    "sg:city":"Indianapolis",
    "sg:classifiers":[
        {
            "category":"Taxi",
            "type":"Transportation"
        },
        {
            "category":"Professional",
            "subcategory":"Business Services",
            "type":"Services"
        },
        {
            "category":"Government",
            "subcategory":"Post Office",
            "type":"Public Place"
        }
    ],
    "sg:phone":"+1 317 791 0611",
    "sg:postcode":"46217",
    "sg:province":"IN",
    "sg:tags":[
        "delivery",
        "messenger",
        "courier"
    ],
    "sg:website":"http://www.fastreactiondelivery.biz",
    "wof:name":"Bottomline Courier Corp",
    "wof:placetype":"venue"
},
  "geometry": {"coordinates":[-86.158739,39.721655],"type":"Point"}
}