{
  "type": "Feature",
  "properties": {
    "iso:country":"US",
    "sg:address":"7207 Indianapolis Blvd",
    "sg:city":"Hammond",
    "sg:classifiers":[
        {
            "category":"Professional",
            "subcategory":"Lawyer & Legal Services",
            "type":"Services"
        }
    ],
    "sg:phone":"+1 219 845 9540",
    "sg:postcode":"46324",
    "sg:province":"IN",
    "sg:tags":[
        "attorney"
    ],
    "wof:name":"Szarmach & Fernandez",
    "wof:placetype":"venue"
},
  "geometry": {"coordinates":[-87.480852,41.581225],"type":"Point"}
}