{
  "type": "Feature",
  "properties": {
    "iso:country":"US",
    "sg:address":"6267 N 825 E",
    "sg:city":"Mentone",
    "sg:classifiers":[
        {
            "category":"Banks & Credit Unions",
            "subcategory":"Bank",
            "type":"Services"
        }
    ],
    "sg:phone":"+1 574 353 7314",
    "sg:postcode":"46539",
    "sg:province":"IN",
    "sg:tags":[
        "broker"
    ],
    "wof:name":"Fareway Mortgage",
    "wof:placetype":"venue"
},
  "geometry": {"coordinates":[-86.091387,41.144847],"type":"Point"}
}