{
  "type": "Feature",
  "properties": {
    "iso:country":"US",
    "sg:address":"4651 S US Hwy 41",
    "sg:city":"Terre Haute",
    "sg:classifiers":[
        {
            "category":"Retail",
            "subcategory":"Portrait Studio",
            "type":"Services"
        }
    ],
    "sg:phone":"+1 812 298 0267",
    "sg:postcode":"47802",
    "sg:province":"IN",
    "sg:tags":[
        "photographer"
    ],
    "wof:name":"Olan Mills Portrait Studio",
    "wof:placetype":"venue"
},
  "geometry": {"coordinates":[-87.412621,39.410957],"type":"Point"}
}