{
  "type": "Feature",
  "properties": {
    "iso:country":"US",
    "sg:address":"15135 Hawthorne Ct",
    "sg:city":"Cedar Lake",
    "sg:classifiers":[
        {
            "category":"Real Estate",
            "subcategory":"Architect",
            "type":"Services"
        }
    ],
    "sg:phone":"+1 219 696 6626",
    "sg:postcode":"46303",
    "sg:province":"IN",
    "sg:tags":[
        "building",
        "construction"
    ],
    "wof:name":"JCB Co",
    "wof:placetype":"venue"
},
  "geometry": {"coordinates":[-87.478261,41.344672],"type":"Point"}
}