{
  "type": "Feature",
  "properties": {
    "iso:country":"US",
    "sg:address":"1120 W 15th St",
    "sg:city":"Auburn",
    "sg:classifiers":[
        {
            "category":"Retail",
            "subcategory":"Portrait Studio",
            "type":"Services"
        }
    ],
    "sg:phone":"+1 260 927 9115",
    "sg:postcode":"46706",
    "sg:province":"IN",
    "sg:tags":[
        "photographer"
    ],
    "wof:name":"Fifteenth Street Portraits",
    "wof:placetype":"venue"
},
  "geometry": {"coordinates":[-85.070447,41.362385],"type":"Point"}
}