{
  "type": "Feature",
  "properties": {
    "iso:country":"US",
    "sg:address":"6501 Grape Rd",
    "sg:city":"Mishawaka",
    "sg:classifiers":[
        {
            "category":"Ice Cream",
            "type":"Food & Drink"
        }
    ],
    "sg:menulink":"http://www.allmenus.com/in/georgetown/227628-dippin-dots/menu/",
    "sg:phone":"+1 574 271 0907",
    "sg:postcode":"46545",
    "sg:province":"IN",
    "sg:tags":[
        "american"
    ],
    "wof:name":"Dippin' Dots",
    "wof:placetype":"venue"
},
  "geometry": {"coordinates":[-86.187601,41.716343],"type":"Point"}
}