{
  "type": "Feature",
  "properties": {
    "iso:country":"US",
    "sg:address":"1033 3rd Ave SW",
    "sg:city":"Carmel",
    "sg:classifiers":[
        {
            "category":"Professional",
            "subcategory":"Management & Consulting",
            "type":"Services"
        }
    ],
    "sg:phone":"+1 317 582 0953",
    "sg:postcode":"46032",
    "sg:province":"IN",
    "sg:tags":[
        "consultant"
    ],
    "wof:name":"EJH Consulting",
    "wof:placetype":"venue"
},
  "geometry": {"coordinates":[-86.131862,39.963317],"type":"Point"}
}