{
  "type": "Feature",
  "properties": {
    "iso:country":"US",
    "sg:address":"2120 S Harrison St",
    "sg:city":"Fort Wayne",
    "sg:classifiers":[
        {
            "category":"Restaurant",
            "type":"Food & Drink"
        }
    ],
    "sg:phone":"+1 260 745 7467",
    "sg:postcode":"46802",
    "sg:province":"IN",
    "sg:tags":[
        "caterer"
    ],
    "wof:name":"Hungry For Home",
    "wof:placetype":"venue"
},
  "geometry": {"coordinates":[-85.139464,41.065503],"type":"Point"}
}