{
  "type": "Feature",
  "properties": {
    "iso:country":"US",
    "sg:address":"701 Kentucky Ave",
    "sg:city":"Indianapolis",
    "sg:classifiers":[
        {
            "category":"Manufacturing",
            "subcategory":"Metals",
            "type":"Manufacturing & Wholesale Goods"
        }
    ],
    "sg:phone":"+1 317 635 1177",
    "sg:postcode":"46225",
    "sg:province":"IN",
    "sg:tags":[
        "steel"
    ],
    "wof:name":"Custom Fabricating Inc",
    "wof:placetype":"venue"
},
  "geometry": {"coordinates":[-86.17214800000001,39.757828],"type":"Point"}
}