{
  "type": "Feature",
  "properties": {
    "iso:country":"US",
    "sg:address":"6319 Kentstone Dr",
    "sg:city":"Indianapolis",
    "sg:classifiers":[
        {
            "category":"Professional",
            "subcategory":"Business Services",
            "type":"Services"
        }
    ],
    "sg:phone":"+1 317 297 4687",
    "sg:postcode":"46268",
    "sg:province":"IN",
    "wof:name":"Farris Holding Group Inc",
    "wof:placetype":"venue"
},
  "geometry": {"coordinates":[-86.21916299999999,39.873003],"type":"Point"}
}