{
  "type": "Feature",
  "properties": {
    "iso:country":"US",
    "sg:address":"8611 Allisonville Rd",
    "sg:city":"Indianapolis",
    "sg:classifiers":[
        {
            "category":"Shopping",
            "subcategory":"Musical Instruments",
            "type":"Retail Goods"
        }
    ],
    "sg:phone":"+1 317 849 8848",
    "sg:postcode":"46250",
    "sg:province":"IN",
    "wof:name":"Guitars & More Music Ctr",
    "wof:placetype":"venue"
},
  "geometry": {"coordinates":[-86.073882,39.914669],"type":"Point"}
}