{
  "type": "Feature",
  "properties": {
    "iso:country":"US",
    "sg:address":"1635 Broadway",
    "sg:city":"Fort Wayne",
    "sg:classifiers":[
        {
            "category":"Manufacturing",
            "subcategory":"Tools & Machinery",
            "type":"Manufacturing & Wholesale Goods"
        }
    ],
    "sg:phone":"+1 260 439 2000",
    "sg:postcode":"46802",
    "sg:province":"IN",
    "sg:tags":[
        "motor",
        "generator"
    ],
    "wof:name":"GE Co",
    "wof:placetype":"venue"
},
  "geometry": {"coordinates":[-85.148327,41.072168],"type":"Point"}
}