{
  "type": "Feature",
  "properties": {
    "iso:country":"US",
    "sg:address":"56577 Hollywood Blvd",
    "sg:city":"South Bend",
    "sg:classifiers":[
        {
            "category":"Organizations",
            "subcategory":"Religious Organization",
            "type":"Services"
        }
    ],
    "sg:phone":"+1 574 287 7843",
    "sg:postcode":"46619",
    "sg:province":"IN",
    "wof:name":"Holy Family Athletic Dept",
    "wof:placetype":"venue"
},
  "geometry": {"coordinates":[-86.32459,41.670732],"type":"Point"}
}