{
  "type": "Feature",
  "properties": {
    "addr:full":"412 Mulberry St Madison IN 47250",
    "addr:housenumber":"412",
    "addr:postcode":"47250",
    "addr:street":"Mulberry St",
    "iso:country":"US",
    "sg:address":"412 Mulberry St",
    "sg:city":"Madison",
    "sg:classifiers":[
        {
            "category":"Professional",
            "type":"Services"
        }
    ],
    "sg:phone":"+1 812 265 0099",
    "sg:postcode":"47250",
    "sg:province":"IN",
    "sg:tags":[
        "establishment"
    ],
    "wof:name":"Linda's",
    "wof:placetype":"venue"
},
  "geometry": {"coordinates":[-85.37871699999999,38.73673],"type":"Point"}
}