{
  "type": "Feature",
  "properties": {
    "iso:country":"US",
    "sg:address":"900 E 7th St",
    "sg:city":"Bloomington",
    "sg:classifiers":[
        {
            "category":"Restaurant",
            "type":"Food & Drink"
        }
    ],
    "sg:phone":"+1 812 855 2065",
    "sg:postcode":"47405",
    "sg:province":"IN",
    "wof:name":"Burger King",
    "wof:placetype":"venue"
},
  "geometry": {"coordinates":[-86.522337,39.168478],"type":"Point"}
}