{
  "type": "Feature",
  "properties": {
    "iso:country":"US",
    "sg:address":"3401 S US Hwy 41",
    "sg:city":"Terre Haute",
    "sg:classifiers":[
        {
            "category":"Professional",
            "subcategory":"Accounting & Tax Preparation",
            "type":"Services"
        }
    ],
    "sg:phone":"+1 812 234 9640",
    "sg:postcode":"47802",
    "sg:province":"IN",
    "sg:tags":[
        "return",
        "filing"
    ],
    "sg:website":"www.hrblock.com",
    "wof:name":"H & R Block Tax Svc",
    "wof:placetype":"venue"
},
  "geometry": {"coordinates":[-87.416135,39.424134],"type":"Point"}
}