{
  "type": "Feature",
  "properties": {
    "addr:full":"714 S Michigan St South Bend IN 46601",
    "addr:housenumber":"714",
    "addr:postcode":"46601",
    "addr:street":"S Michigan St",
    "iso:country":"US",
    "sg:address":"714 S Michigan St",
    "sg:city":"South Bend",
    "sg:classifiers":[
        {
            "category":"Health Services",
            "subcategory":"Doctor",
            "type":"Services"
        }
    ],
    "sg:phone":"+1 574 647 7477",
    "sg:postcode":"46601",
    "sg:province":"IN",
    "sg:tags":[
        "clinic"
    ],
    "wof:name":"E Blair Warner Family Practice",
    "wof:placetype":"venue"
},
  "geometry": {"coordinates":[-86.250069,41.66648],"type":"Point"}
}