{
  "type": "Feature",
  "properties": {
    "addr:full":"400 Legacy Pkwy Laporte IN 46350",
    "addr:housenumber":"400",
    "addr:postcode":"46350",
    "addr:street":"Legacy Pkwy",
    "iso:country":"US",
    "sg:address":"400 Legacy Pkwy",
    "sg:city":"Laporte",
    "sg:classifiers":[
        {
            "category":"Organizations",
            "subcategory":"Non-profit Organization",
            "type":"Services"
        }
    ],
    "sg:phone":"+1 219 326 6277",
    "sg:postcode":"46350",
    "sg:province":"IN",
    "sg:tags":[
        "disability"
    ],
    "wof:name":"Dungarvin Indiana Inc",
    "wof:placetype":"venue"
},
  "geometry": {"coordinates":[-86.69361600000001,41.601577],"type":"Point"}
}