{
  "type": "Feature",
  "properties": {
    "addr:full":"2009 N 9th Street Rd Lafayette IN 47904",
    "addr:housenumber":"2009",
    "addr:postcode":"47904",
    "addr:street":"N 9Th Street Rd",
    "iso:country":"US",
    "sg:address":"2009 N 9th Street Rd",
    "sg:city":"Lafayette",
    "sg:classifiers":[
        {
            "category":"Freight",
            "type":"Transportation"
        }
    ],
    "sg:phone":"+1 765 742 6116",
    "sg:postcode":"47904",
    "sg:province":"IN",
    "sg:tags":[
        "trucking"
    ],
    "wof:name":"Shaffer Trucking Div",
    "wof:placetype":"venue"
},
  "geometry": {"coordinates":[-86.885733,40.4372],"type":"Point"}
}