{
  "type": "Feature",
  "properties": {
    "iso:country":"US",
    "sg:address":"1060 N Anderson St",
    "sg:city":"Elwood",
    "sg:classifiers":[
        {
            "category":"Manufacturing",
            "subcategory":"Furniture",
            "type":"Manufacturing & Wholesale Goods"
        }
    ],
    "sg:phone":"+1 765 552 5166",
    "sg:postcode":"46036",
    "sg:province":"IN",
    "sg:tags":[
        "upholstered",
        "wood"
    ],
    "wof:name":"Old Time Woodwork",
    "wof:placetype":"venue"
},
  "geometry": {"coordinates":[-85.841845,40.286302],"type":"Point"}
}