{
  "type": "Feature",
  "properties": {
    "iso:country":"US",
    "sg:address":"955 Co Rd W 400 S",
    "sg:city":"Kokomo",
    "sg:classifiers":[
        {
            "category":"Organizations",
            "subcategory":"Religious Organization",
            "type":"Services"
        }
    ],
    "sg:phone":"+1 765 453 4409",
    "sg:postcode":"46902",
    "sg:province":"IN",
    "sg:tags":[
        "church"
    ],
    "wof:name":"Southview Assembly Of God",
    "wof:placetype":"venue"
},
  "geometry": {"coordinates":[-86.140609,40.418682],"type":"Point"}
}