{
  "type": "Feature",
  "properties": {
    "iso:country":"US",
    "sg:address":"1725 Farmersville Rd",
    "sg:city":"Mount Vernon",
    "sg:classifiers":[
        {
            "category":"Farming",
            "subcategory":"Livestock Farm",
            "type":"Manufacturing & Wholesale Goods"
        }
    ],
    "sg:phone":"+1 812 838 4943",
    "sg:postcode":"47620",
    "sg:province":"IN",
    "sg:tags":[
        "equine"
    ],
    "wof:name":"Adamsons Appaloosa",
    "wof:placetype":"venue"
},
  "geometry": {"coordinates":[-87.894602,37.980423],"type":"Point"}
}