{
  "type": "Feature",
  "properties": {
    "iso:country":"US",
    "sg:address":"1621 Kerry Ct",
    "sg:city":"South Bend",
    "sg:classifiers":[
        {
            "category":"Professional",
            "subcategory":"Computer Services",
            "type":"Services"
        }
    ],
    "sg:phone":"+1 574 299 0234",
    "sg:postcode":"46614",
    "sg:province":"IN",
    "sg:tags":[
        "prepackaged",
        "school",
        "processing",
        "datum",
        "software"
    ],
    "wof:name":"Computer Helpers",
    "wof:placetype":"venue"
},
  "geometry": {"coordinates":[-86.221619,41.633438],"type":"Point"}
}