{
  "type": "Feature",
  "properties": {
    "iso:country":"US",
    "sg:address":"3801 National Rd E",
    "sg:city":"Richmond",
    "sg:classifiers":[
        {
            "category":"Food & Beverages",
            "subcategory":"Specialty",
            "type":"Retail Goods"
        }
    ],
    "sg:phone":"+1 765 962 3263",
    "sg:postcode":"47374",
    "sg:province":"IN",
    "sg:tags":[
        "health",
        "diet"
    ],
    "wof:name":"GNC",
    "wof:placetype":"venue"
},
  "geometry": {"coordinates":[-84.845767,39.831024],"type":"Point"}
}