{
  "type": "Feature",
  "properties": {
    "iso:country":"US",
    "sg:address":"1551 Clifty Dr",
    "sg:city":"Madison",
    "sg:classifiers":[
        {
            "category":"Manufacturing",
            "subcategory":"Chemicals & Compounds",
            "type":"Manufacturing & Wholesale Goods"
        }
    ],
    "sg:phone":"+1 812 273 2744",
    "sg:postcode":"47250",
    "sg:province":"IN",
    "sg:tags":[
        "plastic"
    ],
    "wof:name":"Gem Plastics Co Inc",
    "wof:placetype":"venue"
},
  "geometry": {"coordinates":[-85.419614,38.771385],"type":"Point"}
}