{
  "type": "Feature",
  "properties": {
    "addr:full":"302 Main St Tell City IN 47586",
    "addr:housenumber":"302",
    "addr:postcode":"47586",
    "addr:street":"Main St",
    "iso:country":"US",
    "sg:address":"302 Main St",
    "sg:city":"Tell City",
    "sg:classifiers":[
        {
            "category":"Building & Trades",
            "subcategory":"Cleaning & Sanitation",
            "type":"Services"
        }
    ],
    "sg:phone":"+1 812 547 8209",
    "sg:postcode":"47586",
    "sg:province":"IN",
    "sg:tags":[
        "maintenance"
    ],
    "wof:name":"Quality Cleaning Services",
    "wof:placetype":"venue"
},
  "geometry": {"coordinates":[-86.76975899999999,37.945235],"type":"Point"}
}