{
  "type": "Feature",
  "properties": {
    "iso:country":"US",
    "sg:address":"2012 S Park Ave",
    "sg:city":"Alexandria",
    "sg:classifiers":[
        {
            "category":"Health Services",
            "subcategory":"Doctor",
            "type":"Services"
        }
    ],
    "sg:phone":"+1 765 724 6226",
    "sg:postcode":"46001",
    "sg:province":"IN",
    "sg:tags":[
        "clinic"
    ],
    "wof:name":"Alexandria Health Ctr",
    "wof:placetype":"venue"
},
  "geometry": {"coordinates":[-85.671328,40.248713],"type":"Point"}
}