{
  "type": "Feature",
  "properties": {
    "iso:country":"US",
    "sg:address":"2268 Oakdale Ave",
    "sg:city":"Highland",
    "sg:classifiers":[
        {
            "category":"Building & Trades",
            "subcategory":"Cleaning & Sanitation",
            "type":"Services"
        }
    ],
    "sg:phone":"+1 219 923 5287",
    "sg:postcode":"46322",
    "sg:province":"IN",
    "sg:tags":[
        "maintenance",
        "merchandise"
    ],
    "wof:name":"Minority Safety Dist Svcs",
    "wof:placetype":"venue"
},
  "geometry": {"coordinates":[-87.473221,41.554746],"type":"Point"}
}