{
  "type": "Feature",
  "properties": {
    "iso:country":"US",
    "sg:address":"1250 N Lincoln Rd",
    "sg:city":"Rockville",
    "sg:classifiers":[
        {
            "category":"Food & Beverages",
            "subcategory":"Groceries & Convenience Stores",
            "type":"Retail Goods"
        }
    ],
    "sg:phone":"+1 765 569 3149",
    "sg:postcode":"47872",
    "sg:province":"IN",
    "sg:tags":[
        "grocer"
    ],
    "wof:name":"Rockville IGA",
    "wof:placetype":"venue"
},
  "geometry": {"coordinates":[-87.236168,39.775501],"type":"Point"}
}