{
  "type": "Feature",
  "properties": {
    "iso:country":"US",
    "sg:address":"1100 S Green River Rd",
    "sg:city":"Evansville",
    "sg:classifiers":[
        {
            "category":"Shopping",
            "subcategory":"Department Store",
            "type":"Retail Goods"
        }
    ],
    "sg:phone":"+1 812 473 8228",
    "sg:postcode":"47715",
    "sg:province":"IN",
    "sg:website":"www.sears.com",
    "wof:name":"Sears Roebuck & Co",
    "wof:placetype":"venue"
},
  "geometry": {"coordinates":[-87.49263999999999,37.961832],"type":"Point"}
}