{
  "type": "Feature",
  "properties": {
    "iso:country":"US",
    "sg:address":"223 E 63rd St",
    "sg:city":"Indianapolis",
    "sg:classifiers":[
        {
            "category":"Retail",
            "subcategory":"Repair Shop",
            "type":"Services"
        }
    ],
    "sg:phone":"+1 317 253 8474",
    "sg:postcode":"46220",
    "sg:province":"IN",
    "sg:tags":[
        "refinish",
        "furniture"
    ],
    "wof:name":"Broad Ripple Refinishing Inc",
    "wof:placetype":"venue"
},
  "geometry": {"coordinates":[-86.153367,39.870318],"type":"Point"}
}