{
  "type": "Feature",
  "properties": {
    "iso:country":"US",
    "sg:address":"3555 W State Rte 62",
    "sg:city":"Boonville",
    "sg:classifiers":[
        {
            "category":"Building & Trades",
            "subcategory":"Equipment Rental",
            "type":"Services"
        }
    ],
    "sg:phone":"+1 812 897 0777",
    "sg:postcode":"47601",
    "sg:province":"IN",
    "sg:tags":[
        "leasing"
    ],
    "sg:website":"www.ruan.com",
    "wof:name":"Ruan Leasing Co",
    "wof:placetype":"venue"
},
  "geometry": {"coordinates":[-87.316855,38.04832],"type":"Point"}
}