{
  "type": "Feature",
  "properties": {
    "iso:country":"US",
    "sg:address":"11917 State Rd 120",
    "sg:city":"Middlebury",
    "sg:classifiers":[
        {
            "category":"Building & Trades",
            "subcategory":"Construction",
            "type":"Services"
        }
    ],
    "sg:phone":"+1 574 825 5791",
    "sg:postcode":"46540",
    "sg:province":"IN",
    "sg:tags":[
        "contractor"
    ],
    "wof:name":"Riteway Builders Inc",
    "wof:placetype":"venue"
},
  "geometry": {"coordinates":[-85.657219,41.725997],"type":"Point"}
}