{
  "type": "Feature",
  "properties": {
    "iso:country":"US",
    "sg:address":"330 E Perry Rd",
    "sg:city":"Ligonier",
    "sg:classifiers":[
        {
            "category":"Personal",
            "subcategory":"Beauty Salon",
            "type":"Services"
        }
    ],
    "sg:phone":"+1 260 894 3316",
    "sg:postcode":"46767",
    "sg:province":"IN",
    "wof:name":"Creative Dimensions",
    "wof:placetype":"venue"
},
  "geometry": {"coordinates":[-85.592855,41.481399],"type":"Point"}
}