{
  "type": "Feature",
  "properties": {
    "iso:country":"US",
    "sg:address":"6060 N College Ave",
    "sg:city":"Indianapolis",
    "sg:classifiers":[
        {
            "category":"Health Services",
            "subcategory":"Health Practitioner",
            "type":"Services"
        }
    ],
    "sg:phone":"+1 317 254 1132",
    "sg:postcode":"46220",
    "sg:province":"IN",
    "sg:tags":[
        "nurse",
        "registry"
    ],
    "sg:website":"www.rnspecialties.com",
    "wof:name":"R N Specialties Inc",
    "wof:placetype":"venue"
},
  "geometry": {"coordinates":[-86.146119,39.864534],"type":"Point"}
}