{
  "type": "Feature",
  "properties": {
    "iso:country":"US",
    "sg:address":"2310 Allison Ln",
    "sg:city":"Jeffersonville",
    "sg:classifiers":[
        {
            "category":"Health Services",
            "subcategory":"Doctor",
            "type":"Services"
        }
    ],
    "sg:phone":"+1 812 288 7135",
    "sg:postcode":"47130",
    "sg:province":"IN",
    "sg:tags":[
        "dentist"
    ],
    "wof:name":"Harris & Coomer",
    "wof:placetype":"venue"
},
  "geometry": {"coordinates":[-85.708355,38.317846],"type":"Point"}
}