{
  "type": "Feature",
  "properties": {
    "iso:country":"US",
    "sg:address":"3313 45th St",
    "sg:city":"Highland",
    "sg:classifiers":[
        {
            "category":"Health Services",
            "subcategory":"Podiatrist",
            "type":"Services"
        }
    ],
    "sg:phone":"+1 219 924 1042",
    "sg:postcode":"46322",
    "sg:province":"IN",
    "wof:name":"Highland Foot Clinic",
    "wof:placetype":"venue"
},
  "geometry": {"coordinates":[-87.448962,41.537491],"type":"Point"}
}