{
  "type": "Feature",
  "properties": {
    "iso:country":"US",
    "sg:address":"6688 W Co Rd 200 S",
    "sg:city":"Frankfort",
    "sg:classifiers":[
        {
            "category":"Personal",
            "subcategory":"Tanning Parlor",
            "type":"Services"
        }
    ],
    "sg:phone":"+1 765 654 6761",
    "sg:postcode":"46041",
    "sg:province":"IN",
    "sg:tags":[
        "salon"
    ],
    "wof:name":"Ike's Jamaica Me Tan",
    "wof:placetype":"venue"
},
  "geometry": {"coordinates":[-86.63635,40.257864],"type":"Point"}
}