{
  "type": "Feature",
  "properties": {
    "iso:country":"US",
    "sg:address":"2327 Delaware St",
    "sg:city":"Anderson",
    "sg:classifiers":[
        {
            "category":"Building & Trades",
            "subcategory":"Plumbing",
            "type":"Services"
        }
    ],
    "sg:phone":"+1 765 644 3358",
    "sg:postcode":"46016",
    "sg:province":"IN",
    "sg:tags":[
        "heating",
        "contractor"
    ],
    "wof:name":"Nardco Heating & Air Cond",
    "wof:placetype":"venue"
},
  "geometry": {"coordinates":[-85.68152000000001,40.09278],"type":"Point"}
}