{
  "type": "Feature",
  "properties": {
    "iso:country":"US",
    "sg:address":"3211 W Division Rd",
    "sg:city":"Bargersville",
    "sg:classifiers":[
        {
            "category":"Farming",
            "subcategory":"Farm",
            "type":"Manufacturing & Wholesale Goods"
        }
    ],
    "sg:phone":"+1 317 422 9565",
    "sg:postcode":"46106",
    "sg:province":"IN",
    "sg:tags":[
        "crop",
        "general"
    ],
    "wof:name":"Lloyd & Ethel Morris",
    "wof:placetype":"venue"
},
  "geometry": {"coordinates":[-86.162356,39.47628],"type":"Point"}
}