{
  "type": "Feature",
  "properties": {
    "iso:country":"US",
    "sg:address":"2120 S US Hwy 35",
    "sg:city":"Knox",
    "sg:classifiers":[
        {
            "category":"Wholesale",
            "subcategory":"Vending Machines",
            "type":"Manufacturing & Wholesale Goods"
        }
    ],
    "sg:phone":"+1 574 772 3012",
    "sg:postcode":"46534",
    "sg:province":"IN",
    "sg:tags":[
        "operated",
        "phonograph"
    ],
    "wof:name":"Automatic Music Inc",
    "wof:placetype":"venue"
},
  "geometry": {"coordinates":[-86.620563,41.271888],"type":"Point"}
}