{
  "type": "Feature",
  "properties": {
    "addr:full":"6785 Woodcliff Cir Zionsville IN 46077",
    "addr:housenumber":"6785",
    "addr:postcode":"46077",
    "addr:street":"Woodcliff Cir",
    "iso:country":"US",
    "sg:address":"6785 Woodcliff Cir",
    "sg:city":"Zionsville",
    "sg:classifiers":[
        {
            "category":"Wholesale",
            "subcategory":"Machinery & Supplies",
            "type":"Manufacturing & Wholesale Goods"
        }
    ],
    "sg:phone":"+1 317 733 9201",
    "sg:postcode":"46077",
    "sg:province":"IN",
    "sg:tags":[
        "director",
        "equipment",
        "funeral"
    ],
    "wof:name":"Indianapolis Fnrl Escort Svc",
    "wof:placetype":"venue"
},
  "geometry": {"coordinates":[-86.33335099999999,39.939875],"type":"Point"}
}