{
  "type": "Feature",
  "properties": {
    "iso:country":"US",
    "sg:address":"330 N Bolton Ave",
    "sg:city":"Indianapolis",
    "sg:classifiers":[
        {
            "category":"Real Estate",
            "subcategory":"Real Estate Agent",
            "type":"Services"
        }
    ],
    "sg:phone":"+1 317 357 4663",
    "sg:postcode":"46219",
    "sg:province":"IN",
    "wof:name":"Irvington Realty",
    "wof:placetype":"venue"
},
  "geometry": {"coordinates":[-86.067308,39.77464],"type":"Point"}
}