{
  "type": "Feature",
  "properties": {
    "iso:country":"US",
    "sg:address":"7272 Fishers Crossing Dr",
    "sg:city":"Fishers",
    "sg:classifiers":[
        {
            "category":"Banks & Credit Unions",
            "subcategory":"Bank",
            "type":"Services"
        }
    ],
    "sg:phone":"+1 317 849 3497",
    "sg:postcode":"46038",
    "sg:province":"IN",
    "sg:tags":[
        "state"
    ],
    "sg:website":"www.53.com",
    "wof:name":"Fifth Third Bank",
    "wof:placetype":"venue"
},
  "geometry": {"coordinates":[-86.041901,39.957298],"type":"Point"}
}