{
  "type": "Feature",
  "properties": {
    "addr:full":"16718 US Hwy 6 Syracuse IN 46567",
    "addr:housenumber":"16718",
    "addr:postcode":"46567",
    "addr:street":"Us Hwy 6",
    "iso:country":"US",
    "sg:address":"16718 US Hwy 6",
    "sg:city":"Syracuse",
    "sg:classifiers":[
        {
            "category":"Farming",
            "subcategory":"Livestock Farm",
            "type":"Manufacturing & Wholesale Goods"
        }
    ],
    "sg:phone":"+1 574 457 3661",
    "sg:postcode":"46567",
    "sg:province":"IN",
    "wof:name":"Lazy T Ranch",
    "wof:placetype":"venue"
},
  "geometry": {"coordinates":[-85.78133800000001,41.449868],"type":"Point"}
}