{
  "type": "Feature",
  "properties": {
    "iso:country":"US",
    "sg:address":"346 W Washington St",
    "sg:city":"Martinsville",
    "sg:classifiers":[
        {
            "category":"Personal",
            "subcategory":"Beauty Salon",
            "type":"Services"
        }
    ],
    "sg:phone":"+1 765 349 2919",
    "sg:postcode":"46151",
    "sg:province":"IN",
    "sg:tags":[
        "spa",
        "day"
    ],
    "wof:name":"Bella Mia Spa & Salon",
    "wof:placetype":"venue"
},
  "geometry": {"coordinates":[-86.432693,39.42698],"type":"Point"}
}