{
  "type": "Feature",
  "properties": {
    "iso:country":"US",
    "sg:address":"223 W 81st Ave",
    "sg:city":"Merrillville",
    "sg:classifiers":[
        {
            "category":"Home & Garden",
            "subcategory":"Household Appliances",
            "type":"Retail Goods"
        }
    ],
    "sg:phone":"+1 219 736 7397",
    "sg:postcode":"46410",
    "sg:province":"IN",
    "sg:tags":[
        "machine",
        "sewing"
    ],
    "wof:name":"Northwest Indiana Sewing Ctr",
    "wof:placetype":"venue"
},
  "geometry": {"coordinates":[-87.338875,41.471012],"type":"Point"}
}