{
  "type": "Feature",
  "properties": {
    "iso:country":"US",
    "sg:address":"606 Mulberry St",
    "sg:city":"Sellersburg",
    "sg:classifiers":[
        {
            "category":"Recreation",
            "type":"Entertainment"
        }
    ],
    "sg:phone":"+1 812 246 9270",
    "sg:postcode":"47172",
    "sg:province":"IN",
    "sg:tags":[
        "amusement"
    ],
    "wof:name":"West Clark Seacats Inc",
    "wof:placetype":"venue"
},
  "geometry": {"coordinates":[-85.758959,38.407432],"type":"Point"}
}