{
  "type": "Feature",
  "properties": {
    "iso:country":"US",
    "sg:address":"7200 E Chestnut St",
    "sg:city":"Evansville",
    "sg:classifiers":[
        {
            "category":"Manufacturing",
            "subcategory":"Apparel",
            "type":"Manufacturing & Wholesale Goods"
        }
    ],
    "sg:phone":"+1 812 473 3719",
    "sg:postcode":"47715",
    "sg:province":"IN",
    "wof:name":"River City Apparel",
    "wof:placetype":"venue"
},
  "geometry": {"coordinates":[-87.462725,37.972249],"type":"Point"}
}