{
  "type": "Feature",
  "properties": {
    "iso:country":"US",
    "sg:address":"7610 Lake Rd",
    "sg:city":"Indianapolis",
    "sg:classifiers":[
        {
            "category":"Building & Trades",
            "subcategory":"Landscaping Services",
            "type":"Services"
        }
    ],
    "sg:phone":"+1 317 882 9351",
    "sg:postcode":"46217",
    "sg:province":"IN",
    "sg:tags":[
        "topsoil"
    ],
    "wof:name":"Kopetsky Hauling",
    "wof:placetype":"venue"
},
  "geometry": {"coordinates":[-86.217926,39.644231],"type":"Point"}
}