{
  "type": "Feature",
  "properties": {
    "iso:country":"US",
    "sg:address":"11111 Dean St",
    "sg:city":"Charlestown",
    "sg:classifiers":[
        {
            "category":"Home & Garden",
            "subcategory":"Carpets & Floor Coverings",
            "type":"Retail Goods"
        }
    ],
    "sg:phone":"+1 812 256 5351",
    "sg:postcode":"47111",
    "sg:province":"IN",
    "sg:tags":[
        "dealer",
        "rug"
    ],
    "wof:name":"Bruce's Floor Covering",
    "wof:placetype":"venue"
},
  "geometry": {"coordinates":[-85.655529,38.443349],"type":"Point"}
}