{
  "type": "Feature",
  "properties": {
    "iso:country":"US",
    "sg:address":"705 N Indiana Ave",
    "sg:city":"Goshen",
    "sg:classifiers":[
        {
            "category":"Professional",
            "subcategory":"Business Services",
            "type":"Services"
        }
    ],
    "sg:phone":"+1 574 534 7372",
    "sg:postcode":"46528",
    "sg:province":"IN",
    "wof:name":"Goshen Auction Service",
    "wof:placetype":"venue"
},
  "geometry": {"coordinates":[-85.848428,41.593964],"type":"Point"}
}