{
  "type": "Feature",
  "properties": {
    "iso:country":"US",
    "sg:address":"2915 S 14th St",
    "sg:city":"New Castle",
    "sg:classifiers":[
        {
            "category":"Food & Beverages",
            "subcategory":"Groceries & Convenience Stores",
            "type":"Retail Goods"
        }
    ],
    "sg:phone":"+1 765 529 2006",
    "sg:postcode":"47362",
    "sg:province":"IN",
    "sg:tags":[
        "grocer"
    ],
    "wof:name":"Marsh Supermarket",
    "wof:placetype":"venue"
},
  "geometry": {"coordinates":[-85.36091500000001,39.904943],"type":"Point"}
}