{
  "type": "Feature",
  "properties": {
    "iso:country":"US",
    "sg:address":"5044 Epworth Rd",
    "sg:city":"Newburgh",
    "sg:classifiers":[
        {
            "category":"Professional",
            "type":"Services"
        }
    ],
    "sg:phone":"+1 812 842 0496",
    "sg:postcode":"47630",
    "sg:province":"IN",
    "wof:name":"Dfc Services",
    "wof:placetype":"venue"
},
  "geometry": {"coordinates":[-87.441311,37.965846],"type":"Point"}
}