{
  "type": "Feature",
  "properties": {
    "iso:country":"US",
    "sg:address":"641 Elm St",
    "sg:city":"Rockport",
    "sg:classifiers":[
        {
            "category":"Social Services",
            "subcategory":"Child Care",
            "type":"Services"
        }
    ],
    "sg:phone":"+1 812 649 4417",
    "sg:postcode":"47635",
    "sg:province":"IN",
    "wof:name":"St Bernard's Preschool & Dayca",
    "wof:placetype":"venue"
},
  "geometry": {"coordinates":[-87.05495500000001,37.884465],"type":"Point"}
}