{
  "type": "Feature",
  "properties": {
    "iso:country":"US",
    "sg:address":"1523 US Hwy 421",
    "sg:city":"Delphi",
    "sg:classifiers":[
        {
            "category":"Government",
            "subcategory":"Office",
            "type":"Public Place"
        }
    ],
    "sg:phone":"+1 765 564 3169",
    "sg:postcode":"46923",
    "sg:province":"IN",
    "wof:name":"Carroll County Cooperative Ext",
    "wof:placetype":"venue"
},
  "geometry": {"coordinates":[-86.659447,40.568627],"type":"Point"}
}