{
  "type": "Feature",
  "properties": {
    "iso:country":"US",
    "sg:address":"11642 W Laughery Creek Rd",
    "sg:city":"Dillsboro",
    "sg:classifiers":[
        {
            "category":"Banks & Credit Unions",
            "subcategory":"Financial Services",
            "type":"Services"
        }
    ],
    "sg:phone":"+1 812 667 2000",
    "sg:postcode":"47018",
    "sg:province":"IN",
    "sg:tags":[
        "international",
        "trade"
    ],
    "wof:name":"Secluded Valley Trading",
    "wof:placetype":"venue"
},
  "geometry": {"coordinates":[-85.039478,38.976662],"type":"Point"}
}