{
  "type": "Feature",
  "properties": {
    "iso:country":"US",
    "sg:address":"664 W 100 N",
    "sg:city":"Williamsport",
    "sg:classifiers":[
        {
            "category":"Social Services",
            "type":"Services"
        }
    ],
    "sg:phone":"+1 765 762 2049",
    "sg:postcode":"47993",
    "sg:province":"IN",
    "sg:tags":[
        "counselor",
        "marriage",
        "family"
    ],
    "wof:name":"Elle Char",
    "wof:placetype":"venue"
},
  "geometry": {"coordinates":[-87.33286,40.331143],"type":"Point"}
}