{
  "type": "Feature",
  "properties": {
    "iso:country":"US",
    "sg:address":"1931 Stout Field West Dr",
    "sg:city":"Indianapolis",
    "sg:classifiers":[
        {
            "category":"Professional",
            "subcategory":"Engineering",
            "type":"Services"
        },
        {
            "category":"Professional",
            "subcategory":"Business Services",
            "type":"Services"
        },
        {
            "category":"Professional",
            "subcategory":"Management & Consulting",
            "type":"Services"
        }
    ],
    "sg:phone":"+1 317 248 0415",
    "sg:postcode":"46241",
    "sg:province":"IN",
    "sg:tags":[
        "consultant",
        "product",
        "engineer",
        "ecological",
        "environmental"
    ],
    "wof:name":"Pettit Environmental",
    "wof:placetype":"venue"
},
  "geometry": {"coordinates":[-86.234368,39.740781],"type":"Point"}
}