{
  "type": "Feature",
  "properties": {
    "iso:country":"US",
    "sg:address":"58800 Executive Dr",
    "sg:city":"Mishawaka",
    "sg:classifiers":[
        {
            "category":"Travel",
            "subcategory":"Travel Agent",
            "type":"Entertainment"
        }
    ],
    "sg:phone":"+1 574 258 0612",
    "sg:postcode":"46544",
    "sg:province":"IN",
    "sg:tags":[
        "tours",
        "promoter"
    ],
    "sg:website":"www.recclub.com",
    "wof:name":"Recreational Club Mgmt Inc",
    "wof:placetype":"venue"
},
  "geometry": {"coordinates":[-86.148967,41.641361],"type":"Point"}
}