{
  "type": "Feature",
  "properties": {
    "addr:full":"145 W Walnut St Hagerstown IN 47346",
    "addr:housenumber":"145",
    "addr:postcode":"47346",
    "addr:street":"W Walnut St",
    "iso:country":"US",
    "sg:address":"145 W Walnut St",
    "sg:city":"Hagerstown",
    "sg:classifiers":[
        {
            "category":"Organizations",
            "subcategory":"Religious Organization",
            "type":"Services"
        }
    ],
    "sg:phone":"+1 765 489 4898",
    "sg:postcode":"47346",
    "sg:province":"IN",
    "sg:tags":[
        "church"
    ],
    "wof:name":"Hagerstown Faith Housing Inc",
    "wof:placetype":"venue"
},
  "geometry": {"coordinates":[-85.163443,39.909947],"type":"Point"}
}