{
  "type": "Feature",
  "properties": {
    "addr:full":"110 E Main St Van Buren IN 46991",
    "addr:housenumber":"110",
    "addr:postcode":"46991",
    "addr:street":"E Main St",
    "iso:country":"US",
    "sg:address":"110 E Main St",
    "sg:city":"Van Buren",
    "sg:classifiers":[
        {
            "category":"Bars & Pubs",
            "type":"Food & Drink"
        }
    ],
    "sg:phone":"+1 765 934 2627",
    "sg:postcode":"46991",
    "sg:province":"IN",
    "wof:name":"Time-Out Tavern Inc",
    "wof:placetype":"venue"
},
  "geometry": {"coordinates":[-85.504532,40.617425],"type":"Point"}
}