{
  "type": "Feature",
  "properties": {
    "iso:country":"US",
    "sg:address":"250 N Wayne St",
    "sg:city":"Waterloo",
    "sg:classifiers":[
        {
            "category":"Insurance",
            "subcategory":"Insurance Agent",
            "type":"Services"
        }
    ],
    "sg:phone":"+1 260 837 7601",
    "sg:postcode":"46793",
    "sg:province":"IN",
    "wof:name":"Baker Insurance",
    "wof:placetype":"venue"
},
  "geometry": {"coordinates":[-85.019892,41.431999],"type":"Point"}
}