{
  "type": "Feature",
  "properties": {
    "addr:full":"409 S Lincoln St Kendallville IN 46755",
    "addr:housenumber":"409",
    "addr:postcode":"46755",
    "addr:street":"S Lincoln St",
    "iso:country":"US",
    "sg:address":"409 S Lincoln St",
    "sg:city":"Kendallville",
    "sg:classifiers":[
        {
            "category":"Health Services",
            "subcategory":"Hospital",
            "type":"Services"
        }
    ],
    "sg:phone":"+1 260 349 0237",
    "sg:postcode":"46755",
    "sg:province":"IN",
    "sg:tags":[
        "mental"
    ],
    "wof:name":"Pioneer Lodge",
    "wof:placetype":"venue"
},
  "geometry": {"coordinates":[-85.267571,41.439811],"type":"Point"}
}