{
  "type": "Feature",
  "properties": {
    "iso:country":"US",
    "sg:address":"4352 Malden Ln",
    "sg:city":"Beech Grove",
    "sg:classifiers":[
        {
            "category":"Professional",
            "type":"Services"
        }
    ],
    "sg:phone":"+1 317 791 9145",
    "sg:postcode":"46107",
    "sg:province":"IN",
    "sg:tags":[
        "hearing",
        "reporter"
    ],
    "wof:name":"Stravers  Cornelis",
    "wof:placetype":"venue"
},
  "geometry": {"coordinates":[-86.093343,39.697084],"type":"Point"}
}