{
  "type": "Feature",
  "properties": {
    "iso:country":"US",
    "sg:address":"9941 Allisonville Rd",
    "sg:city":"Fishers",
    "sg:classifiers":[
        {
            "category":"Utilities",
            "subcategory":"Telephone",
            "type":"Services"
        }
    ],
    "sg:phone":"+1 317 598 8927",
    "sg:postcode":"46038",
    "sg:province":"IN",
    "sg:tags":[
        "communications"
    ],
    "wof:name":"Indywomenconnectcom",
    "wof:placetype":"venue"
},
  "geometry": {"coordinates":[-86.059584,39.931748],"type":"Point"}
}