{
  "type": "Feature",
  "properties": {
    "iso:country":"US",
    "sg:address":"2901 S McIntire Dr",
    "sg:city":"Bloomington",
    "sg:classifiers":[
        {
            "category":"Health Services",
            "subcategory":"Optometrist",
            "type":"Services"
        }
    ],
    "sg:phone":"+1 812 332 1401",
    "sg:postcode":"47403",
    "sg:province":"IN",
    "wof:name":"Trager Melinda J OD",
    "wof:placetype":"venue"
},
  "geometry": {"coordinates":[-86.569768,39.135],"type":"Point"}
}