{
  "type": "Feature",
  "properties": {
    "iso:country":"US",
    "sg:address":"695 3rd Ave",
    "sg:city":"Jasper",
    "sg:classifiers":[
        {
            "category":"Health Services",
            "subcategory":"Doctor",
            "type":"Services"
        }
    ],
    "sg:phone":"+1 812 634 6824",
    "sg:postcode":"47546",
    "sg:province":"IN",
    "sg:tags":[
        "physician",
        "surgeon"
    ],
    "wof:name":"Medical Of Dubois",
    "wof:placetype":"venue"
},
  "geometry": {"coordinates":[-86.91727299999999,38.379048],"type":"Point"}
}