{
  "type": "Feature",
  "properties": {
    "iso:country":"US",
    "sg:address":"2200 E Memorial Dr",
    "sg:city":"Muncie",
    "sg:classifiers":[
        {
            "category":"Home & Garden",
            "subcategory":"Furniture",
            "type":"Retail Goods"
        }
    ],
    "sg:phone":"+1 765 741 0913",
    "sg:postcode":"47302",
    "sg:province":"IN",
    "sg:tags":[
        "cabinet"
    ],
    "wof:name":"Combs Custom Cabinetry",
    "wof:placetype":"venue"
},
  "geometry": {"coordinates":[-85.36146100000001,40.178375],"type":"Point"}
}