{
  "type": "Feature",
  "properties": {
    "iso:country":"US",
    "sg:address":"332 Massachusetts Ave",
    "sg:city":"Indianapolis",
    "sg:classifiers":[
        {
            "category":"Professional",
            "subcategory":"Computer Services",
            "type":"Services"
        }
    ],
    "sg:phone":"+1 317 423 3445",
    "sg:postcode":"46204",
    "sg:province":"IN",
    "sg:tags":[
        "website",
        "design"
    ],
    "sg:website":"www.elavio.com",
    "wof:name":"Elavio Inc",
    "wof:placetype":"venue"
},
  "geometry": {"coordinates":[-86.152885,39.772273],"type":"Point"}
}