{
  "type": "Feature",
  "properties": {
    "addr:full":"8266 W State Rte 62 Chandler IN 47610",
    "addr:housenumber":"8266",
    "addr:postcode":"47610",
    "addr:street":"W State Rte 62",
    "iso:country":"US",
    "sg:address":"8266 W State Rte 62",
    "sg:city":"Chandler",
    "sg:classifiers":[
        {
            "category":"Autos & Motor Vehicles",
            "subcategory":"Automobile Sales",
            "type":"Retail Goods"
        }
    ],
    "sg:phone":"+1 812 925 9905",
    "sg:postcode":"47610",
    "sg:province":"IN",
    "sg:tags":[
        "truck"
    ],
    "wof:name":"Tri-State Truck Sales",
    "wof:placetype":"venue"
},
  "geometry": {"coordinates":[-87.399429,38.028075],"type":"Point"}
}