{
  "type": "Feature",
  "properties": {
    "iso:country":"US",
    "sg:address":"1710 E 10th St",
    "sg:city":"Jeffersonville",
    "sg:classifiers":[
        {
            "category":"Wholesale",
            "subcategory":"Construction Materials",
            "type":"Manufacturing & Wholesale Goods"
        }
    ],
    "sg:phone":"+1 812 285 0411",
    "sg:postcode":"47130",
    "sg:province":"IN",
    "sg:tags":[
        "refuse",
        "system"
    ],
    "wof:name":"Caledonian Company",
    "wof:placetype":"venue"
},
  "geometry": {"coordinates":[-85.726534,38.295413],"type":"Point"}
}