{
  "type": "Feature",
  "properties": {
    "iso:country":"US",
    "sg:address":"1 N Capitol Ave Ste 700",
    "sg:city":"Indianapolis",
    "sg:classifiers":[
        {
            "category":"Government",
            "subcategory":"Office",
            "type":"Public Place"
        }
    ],
    "sg:phone":"+1 317 232 4950",
    "sg:postcode":"46204",
    "sg:province":"IN",
    "sg:tags":[
        "government-united",
        "state"
    ],
    "wof:name":"Marketing/Communications",
    "wof:placetype":"venue"
},
  "geometry": {"coordinates":[-86.16172,39.76717],"type":"Point"}
}