{
  "type": "Feature",
  "properties": {
    "iso:country":"US",
    "sg:address":"3409 W Mishawaka Ave",
    "sg:city":"South Bend",
    "sg:classifiers":[
        {
            "category":"Professional",
            "subcategory":"Computer Services",
            "type":"Services"
        }
    ],
    "sg:phone":"+1 574 289 2448",
    "sg:postcode":"46615",
    "sg:province":"IN",
    "sg:tags":[
        "related"
    ],
    "wof:name":"Craig Consulting Co Inc",
    "wof:placetype":"venue"
},
  "geometry": {"coordinates":[-86.199746,41.665802],"type":"Point"}
}