{
  "type": "Feature",
  "properties": {
    "iso:country":"US",
    "sg:address":"308 S Green St",
    "sg:city":"Crawfordsville",
    "sg:classifiers":[
        {
            "category":"Organizations",
            "subcategory":"Religious Organization",
            "type":"Services"
        }
    ],
    "sg:phone":"+1 765 364 1421",
    "sg:postcode":"47933",
    "sg:province":"IN",
    "sg:tags":[
        "church"
    ],
    "wof:name":"One Way Pene Apos Chrch",
    "wof:placetype":"venue"
},
  "geometry": {"coordinates":[-86.899822,40.039375],"type":"Point"}
}