{
  "type": "Feature",
  "properties": {
    "iso:country":"US",
    "sg:address":"505 Roesner Rd",
    "sg:city":"Evansville",
    "sg:classifiers":[
        {
            "category":"Retail",
            "subcategory":"Repair Shop",
            "type":"Services"
        }
    ],
    "sg:phone":"+1 812 985 2632",
    "sg:postcode":"47712",
    "sg:province":"IN",
    "sg:tags":[
        "welding"
    ],
    "wof:name":"Tom's Welding & Machine Inc",
    "wof:placetype":"venue"
},
  "geometry": {"coordinates":[-87.681897,37.978695],"type":"Point"}
}