{
  "type": "Feature",
  "properties": {
    "iso:country":"US",
    "sg:address":"121 N 9th St",
    "sg:city":"Clinton",
    "sg:classifiers":[
        {
            "category":"Restaurant",
            "type":"Food & Drink"
        }
    ],
    "sg:phone":"+1 765 832 2138",
    "sg:postcode":"47842",
    "sg:province":"IN",
    "wof:name":"9th Street Cafe",
    "wof:placetype":"venue"
},
  "geometry": {"coordinates":[-87.408158,39.660738],"type":"Point"}
}