{
  "type": "Feature",
  "properties": {
    "iso:country":"US",
    "sg:address":"777 S 11th St",
    "sg:city":"Mitchell",
    "sg:classifiers":[
        {
            "category":"Organizations",
            "subcategory":"Religious Organization",
            "type":"Services"
        }
    ],
    "sg:phone":"+1 812 849 3570",
    "sg:postcode":"47446",
    "sg:province":"IN",
    "wof:name":"St Marys Church",
    "wof:placetype":"venue"
},
  "geometry": {"coordinates":[-86.477412,38.726013],"type":"Point"}
}