{
  "type": "Feature",
  "properties": {
    "iso:country":"US",
    "sg:address":"5992 W Jefferson Blvd",
    "sg:city":"Fort Wayne",
    "sg:classifiers":[
        {
            "category":"Food & Beverages",
            "subcategory":"Liquor & Beverages",
            "type":"Retail Goods"
        }
    ],
    "sg:phone":"+1 260 432 6636",
    "sg:postcode":"46804",
    "sg:province":"IN",
    "sg:tags":[
        "wine"
    ],
    "wof:name":"Belmont Beverage Store",
    "wof:placetype":"venue"
},
  "geometry": {"coordinates":[-85.218514,41.059397],"type":"Point"}
}