{
  "type": "Feature",
  "properties": {
    "iso:country":"US",
    "sg:address":"7762 S Co Rd 100 E",
    "sg:city":"Cloverdale",
    "sg:classifiers":[
        {
            "category":"Mining & Drilling",
            "type":"Manufacturing & Wholesale Goods"
        }
    ],
    "sg:phone":"+1 765 653 6413",
    "sg:postcode":"46120",
    "sg:province":"IN",
    "sg:tags":[
        "limestone"
    ],
    "wof:name":"Rock Hill Building & Landscape",
    "wof:placetype":"venue"
},
  "geometry": {"coordinates":[-86.832157,39.546635],"type":"Point"}
}