{
  "type": "Feature",
  "properties": {
    "iso:country":"US",
    "sg:address":"5212 Mosswood Ct",
    "sg:city":"Indianapolis",
    "sg:classifiers":[
        {
            "category":"Organizations",
            "subcategory":"Professional Association",
            "type":"Services"
        }
    ],
    "sg:phone":"+1 317 388 8983",
    "sg:postcode":"46254",
    "sg:province":"IN",
    "sg:website":"www.iosociety.org",
    "wof:name":"Indiana Orthopedic Society",
    "wof:placetype":"venue"
},
  "geometry": {"coordinates":[-86.293778,39.845837],"type":"Point"}
}