{
  "type": "Feature",
  "properties": {
    "iso:country":"US",
    "sg:address":"8935 Broadway",
    "sg:city":"Merrillville",
    "sg:classifiers":[
        {
            "category":"Professional",
            "subcategory":"Lawyer & Legal Services",
            "type":"Services"
        }
    ],
    "sg:phone":"+1 219 769 7060",
    "sg:postcode":"46410",
    "sg:province":"IN",
    "sg:tags":[
        "attorney"
    ],
    "wof:name":"Natasha Bukorovic",
    "wof:placetype":"venue"
},
  "geometry": {"coordinates":[-87.33576499999999,41.456539],"type":"Point"}
}