{
  "type": "Feature",
  "properties": {
    "iso:country":"US",
    "sg:address":"351 E Washington Ave",
    "sg:city":"Peru",
    "sg:classifiers":[
        {
            "category":"Autos & Motor Vehicles",
            "subcategory":"Automobile Sales",
            "type":"Retail Goods"
        }
    ],
    "sg:phone":"+1 765 472 1666",
    "sg:postcode":"46970",
    "sg:province":"IN",
    "sg:tags":[
        "car",
        "dealer"
    ],
    "wof:name":"Instant Auto Sales",
    "wof:placetype":"venue"
},
  "geometry": {"coordinates":[-86.060839,40.763774],"type":"Point"}
}