{
  "type": "Feature",
  "properties": {
    "iso:country":"US",
    "sg:address":"12131 State Rd 23",
    "sg:city":"Granger",
    "sg:classifiers":[
        {
            "category":"Shopping",
            "subcategory":"Hobbies, Toys, & Games",
            "type":"Retail Goods"
        }
    ],
    "sg:phone":"+1 574 243 2390",
    "sg:postcode":"46530",
    "sg:province":"IN",
    "sg:tags":[
        "model",
        "supply"
    ],
    "wof:name":"Granger Hobby Stop",
    "wof:placetype":"venue"
},
  "geometry": {"coordinates":[-86.109422,41.753599],"type":"Point"}
}