{
  "type": "Feature",
  "properties": {
    "iso:country":"US",
    "sg:address":"521 S 1st St",
    "sg:city":"Pierceton",
    "sg:classifiers":[
        {
            "category":"Shopping",
            "subcategory":"Department Store",
            "type":"Retail Goods"
        }
    ],
    "sg:phone":"+1 574 594 2875",
    "sg:postcode":"46562",
    "sg:province":"IN",
    "sg:tags":[
        "shop"
    ],
    "wof:name":"Dollar General",
    "wof:placetype":"venue"
},
  "geometry": {"coordinates":[-85.705188,41.195192],"type":"Point"}
}