{
  "type": "Feature",
  "properties": {
    "iso:country":"US",
    "sg:address":"3399 Warrick Dr",
    "sg:city":"Boonville",
    "sg:classifiers":[
        {
            "category":"Retail",
            "subcategory":"Auto Repair",
            "type":"Services"
        }
    ],
    "sg:phone":"+1 812 897 2700",
    "sg:postcode":"47601",
    "sg:province":"IN",
    "sg:tags":[
        "automobile",
        "customizing"
    ],
    "wof:name":"A Plus Fabricating Inc",
    "wof:placetype":"venue"
},
  "geometry": {"coordinates":[-87.306829,38.047186],"type":"Point"}
}