{
  "type": "Feature",
  "properties": {
    "addr:full":"343 E Parr Rd Berne IN 46711",
    "addr:housenumber":"343",
    "addr:postcode":"in 46711",
    "addr:street":"E Parr Rd",
    "iso:country":"US",
    "sg:address":"343 E Parr Rd",
    "sg:city":"Berne",
    "sg:classifiers":[
        {
            "category":"Government",
            "subcategory":"Office",
            "type":"Public Place"
        }
    ],
    "sg:phone":"+1 260 589 3425",
    "sg:postcode":"46711",
    "sg:province":"IN",
    "sg:tags":[
        "village"
    ],
    "wof:name":"Berne Sewage Treatment Plant",
    "wof:placetype":"venue"
},
  "geometry": {"coordinates":[-84.947121,40.665334],"type":"Point"}
}