{
  "type": "Feature",
  "properties": {
    "iso:country":"US",
    "sg:address":"841 S 35th St",
    "sg:city":"South Bend",
    "sg:classifiers":[
        {
            "category":"Communications",
            "subcategory":"Radio Station",
            "type":"Services"
        }
    ],
    "sg:phone":"+1 574 289 2758",
    "sg:postcode":"46615",
    "sg:province":"IN",
    "sg:tags":[
        "broadcast"
    ],
    "wof:name":"Boise State Radio Foundation",
    "wof:placetype":"venue"
},
  "geometry": {"coordinates":[-86.19916600000001,41.666953],"type":"Point"}
}