{
  "type": "Feature",
  "properties": {
    "iso:country":"US",
    "sg:address":"500 W Short St",
    "sg:city":"Remington",
    "sg:classifiers":[
        {
            "category":"Recreation",
            "type":"Entertainment"
        }
    ],
    "sg:phone":"+1 219 261 3533",
    "sg:postcode":"47977",
    "sg:province":"IN",
    "sg:tags":[
        "parks"
    ],
    "wof:name":"Remington Community Park",
    "wof:placetype":"venue"
},
  "geometry": {"coordinates":[-87.158541,40.769097],"type":"Point"}
}