{
  "type": "Feature",
  "properties": {
    "addr:full":"521 S Main St Monticello IN 47960",
    "addr:housenumber":"521",
    "addr:postcode":"47960",
    "addr:street":"S Main St",
    "iso:country":"US",
    "sg:address":"521 S Main St",
    "sg:city":"Monticello",
    "sg:classifiers":[
        {
            "category":"Organizations",
            "subcategory":"Religious Organization",
            "type":"Services"
        }
    ],
    "sg:phone":"+1 574 583 9694",
    "sg:postcode":"47960",
    "sg:province":"IN",
    "sg:tags":[
        "clergy"
    ],
    "wof:name":"Wayne S Holmes",
    "wof:placetype":"venue"
},
  "geometry": {"coordinates":[-86.76186,40.739869],"type":"Point"}
}