{
  "type": "Feature",
  "properties": {
    "iso:country":"US",
    "sg:address":"2063 Bluff Rd",
    "sg:city":"Indianapolis",
    "sg:classifiers":[
        {
            "category":"Wholesale",
            "subcategory":"Auto Parts",
            "type":"Manufacturing & Wholesale Goods"
        }
    ],
    "sg:phone":"+1 317 972 7898",
    "sg:postcode":"46225",
    "sg:province":"IN",
    "sg:tags":[
        "automobile",
        "rebuilt"
    ],
    "wof:name":"Aacme Auto Parts & Towing",
    "wof:placetype":"venue"
},
  "geometry": {"coordinates":[-86.160442,39.739707],"type":"Point"}
}