{
  "type": "Feature",
  "properties": {
    "addr:full":"4003 N New Jersey St Indianapolis IN 46205",
    "addr:housenumber":"4003",
    "addr:postcode":"46205",
    "addr:street":"N New Jersey St",
    "iso:country":"US",
    "sg:address":"4003 N New Jersey St",
    "sg:city":"Indianapolis",
    "sg:classifiers":[
        {
            "category":"Wholesale",
            "subcategory":"Electrical",
            "type":"Manufacturing & Wholesale Goods"
        }
    ],
    "sg:phone":"+1 317 924 4383",
    "sg:postcode":"46205",
    "sg:province":"IN",
    "sg:tags":[
        "electric",
        "motor"
    ],
    "wof:name":"U S Electrical Motors",
    "wof:placetype":"venue"
},
  "geometry": {"coordinates":[-86.150915,39.830316],"type":"Point"}
}