{
  "type": "Feature",
  "properties": {
    "iso:country":"US",
    "sg:address":"8990 N Kennedys Crossing Rd",
    "sg:city":"Brazil",
    "sg:classifiers":[
        {
            "category":"Recreation",
            "type":"Entertainment"
        }
    ],
    "sg:phone":"+1 812 446 2205",
    "sg:postcode":"47834",
    "sg:province":"IN",
    "sg:tags":[
        "hall",
        "auditorium"
    ],
    "wof:name":"Kennedy Crossing Ctr",
    "wof:placetype":"venue"
},
  "geometry": {"coordinates":[-87.16468999999999,39.517757],"type":"Point"}
}