{
  "type": "Feature",
  "properties": {
    "iso:country":"US",
    "sg:address":"45 E State Rd 8",
    "sg:city":"Kouts",
    "sg:classifiers":[
        {
            "category":"Freight",
            "type":"Transportation"
        }
    ],
    "sg:phone":"+1 219 766 2349",
    "sg:postcode":"46347",
    "sg:province":"IN",
    "sg:tags":[
        "operator",
        "local",
        "trucking"
    ],
    "wof:name":"Gene Nuest Trucking",
    "wof:placetype":"venue"
},
  "geometry": {"coordinates":[-87.059388,41.318586],"type":"Point"}
}