{
  "type": "Feature",
  "properties": {
    "iso:country":"US",
    "sg:address":"3806 E Michigan Rd",
    "sg:city":"Shelbyville",
    "sg:classifiers":[
        {
            "category":"Wholesale",
            "subcategory":"Scrap",
            "type":"Manufacturing & Wholesale Goods"
        }
    ],
    "sg:phone":"+1 317 398 0286",
    "sg:postcode":"46176",
    "sg:province":"IN",
    "sg:tags":[
        "waste",
        "paper"
    ],
    "wof:name":"Hoosier Paper Stock Inc",
    "wof:placetype":"venue"
},
  "geometry": {"coordinates":[-85.707562,39.502331],"type":"Point"}
}