{
  "type": "Feature",
  "properties": {
    "iso:country":"US",
    "sg:address":"817 E 9th St",
    "sg:city":"Rochester",
    "sg:classifiers":[
        {
            "category":"Insurance",
            "subcategory":"Insurance Agent",
            "type":"Services"
        }
    ],
    "sg:phone":"+1 574 223 9137",
    "sg:postcode":"46975",
    "sg:province":"IN",
    "wof:name":"Cameron Financial Svc Inc",
    "wof:placetype":"venue"
},
  "geometry": {"coordinates":[-86.206104,41.064304],"type":"Point"}
}