{
  "type": "Feature",
  "properties": {
    "iso:country":"US",
    "sg:address":"9655 S Co Rd 100 W",
    "sg:city":"Westport",
    "sg:classifiers":[
        {
            "category":"Building & Trades",
            "subcategory":"Cleaning & Sanitation",
            "type":"Services"
        }
    ],
    "sg:phone":"+1 812 352 8181",
    "sg:postcode":"47283",
    "sg:province":"IN",
    "wof:name":"Watkins Cleaning & Restoration",
    "wof:placetype":"venue"
},
  "geometry": {"coordinates":[-85.49853,39.195117],"type":"Point"}
}