{
  "type": "Feature",
  "properties": {
    "iso:country":"US",
    "sg:address":"1602 S 825 E",
    "sg:city":"Zionsville",
    "sg:classifiers":[
        {
            "category":"Professional",
            "subcategory":"Lawyer & Legal Services",
            "type":"Services"
        }
    ],
    "sg:phone":"+1 317 769 6324",
    "sg:postcode":"46077",
    "sg:province":"IN",
    "wof:name":"Richardson & Assoc",
    "wof:placetype":"venue"
},
  "geometry": {"coordinates":[-86.313034,40.017892],"type":"Point"}
}