{
  "type": "Feature",
  "properties": {
    "addr:full":"1502 E North St Crown Point IN 46307",
    "addr:housenumber":"1502",
    "addr:postcode":"46307",
    "addr:street":"E North St",
    "iso:country":"US",
    "sg:address":"1502 E North St",
    "sg:city":"Crown Point",
    "sg:classifiers":[
        {
            "category":"Personal",
            "type":"Services"
        }
    ],
    "sg:phone":"+1 219 662 1007",
    "sg:postcode":"46307",
    "sg:province":"IN",
    "sg:tags":[
        "towing"
    ],
    "wof:name":"Midnight Blue Towing & Recovery",
    "wof:placetype":"venue"
},
  "geometry": {"coordinates":[-87.345398,41.420101],"type":"Point"}
}