{
  "type": "Feature",
  "properties": {
    "iso:country":"US",
    "sg:address":"25 N 7th St",
    "sg:city":"Richmond",
    "sg:classifiers":[
        {
            "category":"Professional",
            "subcategory":"Lawyer & Legal Services",
            "type":"Services"
        }
    ],
    "sg:phone":"+1 765 966 5518",
    "sg:postcode":"47374",
    "sg:province":"IN",
    "sg:tags":[
        "attorney"
    ],
    "wof:name":"Burton & Simkin",
    "wof:placetype":"venue"
},
  "geometry": {"coordinates":[-84.892703,39.829477],"type":"Point"}
}