{
  "type": "Feature",
  "properties": {
    "iso:country":"US",
    "sg:address":"6803 Grand Ave",
    "sg:city":"Hammond",
    "sg:classifiers":[
        {
            "category":"Wholesale",
            "subcategory":"Durable Goods & Equipment",
            "type":"Manufacturing & Wholesale Goods"
        }
    ],
    "sg:phone":"+1 219 844 9111",
    "sg:postcode":"46323",
    "sg:province":"IN",
    "sg:tags":[
        "fire",
        "extinguisher"
    ],
    "wof:name":"AAA Master Fire Equipment",
    "wof:placetype":"venue"
},
  "geometry": {"coordinates":[-87.442117,41.58821],"type":"Point"}
}