{
  "type": "Feature",
  "properties": {
    "iso:country":"US",
    "sg:address":"8055 US Hwy 31 S",
    "sg:city":"Indianapolis",
    "sg:classifiers":[
        {
            "category":"Autos & Motor Vehicles",
            "subcategory":"Automobile Sales",
            "type":"Retail Goods"
        }
    ],
    "sg:phone":"+1 317 882 2600",
    "sg:postcode":"46227",
    "sg:province":"IN",
    "sg:tags":[
        "car",
        "dealer"
    ],
    "sg:website":"www.becktoyota.com",
    "wof:name":"Beck Toyota",
    "wof:placetype":"venue"
},
  "geometry": {"coordinates":[-86.135277,39.647883],"type":"Point"}
}