{
  "type": "Feature",
  "properties": {
    "iso:country":"US",
    "sg:address":"7247 Calumet Ave",
    "sg:city":"Hammond",
    "sg:classifiers":[
        {
            "category":"Autos & Motor Vehicles",
            "subcategory":"Fuel & Gas Station",
            "type":"Retail Goods"
        }
    ],
    "sg:phone":"+1 219 852 4257",
    "sg:postcode":"46324",
    "sg:province":"IN",
    "sg:tags":[
        "oil"
    ],
    "wof:name":"Calumet Marathon",
    "wof:placetype":"venue"
},
  "geometry": {"coordinates":[-87.508933,41.581842],"type":"Point"}
}