{
  "type": "Feature",
  "properties": {
    "iso:country":"US",
    "sg:address":"2307 Flemming Rd",
    "sg:city":"Valparaiso",
    "sg:classifiers":[
        {
            "category":"Professional",
            "subcategory":"Management & Consulting",
            "type":"Services"
        }
    ],
    "sg:phone":"+1 219 465 1117",
    "sg:postcode":"46383",
    "sg:province":"IN",
    "sg:tags":[
        "business"
    ],
    "wof:name":"David Dopp",
    "wof:placetype":"venue"
},
  "geometry": {"coordinates":[-87.032621,41.490555],"type":"Point"}
}