{
  "type": "Feature",
  "properties": {
    "iso:country":"US",
    "sg:address":"504 Saranna Rd",
    "sg:city":"Shelbyville",
    "sg:classifiers":[
        {
            "category":"Banks & Credit Unions",
            "subcategory":"Bank",
            "type":"Services"
        }
    ],
    "sg:phone":"+1 317 398 1111",
    "sg:postcode":"46176",
    "sg:province":"IN",
    "sg:tags":[
        "loan"
    ],
    "wof:name":"Cash Today",
    "wof:placetype":"venue"
},
  "geometry": {"coordinates":[-85.752922,39.51816],"type":"Point"}
}