{
  "type": "Feature",
  "properties": {
    "iso:country":"US",
    "sg:address":"5125 Decatur Blvd",
    "sg:city":"Indianapolis",
    "sg:classifiers":[
        {
            "category":"Manufacturing",
            "subcategory":"Food",
            "type":"Manufacturing & Wholesale Goods"
        }
    ],
    "sg:phone":"+1 317 821 1197",
    "sg:postcode":"46241",
    "sg:province":"IN",
    "sg:tags":[
        "frozen",
        "dessert",
        "ice",
        "cream"
    ],
    "wof:name":"Edy's Grand Ice Cream",
    "wof:placetype":"venue"
},
  "geometry": {"coordinates":[-86.287572,39.688139],"type":"Point"}
}