{
  "type": "Feature",
  "properties": {
    "iso:country":"US",
    "sg:address":"1001 W 10th St",
    "sg:city":"Indianapolis",
    "sg:classifiers":[
        {
            "category":"Professional",
            "subcategory":"Management & Consulting",
            "type":"Services"
        }
    ],
    "sg:phone":"+1 317 630 2486",
    "sg:postcode":"46202",
    "sg:province":"IN",
    "sg:tags":[
        "consultant",
        "energy",
        "conservation"
    ],
    "wof:name":"Father Resource Ctr",
    "wof:placetype":"venue"
},
  "geometry": {"coordinates":[-86.1764,39.780953],"type":"Point"}
}