{
  "type": "Feature",
  "properties": {
    "iso:country":"US",
    "sg:address":"525 Saint Andrews Dr",
    "sg:city":"Schererville",
    "sg:classifiers":[
        {
            "category":"Professional",
            "subcategory":"Computer Services",
            "type":"Services"
        },
        {
            "category":"Internet Cafe",
            "subcategory":"None",
            "type":"Food & Drink"
        }
    ],
    "sg:phone":"+1 219 614 7235",
    "sg:postcode":"46375",
    "sg:province":"IN",
    "sg:tags":[
        "product",
        "software"
    ],
    "wof:name":"Cadcim Technologies",
    "wof:placetype":"venue"
},
  "geometry": {"coordinates":[-87.489548,41.517867],"type":"Point"}
}