{
  "type": "Feature",
  "properties": {
    "iso:country":"US",
    "sg:address":"13615 State Rd 67",
    "sg:city":"Camby",
    "sg:classifiers":[
        {
            "category":"Home & Garden",
            "subcategory":"Furniture",
            "type":"Retail Goods"
        }
    ],
    "sg:phone":"+1 317 834 2260",
    "sg:postcode":"46113",
    "sg:province":"IN",
    "wof:name":"That Furniture Store",
    "wof:placetype":"venue"
},
  "geometry": {"coordinates":[-86.349851,39.629581],"type":"Point"}
}