{
  "type": "Feature",
  "properties": {
    "addr:full":"6385 S Co Rd 325 E Brownstown IN 47220",
    "addr:housenumber":"6385",
    "addr:postcode":"47220",
    "addr:street":"S Co Rd 325 E",
    "iso:country":"US",
    "sg:address":"6385 S Co Rd 325 E",
    "sg:city":"Brownstown",
    "sg:classifiers":[
        {
            "category":"Building & Trades",
            "subcategory":"Plumbing",
            "type":"Services"
        }
    ],
    "sg:phone":"+1 812 358 8311",
    "sg:postcode":"47220",
    "sg:province":"IN",
    "sg:tags":[
        "conditioning",
        "air",
        "system",
        "contractor"
    ],
    "wof:name":"Collins Heating & Air",
    "wof:placetype":"venue"
},
  "geometry": {"coordinates":[-85.97631699999999,38.779575],"type":"Point"}
}