{
  "type": "Feature",
  "properties": {
    "iso:country":"US",
    "sg:address":"631 N Elm St",
    "sg:city":"Seymour",
    "sg:classifiers":[
        {
            "category":"Health Services",
            "subcategory":"Nursing And Care Facility",
            "type":"Services"
        }
    ],
    "sg:phone":"+1 812 523 3940",
    "sg:postcode":"47274",
    "sg:province":"IN",
    "sg:tags":[
        "home",
        "convalescent"
    ],
    "wof:name":"Elm Street Home",
    "wof:placetype":"venue"
},
  "geometry": {"coordinates":[-85.897425,38.963685],"type":"Point"}
}