{
  "type": "Feature",
  "properties": {
    "iso:country":"US",
    "sg:address":"2509 Bradford Ct",
    "sg:city":"Bloomington",
    "sg:classifiers":[
        {
            "category":"Recreation",
            "type":"Entertainment"
        }
    ],
    "sg:phone":"+1 812 824 8783",
    "sg:postcode":"47401",
    "sg:province":"IN",
    "sg:tags":[
        "range",
        "practice",
        "golf"
    ],
    "wof:name":"Backyard Links",
    "wof:placetype":"venue"
},
  "geometry": {"coordinates":[-86.504977,39.09779],"type":"Point"}
}