{
  "type": "Feature",
  "properties": {
    "iso:country":"US",
    "sg:address":"701 N Melville St",
    "sg:city":"Rensselaer",
    "sg:classifiers":[
        {
            "category":"Freight",
            "type":"Transportation"
        }
    ],
    "sg:phone":"+1 219 866 4002",
    "sg:postcode":"47978",
    "sg:province":"IN",
    "sg:tags":[
        "warehouse",
        "public"
    ],
    "wof:name":"Midwest Warehousing & Dstrbtn",
    "wof:placetype":"venue"
},
  "geometry": {"coordinates":[-87.141751,40.945668],"type":"Point"}
}