{
  "type": "Feature",
  "properties": {
    "iso:country":"US",
    "sg:address":"4865 S Water St",
    "sg:city":"Pleasant Lake",
    "sg:classifiers":[
        {
            "category":"Building & Trades",
            "subcategory":"Construction",
            "type":"Services"
        }
    ],
    "sg:phone":"+1 260 475 5737",
    "sg:postcode":"46779",
    "sg:province":"IN",
    "sg:tags":[
        "general",
        "contractor"
    ],
    "wof:name":"Handy Andy Svc",
    "wof:placetype":"venue"
},
  "geometry": {"coordinates":[-85.00267599999999,41.573508],"type":"Point"}
}