{
  "type": "Feature",
  "properties": {
    "iso:country":"US",
    "sg:address":"1700 N Broadway St",
    "sg:city":"Huntington",
    "sg:classifiers":[
        {
            "category":"Building & Trades",
            "subcategory":"Construction",
            "type":"Services"
        }
    ],
    "sg:phone":"+1 260 356 1621",
    "sg:postcode":"46750",
    "sg:province":"IN",
    "sg:tags":[
        "porch",
        "enclosure",
        "patio",
        "deck"
    ],
    "wof:name":"W A Zimmer Co",
    "wof:placetype":"venue"
},
  "geometry": {"coordinates":[-85.47131400000001,40.895877],"type":"Point"}
}