{
  "type": "Feature",
  "properties": {
    "addr:full":"3312 S Western Ave Marion IN 46953",
    "addr:housenumber":"3312",
    "addr:postcode":"46953",
    "addr:street":"S Western Ave",
    "iso:country":"US",
    "sg:address":"3312 S Western Ave",
    "sg:city":"Marion",
    "sg:classifiers":[
        {
            "category":"Banks & Credit Unions",
            "subcategory":"Bank",
            "type":"Services"
        }
    ],
    "sg:phone":"+1 765 668 4050",
    "sg:postcode":"46953",
    "sg:province":"IN",
    "sg:tags":[
        "cashing",
        "check"
    ],
    "wof:name":"Advance America",
    "wof:placetype":"venue"
},
  "geometry": {"coordinates":[-85.67374100000001,40.529737],"type":"Point"}
}