{
  "type": "Feature",
  "properties": {
    "iso:country":"US",
    "sg:address":"1901 Mississippi St",
    "sg:city":"Gary",
    "sg:classifiers":[
        {
            "category":"Government",
            "subcategory":"Fire Station",
            "type":"Public Place"
        }
    ],
    "sg:phone":"+1 219 881 1412",
    "sg:postcode":"46407",
    "sg:province":"IN",
    "sg:tags":[
        "department"
    ],
    "sg:website":"www.cityofgary.com",
    "wof:name":"Gary Fire Dept",
    "wof:placetype":"venue"
},
  "geometry": {"coordinates":[-87.317655,41.583417],"type":"Point"}
}