{
  "type": "Feature",
  "properties": {
    "iso:country":"US",
    "sg:address":"3853 N 100 W",
    "sg:city":"Decatur",
    "sg:phone":"+1 260 724 7589",
    "sg:postcode":"46733",
    "sg:province":"IN",
    "sg:tags":[
        "farm",
        "corn"
    ],
    "wof:name":"Leonard Lengerich",
    "wof:placetype":"venue"
},
  "geometry": {"coordinates":[-84.956181,40.797366],"type":"Point"}
}