{
  "type": "Feature",
  "properties": {
    "addr:full":"106 E Wayne St South Bend IN 46601",
    "addr:housenumber":"106",
    "addr:postcode":"46601",
    "addr:street":"E Wayne St",
    "iso:country":"US",
    "sg:address":"106 E Wayne St",
    "sg:city":"South Bend",
    "sg:classifiers":[
        {
            "category":"Professional",
            "subcategory":"Business Services",
            "type":"Services"
        }
    ],
    "sg:phone":"+1 574 246 0115",
    "sg:postcode":"46601",
    "sg:province":"IN",
    "sg:tags":[
        "telemarketing"
    ],
    "wof:name":"National Handicapped Workshop",
    "wof:placetype":"venue"
},
  "geometry": {"coordinates":[-86.24956400000001,41.673602],"type":"Point"}
}