{
  "type": "Feature",
  "properties": {
    "iso:country":"US",
    "sg:address":"1020 E Tipton St",
    "sg:city":"Seymour",
    "sg:classifiers":[
        {
            "category":"Personal",
            "type":"Services"
        }
    ],
    "sg:phone":"+1 812 524 9871",
    "sg:postcode":"47274",
    "sg:province":"IN",
    "sg:tags":[
        "therapist",
        "massage"
    ],
    "wof:name":"Resque Bodyworks",
    "wof:placetype":"venue"
},
  "geometry": {"coordinates":[-85.875483,38.958034],"type":"Point"}
}