{
  "type": "Feature",
  "properties": {
    "iso:country":"US",
    "sg:address":"35 N Pennsylvania St",
    "sg:city":"Indianapolis",
    "sg:classifiers":[
        {
            "category":"Parking",
            "type":"Transportation"
        }
    ],
    "sg:phone":"+1 317 638 8701",
    "sg:postcode":"46204",
    "sg:province":"IN",
    "sg:tags":[
        "garage"
    ],
    "wof:name":"Penn Park",
    "wof:placetype":"venue"
},
  "geometry": {"coordinates":[-86.15628,39.767046],"type":"Point"}
}