{
  "type": "Feature",
  "properties": {
    "addr:full":"3120 Co Rd 36 Auburn IN 46706",
    "addr:housenumber":"3120;36",
    "addr:postcode":"46706",
    "addr:street":"Co Rd",
    "iso:country":"US",
    "sg:address":"3120 Co Rd 36",
    "sg:city":"Auburn",
    "sg:classifiers":[
        {
            "category":"Retail",
            "subcategory":"Veterinary Services",
            "type":"Services"
        }
    ],
    "sg:phone":"+1 260 925 5339",
    "sg:postcode":"46706",
    "sg:province":"IN",
    "sg:tags":[
        "veterinarian"
    ],
    "wof:name":"Auburn Hills Animal Hospital",
    "wof:placetype":"venue"
},
  "geometry": {"coordinates":[-85.046825,41.396516],"type":"Point"}
}