{
  "type": "Feature",
  "properties": {
    "iso:country":"US",
    "sg:address":"135 S Washington St",
    "sg:city":"Danville",
    "sg:classifiers":[
        {
            "category":"Professional",
            "subcategory":"Lawyer & Legal Services",
            "type":"Services"
        }
    ],
    "sg:phone":"+1 317 745 3034",
    "sg:postcode":"46122",
    "sg:province":"IN",
    "sg:tags":[
        "attorney"
    ],
    "wof:name":"Gary L Wood Law Office",
    "wof:placetype":"venue"
},
  "geometry": {"coordinates":[-86.52381200000001,39.759552],"type":"Point"}
}