{
  "type": "Feature",
  "properties": {
    "iso:country":"US",
    "sg:address":"1250 Wernsing Rd",
    "sg:city":"Jasper",
    "sg:classifiers":[
        {
            "category":"Restaurant",
            "type":"Food & Drink"
        }
    ],
    "sg:phone":"+1 812 482 3322",
    "sg:postcode":"47546",
    "sg:province":"IN",
    "sg:tags":[
        "caterer"
    ],
    "wof:name":"Rainbow Food Svc",
    "wof:placetype":"venue"
},
  "geometry": {"coordinates":[-86.942773,38.370192],"type":"Point"}
}