{
  "type": "Feature",
  "properties": {
    "iso:country":"US",
    "sg:address":"1423 Wellington Ter",
    "sg:city":"Munster",
    "sg:classifiers":[
        {
            "category":"Arts & Performance",
            "subcategory":"Theater",
            "type":"Entertainment"
        }
    ],
    "sg:phone":"+1 219 924 8557",
    "sg:postcode":"46321",
    "sg:province":"IN",
    "sg:tags":[
        "talent",
        "agency",
        "casting"
    ],
    "wof:name":"Edge Talent",
    "wof:placetype":"venue"
},
  "geometry": {"coordinates":[-87.493705,41.528968],"type":"Point"}
}