{
  "type": "Feature",
  "properties": {
    "iso:country":"US",
    "sg:address":"13 N Railroad St",
    "sg:city":"Shelburn",
    "sg:classifiers":[
        {
            "category":"Government",
            "subcategory":"Post Office",
            "type":"Public Place"
        }
    ],
    "sg:phone":"+1 812 397 2123",
    "sg:postcode":"47879",
    "sg:province":"IN",
    "wof:name":"US Post Office",
    "wof:placetype":"venue"
},
  "geometry": {"coordinates":[-87.393345,39.178749],"type":"Point"}
}