{
  "type": "Feature",
  "properties": {
    "iso:country":"US",
    "sg:address":"602 Washington St",
    "sg:city":"Covington",
    "sg:classifiers":[
        {
            "category":"Shopping",
            "subcategory":"Antiques",
            "type":"Retail Goods"
        }
    ],
    "sg:phone":"+1 765 793 2710",
    "sg:postcode":"47932",
    "sg:province":"IN",
    "wof:name":"House With Lion Antiques",
    "wof:placetype":"venue"
},
  "geometry": {"coordinates":[-87.394149,40.137993],"type":"Point"}
}