{
  "type": "Feature",
  "properties": {
    "iso:country":"US",
    "sg:address":"9524 E 126th St",
    "sg:city":"Fishers",
    "sg:classifiers":[
        {
            "category":"Retail",
            "subcategory":"Auto Repair",
            "type":"Services"
        }
    ],
    "sg:phone":"+1 317 776 0500",
    "sg:postcode":"46038",
    "sg:province":"IN",
    "sg:tags":[
        "automobile",
        "lubrication"
    ],
    "wof:name":"Indy Lube Oil Change Ctr",
    "wof:placetype":"venue"
},
  "geometry": {"coordinates":[-85.999512,39.971701],"type":"Point"}
}