{
  "type": "Feature",
  "properties": {
    "addr:full":"3015 Calumet Ave Valparaiso IN 46383",
    "addr:housenumber":"3015",
    "addr:postcode":"46383",
    "addr:street":"Calumet Ave",
    "iso:country":"US",
    "sg:address":"3015 Calumet Ave",
    "sg:city":"Valparaiso",
    "sg:classifiers":[
        {
            "category":"Shopping",
            "subcategory":"Department Store",
            "type":"Retail Goods"
        }
    ],
    "sg:phone":"+1 219 462 5881",
    "sg:postcode":"46383",
    "sg:province":"IN",
    "sg:tags":[
        "shop"
    ],
    "sg:website":"www.biglots.com",
    "wof:name":"Big Lots",
    "wof:placetype":"venue"
},
  "geometry": {"coordinates":[-87.04519000000001,41.495064],"type":"Point"}
}