{
  "type": "Feature",
  "properties": {
    "iso:country":"US",
    "sg:address":"4656 W Jefferson Blvd",
    "sg:city":"Fort Wayne",
    "sg:classifiers":[
        {
            "category":"Real Estate",
            "subcategory":"Real Estate Agent",
            "type":"Services"
        }
    ],
    "sg:phone":"+1 260 459 6000",
    "sg:postcode":"46804",
    "sg:province":"IN",
    "wof:name":"Mc Ardle Realty & Consulting",
    "wof:placetype":"venue"
},
  "geometry": {"coordinates":[-85.200559,41.066794],"type":"Point"}
}