{
  "type": "Feature",
  "properties": {
    "addr:full":"4656 W Jefferson Blvd Fort Wayne IN 46804",
    "addr:housenumber":"4656",
    "addr:postcode":"46804",
    "addr:street":"W Jefferson Blvd",
    "iso:country":"US",
    "sg:address":"4656 W Jefferson Blvd",
    "sg:city":"Fort Wayne",
    "sg:classifiers":[
        {
            "category":"Real Estate",
            "subcategory":"Real Estate Agent",
            "type":"Services"
        }
    ],
    "sg:phone":"+1 260 459 6000",
    "sg:postcode":"46804",
    "sg:province":"IN",
    "wof:name":"Mc Ardle Realty & Consulting",
    "wof:placetype":"venue"
},
  "geometry": {"coordinates":[-85.200559,41.066794],"type":"Point"}
}