{
  "type": "Feature",
  "properties": {
    "iso:country":"US",
    "sg:address":"975 Hawthorne Dr",
    "sg:city":"Carmel",
    "sg:classifiers":[
        {
            "category":"Professional",
            "subcategory":"Business Services",
            "type":"Services"
        }
    ],
    "sg:phone":"+1 317 844 0083",
    "sg:postcode":"46033",
    "sg:province":"IN",
    "wof:name":"John Garrett Music Inc",
    "wof:placetype":"venue"
},
  "geometry": {"coordinates":[-86.103891,39.991075],"type":"Point"}
}