{
  "type": "Feature",
  "properties": {
    "iso:country":"US",
    "sg:address":"1 Court House Sq",
    "sg:city":"Jasper",
    "sg:classifiers":[
        {
            "category":"Government",
            "subcategory":"Court House",
            "type":"Public Place"
        }
    ],
    "sg:phone":"+1 812 481 7070",
    "sg:postcode":"47546",
    "sg:province":"IN",
    "sg:tags":[
        "county"
    ],
    "wof:name":"Dubois Superior Court",
    "wof:placetype":"venue"
},
  "geometry": {"coordinates":[-87.538798,38.604991],"type":"Point"}
}