{
  "type": "Feature",
  "properties": {
    "addr:full":"2906 Priscilla Ave Indianapolis IN 46218",
    "addr:housenumber":"2906",
    "addr:postcode":"46218",
    "addr:street":"Priscilla Ave",
    "iso:country":"US",
    "sg:address":"2906 Priscilla Ave",
    "sg:city":"Indianapolis",
    "sg:classifiers":[
        {
            "category":"Social Services",
            "subcategory":"Child Care",
            "type":"Services"
        }
    ],
    "sg:phone":"+1 317 547 4951",
    "sg:postcode":"46218",
    "sg:province":"IN",
    "wof:name":"Great Kids",
    "wof:placetype":"venue"
},
  "geometry": {"coordinates":[-86.06826100000001,39.808432],"type":"Point"}
}