{
  "type": "Feature",
  "properties": {
    "addr:full":"928 16th St Bedford IN 47421",
    "addr:housenumber":"928",
    "addr:postcode":"47421",
    "addr:street":"16Th St",
    "iso:country":"US",
    "sg:address":"928 16th St",
    "sg:city":"Bedford",
    "sg:classifiers":[
        {
            "category":"Personal",
            "subcategory":"Beauty Salon",
            "type":"Services"
        }
    ],
    "sg:phone":"+1 812 278 9758",
    "sg:postcode":"47421",
    "sg:province":"IN",
    "wof:name":"Under Construction",
    "wof:placetype":"venue"
},
  "geometry": {"coordinates":[-86.483767,38.860934],"type":"Point"}
}