{
  "type": "Feature",
  "properties": {
    "addr:full":"29635 Co Rd 10 Elkhart IN 46514",
    "addr:housenumber":"29635;10",
    "addr:postcode":"46514",
    "addr:street":"Co Rd",
    "iso:country":"US",
    "sg:address":"29635 Co Rd 10",
    "sg:city":"Elkhart",
    "sg:classifiers":[
        {
            "category":"Organizations",
            "subcategory":"Religious Organization",
            "type":"Services"
        }
    ],
    "sg:phone":"+1 574 262 1331",
    "sg:postcode":"46514",
    "sg:province":"IN",
    "sg:tags":[
        "church"
    ],
    "sg:website":"www.cornerstoneelkhart.com",
    "wof:name":"Cornerstone Baptist Church",
    "wof:placetype":"venue"
},
  "geometry": {"coordinates":[-86.033185,41.718111],"type":"Point"}
}