{
  "type": "Feature",
  "properties": {
    "iso:country":"US",
    "sg:address":"551 N Myrtle Ave",
    "sg:city":"Frankfort",
    "sg:classifiers":[
        {
            "category":"Restaurant",
            "type":"Food & Drink"
        }
    ],
    "sg:phone":"+1 765 654 7202",
    "sg:postcode":"46041",
    "sg:province":"IN",
    "wof:name":"Backstreet Cafe",
    "wof:placetype":"venue"
},
  "geometry": {"coordinates":[-86.524522,40.284905],"type":"Point"}
}