{
  "type": "Feature",
  "properties": {
    "addr:full":"5240 Crawfordsville Rd Indianapolis IN 46224",
    "addr:postcode":"5240;46224",
    "addr:street":"Crawfordsville Rd",
    "iso:country":"US",
    "sg:address":"5240 Crawfordsville Rd",
    "sg:city":"Indianapolis",
    "sg:classifiers":[
        {
            "category":"Shopping",
            "subcategory":"Hobbies, Toys, & Games",
            "type":"Retail Goods"
        }
    ],
    "sg:phone":"+1 317 244 2893",
    "sg:postcode":"46224",
    "sg:province":"IN",
    "sg:tags":[
        "model",
        "supply"
    ],
    "wof:name":"Slots West",
    "wof:placetype":"venue"
},
  "geometry": {"coordinates":[-86.25062,39.791856],"type":"Point"}
}