{
  "type": "Feature",
  "properties": {
    "iso:country":"US",
    "sg:address":"7711 Shelby St",
    "sg:city":"Indianapolis",
    "sg:classifiers":[
        {
            "category":"Fast Food",
            "type":"Food & Drink"
        },
        {
            "category":"Professional",
            "type":"Services"
        },
        {
            "category":"Deli",
            "type":"Food & Drink"
        },
        {
            "category":"Food & Beverages",
            "subcategory":"Groceries & Convenience Stores",
            "type":"Retail Goods"
        }
    ],
    "sg:phone":"+1 317 889 7500",
    "sg:postcode":"46227",
    "sg:province":"IN",
    "sg:tags":[
        "shop",
        "sandwich",
        "restaurant",
        "delicatessen",
        "caterer"
    ],
    "sg:website":"http://www.mcalistersdeli.com/",
    "wof:name":"McAlister's Deli",
    "wof:placetype":"venue"
},
  "geometry": {"coordinates":[-86.139426,39.655126],"type":"Point"}
}