{
  "type": "Feature",
  "properties": {
    "addr:full":"315 NW 3rd St Richmond IN 47374",
    "addr:housenumber":"315",
    "addr:postcode":"47374",
    "addr:street":"Nw 3Rd St",
    "iso:country":"US",
    "sg:address":"315 NW 3rd St",
    "sg:city":"Richmond",
    "sg:classifiers":[
        {
            "category":"Education",
            "subcategory":"School",
            "type":"Public Place"
        }
    ],
    "sg:phone":"+1 765 973 3416",
    "sg:postcode":"47374",
    "sg:province":"IN",
    "wof:name":"Early Learning Family Literacy",
    "wof:placetype":"venue"
},
  "geometry": {"coordinates":[-84.904444,39.833141],"type":"Point"}
}