{
  "type": "Feature",
  "properties": {
    "iso:country":"US",
    "sg:address":"1700 S 25th St",
    "sg:city":"Terre Haute",
    "sg:classifiers":[
        {
            "category":"Banks & Credit Unions",
            "subcategory":"Bank",
            "type":"Services"
        }
    ],
    "sg:phone":"+1 812 478 5709",
    "sg:postcode":"47802",
    "sg:province":"IN",
    "sg:tags":[
        "loan",
        "real estate"
    ],
    "wof:name":"Designer Mortgage LLC",
    "wof:placetype":"venue"
},
  "geometry": {"coordinates":[-87.378815,39.447464],"type":"Point"}
}