{
  "type": "Feature",
  "properties": {
    "iso:country":"US",
    "sg:address":"911 Applewood Rd",
    "sg:city":"Fort Wayne",
    "sg:classifiers":[
        {
            "category":"Building & Trades",
            "subcategory":"Construction",
            "type":"Services"
        }
    ],
    "sg:phone":"+1 260 489 6221",
    "sg:postcode":"46825",
    "sg:province":"IN",
    "sg:tags":[
        "floor",
        "installation",
        "covering"
    ],
    "wof:name":"Dons Floor Installations",
    "wof:placetype":"venue"
},
  "geometry": {"coordinates":[-85.128656,41.142178],"type":"Point"}
}