{
  "type": "Feature",
  "properties": {
    "addr:full":"6244 N Thomas Rd Willow Branch IN 46186",
    "addr:housenumber":"6244",
    "addr:postcode":"46186",
    "addr:street":"N Thomas Rd",
    "iso:country":"US",
    "sg:address":"6244 N Thomas Rd",
    "sg:city":"Willow Branch",
    "sg:classifiers":[
        {
            "category":"Organizations",
            "subcategory":"Religious Organization",
            "type":"Services"
        }
    ],
    "sg:phone":"+1 317 326 2502",
    "sg:postcode":"46186",
    "sg:province":"IN",
    "sg:tags":[
        "church"
    ],
    "wof:name":"United Methodist Church",
    "wof:placetype":"venue"
},
  "geometry": {"coordinates":[-85.677533,39.901239],"type":"Point"}
}