{
  "type": "Feature",
  "properties": {
    "addr:full":"379 W US Hwy 30 Valparaiso IN 46385",
    "addr:housenumber":"379",
    "addr:postcode":"46385",
    "addr:street":"W Us Hwy 30",
    "iso:country":"US",
    "sg:address":"379 W US Hwy 30",
    "sg:city":"Valparaiso",
    "sg:classifiers":[
        {
            "category":"Professional",
            "subcategory":"Business Services",
            "type":"Services"
        }
    ],
    "sg:phone":"+1 219 462 1983",
    "sg:postcode":"46385",
    "sg:province":"IN",
    "wof:name":"All States Recovery Bureau",
    "wof:placetype":"venue"
},
  "geometry": {"coordinates":[-87.122376,41.465998],"type":"Point"}
}