{
  "type": "Feature",
  "properties": {
    "iso:country":"US",
    "sg:address":"8813 US Hwy 50",
    "sg:city":"Holton",
    "sg:classifiers":[
        {
            "category":"Wholesale",
            "subcategory":"Machinery & Supplies",
            "type":"Manufacturing & Wholesale Goods"
        }
    ],
    "sg:phone":"+1 812 689 7042",
    "sg:postcode":"47023",
    "sg:province":"IN",
    "sg:tags":[
        "pump"
    ],
    "wof:name":"Jones Water Well & Pump Svc",
    "wof:placetype":"venue"
},
  "geometry": {"coordinates":[-85.420531,39.06627],"type":"Point"}
}