{
  "type": "Feature",
  "properties": {
    "iso:country":"US",
    "sg:address":"4773 E 50 N",
    "sg:city":"Lafayette",
    "sg:classifiers":[
        {
            "category":"Home & Garden",
            "subcategory":"Home Furnishings",
            "type":"Retail Goods"
        }
    ],
    "sg:phone":"+1 765 447 3973",
    "sg:postcode":"47905",
    "sg:province":"IN",
    "sg:tags":[
        "curtain",
        "made",
        "drapery"
    ],
    "wof:name":"Sneek-A-Peek Blind Co",
    "wof:placetype":"venue"
},
  "geometry": {"coordinates":[-86.81051,40.424684],"type":"Point"}
}