{
  "type": "Feature",
  "properties": {
    "iso:country":"US",
    "sg:address":"500 Pearl St",
    "sg:city":"Fort Wayne",
    "sg:classifiers":[
        {
            "category":"Building & Trades",
            "subcategory":"Landscaping Services",
            "type":"Services"
        }
    ],
    "sg:phone":"+1 260 424 3418",
    "sg:postcode":"46802",
    "sg:province":"IN",
    "sg:tags":[
        "landscape",
        "contractor"
    ],
    "wof:name":"Thrifty Mow",
    "wof:placetype":"venue"
},
  "geometry": {"coordinates":[-85.147685,41.079489],"type":"Point"}
}