{
  "type": "Feature",
  "properties": {
    "iso:country":"US",
    "sg:address":"7000 W 128th Pl",
    "sg:city":"Cedar Lake",
    "sg:classifiers":[
        {
            "category":"Professional",
            "type":"Services"
        }
    ],
    "sg:phone":"+1 219 374 5834",
    "sg:postcode":"46303",
    "sg:province":"IN",
    "wof:name":"Jascor Systems",
    "wof:placetype":"venue"
},
  "geometry": {"coordinates":[-87.41676,41.385693],"type":"Point"}
}