{
  "type": "Feature",
  "properties": {
    "iso:country":"US",
    "sg:address":"5019 E Inlow Springs Rd",
    "sg:city":"Muncie",
    "sg:classifiers":[
        {
            "category":"Wholesale",
            "subcategory":"Construction Materials",
            "type":"Manufacturing & Wholesale Goods"
        }
    ],
    "sg:phone":"+1 765 282 6936",
    "sg:postcode":"47302",
    "sg:province":"IN",
    "sg:tags":[
        "fence"
    ],
    "wof:name":"Delaware Vinyl Fence",
    "wof:placetype":"venue"
},
  "geometry": {"coordinates":[-85.32211599999999,40.153642],"type":"Point"}
}