{
  "type": "Feature",
  "properties": {
    "iso:country":"US",
    "sg:address":"827 E Albion St",
    "sg:city":"Avilla",
    "sg:classifiers":[
        {
            "category":"Retail",
            "subcategory":"Auto Repair",
            "type":"Services"
        }
    ],
    "sg:phone":"+1 260 897 3695",
    "sg:postcode":"46710",
    "sg:province":"IN",
    "sg:tags":[
        "body",
        "automobile",
        "painting"
    ],
    "wof:name":"Brad's Body & Paint",
    "wof:placetype":"venue"
},
  "geometry": {"coordinates":[-85.236452,41.365825],"type":"Point"}
}