{
  "type": "Feature",
  "properties": {
    "iso:country":"US",
    "sg:address":"4805 E Michigan St",
    "sg:city":"Indianapolis",
    "sg:classifiers":[
        {
            "category":"Shopping",
            "subcategory":"Bicycles & Sporting Goods",
            "type":"Retail Goods"
        }
    ],
    "sg:phone":"+1 317 359 9868",
    "sg:postcode":"46201",
    "sg:province":"IN",
    "wof:name":"Instant Replay",
    "wof:placetype":"venue"
},
  "geometry": {"coordinates":[-86.087483,39.774778],"type":"Point"}
}