{
  "type": "Feature",
  "properties": {
    "iso:country":"US",
    "sg:address":"1989 Broadway",
    "sg:city":"Gary",
    "sg:classifiers":[
        {
            "category":"Autos & Motor Vehicles",
            "subcategory":"Auto Supplies",
            "type":"Retail Goods"
        }
    ],
    "sg:phone":"+1 219 885 7673",
    "sg:postcode":"46407",
    "sg:province":"IN",
    "sg:tags":[
        "automobile",
        "parts"
    ],
    "wof:name":"Broadway Auto Parts",
    "wof:placetype":"venue"
},
  "geometry": {"coordinates":[-87.33690300000001,41.583836],"type":"Point"}
}