{
  "type": "Feature",
  "properties": {
    "iso:country":"US",
    "sg:address":"11491 Kathmere Dr",
    "sg:city":"Osceola",
    "sg:classifiers":[
        {
            "category":"Professional",
            "subcategory":"Computer Services",
            "type":"Services"
        }
    ],
    "sg:phone":"+1 574 674 0408",
    "sg:postcode":"46561",
    "sg:province":"IN",
    "sg:tags":[
        "related"
    ],
    "wof:name":"Nehls Consulting",
    "wof:placetype":"venue"
},
  "geometry": {"coordinates":[-86.09081,41.679056],"type":"Point"}
}