{
  "type": "Feature",
  "properties": {
    "addr:full":"608 Lake John Cir Winona Lake IN 46590",
    "addr:housenumber":"608",
    "addr:postcode":"46590",
    "addr:street":"Lake John Cir",
    "iso:country":"US",
    "sg:address":"608 Lake John Cir",
    "sg:city":"Winona Lake",
    "sg:classifiers":[
        {
            "category":"Professional",
            "subcategory":"Computer Services",
            "type":"Services"
        }
    ],
    "sg:phone":"+1 574 267 2657",
    "sg:postcode":"46590",
    "sg:province":"IN",
    "sg:tags":[
        "consultant",
        "designer"
    ],
    "wof:name":"Tjm Data Technology Inc",
    "wof:placetype":"venue"
},
  "geometry": {"coordinates":[-85.81522,41.204399],"type":"Point"}
}