{
  "type": "Feature",
  "properties": {
    "iso:country":"US",
    "sg:address":"7623 Sunderland Dr",
    "sg:city":"Fort Wayne",
    "sg:classifiers":[
        {
            "category":"Professional",
            "subcategory":"Business Services",
            "type":"Services"
        }
    ],
    "sg:phone":"+1 260 485 2706",
    "sg:postcode":"46835",
    "sg:province":"IN",
    "wof:name":"Neats Enterprises Corp",
    "wof:placetype":"venue"
},
  "geometry": {"coordinates":[-85.067843,41.151983],"type":"Point"}
}