{
  "type": "Feature",
  "properties": {
    "iso:country":"US",
    "sg:address":"1660 Kessler Boulevard East Dr",
    "sg:city":"Indianapolis",
    "sg:classifiers":[
        {
            "category":"Place Of Worship",
            "subcategory":"Church",
            "type":"Public Place"
        },
        {
            "category":"Place Of Worship",
            "type":"Public Place"
        },
        {
            "category":"Social Services",
            "subcategory":"Child Care",
            "type":"Services"
        }
    ],
    "sg:phone":"+1 317 251 9489",
    "sg:postcode":"46220",
    "sg:province":"IN",
    "sg:tags":[
        "churches-presbyterian-arp",
        "nursery",
        "churches-presbyterian",
        "day"
    ],
    "sg:website":"http://www.pcwoodbury.com",
    "wof:name":"Northminster Cmty Pre-School",
    "wof:placetype":"venue"
},
  "geometry": {"coordinates":[-86.13149,39.862301],"type":"Point"}
}