{
  "type": "Feature",
  "properties": {
    "iso:country":"US",
    "sg:address":"2421 Hamburg Pike",
    "sg:city":"Jeffersonville",
    "sg:classifiers":[
        {
            "category":"Real Estate",
            "subcategory":"Developer",
            "type":"Services"
        }
    ],
    "sg:phone":"+1 812 283 3707",
    "sg:postcode":"47130",
    "sg:province":"IN",
    "sg:tags":[
        "cemetery"
    ],
    "wof:name":"Walnut Ridge Cemetery",
    "wof:placetype":"venue"
},
  "geometry": {"coordinates":[-85.74493200000001,38.305093],"type":"Point"}
}