{
  "type": "Feature",
  "properties": {
    "addr:full":"805 High St Decatur IN 46733",
    "addr:housenumber":"805",
    "addr:postcode":"46733",
    "addr:street":"High St",
    "iso:country":"US",
    "sg:address":"805 High St",
    "sg:city":"Decatur",
    "sg:classifiers":[
        {
            "category":"Organizations",
            "subcategory":"Non-profit Organization",
            "type":"Services"
        }
    ],
    "sg:phone":"+1 260 724 4303",
    "sg:postcode":"46733",
    "sg:province":"IN",
    "sg:tags":[
        "info",
        "addiction",
        "abuse",
        "treatment",
        "drug"
    ],
    "sg:website":"www.adamshospital.com",
    "wof:name":"Behavioral Health",
    "wof:placetype":"venue"
},
  "geometry": {"coordinates":[-84.918492,40.821354],"type":"Point"}
}