{
  "type": "Feature",
  "properties": {
    "addr:full":"140 N Main St Mulberry IN 46058",
    "addr:housenumber":"140",
    "addr:postcode":"46058",
    "addr:street":"N Main St",
    "iso:country":"US",
    "sg:address":"140 N Main St",
    "sg:city":"Mulberry",
    "sg:classifiers":[
        {
            "category":"Building & Trades",
            "subcategory":"Construction",
            "type":"Services"
        }
    ],
    "sg:phone":"+1 765 296 4460",
    "sg:postcode":"46058",
    "sg:province":"IN",
    "sg:tags":[
        "general",
        "contractor"
    ],
    "wof:name":"Quality Gutter Svc",
    "wof:placetype":"venue"
},
  "geometry": {"coordinates":[-86.665149,40.345579],"type":"Point"}
}