{
  "type": "Feature",
  "properties": {
    "iso:country":"US",
    "sg:address":"4451 W 5th Ave",
    "sg:city":"Gary",
    "sg:classifiers":[
        {
            "category":"Home & Garden",
            "subcategory":"Home Furnishings",
            "type":"Retail Goods"
        }
    ],
    "sg:phone":"+1 219 949 1705",
    "sg:postcode":"46406",
    "sg:province":"IN",
    "sg:tags":[
        "mirror"
    ],
    "wof:name":"Glass Depot Inc",
    "wof:placetype":"venue"
},
  "geometry": {"coordinates":[-87.39267700000001,41.601861],"type":"Point"}
}