{
  "type": "Feature",
  "properties": {
    "iso:country":"US",
    "sg:address":"10801 US Hwy 24 E",
    "sg:city":"New Haven",
    "sg:classifiers":[
        {
            "category":"Manufacturing",
            "subcategory":"Metals",
            "type":"Manufacturing & Wholesale Goods"
        }
    ],
    "sg:phone":"+1 260 748 6000",
    "sg:postcode":"46774",
    "sg:province":"IN",
    "wof:name":"Parker-Hannifin Corp",
    "wof:placetype":"venue"
},
  "geometry": {"coordinates":[-85.000807,41.07933],"type":"Point"}
}