{
  "type": "Feature",
  "properties": {
    "iso:country":"US",
    "sg:address":"505 Vistula St",
    "sg:city":"Elkhart",
    "sg:classifiers":[
        {
            "category":"Health Services",
            "subcategory":"Doctor",
            "type":"Services"
        }
    ],
    "sg:phone":"+1 574 293 2003",
    "sg:postcode":"46516",
    "sg:province":"IN",
    "sg:tags":[
        "dentist"
    ],
    "sg:website":"www.drbryan.com",
    "wof:name":"Norman E Bryan DDS",
    "wof:placetype":"venue"
},
  "geometry": {"coordinates":[-85.978695,41.683732],"type":"Point"}
}