{
  "type": "Feature",
  "properties": {
    "iso:country":"US",
    "sg:address":"5121 Archwood Ln",
    "sg:city":"Fort Wayne",
    "sg:classifiers":[
        {
            "category":"Professional",
            "subcategory":"Engineering",
            "type":"Services"
        }
    ],
    "sg:phone":"+1 260 484 8948",
    "sg:postcode":"46825",
    "sg:province":"IN",
    "wof:name":"E L A G Inc",
    "wof:placetype":"venue"
},
  "geometry": {"coordinates":[-85.130872,41.125424],"type":"Point"}
}