{
  "type": "Feature",
  "properties": {
    "iso:country":"US",
    "sg:address":"2314 Lake Ave",
    "sg:city":"Fort Wayne",
    "sg:classifiers":[
        {
            "category":"Social Services",
            "type":"Services"
        }
    ],
    "sg:phone":"+1 260 425 9828",
    "sg:postcode":"46805",
    "sg:province":"IN",
    "sg:tags":[
        "organization",
        "welfare"
    ],
    "sg:website":"www.dunncenter.org",
    "wof:name":"Foster Care Plus",
    "wof:placetype":"venue"
},
  "geometry": {"coordinates":[-85.107188,41.089733],"type":"Point"}
}