{
  "type": "Feature",
  "properties": {
    "iso:country":"US",
    "sg:address":"41 N Madison Ave",
    "sg:city":"Greenwood",
    "sg:classifiers":[
        {
            "category":"Health Services",
            "subcategory":"Doctor",
            "type":"Services"
        }
    ],
    "sg:phone":"+1 317 882 4412",
    "sg:postcode":"46142",
    "sg:province":"IN",
    "sg:tags":[
        "dentist"
    ],
    "wof:name":"Randall C Christie DDS",
    "wof:placetype":"venue"
},
  "geometry": {"coordinates":[-86.1105,39.61606],"type":"Point"}
}