{
  "type": "Feature",
  "properties": {
    "iso:country":"US",
    "sg:address":"10101 N Meridian St",
    "sg:city":"Indianapolis",
    "sg:classifiers":[
        {
            "category":"Retail",
            "subcategory":"Auto Rental",
            "type":"Services"
        }
    ],
    "sg:phone":"+1 317 706 0359",
    "sg:postcode":"46290",
    "sg:province":"IN",
    "sg:tags":[
        "car"
    ],
    "sg:website":"www.enterprise.com",
    "wof:name":"Enterprise Rent-A-Car",
    "wof:placetype":"venue"
},
  "geometry": {"coordinates":[-86.157636,39.933667],"type":"Point"}
}