{
  "type": "Feature",
  "properties": {
    "iso:country":"US",
    "sg:address":"645 W 11th St",
    "sg:city":"Indianapolis",
    "sg:classifiers":[
        {
            "category":"Cinema",
            "subcategory":"Movie Rental",
            "type":"Entertainment"
        }
    ],
    "sg:phone":"+1 317 453 0562",
    "sg:postcode":"46202",
    "sg:province":"IN",
    "sg:tags":[
        "leasing",
        "video",
        "disc",
        "tape"
    ],
    "wof:name":"Hollywood Video",
    "wof:placetype":"venue"
},
  "geometry": {"coordinates":[-86.1703,39.781929],"type":"Point"}
}