{
  "type": "Feature",
  "properties": {
    "addr:full":"5801 Kennedy Ter Gary IN 46403",
    "addr:housenumber":"5801",
    "addr:postcode":"46403",
    "addr:street":"Kennedy Ter Gary",
    "iso:country":"US",
    "sg:address":"5801 Kennedy Ter",
    "sg:city":"Gary",
    "sg:classifiers":[
        {
            "category":"Shopping",
            "subcategory":"Clothing, Apparel, & Fashions",
            "type":"Retail Goods"
        }
    ],
    "sg:phone":"+1 219 938 8908",
    "sg:postcode":"46403",
    "sg:province":"IN",
    "sg:tags":[
        "garment"
    ],
    "wof:name":"Mid West Authentic Apparel",
    "wof:placetype":"venue"
},
  "geometry": {"coordinates":[-87.270003,41.612252],"type":"Point"}
}