{
  "type": "Feature",
  "properties": {
    "iso:country":"US",
    "sg:address":"4821 Hardegan St",
    "sg:city":"Indianapolis",
    "sg:classifiers":[
        {
            "category":"Wholesale",
            "subcategory":"Durable Goods & Equipment",
            "type":"Manufacturing & Wholesale Goods"
        }
    ],
    "sg:phone":"+1 317 783 3360",
    "sg:postcode":"46227",
    "sg:province":"IN",
    "sg:tags":[
        "representative",
        "manufacturer"
    ],
    "wof:name":"Hotle Sales Co",
    "wof:placetype":"venue"
},
  "geometry": {"coordinates":[-86.125144,39.687109],"type":"Point"}
}