{
  "type": "Feature",
  "properties": {
    "iso:country":"US",
    "sg:address":"7030 W 665 S",
    "sg:city":"Topeka",
    "sg:classifiers":[
        {
            "category":"Shopping",
            "subcategory":"Clothing, Apparel, & Fashions",
            "type":"Retail Goods"
        }
    ],
    "sg:phone":"+1 260 593 2937",
    "sg:postcode":"46571",
    "sg:province":"IN",
    "wof:name":"Djs Sportswear",
    "wof:placetype":"venue"
},
  "geometry": {"coordinates":[-85.559577,41.543888],"type":"Point"}
}