{
  "type": "Feature",
  "properties": {
    "iso:country":"US",
    "sg:address":"850 Main St",
    "sg:city":"Ferdinand",
    "sg:classifiers":[
        {
            "category":"Food & Beverages",
            "subcategory":"Groceries & Convenience Stores",
            "type":"Retail Goods"
        }
    ],
    "sg:phone":"+1 812 367 2351",
    "sg:postcode":"47532",
    "sg:province":"IN",
    "wof:name":"Circle S",
    "wof:placetype":"venue"
},
  "geometry": {"coordinates":[-86.862236,38.223136],"type":"Point"}
}