{
  "type": "Feature",
  "properties": {
    "iso:country":"US",
    "sg:address":"2300 Ramblewood Dr",
    "sg:city":"Highland",
    "sg:classifiers":[
        {
            "category":"Banks & Credit Unions",
            "subcategory":"Investment Brokerage",
            "type":"Services"
        }
    ],
    "sg:phone":"+1 219 924 0957",
    "sg:postcode":"46322",
    "sg:province":"IN",
    "sg:tags":[
        "consultant",
        "planning",
        "financial"
    ],
    "wof:name":"American Express Financial Adv",
    "wof:placetype":"venue"
},
  "geometry": {"coordinates":[-87.473249,41.526604],"type":"Point"}
}