{
  "type": "Feature",
  "properties": {
    "iso:country":"US",
    "sg:address":"1508 N Washington St",
    "sg:city":"Kokomo",
    "sg:classifiers":[
        {
            "category":"Retail",
            "subcategory":"Laundry & Dry Cleaning",
            "type":"Services"
        }
    ],
    "sg:phone":"+1 765 459 3473",
    "sg:postcode":"46901",
    "sg:province":"IN",
    "sg:tags":[
        "cleaners",
        "rug",
        "carpet"
    ],
    "wof:name":"Serv Pro",
    "wof:placetype":"venue"
},
  "geometry": {"coordinates":[-86.133663,40.501679],"type":"Point"}
}