{
  "type": "Feature",
  "properties": {
    "iso:country":"US",
    "sg:address":"2134 S Holiday Dr",
    "sg:city":"Peru",
    "sg:classifiers":[
        {
            "category":"Shopping",
            "type":"Retail Goods"
        }
    ],
    "sg:phone":"+1 765 473 9050",
    "sg:postcode":"46970",
    "sg:province":"IN",
    "sg:tags":[
        "merchandise"
    ],
    "wof:name":"Loyalty Rubber Stamp Works",
    "wof:placetype":"venue"
},
  "geometry": {"coordinates":[-86.11279399999999,40.73375],"type":"Point"}
}