{
  "type": "Feature",
  "properties": {
    "iso:country":"US",
    "sg:address":"3824 E State Blvd",
    "sg:city":"Fort Wayne",
    "sg:classifiers":[
        {
            "category":"Education",
            "subcategory":"Dance Studio",
            "type":"Public Place"
        }
    ],
    "sg:phone":"+1 260 483 1139",
    "sg:postcode":"46805",
    "sg:province":"IN",
    "sg:tags":[
        "instruction",
        "dancing"
    ],
    "wof:name":"Arthur Murray Dance Studio",
    "wof:placetype":"venue"
},
  "geometry": {"coordinates":[-85.09040299999999,41.097526],"type":"Point"}
}