{
  "type": "Feature",
  "properties": {
    "addr:full":"539 N Halleck St Demotte IN 46310",
    "addr:housenumber":"539",
    "addr:postcode":"46310",
    "addr:street":"N Halleck St",
    "iso:country":"US",
    "sg:address":"539 N Halleck St",
    "sg:city":"Demotte",
    "sg:classifiers":[
        {
            "category":"Home & Garden",
            "subcategory":"Hardware",
            "type":"Retail Goods"
        }
    ],
    "sg:phone":"+1 219 987 3171",
    "sg:postcode":"46310",
    "sg:province":"IN",
    "wof:name":"Hillside Ace Hardware",
    "wof:placetype":"venue"
},
  "geometry": {"coordinates":[-87.198778,41.207821],"type":"Point"}
}