{
  "type": "Feature",
  "properties": {
    "addr:full":"7014 Beaty Ave Fort Wayne IN 46809",
    "addr:housenumber":"7014",
    "addr:postcode":"46809",
    "addr:street":"Beaty Ave",
    "iso:country":"US",
    "sg:address":"7014 Beaty Ave",
    "sg:city":"Fort Wayne",
    "sg:classifiers":[
        {
            "category":"Professional",
            "type":"Services"
        }
    ],
    "sg:phone":"+1 260 747 5034",
    "sg:postcode":"46809",
    "sg:province":"IN",
    "sg:tags":[
        "creative"
    ],
    "wof:name":"M J Endeavors",
    "wof:placetype":"venue"
},
  "geometry": {"coordinates":[-85.17653,41.017758],"type":"Point"}
}