{
  "type": "Feature",
  "properties": {
    "iso:country":"US",
    "sg:address":"105 N 7th St",
    "sg:city":"Garrett",
    "sg:classifiers":[
        {
            "category":"Real Estate",
            "subcategory":"Real Estate Operator",
            "type":"Services"
        }
    ],
    "sg:phone":"+1 260 357 0532",
    "sg:postcode":"46738",
    "sg:province":"IN",
    "sg:tags":[
        "building",
        "apartment"
    ],
    "wof:name":"Deer Creek Crossing",
    "wof:placetype":"venue"
},
  "geometry": {"coordinates":[-85.11882,41.350591],"type":"Point"}
}