{
  "type": "Feature",
  "properties": {
    "iso:country":"US",
    "sg:address":"14910 Roy J Ln",
    "sg:city":"Borden",
    "sg:classifiers":[
        {
            "category":"Professional",
            "subcategory":"Computer Services",
            "type":"Services"
        }
    ],
    "sg:phone":"+1 812 246 4164",
    "sg:postcode":"47106",
    "sg:province":"IN",
    "sg:tags":[
        "programing",
        "custom"
    ],
    "wof:name":"CA",
    "wof:placetype":"venue"
},
  "geometry": {"coordinates":[-85.858795,38.444413],"type":"Point"}
}