{
  "type": "Feature",
  "properties": {
    "iso:country":"US",
    "sg:address":"3936 Pendleton Way",
    "sg:city":"Indianapolis",
    "sg:classifiers":[
        {
            "category":"Education",
            "subcategory":"Vocational School",
            "type":"Public Place"
        }
    ],
    "sg:phone":"+1 317 541 0737",
    "sg:postcode":"46226",
    "sg:province":"IN",
    "sg:tags":[
        "instruction",
        "truck",
        "driving"
    ],
    "wof:name":"Commercial Career Ctr USA",
    "wof:placetype":"venue"
},
  "geometry": {"coordinates":[-86.035602,39.830066],"type":"Point"}
}