{
  "type": "Feature",
  "properties": {
    "iso:country":"US",
    "sg:address":"220 N Franklin St",
    "sg:city":"Rensselaer",
    "sg:classifiers":[
        {
            "category":"Organizations",
            "subcategory":"Religious Organization",
            "type":"Services"
        }
    ],
    "sg:phone":"+1 219 866 7978",
    "sg:postcode":"47978",
    "sg:province":"IN",
    "wof:name":"Apostolic Bible Church",
    "wof:placetype":"venue"
},
  "geometry": {"coordinates":[-87.14929600000001,40.940376],"type":"Point"}
}