{
  "type": "Feature",
  "properties": {
    "iso:country":"US",
    "sg:address":"807 S Walnut St",
    "sg:city":"Bloomington",
    "sg:classifiers":[
        {
            "category":"Autos & Motor Vehicles",
            "subcategory":"Automobile Sales",
            "type":"Retail Goods"
        }
    ],
    "sg:phone":"+1 812 334 3444",
    "sg:postcode":"47401",
    "sg:province":"IN",
    "sg:tags":[
        "car",
        "dealer"
    ],
    "wof:name":"Indiana Auto Sales Inc",
    "wof:placetype":"venue"
},
  "geometry": {"coordinates":[-86.533588,39.156687],"type":"Point"}
}