{
  "type": "Feature",
  "properties": {
    "iso:country":"US",
    "sg:address":"1501 W Bethel Ave",
    "sg:city":"Muncie",
    "sg:classifiers":[
        {
            "category":"Retail",
            "subcategory":"Auto Repair",
            "type":"Services"
        }
    ],
    "sg:phone":"+1 765 289 5669",
    "sg:postcode":"47304",
    "sg:province":"IN",
    "sg:tags":[
        "repairing",
        "automobile"
    ],
    "wof:name":"Garrett's Automotive",
    "wof:placetype":"venue"
},
  "geometry": {"coordinates":[-85.4046,40.208847],"type":"Point"}
}