{
  "type": "Feature",
  "properties": {
    "iso:country":"US",
    "sg:address":"3800 179th St",
    "sg:city":"Hammond",
    "sg:classifiers":[
        {
            "category":"Professional",
            "subcategory":"Engineering",
            "type":"Services"
        }
    ],
    "sg:phone":"+1 219 989 3300",
    "sg:postcode":"46323",
    "sg:province":"IN",
    "sg:tags":[
        "engineer"
    ],
    "sg:website":"www.orbitalengr.com",
    "wof:name":"Orbital Engineering Inc",
    "wof:placetype":"venue"
},
  "geometry": {"coordinates":[-87.43389999999999,41.56888],"type":"Point"}
}