{
  "type": "Feature",
  "properties": {
    "iso:country":"US",
    "sg:address":"8004 Tyler St",
    "sg:city":"Merrillville",
    "sg:classifiers":[
        {
            "category":"Home & Garden",
            "subcategory":"Household Appliances",
            "type":"Retail Goods"
        }
    ],
    "sg:phone":"+1 219 756 6300",
    "sg:postcode":"46410",
    "sg:province":"IN",
    "sg:tags":[
        "cleaners",
        "vacuum"
    ],
    "wof:name":"Great Lakes Tri Star Inc",
    "wof:placetype":"venue"
},
  "geometry": {"coordinates":[-87.347257,41.472094],"type":"Point"}
}