{
  "type": "Feature",
  "properties": {
    "iso:country":"US",
    "sg:address":"9498 E 250 S",
    "sg:city":"Pierceton",
    "sg:classifiers":[
        {
            "category":"Building & Trades",
            "subcategory":"Construction",
            "type":"Services"
        }
    ],
    "sg:phone":"+1 574 594 5032",
    "sg:postcode":"46562",
    "sg:province":"IN",
    "sg:tags":[
        "home",
        "builder"
    ],
    "wof:name":"Century Cedar Log Homes",
    "wof:placetype":"venue"
},
  "geometry": {"coordinates":[-85.661914,41.200315],"type":"Point"}
}