{
  "type": "Feature",
  "properties": {
    "iso:country":"US",
    "sg:address":"8081 Township Line Rd",
    "sg:city":"Indianapolis",
    "sg:classifiers":[
        {
            "category":"Professional",
            "subcategory":"Research",
            "type":"Services"
        }
    ],
    "sg:phone":"+1 317 875 0303",
    "sg:postcode":"46260",
    "sg:province":"IN",
    "sg:tags":[
        "laboratory"
    ],
    "wof:name":"Indianapolis Laboratory",
    "wof:placetype":"venue"
},
  "geometry": {"coordinates":[-86.20295400000001,39.902665],"type":"Point"}
}