{
  "type": "Feature",
  "properties": {
    "iso:country":"US",
    "sg:address":"1340 N Alabama St",
    "sg:city":"Indianapolis",
    "sg:classifiers":[
        {
            "category":"Travel",
            "subcategory":"Hotels & Motels",
            "type":"Entertainment"
        }
    ],
    "sg:phone":"+1 317 635 9123",
    "sg:postcode":"46202",
    "sg:province":"IN",
    "sg:tags":[
        "breakfast",
        "bed",
        "lodging"
    ],
    "sg:website":"http://www.oldnorthsideinn.com",
    "wof:name":"Old Northside Bed & Breakfast",
    "wof:placetype":"venue"
},
  "geometry": {"coordinates":[-86.15215600000001,39.784885],"type":"Point"}
}