{
  "type": "Feature",
  "properties": {
    "addr:full":"1400 State Rd 28 W Romney IN 47981",
    "addr:housenumber":"1400;28",
    "addr:postcode":"47981",
    "addr:street":"State Rd;W",
    "iso:country":"US",
    "sg:address":"1400 State Rd 28 W",
    "sg:city":"Romney",
    "sg:classifiers":[
        {
            "category":"Farming",
            "subcategory":"Farm",
            "type":"Manufacturing & Wholesale Goods"
        }
    ],
    "sg:phone":"+1 765 538 3667",
    "sg:postcode":"47981",
    "sg:province":"IN",
    "wof:name":"Laffoon Farms",
    "wof:placetype":"venue"
},
  "geometry": {"coordinates":[-86.93153,40.25862],"type":"Point"}
}