{
  "type": "Feature",
  "properties": {
    "iso:country":"US",
    "sg:address":"4612 Standish Dr",
    "sg:city":"Fort Wayne",
    "sg:classifiers":[
        {
            "category":"Retail",
            "subcategory":"Repair Shop",
            "type":"Services"
        }
    ],
    "sg:phone":"+1 260 744 6378",
    "sg:postcode":"46806",
    "sg:province":"IN",
    "sg:tags":[
        "electrical"
    ],
    "wof:name":"Affordable D JS",
    "wof:placetype":"venue"
},
  "geometry": {"coordinates":[-85.107632,41.039451],"type":"Point"}
}