{
  "type": "Feature",
  "properties": {
    "iso:country":"US",
    "sg:address":"7923 Cullen Dr",
    "sg:city":"Indianapolis",
    "sg:classifiers":[
        {
            "category":"Insurance",
            "subcategory":"Insurance Agent",
            "type":"Services"
        }
    ],
    "sg:phone":"+1 317 356 3684",
    "sg:postcode":"46219",
    "sg:province":"IN",
    "wof:name":"Anthenm Blue Cross Blue Shield",
    "wof:placetype":"venue"
},
  "geometry": {"coordinates":[-86.028317,39.800961],"type":"Point"}
}