{
  "type": "Feature",
  "properties": {
    "addr:full":"112 S 12th St Chesterton IN 46304",
    "addr:housenumber":"112",
    "addr:postcode":"46304",
    "addr:street":"S 12Th St",
    "iso:country":"US",
    "sg:address":"112 S 12th St",
    "sg:city":"Chesterton",
    "sg:classifiers":[
        {
            "category":"Shopping",
            "type":"Retail Goods"
        }
    ],
    "sg:phone":"+1 219 395 8887",
    "sg:postcode":"46304",
    "sg:province":"IN",
    "sg:tags":[
        "pet",
        "shop"
    ],
    "wof:name":"Duneland Pet Store",
    "wof:placetype":"venue"
},
  "geometry": {"coordinates":[-87.067893,41.610637],"type":"Point"}
}