{
  "type": "Feature",
  "properties": {
    "iso:country":"US",
    "sg:address":"1051 E Winona Ave",
    "sg:city":"Warsaw",
    "sg:classifiers":[
        {
            "category":"Autos & Motor Vehicles",
            "subcategory":"Automobile Sales",
            "type":"Retail Goods"
        }
    ],
    "sg:phone":"+1 574 268 6366",
    "sg:postcode":"46580",
    "sg:province":"IN",
    "sg:tags":[
        "car",
        "dealer"
    ],
    "wof:name":"T J Auto Sales",
    "wof:placetype":"venue"
},
  "geometry": {"coordinates":[-85.840982,41.235504],"type":"Point"}
}