{
  "type": "Feature",
  "properties": {
    "addr:full":"3728 W 400 S Williamsport IN 47993",
    "addr:housenumber":"3728",
    "addr:postcode":"47993",
    "addr:street":"W 400 S Williamsport",
    "iso:country":"US",
    "sg:address":"3728 W 400 S",
    "sg:city":"Williamsport",
    "sg:classifiers":[
        {
            "category":"Farming",
            "subcategory":"Farm",
            "type":"Manufacturing & Wholesale Goods"
        }
    ],
    "sg:phone":"+1 765 893 4676",
    "sg:postcode":"47993",
    "sg:province":"IN",
    "sg:tags":[
        "crop",
        "general"
    ],
    "wof:name":"John Salts",
    "wof:placetype":"venue"
},
  "geometry": {"coordinates":[-87.392956,40.25801],"type":"Point"}
}