{
  "type": "Feature",
  "properties": {
    "iso:country":"US",
    "sg:address":"2127 Mathias St",
    "sg:city":"Fort Wayne",
    "sg:classifiers":[
        {
            "category":"Retail",
            "subcategory":"Repair Shop",
            "type":"Services"
        }
    ],
    "sg:phone":"+1 260 482 3793",
    "sg:postcode":"46815",
    "sg:province":"IN",
    "sg:tags":[
        "equipment"
    ],
    "wof:name":"Professional Food Equip Svc",
    "wof:placetype":"venue"
},
  "geometry": {"coordinates":[-85.086043,41.097435],"type":"Point"}
}