{
  "type": "Feature",
  "properties": {
    "iso:country":"US",
    "sg:address":"115 E Spring St",
    "sg:city":"New Albany",
    "sg:classifiers":[
        {
            "category":"Manufacturing",
            "subcategory":"Printing",
            "type":"Manufacturing & Wholesale Goods"
        }
    ],
    "sg:phone":"+1 812 945 7453",
    "sg:postcode":"47150",
    "sg:province":"IN",
    "sg:tags":[
        "typesetting"
    ],
    "wof:name":"Pam C Jones Typography",
    "wof:placetype":"venue"
},
  "geometry": {"coordinates":[-85.823584,38.285889],"type":"Point"}
}