{
  "type": "Feature",
  "properties": {
    "iso:country":"US",
    "sg:address":"8796 S US Hwy 231",
    "sg:city":"Brookston",
    "sg:classifiers":[
        {
            "category":"Retail",
            "subcategory":"Repair Shop",
            "type":"Services"
        }
    ],
    "sg:phone":"+1 765 563 3158",
    "sg:postcode":"47923",
    "sg:province":"IN",
    "sg:tags":[
        "welding"
    ],
    "wof:name":"Sunset Prairie",
    "wof:placetype":"venue"
},
  "geometry": {"coordinates":[-87.031105,40.62392],"type":"Point"}
}