{
  "type": "Feature",
  "properties": {
    "iso:country":"US",
    "sg:address":"6600 Springfield Rd",
    "sg:city":"Wadesville",
    "sg:phone":"+1 812 673 4498",
    "sg:postcode":"47638",
    "sg:province":"IN",
    "sg:tags":[
        "farm",
        "corn",
        "soybean"
    ],
    "wof:name":"Tepool Farms",
    "wof:placetype":"venue"
},
  "geometry": {"coordinates":[-87.792371,38.085554],"type":"Point"}
}