{
  "type": "Feature",
  "properties": {
    "iso:country":"US",
    "sg:address":"1250 N McKinley Ave",
    "sg:city":"Rensselaer",
    "sg:classifiers":[
        {
            "category":"Professional",
            "subcategory":"Computer Services",
            "type":"Services"
        }
    ],
    "sg:phone":"+1 219 866 7627",
    "sg:postcode":"47978",
    "sg:province":"IN",
    "wof:name":"Solectek Corp",
    "wof:placetype":"venue"
},
  "geometry": {"coordinates":[-87.15131599999999,40.947302],"type":"Point"}
}