{
  "type": "Feature",
  "properties": {
    "iso:country":"US",
    "sg:address":"581 E Main St",
    "sg:city":"Hagerstown",
    "sg:classifiers":[
        {
            "category":"Autos & Motor Vehicles",
            "subcategory":"Motorcycle Sales",
            "type":"Retail Goods"
        }
    ],
    "sg:phone":"+1 765 489 4075",
    "sg:postcode":"47346",
    "sg:province":"IN",
    "sg:tags":[
        "scooter"
    ],
    "wof:name":"Flatlanders",
    "wof:placetype":"venue"
},
  "geometry": {"coordinates":[-85.152335,39.910476],"type":"Point"}
}