{
  "type": "Feature",
  "properties": {
    "iso:country":"US",
    "sg:address":"3775 E Thompson Rd",
    "sg:city":"Indianapolis",
    "sg:classifiers":[
        {
            "category":"Professional",
            "type":"Services"
        }
    ],
    "sg:phone":"+1 317 784 9474",
    "sg:postcode":"46237",
    "sg:province":"IN",
    "wof:name":"Georgiann Pitcher",
    "wof:placetype":"venue"
},
  "geometry": {"coordinates":[-86.096906,39.693338],"type":"Point"}
}