{
  "type": "Feature",
  "properties": {
    "addr:full":"7171 N Pennsylvania St Indianapolis IN 46240",
    "addr:housenumber":"7171",
    "addr:postcode":"46240",
    "addr:street":"N Pennsylvania St",
    "iso:country":"US",
    "sg:address":"7171 N Pennsylvania St",
    "sg:city":"Indianapolis",
    "sg:classifiers":[
        {
            "category":"Place Of Worship",
            "subcategory":"Church",
            "type":"Public Place"
        },
        {
            "category":"Place Of Worship",
            "type":"Public Place"
        }
    ],
    "sg:phone":"+1 317 257 5397",
    "sg:postcode":"46240",
    "sg:province":"IN",
    "sg:tags":[
        "churches-united",
        "christ",
        "denomination",
        "churches-interdenominational",
        "churches-various"
    ],
    "wof:name":"First Congregational Church",
    "wof:placetype":"venue"
},
  "geometry": {"coordinates":[-86.15541,39.884778],"type":"Point"}
}