{
  "type": "Feature",
  "properties": {
    "addr:full":"5210 E Morgan Ave Evansville IN 47715",
    "addr:housenumber":"5210",
    "addr:postcode":"47715",
    "addr:street":"E Morgan Ave",
    "iso:country":"US",
    "sg:address":"5210 E Morgan Ave",
    "sg:city":"Evansville",
    "sg:classifiers":[
        {
            "category":"Wholesale",
            "subcategory":"Farm Supplies",
            "type":"Manufacturing & Wholesale Goods"
        }
    ],
    "sg:phone":"+1 812 477 6497",
    "sg:postcode":"47715",
    "sg:province":"IN",
    "wof:name":"Tractor Supply Co",
    "wof:placetype":"venue"
},
  "geometry": {"coordinates":[-87.482936,37.993176],"type":"Point"}
}