{
  "type": "Feature",
  "properties": {
    "iso:country":"US",
    "sg:address":"1212 S Bloomington St",
    "sg:city":"Greencastle",
    "sg:classifiers":[
        {
            "category":"Health Services",
            "subcategory":"Doctor",
            "type":"Services"
        }
    ],
    "sg:phone":"+1 765 653 5653",
    "sg:postcode":"46135",
    "sg:province":"IN",
    "sg:tags":[
        "dentist"
    ],
    "wof:name":"Mark A Smith DDS",
    "wof:placetype":"venue"
},
  "geometry": {"coordinates":[-86.851718,39.631822],"type":"Point"}
}