{
  "type": "Feature",
  "properties": {
    "iso:country":"US",
    "sg:address":"108 E Washington St",
    "sg:city":"Hartford City",
    "sg:classifiers":[
        {
            "category":"Bars & Pubs",
            "type":"Food & Drink"
        }
    ],
    "sg:phone":"+1 765 348 9978",
    "sg:postcode":"47348",
    "sg:province":"IN",
    "wof:name":"Glorious Washington Street Bar",
    "wof:placetype":"venue"
},
  "geometry": {"coordinates":[-85.367304,40.451186],"type":"Point"}
}