{
  "type": "Feature",
  "properties": {
    "iso:country":"US",
    "sg:address":"2306 Bishop Rd",
    "sg:city":"Jeffersonville",
    "sg:classifiers":[
        {
            "category":"Professional",
            "subcategory":"Lawyer & Legal Services",
            "type":"Services"
        }
    ],
    "sg:phone":"+1 812 284 1128",
    "sg:postcode":"47130",
    "sg:province":"IN",
    "wof:name":"Bennett C & Associate LLC",
    "wof:placetype":"venue"
},
  "geometry": {"coordinates":[-85.739482,38.336036],"type":"Point"}
}