{
  "type": "Feature",
  "properties": {
    "iso:country":"US",
    "sg:address":"412 Covington St",
    "sg:city":"Crawfordsville",
    "sg:classifiers":[
        {
            "category":"Government",
            "subcategory":"Jail",
            "type":"Public Place"
        }
    ],
    "sg:phone":"+1 765 362 3740",
    "sg:postcode":"47933",
    "sg:province":"IN",
    "sg:tags":[
        "county",
        "govt",
        "institution"
    ],
    "wof:name":"Montgomery County Jail",
    "wof:placetype":"venue"
},
  "geometry": {"coordinates":[-86.906198,40.046848],"type":"Point"}
}