{
  "type": "Feature",
  "properties": {
    "iso:country":"US",
    "sg:address":"715 S Rangeline Rd",
    "sg:city":"Carmel",
    "sg:classifiers":[
        {
            "category":"Personal",
            "subcategory":"Massage",
            "type":"Services"
        },
        {
            "category":"Health Services",
            "subcategory":"Clinic",
            "type":"Services"
        }
    ],
    "sg:phone":"+1 317 569 8716",
    "sg:postcode":"46032",
    "sg:province":"IN",
    "sg:tags":[
        "spa",
        "medical"
    ],
    "wof:name":"Dove Spa",
    "wof:placetype":"venue"
},
  "geometry": {"coordinates":[-86.12697,39.969963],"type":"Point"}
}