{
  "type": "Feature",
  "properties": {
    "iso:country":"US",
    "sg:address":"153 E Main St",
    "sg:city":"New Albany",
    "sg:classifiers":[
        {
            "category":"Autos & Motor Vehicles",
            "subcategory":"Auto Supplies",
            "type":"Retail Goods"
        }
    ],
    "sg:phone":"+1 812 945 8921",
    "sg:postcode":"47150",
    "sg:province":"IN",
    "sg:tags":[
        "automobile",
        "parts"
    ],
    "wof:name":"Happys",
    "wof:placetype":"venue"
},
  "geometry": {"coordinates":[-85.821925,38.283837],"type":"Point"}
}