{
  "type": "Feature",
  "properties": {
    "addr:full":"702 E Indiana Ave South Bend IN 46613",
    "addr:housenumber":"702",
    "addr:postcode":"46613",
    "addr:street":"E Indiana Ave",
    "iso:country":"US",
    "sg:address":"702 E Indiana Ave",
    "sg:city":"South Bend",
    "sg:classifiers":[
        {
            "category":"Retail",
            "subcategory":"Repair Shop",
            "type":"Services"
        }
    ],
    "sg:phone":"+1 574 232 7746",
    "sg:postcode":"46613",
    "sg:province":"IN",
    "sg:tags":[
        "related"
    ],
    "wof:name":"Spin Techs",
    "wof:placetype":"venue"
},
  "geometry": {"coordinates":[-86.24018599999999,41.658068],"type":"Point"}
}