{
  "type": "Feature",
  "properties": {
    "addr:full":"4747 Broadway Gary IN 46409",
    "addr:housenumber":"4747",
    "addr:postcode":"46409",
    "addr:street":"Broadway",
    "iso:country":"US",
    "sg:address":"4747 Broadway",
    "sg:city":"Gary",
    "sg:classifiers":[
        {
            "category":"Professional",
            "subcategory":"Accounting & Tax Preparation",
            "type":"Services"
        }
    ],
    "sg:phone":"+1 219 981 4000",
    "sg:postcode":"46409",
    "sg:province":"IN",
    "sg:tags":[
        "return",
        "filing"
    ],
    "sg:website":"www.jhnet.net",
    "wof:name":"Jackson Hewitt Tax Svc",
    "wof:placetype":"venue"
},
  "geometry": {"coordinates":[-87.336163,41.532148],"type":"Point"}
}