{
  "type": "Feature",
  "properties": {
    "iso:country":"US",
    "sg:address":"1099 N Karwick Rd",
    "sg:city":"Michigan City",
    "sg:classifiers":[
        {
            "category":"Professional",
            "type":"Services"
        }
    ],
    "sg:phone":"+1 219 878 0931",
    "sg:postcode":"46360",
    "sg:province":"IN",
    "wof:name":"Austin Services Corp",
    "wof:placetype":"venue"
},
  "geometry": {"coordinates":[-86.85559000000001,41.739222],"type":"Point"}
}