{
  "type": "Feature",
  "properties": {
    "addr:full":"11228 Carroll Rd Churubusco IN 46723",
    "addr:housenumber":"11228",
    "addr:postcode":"46723",
    "addr:street":"Carroll Rd",
    "iso:country":"US",
    "sg:address":"11228 Carroll Rd",
    "sg:city":"Churubusco",
    "sg:classifiers":[
        {
            "category":"Organizations",
            "subcategory":"Religious Organization",
            "type":"Services"
        }
    ],
    "sg:phone":"+1 260 693 3453",
    "sg:postcode":"46723",
    "sg:province":"IN",
    "wof:name":"First Eel River Baptist Church",
    "wof:placetype":"venue"
},
  "geometry": {"coordinates":[-85.28912800000001,41.189161],"type":"Point"}
}