{
  "type": "Feature",
  "properties": {
    "iso:country":"US",
    "sg:address":"10358 Harrow Pl",
    "sg:city":"Indianapolis",
    "sg:classifiers":[
        {
            "category":"Insurance",
            "subcategory":"Health Insurance",
            "type":"Services"
        }
    ],
    "sg:phone":"+1 317 846 1038",
    "sg:postcode":"46280",
    "sg:province":"IN",
    "sg:tags":[
        "market"
    ],
    "wof:name":"Clark James W",
    "wof:placetype":"venue"
},
  "geometry": {"coordinates":[-86.14160200000001,39.937801],"type":"Point"}
}