{
  "type": "Feature",
  "properties": {
    "addr:full":"15765 E 1000 N Flat Rock IN 47234",
    "addr:housenumber":"15765",
    "addr:postcode":"47234",
    "addr:street":"E 1000 N",
    "iso:country":"US",
    "sg:address":"15765 E 1000 N",
    "sg:city":"Flat Rock",
    "sg:phone":"+1 812 546 4874",
    "sg:postcode":"47234",
    "sg:province":"IN",
    "sg:tags":[
        "farm",
        "corn",
        "soybean"
    ],
    "wof:name":"Richard Hatton",
    "wof:placetype":"venue"
},
  "geometry": {"coordinates":[-85.749059,39.350133],"type":"Point"}
}