{
  "type": "Feature",
  "properties": {
    "iso:country":"US",
    "sg:address":"516 Main St",
    "sg:city":"Lafayette",
    "sg:classifiers":[
        {
            "category":"Shopping",
            "subcategory":"Hobbies, Toys, & Games",
            "type":"Retail Goods"
        }
    ],
    "sg:phone":"+1 765 429 6365",
    "sg:postcode":"47901",
    "sg:province":"IN",
    "sg:tags":[
        "doll"
    ],
    "wof:name":"Marquis Dolls",
    "wof:placetype":"venue"
},
  "geometry": {"coordinates":[-86.890823,40.419236],"type":"Point"}
}