{
  "type": "Feature",
  "properties": {
    "iso:country":"US",
    "sg:address":"2800 Fayette St",
    "sg:city":"Lake Station",
    "sg:classifiers":[
        {
            "category":"Organizations",
            "subcategory":"Religious Organization",
            "type":"Services"
        }
    ],
    "sg:phone":"+1 219 962 1810",
    "sg:postcode":"46405",
    "sg:province":"IN",
    "sg:tags":[
        "church"
    ],
    "wof:name":"Community United Presbyterian",
    "wof:placetype":"venue"
},
  "geometry": {"coordinates":[-87.272474,41.56716],"type":"Point"}
}