{
  "type": "Feature",
  "properties": {
    "addr:full":"8221 E 36th Pl Indianapolis IN 46226",
    "addr:housenumber":"8221",
    "addr:postcode":"46226",
    "addr:street":"E 36Th Pl",
    "iso:country":"US",
    "sg:address":"8221 E 36th Pl",
    "sg:city":"Indianapolis",
    "sg:classifiers":[
        {
            "category":"Organizations",
            "subcategory":"Religious Organization",
            "type":"Services"
        }
    ],
    "sg:phone":"+1 317 897 8865",
    "sg:postcode":"46226",
    "sg:province":"IN",
    "wof:name":"Teacher At Church School",
    "wof:placetype":"venue"
},
  "geometry": {"coordinates":[-86.025249,39.822551],"type":"Point"}
}