{
  "type": "Feature",
  "properties": {
    "iso:country":"US",
    "sg:address":"520 State St",
    "sg:city":"Culver",
    "sg:classifiers":[
        {
            "category":"Professional",
            "type":"Services"
        }
    ],
    "sg:phone":"+1 574 842 5086",
    "sg:postcode":"46511",
    "sg:province":"IN",
    "sg:tags":[
        "establishment"
    ],
    "wof:name":"Tom Kearns & Assoc",
    "wof:placetype":"venue"
},
  "geometry": {"coordinates":[-86.418994,41.222277],"type":"Point"}
}