{
  "type": "Feature",
  "properties": {
    "iso:country":"US",
    "sg:address":"912 W State St",
    "sg:city":"West Lafayette",
    "sg:classifiers":[
        {
            "category":"Organizations",
            "subcategory":"Religious Organization",
            "type":"Services"
        }
    ],
    "sg:phone":"+1 765 743 1293",
    "sg:postcode":"47906",
    "sg:province":"IN",
    "wof:name":"Hillel Foundation",
    "wof:placetype":"venue"
},
  "geometry": {"coordinates":[-86.917913,40.424242],"type":"Point"}
}