{
  "type": "Feature",
  "properties": {
    "iso:country":"US",
    "sg:address":"1320 Ohio St",
    "sg:city":"Terre Haute",
    "sg:classifiers":[
        {
            "category":"Education",
            "subcategory":"School",
            "type":"Public Place"
        }
    ],
    "sg:phone":"+1 812 462 4377",
    "sg:postcode":"47807",
    "sg:province":"IN",
    "wof:name":"Covered Bridge Spec Education",
    "wof:placetype":"venue"
},
  "geometry": {"coordinates":[-87.396662,39.465539],"type":"Point"}
}