{
  "type": "Feature",
  "properties": {
    "iso:country":"US",
    "sg:address":"3615 Central Ave",
    "sg:city":"Lake Station",
    "sg:classifiers":[
        {
            "category":"Retail",
            "subcategory":"Auto Repair",
            "type":"Services"
        }
    ],
    "sg:phone":"+1 219 962 8568",
    "sg:postcode":"46405",
    "sg:province":"IN",
    "sg:tags":[
        "transmission"
    ],
    "wof:name":"Discount Transmissions Inc",
    "wof:placetype":"venue"
},
  "geometry": {"coordinates":[-87.237764,41.574577],"type":"Point"}
}