{
  "type": "Feature",
  "properties": {
    "addr:full":"6327 University Cmns South Bend IN 46635",
    "addr:housenumber":"6327",
    "addr:postcode":"46635",
    "addr:street":"University Cmns",
    "iso:country":"US",
    "sg:address":"6327 University Cmns",
    "sg:city":"South Bend",
    "sg:classifiers":[
        {
            "category":"Shopping",
            "subcategory":"Hobbies, Toys, & Games",
            "type":"Retail Goods"
        }
    ],
    "sg:phone":"+1 574 291 2041",
    "sg:postcode":"46635",
    "sg:province":"IN",
    "sg:website":"www.buymetoys.com",
    "wof:name":"BUYMETOYS.COM",
    "wof:placetype":"venue"
},
  "geometry": {"coordinates":[-86.196078,41.716947],"type":"Point"}
}