{
  "type": "Feature",
  "properties": {
    "iso:country":"US",
    "sg:address":"1211 E Ewing Ave",
    "sg:city":"South Bend",
    "sg:classifiers":[
        {
            "category":"Organizations",
            "subcategory":"Religious Organization",
            "type":"Services"
        }
    ],
    "sg:phone":"+1 574 289 5662",
    "sg:postcode":"46613",
    "sg:province":"IN",
    "sg:tags":[
        "church"
    ],
    "wof:name":"Immanuel United Methodist Chr",
    "wof:placetype":"venue"
},
  "geometry": {"coordinates":[-86.230968,41.651207],"type":"Point"}
}