{
  "type": "Feature",
  "properties": {
    "iso:country":"US",
    "sg:address":"1090 S State Rd 135",
    "sg:city":"Greenwood",
    "sg:classifiers":[
        {
            "category":"Health Services",
            "subcategory":"Doctor",
            "type":"Services"
        }
    ],
    "sg:phone":"+1 317 882 8899",
    "sg:postcode":"46143",
    "sg:province":"IN",
    "sg:tags":[
        "dentist"
    ],
    "wof:name":"Greenwood Family Dental",
    "wof:placetype":"venue"
},
  "geometry": {"coordinates":[-86.15916300000001,39.59534],"type":"Point"}
}