{
  "type": "Feature",
  "properties": {
    "iso:country":"US",
    "sg:address":"55 E Oak St",
    "sg:city":"Zionsville",
    "sg:classifiers":[
        {
            "category":"Professional",
            "subcategory":"Advertising",
            "type":"Services"
        }
    ],
    "sg:phone":"+1 317 873 1678",
    "sg:postcode":"46077",
    "sg:province":"IN",
    "sg:tags":[
        "counselor"
    ],
    "wof:name":"Russo Communication Svc",
    "wof:placetype":"venue"
},
  "geometry": {"coordinates":[-86.260579,39.950929],"type":"Point"}
}