{
  "type": "Feature",
  "properties": {
    "iso:country":"US",
    "sg:address":"915 Main St",
    "sg:city":"Evansville",
    "sg:classifiers":[
        {
            "category":"Professional",
            "subcategory":"Lawyer & Legal Services",
            "type":"Services"
        }
    ],
    "sg:phone":"+1 812 423 4250",
    "sg:postcode":"47708",
    "sg:province":"IN",
    "sg:tags":[
        "attorney"
    ],
    "wof:name":"Dodson & Schaefer",
    "wof:placetype":"venue"
},
  "geometry": {"coordinates":[-87.56489999999999,37.975494],"type":"Point"}
}