{
  "type": "Feature",
  "properties": {
    "iso:country":"US",
    "sg:address":"1950 Conner St",
    "sg:city":"Noblesville",
    "sg:classifiers":[
        {
            "category":"Shopping",
            "subcategory":"Used Merchandise",
            "type":"Retail Goods"
        }
    ],
    "sg:phone":"+1 317 773 6945",
    "sg:postcode":"46060",
    "sg:province":"IN",
    "sg:tags":[
        "personal"
    ],
    "wof:name":"Noblesville Goodwill In",
    "wof:placetype":"venue"
},
  "geometry": {"coordinates":[-86.000066,40.045683],"type":"Point"}
}