{
  "type": "Feature",
  "properties": {
    "iso:country":"US",
    "sg:address":"100 E Thompson Rd",
    "sg:city":"Indianapolis",
    "sg:classifiers":[
        {
            "category":"Shopping",
            "subcategory":"Musical Instruments",
            "type":"Retail Goods"
        }
    ],
    "sg:phone":"+1 317 780 4100",
    "sg:postcode":"46227",
    "sg:province":"IN",
    "sg:tags":[
        "music",
        "dealer"
    ],
    "wof:name":"Indiana State Sch Music Assoc",
    "wof:placetype":"venue"
},
  "geometry": {"coordinates":[-86.156568,39.692756],"type":"Point"}
}