{
  "type": "Feature",
  "properties": {
    "iso:country":"US",
    "sg:address":"115 E Spring St",
    "sg:city":"Lagrange",
    "sg:classifiers":[
        {
            "category":"Manufacturing",
            "subcategory":"Motor Vehicles & Parts",
            "type":"Manufacturing & Wholesale Goods"
        }
    ],
    "sg:phone":"+1 260 463 3513",
    "sg:postcode":"46761",
    "sg:province":"IN",
    "sg:tags":[
        "trailer"
    ],
    "sg:website":"www.hoosiertrailer.com",
    "wof:name":"Spreuer & Son Inc",
    "wof:placetype":"venue"
},
  "geometry": {"coordinates":[-85.417845,41.644024],"type":"Point"}
}