{
  "type": "Feature",
  "properties": {
    "addr:full":"605 Silhavy Rd Valparaiso IN 46383",
    "addr:housenumber":"605",
    "addr:postcode":"46383",
    "addr:street":"Silhavy Rd",
    "iso:country":"US",
    "sg:address":"605 Silhavy Rd",
    "sg:city":"Valparaiso",
    "sg:classifiers":[
        {
            "category":"Home & Garden",
            "subcategory":"Carpets & Floor Coverings",
            "type":"Retail Goods"
        }
    ],
    "sg:phone":"+1 219 462 8026",
    "sg:postcode":"46383",
    "sg:province":"IN",
    "sg:tags":[
        "material"
    ],
    "sg:website":"www.tudorfloors.com",
    "wof:name":"Tudor Floors Carpet One",
    "wof:placetype":"venue"
},
  "geometry": {"coordinates":[-87.02719999999999,41.474882],"type":"Point"}
}