{
  "type": "Feature",
  "properties": {
    "iso:country":"US",
    "sg:address":"101 Lumber Center Rd",
    "sg:city":"Michigan City",
    "sg:classifiers":[
        {
            "category":"Freight",
            "type":"Transportation"
        }
    ],
    "sg:phone":"+1 219 325 3337",
    "sg:postcode":"46360",
    "sg:province":"IN",
    "sg:tags":[
        "commercial",
        "storage"
    ],
    "wof:name":"Quality Storage Systems Inc",
    "wof:placetype":"venue"
},
  "geometry": {"coordinates":[-86.824381,41.711811],"type":"Point"}
}