{
  "type": "Feature",
  "properties": {
    "addr:full":"1934 W Lincoln Ave Goshen IN 46526",
    "addr:housenumber":"1934",
    "addr:postcode":"46526",
    "addr:street":"W Lincoln Ave",
    "iso:country":"US",
    "sg:address":"1934 W Lincoln Ave",
    "sg:city":"Goshen",
    "sg:classifiers":[
        {
            "category":"Health Services",
            "subcategory":"Doctor",
            "type":"Services"
        }
    ],
    "sg:phone":"+1 574 533 0722",
    "sg:postcode":"46526",
    "sg:province":"IN",
    "sg:tags":[
        "dentist"
    ],
    "wof:name":"Paul E Keller DDS",
    "wof:placetype":"venue"
},
  "geometry": {"coordinates":[-85.86512,41.586558],"type":"Point"}
}