{
  "type": "Feature",
  "properties": {
    "iso:country":"US",
    "sg:address":"5131 N US Hwy 31",
    "sg:city":"Columbus",
    "sg:classifiers":[
        {
            "category":"Health Services",
            "subcategory":"Medical Lab",
            "type":"Services"
        }
    ],
    "sg:phone":"+1 812 378 3926",
    "sg:postcode":"47201",
    "sg:province":"IN",
    "sg:tags":[
        "detection",
        "equipment",
        "drug"
    ],
    "wof:name":"West Group",
    "wof:placetype":"venue"
},
  "geometry": {"coordinates":[-85.941949,39.253483],"type":"Point"}
}