{
  "type": "Feature",
  "properties": {
    "iso:country":"US",
    "sg:address":"1629 W McGalliard Rd",
    "sg:city":"Muncie",
    "sg:classifiers":[
        {
            "category":"Shopping",
            "subcategory":"Clothing, Apparel, & Fashions",
            "type":"Retail Goods"
        }
    ],
    "sg:phone":"+1 765 289 5507",
    "sg:postcode":"47304",
    "sg:province":"IN",
    "wof:name":"Deb",
    "wof:placetype":"venue"
},
  "geometry": {"coordinates":[-85.404263,40.218858],"type":"Point"}
}