{
  "type": "Feature",
  "properties": {
    "iso:country":"US",
    "sg:address":"3401 S Dixon Rd",
    "sg:city":"Kokomo",
    "sg:classifiers":[
        {
            "category":"Organizations",
            "subcategory":"Religious Organization",
            "type":"Services"
        }
    ],
    "sg:phone":"+1 765 453 6183",
    "sg:postcode":"46902",
    "sg:province":"IN",
    "sg:tags":[
        "church"
    ],
    "sg:website":"www.christlutherankokomo.org",
    "wof:name":"Christ Lutheran Church",
    "wof:placetype":"venue"
},
  "geometry": {"coordinates":[-86.165189,40.424044],"type":"Point"}
}