{
  "type": "Feature",
  "properties": {
    "iso:country":"US",
    "sg:address":"7187 Oak Cove Ln",
    "sg:city":"Noblesville",
    "sg:classifiers":[
        {
            "category":"Professional",
            "subcategory":"Business Services",
            "type":"Services"
        }
    ],
    "sg:phone":"+1 317 877 8552",
    "sg:postcode":"46062",
    "sg:province":"IN",
    "wof:name":"Mr Duck Enterprises",
    "wof:placetype":"venue"
},
  "geometry": {"coordinates":[-86.039754,40.097403],"type":"Point"}
}