{
  "type": "Feature",
  "properties": {
    "addr:full":"2760 Brentwood Dr Columbus IN 47203",
    "addr:housenumber":"2760",
    "addr:postcode":"47203",
    "addr:street":"Brentwood Dr",
    "iso:country":"US",
    "sg:address":"2760 Brentwood Dr",
    "sg:city":"Columbus",
    "sg:classifiers":[
        {
            "category":"Restaurant",
            "type":"Food & Drink"
        }
    ],
    "sg:menulink":"http://www.allmenus.com/in/columbus/198453-kfc---kentucky-fried-chicken/menu/",
    "sg:phone":"+1 812 372 5502",
    "sg:postcode":"47203",
    "sg:province":"IN",
    "sg:tags":[
        "american",
        "chicken"
    ],
    "wof:name":"KFC - Kentucky Fried Chicken",
    "wof:placetype":"venue"
},
  "geometry": {"coordinates":[-85.89555,39.228265],"type":"Point"}
}