{
  "type": "Feature",
  "properties": {
    "iso:country":"US",
    "sg:address":"1620 Kensington Blvd",
    "sg:city":"Fort Wayne",
    "sg:classifiers":[
        {
            "category":"Professional",
            "subcategory":"Business Services",
            "type":"Services"
        }
    ],
    "sg:phone":"+1 260 422 2059",
    "sg:postcode":"46805",
    "sg:province":"IN",
    "wof:name":"Amy Lindsay Design Services",
    "wof:placetype":"venue"
},
  "geometry": {"coordinates":[-85.113771,41.09196],"type":"Point"}
}