{
  "type": "Feature",
  "properties": {
    "iso:country":"US",
    "sg:address":"485 Mann Ave",
    "sg:city":"Austin",
    "sg:classifiers":[
        {
            "category":"Organizations",
            "subcategory":"Religious Organization",
            "type":"Services"
        }
    ],
    "sg:phone":"+1 812 794 2726",
    "sg:postcode":"47102",
    "sg:province":"IN",
    "sg:tags":[
        "church"
    ],
    "wof:name":"Austin Community Church Of God",
    "wof:placetype":"venue"
},
  "geometry": {"coordinates":[-85.800935,38.7471],"type":"Point"}
}