{
  "type": "Feature",
  "properties": {
    "iso:country":"US",
    "sg:address":"9190 Corporation Dr",
    "sg:city":"Indianapolis",
    "sg:classifiers":[
        {
            "category":"Home & Garden",
            "subcategory":"Hardware",
            "type":"Retail Goods"
        }
    ],
    "sg:phone":"+1 317 558 5700",
    "sg:postcode":"46256",
    "sg:province":"IN",
    "sg:tags":[
        "store"
    ],
    "sg:website":"www.cih-indy.com",
    "wof:name":"Central Indiana Hardware",
    "wof:placetype":"venue"
},
  "geometry": {"coordinates":[-86.036874,39.920461],"type":"Point"}
}