{
  "type": "Feature",
  "properties": {
    "addr:full":"1613 Greenacres Dr Kokomo IN 46901",
    "addr:housenumber":"1613",
    "addr:postcode":"46901",
    "addr:street":"Greenacres Dr",
    "iso:country":"US",
    "sg:address":"1613 Greenacres Dr",
    "sg:city":"Kokomo",
    "sg:classifiers":[
        {
            "category":"Shopping",
            "subcategory":"Bicycles & Sporting Goods",
            "type":"Retail Goods"
        }
    ],
    "sg:phone":"+1 765 883 7617",
    "sg:postcode":"46901",
    "sg:province":"IN",
    "sg:tags":[
        "equipment",
        "golf",
        "supply"
    ],
    "wof:name":"Don's Custom Golf Clubs",
    "wof:placetype":"venue"
},
  "geometry": {"coordinates":[-86.296758,40.468597],"type":"Point"}
}