{
  "type": "Feature",
  "properties": {
    "iso:country":"US",
    "sg:address":"3810 Lake Ave",
    "sg:city":"Fort Wayne",
    "sg:classifiers":[
        {
            "category":"Communications",
            "type":"Services"
        }
    ],
    "sg:phone":"+1 260 424 9762",
    "sg:postcode":"46805",
    "sg:province":"IN",
    "wof:name":"C & J Communications",
    "wof:placetype":"venue"
},
  "geometry": {"coordinates":[-85.09074,41.0903],"type":"Point"}
}