{
  "type": "Feature",
  "properties": {
    "iso:country":"US",
    "sg:address":"3522 N 900 W",
    "sg:city":"Wolcott",
    "sg:classifiers":[
        {
            "category":"Manufacturing",
            "subcategory":"Metals",
            "type":"Manufacturing & Wholesale Goods"
        }
    ],
    "sg:phone":"+1 219 279 2442",
    "sg:postcode":"47995",
    "sg:province":"IN",
    "sg:tags":[
        "industrial",
        "valve",
        "mfg"
    ],
    "wof:name":"Emond Eldon",
    "wof:placetype":"venue"
},
  "geometry": {"coordinates":[-87.042344,40.799389],"type":"Point"}
}