{
  "type": "Feature",
  "properties": {
    "addr:full":"122 W Spring St Brownstown IN 47220",
    "addr:housenumber":"122",
    "addr:postcode":"47220",
    "addr:street":"W Spring St",
    "iso:country":"US",
    "sg:address":"122 W Spring St",
    "sg:city":"Brownstown",
    "sg:classifiers":[
        {
            "category":"Professional",
            "subcategory":"Accounting & Tax Preparation",
            "type":"Services"
        }
    ],
    "sg:phone":"+1 812 358 4432",
    "sg:postcode":"47220",
    "sg:province":"IN",
    "sg:tags":[
        "return",
        "filing"
    ],
    "wof:name":"Robbins Tax Svc",
    "wof:placetype":"venue"
},
  "geometry": {"coordinates":[-86.041706,38.880179],"type":"Point"}
}