{
  "type": "Feature",
  "properties": {
    "addr:full":"6490 US Hwy 421 Osgood IN 47037",
    "addr:housenumber":"6490",
    "addr:postcode":"47037",
    "addr:street":"Us Hwy 421 Osgood",
    "iso:country":"US",
    "sg:address":"6490 US Hwy 421",
    "sg:city":"Osgood",
    "sg:classifiers":[
        {
            "category":"Manufacturing",
            "subcategory":"Chemicals & Compounds",
            "type":"Manufacturing & Wholesale Goods"
        }
    ],
    "sg:phone":"+1 812 852 2080",
    "sg:postcode":"47037",
    "sg:province":"IN",
    "sg:tags":[
        "fertilizer"
    ],
    "wof:name":"Laughery Valley Ag Co-Op",
    "wof:placetype":"venue"
},
  "geometry": {"coordinates":[-85.311025,39.16808],"type":"Point"}
}