{
  "type": "Feature",
  "properties": {
    "iso:country":"US",
    "sg:address":"3005 Commercial Rd",
    "sg:city":"Fort Wayne",
    "sg:classifiers":[
        {
            "category":"Manufacturing",
            "subcategory":"Rubber & Plastics",
            "type":"Manufacturing & Wholesale Goods"
        }
    ],
    "sg:phone":"+1 260 747 7485",
    "sg:postcode":"46809",
    "sg:province":"IN",
    "sg:website":"www.foamex.com",
    "wof:name":"Foamex LP",
    "wof:placetype":"venue"
},
  "geometry": {"coordinates":[-85.177396,41.008639],"type":"Point"}
}