{
  "type": "Feature",
  "properties": {
    "iso:country":"US",
    "sg:address":"1309 Park Rd",
    "sg:city":"Anderson",
    "sg:classifiers":[
        {
            "category":"Real Estate",
            "subcategory":"Real Estate Agent",
            "type":"Services"
        }
    ],
    "sg:phone":"+1 765 683 1490",
    "sg:postcode":"46011",
    "sg:province":"IN",
    "wof:name":"Star Realty",
    "wof:placetype":"venue"
},
  "geometry": {"coordinates":[-85.73013899999999,40.101695],"type":"Point"}
}