{
  "type": "Feature",
  "properties": {
    "iso:country":"US",
    "sg:address":"104 Broadway St",
    "sg:city":"Vincennes",
    "sg:classifiers":[
        {
            "category":"Shopping",
            "subcategory":"Stationery & Office Supplies",
            "type":"Retail Goods"
        }
    ],
    "sg:phone":"+1 812 886 9905",
    "sg:postcode":"47591",
    "sg:province":"IN",
    "wof:name":"Office Connection",
    "wof:placetype":"venue"
},
  "geometry": {"coordinates":[-87.531102,38.681591],"type":"Point"}
}