{
  "type": "Feature",
  "properties": {
    "iso:country":"US",
    "sg:address":"429 S California St",
    "sg:city":"Galveston",
    "sg:classifiers":[
        {
            "category":"Restaurant",
            "type":"Food & Drink"
        }
    ],
    "sg:phone":"+1 574 699 7115",
    "sg:postcode":"46932",
    "sg:province":"IN",
    "wof:name":"Tark's Pizza",
    "wof:placetype":"venue"
},
  "geometry": {"coordinates":[-86.189329,40.574153],"type":"Point"}
}