{
  "type": "Feature",
  "properties": {
    "iso:country":"US",
    "sg:address":"2208 Coliseum Blvd E",
    "sg:city":"Fort Wayne",
    "sg:classifiers":[
        {
            "category":"Organizations",
            "subcategory":"Religious Organization",
            "type":"Services"
        }
    ],
    "sg:phone":"+1 260 483 4915",
    "sg:postcode":"46805",
    "sg:province":"IN",
    "sg:tags":[
        "church"
    ],
    "wof:name":"Statewood Baptist Church",
    "wof:placetype":"venue"
},
  "geometry": {"coordinates":[-85.108406,41.112069],"type":"Point"}
}