{
  "type": "Feature",
  "properties": {
    "iso:country":"US",
    "sg:address":"1348 S Lake Park Ave",
    "sg:city":"Hobart",
    "sg:classifiers":[
        {
            "category":"Health Services",
            "subcategory":"Hospital",
            "type":"Services"
        }
    ],
    "sg:phone":"+1 219 942 4040",
    "sg:postcode":"46342",
    "sg:province":"IN",
    "sg:tags":[
        "mental"
    ],
    "wof:name":"Southlake Center For Mental",
    "wof:placetype":"venue"
},
  "geometry": {"coordinates":[-87.258978,41.512037],"type":"Point"}
}