{
  "type": "Feature",
  "properties": {
    "addr:full":"301 E South St Washington IN 47501",
    "addr:housenumber":"301 e",
    "addr:postcode":"in 47501",
    "addr:street":"South St",
    "iso:country":"US",
    "sg:address":"301 E South St",
    "sg:city":"Washington",
    "sg:classifiers":[
        {
            "category":"Education",
            "subcategory":"School",
            "type":"Public Place"
        }
    ],
    "sg:phone":"+1 812 254 5536",
    "sg:postcode":"47501",
    "sg:province":"IN",
    "wof:name":"Washington Community Schools",
    "wof:placetype":"venue"
},
  "geometry": {"coordinates":[-87.171252,38.656113],"type":"Point"}
}