{
  "type": "Feature",
  "properties": {
    "iso:country":"US",
    "sg:address":"208 E South St",
    "sg:city":"Washington",
    "sg:classifiers":[
        {
            "category":"Autos & Motor Vehicles",
            "subcategory":"Auto Supplies",
            "type":"Retail Goods"
        }
    ],
    "sg:phone":"+1 812 254 0876",
    "sg:postcode":"47501",
    "sg:province":"IN",
    "sg:tags":[
        "automobile",
        "parts"
    ],
    "wof:name":"Washington Auto Electric Inc",
    "wof:placetype":"venue"
},
  "geometry": {"coordinates":[-87.17331,38.656181],"type":"Point"}
}