{
  "type": "Feature",
  "properties": {
    "addr:full":"5251 Co Rd 56 Saint Joe IN 46785",
    "addr:housenumber":"5251;56",
    "addr:postcode":"46785",
    "addr:street":"Co Rd",
    "iso:country":"US",
    "sg:address":"5251 Co Rd 56",
    "sg:city":"Saint Joe",
    "sg:classifiers":[
        {
            "category":"Retail",
            "subcategory":"Repair Shop",
            "type":"Services"
        }
    ],
    "sg:phone":"+1 260 337 5001",
    "sg:postcode":"46785",
    "sg:province":"IN",
    "wof:name":"Fryes Upholstery Shop",
    "wof:placetype":"venue"
},
  "geometry": {"coordinates":[-84.942769,41.326167],"type":"Point"}
}