{
  "type": "Feature",
  "properties": {
    "iso:country":"US",
    "sg:address":"1206 N Miller Ave",
    "sg:city":"Marion",
    "sg:classifiers":[
        {
            "category":"Organizations",
            "subcategory":"Religious Organization",
            "type":"Services"
        }
    ],
    "sg:phone":"+1 765 662 3092",
    "sg:postcode":"46952",
    "sg:province":"IN",
    "sg:tags":[
        "church"
    ],
    "wof:name":"St James Lutheran Church",
    "wof:placetype":"venue"
},
  "geometry": {"coordinates":[-85.693198,40.576909],"type":"Point"}
}