{
  "type": "Feature",
  "properties": {
    "iso:country":"US",
    "sg:address":"3686 E 1100 N",
    "sg:city":"Roanoke",
    "sg:classifiers":[
        {
            "category":"Retail",
            "subcategory":"Repair Shop",
            "type":"Services"
        }
    ],
    "sg:phone":"+1 260 672 3791",
    "sg:postcode":"46783",
    "sg:province":"IN",
    "sg:tags":[
        "taxidermist"
    ],
    "wof:name":"Log Cabin Taxidermy",
    "wof:placetype":"venue"
},
  "geometry": {"coordinates":[-85.381146,40.989593],"type":"Point"}
}