{
  "type": "Feature",
  "properties": {
    "addr:full":"14674 Co Rd 48 Syracuse IN 46567",
    "addr:housenumber":"14674;48",
    "addr:postcode":"46567",
    "addr:street":"Co Rd",
    "iso:country":"US",
    "sg:address":"14674 Co Rd 48",
    "sg:city":"Syracuse",
    "sg:classifiers":[
        {
            "category":"Farming",
            "subcategory":"Farm & Veterinary Services",
            "type":"Manufacturing & Wholesale Goods"
        }
    ],
    "sg:phone":"+1 574 642 3491",
    "sg:postcode":"46567",
    "sg:province":"IN",
    "sg:tags":[
        "crop",
        "harvesting"
    ],
    "wof:name":"Homer Hilbish",
    "wof:placetype":"venue"
},
  "geometry": {"coordinates":[-85.742277,41.480517],"type":"Point"}
}