{
  "type": "Feature",
  "properties": {
    "iso:country":"US",
    "sg:address":"5114 Turner Rd",
    "sg:city":"Richmond",
    "sg:classifiers":[
        {
            "category":"Professional",
            "subcategory":"Management & Consulting",
            "type":"Services"
        }
    ],
    "sg:phone":"+1 765 939 2829",
    "sg:postcode":"47374",
    "sg:province":"IN",
    "sg:tags":[
        "consultant"
    ],
    "wof:name":"RMC Consulting",
    "wof:placetype":"venue"
},
  "geometry": {"coordinates":[-84.83216,39.873233],"type":"Point"}
}