{
  "type": "Feature",
  "properties": {
    "iso:country":"US",
    "sg:address":"801 Lincoln Hwy W",
    "sg:city":"New Haven",
    "sg:classifiers":[
        {
            "category":"Personal",
            "subcategory":"Beauty Salon",
            "type":"Services"
        }
    ],
    "sg:phone":"+1 260 493 0686",
    "sg:postcode":"46774",
    "sg:province":"IN",
    "wof:name":"Great Clips",
    "wof:placetype":"venue"
},
  "geometry": {"coordinates":[-85.03721400000001,41.069885],"type":"Point"}
}