{
  "type": "Feature",
  "properties": {
    "addr:full":"4806 W 400 N Anderson IN 46011",
    "addr:housenumber":"4806",
    "addr:postcode":"46011",
    "addr:street":"W 400 N",
    "iso:country":"US",
    "sg:address":"4806 W 400 N",
    "sg:city":"Anderson",
    "sg:classifiers":[
        {
            "category":"Real Estate",
            "subcategory":"Real Estate Operator",
            "type":"Services"
        }
    ],
    "sg:phone":"+1 765 754 7424",
    "sg:postcode":"46011",
    "sg:province":"IN",
    "sg:tags":[
        "property",
        "lessor"
    ],
    "wof:name":"Lola Edwards",
    "wof:placetype":"venue"
},
  "geometry": {"coordinates":[-85.762846,40.16426],"type":"Point"}
}