{
  "type": "Feature",
  "properties": {
    "iso:country":"US",
    "sg:address":"2771 W Co Rd 775 S",
    "sg:city":"Muncie",
    "sg:phone":"+1 765 755 3501",
    "sg:postcode":"47302",
    "sg:province":"IN",
    "sg:tags":[
        "farm",
        "corn",
        "soybean"
    ],
    "wof:name":"Don Siewert",
    "wof:placetype":"venue"
},
  "geometry": {"coordinates":[-85.416219,40.08005],"type":"Point"}
}