{
  "type": "Feature",
  "properties": {
    "addr:full":"2325 Pointe Pkwy Carmel IN 46032",
    "addr:housenumber":"2325",
    "addr:postcode":"46032",
    "addr:street":"Pointe Pkwy",
    "iso:country":"US",
    "sg:address":"2325 Pointe Pkwy",
    "sg:city":"Carmel",
    "sg:classifiers":[
        {
            "category":"Sports & Exercise",
            "subcategory":"Gym",
            "type":"Entertainment"
        }
    ],
    "sg:phone":"+1 317 846 0700",
    "sg:postcode":"46032",
    "sg:province":"IN",
    "sg:tags":[
        "club",
        "health",
        "studio",
        "gymnasium"
    ],
    "wof:name":"Eclipse Fitness Ctr",
    "wof:placetype":"venue"
},
  "geometry": {"coordinates":[-86.116888,39.955832],"type":"Point"}
}