{
  "type": "Feature",
  "properties": {
    "iso:country":"US",
    "sg:address":"101 E Ensley Ave",
    "sg:city":"Auburn",
    "sg:classifiers":[
        {
            "category":"Building & Trades",
            "subcategory":"Construction",
            "type":"Services"
        }
    ],
    "sg:phone":"+1 260 925 6455",
    "sg:postcode":"46706",
    "sg:province":"IN",
    "sg:tags":[
        "marking",
        "maintenance",
        "parking"
    ],
    "wof:name":"Auburn Street Dept",
    "wof:placetype":"venue"
},
  "geometry": {"coordinates":[-85.054318,41.359047],"type":"Point"}
}