{
  "type": "Feature",
  "properties": {
    "iso:country":"US",
    "sg:address":"230 Mary Ave",
    "sg:city":"Greendale",
    "sg:classifiers":[
        {
            "category":"Social Services",
            "subcategory":"Job Training",
            "type":"Services"
        }
    ],
    "sg:phone":"+1 812 537 2750",
    "sg:postcode":"47025",
    "sg:province":"IN",
    "sg:tags":[
        "employment"
    ],
    "wof:name":"Achieva Resources",
    "wof:placetype":"venue"
},
  "geometry": {"coordinates":[-84.850729,39.092312],"type":"Point"}
}