{
  "type": "Feature",
  "properties": {
    "iso:country":"US",
    "sg:address":"120 N Lebanon St",
    "sg:city":"Lebanon",
    "sg:classifiers":[
        {
            "category":"Insurance",
            "subcategory":"Insurance Agent",
            "type":"Services"
        }
    ],
    "sg:phone":"+1 765 482 1480",
    "sg:postcode":"46052",
    "sg:province":"IN",
    "wof:name":"Lamar & Lamar Insurance",
    "wof:placetype":"venue"
},
  "geometry": {"coordinates":[-86.46926499999999,40.048278],"type":"Point"}
}