{
  "type": "Feature",
  "properties": {
    "iso:country":"US",
    "sg:address":"1457 E 16th St",
    "sg:city":"Indianapolis",
    "sg:classifiers":[
        {
            "category":"Banks & Credit Unions",
            "subcategory":"Bank",
            "type":"Services"
        }
    ],
    "sg:phone":"+1 317 972 4744",
    "sg:postcode":"46201",
    "sg:province":"IN",
    "sg:tags":[
        "loan",
        "real estate"
    ],
    "wof:name":"Baytree Mortgage & Financial",
    "wof:placetype":"venue"
},
  "geometry": {"coordinates":[-86.132865,39.78846],"type":"Point"}
}