{
  "type": "Feature",
  "properties": {
    "iso:country":"US",
    "sg:address":"3860 State Rd 10",
    "sg:city":"Wheatfield",
    "sg:classifiers":[
        {
            "category":"Health Services",
            "subcategory":"Doctor",
            "type":"Services"
        }
    ],
    "sg:phone":"+1 219 956 2044",
    "sg:postcode":"46392",
    "sg:province":"IN",
    "sg:tags":[
        "dentist"
    ],
    "wof:name":"Aldo Largura Orthodontics",
    "wof:placetype":"venue"
},
  "geometry": {"coordinates":[-86.98222,41.186749],"type":"Point"}
}