{
  "type": "Feature",
  "properties": {
    "iso:country":"US",
    "sg:address":"7367 N Shadeland Ave",
    "sg:city":"Indianapolis",
    "sg:classifiers":[
        {
            "category":"Restaurant",
            "type":"Food & Drink"
        }
    ],
    "sg:phone":"+1 317 578 4639",
    "sg:postcode":"46250",
    "sg:province":"IN",
    "wof:name":"Chili Verde Mexican Restaurant",
    "wof:placetype":"venue"
},
  "geometry": {"coordinates":[-86.046035,39.89002],"type":"Point"}
}