{
  "type": "Feature",
  "properties": {
    "addr:full":"570 Maple St Monticello IN 47960",
    "addr:housenumber":"570",
    "addr:postcode":"47960",
    "addr:street":"Maple St",
    "iso:country":"US",
    "sg:address":"570 Maple St",
    "sg:city":"Monticello",
    "sg:classifiers":[
        {
            "category":"Organizations",
            "subcategory":"Non-profit Organization",
            "type":"Services"
        }
    ],
    "sg:phone":"+1 574 583 0003",
    "sg:postcode":"47960",
    "sg:province":"IN",
    "sg:tags":[
        "information",
        "alcoholism",
        "treatment"
    ],
    "wof:name":"Alcoholics Annonymous",
    "wof:placetype":"venue"
},
  "geometry": {"coordinates":[-86.75911000000001,40.7384],"type":"Point"}
}