{
  "type": "Feature",
  "properties": {
    "addr:full":"8106 Castleton Rd Indianapolis IN 46250",
    "addr:housenumber":"8106",
    "addr:postcode":"46250",
    "addr:street":"Castleton Rd",
    "iso:country":"US",
    "sg:address":"8106 Castleton Rd",
    "sg:city":"Indianapolis",
    "sg:classifiers":[
        {
            "category":"Manufacturing",
            "subcategory":"Buildings",
            "type":"Manufacturing & Wholesale Goods"
        },
        {
            "category":"Home & Garden",
            "subcategory":"Building Materials",
            "type":"Retail Goods"
        },
        {
            "category":"Building & Trades",
            "subcategory":"Construction",
            "type":"Services"
        }
    ],
    "sg:phone":"+1 317 849 3732",
    "sg:postcode":"46250",
    "sg:province":"IN",
    "sg:tags":[
        "builder",
        "contractor",
        "concrete",
        "staining",
        "gazebo",
        "patio"
    ],
    "wof:name":"C R Wiegand",
    "wof:placetype":"venue"
},
  "geometry": {"coordinates":[-86.050667,39.903062],"type":"Point"}
}