{
  "type": "Feature",
  "properties": {
    "addr:full":"4884 W 71st St Indianapolis IN 46268",
    "addr:housenumber":"4884",
    "addr:postcode":"46268",
    "addr:street":"W 71St St",
    "iso:country":"US",
    "sg:address":"4884 W 71st St",
    "sg:city":"Indianapolis",
    "sg:classifiers":[
        {
            "category":"Shopping",
            "subcategory":"Jewelry",
            "type":"Retail Goods"
        },
        {
            "category":"Manufacturing",
            "subcategory":"Jewelry",
            "type":"Manufacturing & Wholesale Goods"
        }
    ],
    "sg:phone":"+1 317 387 0232",
    "sg:postcode":"46268",
    "sg:province":"IN",
    "sg:tags":[
        "stone",
        "jewelers-wholesale",
        "watch",
        "jeweler",
        "precious",
        "semi-precious",
        "manufacturer"
    ],
    "wof:name":"Indy Gem",
    "wof:placetype":"venue"
},
  "geometry": {"coordinates":[-86.242171,39.882038],"type":"Point"}
}