{
  "type": "Feature",
  "properties": {
    "addr:full":"1010 W Cherry St Bluffton IN 46714",
    "addr:housenumber":"1010",
    "addr:postcode":"46714",
    "addr:street":"W Cherry St",
    "iso:country":"US",
    "sg:address":"1010 W Cherry St",
    "sg:city":"Bluffton",
    "sg:classifiers":[
        {
            "category":"Professional",
            "subcategory":"Computer Services",
            "type":"Services"
        }
    ],
    "sg:phone":"+1 260 824 9115",
    "sg:postcode":"46714",
    "sg:province":"IN",
    "sg:tags":[
        "related"
    ],
    "wof:name":"James Studabaker",
    "wof:placetype":"venue"
},
  "geometry": {"coordinates":[-85.183772,40.737668],"type":"Point"}
}