{
  "type": "Feature",
  "properties": {
    "iso:country":"US",
    "sg:address":"6225 E Columbia St",
    "sg:city":"Evansville",
    "sg:classifiers":[
        {
            "category":"Health Services",
            "subcategory":"Doctor",
            "type":"Services"
        }
    ],
    "sg:phone":"+1 812 474 1110",
    "sg:postcode":"47715",
    "sg:province":"IN",
    "sg:tags":[
        "clinic"
    ],
    "wof:name":"Tri-State Prostate Cancer Ctr",
    "wof:placetype":"venue"
},
  "geometry": {"coordinates":[-87.520019,37.98428],"type":"Point"}
}