{
  "type": "Feature",
  "properties": {
    "iso:country":"US",
    "sg:address":"1801 Main St",
    "sg:city":"Lafayette",
    "sg:classifiers":[
        {
            "category":"Real Estate",
            "subcategory":"Real Estate Agent",
            "type":"Services"
        }
    ],
    "sg:phone":"+1 765 742 0226",
    "sg:postcode":"47904",
    "sg:province":"IN",
    "wof:name":"Lafayette Realty",
    "wof:placetype":"venue"
},
  "geometry": {"coordinates":[-86.87552599999999,40.414578],"type":"Point"}
}