{
  "type": "Feature",
  "properties": {
    "iso:country":"US",
    "sg:address":"10240 E 21st St",
    "sg:city":"Indianapolis",
    "sg:classifiers":[
        {
            "category":"Organizations",
            "subcategory":"Religious Organization",
            "type":"Services"
        }
    ],
    "sg:phone":"+1 317 894 4456",
    "sg:postcode":"46229",
    "sg:province":"IN",
    "sg:tags":[
        "church"
    ],
    "wof:name":"First Korean Methodist Church",
    "wof:placetype":"venue"
},
  "geometry": {"coordinates":[-85.989478,39.797028],"type":"Point"}
}