{
  "type": "Feature",
  "properties": {
    "iso:country":"US",
    "sg:address":"11907 Exit 5 Pkwy",
    "sg:city":"Fishers",
    "sg:classifiers":[
        {
            "category":"Manufacturing",
            "subcategory":"Printing",
            "type":"Manufacturing & Wholesale Goods"
        }
    ],
    "sg:phone":"+1 317 806 0021",
    "sg:postcode":"46037",
    "sg:province":"IN",
    "sg:tags":[
        "newspaper"
    ],
    "sg:website":"www.trader.com",
    "wof:name":"TRADER.COM",
    "wof:placetype":"venue"
},
  "geometry": {"coordinates":[-86.00255199999999,39.957319],"type":"Point"}
}