{
  "type": "Feature",
  "properties": {
    "iso:country":"US",
    "sg:address":"970 E Eads Pkwy",
    "sg:city":"Greendale",
    "sg:classifiers":[
        {
            "category":"Personal",
            "subcategory":"Tanning Parlor",
            "type":"Services"
        }
    ],
    "sg:phone":"+1 812 537 1482",
    "sg:postcode":"47025",
    "sg:province":"IN",
    "sg:tags":[
        "salon"
    ],
    "wof:name":"M & M Tans & Vans",
    "wof:placetype":"venue"
},
  "geometry": {"coordinates":[-84.842201,39.121874],"type":"Point"}
}