{
  "type": "Feature",
  "properties": {
    "addr:full":"8935 E 46th St Indianapolis IN 46226",
    "addr:housenumber":"8935",
    "addr:postcode":"46226",
    "addr:street":"E 46Th St",
    "iso:country":"US",
    "sg:address":"8935 E 46th St",
    "sg:city":"Indianapolis",
    "sg:classifiers":[
        {
            "category":"Health Services",
            "subcategory":"Nursing And Care Facility",
            "type":"Services"
        }
    ],
    "sg:phone":"+1 317 898 1515",
    "sg:postcode":"46226",
    "sg:province":"IN",
    "sg:tags":[
        "a",
        "skilled",
        "rest",
        "operates",
        "as",
        "intermediate",
        "home"
    ],
    "wof:name":"Lawrence Manor Health Care Ctr",
    "wof:placetype":"venue"
},
  "geometry": {"coordinates":[-86.01218900000001,39.84057],"type":"Point"}
}