{
  "type": "Feature",
  "properties": {
    "addr:full":"1411 S Woodland Ave Michigan City IN 46360",
    "addr:housenumber":"1411",
    "addr:postcode":"46360",
    "addr:street":"S Woodland Ave",
    "iso:country":"US",
    "sg:address":"1411 S Woodland Ave",
    "sg:city":"Michigan City",
    "sg:classifiers":[
        {
            "category":"Building & Trades",
            "subcategory":"Construction",
            "type":"Services"
        }
    ],
    "sg:phone":"+1 219 872 0318",
    "sg:postcode":"46360",
    "sg:province":"IN",
    "sg:tags":[
        "general",
        "contractor"
    ],
    "wof:name":"Michiana Construction & Mgmt",
    "wof:placetype":"venue"
},
  "geometry": {"coordinates":[-86.87438899999999,41.689301],"type":"Point"}
}