{
  "type": "Feature",
  "properties": {
    "iso:country":"US",
    "sg:address":"3375 Calcutta Dr",
    "sg:city":"Greenwood",
    "sg:classifiers":[
        {
            "category":"Wholesale",
            "subcategory":"Machinery & Supplies",
            "type":"Manufacturing & Wholesale Goods"
        }
    ],
    "sg:phone":"+1 317 535 5590",
    "sg:postcode":"46143",
    "sg:province":"IN",
    "sg:tags":[
        "equipment",
        "establishment"
    ],
    "wof:name":"Harlee Inc",
    "wof:placetype":"venue"
},
  "geometry": {"coordinates":[-86.166946,39.580587],"type":"Point"}
}