{
  "type": "Feature",
  "properties": {
    "iso:country":"US",
    "sg:address":"15 E Oak St",
    "sg:city":"Zionsville",
    "sg:classifiers":[
        {
            "category":"Professional",
            "subcategory":"Lawyer & Legal Services",
            "type":"Services"
        }
    ],
    "sg:phone":"+1 317 733 8888",
    "sg:postcode":"46077",
    "sg:province":"IN",
    "sg:tags":[
        "attorney"
    ],
    "wof:name":"Chris Atkinson Law Office",
    "wof:placetype":"venue"
},
  "geometry": {"coordinates":[-86.261217,39.950747],"type":"Point"}
}