{
  "type": "Feature",
  "properties": {
    "addr:full":"1600 E Poplar St Terre Haute IN 47807",
    "addr:housenumber":"1600",
    "addr:postcode":"47807",
    "addr:street":"E Poplar St",
    "iso:country":"US",
    "sg:address":"1600 E Poplar St",
    "sg:city":"Terre Haute",
    "sg:classifiers":[
        {
            "category":"Retail",
            "subcategory":"Auto Repair",
            "type":"Services"
        }
    ],
    "sg:phone":"+1 812 232 8877",
    "sg:postcode":"47807",
    "sg:province":"IN",
    "sg:tags":[
        "automobile",
        "installation",
        "glass"
    ],
    "wof:name":"American Eagle Auto Glass",
    "wof:placetype":"venue"
},
  "geometry": {"coordinates":[-87.39064399999999,39.462883],"type":"Point"}
}