{
  "type": "Feature",
  "properties": {
    "iso:country":"US",
    "sg:address":"203 Broadway",
    "sg:city":"Chesterton",
    "sg:classifiers":[
        {
            "category":"Shopping",
            "type":"Retail Goods"
        }
    ],
    "sg:phone":"+1 219 926 9888",
    "sg:postcode":"46304",
    "sg:province":"IN",
    "sg:tags":[
        "hearing",
        "equipment",
        "supply",
        "impaired"
    ],
    "wof:name":"Accurate Hearing Aid Svc",
    "wof:placetype":"venue"
},
  "geometry": {"coordinates":[-87.054534,41.610848],"type":"Point"}
}