{
  "type": "Feature",
  "properties": {
    "iso:country":"US",
    "sg:address":"1302 119th St",
    "sg:city":"Whiting",
    "sg:classifiers":[
        {
            "category":"Recreation",
            "type":"Entertainment"
        }
    ],
    "sg:phone":"+1 219 659 8513",
    "sg:postcode":"46394",
    "sg:province":"IN",
    "sg:tags":[
        "martial",
        "arts",
        "instruction"
    ],
    "wof:name":"Arts Wisdom Kung Fu & Tai CHI",
    "wof:placetype":"venue"
},
  "geometry": {"coordinates":[-87.497702,41.67926],"type":"Point"}
}