{
  "type": "Feature",
  "properties": {
    "iso:country":"US",
    "sg:address":"329 S Lincoln Ave",
    "sg:city":"Rockport",
    "sg:classifiers":[
        {
            "category":"Retail",
            "subcategory":"Repair Shop",
            "type":"Services"
        }
    ],
    "sg:phone":"+1 812 649 4402",
    "sg:postcode":"47635",
    "sg:province":"IN",
    "sg:tags":[
        "scooter",
        "motorcycle",
        "motor"
    ],
    "wof:name":"Steve's American Cycle",
    "wof:placetype":"venue"
},
  "geometry": {"coordinates":[-87.05509600000001,37.880576],"type":"Point"}
}