{
  "type": "Feature",
  "properties": {
    "iso:country":"US",
    "sg:address":"7414 Country Brook Dr",
    "sg:city":"Indianapolis",
    "sg:classifiers":[
        {
            "category":"Professional",
            "subcategory":"Business Services",
            "type":"Services"
        }
    ],
    "sg:phone":"+1 317 808 7000",
    "sg:postcode":"46260",
    "sg:province":"IN",
    "sg:tags":[
        "broker",
        "merchandise"
    ],
    "wof:name":"Lynx Brokerage Firm",
    "wof:placetype":"venue"
},
  "geometry": {"coordinates":[-86.182673,39.887996],"type":"Point"}
}