{
  "type": "Feature",
  "properties": {
    "iso:country":"US",
    "sg:address":"3155 Broadway Ave",
    "sg:city":"Evansville",
    "sg:classifiers":[
        {
            "category":"Manufacturing",
            "subcategory":"Glass & Minerals",
            "type":"Manufacturing & Wholesale Goods"
        }
    ],
    "sg:phone":"+1 812 468 4299",
    "sg:postcode":"47712",
    "sg:province":"IN",
    "sg:tags":[
        "refractory"
    ],
    "wof:name":"RTW Industrial Maintenance",
    "wof:placetype":"venue"
},
  "geometry": {"coordinates":[-87.61514099999999,37.961169],"type":"Point"}
}