{
  "type": "Feature",
  "properties": {
    "iso:country":"US",
    "sg:address":"3707 Lisa Ln",
    "sg:city":"Plainfield",
    "sg:classifiers":[
        {
            "category":"Insurance",
            "subcategory":"Insurance Agent",
            "type":"Services"
        }
    ],
    "sg:phone":"+1 317 837 9737",
    "sg:postcode":"46168",
    "sg:province":"IN",
    "wof:name":"Chitwood Insurance Svc",
    "wof:placetype":"venue"
},
  "geometry": {"coordinates":[-86.419584,39.707659],"type":"Point"}
}