{
  "type": "Feature",
  "properties": {
    "iso:country":"US",
    "sg:address":"114 E Carroll St",
    "sg:city":"Kentland",
    "sg:classifiers":[
        {
            "category":"Farming",
            "subcategory":"Farm",
            "type":"Manufacturing & Wholesale Goods"
        }
    ],
    "sg:phone":"+1 219 474 5075",
    "sg:postcode":"47951",
    "sg:province":"IN",
    "sg:tags":[
        "crop",
        "general"
    ],
    "wof:name":"Cassidy Farms",
    "wof:placetype":"venue"
},
  "geometry": {"coordinates":[-87.448577,40.771367],"type":"Point"}
}