{
  "type": "Feature",
  "properties": {
    "iso:country":"US",
    "sg:address":"7140 Georgetown Rd",
    "sg:city":"Indianapolis",
    "sg:classifiers":[
        {
            "category":"Restaurant",
            "type":"Food & Drink"
        }
    ],
    "sg:phone":"+1 317 347 0908",
    "sg:postcode":"46268",
    "sg:province":"IN",
    "wof:name":"Burger King",
    "wof:placetype":"venue"
},
  "geometry": {"coordinates":[-86.241801,39.892464],"type":"Point"}
}