{
  "type": "Feature",
  "properties": {
    "iso:country":"US",
    "sg:address":"3122 Hazel Foster Dr",
    "sg:city":"Carmel",
    "sg:classifiers":[
        {
            "category":"Wholesale",
            "subcategory":"Durable Goods & Equipment",
            "type":"Manufacturing & Wholesale Goods"
        }
    ],
    "sg:phone":"+1 317 573 0006",
    "sg:postcode":"46033",
    "sg:province":"IN",
    "sg:tags":[
        "representative",
        "manufacturer"
    ],
    "wof:name":"Larkin Sales Inc",
    "wof:placetype":"venue"
},
  "geometry": {"coordinates":[-86.11106700000001,39.99665],"type":"Point"}
}