{
  "type": "Feature",
  "properties": {
    "iso:country":"US",
    "sg:address":"8031 Kinnerk Rd",
    "sg:city":"Fort Wayne",
    "sg:classifiers":[
        {
            "category":"Building & Trades",
            "subcategory":"Landscaping Services",
            "type":"Services"
        }
    ],
    "sg:phone":"+1 260 478 1192",
    "sg:postcode":"46819",
    "sg:province":"IN",
    "sg:tags":[
        "tree"
    ],
    "wof:name":"Affordable Tree Svc",
    "wof:placetype":"venue"
},
  "geometry": {"coordinates":[-85.144602,41.015939],"type":"Point"}
}