{
  "type": "Feature",
  "properties": {
    "iso:country":"US",
    "sg:address":"1206 Sturdy Rd",
    "sg:city":"Valparaiso",
    "sg:classifiers":[
        {
            "category":"Professional",
            "type":"Services"
        }
    ],
    "sg:phone":"+1 219 531 4993",
    "sg:postcode":"46383",
    "sg:province":"IN",
    "sg:tags":[
        "establishment"
    ],
    "wof:name":"Manwaring C",
    "wof:placetype":"venue"
},
  "geometry": {"coordinates":[-87.03671,41.478856],"type":"Point"}
}