{
  "type": "Feature",
  "properties": {
    "iso:country":"US",
    "sg:address":"988 W Lincoln St",
    "sg:city":"Danville",
    "sg:classifiers":[
        {
            "category":"Freight",
            "type":"Transportation"
        }
    ],
    "sg:phone":"+1 317 745 1335",
    "sg:postcode":"46122",
    "sg:province":"IN",
    "sg:tags":[
        "broker",
        "trucking"
    ],
    "wof:name":"K & T Transport Inc",
    "wof:placetype":"venue"
},
  "geometry": {"coordinates":[-86.535005,39.753234],"type":"Point"}
}