{
  "type": "Feature",
  "properties": {
    "iso:country":"US",
    "sg:address":"15606 Broadway St",
    "sg:city":"Lowell",
    "sg:classifiers":[
        {
            "category":"Building & Trades",
            "subcategory":"Landscaping Services",
            "type":"Services"
        }
    ],
    "sg:phone":"+1 219 690 0920",
    "sg:postcode":"46356",
    "sg:province":"IN",
    "sg:tags":[
        "lawn",
        "maintenance",
        "grounds"
    ],
    "wof:name":"Greenskeeper Lawncare",
    "wof:placetype":"venue"
},
  "geometry": {"coordinates":[-87.335371,41.333499],"type":"Point"}
}