{
  "type": "Feature",
  "properties": {
    "addr:full":"7164 Graham Rd Indianapolis IN 46250",
    "addr:housenumber":"7164",
    "addr:postcode":"46250",
    "addr:street":"Graham Rd",
    "iso:country":"US",
    "sg:address":"7164 Graham Rd",
    "sg:city":"Indianapolis",
    "sg:classifiers":[
        {
            "category":"Building & Trades",
            "subcategory":"Construction",
            "type":"Services"
        }
    ],
    "sg:phone":"+1 317 842 7766",
    "sg:postcode":"46250",
    "sg:province":"IN",
    "sg:tags":[
        "culvert"
    ],
    "wof:name":"Contech Construction Prods Inc",
    "wof:placetype":"venue"
},
  "geometry": {"coordinates":[-86.069795,39.88422],"type":"Point"}
}