{
  "type": "Feature",
  "properties": {
    "iso:country":"US",
    "sg:address":"501 S Airport St",
    "sg:city":"Terre Haute",
    "sg:classifiers":[
        {
            "category":"Education",
            "subcategory":"College",
            "type":"Public Place"
        }
    ],
    "sg:phone":"+1 812 877 3616",
    "sg:postcode":"47803",
    "sg:province":"IN",
    "sg:tags":[
        "academic",
        "school"
    ],
    "wof:name":"Ivy Tech State College",
    "wof:placetype":"venue"
},
  "geometry": {"coordinates":[-87.303496,39.461524],"type":"Point"}
}