{
  "type": "Feature",
  "properties": {
    "iso:country":"US",
    "sg:address":"1615 W 79th St",
    "sg:city":"Indianapolis",
    "sg:classifiers":[
        {
            "category":"Professional",
            "subcategory":"Management & Consulting",
            "type":"Services"
        }
    ],
    "sg:phone":"+1 317 872 3600",
    "sg:postcode":"46260",
    "sg:province":"IN",
    "wof:name":"A W Training",
    "wof:placetype":"venue"
},
  "geometry": {"coordinates":[-86.186483,39.897504],"type":"Point"}
}