{
  "type": "Feature",
  "properties": {
    "iso:country":"US",
    "sg:address":"1003 S Saint James Blvd",
    "sg:city":"Evansville",
    "sg:classifiers":[
        {
            "category":"Professional",
            "subcategory":"Accounting & Tax Preparation",
            "type":"Services"
        }
    ],
    "sg:phone":"+1 812 473 9977",
    "sg:postcode":"47714",
    "sg:province":"IN",
    "sg:tags":[
        "accountant"
    ],
    "wof:name":"Burtis W Cloud CPA",
    "wof:placetype":"venue"
},
  "geometry": {"coordinates":[-87.517506,37.96173],"type":"Point"}
}