{
  "type": "Feature",
  "properties": {
    "iso:country":"US",
    "sg:address":"10435 Indianapolis Blvd",
    "sg:city":"Highland",
    "sg:classifiers":[
        {
            "category":"Banks & Credit Unions",
            "subcategory":"Bank",
            "type":"Services"
        }
    ],
    "sg:phone":"+1 219 922 9355",
    "sg:postcode":"46322",
    "sg:province":"IN",
    "sg:tags":[
        "loan"
    ],
    "wof:name":"Citi Financial",
    "wof:placetype":"venue"
},
  "geometry": {"coordinates":[-87.47115700000001,41.525563],"type":"Point"}
}