{
  "type": "Feature",
  "properties": {
    "iso:country":"US",
    "sg:address":"3730 E 82nd St",
    "sg:city":"Indianapolis",
    "sg:classifiers":[
        {
            "category":"Food & Beverages",
            "subcategory":"Specialty",
            "type":"Retail Goods"
        }
    ],
    "sg:phone":"+1 317 570 9358",
    "sg:postcode":"46240",
    "sg:province":"IN",
    "sg:tags":[
        "vitamin"
    ],
    "sg:website":"www.vitaminshoppe.com",
    "wof:name":"Vitamin Shoppe",
    "wof:placetype":"venue"
},
  "geometry": {"coordinates":[-86.103091,39.909566],"type":"Point"}
}