{
  "type": "Feature",
  "properties": {
    "iso:country":"US",
    "sg:address":"2507 Bridgewood Ct",
    "sg:city":"Indianapolis",
    "sg:classifiers":[
        {
            "category":"Personal",
            "subcategory":"Beauty Salon",
            "type":"Services"
        }
    ],
    "sg:phone":"+1 317 298 8042",
    "sg:postcode":"46268",
    "sg:province":"IN",
    "sg:tags":[
        "cosmetologist"
    ],
    "wof:name":"Carolyn A Moore-Collins",
    "wof:placetype":"venue"
},
  "geometry": {"coordinates":[-86.20744500000001,39.882843],"type":"Point"}
}