{
  "type": "Feature",
  "properties": {
    "addr:full":"1 Hamilton County Sq Noblesville IN 46060",
    "addr:housenumber":"1",
    "addr:postcode":"noblesville in 46060",
    "addr:street":"Hamilton",
    "iso:country":"US",
    "sg:address":"1 Hamilton County Sq",
    "sg:city":"Noblesville",
    "sg:classifiers":[
        {
            "category":"Government",
            "subcategory":"Court House",
            "type":"Public Place"
        }
    ],
    "sg:phone":"+1 317 776 9612",
    "sg:postcode":"46060",
    "sg:province":"IN",
    "sg:tags":[
        "county"
    ],
    "wof:name":"Hamilton County Superior Court",
    "wof:placetype":"venue"
},
  "geometry": {"coordinates":[-86.014707,40.046538],"type":"Point"}
}