{
  "type": "Feature",
  "properties": {
    "iso:country":"US",
    "sg:address":"3552 Alpine Pl",
    "sg:city":"Indianapolis",
    "sg:classifiers":[
        {
            "category":"Shopping",
            "subcategory":"Gifts & Souvenirs",
            "type":"Retail Goods"
        }
    ],
    "sg:phone":"+1 317 895 5854",
    "sg:postcode":"46226",
    "sg:province":"IN",
    "wof:name":"Transgender Identity Cards",
    "wof:placetype":"venue"
},
  "geometry": {"coordinates":[-86.01921,39.820348],"type":"Point"}
}