{
  "type": "Feature",
  "properties": {
    "addr:full":"7446 Fishers Station Dr Fishers IN 46038",
    "addr:housenumber":"7446",
    "addr:postcode":"46038",
    "addr:street":"Fishers Station Dr",
    "iso:country":"US",
    "sg:address":"7446 Fishers Station Dr",
    "sg:city":"Fishers",
    "sg:classifiers":[
        {
            "category":"Shopping",
            "subcategory":"Bicycles & Sporting Goods",
            "type":"Retail Goods"
        }
    ],
    "sg:phone":"+1 317 595 1101",
    "sg:postcode":"46038",
    "sg:province":"IN",
    "wof:name":"Funke Performance Hockey",
    "wof:placetype":"venue"
},
  "geometry": {"coordinates":[-86.03719700000001,39.957405],"type":"Point"}
}