{
  "type": "Feature",
  "properties": {
    "iso:country":"US",
    "sg:address":"9500 N Schindel Rd",
    "sg:city":"Albany",
    "sg:classifiers":[
        {
            "category":"Retail",
            "subcategory":"Laundry & Dry Cleaning",
            "type":"Services"
        }
    ],
    "sg:phone":"+1 765 789 4087",
    "sg:postcode":"47320",
    "sg:province":"IN",
    "sg:tags":[
        "repairing",
        "lamp",
        "shades"
    ],
    "wof:name":"C-Mor Lamp Co",
    "wof:placetype":"venue"
},
  "geometry": {"coordinates":[-85.28864799999999,40.275492],"type":"Point"}
}