{
  "type": "Feature",
  "properties": {
    "addr:full":"7293 W 1100 N Nappanee IN 46550",
    "addr:housenumber":"7293",
    "addr:postcode":"46550",
    "addr:street":"W 1100 N",
    "iso:country":"US",
    "sg:address":"7293 W 1100 N",
    "sg:city":"Nappanee",
    "sg:classifiers":[
        {
            "category":"Real Estate",
            "subcategory":"Real Estate Operator",
            "type":"Services"
        }
    ],
    "sg:phone":"+1 574 773 7407",
    "sg:postcode":"46550",
    "sg:province":"IN",
    "sg:tags":[
        "property",
        "lessor"
    ],
    "wof:name":"Ruth Craig",
    "wof:placetype":"venue"
},
  "geometry": {"coordinates":[-85.987089,41.390304],"type":"Point"}
}