{
  "type": "Feature",
  "properties": {
    "iso:country":"US",
    "sg:address":"2758 W Maple St",
    "sg:city":"Winamac",
    "sg:classifiers":[
        {
            "category":"Organizations",
            "subcategory":"Religious Organization",
            "type":"Services"
        }
    ],
    "sg:phone":"+1 574 595 7147",
    "sg:postcode":"46901",
    "sg:province":"IN",
    "sg:tags":[
        "church"
    ],
    "wof:name":"Pulaski Presbyterian Chr",
    "wof:placetype":"venue"
},
  "geometry": {"coordinates":[-86.1709,40.485835],"type":"Point"}
}