{
  "type": "Feature",
  "properties": {
    "iso:country":"US",
    "sg:address":"37 W High St",
    "sg:city":"Lawrenceburg",
    "sg:classifiers":[
        {
            "category":"Building & Trades",
            "subcategory":"Construction",
            "type":"Services"
        }
    ],
    "sg:phone":"+1 812 537 0066",
    "sg:postcode":"47025",
    "sg:province":"IN",
    "sg:tags":[
        "general",
        "contractor"
    ],
    "wof:name":"Roy A Miller & Son Inc",
    "wof:placetype":"venue"
},
  "geometry": {"coordinates":[-84.847808,39.092532],"type":"Point"}
}