{
  "type": "Feature",
  "properties": {
    "addr:full":"5730 E Washington St Indianapolis IN 46219",
    "addr:housenumber":"5730",
    "addr:postcode":"46219",
    "addr:street":"E Washington St",
    "iso:country":"US",
    "sg:address":"5730 E Washington St",
    "sg:city":"Indianapolis",
    "sg:classifiers":[
        {
            "category":"Real Estate",
            "subcategory":"Real Estate Operator",
            "type":"Services"
        }
    ],
    "sg:phone":"+1 317 356 2971",
    "sg:postcode":"46219",
    "sg:province":"IN",
    "sg:tags":[
        "apartment"
    ],
    "sg:website":"www.stallardonline.com",
    "wof:name":"Saxony Court Apartments",
    "wof:placetype":"venue"
},
  "geometry": {"coordinates":[-86.067663,39.771001],"type":"Point"}
}