{
  "type": "Feature",
  "properties": {
    "iso:country":"US",
    "sg:address":"3716 W Ridge Rd",
    "sg:city":"Gary",
    "sg:classifiers":[
        {
            "category":"Building & Trades",
            "subcategory":"Plumbing",
            "type":"Services"
        }
    ],
    "sg:phone":"+1 219 884 8932",
    "sg:postcode":"46408",
    "sg:province":"IN",
    "sg:tags":[
        "tank",
        "septic"
    ],
    "wof:name":"S & S Sewer & Septic",
    "wof:placetype":"venue"
},
  "geometry": {"coordinates":[-87.384619,41.548131],"type":"Point"}
}