{
  "type": "Feature",
  "properties": {
    "iso:country":"US",
    "sg:address":"2685 S 1000 W",
    "sg:city":"Shipshewana",
    "sg:classifiers":[
        {
            "category":"Home & Garden",
            "subcategory":"Garden Supply",
            "type":"Retail Goods"
        }
    ],
    "sg:phone":"+1 260 768 4367",
    "sg:postcode":"46565",
    "sg:province":"IN",
    "sg:tags":[
        "nurseryman"
    ],
    "wof:name":"Stoney Acres",
    "wof:placetype":"venue"
},
  "geometry": {"coordinates":[-85.617787,41.601031],"type":"Point"}
}