{
  "type": "Feature",
  "properties": {
    "addr:full":"6501 Grape Rd Mishawaka IN 46545",
    "addr:housenumber":"6501",
    "addr:postcode":"46545",
    "addr:street":"Grape Rd",
    "iso:country":"US",
    "sg:address":"6501 Grape Rd",
    "sg:city":"Mishawaka",
    "sg:classifiers":[
        {
            "category":"Shopping",
            "subcategory":"Department Store",
            "type":"Retail Goods"
        }
    ],
    "sg:phone":"+1 574 277 6000",
    "sg:postcode":"46545",
    "sg:province":"IN",
    "wof:name":"J C Penney Co",
    "wof:placetype":"venue"
},
  "geometry": {"coordinates":[-86.187781,41.716898],"type":"Point"}
}