{
  "type": "Feature",
  "properties": {
    "addr:full":"5350 N Capitol Ave Indianapolis IN 46208",
    "addr:housenumber":"5350",
    "addr:postcode":"46208",
    "addr:street":"N Capitol Ave",
    "iso:country":"US",
    "sg:address":"5350 N Capitol Ave",
    "sg:city":"Indianapolis",
    "sg:classifiers":[
        {
            "category":"Professional",
            "subcategory":"Management & Consulting",
            "type":"Services"
        }
    ],
    "sg:phone":"+1 317 257 7975",
    "sg:postcode":"46208",
    "sg:province":"IN",
    "wof:name":"Jerry Musich & Assoc",
    "wof:placetype":"venue"
},
  "geometry": {"coordinates":[-86.161902,39.84762],"type":"Point"}
}