{
  "type": "Feature",
  "properties": {
    "addr:full":"8500 Broadway Merrillville IN 46410",
    "addr:housenumber":"8500",
    "addr:postcode":"46410",
    "addr:street":"Broadway",
    "iso:country":"US",
    "sg:address":"8500 Broadway",
    "sg:city":"Merrillville",
    "sg:classifiers":[
        {
            "category":"Health Services",
            "subcategory":"Doctor",
            "type":"Services"
        }
    ],
    "sg:phone":"+1 219 736 1500",
    "sg:postcode":"46410",
    "sg:province":"IN",
    "sg:tags":[
        "physician",
        "surgeon"
    ],
    "wof:name":"Magno Medical LLC",
    "wof:placetype":"venue"
},
  "geometry": {"coordinates":[-87.335972,41.463335],"type":"Point"}
}