{
  "type": "Feature",
  "properties": {
    "iso:country":"US",
    "sg:address":"4215 Edison Lakes Pkwy",
    "sg:city":"Mishawaka",
    "sg:classifiers":[
        {
            "category":"Health Services",
            "subcategory":"Doctor",
            "type":"Services"
        }
    ],
    "sg:phone":"+1 574 271 5171",
    "sg:postcode":"46545",
    "sg:province":"IN",
    "sg:tags":[
        "physician",
        "surgeon"
    ],
    "wof:name":"Louis Mini MD",
    "wof:placetype":"venue"
},
  "geometry": {"coordinates":[-86.177618,41.701854],"type":"Point"}
}