{
  "type": "Feature",
  "properties": {
    "iso:country":"US",
    "sg:address":"9101 Old State Rd",
    "sg:city":"Evansville",
    "sg:classifiers":[
        {
            "category":"Freight",
            "type":"Transportation"
        }
    ],
    "sg:phone":"+1 812 867 5092",
    "sg:postcode":"47711",
    "sg:province":"IN",
    "sg:tags":[
        "operator",
        "local",
        "trucking"
    ],
    "wof:name":"Shepherd Trucking",
    "wof:placetype":"venue"
},
  "geometry": {"coordinates":[-87.560874,38.066151],"type":"Point"}
}