{
  "type": "Feature",
  "properties": {
    "iso:country":"US",
    "sg:address":"1045 S Main St",
    "sg:city":"Elkhart",
    "sg:classifiers":[
        {
            "category":"Bars & Pubs",
            "type":"Food & Drink"
        }
    ],
    "sg:phone":"+1 574 522 3522",
    "sg:postcode":"46516",
    "sg:province":"IN",
    "wof:name":"Louie & Kelly's",
    "wof:placetype":"venue"
},
  "geometry": {"coordinates":[-85.965954,41.67808],"type":"Point"}
}