{
  "type": "Feature",
  "properties": {
    "iso:country":"US",
    "sg:address":"8835 Haddington Dr N",
    "sg:city":"Indianapolis",
    "sg:classifiers":[
        {
            "category":"Restaurant",
            "type":"Food & Drink"
        }
    ],
    "sg:phone":"+1 317 585 9162",
    "sg:postcode":"46256",
    "sg:province":"IN",
    "wof:name":"Harvest Cafe Coffee Co",
    "wof:placetype":"venue"
},
  "geometry": {"coordinates":[-86.012968,39.925793],"type":"Point"}
}