{
  "type": "Feature",
  "properties": {
    "iso:country":"US",
    "sg:address":"2012 O St",
    "sg:city":"Bedford",
    "sg:classifiers":[
        {
            "category":"Shopping",
            "subcategory":"Clothing, Apparel, & Fashions",
            "type":"Retail Goods"
        }
    ],
    "sg:phone":"+1 812 275 4327",
    "sg:postcode":"47421",
    "sg:province":"IN",
    "sg:tags":[
        "baby",
        "store"
    ],
    "wof:name":"All About Baby",
    "wof:placetype":"venue"
},
  "geometry": {"coordinates":[-86.491451,38.856546],"type":"Point"}
}