{
  "type": "Feature",
  "properties": {
    "iso:country":"US",
    "sg:address":"1201 Kenwood Ave",
    "sg:city":"Valparaiso",
    "sg:classifiers":[
        {
            "category":"Professional",
            "subcategory":"Business Services",
            "type":"Services"
        }
    ],
    "sg:phone":"+1 219 464 7946",
    "sg:postcode":"46385",
    "sg:province":"IN",
    "wof:name":"J Henri Group",
    "wof:placetype":"venue"
},
  "geometry": {"coordinates":[-87.074518,41.479561],"type":"Point"}
}