{
  "type": "Feature",
  "properties": {
    "iso:country":"US",
    "sg:address":"1331 Park Meadow Dr",
    "sg:city":"Beech Grove",
    "sg:classifiers":[
        {
            "category":"Professional",
            "subcategory":"Management & Consulting",
            "type":"Services"
        }
    ],
    "sg:phone":"+1 317 780 0563",
    "sg:postcode":"46107",
    "sg:province":"IN",
    "sg:tags":[
        "consultant",
        "training"
    ],
    "wof:name":"Jeff Cowans Pro Talk",
    "wof:placetype":"venue"
},
  "geometry": {"coordinates":[-86.099218,39.714815],"type":"Point"}
}