{
  "type": "Feature",
  "properties": {
    "addr:full":"2714 Wilson Dr Terre Haute IN 47803",
    "addr:housenumber":"2714",
    "addr:postcode":"47803",
    "addr:street":"Wilson Dr",
    "iso:country":"US",
    "sg:address":"2714 Wilson Dr",
    "sg:city":"Terre Haute",
    "sg:classifiers":[
        {
            "category":"Professional",
            "subcategory":"Management & Consulting",
            "type":"Services"
        }
    ],
    "sg:phone":"+1 812 232 5743",
    "sg:postcode":"47803",
    "sg:province":"IN",
    "sg:tags":[
        "business"
    ],
    "wof:name":"Indiana Evaluations Services",
    "wof:placetype":"venue"
},
  "geometry": {"coordinates":[-87.37572900000001,39.460182],"type":"Point"}
}