{
  "type": "Feature",
  "properties": {
    "iso:country":"US",
    "sg:address":"1202 W Kem Rd",
    "sg:city":"Marion",
    "sg:classifiers":[
        {
            "category":"Retail",
            "subcategory":"Funeral Services",
            "type":"Services"
        }
    ],
    "sg:phone":"+1 765 664 6271",
    "sg:postcode":"46952",
    "sg:province":"IN",
    "sg:tags":[
        "director"
    ],
    "wof:name":"Raven-Choate Funeral Home",
    "wof:placetype":"venue"
},
  "geometry": {"coordinates":[-85.673536,40.574407],"type":"Point"}
}