{
  "type": "Feature",
  "properties": {
    "iso:country":"US",
    "sg:address":"3509 N Everbrook Ln",
    "sg:city":"Muncie",
    "sg:classifiers":[
        {
            "category":"Travel",
            "subcategory":"Hotels & Motels",
            "type":"Entertainment"
        }
    ],
    "sg:phone":"+1 765 288 2311",
    "sg:postcode":"47304",
    "sg:province":"IN",
    "sg:website":"www.daysinn.com",
    "wof:name":"Days Inn",
    "wof:placetype":"venue"
},
  "geometry": {"coordinates":[-85.42679200000001,40.222717],"type":"Point"}
}