{
  "type": "Feature",
  "properties": {
    "iso:country":"US",
    "sg:address":"501 Northridge Dr",
    "sg:city":"Shelbyville",
    "sg:classifiers":[
        {
            "category":"Manufacturing",
            "subcategory":"Motor Vehicles & Parts",
            "type":"Manufacturing & Wholesale Goods"
        }
    ],
    "sg:phone":"+1 317 392 8000",
    "sg:postcode":"46176",
    "sg:province":"IN",
    "sg:tags":[
        "automobile",
        "supply"
    ],
    "wof:name":"Meridian Automotive Systems",
    "wof:placetype":"venue"
},
  "geometry": {"coordinates":[-85.793484,39.545562],"type":"Point"}
}