{
  "type": "Feature",
  "properties": {
    "iso:country":"US",
    "sg:address":"4255 N State Rd 39",
    "sg:city":"Laporte",
    "sg:classifiers":[
        {
            "category":"Government",
            "subcategory":"Office",
            "type":"Public Place"
        }
    ],
    "sg:phone":"+1 219 362 3428",
    "sg:postcode":"46350",
    "sg:province":"IN",
    "sg:tags":[
        "state",
        "program"
    ],
    "wof:name":"Toll Road",
    "wof:placetype":"venue"
},
  "geometry": {"coordinates":[-86.73860999999999,41.667859],"type":"Point"}
}