{
  "type": "Feature",
  "properties": {
    "addr:full":"3010 Laporte St Highland IN 46322",
    "addr:housenumber":"3010",
    "addr:postcode":"46322",
    "addr:street":"Laporte St",
    "iso:country":"US",
    "sg:address":"3010 Laporte St",
    "sg:city":"Highland",
    "sg:classifiers":[
        {
            "category":"Insurance",
            "subcategory":"Insurance Agent",
            "type":"Services"
        }
    ],
    "sg:phone":"+1 219 838 3318",
    "sg:postcode":"46322",
    "sg:province":"IN",
    "sg:tags":[
        "adjuster",
        "public",
        "certified"
    ],
    "wof:name":"Hoffman Adjustment Company",
    "wof:placetype":"venue"
},
  "geometry": {"coordinates":[-87.255562,41.564699],"type":"Point"}
}