{
  "type": "Feature",
  "properties": {
    "addr:full":"9010 Hook St Highland IN 46322",
    "addr:housenumber":"9010",
    "addr:postcode":"46322",
    "addr:street":"Hook St",
    "iso:country":"US",
    "sg:address":"9010 Hook St",
    "sg:city":"Highland",
    "sg:classifiers":[
        {
            "category":"Manufacturing",
            "subcategory":"Glass & Minerals",
            "type":"Manufacturing & Wholesale Goods"
        }
    ],
    "sg:phone":"+1 219 838 0227",
    "sg:postcode":"46322",
    "sg:province":"IN",
    "sg:tags":[
        "refractory"
    ],
    "sg:website":"www.alltherm.com",
    "wof:name":"Alltherm Services Inc",
    "wof:placetype":"venue"
},
  "geometry": {"coordinates":[-87.46590399999999,41.54969],"type":"Point"}
}