{
  "type": "Feature",
  "properties": {
    "iso:country":"US",
    "sg:address":"5475 Broadway",
    "sg:city":"Merrillville",
    "sg:classifiers":[
        {
            "category":"Organizations",
            "subcategory":"Religious Organization",
            "type":"Services"
        }
    ],
    "sg:phone":"+1 219 981 9188",
    "sg:postcode":"46410",
    "sg:province":"IN",
    "sg:tags":[
        "church"
    ],
    "wof:name":"Eternal Word Kingdom Ministry",
    "wof:placetype":"venue"
},
  "geometry": {"coordinates":[-87.33608,41.519728],"type":"Point"}
}