{
  "type": "Feature",
  "properties": {
    "iso:country":"US",
    "sg:address":"7990 W Rd 75 N",
    "sg:city":"Bargersville",
    "sg:classifiers":[
        {
            "category":"Farming",
            "subcategory":"Farm",
            "type":"Manufacturing & Wholesale Goods"
        }
    ],
    "sg:phone":"+1 317 422 9059",
    "sg:postcode":"46106",
    "sg:province":"IN",
    "wof:name":"Arrowhead Farms",
    "wof:placetype":"venue"
},
  "geometry": {"coordinates":[-86.251123,39.484982],"type":"Point"}
}