{
  "type": "Feature",
  "properties": {
    "addr:full":"900 Husky Trl Warsaw IN 46582",
    "addr:housenumber":"900",
    "addr:postcode":"46582",
    "addr:street":"Husky Trl",
    "iso:country":"US",
    "sg:address":"900 Husky Trl",
    "sg:city":"Warsaw",
    "sg:classifiers":[
        {
            "category":"Home & Garden",
            "subcategory":"Mobile Homes",
            "type":"Retail Goods"
        }
    ],
    "sg:phone":"+1 574 268 1400",
    "sg:postcode":"46582",
    "sg:province":"IN",
    "wof:name":"Four Seasons Housing Factory",
    "wof:placetype":"venue"
},
  "geometry": {"coordinates":[-85.82347799999999,41.250543],"type":"Point"}
}