{
  "type": "Feature",
  "properties": {
    "iso:country":"US",
    "sg:address":"3324 N Franklin St",
    "sg:city":"Muncie",
    "sg:classifiers":[
        {
            "category":"Personal",
            "subcategory":"Beauty Salon",
            "type":"Services"
        }
    ],
    "sg:phone":"+1 765 286 7065",
    "sg:postcode":"47303",
    "sg:province":"IN",
    "sg:tags":[
        "manicuring"
    ],
    "wof:name":"Nu Nails",
    "wof:placetype":"venue"
},
  "geometry": {"coordinates":[-85.388801,40.220441],"type":"Point"}
}