{
  "type": "Feature",
  "properties": {
    "addr:full":"172 Bradford Rd Bennington IN 47011",
    "addr:housenumber":"172",
    "addr:postcode":"47011",
    "addr:street":"Bradford Rd",
    "iso:country":"US",
    "sg:address":"172 Bradford Rd",
    "sg:city":"Bennington",
    "sg:phone":"+1 812 534 3608",
    "sg:postcode":"47011",
    "sg:province":"IN",
    "sg:tags":[
        "farm",
        "corn"
    ],
    "wof:name":"Louis Kappes",
    "wof:placetype":"venue"
},
  "geometry": {"coordinates":[-85.059358,38.858403],"type":"Point"}
}