{
  "type": "Feature",
  "properties": {
    "iso:country":"US",
    "sg:address":"500 N 2nd Ave",
    "sg:city":"Evansville",
    "sg:classifiers":[
        {
            "category":"Organizations",
            "subcategory":"Non-profit Organization",
            "type":"Services"
        }
    ],
    "sg:phone":"+1 812 421 4533",
    "sg:postcode":"47710",
    "sg:province":"IN",
    "wof:name":"Low Vision Ctr",
    "wof:placetype":"venue"
},
  "geometry": {"coordinates":[-87.576118,37.983059],"type":"Point"}
}