{
  "type": "Feature",
  "properties": {
    "iso:country":"US",
    "sg:address":"411 W McKinley Ave",
    "sg:city":"Mishawaka",
    "sg:classifiers":[
        {
            "category":"Banks & Credit Unions",
            "subcategory":"Bank",
            "type":"Services"
        }
    ],
    "sg:phone":"+1 574 259 5671",
    "sg:postcode":"46545",
    "sg:province":"IN",
    "wof:name":"MFB Financial",
    "wof:placetype":"venue"
},
  "geometry": {"coordinates":[-86.188129,41.680271],"type":"Point"}
}