{
  "type": "Feature",
  "properties": {
    "iso:country":"US",
    "sg:address":"8014 State Rd 311",
    "sg:city":"Sellersburg",
    "sg:classifiers":[
        {
            "category":"Government",
            "subcategory":"Police Station",
            "type":"Public Place"
        }
    ],
    "sg:phone":"+1 812 246 5424",
    "sg:postcode":"47172",
    "sg:province":"IN",
    "sg:tags":[
        "state"
    ],
    "wof:name":"State Police",
    "wof:placetype":"venue"
},
  "geometry": {"coordinates":[-85.766297,38.387039],"type":"Point"}
}