{
  "type": "Feature",
  "properties": {
    "addr:full":"193 E Main St Bloomfield IN 47424",
    "addr:housenumber":"193",
    "addr:postcode":"47424",
    "addr:street":"E Main St",
    "iso:country":"US",
    "sg:address":"193 E Main St",
    "sg:city":"Bloomfield",
    "sg:classifiers":[
        {
            "category":"Home & Garden",
            "subcategory":"Building Materials",
            "type":"Retail Goods"
        }
    ],
    "sg:phone":"+1 812 384 3158",
    "sg:postcode":"47424",
    "sg:province":"IN",
    "sg:tags":[
        "paint"
    ],
    "wof:name":"D & R Paint & Decorating Ctr",
    "wof:placetype":"venue"
},
  "geometry": {"coordinates":[-86.93728900000001,39.026691],"type":"Point"}
}