{
  "type": "Feature",
  "properties": {
    "iso:country":"US",
    "sg:address":"812 Columbine Ct",
    "sg:city":"Auburn",
    "sg:classifiers":[
        {
            "category":"Professional",
            "type":"Services"
        }
    ],
    "sg:phone":"+1 260 925 0000",
    "sg:postcode":"46706",
    "sg:province":"IN",
    "wof:name":"Future World Leaders Inc",
    "wof:placetype":"venue"
},
  "geometry": {"coordinates":[-85.046325,41.373966],"type":"Point"}
}