{
  "type": "Feature",
  "properties": {
    "iso:country":"US",
    "sg:address":"2 W Mill St",
    "sg:city":"Cloverdale",
    "sg:classifiers":[
        {
            "category":"Food & Beverages",
            "subcategory":"Groceries & Convenience Stores",
            "type":"Retail Goods"
        }
    ],
    "sg:phone":"+1 765 795 4552",
    "sg:postcode":"46115",
    "sg:province":"IN",
    "sg:tags":[
        "grocer"
    ],
    "wof:name":"Priceless Foods-Deli & Bakery",
    "wof:placetype":"venue"
},
  "geometry": {"coordinates":[-85.573127,39.738372],"type":"Point"}
}