{
  "type": "Feature",
  "properties": {
    "addr:full":"601 W National Ave West Terre Haute IN 47885",
    "addr:housenumber":"601",
    "addr:postcode":"47885",
    "addr:street":"W National Ave",
    "iso:country":"US",
    "sg:address":"601 W National Ave",
    "sg:city":"West Terre Haute",
    "sg:classifiers":[
        {
            "category":"Building & Trades",
            "subcategory":"Construction",
            "type":"Services"
        }
    ],
    "sg:phone":"+1 812 533 1380",
    "sg:postcode":"47885",
    "sg:province":"IN",
    "sg:tags":[
        "maker",
        "cabinet"
    ],
    "wof:name":"Macksville Station",
    "wof:placetype":"venue"
},
  "geometry": {"coordinates":[-87.45104499999999,39.464842],"type":"Point"}
}