{
  "type": "Feature",
  "properties": {
    "iso:country":"US",
    "sg:address":"1004 N Washington St",
    "sg:city":"Kokomo",
    "sg:classifiers":[
        {
            "category":"Bars & Pubs",
            "type":"Food & Drink"
        }
    ],
    "sg:phone":"+1 765 457 9940",
    "sg:postcode":"46901",
    "sg:province":"IN",
    "wof:name":"Bill Gentry's Elbow Room",
    "wof:placetype":"venue"
},
  "geometry": {"coordinates":[-86.133643,40.495424],"type":"Point"}
}