{
  "type": "Feature",
  "properties": {
    "addr:full":"832 E McGalliard Rd Muncie IN 47303",
    "addr:housenumber":"832",
    "addr:postcode":"47303",
    "addr:street":"E Mcgalliard Rd",
    "iso:country":"US",
    "sg:address":"832 E McGalliard Rd",
    "sg:city":"Muncie",
    "sg:classifiers":[
        {
            "category":"Shopping",
            "subcategory":"Clothing, Apparel, & Fashions",
            "type":"Retail Goods"
        }
    ],
    "sg:phone":"+1 765 289 7991",
    "sg:postcode":"47303",
    "sg:province":"IN",
    "sg:tags":[
        "infant",
        "wear"
    ],
    "wof:name":"Here We Grow Again",
    "wof:placetype":"venue"
},
  "geometry": {"coordinates":[-85.375657,40.219104],"type":"Point"}
}