{
  "type": "Feature",
  "properties": {
    "addr:full":"3 S 12th St Richmond IN 47374",
    "addr:housenumber":"3",
    "addr:postcode":"47374",
    "addr:street":"S 12Th St",
    "iso:country":"US",
    "sg:address":"3 S 12th St",
    "sg:city":"Richmond",
    "sg:classifiers":[
        {
            "category":"Real Estate",
            "subcategory":"Real Estate Operator",
            "type":"Services"
        }
    ],
    "sg:phone":"+1 765 962 3497",
    "sg:postcode":"47374",
    "sg:province":"IN",
    "sg:tags":[
        "apartment"
    ],
    "wof:name":"Drexler-Stiens Property Mgmt",
    "wof:placetype":"venue"
},
  "geometry": {"coordinates":[-84.886129,39.829205],"type":"Point"}
}