{
  "type": "Feature",
  "properties": {
    "iso:country":"US",
    "sg:address":"312 Fox Ct",
    "sg:city":"Carmel",
    "sg:classifiers":[
        {
            "category":"Retail",
            "subcategory":"Auto Repair",
            "type":"Services"
        }
    ],
    "sg:phone":"+1 317 844 0327",
    "sg:postcode":"46032",
    "sg:province":"IN",
    "sg:tags":[
        "automobile",
        "restoration",
        "classic"
    ],
    "wof:name":"Burnsy Enterprises Inc",
    "wof:placetype":"venue"
},
  "geometry": {"coordinates":[-86.16387400000001,40.00744],"type":"Point"}
}