{
  "type": "Feature",
  "properties": {
    "iso:country":"US",
    "sg:address":"2292 N US Hwy 33",
    "sg:city":"Decatur",
    "sg:classifiers":[
        {
            "category":"Building & Trades",
            "subcategory":"Construction",
            "type":"Services"
        }
    ],
    "sg:phone":"+1 260 592 7008",
    "sg:postcode":"46733",
    "sg:province":"IN",
    "sg:tags":[
        "woodworker"
    ],
    "wof:name":"Eckhart Woodworking",
    "wof:placetype":"venue"
},
  "geometry": {"coordinates":[-84.844222,40.779229],"type":"Point"}
}