{
  "type": "Feature",
  "properties": {
    "iso:country":"US",
    "sg:address":"321 S Grant St",
    "sg:city":"Bloomington",
    "sg:classifiers":[
        {
            "category":"Professional",
            "subcategory":"Credit Reporting & Collection",
            "type":"Services"
        }
    ],
    "sg:phone":"+1 812 339 5517",
    "sg:postcode":"47401",
    "sg:province":"IN",
    "sg:tags":[
        "agency"
    ],
    "wof:name":"Bloomington Accounts Svc",
    "wof:placetype":"venue"
},
  "geometry": {"coordinates":[-86.529754,39.163184],"type":"Point"}
}