{
  "type": "Feature",
  "properties": {
    "iso:country":"US",
    "sg:address":"424 W Howard St",
    "sg:city":"Galveston",
    "sg:classifiers":[
        {
            "category":"Government",
            "subcategory":"Office",
            "type":"Public Place"
        }
    ],
    "sg:phone":"+1 574 699 6677",
    "sg:postcode":"46932",
    "sg:province":"IN",
    "sg:tags":[
        "village"
    ],
    "wof:name":"Jackson Township Trustee",
    "wof:placetype":"venue"
},
  "geometry": {"coordinates":[-86.184723,40.57803],"type":"Point"}
}