{
  "type": "Feature",
  "properties": {
    "iso:country":"US",
    "sg:address":"2059 Crisman Rd",
    "sg:city":"Portage",
    "sg:classifiers":[
        {
            "category":"Insurance",
            "subcategory":"Insurance Agent",
            "type":"Services"
        }
    ],
    "sg:phone":"+1 219 764 9299",
    "sg:postcode":"46368",
    "sg:province":"IN",
    "wof:name":"Acceptance Insurance Co",
    "wof:placetype":"venue"
},
  "geometry": {"coordinates":[-87.173587,41.593803],"type":"Point"}
}