{
  "type": "Feature",
  "properties": {
    "addr:full":"3999 N Co Rd 750 W Holton IN 47023",
    "addr:housenumber":"3999;750",
    "addr:postcode":"47023",
    "addr:street":"N Co Rd;W Holton",
    "iso:country":"US",
    "sg:address":"3999 N Co Rd 750 W",
    "sg:city":"Holton",
    "sg:classifiers":[
        {
            "category":"Farming",
            "subcategory":"Livestock Farm",
            "type":"Manufacturing & Wholesale Goods"
        }
    ],
    "sg:phone":"+1 812 689 4638",
    "sg:postcode":"47023",
    "sg:province":"IN",
    "sg:tags":[
        "beef",
        "feedlot",
        "cattle"
    ],
    "wof:name":"Jack May",
    "wof:placetype":"venue"
},
  "geometry": {"coordinates":[-85.39455599999999,39.128916],"type":"Point"}
}