{
  "type": "Feature",
  "properties": {
    "iso:country":"US",
    "sg:address":"54 Monument Cir",
    "sg:city":"Indianapolis",
    "sg:classifiers":[
        {
            "category":"Banks & Credit Unions",
            "subcategory":"Bank",
            "type":"Services"
        }
    ],
    "sg:phone":"+1 317 633 0914",
    "sg:postcode":"46204",
    "sg:province":"IN",
    "sg:tags":[
        "company",
        "mortgage"
    ],
    "wof:name":"Landmark Mortgage Company",
    "wof:placetype":"venue"
},
  "geometry": {"coordinates":[-86.158592,39.768052],"type":"Point"}
}