{
  "type": "Feature",
  "properties": {
    "iso:country":"US",
    "sg:address":"9019 Broken Arrow Rd",
    "sg:city":"Indianapolis",
    "sg:classifiers":[
        {
            "category":"Manufacturing",
            "subcategory":"Metals",
            "type":"Manufacturing & Wholesale Goods"
        }
    ],
    "sg:phone":"+1 317 271 7362",
    "sg:postcode":"46234",
    "sg:province":"IN",
    "sg:tags":[
        "coating"
    ],
    "wof:name":"Praxair",
    "wof:placetype":"venue"
},
  "geometry": {"coordinates":[-86.324258,39.769276],"type":"Point"}
}