{
  "type": "Feature",
  "properties": {
    "addr:full":"415 Steven's Way Seymour IN 47274",
    "addr:housenumber":"415",
    "addr:postcode":"47274",
    "addr:street":"Steven'S Way",
    "iso:country":"US",
    "sg:address":"415 Steven's Way",
    "sg:city":"Seymour",
    "sg:classifiers":[
        {
            "category":"Wholesale",
            "subcategory":"Machinery & Supplies",
            "type":"Manufacturing & Wholesale Goods"
        }
    ],
    "sg:phone":"+1 812 523 5050",
    "sg:postcode":"47274",
    "sg:province":"IN",
    "sg:tags":[
        "farm",
        "equipment"
    ],
    "sg:website":"www.jacobisales.com",
    "wof:name":"Jacobi Sales",
    "wof:placetype":"venue"
},
  "geometry": {"coordinates":[-85.837591,38.958794],"type":"Point"}
}