{
  "type": "Feature",
  "properties": {
    "iso:country":"US",
    "sg:address":"724 Savannah Dr",
    "sg:city":"Crown Point",
    "sg:classifiers":[
        {
            "category":"Health Services",
            "subcategory":"Dentist",
            "type":"Services"
        }
    ],
    "sg:phone":"+1 219 663 9086",
    "sg:postcode":"46307",
    "sg:province":"IN",
    "wof:name":"Smith David M DDS",
    "wof:placetype":"venue"
},
  "geometry": {"coordinates":[-87.34341499999999,41.405213],"type":"Point"}
}