{
  "type": "Feature",
  "properties": {
    "iso:country":"US",
    "sg:address":"130 W Griffith St",
    "sg:city":"Galveston",
    "sg:classifiers":[
        {
            "category":"Building & Trades",
            "subcategory":"Cleaning & Sanitation",
            "type":"Services"
        }
    ],
    "sg:phone":"+1 574 699 7942",
    "sg:postcode":"46932",
    "sg:province":"IN",
    "sg:tags":[
        "janitor"
    ],
    "wof:name":"TNT Janitorial Svc Inc",
    "wof:placetype":"venue"
},
  "geometry": {"coordinates":[-86.191108,40.576057],"type":"Point"}
}