{
  "type": "Feature",
  "properties": {
    "iso:country":"US",
    "sg:address":"501 N Meadow Wood Dr",
    "sg:city":"Muncie",
    "sg:classifiers":[
        {
            "category":"Home & Garden",
            "subcategory":"Building Materials",
            "type":"Retail Goods"
        }
    ],
    "sg:phone":"+1 765 282 7985",
    "sg:postcode":"47304",
    "sg:province":"IN",
    "sg:tags":[
        "brick"
    ],
    "wof:name":"GEO Dynamics-Blocks & Pavers",
    "wof:placetype":"venue"
},
  "geometry": {"coordinates":[-85.463205,40.196748],"type":"Point"}
}