{
  "type": "Feature",
  "properties": {
    "iso:country":"US",
    "sg:address":"2201 E National Hwy",
    "sg:city":"Washington",
    "sg:classifiers":[
        {
            "category":"Restaurant",
            "type":"Food & Drink"
        }
    ],
    "sg:phone":"+1 812 254 1884",
    "sg:postcode":"47501",
    "sg:province":"IN",
    "wof:name":"Mr Gatti's Pizza",
    "wof:placetype":"venue"
},
  "geometry": {"coordinates":[-87.141219,38.654524],"type":"Point"}
}