{
  "type": "Feature",
  "properties": {
    "iso:country":"US",
    "sg:address":"7001 Old Boonville Hwy",
    "sg:city":"Evansville",
    "sg:classifiers":[
        {
            "category":"Organizations",
            "subcategory":"Community Association",
            "type":"Services"
        }
    ],
    "sg:phone":"+1 812 473 0462",
    "sg:postcode":"47715",
    "sg:province":"IN",
    "wof:name":"Kappa Kappa Iota",
    "wof:placetype":"venue"
},
  "geometry": {"coordinates":[-87.46598,38.005455],"type":"Point"}
}