{
  "type": "Feature",
  "properties": {
    "addr:full":"7470 Geist Valley Blvd Indianapolis IN 46236",
    "addr:housenumber":"7470",
    "addr:postcode":"46236",
    "addr:street":"Geist Valley Blvd",
    "iso:country":"US",
    "sg:address":"7470 Geist Valley Blvd",
    "sg:city":"Indianapolis",
    "sg:classifiers":[
        {
            "category":"Organizations",
            "subcategory":"Religious Organization",
            "type":"Services"
        }
    ],
    "sg:phone":"+1 317 823 8118",
    "sg:postcode":"46236",
    "sg:province":"IN",
    "wof:name":"Holy Cross Lutheran Church",
    "wof:placetype":"venue"
},
  "geometry": {"coordinates":[-85.95477,39.890718],"type":"Point"}
}