{
  "type": "Feature",
  "properties": {
    "iso:country":"US",
    "sg:address":"2455 S Saltillo Rd",
    "sg:city":"Campbellsburg",
    "sg:classifiers":[
        {
            "category":"Real Estate",
            "subcategory":"Real Estate Operator",
            "type":"Services"
        }
    ],
    "sg:phone":"+1 812 755 4243",
    "sg:postcode":"47108",
    "sg:province":"IN",
    "sg:tags":[
        "property",
        "lessor"
    ],
    "wof:name":"Greg Bishop",
    "wof:placetype":"venue"
},
  "geometry": {"coordinates":[-86.289465,38.573121],"type":"Point"}
}