{
  "type": "Feature",
  "properties": {
    "iso:country":"US",
    "sg:address":"810 Coliseum Blvd N",
    "sg:city":"Fort Wayne",
    "sg:classifiers":[
        {
            "category":"Personal",
            "subcategory":"Beauty Salon",
            "type":"Services"
        }
    ],
    "sg:phone":"+1 260 471 0344",
    "sg:postcode":"46805",
    "sg:province":"IN",
    "wof:name":"Lans Nail Salon",
    "wof:placetype":"venue"
},
  "geometry": {"coordinates":[-85.08779,41.087172],"type":"Point"}
}