{
  "type": "Feature",
  "properties": {
    "iso:country":"US",
    "sg:address":"69 N Colfax St",
    "sg:city":"Martinsville",
    "sg:classifiers":[
        {
            "category":"Real Estate",
            "subcategory":"Real Estate Agent",
            "type":"Services"
        }
    ],
    "sg:phone":"+1 765 342 5500",
    "sg:postcode":"46151",
    "sg:province":"IN",
    "wof:name":"Shelia Scott Realty Group Inc",
    "wof:placetype":"venue"
},
  "geometry": {"coordinates":[-86.418849,39.427658],"type":"Point"}
}