{
  "type": "Feature",
  "properties": {
    "iso:country":"US",
    "sg:address":"4941 Kuebler Rd",
    "sg:city":"Evansville",
    "sg:classifiers":[
        {
            "category":"Health Services",
            "subcategory":"Medical Lab",
            "type":"Services"
        }
    ],
    "sg:phone":"+1 812 963 3072",
    "sg:postcode":"47720",
    "sg:province":"IN",
    "sg:tags":[
        "laboratory"
    ],
    "wof:name":"Manchette Dental Laboratories",
    "wof:placetype":"venue"
},
  "geometry": {"coordinates":[-87.62132,38.056864],"type":"Point"}
}