{
  "type": "Feature",
  "properties": {
    "iso:country":"US",
    "sg:address":"327 W 100 S",
    "sg:city":"Huntington",
    "sg:classifiers":[
        {
            "category":"Farming",
            "subcategory":"Livestock Farm",
            "type":"Manufacturing & Wholesale Goods"
        }
    ],
    "sg:phone":"+1 260 468 2505",
    "sg:postcode":"46750",
    "sg:province":"IN",
    "sg:tags":[
        "ranch"
    ],
    "wof:name":"Boot Hill Ranch",
    "wof:placetype":"venue"
},
  "geometry": {"coordinates":[-85.456754,40.814431],"type":"Point"}
}