{
  "type": "Feature",
  "properties": {
    "addr:full":"421 W 1st St Bloomington IN 47403",
    "addr:housenumber":"421",
    "addr:postcode":"47403",
    "addr:street":"W 1St St",
    "iso:country":"US",
    "sg:address":"421 W 1st St",
    "sg:city":"Bloomington",
    "sg:classifiers":[
        {
            "category":"Health Services",
            "subcategory":"Doctor",
            "type":"Services"
        },
        {
            "category":"Health Services",
            "subcategory":"Clinic",
            "type":"Services"
        }
    ],
    "sg:phone":"+1 812 336 0168",
    "sg:postcode":"47403",
    "sg:province":"IN",
    "sg:tags":[
        "counseling",
        "obstetrician",
        "mental",
        "gynecologist"
    ],
    "sg:website":"www.bloomingtonobgyn.net",
    "wof:name":"Stauffer Dwight L MD",
    "wof:placetype":"venue"
},
  "geometry": {"coordinates":[-86.540497,39.159302],"type":"Point"}
}