{
  "type": "Feature",
  "properties": {
    "iso:country":"US",
    "sg:address":"6502 Grape Rd",
    "sg:city":"Mishawaka",
    "sg:classifiers":[
        {
            "category":"Shopping",
            "subcategory":"Catalog Store",
            "type":"Retail Goods"
        }
    ],
    "sg:phone":"+1 574 272 4030",
    "sg:postcode":"46545",
    "sg:province":"IN",
    "sg:tags":[
        "mail",
        "house"
    ],
    "wof:name":"Gateway",
    "wof:placetype":"venue"
},
  "geometry": {"coordinates":[-86.187534,41.717887],"type":"Point"}
}