{
  "type": "Feature",
  "properties": {
    "iso:country":"US",
    "sg:address":"305 Tippecanoe St",
    "sg:city":"Battle Ground",
    "sg:classifiers":[
        {
            "category":"Professional",
            "subcategory":"Business Services",
            "type":"Services"
        }
    ],
    "sg:phone":"+1 765 567 4779",
    "sg:postcode":"47920",
    "sg:province":"IN",
    "wof:name":"Business Number 765 567-4567",
    "wof:placetype":"venue"
},
  "geometry": {"coordinates":[-86.83457300000001,40.51499],"type":"Point"}
}