{
  "type": "Feature",
  "properties": {
    "addr:full":"1966 Co Rd 31 Waterloo IN 46793",
    "addr:housenumber":"1966;31",
    "addr:postcode":"46793",
    "addr:street":"Co Rd",
    "iso:country":"US",
    "sg:address":"1966 Co Rd 31",
    "sg:city":"Waterloo",
    "sg:phone":"+1 260 837 7673",
    "sg:postcode":"46793",
    "sg:province":"IN",
    "sg:tags":[
        "farm",
        "corn",
        "soybean"
    ],
    "wof:name":"Marie Sanders",
    "wof:placetype":"venue"
},
  "geometry": {"coordinates":[-85.044253,41.459985],"type":"Point"}
}