{
  "type": "Feature",
  "properties": {
    "addr:full":"126 N Harrison St Shelbyville IN 46176",
    "addr:housenumber":"126",
    "addr:postcode":"46176",
    "addr:street":"N Harrison St",
    "iso:country":"US",
    "sg:address":"126 N Harrison St",
    "sg:city":"Shelbyville",
    "sg:classifiers":[
        {
            "category":"Organizations",
            "subcategory":"Professional Association",
            "type":"Services"
        }
    ],
    "sg:phone":"+1 317 398 6203",
    "sg:postcode":"46176",
    "sg:province":"IN",
    "wof:name":"New Hope Counseling Ctr",
    "wof:placetype":"venue"
},
  "geometry": {"coordinates":[-85.77692999999999,39.525519],"type":"Point"}
}