{
  "type": "Feature",
  "properties": {
    "iso:country":"US",
    "sg:address":"11529 Wayfair Pl",
    "sg:city":"Fort Wayne",
    "sg:classifiers":[
        {
            "category":"Real Estate",
            "subcategory":"Real Estate Agent",
            "type":"Services"
        }
    ],
    "sg:phone":"+1 260 637 8551",
    "sg:postcode":"46845",
    "sg:province":"IN",
    "wof:name":"Clay Alva Real Estate",
    "wof:placetype":"venue"
},
  "geometry": {"coordinates":[-85.11607600000001,41.187756],"type":"Point"}
}