{
  "type": "Feature",
  "properties": {
    "iso:country":"US",
    "sg:address":"289 N Gardner St",
    "sg:city":"Scottsburg",
    "sg:classifiers":[
        {
            "category":"Autos & Motor Vehicles",
            "subcategory":"Automobile Sales",
            "type":"Retail Goods"
        }
    ],
    "sg:phone":"+1 812 752 0033",
    "sg:postcode":"47170",
    "sg:province":"IN",
    "sg:tags":[
        "car",
        "dealer"
    ],
    "wof:name":"Good Import Auto Sales",
    "wof:placetype":"venue"
},
  "geometry": {"coordinates":[-85.779242,38.690463],"type":"Point"}
}