{
  "type": "Feature",
  "properties": {
    "iso:country":"US",
    "sg:address":"4065 Asbury St",
    "sg:city":"Indianapolis",
    "sg:classifiers":[
        {
            "category":"Education",
            "subcategory":"School",
            "type":"Public Place"
        }
    ],
    "sg:phone":"+1 317 226 4265",
    "sg:postcode":"46227",
    "sg:province":"IN",
    "wof:name":"Raymond F Brandes School",
    "wof:placetype":"venue"
},
  "geometry": {"coordinates":[-86.12815399999999,39.705155],"type":"Point"}
}