{
  "type": "Feature",
  "properties": {
    "iso:country":"US",
    "sg:address":"1611 Charlestown New Albany Rd",
    "sg:city":"Jeffersonville",
    "sg:classifiers":[
        {
            "category":"Restaurant",
            "type":"Food & Drink"
        }
    ],
    "sg:phone":"+1 812 283 4061",
    "sg:postcode":"47130",
    "sg:province":"IN",
    "sg:tags":[
        "barbecue"
    ],
    "wof:name":"Smokin' Bar BQ",
    "wof:placetype":"venue"
},
  "geometry": {"coordinates":[-85.743246,38.324615],"type":"Point"}
}