{
  "type": "Feature",
  "properties": {
    "addr:full":"1301 W Lincoln Rd Kokomo IN 46902",
    "addr:housenumber":"1301",
    "addr:postcode":"46902",
    "addr:street":"W Lincoln Rd",
    "iso:country":"US",
    "sg:address":"1301 W Lincoln Rd",
    "sg:city":"Kokomo",
    "sg:classifiers":[
        {
            "category":"Sports & Exercise",
            "subcategory":"Bowling",
            "type":"Entertainment"
        }
    ],
    "sg:phone":"+1 765 453 7781",
    "sg:postcode":"46902",
    "sg:province":"IN",
    "sg:tags":[
        "center"
    ],
    "wof:name":"Don Lowry Lanes",
    "wof:placetype":"venue"
},
  "geometry": {"coordinates":[-86.14617699999999,40.454603],"type":"Point"}
}