{
  "type": "Feature",
  "properties": {
    "iso:country":"US",
    "sg:address":"1500 165th St",
    "sg:city":"Hammond",
    "sg:classifiers":[
        {
            "category":"Utilities",
            "subcategory":"Electric",
            "type":"Services"
        }
    ],
    "sg:phone":"+1 219 853 5168",
    "sg:postcode":"46324",
    "sg:province":"IN",
    "sg:tags":[
        "marketing",
        "power"
    ],
    "wof:name":"Nipsco Energy Services Inc",
    "wof:placetype":"venue"
},
  "geometry": {"coordinates":[-87.48093,41.595711],"type":"Point"}
}