{
  "type": "Feature",
  "properties": {
    "iso:country":"US",
    "sg:address":"5337 Tara Ct N",
    "sg:city":"Indianapolis",
    "sg:classifiers":[
        {
            "category":"Social Services",
            "subcategory":"Child Care",
            "type":"Services"
        }
    ],
    "sg:phone":"+1 317 290 1011",
    "sg:postcode":"46224",
    "sg:province":"IN",
    "wof:name":"Little Bit Of Love Daycare",
    "wof:placetype":"venue"
},
  "geometry": {"coordinates":[-86.254403,39.814456],"type":"Point"}
}