{
  "type": "Feature",
  "properties": {
    "iso:country":"US",
    "sg:address":"1263 E Morgan Ave",
    "sg:city":"Evansville",
    "sg:classifiers":[
        {
            "category":"Manufacturing",
            "subcategory":"Tools & Machinery",
            "type":"Manufacturing & Wholesale Goods"
        }
    ],
    "sg:phone":"+1 812 425 4888",
    "sg:postcode":"47711",
    "sg:province":"IN",
    "sg:tags":[
        "storage"
    ],
    "wof:name":"Wood's Battery & Auto Elec Co",
    "wof:placetype":"venue"
},
  "geometry": {"coordinates":[-87.540455,37.991817],"type":"Point"}
}