{
  "type": "Feature",
  "properties": {
    "iso:country":"US",
    "sg:address":"417 College Ave",
    "sg:city":"Vincennes",
    "sg:classifiers":[
        {
            "category":"Personal",
            "type":"Services"
        }
    ],
    "sg:phone":"+1 812 882 8288",
    "sg:postcode":"47591",
    "sg:province":"IN",
    "sg:tags":[
        "body",
        "piercing"
    ],
    "sg:website":"http://www.alteredimagetattos.com",
    "wof:name":"Altered Image",
    "wof:placetype":"venue"
},
  "geometry": {"coordinates":[-87.52112099999999,38.682875],"type":"Point"}
}