{
  "type": "Feature",
  "properties": {
    "iso:country":"US",
    "sg:address":"619 W Howard St",
    "sg:city":"Muncie",
    "sg:classifiers":[
        {
            "category":"Real Estate",
            "subcategory":"Real Estate Operator",
            "type":"Services"
        }
    ],
    "sg:phone":"+1 765 284 7816",
    "sg:postcode":"47305",
    "sg:province":"IN",
    "sg:tags":[
        "property",
        "lessor"
    ],
    "wof:name":"Donald Souffrant",
    "wof:placetype":"venue"
},
  "geometry": {"coordinates":[-85.39307,40.190194],"type":"Point"}
}