{
  "type": "Feature",
  "properties": {
    "iso:country":"US",
    "sg:address":"1563 N State Rd 5",
    "sg:city":"Larwill",
    "sg:classifiers":[
        {
            "category":"Building & Trades",
            "subcategory":"Construction",
            "type":"Services"
        }
    ],
    "sg:phone":"+1 260 327 3855",
    "sg:postcode":"46764",
    "sg:province":"IN",
    "sg:tags":[
        "maker",
        "cabinet"
    ],
    "wof:name":"M & D Custom Cabinetry",
    "wof:placetype":"venue"
},
  "geometry": {"coordinates":[-85.625157,41.192803],"type":"Point"}
}