{
  "type": "Feature",
  "properties": {
    "iso:country":"US",
    "sg:address":"3167 S State Rd 3",
    "sg:city":"New Castle",
    "sg:classifiers":[
        {
            "category":"Personal",
            "subcategory":"Beauty Salon",
            "type":"Services"
        }
    ],
    "sg:phone":"+1 765 521 4819",
    "sg:postcode":"47362",
    "sg:province":"IN",
    "wof:name":"Smart Style Family Hair Salon",
    "wof:placetype":"venue"
},
  "geometry": {"coordinates":[-85.385784,39.885598],"type":"Point"}
}