{
  "type": "Feature",
  "properties": {
    "iso:country":"US",
    "sg:address":"720 S Curry Pike",
    "sg:city":"Bloomington",
    "sg:classifiers":[
        {
            "category":"Social Services",
            "subcategory":"Child Care",
            "type":"Services"
        }
    ],
    "sg:phone":"+1 812 336 0328",
    "sg:postcode":"47403",
    "sg:province":"IN",
    "sg:tags":[
        "day"
    ],
    "wof:name":"Little Luvs Day Care PR-Shcool",
    "wof:placetype":"venue"
},
  "geometry": {"coordinates":[-86.582737,39.158317],"type":"Point"}
}