{
  "type": "Feature",
  "properties": {
    "iso:country":"US",
    "sg:address":"398 Urban St",
    "sg:city":"Danville",
    "sg:classifiers":[
        {
            "category":"Education",
            "subcategory":"School",
            "type":"Public Place"
        }
    ],
    "sg:phone":"+1 317 745 2610",
    "sg:postcode":"46122",
    "sg:province":"IN",
    "sg:website":"www.danville.k12.in.us",
    "wof:name":"Danville North Elementary Schl",
    "wof:placetype":"venue"
},
  "geometry": {"coordinates":[-86.533337,39.764665],"type":"Point"}
}