{
  "type": "Feature",
  "properties": {
    "iso:country":"US",
    "sg:address":"2110 Burton Ln",
    "sg:city":"Martinsville",
    "sg:classifiers":[
        {
            "category":"Banks & Credit Unions",
            "subcategory":"Bank",
            "type":"Services"
        }
    ],
    "sg:phone":"+1 765 342 7200",
    "sg:postcode":"46151",
    "sg:province":"IN",
    "wof:name":"First National Bank & Trust",
    "wof:placetype":"venue"
},
  "geometry": {"coordinates":[-86.437243,39.406393],"type":"Point"}
}