{
  "type": "Feature",
  "properties": {
    "addr:full":"112 E Water St Pendleton IN 46064",
    "addr:housenumber":"112",
    "addr:postcode":"46064",
    "addr:street":"E Water St",
    "iso:country":"US",
    "sg:address":"112 E Water St",
    "sg:city":"Pendleton",
    "sg:classifiers":[
        {
            "category":"Personal",
            "subcategory":"Beauty Salon",
            "type":"Services"
        }
    ],
    "sg:phone":"+1 765 778 7258",
    "sg:postcode":"46064",
    "sg:province":"IN",
    "wof:name":"Shear Sensation",
    "wof:placetype":"venue"
},
  "geometry": {"coordinates":[-85.745529,40.003682],"type":"Point"}
}