{
  "type": "Feature",
  "properties": {
    "iso:country":"US",
    "sg:address":"100 E Main St",
    "sg:city":"Albion",
    "sg:classifiers":[
        {
            "category":"Social Services",
            "type":"Services"
        }
    ],
    "sg:phone":"+1 260 636 2320",
    "sg:postcode":"46701",
    "sg:province":"IN",
    "sg:tags":[
        "organization",
        "welfare"
    ],
    "wof:name":"Drug-Free Noble County",
    "wof:placetype":"venue"
},
  "geometry": {"coordinates":[-85.422694,41.395648],"type":"Point"}
}