{
  "type": "Feature",
  "properties": {
    "iso:country":"US",
    "sg:address":"402 W Plaza Dr",
    "sg:city":"Columbia City",
    "sg:classifiers":[
        {
            "category":"Utilities",
            "subcategory":"Mobile Phone",
            "type":"Services"
        }
    ],
    "sg:phone":"+1 260 248 2961",
    "sg:postcode":"46725",
    "sg:province":"IN",
    "sg:tags":[
        "telephone",
        "cellular"
    ],
    "wof:name":"Us Cellular Inc",
    "wof:placetype":"venue"
},
  "geometry": {"coordinates":[-85.493348,41.170338],"type":"Point"}
}