{
  "type": "Feature",
  "properties": {
    "iso:country":"US",
    "sg:address":"505 N 6th St",
    "sg:city":"Vincennes",
    "sg:classifiers":[
        {
            "category":"Professional",
            "subcategory":"Accounting & Tax Preparation",
            "type":"Services"
        }
    ],
    "sg:phone":"+1 812 882 7730",
    "sg:postcode":"47591",
    "sg:province":"IN",
    "sg:tags":[
        "accountant"
    ],
    "sg:website":"www.kempercpa.com",
    "wof:name":"Kemper CPA Group LLC",
    "wof:placetype":"venue"
},
  "geometry": {"coordinates":[-87.524149,38.679921],"type":"Point"}
}