{
  "type": "Feature",
  "properties": {
    "addr:full":"1924 Wellesley Blvd Indianapolis Indianapolis IN 46219",
    "addr:housenumber":"1924",
    "addr:postcode":"46219",
    "addr:street":"Wellesley Blvd",
    "iso:country":"US",
    "sg:address":"1924 Wellesley Blvd Indianapolis",
    "sg:city":"Indianapolis",
    "sg:classifiers":[
        {
            "category":"Social Services",
            "subcategory":"Job Training",
            "type":"Services"
        },
        {
            "category":"Health Services",
            "subcategory":"Nursing And Care Facility",
            "type":"Services"
        },
        {
            "category":"Social Services",
            "subcategory":"Retirement Home",
            "type":"Services"
        },
        {
            "category":"Health Services",
            "subcategory":"Clinic",
            "type":"Services"
        }
    ],
    "sg:phone":"+1 317 782 5942",
    "sg:postcode":"46219",
    "sg:province":"IN",
    "sg:tags":[
        "living",
        "homes-skilled",
        "people",
        "assisted",
        "homes-elderly",
        "rehabilitation"
    ],
    "sg:website":"http://americansrcommunities.com/wlm",
    "wof:name":"Wellington Manor",
    "wof:placetype":"venue"
},
  "geometry": {"coordinates":[-86.03112900000001,39.793696],"type":"Point"}
}