{
  "type": "Feature",
  "properties": {
    "iso:country":"US",
    "sg:address":"302 Washington St",
    "sg:city":"Columbus",
    "sg:classifiers":[
        {
            "category":"Education",
            "subcategory":"Dance Studio",
            "type":"Public Place"
        }
    ],
    "sg:phone":"+1 812 376 2539",
    "sg:postcode":"47201",
    "sg:province":"IN",
    "wof:name":"Dance Partners Inc",
    "wof:placetype":"venue"
},
  "geometry": {"coordinates":[-85.921128,39.202432],"type":"Point"}
}