{
  "type": "Feature",
  "properties": {
    "iso:country":"US",
    "sg:address":"8420 Olin Rd",
    "sg:city":"Indianapolis",
    "sg:classifiers":[
        {
            "category":"Professional",
            "subcategory":"Computer Services",
            "type":"Services"
        }
    ],
    "sg:phone":"+1 317 228 9801",
    "sg:postcode":"46278",
    "sg:province":"IN",
    "wof:name":"Online Resources Corp",
    "wof:placetype":"venue"
},
  "geometry": {"coordinates":[-86.312522,39.906658],"type":"Point"}
}