{
  "type": "Feature",
  "properties": {
    "iso:country":"US",
    "sg:address":"175 E 6th St",
    "sg:city":"Jasper",
    "sg:classifiers":[
        {
            "category":"Real Estate",
            "subcategory":"Real Estate Agent",
            "type":"Services"
        }
    ],
    "sg:phone":"+1 812 634 1558",
    "sg:postcode":"47546",
    "sg:province":"IN",
    "sg:tags":[
        "appraiser"
    ],
    "wof:name":"Persohn & Assoc",
    "wof:placetype":"venue"
},
  "geometry": {"coordinates":[-86.93019700000001,38.391308],"type":"Point"}
}