{
  "type": "Feature",
  "properties": {
    "addr:full":"3053 Desoto Way Columbus IN 47203",
    "addr:housenumber":"3053",
    "addr:postcode":"47203",
    "addr:street":"Desoto Way",
    "iso:country":"US",
    "sg:address":"3053 Desoto Way",
    "sg:city":"Columbus",
    "sg:classifiers":[
        {
            "category":"Building & Trades",
            "subcategory":"Construction",
            "type":"Services"
        }
    ],
    "sg:phone":"+1 812 379 4854",
    "sg:postcode":"47203",
    "sg:province":"IN",
    "sg:tags":[
        "roofing",
        "contractor"
    ],
    "wof:name":"Overfelt Roofing",
    "wof:placetype":"venue"
},
  "geometry": {"coordinates":[-85.892821,39.227056],"type":"Point"}
}