{
  "type": "Feature",
  "properties": {
    "iso:country":"US",
    "sg:address":"2720 U St",
    "sg:city":"Bedford",
    "sg:classifiers":[
        {
            "category":"Real Estate",
            "subcategory":"Real Estate Agent",
            "type":"Services"
        }
    ],
    "sg:phone":"+1 812 277 9684",
    "sg:postcode":"47421",
    "sg:province":"IN",
    "wof:name":"M & N Proerties",
    "wof:placetype":"venue"
},
  "geometry": {"coordinates":[-86.499688,38.847939],"type":"Point"}
}