{
  "type": "Feature",
  "properties": {
    "addr:full":"5725 W Minnesota St Indianapolis IN 46241",
    "addr:housenumber":"5725",
    "addr:postcode":"46241",
    "addr:street":"W Minnesota St",
    "iso:country":"US",
    "sg:address":"5725 W Minnesota St",
    "sg:city":"Indianapolis",
    "sg:classifiers":[
        {
            "category":"Wholesale",
            "subcategory":"Non-durable Goods",
            "type":"Manufacturing & Wholesale Goods"
        },
        {
            "category":"Shopping",
            "subcategory":"Department Store",
            "type":"Retail Goods"
        },
        {
            "category":"Building & Trades",
            "subcategory":"Cleaning & Sanitation",
            "type":"Services"
        },
        {
            "category":"Home & Garden",
            "subcategory":"Hardware",
            "type":"Retail Goods"
        }
    ],
    "sg:phone":"+1 317 243 7040",
    "sg:postcode":"46241",
    "sg:province":"IN",
    "sg:tags":[
        "cleaner",
        "supply",
        "house",
        "equipment",
        "janitor",
        "supplies-wholesale",
        "manufacturer"
    ],
    "wof:name":"Abm Industries",
    "wof:placetype":"venue"
},
  "geometry": {"coordinates":[-86.258713,39.742985],"type":"Point"}
}