{
  "type": "Feature",
  "properties": {
    "iso:country":"US",
    "sg:address":"715 N Rogers St",
    "sg:city":"Bloomington",
    "sg:classifiers":[
        {
            "category":"Freight",
            "type":"Transportation"
        }
    ],
    "sg:phone":"+1 812 333 4755",
    "sg:postcode":"47404",
    "sg:province":"IN",
    "sg:tags":[
        "mover",
        "full",
        "storage"
    ],
    "sg:website":"http://new.softtouchmovingandstorage.com",
    "wof:name":"A Soft Touch Moving & Storage Co.",
    "wof:placetype":"venue"
},
  "geometry": {"coordinates":[-86.538579,39.173358],"type":"Point"}
}