{
  "type": "Feature",
  "properties": {
    "iso:country":"US",
    "sg:address":"4664 Woodscliff Cir",
    "sg:city":"Anderson",
    "sg:classifiers":[
        {
            "category":"Organizations",
            "subcategory":"Religious Organization",
            "type":"Services"
        }
    ],
    "sg:phone":"+1 765 378 5918",
    "sg:postcode":"46012",
    "sg:province":"IN",
    "sg:tags":[
        "clergy"
    ],
    "wof:name":"J Mark Freeman",
    "wof:placetype":"venue"
},
  "geometry": {"coordinates":[-85.581488,40.1248],"type":"Point"}
}