{
  "type": "Feature",
  "properties": {
    "addr:full":"2805 N Franklin Rd Indianapolis IN 46219",
    "addr:housenumber":"2805",
    "addr:postcode":"46219",
    "addr:street":"N Franklin Rd",
    "iso:country":"US",
    "sg:address":"2805 N Franklin Rd",
    "sg:city":"Indianapolis",
    "sg:classifiers":[
        {
            "category":"Restaurant",
            "type":"Food & Drink"
        }
    ],
    "sg:phone":"+1 317 897 4191",
    "sg:postcode":"46219",
    "sg:province":"IN",
    "wof:name":"Dirty Nelly's Eater & Pub",
    "wof:placetype":"venue"
},
  "geometry": {"coordinates":[-86.026995,39.807452],"type":"Point"}
}