{
  "type": "Feature",
  "properties": {
    "iso:country":"US",
    "sg:address":"64340 Co Rd 11",
    "sg:city":"Goshen",
    "sg:classifiers":[
        {
            "category":"Freight",
            "type":"Transportation"
        }
    ],
    "sg:phone":"+1 574 862 1567",
    "sg:postcode":"46526",
    "sg:province":"IN",
    "sg:tags":[
        "hauling",
        "trucking"
    ],
    "wof:name":"Harrison Hauling Inc",
    "wof:placetype":"venue"
},
  "geometry": {"coordinates":[-85.944217,41.560649],"type":"Point"}
}