{
  "type": "Feature",
  "properties": {
    "iso:country":"US",
    "sg:address":"7511 Knickerbocker Pkwy",
    "sg:city":"Hammond",
    "sg:classifiers":[
        {
            "category":"Building & Trades",
            "subcategory":"Cleaning & Sanitation",
            "type":"Services"
        }
    ],
    "sg:phone":"+1 219 844 4796",
    "sg:postcode":"46323",
    "sg:province":"IN",
    "sg:tags":[
        "carpet"
    ],
    "sg:website":"www.chemdry.com",
    "wof:name":"Region Chem-Dry",
    "wof:placetype":"venue"
},
  "geometry": {"coordinates":[-87.47730300000001,41.577099],"type":"Point"}
}