{
  "type": "Feature",
  "properties": {
    "iso:country":"US",
    "sg:address":"3315 Zartman Rd",
    "sg:city":"Kokomo",
    "sg:classifiers":[
        {
            "category":"Social Services",
            "subcategory":"Adult Care",
            "type":"Services"
        }
    ],
    "sg:phone":"+1 765 455 1167",
    "sg:postcode":"46902",
    "sg:province":"IN",
    "sg:tags":[
        "home",
        "group"
    ],
    "wof:name":"Group Home",
    "wof:placetype":"venue"
},
  "geometry": {"coordinates":[-86.183873,40.446932],"type":"Point"}
}