{
  "type": "Feature",
  "properties": {
    "iso:country":"US",
    "sg:address":"710 Garfield St",
    "sg:city":"Lebanon",
    "sg:classifiers":[
        {
            "category":"Building & Trades",
            "subcategory":"Plumbing",
            "type":"Services"
        }
    ],
    "sg:phone":"+1 765 482 2096",
    "sg:postcode":"46052",
    "sg:province":"IN",
    "sg:tags":[
        "conditioning",
        "air",
        "system",
        "contractor"
    ],
    "wof:name":"Jones & Sons Heating & AC",
    "wof:placetype":"venue"
},
  "geometry": {"coordinates":[-86.477595,40.05371],"type":"Point"}
}