{
  "type": "Feature",
  "properties": {
    "iso:country":"US",
    "sg:address":"760 McCool Rd",
    "sg:city":"Valparaiso",
    "sg:classifiers":[
        {
            "category":"Organizations",
            "subcategory":"Religious Organization",
            "type":"Services"
        }
    ],
    "sg:phone":"+1 219 759 3317",
    "sg:postcode":"46385",
    "sg:province":"IN",
    "sg:tags":[
        "church"
    ],
    "wof:name":"Emmanuel Baptist Church",
    "wof:placetype":"venue"
},
  "geometry": {"coordinates":[-87.143486,41.544426],"type":"Point"}
}