{
  "type": "Feature",
  "properties": {
    "iso:country":"US",
    "sg:address":"6049 Lakeside Blvd",
    "sg:city":"Indianapolis",
    "sg:classifiers":[
        {
            "category":"Professional",
            "subcategory":"Business Services",
            "type":"Services"
        }
    ],
    "sg:phone":"+1 317 280 8007",
    "sg:postcode":"46278",
    "sg:province":"IN",
    "sg:tags":[
        "convention",
        "meeting",
        "facility"
    ],
    "wof:name":"Idea Center-Herron Assoc",
    "wof:placetype":"venue"
},
  "geometry": {"coordinates":[-86.266162,39.876692],"type":"Point"}
}