{
  "type": "Feature",
  "properties": {
    "addr:full":"6590 E Co Rd 1000 N Brownsburg IN 46112",
    "addr:housenumber":"6590",
    "addr:postcode":"46112",
    "addr:street":"E Co Rd 1000 N",
    "iso:country":"US",
    "sg:address":"6590 E Co Rd 1000 N",
    "sg:city":"Brownsburg",
    "sg:classifiers":[
        {
            "category":"Organizations",
            "subcategory":"Religious Organization",
            "type":"Services"
        }
    ],
    "sg:phone":"+1 317 892 4876",
    "sg:postcode":"46112",
    "sg:province":"IN",
    "sg:tags":[
        "church"
    ],
    "wof:name":"Countryside Community Church",
    "wof:placetype":"venue"
},
  "geometry": {"coordinates":[-86.400094,39.90923],"type":"Point"}
}