{
  "type": "Feature",
  "properties": {
    "addr:full":"4830 Jean Dr Fort Wayne IN 46825",
    "addr:housenumber":"4830",
    "addr:postcode":"46825",
    "addr:street":"Jean Dr",
    "iso:country":"US",
    "sg:address":"4830 Jean Dr",
    "sg:city":"Fort Wayne",
    "sg:classifiers":[
        {
            "category":"Building & Trades",
            "subcategory":"Construction",
            "type":"Services"
        }
    ],
    "sg:phone":"+1 260 492 8585",
    "sg:postcode":"46825",
    "sg:province":"IN",
    "sg:tags":[
        "elevator"
    ],
    "wof:name":"Alternative Elevator Svc",
    "wof:placetype":"venue"
},
  "geometry": {"coordinates":[-85.14070599999999,41.122166],"type":"Point"}
}