{
  "type": "Feature",
  "properties": {
    "addr:full":"100 Growth Pkwy Angola IN 46703",
    "addr:housenumber":"100",
    "addr:postcode":"46703",
    "addr:street":"Growth Pkwy",
    "iso:country":"US",
    "sg:address":"100 Growth Pkwy",
    "sg:city":"Angola",
    "sg:classifiers":[
        {
            "category":"Banks & Credit Unions",
            "subcategory":"Bank",
            "type":"Services"
        }
    ],
    "sg:phone":"+1 260 668 8845",
    "sg:postcode":"46703",
    "sg:province":"IN",
    "wof:name":"Fifth Third Bank",
    "wof:placetype":"venue"
},
  "geometry": {"coordinates":[-84.99963,41.665667],"type":"Point"}
}