{
  "type": "Feature",
  "properties": {
    "addr:full":"725 S Main St Kokomo IN 46901",
    "addr:housenumber":"725",
    "addr:postcode":"46901",
    "addr:street":"S Main St",
    "iso:country":"US",
    "sg:address":"725 S Main St",
    "sg:city":"Kokomo",
    "sg:classifiers":[
        {
            "category":"Retail",
            "subcategory":"Funeral Services",
            "type":"Services"
        }
    ],
    "sg:phone":"+1 765 457 6644",
    "sg:postcode":"46901",
    "sg:province":"IN",
    "sg:tags":[
        "director"
    ],
    "wof:name":"Ellers Mortuary",
    "wof:placetype":"venue"
},
  "geometry": {"coordinates":[-86.13117,40.479829],"type":"Point"}
}