{
  "type": "Feature",
  "properties": {
    "addr:full":"12400 N Meridian St Carmel IN 46032",
    "addr:housenumber":"12400",
    "addr:postcode":"46032",
    "addr:street":"N Meridian St",
    "iso:country":"US",
    "sg:address":"12400 N Meridian St",
    "sg:city":"Carmel",
    "sg:classifiers":[
        {
            "category":"Professional",
            "subcategory":"Engineering",
            "type":"Services"
        },
        {
            "category":"Building & Trades",
            "subcategory":"Plumbing",
            "type":"Services"
        }
    ],
    "sg:phone":"+1 317 848 5045",
    "sg:postcode":"46032",
    "sg:province":"IN",
    "sg:tags":[
        "consulting",
        "engineer",
        "electrical",
        "mechanical"
    ],
    "sg:website":"http://www.moore-engineers.com",
    "wof:name":"Moore Engineers",
    "wof:placetype":"venue"
},
  "geometry": {"coordinates":[-86.158841,39.970794],"type":"Point"}
}