{
  "type": "Feature",
  "properties": {
    "iso:country":"US",
    "sg:address":"125 N Weinbach Ave",
    "sg:city":"Evansville",
    "sg:classifiers":[
        {
            "category":"Banks & Credit Unions",
            "subcategory":"Bank",
            "type":"Services"
        }
    ],
    "sg:phone":"+1 812 475 0500",
    "sg:postcode":"47711",
    "sg:province":"IN",
    "sg:tags":[
        "loan"
    ],
    "sg:website":"www.loans-unlimited.com",
    "wof:name":"Loans Unlimited",
    "wof:placetype":"venue"
},
  "geometry": {"coordinates":[-87.52933,37.977162],"type":"Point"}
}