{
  "type": "Feature",
  "properties": {
    "iso:country":"US",
    "sg:address":"5320 W 96th St",
    "sg:city":"Indianapolis",
    "sg:classifiers":[
        {
            "category":"Professional",
            "subcategory":"Management & Consulting",
            "type":"Services"
        }
    ],
    "sg:phone":"+1 317 733 2388",
    "sg:postcode":"46268",
    "sg:province":"IN",
    "sg:tags":[
        "consultant"
    ],
    "wof:name":"Promethius Consulting LLC",
    "wof:placetype":"venue"
},
  "geometry": {"coordinates":[-86.249461,39.925732],"type":"Point"}
}