{
  "type": "Feature",
  "properties": {
    "iso:country":"US",
    "sg:address":"6205 Rucker Rd",
    "sg:city":"Indianapolis",
    "sg:classifiers":[
        {
            "category":"Personal",
            "type":"Services"
        },
        {
            "category":"Sports & Exercise",
            "subcategory":"Gym",
            "type":"Entertainment"
        }
    ],
    "sg:phone":"+1 317 282 0325",
    "sg:postcode":"46220",
    "sg:province":"IN",
    "sg:tags":[
        "trainer",
        "consultant",
        "program",
        "physical",
        "fitness"
    ],
    "sg:website":"http://indianapolis.citysearch.com/profile/external/603957562/inpolis_in/jazzercise_inpolis_church_of_the_saviour_united_methodist.html?publisher=yellowpages&reference_id=1&placement=ypwebsitemip",
    "wof:name":"Jazzercise Inpolis Church Of The Saviour United Methodist",
    "wof:placetype":"venue"
},
  "geometry": {"coordinates":[-86.079353,39.868742],"type":"Point"}
}