{
  "type": "Feature",
  "properties": {
    "iso:country":"US",
    "sg:address":"214 E South St",
    "sg:city":"Remington",
    "sg:classifiers":[
        {
            "category":"Real Estate",
            "subcategory":"Real Estate Operator",
            "type":"Services"
        }
    ],
    "sg:phone":"+1 219 261 2926",
    "sg:postcode":"47977",
    "sg:province":"IN",
    "sg:tags":[
        "property",
        "lessor"
    ],
    "wof:name":"Gwendolyn Lehe",
    "wof:placetype":"venue"
},
  "geometry": {"coordinates":[-87.14803999999999,40.759685],"type":"Point"}
}