{
  "type": "Feature",
  "properties": {
    "iso:country":"US",
    "sg:address":"1326 N Weinbach Ave",
    "sg:city":"Evansville",
    "sg:classifiers":[
        {
            "category":"Banks & Credit Unions",
            "subcategory":"Bank",
            "type":"Services"
        }
    ],
    "sg:phone":"+1 812 402 5626",
    "sg:postcode":"47711",
    "sg:province":"IN",
    "sg:tags":[
        "loan",
        "real estate"
    ],
    "wof:name":"First Financial Mortgage",
    "wof:placetype":"venue"
},
  "geometry": {"coordinates":[-87.529246,37.991437],"type":"Point"}
}