{
  "type": "Feature",
  "properties": {
    "iso:country":"US",
    "sg:address":"2502 Marquette Circle North Dr",
    "sg:city":"Indianapolis",
    "sg:classifiers":[
        {
            "category":"Professional",
            "subcategory":"Lawyer & Legal Services",
            "type":"Services"
        }
    ],
    "sg:phone":"+1 317 802 9525",
    "sg:postcode":"46268",
    "sg:province":"IN",
    "sg:tags":[
        "attorney"
    ],
    "wof:name":"Ayres Carr & Sullivan",
    "wof:placetype":"venue"
},
  "geometry": {"coordinates":[-86.203954,39.904165],"type":"Point"}
}