{
  "type": "Feature",
  "properties": {
    "iso:country":"US",
    "sg:address":"1111 W 17th St",
    "sg:city":"Bloomington",
    "sg:classifiers":[
        {
            "category":"Social Services",
            "type":"Services"
        }
    ],
    "sg:phone":"+1 812 961 0080",
    "sg:postcode":"47404",
    "sg:province":"IN",
    "sg:tags":[
        "counseling"
    ],
    "wof:name":"City On A Hill",
    "wof:placetype":"venue"
},
  "geometry": {"coordinates":[-86.548865,39.178998],"type":"Point"}
}