{
  "type": "Feature",
  "properties": {
    "iso:country":"US",
    "sg:address":"2510 S Airport Rd",
    "sg:city":"Monticello",
    "sg:classifiers":[
        {
            "category":"Building & Trades",
            "subcategory":"Landscaping Services",
            "type":"Services"
        }
    ],
    "sg:phone":"+1 574 583 8821",
    "sg:postcode":"47960",
    "sg:province":"IN",
    "sg:tags":[
        "landscape",
        "contractor"
    ],
    "wof:name":"Terry's Lawn Care Svc",
    "wof:placetype":"venue"
},
  "geometry": {"coordinates":[-86.763103,40.715407],"type":"Point"}
}