{
  "type": "Feature",
  "properties": {
    "iso:country":"US",
    "sg:address":"100 E Washington Blvd",
    "sg:city":"Fort Wayne",
    "sg:classifiers":[
        {
            "category":"Government",
            "subcategory":"Office",
            "type":"Public Place"
        }
    ],
    "sg:phone":"+1 260 427 1256",
    "sg:postcode":"46802",
    "sg:province":"IN",
    "sg:tags":[
        "village"
    ],
    "wof:name":"Fort Wayne Civic Ctr Parking",
    "wof:placetype":"venue"
},
  "geometry": {"coordinates":[-85.137486,41.077488],"type":"Point"}
}