{
  "type": "Feature",
  "properties": {
    "addr:full":"5215 Millwright Pl Fort Wayne IN 46835",
    "addr:postcode":"5215;46835",
    "addr:street":"Millwright Pl",
    "iso:country":"US",
    "sg:address":"5215 Millwright Pl",
    "sg:city":"Fort Wayne",
    "sg:classifiers":[
        {
            "category":"Building & Trades",
            "subcategory":"Landscaping Services",
            "type":"Services"
        }
    ],
    "sg:phone":"+1 260 485 5405",
    "sg:postcode":"46835",
    "sg:province":"IN",
    "wof:name":"Stagreen",
    "wof:placetype":"venue"
},
  "geometry": {"coordinates":[-85.01922399999999,41.130142],"type":"Point"}
}