{
  "type": "Feature",
  "properties": {
    "iso:country":"US",
    "sg:address":"8520 Kennedy Ave",
    "sg:city":"Highland",
    "sg:classifiers":[
        {
            "category":"Building & Trades",
            "subcategory":"Plumbing",
            "type":"Services"
        }
    ],
    "sg:phone":"+1 219 923 3968",
    "sg:postcode":"46322",
    "sg:province":"IN",
    "sg:tags":[
        "heating",
        "contractor"
    ],
    "wof:name":"Mendoza Heating & Air Cond",
    "wof:placetype":"venue"
},
  "geometry": {"coordinates":[-87.461725,41.56002],"type":"Point"}
}