{
  "type": "Feature",
  "properties": {
    "iso:country":"US",
    "sg:address":"50601 Hedgewood Ct",
    "sg:city":"Granger",
    "sg:classifiers":[
        {
            "category":"Professional",
            "subcategory":"Business Services",
            "type":"Services"
        }
    ],
    "sg:phone":"+1 574 533 1090",
    "sg:postcode":"46530",
    "sg:province":"IN",
    "wof:name":"Hensel Assoc Inc",
    "wof:placetype":"venue"
},
  "geometry": {"coordinates":[-86.150324,41.759127],"type":"Point"}
}