{
  "type": "Feature",
  "properties": {
    "iso:country":"US",
    "sg:address":"200 E 89th Ave",
    "sg:city":"Merrillville",
    "sg:classifiers":[
        {
            "category":"Health Services",
            "subcategory":"Doctor",
            "type":"Services"
        }
    ],
    "sg:phone":"+1 219 791 1555",
    "sg:postcode":"46410",
    "sg:province":"IN",
    "sg:tags":[
        "physician",
        "surgeon"
    ],
    "wof:name":"Nephrology Associates Of N In",
    "wof:placetype":"venue"
},
  "geometry": {"coordinates":[-87.332233,41.457305],"type":"Point"}
}