{
  "type": "Feature",
  "properties": {
    "addr:full":"7950 Hwy 135 NE New Salisbury IN 47161",
    "addr:housenumber":"7950",
    "addr:postcode":"47161",
    "addr:street":"Hwy 135 Ne New",
    "iso:country":"US",
    "sg:address":"7950 Hwy 135 NE",
    "sg:city":"New Salisbury",
    "sg:classifiers":[
        {
            "category":"Banks & Credit Unions",
            "subcategory":"Bank",
            "type":"Services"
        }
    ],
    "sg:phone":"+1 812 347 2455",
    "sg:postcode":"47161",
    "sg:province":"IN",
    "wof:name":"Regions",
    "wof:placetype":"venue"
},
  "geometry": {"coordinates":[-86.094657,38.316145],"type":"Point"}
}