{
  "type": "Feature",
  "properties": {
    "iso:country":"US",
    "sg:address":"218 N College St",
    "sg:city":"Rockville",
    "sg:classifiers":[
        {
            "category":"Retail",
            "subcategory":"Funeral Services",
            "type":"Services"
        }
    ],
    "sg:phone":"+1 765 569 5222",
    "sg:postcode":"47872",
    "sg:province":"IN",
    "sg:tags":[
        "director"
    ],
    "wof:name":"Butler Funeral Home",
    "wof:placetype":"venue"
},
  "geometry": {"coordinates":[-87.234152,39.763792],"type":"Point"}
}