{
  "type": "Feature",
  "properties": {
    "iso:country":"US",
    "sg:address":"23902 Himebaugh Ave",
    "sg:city":"Elkhart",
    "sg:classifiers":[
        {
            "category":"Building & Trades",
            "subcategory":"Plumbing",
            "type":"Services"
        }
    ],
    "sg:phone":"+1 574 875 1035",
    "sg:postcode":"46516",
    "sg:province":"IN",
    "sg:tags":[
        "sewer",
        "cleaning",
        "drain"
    ],
    "wof:name":"Easy Clean Sewer & Drain Svc",
    "wof:placetype":"venue"
},
  "geometry": {"coordinates":[-85.925403,41.643868],"type":"Point"}
}