{
  "type": "Feature",
  "properties": {
    "iso:country":"US",
    "sg:address":"105 S Franklin St",
    "sg:city":"Greensburg",
    "sg:classifiers":[
        {
            "category":"Real Estate",
            "subcategory":"Real Estate Operator",
            "type":"Services"
        }
    ],
    "sg:phone":"+1 812 663 5576",
    "sg:postcode":"47240",
    "sg:province":"IN",
    "sg:tags":[
        "apartment"
    ],
    "wof:name":"Decatur Apartments",
    "wof:placetype":"venue"
},
  "geometry": {"coordinates":[-85.48284700000001,39.33655],"type":"Point"}
}