{
  "type": "Feature",
  "properties": {
    "iso:country":"US",
    "sg:address":"5430 Green Rd",
    "sg:city":"New Haven",
    "sg:classifiers":[
        {
            "category":"Professional",
            "subcategory":"Management & Consulting",
            "type":"Services"
        }
    ],
    "sg:phone":"+1 260 749 7226",
    "sg:postcode":"46774",
    "sg:province":"IN",
    "wof:name":"Holt Pam One To One",
    "wof:placetype":"venue"
},
  "geometry": {"coordinates":[-85.010699,41.045343],"type":"Point"}
}