{
  "type": "Feature",
  "properties": {
    "iso:country":"US",
    "sg:address":"2927 Colerain Dr",
    "sg:city":"Indianapolis",
    "sg:classifiers":[
        {
            "category":"Building & Trades",
            "subcategory":"Construction",
            "type":"Services"
        }
    ],
    "sg:phone":"+1 317 924 9454",
    "sg:postcode":"46222",
    "sg:province":"IN",
    "sg:tags":[
        "concrete",
        "contractor"
    ],
    "wof:name":"Jamison Concrete Svc Inc",
    "wof:placetype":"venue"
},
  "geometry": {"coordinates":[-86.210701,39.80303],"type":"Point"}
}