{
  "type": "Feature",
  "properties": {
    "iso:country":"US",
    "sg:address":"4152 W 100 N",
    "sg:city":"Huntington",
    "sg:classifiers":[
        {
            "category":"Building & Trades",
            "subcategory":"Construction",
            "type":"Services"
        }
    ],
    "sg:phone":"+1 260 356 2534",
    "sg:postcode":"46750",
    "sg:province":"IN",
    "sg:tags":[
        "excavation",
        "contractor"
    ],
    "wof:name":"Bickel Excavating",
    "wof:placetype":"venue"
},
  "geometry": {"coordinates":[-85.530582,40.84412],"type":"Point"}
}