{
  "type": "Feature",
  "properties": {
    "iso:country":"US",
    "sg:address":"3302 S Adams St",
    "sg:city":"Marion",
    "sg:classifiers":[
        {
            "category":"Restaurant",
            "type":"Food & Drink"
        }
    ],
    "sg:phone":"+1 765 674 8323",
    "sg:postcode":"46953",
    "sg:province":"IN",
    "wof:name":"Carey's Restaurant",
    "wof:placetype":"venue"
},
  "geometry": {"coordinates":[-85.658599,40.529256],"type":"Point"}
}