{
  "type": "Feature",
  "properties": {
    "iso:country":"US",
    "sg:address":"8440 N Michigan Rd",
    "sg:city":"Indianapolis",
    "sg:classifiers":[
        {
            "category":"Home & Garden",
            "subcategory":"Building Materials",
            "type":"Retail Goods"
        }
    ],
    "sg:phone":"+1 317 875 6885",
    "sg:postcode":"46268",
    "sg:province":"IN",
    "sg:tags":[
        "center"
    ],
    "wof:name":"Lowe's",
    "wof:placetype":"venue"
},
  "geometry": {"coordinates":[-86.22120099999999,39.908236],"type":"Point"}
}