{
  "type": "Feature",
  "properties": {
    "addr:full":"1058 W Market St Nappanee IN 46550",
    "addr:housenumber":"1058",
    "addr:postcode":"46550",
    "addr:street":"W Market St",
    "iso:country":"US",
    "sg:address":"1058 W Market St",
    "sg:city":"Nappanee",
    "sg:classifiers":[
        {
            "category":"Restaurant",
            "type":"Food & Drink"
        }
    ],
    "sg:phone":"+1 574 773 2856",
    "sg:postcode":"46550",
    "sg:province":"IN",
    "sg:tags":[
        "eating"
    ],
    "wof:name":"Nangs Chinese Restaurant LLC",
    "wof:placetype":"venue"
},
  "geometry": {"coordinates":[-86.01245299999999,41.442773],"type":"Point"}
}