{
  "type": "Feature",
  "properties": {
    "iso:country":"US",
    "sg:address":"4811 S High School Rd",
    "sg:city":"Indianapolis",
    "sg:classifiers":[
        {
            "category":"Food & Beverages",
            "subcategory":"Groceries & Convenience Stores",
            "type":"Retail Goods"
        }
    ],
    "sg:phone":"+1 317 821 1165",
    "sg:postcode":"46221",
    "sg:province":"IN",
    "sg:tags":[
        "product"
    ],
    "wof:name":"Quality Foods Inc",
    "wof:placetype":"venue"
},
  "geometry": {"coordinates":[-86.269315,39.692855],"type":"Point"}
}