{
  "type": "Feature",
  "properties": {
    "addr:full":"3388 Libbert Rd Newburgh IN 47630",
    "addr:housenumber":"3388",
    "addr:postcode":"47630",
    "addr:street":"Libbert Rd",
    "iso:country":"US",
    "sg:address":"3388 Libbert Rd",
    "sg:city":"Newburgh",
    "sg:classifiers":[
        {
            "category":"Retail",
            "subcategory":"Auto Repair",
            "type":"Services"
        }
    ],
    "sg:phone":"+1 812 853 7965",
    "sg:postcode":"47630",
    "sg:province":"IN",
    "sg:tags":[
        "general"
    ],
    "wof:name":"Loehr Brothers Garage",
    "wof:placetype":"venue"
},
  "geometry": {"coordinates":[-87.41374399999999,37.989512],"type":"Point"}
}