{
  "type": "Feature",
  "properties": {
    "iso:country":"US",
    "sg:address":"207 N Prettyman St",
    "sg:city":"Knox",
    "sg:classifiers":[
        {
            "category":"Organizations",
            "subcategory":"Religious Organization",
            "type":"Services"
        }
    ],
    "sg:phone":"+1 574 772 4640",
    "sg:postcode":"46534",
    "sg:province":"IN",
    "sg:tags":[
        "church"
    ],
    "wof:name":"Romanian Pentecostal Church",
    "wof:placetype":"venue"
},
  "geometry": {"coordinates":[-86.619545,41.300146],"type":"Point"}
}