{
  "type": "Feature",
  "properties": {
    "iso:country":"US",
    "sg:address":"3 W 79th St",
    "sg:city":"Indianapolis",
    "sg:classifiers":[
        {
            "category":"Real Estate",
            "subcategory":"Real Estate Agent",
            "type":"Services"
        }
    ],
    "sg:phone":"+1 317 259 0001",
    "sg:postcode":"46260",
    "sg:province":"IN",
    "wof:name":"George Sior Charbonneau",
    "wof:placetype":"venue"
},
  "geometry": {"coordinates":[-86.159168,39.898664],"type":"Point"}
}