{
  "type": "Feature",
  "properties": {
    "iso:country":"US",
    "sg:address":"616 McKinnie Ave",
    "sg:city":"Fort Wayne",
    "sg:classifiers":[
        {
            "category":"Personal",
            "subcategory":"Beauty Salon",
            "type":"Services"
        }
    ],
    "sg:phone":"+1 260 456 1106",
    "sg:postcode":"46806",
    "sg:province":"IN",
    "wof:name":"Sweet Impressions Hair & Nails",
    "wof:placetype":"venue"
},
  "geometry": {"coordinates":[-85.127698,41.0461],"type":"Point"}
}