{
  "type": "Feature",
  "properties": {
    "iso:country":"US",
    "sg:address":"10702 Willow Creek Dr",
    "sg:city":"Fort Wayne",
    "sg:classifiers":[
        {
            "category":"Building & Trades",
            "subcategory":"Construction",
            "type":"Services"
        }
    ],
    "sg:phone":"+1 260 760 2935",
    "sg:postcode":"46845",
    "sg:province":"IN",
    "sg:tags":[
        "hanging",
        "contractor"
    ],
    "wof:name":"Kent Greer Painting",
    "wof:placetype":"venue"
},
  "geometry": {"coordinates":[-85.060654,41.183327],"type":"Point"}
}