{
  "type": "Feature",
  "properties": {
    "iso:country":"US",
    "sg:address":"1480 14th St",
    "sg:city":"Columbus",
    "sg:classifiers":[
        {
            "category":"Manufacturing",
            "subcategory":"Tools & Machinery",
            "type":"Manufacturing & Wholesale Goods"
        }
    ],
    "sg:phone":"+1 812 372 4421",
    "sg:postcode":"47201",
    "sg:province":"IN",
    "sg:tags":[
        "die",
        "maker"
    ],
    "wof:name":"Product Engineering Co",
    "wof:placetype":"venue"
},
  "geometry": {"coordinates":[-85.909639,39.212352],"type":"Point"}
}