{
  "type": "Feature",
  "properties": {
    "iso:country":"US",
    "sg:address":"4113 National Rd W",
    "sg:city":"Richmond",
    "sg:classifiers":[
        {
            "category":"Building & Trades",
            "subcategory":"Construction",
            "type":"Services"
        }
    ],
    "sg:phone":"+1 765 962 8833",
    "sg:postcode":"47374",
    "sg:province":"IN",
    "sg:tags":[
        "general",
        "contractor"
    ],
    "wof:name":"Dickenson Homes Inc",
    "wof:placetype":"venue"
},
  "geometry": {"coordinates":[-84.955688,39.821114],"type":"Point"}
}