{
  "type": "Feature",
  "properties": {
    "iso:country":"US",
    "sg:address":"6782 N Wahoo Tree St",
    "sg:city":"Terre Haute",
    "sg:classifiers":[
        {
            "category":"Building & Trades",
            "subcategory":"Cleaning & Sanitation",
            "type":"Services"
        }
    ],
    "sg:phone":"+1 812 460 4180",
    "sg:postcode":"47805",
    "sg:province":"IN",
    "sg:tags":[
        "janitor"
    ],
    "wof:name":"Clean Sweep",
    "wof:placetype":"venue"
},
  "geometry": {"coordinates":[-87.365628,39.548574],"type":"Point"}
}