{
  "type": "Feature",
  "properties": {
    "iso:country":"US",
    "sg:address":"6020 E 82nd St",
    "sg:city":"Indianapolis",
    "sg:classifiers":[
        {
            "category":"Shopping",
            "subcategory":"Computers & Home Electronics",
            "type":"Retail Goods"
        }
    ],
    "sg:phone":"+1 317 845 8803",
    "sg:postcode":"46250",
    "sg:province":"IN",
    "sg:tags":[
        "game",
        "video"
    ],
    "wof:name":"Electronics Boutique",
    "wof:placetype":"venue"
},
  "geometry": {"coordinates":[-86.063558,39.905357],"type":"Point"}
}