{
  "type": "Feature",
  "properties": {
    "iso:country":"US",
    "sg:address":"4978 Limberlost Trce",
    "sg:city":"Carmel",
    "sg:classifiers":[
        {
            "category":"Professional",
            "subcategory":"Engineering",
            "type":"Services"
        }
    ],
    "sg:phone":"+1 317 574 9546",
    "sg:postcode":"46033",
    "sg:province":"IN",
    "sg:tags":[
        "engineer"
    ],
    "wof:name":"Seneca Consulting",
    "wof:placetype":"venue"
},
  "geometry": {"coordinates":[-86.085157,39.977013],"type":"Point"}
}