{
  "type": "Feature",
  "properties": {
    "iso:country":"US",
    "sg:address":"4475 Darwin Rd",
    "sg:city":"West Terre Haute",
    "sg:classifiers":[
        {
            "category":"Manufacturing",
            "subcategory":"Electronics",
            "type":"Manufacturing & Wholesale Goods"
        }
    ],
    "sg:phone":"+1 812 533 9449",
    "sg:postcode":"47885",
    "sg:province":"IN",
    "sg:tags":[
        "retail",
        "coating",
        "powder"
    ],
    "wof:name":"Speed Shop Inc",
    "wof:placetype":"venue"
},
  "geometry": {"coordinates":[-87.493231,39.422504],"type":"Point"}
}