{
  "type": "Feature",
  "properties": {
    "iso:country":"US",
    "sg:address":"5212 W State Rd 56",
    "sg:city":"Jasper",
    "sg:classifiers":[
        {
            "category":"Retail",
            "subcategory":"Auto Repair",
            "type":"Services"
        }
    ],
    "sg:phone":"+1 812 482 7616",
    "sg:postcode":"47546",
    "sg:province":"IN",
    "sg:tags":[
        "repairing",
        "automobile"
    ],
    "wof:name":"Bob's Auto Svc",
    "wof:placetype":"venue"
},
  "geometry": {"coordinates":[-87.002781,38.416238],"type":"Point"}
}