{
  "type": "Feature",
  "properties": {
    "addr:full":"5350 Elmwood Ave Indianapolis IN 46203",
    "addr:housenumber":"5350",
    "addr:postcode":"46203",
    "addr:street":"Elmwood Ave",
    "iso:country":"US",
    "sg:address":"5350 Elmwood Ave",
    "sg:city":"Indianapolis",
    "sg:classifiers":[
        {
            "category":"Autos & Motor Vehicles",
            "subcategory":"Auto Supplies",
            "type":"Retail Goods"
        },
        {
            "category":"Wholesale",
            "subcategory":"Electrical",
            "type":"Manufacturing & Wholesale Goods"
        },
        {
            "category":"Wholesale",
            "subcategory":"Auto Parts",
            "type":"Manufacturing & Wholesale Goods"
        }
    ],
    "sg:phone":"+1 317 783 2301",
    "sg:postcode":"46203",
    "sg:province":"IN",
    "sg:tags":[
        "battery",
        "automobile",
        "accessory",
        "equipment",
        "truck",
        "engines-supplies"
    ],
    "sg:website":"http://ad.doubleclick.net/clk;221862232;45455595;j?http://www.carquest.com/carquest/store_locator.html",
    "wof:name":"CARQUEST Auto Parts",
    "wof:placetype":"venue"
},
  "geometry": {"coordinates":[-86.07663700000001,39.705609],"type":"Point"}
}