{
  "type": "Feature",
  "properties": {
    "iso:country":"US",
    "sg:address":"2420 E 146th St",
    "sg:city":"Carmel",
    "sg:classifiers":[
        {
            "category":"Restaurant",
            "type":"Food & Drink"
        }
    ],
    "sg:phone":"+1 317 816 0033",
    "sg:postcode":"46033",
    "sg:province":"IN",
    "sg:tags":[
        "mexican"
    ],
    "sg:website":"www.chipotle.com",
    "wof:name":"Chipotle",
    "wof:placetype":"venue"
},
  "geometry": {"coordinates":[-86.118956,40.000826],"type":"Point"}
}