{
  "type": "Feature",
  "properties": {
    "iso:country":"US",
    "sg:address":"14489 US Hwy 20",
    "sg:city":"Middlebury",
    "sg:classifiers":[
        {
            "category":"Wholesale",
            "subcategory":"Motor Vehicles",
            "type":"Manufacturing & Wholesale Goods"
        }
    ],
    "sg:phone":"+1 574 825 8686",
    "sg:postcode":"46540",
    "sg:province":"IN",
    "sg:tags":[
        "recreational"
    ],
    "sg:website":"www.pilgriminternational.com",
    "wof:name":"Pilgrim International Inc",
    "wof:placetype":"venue"
},
  "geometry": {"coordinates":[-85.744556,41.668087],"type":"Point"}
}