{
  "type": "Feature",
  "properties": {
    "iso:country":"US",
    "sg:address":"11440 US Hwy 231 S",
    "sg:city":"Romney",
    "sg:classifiers":[
        {
            "category":"Government",
            "subcategory":"Post Office",
            "type":"Public Place"
        }
    ],
    "sg:phone":"+1 765 538 2860",
    "sg:postcode":"47981",
    "sg:province":"IN",
    "wof:name":"US Post Office",
    "wof:placetype":"venue"
},
  "geometry": {"coordinates":[-86.903868,40.252257],"type":"Point"}
}