{
  "type": "Feature",
  "properties": {
    "addr:full":"2805 E 96th St Indianapolis IN 46240",
    "addr:housenumber":"2805",
    "addr:postcode":"46240",
    "addr:street":"E 96Th St",
    "iso:country":"US",
    "sg:address":"2805 E 96th St",
    "sg:city":"Indianapolis",
    "sg:classifiers":[
        {
            "category":"Real Estate",
            "subcategory":"Real Estate Agent",
            "type":"Services"
        }
    ],
    "sg:phone":"+1 317 819 0633",
    "sg:postcode":"46240",
    "sg:province":"IN",
    "sg:tags":[
        "inspection"
    ],
    "wof:name":"Meridian Inspection Group",
    "wof:placetype":"venue"
},
  "geometry": {"coordinates":[-86.115128,39.926829],"type":"Point"}
}