{
  "type": "Feature",
  "properties": {
    "iso:country":"US",
    "sg:address":"2255 Hayes Leonard Rd",
    "sg:city":"Valparaiso",
    "sg:classifiers":[
        {
            "category":"Insurance",
            "subcategory":"Insurance Agent",
            "type":"Services"
        }
    ],
    "sg:phone":"+1 219 462 9994",
    "sg:postcode":"46385",
    "sg:province":"IN",
    "wof:name":"Sandra Paulson",
    "wof:placetype":"venue"
},
  "geometry": {"coordinates":[-87.094752,41.455829],"type":"Point"}
}