{
  "type": "Feature",
  "properties": {
    "iso:country":"US",
    "sg:address":"7705 G Antony Dr-92",
    "sg:city":"Fort Wayne",
    "sg:classifiers":[
        {
            "category":"Professional",
            "type":"Services"
        }
    ],
    "sg:phone":"+1 260 625 6034",
    "sg:postcode":"46818",
    "sg:province":"IN",
    "wof:name":"KLR Svc Inc",
    "wof:placetype":"venue"
},
  "geometry": {"coordinates":[-85.341759,41.081634],"type":"Point"}
}