{
  "type": "Feature",
  "properties": {
    "iso:country":"US",
    "sg:address":"9609 Pioneer Trl",
    "sg:city":"Leo",
    "sg:classifiers":[
        {
            "category":"Retail",
            "subcategory":"Portrait Studio",
            "type":"Services"
        }
    ],
    "sg:phone":"+1 260 627 8167",
    "sg:postcode":"46765",
    "sg:province":"IN",
    "sg:tags":[
        "photo"
    ],
    "wof:name":"Stemen Stock Photos",
    "wof:placetype":"venue"
},
  "geometry": {"coordinates":[-85.022542,41.2171],"type":"Point"}
}