{
  "type": "Feature",
  "properties": {
    "iso:country":"US",
    "sg:address":"8400 N 400 E",
    "sg:city":"Kirklin",
    "sg:classifiers":[
        {
            "category":"Wholesale",
            "subcategory":"Auto Parts",
            "type":"Manufacturing & Wholesale Goods"
        }
    ],
    "sg:phone":"+1 765 325 2321",
    "sg:postcode":"46050",
    "sg:province":"IN",
    "sg:tags":[
        "automobile",
        "used"
    ],
    "wof:name":"Lowe Gary",
    "wof:placetype":"venue"
},
  "geometry": {"coordinates":[-86.394306,40.162641],"type":"Point"}
}