{
  "type": "Feature",
  "properties": {
    "iso:country":"US",
    "sg:address":"1531 Indianapolis Blvd",
    "sg:city":"Whiting",
    "sg:classifiers":[
        {
            "category":"Bagels",
            "type":"Food & Drink"
        },
        {
            "category":"Coffee & Tea",
            "type":"Food & Drink"
        },
        {
            "category":"Food & Beverages",
            "subcategory":"Bakery",
            "type":"Retail Goods"
        },
        {
            "category":"Bakery",
            "type":"Food & Drink"
        },
        {
            "category":"Donuts",
            "type":"Food & Drink"
        }
    ],
    "sg:menulink":"http://www.allmenus.com/in/north/133174-dunkin-donuts/menu/",
    "sg:phone":"+1 219 659 0232",
    "sg:postcode":"46394",
    "sg:province":"IN",
    "sg:tags":[
        "coffee",
        "tea",
        "american",
        "bagel",
        "bakery",
        "pastry"
    ],
    "wof:name":"Dunkin' Donuts",
    "wof:placetype":"venue"
},
  "geometry": {"coordinates":[-87.50528199999999,41.685429],"type":"Point"}
}