{
  "type": "Feature",
  "properties": {
    "iso:country":"US",
    "sg:address":"5094 State Rd 16",
    "sg:city":"Roann",
    "sg:classifiers":[
        {
            "category":"Freight",
            "type":"Transportation"
        }
    ],
    "sg:phone":"+1 765 833 5171",
    "sg:postcode":"46974",
    "sg:province":"IN",
    "sg:tags":[
        "yard",
        "stock"
    ],
    "wof:name":"United Producers",
    "wof:placetype":"venue"
},
  "geometry": {"coordinates":[-85.893002,40.913432],"type":"Point"}
}