{
  "type": "Feature",
  "properties": {
    "addr:full":"49 W Maryland St Indianapolis IN 46204",
    "addr:housenumber":"49",
    "addr:postcode":"46204",
    "addr:street":"W Maryland St",
    "iso:country":"US",
    "sg:address":"49 W Maryland St",
    "sg:city":"Indianapolis",
    "sg:classifiers":[
        {
            "category":"Shopping",
            "subcategory":"Luggage & Leather Goods",
            "type":"Retail Goods"
        }
    ],
    "sg:phone":"+1 317 269 0223",
    "sg:postcode":"46204",
    "sg:province":"IN",
    "wof:name":"Bag N Baggage",
    "wof:placetype":"venue"
},
  "geometry": {"coordinates":[-86.159267,39.765585],"type":"Point"}
}