{
  "type": "Feature",
  "properties": {
    "addr:full":"319 E Hendricks St Greensburg IN 47240",
    "addr:housenumber":"319",
    "addr:postcode":"47240",
    "addr:street":"E Hendricks St",
    "iso:country":"US",
    "sg:address":"319 E Hendricks St",
    "sg:city":"Greensburg",
    "sg:classifiers":[
        {
            "category":"Organizations",
            "subcategory":"Religious Organization",
            "type":"Services"
        }
    ],
    "sg:phone":"+1 812 663 5219",
    "sg:postcode":"47240",
    "sg:province":"IN",
    "wof:name":"Church Of Christ",
    "wof:placetype":"venue"
},
  "geometry": {"coordinates":[-85.48115,39.340897],"type":"Point"}
}