{
  "type": "Feature",
  "properties": {
    "iso:country":"US",
    "sg:address":"1927 N Cedar St",
    "sg:city":"Mishawaka",
    "sg:classifiers":[
        {
            "category":"Manufacturing",
            "subcategory":"Tools & Machinery",
            "type":"Manufacturing & Wholesale Goods"
        }
    ],
    "sg:phone":"+1 574 259 8622",
    "sg:postcode":"46545",
    "sg:province":"IN",
    "sg:tags":[
        "mold",
        "special"
    ],
    "wof:name":"Budco Tool & Die",
    "wof:placetype":"venue"
},
  "geometry": {"coordinates":[-86.171475,41.673857],"type":"Point"}
}