{
  "type": "Feature",
  "properties": {
    "iso:country":"US",
    "sg:address":"3161 Sumac Ct",
    "sg:city":"Columbus",
    "sg:classifiers":[
        {
            "category":"Insurance",
            "subcategory":"Insurance Agent",
            "type":"Services"
        }
    ],
    "sg:phone":"+1 812 376 0325",
    "sg:postcode":"47203",
    "sg:province":"IN",
    "wof:name":"Robert W Sprague",
    "wof:placetype":"venue"
},
  "geometry": {"coordinates":[-85.874044,39.23094],"type":"Point"}
}