{
  "type": "Feature",
  "properties": {
    "iso:country":"US",
    "sg:address":"9362 235th St",
    "sg:city":"Cicero",
    "sg:classifiers":[
        {
            "category":"Real Estate",
            "subcategory":"Real Estate Operator",
            "type":"Services"
        }
    ],
    "sg:phone":"+1 317 984 4071",
    "sg:postcode":"46034",
    "sg:province":"IN",
    "sg:tags":[
        "property",
        "lessor"
    ],
    "wof:name":"Mamie Flowers",
    "wof:placetype":"venue"
},
  "geometry": {"coordinates":[-86.002591,40.130675],"type":"Point"}
}