{
  "type": "Feature",
  "properties": {
    "iso:country":"US",
    "sg:address":"5422 W State Rte 62",
    "sg:city":"Boonville",
    "sg:classifiers":[
        {
            "category":"Personal",
            "subcategory":"Beauty Salon",
            "type":"Services"
        }
    ],
    "sg:phone":"+1 812 925 7722",
    "sg:postcode":"47601",
    "sg:province":"IN",
    "wof:name":"Mane-Tainer Hair & Nail Salon",
    "wof:placetype":"venue"
},
  "geometry": {"coordinates":[-87.34629,38.046749],"type":"Point"}
}