{
  "type": "Feature",
  "properties": {
    "iso:country":"US",
    "sg:address":"203 W Pearl St",
    "sg:city":"Batesville",
    "sg:classifiers":[
        {
            "category":"Recreation",
            "type":"Entertainment"
        }
    ],
    "sg:phone":"+1 812 934 0131",
    "sg:postcode":"47006",
    "sg:province":"IN",
    "sg:tags":[
        "paint",
        "ball",
        "sport"
    ],
    "wof:name":"Gotcha Covered Paintball II",
    "wof:placetype":"venue"
},
  "geometry": {"coordinates":[-85.2257,39.300111],"type":"Point"}
}