{
  "type": "Feature",
  "properties": {
    "addr:full":"2413 E 650 S Columbus IN 47201",
    "addr:housenumber":"2413",
    "addr:postcode":"47201",
    "addr:street":"E 650 S",
    "iso:country":"US",
    "sg:address":"2413 E 650 S",
    "sg:city":"Columbus",
    "sg:classifiers":[
        {
            "category":"Wholesale",
            "subcategory":"Machinery & Supplies",
            "type":"Manufacturing & Wholesale Goods"
        }
    ],
    "sg:phone":"+1 812 342 2816",
    "sg:postcode":"47201",
    "sg:province":"IN",
    "sg:tags":[
        "equipment",
        "industrial"
    ],
    "wof:name":"Industrial Sales Inc",
    "wof:placetype":"venue"
},
  "geometry": {"coordinates":[-85.90096,39.106174],"type":"Point"}
}