{
  "type": "Feature",
  "properties": {
    "iso:country":"US",
    "sg:address":"2624 E Jefferson St",
    "sg:city":"Warsaw",
    "sg:classifiers":[
        {
            "category":"Personal",
            "subcategory":"Tanning Parlor",
            "type":"Services"
        }
    ],
    "sg:phone":"+1 574 268 2826",
    "sg:postcode":"46580",
    "sg:province":"IN",
    "sg:tags":[
        "salon"
    ],
    "wof:name":"Maxx Tan 2 Inc",
    "wof:placetype":"venue"
},
  "geometry": {"coordinates":[-85.821256,41.23599],"type":"Point"}
}