{
  "type": "Feature",
  "properties": {
    "iso:country":"US",
    "sg:address":"4410 Wynbrooke Ct",
    "sg:city":"Newburgh",
    "sg:classifiers":[
        {
            "category":"Building & Trades",
            "subcategory":"Construction",
            "type":"Services"
        }
    ],
    "sg:phone":"+1 812 490 2699",
    "sg:postcode":"47630",
    "sg:province":"IN",
    "sg:tags":[
        "house"
    ],
    "wof:name":"Larry Doss Construction",
    "wof:placetype":"venue"
},
  "geometry": {"coordinates":[-87.429728,37.970439],"type":"Point"}
}