{
  "type": "Feature",
  "properties": {
    "iso:country":"US",
    "sg:address":"1221 S Kentucky Ave",
    "sg:city":"Evansville",
    "sg:classifiers":[
        {
            "category":"Social Services",
            "subcategory":"Child Care",
            "type":"Services"
        }
    ],
    "sg:phone":"+1 812 402 3508",
    "sg:postcode":"47714",
    "sg:province":"IN",
    "wof:name":"Angels Of The Night Child Care",
    "wof:placetype":"venue"
},
  "geometry": {"coordinates":[-87.54794099999999,37.95942],"type":"Point"}
}