{
  "type": "Feature",
  "properties": {
    "iso:country":"US",
    "sg:address":"6101 Flightline Dr",
    "sg:city":"Evansville",
    "sg:classifiers":[
        {
            "category":"Retail",
            "subcategory":"Auto Rental",
            "type":"Services"
        }
    ],
    "sg:phone":"+1 812 434 0069",
    "sg:postcode":"47711",
    "sg:province":"IN",
    "sg:tags":[
        "renting",
        "automobile"
    ],
    "wof:name":"Enterprise Rent-A-Car",
    "wof:placetype":"venue"
},
  "geometry": {"coordinates":[-87.538197,38.034498],"type":"Point"}
}