{
  "type": "Feature",
  "properties": {
    "iso:country":"US",
    "sg:address":"2793 Maplecrest Rd",
    "sg:city":"Fort Wayne",
    "sg:classifiers":[
        {
            "category":"Real Estate",
            "subcategory":"Real Estate Agent",
            "type":"Services"
        }
    ],
    "sg:phone":"+1 260 485 4343",
    "sg:postcode":"46815",
    "sg:province":"IN",
    "wof:name":"Prestige Realtors GMAC",
    "wof:placetype":"venue"
},
  "geometry": {"coordinates":[-85.06040299999999,41.103225],"type":"Point"}
}