{
  "type": "Feature",
  "properties": {
    "addr:full":"991 Market St Charlestown IN 47111",
    "addr:housenumber":"991",
    "addr:postcode":"47111",
    "addr:street":"Market St",
    "iso:country":"US",
    "sg:address":"991 Market St",
    "sg:city":"Charlestown",
    "sg:classifiers":[
        {
            "category":"Shopping",
            "subcategory":"Department Store",
            "type":"Retail Goods"
        }
    ],
    "sg:phone":"+1 812 256 0273",
    "sg:postcode":"47111",
    "sg:province":"IN",
    "sg:tags":[
        "shop"
    ],
    "wof:name":"Family Dollar Store",
    "wof:placetype":"venue"
},
  "geometry": {"coordinates":[-85.669222,38.451244],"type":"Point"}
}