{
  "type": "Feature",
  "properties": {
    "addr:full":"5465 E Edgewood Ave Indianapolis IN 46237",
    "addr:housenumber":"5465",
    "addr:postcode":"46237",
    "addr:street":"E Edgewood Ave",
    "iso:country":"US",
    "sg:address":"5465 E Edgewood Ave",
    "sg:city":"Indianapolis",
    "sg:classifiers":[
        {
            "category":"Social Services",
            "subcategory":"Child Care",
            "type":"Services"
        }
    ],
    "sg:phone":"+1 317 783 5454",
    "sg:postcode":"46237",
    "sg:province":"IN",
    "wof:name":"Lil Hoppers Inc",
    "wof:placetype":"venue"
},
  "geometry": {"coordinates":[-86.072706,39.680754],"type":"Point"}
}