{
  "type": "Feature",
  "properties": {
    "iso:country":"US",
    "sg:address":"5502 Brookville Rd",
    "sg:city":"Indianapolis",
    "sg:classifiers":[
        {
            "category":"Shopping",
            "subcategory":"Tobacco",
            "type":"Retail Goods"
        }
    ],
    "sg:phone":"+1 317 354 0507",
    "sg:postcode":"46219",
    "sg:province":"IN",
    "sg:tags":[
        "cigarette",
        "cigar",
        "dealer"
    ],
    "wof:name":"Puff & Chew",
    "wof:placetype":"venue"
},
  "geometry": {"coordinates":[-86.070857,39.75948],"type":"Point"}
}