{
  "type": "Feature",
  "properties": {
    "iso:country":"US",
    "sg:address":"2844 Jarrett Dr",
    "sg:city":"Schererville",
    "sg:classifiers":[
        {
            "category":"Arts & Performance",
            "subcategory":"Theater",
            "type":"Entertainment"
        }
    ],
    "sg:phone":"+1 219 365 7027",
    "sg:postcode":"46375",
    "sg:province":"IN",
    "sg:tags":[
        "group"
    ],
    "wof:name":"Sensational Sounds Inc",
    "wof:placetype":"venue"
},
  "geometry": {"coordinates":[-87.46493700000001,41.471732],"type":"Point"}
}