{
  "type": "Feature",
  "properties": {
    "iso:country":"US",
    "sg:address":"10479 Vistula Rd",
    "sg:city":"Osceola",
    "sg:classifiers":[
        {
            "category":"Professional",
            "subcategory":"Management & Consulting",
            "type":"Services"
        }
    ],
    "sg:phone":"+1 574 674 9043",
    "sg:postcode":"46561",
    "sg:province":"IN",
    "sg:tags":[
        "educational"
    ],
    "wof:name":"Susan Cox",
    "wof:placetype":"venue"
},
  "geometry": {"coordinates":[-86.06895299999999,41.675694],"type":"Point"}
}