{
  "type": "Feature",
  "properties": {
    "addr:full":"1753 E 12th St Mishawaka IN 46544",
    "addr:housenumber":"1753",
    "addr:postcode":"46544",
    "addr:street":"E 12Th St",
    "iso:country":"US",
    "sg:address":"1753 E 12th St",
    "sg:city":"Mishawaka",
    "sg:classifiers":[
        {
            "category":"Personal",
            "subcategory":"Tanning Parlor",
            "type":"Services"
        },
        {
            "category":"Personal",
            "type":"Services"
        }
    ],
    "sg:phone":"+1 574 257 1636",
    "sg:postcode":"46544",
    "sg:province":"IN",
    "sg:tags":[
        "salon"
    ],
    "wof:name":"California Dreaming",
    "wof:placetype":"venue"
},
  "geometry": {"coordinates":[-86.148746,41.651264],"type":"Point"}
}