{
  "type": "Feature",
  "properties": {
    "iso:country":"US",
    "sg:address":"3356 W Deputy Pike Rd",
    "sg:city":"Madison",
    "sg:classifiers":[
        {
            "category":"Real Estate",
            "subcategory":"Real Estate Operator",
            "type":"Services"
        }
    ],
    "sg:phone":"+1 812 273 1218",
    "sg:postcode":"47250",
    "sg:province":"IN",
    "sg:tags":[
        "farm",
        "corn",
        "property",
        "soybean",
        "lessor"
    ],
    "wof:name":"Martin Schafer",
    "wof:placetype":"venue"
},
  "geometry": {"coordinates":[-85.449552,38.781975],"type":"Point"}
}