{
  "type": "Feature",
  "properties": {
    "iso:country":"US",
    "sg:address":"6 West Rd",
    "sg:city":"Chesterton",
    "sg:classifiers":[
        {
            "category":"Real Estate",
            "subcategory":"Real Estate Agent",
            "type":"Services"
        }
    ],
    "sg:phone":"+1 219 787 8268",
    "sg:postcode":"46304",
    "sg:province":"IN",
    "wof:name":"Dune Acres Real Estate",
    "wof:placetype":"venue"
},
  "geometry": {"coordinates":[-87.090523,41.650092],"type":"Point"}
}