{
  "type": "Feature",
  "properties": {
    "iso:country":"US",
    "sg:address":"4582 State Rd 62",
    "sg:city":"Hanover",
    "sg:classifiers":[
        {
            "category":"Building & Trades",
            "subcategory":"Plumbing",
            "type":"Services"
        }
    ],
    "sg:phone":"+1 812 866 5096",
    "sg:postcode":"47243",
    "sg:province":"IN",
    "sg:tags":[
        "heating",
        "contractor"
    ],
    "wof:name":"Higdon Heating & Air Inc",
    "wof:placetype":"venue"
},
  "geometry": {"coordinates":[-85.525394,38.671075],"type":"Point"}
}