{
  "type": "Feature",
  "properties": {
    "iso:country":"US",
    "sg:address":"4078 Lincoln St",
    "sg:city":"Gary",
    "sg:classifiers":[
        {
            "category":"Organizations",
            "subcategory":"Religious Organization",
            "type":"Services"
        }
    ],
    "sg:phone":"+1 219 884 1353",
    "sg:postcode":"46408",
    "sg:province":"IN",
    "sg:tags":[
        "church"
    ],
    "wof:name":"Whole Truth Gospel Tabernacle",
    "wof:placetype":"venue"
},
  "geometry": {"coordinates":[-87.353437,41.545589],"type":"Point"}
}