{
  "type": "Feature",
  "properties": {
    "iso:country":"US",
    "sg:address":"3130 S 14th St",
    "sg:city":"New Castle",
    "sg:classifiers":[
        {
            "category":"Insurance",
            "subcategory":"Insurance Agent",
            "type":"Services"
        }
    ],
    "sg:phone":"+1 765 529 7010",
    "sg:postcode":"47362",
    "sg:province":"IN",
    "wof:name":"State Farm Insurance",
    "wof:placetype":"venue"
},
  "geometry": {"coordinates":[-85.359577,39.902175],"type":"Point"}
}