{
  "type": "Feature",
  "properties": {
    "iso:country":"US",
    "sg:address":"707 Coliseum Blvd N",
    "sg:city":"Fort Wayne",
    "sg:classifiers":[
        {
            "category":"Recreation",
            "type":"Entertainment"
        }
    ],
    "sg:phone":"+1 260 426 4108",
    "sg:postcode":"46805",
    "sg:province":"IN",
    "sg:tags":[
        "range",
        "practice",
        "golf"
    ],
    "wof:name":"On Target Golf Ctr",
    "wof:placetype":"venue"
},
  "geometry": {"coordinates":[-85.087932,41.088615],"type":"Point"}
}