{
  "type": "Feature",
  "properties": {
    "iso:country":"US",
    "sg:address":"3539 N Clinton St",
    "sg:city":"Fort Wayne",
    "sg:classifiers":[
        {
            "category":"Wholesale",
            "subcategory":"Auto Parts",
            "type":"Manufacturing & Wholesale Goods"
        }
    ],
    "sg:phone":"+1 260 483 8102",
    "sg:postcode":"46805",
    "sg:province":"IN",
    "sg:tags":[
        "body",
        "automobile",
        "shop"
    ],
    "wof:name":"Automotive Color & Supply Corp",
    "wof:placetype":"venue"
},
  "geometry": {"coordinates":[-85.13682900000001,41.108981],"type":"Point"}
}