{
  "type": "Feature",
  "properties": {
    "iso:country":"US",
    "sg:address":"4519 E 82nd St",
    "sg:city":"Indianapolis",
    "sg:classifiers":[
        {
            "category":"Social Services",
            "subcategory":"Adult Care",
            "type":"Services"
        }
    ],
    "sg:phone":"+1 317 849 2244",
    "sg:postcode":"46250",
    "sg:province":"IN",
    "sg:tags":[
        "home",
        "residential"
    ],
    "wof:name":"Clearwater Commons Assisted",
    "wof:placetype":"venue"
},
  "geometry": {"coordinates":[-86.094313,39.906784],"type":"Point"}
}