{
  "type": "Feature",
  "properties": {
    "iso:country":"US",
    "sg:address":"1075 E Eads Pkwy",
    "sg:city":"Greendale",
    "sg:classifiers":[
        {
            "category":"Travel",
            "subcategory":"Hotels & Motels",
            "type":"Entertainment"
        }
    ],
    "sg:phone":"+1 812 537 1440",
    "sg:postcode":"47025",
    "sg:province":"IN",
    "sg:tags":[
        "building",
        "operator",
        "apartment"
    ],
    "wof:name":"Wishing Well Motel",
    "wof:placetype":"venue"
},
  "geometry": {"coordinates":[-84.841674,39.12213],"type":"Point"}
}