{
  "type": "Feature",
  "properties": {
    "iso:country":"US",
    "sg:address":"8402 Harcourt Rd",
    "sg:city":"Indianapolis",
    "sg:classifiers":[
        {
            "category":"Health Services",
            "subcategory":"Doctor",
            "type":"Services"
        }
    ],
    "sg:phone":"+1 317 338 5431",
    "sg:postcode":"46260",
    "sg:province":"IN",
    "sg:tags":[
        "physician",
        "surgeon"
    ],
    "wof:name":"St Vincent Primary Care",
    "wof:placetype":"venue"
},
  "geometry": {"coordinates":[-86.193977,39.908535],"type":"Point"}
}