{
  "type": "Feature",
  "properties": {
    "addr:full":"10666 Millard Dr St John IN 46373",
    "addr:housenumber":"10666",
    "addr:postcode":"46373",
    "addr:street":"Millard Dr St John",
    "iso:country":"US",
    "sg:address":"10666 Millard Dr",
    "sg:city":"St John",
    "sg:classifiers":[
        {
            "category":"Building & Trades",
            "subcategory":"Construction",
            "type":"Services"
        }
    ],
    "sg:phone":"+1 219 365 0153",
    "sg:postcode":"46373",
    "sg:province":"IN",
    "sg:tags":[
        "concrete",
        "contractor"
    ],
    "wof:name":"White's Custom Concrete",
    "wof:placetype":"venue"
},
  "geometry": {"coordinates":[-87.48854799999999,41.424265],"type":"Point"}
}