{
  "type": "Feature",
  "properties": {
    "iso:country":"US",
    "sg:address":"8501 E 56th St",
    "sg:city":"Indianapolis",
    "sg:classifiers":[
        {
            "category":"Health Services",
            "subcategory":"Health Practitioner",
            "type":"Services"
        }
    ],
    "sg:phone":"+1 317 621 3000",
    "sg:postcode":"46216",
    "sg:province":"IN",
    "sg:tags":[
        "therapist",
        "physical"
    ],
    "wof:name":"Hook Rehabilitation Outpatient",
    "wof:placetype":"venue"
},
  "geometry": {"coordinates":[-86.02008,39.855111],"type":"Point"}
}