{
  "type": "Feature",
  "properties": {
    "iso:country":"US",
    "sg:address":"616 S 1250 W",
    "sg:city":"Parker City",
    "sg:classifiers":[
        {
            "category":"Organizations",
            "subcategory":"Religious Organization",
            "type":"Services"
        }
    ],
    "sg:phone":"+1 765 468 8168",
    "sg:postcode":"47368",
    "sg:province":"IN",
    "sg:tags":[
        "church"
    ],
    "wof:name":"Windsor United Methodist",
    "wof:placetype":"venue"
},
  "geometry": {"coordinates":[-85.213025,40.154482],"type":"Point"}
}