{
  "type": "Feature",
  "properties": {
    "iso:country":"US",
    "sg:address":"2584 S Main St",
    "sg:city":"Vallonia",
    "sg:classifiers":[
        {
            "category":"Farming",
            "subcategory":"Farm",
            "type":"Manufacturing & Wholesale Goods"
        }
    ],
    "sg:phone":"+1 812 358 2143",
    "sg:postcode":"47281",
    "sg:province":"IN",
    "wof:name":"Burcham Farms",
    "wof:placetype":"venue"
},
  "geometry": {"coordinates":[-86.098147,38.843677],"type":"Point"}
}