{
  "type": "Feature",
  "properties": {
    "iso:country":"US",
    "sg:address":"1716 Elkhart Rd",
    "sg:city":"Goshen",
    "sg:classifiers":[
        {
            "category":"Banks & Credit Unions",
            "subcategory":"Bank",
            "type":"Services"
        }
    ],
    "sg:phone":"+1 574 538 5251",
    "sg:postcode":"46526",
    "sg:province":"IN",
    "wof:name":"Bank One Mortgage",
    "wof:placetype":"venue"
},
  "geometry": {"coordinates":[-85.857203,41.593859],"type":"Point"}
}