{
  "type": "Feature",
  "properties": {
    "iso:country":"US",
    "sg:address":"1225 Brookville Way",
    "sg:city":"Indianapolis",
    "sg:classifiers":[
        {
            "category":"Health Services",
            "subcategory":"Doctor",
            "type":"Services"
        }
    ],
    "sg:phone":"+1 317 322 5206",
    "sg:postcode":"46239",
    "sg:province":"IN",
    "sg:tags":[
        "medical",
        "imaging"
    ],
    "wof:name":"Suncare Respiratory Svc Inc",
    "wof:placetype":"venue"
},
  "geometry": {"coordinates":[-86.04463699999999,39.751115],"type":"Point"}
}