{
  "type": "Feature",
  "properties": {
    "iso:country":"US",
    "sg:address":"213 Arthur St",
    "sg:city":"Michigan City",
    "sg:classifiers":[
        {
            "category":"Retail",
            "subcategory":"Auto Repair",
            "type":"Services"
        }
    ],
    "sg:phone":"+1 219 861 0353",
    "sg:postcode":"46360",
    "sg:province":"IN",
    "sg:tags":[
        "repairing",
        "automobile"
    ],
    "wof:name":"Bill's Family Auto Svc",
    "wof:placetype":"venue"
},
  "geometry": {"coordinates":[-86.89070100000001,41.700796],"type":"Point"}
}