{
  "type": "Feature",
  "properties": {
    "addr:full":"3804 N 150 E Rushville IN 46173",
    "addr:housenumber":"3804",
    "addr:postcode":"46173",
    "addr:street":"N 150 E Rushville",
    "iso:country":"US",
    "sg:address":"3804 N 150 E",
    "sg:city":"Rushville",
    "sg:classifiers":[
        {
            "category":"Government",
            "subcategory":"Office",
            "type":"Public Place"
        }
    ],
    "sg:phone":"+1 765 932 3899",
    "sg:postcode":"46173",
    "sg:province":"IN",
    "sg:tags":[
        "village"
    ],
    "wof:name":"Jackson Twp Trustee",
    "wof:placetype":"venue"
},
  "geometry": {"coordinates":[-85.416214,39.66253],"type":"Point"}
}