{
  "type": "Feature",
  "properties": {
    "iso:country":"US",
    "sg:address":"2102 Woodmere Dr",
    "sg:city":"Valparaiso",
    "sg:classifiers":[
        {
            "category":"Professional",
            "subcategory":"Accounting & Tax Preparation",
            "type":"Services"
        }
    ],
    "sg:phone":"+1 219 477 6500",
    "sg:postcode":"46383",
    "sg:province":"IN",
    "sg:tags":[
        "accountant"
    ],
    "wof:name":"Allen J Gabriel CPA",
    "wof:placetype":"venue"
},
  "geometry": {"coordinates":[-87.035642,41.514523],"type":"Point"}
}