{
  "type": "Feature",
  "properties": {
    "iso:country":"US",
    "sg:address":"416 Jackson St",
    "sg:city":"Jasper",
    "sg:classifiers":[
        {
            "category":"Home & Garden",
            "subcategory":"Furniture",
            "type":"Retail Goods"
        }
    ],
    "sg:phone":"+1 812 481 9192",
    "sg:postcode":"47546",
    "sg:province":"IN",
    "wof:name":"Fritz Keith Fine Furniture",
    "wof:placetype":"venue"
},
  "geometry": {"coordinates":[-86.929757,38.390555],"type":"Point"}
}