{
  "type": "Feature",
  "properties": {
    "iso:country":"US",
    "sg:address":"201 W National Ave",
    "sg:city":"Brazil",
    "sg:classifiers":[
        {
            "category":"Professional",
            "subcategory":"Accounting & Tax Preparation",
            "type":"Services"
        }
    ],
    "sg:phone":"+1 812 448 2551",
    "sg:postcode":"47834",
    "sg:province":"IN",
    "sg:tags":[
        "accountant"
    ],
    "sg:website":"www.smacpas.com",
    "wof:name":"Spencer-Miller & Assoc",
    "wof:placetype":"venue"
},
  "geometry": {"coordinates":[-87.129927,39.522563],"type":"Point"}
}