{
  "type": "Feature",
  "properties": {
    "iso:country":"US",
    "sg:address":"2401 N Executive Park Rd",
    "sg:city":"Yorktown",
    "sg:classifiers":[
        {
            "category":"Building & Trades",
            "subcategory":"Construction",
            "type":"Services"
        }
    ],
    "sg:phone":"+1 765 282 5500",
    "sg:postcode":"47396",
    "sg:province":"IN",
    "sg:tags":[
        "home",
        "builder"
    ],
    "sg:website":"www.tkconstructors.com",
    "wof:name":"T K Constructors",
    "wof:placetype":"venue"
},
  "geometry": {"coordinates":[-85.55458900000001,40.21077],"type":"Point"}
}