{
  "type": "Feature",
  "properties": {
    "iso:country":"US",
    "sg:address":"320 Walnut St",
    "sg:city":"Madison",
    "sg:classifiers":[
        {
            "category":"Real Estate",
            "subcategory":"Real Estate Services",
            "type":"Services"
        }
    ],
    "sg:phone":"+1 812 265 3030",
    "sg:postcode":"47250",
    "sg:province":"IN",
    "sg:tags":[
        "company",
        "title"
    ],
    "sg:website":"www.jclt.com",
    "wof:name":"Jefferson County Title Corp",
    "wof:placetype":"venue"
},
  "geometry": {"coordinates":[-85.375642,38.735435],"type":"Point"}
}