{
  "type": "Feature",
  "properties": {
    "iso:country":"US",
    "sg:address":"723 E 5th St",
    "sg:city":"Connersville",
    "sg:classifiers":[
        {
            "category":"Building & Trades",
            "subcategory":"Plumbing",
            "type":"Services"
        }
    ],
    "sg:phone":"+1 765 825 3854",
    "sg:postcode":"47331",
    "sg:province":"IN",
    "sg:tags":[
        "heating",
        "contractor"
    ],
    "wof:name":"Coldiron Heating & Plumbing",
    "wof:placetype":"venue"
},
  "geometry": {"coordinates":[-85.127386,39.638802],"type":"Point"}
}