{
  "type": "Feature",
  "properties": {
    "iso:country":"US",
    "sg:address":"10092 E 221st St",
    "sg:city":"Noblesville",
    "sg:classifiers":[
        {
            "category":"Personal",
            "subcategory":"Beauty Salon",
            "type":"Services"
        }
    ],
    "sg:phone":"+1 317 770 0567",
    "sg:postcode":"46062",
    "sg:province":"IN",
    "sg:tags":[
        "shop"
    ],
    "wof:name":"Victorias Station Inc",
    "wof:placetype":"venue"
},
  "geometry": {"coordinates":[-85.99306,40.109187],"type":"Point"}
}