{
  "type": "Feature",
  "properties": {
    "addr:full":"1600 E Washington Blvd Fort Wayne IN 46803",
    "addr:housenumber":"1600",
    "addr:postcode":"46803",
    "addr:street":"E Washington Blvd",
    "iso:country":"US",
    "sg:address":"1600 E Washington Blvd",
    "sg:city":"Fort Wayne",
    "sg:classifiers":[
        {
            "category":"Professional",
            "type":"Services"
        }
    ],
    "sg:phone":"+1 260 420 1453",
    "sg:postcode":"46803",
    "sg:province":"IN",
    "sg:tags":[
        "establishment"
    ],
    "wof:name":"Idea Center",
    "wof:placetype":"venue"
},
  "geometry": {"coordinates":[-85.114659,41.07909],"type":"Point"}
}