{
  "type": "Feature",
  "properties": {
    "iso:country":"US",
    "sg:address":"3320 E State Rd 218",
    "sg:city":"Bluffton",
    "sg:classifiers":[
        {
            "category":"Real Estate",
            "subcategory":"Real Estate Operator",
            "type":"Services"
        }
    ],
    "sg:phone":"+1 260 346 2466",
    "sg:postcode":"46714",
    "sg:province":"IN",
    "sg:tags":[
        "property",
        "lessor"
    ],
    "wof:name":"Wayne Reff",
    "wof:placetype":"venue"
},
  "geometry": {"coordinates":[-85.16161099999999,40.654902],"type":"Point"}
}