{
  "type": "Feature",
  "properties": {
    "iso:country":"US",
    "sg:address":"233 NW Passage Trl",
    "sg:city":"Fort Wayne",
    "sg:classifiers":[
        {
            "category":"Freight",
            "type":"Transportation"
        }
    ],
    "sg:phone":"+1 260 490 9051",
    "sg:postcode":"46825",
    "sg:province":"IN",
    "sg:tags":[
        "trucking"
    ],
    "wof:name":"Montgomery Trucking Inc Of In",
    "wof:placetype":"venue"
},
  "geometry": {"coordinates":[-85.137398,41.175008],"type":"Point"}
}