{
  "type": "Feature",
  "properties": {
    "addr:full":"4810 Illinois Rd Fort Wayne IN 46804",
    "addr:housenumber":"4810",
    "addr:postcode":"46804",
    "addr:street":"Illinois Rd",
    "iso:country":"US",
    "sg:address":"4810 Illinois Rd",
    "sg:city":"Fort Wayne",
    "sg:classifiers":[
        {
            "category":"Personal",
            "subcategory":"Beauty Salon",
            "type":"Services"
        }
    ],
    "sg:phone":"+1 260 434 9110",
    "sg:postcode":"46804",
    "sg:province":"IN",
    "wof:name":"Bellhouse Spa & Hair Salon",
    "wof:placetype":"venue"
},
  "geometry": {"coordinates":[-85.20531,41.074568],"type":"Point"}
}