{
  "type": "Feature",
  "properties": {
    "addr:full":"234 E Harvest Ln Petersburg IN 47567",
    "addr:housenumber":"234",
    "addr:postcode":"47567",
    "addr:street":"E Harvest Ln",
    "iso:country":"US",
    "sg:address":"234 E Harvest Ln",
    "sg:city":"Petersburg",
    "sg:classifiers":[
        {
            "category":"Manufacturing",
            "subcategory":"Apparel",
            "type":"Manufacturing & Wholesale Goods"
        }
    ],
    "sg:phone":"+1 812 354 2233",
    "sg:postcode":"47567",
    "sg:province":"IN",
    "wof:name":"Moore Designs Unlmtd",
    "wof:placetype":"venue"
},
  "geometry": {"coordinates":[-87.28165199999999,38.5028],"type":"Point"}
}