{
  "type": "Feature",
  "properties": {
    "iso:country":"US",
    "sg:address":"2010 Lanier Dr",
    "sg:city":"Madison",
    "sg:classifiers":[
        {
            "category":"Retail",
            "subcategory":"Auto Repair",
            "type":"Services"
        }
    ],
    "sg:phone":"+1 812 273 5025",
    "sg:postcode":"47250",
    "sg:province":"IN",
    "sg:tags":[
        "transmission",
        "tractor"
    ],
    "wof:name":"Transmission Unlimited",
    "wof:placetype":"venue"
},
  "geometry": {"coordinates":[-85.409114,38.764741],"type":"Point"}
}