{
  "type": "Feature",
  "properties": {
    "iso:country":"US",
    "sg:address":"2421 SE Browning Rd",
    "sg:city":"Evansville",
    "sg:classifiers":[
        {
            "category":"Real Estate",
            "subcategory":"Real Estate Operator",
            "type":"Services"
        }
    ],
    "sg:phone":"+1 812 867 3750",
    "sg:postcode":"47725",
    "sg:province":"IN",
    "sg:tags":[
        "property",
        "lessor"
    ],
    "wof:name":"Wood Alvah",
    "wof:placetype":"venue"
},
  "geometry": {"coordinates":[-87.523775,38.064244],"type":"Point"}
}