{
  "type": "Feature",
  "properties": {
    "iso:country":"US",
    "sg:address":"401 N Saint Joseph Ave",
    "sg:city":"Evansville",
    "sg:classifiers":[
        {
            "category":"Restaurant",
            "type":"Food & Drink"
        }
    ],
    "sg:phone":"+1 812 423 0035",
    "sg:postcode":"47712",
    "sg:province":"IN",
    "wof:name":"Subway Sandwiches & Salads",
    "wof:placetype":"venue"
},
  "geometry": {"coordinates":[-87.600527,37.981981],"type":"Point"}
}