{
  "type": "Feature",
  "properties": {
    "iso:country":"US",
    "sg:address":"317 N Main St",
    "sg:city":"Edinburgh",
    "sg:classifiers":[
        {
            "category":"Manufacturing",
            "subcategory":"Metals",
            "type":"Manufacturing & Wholesale Goods"
        }
    ],
    "sg:phone":"+1 812 526 5137",
    "sg:postcode":"46124",
    "sg:province":"IN",
    "sg:tags":[
        "fabricator",
        "sheet"
    ],
    "wof:name":"C & D Svc Inc",
    "wof:placetype":"venue"
},
  "geometry": {"coordinates":[-85.967834,39.357045],"type":"Point"}
}