{
  "type": "Feature",
  "properties": {
    "iso:country":"US",
    "sg:address":"138 S Jefferson St",
    "sg:city":"Nashville",
    "sg:classifiers":[
        {
            "category":"Personal",
            "subcategory":"Beauty Salon",
            "type":"Services"
        }
    ],
    "sg:phone":"+1 812 988 7475",
    "sg:postcode":"47448",
    "sg:province":"IN",
    "wof:name":"Cutting Edge",
    "wof:placetype":"venue"
},
  "geometry": {"coordinates":[-86.248211,39.206397],"type":"Point"}
}