{
  "type": "Feature",
  "properties": {
    "iso:country":"US",
    "sg:address":"5160 Clear Lake Ct",
    "sg:city":"Carmel",
    "sg:classifiers":[
        {
            "category":"Professional",
            "subcategory":"Management & Consulting",
            "type":"Services"
        }
    ],
    "sg:phone":"+1 317 571 0340",
    "sg:postcode":"46033",
    "sg:province":"IN",
    "sg:tags":[
        "business"
    ],
    "wof:name":"Vw Association",
    "wof:placetype":"venue"
},
  "geometry": {"coordinates":[-86.078908,39.96182],"type":"Point"}
}