{
  "type": "Feature",
  "properties": {
    "iso:country":"US",
    "sg:address":"906 Main St",
    "sg:city":"Rochester",
    "sg:classifiers":[
        {
            "category":"Shopping",
            "subcategory":"Pharmacy",
            "type":"Retail Goods"
        }
    ],
    "sg:phone":"+1 574 223 4391",
    "sg:postcode":"46975",
    "sg:province":"IN",
    "wof:name":"Walgreens",
    "wof:placetype":"venue"
},
  "geometry": {"coordinates":[-86.21612399999999,41.0649],"type":"Point"}
}