{
  "type": "Feature",
  "properties": {
    "iso:country":"US",
    "sg:address":"6575 Saint Marys Rd",
    "sg:city":"Floyds Knobs",
    "sg:classifiers":[
        {
            "category":"Building & Trades",
            "subcategory":"Construction",
            "type":"Services"
        }
    ],
    "sg:phone":"+1 812 923 3087",
    "sg:postcode":"47119",
    "sg:province":"IN",
    "sg:tags":[
        "paving",
        "contractor"
    ],
    "wof:name":"Striegel Asphalt",
    "wof:placetype":"venue"
},
  "geometry": {"coordinates":[-85.86468000000001,38.370094],"type":"Point"}
}