{
  "type": "Feature",
  "properties": {
    "iso:country":"US",
    "sg:address":"8555 One West Dr",
    "sg:city":"Indianapolis",
    "sg:classifiers":[
        {
            "category":"Building & Trades",
            "subcategory":"Construction",
            "type":"Services"
        }
    ],
    "sg:phone":"+1 317 251 5608",
    "sg:postcode":"46260",
    "sg:province":"IN",
    "sg:tags":[
        "home",
        "builder"
    ],
    "wof:name":"Eaton Residential LTD",
    "wof:placetype":"venue"
},
  "geometry": {"coordinates":[-86.15904,39.911805],"type":"Point"}
}