{
  "type": "Feature",
  "properties": {
    "iso:country":"US",
    "sg:address":"848 Logan St",
    "sg:city":"Noblesville",
    "sg:classifiers":[
        {
            "category":"Real Estate",
            "subcategory":"Real Estate Services",
            "type":"Services"
        }
    ],
    "sg:phone":"+1 317 774 9610",
    "sg:postcode":"46060",
    "sg:province":"IN",
    "sg:tags":[
        "company",
        "title"
    ],
    "wof:name":"Express One Research Group",
    "wof:placetype":"venue"
},
  "geometry": {"coordinates":[-86.013949,40.046614],"type":"Point"}
}