{
  "type": "Feature",
  "properties": {
    "iso:country":"US",
    "sg:address":"633 Tavern St",
    "sg:city":"New Harmony",
    "sg:classifiers":[
        {
            "category":"Retail",
            "subcategory":"Auto Repair",
            "type":"Services"
        }
    ],
    "sg:phone":"+1 812 682 4206",
    "sg:postcode":"47631",
    "sg:province":"IN",
    "sg:tags":[
        "repairing",
        "automobile"
    ],
    "wof:name":"Naas Hardware & Auto Ctr",
    "wof:placetype":"venue"
},
  "geometry": {"coordinates":[-87.932868,38.129079],"type":"Point"}
}