{
  "type": "Feature",
  "properties": {
    "iso:country":"US",
    "sg:address":"800 Golfview Rd",
    "sg:city":"Lafayette",
    "sg:classifiers":[
        {
            "category":"Sports & Exercise",
            "subcategory":"Golf",
            "type":"Entertainment"
        }
    ],
    "sg:phone":"+1 765 420 0615",
    "sg:postcode":"47904",
    "sg:province":"IN",
    "sg:tags":[
        "course"
    ],
    "sg:website":"www.lafayettegc.com",
    "wof:name":"Lafayette Golf",
    "wof:placetype":"venue"
},
  "geometry": {"coordinates":[-86.887984,40.441807],"type":"Point"}
}