{
  "type": "Feature",
  "properties": {
    "iso:country":"US",
    "sg:address":"1802 E US Hwy 20",
    "sg:city":"Michigan City",
    "sg:classifiers":[
        {
            "category":"Building & Trades",
            "subcategory":"Construction",
            "type":"Services"
        }
    ],
    "sg:phone":"+1 219 874 6768",
    "sg:postcode":"46360",
    "sg:province":"IN",
    "sg:tags":[
        "general",
        "contractor"
    ],
    "wof:name":"Pritz Construction Inc",
    "wof:placetype":"venue"
},
  "geometry": {"coordinates":[-86.85956299999999,41.687412],"type":"Point"}
}