{
  "type": "Feature",
  "properties": {
    "iso:country":"US",
    "sg:address":"607 W Mulberry St",
    "sg:city":"Kokomo",
    "sg:classifiers":[
        {
            "category":"Professional",
            "type":"Services"
        }
    ],
    "sg:phone":"+1 765 236 0745",
    "sg:postcode":"46901",
    "sg:province":"IN",
    "wof:name":"Wayne Anthony Services",
    "wof:placetype":"venue"
},
  "geometry": {"coordinates":[-86.138581,40.488212],"type":"Point"}
}