{
  "type": "Feature",
  "properties": {
    "iso:country":"US",
    "sg:address":"6520 W Lincoln Hwy",
    "sg:city":"Schererville",
    "sg:classifiers":[
        {
            "category":"Shopping",
            "subcategory":"Gifts & Souvenirs",
            "type":"Retail Goods"
        }
    ],
    "sg:phone":"+1 219 865 8457",
    "sg:postcode":"46375",
    "sg:province":"IN",
    "sg:tags":[
        "shop"
    ],
    "wof:name":"Holmstead Cider Gifts",
    "wof:placetype":"venue"
},
  "geometry": {"coordinates":[-87.42940400000001,41.481325],"type":"Point"}
}