{
  "type": "Feature",
  "properties": {
    "iso:country":"US",
    "sg:address":"2211 E Co Rd 820 S",
    "sg:city":"Greensburg",
    "sg:classifiers":[
        {
            "category":"Autos & Motor Vehicles",
            "subcategory":"Motorcycle Sales",
            "type":"Retail Goods"
        }
    ],
    "sg:phone":"+1 812 591 2483",
    "sg:postcode":"47240",
    "sg:province":"IN",
    "sg:tags":[
        "scooter"
    ],
    "wof:name":"Zaps ATV & Cycle",
    "wof:placetype":"venue"
},
  "geometry": {"coordinates":[-85.434398,39.211096],"type":"Point"}
}