{
  "type": "Feature",
  "properties": {
    "iso:country":"US",
    "sg:address":"6625 E Co Rd 500 S",
    "sg:city":"New Lisbon",
    "sg:classifiers":[
        {
            "category":"Government",
            "subcategory":"Post Office",
            "type":"Public Place"
        }
    ],
    "sg:phone":"+1 765 332 2153",
    "sg:postcode":"47302",
    "sg:province":"IN",
    "wof:name":"US Post Office",
    "wof:placetype":"venue"
},
  "geometry": {"coordinates":[-85.300714,40.120589],"type":"Point"}
}