{
  "type": "Feature",
  "properties": {
    "iso:country":"US",
    "sg:address":"504 Colerain St",
    "sg:city":"Wabash",
    "sg:classifiers":[
        {
            "category":"Health Services",
            "subcategory":"Health Practitioner",
            "type":"Services"
        }
    ],
    "sg:phone":"+1 260 569 2206",
    "sg:postcode":"46992",
    "sg:province":"IN",
    "sg:tags":[
        "therapist",
        "physical"
    ],
    "wof:name":"Rehab Place",
    "wof:placetype":"venue"
},
  "geometry": {"coordinates":[-85.830869,40.807831],"type":"Point"}
}