{
  "type": "Feature",
  "properties": {
    "addr:full":"795 W 400 N Warsaw IN 46580",
    "addr:housenumber":"795",
    "addr:postcode":"46580",
    "addr:street":"W 400 N",
    "iso:country":"US",
    "sg:address":"795 W 400 N",
    "sg:city":"Warsaw",
    "sg:classifiers":[
        {
            "category":"Autos & Motor Vehicles",
            "subcategory":"Boat Sales",
            "type":"Retail Goods"
        }
    ],
    "sg:phone":"+1 574 268 2696",
    "sg:postcode":"46580",
    "sg:province":"IN",
    "sg:tags":[
        "dealer",
        "sales"
    ],
    "wof:name":"Tri-Lakes Marine",
    "wof:placetype":"venue"
},
  "geometry": {"coordinates":[-85.858125,41.291725],"type":"Point"}
}