{
  "type": "Feature",
  "properties": {
    "iso:country":"US",
    "sg:address":"5342 Elmwood Ave",
    "sg:city":"Indianapolis",
    "sg:classifiers":[
        {
            "category":"Retail",
            "subcategory":"Auto Repair",
            "type":"Services"
        }
    ],
    "sg:phone":"+1 317 786 6646",
    "sg:postcode":"46203",
    "sg:province":"IN",
    "sg:tags":[
        "body",
        "automobile",
        "painting"
    ],
    "wof:name":"A & M Customs",
    "wof:placetype":"venue"
},
  "geometry": {"coordinates":[-86.081588,39.705603],"type":"Point"}
}