{
  "type": "Feature",
  "properties": {
    "iso:country":"US",
    "sg:address":"2106 Ohio Ave",
    "sg:city":"Anderson",
    "sg:classifiers":[
        {
            "category":"Building & Trades",
            "subcategory":"Electrical",
            "type":"Services"
        }
    ],
    "sg:phone":"+1 765 643 8854",
    "sg:postcode":"46016",
    "sg:province":"IN",
    "sg:tags":[
        "electric",
        "contractor"
    ],
    "wof:name":"Nugent Electric Co",
    "wof:placetype":"venue"
},
  "geometry": {"coordinates":[-85.660429,40.095541],"type":"Point"}
}