{
  "type": "Feature",
  "properties": {
    "iso:country":"US",
    "sg:address":"8720 Castle Creek Parkway East Dr",
    "sg:city":"Indianapolis",
    "sg:classifiers":[
        {
            "category":"Wholesale",
            "subcategory":"Stationery",
            "type":"Manufacturing & Wholesale Goods"
        }
    ],
    "sg:phone":"+1 317 594 0692",
    "sg:postcode":"46250",
    "sg:province":"IN",
    "sg:tags":[
        "business",
        "form",
        "system"
    ],
    "wof:name":"Miami Systems Corp",
    "wof:placetype":"venue"
},
  "geometry": {"coordinates":[-86.06903,39.913863],"type":"Point"}
}