{
  "type": "Feature",
  "properties": {
    "iso:country":"US",
    "sg:address":"723 W 5th St",
    "sg:city":"Bloomington",
    "sg:classifiers":[
        {
            "category":"Personal",
            "subcategory":"Beauty Salon",
            "type":"Services"
        }
    ],
    "sg:phone":"+1 812 824 9232",
    "sg:postcode":"47404",
    "sg:province":"IN",
    "wof:name":"Kim's KUT & KURL",
    "wof:placetype":"venue"
},
  "geometry": {"coordinates":[-86.541906,39.166575],"type":"Point"}
}