{
  "type": "Feature",
  "properties": {
    "iso:country":"US",
    "sg:address":"307 US Hwy 41",
    "sg:city":"Fort Branch",
    "sg:classifiers":[
        {
            "category":"Shopping",
            "subcategory":"Clothing, Apparel, & Fashions",
            "type":"Retail Goods"
        }
    ],
    "sg:phone":"+1 812 753 4545",
    "sg:postcode":"47648",
    "sg:province":"IN",
    "sg:tags":[
        "t"
    ],
    "sg:website":"www.chipshirt.com",
    "wof:name":"Chips Inc",
    "wof:placetype":"venue"
},
  "geometry": {"coordinates":[-87.56786700000001,38.244937],"type":"Point"}
}