{
  "type": "Feature",
  "properties": {
    "iso:country":"US",
    "sg:address":"402 Wallen Hills Dr",
    "sg:city":"Fort Wayne",
    "sg:classifiers":[
        {
            "category":"Real Estate",
            "subcategory":"Real Estate Operator",
            "type":"Services"
        }
    ],
    "sg:phone":"+1 260 489 1166",
    "sg:postcode":"46825",
    "sg:province":"IN",
    "sg:tags":[
        "apartment"
    ],
    "wof:name":"Wallen Hills Apartments",
    "wof:placetype":"venue"
},
  "geometry": {"coordinates":[-85.137016,41.164943],"type":"Point"}
}