{
  "type": "Feature",
  "properties": {
    "addr:full":"1125 Indy Ct Evansville IN 47725",
    "addr:housenumber":"1125",
    "addr:postcode":"47725",
    "addr:street":"Indy Ct",
    "iso:country":"US",
    "sg:address":"1125 Indy Ct",
    "sg:city":"Evansville",
    "sg:classifiers":[
        {
            "category":"Building & Trades",
            "subcategory":"Construction",
            "type":"Services"
        }
    ],
    "sg:phone":"+1 812 867 5144",
    "sg:postcode":"47725",
    "sg:province":"IN",
    "sg:tags":[
        "concrete",
        "contractor"
    ],
    "wof:name":"A & S Construction",
    "wof:placetype":"venue"
},
  "geometry": {"coordinates":[-87.542995,38.052122],"type":"Point"}
}