{
  "type": "Feature",
  "properties": {
    "iso:country":"US",
    "sg:address":"426 N Main St",
    "sg:city":"Elkhart",
    "sg:classifiers":[
        {
            "category":"Manufacturing",
            "subcategory":"Lumber",
            "type":"Manufacturing & Wholesale Goods"
        }
    ],
    "sg:phone":"+1 574 389 5400",
    "sg:postcode":"46514",
    "sg:province":"IN",
    "wof:name":"Banks Lumber Co",
    "wof:placetype":"venue"
},
  "geometry": {"coordinates":[-85.97546,41.691394],"type":"Point"}
}