{
  "type": "Feature",
  "properties": {
    "iso:country":"US",
    "sg:address":"207 E Main St",
    "sg:city":"Anderson",
    "sg:classifiers":[
        {
            "category":"Government",
            "subcategory":"Fire Station",
            "type":"Public Place"
        }
    ],
    "sg:phone":"+1 765 378 7255",
    "sg:postcode":"46017",
    "sg:province":"IN",
    "sg:tags":[
        "department"
    ],
    "wof:name":"Chesterfield-Union Twp Fire",
    "wof:placetype":"venue"
},
  "geometry": {"coordinates":[-85.593585,40.113402],"type":"Point"}
}