{
  "type": "Feature",
  "properties": {
    "addr:full":"9800 Valparaiso Dr Munster IN 46321",
    "addr:housenumber":"9800",
    "addr:postcode":"46321",
    "addr:street":"Valparaiso Dr",
    "iso:country":"US",
    "sg:address":"9800 Valparaiso Dr",
    "sg:city":"Munster",
    "sg:classifiers":[
        {
            "category":"Health Services",
            "subcategory":"Doctor",
            "type":"Services"
        },
        {
            "category":"Health Services",
            "subcategory":"Clinic",
            "type":"Services"
        },
        {
            "category":"Health Services",
            "subcategory":"Podiatrist",
            "type":"Services"
        }
    ],
    "sg:phone":"+1 219 934 9800",
    "sg:postcode":"46321",
    "sg:province":"IN",
    "sg:tags":[
        "physician",
        "family",
        "medical",
        "practice",
        "surgeons",
        "medicine"
    ],
    "sg:website":"http://www.hammondclinic.com",
    "wof:name":"Hammond Clinic",
    "wof:placetype":"venue"
},
  "geometry": {"coordinates":[-87.511217,41.534684],"type":"Point"}
}