{
  "type": "Feature",
  "properties": {
    "iso:country":"US",
    "sg:address":"912 Johnson St",
    "sg:city":"Elkhart",
    "sg:classifiers":[
        {
            "category":"Retail",
            "subcategory":"Car Wash",
            "type":"Services"
        }
    ],
    "sg:phone":"+1 574 262 3951",
    "sg:postcode":"46514",
    "sg:province":"IN",
    "sg:tags":[
        "polishing",
        "washing"
    ],
    "wof:name":"Super Wash",
    "wof:placetype":"venue"
},
  "geometry": {"coordinates":[-85.966044,41.69451],"type":"Point"}
}