{
  "type": "Feature",
  "properties": {
    "iso:country":"US",
    "sg:address":"3500 W Maple Grove Rd",
    "sg:city":"Bloomington",
    "sg:classifiers":[
        {
            "category":"Building & Trades",
            "subcategory":"Plumbing",
            "type":"Services"
        }
    ],
    "sg:phone":"+1 812 876 7776",
    "sg:postcode":"47404",
    "sg:province":"IN",
    "sg:tags":[
        "contractor"
    ],
    "wof:name":"Terrell Heating",
    "wof:placetype":"venue"
},
  "geometry": {"coordinates":[-86.58508,39.24464],"type":"Point"}
}