{
  "type": "Feature",
  "properties": {
    "addr:full":"308 Lakeland Dr Lowell IN 46356",
    "addr:housenumber":"308",
    "addr:postcode":"46356",
    "addr:street":"Lakeland Dr",
    "iso:country":"US",
    "sg:address":"308 Lakeland Dr",
    "sg:city":"Lowell",
    "sg:classifiers":[
        {
            "category":"Manufacturing",
            "subcategory":"Metals",
            "type":"Manufacturing & Wholesale Goods"
        }
    ],
    "sg:phone":"+1 219 696 2661",
    "sg:postcode":"46356",
    "sg:province":"IN",
    "sg:tags":[
        "steel",
        "cold",
        "shape",
        "mfg"
    ],
    "wof:name":"Quanex Corporation",
    "wof:placetype":"venue"
},
  "geometry": {"coordinates":[-87.398956,41.294011],"type":"Point"}
}