{
  "type": "Feature",
  "properties": {
    "addr:full":"6740 Massachusetts Ave Indianapolis IN 46226",
    "addr:housenumber":"6740",
    "addr:postcode":"46226",
    "addr:street":"Massachusetts Ave",
    "iso:country":"US",
    "sg:address":"6740 Massachusetts Ave",
    "sg:city":"Indianapolis",
    "sg:classifiers":[
        {
            "category":"Manufacturing",
            "subcategory":"Signs",
            "type":"Manufacturing & Wholesale Goods"
        }
    ],
    "sg:phone":"+1 317 542 1934",
    "sg:postcode":"46226",
    "sg:province":"IN",
    "wof:name":"All Sign Co & Screen Printing",
    "wof:placetype":"venue"
},
  "geometry": {"coordinates":[-86.053725,39.823384],"type":"Point"}
}