{
  "type": "Feature",
  "properties": {
    "iso:country":"US",
    "sg:address":"4550 E Co Rd 400 N",
    "sg:city":"Michigantown",
    "sg:classifiers":[
        {
            "category":"Professional",
            "subcategory":"Accounting & Tax Preparation",
            "type":"Services"
        }
    ],
    "sg:phone":"+1 765 249 2328",
    "sg:postcode":"46057",
    "sg:province":"IN",
    "sg:tags":[
        "accountant"
    ],
    "wof:name":"Christine K Davis CPA",
    "wof:placetype":"venue"
},
  "geometry": {"coordinates":[-86.430917,40.344561],"type":"Point"}
}