{
  "type": "Feature",
  "properties": {
    "iso:country":"US",
    "sg:address":"115 W Webster St",
    "sg:city":"Ashley",
    "sg:classifiers":[
        {
            "category":"Building & Trades",
            "subcategory":"Electrical",
            "type":"Services"
        }
    ],
    "sg:phone":"+1 260 587 9229",
    "sg:postcode":"46705",
    "sg:province":"IN",
    "sg:tags":[
        "electric",
        "contractor"
    ],
    "wof:name":"Sondguard Security Electric",
    "wof:placetype":"venue"
},
  "geometry": {"coordinates":[-85.06467,41.524142],"type":"Point"}
}