{
  "type": "Feature",
  "properties": {
    "iso:country":"US",
    "sg:address":"280 E 96th St Ste 350",
    "sg:city":"Indianapolis",
    "sg:classifiers":[
        {
            "category":"Professional",
            "subcategory":"Computer Services",
            "type":"Services"
        }
    ],
    "sg:phone":"+1 317 509 9563",
    "sg:postcode":"46240",
    "sg:province":"IN",
    "sg:tags":[
        "technical",
        "assistance",
        "support"
    ],
    "wof:name":"Constant Technology, Inc",
    "wof:placetype":"venue"
},
  "geometry": {"coordinates":[-86.15254400000001,39.927069],"type":"Point"}
}