{
  "type": "Feature",
  "properties": {
    "iso:country":"US",
    "sg:address":"202 E 3rd St",
    "sg:city":"Ferdinand",
    "sg:classifiers":[
        {
            "category":"Health Services",
            "subcategory":"Doctor",
            "type":"Services"
        }
    ],
    "sg:phone":"+1 812 367 1112",
    "sg:postcode":"47546",
    "sg:province":"IN",
    "sg:tags":[
        "physician",
        "surgeon"
    ],
    "wof:name":"Ferdinand Clinic",
    "wof:placetype":"venue"
},
  "geometry": {"coordinates":[-86.86241800000001,38.219401],"type":"Point"}
}