{
  "type": "Feature",
  "properties": {
    "iso:country":"US",
    "sg:address":"333 W Jackson St",
    "sg:city":"Tipton",
    "sg:classifiers":[
        {
            "category":"Recreation",
            "type":"Entertainment"
        }
    ],
    "sg:phone":"+1 765 675 3595",
    "sg:postcode":"46072",
    "sg:province":"IN",
    "sg:tags":[
        "parlor",
        "billiard"
    ],
    "wof:name":"Rabbits Family Billiards",
    "wof:placetype":"venue"
},
  "geometry": {"coordinates":[-86.04539699999999,40.278311],"type":"Point"}
}