{
  "type": "Feature",
  "properties": {
    "iso:country":"US",
    "sg:address":"113 S Washington St",
    "sg:city":"Delphi",
    "sg:classifiers":[
        {
            "category":"Restaurant",
            "type":"Food & Drink"
        }
    ],
    "sg:phone":"+1 765 564 6151",
    "sg:postcode":"46923",
    "sg:province":"IN",
    "wof:name":"Mister D's Pizza",
    "wof:placetype":"venue"
},
  "geometry": {"coordinates":[-86.674429,40.586921],"type":"Point"}
}