{
  "type": "Feature",
  "properties": {
    "addr:full":"2934 Greenview Way Indianapolis IN 46229",
    "addr:housenumber":"2934",
    "addr:postcode":"46229",
    "addr:street":"Greenview Way",
    "iso:country":"US",
    "sg:address":"2934 Greenview Way",
    "sg:city":"Indianapolis",
    "sg:classifiers":[
        {
            "category":"Building & Trades",
            "subcategory":"Construction",
            "type":"Services"
        }
    ],
    "sg:phone":"+1 317 418 7359",
    "sg:postcode":"46229",
    "sg:province":"IN",
    "sg:tags":[
        "fork",
        "lift",
        "trucks-industrial"
    ],
    "wof:name":"Circle City Express",
    "wof:placetype":"venue"
},
  "geometry": {"coordinates":[-85.977692,39.811119],"type":"Point"}
}