{
  "type": "Feature",
  "properties": {
    "iso:country":"US",
    "sg:address":"1242 Main St",
    "sg:city":"Monroe City",
    "sg:classifiers":[
        {
            "category":"Organizations",
            "subcategory":"Membership Organization",
            "type":"Services"
        }
    ],
    "sg:phone":"+1 812 743 2570",
    "sg:postcode":"47557",
    "sg:province":"IN",
    "sg:tags":[
        "athletic"
    ],
    "wof:name":"South KNOX Baseball League",
    "wof:placetype":"venue"
},
  "geometry": {"coordinates":[-87.351502,38.612997],"type":"Point"}
}