{
  "type": "Feature",
  "properties": {
    "addr:full":"2100 N 925 W West Lafayette IN 47906",
    "addr:housenumber":"2100",
    "addr:postcode":"47906",
    "addr:street":"N 925 W",
    "iso:country":"US",
    "sg:address":"2100 N 925 W",
    "sg:city":"West Lafayette",
    "sg:classifiers":[
        {
            "category":"Building & Trades",
            "subcategory":"Construction",
            "type":"Services"
        }
    ],
    "sg:phone":"+1 765 583 2342",
    "sg:postcode":"47906",
    "sg:province":"IN",
    "sg:tags":[
        "home",
        "builder"
    ],
    "wof:name":"Ken Ade Construction Inc",
    "wof:placetype":"venue"
},
  "geometry": {"coordinates":[-87.078525,40.451139],"type":"Point"}
}