{
  "type": "Feature",
  "properties": {
    "addr:full":"3449 W Fort Hill Rd Salem IN 47167",
    "addr:housenumber":"3449",
    "addr:postcode":"47167",
    "addr:street":"W Fort Hill Rd",
    "iso:country":"US",
    "sg:address":"3449 W Fort Hill Rd",
    "sg:city":"Salem",
    "sg:classifiers":[
        {
            "category":"Retail",
            "subcategory":"Auto Repair",
            "type":"Services"
        }
    ],
    "sg:phone":"+1 812 883 3806",
    "sg:postcode":"47167",
    "sg:province":"IN",
    "sg:tags":[
        "general"
    ],
    "wof:name":"Atkins Garage",
    "wof:placetype":"venue"
},
  "geometry": {"coordinates":[-86.15838100000001,38.572476],"type":"Point"}
}