{
  "type": "Feature",
  "properties": {
    "addr:full":"5525 W Bracken Rd Huntington IN 46750",
    "addr:housenumber":"5525",
    "addr:postcode":"46750",
    "addr:street":"W Bracken Rd",
    "iso:country":"US",
    "sg:address":"5525 W Bracken Rd",
    "sg:city":"Huntington",
    "sg:phone":"+1 260 344 1037",
    "sg:postcode":"46750",
    "sg:province":"IN",
    "sg:tags":[
        "farm",
        "soybean"
    ],
    "wof:name":"Keith Swain",
    "wof:placetype":"venue"
},
  "geometry": {"coordinates":[-85.56591299999999,40.959196],"type":"Point"}
}