{
  "type": "Feature",
  "properties": {
    "iso:country":"US",
    "sg:address":"1005 S Kentucky Ave",
    "sg:city":"Evansville",
    "sg:classifiers":[
        {
            "category":"Restaurant",
            "type":"Food & Drink"
        }
    ],
    "sg:phone":"+1 812 423 5553",
    "sg:postcode":"47714",
    "sg:province":"IN",
    "sg:tags":[
        "cafe"
    ],
    "wof:name":"PAR K Cafe",
    "wof:placetype":"venue"
},
  "geometry": {"coordinates":[-87.547861,37.96239],"type":"Point"}
}