{
  "type": "Feature",
  "properties": {
    "iso:country":"US",
    "sg:address":"5024 W Western Ave",
    "sg:city":"South Bend",
    "sg:classifiers":[
        {
            "category":"Health Services",
            "subcategory":"Clinic",
            "type":"Services"
        }
    ],
    "sg:phone":"+1 574 233 0331",
    "sg:postcode":"46619",
    "sg:province":"IN",
    "sg:website":"www.leealanbryant.com",
    "wof:name":"West Park Health Care Fclts",
    "wof:placetype":"venue"
},
  "geometry": {"coordinates":[-86.320858,41.671727],"type":"Point"}
}