{
  "type": "Feature",
  "properties": {
    "iso:country":"US",
    "sg:address":"615 W South St",
    "sg:city":"Winchester",
    "sg:classifiers":[
        {
            "category":"Education",
            "subcategory":"School",
            "type":"Public Place"
        }
    ],
    "sg:phone":"+1 765 584 9171",
    "sg:postcode":"47394",
    "sg:province":"IN",
    "wof:name":"Willard Elementary School",
    "wof:placetype":"venue"
},
  "geometry": {"coordinates":[-84.988363,40.170321],"type":"Point"}
}