{
  "type": "Feature",
  "properties": {
    "iso:country":"US",
    "sg:address":"2128 S Harding St",
    "sg:city":"Indianapolis",
    "sg:classifiers":[
        {
            "category":"Professional",
            "type":"Services"
        }
    ],
    "sg:phone":"+1 317 639 4207",
    "sg:postcode":"46221",
    "sg:province":"IN",
    "sg:tags":[
        "establishment"
    ],
    "wof:name":"Central Indiana Truck Equip",
    "wof:placetype":"venue"
},
  "geometry": {"coordinates":[-86.187405,39.743535],"type":"Point"}
}