{
  "type": "Feature",
  "properties": {
    "addr:full":"2859 Northpark Ave Huntington IN 46750",
    "addr:housenumber":"2859",
    "addr:postcode":"46750",
    "addr:street":"Northpark Ave",
    "iso:country":"US",
    "sg:address":"2859 Northpark Ave",
    "sg:city":"Huntington",
    "sg:classifiers":[
        {
            "category":"Banks & Credit Unions",
            "subcategory":"Investment Brokerage",
            "type":"Services"
        }
    ],
    "sg:phone":"+1 260 356 0117",
    "sg:postcode":"46750",
    "sg:province":"IN",
    "sg:tags":[
        "stock",
        "bond"
    ],
    "wof:name":"Edward Jones Co",
    "wof:placetype":"venue"
},
  "geometry": {"coordinates":[-85.509224,40.901775],"type":"Point"}
}