{
  "type": "Feature",
  "properties": {
    "iso:country":"US",
    "sg:address":"15800 W Co Rd 400 S",
    "sg:city":"Daleville",
    "sg:classifiers":[
        {
            "category":"Building & Trades",
            "subcategory":"Construction",
            "type":"Services"
        }
    ],
    "sg:phone":"+1 765 621 3687",
    "sg:postcode":"47334",
    "sg:province":"IN",
    "sg:tags":[
        "home",
        "builder"
    ],
    "wof:name":"Tocci Construction",
    "wof:placetype":"venue"
},
  "geometry": {"coordinates":[-85.57102,40.134946],"type":"Point"}
}