{
  "type": "Feature",
  "properties": {
    "iso:country":"US",
    "sg:address":"6960 S 500 E",
    "sg:city":"Lafayette",
    "sg:classifiers":[
        {
            "category":"Retail",
            "subcategory":"Repair Shop",
            "type":"Services"
        }
    ],
    "sg:phone":"+1 765 523 2366",
    "sg:postcode":"47909",
    "sg:province":"IN",
    "wof:name":"Second Loks Furn Rfnshing Antq",
    "wof:placetype":"venue"
},
  "geometry": {"coordinates":[-86.809214,40.33008],"type":"Point"}
}