{
  "type": "Feature",
  "properties": {
    "iso:country":"US",
    "sg:address":"307 E 3rd St",
    "sg:city":"Bloomington",
    "sg:classifiers":[
        {
            "category":"Restaurant",
            "type":"Food & Drink"
        }
    ],
    "sg:phone":"+1 812 333 5262",
    "sg:postcode":"47401",
    "sg:province":"IN",
    "sg:tags":[
        "chinese"
    ],
    "wof:name":"Lucky Express",
    "wof:placetype":"venue"
},
  "geometry": {"coordinates":[-86.53099400000001,39.164581],"type":"Point"}
}