{
  "type": "Feature",
  "properties": {
    "addr:full":"887 S State Rd 3 Rushville IN 46173",
    "addr:housenumber":"887",
    "addr:postcode":"46173",
    "addr:street":"S State Rd 3 Rushville",
    "iso:country":"US",
    "sg:address":"887 S State Rd 3",
    "sg:city":"Rushville",
    "sg:classifiers":[
        {
            "category":"Real Estate",
            "subcategory":"Real Estate Agent",
            "type":"Services"
        }
    ],
    "sg:phone":"+1 765 932 2160",
    "sg:postcode":"46173",
    "sg:province":"IN",
    "wof:name":"Schroeder-Hoff Real Estate",
    "wof:placetype":"venue"
},
  "geometry": {"coordinates":[-85.444838,39.615213],"type":"Point"}
}