{
  "type": "Feature",
  "properties": {
    "iso:country":"US",
    "sg:address":"2213 Scatterfield Rd",
    "sg:city":"Anderson",
    "sg:classifiers":[
        {
            "category":"Personal",
            "subcategory":"Beauty Salon",
            "type":"Services"
        }
    ],
    "sg:phone":"+1 765 622 1300",
    "sg:postcode":"46016",
    "sg:province":"IN",
    "sg:tags":[
        "manicuring"
    ],
    "wof:name":"Red Nail",
    "wof:placetype":"venue"
},
  "geometry": {"coordinates":[-85.65275099999999,40.09507],"type":"Point"}
}