{
  "type": "Feature",
  "properties": {
    "addr:full":"1804 Sheridan St Warsaw IN 46580",
    "addr:housenumber":"1804",
    "addr:postcode":"46580",
    "addr:street":"Sheridan St",
    "iso:country":"US",
    "sg:address":"1804 Sheridan St",
    "sg:city":"Warsaw",
    "sg:classifiers":[
        {
            "category":"Retail",
            "subcategory":"Laundry & Dry Cleaning",
            "type":"Services"
        }
    ],
    "sg:phone":"+1 574 269 2572",
    "sg:postcode":"46580",
    "sg:province":"IN",
    "wof:name":"Mr Tidy",
    "wof:placetype":"venue"
},
  "geometry": {"coordinates":[-85.832954,41.241739],"type":"Point"}
}