{
  "type": "Feature",
  "properties": {
    "addr:full":"5350 Cider Mill Ln Indianapolis IN 46226",
    "addr:housenumber":"5350",
    "addr:postcode":"46226",
    "addr:street":"Cider Mill Ln",
    "iso:country":"US",
    "sg:address":"5350 Cider Mill Ln",
    "sg:city":"Indianapolis",
    "sg:classifiers":[
        {
            "category":"Real Estate",
            "subcategory":"Real Estate Operator",
            "type":"Services"
        }
    ],
    "sg:phone":"+1 317 545 2226",
    "sg:postcode":"46226",
    "sg:province":"IN",
    "sg:tags":[
        "apartment"
    ],
    "wof:name":"Orchard Apartments",
    "wof:placetype":"venue"
},
  "geometry": {"coordinates":[-86.044516,39.849516],"type":"Point"}
}