{
  "type": "Feature",
  "properties": {
    "iso:country":"US",
    "sg:address":"3633 W State Blvd",
    "sg:city":"Fort Wayne",
    "sg:classifiers":[
        {
            "category":"Building & Trades",
            "subcategory":"Construction",
            "type":"Services"
        }
    ],
    "sg:phone":"+1 260 432 5124",
    "sg:postcode":"46808",
    "sg:province":"IN",
    "sg:tags":[
        "contractor"
    ],
    "wof:name":"Ebnit Builder & Real Estate",
    "wof:placetype":"venue"
},
  "geometry": {"coordinates":[-85.191598,41.095586],"type":"Point"}
}