{
  "type": "Feature",
  "properties": {
    "iso:country":"US",
    "sg:address":"487 State Rd 44",
    "sg:city":"Liberty",
    "sg:classifiers":[
        {
            "category":"Insurance",
            "subcategory":"Insurance Agent",
            "type":"Services"
        }
    ],
    "sg:phone":"+1 765 458 5189",
    "sg:postcode":"47353",
    "sg:province":"IN",
    "wof:name":"Farm Bureau Insurance",
    "wof:placetype":"venue"
},
  "geometry": {"coordinates":[-84.936114,39.635535],"type":"Point"}
}