{
  "type": "Feature",
  "properties": {
    "iso:country":"US",
    "sg:address":"16 Frederick St",
    "sg:city":"Logansport",
    "sg:classifiers":[
        {
            "category":"Autos & Motor Vehicles",
            "subcategory":"Automobile Sales",
            "type":"Retail Goods"
        }
    ],
    "sg:phone":"+1 574 753 2529",
    "sg:postcode":"46947",
    "sg:province":"IN",
    "sg:tags":[
        "used"
    ],
    "wof:name":"Scott Eakins Motor Sales",
    "wof:placetype":"venue"
},
  "geometry": {"coordinates":[-86.375983,40.767911],"type":"Point"}
}