{
  "type": "Feature",
  "properties": {
    "iso:country":"US",
    "sg:address":"160 N Park Ave",
    "sg:city":"Martinsville",
    "sg:classifiers":[
        {
            "category":"Government",
            "subcategory":"Fire Station",
            "type":"Public Place"
        }
    ],
    "sg:phone":"+1 765 342 8261",
    "sg:postcode":"46151",
    "sg:province":"IN",
    "sg:tags":[
        "department"
    ],
    "wof:name":"Green Twp Volunteer Fire Dept",
    "wof:placetype":"venue"
},
  "geometry": {"coordinates":[-86.437979,39.428798],"type":"Point"}
}