{
  "type": "Feature",
  "properties": {
    "addr:full":"5170 N Co Rd 1000 W Scipio IN 47273",
    "addr:housenumber":"5170",
    "addr:postcode":"47273",
    "addr:street":"N Co Rd 1000 W Scipio",
    "iso:country":"US",
    "sg:address":"5170 N Co Rd 1000 W",
    "sg:city":"Scipio",
    "sg:phone":"+1 812 445 3259",
    "sg:postcode":"47273",
    "sg:province":"IN",
    "sg:tags":[
        "farm",
        "corn",
        "soybean"
    ],
    "wof:name":"Gerald Helt",
    "wof:placetype":"venue"
},
  "geometry": {"coordinates":[-85.79849299999999,39.057695],"type":"Point"}
}