{
  "type": "Feature",
  "properties": {
    "iso:country":"US",
    "sg:address":"55 S Morton St",
    "sg:city":"Franklin",
    "sg:classifiers":[
        {
            "category":"Retail",
            "subcategory":"Auto Repair",
            "type":"Services"
        }
    ],
    "sg:phone":"+1 317 736 8282",
    "sg:postcode":"46131",
    "sg:province":"IN",
    "sg:tags":[
        "repairing",
        "automobile"
    ],
    "wof:name":"Franklin Muffler & Brakes",
    "wof:placetype":"venue"
},
  "geometry": {"coordinates":[-86.059259,39.4707],"type":"Point"}
}