{
  "type": "Feature",
  "properties": {
    "addr:full":"1545 Westminster Rd Evansville IN 47725",
    "addr:housenumber":"1545",
    "addr:postcode":"47725",
    "addr:street":"Westminster Rd",
    "iso:country":"US",
    "sg:address":"1545 Westminster Rd",
    "sg:city":"Evansville",
    "sg:classifiers":[
        {
            "category":"Building & Trades",
            "subcategory":"Construction",
            "type":"Services"
        }
    ],
    "sg:phone":"+1 812 867 2078",
    "sg:postcode":"47725",
    "sg:province":"IN",
    "sg:tags":[
        "designer",
        "dealer",
        "pool",
        "swimming"
    ],
    "wof:name":"Aquaguard Pools",
    "wof:placetype":"venue"
},
  "geometry": {"coordinates":[-87.53437,38.058627],"type":"Point"}
}