{
  "type": "Feature",
  "properties": {
    "iso:country":"US",
    "sg:address":"203 Columbia St",
    "sg:city":"Mishawaka",
    "sg:classifiers":[
        {
            "category":"Professional",
            "subcategory":"Engineering",
            "type":"Services"
        }
    ],
    "sg:phone":"+1 574 329 6742",
    "sg:postcode":"46544",
    "sg:province":"IN",
    "sg:tags":[
        "engineer"
    ],
    "wof:name":"Sybrsound Sound Engineers",
    "wof:placetype":"venue"
},
  "geometry": {"coordinates":[-86.195626,41.659192],"type":"Point"}
}