{
  "type": "Feature",
  "properties": {
    "iso:country":"US",
    "sg:address":"100 Crossroads Dr",
    "sg:city":"Whiteland",
    "sg:classifiers":[
        {
            "category":"Recreation",
            "type":"Entertainment"
        }
    ],
    "sg:phone":"+1 317 339 3567",
    "sg:postcode":"46184",
    "sg:province":"IN",
    "sg:tags":[
        "aquarium"
    ],
    "wof:name":"Ocean Reflections",
    "wof:placetype":"venue"
},
  "geometry": {"coordinates":[-86.095149,39.576934],"type":"Point"}
}