{
  "type": "Feature",
  "properties": {
    "iso:country":"US",
    "sg:address":"2455 N Tamarack Trl",
    "sg:city":"Bloomington",
    "sg:classifiers":[
        {
            "category":"Health Services",
            "subcategory":"Health Practitioner",
            "type":"Services"
        }
    ],
    "sg:phone":"+1 812 334 2589",
    "sg:postcode":"47408",
    "sg:province":"IN",
    "sg:tags":[
        "therapy",
        "physical"
    ],
    "wof:name":"Aegis Therapies",
    "wof:placetype":"venue"
},
  "geometry": {"coordinates":[-86.524968,39.192306],"type":"Point"}
}