{
  "type": "Feature",
  "properties": {
    "iso:country":"US",
    "sg:address":"1211 Tutor Ln",
    "sg:city":"Evansville",
    "sg:classifiers":[
        {
            "category":"Shopping",
            "type":"Retail Goods"
        }
    ],
    "sg:phone":"+1 812 473 8000",
    "sg:postcode":"47715",
    "sg:province":"IN",
    "sg:tags":[
        "hearing",
        "equipment",
        "supply",
        "impaired"
    ],
    "wof:name":"Beltone Hearing Aid Ctr",
    "wof:placetype":"venue"
},
  "geometry": {"coordinates":[-87.474937,37.989628],"type":"Point"}
}