{
  "type": "Feature",
  "properties": {
    "iso:country":"US",
    "sg:address":"2642 W State Rd 28",
    "sg:city":"Frankfort",
    "sg:classifiers":[
        {
            "category":"Manufacturing",
            "subcategory":"Chemicals & Compounds",
            "type":"Manufacturing & Wholesale Goods"
        }
    ],
    "sg:phone":"+1 765 659 1864",
    "sg:postcode":"46041",
    "sg:province":"IN",
    "sg:tags":[
        "lithographing",
        "ink"
    ],
    "wof:name":"Sun Chemical Gpi",
    "wof:placetype":"venue"
},
  "geometry": {"coordinates":[-86.555143,40.278961],"type":"Point"}
}