{
  "type": "Feature",
  "properties": {
    "addr:full":"120 S Center St Plainfield IN 46168",
    "addr:housenumber":"120",
    "addr:postcode":"46168",
    "addr:street":"S Center St",
    "iso:country":"US",
    "sg:address":"120 S Center St",
    "sg:city":"Plainfield",
    "sg:classifiers":[
        {
            "category":"Social Services",
            "type":"Services"
        },
        {
            "category":"Professional",
            "subcategory":"Employment Agencies",
            "type":"Services"
        },
        {
            "category":"Organizations",
            "subcategory":"Membership Organization",
            "type":"Services"
        }
    ],
    "sg:phone":"+1 317 837 9640",
    "sg:postcode":"46168",
    "sg:province":"IN",
    "sg:tags":[
        "workers'",
        "sorority",
        "placement",
        "fraternity",
        "volunteer"
    ],
    "wof:name":"Triangle Fraternity",
    "wof:placetype":"venue"
},
  "geometry": {"coordinates":[-86.40261599999999,39.702035],"type":"Point"}
}