{
  "type": "Feature",
  "properties": {
    "iso:country":"US",
    "sg:address":"4310 Wembley Ct",
    "sg:city":"Bloomington",
    "sg:classifiers":[
        {
            "category":"Professional",
            "subcategory":"Computer Services",
            "type":"Services"
        }
    ],
    "sg:phone":"+1 812 336 8044",
    "sg:postcode":"47408",
    "sg:province":"IN",
    "sg:tags":[
        "datum"
    ],
    "wof:name":"Ib4 Designs Company",
    "wof:placetype":"venue"
},
  "geometry": {"coordinates":[-86.475837,39.17157],"type":"Point"}
}