{
  "type": "Feature",
  "properties": {
    "iso:country":"US",
    "sg:address":"1407 Main St",
    "sg:city":"Anderson",
    "sg:classifiers":[
        {
            "category":"Shopping",
            "subcategory":"Used Merchandise",
            "type":"Retail Goods"
        }
    ],
    "sg:phone":"+1 765 622 9517",
    "sg:postcode":"46016",
    "sg:province":"IN",
    "sg:tags":[
        "antique"
    ],
    "wof:name":"Anderson Antique Mall",
    "wof:placetype":"venue"
},
  "geometry": {"coordinates":[-85.67822099999999,40.101468],"type":"Point"}
}