{
  "type": "Feature",
  "properties": {
    "iso:country":"US",
    "sg:address":"417 E Main St",
    "sg:city":"Greentown",
    "sg:classifiers":[
        {
            "category":"Retail",
            "subcategory":"Repair Shop",
            "type":"Services"
        }
    ],
    "sg:phone":"+1 765 628 2226",
    "sg:postcode":"46936",
    "sg:province":"IN",
    "sg:tags":[
        "scooter",
        "motorcycle",
        "motor"
    ],
    "wof:name":"Jugz Garage & V Twin Acces",
    "wof:placetype":"venue"
},
  "geometry": {"coordinates":[-85.962888,40.477903],"type":"Point"}
}