{
  "type": "Feature",
  "properties": {
    "iso:country":"US",
    "sg:address":"103 E Beaver St",
    "sg:city":"Corydon",
    "sg:classifiers":[
        {
            "category":"Professional",
            "subcategory":"Lawyer & Legal Services",
            "type":"Services"
        }
    ],
    "sg:phone":"+1 812 738 4061",
    "sg:postcode":"47112",
    "sg:province":"IN",
    "sg:tags":[
        "attorney"
    ],
    "wof:name":"John T Evans",
    "wof:placetype":"venue"
},
  "geometry": {"coordinates":[-86.125416,38.210944],"type":"Point"}
}