{
  "type": "Feature",
  "properties": {
    "iso:country":"US",
    "sg:address":"133 Works Rd",
    "sg:city":"Bennington",
    "sg:classifiers":[
        {
            "category":"Wholesale",
            "subcategory":"Machinery & Supplies",
            "type":"Manufacturing & Wholesale Goods"
        }
    ],
    "sg:phone":"+1 812 534 3471",
    "sg:postcode":"47011",
    "sg:province":"IN",
    "sg:tags":[
        "farm",
        "equipment"
    ],
    "wof:name":"Works Sales & Svc",
    "wof:placetype":"venue"
},
  "geometry": {"coordinates":[-85.030985,38.901751],"type":"Point"}
}