{
  "type": "Feature",
  "properties": {
    "iso:country":"US",
    "sg:address":"5150 E Margaret Dr",
    "sg:city":"Terre Haute",
    "sg:classifiers":[
        {
            "category":"Retail",
            "subcategory":"Laundry & Dry Cleaning",
            "type":"Services"
        }
    ],
    "sg:phone":"+1 812 877 9115",
    "sg:postcode":"47803",
    "sg:province":"IN",
    "sg:tags":[
        "uniform",
        "supply"
    ],
    "wof:name":"Cintas The Uniform People",
    "wof:placetype":"venue"
},
  "geometry": {"coordinates":[-87.341051,39.433843],"type":"Point"}
}