{
  "type": "Feature",
  "properties": {
    "iso:country":"US",
    "sg:address":"116 S Buffalo St",
    "sg:city":"Warsaw",
    "sg:classifiers":[
        {
            "category":"Manufacturing",
            "subcategory":"Glass & Minerals",
            "type":"Manufacturing & Wholesale Goods"
        }
    ],
    "sg:phone":"+1 574 269 5363",
    "sg:postcode":"46580",
    "sg:province":"IN",
    "sg:tags":[
        "fabricator",
        "fiber"
    ],
    "wof:name":"Makit",
    "wof:placetype":"venue"
},
  "geometry": {"coordinates":[-85.856717,41.237932],"type":"Point"}
}