{
  "type": "Feature",
  "properties": {
    "iso:country":"US",
    "sg:address":"721 Valley St",
    "sg:city":"Tipton",
    "sg:classifiers":[
        {
            "category":"Organizations",
            "subcategory":"Religious Organization",
            "type":"Services"
        }
    ],
    "sg:phone":"+1 765 675 4856",
    "sg:postcode":"46072",
    "sg:province":"IN",
    "wof:name":"Westrick Logan",
    "wof:placetype":"venue"
},
  "geometry": {"coordinates":[-86.031974,40.289571],"type":"Point"}
}