{
  "type": "Feature",
  "properties": {
    "addr:full":"311 Railroad St Angola IN 46703",
    "addr:housenumber":"311",
    "addr:postcode":"46703",
    "addr:street":"Railroad St",
    "iso:country":"US",
    "sg:address":"311 Railroad St",
    "sg:city":"Angola",
    "sg:classifiers":[
        {
            "category":"Building & Trades",
            "subcategory":"Construction",
            "type":"Services"
        }
    ],
    "sg:phone":"+1 260 665 1411",
    "sg:postcode":"46703",
    "sg:province":"IN",
    "sg:tags":[
        "concrete",
        "contractor"
    ],
    "wof:name":"Concrete Resurfacing",
    "wof:placetype":"venue"
},
  "geometry": {"coordinates":[-85.007273,41.634314],"type":"Point"}
}