{
  "type": "Feature",
  "properties": {
    "iso:country":"US",
    "sg:address":"2232 Blackmore St",
    "sg:city":"Madison",
    "sg:classifiers":[
        {
            "category":"Shopping",
            "subcategory":"Used Merchandise",
            "type":"Retail Goods"
        }
    ],
    "sg:phone":"+1 812 273 2231",
    "sg:postcode":"47250",
    "sg:province":"IN",
    "sg:tags":[
        "shop",
        "consignment"
    ],
    "wof:name":"Artsy Decor",
    "wof:placetype":"venue"
},
  "geometry": {"coordinates":[-85.393008,38.770794],"type":"Point"}
}