{
  "type": "Feature",
  "properties": {
    "iso:country":"US",
    "sg:address":"1629 S Packerton Rd",
    "sg:city":"Winona Lake",
    "sg:classifiers":[
        {
            "category":"Social Services",
            "subcategory":"Child Care",
            "type":"Services"
        }
    ],
    "sg:phone":"+1 574 268 1610",
    "sg:postcode":"46590",
    "sg:province":"IN",
    "sg:tags":[
        "day"
    ],
    "wof:name":"College Care Packages",
    "wof:placetype":"venue"
},
  "geometry": {"coordinates":[-85.806708,41.209512],"type":"Point"}
}