{
  "type": "Feature",
  "properties": {
    "iso:country":"US",
    "sg:address":"317 W 30th St",
    "sg:city":"Indianapolis",
    "sg:classifiers":[
        {
            "category":"Restaurant",
            "type":"Food & Drink"
        }
    ],
    "sg:phone":"+1 317 931 1000",
    "sg:postcode":"46208",
    "sg:province":"IN",
    "wof:name":"Vision Soul Food",
    "wof:placetype":"venue"
},
  "geometry": {"coordinates":[-86.163252,39.810054],"type":"Point"}
}