{
  "type": "Feature",
  "properties": {
    "iso:country":"US",
    "sg:address":"1457 Blaine Ave",
    "sg:city":"Indianapolis",
    "sg:classifiers":[
        {
            "category":"Personal",
            "subcategory":"Adult",
            "type":"Services"
        }
    ],
    "sg:phone":"+1 317 423 3224",
    "sg:postcode":"46221",
    "sg:province":"IN",
    "sg:tags":[
        "escort"
    ],
    "wof:name":"Skeet Spot",
    "wof:placetype":"venue"
},
  "geometry": {"coordinates":[-86.18830800000001,39.746788],"type":"Point"}
}