{
  "type": "Feature",
  "properties": {
    "addr:full":"3929 E 3rd St Bloomington IN 47401",
    "addr:housenumber":"3929",
    "addr:postcode":"47401",
    "addr:street":"E 3Rd St",
    "iso:country":"US",
    "sg:address":"3929 E 3rd St",
    "sg:city":"Bloomington",
    "sg:classifiers":[
        {
            "category":"Health Services",
            "subcategory":"Doctor",
            "type":"Services"
        }
    ],
    "sg:phone":"+1 812 339 7371",
    "sg:postcode":"47401",
    "sg:province":"IN",
    "sg:tags":[
        "surgeon",
        "oral"
    ],
    "wof:name":"Dr Rhett W Tharp DDS",
    "wof:placetype":"venue"
},
  "geometry": {"coordinates":[-86.480103,39.1642],"type":"Point"}
}