{
  "type": "Feature",
  "properties": {
    "addr:full":"701 E 4th St Mishawaka IN 46544",
    "addr:housenumber":"701",
    "addr:postcode":"46544",
    "addr:street":"E 4Th St",
    "iso:country":"US",
    "sg:address":"701 E 4th St",
    "sg:city":"Mishawaka",
    "sg:classifiers":[
        {
            "category":"Building & Trades",
            "subcategory":"Plumbing",
            "type":"Services"
        }
    ],
    "sg:phone":"+1 574 257 4363",
    "sg:postcode":"46544",
    "sg:province":"IN",
    "sg:tags":[
        "conditioning",
        "air",
        "system",
        "contractor"
    ],
    "wof:name":"Justice Heating & Air",
    "wof:placetype":"venue"
},
  "geometry": {"coordinates":[-86.167299,41.659414],"type":"Point"}
}