{
  "type": "Feature",
  "properties": {
    "iso:country":"US",
    "sg:address":"114 E Garro St",
    "sg:city":"Plymouth",
    "sg:classifiers":[
        {
            "category":"Freight",
            "type":"Transportation"
        }
    ],
    "sg:phone":"+1 574 936 7421",
    "sg:postcode":"46563",
    "sg:province":"IN",
    "sg:tags":[
        "commercial",
        "storage"
    ],
    "wof:name":"Plymouth U-Store Warehouse",
    "wof:placetype":"venue"
},
  "geometry": {"coordinates":[-86.30803899999999,41.340834],"type":"Point"}
}