{
  "type": "Feature",
  "properties": {
    "addr:full":"1713 E Elm St Griffith IN 46319",
    "addr:housenumber":"1713",
    "addr:postcode":"46319",
    "addr:street":"E Elm St",
    "iso:country":"US",
    "sg:address":"1713 E Elm St",
    "sg:city":"Griffith",
    "sg:classifiers":[
        {
            "category":"Shopping",
            "subcategory":"Used Merchandise",
            "type":"Retail Goods"
        }
    ],
    "sg:phone":"+1 219 924 2161",
    "sg:postcode":"46319",
    "sg:province":"IN",
    "sg:tags":[
        "antique"
    ],
    "wof:name":"Chrissie's Four Corners",
    "wof:placetype":"venue"
},
  "geometry": {"coordinates":[-87.410718,41.529892],"type":"Point"}
}