{
  "type": "Feature",
  "properties": {
    "iso:country":"US",
    "sg:address":"3370 State Rd 32 W",
    "sg:city":"Crawfordsville",
    "sg:classifiers":[
        {
            "category":"Manufacturing",
            "subcategory":"Printing",
            "type":"Manufacturing & Wholesale Goods"
        }
    ],
    "sg:phone":"+1 765 361 0382",
    "sg:postcode":"47933",
    "sg:province":"IN",
    "sg:tags":[
        "printer"
    ],
    "sg:website":"www.tonertek.com",
    "wof:name":"Toner Tek",
    "wof:placetype":"venue"
},
  "geometry": {"coordinates":[-86.965766,40.024764],"type":"Point"}
}