{
  "type": "Feature",
  "properties": {
    "addr:full":"2317 W Western Ave South Bend IN 46619",
    "addr:housenumber":"2317",
    "addr:postcode":"46619",
    "addr:street":"W Western Ave",
    "iso:country":"US",
    "sg:address":"2317 W Western Ave",
    "sg:city":"South Bend",
    "sg:classifiers":[
        {
            "category":"Banks & Credit Unions",
            "subcategory":"Bank",
            "type":"Services"
        }
    ],
    "sg:phone":"+1 574 237 3500",
    "sg:postcode":"46619",
    "sg:province":"IN",
    "sg:website":"www.towells.com",
    "wof:name":"Wells Fargo Bank",
    "wof:placetype":"venue"
},
  "geometry": {"coordinates":[-86.28313199999999,41.672164],"type":"Point"}
}