{
  "type": "Feature",
  "properties": {
    "addr:full":"3637 Grant St Gary IN 46408",
    "addr:housenumber":"3637",
    "addr:postcode":"46408",
    "addr:street":"Grant St Gary",
    "iso:country":"US",
    "sg:address":"3637 Grant St",
    "sg:city":"Gary",
    "sg:classifiers":[
        {
            "category":"Personal",
            "type":"Services"
        }
    ],
    "sg:phone":"+1 219 980 4800",
    "sg:postcode":"46408",
    "sg:province":"IN",
    "sg:tags":[
        "credit",
        "debt",
        "counseling"
    ],
    "wof:name":"Consumer Credit Counseling Svc",
    "wof:placetype":"venue"
},
  "geometry": {"coordinates":[-87.355796,41.552078],"type":"Point"}
}