{
  "type": "Feature",
  "properties": {
    "iso:country":"US",
    "sg:address":"1234 S 15th St",
    "sg:city":"Noblesville",
    "sg:classifiers":[
        {
            "category":"Organizations",
            "subcategory":"Religious Organization",
            "type":"Services"
        }
    ],
    "sg:phone":"+1 317 773 5031",
    "sg:postcode":"46060",
    "sg:province":"IN",
    "sg:tags":[
        "church"
    ],
    "wof:name":"Lighthouse Fellowship",
    "wof:placetype":"venue"
},
  "geometry": {"coordinates":[-86.006227,40.034289],"type":"Point"}
}