{
  "type": "Feature",
  "properties": {
    "iso:country":"US",
    "sg:address":"305 S 13th St",
    "sg:city":"Terre Haute",
    "sg:classifiers":[
        {
            "category":"Professional",
            "subcategory":"Computer Services",
            "type":"Services"
        }
    ],
    "sg:phone":"+1 812 478 9020",
    "sg:postcode":"47807",
    "sg:province":"IN",
    "sg:tags":[
        "home",
        "consulting",
        "page",
        "dev",
        "internet"
    ],
    "wof:name":"Private Web Communities Inc",
    "wof:placetype":"venue"
},
  "geometry": {"coordinates":[-87.39774199999999,39.463473],"type":"Point"}
}