{
  "type": "Feature",
  "properties": {
    "iso:country":"US",
    "sg:address":"604 E 3rd St",
    "sg:city":"Hobart",
    "sg:classifiers":[
        {
            "category":"Shopping",
            "subcategory":"Clothing, Apparel, & Fashions",
            "type":"Retail Goods"
        },
        {
            "category":"Shopping",
            "subcategory":"Crafts & Fabrics",
            "type":"Retail Goods"
        }
    ],
    "sg:phone":"+1 219 942 5101",
    "sg:postcode":"46342",
    "sg:province":"IN",
    "sg:tags":[
        "shop",
        "apparel",
        "racing",
        "sportswear",
        "merchandise"
    ],
    "wof:name":"Easton's Lettering Service",
    "wof:placetype":"venue"
},
  "geometry": {"coordinates":[-87.25366200000001,41.532444],"type":"Point"}
}