{
  "type": "Feature",
  "properties": {
    "iso:country":"US",
    "sg:address":"1732 E McKinley Ave",
    "sg:city":"Mishawaka",
    "sg:classifiers":[
        {
            "category":"Wholesale",
            "subcategory":"Auto Parts",
            "type":"Manufacturing & Wholesale Goods"
        }
    ],
    "sg:phone":"+1 574 259 4644",
    "sg:postcode":"46545",
    "sg:province":"IN",
    "sg:tags":[
        "automobile",
        "rebuilt"
    ],
    "wof:name":"Mike's Auto Salvage",
    "wof:placetype":"venue"
},
  "geometry": {"coordinates":[-86.156685,41.680368],"type":"Point"}
}