{
  "type": "Feature",
  "properties": {
    "iso:country":"US",
    "sg:address":"1014 S Monticello St",
    "sg:city":"Winamac",
    "sg:classifiers":[
        {
            "category":"Autos & Motor Vehicles",
            "subcategory":"Automobile Sales",
            "type":"Retail Goods"
        }
    ],
    "sg:phone":"+1 574 946 6662",
    "sg:postcode":"46996",
    "sg:province":"IN",
    "sg:tags":[
        "car",
        "dealer"
    ],
    "wof:name":"Braun Chevrolet Buick Inc",
    "wof:placetype":"venue"
},
  "geometry": {"coordinates":[-86.598341,41.04384],"type":"Point"}
}