{
  "type": "Feature",
  "properties": {
    "iso:country":"US",
    "sg:address":"487 Broadway",
    "sg:city":"Gary",
    "sg:classifiers":[
        {
            "category":"Arts & Performance",
            "subcategory":"Theater",
            "type":"Entertainment"
        }
    ],
    "sg:phone":"+1 219 882 5354",
    "sg:postcode":"46407",
    "sg:province":"IN",
    "wof:name":"Cultural Consortium",
    "wof:placetype":"venue"
},
  "geometry": {"coordinates":[-87.33710499999999,41.603648],"type":"Point"}
}