{
  "type": "Feature",
  "properties": {
    "iso:country":"US",
    "sg:address":"929 12th St",
    "sg:city":"Tell City",
    "sg:classifiers":[
        {
            "category":"Health Services",
            "subcategory":"Doctor",
            "type":"Services"
        }
    ],
    "sg:phone":"+1 812 548 0086",
    "sg:postcode":"47586",
    "sg:province":"IN",
    "sg:tags":[
        "physician",
        "surgeon"
    ],
    "wof:name":"Liberty Laboratory",
    "wof:placetype":"venue"
},
  "geometry": {"coordinates":[-86.764578,37.954862],"type":"Point"}
}