{
  "type": "Feature",
  "properties": {
    "addr:full":"7215 W 10th St Indianapolis IN 46214",
    "addr:housenumber":"7215",
    "addr:postcode":"46214",
    "addr:street":"W 10Th St",
    "iso:country":"US",
    "sg:address":"7215 W 10th St",
    "sg:city":"Indianapolis",
    "sg:classifiers":[
        {
            "category":"Retail",
            "subcategory":"Repair Shop",
            "type":"Services"
        }
    ],
    "sg:phone":"+1 317 247 7363",
    "sg:postcode":"46214",
    "sg:province":"IN",
    "sg:tags":[
        "lock",
        "locksmith"
    ],
    "wof:name":"A Affordable Lock Svc",
    "wof:placetype":"venue"
},
  "geometry": {"coordinates":[-86.28888499999999,39.77915],"type":"Point"}
}