{
  "type": "Feature",
  "properties": {
    "iso:country":"US",
    "sg:address":"316 W Indiana Ave",
    "sg:city":"Chesterton",
    "sg:classifiers":[
        {
            "category":"Personal",
            "type":"Services"
        }
    ],
    "sg:phone":"+1 219 926 5901",
    "sg:postcode":"46304",
    "sg:province":"IN",
    "sg:tags":[
        "therapist",
        "massage"
    ],
    "wof:name":"Gloria Piette's Therapeutic",
    "wof:placetype":"venue"
},
  "geometry": {"coordinates":[-87.055711,41.610129],"type":"Point"}
}