{
  "type": "Feature",
  "properties": {
    "iso:country":"US",
    "sg:address":"770 N Range Line Rd",
    "sg:city":"Carmel",
    "sg:classifiers":[
        {
            "category":"Professional",
            "subcategory":"Business Services",
            "type":"Services"
        }
    ],
    "sg:phone":"+1 317 848 3847",
    "sg:postcode":"46032",
    "sg:province":"IN",
    "wof:name":"Azmyth Recording Studio",
    "wof:placetype":"venue"
},
  "geometry": {"coordinates":[-86.12716899999999,39.985308],"type":"Point"}
}