{
  "type": "Feature",
  "properties": {
    "addr:full":"210 S Capitol Ave Indianapolis IN 46225",
    "addr:housenumber":"210",
    "addr:postcode":"46225",
    "addr:street":"S Capitol Ave",
    "iso:country":"US",
    "sg:address":"210 S Capitol Ave",
    "sg:city":"Indianapolis",
    "sg:classifiers":[
        {
            "category":"Organizations",
            "subcategory":"Professional Association",
            "type":"Services"
        }
    ],
    "sg:phone":"+1 317 829 5600",
    "sg:postcode":"46225",
    "sg:province":"IN",
    "wof:name":"Black Coaches Assoc",
    "wof:placetype":"venue"
},
  "geometry": {"coordinates":[-86.16193,39.763365],"type":"Point"}
}