{
  "type": "Feature",
  "properties": {
    "iso:country":"US",
    "sg:address":"4211 Clubview Dr",
    "sg:city":"Fort Wayne",
    "sg:classifiers":[
        {
            "category":"Building & Trades",
            "subcategory":"Electrical",
            "type":"Services"
        }
    ],
    "sg:phone":"+1 260 432 4556",
    "sg:postcode":"46804",
    "sg:province":"IN",
    "sg:tags":[
        "installation"
    ],
    "wof:name":"Professional Systems Install",
    "wof:placetype":"venue"
},
  "geometry": {"coordinates":[-85.197922,41.041818],"type":"Point"}
}