{
  "type": "Feature",
  "properties": {
    "addr:full":"11039 Co Rd 126 Middlebury IN 46540",
    "addr:housenumber":"11039",
    "addr:postcode":"46540",
    "addr:street":"Co Rd 126",
    "iso:country":"US",
    "sg:address":"11039 Co Rd 126",
    "sg:city":"Middlebury",
    "sg:classifiers":[
        {
            "category":"Farming",
            "subcategory":"Dairy Farm",
            "type":"Manufacturing & Wholesale Goods"
        }
    ],
    "sg:phone":"+1 574 825 2508",
    "sg:postcode":"46540",
    "sg:province":"IN",
    "wof:name":"Loyal Acres Inc",
    "wof:placetype":"venue"
},
  "geometry": {"coordinates":[-85.679731,41.617483],"type":"Point"}
}