{
  "type": "Feature",
  "properties": {
    "iso:country":"US",
    "sg:address":"2719 W 236th St",
    "sg:city":"Sheridan",
    "sg:classifiers":[
        {
            "category":"Real Estate",
            "subcategory":"Real Estate Agent",
            "type":"Services"
        }
    ],
    "sg:phone":"+1 317 758 4547",
    "sg:postcode":"46069",
    "sg:province":"IN",
    "wof:name":"Remax Hometown Agents",
    "wof:placetype":"venue"
},
  "geometry": {"coordinates":[-86.209978,40.129919],"type":"Point"}
}