{
  "type": "Feature",
  "properties": {
    "iso:country":"US",
    "sg:address":"135 N Shortridge Rd",
    "sg:city":"Indianapolis",
    "sg:classifiers":[
        {
            "category":"Health Services",
            "subcategory":"Doctor",
            "type":"Services"
        }
    ],
    "sg:phone":"+1 317 357 8548",
    "sg:postcode":"46219",
    "sg:province":"IN",
    "sg:tags":[
        "dentist"
    ],
    "wof:name":"East Indianapolis Dental Assoc",
    "wof:placetype":"venue"
},
  "geometry": {"coordinates":[-86.040544,39.776797],"type":"Point"}
}