{
  "type": "Feature",
  "properties": {
    "iso:country":"US",
    "sg:address":"204 S Main St",
    "sg:city":"South Bend",
    "sg:classifiers":[
        {
            "category":"Government",
            "subcategory":"Office",
            "type":"Public Place"
        }
    ],
    "sg:phone":"+1 574 246 8150",
    "sg:postcode":"46601",
    "sg:province":"IN",
    "wof:name":"Honorable Kenneth F Ripple",
    "wof:placetype":"venue"
},
  "geometry": {"coordinates":[-86.251867,41.674385],"type":"Point"}
}