{
  "type": "Feature",
  "properties": {
    "iso:country":"US",
    "sg:address":"125 Spriggs Blvd",
    "sg:city":"Bloomington",
    "sg:classifiers":[
        {
            "category":"Food & Beverages",
            "subcategory":"Bakery",
            "type":"Retail Goods"
        }
    ],
    "sg:phone":"+1 812 825 8449",
    "sg:postcode":"47403",
    "sg:province":"IN",
    "wof:name":"James E Dunbar",
    "wof:placetype":"venue"
},
  "geometry": {"coordinates":[-86.59994,39.16449],"type":"Point"}
}