{
  "type": "Feature",
  "properties": {
    "iso:country":"US",
    "sg:address":"15 S Cedar Cliff Dr",
    "sg:city":"Madison",
    "sg:classifiers":[
        {
            "category":"Building & Trades",
            "subcategory":"Construction",
            "type":"Services"
        }
    ],
    "sg:phone":"+1 812 265 2190",
    "sg:postcode":"47250",
    "sg:province":"IN",
    "wof:name":"Abe Babe Construction",
    "wof:placetype":"venue"
},
  "geometry": {"coordinates":[-85.345609,38.738463],"type":"Point"}
}