{
  "type": "Feature",
  "properties": {
    "addr:full":"23959 Co Rd 106 Elkhart IN 46514",
    "addr:housenumber":"23959;106",
    "addr:postcode":"46514",
    "addr:street":"Co Rd",
    "iso:country":"US",
    "sg:address":"23959 Co Rd 106",
    "sg:city":"Elkhart",
    "sg:classifiers":[
        {
            "category":"Recreation",
            "type":"Entertainment"
        }
    ],
    "sg:phone":"+1 574 264 0611",
    "sg:postcode":"46514",
    "sg:province":"IN",
    "sg:tags":[
        "tennis",
        "court"
    ],
    "wof:name":"Eastlake Athletic Club",
    "wof:placetype":"venue"
},
  "geometry": {"coordinates":[-85.923394,41.716858],"type":"Point"}
}