{
  "type": "Feature",
  "properties": {
    "iso:country":"US",
    "sg:address":"109 W Market St",
    "sg:city":"Warsaw",
    "sg:classifiers":[
        {
            "category":"Organizations",
            "subcategory":"Non-profit Organization",
            "type":"Services"
        }
    ],
    "sg:phone":"+1 574 267 3481",
    "sg:postcode":"46580",
    "sg:province":"IN",
    "sg:tags":[
        "alternative",
        "abortion"
    ],
    "sg:website":"www.kcrtl.org",
    "wof:name":"Right To Life Of Kosciusko",
    "wof:placetype":"venue"
},
  "geometry": {"coordinates":[-85.857887,41.237027],"type":"Point"}
}