{
  "type": "Feature",
  "properties": {
    "iso:country":"US",
    "sg:address":"601 E 199th St",
    "sg:city":"Westfield",
    "sg:classifiers":[
        {
            "category":"Building & Trades",
            "subcategory":"Landscaping Services",
            "type":"Services"
        }
    ],
    "sg:phone":"+1 317 758 9055",
    "sg:postcode":"46074",
    "sg:province":"IN",
    "sg:tags":[
        "company",
        "landscape"
    ],
    "wof:name":"Robinson Outdoor Services",
    "wof:placetype":"venue"
},
  "geometry": {"coordinates":[-86.14708,40.076102],"type":"Point"}
}