{
  "type": "Feature",
  "properties": {
    "iso:country":"US",
    "sg:address":"1019 Conkey St",
    "sg:city":"Hammond",
    "sg:classifiers":[
        {
            "category":"Shopping",
            "subcategory":"Clothing, Apparel, & Fashions",
            "type":"Retail Goods"
        }
    ],
    "sg:phone":"+1 219 932 4155",
    "sg:postcode":"46320",
    "sg:province":"IN",
    "sg:tags":[
        "woman"
    ],
    "wof:name":"Elegance & Grace Boutique",
    "wof:placetype":"venue"
},
  "geometry": {"coordinates":[-87.502883,41.601099],"type":"Point"}
}