{
  "type": "Feature",
  "properties": {
    "iso:country":"US",
    "sg:address":"2200 McKinley Ave",
    "sg:city":"South Bend",
    "sg:classifiers":[
        {
            "category":"Organizations",
            "subcategory":"Community Association",
            "type":"Services"
        }
    ],
    "sg:phone":"+1 574 282 3726",
    "sg:postcode":"46615",
    "sg:province":"IN",
    "sg:tags":[
        "club"
    ],
    "wof:name":"Club House",
    "wof:placetype":"venue"
},
  "geometry": {"coordinates":[-86.214965,41.680223],"type":"Point"}
}