{
  "type": "Feature",
  "properties": {
    "iso:country":"US",
    "sg:address":"3611 Ferguson Rd",
    "sg:city":"Indianapolis",
    "sg:classifiers":[
        {
            "category":"Social Services",
            "subcategory":"Child Care",
            "type":"Services"
        }
    ],
    "sg:phone":"+1 317 862 3014",
    "sg:postcode":"46239",
    "sg:province":"IN",
    "wof:name":"Small Miracles Children's Ctr",
    "wof:placetype":"venue"
},
  "geometry": {"coordinates":[-86.030232,39.710503],"type":"Point"}
}