{
  "type": "Feature",
  "properties": {
    "iso:country":"US",
    "sg:address":"3508 Helmsburg Rd",
    "sg:city":"Nashville",
    "sg:classifiers":[
        {
            "category":"Wholesale",
            "subcategory":"Durable Goods & Equipment",
            "type":"Manufacturing & Wholesale Goods"
        }
    ],
    "sg:phone":"+1 812 988 9889",
    "sg:postcode":"47448",
    "sg:province":"IN",
    "sg:tags":[
        "magnet",
        "magnetic",
        "devices"
    ],
    "wof:name":"Magnet Mania",
    "wof:placetype":"venue"
},
  "geometry": {"coordinates":[-86.29078,39.249254],"type":"Point"}
}