{
  "type": "Feature",
  "properties": {
    "iso:country":"US",
    "sg:address":"1230 Jefferson Ave",
    "sg:city":"Shelbyville",
    "sg:classifiers":[
        {
            "category":"Building & Trades",
            "subcategory":"Construction",
            "type":"Services"
        }
    ],
    "sg:phone":"+1 317 398 9873",
    "sg:postcode":"46176",
    "sg:province":"IN",
    "sg:tags":[
        "resurfacing",
        "laying",
        "refinishing",
        "floor"
    ],
    "sg:website":"www.yagerbowl.com",
    "wof:name":"Yager Hardwood Flooring",
    "wof:placetype":"venue"
},
  "geometry": {"coordinates":[-85.777032,39.513236],"type":"Point"}
}