{
  "type": "Feature",
  "properties": {
    "iso:country":"US",
    "sg:address":"8229 Indy Ln",
    "sg:city":"Indianapolis",
    "sg:classifiers":[
        {
            "category":"Manufacturing",
            "subcategory":"Tools & Machinery",
            "type":"Manufacturing & Wholesale Goods"
        }
    ],
    "sg:phone":"+1 317 209 8238",
    "sg:postcode":"46214",
    "sg:province":"IN",
    "sg:tags":[
        "machine",
        "shop"
    ],
    "wof:name":"Merit Machine Inc",
    "wof:placetype":"venue"
},
  "geometry": {"coordinates":[-86.305377,39.789238],"type":"Point"}
}