{
  "type": "Feature",
  "properties": {
    "iso:country":"US",
    "sg:address":"5328 Thornleigh Dr",
    "sg:city":"Indianapolis",
    "sg:classifiers":[
        {
            "category":"Professional",
            "subcategory":"Management & Consulting",
            "type":"Services"
        }
    ],
    "sg:phone":"+1 317 997 8934",
    "sg:postcode":"46226",
    "sg:province":"IN",
    "sg:tags":[
        "sound",
        "consultant",
        "system"
    ],
    "wof:name":"Naptown Sounds Recording",
    "wof:placetype":"venue"
},
  "geometry": {"coordinates":[-86.07688,39.843425],"type":"Point"}
}