{
  "type": "Feature",
  "properties": {
    "iso:country":"US",
    "sg:address":"1756 W 100 S",
    "sg:city":"Portland",
    "sg:classifiers":[
        {
            "category":"Health Services",
            "subcategory":"Health Practitioner",
            "type":"Services"
        }
    ],
    "sg:phone":"+1 260 726 4020",
    "sg:postcode":"47371",
    "sg:province":"IN",
    "sg:tags":[
        "therapist",
        "physical"
    ],
    "wof:name":"CHS Health Strategies",
    "wof:placetype":"venue"
},
  "geometry": {"coordinates":[-85.014893,40.424564],"type":"Point"}
}