{
  "type": "Feature",
  "properties": {
    "iso:country":"US",
    "sg:address":"88 E Washington St",
    "sg:city":"Medora",
    "sg:classifiers":[
        {
            "category":"Personal",
            "subcategory":"Beauty Salon",
            "type":"Services"
        }
    ],
    "sg:phone":"+1 812 966 2813",
    "sg:postcode":"47260",
    "sg:province":"IN",
    "wof:name":"Donna's Beauty Shop",
    "wof:placetype":"venue"
},
  "geometry": {"coordinates":[-86.167948,38.822219],"type":"Point"}
}