{
  "type": "Feature",
  "properties": {
    "iso:country":"US",
    "sg:address":"511 N 4th St",
    "sg:city":"Lafayette",
    "sg:classifiers":[
        {
            "category":"Personal",
            "subcategory":"Beauty Salon",
            "type":"Services"
        }
    ],
    "sg:phone":"+1 765 742 1410",
    "sg:postcode":"47901",
    "sg:province":"IN",
    "sg:tags":[
        "shop"
    ],
    "wof:name":"Marianne's Place",
    "wof:placetype":"venue"
},
  "geometry": {"coordinates":[-86.893031,40.422629],"type":"Point"}
}