{
  "type": "Feature",
  "properties": {
    "addr:full":"8237 N Fox Hollow Rd Bloomington IN 47408",
    "addr:housenumber":"8237",
    "addr:postcode":"47408",
    "addr:street":"N Fox Hollow Rd",
    "iso:country":"US",
    "sg:address":"8237 N Fox Hollow Rd",
    "sg:city":"Bloomington",
    "sg:classifiers":[
        {
            "category":"Building & Trades",
            "subcategory":"Construction",
            "type":"Services"
        }
    ],
    "sg:phone":"+1 812 325 7408",
    "sg:postcode":"47408",
    "sg:province":"IN",
    "sg:tags":[
        "paving",
        "contractor"
    ],
    "wof:name":"Griffin Paving",
    "wof:placetype":"venue"
},
  "geometry": {"coordinates":[-86.51244699999999,39.28231],"type":"Point"}
}