{
  "type": "Feature",
  "properties": {
    "iso:country":"US",
    "sg:address":"709 Roosevelt Ave",
    "sg:city":"Edinburgh",
    "sg:classifiers":[
        {
            "category":"Building & Trades",
            "subcategory":"Cleaning & Sanitation",
            "type":"Services"
        }
    ],
    "sg:phone":"+1 812 526 8520",
    "sg:postcode":"46124",
    "sg:province":"IN",
    "sg:tags":[
        "janitor"
    ],
    "wof:name":"Dirt B Gone Ind Cleaning",
    "wof:placetype":"venue"
},
  "geometry": {"coordinates":[-85.963999,39.348442],"type":"Point"}
}