{
  "type": "Feature",
  "properties": {
    "addr:full":"6254 W Co Rd 500 N Kokomo IN 46978",
    "addr:housenumber":"6254;500",
    "addr:postcode":"46978",
    "addr:street":"W Co Rd;N",
    "iso:country":"US",
    "sg:address":"6254 W Co Rd 500 N",
    "sg:city":"Kokomo",
    "sg:classifiers":[
        {
            "category":"Building & Trades",
            "subcategory":"Construction",
            "type":"Services"
        }
    ],
    "sg:phone":"+1 765 452 7089",
    "sg:postcode":"46978",
    "sg:province":"IN",
    "sg:tags":[
        "general",
        "contractor"
    ],
    "wof:name":"T W General Contracting Svc",
    "wof:placetype":"venue"
},
  "geometry": {"coordinates":[-86.49223499999999,40.837639],"type":"Point"}
}