{
  "type": "Feature",
  "properties": {
    "addr:full":"216 E Broadway St Brook IN 47922",
    "addr:housenumber":"216",
    "addr:postcode":"47922",
    "addr:street":"E Broadway St",
    "iso:country":"US",
    "sg:address":"216 E Broadway St",
    "sg:city":"Brook",
    "sg:classifiers":[
        {
            "category":"Building & Trades",
            "subcategory":"Construction",
            "type":"Services"
        }
    ],
    "sg:phone":"+1 219 275 4402",
    "sg:postcode":"47922",
    "sg:province":"IN",
    "sg:tags":[
        "house",
        "residential"
    ],
    "wof:name":"Dennies Construction",
    "wof:placetype":"venue"
},
  "geometry": {"coordinates":[-87.361181,40.864677],"type":"Point"}
}