{
  "type": "Feature",
  "properties": {
    "iso:country":"US",
    "sg:address":"18997 Casey Rd",
    "sg:city":"Sheridan",
    "sg:classifiers":[
        {
            "category":"Building & Trades",
            "subcategory":"Landscaping Services",
            "type":"Services"
        }
    ],
    "sg:phone":"+1 317 867 1740",
    "sg:postcode":"46074",
    "sg:province":"IN",
    "sg:tags":[
        "landscape",
        "contractor"
    ],
    "sg:website":"www.riclandscaping.com",
    "wof:name":"Roudebush Improvement Corp",
    "wof:placetype":"venue"
},
  "geometry": {"coordinates":[-86.17982000000001,40.062653],"type":"Point"}
}