{
  "type": "Feature",
  "properties": {
    "iso:country":"US",
    "sg:address":"3524 Co Rd 750",
    "sg:city":"Wheatfield",
    "sg:classifiers":[
        {
            "category":"Shopping",
            "subcategory":"Crafts & Fabrics",
            "type":"Retail Goods"
        }
    ],
    "sg:phone":"+1 219 956 4171",
    "sg:postcode":"46392",
    "sg:province":"IN",
    "sg:tags":[
        "sewing"
    ],
    "wof:name":"Fabric Cottage",
    "wof:placetype":"venue"
},
  "geometry": {"coordinates":[-86.978339,41.121738],"type":"Point"}
}