{
  "type": "Feature",
  "properties": {
    "iso:country":"US",
    "sg:address":"10738 Belmont Cir",
    "sg:city":"Indianapolis",
    "sg:classifiers":[
        {
            "category":"Insurance",
            "subcategory":"Insurance Agent",
            "type":"Services"
        }
    ],
    "sg:phone":"+1 317 575 4140",
    "sg:postcode":"46280",
    "sg:province":"IN",
    "wof:name":"Stuart & Co Group Ins Broker",
    "wof:placetype":"venue"
},
  "geometry": {"coordinates":[-86.139755,39.946927],"type":"Point"}
}