{
  "type": "Feature",
  "properties": {
    "iso:country":"US",
    "sg:address":"P.O. Box 2467 c/o Aubice LLC",
    "sg:city":"West Lafayette",
    "sg:classifiers":[
        {
            "category":"Professional",
            "subcategory":"Computer Services",
            "type":"Services"
        }
    ],
    "sg:phone":"+1 765 588 1009",
    "sg:postcode":"47996-2467",
    "sg:province":"IN",
    "sg:tags":[
        "social-network",
        "social-search",
        "link",
        "share",
        "browser",
        "add-on",
        "search",
        "bookmarking"
    ],
    "sg:website":"http://www.searchlikeme.com",
    "wof:name":"SLiM Search Technologies",
    "wof:placetype":"venue"
},
  "geometry": {"coordinates":[-86.894908,40.388656],"type":"Point"}
}