{
  "type": "Feature",
  "properties": {
    "iso:country":"US",
    "sg:address":"68 S Jefferson St",
    "sg:city":"Danville",
    "sg:classifiers":[
        {
            "category":"Real Estate",
            "subcategory":"Real Estate Agent",
            "type":"Services"
        }
    ],
    "sg:phone":"+1 317 745 1996",
    "sg:postcode":"46122",
    "sg:province":"IN",
    "wof:name":"Port Wood Realty",
    "wof:placetype":"venue"
},
  "geometry": {"coordinates":[-86.52514,39.760147],"type":"Point"}
}