{
  "type": "Feature",
  "properties": {
    "iso:country":"US",
    "sg:address":"310 E 20th St",
    "sg:city":"Bloomington",
    "sg:classifiers":[
        {
            "category":"Real Estate",
            "subcategory":"Real Estate Operator",
            "type":"Services"
        }
    ],
    "sg:phone":"+1 812 333 9201",
    "sg:postcode":"47408",
    "sg:province":"IN",
    "sg:tags":[
        "apartment"
    ],
    "wof:name":"Stadium View Apartments",
    "wof:placetype":"venue"
},
  "geometry": {"coordinates":[-86.528325,39.181795],"type":"Point"}
}