{
  "type": "Feature",
  "properties": {
    "iso:country":"US",
    "sg:address":"2208 Miami Rd",
    "sg:city":"South Bend",
    "sg:classifiers":[
        {
            "category":"Shopping",
            "subcategory":"Florist",
            "type":"Retail Goods"
        }
    ],
    "sg:phone":"+1 574 287 2811",
    "sg:postcode":"46613",
    "sg:province":"IN",
    "wof:name":"Miami Florist & Gift Shoppe",
    "wof:placetype":"venue"
},
  "geometry": {"coordinates":[-86.234821,41.651986],"type":"Point"}
}