{
  "type": "Feature",
  "properties": {
    "addr:full":"2075 Main St Lafayette IN 47904",
    "addr:housenumber":"2075",
    "addr:postcode":"47904",
    "addr:street":"Main St",
    "iso:country":"US",
    "sg:address":"2075 Main St",
    "sg:city":"Lafayette",
    "sg:classifiers":[
        {
            "category":"Insurance",
            "subcategory":"Insurance Agent",
            "type":"Services"
        }
    ],
    "sg:phone":"+1 765 447 3708",
    "sg:postcode":"47904",
    "sg:province":"IN",
    "wof:name":"State Farm Insurance",
    "wof:placetype":"venue"
},
  "geometry": {"coordinates":[-86.87305600000001,40.412298],"type":"Point"}
}