{
  "type": "Feature",
  "properties": {
    "addr:full":"1223 Chicago Ave Goshen IN 46528",
    "addr:housenumber":"1223",
    "addr:postcode":"46528",
    "addr:street":"Chicago Ave",
    "iso:country":"US",
    "sg:address":"1223 Chicago Ave",
    "sg:city":"Goshen",
    "sg:classifiers":[
        {
            "category":"Wholesale",
            "subcategory":"Machinery & Supplies",
            "type":"Manufacturing & Wholesale Goods"
        }
    ],
    "sg:phone":"+1 574 533 8565",
    "sg:postcode":"46528",
    "sg:province":"IN",
    "sg:tags":[
        "equipment",
        "industrial"
    ],
    "wof:name":"Hoosier Industrial Supply",
    "wof:placetype":"venue"
},
  "geometry": {"coordinates":[-85.852198,41.593676],"type":"Point"}
}