{
  "type": "Feature",
  "properties": {
    "addr:full":"2816 Calumet Ave Valparaiso IN 46383",
    "addr:housenumber":"2816",
    "addr:postcode":"46383",
    "addr:street":"Calumet Ave",
    "iso:country":"US",
    "sg:address":"2816 Calumet Ave",
    "sg:city":"Valparaiso",
    "sg:classifiers":[
        {
            "category":"Fast Food",
            "type":"Food & Drink"
        },
        {
            "category":"Restaurant",
            "type":"Food & Drink"
        }
    ],
    "sg:phone":"+1 219 464 2996",
    "sg:postcode":"46383",
    "sg:province":"IN",
    "sg:tags":[
        "style",
        "hamburger",
        "dog",
        "family",
        "hot"
    ],
    "wof:name":"Schoop's Hamburgers",
    "wof:placetype":"venue"
},
  "geometry": {"coordinates":[-87.04628700000001,41.493029],"type":"Point"}
}