{
  "type": "Feature",
  "properties": {
    "iso:country":"US",
    "sg:address":"1457 W 100 N",
    "sg:city":"Portland",
    "sg:classifiers":[
        {
            "category":"Banks & Credit Unions",
            "subcategory":"Financial Services",
            "type":"Services"
        }
    ],
    "sg:phone":"+1 260 726 6415",
    "sg:postcode":"47371",
    "sg:province":"IN",
    "sg:tags":[
        "trust",
        "management"
    ],
    "wof:name":"Howard Ontrop",
    "wof:placetype":"venue"
},
  "geometry": {"coordinates":[-85.007762,40.453384],"type":"Point"}
}