{
  "type": "Feature",
  "properties": {
    "iso:country":"US",
    "sg:address":"4301 Champlain Dr",
    "sg:city":"Fort Wayne",
    "sg:classifiers":[
        {
            "category":"Social Services",
            "subcategory":"Child Care",
            "type":"Services"
        }
    ],
    "sg:phone":"+1 260 744 0412",
    "sg:postcode":"46806",
    "sg:province":"IN",
    "wof:name":"Our Heavenly Fathers Daycare",
    "wof:placetype":"venue"
},
  "geometry": {"coordinates":[-85.133359,41.045314],"type":"Point"}
}