{
  "type": "Feature",
  "properties": {
    "iso:country":"US",
    "sg:address":"500 W Main St",
    "sg:city":"Centerville",
    "sg:classifiers":[
        {
            "category":"Real Estate",
            "subcategory":"Real Estate Operator",
            "type":"Services"
        }
    ],
    "sg:phone":"+1 765 855 3321",
    "sg:postcode":"47330",
    "sg:province":"IN",
    "sg:tags":[
        "property",
        "lessor"
    ],
    "wof:name":"Lowell Brooks",
    "wof:placetype":"venue"
},
  "geometry": {"coordinates":[-85.002705,39.81753],"type":"Point"}
}