{
  "type": "Feature",
  "properties": {
    "iso:country":"US",
    "sg:address":"5155 W Co Rd 1000 N",
    "sg:city":"Russellville",
    "sg:classifiers":[
        {
            "category":"Home & Garden",
            "subcategory":"Building Materials",
            "type":"Retail Goods"
        }
    ],
    "sg:phone":"+1 765 435 3691",
    "sg:postcode":"46175",
    "sg:province":"IN",
    "sg:tags":[
        "glass",
        "leaded"
    ],
    "wof:name":"Artistry In Design Stained",
    "wof:placetype":"venue"
},
  "geometry": {"coordinates":[-86.941612,39.809188],"type":"Point"}
}