{
  "type": "Feature",
  "properties": {
    "iso:country":"US",
    "sg:address":"6180 N Washington Blvd",
    "sg:city":"Indianapolis",
    "sg:classifiers":[
        {
            "category":"Retail",
            "subcategory":"Portrait Studio",
            "type":"Services"
        }
    ],
    "sg:phone":"+1 317 255 0503",
    "sg:postcode":"46220",
    "sg:province":"IN",
    "sg:tags":[
        "photographer"
    ],
    "wof:name":"Michael Mendez Portrait Art",
    "wof:placetype":"venue"
},
  "geometry": {"coordinates":[-86.151737,39.867161],"type":"Point"}
}