{
  "type": "Feature",
  "properties": {
    "iso:country":"US",
    "sg:address":"7980 Beech Ave",
    "sg:city":"Munster",
    "sg:classifiers":[
        {
            "category":"Organizations",
            "subcategory":"Non-profit Organization",
            "type":"Services"
        }
    ],
    "sg:phone":"+1 219 838 3848",
    "sg:postcode":"46321",
    "sg:province":"IN",
    "sg:tags":[
        "fund",
        "counselor",
        "raising"
    ],
    "wof:name":"Arv Group",
    "wof:placetype":"venue"
},
  "geometry": {"coordinates":[-87.494088,41.568047],"type":"Point"}
}