{
  "type": "Feature",
  "properties": {
    "iso:country":"US",
    "sg:address":"134 Depot St",
    "sg:city":"Butler",
    "sg:classifiers":[
        {
            "category":"Building & Trades",
            "subcategory":"Cleaning & Sanitation",
            "type":"Services"
        }
    ],
    "sg:phone":"+1 260 868 5006",
    "sg:postcode":"46721",
    "sg:province":"IN",
    "sg:tags":[
        "janitor"
    ],
    "wof:name":"Maintenance On Wheels Inc",
    "wof:placetype":"venue"
},
  "geometry": {"coordinates":[-84.874004,41.427776],"type":"Point"}
}