{
  "type": "Feature",
  "properties": {
    "iso:country":"US",
    "sg:address":"600 E 96th St Ste 400",
    "sg:city":"Indianapolis",
    "sg:classifiers":[
        {
            "category":"Insurance",
            "subcategory":"Insurance Agent",
            "type":"Services"
        },
        {
            "category":"Insurance",
            "subcategory":"Hazard Insurance",
            "type":"Services"
        }
    ],
    "sg:phone":"+1 317 817 9735",
    "sg:postcode":"46240",
    "sg:province":"IN",
    "sg:tags":[
        "fire",
        "property",
        "casualty"
    ],
    "wof:name":"Indiana Insurance Company",
    "wof:placetype":"venue"
},
  "geometry": {"coordinates":[-86.14753,39.927151],"type":"Point"}
}