{
  "type": "Feature",
  "properties": {
    "iso:country":"US",
    "sg:address":"8737 Lake Shore Dr",
    "sg:city":"Gary",
    "sg:classifiers":[
        {
            "category":"Real Estate",
            "subcategory":"Real Estate Agent",
            "type":"Services"
        }
    ],
    "sg:phone":"+1 219 938 0786",
    "sg:postcode":"46403",
    "sg:province":"IN",
    "wof:name":"Cecil Real Estate Inc",
    "wof:placetype":"venue"
},
  "geometry": {"coordinates":[-87.233651,41.622064],"type":"Point"}
}