{
  "type": "Feature",
  "properties": {
    "iso:country":"US",
    "sg:address":"638 N Calumet Rd",
    "sg:city":"Chesterton",
    "sg:classifiers":[
        {
            "category":"Organizations",
            "subcategory":"Religious Organization",
            "type":"Services"
        }
    ],
    "sg:phone":"+1 219 926 1282",
    "sg:postcode":"46304",
    "sg:province":"IN",
    "sg:tags":[
        "church"
    ],
    "wof:name":"St Patrick Catholic Church",
    "wof:placetype":"venue"
},
  "geometry": {"coordinates":[-87.049789,41.618301],"type":"Point"}
}