{
  "type": "Feature",
  "properties": {
    "iso:country":"US",
    "sg:address":"6817 Kennedy Ave",
    "sg:city":"Hammond",
    "sg:classifiers":[
        {
            "category":"Personal",
            "subcategory":"Tattoo Parlor",
            "type":"Services"
        }
    ],
    "sg:phone":"+1 219 844 9976",
    "sg:postcode":"46323",
    "sg:province":"IN",
    "sg:website":"www.thetattoolady.com",
    "wof:name":"The Tattoo Lady",
    "wof:placetype":"venue"
},
  "geometry": {"coordinates":[-87.461502,41.59],"type":"Point"}
}