{
  "type": "Feature",
  "properties": {
    "iso:country":"US",
    "sg:address":"1818 N 3rd St",
    "sg:city":"Terre Haute",
    "sg:classifiers":[
        {
            "category":"Health Services",
            "subcategory":"Health Practitioner",
            "type":"Services"
        }
    ],
    "sg:phone":"+1 812 478 9494",
    "sg:postcode":"47804",
    "sg:province":"IN",
    "sg:tags":[
        "therapist",
        "physical"
    ],
    "wof:name":"Therapy Alternatives Rehab Svc",
    "wof:placetype":"venue"
},
  "geometry": {"coordinates":[-87.41406000000001,39.488168],"type":"Point"}
}