{
  "type": "Feature",
  "properties": {
    "iso:country":"US",
    "sg:address":"6291 E Dublin Pike",
    "sg:city":"Straughn",
    "sg:classifiers":[
        {
            "category":"Organizations",
            "subcategory":"Religious Organization",
            "type":"Services"
        }
    ],
    "sg:phone":"+1 765 332 2845",
    "sg:postcode":"47387",
    "sg:province":"IN",
    "sg:tags":[
        "church"
    ],
    "wof:name":"Allegheny Weslyan Church",
    "wof:placetype":"venue"
},
  "geometry": {"coordinates":[-85.265536,39.865936],"type":"Point"}
}