{
  "type": "Feature",
  "properties": {
    "addr:full":"450 Campbell St Valparaiso IN 46385",
    "addr:housenumber":"450",
    "addr:postcode":"46385",
    "addr:street":"Campbell St",
    "iso:country":"US",
    "sg:address":"450 Campbell St",
    "sg:city":"Valparaiso",
    "sg:classifiers":[
        {
            "category":"Manufacturing",
            "subcategory":"Metals",
            "type":"Manufacturing & Wholesale Goods"
        }
    ],
    "sg:phone":"+1 219 531 2583",
    "sg:postcode":"46385",
    "sg:province":"IN",
    "sg:tags":[
        "stamping"
    ],
    "wof:name":"Tribsys LLC",
    "wof:placetype":"venue"
},
  "geometry": {"coordinates":[-87.065815,41.471666],"type":"Point"}
}