{
  "type": "Feature",
  "properties": {
    "iso:country":"US",
    "sg:address":"7398 N State Road 37",
    "sg:city":"Bloomington",
    "sg:classifiers":[
        {
            "category":"Utilities",
            "subcategory":"Electric",
            "type":"Services"
        }
    ],
    "sg:phone":"+1 812 876 0288",
    "sg:postcode":"47404",
    "sg:province":"IN",
    "wof:name":"Hoosier Energy Rural Electric Cooperative Inc",
    "wof:placetype":"venue"
},
  "geometry": {"coordinates":[-86.52296200000001,39.261211],"type":"Point"}
}