{
  "type": "Feature",
  "properties": {
    "iso:country":"US",
    "sg:address":"67 South St",
    "sg:city":"Southport",
    "sg:classifiers":[
        {
            "category":"Building & Trades",
            "subcategory":"Construction",
            "type":"Services"
        }
    ],
    "sg:phone":"+1 317 557 6703",
    "sg:postcode":"46227",
    "sg:province":"IN",
    "sg:tags":[
        "siding",
        "contractor"
    ],
    "wof:name":"J & W Remodeling",
    "wof:placetype":"venue"
},
  "geometry": {"coordinates":[-86.124999,39.662071],"type":"Point"}
}