{
  "type": "Feature",
  "properties": {
    "iso:country":"US",
    "sg:address":"2629 Lincoln Way W",
    "sg:city":"Mishawaka",
    "sg:classifiers":[
        {
            "category":"Wholesale",
            "subcategory":"Durable Goods & Equipment",
            "type":"Manufacturing & Wholesale Goods"
        }
    ],
    "sg:phone":"+1 574 259 0411",
    "sg:postcode":"46544",
    "sg:province":"IN",
    "sg:tags":[
        "fire",
        "extinguisher"
    ],
    "wof:name":"S & H Carbonic Inc",
    "wof:placetype":"venue"
},
  "geometry": {"coordinates":[-86.21297300000001,41.65765],"type":"Point"}
}