{
  "type": "Feature",
  "properties": {
    "addr:full":"555 N 650 E Lebanon IN 46052",
    "addr:housenumber":"555",
    "addr:postcode":"46052",
    "addr:street":"N 650 E",
    "iso:country":"US",
    "sg:address":"555 N 650 E",
    "sg:city":"Lebanon",
    "sg:classifiers":[
        {
            "category":"Wholesale",
            "subcategory":"Metals & Minerals",
            "type":"Manufacturing & Wholesale Goods"
        }
    ],
    "sg:phone":"+1 317 769 2796",
    "sg:postcode":"46052",
    "sg:province":"IN",
    "sg:tags":[
        "specialty"
    ],
    "wof:name":"Cryogenics Of Indiana",
    "wof:placetype":"venue"
},
  "geometry": {"coordinates":[-86.345803,40.050863],"type":"Point"}
}