{
  "type": "Feature",
  "properties": {
    "addr:full":"10850 Windfall Pl Camby IN 46113",
    "addr:housenumber":"10850",
    "addr:postcode":"46113",
    "addr:street":"Windfall Pl",
    "iso:country":"US",
    "sg:address":"10850 Windfall Pl",
    "sg:city":"Camby",
    "sg:classifiers":[
        {
            "category":"Fast Food",
            "type":"Food & Drink"
        },
        {
            "category":"Restaurant",
            "type":"Food & Drink"
        }
    ],
    "sg:phone":"+1 317 821 0452",
    "sg:postcode":"46113",
    "sg:province":"IN",
    "sg:tags":[
        "mexican"
    ],
    "sg:website":"http://www.tacobell.com",
    "wof:name":"Taco Bell",
    "wof:placetype":"venue"
},
  "geometry": {"coordinates":[-86.334644,39.63973],"type":"Point"}
}