{
  "type": "Feature",
  "properties": {
    "iso:country":"US",
    "sg:address":"921 Main St",
    "sg:city":"Vincennes",
    "sg:classifiers":[
        {
            "category":"Home & Garden",
            "subcategory":"Hardware",
            "type":"Retail Goods"
        }
    ],
    "sg:phone":"+1 812 882 8138",
    "sg:postcode":"47591",
    "sg:province":"IN",
    "wof:name":"Beard's Hardware & Supply Inc",
    "wof:placetype":"venue"
},
  "geometry": {"coordinates":[-87.526957,38.674309],"type":"Point"}
}