{
  "type": "Feature",
  "properties": {
    "iso:country":"US",
    "sg:address":"16 E Reel Ave",
    "sg:city":"Vincennes",
    "sg:classifiers":[
        {
            "category":"Social Services",
            "subcategory":"Child Care",
            "type":"Services"
        }
    ],
    "sg:phone":"+1 812 886 4347",
    "sg:postcode":"47591",
    "sg:province":"IN",
    "wof:name":"Little Angels Daycare Ctr",
    "wof:placetype":"venue"
},
  "geometry": {"coordinates":[-87.513544,38.69133],"type":"Point"}
}