{
  "type": "Feature",
  "properties": {
    "iso:country":"US",
    "sg:address":"216 S 15th St",
    "sg:city":"Vincennes",
    "sg:classifiers":[
        {
            "category":"Retail",
            "subcategory":"Auto Repair",
            "type":"Services"
        }
    ],
    "sg:phone":"+1 812 882 8990",
    "sg:postcode":"47591",
    "sg:province":"IN",
    "sg:tags":[
        "repairing",
        "automobile"
    ],
    "wof:name":"Vennard's Auto Clinic",
    "wof:placetype":"venue"
},
  "geometry": {"coordinates":[-87.523191,38.667598],"type":"Point"}
}