{
  "type": "Feature",
  "properties": {
    "iso:country":"US",
    "sg:address":"758 Hamilton Ave",
    "sg:city":"Franklin",
    "sg:classifiers":[
        {
            "category":"Wholesale",
            "subcategory":"Farm Supplies",
            "type":"Manufacturing & Wholesale Goods"
        }
    ],
    "sg:phone":"+1 317 736 8384",
    "sg:postcode":"46131",
    "sg:province":"IN",
    "sg:tags":[
        "fertilizer"
    ],
    "wof:name":"Crop Production Svc Inc",
    "wof:placetype":"venue"
},
  "geometry": {"coordinates":[-86.045644,39.489465],"type":"Point"}
}