{
  "type": "Feature",
  "properties": {
    "iso:country":"US",
    "sg:address":"5509 Coldwater Rd",
    "sg:city":"Fort Wayne",
    "sg:classifiers":[
        {
            "category":"Shopping",
            "subcategory":"Books",
            "type":"Retail Goods"
        }
    ],
    "sg:phone":"+1 260 484 9027",
    "sg:postcode":"46825",
    "sg:province":"IN",
    "sg:tags":[
        "dealer"
    ],
    "wof:name":"Family Christian Book Store",
    "wof:placetype":"venue"
},
  "geometry": {"coordinates":[-85.13591700000001,41.129333],"type":"Point"}
}