{
  "type": "Feature",
  "properties": {
    "addr:full":"3321 N 1st Ave Evansville IN 47710",
    "addr:housenumber":"3321",
    "addr:postcode":"47710",
    "addr:street":"N 1St Ave",
    "iso:country":"US",
    "sg:address":"3321 N 1st Ave",
    "sg:city":"Evansville",
    "sg:classifiers":[
        {
            "category":"Retail",
            "subcategory":"Auto Rental",
            "type":"Services"
        }
    ],
    "sg:phone":"+1 812 425 0050",
    "sg:postcode":"47710",
    "sg:province":"IN",
    "sg:tags":[
        "renting",
        "automobile"
    ],
    "wof:name":"Enterprise Rent-A-Car",
    "wof:placetype":"venue"
},
  "geometry": {"coordinates":[-87.57418199999999,38.009393],"type":"Point"}
}