{
  "type": "Feature",
  "properties": {
    "iso:country":"US",
    "sg:address":"13215 W Sherbern Dr",
    "sg:city":"Carmel",
    "sg:classifiers":[
        {
            "category":"Professional",
            "subcategory":"Employment Agencies",
            "type":"Services"
        }
    ],
    "sg:phone":"+1 317 581 0627",
    "sg:postcode":"46032",
    "sg:province":"IN",
    "sg:tags":[
        "employee",
        "benefit",
        "consulting"
    ],
    "wof:name":"Balgarren Group Inc",
    "wof:placetype":"venue"
},
  "geometry": {"coordinates":[-86.187318,39.979897],"type":"Point"}
}