{
  "type": "Feature",
  "properties": {
    "iso:country":"US",
    "sg:address":"535 Green Blvd",
    "sg:city":"Aurora",
    "sg:classifiers":[
        {
            "category":"Shopping",
            "type":"Retail Goods"
        }
    ],
    "sg:phone":"+1 812 926 4567",
    "sg:postcode":"47001",
    "sg:province":"IN",
    "sg:tags":[
        "hearing",
        "equipment",
        "supply",
        "impaired"
    ],
    "wof:name":"Audiology & Hearing Care",
    "wof:placetype":"venue"
},
  "geometry": {"coordinates":[-84.897223,39.062772],"type":"Point"}
}