{
  "type": "Feature",
  "properties": {
    "iso:country":"US",
    "sg:address":"200 W South St",
    "sg:city":"Centerville",
    "sg:classifiers":[
        {
            "category":"Education",
            "subcategory":"School",
            "type":"Public Place"
        }
    ],
    "sg:phone":"+1 765 855 5132",
    "sg:postcode":"47330",
    "sg:province":"IN",
    "sg:website":"www.centerville.k12.in.us",
    "wof:name":"Centerville Elementary School",
    "wof:placetype":"venue"
},
  "geometry": {"coordinates":[-84.99940599999999,39.814648],"type":"Point"}
}