{
  "type": "Feature",
  "properties": {
    "addr:full":"2003 Broadway St Anderson IN 46012",
    "addr:housenumber":"2003",
    "addr:postcode":"46012",
    "addr:street":"Broadway St",
    "iso:country":"US",
    "sg:address":"2003 Broadway St",
    "sg:city":"Anderson",
    "sg:classifiers":[
        {
            "category":"Shopping",
            "subcategory":"Pharmacy",
            "type":"Retail Goods"
        }
    ],
    "sg:phone":"+1 765 643 1515",
    "sg:postcode":"46012",
    "sg:province":"IN",
    "wof:name":"CVS Pharmacy",
    "wof:placetype":"venue"
},
  "geometry": {"coordinates":[-85.67772100000001,40.136449],"type":"Point"}
}