{
  "type": "Feature",
  "properties": {
    "iso:country":"US",
    "sg:address":"105 W Hammond St",
    "sg:city":"Dale",
    "sg:classifiers":[
        {
            "category":"Recreation",
            "type":"Entertainment"
        }
    ],
    "sg:phone":"+1 812 937 2446",
    "sg:postcode":"47523",
    "sg:province":"IN",
    "sg:tags":[
        "hall",
        "auditorium"
    ],
    "wof:name":"Dale City Community Ctr",
    "wof:placetype":"venue"
},
  "geometry": {"coordinates":[-86.99110899999999,38.170243],"type":"Point"}
}