{
  "type": "Feature",
  "properties": {
    "iso:country":"US",
    "sg:address":"220 E Sycamore St",
    "sg:city":"Kokomo",
    "sg:classifiers":[
        {
            "category":"Professional",
            "subcategory":"Business Services",
            "type":"Services"
        }
    ],
    "sg:phone":"+1 765 452 2927",
    "sg:postcode":"46901",
    "sg:province":"IN",
    "sg:tags":[
        "appraiser"
    ],
    "wof:name":"Bulger Appraisal",
    "wof:placetype":"venue"
},
  "geometry": {"coordinates":[-86.128947,40.486559],"type":"Point"}
}