{
  "type": "Feature",
  "properties": {
    "iso:country":"US",
    "sg:address":"6215 Commodity Ct",
    "sg:city":"Fort Wayne",
    "sg:classifiers":[
        {
            "category":"Bus Charters",
            "type":"Transportation"
        }
    ],
    "sg:phone":"+1 260 489 3556",
    "sg:postcode":"46818",
    "sg:province":"IN",
    "sg:tags":[
        "rental"
    ],
    "sg:website":"www.excellentadventuresinc.com",
    "wof:name":"Excellent Adventures",
    "wof:placetype":"venue"
},
  "geometry": {"coordinates":[-85.200107,41.136764],"type":"Point"}
}