{
  "type": "Feature",
  "properties": {
    "iso:country":"US",
    "sg:address":"91 N Spring St",
    "sg:city":"Greenfield",
    "sg:classifiers":[
        {
            "category":"Professional",
            "subcategory":"Art Services",
            "type":"Services"
        }
    ],
    "sg:phone":"+1 317 462 4040",
    "sg:postcode":"46140",
    "sg:province":"IN",
    "sg:tags":[
        "commercial",
        "design"
    ],
    "wof:name":"Goddard Graphic Arts LLC",
    "wof:placetype":"venue"
},
  "geometry": {"coordinates":[-85.7663,39.785444],"type":"Point"}
}