{
  "type": "Feature",
  "properties": {
    "iso:country":"US",
    "sg:address":"424 W 30th St",
    "sg:city":"Marion",
    "sg:classifiers":[
        {
            "category":"Social Services",
            "subcategory":"Child Care",
            "type":"Services"
        }
    ],
    "sg:phone":"+1 765 664 7606",
    "sg:postcode":"46953",
    "sg:province":"IN",
    "sg:tags":[
        "day"
    ],
    "wof:name":"Minnie Shoup",
    "wof:placetype":"venue"
},
  "geometry": {"coordinates":[-85.664443,40.533858],"type":"Point"}
}