{
  "type": "Feature",
  "properties": {
    "addr:full":"1570 E Commerce Dr Greensburg IN 47240",
    "addr:housenumber":"1570",
    "addr:postcode":"47240",
    "addr:street":"E Commerce Dr",
    "iso:country":"US",
    "sg:address":"1570 E Commerce Dr",
    "sg:city":"Greensburg",
    "sg:classifiers":[
        {
            "category":"Health Services",
            "subcategory":"Chiropractor",
            "type":"Services"
        }
    ],
    "sg:phone":"+1 812 663 7818",
    "sg:postcode":"47240",
    "sg:province":"IN",
    "wof:name":"Family Chiropractic Clinic",
    "wof:placetype":"venue"
},
  "geometry": {"coordinates":[-85.471799,39.353403],"type":"Point"}
}