{
  "type": "Feature",
  "properties": {
    "iso:country":"US",
    "sg:address":"5711 W 73rd St",
    "sg:city":"Indianapolis",
    "sg:classifiers":[
        {
            "category":"Professional",
            "subcategory":"Engineering",
            "type":"Services"
        }
    ],
    "sg:phone":"+1 317 388 8532",
    "sg:postcode":"46278",
    "sg:province":"IN",
    "sg:tags":[
        "engineer"
    ],
    "sg:website":"www.riteng.com",
    "wof:name":"Ritchie Engineering Inc",
    "wof:placetype":"venue"
},
  "geometry": {"coordinates":[-86.265395,39.884788],"type":"Point"}
}