{
  "type": "Feature",
  "properties": {
    "addr:full":"112 W 5th St Jasper IN 47546",
    "addr:housenumber":"112",
    "addr:postcode":"47546",
    "addr:street":"W 5Th St",
    "iso:country":"US",
    "sg:address":"112 W 5th St",
    "sg:city":"Jasper",
    "sg:classifiers":[
        {
            "category":"Professional",
            "subcategory":"Accounting & Tax Preparation",
            "type":"Services"
        }
    ],
    "sg:phone":"+1 812 482 6330",
    "sg:postcode":"47546",
    "sg:province":"IN",
    "sg:tags":[
        "accountant"
    ],
    "wof:name":"Nonte & Co",
    "wof:placetype":"venue"
},
  "geometry": {"coordinates":[-86.93169899999999,38.390761],"type":"Point"}
}