{
  "type": "Feature",
  "properties": {
    "iso:country":"US",
    "sg:address":"3735 Parkhill Ave",
    "sg:city":"Fort Wayne",
    "sg:classifiers":[
        {
            "category":"Education",
            "subcategory":"Dance Studio",
            "type":"Public Place"
        }
    ],
    "sg:phone":"+1 260 484 3257",
    "sg:postcode":"46805",
    "sg:province":"IN",
    "sg:tags":[
        "instruction",
        "dancing"
    ],
    "wof:name":"Dancer's Paradise",
    "wof:placetype":"venue"
},
  "geometry": {"coordinates":[-85.13317000000001,41.111244],"type":"Point"}
}