{
  "type": "Feature",
  "properties": {
    "iso:country":"US",
    "sg:address":"20480 Co Rd 50",
    "sg:city":"New Paris",
    "sg:classifiers":[
        {
            "category":"Building & Trades",
            "subcategory":"Construction",
            "type":"Services"
        }
    ],
    "sg:phone":"+1 574 831 4473",
    "sg:postcode":"46553",
    "sg:province":"IN",
    "sg:tags":[
        "home",
        "builder"
    ],
    "wof:name":"Stephen Yoder Custom Built Hms",
    "wof:placetype":"venue"
},
  "geometry": {"coordinates":[-85.848421,41.471236],"type":"Point"}
}