{
  "type": "Feature",
  "properties": {
    "addr:full":"1157 E Co Rd 500 N Orleans IN 47452",
    "addr:housenumber":"1157;500",
    "addr:postcode":"47452",
    "addr:street":"E Co Rd;N Orleans",
    "iso:country":"US",
    "sg:address":"1157 E Co Rd 500 N",
    "sg:city":"Orleans",
    "sg:classifiers":[
        {
            "category":"Farming",
            "subcategory":"Farm",
            "type":"Manufacturing & Wholesale Goods"
        }
    ],
    "sg:phone":"+1 812 865 3676",
    "sg:postcode":"47452",
    "sg:province":"IN",
    "sg:tags":[
        "crop",
        "general"
    ],
    "wof:name":"Ronald Taylor",
    "wof:placetype":"venue"
},
  "geometry": {"coordinates":[-86.42343700000001,38.629474],"type":"Point"}
}