{
  "type": "Feature",
  "properties": {
    "iso:country":"US",
    "sg:address":"2892 W 450 N",
    "sg:city":"Laporte",
    "sg:classifiers":[
        {
            "category":"Wholesale",
            "subcategory":"Machinery & Supplies",
            "type":"Manufacturing & Wholesale Goods"
        }
    ],
    "sg:phone":"+1 219 326 8425",
    "sg:postcode":"46350",
    "sg:province":"IN",
    "sg:tags":[
        "truck"
    ],
    "wof:name":"Pauls Lift Truck Svc",
    "wof:placetype":"venue"
},
  "geometry": {"coordinates":[-86.75667900000001,41.671781],"type":"Point"}
}