{
  "type": "Feature",
  "properties": {
    "addr:full":"2525 W Lexington Ave Elkhart IN 46514",
    "addr:housenumber":"2525",
    "addr:postcode":"46514",
    "addr:street":"W Lexington Ave",
    "iso:country":"US",
    "sg:address":"2525 W Lexington Ave",
    "sg:city":"Elkhart",
    "sg:classifiers":[
        {
            "category":"Professional",
            "subcategory":"Employment Agencies",
            "type":"Services"
        }
    ],
    "sg:phone":"+1 574 293 5900",
    "sg:postcode":"46514",
    "sg:province":"IN",
    "sg:tags":[
        "opportunity"
    ],
    "wof:name":"Forge Industrial Staffing",
    "wof:placetype":"venue"
},
  "geometry": {"coordinates":[-86.013476,41.686405],"type":"Point"}
}