{
  "type": "Feature",
  "properties": {
    "iso:country":"US",
    "sg:address":"112 N Buffalo St",
    "sg:city":"Warsaw",
    "sg:classifiers":[
        {
            "category":"Shopping",
            "subcategory":"Books",
            "type":"Retail Goods"
        }
    ],
    "sg:phone":"+1 574 267 5662",
    "sg:postcode":"46580",
    "sg:province":"IN",
    "sg:tags":[
        "dealer"
    ],
    "wof:name":"Readers World",
    "wof:placetype":"venue"
},
  "geometry": {"coordinates":[-85.856561,41.238968],"type":"Point"}
}