{
  "type": "Feature",
  "properties": {
    "iso:country":"US",
    "sg:address":"21198 Wilshire Ct",
    "sg:city":"Bristol",
    "sg:classifiers":[
        {
            "category":"Education",
            "subcategory":"Dance Studio",
            "type":"Public Place"
        }
    ],
    "sg:phone":"+1 574 848 4268",
    "sg:postcode":"46507",
    "sg:province":"IN",
    "sg:tags":[
        "instruction",
        "dancing"
    ],
    "wof:name":"Studio Granger",
    "wof:placetype":"venue"
},
  "geometry": {"coordinates":[-85.877965,41.72291],"type":"Point"}
}