{
  "type": "Feature",
  "properties": {
    "iso:country":"US",
    "sg:address":"328 Vincennes St",
    "sg:city":"New Albany",
    "sg:classifiers":[
        {
            "category":"Shopping",
            "subcategory":"Florist",
            "type":"Retail Goods"
        }
    ],
    "sg:phone":"+1 812 981 8155",
    "sg:postcode":"47150",
    "sg:province":"IN",
    "wof:name":"Flowers With Flair",
    "wof:placetype":"venue"
},
  "geometry": {"coordinates":[-85.806997,38.29258],"type":"Point"}
}