{
  "type": "Feature",
  "properties": {
    "iso:country":"US",
    "sg:address":"828 N Market St",
    "sg:city":"Winamac",
    "sg:classifiers":[
        {
            "category":"Organizations",
            "subcategory":"Religious Organization",
            "type":"Services"
        }
    ],
    "sg:phone":"+1 574 946 6922",
    "sg:postcode":"46996",
    "sg:province":"IN",
    "sg:tags":[
        "church"
    ],
    "wof:name":"Calvary Baptist Church",
    "wof:placetype":"venue"
},
  "geometry": {"coordinates":[-86.606702,41.059487],"type":"Point"}
}