{
  "type": "Feature",
  "properties": {
    "addr:full":"1112 119th St Whiting IN 46394",
    "addr:housenumber":"1112",
    "addr:postcode":"46394",
    "addr:street":"119Th St",
    "iso:country":"US",
    "sg:address":"1112 119th St",
    "sg:city":"Whiting",
    "sg:classifiers":[
        {
            "category":"Professional",
            "subcategory":"Computer Services",
            "type":"Services"
        }
    ],
    "sg:phone":"+1 219 659 1003",
    "sg:postcode":"46394",
    "sg:province":"IN",
    "sg:tags":[
        "repair"
    ],
    "wof:name":"Compusat",
    "wof:placetype":"venue"
},
  "geometry": {"coordinates":[-87.50031300000001,41.679223],"type":"Point"}
}