{
  "type": "Feature",
  "properties": {
    "addr:full":"2512 N Cullen Ave Evansville IN 47715",
    "addr:housenumber":"2512",
    "addr:postcode":"47715",
    "addr:street":"N Cullen Ave",
    "iso:country":"US",
    "sg:address":"2512 N Cullen Ave",
    "sg:city":"Evansville",
    "sg:classifiers":[
        {
            "category":"Wholesale",
            "subcategory":"Machinery & Supplies",
            "type":"Manufacturing & Wholesale Goods"
        }
    ],
    "sg:phone":"+1 812 474 1717",
    "sg:postcode":"47715",
    "sg:province":"IN",
    "sg:tags":[
        "bearing"
    ],
    "sg:website":"www.kaman.com",
    "wof:name":"Kaman Industrial Tech",
    "wof:placetype":"venue"
},
  "geometry": {"coordinates":[-87.48640899999999,38.000303],"type":"Point"}
}