{
  "type": "Feature",
  "properties": {
    "iso:country":"US",
    "sg:address":"14125 W 130th Pl",
    "sg:city":"Cedar Lake",
    "sg:classifiers":[
        {
            "category":"Building & Trades",
            "subcategory":"Plumbing",
            "type":"Services"
        }
    ],
    "sg:phone":"+1 219 374 2779",
    "sg:postcode":"46303",
    "sg:province":"IN",
    "sg:tags":[
        "conditioning",
        "air",
        "system",
        "contractor"
    ],
    "wof:name":"KNZ Corp",
    "wof:placetype":"venue"
},
  "geometry": {"coordinates":[-87.504177,41.381518],"type":"Point"}
}