{
  "type": "Feature",
  "properties": {
    "iso:country":"US",
    "sg:address":"8241 Pendleton Pike",
    "sg:city":"Indianapolis",
    "sg:classifiers":[
        {
            "category":"Banks & Credit Unions",
            "subcategory":"Bank",
            "type":"Services"
        }
    ],
    "sg:phone":"+1 317 897 1648",
    "sg:postcode":"46226",
    "sg:province":"IN",
    "sg:tags":[
        "cashing",
        "check"
    ],
    "wof:name":"Advance America",
    "wof:placetype":"venue"
},
  "geometry": {"coordinates":[-86.02383500000001,39.83765],"type":"Point"}
}