{
  "type": "Feature",
  "properties": {
    "addr:full":"900 Tutor Ln Evansville IN 47715",
    "addr:housenumber":"900",
    "addr:postcode":"47715",
    "addr:street":"Tutor Ln",
    "iso:country":"US",
    "sg:address":"900 Tutor Ln",
    "sg:city":"Evansville",
    "sg:classifiers":[
        {
            "category":"Health Services",
            "subcategory":"Chiropractor",
            "type":"Services"
        }
    ],
    "sg:phone":"+1 812 479 8350",
    "sg:postcode":"47715",
    "sg:province":"IN",
    "wof:name":"Lawrence Chiropractic & Rehab",
    "wof:placetype":"venue"
},
  "geometry": {"coordinates":[-87.47507299999999,37.983922],"type":"Point"}
}