{
  "type": "Feature",
  "properties": {
    "iso:country":"US",
    "sg:address":"1812 US Hwy 231 S",
    "sg:city":"Crawfordsville",
    "sg:classifiers":[
        {
            "category":"Home & Garden",
            "subcategory":"Hardware",
            "type":"Retail Goods"
        }
    ],
    "sg:phone":"+1 765 362 5800",
    "sg:postcode":"47933",
    "sg:province":"IN",
    "wof:name":"Stevenson's Ace Hardware Inc",
    "wof:placetype":"venue"
},
  "geometry": {"coordinates":[-86.90379,40.013496],"type":"Point"}
}