{
  "type": "Feature",
  "properties": {
    "iso:country":"US",
    "sg:address":"8859 Southeastern Ave",
    "sg:city":"Indianapolis",
    "sg:classifiers":[
        {
            "category":"Retail",
            "subcategory":"Auto Repair",
            "type":"Services"
        }
    ],
    "sg:phone":"+1 317 862 2647",
    "sg:postcode":"46239",
    "sg:province":"IN",
    "sg:tags":[
        "repairing",
        "automobile"
    ],
    "wof:name":"Logan's",
    "wof:placetype":"venue"
},
  "geometry": {"coordinates":[-86.011365,39.705638],"type":"Point"}
}