{
  "type": "Feature",
  "properties": {
    "iso:country":"US",
    "sg:address":"511 W Ridge Rd",
    "sg:city":"Gary",
    "sg:classifiers":[
        {
            "category":"Education",
            "subcategory":"Special Training",
            "type":"Public Place"
        }
    ],
    "sg:phone":"+1 219 985 9276",
    "sg:postcode":"46408",
    "sg:province":"IN",
    "sg:tags":[
        "instruction",
        "music"
    ],
    "wof:name":"All About Music",
    "wof:placetype":"venue"
},
  "geometry": {"coordinates":[-87.343633,41.549168],"type":"Point"}
}