{
  "type": "Feature",
  "properties": {
    "iso:country":"US",
    "sg:address":"5370 W 84th St",
    "sg:city":"Indianapolis",
    "sg:classifiers":[
        {
            "category":"Manufacturing",
            "subcategory":"Petroleum Products",
            "type":"Manufacturing & Wholesale Goods"
        }
    ],
    "sg:phone":"+1 317 875 6969",
    "sg:postcode":"46268",
    "sg:province":"IN",
    "sg:tags":[
        "contract"
    ],
    "wof:name":"Front Row Sports Tech",
    "wof:placetype":"venue"
},
  "geometry": {"coordinates":[-86.25409999999999,39.907143],"type":"Point"}
}