{
  "type": "Feature",
  "properties": {
    "addr:full":"109 N Railroad St Battle Ground IN 47920",
    "addr:housenumber":"109",
    "addr:postcode":"47920",
    "addr:street":"N Railroad St",
    "iso:country":"US",
    "sg:address":"109 N Railroad St",
    "sg:city":"Battle Ground",
    "sg:classifiers":[
        {
            "category":"Restaurant",
            "type":"Food & Drink"
        }
    ],
    "sg:phone":"+1 765 567 2838",
    "sg:postcode":"47920",
    "sg:province":"IN",
    "sg:tags":[
        "drinking",
        "eating"
    ],
    "wof:name":"T C's Restaurant & Tavern",
    "wof:placetype":"venue"
},
  "geometry": {"coordinates":[-86.836444,40.513572],"type":"Point"}
}