{
  "type": "Feature",
  "properties": {
    "addr:full":"75 N State Road 135 Greenwood IN 46142",
    "addr:housenumber":"75",
    "addr:postcode":"46142",
    "addr:street":"N State Road 135",
    "iso:country":"US",
    "sg:address":"75 N State Road 135",
    "sg:city":"Greenwood",
    "sg:classifiers":[
        {
            "category":"Shopping",
            "subcategory":"Beauty & Cosmetics",
            "type":"Retail Goods"
        }
    ],
    "sg:phone":"+1 317 885 7006",
    "sg:postcode":"46142",
    "sg:province":"IN",
    "sg:tags":[
        "perfume",
        "salons-equipment",
        "supply"
    ],
    "wof:name":"Walton Family & Cosmetic Denti",
    "wof:placetype":"venue"
},
  "geometry": {"coordinates":[-86.158474,39.614337],"type":"Point"}
}