{
  "type": "Feature",
  "properties": {
    "iso:country":"US",
    "sg:address":"200 S Governor St",
    "sg:city":"Evansville",
    "sg:classifiers":[
        {
            "category":"Building & Trades",
            "subcategory":"Plumbing",
            "type":"Services"
        }
    ],
    "sg:phone":"+1 812 424 5878",
    "sg:postcode":"47713",
    "sg:province":"IN",
    "sg:tags":[
        "conditioning",
        "air",
        "system",
        "contractor"
    ],
    "sg:website":"www.schmittrefrigeration.com",
    "wof:name":"Schmitt Refrigeration & AC",
    "wof:placetype":"venue"
},
  "geometry": {"coordinates":[-87.559005,37.974596],"type":"Point"}
}