{
  "type": "Feature",
  "properties": {
    "addr:full":"441 S Memorial Dr New Castle IN 47362",
    "addr:housenumber":"441",
    "addr:postcode":"47362",
    "addr:street":"S Memorial Dr",
    "iso:country":"US",
    "sg:address":"441 S Memorial Dr",
    "sg:city":"New Castle",
    "sg:classifiers":[
        {
            "category":"Shopping",
            "subcategory":"Crafts & Fabrics",
            "type":"Retail Goods"
        }
    ],
    "sg:phone":"+1 765 529 1211",
    "sg:postcode":"47362",
    "sg:province":"IN",
    "sg:tags":[
        "shop"
    ],
    "sg:website":"www.joann.com",
    "wof:name":"Jo-Ann Fabrics & Crafts",
    "wof:placetype":"venue"
},
  "geometry": {"coordinates":[-85.381822,39.927842],"type":"Point"}
}