{
  "type": "Feature",
  "properties": {
    "iso:country":"US",
    "sg:address":"2200 US Hwy 27",
    "sg:city":"Richmond",
    "sg:classifiers":[
        {
            "category":"Manufacturing",
            "subcategory":"Metals",
            "type":"Manufacturing & Wholesale Goods"
        }
    ],
    "sg:phone":"+1 765 983 5200",
    "sg:postcode":"47374",
    "sg:province":"IN",
    "sg:tags":[
        "product",
        "wire"
    ],
    "sg:website":"www.belden.com",
    "wof:name":"Belden Wire & Cable Co",
    "wof:placetype":"venue"
},
  "geometry": {"coordinates":[-84.888798,39.856249],"type":"Point"}
}