{
  "type": "Feature",
  "properties": {
    "iso:country":"US",
    "sg:address":"137 E Indiana Ave",
    "sg:city":"Granger",
    "sg:classifiers":[
        {
            "category":"Organizations",
            "subcategory":"Religious Organization",
            "type":"Services"
        }
    ],
    "sg:phone":"+1 574 273 6511",
    "sg:postcode":"46516",
    "sg:province":"IN",
    "wof:name":"Mount Carmel Missionary Chur",
    "wof:placetype":"venue"
},
  "geometry": {"coordinates":[-85.965378,41.673834],"type":"Point"}
}