{
  "type": "Feature",
  "properties": {
    "addr:full":"21580 Jackson Rd South Bend IN 46614",
    "addr:housenumber":"21580",
    "addr:postcode":"46614",
    "addr:street":"Jackson Rd",
    "iso:country":"US",
    "sg:address":"21580 Jackson Rd",
    "sg:city":"South Bend",
    "sg:classifiers":[
        {
            "category":"Freight",
            "type":"Transportation"
        }
    ],
    "sg:phone":"+1 574 231 9347",
    "sg:postcode":"46614",
    "sg:province":"IN",
    "sg:tags":[
        "hauling",
        "trucking"
    ],
    "wof:name":"Cross Transportation",
    "wof:placetype":"venue"
},
  "geometry": {"coordinates":[-86.283604,41.621309],"type":"Point"}
}