{
  "type": "Feature",
  "properties": {
    "iso:country":"US",
    "sg:address":"163 S 3rd Ave",
    "sg:city":"Evansville",
    "sg:classifiers":[
        {
            "category":"Wholesale",
            "subcategory":"Machinery & Supplies",
            "type":"Manufacturing & Wholesale Goods"
        }
    ],
    "sg:phone":"+1 812 464 5916",
    "sg:postcode":"47639",
    "sg:province":"IN",
    "sg:tags":[
        "equipment",
        "safety",
        "clothing"
    ],
    "wof:name":"Stagg Safety Equipment Inc",
    "wof:placetype":"venue"
},
  "geometry": {"coordinates":[-87.578616,37.973861],"type":"Point"}
}