{
  "type": "Feature",
  "properties": {
    "iso:country":"US",
    "sg:address":"358 Rolling Trails Rd",
    "sg:city":"Greenwood",
    "sg:classifiers":[
        {
            "category":"Wholesale",
            "subcategory":"Stationery",
            "type":"Manufacturing & Wholesale Goods"
        }
    ],
    "sg:phone":"+1 317 888 2503",
    "sg:postcode":"46142",
    "sg:province":"IN",
    "sg:tags":[
        "packaging",
        "material"
    ],
    "wof:name":"RMR Inc",
    "wof:placetype":"venue"
},
  "geometry": {"coordinates":[-86.185597,39.618175],"type":"Point"}
}