{
  "type": "Feature",
  "properties": {
    "iso:country":"US",
    "sg:address":"1402 S Keystone Ave",
    "sg:city":"Indianapolis",
    "sg:classifiers":[
        {
            "category":"Organizations",
            "subcategory":"Religious Organization",
            "type":"Services"
        }
    ],
    "sg:phone":"+1 317 780 0597",
    "sg:postcode":"46203",
    "sg:province":"IN",
    "sg:tags":[
        "church"
    ],
    "wof:name":"Keystone Ave House Of Praise",
    "wof:placetype":"venue"
},
  "geometry": {"coordinates":[-86.121182,39.747958],"type":"Point"}
}