{
  "type": "Feature",
  "properties": {
    "addr:full":"5614 Renn Ln Indianapolis IN 46254",
    "addr:postcode":"5614;46254",
    "addr:street":"Renn Ln",
    "iso:country":"US",
    "sg:address":"5614 Renn Ln",
    "sg:city":"Indianapolis",
    "sg:classifiers":[
        {
            "category":"Food & Beverages",
            "subcategory":"Candy",
            "type":"Retail Goods"
        }
    ],
    "sg:phone":"+1 317 299 6796",
    "sg:postcode":"46254",
    "sg:province":"IN",
    "sg:tags":[
        "confectionery"
    ],
    "wof:name":"Mondra's Candy Store",
    "wof:placetype":"venue"
},
  "geometry": {"coordinates":[-86.25942499999999,39.835628],"type":"Point"}
}