{
  "type": "Feature",
  "properties": {
    "addr:full":"420 Eastern Blvd Clarksville IN 47129",
    "addr:housenumber":"420",
    "addr:postcode":"47129",
    "addr:street":"Eastern Blvd",
    "iso:country":"US",
    "sg:address":"420 Eastern Blvd",
    "sg:city":"Clarksville",
    "sg:classifiers":[
        {
            "category":"Health Services",
            "subcategory":"Podiatrist",
            "type":"Services"
        }
    ],
    "sg:phone":"+1 812 218 8250",
    "sg:postcode":"47129",
    "sg:province":"IN",
    "wof:name":"Big Foot & Johnson Oil Co",
    "wof:placetype":"venue"
},
  "geometry": {"coordinates":[-85.75801199999999,38.295524],"type":"Point"}
}