{
  "type": "Feature",
  "properties": {
    "addr:full":"809 E Washington St Lebanon IN 46052",
    "addr:housenumber":"809",
    "addr:postcode":"46052",
    "addr:street":"E Washington St",
    "iso:country":"US",
    "sg:address":"809 E Washington St",
    "sg:city":"Lebanon",
    "sg:classifiers":[
        {
            "category":"Professional",
            "subcategory":"Research",
            "type":"Services"
        }
    ],
    "sg:phone":"+1 765 482 1434",
    "sg:postcode":"46052",
    "sg:province":"IN",
    "sg:tags":[
        "commercial",
        "physical"
    ],
    "wof:name":"Natural Instinct Inc",
    "wof:placetype":"venue"
},
  "geometry": {"coordinates":[-86.45964499999999,40.048394],"type":"Point"}
}