{
  "type": "Feature",
  "properties": {
    "addr:full":"601 Jay St New Albany IN 47150",
    "addr:housenumber":"601",
    "addr:postcode":"47150",
    "addr:street":"Jay St",
    "iso:country":"US",
    "sg:address":"601 Jay St",
    "sg:city":"New Albany",
    "sg:classifiers":[
        {
            "category":"Personal",
            "subcategory":"Beauty Salon",
            "type":"Services"
        }
    ],
    "sg:phone":"+1 812 944 0863",
    "sg:postcode":"47150",
    "sg:province":"IN",
    "sg:tags":[
        "shop"
    ],
    "wof:name":"Mildred S Beauty Salon",
    "wof:placetype":"venue"
},
  "geometry": {"coordinates":[-85.803928,38.298539],"type":"Point"}
}