{
  "type": "Feature",
  "properties": {
    "iso:country":"US",
    "sg:address":"5200 E 64th St",
    "sg:city":"Indianapolis",
    "sg:classifiers":[
        {
            "category":"Home & Garden",
            "subcategory":"Building Materials",
            "type":"Retail Goods"
        }
    ],
    "sg:phone":"+1 317 252 5415",
    "sg:postcode":"46220",
    "sg:province":"IN",
    "sg:tags":[
        "insulation",
        "heat"
    ],
    "sg:website":"www.sewardsales.com",
    "wof:name":"Seward Sales Corp",
    "wof:placetype":"venue"
},
  "geometry": {"coordinates":[-86.085881,39.87246],"type":"Point"}
}