{
  "type": "Feature",
  "properties": {
    "iso:country":"US",
    "sg:address":"5201 Cider Mill Ln",
    "sg:city":"Indianapolis",
    "sg:classifiers":[
        {
            "category":"Real Estate",
            "subcategory":"Real Estate Agent",
            "type":"Services"
        }
    ],
    "sg:phone":"+1 317 545 1517",
    "sg:postcode":"46226",
    "sg:province":"IN",
    "sg:tags":[
        "management"
    ],
    "wof:name":"Ams Management LLC",
    "wof:placetype":"venue"
},
  "geometry": {"coordinates":[-86.042822,39.848106],"type":"Point"}
}