{
  "type": "Feature",
  "properties": {
    "iso:country":"US",
    "sg:address":"5140 Saddle Dr",
    "sg:city":"Lafayette",
    "sg:classifiers":[
        {
            "category":"Professional",
            "type":"Services"
        }
    ],
    "sg:phone":"+1 765 449 7944",
    "sg:postcode":"47905",
    "sg:province":"IN",
    "sg:tags":[
        "establishment"
    ],
    "wof:name":"David Owens & Sons Inc",
    "wof:placetype":"venue"
},
  "geometry": {"coordinates":[-86.805553,40.412931],"type":"Point"}
}