{
  "type": "Feature",
  "properties": {
    "iso:country":"US",
    "sg:address":"525 W Cleveland Rd",
    "sg:city":"Mishawaka",
    "sg:classifiers":[
        {
            "category":"Banks & Credit Unions",
            "subcategory":"Bank",
            "type":"Services"
        }
    ],
    "sg:phone":"+1 574 247 2860",
    "sg:postcode":"46545",
    "sg:province":"IN",
    "wof:name":"Key Bank",
    "wof:placetype":"venue"
},
  "geometry": {"coordinates":[-86.190128,41.723825],"type":"Point"}
}