{
  "type": "Feature",
  "properties": {
    "addr:full":"530 E Ohio St Indianapolis IN 46204",
    "addr:housenumber":"530",
    "addr:postcode":"46204",
    "addr:street":"E Ohio St",
    "iso:country":"US",
    "sg:address":"530 E Ohio St",
    "sg:city":"Indianapolis",
    "sg:classifiers":[
        {
            "category":"Home & Garden",
            "subcategory":"Building Materials",
            "type":"Retail Goods"
        }
    ],
    "sg:phone":"+1 317 639 6268",
    "sg:postcode":"46204",
    "sg:province":"IN",
    "sg:tags":[
        "glass",
        "window",
        "plate"
    ],
    "wof:name":"Harmon Auto Glass",
    "wof:placetype":"venue"
},
  "geometry": {"coordinates":[-86.14892999999999,39.769712],"type":"Point"}
}