{
  "type": "Feature",
  "properties": {
    "addr:full":"1203 N Main St Crown Point IN 46307",
    "addr:housenumber":"1203",
    "addr:postcode":"46307",
    "addr:street":"N Main St",
    "iso:country":"US",
    "sg:address":"1203 N Main St",
    "sg:city":"Crown Point",
    "sg:classifiers":[
        {
            "category":"Restaurant",
            "type":"Food & Drink"
        }
    ],
    "sg:menulink":"http://www.allmenus.com/in/crown-point/77333-papa-murphys/menu/",
    "sg:phone":"+1 219 226 9700",
    "sg:postcode":"46307",
    "sg:province":"IN",
    "sg:tags":[
        "american",
        "pizza"
    ],
    "wof:name":"Papa Murphy's",
    "wof:placetype":"venue"
},
  "geometry": {"coordinates":[-87.364457,41.432838],"type":"Point"}
}