{
  "type": "Feature",
  "properties": {
    "iso:country":"US",
    "sg:address":"2303 N Headley Rd",
    "sg:city":"Bloomington",
    "sg:classifiers":[
        {
            "category":"Wholesale",
            "subcategory":"Electrical",
            "type":"Manufacturing & Wholesale Goods"
        }
    ],
    "sg:phone":"+1 812 333 2288",
    "sg:postcode":"47408",
    "sg:province":"IN",
    "sg:tags":[
        "alarm",
        "burglar",
        "system"
    ],
    "wof:name":"Liberty Security",
    "wof:placetype":"venue"
},
  "geometry": {"coordinates":[-86.514504,39.189005],"type":"Point"}
}