{
  "type": "Feature",
  "properties": {
    "iso:country":"US",
    "sg:address":"40 Vernon St",
    "sg:city":"North Vernon",
    "sg:classifiers":[
        {
            "category":"Organizations",
            "subcategory":"Religious Organization",
            "type":"Services"
        }
    ],
    "sg:phone":"+1 812 873 6439",
    "sg:postcode":"47265",
    "sg:province":"IN",
    "sg:tags":[
        "church"
    ],
    "wof:name":"Graham Presbyterian Church",
    "wof:placetype":"venue"
},
  "geometry": {"coordinates":[-85.624216,39.001845],"type":"Point"}
}