{
  "type": "Feature",
  "properties": {
    "iso:country":"US",
    "sg:address":"18657 Co Rd 14",
    "sg:city":"Bristol",
    "sg:classifiers":[
        {
            "category":"Home & Garden",
            "subcategory":"Hardware",
            "type":"Retail Goods"
        }
    ],
    "sg:phone":"+1 574 848 7655",
    "sg:postcode":"46507",
    "sg:province":"IN",
    "wof:name":"Snap-On Tools",
    "wof:placetype":"venue"
},
  "geometry": {"coordinates":[-85.824738,41.692929],"type":"Point"}
}