{
  "type": "Feature",
  "properties": {
    "addr:full":"7120 E State Road 45 Bloomington IN 47408",
    "addr:housenumber":"7120",
    "addr:postcode":"47408",
    "addr:street":"E State Road 45",
    "iso:country":"US",
    "sg:address":"7120 E State Road 45",
    "sg:city":"Bloomington",
    "sg:classifiers":[
        {
            "category":"Building & Trades",
            "subcategory":"Construction",
            "type":"Services"
        }
    ],
    "sg:phone":"+1 812 330 0588",
    "sg:postcode":"47408",
    "sg:province":"IN",
    "sg:tags":[
        "contractor"
    ],
    "wof:name":"Ten O'clock Log Homes",
    "wof:placetype":"venue"
},
  "geometry": {"coordinates":[-86.43940600000001,39.225301],"type":"Point"}
}