{
  "type": "Feature",
  "properties": {
    "iso:country":"US",
    "sg:address":"6745 Gray Rd",
    "sg:city":"Indianapolis",
    "sg:classifiers":[
        {
            "category":"Social Services",
            "type":"Services"
        }
    ],
    "sg:phone":"+1 317 780 1681",
    "sg:postcode":"46237",
    "sg:province":"IN",
    "sg:tags":[
        "counselor",
        "marriage",
        "family"
    ],
    "wof:name":"Paula Chavkin",
    "wof:placetype":"venue"
},
  "geometry": {"coordinates":[-86.096687,39.669345],"type":"Point"}
}