{
  "type": "Feature",
  "properties": {
    "iso:country":"US",
    "sg:address":"13485 E 116th St",
    "sg:city":"Fishers",
    "sg:classifiers":[
        {
            "category":"Building & Trades",
            "subcategory":"Construction",
            "type":"Services"
        }
    ],
    "sg:phone":"+1 317 595 0412",
    "sg:postcode":"46037",
    "sg:province":"IN",
    "sg:tags":[
        "contractor"
    ],
    "wof:name":"Berns Construction",
    "wof:placetype":"venue"
},
  "geometry": {"coordinates":[-85.924677,39.957629],"type":"Point"}
}