{
  "type": "Feature",
  "properties": {
    "iso:country":"US",
    "sg:address":"3606 E Jefferson Blvd",
    "sg:city":"South Bend",
    "sg:classifiers":[
        {
            "category":"Shopping",
            "subcategory":"Shoes",
            "type":"Retail Goods"
        }
    ],
    "sg:phone":"+1 574 233 9510",
    "sg:postcode":"46615",
    "sg:province":"IN",
    "wof:name":"Veldman's Family Footware",
    "wof:placetype":"venue"
},
  "geometry": {"coordinates":[-86.197236,41.672863],"type":"Point"}
}