{
  "type": "Feature",
  "properties": {
    "addr:full":"4 W US Hwy 6 Valparaiso IN 46385",
    "addr:housenumber":"4",
    "addr:postcode":"46385",
    "addr:street":"W Us Hwy 6",
    "iso:country":"US",
    "sg:address":"4 W US Hwy 6",
    "sg:city":"Valparaiso",
    "sg:classifiers":[
        {
            "category":"Bars & Pubs",
            "type":"Food & Drink"
        }
    ],
    "sg:phone":"+1 219 462 8415",
    "sg:postcode":"46385",
    "sg:province":"IN",
    "wof:name":"Roadhouse Bar & Grill",
    "wof:placetype":"venue"
},
  "geometry": {"coordinates":[-87.06832900000001,41.549853],"type":"Point"}
}