{
  "type": "Feature",
  "properties": {
    "iso:country":"US",
    "sg:address":"4035 S Perry St",
    "sg:city":"Whitestown",
    "sg:classifiers":[
        {
            "category":"Building & Trades",
            "subcategory":"Construction",
            "type":"Services"
        }
    ],
    "sg:phone":"+1 317 769 3663",
    "sg:postcode":"46050",
    "sg:province":"IN",
    "sg:tags":[
        "hanging",
        "contractor"
    ],
    "wof:name":"Simon Watt LLC",
    "wof:placetype":"venue"
},
  "geometry": {"coordinates":[-86.36165200000001,40.190471],"type":"Point"}
}