{
  "type": "Feature",
  "properties": {
    "iso:country":"US",
    "sg:address":"5259 David St",
    "sg:city":"Indianapolis",
    "sg:classifiers":[
        {
            "category":"Education",
            "subcategory":"School",
            "type":"Public Place"
        }
    ],
    "sg:phone":"+1 317 546 4988",
    "sg:postcode":"46226",
    "sg:province":"IN",
    "sg:website":"www.msdlt.k12.in.us",
    "wof:name":"Brook Park Elementary School",
    "wof:placetype":"venue"
},
  "geometry": {"coordinates":[-86.050273,39.850913],"type":"Point"}
}