{
  "type": "Feature",
  "properties": {
    "iso:country":"US",
    "sg:address":"24615 Co Rd 45",
    "sg:city":"Elkhart",
    "sg:classifiers":[
        {
            "category":"Autos & Motor Vehicles",
            "subcategory":"Recreational Vehicle Sales",
            "type":"Retail Goods"
        }
    ],
    "sg:phone":"+1 574 293 0655",
    "sg:postcode":"46516",
    "sg:province":"IN",
    "wof:name":"Coach Glass",
    "wof:placetype":"venue"
},
  "geometry": {"coordinates":[-85.939611,41.65369],"type":"Point"}
}