{
  "type": "Feature",
  "properties": {
    "iso:country":"US",
    "sg:address":"2840 Guilford St",
    "sg:city":"Huntington",
    "sg:classifiers":[
        {
            "category":"Food & Beverages",
            "subcategory":"Groceries & Convenience Stores",
            "type":"Retail Goods"
        }
    ],
    "sg:phone":"+1 260 356 0130",
    "sg:postcode":"46750",
    "sg:province":"IN",
    "wof:name":"Johnson Junction Inc",
    "wof:placetype":"venue"
},
  "geometry": {"coordinates":[-85.508366,40.903582],"type":"Point"}
}