{
  "type": "Feature",
  "properties": {
    "addr:full":"24 W Main St Peru IN 46970",
    "addr:housenumber":"24",
    "addr:postcode":"46970",
    "addr:street":"W Main St",
    "iso:country":"US",
    "sg:address":"24 W Main St",
    "sg:city":"Peru",
    "sg:classifiers":[
        {
            "category":"Shopping",
            "subcategory":"Books",
            "type":"Retail Goods"
        }
    ],
    "sg:phone":"+1 765 472 5891",
    "sg:postcode":"46970",
    "sg:province":"IN",
    "sg:tags":[
        "dealer"
    ],
    "wof:name":"Christian Book Inn",
    "wof:placetype":"venue"
},
  "geometry": {"coordinates":[-86.06967400000001,40.753466],"type":"Point"}
}