{
  "type": "Feature",
  "properties": {
    "iso:country":"US",
    "sg:address":"1600 W Markland Ave",
    "sg:city":"Kokomo",
    "sg:classifiers":[
        {
            "category":"Wholesale",
            "subcategory":"Toys & Hobbies",
            "type":"Manufacturing & Wholesale Goods"
        }
    ],
    "sg:phone":"+1 765 868 9436",
    "sg:postcode":"46901",
    "sg:province":"IN",
    "sg:tags":[
        "model",
        "supply"
    ],
    "wof:name":"RJR Engineering",
    "wof:placetype":"venue"
},
  "geometry": {"coordinates":[-86.15387800000001,40.476279],"type":"Point"}
}