{
  "type": "Feature",
  "properties": {
    "iso:country":"US",
    "sg:address":"681 N 850 E",
    "sg:city":"Greenfield",
    "sg:classifiers":[
        {
            "category":"Building & Trades",
            "subcategory":"Construction",
            "type":"Services"
        }
    ],
    "sg:phone":"+1 317 523 1012",
    "sg:postcode":"46140",
    "sg:province":"IN",
    "sg:tags":[
        "contractor"
    ],
    "wof:name":"Robert A Lardon III",
    "wof:placetype":"venue"
},
  "geometry": {"coordinates":[-85.644688,39.79166],"type":"Point"}
}