{
  "type": "Feature",
  "properties": {
    "iso:country":"US",
    "sg:address":"411 SE 4th St",
    "sg:city":"Washington",
    "sg:classifiers":[
        {
            "category":"Food & Beverages",
            "subcategory":"Liquor & Beverages",
            "type":"Retail Goods"
        }
    ],
    "sg:phone":"+1 812 254 6144",
    "sg:postcode":"47501",
    "sg:province":"IN",
    "wof:name":"PAR-T-Pac Store",
    "wof:placetype":"venue"
},
  "geometry": {"coordinates":[-87.17092700000001,38.653197],"type":"Point"}
}