{
  "type": "Feature",
  "properties": {
    "iso:country":"US",
    "sg:address":"2609 S Clinton St",
    "sg:city":"Fort Wayne",
    "sg:classifiers":[
        {
            "category":"Autos & Motor Vehicles",
            "subcategory":"Auto Supplies",
            "type":"Retail Goods"
        }
    ],
    "sg:phone":"+1 260 745 3016",
    "sg:postcode":"46803",
    "sg:province":"IN",
    "sg:tags":[
        "tire"
    ],
    "wof:name":"E & M Tire Svc",
    "wof:placetype":"venue"
},
  "geometry": {"coordinates":[-85.136191,41.06091],"type":"Point"}
}