{
  "type": "Feature",
  "properties": {
    "addr:full":"202 E Tipton St Seymour IN 47274",
    "addr:housenumber":"202",
    "addr:postcode":"47274",
    "addr:street":"E Tipton St",
    "iso:country":"US",
    "sg:address":"202 E Tipton St",
    "sg:city":"Seymour",
    "sg:classifiers":[
        {
            "category":"Banks & Credit Unions",
            "subcategory":"Bank",
            "type":"Services"
        }
    ],
    "sg:phone":"+1 812 000 1111",
    "sg:postcode":"47274",
    "sg:province":"IN",
    "wof:name":"Irwin Union Bank",
    "wof:placetype":"venue"
},
  "geometry": {"coordinates":[-85.88540999999999,38.957405],"type":"Point"}
}