{
  "type": "Feature",
  "properties": {
    "addr:full":"1637 Prospect St Indianapolis IN 46203",
    "addr:housenumber":"1637",
    "addr:postcode":"46203",
    "addr:street":"Prospect St",
    "iso:country":"US",
    "sg:address":"1637 Prospect St",
    "sg:city":"Indianapolis",
    "sg:classifiers":[
        {
            "category":"Social Services",
            "type":"Services"
        },
        {
            "category":"Organizations",
            "subcategory":"Community Association",
            "type":"Services"
        },
        {
            "category":"Community Center",
            "type":"Public Place"
        }
    ],
    "sg:phone":"+1 317 636 3466",
    "sg:postcode":"46203",
    "sg:province":"IN",
    "sg:tags":[
        "recreation"
    ],
    "wof:name":"Fletcher Place Community Center",
    "wof:placetype":"venue"
},
  "geometry": {"coordinates":[-86.06362,39.753021],"type":"Point"}
}