{
  "type": "Feature",
  "properties": {
    "iso:country":"US",
    "sg:address":"4506 Co Rd 59",
    "sg:city":"Butler",
    "sg:classifiers":[
        {
            "category":"Mining & Drilling",
            "type":"Manufacturing & Wholesale Goods"
        }
    ],
    "sg:phone":"+1 260 868 5123",
    "sg:postcode":"46721",
    "sg:province":"IN",
    "sg:tags":[
        "stone"
    ],
    "wof:name":"Butler Mill Svc Co",
    "wof:placetype":"venue"
},
  "geometry": {"coordinates":[-84.908056,41.370218],"type":"Point"}
}