{
  "type": "Feature",
  "properties": {
    "addr:full":"3705 S Anthony Blvd Fort Wayne IN 46806",
    "addr:housenumber":"3705",
    "addr:postcode":"46806",
    "addr:street":"S Anthony Blvd",
    "iso:country":"US",
    "sg:address":"3705 S Anthony Blvd",
    "sg:city":"Fort Wayne",
    "sg:classifiers":[
        {
            "category":"Organizations",
            "subcategory":"Religious Organization",
            "type":"Services"
        }
    ],
    "sg:phone":"+1 260 744 3228",
    "sg:postcode":"46806",
    "sg:province":"IN",
    "wof:name":"Bethlehem Lutheran Church",
    "wof:placetype":"venue"
},
  "geometry": {"coordinates":[-85.113411,41.050166],"type":"Point"}
}