{
  "type": "Feature",
  "properties": {
    "iso:country":"US",
    "sg:address":"6344 E State Blvd",
    "sg:city":"Fort Wayne",
    "sg:classifiers":[
        {
            "category":"Food & Beverages",
            "subcategory":"Specialty",
            "type":"Retail Goods"
        }
    ],
    "sg:phone":"+1 260 493 9199",
    "sg:postcode":"46815",
    "sg:province":"IN",
    "sg:tags":[
        "health",
        "diet"
    ],
    "wof:name":"Health Kick Sports Supplements",
    "wof:placetype":"venue"
},
  "geometry": {"coordinates":[-85.05971599999999,41.100701],"type":"Point"}
}