{
  "type": "Feature",
  "properties": {
    "iso:country":"US",
    "sg:address":"12836 North St",
    "sg:city":"Dillsboro",
    "sg:classifiers":[
        {
            "category":"Shopping",
            "subcategory":"Pharmacy",
            "type":"Retail Goods"
        }
    ],
    "sg:phone":"+1 812 432 5684",
    "sg:postcode":"47018",
    "sg:province":"IN",
    "sg:website":"www.devillepharmacy.com",
    "wof:name":"Dillsboro Drug Store",
    "wof:placetype":"venue"
},
  "geometry": {"coordinates":[-85.057873,39.017855],"type":"Point"}
}