{
  "type": "Feature",
  "properties": {
    "addr:full":"2217 E 80th St Indianapolis IN 46240",
    "addr:housenumber":"2217",
    "addr:postcode":"46240",
    "addr:street":"E 80Th St",
    "iso:country":"US",
    "sg:address":"2217 E 80th St",
    "sg:city":"Indianapolis",
    "sg:classifiers":[
        {
            "category":"Organizations",
            "subcategory":"Religious Organization",
            "type":"Services"
        }
    ],
    "sg:phone":"+1 317 259 4583",
    "sg:postcode":"46240",
    "sg:province":"IN",
    "wof:name":"Ministers of Defense Inc",
    "wof:placetype":"venue"
},
  "geometry": {"coordinates":[-86.122624,39.901349],"type":"Point"}
}