{
  "type": "Feature",
  "properties": {
    "iso:country":"US",
    "sg:address":"534 S Michigan St",
    "sg:city":"South Bend",
    "sg:classifiers":[
        {
            "category":"Autos & Motor Vehicles",
            "subcategory":"Automobile Sales",
            "type":"Retail Goods"
        }
    ],
    "sg:phone":"+1 574 232 2442",
    "sg:postcode":"46601",
    "sg:province":"IN",
    "sg:tags":[
        "car",
        "dealer"
    ],
    "wof:name":"Thomas Motors",
    "wof:placetype":"venue"
},
  "geometry": {"coordinates":[-86.250167,41.670771],"type":"Point"}
}