{
  "type": "Feature",
  "properties": {
    "iso:country":"US",
    "sg:address":"9418 Haverstick Rd",
    "sg:city":"Indianapolis",
    "sg:classifiers":[
        {
            "category":"Health Services",
            "subcategory":"Doctor",
            "type":"Services"
        }
    ],
    "sg:phone":"+1 317 844 5662",
    "sg:postcode":"46240",
    "sg:province":"IN",
    "wof:name":"Moore Thomas J MD",
    "wof:placetype":"venue"
},
  "geometry": {"coordinates":[-86.117203,39.925598],"type":"Point"}
}