{
  "type": "Feature",
  "properties": {
    "iso:country":"US",
    "sg:address":"1649 Central Ave",
    "sg:city":"Whiting",
    "sg:classifiers":[
        {
            "category":"Shopping",
            "subcategory":"Gifts & Souvenirs",
            "type":"Retail Goods"
        }
    ],
    "sg:phone":"+1 219 659 2508",
    "sg:postcode":"46394",
    "sg:province":"IN",
    "wof:name":"Gifts & More From Cinotto Ente",
    "wof:placetype":"venue"
},
  "geometry": {"coordinates":[-87.49780800000001,41.683702],"type":"Point"}
}