{
  "type": "Feature",
  "properties": {
    "iso:country":"US",
    "sg:address":"8814 State Rd 236",
    "sg:city":"Middletown",
    "sg:classifiers":[
        {
            "category":"Organizations",
            "subcategory":"Religious Organization",
            "type":"Services"
        }
    ],
    "sg:phone":"+1 765 354 2088",
    "sg:postcode":"47356",
    "sg:province":"IN",
    "sg:tags":[
        "church"
    ],
    "wof:name":"Fall Creek Apostolic Church",
    "wof:placetype":"venue"
},
  "geometry": {"coordinates":[-85.553505,40.062247],"type":"Point"}
}