{
  "type": "Feature",
  "properties": {
    "iso:country":"US",
    "sg:address":"51 Hornaday Rd",
    "sg:city":"Brownsburg",
    "sg:classifiers":[
        {
            "category":"Food & Beverages",
            "subcategory":"Groceries & Convenience Stores",
            "type":"Retail Goods"
        }
    ],
    "sg:phone":"+1 317 858 2365",
    "sg:postcode":"46112",
    "sg:province":"IN",
    "wof:name":"Village Pantry",
    "wof:placetype":"venue"
},
  "geometry": {"coordinates":[-86.381834,39.837106],"type":"Point"}
}