{
  "type": "Feature",
  "properties": {
    "iso:country":"US",
    "sg:address":"413 Main St",
    "sg:city":"Rising Sun",
    "sg:classifiers":[
        {
            "category":"Professional",
            "type":"Services"
        }
    ],
    "sg:phone":"+1 812 438 4075",
    "sg:postcode":"47040",
    "sg:province":"IN",
    "wof:name":"Ohio County Veterans Svc Offcr",
    "wof:placetype":"venue"
},
  "geometry": {"coordinates":[-84.855874,38.950081],"type":"Point"}
}