{
  "type": "Feature",
  "properties": {
    "addr:full":"6847 Hillsdale Ct Indianapolis IN 46250",
    "addr:housenumber":"6847",
    "addr:postcode":"46250",
    "addr:street":"Hillsdale Ct",
    "iso:country":"US",
    "sg:address":"6847 Hillsdale Ct",
    "sg:city":"Indianapolis",
    "sg:classifiers":[
        {
            "category":"Home & Garden",
            "subcategory":"Furniture",
            "type":"Retail Goods"
        }
    ],
    "sg:phone":"+1 317 897 5429",
    "sg:postcode":"46250",
    "sg:province":"IN",
    "sg:tags":[
        "cabinet"
    ],
    "wof:name":"HCI Cabinetry Inc",
    "wof:placetype":"venue"
},
  "geometry": {"coordinates":[-86.049689,39.896092],"type":"Point"}
}