{
  "type": "Feature",
  "properties": {
    "iso:country":"US",
    "sg:address":"1515 Indianapolis Ave",
    "sg:city":"Lebanon",
    "sg:classifiers":[
        {
            "category":"Autos & Motor Vehicles",
            "subcategory":"Automobile Sales",
            "type":"Retail Goods"
        }
    ],
    "sg:phone":"+1 765 482 0170",
    "sg:postcode":"46052",
    "sg:province":"IN",
    "sg:tags":[
        "car",
        "dealer"
    ],
    "sg:website":"www.genelewisford.com",
    "wof:name":"Gene Lewis Ford",
    "wof:placetype":"venue"
},
  "geometry": {"coordinates":[-86.454433,40.03598],"type":"Point"}
}