{
  "type": "Feature",
  "properties": {
    "iso:country":"US",
    "sg:address":"950 150th St",
    "sg:city":"Hammond",
    "sg:classifiers":[
        {
            "category":"Building & Trades",
            "subcategory":"Construction",
            "type":"Services"
        }
    ],
    "sg:phone":"+1 219 932 0812",
    "sg:postcode":"46327",
    "sg:province":"IN",
    "sg:tags":[
        "contractor"
    ],
    "wof:name":"Ironwood Construction Inc",
    "wof:placetype":"venue"
},
  "geometry": {"coordinates":[-87.504683,41.622955],"type":"Point"}
}