{
  "type": "Feature",
  "properties": {
    "iso:country":"US",
    "sg:address":"11386 US Hwy 50",
    "sg:city":"Norman",
    "sg:classifiers":[
        {
            "category":"Farming",
            "subcategory":"Farm",
            "type":"Manufacturing & Wholesale Goods"
        }
    ],
    "sg:phone":"+1 812 995 3642",
    "sg:postcode":"47264",
    "sg:province":"IN",
    "wof:name":"Shady Springs Farms",
    "wof:placetype":"venue"
},
  "geometry": {"coordinates":[-86.254494,38.884429],"type":"Point"}
}