{
  "type": "Feature",
  "properties": {
    "iso:country":"US",
    "sg:address":"9196 State Rd 46",
    "sg:city":"Brookville",
    "sg:classifiers":[
        {
            "category":"Utilities",
            "subcategory":"Telephone",
            "type":"Services"
        }
    ],
    "sg:phone":"+1 812 576 0747",
    "sg:postcode":"47041",
    "sg:province":"IN",
    "sg:tags":[
        "telecommunication"
    ],
    "wof:name":"Cincinnati Bell Wireless",
    "wof:placetype":"venue"
},
  "geometry": {"coordinates":[-84.99636599999999,39.285049],"type":"Point"}
}