{
  "type": "Feature",
  "properties": {
    "iso:country":"US",
    "sg:address":"806 S Green River Rd",
    "sg:city":"Evansville",
    "sg:classifiers":[
        {
            "category":"Shopping",
            "subcategory":"Gifts & Souvenirs",
            "type":"Retail Goods"
        }
    ],
    "sg:phone":"+1 812 476 3637",
    "sg:postcode":"47715",
    "sg:province":"IN",
    "sg:tags":[
        "shop"
    ],
    "wof:name":"Jennifer's Hallmark",
    "wof:placetype":"venue"
},
  "geometry": {"coordinates":[-87.492611,37.962436],"type":"Point"}
}