{
  "type": "Feature",
  "properties": {
    "iso:country":"US",
    "sg:address":"110 Burlington Ave",
    "sg:city":"Logansport",
    "sg:classifiers":[
        {
            "category":"Wholesale",
            "subcategory":"Electrical",
            "type":"Manufacturing & Wholesale Goods"
        }
    ],
    "sg:phone":"+1 574 753 3597",
    "sg:postcode":"46947",
    "sg:province":"IN",
    "sg:tags":[
        "electric",
        "motor"
    ],
    "wof:name":"Tweedie Electric Motor Svc",
    "wof:placetype":"venue"
},
  "geometry": {"coordinates":[-86.366182,40.748239],"type":"Point"}
}