{
  "type": "Feature",
  "properties": {
    "addr:full":"117 N 3rd St Gas City IN 46933",
    "addr:housenumber":"117",
    "addr:postcode":"46933",
    "addr:street":"N 3Rd St",
    "iso:country":"US",
    "sg:address":"117 N 3rd St",
    "sg:city":"Gas City",
    "sg:classifiers":[
        {
            "category":"Shopping",
            "subcategory":"Florist",
            "type":"Retail Goods"
        }
    ],
    "sg:phone":"+1 765 677 0340",
    "sg:postcode":"46933",
    "sg:province":"IN",
    "wof:name":"Grandma Jenny's Flower",
    "wof:placetype":"venue"
},
  "geometry": {"coordinates":[-85.611109,40.488687],"type":"Point"}
}