{
  "type": "Feature",
  "properties": {
    "iso:country":"US",
    "sg:address":"2707 Newton St",
    "sg:city":"Jasper",
    "sg:classifiers":[
        {
            "category":"Food & Beverages",
            "subcategory":"Groceries & Convenience Stores",
            "type":"Retail Goods"
        }
    ],
    "sg:phone":"+1 812 482 6363",
    "sg:postcode":"47546",
    "sg:province":"IN",
    "wof:name":"Citgo",
    "wof:placetype":"venue"
},
  "geometry": {"coordinates":[-86.93797000000001,38.412926],"type":"Point"}
}