{
  "type": "Feature",
  "properties": {
    "iso:country":"US",
    "sg:address":"1500 E State Rd 32",
    "sg:city":"Veedersburg",
    "sg:classifiers":[
        {
            "category":"Building & Trades",
            "subcategory":"Construction",
            "type":"Services"
        }
    ],
    "sg:phone":"+1 765 798 5244",
    "sg:postcode":"47987",
    "sg:province":"IN",
    "sg:tags":[
        "house"
    ],
    "wof:name":"Meuser Construction",
    "wof:placetype":"venue"
},
  "geometry": {"coordinates":[-87.186597,40.03939],"type":"Point"}
}