{
  "type": "Feature",
  "properties": {
    "iso:country":"US",
    "sg:address":"716 S Park Ave",
    "sg:city":"Batesville",
    "sg:classifiers":[
        {
            "category":"Recreation",
            "type":"Entertainment"
        }
    ],
    "sg:phone":"+1 812 934 4560",
    "sg:postcode":"47006",
    "sg:province":"IN",
    "sg:tags":[
        "parks"
    ],
    "wof:name":"Batesville Parks & Recreation",
    "wof:placetype":"venue"
},
  "geometry": {"coordinates":[-85.22193900000001,39.291394],"type":"Point"}
}