{
  "type": "Feature",
  "properties": {
    "iso:country":"US",
    "sg:address":"709 E Main St",
    "sg:city":"Washington",
    "sg:classifiers":[
        {
            "category":"Social Services",
            "type":"Services"
        }
    ],
    "sg:phone":"+1 812 254 7693",
    "sg:postcode":"47501",
    "sg:province":"IN",
    "wof:name":"Power House",
    "wof:placetype":"venue"
},
  "geometry": {"coordinates":[-87.167441,38.656881],"type":"Point"}
}