{
  "type": "Feature",
  "properties": {
    "iso:country":"US",
    "sg:address":"1716 Wayne St",
    "sg:city":"Auburn",
    "sg:classifiers":[
        {
            "category":"Home & Garden",
            "subcategory":"Furniture",
            "type":"Retail Goods"
        }
    ],
    "sg:phone":"+1 260 925 9259",
    "sg:postcode":"46706",
    "sg:province":"IN",
    "sg:tags":[
        "bedding"
    ],
    "wof:name":"Corunna Bedding Co",
    "wof:placetype":"venue"
},
  "geometry": {"coordinates":[-85.058037,41.354953],"type":"Point"}
}