{
  "type": "Feature",
  "properties": {
    "iso:country":"US",
    "sg:address":"244 N Main St",
    "sg:city":"Versailles",
    "sg:classifiers":[
        {
            "category":"Real Estate",
            "subcategory":"Surveying",
            "type":"Services"
        }
    ],
    "sg:phone":"+1 812 689 5995",
    "sg:postcode":"47042",
    "sg:province":"IN",
    "sg:tags":[
        "surveyor"
    ],
    "wof:name":"French & Assoc",
    "wof:placetype":"venue"
},
  "geometry": {"coordinates":[-85.251024,39.073056],"type":"Point"}
}