{
  "type": "Feature",
  "properties": {
    "iso:country":"US",
    "sg:address":"8902 E 38th St",
    "sg:city":"Indianapolis",
    "sg:classifiers":[
        {
            "category":"Organizations",
            "subcategory":"Religious Organization",
            "type":"Services"
        }
    ],
    "sg:phone":"+1 317 899 6771",
    "sg:postcode":"46226",
    "sg:province":"IN",
    "wof:name":"New Wineskin Ministries East",
    "wof:placetype":"venue"
},
  "geometry": {"coordinates":[-86.01146300000001,39.8261],"type":"Point"}
}