{
  "type": "Feature",
  "properties": {
    "iso:country":"US",
    "sg:address":"10930 Marlin Rd",
    "sg:city":"Wanamaker",
    "sg:classifiers":[
        {
            "category":"Building & Trades",
            "subcategory":"Construction",
            "type":"Services"
        }
    ],
    "sg:phone":"+1 317 862 5189",
    "sg:postcode":"46239",
    "sg:province":"IN",
    "sg:tags":[
        "excavating",
        "contractor"
    ],
    "wof:name":"Russell Excavating Inc",
    "wof:placetype":"venue"
},
  "geometry": {"coordinates":[-85.967598,39.704297],"type":"Point"}
}