{
  "type": "Feature",
  "properties": {
    "iso:country":"US",
    "sg:address":"3876 S Village Row",
    "sg:city":"New Palestine",
    "sg:classifiers":[
        {
            "category":"Professional",
            "subcategory":"Business Services",
            "type":"Services"
        }
    ],
    "sg:phone":"+1 317 861 4847",
    "sg:postcode":"46163",
    "sg:province":"IN",
    "wof:name":"Russell Associates LLC",
    "wof:placetype":"venue"
},
  "geometry": {"coordinates":[-85.943079,39.728323],"type":"Point"}
}