{
  "type": "Feature",
  "properties": {
    "addr:full":"5150 Moller Rd Indianapolis IN 46254",
    "addr:housenumber":"5150",
    "addr:postcode":"46254",
    "addr:street":"Moller Rd",
    "iso:country":"US",
    "sg:address":"5150 Moller Rd",
    "sg:city":"Indianapolis",
    "sg:classifiers":[
        {
            "category":"Organizations",
            "subcategory":"Religious Organization",
            "type":"Services"
        }
    ],
    "sg:phone":"+1 317 297 3472",
    "sg:postcode":"46254",
    "sg:province":"IN",
    "sg:tags":[
        "church"
    ],
    "wof:name":"Jehovah's Witnesses",
    "wof:placetype":"venue"
},
  "geometry": {"coordinates":[-86.262255,39.845281],"type":"Point"}
}