{
  "type": "Feature",
  "properties": {
    "iso:country":"US",
    "sg:address":"3210 Waterloo Rd",
    "sg:city":"Connersville",
    "sg:classifiers":[
        {
            "category":"Organizations",
            "subcategory":"Religious Organization",
            "type":"Services"
        }
    ],
    "sg:phone":"+1 765 827 5881",
    "sg:postcode":"47331",
    "sg:province":"IN",
    "sg:tags":[
        "church"
    ],
    "wof:name":"Church Of God Of Prophecy",
    "wof:placetype":"venue"
},
  "geometry": {"coordinates":[-85.124036,39.674911],"type":"Point"}
}