{
  "type": "Feature",
  "properties": {
    "iso:country":"US",
    "sg:address":"1362 State Rd 46",
    "sg:city":"Batesville",
    "sg:classifiers":[
        {
            "category":"Home & Garden",
            "subcategory":"Building Materials",
            "type":"Retail Goods"
        }
    ],
    "sg:phone":"+1 812 273 5335",
    "sg:postcode":"47006",
    "sg:province":"IN",
    "sg:tags":[
        "glass",
        "window",
        "plate"
    ],
    "wof:name":"Horizon Auto Glass",
    "wof:placetype":"venue"
},
  "geometry": {"coordinates":[-85.205405,39.29084],"type":"Point"}
}