{
  "type": "Feature",
  "properties": {
    "addr:full":"200 E 7th St Auburn IN 46706",
    "addr:housenumber":"200",
    "addr:postcode":"46706",
    "addr:street":"E 7Th St",
    "iso:country":"US",
    "sg:address":"200 E 7th St",
    "sg:city":"Auburn",
    "sg:classifiers":[
        {
            "category":"Banks & Credit Unions",
            "subcategory":"Investment Brokerage",
            "type":"Services"
        }
    ],
    "sg:phone":"+1 260 925 0925",
    "sg:postcode":"46706",
    "sg:province":"IN",
    "sg:tags":[
        "stock",
        "bond"
    ],
    "wof:name":"Edward Jones Co",
    "wof:placetype":"venue"
},
  "geometry": {"coordinates":[-85.053321,41.366966],"type":"Point"}
}