{
  "type": "Feature",
  "properties": {
    "iso:country":"US",
    "sg:address":"24577 Green Valley Pkwy",
    "sg:city":"Elkhart",
    "sg:classifiers":[
        {
            "category":"Professional",
            "subcategory":"Management & Consulting",
            "type":"Services"
        }
    ],
    "sg:phone":"+1 574 875 1133",
    "sg:postcode":"46517",
    "sg:province":"IN",
    "sg:tags":[
        "consultant",
        "energy",
        "conservation"
    ],
    "wof:name":"Resources For Microelectronics",
    "wof:placetype":"venue"
},
  "geometry": {"coordinates":[-85.937853,41.634701],"type":"Point"}
}