{
  "type": "Feature",
  "properties": {
    "iso:country":"US",
    "sg:address":"5835 W Co Rd 200 S",
    "sg:city":"New Castle",
    "sg:classifiers":[
        {
            "category":"Travel",
            "subcategory":"Hotels & Motels",
            "type":"Entertainment"
        }
    ],
    "sg:phone":"+1 765 785 2810",
    "sg:postcode":"47362",
    "sg:province":"IN",
    "wof:name":"LA Casa Di' Maroni",
    "wof:placetype":"venue"
},
  "geometry": {"coordinates":[-85.497018,39.902361],"type":"Point"}
}