{
  "type": "Feature",
  "properties": {
    "iso:country":"US",
    "sg:address":"527 Main St",
    "sg:city":"Lafayette",
    "sg:classifiers":[
        {
            "category":"Banks & Credit Unions",
            "subcategory":"Bank",
            "type":"Services"
        }
    ],
    "sg:phone":"+1 765 423 2326",
    "sg:postcode":"47901",
    "sg:province":"IN",
    "sg:tags":[
        "loan",
        "real estate"
    ],
    "wof:name":"A Fairway Mortgage",
    "wof:placetype":"venue"
},
  "geometry": {"coordinates":[-86.890948,40.419084],"type":"Point"}
}