{
  "type": "Feature",
  "properties": {
    "iso:country":"US",
    "sg:address":"2001 S Calhoun St",
    "sg:city":"Fort Wayne",
    "sg:classifiers":[
        {
            "category":"Home & Garden",
            "subcategory":"Building Materials",
            "type":"Retail Goods"
        }
    ],
    "sg:phone":"+1 260 456 4581",
    "sg:postcode":"46802",
    "sg:province":"IN",
    "sg:tags":[
        "windows"
    ],
    "sg:website":"www.fortwayne.pella.com",
    "wof:name":"Irmscher Suppliers Inc",
    "wof:placetype":"venue"
},
  "geometry": {"coordinates":[-85.138067,41.066328],"type":"Point"}
}