{
  "type": "Feature",
  "properties": {
    "iso:country":"US",
    "sg:address":"203 S Huntington St",
    "sg:city":"Syracuse",
    "sg:classifiers":[
        {
            "category":"Manufacturing",
            "subcategory":"Buildings",
            "type":"Manufacturing & Wholesale Goods"
        }
    ],
    "sg:phone":"+1 574 457 3121",
    "sg:postcode":"46567",
    "sg:province":"IN",
    "sg:tags":[
        "mobile",
        "home"
    ],
    "sg:website":"www.libertyhomesinc.com",
    "wof:name":"Liberty Homes Inc",
    "wof:placetype":"venue"
},
  "geometry": {"coordinates":[-85.747532,41.420087],"type":"Point"}
}