{
  "type": "Feature",
  "properties": {
    "iso:country":"US",
    "sg:address":"111 Bing Blvd",
    "sg:city":"Chesterfield",
    "sg:classifiers":[
        {
            "category":"Organizations",
            "subcategory":"Labor Organization",
            "type":"Services"
        }
    ],
    "sg:phone":"+1 765 378 5242",
    "sg:postcode":"46017",
    "sg:province":"IN",
    "wof:name":"D C 91",
    "wof:placetype":"venue"
},
  "geometry": {"coordinates":[-85.603928,40.115473],"type":"Point"}
}