{
  "type": "Feature",
  "properties": {
    "addr:full":"204 S Wayne St Angola IN 46703",
    "addr:housenumber":"204",
    "addr:postcode":"46703",
    "addr:street":"S Wayne St",
    "iso:country":"US",
    "sg:address":"204 S Wayne St",
    "sg:city":"Angola",
    "sg:classifiers":[
        {
            "category":"Professional",
            "type":"Services"
        }
    ],
    "sg:phone":"+1 260 665 5860",
    "sg:postcode":"46703",
    "sg:province":"IN",
    "sg:tags":[
        "establishment"
    ],
    "wof:name":"3-D Optics",
    "wof:placetype":"venue"
},
  "geometry": {"coordinates":[-84.999326,41.633951],"type":"Point"}
}