{
  "type": "Feature",
  "properties": {
    "iso:country":"US",
    "sg:address":"1808 Coliseum Blvd N",
    "sg:city":"Fort Wayne",
    "sg:classifiers":[
        {
            "category":"Home & Garden",
            "subcategory":"Furniture",
            "type":"Retail Goods"
        }
    ],
    "sg:phone":"+1 260 424 8800",
    "sg:postcode":"46805",
    "sg:province":"IN",
    "sg:tags":[
        "mattress"
    ],
    "wof:name":"Mattress Warehouse",
    "wof:placetype":"venue"
},
  "geometry": {"coordinates":[-85.08818100000001,41.093804],"type":"Point"}
}