{
  "type": "Feature",
  "properties": {
    "iso:country":"US",
    "sg:address":"2814 N Granville Ave",
    "sg:city":"Muncie",
    "sg:classifiers":[
        {
            "category":"Shopping",
            "subcategory":"Used Merchandise",
            "type":"Retail Goods"
        }
    ],
    "sg:phone":"+1 765 741 9692",
    "sg:postcode":"47303",
    "sg:province":"IN",
    "sg:tags":[
        "pawnbroker"
    ],
    "wof:name":"Delaware County Pawn Brokers",
    "wof:placetype":"venue"
},
  "geometry": {"coordinates":[-85.376791,40.215831],"type":"Point"}
}