{
  "type": "Feature",
  "properties": {
    "addr:full":"6531 N Co Rd 800 W Yorktown IN 47396",
    "addr:housenumber":"6531",
    "addr:postcode":"47396",
    "addr:street":"N Co Rd 800 W",
    "iso:country":"US",
    "sg:address":"6531 N Co Rd 800 W",
    "sg:city":"Yorktown",
    "sg:classifiers":[
        {
            "category":"Building & Trades",
            "subcategory":"Landscaping Services",
            "type":"Services"
        }
    ],
    "sg:phone":"+1 765 759 5835",
    "sg:postcode":"47396",
    "sg:province":"IN",
    "sg:tags":[
        "landscape",
        "contractor"
    ],
    "wof:name":"Global Tech Hydroseeding",
    "wof:placetype":"venue"
},
  "geometry": {"coordinates":[-85.538625,40.247249],"type":"Point"}
}