{
  "type": "Feature",
  "properties": {
    "iso:country":"US",
    "sg:address":"502 E Daisy Ln",
    "sg:city":"New Albany",
    "sg:classifiers":[
        {
            "category":"Building & Trades",
            "subcategory":"Plumbing",
            "type":"Services"
        }
    ],
    "sg:phone":"+1 812 542 1800",
    "sg:postcode":"47150",
    "sg:province":"IN",
    "sg:tags":[
        "plumbing",
        "contractor"
    ],
    "wof:name":"H2o Plumbing LLC",
    "wof:placetype":"venue"
},
  "geometry": {"coordinates":[-85.826194,38.309655],"type":"Point"}
}