{
  "type": "Feature",
  "properties": {
    "iso:country":"US",
    "sg:address":"216 Wedeking Ave",
    "sg:city":"Evansville",
    "sg:classifiers":[
        {
            "category":"Organizations",
            "subcategory":"Religious Organization",
            "type":"Services"
        }
    ],
    "sg:phone":"+1 812 867 7859",
    "sg:postcode":"47711",
    "sg:province":"IN",
    "wof:name":"Grace Fellowship Chapel",
    "wof:placetype":"venue"
},
  "geometry": {"coordinates":[-87.558722,37.997674],"type":"Point"}
}