{
  "type": "Feature",
  "properties": {
    "iso:country":"US",
    "sg:address":"700 Park Ave",
    "sg:city":"Winona Lake",
    "sg:classifiers":[
        {
            "category":"Shopping",
            "subcategory":"Gifts & Souvenirs",
            "type":"Retail Goods"
        }
    ],
    "sg:phone":"+1 574 269 3232",
    "sg:postcode":"46590",
    "sg:province":"IN",
    "sg:tags":[
        "shop"
    ],
    "wof:name":"Winona Mercantile",
    "wof:placetype":"venue"
},
  "geometry": {"coordinates":[-85.822856,41.231052],"type":"Point"}
}