{
  "type": "Feature",
  "properties": {
    "iso:country":"US",
    "sg:address":"5475 State Rd 7",
    "sg:city":"Scipio",
    "sg:classifiers":[
        {
            "category":"Autos & Motor Vehicles",
            "subcategory":"Fuel & Gas Station",
            "type":"Retail Goods"
        }
    ],
    "sg:phone":"+1 812 392 2034",
    "sg:postcode":"47273",
    "sg:province":"IN",
    "sg:tags":[
        "station",
        "gasoline",
        "oil"
    ],
    "wof:name":"Alexander's Gas & Grocery",
    "wof:placetype":"venue"
},
  "geometry": {"coordinates":[-85.698763,39.064329],"type":"Point"}
}