{
  "type": "Feature",
  "properties": {
    "iso:country":"US",
    "sg:address":"133 S Benton St",
    "sg:city":"Millersburg",
    "sg:classifiers":[
        {
            "category":"Retail",
            "subcategory":"Auto Repair",
            "type":"Services"
        }
    ],
    "sg:phone":"+1 574 642 4334",
    "sg:postcode":"46543",
    "sg:province":"IN",
    "sg:tags":[
        "repairing",
        "automobile"
    ],
    "wof:name":"Larry's Car Care",
    "wof:placetype":"venue"
},
  "geometry": {"coordinates":[-85.693389,41.524029],"type":"Point"}
}