{
  "type": "Feature",
  "properties": {
    "iso:country":"US",
    "sg:address":"1123 N Western Ave",
    "sg:city":"Marion",
    "sg:classifiers":[
        {
            "category":"Real Estate",
            "subcategory":"Real Estate Agent",
            "type":"Services"
        }
    ],
    "sg:phone":"+1 765 664 2322",
    "sg:postcode":"46952",
    "sg:province":"IN",
    "wof:name":"Re/Max Regency Realtors",
    "wof:placetype":"venue"
},
  "geometry": {"coordinates":[-85.674289,40.573983],"type":"Point"}
}