{
  "type": "Feature",
  "properties": {
    "iso:country":"US",
    "sg:address":"2118 Inwood Dr",
    "sg:city":"Fort Wayne",
    "sg:classifiers":[
        {
            "category":"Professional",
            "subcategory":"Advertising",
            "type":"Services"
        }
    ],
    "sg:phone":"+1 260 483 6478",
    "sg:postcode":"46815",
    "sg:province":"IN",
    "sg:tags":[
        "counselor"
    ],
    "wof:name":"Advangelism",
    "wof:placetype":"venue"
},
  "geometry": {"coordinates":[-85.08662,41.098623],"type":"Point"}
}