{
  "type": "Feature",
  "properties": {
    "addr:full":"17 Joliet St Dyer IN 46311",
    "addr:housenumber":"17",
    "addr:postcode":"46311",
    "addr:street":"Joliet St",
    "iso:country":"US",
    "sg:address":"17 Joliet St",
    "sg:city":"Dyer",
    "sg:classifiers":[
        {
            "category":"Shopping",
            "subcategory":"Tobacco",
            "type":"Retail Goods"
        }
    ],
    "sg:phone":"+1 219 865 5405",
    "sg:postcode":"46311",
    "sg:province":"IN",
    "sg:tags":[
        "cigarette",
        "cigar",
        "dealer"
    ],
    "wof:name":"Smokes",
    "wof:placetype":"venue"
},
  "geometry": {"coordinates":[-87.525032,41.494713],"type":"Point"}
}