{
  "type": "Feature",
  "properties": {
    "iso:country":"US",
    "sg:address":"420 Main St",
    "sg:city":"Evansville",
    "sg:classifiers":[
        {
            "category":"Organizations",
            "subcategory":"Community Association",
            "type":"Services"
        }
    ],
    "sg:phone":"+1 812 423 4422",
    "sg:postcode":"47708",
    "sg:province":"IN",
    "sg:tags":[
        "club"
    ],
    "wof:name":"Petroleum Club Inc",
    "wof:placetype":"venue"
},
  "geometry": {"coordinates":[-87.57026999999999,37.972055],"type":"Point"}
}