{
  "type": "Feature",
  "properties": {
    "iso:country":"US",
    "sg:address":"603 N Townline Rd",
    "sg:city":"Lagrange",
    "sg:classifiers":[
        {
            "category":"Education",
            "subcategory":"School",
            "type":"Public Place"
        }
    ],
    "sg:phone":"+1 260 463 9916",
    "sg:postcode":"46761",
    "sg:province":"IN",
    "sg:tags":[
        "educational",
        "program"
    ],
    "wof:name":"Four County Area Vocational",
    "wof:placetype":"venue"
},
  "geometry": {"coordinates":[-85.424955,41.649237],"type":"Point"}
}