{
  "type": "Feature",
  "properties": {
    "iso:country":"US",
    "sg:address":"6998 N State Rd 29",
    "sg:city":"Frankfort",
    "sg:classifiers":[
        {
            "category":"Utilities",
            "subcategory":"Mobile Phone",
            "type":"Services"
        }
    ],
    "sg:phone":"+1 765 249 2304",
    "sg:postcode":"46041",
    "sg:province":"IN",
    "sg:tags":[
        "telephone",
        "cellular"
    ],
    "wof:name":"Veristar Wireless Svc Inc",
    "wof:placetype":"venue"
},
  "geometry": {"coordinates":[-86.39325599999999,40.377535],"type":"Point"}
}