{
  "type": "Feature",
  "properties": {
    "addr:full":"1070 Millville Ave Hamilton IN 45013",
    "addr:housenumber":"1070",
    "addr:postcode":"45013",
    "addr:street":"Millville Ave",
    "iso:country":"US",
    "sg:address":"1070 Millville Ave",
    "sg:city":"Hamilton",
    "sg:classifiers":[
        {
            "category":"Personal",
            "subcategory":"Barber",
            "type":"Services"
        }
    ],
    "sg:phone":"+1 513 892 8881",
    "sg:postcode":"45013",
    "sg:province":"IN",
    "wof:name":"Doug's Barber Shop",
    "wof:placetype":"venue"
},
  "geometry": {"coordinates":[-84.59805299999999,39.40619],"type":"Point"}
}