{
  "type": "Feature",
  "properties": {
    "iso:country":"US",
    "sg:address":"4420 E Bristol St",
    "sg:city":"Elkhart",
    "sg:classifiers":[
        {
            "category":"Health Services",
            "subcategory":"Doctor",
            "type":"Services"
        }
    ],
    "sg:phone":"+1 574 264 9499",
    "sg:postcode":"46514",
    "sg:province":"IN",
    "sg:tags":[
        "dentist"
    ],
    "wof:name":"Gregory A Robbins PC",
    "wof:placetype":"venue"
},
  "geometry": {"coordinates":[-85.927815,41.702232],"type":"Point"}
}