{
  "type": "Feature",
  "properties": {
    "addr:full":"752 N Dan Jones Rd Plainfield IN 46168",
    "addr:housenumber":"752",
    "addr:postcode":"46168",
    "addr:street":"N Dan Jones Rd",
    "iso:country":"US",
    "sg:address":"752 N Dan Jones Rd",
    "sg:city":"Plainfield",
    "sg:classifiers":[
        {
            "category":"Place Of Worship",
            "subcategory":"Church",
            "type":"Public Place"
        },
        {
            "category":"Place Of Worship",
            "type":"Public Place"
        }
    ],
    "sg:phone":"+1 317 839 7592",
    "sg:postcode":"46168",
    "sg:province":"IN",
    "sg:tags":[
        "bible",
        "churches-independent"
    ],
    "sg:website":"http://www.plainfieldbible.com",
    "wof:name":"Plainfield Bible Church",
    "wof:placetype":"venue"
},
  "geometry": {"coordinates":[-86.38081699999999,39.71835],"type":"Point"}
}