{
  "type": "Feature",
  "properties": {
    "addr:full":"8902 E 38th St Indianapolis IN 46226",
    "addr:housenumber":"8902",
    "addr:postcode":"46226",
    "addr:street":"E 38Th St",
    "iso:country":"US",
    "sg:address":"8902 E 38th St",
    "sg:city":"Indianapolis",
    "sg:classifiers":[
        {
            "category":"Social Services",
            "subcategory":"Child Care",
            "type":"Services"
        }
    ],
    "sg:phone":"+1 317 803 9607",
    "sg:postcode":"46226",
    "sg:province":"IN",
    "sg:tags":[
        "kindergarten",
        "academic",
        "school"
    ],
    "wof:name":"Cafe Head Start",
    "wof:placetype":"venue"
},
  "geometry": {"coordinates":[-86.01146300000001,39.8261],"type":"Point"}
}