{
  "type": "Feature",
  "properties": {
    "iso:country":"US",
    "sg:address":"7410 N Irvington Ave",
    "sg:city":"Indianapolis",
    "sg:classifiers":[
        {
            "category":"Professional",
            "subcategory":"Management & Consulting",
            "type":"Services"
        }
    ],
    "sg:phone":"+1 317 585 1645",
    "sg:postcode":"46250",
    "sg:province":"IN",
    "sg:tags":[
        "marketing",
        "consultant"
    ],
    "wof:name":"Fanastic Sams",
    "wof:placetype":"venue"
},
  "geometry": {"coordinates":[-86.077426,39.887542],"type":"Point"}
}