{
  "type": "Feature",
  "properties": {
    "iso:country":"US",
    "sg:address":"173 N Van Buren St",
    "sg:city":"Nashville",
    "sg:classifiers":[
        {
            "category":"Shopping",
            "subcategory":"Gifts & Souvenirs",
            "type":"Retail Goods"
        }
    ],
    "sg:phone":"+1 812 988 8068",
    "sg:postcode":"47448",
    "sg:province":"IN",
    "sg:tags":[
        "shop"
    ],
    "wof:name":"Now & Then",
    "wof:placetype":"venue"
},
  "geometry": {"coordinates":[-86.246859,39.207375],"type":"Point"}
}