{
  "type": "Feature",
  "properties": {
    "iso:country":"US",
    "sg:address":"3901 US Hwy 41",
    "sg:city":"Evansville",
    "sg:classifiers":[
        {
            "category":"Travel",
            "subcategory":"Hotels & Motels",
            "type":"Entertainment"
        }
    ],
    "sg:phone":"+1 812 423 5818",
    "sg:postcode":"47711",
    "sg:province":"IN",
    "wof:name":"Drury Inns",
    "wof:placetype":"venue"
},
  "geometry": {"coordinates":[-87.539324,38.017026],"type":"Point"}
}