{
  "type": "Feature",
  "properties": {
    "iso:country":"US",
    "sg:address":"3994 US Hwy 40 Scn",
    "sg:city":"Clayton",
    "sg:classifiers":[
        {
            "category":"Autos & Motor Vehicles",
            "subcategory":"Automobile Sales",
            "type":"Retail Goods"
        }
    ],
    "sg:phone":"+1 317 837 7149",
    "sg:postcode":"46118",
    "sg:province":"IN",
    "sg:tags":[
        "truck"
    ],
    "wof:name":"Plainfield Truck Sales",
    "wof:placetype":"venue"
},
  "geometry": {"coordinates":[-86.458579,39.685286],"type":"Point"}
}