{
  "type": "Feature",
  "properties": {
    "iso:country":"US",
    "sg:address":"17715 Commerce Dr",
    "sg:city":"Westfield",
    "sg:classifiers":[
        {
            "category":"Manufacturing",
            "subcategory":"Building Materials",
            "type":"Manufacturing & Wholesale Goods"
        }
    ],
    "sg:phone":"+1 317 867 3660",
    "sg:postcode":"46074",
    "sg:province":"IN",
    "wof:name":"Wholesale Hardwood Interiors",
    "wof:placetype":"venue"
},
  "geometry": {"coordinates":[-86.149542,40.044469],"type":"Point"}
}