{
  "type": "Feature",
  "properties": {
    "iso:country":"US",
    "sg:address":"3087 N Morton St",
    "sg:city":"Franklin",
    "sg:classifiers":[
        {
            "category":"Recreation",
            "type":"Entertainment"
        }
    ],
    "sg:phone":"+1 317 738 3106",
    "sg:postcode":"46131",
    "sg:province":"IN",
    "sg:tags":[
        "instruction",
        "gymnastic"
    ],
    "wof:name":"Gymnastics With Heart",
    "wof:placetype":"venue"
},
  "geometry": {"coordinates":[-86.075068,39.519371],"type":"Point"}
}