{
  "type": "Feature",
  "properties": {
    "iso:country":"US",
    "sg:address":"115 W Elm St",
    "sg:city":"Gaston",
    "sg:classifiers":[
        {
            "category":"Building & Trades",
            "subcategory":"Electrical",
            "type":"Services"
        }
    ],
    "sg:phone":"+1 765 358 3008",
    "sg:postcode":"47342",
    "sg:province":"IN",
    "sg:tags":[
        "telecommunication",
        "contractor"
    ],
    "wof:name":"Cable Source Inc",
    "wof:placetype":"venue"
},
  "geometry": {"coordinates":[-85.500889,40.313688],"type":"Point"}
}