{
  "type": "Feature",
  "properties": {
    "addr:full":"8250 E Washington St Indianapolis IN 46219",
    "addr:housenumber":"8250",
    "addr:postcode":"46219",
    "addr:street":"E Washington St",
    "iso:country":"US",
    "sg:address":"8250 E Washington St",
    "sg:city":"Indianapolis",
    "sg:classifiers":[
        {
            "category":"Home & Garden",
            "subcategory":"Building Materials",
            "type":"Retail Goods"
        }
    ],
    "sg:phone":"+1 317 898 1266",
    "sg:postcode":"46219",
    "sg:province":"IN",
    "sg:tags":[
        "paint"
    ],
    "wof:name":"MAB Paint Store",
    "wof:placetype":"venue"
},
  "geometry": {"coordinates":[-86.021951,39.773346],"type":"Point"}
}