{
  "type": "Feature",
  "properties": {
    "addr:full":"619 Wall St Jeffersonville IN 47130",
    "addr:housenumber":"619",
    "addr:postcode":"47130",
    "addr:street":"Wall St",
    "iso:country":"US",
    "sg:address":"619 Wall St",
    "sg:city":"Jeffersonville",
    "sg:classifiers":[
        {
            "category":"Social Services",
            "subcategory":"Child Care",
            "type":"Services"
        }
    ],
    "sg:phone":"+1 812 288 8666",
    "sg:postcode":"47130",
    "sg:province":"IN",
    "wof:name":"Child Care Partners Inc",
    "wof:placetype":"venue"
},
  "geometry": {"coordinates":[-85.74194900000001,38.275961],"type":"Point"}
}