{
  "type": "Feature",
  "properties": {
    "iso:country":"US",
    "sg:address":"450 NE E St",
    "sg:city":"Linton",
    "sg:classifiers":[
        {
            "category":"Organizations",
            "subcategory":"Community Association",
            "type":"Services"
        }
    ],
    "sg:phone":"+1 812 847 2799",
    "sg:postcode":"47441",
    "sg:province":"IN",
    "sg:tags":[
        "fraternal"
    ],
    "wof:name":"Knights Of Columbus",
    "wof:placetype":"venue"
},
  "geometry": {"coordinates":[-87.161331,39.038613],"type":"Point"}
}