{
  "type": "Feature",
  "properties": {
    "iso:country":"US",
    "sg:address":"705 Franklin St",
    "sg:city":"Michigan City",
    "sg:classifiers":[
        {
            "category":"Autos & Motor Vehicles",
            "subcategory":"Boat Sales",
            "type":"Retail Goods"
        }
    ],
    "sg:phone":"+1 219 879 7152",
    "sg:postcode":"46360",
    "sg:province":"IN",
    "sg:tags":[
        "dealer",
        "sales"
    ],
    "wof:name":"H & M Yacht Brokers",
    "wof:placetype":"venue"
},
  "geometry": {"coordinates":[-86.900255,41.713952],"type":"Point"}
}