{
  "type": "Feature",
  "properties": {
    "addr:full":"126 S Main St Milford IN 46542",
    "addr:housenumber":"126",
    "addr:postcode":"46542",
    "addr:street":"S Main St",
    "iso:country":"US",
    "sg:address":"126 S Main St",
    "sg:city":"Milford",
    "sg:classifiers":[
        {
            "category":"Government",
            "subcategory":"Post Office",
            "type":"Public Place"
        }
    ],
    "sg:phone":"+1 574 658 4887",
    "sg:postcode":"46542",
    "sg:province":"IN",
    "sg:website":"www.usps.gov",
    "wof:name":"US Post Office",
    "wof:placetype":"venue"
},
  "geometry": {"coordinates":[-85.845932,41.409478],"type":"Point"}
}