{
  "type": "Feature",
  "properties": {
    "iso:country":"US",
    "sg:address":"1124 N Eastern Ave",
    "sg:city":"Connersville",
    "sg:classifiers":[
        {
            "category":"Restaurant",
            "type":"Food & Drink"
        }
    ],
    "sg:phone":"+1 765 827 8776",
    "sg:postcode":"47331",
    "sg:province":"IN",
    "wof:name":"Maggie's Diner",
    "wof:placetype":"venue"
},
  "geometry": {"coordinates":[-85.133263,39.646838],"type":"Point"}
}