{
  "type": "Feature",
  "properties": {
    "addr:full":"1218 S Ironwood Dr Mishawaka IN 46544",
    "addr:housenumber":"1218",
    "addr:postcode":"46544",
    "addr:street":"S Ironwood Dr",
    "iso:country":"US",
    "sg:address":"1218 S Ironwood Dr",
    "sg:city":"Mishawaka",
    "sg:classifiers":[
        {
            "category":"Professional",
            "type":"Services"
        }
    ],
    "sg:phone":"+1 574 288 1678",
    "sg:postcode":"46544",
    "sg:province":"IN",
    "wof:name":"Mishawaka Wireless",
    "wof:placetype":"venue"
},
  "geometry": {"coordinates":[-86.215653,41.647783],"type":"Point"}
}