{
  "type": "Feature",
  "properties": {
    "iso:country":"US",
    "sg:address":"3151 Development Way",
    "sg:city":"Sellersburg",
    "sg:classifiers":[
        {
            "category":"Building & Trades",
            "subcategory":"Construction",
            "type":"Services"
        }
    ],
    "sg:phone":"+1 812 246 6111",
    "sg:postcode":"47172",
    "sg:province":"IN",
    "sg:tags":[
        "general",
        "contractor"
    ],
    "wof:name":"Team Contracting",
    "wof:placetype":"venue"
},
  "geometry": {"coordinates":[-85.740852,38.375611],"type":"Point"}
}