{
  "type": "Feature",
  "properties": {
    "iso:country":"US",
    "sg:address":"4110 Broadway Ave",
    "sg:city":"Evansville",
    "sg:classifiers":[
        {
            "category":"Manufacturing",
            "subcategory":"Motor Vehicles & Parts",
            "type":"Manufacturing & Wholesale Goods"
        }
    ],
    "sg:phone":"+1 812 429 0220",
    "sg:postcode":"47712",
    "sg:province":"IN",
    "sg:tags":[
        "automotive",
        "findings"
    ],
    "wof:name":"C & C Sports",
    "wof:placetype":"venue"
},
  "geometry": {"coordinates":[-87.626985,37.960284],"type":"Point"}
}