{
  "type": "Feature",
  "properties": {
    "iso:country":"US",
    "sg:address":"411 Central Ave",
    "sg:city":"Lake Station",
    "sg:classifiers":[
        {
            "category":"Autos & Motor Vehicles",
            "subcategory":"Automobile Sales",
            "type":"Retail Goods"
        }
    ],
    "sg:phone":"+1 219 962 9819",
    "sg:postcode":"46405",
    "sg:province":"IN",
    "sg:tags":[
        "car",
        "dealer"
    ],
    "wof:name":"Halls Auto Sales",
    "wof:placetype":"venue"
},
  "geometry": {"coordinates":[-87.278227,41.570278],"type":"Point"}
}