{
  "type": "Feature",
  "properties": {
    "iso:country":"US",
    "sg:address":"2459 N Pennsylvania St",
    "sg:city":"Indianapolis",
    "sg:classifiers":[
        {
            "category":"Home & Garden",
            "subcategory":"Mobile Homes",
            "type":"Retail Goods"
        }
    ],
    "sg:phone":"+1 317 923 5550",
    "sg:postcode":"46205",
    "sg:province":"IN",
    "wof:name":"Vintage Homes",
    "wof:placetype":"venue"
},
  "geometry": {"coordinates":[-86.155575,39.801106],"type":"Point"}
}