{
  "type": "Feature",
  "properties": {
    "addr:full":"314 Russell St West Lafayette IN 47906",
    "addr:housenumber":"314",
    "addr:postcode":"47906",
    "addr:street":"Russell St",
    "iso:country":"US",
    "sg:address":"314 Russell St",
    "sg:city":"West Lafayette",
    "sg:classifiers":[
        {
            "category":"Organizations",
            "subcategory":"Community Association",
            "type":"Services"
        }
    ],
    "sg:phone":"+1 765 746 2612",
    "sg:postcode":"47906",
    "sg:province":"IN",
    "sg:tags":[
        "sorority",
        "fraternity"
    ],
    "wof:name":"Alpha Tau Omega Fraternity",
    "wof:placetype":"venue"
},
  "geometry": {"coordinates":[-86.91907999999999,40.428165],"type":"Point"}
}