{
  "type": "Feature",
  "properties": {
    "addr:full":"1415 E State Blvd Fort Wayne IN 46805",
    "addr:housenumber":"1415",
    "addr:postcode":"46805",
    "addr:street":"E State Blvd",
    "iso:country":"US",
    "sg:address":"1415 E State Blvd",
    "sg:city":"Fort Wayne",
    "sg:classifiers":[
        {
            "category":"Food & Beverages",
            "subcategory":"Candy",
            "type":"Retail Goods"
        }
    ],
    "sg:phone":"+1 260 482 1160",
    "sg:postcode":"46805",
    "sg:province":"IN",
    "sg:tags":[
        "confectionery"
    ],
    "wof:name":"Abby Brown's Chocolates",
    "wof:placetype":"venue"
},
  "geometry": {"coordinates":[-85.11961100000001,41.096874],"type":"Point"}
}