{
  "type": "Feature",
  "properties": {
    "iso:country":"US",
    "sg:address":"5430 Victory Dr",
    "sg:city":"Indianapolis",
    "sg:classifiers":[
        {
            "category":"Retail",
            "subcategory":"Repair Shop",
            "type":"Services"
        }
    ],
    "sg:phone":"+1 317 786 9302",
    "sg:postcode":"46203",
    "sg:province":"IN",
    "sg:tags":[
        "scooter",
        "motorcycle",
        "motor"
    ],
    "wof:name":"Victory Drive V-Twins",
    "wof:placetype":"venue"
},
  "geometry": {"coordinates":[-86.071511,39.702228],"type":"Point"}
}