{
  "type": "Feature",
  "properties": {
    "iso:country":"US",
    "sg:address":"1751 N Jefferson St",
    "sg:city":"Huntington",
    "sg:classifiers":[
        {
            "category":"Professional",
            "type":"Services"
        }
    ],
    "sg:phone":"+1 260 356 1490",
    "sg:postcode":"46750",
    "sg:province":"IN",
    "sg:tags":[
        "establishment"
    ],
    "wof:name":"Parcel Parts",
    "wof:placetype":"venue"
},
  "geometry": {"coordinates":[-85.503823,40.891208],"type":"Point"}
}