{
  "type": "Feature",
  "properties": {
    "iso:country":"US",
    "sg:address":"2222 Kensington Blvd",
    "sg:city":"Fort Wayne",
    "sg:classifiers":[
        {
            "category":"Organizations",
            "subcategory":"Non-profit Organization",
            "type":"Services"
        }
    ],
    "sg:phone":"+1 260 482 8222",
    "sg:postcode":"46805",
    "sg:province":"IN",
    "wof:name":"Samaritan's House Inc",
    "wof:placetype":"venue"
},
  "geometry": {"coordinates":[-85.113987,41.095824],"type":"Point"}
}