{
  "type": "Feature",
  "properties": {
    "iso:country":"US",
    "sg:address":"608 Adams St",
    "sg:city":"Gary",
    "sg:classifiers":[
        {
            "category":"Retail",
            "subcategory":"Auto Repair",
            "type":"Services"
        }
    ],
    "sg:phone":"+1 219 886 9501",
    "sg:postcode":"46402",
    "sg:province":"IN",
    "sg:tags":[
        "body",
        "automobile",
        "painting"
    ],
    "wof:name":"Straughter Auto Body Shop",
    "wof:placetype":"venue"
},
  "geometry": {"coordinates":[-87.33968,41.598521],"type":"Point"}
}