{
  "type": "Feature",
  "properties": {
    "iso:country":"US",
    "sg:address":"505 Bundy Ave",
    "sg:city":"New Castle",
    "sg:classifiers":[
        {
            "category":"Real Estate",
            "subcategory":"Developer",
            "type":"Services"
        }
    ],
    "sg:phone":"+1 765 521 6850",
    "sg:postcode":"47362",
    "sg:province":"IN",
    "sg:tags":[
        "cemetery"
    ],
    "wof:name":"South Mound Cemetery",
    "wof:placetype":"venue"
},
  "geometry": {"coordinates":[-85.37330900000001,39.92238],"type":"Point"}
}