{
  "type": "Feature",
  "properties": {
    "iso:country":"US",
    "sg:address":"117 W Elm St",
    "sg:city":"Lebanon",
    "sg:classifiers":[
        {
            "category":"Professional",
            "subcategory":"Engineering",
            "type":"Services"
        }
    ],
    "sg:phone":"+1 765 485 0000",
    "sg:postcode":"46052",
    "sg:province":"IN",
    "sg:tags":[
        "engineer"
    ],
    "wof:name":"Badger Engineering & Assoc Inc",
    "wof:placetype":"venue"
},
  "geometry": {"coordinates":[-86.468492,40.043915],"type":"Point"}
}