{
  "type": "Feature",
  "properties": {
    "addr:full":"610 E Main St Richmond IN 47374",
    "addr:housenumber":"610",
    "addr:postcode":"47374",
    "addr:street":"E Main St",
    "iso:country":"US",
    "sg:address":"610 E Main St",
    "sg:city":"Richmond",
    "sg:classifiers":[
        {
            "category":"Food & Beverages",
            "subcategory":"Bakery",
            "type":"Retail Goods"
        }
    ],
    "sg:phone":"+1 765 962 1705",
    "sg:postcode":"47374",
    "sg:province":"IN",
    "sg:tags":[
        "baker"
    ],
    "wof:name":"Joy Ann Cake Shop",
    "wof:placetype":"venue"
},
  "geometry": {"coordinates":[-84.893896,39.82899],"type":"Point"}
}