{
  "type": "Feature",
  "properties": {
    "addr:full":"3859 E Blocher Rd Scottsburg IN 47170",
    "addr:housenumber":"3859",
    "addr:postcode":"47170",
    "addr:street":"E Blocher Rd",
    "iso:country":"US",
    "sg:address":"3859 E Blocher Rd",
    "sg:city":"Scottsburg",
    "sg:classifiers":[
        {
            "category":"Building & Trades",
            "subcategory":"Cleaning & Sanitation",
            "type":"Services"
        }
    ],
    "sg:phone":"+1 812 752 3249",
    "sg:postcode":"47170",
    "sg:province":"IN",
    "sg:tags":[
        "janitor"
    ],
    "wof:name":"Glen's Cleaning Svc Inc",
    "wof:placetype":"venue"
},
  "geometry": {"coordinates":[-85.707082,38.708119],"type":"Point"}
}