{
  "type": "Feature",
  "properties": {
    "addr:full":"929 W 2nd St Madison IN 47250",
    "addr:housenumber":"929",
    "addr:postcode":"47250",
    "addr:street":"W 2Nd St",
    "iso:country":"US",
    "sg:address":"929 W 2nd St",
    "sg:city":"Madison",
    "sg:classifiers":[
        {
            "category":"Professional",
            "type":"Services"
        }
    ],
    "sg:phone":"+1 812 273 4168",
    "sg:postcode":"47250",
    "sg:province":"IN",
    "sg:tags":[
        "establishment"
    ],
    "wof:name":"Sports Section",
    "wof:placetype":"venue"
},
  "geometry": {"coordinates":[-85.39112799999999,38.737103],"type":"Point"}
}