{
  "type": "Feature",
  "properties": {
    "iso:country":"US",
    "sg:address":"5632 E Washington St",
    "sg:city":"Indianapolis",
    "sg:classifiers":[
        {
            "category":"Shopping",
            "subcategory":"Musical Instruments",
            "type":"Retail Goods"
        }
    ],
    "sg:phone":"+1 317 353 6565",
    "sg:postcode":"46219",
    "sg:province":"IN",
    "wof:name":"Sticks & Tones",
    "wof:placetype":"venue"
},
  "geometry": {"coordinates":[-86.071681,39.770801],"type":"Point"}
}