{
  "type": "Feature",
  "properties": {
    "iso:country":"US",
    "sg:address":"4530 N County Line Rd E",
    "sg:city":"Huntertown",
    "sg:classifiers":[
        {
            "category":"Professional",
            "subcategory":"Business Services",
            "type":"Services"
        }
    ],
    "sg:phone":"+1 260 627 5684",
    "sg:postcode":"46748",
    "sg:province":"IN",
    "sg:tags":[
        "broker"
    ],
    "wof:name":"Creative Capital Svc",
    "wof:placetype":"venue"
},
  "geometry": {"coordinates":[-85.093105,41.265417],"type":"Point"}
}