{
  "type": "Feature",
  "properties": {
    "iso:country":"US",
    "sg:address":"2801 E Boonville New Harmony Rd",
    "sg:city":"Evansville",
    "sg:classifiers":[
        {
            "category":"Restaurant",
            "type":"Food & Drink"
        }
    ],
    "sg:phone":"+1 812 867 9131",
    "sg:postcode":"47725",
    "sg:province":"IN",
    "sg:tags":[
        "pizza"
    ],
    "wof:name":"Pizza Depot",
    "wof:placetype":"venue"
},
  "geometry": {"coordinates":[-87.513043,38.085803],"type":"Point"}
}