{
  "type": "Feature",
  "properties": {
    "iso:country":"US",
    "sg:address":"3151 Old State Rd 37",
    "sg:city":"Greenwood",
    "sg:classifiers":[
        {
            "category":"Organizations",
            "subcategory":"Religious Organization",
            "type":"Services"
        }
    ],
    "sg:phone":"+1 317 422 3755",
    "sg:postcode":"46143",
    "sg:province":"IN",
    "wof:name":"Spirit of Truth Inc",
    "wof:placetype":"venue"
},
  "geometry": {"coordinates":[-86.234837,39.586091],"type":"Point"}
}