{
  "type": "Feature",
  "properties": {
    "iso:country":"US",
    "sg:address":"320 Eagle Crest Dr",
    "sg:city":"Evansville",
    "sg:classifiers":[
        {
            "category":"Insurance",
            "subcategory":"Insurance Agent",
            "type":"Services"
        }
    ],
    "sg:phone":"+1 812 474 7700",
    "sg:postcode":"47715",
    "sg:province":"IN",
    "sg:website":"www.statefarm.com",
    "wof:name":"State Farm Insurance",
    "wof:placetype":"venue"
},
  "geometry": {"coordinates":[-87.45689400000001,37.975067],"type":"Point"}
}