{
  "type": "Feature",
  "properties": {
    "iso:country":"US",
    "sg:address":"4862 E Old Road 30",
    "sg:city":"Pierceton",
    "sg:classifiers":[
        {
            "category":"Education",
            "subcategory":"Special Training",
            "type":"Public Place"
        }
    ],
    "sg:phone":"+1 574 269 6215",
    "sg:postcode":"46562",
    "sg:province":"IN",
    "wof:name":"Lane Lightfoot Piano Lessons",
    "wof:placetype":"venue"
},
  "geometry": {"coordinates":[-85.752179,41.235794],"type":"Point"}
}