{
  "type": "Feature",
  "properties": {
    "iso:country":"US",
    "sg:address":"1230 Willow St",
    "sg:city":"Vincennes",
    "sg:classifiers":[
        {
            "category":"Retail",
            "subcategory":"Auto Repair",
            "type":"Services"
        }
    ],
    "sg:phone":"+1 812 882 0806",
    "sg:postcode":"47591",
    "sg:province":"IN",
    "sg:tags":[
        "muffler",
        "exhaust",
        "system"
    ],
    "wof:name":"Mr Muffler",
    "wof:placetype":"venue"
},
  "geometry": {"coordinates":[-87.533618,38.665441],"type":"Point"}
}