{
  "type": "Feature",
  "properties": {
    "iso:country":"US",
    "sg:address":"10353 Lakeshore Dr E",
    "sg:city":"Carmel",
    "sg:classifiers":[
        {
            "category":"Autos & Motor Vehicles",
            "subcategory":"Fuel & Gas Station",
            "type":"Retail Goods"
        }
    ],
    "sg:phone":"+1 317 575 6486",
    "sg:postcode":"46033",
    "sg:province":"IN",
    "sg:tags":[
        "a",
        "convenience",
        "station",
        "gasoline",
        "operates"
    ],
    "wof:name":"Turtle Stop",
    "wof:placetype":"venue"
},
  "geometry": {"coordinates":[-86.104132,39.937722],"type":"Point"}
}