{
  "type": "Feature",
  "properties": {
    "iso:country":"US",
    "sg:address":"3001 Mounds Rd",
    "sg:city":"Anderson",
    "sg:classifiers":[
        {
            "category":"Organizations",
            "subcategory":"Religious Organization",
            "type":"Services"
        }
    ],
    "sg:phone":"+1 765 642 5416",
    "sg:postcode":"46016",
    "sg:province":"IN",
    "sg:tags":[
        "church"
    ],
    "wof:name":"Mounds Baptist Church",
    "wof:placetype":"venue"
},
  "geometry": {"coordinates":[-85.63869,40.089515],"type":"Point"}
}