{
  "type": "Feature",
  "properties": {
    "addr:full":"600 E 96th St Indianapolis IN 46240",
    "addr:housenumber":"600",
    "addr:postcode":"46240",
    "addr:street":"E 96Th St",
    "iso:country":"US",
    "sg:address":"600 E 96th St",
    "sg:city":"Indianapolis",
    "sg:classifiers":[
        {
            "category":"Professional",
            "subcategory":"Lawyer & Legal Services",
            "type":"Services"
        }
    ],
    "sg:phone":"+1 317 574 3728",
    "sg:postcode":"46240",
    "sg:province":"IN",
    "wof:name":"Carlino James C Atty",
    "wof:placetype":"venue"
},
  "geometry": {"coordinates":[-86.148003,39.9272],"type":"Point"}
}