{
  "type": "Feature",
  "properties": {
    "iso:country":"US",
    "sg:address":"938 W 81st Ave",
    "sg:city":"Merrillville",
    "sg:classifiers":[
        {
            "category":"Restaurant",
            "type":"Food & Drink"
        }
    ],
    "sg:phone":"+1 219 736 8869",
    "sg:postcode":"46410",
    "sg:province":"IN",
    "wof:name":"Oriental Buffet",
    "wof:placetype":"venue"
},
  "geometry": {"coordinates":[-87.344167,41.471169],"type":"Point"}
}