{
  "type": "Feature",
  "properties": {
    "iso:country":"US",
    "sg:address":"509 W Temperance St",
    "sg:city":"Ellettsville",
    "sg:classifiers":[
        {
            "category":"Retail",
            "subcategory":"Auto Repair",
            "type":"Services"
        }
    ],
    "sg:phone":"+1 812 876 4200",
    "sg:postcode":"47429",
    "sg:province":"IN",
    "sg:tags":[
        "transmission"
    ],
    "wof:name":"Stop N Go Muffler Ctr Inc",
    "wof:placetype":"venue"
},
  "geometry": {"coordinates":[-86.625615,39.23426],"type":"Point"}
}