{
  "type": "Feature",
  "properties": {
    "iso:country":"US",
    "sg:address":"13971 Stone Key Way",
    "sg:city":"Fortville",
    "sg:classifiers":[
        {
            "category":"Personal",
            "subcategory":"Beauty Salon",
            "type":"Services"
        }
    ],
    "sg:phone":"+1 317 826 8051",
    "sg:postcode":"46040",
    "sg:province":"IN",
    "wof:name":"Sport Clips",
    "wof:placetype":"venue"
},
  "geometry": {"coordinates":[-85.916422,39.954692],"type":"Point"}
}