{
  "type": "Feature",
  "properties": {
    "iso:country":"US",
    "sg:address":"4020 W 61st Ave",
    "sg:city":"Hobart",
    "sg:classifiers":[
        {
            "category":"Real Estate",
            "subcategory":"Real Estate Operator",
            "type":"Services"
        }
    ],
    "sg:phone":"+1 219 947 1317",
    "sg:postcode":"46342",
    "sg:province":"IN",
    "sg:tags":[
        "apartment"
    ],
    "wof:name":"Affordable Home Inspection",
    "wof:placetype":"venue"
},
  "geometry": {"coordinates":[-87.30719999999999,41.507328],"type":"Point"}
}