{
  "type": "Feature",
  "properties": {
    "iso:country":"US",
    "sg:address":"11345 Arborview Dr",
    "sg:city":"Indianapolis",
    "sg:classifiers":[
        {
            "category":"Real Estate",
            "subcategory":"Real Estate Operator",
            "type":"Services"
        }
    ],
    "sg:phone":"+1 317 826 9000",
    "sg:postcode":"46236",
    "sg:province":"IN",
    "sg:tags":[
        "apartment"
    ],
    "wof:name":"Grande Reserve At Geist",
    "wof:placetype":"venue"
},
  "geometry": {"coordinates":[-85.966107,39.901378],"type":"Point"}
}