{
  "type": "Feature",
  "properties": {
    "addr:full":"20 3rd Ave NW Carmel IN 46032",
    "addr:housenumber":"20",
    "addr:postcode":"46032",
    "addr:street":"3Rd Ave Nw",
    "iso:country":"US",
    "sg:address":"20 3rd Ave NW",
    "sg:city":"Carmel",
    "sg:classifiers":[
        {
            "category":"Wholesale",
            "subcategory":"Computers",
            "type":"Manufacturing & Wholesale Goods"
        }
    ],
    "sg:phone":"+1 317 571 1840",
    "sg:postcode":"46032",
    "sg:province":"IN",
    "wof:name":"Net Results",
    "wof:placetype":"venue"
},
  "geometry": {"coordinates":[-86.13109900000001,39.978501],"type":"Point"}
}