{
  "type": "Feature",
  "properties": {
    "iso:country":"US",
    "sg:address":"520 E Main St",
    "sg:city":"Greenfield",
    "sg:classifiers":[
        {
            "category":"Retail",
            "subcategory":"Auto Repair",
            "type":"Services"
        }
    ],
    "sg:phone":"+1 317 462 8804",
    "sg:postcode":"46140",
    "sg:province":"IN",
    "sg:tags":[
        "repairing",
        "automobile"
    ],
    "wof:name":"Automotive Maintenance Svc",
    "wof:placetype":"venue"
},
  "geometry": {"coordinates":[-85.762887,39.785598],"type":"Point"}
}