{
  "type": "Feature",
  "properties": {
    "iso:country":"US",
    "sg:address":"4108 Madison Ave",
    "sg:city":"Indianapolis",
    "sg:classifiers":[
        {
            "category":"Shopping",
            "subcategory":"Musical Instruments",
            "type":"Retail Goods"
        }
    ],
    "sg:phone":"+1 317 780 0534",
    "sg:postcode":"46227",
    "sg:province":"IN",
    "wof:name":"B J's Guitar Island Inc",
    "wof:placetype":"venue"
},
  "geometry": {"coordinates":[-86.141392,39.70582],"type":"Point"}
}