{
  "type": "Feature",
  "properties": {
    "iso:country":"US",
    "sg:address":"1817 W Michigan St",
    "sg:city":"Evansville",
    "sg:classifiers":[
        {
            "category":"Wholesale",
            "subcategory":"Hardware",
            "type":"Manufacturing & Wholesale Goods"
        }
    ],
    "sg:phone":"+1 812 425 3115",
    "sg:postcode":"47712",
    "sg:province":"IN",
    "sg:tags":[
        "plumbing",
        "fixture",
        "supply"
    ],
    "wof:name":"Evansville Plumbers Supply Co",
    "wof:placetype":"venue"
},
  "geometry": {"coordinates":[-87.591983,37.981512],"type":"Point"}
}