{
  "type": "Feature",
  "properties": {
    "iso:country":"US",
    "sg:address":"2291 Random Rd",
    "sg:city":"Columbus",
    "sg:classifiers":[
        {
            "category":"Building & Trades",
            "subcategory":"Landscaping Services",
            "type":"Services"
        }
    ],
    "sg:phone":"+1 812 526 0015",
    "sg:postcode":"47201",
    "sg:province":"IN",
    "wof:name":"Hundleys Mowing & Landscp",
    "wof:placetype":"venue"
},
  "geometry": {"coordinates":[-85.950637,39.284518],"type":"Point"}
}