{
  "type": "Feature",
  "properties": {
    "addr:full":"1419 Fabricon Blvd Jeffersonville IN 47130",
    "addr:housenumber":"1419",
    "addr:postcode":"47130",
    "addr:street":"Fabricon Blvd",
    "iso:country":"US",
    "sg:address":"1419 Fabricon Blvd",
    "sg:city":"Jeffersonville",
    "sg:classifiers":[
        {
            "category":"Professional",
            "subcategory":"Art Services",
            "type":"Services"
        }
    ],
    "sg:phone":"+1 812 283 0455",
    "sg:postcode":"47130",
    "sg:province":"IN",
    "sg:tags":[
        "graphic",
        "designer"
    ],
    "wof:name":"Stewart Graphics",
    "wof:placetype":"venue"
},
  "geometry": {"coordinates":[-85.74959,38.3159],"type":"Point"}
}