{
  "type": "Feature",
  "properties": {
    "iso:country":"US",
    "sg:address":"1813 W University Ave",
    "sg:city":"Muncie",
    "sg:classifiers":[
        {
            "category":"Restaurant",
            "type":"Food & Drink"
        }
    ],
    "sg:phone":"+1 765 286 0473",
    "sg:postcode":"47303",
    "sg:province":"IN",
    "wof:name":"Romo's Pizza",
    "wof:placetype":"venue"
},
  "geometry": {"coordinates":[-85.40768300000001,40.197581],"type":"Point"}
}