{
  "type": "Feature",
  "properties": {
    "addr:full":"7806 E 37th Ave Hobart IN 46342",
    "addr:housenumber":"7806",
    "addr:postcode":"46342",
    "addr:street":"E 37Th Ave",
    "iso:country":"US",
    "sg:address":"7806 E 37th Ave",
    "sg:city":"Hobart",
    "sg:classifiers":[
        {
            "category":"Shopping",
            "subcategory":"Clothing, Apparel, & Fashions",
            "type":"Retail Goods"
        }
    ],
    "sg:phone":"+1 219 962 6916",
    "sg:postcode":"46342",
    "sg:province":"IN",
    "wof:name":"Fashion Bug",
    "wof:placetype":"venue"
},
  "geometry": {"coordinates":[-87.244134,41.550788],"type":"Point"}
}