{
  "type": "Feature",
  "properties": {
    "iso:country":"US",
    "sg:address":"912 N Parkway Dr",
    "sg:city":"Anderson",
    "sg:classifiers":[
        {
            "category":"Local Transit",
            "type":"Transportation"
        }
    ],
    "sg:phone":"+1 765 649 2739",
    "sg:postcode":"46011",
    "sg:province":"IN",
    "sg:tags":[
        "handicapped"
    ],
    "wof:name":"Developmental Svc Alternatives",
    "wof:placetype":"venue"
},
  "geometry": {"coordinates":[-85.687863,40.079125],"type":"Point"}
}