{
  "type": "Feature",
  "properties": {
    "iso:country":"US",
    "sg:address":"1210 W 3rd St",
    "sg:city":"Connersville",
    "sg:classifiers":[
        {
            "category":"Building & Trades",
            "subcategory":"Plumbing",
            "type":"Services"
        }
    ],
    "sg:phone":"+1 765 825 7984",
    "sg:postcode":"47331",
    "sg:province":"IN",
    "sg:tags":[
        "contractor"
    ],
    "wof:name":"Templetons Sewer Drain Clg Plu",
    "wof:placetype":"venue"
},
  "geometry": {"coordinates":[-85.164177,39.638699],"type":"Point"}
}