{
  "type": "Feature",
  "properties": {
    "iso:country":"US",
    "sg:address":"402 S Washington St",
    "sg:city":"Marion",
    "sg:classifiers":[
        {
            "category":"Health Services",
            "subcategory":"Optometrist",
            "type":"Services"
        }
    ],
    "sg:phone":"+1 765 662 2595",
    "sg:postcode":"46953",
    "sg:province":"IN",
    "wof:name":"Robbins & Zirkle",
    "wof:placetype":"venue"
},
  "geometry": {"coordinates":[-85.659857,40.556946],"type":"Point"}
}