{
  "type": "Feature",
  "properties": {
    "iso:country":"US",
    "sg:address":"612 E 14th St",
    "sg:city":"Bloomington",
    "sg:classifiers":[
        {
            "category":"Personal",
            "type":"Services"
        }
    ],
    "sg:phone":"+1 812 961 0100",
    "sg:postcode":"47408",
    "sg:province":"IN",
    "sg:tags":[
        "therapist",
        "massage"
    ],
    "wof:name":"Treva Fortner Certified Thera",
    "wof:placetype":"venue"
},
  "geometry": {"coordinates":[-86.526014,39.17612],"type":"Point"}
}