{
  "type": "Feature",
  "properties": {
    "iso:country":"US",
    "sg:address":"2123 Taylor St",
    "sg:city":"Fort Wayne",
    "sg:classifiers":[
        {
            "category":"Bars & Pubs",
            "type":"Food & Drink"
        }
    ],
    "sg:phone":"+1 260 434 1787",
    "sg:postcode":"46802",
    "sg:province":"IN",
    "wof:name":"Library Tavern",
    "wof:placetype":"venue"
},
  "geometry": {"coordinates":[-85.168379,41.067631],"type":"Point"}
}