{
  "type": "Feature",
  "properties": {
    "iso:country":"US",
    "sg:address":"6004 Highview Dr",
    "sg:city":"Fort Wayne",
    "sg:classifiers":[
        {
            "category":"Wholesale",
            "subcategory":"Machinery & Supplies",
            "type":"Manufacturing & Wholesale Goods"
        }
    ],
    "sg:phone":"+1 260 416 0078",
    "sg:postcode":"46818",
    "sg:province":"IN",
    "sg:tags":[
        "equipment",
        "industrial"
    ],
    "wof:name":"Kellermeyer Company",
    "wof:placetype":"venue"
},
  "geometry": {"coordinates":[-85.18965,41.133908],"type":"Point"}
}