{
  "type": "Feature",
  "properties": {
    "iso:country":"US",
    "sg:address":"4 N Main St",
    "sg:city":"Brooklyn",
    "sg:classifiers":[
        {
            "category":"Government",
            "subcategory":"Office",
            "type":"Public Place"
        }
    ],
    "sg:phone":"+1 317 831 3343",
    "sg:postcode":"46111",
    "sg:province":"IN",
    "sg:tags":[
        "city"
    ],
    "wof:name":"Brooklyn Town Clerk/Treasurer",
    "wof:placetype":"venue"
},
  "geometry": {"coordinates":[-86.370554,39.539368],"type":"Point"}
}