{
  "type": "Feature",
  "properties": {
    "iso:country":"US",
    "sg:address":"8705 Sandpiper Ct",
    "sg:city":"Fort Wayne",
    "sg:classifiers":[
        {
            "category":"Professional",
            "subcategory":"Computer Services",
            "type":"Services"
        }
    ],
    "sg:phone":"+1 260 436 6822",
    "sg:postcode":"46804",
    "sg:province":"IN",
    "sg:tags":[
        "internet"
    ],
    "wof:name":"Lantastics GIE",
    "wof:placetype":"venue"
},
  "geometry": {"coordinates":[-85.255931,41.066478],"type":"Point"}
}