{
  "type": "Feature",
  "properties": {
    "iso:country":"US",
    "sg:address":"8244 Greenwood Ave",
    "sg:city":"Munster",
    "sg:classifiers":[
        {
            "category":"Retail",
            "subcategory":"Repair Shop",
            "type":"Services"
        }
    ],
    "sg:phone":"+1 219 838 4942",
    "sg:postcode":"46321",
    "sg:province":"IN",
    "sg:tags":[
        "plumbing",
        "drain",
        "cleaning",
        "sewer"
    ],
    "wof:name":"R A Oros Inc",
    "wof:placetype":"venue"
},
  "geometry": {"coordinates":[-87.495444,41.562956],"type":"Point"}
}