{
  "type": "Feature",
  "properties": {
    "iso:country":"US",
    "sg:address":"8907 Crestfield Ct",
    "sg:city":"Fort Wayne",
    "sg:classifiers":[
        {
            "category":"Professional",
            "subcategory":"Business Services",
            "type":"Services"
        }
    ],
    "sg:phone":"+1 260 484 7384",
    "sg:postcode":"46835",
    "sg:province":"IN",
    "sg:tags":[
        "interior",
        "consultant",
        "design",
        "decorator"
    ],
    "wof:name":"Angel Interiors",
    "wof:placetype":"venue"
},
  "geometry": {"coordinates":[-85.028496,41.142366],"type":"Point"}
}