{
  "type": "Feature",
  "properties": {
    "iso:country":"US",
    "sg:address":"137 S Michigan St",
    "sg:city":"South Bend",
    "sg:classifiers":[
        {
            "category":"Real Estate",
            "subcategory":"Real Estate Agent",
            "type":"Services"
        }
    ],
    "sg:phone":"+1 574 233 4401",
    "sg:postcode":"46601",
    "sg:province":"IN",
    "wof:name":"Destiny Real Estate Group",
    "wof:placetype":"venue"
},
  "geometry": {"coordinates":[-86.250422,41.675524],"type":"Point"}
}