{
  "type": "Feature",
  "properties": {
    "iso:country":"US",
    "sg:address":"352 W North St",
    "sg:city":"Kendallville",
    "sg:classifiers":[
        {
            "category":"Home & Garden",
            "subcategory":"Hardware",
            "type":"Retail Goods"
        }
    ],
    "sg:phone":"+1 260 347 3552",
    "sg:postcode":"46755",
    "sg:province":"IN",
    "wof:name":"True Value Hardware",
    "wof:placetype":"venue"
},
  "geometry": {"coordinates":[-85.271765,41.452426],"type":"Point"}
}