{
  "type": "Feature",
  "properties": {
    "addr:full":"13801 W Main St Daleville IN 47334",
    "addr:housenumber":"13801",
    "addr:postcode":"47334",
    "addr:street":"W Main St",
    "iso:country":"US",
    "sg:address":"13801 W Main St",
    "sg:city":"Daleville",
    "sg:classifiers":[
        {
            "category":"Organizations",
            "subcategory":"Religious Organization",
            "type":"Services"
        }
    ],
    "sg:phone":"+1 765 378 3634",
    "sg:postcode":"47334",
    "sg:province":"IN",
    "sg:tags":[
        "church"
    ],
    "wof:name":"Trinity Community Church",
    "wof:placetype":"venue"
},
  "geometry": {"coordinates":[-85.54788600000001,40.131517],"type":"Point"}
}