{
  "type": "Feature",
  "properties": {
    "iso:country":"US",
    "sg:address":"101 W Miami Ave",
    "sg:city":"Logansport",
    "sg:classifiers":[
        {
            "category":"Building & Trades",
            "subcategory":"Construction",
            "type":"Services"
        }
    ],
    "sg:phone":"+1 574 753 0237",
    "sg:postcode":"46947",
    "sg:province":"IN",
    "sg:tags":[
        "downspouts",
        "gutter"
    ],
    "wof:name":"Fox Continuous Gutter",
    "wof:placetype":"venue"
},
  "geometry": {"coordinates":[-86.370541,40.757309],"type":"Point"}
}