{
  "type": "Feature",
  "properties": {
    "iso:country":"US",
    "sg:address":"8995 S Co Rd 375 W",
    "sg:city":"Reelsville",
    "sg:classifiers":[
        {
            "category":"Shopping",
            "type":"Retail Goods"
        }
    ],
    "sg:phone":"+1 765 672 4922",
    "sg:postcode":"46171",
    "sg:province":"IN",
    "sg:tags":[
        "candle"
    ],
    "wof:name":"Leatherwood Hill Candles",
    "wof:placetype":"venue"
},
  "geometry": {"coordinates":[-86.916743,39.532263],"type":"Point"}
}