{
  "type": "Feature",
  "properties": {
    "iso:country":"US",
    "sg:address":"113 E Washington St",
    "sg:city":"Monroe",
    "sg:classifiers":[
        {
            "category":"Government",
            "subcategory":"Post Office",
            "type":"Public Place"
        }
    ],
    "sg:phone":"+1 260 692 6361",
    "sg:postcode":"46772",
    "sg:province":"IN",
    "wof:name":"US Post Office",
    "wof:placetype":"venue"
},
  "geometry": {"coordinates":[-84.938358,40.745099],"type":"Point"}
}