{
  "type": "Feature",
  "properties": {
    "addr:full":"7905 State Rd 38 E Lafayette IN 47905",
    "addr:housenumber":"7905;38 e",
    "addr:postcode":"47905",
    "addr:street":"State Rd",
    "iso:country":"US",
    "sg:address":"7905 State Rd 38 E",
    "sg:city":"Lafayette",
    "sg:classifiers":[
        {
            "category":"Building & Trades",
            "subcategory":"Plumbing",
            "type":"Services"
        }
    ],
    "sg:phone":"+1 765 296 4201",
    "sg:postcode":"47905",
    "sg:province":"IN",
    "sg:tags":[
        "mechanical",
        "contractor"
    ],
    "wof:name":"Mitchell Mechanical",
    "wof:placetype":"venue"
},
  "geometry": {"coordinates":[-86.75969499999999,40.374196],"type":"Point"}
}