{
  "type": "Feature",
  "properties": {
    "iso:country":"US",
    "sg:address":"2401 W University Ave",
    "sg:city":"Muncie",
    "sg:classifiers":[
        {
            "category":"Shopping",
            "type":"Retail Goods"
        }
    ],
    "sg:phone":"+1 765 751 5302",
    "sg:postcode":"47303",
    "sg:province":"IN",
    "sg:tags":[
        "miscellaneous",
        "store"
    ],
    "wof:name":"Cancer Center Boutique",
    "wof:placetype":"venue"
},
  "geometry": {"coordinates":[-85.413681,40.197533],"type":"Point"}
}