{
  "type": "Feature",
  "properties": {
    "iso:country":"US",
    "sg:address":"2113 Maxwell Ave",
    "sg:city":"Evansville",
    "sg:classifiers":[
        {
            "category":"Health Services",
            "subcategory":"Clinic",
            "type":"Services"
        }
    ],
    "sg:phone":"+1 812 469 7900",
    "sg:postcode":"47711",
    "sg:province":"IN",
    "sg:tags":[
        "banks",
        "blood",
        "center"
    ],
    "wof:name":"Evansville Community Blood Ctr",
    "wof:placetype":"venue"
},
  "geometry": {"coordinates":[-87.53556399999999,37.993565],"type":"Point"}
}