{
  "type": "Feature",
  "properties": {
    "iso:country":"US",
    "sg:address":"213 W Main St",
    "sg:city":"Camden",
    "sg:classifiers":[
        {
            "category":"Food & Beverages",
            "subcategory":"Groceries & Convenience Stores",
            "type":"Retail Goods"
        }
    ],
    "sg:phone":"+1 574 686 2123",
    "sg:postcode":"46917",
    "sg:province":"IN",
    "sg:tags":[
        "grocer"
    ],
    "wof:name":"Camden Grocery & Meats",
    "wof:placetype":"venue"
},
  "geometry": {"coordinates":[-86.540803,40.608643],"type":"Point"}
}