{
  "type": "Feature",
  "properties": {
    "iso:country":"US",
    "sg:address":"6390 Turner Dr",
    "sg:city":"Indianapolis",
    "sg:classifiers":[
        {
            "category":"Professional",
            "type":"Services"
        }
    ],
    "sg:phone":"+1 317 243 7157",
    "sg:postcode":"46241",
    "sg:province":"IN",
    "sg:tags":[
        "establishment"
    ],
    "wof:name":"W R Kelso Co Inc",
    "wof:placetype":"venue"
},
  "geometry": {"coordinates":[-86.271879,39.727576],"type":"Point"}
}