{
  "type": "Feature",
  "properties": {
    "iso:country":"US",
    "sg:address":"4075 Bridgeport Rd",
    "sg:city":"Indianapolis",
    "sg:classifiers":[
        {
            "category":"Building & Trades",
            "subcategory":"Construction",
            "type":"Services"
        }
    ],
    "sg:phone":"+1 317 246 5556",
    "sg:postcode":"46231",
    "sg:province":"IN",
    "sg:tags":[
        "general",
        "contractor"
    ],
    "wof:name":"Walsh Construction Co",
    "wof:placetype":"venue"
},
  "geometry": {"coordinates":[-86.32405,39.703745],"type":"Point"}
}