{
  "type": "Feature",
  "properties": {
    "iso:country":"US",
    "sg:address":"590 Missouri Ave",
    "sg:city":"Jeffersonville",
    "sg:classifiers":[
        {
            "category":"Shopping",
            "subcategory":"Computers & Home Electronics",
            "type":"Retail Goods"
        }
    ],
    "sg:phone":"+1 812 285 8944",
    "sg:postcode":"47130",
    "sg:province":"IN",
    "sg:tags":[
        "software"
    ],
    "wof:name":"Meditech Inc",
    "wof:placetype":"venue"
},
  "geometry": {"coordinates":[-85.750305,38.271828],"type":"Point"}
}