{
  "type": "Feature",
  "properties": {
    "iso:country":"US",
    "sg:address":"414 N Clark St",
    "sg:city":"Auburn",
    "sg:classifiers":[
        {
            "category":"Professional",
            "subcategory":"Art Services",
            "type":"Services"
        }
    ],
    "sg:phone":"+1 260 925 4921",
    "sg:postcode":"46706",
    "sg:province":"IN",
    "sg:tags":[
        "commercial",
        "design"
    ],
    "wof:name":"Maureen Albright Graphic Desig",
    "wof:placetype":"venue"
},
  "geometry": {"coordinates":[-85.04141799999999,41.371102],"type":"Point"}
}