{
  "type": "Feature",
  "properties": {
    "iso:country":"US",
    "sg:address":"3905 W 96th St",
    "sg:city":"Indianapolis",
    "sg:classifiers":[
        {
            "category":"Professional",
            "subcategory":"Employment Agencies",
            "type":"Services"
        }
    ],
    "sg:phone":"+1 317 471 1300",
    "sg:postcode":"46268",
    "sg:province":"IN",
    "sg:tags":[
        "supply",
        "help",
        "contractor"
    ],
    "wof:name":"Forge Industrial Staffing",
    "wof:placetype":"venue"
},
  "geometry": {"coordinates":[-86.22869,39.926266],"type":"Point"}
}