{
  "type": "Feature",
  "properties": {
    "iso:country":"US",
    "sg:address":"5001 de Ann Dr",
    "sg:city":"Bloomington",
    "sg:classifiers":[
        {
            "category":"Professional",
            "subcategory":"Research",
            "type":"Services"
        }
    ],
    "sg:phone":"+1 812 876 3300",
    "sg:postcode":"47404",
    "sg:province":"IN",
    "sg:tags":[
        "environmental",
        "ecological"
    ],
    "wof:name":"KERR Environmental Svc Inc",
    "wof:placetype":"venue"
},
  "geometry": {"coordinates":[-86.59338099999999,39.21036],"type":"Point"}
}