{
  "type": "Feature",
  "properties": {
    "iso:country":"US",
    "sg:address":"2114 Scott St",
    "sg:city":"Lafayette",
    "sg:classifiers":[
        {
            "category":"Health Services",
            "subcategory":"Doctor",
            "type":"Services"
        }
    ],
    "sg:phone":"+1 765 448 1539",
    "sg:postcode":"47904",
    "sg:province":"IN",
    "sg:tags":[
        "dentist"
    ],
    "wof:name":"Stephen Cook DDS",
    "wof:placetype":"venue"
},
  "geometry": {"coordinates":[-86.87029,40.416773],"type":"Point"}
}