{
  "type": "Feature",
  "properties": {
    "iso:country":"US",
    "sg:address":"505 N Main St",
    "sg:city":"Farmland",
    "sg:classifiers":[
        {
            "category":"Autos & Motor Vehicles",
            "subcategory":"Fuel & Gas Station",
            "type":"Retail Goods"
        }
    ],
    "sg:phone":"+1 765 468 7601",
    "sg:postcode":"47340",
    "sg:province":"IN",
    "sg:tags":[
        "oil"
    ],
    "wof:name":"Newton Shell Svc Station",
    "wof:placetype":"venue"
},
  "geometry": {"coordinates":[-85.127823,40.191916],"type":"Point"}
}