{
  "type": "Feature",
  "properties": {
    "addr:full":"855 S Emerson Ave Indianapolis IN 46203",
    "addr:housenumber":"855",
    "addr:postcode":"46203",
    "addr:street":"S Emerson Ave",
    "iso:country":"US",
    "sg:address":"855 S Emerson Ave",
    "sg:city":"Indianapolis",
    "sg:classifiers":[
        {
            "category":"Train Station",
            "subcategory":"Rail",
            "type":"Transportation"
        }
    ],
    "sg:phone":"+1 317 267 4440",
    "sg:postcode":"46203",
    "sg:province":"IN",
    "sg:tags":[
        "railroad"
    ],
    "sg:website":"http://www.csxt.com",
    "wof:name":"Csx",
    "wof:placetype":"venue"
},
  "geometry": {"coordinates":[-86.08252299999999,39.69668],"type":"Point"}
}