{
  "type": "Feature",
  "properties": {
    "addr:full":"635 Westfield Rd Noblesville IN 46060",
    "addr:housenumber":"635",
    "addr:postcode":"46060",
    "addr:street":"Westfield Rd",
    "iso:country":"US",
    "sg:address":"635 Westfield Rd",
    "sg:city":"Noblesville",
    "sg:classifiers":[
        {
            "category":"Wholesale",
            "subcategory":"Groceries",
            "type":"Manufacturing & Wholesale Goods"
        }
    ],
    "sg:phone":"+1 317 776 4775",
    "sg:postcode":"46060",
    "sg:province":"IN",
    "sg:tags":[
        "grocer"
    ],
    "wof:name":"Butterfield Foods",
    "wof:placetype":"venue"
},
  "geometry": {"coordinates":[-86.027603,40.046902],"type":"Point"}
}