{
  "type": "Feature",
  "properties": {
    "addr:full":"5162 E 11th St Indianapolis IN 46219",
    "addr:housenumber":"5162",
    "addr:postcode":"46219",
    "addr:street":"E 11Th St",
    "iso:country":"US",
    "sg:address":"5162 E 11th St",
    "sg:city":"Indianapolis",
    "sg:classifiers":[
        {
            "category":"Health Services",
            "subcategory":"Doctor",
            "type":"Services"
        }
    ],
    "sg:phone":"+1 317 882 4455",
    "sg:postcode":"46219",
    "sg:province":"IN",
    "sg:tags":[
        "physician",
        "surgeon"
    ],
    "wof:name":"William M Gilkison MD",
    "wof:placetype":"venue"
},
  "geometry": {"coordinates":[-86.082508,39.782604],"type":"Point"}
}