{
  "type": "Feature",
  "properties": {
    "iso:country":"US",
    "sg:address":"400 Kentwood Dr",
    "sg:city":"Frankfort",
    "sg:classifiers":[
        {
            "category":"Health Services",
            "subcategory":"Doctor",
            "type":"Services"
        }
    ],
    "sg:phone":"+1 765 654 4458",
    "sg:postcode":"46041",
    "sg:province":"IN",
    "sg:tags":[
        "dentist"
    ],
    "wof:name":"Ramos Dental Ctr",
    "wof:placetype":"venue"
},
  "geometry": {"coordinates":[-86.489405,40.277901],"type":"Point"}
}