{
  "type": "Feature",
  "properties": {
    "addr:full":"11608 Yellowstone Trl Harlan IN 46743",
    "addr:housenumber":"11608",
    "addr:postcode":"46743",
    "addr:street":"Yellowstone Trl",
    "iso:country":"US",
    "sg:address":"11608 Yellowstone Trl",
    "sg:city":"Harlan",
    "sg:classifiers":[
        {
            "category":"Building & Trades",
            "subcategory":"Construction",
            "type":"Services"
        }
    ],
    "sg:phone":"+1 260 657 0200",
    "sg:postcode":"46743",
    "sg:province":"IN",
    "sg:tags":[
        "repairing",
        "remodeling",
        "contractor"
    ],
    "wof:name":"Sunnyland Construction",
    "wof:placetype":"venue"
},
  "geometry": {"coordinates":[-84.927622,41.193709],"type":"Point"}
}