{
  "type": "Feature",
  "properties": {
    "addr:full":"508 S Bloomington St Greencastle IN 46135",
    "addr:housenumber":"508",
    "addr:postcode":"46135",
    "addr:street":"S Bloomington St",
    "iso:country":"US",
    "sg:address":"508 S Bloomington St",
    "sg:city":"Greencastle",
    "sg:classifiers":[
        {
            "category":"Retail",
            "subcategory":"Auto Repair",
            "type":"Services"
        }
    ],
    "sg:phone":"+1 765 655 2165",
    "sg:postcode":"46135",
    "sg:province":"IN",
    "sg:tags":[
        "transmission"
    ],
    "wof:name":"Tom's Transmission Repair",
    "wof:placetype":"venue"
},
  "geometry": {"coordinates":[-86.854102,39.637071],"type":"Point"}
}