{
  "type": "Feature",
  "properties": {
    "iso:country":"US",
    "sg:address":"34 S Franklin St",
    "sg:city":"Bloomfield",
    "sg:classifiers":[
        {
            "category":"Building & Trades",
            "subcategory":"Plumbing",
            "type":"Services"
        }
    ],
    "sg:phone":"+1 812 384 4285",
    "sg:postcode":"47424",
    "sg:province":"IN",
    "sg:tags":[
        "heating",
        "contractor"
    ],
    "wof:name":"Branstetter-Pullen Heating",
    "wof:placetype":"venue"
},
  "geometry": {"coordinates":[-86.938551,39.02647],"type":"Point"}
}