{
  "type": "Feature",
  "properties": {
    "iso:country":"US",
    "sg:address":"309 E Franklin St",
    "sg:city":"Greencastle",
    "sg:classifiers":[
        {
            "category":"Professional",
            "type":"Services"
        }
    ],
    "sg:phone":"+1 765 653 0956",
    "sg:postcode":"46135",
    "sg:province":"IN",
    "sg:tags":[
        "establishment"
    ],
    "wof:name":"Gibson & Lewis",
    "wof:placetype":"venue"
},
  "geometry": {"coordinates":[-86.861556,39.644832],"type":"Point"}
}