{
  "type": "Feature",
  "properties": {
    "addr:full":"309 E Franklin St Greencastle IN 46135",
    "addr:housenumber":"309",
    "addr:postcode":"46135",
    "addr:street":"E Franklin St",
    "iso:country":"US",
    "sg:address":"309 E Franklin St",
    "sg:city":"Greencastle",
    "sg:classifiers":[
        {
            "category":"Professional",
            "type":"Services"
        }
    ],
    "sg:phone":"+1 765 653 0956",
    "sg:postcode":"46135",
    "sg:province":"IN",
    "sg:tags":[
        "establishment"
    ],
    "wof:name":"Gibson & Lewis",
    "wof:placetype":"venue"
},
  "geometry": {"coordinates":[-86.86155599999999,39.644832],"type":"Point"}
}