{
  "type": "Feature",
  "properties": {
    "addr:full":"707 State Rd 257 Washington IN 47501",
    "addr:housenumber":"707;257",
    "addr:postcode":"47501",
    "addr:street":"State Rd;Washington",
    "iso:country":"US",
    "sg:address":"707 State Rd 257",
    "sg:city":"Washington",
    "sg:classifiers":[
        {
            "category":"Real Estate",
            "subcategory":"Real Estate Agent",
            "type":"Services"
        }
    ],
    "sg:phone":"+1 812 254 6064",
    "sg:postcode":"47501",
    "sg:province":"IN",
    "sg:tags":[
        "appraisal"
    ],
    "wof:name":"M & M Appraisers",
    "wof:placetype":"venue"
},
  "geometry": {"coordinates":[-87.153322,38.646203],"type":"Point"}
}