{
  "type": "Feature",
  "properties": {
    "addr:full":"2405 State St New Albany IN 47150",
    "addr:housenumber":"2405",
    "addr:postcode":"47150",
    "addr:street":"State St",
    "iso:country":"US",
    "sg:address":"2405 State St",
    "sg:city":"New Albany",
    "sg:classifiers":[
        {
            "category":"Restaurant",
            "type":"Food & Drink"
        }
    ],
    "sg:phone":"+1 812 944 9999",
    "sg:postcode":"47150",
    "sg:province":"IN",
    "wof:name":"Tucker's",
    "wof:placetype":"venue"
},
  "geometry": {"coordinates":[-85.84620200000001,38.311206],"type":"Point"}
}