{
  "type": "Feature",
  "properties": {
    "iso:country":"US",
    "sg:address":"5516 E 21st St",
    "sg:city":"Indianapolis",
    "sg:classifiers":[
        {
            "category":"Personal",
            "subcategory":"Beauty Salon",
            "type":"Services"
        }
    ],
    "sg:phone":"+1 317 356 0229",
    "sg:postcode":"46218",
    "sg:province":"IN",
    "wof:name":"Shelly's Hair Design",
    "wof:placetype":"venue"
},
  "geometry": {"coordinates":[-86.073103,39.796346],"type":"Point"}
}