{
  "type": "Feature",
  "properties": {
    "iso:country":"US",
    "sg:address":"52864 Lillian Ave",
    "sg:city":"Elkhart",
    "sg:classifiers":[
        {
            "category":"Manufacturing",
            "subcategory":"Tools & Machinery",
            "type":"Manufacturing & Wholesale Goods"
        }
    ],
    "sg:phone":"+1 574 264 0711",
    "sg:postcode":"46514",
    "sg:province":"IN",
    "sg:tags":[
        "equipment",
        "lighting"
    ],
    "sg:website":"www.vistamfg.com",
    "wof:name":"Vista Manufacturing Inc",
    "wof:placetype":"venue"
},
  "geometry": {"coordinates":[-85.991991,41.725576],"type":"Point"}
}