{
  "type": "Feature",
  "properties": {
    "iso:country":"US",
    "sg:address":"11215 Crested Oak Ct",
    "sg:city":"Fort Wayne",
    "sg:classifiers":[
        {
            "category":"Professional",
            "subcategory":"Business Services",
            "type":"Services"
        }
    ],
    "sg:phone":"+1 260 373 0371",
    "sg:postcode":"46845",
    "sg:province":"IN",
    "wof:name":"Sakells Enterprises Inc",
    "wof:placetype":"venue"
},
  "geometry": {"coordinates":[-85.07958600000001,41.187537],"type":"Point"}
}