{
  "type": "Feature",
  "properties": {
    "addr:full":"206 Coles St Logansport IN 46947",
    "addr:housenumber":"206",
    "addr:postcode":"46947",
    "addr:street":"Coles St",
    "iso:country":"US",
    "sg:address":"206 Coles St",
    "sg:city":"Logansport",
    "sg:classifiers":[
        {
            "category":"Wholesale",
            "subcategory":"Machinery & Supplies",
            "type":"Manufacturing & Wholesale Goods"
        }
    ],
    "sg:phone":"+1 574 753 4715",
    "sg:postcode":"46947",
    "sg:province":"IN",
    "sg:tags":[
        "pump"
    ],
    "wof:name":"Denny's Pump & Sewer Svc Inc",
    "wof:placetype":"venue"
},
  "geometry": {"coordinates":[-86.363303,40.746088],"type":"Point"}
}