{
  "type": "Feature",
  "properties": {
    "iso:country":"US",
    "sg:address":"119 N Vine St",
    "sg:city":"Plainfield",
    "sg:classifiers":[
        {
            "category":"Personal",
            "subcategory":"Beauty Salon",
            "type":"Services"
        }
    ],
    "sg:phone":"+1 317 839 4474",
    "sg:postcode":"46168",
    "sg:province":"IN",
    "wof:name":"Concepts Styling Salon",
    "wof:placetype":"venue"
},
  "geometry": {"coordinates":[-86.402276,39.703815],"type":"Point"}
}