{
  "type": "Feature",
  "properties": {
    "iso:country":"US",
    "sg:address":"2332 Golden Oaks N",
    "sg:city":"Indianapolis",
    "sg:classifiers":[
        {
            "category":"Professional",
            "type":"Services"
        }
    ],
    "sg:phone":"+1 317 872 8006",
    "sg:postcode":"46260",
    "sg:province":"IN",
    "sg:tags":[
        "establishment"
    ],
    "wof:name":"Koehler",
    "wof:placetype":"venue"
},
  "geometry": {"coordinates":[-86.200792,39.923221],"type":"Point"}
}