{
  "type": "Feature",
  "properties": {
    "iso:country":"US",
    "sg:address":"2100 Dakota Dr",
    "sg:city":"Franklin",
    "sg:classifiers":[
        {
            "category":"Professional",
            "type":"Services"
        }
    ],
    "sg:phone":"+1 317 738 9738",
    "sg:postcode":"46131",
    "sg:province":"IN",
    "sg:tags":[
        "establishment"
    ],
    "wof:name":"Inpulse Technologies",
    "wof:placetype":"venue"
},
  "geometry": {"coordinates":[-86.081539,39.49149],"type":"Point"}
}