{
  "type": "Feature",
  "properties": {
    "iso:country":"US",
    "sg:address":"2711 E Michigan St",
    "sg:city":"Indianapolis",
    "sg:classifiers":[
        {
            "category":"Food & Beverages",
            "subcategory":"Liquor & Beverages",
            "type":"Retail Goods"
        }
    ],
    "sg:phone":"+1 317 631 9875",
    "sg:postcode":"46201",
    "sg:province":"IN",
    "sg:tags":[
        "store"
    ],
    "wof:name":"M & K Liquors",
    "wof:placetype":"venue"
},
  "geometry": {"coordinates":[-86.116596,39.774394],"type":"Point"}
}