{
  "type": "Feature",
  "properties": {
    "addr:full":"2301 N Wayne St Angola IN 46703",
    "addr:housenumber":"2301",
    "addr:postcode":"46703",
    "addr:street":"N Wayne St",
    "iso:country":"US",
    "sg:address":"2301 N Wayne St",
    "sg:city":"Angola",
    "sg:classifiers":[
        {
            "category":"Autos & Motor Vehicles",
            "subcategory":"Boat Sales",
            "type":"Retail Goods"
        }
    ],
    "sg:phone":"+1 260 665 9913",
    "sg:postcode":"46703",
    "sg:province":"IN",
    "sg:tags":[
        "top",
        "upholstery",
        "cover"
    ],
    "wof:name":"Angola Canvas Co",
    "wof:placetype":"venue"
},
  "geometry": {"coordinates":[-84.999607,41.663766],"type":"Point"}
}