{
  "type": "Feature",
  "properties": {
    "iso:country":"US",
    "sg:address":"225 E Washington St",
    "sg:city":"Martinsville",
    "sg:classifiers":[
        {
            "category":"Shopping",
            "subcategory":"Optical Goods",
            "type":"Retail Goods"
        }
    ],
    "sg:phone":"+1 765 342 0418",
    "sg:postcode":"46151",
    "sg:province":"IN",
    "wof:name":"Superior Optical Co",
    "wof:placetype":"venue"
},
  "geometry": {"coordinates":[-86.425866,39.426802],"type":"Point"}
}