{
  "type": "Feature",
  "properties": {
    "iso:country":"US",
    "sg:address":"107 N Jefferson St",
    "sg:city":"Flora",
    "sg:classifiers":[
        {
            "category":"Shopping",
            "subcategory":"Used Merchandise",
            "type":"Retail Goods"
        }
    ],
    "sg:phone":"+1 765 395 5022",
    "sg:postcode":"46929",
    "sg:province":"IN",
    "sg:tags":[
        "antique"
    ],
    "wof:name":"Hayley's Antiques",
    "wof:placetype":"venue"
},
  "geometry": {"coordinates":[-86.52843,40.549448],"type":"Point"}
}