{
  "type": "Feature",
  "properties": {
    "iso:country":"US",
    "sg:address":"3205 Slate Creek Ct",
    "sg:city":"New Albany",
    "sg:classifiers":[
        {
            "category":"Building & Trades",
            "subcategory":"Construction",
            "type":"Services"
        }
    ],
    "sg:phone":"+1 812 945 1882",
    "sg:postcode":"47150",
    "sg:province":"IN",
    "sg:tags":[
        "general",
        "contractor"
    ],
    "wof:name":"Harter Construction Inc",
    "wof:placetype":"venue"
},
  "geometry": {"coordinates":[-85.823165,38.326824],"type":"Point"}
}