{
  "type": "Feature",
  "properties": {
    "iso:country":"US",
    "sg:address":"3449 W Jonathan Moore Pike",
    "sg:city":"Columbus",
    "sg:classifiers":[
        {
            "category":"Food & Beverages",
            "subcategory":"Liquor & Beverages",
            "type":"Retail Goods"
        }
    ],
    "sg:phone":"+1 812 378 5616",
    "sg:postcode":"47201",
    "sg:province":"IN",
    "sg:tags":[
        "alcoholic"
    ],
    "sg:website":"www.bigredliquors.com",
    "wof:name":"Big Red Liquors Inc",
    "wof:placetype":"venue"
},
  "geometry": {"coordinates":[-85.96283099999999,39.200044],"type":"Point"}
}