{
  "type": "Feature",
  "properties": {
    "iso:country":"US",
    "sg:address":"12614 Gunnison Dr",
    "sg:city":"Indianapolis",
    "sg:classifiers":[
        {
            "category":"Wholesale",
            "subcategory":"Machinery & Supplies",
            "type":"Manufacturing & Wholesale Goods"
        }
    ],
    "sg:phone":"+1 317 443 4138",
    "sg:postcode":"46236",
    "sg:province":"IN",
    "sg:tags":[
        "equipment",
        "industrial"
    ],
    "wof:name":"Covenant Industrial Supply",
    "wof:placetype":"venue"
},
  "geometry": {"coordinates":[-85.940963,39.905294],"type":"Point"}
}