{
  "type": "Feature",
  "properties": {
    "addr:full":"7781 E Ridge Rd Hobart IN 46342",
    "addr:housenumber":"7781",
    "addr:postcode":"46342",
    "addr:street":"E Ridge Rd",
    "iso:country":"US",
    "sg:address":"7781 E Ridge Rd",
    "sg:city":"Hobart",
    "sg:classifiers":[
        {
            "category":"Sports & Exercise",
            "subcategory":"Gym",
            "type":"Entertainment"
        }
    ],
    "sg:phone":"+1 219 942 1020",
    "sg:postcode":"46342",
    "sg:province":"IN",
    "sg:tags":[
        "club",
        "health",
        "studio",
        "gymnasium"
    ],
    "wof:name":"Curves For Women",
    "wof:placetype":"venue"
},
  "geometry": {"coordinates":[-87.244176,41.55064],"type":"Point"}
}