{
  "type": "Feature",
  "properties": {
    "iso:country":"US",
    "sg:address":"710 E Northshore Dr",
    "sg:city":"Syracuse",
    "sg:classifiers":[
        {
            "category":"Professional",
            "subcategory":"Management & Consulting",
            "type":"Services"
        }
    ],
    "sg:phone":"+1 574 457 4551",
    "sg:postcode":"46567",
    "sg:province":"IN",
    "sg:tags":[
        "business"
    ],
    "wof:name":"Sherry Laboratories",
    "wof:placetype":"venue"
},
  "geometry": {"coordinates":[-85.74804,41.431165],"type":"Point"}
}