{
  "type": "Feature",
  "properties": {
    "iso:country":"US",
    "sg:address":"2000 Salisbury Rd N",
    "sg:city":"Richmond",
    "sg:classifiers":[
        {
            "category":"Wholesale",
            "subcategory":"Auto Parts",
            "type":"Manufacturing & Wholesale Goods"
        }
    ],
    "sg:phone":"+1 765 962 0602",
    "sg:postcode":"47374",
    "sg:province":"IN",
    "sg:tags":[
        "automobile",
        "rebuilt"
    ],
    "wof:name":"Wise Auto Parts",
    "wof:placetype":"venue"
},
  "geometry": {"coordinates":[-84.939054,39.854187],"type":"Point"}
}