{
  "type": "Feature",
  "properties": {
    "addr:full":"1827 Buntin St Vincennes IN 47591",
    "addr:housenumber":"1827",
    "addr:postcode":"47591",
    "addr:street":"Buntin St",
    "iso:country":"US",
    "sg:address":"1827 Buntin St",
    "sg:city":"Vincennes",
    "sg:classifiers":[
        {
            "category":"Communications",
            "subcategory":"Radio Station",
            "type":"Services"
        }
    ],
    "sg:phone":"+1 812 882 8872",
    "sg:postcode":"47591",
    "sg:province":"IN",
    "sg:tags":[
        "equipment",
        "system"
    ],
    "wof:name":"Crown Electronics & Communications",
    "wof:placetype":"venue"
},
  "geometry": {"coordinates":[-87.515394,38.667132],"type":"Point"}
}