{
  "type": "Feature",
  "properties": {
    "iso:country":"US",
    "sg:address":"755 E 82nd Ave",
    "sg:city":"Merrillville",
    "sg:classifiers":[
        {
            "category":"Autos & Motor Vehicles",
            "subcategory":"Auto Supplies",
            "type":"Retail Goods"
        }
    ],
    "sg:phone":"+1 219 769 1400",
    "sg:postcode":"46410",
    "sg:province":"IN",
    "sg:tags":[
        "automobile",
        "parts"
    ],
    "sg:website":"www.lascolwi.com",
    "wof:name":"Northwest Indiana Auto Supply",
    "wof:placetype":"venue"
},
  "geometry": {"coordinates":[-87.329038,41.469177],"type":"Point"}
}