{
  "type": "Feature",
  "properties": {
    "iso:country":"US",
    "sg:address":"3833 Prospect St",
    "sg:city":"Indianapolis",
    "sg:classifiers":[
        {
            "category":"Shopping",
            "subcategory":"Used Merchandise",
            "type":"Retail Goods"
        }
    ],
    "sg:phone":"+1 317 322 1867",
    "sg:postcode":"46203",
    "sg:province":"IN",
    "wof:name":"Value Village Inc",
    "wof:placetype":"venue"
},
  "geometry": {"coordinates":[-86.101045,39.752644],"type":"Point"}
}