{
  "type": "Feature",
  "properties": {
    "iso:country":"US",
    "sg:address":"1100 Ranch Rd",
    "sg:city":"Connersville",
    "sg:classifiers":[
        {
            "category":"Real Estate",
            "subcategory":"Real Estate Agent",
            "type":"Services"
        }
    ],
    "sg:phone":"+1 765 825 1773",
    "sg:postcode":"47331",
    "sg:province":"IN",
    "wof:name":"Taylor RE Appraisal Svc",
    "wof:placetype":"venue"
},
  "geometry": {"coordinates":[-85.160907,39.637831],"type":"Point"}
}