{
  "type": "Feature",
  "properties": {
    "addr:full":"317 E McKinley Ave Mishawaka IN 46545",
    "addr:housenumber":"317",
    "addr:postcode":"46545",
    "addr:street":"E Mckinley Ave",
    "iso:country":"US",
    "sg:address":"317 E McKinley Ave",
    "sg:city":"Mishawaka",
    "sg:classifiers":[
        {
            "category":"Retail",
            "subcategory":"Auto Rental",
            "type":"Services"
        }
    ],
    "sg:phone":"+1 574 252 5119",
    "sg:postcode":"46545",
    "sg:province":"IN",
    "sg:tags":[
        "renting",
        "automobile"
    ],
    "wof:name":"Hertz Rent A Car",
    "wof:placetype":"venue"
},
  "geometry": {"coordinates":[-86.1778,41.680366],"type":"Point"}
}