{
  "type": "Feature",
  "properties": {
    "addr:full":"2015 N State Rd 3 Greensburg IN 47240",
    "addr:housenumber":"2015",
    "addr:postcode":"47240",
    "addr:street":"N State Rd 3",
    "iso:country":"US",
    "sg:address":"2015 N State Rd 3",
    "sg:city":"Greensburg",
    "sg:classifiers":[
        {
            "category":"Restaurant",
            "type":"Food & Drink"
        }
    ],
    "sg:phone":"+1 812 663 2926",
    "sg:postcode":"47240",
    "sg:province":"IN",
    "sg:website":"www.burgerking.com",
    "wof:name":"Burger King",
    "wof:placetype":"venue"
},
  "geometry": {"coordinates":[-85.479664,39.367536],"type":"Point"}
}