{
  "type": "Feature",
  "properties": {
    "addr:full":"28126 Co Rd 4 Elkhart IN 46514",
    "addr:postcode":"28126;46514",
    "addr:street":"Co Rd 4",
    "iso:country":"US",
    "sg:address":"28126 Co Rd 4",
    "sg:city":"Elkhart",
    "sg:classifiers":[
        {
            "category":"Organizations",
            "subcategory":"Religious Organization",
            "type":"Services"
        }
    ],
    "sg:phone":"+1 574 264 0811",
    "sg:postcode":"46514",
    "sg:province":"IN",
    "wof:name":"Church Of God",
    "wof:placetype":"venue"
},
  "geometry": {"coordinates":[-86.01005499999999,41.739007],"type":"Point"}
}