{
  "type": "Feature",
  "properties": {
    "iso:country":"US",
    "sg:address":"1412 Schuler Dr",
    "sg:city":"Kokomo",
    "sg:classifiers":[
        {
            "category":"Communications",
            "subcategory":"Film & Video Production",
            "type":"Services"
        }
    ],
    "sg:phone":"+1 765 854 1272",
    "sg:postcode":"46901",
    "sg:province":"IN",
    "sg:tags":[
        "motion"
    ],
    "wof:name":"Memories R Great",
    "wof:placetype":"venue"
},
  "geometry": {"coordinates":[-86.147489,40.499395],"type":"Point"}
}