{
  "type": "Feature",
  "properties": {
    "addr:full":"2000 Elkhart Rd Goshen IN 46526",
    "addr:housenumber":"2000",
    "addr:postcode":"46526",
    "addr:street":"Elkhart Rd",
    "iso:country":"US",
    "sg:address":"2000 Elkhart Rd",
    "sg:city":"Goshen",
    "sg:classifiers":[
        {
            "category":"Insurance",
            "subcategory":"Insurance Agent",
            "type":"Services"
        }
    ],
    "sg:phone":"+1 574 534 0499",
    "sg:postcode":"46526",
    "sg:province":"IN",
    "wof:name":"Holdread Insurance",
    "wof:placetype":"venue"
},
  "geometry": {"coordinates":[-85.8647,41.600101],"type":"Point"}
}