{
  "type": "Feature",
  "properties": {
    "addr:full":"519 Wyndclyff Dr Evansville IN 47711",
    "addr:housenumber":"519",
    "addr:postcode":"47711",
    "addr:street":"Wyndclyff Dr",
    "iso:country":"US",
    "sg:address":"519 Wyndclyff Dr",
    "sg:city":"Evansville",
    "sg:classifiers":[
        {
            "category":"Wholesale",
            "subcategory":"Hardware",
            "type":"Manufacturing & Wholesale Goods"
        }
    ],
    "sg:phone":"+1 812 421 1894",
    "sg:postcode":"47711",
    "sg:province":"IN",
    "sg:tags":[
        "plumbing",
        "ac",
        "heating"
    ],
    "wof:name":"Podvin Sales Corp",
    "wof:placetype":"venue"
},
  "geometry": {"coordinates":[-87.555379,38.016808],"type":"Point"}
}