{
  "type": "Feature",
  "properties": {
    "addr:full":"2220 Woodcrest Rd Indianapolis IN 46227",
    "addr:housenumber":"2220",
    "addr:postcode":"46227",
    "addr:street":"Woodcrest Rd",
    "iso:country":"US",
    "sg:address":"2220 Woodcrest Rd",
    "sg:city":"Indianapolis",
    "sg:classifiers":[
        {
            "category":"Building & Trades",
            "subcategory":"Construction",
            "type":"Services"
        }
    ],
    "sg:phone":"+1 317 783 9130",
    "sg:postcode":"46227",
    "sg:province":"IN",
    "sg:tags":[
        "caulking",
        "contractor"
    ],
    "wof:name":"Cox-Jones Contracting Inc",
    "wof:placetype":"venue"
},
  "geometry": {"coordinates":[-86.12194,39.700546],"type":"Point"}
}