{
  "type": "Feature",
  "properties": {
    "iso:country":"US",
    "sg:address":"7520 River Rd",
    "sg:city":"Indianapolis",
    "sg:classifiers":[
        {
            "category":"Shopping",
            "subcategory":"Jewelry",
            "type":"Retail Goods"
        }
    ],
    "sg:phone":"+1 317 257 7076",
    "sg:postcode":"46240",
    "sg:province":"IN",
    "wof:name":"Glass Harmonica",
    "wof:placetype":"venue"
},
  "geometry": {"coordinates":[-86.11928,39.891544],"type":"Point"}
}