{
  "type": "Feature",
  "properties": {
    "iso:country":"US",
    "sg:address":"7600 State Rd 64",
    "sg:city":"Georgetown",
    "sg:classifiers":[
        {
            "category":"Shopping",
            "subcategory":"Department Store",
            "type":"Retail Goods"
        }
    ],
    "sg:phone":"+1 812 951 3827",
    "sg:postcode":"47122",
    "sg:province":"IN",
    "sg:tags":[
        "shop"
    ],
    "wof:name":"Family Dollar Store",
    "wof:placetype":"venue"
},
  "geometry": {"coordinates":[-85.949898,38.294879],"type":"Point"}
}