{
  "type": "Feature",
  "properties": {
    "addr:full":"47 S Elm St Zionsville IN 46077",
    "addr:housenumber":"47",
    "addr:postcode":"46077",
    "addr:street":"S Elm St",
    "iso:country":"US",
    "sg:address":"47 S Elm St",
    "sg:city":"Zionsville",
    "sg:classifiers":[
        {
            "category":"Professional",
            "subcategory":"Management & Consulting",
            "type":"Services"
        }
    ],
    "sg:phone":"+1 317 873 9388",
    "sg:postcode":"46077",
    "sg:province":"IN",
    "sg:tags":[
        "consultant",
        "business"
    ],
    "wof:name":"Highlands Group LLC",
    "wof:placetype":"venue"
},
  "geometry": {"coordinates":[-86.260503,39.951283],"type":"Point"}
}