{
  "type": "Feature",
  "properties": {
    "iso:country":"US",
    "sg:address":"1720 Alvord St",
    "sg:city":"Indianapolis",
    "sg:classifiers":[
        {
            "category":"Organizations",
            "subcategory":"Community Association",
            "type":"Services"
        }
    ],
    "sg:phone":"+1 317 927 9127",
    "sg:postcode":"46202",
    "sg:province":"IN",
    "sg:tags":[
        "club"
    ],
    "wof:name":"Rough Riders Motorcycle Club",
    "wof:placetype":"venue"
},
  "geometry": {"coordinates":[-86.139335,39.79199],"type":"Point"}
}