{
  "type": "Feature",
  "properties": {
    "iso:country":"US",
    "sg:address":"28 S Main St",
    "sg:city":"Linton",
    "sg:classifiers":[
        {
            "category":"Home & Garden",
            "subcategory":"Building Materials",
            "type":"Retail Goods"
        }
    ],
    "sg:phone":"+1 812 847 7984",
    "sg:postcode":"47441",
    "sg:province":"IN",
    "sg:tags":[
        "wallpaper"
    ],
    "wof:name":"Diana's Paint & Wallpaper Co",
    "wof:placetype":"venue"
},
  "geometry": {"coordinates":[-87.1662,39.033691],"type":"Point"}
}