{
  "type": "Feature",
  "properties": {
    "iso:country":"US",
    "sg:address":"10635 E State Rd 8",
    "sg:city":"Knox",
    "sg:classifiers":[
        {
            "category":"Bars & Pubs",
            "type":"Food & Drink"
        }
    ],
    "sg:phone":"+1 574 772 4723",
    "sg:postcode":"46534",
    "sg:province":"IN",
    "wof:name":"L & J's Round-Up",
    "wof:placetype":"venue"
},
  "geometry": {"coordinates":[-86.492703,41.287719],"type":"Point"}
}