{
  "type": "Feature",
  "properties": {
    "addr:full":"308 N Jefferson St Huntington IN 46750",
    "addr:housenumber":"308",
    "addr:postcode":"46750",
    "addr:street":"N Jefferson",
    "iso:country":"US",
    "sg:address":"308 N Jefferson St",
    "sg:city":"Huntington",
    "sg:classifiers":[
        {
            "category":"Insurance",
            "subcategory":"Insurance Agent",
            "type":"Services"
        }
    ],
    "sg:phone":"+1 260 356 2600",
    "sg:postcode":"46750",
    "sg:province":"IN",
    "wof:name":"BSB Insurance Svc Inc",
    "wof:placetype":"venue"
},
  "geometry": {"coordinates":[-85.494326,40.881175],"type":"Point"}
}