{
  "type": "Feature",
  "properties": {
    "iso:country":"US",
    "sg:address":"2728 W 15th Ave",
    "sg:city":"Gary",
    "sg:classifiers":[
        {
            "category":"Shopping",
            "subcategory":"Used Merchandise",
            "type":"Retail Goods"
        }
    ],
    "sg:phone":"+1 219 977 9282",
    "sg:postcode":"46404",
    "sg:province":"IN",
    "sg:tags":[
        "shop",
        "consignment"
    ],
    "wof:name":"Temlola's Just Like New",
    "wof:placetype":"venue"
},
  "geometry": {"coordinates":[-87.371677,41.587941],"type":"Point"}
}