{
  "type": "Feature",
  "properties": {
    "iso:country":"US",
    "sg:address":"208 Ivanhoe Ct",
    "sg:city":"Griffith",
    "sg:classifiers":[
        {
            "category":"Retail",
            "subcategory":"Auto Repair",
            "type":"Services"
        }
    ],
    "sg:phone":"+1 219 934 9085",
    "sg:postcode":"46319",
    "sg:province":"IN",
    "sg:tags":[
        "repairing",
        "automobile"
    ],
    "wof:name":"KLEN Automotive INC",
    "wof:placetype":"venue"
},
  "geometry": {"coordinates":[-87.410796,41.519021],"type":"Point"}
}