{
  "type": "Feature",
  "properties": {
    "iso:country":"US",
    "sg:address":"4726 W Washington St",
    "sg:city":"Indianapolis",
    "sg:classifiers":[
        {
            "category":"Restaurant",
            "type":"Food & Drink"
        }
    ],
    "sg:phone":"+1 317 240 2826",
    "sg:postcode":"46241",
    "sg:province":"IN",
    "wof:name":"Little By Little Tavern",
    "wof:placetype":"venue"
},
  "geometry": {"coordinates":[-86.240976,39.755778],"type":"Point"}
}