{
  "type": "Feature",
  "properties": {
    "iso:country":"US",
    "sg:address":"2 W Main St",
    "sg:city":"Greenfield",
    "sg:classifiers":[
        {
            "category":"Social Services",
            "type":"Services"
        }
    ],
    "sg:phone":"+1 317 462 1135",
    "sg:postcode":"46140",
    "sg:province":"IN",
    "sg:tags":[
        "probation"
    ],
    "wof:name":"Hancock County Probation Dept",
    "wof:placetype":"venue"
},
  "geometry": {"coordinates":[-85.76931399999999,39.785216],"type":"Point"}
}