{
  "type": "Feature",
  "properties": {
    "iso:country":"US",
    "sg:address":"430 N Grandstaff Dr",
    "sg:city":"Auburn",
    "sg:classifiers":[
        {
            "category":"Shopping",
            "subcategory":"Used Merchandise",
            "type":"Retail Goods"
        }
    ],
    "sg:phone":"+1 260 572 0042",
    "sg:postcode":"46706",
    "sg:province":"IN",
    "sg:tags":[
        "shop",
        "thrift"
    ],
    "wof:name":"Goodwill Industries",
    "wof:placetype":"venue"
},
  "geometry": {"coordinates":[-85.071538,41.368073],"type":"Point"}
}