{
  "type": "Feature",
  "properties": {
    "iso:country":"US",
    "sg:address":"261 E Division Rd",
    "sg:city":"Valparaiso",
    "sg:classifiers":[
        {
            "category":"Real Estate",
            "subcategory":"Real Estate Operator",
            "type":"Services"
        }
    ],
    "sg:phone":"+1 219 462 7993",
    "sg:postcode":"46383",
    "sg:province":"IN",
    "sg:tags":[
        "property",
        "lessor"
    ],
    "wof:name":"Marvin Stoner",
    "wof:placetype":"venue"
},
  "geometry": {"coordinates":[-87.015668,41.434517],"type":"Point"}
}