{
  "type": "Feature",
  "properties": {
    "iso:country":"US",
    "sg:address":"25772 Co Rd 40",
    "sg:city":"Goshen",
    "sg:classifiers":[
        {
            "category":"Retail",
            "subcategory":"Repair Shop",
            "type":"Services"
        }
    ],
    "sg:phone":"+1 574 862 1123",
    "sg:postcode":"46526",
    "sg:province":"IN",
    "sg:tags":[
        "repairing",
        "lawn",
        "mower"
    ],
    "wof:name":"Martin's Small Engine Repair",
    "wof:placetype":"venue"
},
  "geometry": {"coordinates":[-85.957581,41.536449],"type":"Point"}
}