{
  "type": "Feature",
  "properties": {
    "iso:country":"US",
    "sg:address":"305 Main St",
    "sg:city":"Vincennes",
    "sg:classifiers":[
        {
            "category":"Professional",
            "subcategory":"Detective & Security Services",
            "type":"Services"
        }
    ],
    "sg:phone":"+1 812 886 9454",
    "sg:postcode":"47591",
    "sg:province":"IN",
    "wof:name":"Lynn Stangle",
    "wof:placetype":"venue"
},
  "geometry": {"coordinates":[-87.531638,38.679073],"type":"Point"}
}