{
  "type": "Feature",
  "properties": {
    "iso:country":"US",
    "sg:address":"645 W Carmel Dr",
    "sg:city":"Carmel",
    "sg:classifiers":[
        {
            "category":"Health Services",
            "subcategory":"Health Practitioner",
            "type":"Services"
        }
    ],
    "sg:phone":"+1 317 846 5437",
    "sg:postcode":"46032",
    "sg:province":"IN",
    "sg:tags":[
        "psychologist"
    ],
    "wof:name":"Jackson B Dimovski",
    "wof:placetype":"venue"
},
  "geometry": {"coordinates":[-86.132921,39.962238],"type":"Point"}
}