{
  "type": "Feature",
  "properties": {
    "iso:country":"US",
    "sg:address":"2126 W Wilden Ave",
    "sg:city":"Goshen",
    "sg:classifiers":[
        {
            "category":"Building & Trades",
            "subcategory":"Landscaping Services",
            "type":"Services"
        }
    ],
    "sg:phone":"+1 574 534 3298",
    "sg:postcode":"46528",
    "sg:province":"IN",
    "sg:tags":[
        "designer",
        "landscape"
    ],
    "wof:name":"New Vistas Landscaping Ctr",
    "wof:placetype":"venue"
},
  "geometry": {"coordinates":[-85.864925,41.601944],"type":"Point"}
}