{
  "type": "Feature",
  "properties": {
    "iso:country":"US",
    "sg:address":"7626 E 53rd St",
    "sg:city":"Indianapolis",
    "sg:classifiers":[
        {
            "category":"Restaurant",
            "type":"Food & Drink"
        }
    ],
    "sg:phone":"+1 317 377 0257",
    "sg:postcode":"46226",
    "sg:province":"IN",
    "sg:tags":[
        "eating"
    ],
    "wof:name":"In Catfish Assn",
    "wof:placetype":"venue"
},
  "geometry": {"coordinates":[-86.032043,39.84985],"type":"Point"}
}