{
  "type": "Feature",
  "properties": {
    "iso:country":"US",
    "sg:address":"1743 E Margaret Ave",
    "sg:city":"Terre Haute",
    "sg:classifiers":[
        {
            "category":"Personal",
            "subcategory":"Beauty Salon",
            "type":"Services"
        }
    ],
    "sg:phone":"+1 812 231 1010",
    "sg:postcode":"47802",
    "sg:province":"IN",
    "wof:name":"High Maintenance",
    "wof:placetype":"venue"
},
  "geometry": {"coordinates":[-87.392579,39.433691],"type":"Point"}
}