{
  "type": "Feature",
  "properties": {
    "iso:country":"US",
    "sg:address":"4953 W State Rd 56",
    "sg:city":"Jasper",
    "sg:classifiers":[
        {
            "category":"Food & Beverages",
            "subcategory":"Groceries & Convenience Stores",
            "type":"Retail Goods"
        }
    ],
    "sg:phone":"+1 812 482 7031",
    "sg:postcode":"47546",
    "sg:province":"IN",
    "sg:tags":[
        "grocer"
    ],
    "wof:name":"Spud's Food Mart Inc",
    "wof:placetype":"venue"
},
  "geometry": {"coordinates":[-86.990933,38.411708],"type":"Point"}
}