{
  "type": "Feature",
  "properties": {
    "addr:full":"4504 Lima Rd Fort Wayne IN 46808",
    "addr:housenumber":"4504",
    "addr:postcode":"46808",
    "addr:street":"Lima Rd",
    "iso:country":"US",
    "sg:address":"4504 Lima Rd",
    "sg:city":"Fort Wayne",
    "sg:classifiers":[
        {
            "category":"Retail",
            "subcategory":"Auto Repair",
            "type":"Services"
        }
    ],
    "sg:phone":"+1 260 484 0341",
    "sg:postcode":"46808",
    "sg:province":"IN",
    "sg:tags":[
        "repairing",
        "automobile"
    ],
    "wof:name":"Exhaust World Inc",
    "wof:placetype":"venue"
},
  "geometry": {"coordinates":[-85.149463,41.118165],"type":"Point"}
}