{
  "type": "Feature",
  "properties": {
    "iso:country":"US",
    "sg:address":"5455 E 150 N",
    "sg:city":"Decatur",
    "sg:classifiers":[
        {
            "category":"Freight",
            "type":"Transportation"
        }
    ],
    "sg:phone":"+1 260 592 7373",
    "sg:postcode":"46733",
    "sg:province":"IN",
    "sg:tags":[
        "operator",
        "local",
        "trucking"
    ],
    "wof:name":"Hunter Ice Delivery",
    "wof:placetype":"venue"
},
  "geometry": {"coordinates":[-84.837939,40.768659],"type":"Point"}
}