{
  "type": "Feature",
  "properties": {
    "iso:country":"US",
    "sg:address":"7101 E Piccadilly Rd",
    "sg:city":"Muncie",
    "sg:classifiers":[
        {
            "category":"Building & Trades",
            "subcategory":"Landscaping Services",
            "type":"Services"
        }
    ],
    "sg:phone":"+1 765 747 0725",
    "sg:postcode":"47303",
    "sg:province":"IN",
    "sg:tags":[
        "tree"
    ],
    "wof:name":"Advance Tree Care",
    "wof:placetype":"venue"
},
  "geometry": {"coordinates":[-85.30195999999999,40.191964],"type":"Point"}
}