{
  "type": "Feature",
  "properties": {
    "iso:country":"US",
    "sg:address":"109 W Washington St",
    "sg:city":"South Bend",
    "sg:classifiers":[
        {
            "category":"Food & Beverages",
            "subcategory":"Specialty",
            "type":"Retail Goods"
        }
    ],
    "sg:phone":"+1 574 282 2522",
    "sg:postcode":"46601",
    "sg:province":"IN",
    "sg:tags":[
        "tea",
        "coffee"
    ],
    "wof:name":"Higher Grounds",
    "wof:placetype":"venue"
},
  "geometry": {"coordinates":[-86.250851,41.676451],"type":"Point"}
}