{
  "type": "Feature",
  "properties": {
    "iso:country":"US",
    "sg:address":"1555 Harrison Plz",
    "sg:city":"Bluffton",
    "sg:classifiers":[
        {
            "category":"Food & Beverages",
            "subcategory":"Groceries & Convenience Stores",
            "type":"Retail Goods"
        }
    ],
    "sg:phone":"+1 260 824 3700",
    "sg:postcode":"46714",
    "sg:province":"IN",
    "sg:tags":[
        "grocer"
    ],
    "wof:name":"Scott's Food Stores",
    "wof:placetype":"venue"
},
  "geometry": {"coordinates":[-85.16925999999999,40.720974],"type":"Point"}
}