{
  "type": "Feature",
  "properties": {
    "addr:full":"3120 State Rd 67 Martinsville IN 46151",
    "addr:housenumber":"3120;67",
    "addr:postcode":"46151",
    "addr:street":"State Rd",
    "iso:country":"US",
    "sg:address":"3120 State Rd 67",
    "sg:city":"Martinsville",
    "sg:classifiers":[
        {
            "category":"Shopping",
            "type":"Retail Goods"
        }
    ],
    "sg:phone":"+1 765 349 2816",
    "sg:postcode":"46151",
    "sg:province":"IN",
    "sg:tags":[
        "art",
        "gallery",
        "dealer"
    ],
    "wof:name":"Art Expresion",
    "wof:placetype":"venue"
},
  "geometry": {"coordinates":[-86.484038,39.416231],"type":"Point"}
}