{
  "type": "Feature",
  "properties": {
    "iso:country":"US",
    "sg:address":"1829 Cunningham Rd",
    "sg:city":"Indianapolis",
    "sg:classifiers":[
        {
            "category":"Travel",
            "subcategory":"Hotels & Motels",
            "type":"Entertainment"
        }
    ],
    "sg:phone":"+1 317 487 6531",
    "sg:postcode":"46224",
    "sg:province":"IN",
    "sg:tags":[
        "operation"
    ],
    "wof:name":"Speedway Bed & Breakfast",
    "wof:placetype":"venue"
},
  "geometry": {"coordinates":[-86.26094399999999,39.792227],"type":"Point"}
}