{
  "type": "Feature",
  "properties": {
    "iso:country":"US",
    "sg:address":"8170 N 600 W",
    "sg:city":"Ligonier",
    "sg:classifiers":[
        {
            "category":"Freight",
            "type":"Transportation"
        }
    ],
    "sg:phone":"+1 260 894 7355",
    "sg:postcode":"46767",
    "sg:province":"IN",
    "sg:tags":[
        "operator",
        "local",
        "trucking"
    ],
    "wof:name":"B&B Associates",
    "wof:placetype":"venue"
},
  "geometry": {"coordinates":[-85.538387,41.471651],"type":"Point"}
}