{
  "type": "Feature",
  "properties": {
    "iso:country":"US",
    "sg:address":"355 E Co Rd 1125 S",
    "sg:city":"Cloverdale",
    "sg:classifiers":[
        {
            "category":"Building & Trades",
            "subcategory":"Construction",
            "type":"Services"
        }
    ],
    "sg:phone":"+1 765 795 4716",
    "sg:postcode":"46120",
    "sg:province":"IN",
    "sg:tags":[
        "dry wall",
        "contractor"
    ],
    "wof:name":"Hilbert Drywall",
    "wof:placetype":"venue"
},
  "geometry": {"coordinates":[-86.84918,39.497656],"type":"Point"}
}