{
  "type": "Feature",
  "properties": {
    "iso:country":"US",
    "sg:address":"33 E 6th St",
    "sg:city":"Peru",
    "sg:classifiers":[
        {
            "category":"Organizations",
            "subcategory":"Community Association",
            "type":"Services"
        }
    ],
    "sg:phone":"+1 765 472 3857",
    "sg:postcode":"46970",
    "sg:province":"IN",
    "sg:tags":[
        "military"
    ],
    "wof:name":"American Legion",
    "wof:placetype":"venue"
},
  "geometry": {"coordinates":[-86.069714,40.755601],"type":"Point"}
}