{
  "type": "Feature",
  "properties": {
    "iso:country":"US",
    "sg:address":"4512 W 300 S",
    "sg:city":"Anderson",
    "sg:classifiers":[
        {
            "category":"Communications",
            "subcategory":"Film & Video Production",
            "type":"Services"
        }
    ],
    "sg:phone":"+1 765 644 8230",
    "sg:postcode":"46011",
    "sg:province":"IN",
    "wof:name":"Steve Crandall",
    "wof:placetype":"venue"
},
  "geometry": {"coordinates":[-85.758648,40.061118],"type":"Point"}
}