{
  "type": "Feature",
  "properties": {
    "iso:country":"US",
    "sg:address":"736 10th Pl",
    "sg:city":"Mishawaka",
    "sg:classifiers":[
        {
            "category":"Professional",
            "subcategory":"Employment Agencies",
            "type":"Services"
        }
    ],
    "sg:phone":"+1 574 247 9052",
    "sg:postcode":"46544",
    "sg:province":"IN",
    "sg:tags":[
        "modeling"
    ],
    "wof:name":"AAA Modeling & Talent Agency",
    "wof:placetype":"venue"
},
  "geometry": {"coordinates":[-86.16899600000001,41.653026],"type":"Point"}
}