{
  "type": "Feature",
  "properties": {
    "iso:country":"US",
    "sg:address":"927 Coliseum Blvd N",
    "sg:city":"Fort Wayne",
    "sg:classifiers":[
        {
            "category":"Personal",
            "subcategory":"Beauty Salon",
            "type":"Services"
        }
    ],
    "sg:phone":"+1 260 484 1129",
    "sg:postcode":"46805",
    "sg:province":"IN",
    "sg:tags":[
        "manicuring"
    ],
    "wof:name":"Golden Nails",
    "wof:placetype":"venue"
},
  "geometry": {"coordinates":[-85.087846,41.085479],"type":"Point"}
}