{
  "type": "Feature",
  "properties": {
    "iso:country":"US",
    "sg:address":"3350 E 400 N",
    "sg:city":"Winchester",
    "sg:classifiers":[
        {
            "category":"Farming",
            "subcategory":"Farm",
            "type":"Manufacturing & Wholesale Goods"
        }
    ],
    "sg:phone":"+1 765 584 0878",
    "sg:postcode":"47394",
    "sg:province":"IN",
    "sg:tags":[
        "crop",
        "general"
    ],
    "wof:name":"Wiist Farms",
    "wof:placetype":"venue"
},
  "geometry": {"coordinates":[-84.91227499999999,40.222477],"type":"Point"}
}