{
  "type": "Feature",
  "properties": {
    "addr:full":"889 Crown Ct Crown Point IN 46307",
    "addr:housenumber":"889",
    "addr:postcode":"46307",
    "addr:street":"Crown Ct",
    "iso:country":"US",
    "sg:address":"889 Crown Ct",
    "sg:city":"Crown Point",
    "sg:classifiers":[
        {
            "category":"Recreation",
            "type":"Entertainment"
        }
    ],
    "sg:phone":"+1 219 661 3071",
    "sg:postcode":"46307",
    "sg:province":"IN",
    "sg:tags":[
        "fairground"
    ],
    "wof:name":"Lake County Fairgrounds",
    "wof:placetype":"venue"
},
  "geometry": {"coordinates":[-87.35333799999999,41.431127],"type":"Point"}
}