{
  "type": "Feature",
  "properties": {
    "iso:country":"US",
    "sg:address":"495 3rd Ave",
    "sg:city":"Jasper",
    "sg:classifiers":[
        {
            "category":"Retail",
            "subcategory":"Repair Shop",
            "type":"Services"
        }
    ],
    "sg:phone":"+1 812 482 3366",
    "sg:postcode":"47546",
    "sg:province":"IN",
    "sg:tags":[
        "scooter",
        "motorcycle",
        "motor"
    ],
    "wof:name":"A J Cycle Atv Svc",
    "wof:placetype":"venue"
},
  "geometry": {"coordinates":[-86.920076,38.381436],"type":"Point"}
}