{
  "type": "Feature",
  "properties": {
    "iso:country":"US",
    "sg:address":"4660 Cleveland St",
    "sg:city":"Gary",
    "sg:classifiers":[
        {
            "category":"Manufacturing",
            "subcategory":"Building Materials",
            "type":"Manufacturing & Wholesale Goods"
        }
    ],
    "sg:phone":"+1 219 884 6890",
    "sg:postcode":"46408",
    "sg:province":"IN",
    "sg:tags":[
        "cabinet"
    ],
    "wof:name":"Ridge Home Equipment Co",
    "wof:placetype":"venue"
},
  "geometry": {"coordinates":[-87.360544,41.534416],"type":"Point"}
}