{
  "type": "Feature",
  "properties": {
    "iso:country":"US",
    "sg:address":"5667 W 74th St",
    "sg:city":"Indianapolis",
    "sg:classifiers":[
        {
            "category":"Wholesale",
            "subcategory":"Machinery & Supplies",
            "type":"Manufacturing & Wholesale Goods"
        }
    ],
    "sg:phone":"+1 317 347 0100",
    "sg:postcode":"46278",
    "sg:province":"IN",
    "sg:tags":[
        "equipment",
        "industrial"
    ],
    "wof:name":"MPW Filtration",
    "wof:placetype":"venue"
},
  "geometry": {"coordinates":[-86.260565,39.887323],"type":"Point"}
}