{
  "type": "Feature",
  "properties": {
    "iso:country":"US",
    "sg:address":"120 S Cale St",
    "sg:city":"Poseyville",
    "sg:classifiers":[
        {
            "category":"Retail",
            "subcategory":"Auto Repair",
            "type":"Services"
        }
    ],
    "sg:phone":"+1 812 874 2715",
    "sg:postcode":"47633",
    "sg:province":"IN",
    "sg:tags":[
        "body",
        "repairing",
        "painting",
        "automobile"
    ],
    "wof:name":"Collins Body Shop Inc",
    "wof:placetype":"venue"
},
  "geometry": {"coordinates":[-87.783286,38.166501],"type":"Point"}
}