{
  "type": "Feature",
  "properties": {
    "addr:full":"271 Merchants Square Dr Carmel IN 46032",
    "addr:housenumber":"271",
    "addr:postcode":"46032",
    "addr:street":"Merchants Square Dr",
    "iso:country":"US",
    "sg:address":"271 Merchants Square Dr",
    "sg:city":"Carmel",
    "sg:phone":"+1 317 844 0657",
    "sg:postcode":"46032",
    "sg:province":"IN",
    "wof:name":"Adamson's Karate Studio Inc",
    "wof:placetype":"venue"
},
  "geometry": {"coordinates":[-86.120018,39.958642],"type":"Point"}
}