{
  "type": "Feature",
  "properties": {
    "addr:full":"3125 Hwy 135 NE Corydon IN 47112",
    "addr:housenumber":"3125",
    "addr:postcode":"47112",
    "addr:street":"Hwy 135 Ne",
    "iso:country":"US",
    "sg:address":"3125 Hwy 135 NE",
    "sg:city":"Corydon",
    "sg:classifiers":[
        {
            "category":"Autos & Motor Vehicles",
            "subcategory":"Automobile Sales",
            "type":"Retail Goods"
        }
    ],
    "sg:phone":"+1 812 738 1060",
    "sg:postcode":"47112",
    "sg:province":"IN",
    "sg:tags":[
        "recreational",
        "c",
        "used",
        "passenger"
    ],
    "wof:name":"Sky-Lite Mobile Home Parts",
    "wof:placetype":"venue"
},
  "geometry": {"coordinates":[-86.12475999999999,38.251694],"type":"Point"}
}