{
  "type": "Feature",
  "properties": {
    "addr:full":"304 Walnut St Lawrenceburg IN 47025",
    "addr:housenumber":"304",
    "addr:postcode":"47025",
    "addr:street":"Walnut St",
    "iso:country":"US",
    "sg:address":"304 Walnut St",
    "sg:city":"Lawrenceburg",
    "sg:classifiers":[
        {
            "category":"Shopping",
            "type":"Retail Goods"
        }
    ],
    "sg:phone":"+1 812 539 2872",
    "sg:postcode":"47025",
    "sg:province":"IN",
    "sg:tags":[
        "candle"
    ],
    "wof:name":"Hoosier Hills Candle Works",
    "wof:placetype":"venue"
},
  "geometry": {"coordinates":[-84.85096,39.095272],"type":"Point"}
}