{
  "type": "Feature",
  "properties": {
    "iso:country":"US",
    "sg:address":"299 Bus Park Dr",
    "sg:city":"Fortville",
    "sg:classifiers":[
        {
            "category":"Building & Trades",
            "subcategory":"Equipment Rental",
            "type":"Services"
        }
    ],
    "sg:phone":"+1 317 485 4981",
    "sg:postcode":"46040",
    "sg:province":"IN",
    "sg:tags":[
        "audio",
        "leasing"
    ],
    "wof:name":"Stage Tech Inc",
    "wof:placetype":"venue"
},
  "geometry": {"coordinates":[-85.837739,39.936659],"type":"Point"}
}