{
  "type": "Feature",
  "properties": {
    "iso:country":"US",
    "sg:address":"4545 W 15th Ave",
    "sg:city":"Gary",
    "sg:classifiers":[
        {
            "category":"Food & Beverages",
            "subcategory":"Liquor & Beverages",
            "type":"Retail Goods"
        }
    ],
    "sg:phone":"+1 219 949 5629",
    "sg:postcode":"46404",
    "sg:province":"IN",
    "wof:name":"Discount Liquors",
    "wof:placetype":"venue"
},
  "geometry": {"coordinates":[-87.39260299999999,41.587911],"type":"Point"}
}