{
  "type": "Feature",
  "properties": {
    "iso:country":"US",
    "sg:address":"3737 S Clinton St",
    "sg:city":"Fort Wayne",
    "sg:classifiers":[
        {
            "category":"Personal",
            "type":"Services"
        }
    ],
    "sg:phone":"+1 260 456 7206",
    "sg:postcode":"46806",
    "sg:province":"IN",
    "sg:tags":[
        "hair",
        "replacement"
    ],
    "wof:name":"Personal Touch Hair Rplcmnts",
    "wof:placetype":"venue"
},
  "geometry": {"coordinates":[-85.134599,41.050413],"type":"Point"}
}