{
  "type": "Feature",
  "properties": {
    "addr:full":"1830 16th St Bedford IN 47421",
    "addr:housenumber":"1830",
    "addr:postcode":"47421",
    "addr:street":"16Th St",
    "iso:country":"US",
    "sg:address":"1830 16th St",
    "sg:city":"Bedford",
    "sg:classifiers":[
        {
            "category":"Social Services",
            "type":"Services"
        }
    ],
    "sg:phone":"+1 812 275 2235",
    "sg:postcode":"47421",
    "sg:province":"IN",
    "sg:tags":[
        "youth",
        "organization",
        "center"
    ],
    "wof:name":"Boy's Club",
    "wof:placetype":"venue"
},
  "geometry": {"coordinates":[-86.495001,38.861028],"type":"Point"}
}