{
  "type": "Feature",
  "properties": {
    "iso:country":"US",
    "sg:address":"5221 Keystone Ct",
    "sg:city":"Indianapolis",
    "sg:classifiers":[
        {
            "category":"Organizations",
            "subcategory":"Religious Organization",
            "type":"Services"
        }
    ],
    "sg:phone":"+1 317 205 9350",
    "sg:postcode":"46220",
    "sg:province":"IN",
    "sg:tags":[
        "church"
    ],
    "wof:name":"Bread Of Life Fellowship",
    "wof:placetype":"venue"
},
  "geometry": {"coordinates":[-86.123606,39.849034],"type":"Point"}
}