{
  "type": "Feature",
  "properties": {
    "addr:full":"213 E Maple St Jeffersonville IN 47130",
    "addr:housenumber":"213",
    "addr:postcode":"47130",
    "addr:street":"E Maple St",
    "iso:country":"US",
    "sg:address":"213 E Maple St",
    "sg:city":"Jeffersonville",
    "sg:classifiers":[
        {
            "category":"Social Services",
            "type":"Services"
        }
    ],
    "sg:phone":"+1 812 282 0063",
    "sg:postcode":"47130",
    "sg:province":"IN",
    "sg:tags":[
        "organization",
        "welfare"
    ],
    "wof:name":"Center For Lay Ministries Inc",
    "wof:placetype":"venue"
},
  "geometry": {"coordinates":[-85.738951,38.274225],"type":"Point"}
}