{
  "type": "Feature",
  "properties": {
    "iso:country":"US",
    "sg:address":"143 E Market St",
    "sg:city":"Indianapolis",
    "sg:classifiers":[
        {
            "category":"Professional",
            "subcategory":"Lawyer & Legal Services",
            "type":"Services"
        }
    ],
    "sg:phone":"+1 317 636 4722",
    "sg:postcode":"46204",
    "sg:province":"IN",
    "sg:tags":[
        "attorney"
    ],
    "wof:name":"Lorine B Regulus",
    "wof:placetype":"venue"
},
  "geometry": {"coordinates":[-86.154415,39.768437],"type":"Point"}
}