{
  "type": "Feature",
  "properties": {
    "iso:country":"US",
    "sg:address":"1710 E US Hwy 20",
    "sg:city":"Michigan City",
    "sg:classifiers":[
        {
            "category":"Sports & Exercise",
            "subcategory":"Gym",
            "type":"Entertainment"
        }
    ],
    "sg:phone":"+1 219 878 1715",
    "sg:postcode":"46360",
    "sg:province":"IN",
    "sg:tags":[
        "club",
        "health",
        "studio",
        "gymnasium"
    ],
    "wof:name":"Burnett Enterprises LLC",
    "wof:placetype":"venue"
},
  "geometry": {"coordinates":[-86.862473,41.687504],"type":"Point"}
}