{
  "type": "Feature",
  "properties": {
    "iso:country":"US",
    "sg:address":"705 E New York St",
    "sg:city":"Knox",
    "sg:classifiers":[
        {
            "category":"Manufacturing",
            "subcategory":"Motor Vehicles & Parts",
            "type":"Manufacturing & Wholesale Goods"
        }
    ],
    "sg:phone":"+1 574 772 2148",
    "sg:postcode":"46534",
    "sg:province":"IN",
    "sg:tags":[
        "truck"
    ],
    "wof:name":"Obrecht Trailer Mfg",
    "wof:placetype":"venue"
},
  "geometry": {"coordinates":[-86.61449500000001,41.293883],"type":"Point"}
}