{
  "type": "Feature",
  "properties": {
    "iso:country":"US",
    "sg:address":"9013 N Raider Rd",
    "sg:city":"Middletown",
    "sg:classifiers":[
        {
            "category":"Insurance",
            "subcategory":"Insurance Agent",
            "type":"Services"
        }
    ],
    "sg:phone":"+1 765 779 0662",
    "sg:postcode":"47356",
    "sg:province":"IN",
    "wof:name":"Tanya R Bennett",
    "wof:placetype":"venue"
},
  "geometry": {"coordinates":[-85.53353799999999,40.062721],"type":"Point"}
}