{
  "type": "Feature",
  "properties": {
    "iso:country":"US",
    "sg:address":"1243 E Poplar St",
    "sg:city":"Terre Haute",
    "sg:classifiers":[
        {
            "category":"Autos & Motor Vehicles",
            "subcategory":"Automobile Sales",
            "type":"Retail Goods"
        }
    ],
    "sg:phone":"+1 812 232 1532",
    "sg:postcode":"47807",
    "sg:province":"IN",
    "sg:tags":[
        "car",
        "used",
        "dealer"
    ],
    "wof:name":"Bob Nasser Used Cars",
    "wof:placetype":"venue"
},
  "geometry": {"coordinates":[-87.398327,39.462839],"type":"Point"}
}