{
  "type": "Feature",
  "properties": {
    "iso:country":"US",
    "sg:address":"1138 W Washington St",
    "sg:city":"South Bend",
    "sg:classifiers":[
        {
            "category":"Building & Trades",
            "subcategory":"Construction",
            "type":"Services"
        }
    ],
    "sg:phone":"+1 574 288 4764",
    "sg:postcode":"46601",
    "sg:province":"IN",
    "sg:tags":[
        "roofing",
        "contractor"
    ],
    "wof:name":"South Bend Roofing & Siding Co",
    "wof:placetype":"venue"
},
  "geometry": {"coordinates":[-86.267678,41.676133],"type":"Point"}
}