{
  "type": "Feature",
  "properties": {
    "iso:country":"US",
    "sg:address":"101 Roosevelt Dr",
    "sg:city":"Mt Vernon",
    "sg:classifiers":[
        {
            "category":"Organizations",
            "subcategory":"Religious Organization",
            "type":"Services"
        }
    ],
    "sg:phone":"+1 812 838 5447",
    "sg:postcode":"47620",
    "sg:province":"IN",
    "sg:tags":[
        "church"
    ],
    "wof:name":"Harvestime Temple",
    "wof:placetype":"venue"
},
  "geometry": {"coordinates":[-87.898823,37.948798],"type":"Point"}
}