{
  "type": "Feature",
  "properties": {
    "addr:full":"240 Waterfall Dr Elkhart IN 46516",
    "addr:housenumber":"240",
    "addr:postcode":"46516",
    "addr:street":"Waterfall Dr",
    "iso:country":"US",
    "sg:address":"240 Waterfall Dr",
    "sg:city":"Elkhart",
    "sg:classifiers":[
        {
            "category":"Professional",
            "subcategory":"Lawyer & Legal Services",
            "type":"Services"
        }
    ],
    "sg:phone":"+1 574 295 2280",
    "sg:postcode":"46516",
    "sg:province":"IN",
    "sg:tags":[
        "attorney"
    ],
    "wof:name":"Jack P Cittadine",
    "wof:placetype":"venue"
},
  "geometry": {"coordinates":[-85.967601,41.684718],"type":"Point"}
}