{
  "type": "Feature",
  "properties": {
    "iso:country":"US",
    "sg:address":"290 A St NE",
    "sg:city":"Linton",
    "sg:classifiers":[
        {
            "category":"Health Services",
            "subcategory":"Doctor",
            "type":"Services"
        }
    ],
    "sg:phone":"+1 812 847 2273",
    "sg:postcode":"47441",
    "sg:province":"IN",
    "sg:tags":[
        "dentist"
    ],
    "sg:website":"www.broshears.net",
    "wof:name":"Linton Dental Clinic",
    "wof:placetype":"venue"
},
  "geometry": {"coordinates":[-87.163296,39.035085],"type":"Point"}
}