{
  "type": "Feature",
  "properties": {
    "iso:country":"US",
    "sg:address":"136 E Market St",
    "sg:city":"Indianapolis",
    "sg:classifiers":[
        {
            "category":"Organizations",
            "subcategory":"Non-profit Organization",
            "type":"Services"
        }
    ],
    "sg:phone":"+1 317 634 1322",
    "sg:postcode":"46204",
    "sg:province":"IN",
    "wof:name":"Progress House Dev Office",
    "wof:placetype":"venue"
},
  "geometry": {"coordinates":[-86.154556,39.768516],"type":"Point"}
}