{
  "type": "Feature",
  "properties": {
    "iso:country":"US",
    "sg:address":"6625 N Sherman Dr",
    "sg:city":"Indianapolis",
    "sg:classifiers":[
        {
            "category":"Organizations",
            "subcategory":"Religious Organization",
            "type":"Services"
        }
    ],
    "sg:phone":"+1 317 291 5191",
    "sg:postcode":"46220",
    "sg:province":"IN",
    "wof:name":"Wm M Schwein Rev",
    "wof:placetype":"venue"
},
  "geometry": {"coordinates":[-86.103296,39.881226],"type":"Point"}
}