{
  "type": "Feature",
  "properties": {
    "addr:full":"818 Bruce St South Bend IN 46613",
    "addr:housenumber":"818",
    "addr:postcode":"46613",
    "addr:street":"Bruce St",
    "iso:country":"US",
    "sg:address":"818 Bruce St",
    "sg:city":"South Bend",
    "sg:classifiers":[
        {
            "category":"Organizations",
            "subcategory":"Religious Organization",
            "type":"Services"
        }
    ],
    "sg:phone":"+1 574 288 2829",
    "sg:postcode":"46613",
    "sg:province":"IN",
    "sg:tags":[
        "church"
    ],
    "wof:name":"Our Lady Of Hungary Parish",
    "wof:placetype":"venue"
},
  "geometry": {"coordinates":[-86.261441,41.654716],"type":"Point"}
}