{
  "type": "Feature",
  "properties": {
    "iso:country":"US",
    "sg:address":"1939 N Carver St",
    "sg:city":"Greensburg",
    "sg:classifiers":[
        {
            "category":"Real Estate",
            "subcategory":"Real Estate Operator",
            "type":"Services"
        }
    ],
    "sg:phone":"+1 812 662 8580",
    "sg:postcode":"47240",
    "sg:province":"IN",
    "sg:tags":[
        "apartment"
    ],
    "wof:name":"Ridgecrest Apartments",
    "wof:placetype":"venue"
},
  "geometry": {"coordinates":[-85.49164399999999,39.355294],"type":"Point"}
}