{
  "type": "Feature",
  "properties": {
    "addr:full":"1320 E Angelica St Rensselaer IN 47978",
    "addr:housenumber":"1320",
    "addr:postcode":"47978",
    "addr:street":"E Angelica St",
    "iso:country":"US",
    "sg:address":"1320 E Angelica St",
    "sg:city":"Rensselaer",
    "sg:classifiers":[
        {
            "category":"Social Services",
            "subcategory":"Child Care",
            "type":"Services"
        }
    ],
    "sg:phone":"+1 219 866 3282",
    "sg:postcode":"47978",
    "sg:province":"IN",
    "wof:name":"CDC Resources Inc",
    "wof:placetype":"venue"
},
  "geometry": {"coordinates":[-87.137023,40.939463],"type":"Point"}
}