{
  "type": "Feature",
  "properties": {
    "addr:full":"2270 Greenfield Ave Noblesville IN 46060",
    "addr:housenumber":"2270",
    "addr:postcode":"46060",
    "addr:street":"Greenfield Ave",
    "iso:country":"US",
    "sg:address":"2270 Greenfield Ave",
    "sg:city":"Noblesville",
    "sg:classifiers":[
        {
            "category":"Real Estate",
            "subcategory":"Real Estate Agent",
            "type":"Services"
        }
    ],
    "sg:phone":"+1 317 770 1122",
    "sg:postcode":"46060",
    "sg:province":"IN",
    "wof:name":"Carpenter GMAC Real Estate",
    "wof:placetype":"venue"
},
  "geometry": {"coordinates":[-85.99959,40.025651],"type":"Point"}
}