{
  "type": "Feature",
  "properties": {
    "iso:country":"US",
    "sg:address":"1004 W Indiana Ave",
    "sg:city":"Elkhart",
    "sg:classifiers":[
        {
            "category":"Building & Trades",
            "subcategory":"Construction",
            "type":"Services"
        }
    ],
    "sg:phone":"+1 574 522 8088",
    "sg:postcode":"46516",
    "sg:province":"IN",
    "sg:tags":[
        "home",
        "builder"
    ],
    "wof:name":"Garden Homes",
    "wof:placetype":"venue"
},
  "geometry": {"coordinates":[-85.983838,41.674196],"type":"Point"}
}