{
  "type": "Feature",
  "properties": {
    "iso:country":"US",
    "sg:address":"500 E Washington St",
    "sg:city":"Frankfort",
    "sg:classifiers":[
        {
            "category":"Organizations",
            "subcategory":"Non-profit Organization",
            "type":"Services"
        }
    ],
    "sg:phone":"+1 765 659 2444",
    "sg:postcode":"46041",
    "sg:province":"IN",
    "sg:tags":[
        "alternative",
        "abortion"
    ],
    "wof:name":"Crisis Pregnancy Ctr Inc",
    "wof:placetype":"venue"
},
  "geometry": {"coordinates":[-86.507129,40.281625],"type":"Point"}
}