{
  "type": "Feature",
  "properties": {
    "iso:country":"US",
    "sg:address":"125 E Broadway St",
    "sg:city":"Shelbyville",
    "sg:classifiers":[
        {
            "category":"Organizations",
            "subcategory":"Religious Organization",
            "type":"Services"
        }
    ],
    "sg:phone":"+1 317 398 6377",
    "sg:postcode":"46176",
    "sg:province":"IN",
    "wof:name":"St Joseph Catholic Church",
    "wof:placetype":"venue"
},
  "geometry": {"coordinates":[-85.77444199999999,39.522854],"type":"Point"}
}