{
  "type": "Feature",
  "properties": {
    "iso:country":"US",
    "sg:address":"124 W 4th St",
    "sg:city":"Michigan City",
    "sg:classifiers":[
        {
            "category":"Bars & Pubs",
            "type":"Food & Drink"
        }
    ],
    "sg:phone":"+1 219 879 9956",
    "sg:postcode":"46360",
    "sg:province":"IN",
    "wof:name":"Ritz KLUB",
    "wof:placetype":"venue"
},
  "geometry": {"coordinates":[-86.902716,41.718195],"type":"Point"}
}