{
  "type": "Feature",
  "properties": {
    "iso:country":"US",
    "sg:address":"1130 Industrial Rd",
    "sg:city":"Columbus",
    "sg:classifiers":[
        {
            "category":"Wholesale",
            "subcategory":"Auto Parts",
            "type":"Manufacturing & Wholesale Goods"
        }
    ],
    "sg:phone":"+1 812 372 9085",
    "sg:postcode":"47203",
    "sg:province":"IN",
    "sg:tags":[
        "equipment",
        "towing"
    ],
    "wof:name":"Bishop Inc Towing & Recovery",
    "wof:placetype":"venue"
},
  "geometry": {"coordinates":[-85.93955200000001,39.24911],"type":"Point"}
}