{
  "type": "Feature",
  "properties": {
    "addr:full":"8173 W 300 N Pennville IN 47369",
    "addr:housenumber":"8173",
    "addr:postcode":"47369",
    "addr:street":"W 300 N",
    "iso:country":"US",
    "sg:address":"8173 W 300 N",
    "sg:city":"Pennville",
    "sg:classifiers":[
        {
            "category":"Building & Trades",
            "subcategory":"Construction",
            "type":"Services"
        }
    ],
    "sg:phone":"+1 260 731 3921",
    "sg:postcode":"47369",
    "sg:province":"IN",
    "sg:tags":[
        "family",
        "contractor",
        "representative",
        "for",
        "mfg"
    ],
    "wof:name":"Dale Construction",
    "wof:placetype":"venue"
},
  "geometry": {"coordinates":[-85.138425,40.482181],"type":"Point"}
}