{
  "type": "Feature",
  "properties": {
    "iso:country":"US",
    "sg:address":"6049 Lakeside Blvd",
    "sg:city":"Indianapolis",
    "sg:classifiers":[
        {
            "category":"Banks & Credit Unions",
            "subcategory":"Financial Services",
            "type":"Services"
        }
    ],
    "sg:phone":"+1 317 280 2052",
    "sg:postcode":"46278",
    "sg:province":"IN",
    "sg:tags":[
        "investor"
    ],
    "wof:name":"Cal East Ind Investors",
    "wof:placetype":"venue"
},
  "geometry": {"coordinates":[-86.266162,39.876692],"type":"Point"}
}