{
  "type": "Feature",
  "properties": {
    "iso:country":"US",
    "sg:address":"116 Broadway St",
    "sg:city":"Brook",
    "sg:classifiers":[
        {
            "category":"Retail",
            "subcategory":"Auto Repair",
            "type":"Services"
        }
    ],
    "sg:phone":"+1 219 275 2361",
    "sg:postcode":"47922",
    "sg:province":"IN",
    "sg:tags":[
        "repairing",
        "automobile"
    ],
    "wof:name":"Brook Farmer Supply",
    "wof:placetype":"venue"
},
  "geometry": {"coordinates":[-87.364428,40.864569],"type":"Point"}
}