{
  "type": "Feature",
  "properties": {
    "iso:country":"US",
    "sg:address":"1616 Garfield St",
    "sg:city":"Wabash",
    "sg:classifiers":[
        {
            "category":"Retail",
            "subcategory":"Auto Repair",
            "type":"Services"
        }
    ],
    "sg:phone":"+1 260 563 8655",
    "sg:postcode":"46992",
    "sg:province":"IN",
    "sg:tags":[
        "body",
        "automobile",
        "painting"
    ],
    "wof:name":"Wabash Body Shop",
    "wof:placetype":"venue"
},
  "geometry": {"coordinates":[-85.846977,40.801837],"type":"Point"}
}