{
  "type": "Feature",
  "properties": {
    "addr:full":"5555 S US Hwy 41 Terre Haute IN 47802",
    "addr:housenumber":"5555",
    "addr:postcode":"47802",
    "addr:street":"S Us Hwy 41",
    "iso:country":"US",
    "sg:address":"5555 S US Hwy 41",
    "sg:city":"Terre Haute",
    "sg:classifiers":[
        {
            "category":"Restaurant",
            "type":"Food & Drink"
        }
    ],
    "sg:phone":"+1 812 299 0031",
    "sg:postcode":"47802",
    "sg:province":"IN",
    "wof:name":"Mc Donald's",
    "wof:placetype":"venue"
},
  "geometry": {"coordinates":[-87.403234,39.401713],"type":"Point"}
}