{
  "type": "Feature",
  "properties": {
    "iso:country":"US",
    "sg:address":"33 W Market St",
    "sg:city":"Huntington",
    "sg:classifiers":[
        {
            "category":"Personal",
            "subcategory":"Beauty Salon",
            "type":"Services"
        }
    ],
    "sg:phone":"+1 260 358 9123",
    "sg:postcode":"46750",
    "sg:province":"IN",
    "sg:tags":[
        "shop"
    ],
    "wof:name":"Classicut-Natural Nails",
    "wof:placetype":"venue"
},
  "geometry": {"coordinates":[-85.495012,40.881736],"type":"Point"}
}