{
  "type": "Feature",
  "properties": {
    "iso:country":"US",
    "sg:address":"8143 E Co Rd 600 S",
    "sg:city":"Coatesville",
    "sg:classifiers":[
        {
            "category":"Professional",
            "subcategory":"Engineering",
            "type":"Services"
        }
    ],
    "sg:phone":"+1 765 526 6330",
    "sg:postcode":"46121",
    "sg:province":"IN",
    "sg:tags":[
        "engineer"
    ],
    "wof:name":"Jasper Manufacturing",
    "wof:placetype":"venue"
},
  "geometry": {"coordinates":[-86.703476,39.572224],"type":"Point"}
}