{
  "type": "Feature",
  "properties": {
    "iso:country":"US",
    "sg:address":"6300 E 116th St",
    "sg:city":"Fishers",
    "sg:classifiers":[
        {
            "category":"Real Estate",
            "subcategory":"Real Estate Agent",
            "type":"Services"
        }
    ],
    "sg:phone":"+1 317 577 9885",
    "sg:postcode":"46038",
    "sg:province":"IN",
    "wof:name":"Seeley Appraisal Service",
    "wof:placetype":"venue"
},
  "geometry": {"coordinates":[-86.057817,39.956569],"type":"Point"}
}