{
  "type": "Feature",
  "properties": {
    "iso:country":"US",
    "sg:address":"275 Grove Rd",
    "sg:city":"Richmond",
    "sg:classifiers":[
        {
            "category":"Organizations",
            "subcategory":"Non-profit Organization",
            "type":"Services"
        }
    ],
    "sg:phone":"+1 765 935 3000",
    "sg:postcode":"47330",
    "sg:province":"IN",
    "sg:tags":[
        "info",
        "addiction",
        "abuse",
        "treatment",
        "drug"
    ],
    "wof:name":"Hope House Addiction Recovery",
    "wof:placetype":"venue"
},
  "geometry": {"coordinates":[-85.014659,39.836453],"type":"Point"}
}