{
  "type": "Feature",
  "properties": {
    "iso:country":"US",
    "sg:address":"7107 Courthouse Dr",
    "sg:city":"Indianapolis",
    "sg:classifiers":[
        {
            "category":"Professional",
            "subcategory":"Computer Services",
            "type":"Services"
        }
    ],
    "sg:phone":"+1 317 546 4830",
    "sg:postcode":"46226",
    "sg:province":"IN",
    "sg:tags":[
        "consultant",
        "designer"
    ],
    "wof:name":"Af-AM Consulting Inc",
    "wof:placetype":"venue"
},
  "geometry": {"coordinates":[-86.044113,39.857916],"type":"Point"}
}