{
  "type": "Feature",
  "properties": {
    "iso:country":"US",
    "sg:address":"6732 E State Blvd",
    "sg:city":"Fort Wayne",
    "sg:classifiers":[
        {
            "category":"Building & Trades",
            "subcategory":"Construction",
            "type":"Services"
        }
    ],
    "sg:phone":"+1 260 422 5600",
    "sg:postcode":"46815",
    "sg:province":"IN",
    "sg:tags":[
        "painter"
    ],
    "wof:name":"Bockman Co",
    "wof:placetype":"venue"
},
  "geometry": {"coordinates":[-85.054862,41.103767],"type":"Point"}
}