{
  "type": "Feature",
  "properties": {
    "iso:country":"US",
    "sg:address":"1500 Washington St",
    "sg:city":"New Castle",
    "sg:classifiers":[
        {
            "category":"Health Services",
            "subcategory":"Optometrist",
            "type":"Services"
        }
    ],
    "sg:phone":"+1 765 529 9364",
    "sg:postcode":"47362",
    "sg:province":"IN",
    "wof:name":"Bailey Optometry",
    "wof:placetype":"venue"
},
  "geometry": {"coordinates":[-85.366196,39.939114],"type":"Point"}
}