{
  "type": "Feature",
  "properties": {
    "iso:country":"US",
    "sg:address":"7900 US Hwy 36",
    "sg:city":"Avon",
    "sg:classifiers":[
        {
            "category":"Shopping",
            "subcategory":"Computers & Home Electronics",
            "type":"Retail Goods"
        }
    ],
    "sg:phone":"+1 317 272 0170",
    "sg:postcode":"46123",
    "sg:province":"IN",
    "sg:tags":[
        "equipment",
        "electronic",
        "supply"
    ],
    "wof:name":"Radio Shack",
    "wof:placetype":"venue"
},
  "geometry": {"coordinates":[-86.39516500000001,39.762977],"type":"Point"}
}