{
  "type": "Feature",
  "properties": {
    "addr:full":"2447 S Western Ave Marion IN 46953",
    "addr:housenumber":"2447",
    "addr:postcode":"46953",
    "addr:street":"S Western Ave",
    "iso:country":"US",
    "sg:address":"2447 S Western Ave",
    "sg:city":"Marion",
    "sg:classifiers":[
        {
            "category":"Autos & Motor Vehicles",
            "subcategory":"Automobile Sales",
            "type":"Retail Goods"
        }
    ],
    "sg:phone":"+1 765 664 6606",
    "sg:postcode":"46953",
    "sg:province":"IN",
    "sg:tags":[
        "car",
        "dealer"
    ],
    "wof:name":"Courtesy Motors",
    "wof:placetype":"venue"
},
  "geometry": {"coordinates":[-85.673633,40.540191],"type":"Point"}
}