{
  "type": "Feature",
  "properties": {
    "iso:country":"US",
    "sg:address":"80 W 5th St",
    "sg:city":"Peru",
    "sg:classifiers":[
        {
            "category":"Education",
            "subcategory":"School",
            "type":"Public Place"
        }
    ],
    "sg:phone":"+1 765 473 5669",
    "sg:postcode":"46970",
    "sg:province":"IN",
    "wof:name":"St Charles Catholic School",
    "wof:placetype":"venue"
},
  "geometry": {"coordinates":[-86.07213400000001,40.753549],"type":"Point"}
}