{
  "type": "Feature",
  "properties": {
    "addr:full":"28591 Old US Hwy 33 Elkhart IN 46516",
    "addr:housenumber":"28591",
    "addr:postcode":"46516",
    "addr:street":"Old Us Hwy 33",
    "iso:country":"US",
    "sg:address":"28591 Old US Hwy 33",
    "sg:city":"Elkhart",
    "sg:classifiers":[
        {
            "category":"Retail",
            "subcategory":"Repair Shop",
            "type":"Services"
        }
    ],
    "sg:phone":"+1 574 294 3749",
    "sg:postcode":"46516",
    "sg:province":"IN",
    "sg:tags":[
        "refinishing",
        "furniture"
    ],
    "wof:name":"James Madison Furniture Strip",
    "wof:placetype":"venue"
},
  "geometry": {"coordinates":[-86.008368,41.669408],"type":"Point"}
}