{
  "type": "Feature",
  "properties": {
    "iso:country":"US",
    "sg:address":"4635 W Richland Plz",
    "sg:city":"Bloomington",
    "sg:classifiers":[
        {
            "category":"Food & Beverages",
            "subcategory":"Specialty",
            "type":"Retail Goods"
        }
    ],
    "sg:phone":"+1 812 876 3566",
    "sg:postcode":"47404",
    "sg:province":"IN",
    "sg:tags":[
        "health",
        "diet"
    ],
    "wof:name":"Molly's Foods Unique",
    "wof:placetype":"venue"
},
  "geometry": {"coordinates":[-86.593157,39.214652],"type":"Point"}
}