{
  "type": "Feature",
  "properties": {
    "iso:country":"US",
    "sg:address":"901 14th St",
    "sg:city":"Bedford",
    "sg:classifiers":[
        {
            "category":"Retail",
            "subcategory":"Auto Repair",
            "type":"Services"
        }
    ],
    "sg:phone":"+1 812 279 9115",
    "sg:postcode":"47421",
    "sg:province":"IN",
    "sg:tags":[
        "repairing",
        "automobile"
    ],
    "wof:name":"Jed's Auto Svc",
    "wof:placetype":"venue"
},
  "geometry": {"coordinates":[-86.484172,38.863321],"type":"Point"}
}