{
  "type": "Feature",
  "properties": {
    "iso:country":"US",
    "sg:address":"10109 Rain Drop Cir",
    "sg:city":"Granger",
    "sg:classifiers":[
        {
            "category":"Professional",
            "subcategory":"Art Services",
            "type":"Services"
        }
    ],
    "sg:phone":"+1 574 674 6521",
    "sg:postcode":"46530",
    "sg:province":"IN",
    "sg:tags":[
        "commercial",
        "design"
    ],
    "wof:name":"Duckworth Illstrtns Grphc Dsgn",
    "wof:placetype":"venue"
},
  "geometry": {"coordinates":[-86.064171,41.743314],"type":"Point"}
}