{
  "type": "Feature",
  "properties": {
    "iso:country":"US",
    "sg:address":"7427 E 34th St",
    "sg:city":"Indianapolis",
    "sg:classifiers":[
        {
            "category":"Organizations",
            "subcategory":"Religious Organization",
            "type":"Services"
        }
    ],
    "sg:phone":"+1 317 545 4509",
    "sg:postcode":"46226",
    "sg:province":"IN",
    "sg:tags":[
        "churches-baptist",
        "church"
    ],
    "sg:website":"http://www.shadelandbaptistchurch.com",
    "wof:name":"Shadeland Baptist Church",
    "wof:placetype":"venue"
},
  "geometry": {"coordinates":[-86.037023,39.818411],"type":"Point"}
}