{
  "type": "Feature",
  "properties": {
    "addr:full":"6901 E 10th St Indianapolis IN 46219",
    "addr:housenumber":"6901",
    "addr:postcode":"46219",
    "addr:street":"E 10Th St",
    "iso:country":"US",
    "sg:address":"6901 E 10th St",
    "sg:city":"Indianapolis",
    "sg:classifiers":[
        {
            "category":"Professional",
            "subcategory":"Detective & Security Services",
            "type":"Services"
        }
    ],
    "sg:phone":"+1 317 351 4238",
    "sg:postcode":"46219",
    "sg:province":"IN",
    "sg:tags":[
        "guard",
        "patrol"
    ],
    "wof:name":"Peace Of Mind Security Spec",
    "wof:placetype":"venue"
},
  "geometry": {"coordinates":[-86.045407,39.781756],"type":"Point"}
}