{
  "type": "Feature",
  "properties": {
    "iso:country":"US",
    "sg:address":"6320 Guilford Ave",
    "sg:city":"Indianapolis",
    "sg:classifiers":[
        {
            "category":"Building & Trades",
            "subcategory":"Equipment Rental",
            "type":"Services"
        }
    ],
    "sg:phone":"+1 317 253 4415",
    "sg:postcode":"46220",
    "sg:province":"IN",
    "sg:tags":[
        "leasing"
    ],
    "wof:name":"Quality Leasing Co",
    "wof:placetype":"venue"
},
  "geometry": {"coordinates":[-86.142993,39.870042],"type":"Point"}
}