{
  "type": "Feature",
  "properties": {
    "addr:full":"1720 Holsapple Rd Richmond IN 47374",
    "addr:housenumber":"1720",
    "addr:postcode":"47374",
    "addr:street":"Holsapple Rd",
    "iso:country":"US",
    "sg:address":"1720 Holsapple Rd",
    "sg:city":"Richmond",
    "sg:classifiers":[
        {
            "category":"Organizations",
            "subcategory":"Religious Organization",
            "type":"Services"
        }
    ],
    "sg:phone":"+1 765 935 6558",
    "sg:postcode":"47374",
    "sg:province":"IN",
    "wof:name":"Richmond Four Square",
    "wof:placetype":"venue"
},
  "geometry": {"coordinates":[-84.926253,39.860942],"type":"Point"}
}