{
  "type": "Feature",
  "properties": {
    "addr:full":"603 E Washington St Indianapolis IN 46204",
    "addr:housenumber":"603",
    "addr:postcode":"46204",
    "addr:street":"E Washington St",
    "iso:country":"US",
    "sg:address":"603 E Washington St",
    "sg:city":"Indianapolis",
    "sg:classifiers":[
        {
            "category":"Organizations",
            "subcategory":"Community Association",
            "type":"Services"
        }
    ],
    "sg:phone":"+1 317 396 2700",
    "sg:postcode":"46204",
    "sg:province":"IN",
    "wof:name":"Indiana Youth Institute",
    "wof:placetype":"venue"
},
  "geometry": {"coordinates":[-86.145984,39.766786],"type":"Point"}
}