{
  "type": "Feature",
  "properties": {
    "iso:country":"US",
    "sg:address":"900 S Sawmill Rd",
    "sg:city":"Whiteland",
    "sg:classifiers":[
        {
            "category":"Education",
            "subcategory":"School",
            "type":"Public Place"
        }
    ],
    "sg:phone":"+1 317 535 7536",
    "sg:postcode":"46184",
    "sg:province":"IN",
    "wof:name":"Break-O-Day Elementary School",
    "wof:placetype":"venue"
},
  "geometry": {"coordinates":[-86.101544,39.536045],"type":"Point"}
}