{
  "type": "Feature",
  "properties": {
    "iso:country":"US",
    "sg:address":"3077 Broadway",
    "sg:city":"Gary",
    "sg:classifiers":[
        {
            "category":"Professional",
            "type":"Services"
        }
    ],
    "sg:phone":"+1 219 884 0306",
    "sg:postcode":"46409",
    "sg:province":"IN",
    "sg:tags":[
        "establishment"
    ],
    "wof:name":"Anish Chittalakatta",
    "wof:placetype":"venue"
},
  "geometry": {"coordinates":[-87.336596,41.562424],"type":"Point"}
}