{
  "type": "Feature",
  "properties": {
    "iso:country":"US",
    "sg:address":"339 E North St",
    "sg:city":"Winchester",
    "sg:classifiers":[
        {
            "category":"Shopping",
            "subcategory":"Computers & Home Electronics",
            "type":"Retail Goods"
        }
    ],
    "sg:phone":"+1 765 584 0409",
    "sg:postcode":"47394",
    "sg:province":"IN",
    "sg:tags":[
        "repair"
    ],
    "wof:name":"Kaufman Electronics",
    "wof:placetype":"venue"
},
  "geometry": {"coordinates":[-84.976341,40.173836],"type":"Point"}
}