{
  "type": "Feature",
  "properties": {
    "iso:country":"US",
    "sg:address":"1240 S Grandstaff Dr",
    "sg:city":"Auburn",
    "sg:classifiers":[
        {
            "category":"Government",
            "subcategory":"Office",
            "type":"Public Place"
        }
    ],
    "sg:phone":"+1 260 925 0494",
    "sg:postcode":"46706",
    "sg:province":"IN",
    "sg:tags":[
        "federal",
        "human"
    ],
    "wof:name":"US Social Security Adm",
    "wof:placetype":"venue"
},
  "geometry": {"coordinates":[-85.071332,41.357322],"type":"Point"}
}