{
  "type": "Feature",
  "properties": {
    "iso:country":"US",
    "sg:address":"1 Hamilton County Sq",
    "sg:city":"Noblesville",
    "sg:classifiers":[
        {
            "category":"Government",
            "subcategory":"Office",
            "type":"Public Place"
        }
    ],
    "sg:phone":"+1 317 776 8429",
    "sg:postcode":"46060",
    "sg:province":"IN",
    "sg:tags":[
        "govt",
        "agency"
    ],
    "wof:name":"Hamilton County Counsel On ALC",
    "wof:placetype":"venue"
},
  "geometry": {"coordinates":[-86.014707,40.046538],"type":"Point"}
}