{
  "type": "Feature",
  "properties": {
    "iso:country":"US",
    "sg:address":"958 W Water St",
    "sg:city":"Borden",
    "sg:classifiers":[
        {
            "category":"Retail",
            "subcategory":"Repair Shop",
            "type":"Services"
        }
    ],
    "sg:phone":"+1 812 967 3071",
    "sg:postcode":"47106",
    "sg:province":"IN",
    "sg:tags":[
        "equipment",
        "electronic",
        "supply"
    ],
    "wof:name":"Industrial Electronics",
    "wof:placetype":"venue"
},
  "geometry": {"coordinates":[-85.964415,38.473196],"type":"Point"}
}