{
  "type": "Feature",
  "properties": {
    "iso:country":"US",
    "sg:address":"6225 Constitution Dr",
    "sg:city":"Fort Wayne",
    "sg:classifiers":[
        {
            "category":"Shopping",
            "type":"Retail Goods"
        }
    ],
    "sg:phone":"+1 260 432 2252",
    "sg:postcode":"46804",
    "sg:province":"IN",
    "sg:tags":[
        "art",
        "gallery",
        "dealer"
    ],
    "wof:name":"Sharon Eisbart Corporate Art",
    "wof:placetype":"venue"
},
  "geometry": {"coordinates":[-85.223565,41.067863],"type":"Point"}
}