{
  "type": "Feature",
  "properties": {
    "iso:country":"US",
    "sg:address":"4201 S Sherman Dr",
    "sg:city":"Indianapolis",
    "sg:classifiers":[
        {
            "category":"Real Estate",
            "subcategory":"Real Estate Operator",
            "type":"Services"
        }
    ],
    "sg:phone":"+1 317 784 2291",
    "sg:postcode":"46237",
    "sg:province":"IN",
    "sg:tags":[
        "building",
        "apartment"
    ],
    "wof:name":"Timbers of Indianapolis",
    "wof:placetype":"venue"
},
  "geometry": {"coordinates":[-86.103946,39.705884],"type":"Point"}
}