{
  "type": "Feature",
  "properties": {
    "iso:country":"US",
    "sg:address":"6351 S East St",
    "sg:city":"Indianapolis",
    "sg:classifiers":[
        {
            "category":"Health Services",
            "subcategory":"Doctor",
            "type":"Services"
        }
    ],
    "sg:phone":"+1 317 783 3390",
    "sg:postcode":"46227",
    "sg:province":"IN",
    "sg:tags":[
        "dentist"
    ],
    "wof:name":"John F Jansen DDS",
    "wof:placetype":"venue"
},
  "geometry": {"coordinates":[-86.149157,39.672489],"type":"Point"}
}