{
  "type": "Feature",
  "properties": {
    "iso:country":"US",
    "sg:address":"117 Top Flight Rd",
    "sg:city":"Michigan City",
    "sg:classifiers":[
        {
            "category":"Building & Trades",
            "subcategory":"Construction",
            "type":"Services"
        }
    ],
    "sg:phone":"+1 219 879 2770",
    "sg:postcode":"46360",
    "sg:province":"IN",
    "sg:tags":[
        "house"
    ],
    "wof:name":"Michiana Home Improvement",
    "wof:placetype":"venue"
},
  "geometry": {"coordinates":[-86.826428,41.74284],"type":"Point"}
}