{
  "type": "Feature",
  "properties": {
    "iso:country":"US",
    "sg:address":"901 E 2nd St",
    "sg:city":"Veedersburg",
    "sg:classifiers":[
        {
            "category":"Local Transit",
            "type":"Transportation"
        }
    ],
    "sg:phone":"+1 765 294 2522",
    "sg:postcode":"47987",
    "sg:province":"IN",
    "sg:tags":[
        "ambulance"
    ],
    "wof:name":"Fountain County Ambulance Svc",
    "wof:placetype":"venue"
},
  "geometry": {"coordinates":[-87.249881,40.113124],"type":"Point"}
}