{
  "type": "Feature",
  "properties": {
    "iso:country":"US",
    "sg:address":"3903 State Rd 9",
    "sg:city":"Albion",
    "sg:classifiers":[
        {
            "category":"Manufacturing",
            "subcategory":"Tools & Machinery",
            "type":"Manufacturing & Wholesale Goods"
        }
    ],
    "sg:phone":"+1 260 636 7588",
    "sg:postcode":"46701",
    "sg:province":"IN",
    "sg:tags":[
        "industry",
        "special"
    ],
    "sg:website":"www.dialx.com",
    "wof:name":"Dial X Inc",
    "wof:placetype":"venue"
},
  "geometry": {"coordinates":[-85.424048,41.29527],"type":"Point"}
}