{
  "type": "Feature",
  "properties": {
    "iso:country":"US",
    "sg:address":"26 S 3rd St",
    "sg:city":"Logansport",
    "sg:classifiers":[
        {
            "category":"Bars & Pubs",
            "type":"Food & Drink"
        }
    ],
    "sg:phone":"+1 574 722 9726",
    "sg:postcode":"46947",
    "sg:province":"IN",
    "wof:name":"Steve's Place",
    "wof:placetype":"venue"
},
  "geometry": {"coordinates":[-86.36767500000001,40.755153],"type":"Point"}
}