{
  "type": "Feature",
  "properties": {
    "iso:country":"US",
    "sg:address":"3307 45th St",
    "sg:city":"Highland",
    "sg:classifiers":[
        {
            "category":"Health Services",
            "subcategory":"Doctor",
            "type":"Services"
        }
    ],
    "sg:phone":"+1 219 922 1622",
    "sg:postcode":"46322",
    "sg:province":"IN",
    "sg:tags":[
        "dentist"
    ],
    "wof:name":"Highland Dental Care",
    "wof:placetype":"venue"
},
  "geometry": {"coordinates":[-87.449091,41.537492],"type":"Point"}
}