{
  "type": "Feature",
  "properties": {
    "iso:country":"US",
    "sg:address":"3781 S 300 W",
    "sg:city":"Liberty Center",
    "sg:classifiers":[
        {
            "category":"Real Estate",
            "subcategory":"Real Estate Operator",
            "type":"Services"
        }
    ],
    "sg:phone":"+1 260 694 6103",
    "sg:postcode":"46766",
    "sg:province":"IN",
    "sg:tags":[
        "property",
        "lessor"
    ],
    "wof:name":"William Poulson",
    "wof:placetype":"venue"
},
  "geometry": {"coordinates":[-85.278831,40.686791],"type":"Point"}
}