{
  "type": "Feature",
  "properties": {
    "iso:country":"US",
    "sg:address":"8887 S Addison Ave",
    "sg:city":"Knightstown",
    "sg:classifiers":[
        {
            "category":"Shopping",
            "subcategory":"Florist",
            "type":"Retail Goods"
        }
    ],
    "sg:phone":"+1 765 345 2036",
    "sg:postcode":"46148",
    "sg:province":"IN",
    "wof:name":"Hilltop Florist",
    "wof:placetype":"venue"
},
  "geometry": {"coordinates":[-85.480372,39.805036],"type":"Point"}
}