{
  "type": "Feature",
  "properties": {
    "iso:country":"US",
    "sg:address":"3740 Lafayette Rd",
    "sg:city":"Indianapolis",
    "sg:classifiers":[
        {
            "category":"Retail",
            "subcategory":"Laundry & Dry Cleaning",
            "type":"Services"
        }
    ],
    "sg:phone":"+1 317 297 0584",
    "sg:postcode":"46222",
    "sg:province":"IN",
    "sg:tags":[
        "cleaners"
    ],
    "wof:name":"Henry's One Hour Cleaner",
    "wof:placetype":"venue"
},
  "geometry": {"coordinates":[-86.227981,39.816852],"type":"Point"}
}