{
  "type": "Feature",
  "properties": {
    "addr:full":"1735 W State Rd 28 Frankfort IN 46041",
    "addr:housenumber":"1735;28",
    "addr:postcode":"46041",
    "addr:street":"W State Rd",
    "iso:country":"US",
    "sg:address":"1735 W State Rd 28",
    "sg:city":"Frankfort",
    "sg:classifiers":[
        {
            "category":"Home & Garden",
            "subcategory":"Building Materials",
            "type":"Retail Goods"
        }
    ],
    "sg:phone":"+1 765 654 4923",
    "sg:postcode":"46041",
    "sg:province":"IN",
    "sg:tags":[
        "door"
    ],
    "wof:name":"Door Pro",
    "wof:placetype":"venue"
},
  "geometry": {"coordinates":[-86.53227800000001,40.278922],"type":"Point"}
}