{
  "type": "Feature",
  "properties": {
    "addr:full":"114 S Earl Ave Lafayette IN 47904",
    "addr:housenumber":"114",
    "addr:postcode":"47904",
    "addr:street":"S Earl Ave",
    "iso:country":"US",
    "sg:address":"114 S Earl Ave",
    "sg:city":"Lafayette",
    "sg:classifiers":[
        {
            "category":"Insurance",
            "subcategory":"Insurance Agent",
            "type":"Services"
        }
    ],
    "sg:phone":"+1 765 447 6633",
    "sg:postcode":"47904",
    "sg:province":"IN",
    "wof:name":"Farmers Insurance Group",
    "wof:placetype":"venue"
},
  "geometry": {"coordinates":[-86.86075700000001,40.414765],"type":"Point"}
}