{
  "type": "Feature",
  "properties": {
    "iso:country":"US",
    "sg:address":"205 N Tillotson Ave",
    "sg:city":"Muncie",
    "sg:classifiers":[
        {
            "category":"Shopping",
            "subcategory":"Pharmacy",
            "type":"Retail Goods"
        }
    ],
    "sg:phone":"+1 765 213 2200",
    "sg:postcode":"47304",
    "sg:province":"IN",
    "wof:name":"Kenmore Health Care Pharmacy",
    "wof:placetype":"venue"
},
  "geometry": {"coordinates":[-85.419225,40.194715],"type":"Point"}
}