{
  "type": "Feature",
  "properties": {
    "addr:full":"10 Plaza Dr Washington IN 47501",
    "addr:housenumber":"10",
    "addr:postcode":"47501",
    "addr:street":"Plaza Dr",
    "iso:country":"US",
    "sg:address":"10 Plaza Dr",
    "sg:city":"Washington",
    "sg:classifiers":[
        {
            "category":"Personal",
            "subcategory":"Barber",
            "type":"Services"
        }
    ],
    "sg:phone":"+1 812 254 9969",
    "sg:postcode":"47501",
    "sg:province":"IN",
    "sg:tags":[
        "shop"
    ],
    "wof:name":"Ron's Barber Shop",
    "wof:placetype":"venue"
},
  "geometry": {"coordinates":[-87.184217,38.654412],"type":"Point"}
}