{
  "type": "Feature",
  "properties": {
    "iso:country":"US",
    "sg:address":"4133 New Haven Ave",
    "sg:city":"Fort Wayne",
    "sg:classifiers":[
        {
            "category":"Building & Trades",
            "subcategory":"Construction",
            "type":"Services"
        }
    ],
    "sg:phone":"+1 260 422 1609",
    "sg:postcode":"46803",
    "sg:province":"IN",
    "sg:tags":[
        "excavating",
        "contractor"
    ],
    "wof:name":"O'Neal Excavating & Constr",
    "wof:placetype":"venue"
},
  "geometry": {"coordinates":[-85.086702,41.068933],"type":"Point"}
}