{
  "type": "Feature",
  "properties": {
    "iso:country":"US",
    "sg:address":"2720 Central Ave",
    "sg:city":"Anderson",
    "sg:classifiers":[
        {
            "category":"Building & Trades",
            "subcategory":"Cleaning & Sanitation",
            "type":"Services"
        }
    ],
    "sg:phone":"+1 765 641 7423",
    "sg:postcode":"46016",
    "sg:province":"IN",
    "sg:tags":[
        "janitor"
    ],
    "wof:name":"Jones's Cleaning Svc",
    "wof:placetype":"venue"
},
  "geometry": {"coordinates":[-85.676754,40.087439],"type":"Point"}
}