{
  "type": "Feature",
  "properties": {
    "iso:country":"US",
    "sg:address":"3700 E Lincoln Hwy",
    "sg:city":"Merrillville",
    "sg:classifiers":[
        {
            "category":"Professional",
            "subcategory":"Lawyer & Legal Services",
            "type":"Services"
        }
    ],
    "sg:phone":"+1 219 942 3710",
    "sg:postcode":"46410",
    "sg:province":"IN",
    "sg:tags":[
        "attorney"
    ],
    "wof:name":"Herbert Lasser & Assoc",
    "wof:placetype":"venue"
},
  "geometry": {"coordinates":[-87.293891,41.471159],"type":"Point"}
}