{
  "type": "Feature",
  "properties": {
    "iso:country":"US",
    "sg:address":"1537 W Harlan Dr",
    "sg:city":"Terre Haute",
    "sg:classifiers":[
        {
            "category":"Manufacturing",
            "subcategory":"Tools & Machinery",
            "type":"Manufacturing & Wholesale Goods"
        }
    ],
    "sg:phone":"+1 812 299 5255",
    "sg:postcode":"47802",
    "sg:province":"IN",
    "sg:tags":[
        "machine",
        "shop"
    ],
    "wof:name":"Honey Creek Machine LLC",
    "wof:placetype":"venue"
},
  "geometry": {"coordinates":[-87.439591,39.346925],"type":"Point"}
}