{
  "type": "Feature",
  "properties": {
    "iso:country":"US",
    "sg:address":"18 W 8th St",
    "sg:city":"Anderson",
    "sg:classifiers":[
        {
            "category":"Organizations",
            "subcategory":"Political Organization",
            "type":"Services"
        }
    ],
    "sg:phone":"+1 765 642 0840",
    "sg:postcode":"46016",
    "sg:province":"IN",
    "wof:name":"Madison Cnty Demcrt Cntrl Comm",
    "wof:placetype":"venue"
},
  "geometry": {"coordinates":[-85.680378,40.107964],"type":"Point"}
}