{
  "type": "Feature",
  "properties": {
    "iso:country":"US",
    "sg:address":"5025 New Haven Ave",
    "sg:city":"Fort Wayne",
    "sg:classifiers":[
        {
            "category":"Professional",
            "subcategory":"Business Services",
            "type":"Services"
        }
    ],
    "sg:phone":"+1 260 493 7171",
    "sg:postcode":"46803",
    "sg:province":"IN",
    "wof:name":"Leads Group",
    "wof:placetype":"venue"
},
  "geometry": {"coordinates":[-85.076321,41.069057],"type":"Point"}
}