{
  "type": "Feature",
  "properties": {
    "iso:country":"US",
    "sg:address":"904 E Troy Ave",
    "sg:city":"Indianapolis",
    "sg:classifiers":[
        {
            "category":"Shopping",
            "subcategory":"Hobbies, Toys, & Games",
            "type":"Retail Goods"
        }
    ],
    "sg:phone":"+1 317 788 1311",
    "sg:postcode":"46203",
    "sg:province":"IN",
    "sg:tags":[
        "equipment",
        "ceramic",
        "supply"
    ],
    "wof:name":"Grandmas' Ceramic Nook Inc",
    "wof:placetype":"venue"
},
  "geometry": {"coordinates":[-86.14540100000001,39.722654],"type":"Point"}
}