{
  "type": "Feature",
  "properties": {
    "iso:country":"US",
    "sg:address":"7515 W 8th Street Rd",
    "sg:city":"Anderson",
    "sg:classifiers":[
        {
            "category":"Real Estate",
            "subcategory":"Real Estate Operator",
            "type":"Services"
        }
    ],
    "sg:phone":"+1 765 734 1470",
    "sg:postcode":"46011",
    "sg:province":"IN",
    "sg:tags":[
        "property",
        "lessor"
    ],
    "wof:name":"William Hobbs",
    "wof:placetype":"venue"
},
  "geometry": {"coordinates":[-85.80390300000001,40.126051],"type":"Point"}
}