{
  "type": "Feature",
  "properties": {
    "iso:country":"US",
    "sg:address":"108 E Kirkwood Ave",
    "sg:city":"Bloomington",
    "sg:classifiers":[
        {
            "category":"Restaurant",
            "type":"Food & Drink"
        }
    ],
    "sg:phone":"+1 812 323 0002",
    "sg:postcode":"47408",
    "sg:province":"IN",
    "sg:tags":[
        "new",
        "american"
    ],
    "sg:website":"www.farm-bloomington.com",
    "wof:name":"FARMbloomington",
    "wof:placetype":"venue"
},
  "geometry": {"coordinates":[-86.533512,39.16658],"type":"Point"}
}