{
  "type": "Feature",
  "properties": {
    "iso:country":"US",
    "sg:address":"237 E Winslow Rd",
    "sg:city":"Bloomington",
    "sg:classifiers":[
        {
            "category":"Real Estate",
            "subcategory":"Real Estate Agent",
            "type":"Services"
        }
    ],
    "sg:phone":"+1 812 333 4663",
    "sg:postcode":"47401",
    "sg:province":"IN",
    "wof:name":"Hometown Realtors",
    "wof:placetype":"venue"
},
  "geometry": {"coordinates":[-86.524669,39.136033],"type":"Point"}
}