{
  "type": "Feature",
  "properties": {
    "iso:country":"US",
    "sg:address":"3263 W State Rd 154",
    "sg:city":"Sullivan",
    "sg:classifiers":[
        {
            "category":"Home & Garden",
            "subcategory":"Garden Supply",
            "type":"Retail Goods"
        }
    ],
    "sg:phone":"+1 812 382 4413",
    "sg:postcode":"47882",
    "sg:province":"IN",
    "sg:tags":[
        "fertilizer"
    ],
    "wof:name":"Growers Co-Op Inc",
    "wof:placetype":"venue"
},
  "geometry": {"coordinates":[-87.47072,39.104351],"type":"Point"}
}