{
  "type": "Feature",
  "properties": {
    "iso:country":"US",
    "sg:address":"235 Frontage Rd",
    "sg:city":"Columbia City",
    "sg:classifiers":[
        {
            "category":"Travel",
            "subcategory":"Hotels & Motels",
            "type":"Entertainment"
        }
    ],
    "sg:phone":"+1 260 244 5300",
    "sg:postcode":"46725",
    "sg:province":"IN",
    "wof:name":"Lees Inn",
    "wof:placetype":"venue"
},
  "geometry": {"coordinates":[-85.487967,41.169834],"type":"Point"}
}