{
  "type": "Feature",
  "properties": {
    "iso:country":"US",
    "sg:address":"601 E 23rd St",
    "sg:city":"Ferdinand",
    "sg:classifiers":[
        {
            "category":"Professional",
            "subcategory":"Business Services",
            "type":"Services"
        }
    ],
    "sg:phone":"+1 812 367 1490",
    "sg:postcode":"47532",
    "sg:province":"IN",
    "wof:name":"Ruhe Family Ltd Partnership",
    "wof:placetype":"venue"
},
  "geometry": {"coordinates":[-86.85664,38.238335],"type":"Point"}
}