{
  "type": "Feature",
  "properties": {
    "addr:full":"10095 N Turkey Creek Rd Syracuse IN 46567",
    "addr:housenumber":"10095",
    "addr:postcode":"46567",
    "addr:street":"N Turkey Creek Rd",
    "iso:country":"US",
    "sg:address":"10095 N Turkey Creek Rd",
    "sg:city":"Syracuse",
    "sg:classifiers":[
        {
            "category":"Building & Trades",
            "subcategory":"Construction",
            "type":"Services"
        }
    ],
    "sg:phone":"+1 260 856 3470",
    "sg:postcode":"46567",
    "sg:province":"IN",
    "sg:tags":[
        "home",
        "builder"
    ],
    "wof:name":"Runaway Bay Home Owners",
    "wof:placetype":"venue"
},
  "geometry": {"coordinates":[-85.66768,41.3816],"type":"Point"}
}