{
  "type": "Feature",
  "properties": {
    "iso:country":"US",
    "sg:address":"8372 State Rd 56",
    "sg:city":"West Baden Spgs",
    "sg:classifiers":[
        {
            "category":"Autos & Motor Vehicles",
            "subcategory":"Auto Supplies",
            "type":"Retail Goods"
        }
    ],
    "sg:phone":"+1 812 936 4200",
    "sg:postcode":"47469",
    "sg:province":"IN",
    "sg:tags":[
        "automobile",
        "parts"
    ],
    "wof:name":"Rolling Automotive",
    "wof:placetype":"venue"
},
  "geometry": {"coordinates":[-86.613834,38.576211],"type":"Point"}
}