{
  "type": "Feature",
  "properties": {
    "addr:full":"909 Coliseum Blvd N Fort Wayne IN 46805",
    "addr:housenumber":"909",
    "addr:postcode":"46805",
    "addr:street":"Coliseum Blvd N",
    "iso:country":"US",
    "sg:address":"909 Coliseum Blvd N",
    "sg:city":"Fort Wayne",
    "sg:classifiers":[
        {
            "category":"Utilities",
            "subcategory":"Telephone",
            "type":"Services"
        }
    ],
    "sg:phone":"+1 260 422 7799",
    "sg:postcode":"46805",
    "sg:province":"IN",
    "sg:tags":[
        "company"
    ],
    "wof:name":"KMC Telecom I",
    "wof:placetype":"venue"
},
  "geometry": {"coordinates":[-85.087864,41.085775],"type":"Point"}
}