{
  "type": "Feature",
  "properties": {
    "addr:full":"1250 W Main St Greenfield IN 46140",
    "addr:housenumber":"1250",
    "addr:postcode":"46140",
    "addr:street":"W Main St",
    "iso:country":"US",
    "sg:address":"1250 W Main St",
    "sg:city":"Greenfield",
    "sg:classifiers":[
        {
            "category":"Shopping",
            "subcategory":"Department Store",
            "type":"Retail Goods"
        }
    ],
    "sg:phone":"+1 317 462 0604",
    "sg:postcode":"46140",
    "sg:province":"IN",
    "sg:tags":[
        "shop"
    ],
    "sg:website":"www.familydollar.com",
    "wof:name":"Family Dollar Store",
    "wof:placetype":"venue"
},
  "geometry": {"coordinates":[-85.78729,39.784281],"type":"Point"}
}