{
  "type": "Feature",
  "properties": {
    "iso:country":"US",
    "sg:address":"4925 Gladiola St",
    "sg:city":"East Chicago",
    "sg:classifiers":[
        {
            "category":"Sports & Exercise",
            "subcategory":"Sports Center",
            "type":"Entertainment"
        }
    ],
    "sg:phone":"+1 219 391 8392",
    "sg:postcode":"46312",
    "sg:province":"IN",
    "sg:tags":[
        "amateur",
        "team"
    ],
    "wof:name":"East Chicago City of",
    "wof:placetype":"venue"
},
  "geometry": {"coordinates":[-87.46731200000001,41.624019],"type":"Point"}
}