{
  "type": "Feature",
  "properties": {
    "iso:country":"US",
    "sg:address":"14 S Plank St",
    "sg:city":"Rossville",
    "sg:classifiers":[
        {
            "category":"Health Services",
            "subcategory":"Doctor",
            "type":"Services"
        }
    ],
    "sg:phone":"+1 765 379 3311",
    "sg:postcode":"46065",
    "sg:province":"IN",
    "sg:tags":[
        "physician",
        "surgeon"
    ],
    "sg:website":"www.arnett.com",
    "wof:name":"Arnett Clinic-Rossville",
    "wof:placetype":"venue"
},
  "geometry": {"coordinates":[-86.59482199999999,40.416021],"type":"Point"}
}