{
  "type": "Feature",
  "properties": {
    "iso:country":"US",
    "sg:address":"148 Creekside Dr",
    "sg:city":"Kokomo",
    "sg:classifiers":[
        {
            "category":"Shopping",
            "subcategory":"Bicycles & Sporting Goods",
            "type":"Retail Goods"
        }
    ],
    "sg:phone":"+1 765 459 0077",
    "sg:postcode":"46901",
    "sg:province":"IN",
    "sg:tags":[
        "gun",
        "gunsmith"
    ],
    "sg:website":"www.bullseyeboats.com",
    "wof:name":"Bullseye Outdoors",
    "wof:placetype":"venue"
},
  "geometry": {"coordinates":[-86.108487,40.487973],"type":"Point"}
}