{
  "type": "Feature",
  "properties": {
    "iso:country":"US",
    "sg:address":"8225 S Ketcham Rd",
    "sg:city":"Bloomington",
    "sg:classifiers":[
        {
            "category":"Organizations",
            "subcategory":"Religious Organization",
            "type":"Services"
        }
    ],
    "sg:phone":"+1 812 824 9727",
    "sg:postcode":"47403",
    "sg:province":"IN",
    "sg:tags":[
        "clergy"
    ],
    "wof:name":"Russell L Elkins Rev",
    "wof:placetype":"venue"
},
  "geometry": {"coordinates":[-86.56919600000001,39.047091],"type":"Point"}
}