{
  "type": "Feature",
  "properties": {
    "iso:country":"US",
    "sg:address":"3420 Mounds Rd",
    "sg:city":"Anderson",
    "sg:classifiers":[
        {
            "category":"Government",
            "subcategory":"Office",
            "type":"Public Place"
        }
    ],
    "sg:phone":"+1 765 646 9264",
    "sg:postcode":"46017",
    "sg:province":"IN",
    "sg:tags":[
        "housing",
        "program"
    ],
    "wof:name":"Hawthorne House",
    "wof:placetype":"venue"
},
  "geometry": {"coordinates":[-85.63173,40.089911],"type":"Point"}
}