{
  "type": "Feature",
  "properties": {
    "iso:country":"US",
    "sg:address":"2610 Shelby St",
    "sg:city":"Indianapolis",
    "sg:classifiers":[
        {
            "category":"Retail",
            "subcategory":"Repair Shop",
            "type":"Services"
        }
    ],
    "sg:phone":"+1 317 784 7333",
    "sg:postcode":"46203",
    "sg:province":"IN",
    "sg:tags":[
        "appliance"
    ],
    "wof:name":"All Brands Appliance",
    "wof:placetype":"venue"
},
  "geometry": {"coordinates":[-86.139723,39.730046],"type":"Point"}
}