{
  "type": "Feature",
  "properties": {
    "addr:full":"1393 S Adams St Versailles IN 47042",
    "addr:housenumber":"1393",
    "addr:postcode":"47042",
    "addr:street":"S Adams St",
    "iso:country":"US",
    "sg:address":"1393 S Adams St",
    "sg:city":"Versailles",
    "sg:classifiers":[
        {
            "category":"Autos & Motor Vehicles",
            "subcategory":"Automobile Sales",
            "type":"Retail Goods"
        }
    ],
    "sg:phone":"+1 812 689 3133",
    "sg:postcode":"47042",
    "sg:province":"IN",
    "sg:tags":[
        "car",
        "dealer"
    ],
    "wof:name":"T S Auto Sales",
    "wof:placetype":"venue"
},
  "geometry": {"coordinates":[-85.25925700000001,39.053439],"type":"Point"}
}