{
  "type": "Feature",
  "properties": {
    "iso:country":"US",
    "sg:address":"2202 N Heidelbach Ave",
    "sg:city":"Evansville",
    "sg:classifiers":[
        {
            "category":"Professional",
            "subcategory":"Management & Consulting",
            "type":"Services"
        }
    ],
    "sg:phone":"+1 812 464 5425",
    "sg:postcode":"47711",
    "sg:province":"IN",
    "sg:tags":[
        "party",
        "planning"
    ],
    "wof:name":"Brice's Taekwondo USA-Karate",
    "wof:placetype":"venue"
},
  "geometry": {"coordinates":[-87.560878,37.998539],"type":"Point"}
}