{
  "type": "Feature",
  "properties": {
    "iso:country":"US",
    "sg:address":"2640 Calumet Ave",
    "sg:city":"Hammond",
    "sg:classifiers":[
        {
            "category":"Wholesale",
            "subcategory":"Construction Materials",
            "type":"Manufacturing & Wholesale Goods"
        },
        {
            "category":"Professional",
            "subcategory":"Business Services",
            "type":"Services"
        },
        {
            "category":"Manufacturing",
            "subcategory":"Lumber",
            "type":"Manufacturing & Wholesale Goods"
        }
    ],
    "sg:phone":"+1 708 891 4550",
    "sg:postcode":"46320",
    "sg:province":"IN",
    "sg:tags":[
        "product",
        "pallet",
        "environmental",
        "ecological",
        "lumber-wholesale",
        "skid"
    ],
    "sg:website":"http://www.calumetpallet.com",
    "wof:name":"Calumet Pallet Co Inc",
    "wof:placetype":"venue"
},
  "geometry": {"coordinates":[-87.508624,41.663801],"type":"Point"}
}