{
  "type": "Feature",
  "properties": {
    "iso:country":"US",
    "sg:address":"3145 State Rd 5",
    "sg:city":"Shipshewana",
    "sg:classifiers":[
        {
            "category":"Wholesale",
            "subcategory":"Toys & Hobbies",
            "type":"Manufacturing & Wholesale Goods"
        }
    ],
    "sg:phone":"+1 260 768 7676",
    "sg:postcode":"46565",
    "sg:province":"IN",
    "sg:tags":[
        "firework"
    ],
    "wof:name":"M T Fireworks",
    "wof:placetype":"venue"
},
  "geometry": {"coordinates":[-85.580851,41.68943],"type":"Point"}
}