{
  "type": "Feature",
  "properties": {
    "iso:country":"US",
    "sg:address":"2825 W Perimeter Rd",
    "sg:city":"Indianapolis",
    "sg:classifiers":[
        {
            "category":"Insurance",
            "subcategory":"Insurance Agent",
            "type":"Services"
        },
        {
            "category":"Insurance",
            "subcategory":"Hazard Insurance",
            "type":"Services"
        }
    ],
    "sg:phone":"+1 317 240 0407",
    "sg:postcode":"46241",
    "sg:province":"IN",
    "sg:tags":[
        "consultant",
        "analyst"
    ],
    "wof:name":"Baa",
    "wof:placetype":"venue"
},
  "geometry": {"coordinates":[-86.31409499999999,39.697973],"type":"Point"}
}