{
  "type": "Feature",
  "properties": {
    "addr:full":"2940 Jefferson St Terre Haute IN 47802",
    "addr:housenumber":"2940",
    "addr:postcode":"47802",
    "addr:street":"Jefferson St",
    "iso:country":"US",
    "sg:address":"2940 Jefferson St",
    "sg:city":"Terre Haute",
    "sg:classifiers":[
        {
            "category":"Organizations",
            "subcategory":"Non-profit Organization",
            "type":"Services"
        }
    ],
    "sg:phone":"+1 812 232 5272",
    "sg:postcode":"47802",
    "sg:province":"IN",
    "sg:tags":[
        "information",
        "alcoholism",
        "treatment"
    ],
    "wof:name":"Recovery Associates",
    "wof:placetype":"venue"
},
  "geometry": {"coordinates":[-87.421944,39.435652],"type":"Point"}
}