{
  "type": "Feature",
  "properties": {
    "iso:country":"US",
    "sg:address":"1936 W 2nd Ave",
    "sg:city":"Gary",
    "sg:classifiers":[
        {
            "category":"Real Estate",
            "subcategory":"Real Estate Agent",
            "type":"Services"
        }
    ],
    "sg:phone":"+1 219 882 3077",
    "sg:postcode":"46404",
    "sg:province":"IN",
    "wof:name":"Devine Connection",
    "wof:placetype":"venue"
},
  "geometry": {"coordinates":[-87.36075599999999,41.607076],"type":"Point"}
}