{
  "type": "Feature",
  "properties": {
    "iso:country":"US",
    "sg:address":"402 W 6th St",
    "sg:city":"Bloomington",
    "sg:classifiers":[
        {
            "category":"Shopping",
            "subcategory":"Clothing, Apparel, & Fashions",
            "type":"Retail Goods"
        }
    ],
    "sg:phone":"+1 812 339 2063",
    "sg:postcode":"47404",
    "sg:province":"IN",
    "sg:tags":[
        "shop",
        "bridal"
    ],
    "wof:name":"Bella Sera",
    "wof:placetype":"venue"
},
  "geometry": {"coordinates":[-86.53865500000001,39.16767],"type":"Point"}
}