{
  "type": "Feature",
  "properties": {
    "addr:full":"917 Meridian St Anderson IN 46016",
    "addr:housenumber":"917",
    "addr:postcode":"46016",
    "addr:street":"Meridian St",
    "iso:country":"US",
    "sg:address":"917 Meridian St",
    "sg:city":"Anderson",
    "sg:classifiers":[
        {
            "category":"Professional",
            "subcategory":"Lawyer & Legal Services",
            "type":"Services"
        }
    ],
    "sg:phone":"+1 765 644 0200",
    "sg:postcode":"46016",
    "sg:province":"IN",
    "sg:tags":[
        "attorney"
    ],
    "wof:name":"Mc Nabney Law Office",
    "wof:placetype":"venue"
},
  "geometry": {"coordinates":[-85.679283,40.106247],"type":"Point"}
}