{
  "type": "Feature",
  "properties": {
    "addr:full":"833 N Green River Rd Evansville IN 47715",
    "addr:housenumber":"833",
    "addr:postcode":"47715",
    "addr:street":"N Green River Rd",
    "iso:country":"US",
    "sg:address":"833 N Green River Rd",
    "sg:city":"Evansville",
    "sg:classifiers":[
        {
            "category":"Shopping",
            "subcategory":"Used Merchandise",
            "type":"Retail Goods"
        }
    ],
    "sg:phone":"+1 812 473 2445",
    "sg:postcode":"47715",
    "sg:province":"IN",
    "sg:tags":[
        "clothing"
    ],
    "wof:name":"Plato's Closet",
    "wof:placetype":"venue"
},
  "geometry": {"coordinates":[-87.49260200000001,37.984425],"type":"Point"}
}