{
  "type": "Feature",
  "properties": {
    "iso:country":"US",
    "sg:address":"418 E Chicago St",
    "sg:city":"Columbia City",
    "sg:classifiers":[
        {
            "category":"Real Estate",
            "subcategory":"Real Estate Agent",
            "type":"Services"
        }
    ],
    "sg:phone":"+1 260 625 3487",
    "sg:postcode":"46725",
    "sg:province":"IN",
    "wof:name":"Grable & Associates Realty",
    "wof:placetype":"venue"
},
  "geometry": {"coordinates":[-85.483286,41.149214],"type":"Point"}
}