{
  "type": "Feature",
  "properties": {
    "iso:country":"US",
    "sg:address":"925 Lake Ave",
    "sg:city":"Fort Wayne",
    "sg:classifiers":[
        {
            "category":"Shopping",
            "type":"Retail Goods"
        }
    ],
    "sg:phone":"+1 260 426 9379",
    "sg:postcode":"46805",
    "sg:province":"IN",
    "sg:tags":[
        "merchandise"
    ],
    "wof:name":"Twilight Sales",
    "wof:placetype":"venue"
},
  "geometry": {"coordinates":[-85.1276,41.085254],"type":"Point"}
}