{
  "type": "Feature",
  "properties": {
    "iso:country":"US",
    "sg:address":"8737 Cottage Grove Ave",
    "sg:city":"Highland",
    "sg:classifiers":[
        {
            "category":"Autos & Motor Vehicles",
            "subcategory":"Automobile Sales",
            "type":"Retail Goods"
        }
    ],
    "sg:phone":"+1 219 776 8291",
    "sg:postcode":"46322",
    "sg:province":"IN",
    "sg:tags":[
        "used"
    ],
    "wof:name":"D & M Auto Sales",
    "wof:placetype":"venue"
},
  "geometry": {"coordinates":[-87.449454,41.554219],"type":"Point"}
}