{
  "type": "Feature",
  "properties": {
    "iso:country":"US",
    "sg:address":"503 S Main St",
    "sg:city":"Nappanee",
    "sg:classifiers":[
        {
            "category":"Manufacturing",
            "subcategory":"Furniture",
            "type":"Manufacturing & Wholesale Goods"
        }
    ],
    "sg:phone":"+1 574 773 7751",
    "sg:postcode":"46550",
    "sg:province":"IN",
    "sg:tags":[
        "drapery"
    ],
    "sg:website":"www.ascotent.com",
    "wof:name":"Ascot Enterprises Inc",
    "wof:placetype":"venue"
},
  "geometry": {"coordinates":[-86.001293,41.43881],"type":"Point"}
}