{
  "type": "Feature",
  "properties": {
    "addr:full":"5321 E 42nd St Indianapolis IN 46226",
    "addr:housenumber":"5321",
    "addr:postcode":"46226",
    "addr:street":"E 42Nd St",
    "iso:country":"US",
    "sg:address":"5321 E 42nd St",
    "sg:city":"Indianapolis",
    "sg:classifiers":[
        {
            "category":"Organizations",
            "subcategory":"Religious Organization",
            "type":"Services"
        }
    ],
    "sg:phone":"+1 317 546 3085",
    "sg:postcode":"46226",
    "sg:province":"IN",
    "sg:tags":[
        "church"
    ],
    "wof:name":"First Trinity Lutheran Church",
    "wof:placetype":"venue"
},
  "geometry": {"coordinates":[-86.077881,39.832985],"type":"Point"}
}