{
  "type": "Feature",
  "properties": {
    "addr:full":"1479 N State St North Vernon IN 47265",
    "addr:housenumber":"1479",
    "addr:postcode":"47265",
    "addr:street":"N State St",
    "iso:country":"US",
    "sg:address":"1479 N State St",
    "sg:city":"North Vernon",
    "sg:classifiers":[
        {
            "category":"Restaurant",
            "type":"Food & Drink"
        }
    ],
    "sg:menulink":"http://www.allmenus.com/in/north-vernon/186514-mcdonalds/menu/",
    "sg:postcode":"47265",
    "sg:province":"IN",
    "sg:tags":[
        "burger",
        "american"
    ],
    "wof:name":"McDonald's",
    "wof:placetype":"venue"
},
  "geometry": {"coordinates":[-85.637238,39.012474],"type":"Point"}
}