{
  "type": "Feature",
  "properties": {
    "addr:full":"5695 S 400 W Winamac IN 46996",
    "addr:housenumber":"5695;400",
    "addr:postcode":"46996",
    "addr:street":"S;W",
    "iso:country":"US",
    "sg:address":"5695 S 400 W",
    "sg:city":"Winamac",
    "sg:classifiers":[
        {
            "category":"Farming",
            "subcategory":"Farm",
            "type":"Manufacturing & Wholesale Goods"
        }
    ],
    "sg:phone":"+1 574 595 7841",
    "sg:postcode":"46996",
    "sg:province":"IN",
    "wof:name":"Tim's Farms",
    "wof:placetype":"venue"
},
  "geometry": {"coordinates":[-86.681365,40.974748],"type":"Point"}
}