{
  "type": "Feature",
  "properties": {
    "iso:country":"US",
    "sg:address":"14909 N Meridian St",
    "sg:city":"Carmel",
    "sg:classifiers":[
        {
            "category":"Fast Food",
            "type":"Food & Drink"
        }
    ],
    "sg:phone":"+1 317 580 0890",
    "sg:postcode":"46032",
    "sg:province":"IN",
    "sg:tags":[
        "restaurant"
    ],
    "sg:website":"http://www.steaknshake.com",
    "wof:name":"Steak 'n Shake",
    "wof:placetype":"venue"
},
  "geometry": {"coordinates":[-86.13103099999999,40.01898],"type":"Point"}
}