{
  "type": "Feature",
  "properties": {
    "iso:country":"US",
    "sg:address":"7811 US Hwy 31 S",
    "sg:city":"Indianapolis",
    "sg:classifiers":[
        {
            "category":"Restaurant",
            "type":"Food & Drink"
        }
    ],
    "sg:phone":"+1 317 889 7776",
    "sg:postcode":"46227",
    "sg:province":"IN",
    "wof:name":"China King",
    "wof:placetype":"venue"
},
  "geometry": {"coordinates":[-86.138175,39.651751],"type":"Point"}
}