{
  "type": "Feature",
  "properties": {
    "iso:country":"US",
    "sg:address":"2495 State Rd 15",
    "sg:city":"Wabash",
    "sg:classifiers":[
        {
            "category":"Wholesale",
            "subcategory":"Construction Materials",
            "type":"Manufacturing & Wholesale Goods"
        }
    ],
    "sg:phone":"+1 260 563 2509",
    "sg:postcode":"46992",
    "sg:province":"IN",
    "sg:tags":[
        "pallet",
        "skid"
    ],
    "wof:name":"Pallets R Us",
    "wof:placetype":"venue"
},
  "geometry": {"coordinates":[-85.881055,40.862623],"type":"Point"}
}