{
  "type": "Feature",
  "properties": {
    "iso:country":"US",
    "sg:address":"8008 Castleway Dr",
    "sg:city":"Indianapolis",
    "sg:classifiers":[
        {
            "category":"Wholesale",
            "subcategory":"Groceries",
            "type":"Manufacturing & Wholesale Goods"
        }
    ],
    "sg:phone":"+1 317 576 5335",
    "sg:postcode":"46250",
    "sg:province":"IN",
    "sg:tags":[
        "confectionery",
        "candy"
    ],
    "wof:name":"Fairley & Co Inc",
    "wof:placetype":"venue"
},
  "geometry": {"coordinates":[-86.056483,39.899659],"type":"Point"}
}