{
  "type": "Feature",
  "properties": {
    "iso:country":"US",
    "sg:address":"5845 Rockville Rd",
    "sg:city":"Indianapolis",
    "sg:classifiers":[
        {
            "category":"Travel",
            "subcategory":"Hotels & Motels",
            "type":"Entertainment"
        }
    ],
    "sg:phone":"+1 317 247 4100",
    "sg:postcode":"46224",
    "sg:province":"IN",
    "sg:website":"www.sleepinn.com",
    "wof:name":"Sleep Inn",
    "wof:placetype":"venue"
},
  "geometry": {"coordinates":[-86.261658,39.764862],"type":"Point"}
}