{
  "type": "Feature",
  "properties": {
    "iso:country":"US",
    "sg:address":"151 W Pine St",
    "sg:city":"Poseyville",
    "sg:classifiers":[
        {
            "category":"Retail",
            "subcategory":"Auto Repair",
            "type":"Services"
        }
    ],
    "sg:phone":"+1 812 874 3577",
    "sg:postcode":"47633",
    "sg:province":"IN",
    "sg:tags":[
        "repairing",
        "automobile"
    ],
    "wof:name":"Don's Garage",
    "wof:placetype":"venue"
},
  "geometry": {"coordinates":[-87.785449,38.165224],"type":"Point"}
}