{
  "type": "Feature",
  "properties": {
    "iso:country":"US",
    "sg:address":"2725 24th St",
    "sg:city":"Columbus",
    "sg:classifiers":[
        {
            "category":"Shopping",
            "subcategory":"Jewelry",
            "type":"Retail Goods"
        }
    ],
    "sg:phone":"+1 812 372 6530",
    "sg:postcode":"47201",
    "sg:province":"IN",
    "sg:tags":[
        "jeweler"
    ],
    "wof:name":"Columbus Gold & Diamond Outlet",
    "wof:placetype":"venue"
},
  "geometry": {"coordinates":[-85.891361,39.221957],"type":"Point"}
}