{
  "type": "Feature",
  "properties": {
    "iso:country":"US",
    "sg:address":"505 N Carroll Ave",
    "sg:city":"Michigan City",
    "sg:classifiers":[
        {
            "category":"Railroad",
            "type":"Transportation"
        }
    ],
    "sg:phone":"+1 219 874 9000",
    "sg:postcode":"46360",
    "sg:province":"IN",
    "wof:name":"Chicago Southshore & South Bnd",
    "wof:placetype":"venue"
},
  "geometry": {"coordinates":[-86.869725,41.713859],"type":"Point"}
}