{
  "type": "Feature",
  "properties": {
    "iso:country":"US",
    "sg:address":"4139 State Rte 340",
    "sg:city":"Brazil",
    "sg:classifiers":[
        {
            "category":"Retail",
            "subcategory":"Laundry & Dry Cleaning",
            "type":"Services"
        }
    ],
    "sg:phone":"+1 812 443 6800",
    "sg:postcode":"47834",
    "sg:province":"IN",
    "sg:tags":[
        "cleaners",
        "rug",
        "carpet"
    ],
    "wof:name":"Mobile Clean Carpet",
    "wof:placetype":"venue"
},
  "geometry": {"coordinates":[-87.184209,39.510754],"type":"Point"}
}