{
  "type": "Feature",
  "properties": {
    "iso:country":"US",
    "sg:address":"121 E Main St",
    "sg:city":"Greensburg",
    "sg:classifiers":[
        {
            "category":"Home & Garden",
            "subcategory":"Household Appliances",
            "type":"Retail Goods"
        }
    ],
    "sg:phone":"+1 812 663 6225",
    "sg:postcode":"47240",
    "sg:province":"IN",
    "wof:name":"Excel Appliances",
    "wof:placetype":"venue"
},
  "geometry": {"coordinates":[-85.48392,39.336491],"type":"Point"}
}