{
  "type": "Feature",
  "properties": {
    "addr:full":"4630 W Jefferson Blvd Fort Wayne IN 46804",
    "addr:housenumber":"4630",
    "addr:postcode":"46804",
    "addr:street":"W Jefferson Blvd",
    "iso:country":"US",
    "sg:address":"4630 W Jefferson Blvd",
    "sg:city":"Fort Wayne",
    "sg:classifiers":[
        {
            "category":"Banks & Credit Unions",
            "subcategory":"Bank",
            "type":"Services"
        }
    ],
    "sg:phone":"+1 260 432 4246",
    "sg:postcode":"46804",
    "sg:province":"IN",
    "wof:name":"Essex Group Fed Credit Union",
    "wof:placetype":"venue"
},
  "geometry": {"coordinates":[-85.20098400000001,41.066558],"type":"Point"}
}