{
  "type": "Feature",
  "properties": {
    "iso:country":"US",
    "sg:address":"3507 S Co Rd 25 W",
    "sg:city":"Greencastle",
    "sg:classifiers":[
        {
            "category":"Insurance",
            "subcategory":"Hazard Insurance",
            "type":"Services"
        }
    ],
    "sg:phone":"+1 765 653 1308",
    "sg:postcode":"46135",
    "sg:province":"IN",
    "sg:tags":[
        "bond"
    ],
    "wof:name":"Hoosier Bail Bonds",
    "wof:placetype":"venue"
},
  "geometry": {"coordinates":[-86.855356,39.609917],"type":"Point"}
}