{
  "type": "Feature",
  "properties": {
    "iso:country":"US",
    "sg:address":"209 4th St",
    "sg:city":"Lawrenceburg",
    "sg:classifiers":[
        {
            "category":"Professional",
            "subcategory":"Accounting & Tax Preparation",
            "type":"Services"
        }
    ],
    "sg:phone":"+1 812 537 2572",
    "sg:postcode":"47025",
    "sg:province":"IN",
    "sg:tags":[
        "return",
        "filing"
    ],
    "wof:name":"Reliable Tax Svc",
    "wof:placetype":"venue"
},
  "geometry": {"coordinates":[-84.857696,39.097428],"type":"Point"}
}