{
  "type": "Feature",
  "properties": {
    "iso:country":"US",
    "sg:address":"1360 Jackson St",
    "sg:city":"Columbus",
    "sg:classifiers":[
        {
            "category":"Farming",
            "subcategory":"Farm",
            "type":"Manufacturing & Wholesale Goods"
        }
    ],
    "sg:phone":"+1 812 372 8486",
    "sg:postcode":"47201",
    "sg:province":"IN",
    "sg:tags":[
        "crop",
        "general"
    ],
    "wof:name":"Donald Lienhoop",
    "wof:placetype":"venue"
},
  "geometry": {"coordinates":[-85.92321099999999,39.213092],"type":"Point"}
}