{
  "type": "Feature",
  "properties": {
    "iso:country":"US",
    "sg:address":"11835 N State Rd 13",
    "sg:city":"Syracuse",
    "sg:classifiers":[
        {
            "category":"Building & Trades",
            "subcategory":"Construction",
            "type":"Services"
        }
    ],
    "sg:phone":"+1 574 457 8670",
    "sg:postcode":"46567",
    "sg:province":"IN",
    "sg:tags":[
        "contractor"
    ],
    "wof:name":"Fawley & Sons Inc",
    "wof:placetype":"venue"
},
  "geometry": {"coordinates":[-85.742347,41.401795],"type":"Point"}
}