{
  "type": "Feature",
  "properties": {
    "iso:country":"US",
    "sg:address":"505 E 2nd St",
    "sg:city":"North Manchester",
    "sg:classifiers":[
        {
            "category":"Food & Beverages",
            "subcategory":"Liquor & Beverages",
            "type":"Retail Goods"
        }
    ],
    "sg:phone":"+1 260 982 2419",
    "sg:postcode":"46962",
    "sg:province":"IN",
    "sg:tags":[
        "alcoholic"
    ],
    "wof:name":"Eel River Package Store",
    "wof:placetype":"venue"
},
  "geometry": {"coordinates":[-85.763701,41.000185],"type":"Point"}
}