{
  "type": "Feature",
  "properties": {
    "iso:country":"US",
    "sg:address":"1626 Indianapolis Blvd",
    "sg:city":"Whiting",
    "sg:classifiers":[
        {
            "category":"Building & Trades",
            "subcategory":"Construction",
            "type":"Services"
        }
    ],
    "sg:phone":"+1 219 853 7028",
    "sg:postcode":"46394",
    "sg:province":"IN",
    "sg:tags":[
        "roofing",
        "contractor"
    ],
    "wof:name":"Bill's Roofing",
    "wof:placetype":"venue"
},
  "geometry": {"coordinates":[-87.503623,41.683388],"type":"Point"}
}