{
  "type": "Feature",
  "properties": {
    "addr:full":"5380 S Sweetwater Ln Bloomington IN 47403",
    "addr:housenumber":"5380",
    "addr:postcode":"47403",
    "addr:street":"S Sweetwater Ln",
    "iso:country":"US",
    "sg:address":"5380 S Sweetwater Ln",
    "sg:city":"Bloomington",
    "sg:classifiers":[
        {
            "category":"Building & Trades",
            "subcategory":"Construction",
            "type":"Services"
        }
    ],
    "sg:phone":"+1 812 824 7845",
    "sg:postcode":"47403",
    "sg:province":"IN",
    "sg:tags":[
        "hanging",
        "contractor"
    ],
    "wof:name":"Rk Painting",
    "wof:placetype":"venue"
},
  "geometry": {"coordinates":[-86.57517,39.103153],"type":"Point"}
}