{
  "type": "Feature",
  "properties": {
    "iso:country":"US",
    "sg:address":"210 E Chicago Ave",
    "sg:city":"East Chicago",
    "sg:classifiers":[
        {
            "category":"Education",
            "subcategory":"School",
            "type":"Public Place"
        }
    ],
    "sg:phone":"+1 219 391 4100",
    "sg:postcode":"46312",
    "sg:province":"IN",
    "sg:website":"www.ecps.org",
    "wof:name":"East Chicago School Supt",
    "wof:placetype":"venue"
},
  "geometry": {"coordinates":[-87.470483,41.629397],"type":"Point"}
}