{
  "type": "Feature",
  "properties": {
    "iso:country":"US",
    "sg:address":"2435 S State Road 135",
    "sg:city":"Greenwood",
    "sg:classifiers":[
        {
            "category":"Shopping",
            "subcategory":"Pets & Pet Supplies",
            "type":"Retail Goods"
        },
        {
            "category":"Retail",
            "subcategory":"Animal Services",
            "type":"Services"
        }
    ],
    "sg:phone":"+1 317 919 5471",
    "sg:postcode":"46143",
    "sg:province":"IN",
    "sg:tags":[
        "grooming",
        "dog",
        "cat"
    ],
    "wof:name":"Grooming School Of Indiana",
    "wof:placetype":"venue"
},
  "geometry": {"coordinates":[-86.15900600000001,39.586095],"type":"Point"}
}