{
  "type": "Feature",
  "properties": {
    "iso:country":"US",
    "sg:address":"150 N Green River Rd",
    "sg:city":"Evansville",
    "sg:classifiers":[
        {
            "category":"Autos & Motor Vehicles",
            "subcategory":"Auto Supplies",
            "type":"Retail Goods"
        }
    ],
    "sg:phone":"+1 812 473 6558",
    "sg:postcode":"47715",
    "sg:province":"IN",
    "sg:tags":[
        "automobile",
        "parts"
    ],
    "sg:website":"www.dpat.com",
    "wof:name":"D-Patrick Honda/Nissan",
    "wof:placetype":"venue"
},
  "geometry": {"coordinates":[-87.49267500000001,37.978564],"type":"Point"}
}