{
  "type": "Feature",
  "properties": {
    "iso:country":"US",
    "sg:address":"12500 S 96 E Rd",
    "sg:city":"Muncie",
    "sg:classifiers":[
        {
            "category":"Real Estate",
            "subcategory":"Real Estate Agent",
            "type":"Services"
        }
    ],
    "sg:phone":"+1 765 284 6040",
    "sg:postcode":"47302",
    "sg:province":"IN",
    "wof:name":"Ken Harden Appraisals",
    "wof:placetype":"venue"
},
  "geometry": {"coordinates":[-85.366136,40.076395],"type":"Point"}
}