{
  "type": "Feature",
  "properties": {
    "iso:country":"US",
    "sg:address":"601 Union St",
    "sg:city":"Lafayette",
    "sg:classifiers":[
        {
            "category":"Food & Beverages",
            "subcategory":"Groceries & Convenience Stores",
            "type":"Retail Goods"
        }
    ],
    "sg:phone":"+1 765 423 2177",
    "sg:postcode":"47904",
    "sg:province":"IN",
    "wof:name":"Village Pantry",
    "wof:placetype":"venue"
},
  "geometry": {"coordinates":[-86.88950199999999,40.424697],"type":"Point"}
}