{
  "type": "Feature",
  "properties": {
    "iso:country":"US",
    "sg:address":"5379 E Main St",
    "sg:city":"Dubois",
    "sg:classifiers":[
        {
            "category":"Education",
            "subcategory":"School",
            "type":"Public Place"
        }
    ],
    "sg:phone":"+1 812 678 2781",
    "sg:postcode":"47527",
    "sg:province":"IN",
    "wof:name":"Northeast Dubois County School",
    "wof:placetype":"venue"
},
  "geometry": {"coordinates":[-86.80569,38.445509],"type":"Point"}
}