{
  "type": "Feature",
  "properties": {
    "addr:full":"11306 S 800 W 35 Marion IN 46952",
    "addr:housenumber":"11306;800",
    "addr:postcode":"46952",
    "addr:street":"S;W 35",
    "iso:country":"US",
    "sg:address":"11306 S 800 W 35",
    "sg:city":"Marion",
    "sg:classifiers":[
        {
            "category":"Farming",
            "subcategory":"Farm",
            "type":"Manufacturing & Wholesale Goods"
        }
    ],
    "sg:phone":"+1 765 664 7626",
    "sg:postcode":"46952",
    "sg:province":"IN",
    "sg:tags":[
        "crop",
        "general"
    ],
    "wof:name":"Kratzer Family Farms Inc",
    "wof:placetype":"venue"
},
  "geometry": {"coordinates":[-85.600655,40.663123],"type":"Point"}
}