{
  "type": "Feature",
  "properties": {
    "iso:country":"US",
    "sg:address":"11015 Acton Ct",
    "sg:city":"Fort Wayne",
    "sg:classifiers":[
        {
            "category":"Professional",
            "type":"Services"
        }
    ],
    "sg:phone":"+1 260 432 8703",
    "sg:postcode":"46814",
    "sg:province":"IN",
    "sg:tags":[
        "establishment"
    ],
    "wof:name":"Southlake Companies",
    "wof:placetype":"venue"
},
  "geometry": {"coordinates":[-85.28591400000001,41.033408],"type":"Point"}
}