{
  "type": "Feature",
  "properties": {
    "iso:country":"US",
    "sg:address":"14620 Co Rd 380",
    "sg:city":"Remington",
    "sg:classifiers":[
        {
            "category":"Farming",
            "subcategory":"Farm & Veterinary Services",
            "type":"Manufacturing & Wholesale Goods"
        }
    ],
    "sg:phone":"+1 219 261 3392",
    "sg:postcode":"47977",
    "sg:province":"IN",
    "wof:name":"Lehe Farms Trucking",
    "wof:placetype":"venue"
},
  "geometry": {"coordinates":[-87.118821,40.800265],"type":"Point"}
}