{
  "type": "Feature",
  "properties": {
    "iso:country":"US",
    "sg:address":"4979 N Franklin Rd",
    "sg:city":"Indianapolis",
    "sg:classifiers":[
        {
            "category":"Manufacturing",
            "subcategory":"Printing",
            "type":"Manufacturing & Wholesale Goods"
        }
    ],
    "sg:phone":"+1 317 545 0421",
    "sg:postcode":"46226",
    "sg:province":"IN",
    "sg:tags":[
        "screen"
    ],
    "wof:name":"American Silk Screen Printing",
    "wof:placetype":"venue"
},
  "geometry": {"coordinates":[-86.027123,39.844964],"type":"Point"}
}