{
  "type": "Feature",
  "properties": {
    "iso:country":"US",
    "sg:address":"1640 Bellemeade Avenue",
    "sg:city":"Bloomington",
    "sg:classifiers":[
        {
            "category":"Building & Trades",
            "subcategory":"Construction",
            "type":"Services"
        }
    ],
    "sg:phone":"+1 812 360 7308",
    "sg:postcode":"47401",
    "sg:province":"IN",
    "sg:tags":[
        "contractor"
    ],
    "sg:website":"www.archadeck.com",
    "wof:name":"Archadeck of South Central Indiana",
    "wof:placetype":"venue"
},
  "geometry": {"coordinates":[-86.445053,39.146417],"type":"Point"}
}