{
  "type": "Feature",
  "properties": {
    "iso:country":"US",
    "sg:address":"131 W Broadway",
    "sg:city":"Bunker Hill",
    "sg:classifiers":[
        {
            "category":"Banks & Credit Unions",
            "subcategory":"Bank",
            "type":"Services"
        }
    ],
    "sg:phone":"+1 765 689 0226",
    "sg:postcode":"46914",
    "sg:province":"IN",
    "wof:name":"Ium Federal Credit Union",
    "wof:placetype":"venue"
},
  "geometry": {"coordinates":[-86.103936,40.660108],"type":"Point"}
}