{
  "type": "Feature",
  "properties": {
    "iso:country":"US",
    "sg:address":"2601 E 56th St",
    "sg:city":"Indianapolis",
    "sg:classifiers":[
        {
            "category":"Building & Trades",
            "subcategory":"Construction",
            "type":"Services"
        }
    ],
    "sg:phone":"+1 317 251 1935",
    "sg:postcode":"46220",
    "sg:province":"IN",
    "sg:tags":[
        "fire",
        "restoration",
        "damage",
        "preservation"
    ],
    "wof:name":"Michaelis",
    "wof:placetype":"venue"
},
  "geometry": {"coordinates":[-86.119546,39.854987],"type":"Point"}
}