{
  "type": "Feature",
  "properties": {
    "iso:country":"US",
    "sg:address":"11929 Vienna Rd",
    "sg:city":"Wadesville",
    "sg:classifiers":[
        {
            "category":"Professional",
            "type":"Services"
        }
    ],
    "sg:phone":"+1 812 985 7843",
    "sg:postcode":"47638",
    "sg:province":"IN",
    "wof:name":"Indiana KY Ill Miniature Hors",
    "wof:placetype":"venue"
},
  "geometry": {"coordinates":[-87.698034,38.062273],"type":"Point"}
}