{
  "type": "Feature",
  "properties": {
    "addr:full":"5411 S Stonewood Dr Mt Vernon IN 47620",
    "addr:housenumber":"5411",
    "addr:postcode":"47620",
    "addr:street":"S Stonewood Dr",
    "iso:country":"US",
    "sg:address":"5411 S Stonewood Dr",
    "sg:city":"Mt Vernon",
    "sg:classifiers":[
        {
            "category":"Professional",
            "type":"Services"
        }
    ],
    "sg:phone":"+1 812 985 9963",
    "sg:postcode":"47620",
    "sg:province":"IN",
    "sg:tags":[
        "establishment"
    ],
    "wof:name":"Powell Koch",
    "wof:placetype":"venue"
},
  "geometry": {"coordinates":[-87.74864100000001,37.958613],"type":"Point"}
}