{
  "type": "Feature",
  "properties": {
    "iso:country":"US",
    "sg:address":"5855 N US Hwy 35",
    "sg:city":"Laporte",
    "sg:classifiers":[
        {
            "category":"Shopping",
            "type":"Retail Goods"
        }
    ],
    "sg:phone":"+1 219 879 7112",
    "sg:postcode":"46350",
    "sg:province":"IN",
    "sg:tags":[
        "ice"
    ],
    "wof:name":"City's Pure Ice Inc",
    "wof:placetype":"venue"
},
  "geometry": {"coordinates":[-86.802796,41.690323],"type":"Point"}
}