{
  "type": "Feature",
  "properties": {
    "iso:country":"US",
    "sg:address":"617 Green Rd",
    "sg:city":"Madison",
    "sg:classifiers":[
        {
            "category":"Professional",
            "subcategory":"Business Services",
            "type":"Services"
        }
    ],
    "sg:phone":"+1 812 273 0860",
    "sg:postcode":"47250",
    "sg:province":"IN",
    "sg:tags":[
        "embroidery"
    ],
    "wof:name":"Columbus Embroidery",
    "wof:placetype":"venue"
},
  "geometry": {"coordinates":[-85.39854,38.761788],"type":"Point"}
}