{
  "type": "Feature",
  "properties": {
    "iso:country":"US",
    "sg:address":"216 Deer Run",
    "sg:city":"Evansville",
    "sg:classifiers":[
        {
            "category":"Real Estate",
            "subcategory":"Real Estate Operator",
            "type":"Services"
        }
    ],
    "sg:phone":"+1 812 985 5775",
    "sg:postcode":"47712",
    "sg:province":"IN",
    "sg:tags":[
        "mobile",
        "home",
        "community"
    ],
    "wof:name":"Twin Lakes Mobile Home Park",
    "wof:placetype":"venue"
},
  "geometry": {"coordinates":[-87.70407,37.925077],"type":"Point"}
}