{
  "type": "Feature",
  "properties": {
    "addr:full":"213 SW 2nd St Richmond IN 47374",
    "addr:housenumber":"213",
    "addr:postcode":"47374",
    "addr:street":"Sw 2Nd St",
    "iso:country":"US",
    "sg:address":"213 SW 2nd St",
    "sg:city":"Richmond",
    "sg:classifiers":[
        {
            "category":"Health Services",
            "subcategory":"Optometrist",
            "type":"Services"
        }
    ],
    "sg:phone":"+1 765 939 2000",
    "sg:postcode":"47374",
    "sg:province":"IN",
    "sg:tags":[
        "visual",
        "training"
    ],
    "wof:name":"Owens Optometry",
    "wof:placetype":"venue"
},
  "geometry": {"coordinates":[-84.904173,39.827036],"type":"Point"}
}