{
  "type": "Feature",
  "properties": {
    "iso:country":"US",
    "sg:address":"5894 W State Rd 46",
    "sg:city":"Columbus",
    "sg:phone":"+1 812 342 4998",
    "sg:postcode":"47201",
    "sg:province":"IN",
    "sg:tags":[
        "farm",
        "corn",
        "soybean"
    ],
    "wof:name":"Kenneth Allison",
    "wof:placetype":"venue"
},
  "geometry": {"coordinates":[-85.987144,39.198414],"type":"Point"}
}