{
  "type": "Feature",
  "properties": {
    "iso:country":"US",
    "sg:address":"5525 Coldwater Rd",
    "sg:city":"Fort Wayne",
    "sg:classifiers":[
        {
            "category":"Banks & Credit Unions",
            "subcategory":"Bank",
            "type":"Services"
        }
    ],
    "sg:phone":"+1 260 496 9765",
    "sg:postcode":"46825",
    "sg:province":"IN",
    "wof:name":"Union Federal Bank",
    "wof:placetype":"venue"
},
  "geometry": {"coordinates":[-85.135912,41.129177],"type":"Point"}
}