{
  "type": "Feature",
  "properties": {
    "addr:full":"18 W Canal St Peru IN 46970",
    "addr:housenumber":"18",
    "addr:postcode":"46970",
    "addr:street":"W Canal St",
    "iso:country":"US",
    "sg:address":"18 W Canal St",
    "sg:city":"Peru",
    "sg:classifiers":[
        {
            "category":"Restaurant",
            "type":"Food & Drink"
        }
    ],
    "sg:phone":"+1 765 473 9054",
    "sg:postcode":"46970",
    "sg:province":"IN",
    "wof:name":"Big John's BBQ",
    "wof:placetype":"venue"
},
  "geometry": {"coordinates":[-86.067549,40.751019],"type":"Point"}
}