{
  "type": "Feature",
  "properties": {
    "iso:country":"US",
    "sg:address":"121 S Main St",
    "sg:city":"Elkhart",
    "sg:classifiers":[
        {
            "category":"Personal",
            "subcategory":"Barber",
            "type":"Services"
        }
    ],
    "sg:phone":"+1 574 293 6072",
    "sg:postcode":"46516",
    "sg:province":"IN",
    "sg:tags":[
        "shop"
    ],
    "wof:name":"Seville Barber Shop",
    "wof:placetype":"venue"
},
  "geometry": {"coordinates":[-85.973175,41.686502],"type":"Point"}
}