{
  "type": "Feature",
  "properties": {
    "iso:country":"US",
    "sg:address":"103 W 18th St",
    "sg:city":"Laporte",
    "sg:classifiers":[
        {
            "category":"Social Services",
            "subcategory":"Child Care",
            "type":"Services"
        }
    ],
    "sg:phone":"+1 219 324 0003",
    "sg:postcode":"46350",
    "sg:province":"IN",
    "wof:name":"All For Kids",
    "wof:placetype":"venue"
},
  "geometry": {"coordinates":[-86.720833,41.591469],"type":"Point"}
}