{
  "type": "Feature",
  "properties": {
    "iso:country":"US",
    "sg:address":"2600 Beech St",
    "sg:city":"Valparaiso",
    "sg:classifiers":[
        {
            "category":"Professional",
            "subcategory":"Management & Consulting",
            "type":"Services"
        }
    ],
    "sg:phone":"+1 219 548 8191",
    "sg:postcode":"46383",
    "sg:province":"IN",
    "sg:tags":[
        "consultant"
    ],
    "wof:name":"Axiom Consulting",
    "wof:placetype":"venue"
},
  "geometry": {"coordinates":[-87.030523,41.473829],"type":"Point"}
}