{
  "type": "Feature",
  "properties": {
    "iso:country":"US",
    "sg:address":"718 W McClain St",
    "sg:city":"Scottsburg",
    "sg:classifiers":[
        {
            "category":"Professional",
            "subcategory":"Management & Consulting",
            "type":"Services"
        }
    ],
    "sg:phone":"+1 812 752 5341",
    "sg:postcode":"47170",
    "sg:province":"IN",
    "sg:tags":[
        "business"
    ],
    "wof:name":"Verizon",
    "wof:placetype":"venue"
},
  "geometry": {"coordinates":[-85.77751600000001,38.685737],"type":"Point"}
}