{
  "type": "Feature",
  "properties": {
    "iso:country":"US",
    "sg:address":"140 Co Rd 6 W",
    "sg:city":"Elkhart",
    "sg:classifiers":[
        {
            "category":"Retail",
            "subcategory":"Auto Repair",
            "type":"Services"
        }
    ],
    "sg:phone":"+1 574 266 4573",
    "sg:postcode":"46514",
    "sg:province":"IN",
    "sg:tags":[
        "repairing",
        "automobile"
    ],
    "wof:name":"North Side Svc & Alignment",
    "wof:placetype":"venue"
},
  "geometry": {"coordinates":[-85.97577699999999,41.724238],"type":"Point"}
}