{
  "type": "Feature",
  "properties": {
    "iso:country":"US",
    "sg:address":"10501 W 133rd Ave",
    "sg:city":"Cedar Lake",
    "sg:classifiers":[
        {
            "category":"Manufacturing",
            "subcategory":"Metals",
            "type":"Manufacturing & Wholesale Goods"
        }
    ],
    "sg:phone":"+1 219 374 5567",
    "sg:postcode":"46303",
    "sg:province":"IN",
    "sg:tags":[
        "windows",
        "door",
        "storm"
    ],
    "sg:website":"www.grsd.com",
    "wof:name":"Grand Rapids Sash & Door",
    "wof:placetype":"venue"
},
  "geometry": {"coordinates":[-87.461754,41.377257],"type":"Point"}
}