{
  "type": "Feature",
  "properties": {
    "iso:country":"US",
    "sg:address":"333 US Hwy 150",
    "sg:city":"Hardinsburg",
    "sg:classifiers":[
        {
            "category":"Organizations",
            "subcategory":"Professional Association",
            "type":"Services"
        }
    ],
    "sg:phone":"+1 812 472 9444",
    "sg:postcode":"47125",
    "sg:province":"IN",
    "wof:name":"Hardinsburg Community Assn",
    "wof:placetype":"venue"
},
  "geometry": {"coordinates":[-86.27706,38.459439],"type":"Point"}
}