{
  "type": "Feature",
  "properties": {
    "iso:country":"US",
    "sg:address":"910 E Washington St",
    "sg:city":"Winchester",
    "sg:classifiers":[
        {
            "category":"Banks & Credit Unions",
            "subcategory":"Bank",
            "type":"Services"
        }
    ],
    "sg:phone":"+1 765 584 2274",
    "sg:postcode":"47394",
    "sg:province":"IN",
    "sg:tags":[
        "cashing",
        "check"
    ],
    "wof:name":"United Cash ADVANCE",
    "wof:placetype":"venue"
},
  "geometry": {"coordinates":[-84.96666,40.172017],"type":"Point"}
}