{
  "type": "Feature",
  "properties": {
    "iso:country":"US",
    "sg:address":"6707 W Washington St",
    "sg:city":"Indianapolis",
    "sg:classifiers":[
        {
            "category":"Restaurant",
            "type":"Food & Drink"
        }
    ],
    "sg:phone":"+1 317 244 3988",
    "sg:postcode":"46241",
    "sg:province":"IN",
    "wof:name":"Taqueria Elrodeo",
    "wof:placetype":"venue"
},
  "geometry": {"coordinates":[-86.278009,39.744235],"type":"Point"}
}