{
  "type": "Feature",
  "properties": {
    "addr:full":"1 Virginia Ave Indianapolis IN 46204",
    "addr:housenumber":"1",
    "addr:postcode":"46204",
    "addr:street":"Virginia",
    "iso:country":"US",
    "sg:address":"1 Virginia Ave",
    "sg:city":"Indianapolis",
    "sg:classifiers":[
        {
            "category":"Professional",
            "subcategory":"Accounting & Tax Preparation",
            "type":"Services"
        }
    ],
    "sg:phone":"+1 317 635 1020",
    "sg:postcode":"46204",
    "sg:province":"IN",
    "sg:tags":[
        "return"
    ],
    "wof:name":"George A Farley",
    "wof:placetype":"venue"
},
  "geometry": {"coordinates":[-86.15450800000001,39.76582],"type":"Point"}
}