{
  "type": "Feature",
  "properties": {
    "iso:country":"US",
    "sg:address":"112 Princeton Ln",
    "sg:city":"Logansport",
    "sg:classifiers":[
        {
            "category":"Organizations",
            "subcategory":"Religious Organization",
            "type":"Services"
        }
    ],
    "sg:phone":"+1 574 732 0231",
    "sg:postcode":"46947",
    "sg:province":"IN",
    "wof:name":"Womens Aglow Fellowship",
    "wof:placetype":"venue"
},
  "geometry": {"coordinates":[-86.308074,40.762518],"type":"Point"}
}