{
  "type": "Feature",
  "properties": {
    "iso:country":"US",
    "sg:address":"1070 E 86th St",
    "sg:city":"Indianapolis",
    "sg:classifiers":[
        {
            "category":"Personal",
            "type":"Services"
        }
    ],
    "sg:phone":"+1 317 580 1967",
    "sg:postcode":"46240",
    "sg:province":"IN",
    "sg:tags":[
        "consultant",
        "program",
        "health",
        "fitness"
    ],
    "wof:name":"Flexfitt",
    "wof:placetype":"venue"
},
  "geometry": {"coordinates":[-86.140505,39.912611],"type":"Point"}
}