{
  "type": "Feature",
  "properties": {
    "iso:country":"US",
    "sg:address":"341 N Buckeye St",
    "sg:city":"Osgood",
    "sg:classifiers":[
        {
            "category":"Shopping",
            "subcategory":"Florist",
            "type":"Retail Goods"
        }
    ],
    "sg:phone":"+1 812 689 5349",
    "sg:postcode":"47037",
    "sg:province":"IN",
    "wof:name":"Rose's Floral",
    "wof:placetype":"venue"
},
  "geometry": {"coordinates":[-85.292452,39.131686],"type":"Point"}
}