{
  "type": "Feature",
  "properties": {
    "iso:country":"US",
    "sg:address":"3555 N Fruitridge Ave",
    "sg:city":"Terre Haute",
    "sg:classifiers":[
        {
            "category":"Retail",
            "subcategory":"Auto Repair",
            "type":"Services"
        }
    ],
    "sg:phone":"+1 812 466 9888",
    "sg:postcode":"47804",
    "sg:province":"IN",
    "sg:tags":[
        "repairing",
        "tire"
    ],
    "wof:name":"Fort Harrison Truck Tire Ctr",
    "wof:placetype":"venue"
},
  "geometry": {"coordinates":[-87.360345,39.508322],"type":"Point"}
}