{
  "type": "Feature",
  "properties": {
    "iso:country":"US",
    "sg:address":"4814 E Indian Hollow Rd",
    "sg:city":"Leavenworth",
    "sg:classifiers":[
        {
            "category":"Farming",
            "subcategory":"Farm",
            "type":"Manufacturing & Wholesale Goods"
        }
    ],
    "sg:phone":"+1 812 739 2603",
    "sg:postcode":"47137",
    "sg:province":"IN",
    "sg:tags":[
        "crop",
        "general"
    ],
    "wof:name":"David Schrader Farm",
    "wof:placetype":"venue"
},
  "geometry": {"coordinates":[-86.361968,38.199681],"type":"Point"}
}