{
  "type": "Feature",
  "properties": {
    "iso:country":"US",
    "sg:address":"1105 State Rd 32",
    "sg:city":"Union City",
    "sg:classifiers":[
        {
            "category":"Manufacturing",
            "subcategory":"Metals",
            "type":"Manufacturing & Wholesale Goods"
        }
    ],
    "sg:phone":"+1 765 964 4422",
    "sg:postcode":"47390",
    "sg:province":"IN",
    "sg:tags":[
        "steel"
    ],
    "wof:name":"John Mitchem Outsource",
    "wof:placetype":"venue"
},
  "geometry": {"coordinates":[-84.820819,40.194746],"type":"Point"}
}