{
  "type": "Feature",
  "properties": {
    "addr:full":"7690 Zionsville Rd Indianapolis IN 46268",
    "addr:postcode":"7690;46268",
    "addr:street":"Zionsville Rd",
    "iso:country":"US",
    "sg:address":"7690 Zionsville Rd",
    "sg:city":"Indianapolis",
    "sg:classifiers":[
        {
            "category":"Home & Garden",
            "subcategory":"Building Materials",
            "type":"Retail Goods"
        },
        {
            "category":"Manufacturing",
            "subcategory":"Building Materials",
            "type":"Manufacturing & Wholesale Goods"
        }
    ],
    "sg:phone":"+1 800 732 1379",
    "sg:postcode":"46268",
    "sg:province":"IN",
    "sg:tags":[
        "doors-wholesale",
        "accessory",
        "window",
        "doors",
        "frames",
        "manufacturer"
    ],
    "wof:name":"McComb Window & Door",
    "wof:placetype":"venue"
},
  "geometry": {"coordinates":[-86.259812,39.891274],"type":"Point"}
}