{
  "type": "Feature",
  "properties": {
    "iso:country":"US",
    "sg:address":"635 Barnhill Dr Med Scnce Med Science",
    "sg:city":"Indianapolis",
    "sg:classifiers":[
        {
            "category":"Education",
            "subcategory":"Special Training",
            "type":"Public Place"
        }
    ],
    "sg:phone":"+1 317 274 1734",
    "sg:postcode":"46202",
    "sg:province":"IN",
    "sg:tags":[
        "educational"
    ],
    "wof:name":"I U Med-Pathology Department",
    "wof:placetype":"venue"
},
  "geometry": {"coordinates":[-86.17861499999999,39.776719],"type":"Point"}
}