{
  "type": "Feature",
  "properties": {
    "addr:full":"1248 N Nappanee St Elkhart IN 46514",
    "addr:housenumber":"1248",
    "addr:postcode":"46514",
    "addr:street":"N Nappanee St",
    "iso:country":"US",
    "sg:address":"1248 N Nappanee St",
    "sg:city":"Elkhart",
    "sg:classifiers":[
        {
            "category":"Restaurant",
            "type":"Food & Drink"
        }
    ],
    "sg:menulink":"http://www.allmenus.com/in/osolo/121574-fazolis/menu/",
    "sg:phone":"+1 574 262 9873",
    "sg:postcode":"46514",
    "sg:province":"IN",
    "sg:tags":[
        "italian"
    ],
    "wof:name":"Fazoli's",
    "wof:placetype":"venue"
},
  "geometry": {"coordinates":[-86.003067,41.700702],"type":"Point"}
}