{
  "type": "Feature",
  "properties": {
    "iso:country":"US",
    "sg:address":"51382 Co Rd 133",
    "sg:city":"Bristol",
    "sg:classifiers":[
        {
            "category":"Farming",
            "subcategory":"Dairy Farm",
            "type":"Manufacturing & Wholesale Goods"
        }
    ],
    "sg:phone":"+1 574 825 2369",
    "sg:postcode":"46507",
    "sg:province":"IN",
    "wof:name":"Ray Brenneman",
    "wof:placetype":"venue"
},
  "geometry": {"coordinates":[-85.737515,41.74595],"type":"Point"}
}