{
  "type": "Feature",
  "properties": {
    "iso:country":"US",
    "sg:address":"5046 W Sycamore St",
    "sg:city":"Amo",
    "sg:classifiers":[
        {
            "category":"Real Estate",
            "subcategory":"Real Estate Operator",
            "type":"Services"
        }
    ],
    "sg:phone":"+1 317 539 6030",
    "sg:postcode":"46103",
    "sg:province":"IN",
    "sg:tags":[
        "building",
        "parks"
    ],
    "wof:name":"Town Of Amo Community Building",
    "wof:placetype":"venue"
},
  "geometry": {"coordinates":[-86.615212,39.68994],"type":"Point"}
}