{
  "type": "Feature",
  "properties": {
    "iso:country":"US",
    "sg:address":"14800 McCutchan Rd",
    "sg:city":"Evansville",
    "sg:classifiers":[
        {
            "category":"Personal",
            "type":"Services"
        }
    ],
    "sg:phone":"+1 812 867 3221",
    "sg:postcode":"47725",
    "sg:province":"IN",
    "sg:tags":[
        "consulting"
    ],
    "wof:name":"Beauticontrol",
    "wof:placetype":"venue"
},
  "geometry": {"coordinates":[-87.513035,38.11642],"type":"Point"}
}