{
  "type": "Feature",
  "properties": {
    "iso:country":"US",
    "sg:address":"5615 S Calumet Ave",
    "sg:city":"Hammond",
    "sg:classifiers":[
        {
            "category":"Food & Beverages",
            "subcategory":"Liquor & Beverages",
            "type":"Retail Goods"
        }
    ],
    "sg:phone":"+1 219 937 6044",
    "sg:postcode":"46320",
    "sg:province":"IN",
    "sg:tags":[
        "beer",
        "spirit",
        "wine"
    ],
    "wof:name":"A B Liquors",
    "wof:placetype":"venue"
},
  "geometry": {"coordinates":[-87.508797,41.611301],"type":"Point"}
}