{
  "type": "Feature",
  "properties": {
    "iso:country":"US",
    "sg:address":"16710 Maple City Dr",
    "sg:city":"Goshen",
    "sg:classifiers":[
        {
            "category":"Professional",
            "type":"Services"
        }
    ],
    "sg:phone":"+1 574 538 5112",
    "sg:postcode":"46526",
    "sg:province":"IN",
    "sg:tags":[
        "establishment"
    ],
    "wof:name":"Fabwell Composites",
    "wof:placetype":"venue"
},
  "geometry": {"coordinates":[-85.785309,41.548219],"type":"Point"}
}