{
  "type": "Feature",
  "properties": {
    "addr:full":"701 Wall St Valparaiso IN 46383",
    "addr:housenumber":"701",
    "addr:postcode":"46383",
    "addr:street":"Wall St",
    "iso:country":"US",
    "sg:address":"701 Wall St",
    "sg:city":"Valparaiso",
    "sg:classifiers":[
        {
            "category":"Professional",
            "subcategory":"Management & Consulting",
            "type":"Services"
        }
    ],
    "sg:phone":"+1 219 462 4258",
    "sg:postcode":"46383",
    "sg:province":"IN",
    "sg:tags":[
        "business"
    ],
    "wof:name":"Porter Stark Services",
    "wof:placetype":"venue"
},
  "geometry": {"coordinates":[-87.051053,41.489131],"type":"Point"}
}