{
  "type": "Feature",
  "properties": {
    "iso:country":"US",
    "sg:address":"3102 Brooklyn Ave",
    "sg:city":"Fort Wayne",
    "sg:classifiers":[
        {
            "category":"Wholesale",
            "subcategory":"Apparel",
            "type":"Manufacturing & Wholesale Goods"
        }
    ],
    "sg:phone":"+1 260 478 2723",
    "sg:postcode":"46809",
    "sg:province":"IN",
    "sg:tags":[
        "sportswear"
    ],
    "wof:name":"Alpha Shirt Co",
    "wof:placetype":"venue"
},
  "geometry": {"coordinates":[-85.16511,41.05737],"type":"Point"}
}