{
  "type": "Feature",
  "properties": {
    "iso:country":"US",
    "sg:address":"8774 US Hwy 421",
    "sg:city":"Osgood",
    "sg:classifiers":[
        {
            "category":"Food & Beverages",
            "subcategory":"Liquor & Beverages",
            "type":"Retail Goods"
        }
    ],
    "sg:phone":"+1 812 852 4380",
    "sg:postcode":"47037",
    "sg:province":"IN",
    "sg:tags":[
        "alcoholic"
    ],
    "wof:name":"Napoleon Package Liquor",
    "wof:placetype":"venue"
},
  "geometry": {"coordinates":[-85.33038500000001,39.20188],"type":"Point"}
}