{
  "type": "Feature",
  "properties": {
    "iso:country":"US",
    "sg:address":"2405 W Lexington Ave",
    "sg:city":"Elkhart",
    "sg:classifiers":[
        {
            "category":"Health Services",
            "subcategory":"Doctor",
            "type":"Services"
        }
    ],
    "sg:phone":"+1 574 295 8805",
    "sg:postcode":"46514",
    "sg:province":"IN",
    "sg:tags":[
        "physician",
        "surgeon"
    ],
    "wof:name":"River Oaks Ob/Gyn Assoc",
    "wof:placetype":"venue"
},
  "geometry": {"coordinates":[-86.008033,41.684237],"type":"Point"}
}