{
  "type": "Feature",
  "properties": {
    "iso:country":"US",
    "sg:address":"301 N Morton St",
    "sg:city":"Bloomington",
    "sg:classifiers":[
        {
            "category":"Travel",
            "subcategory":"Travel Agent",
            "type":"Entertainment"
        }
    ],
    "sg:phone":"+1 812 336 6811",
    "sg:postcode":"47404",
    "sg:province":"IN",
    "sg:tags":[
        "agency",
        "bureau"
    ],
    "sg:website":"www.startravelservices.com",
    "wof:name":"Star Travel Svc Inc",
    "wof:placetype":"venue"
},
  "geometry": {"coordinates":[-86.536125,39.169512],"type":"Point"}
}