{
  "type": "Feature",
  "properties": {
    "iso:country":"US",
    "sg:address":"8204 Rockville Rd",
    "sg:city":"Indianapolis",
    "sg:classifiers":[
        {
            "category":"Retail",
            "subcategory":"Laundry & Dry Cleaning",
            "type":"Services"
        }
    ],
    "sg:phone":"+1 317 271 3525",
    "sg:postcode":"46214",
    "sg:province":"IN",
    "sg:tags":[
        "commercial"
    ],
    "wof:name":"One Hour Martinizing",
    "wof:placetype":"venue"
},
  "geometry": {"coordinates":[-86.306404,39.764117],"type":"Point"}
}