{
  "type": "Feature",
  "properties": {
    "iso:country":"US",
    "sg:address":"6375 E Dublin Pike",
    "sg:city":"New Lisbon",
    "sg:classifiers":[
        {
            "category":"Utilities",
            "subcategory":"Telephone",
            "type":"Services"
        }
    ],
    "sg:phone":"+1 765 332 2413",
    "sg:postcode":"47387",
    "sg:province":"IN",
    "sg:tags":[
        "company"
    ],
    "sg:website":"www.nltc.net",
    "wof:name":"New Lisbon Telephone Co",
    "wof:placetype":"venue"
},
  "geometry": {"coordinates":[-85.264108,39.86387],"type":"Point"}
}