{
  "type": "Feature",
  "properties": {
    "iso:country":"US",
    "sg:address":"301 Dal Mar Way",
    "sg:city":"Nappanee",
    "sg:classifiers":[
        {
            "category":"Wholesale",
            "subcategory":"Furniture",
            "type":"Manufacturing & Wholesale Goods"
        }
    ],
    "sg:phone":"+1 574 773 7087",
    "sg:postcode":"46550",
    "sg:province":"IN",
    "sg:tags":[
        "seating",
        "company"
    ],
    "sg:website":"www.rameinc.com",
    "wof:name":"Rame",
    "wof:placetype":"venue"
},
  "geometry": {"coordinates":[-85.97797,41.44367],"type":"Point"}
}