{
  "type": "Feature",
  "properties": {
    "addr:full":"307 E 3rd St Marion IN 46952",
    "addr:housenumber":"307",
    "addr:postcode":"46952",
    "addr:street":"E 3Rd St",
    "iso:country":"US",
    "sg:address":"307 E 3rd St",
    "sg:city":"Marion",
    "sg:classifiers":[
        {
            "category":"Retail",
            "subcategory":"Auto Repair",
            "type":"Services"
        }
    ],
    "sg:phone":"+1 765 664 3991",
    "sg:postcode":"46952",
    "sg:province":"IN",
    "sg:tags":[
        "muffler",
        "exhaust",
        "system",
        "automotive"
    ],
    "wof:name":"Holt Muffler Shops",
    "wof:placetype":"venue"
},
  "geometry": {"coordinates":[-85.656226,40.558896],"type":"Point"}
}