{
  "type": "Feature",
  "properties": {
    "iso:country":"US",
    "sg:address":"2120 Indianapolis Blvd",
    "sg:city":"Schererville",
    "sg:classifiers":[
        {
            "category":"Banks & Credit Unions",
            "subcategory":"Investment Brokerage",
            "type":"Services"
        }
    ],
    "sg:phone":"+1 219 322 9932",
    "sg:postcode":"46375",
    "sg:province":"IN",
    "sg:tags":[
        "advisory"
    ],
    "wof:name":"Eylander Financial Services",
    "wof:placetype":"venue"
},
  "geometry": {"coordinates":[-87.470764,41.486805],"type":"Point"}
}