{
  "type": "Feature",
  "properties": {
    "iso:country":"US",
    "sg:address":"14170 Greene St NE",
    "sg:city":"Palmyra",
    "sg:classifiers":[
        {
            "category":"Organizations",
            "subcategory":"Religious Organization",
            "type":"Services"
        }
    ],
    "sg:phone":"+1 812 364 4126",
    "sg:postcode":"47164",
    "sg:province":"IN",
    "sg:tags":[
        "church"
    ],
    "wof:name":"Palmyra United Methodist Chr",
    "wof:placetype":"venue"
},
  "geometry": {"coordinates":[-86.11012599999999,38.407294],"type":"Point"}
}