{
  "type": "Feature",
  "properties": {
    "addr:full":"4475 N Benton Ct Bloomington IN 47408",
    "addr:housenumber":"4475",
    "addr:postcode":"47408",
    "addr:street":"N Benton Ct",
    "iso:country":"US",
    "sg:address":"4475 N Benton Ct",
    "sg:city":"Bloomington",
    "sg:classifiers":[
        {
            "category":"Professional",
            "subcategory":"Lawyer & Legal Services",
            "type":"Services"
        }
    ],
    "sg:phone":"+1 812 333 1384",
    "sg:postcode":"47408",
    "sg:province":"IN",
    "wof:name":"Hager C Paul Jr",
    "wof:placetype":"venue"
},
  "geometry": {"coordinates":[-86.46959699999999,39.2313],"type":"Point"}
}