{
  "type": "Feature",
  "properties": {
    "iso:country":"US",
    "sg:address":"13514 Dallas Ln",
    "sg:city":"Carmel",
    "sg:classifiers":[
        {
            "category":"Home & Garden",
            "subcategory":"Garden Supply",
            "type":"Retail Goods"
        }
    ],
    "sg:phone":"+1 317 846 3400",
    "sg:postcode":"46033",
    "sg:province":"IN",
    "sg:tags":[
        "nurseryman"
    ],
    "wof:name":"John Platte Office",
    "wof:placetype":"venue"
},
  "geometry": {"coordinates":[-86.098422,39.982807],"type":"Point"}
}