{
  "type": "Feature",
  "properties": {
    "addr:full":"3607 S Fagin St Terre Haute IN 47802",
    "addr:housenumber":"3607",
    "addr:postcode":"47802",
    "addr:street":"S Fagin St",
    "iso:country":"US",
    "sg:address":"3607 S Fagin St",
    "sg:city":"Terre Haute",
    "sg:classifiers":[
        {
            "category":"Retail",
            "subcategory":"Repair Shop",
            "type":"Services"
        }
    ],
    "sg:phone":"+1 812 234 3637",
    "sg:postcode":"47802",
    "sg:province":"IN",
    "sg:tags":[
        "welding"
    ],
    "wof:name":"Tipton Welding",
    "wof:placetype":"venue"
},
  "geometry": {"coordinates":[-87.36944699999999,39.423835],"type":"Point"}
}