{
  "type": "Feature",
  "properties": {
    "iso:country":"US",
    "sg:address":"2811 Oxford Ln",
    "sg:city":"Indianapolis",
    "sg:classifiers":[
        {
            "category":"Professional",
            "type":"Services"
        }
    ],
    "sg:phone":"+1 317 926 4191",
    "sg:postcode":"46218",
    "sg:province":"IN",
    "sg:tags":[
        "establishment"
    ],
    "wof:name":"Express Pay",
    "wof:placetype":"venue"
},
  "geometry": {"coordinates":[-86.116699,39.803867],"type":"Point"}
}