{
  "type": "Feature",
  "properties": {
    "iso:country":"US",
    "sg:address":"1813 E 12th St",
    "sg:city":"Mishawaka",
    "sg:classifiers":[
        {
            "category":"Restaurant",
            "type":"Food & Drink"
        }
    ],
    "sg:phone":"+1 574 259 3898",
    "sg:postcode":"46544",
    "sg:province":"IN",
    "wof:name":"Office Lounge",
    "wof:placetype":"venue"
},
  "geometry": {"coordinates":[-86.144879,41.651288],"type":"Point"}
}