{
  "type": "Feature",
  "properties": {
    "iso:country":"US",
    "sg:address":"4803 State Rd 3",
    "sg:city":"Otisco",
    "sg:classifiers":[
        {
            "category":"Freight",
            "type":"Transportation"
        }
    ],
    "sg:phone":"+1 812 256 2371",
    "sg:postcode":"47163",
    "sg:province":"IN",
    "sg:tags":[
        "operator",
        "local",
        "trucking"
    ],
    "wof:name":"R G Transportation Inc",
    "wof:placetype":"venue"
},
  "geometry": {"coordinates":[-85.669055,38.512598],"type":"Point"}
}