{
  "type": "Feature",
  "properties": {
    "iso:country":"US",
    "sg:address":"1480 Fort Harrison Rd",
    "sg:city":"Terre Haute",
    "sg:classifiers":[
        {
            "category":"Shopping",
            "subcategory":"Gifts & Souvenirs",
            "type":"Retail Goods"
        }
    ],
    "sg:phone":"+1 812 466 5878",
    "sg:postcode":"47804",
    "sg:province":"IN",
    "sg:tags":[
        "party",
        "supply"
    ],
    "wof:name":"Dean's Party Mania North",
    "wof:placetype":"venue"
},
  "geometry": {"coordinates":[-87.394654,39.506751],"type":"Point"}
}