{
  "type": "Feature",
  "properties": {
    "addr:full":"10640 E 59th St Indianapolis IN 46236",
    "addr:housenumber":"10640",
    "addr:postcode":"46236",
    "addr:street":"E 59Th St",
    "iso:country":"US",
    "sg:address":"10640 E 59th St",
    "sg:city":"Indianapolis",
    "sg:classifiers":[
        {
            "category":"Retail",
            "subcategory":"Repair Shop",
            "type":"Services"
        }
    ],
    "sg:phone":"+1 317 826 3200",
    "sg:postcode":"46236",
    "sg:province":"IN",
    "sg:tags":[
        "refrigerator",
        "freezer"
    ],
    "sg:website":"www.icorinternational.com",
    "wof:name":"Icor International Inc",
    "wof:placetype":"venue"
},
  "geometry": {"coordinates":[-85.976596,39.863201],"type":"Point"}
}