{
  "type": "Feature",
  "properties": {
    "iso:country":"US",
    "sg:address":"2500 McKinley Ave",
    "sg:city":"Fort Wayne",
    "sg:classifiers":[
        {
            "category":"Home & Garden",
            "subcategory":"Building Materials",
            "type":"Retail Goods"
        }
    ],
    "sg:phone":"+1 260 432 4524",
    "sg:postcode":"46802",
    "sg:province":"IN",
    "sg:tags":[
        "glass",
        "window",
        "plate"
    ],
    "wof:name":"Affordable Auto Glass",
    "wof:placetype":"venue"
},
  "geometry": {"coordinates":[-85.171368,41.060276],"type":"Point"}
}