{
  "type": "Feature",
  "properties": {
    "iso:country":"US",
    "sg:address":"635 E Carmel Dr",
    "sg:city":"Carmel",
    "sg:classifiers":[
        {
            "category":"Restaurant",
            "type":"Food & Drink"
        },
        {
            "category":"Ice Cream",
            "type":"Food & Drink"
        }
    ],
    "sg:menulink":"http://www.allmenus.com/in/carmel/92512-steak-n-shake/menu/",
    "sg:phone":"+1 317 844 3936",
    "sg:postcode":"46032",
    "sg:province":"IN",
    "sg:tags":[
        "american",
        "ice",
        "cream"
    ],
    "wof:name":"Steak 'n Shake",
    "wof:placetype":"venue"
},
  "geometry": {"coordinates":[-86.115313,39.961562],"type":"Point"}
}