{
  "type": "Feature",
  "properties": {
    "addr:full":"1001 Broad Ripple Ave Ste C Indianapolis IN 46220",
    "addr:housenumber":"1001",
    "addr:postcode":"46220",
    "addr:street":"Broad Ripple Ave Ste C",
    "iso:country":"US",
    "sg:address":"1001 Broad Ripple Ave Ste C",
    "sg:city":"Indianapolis",
    "sg:classifiers":[
        {
            "category":"Arena",
            "subcategory":"Sports Club",
            "type":"Entertainment"
        }
    ],
    "sg:phone":"+1 317 255 3220",
    "sg:postcode":"46220",
    "sg:province":"IN",
    "sg:tags":[
        "ticket",
        "sale"
    ],
    "sg:website":"http://www.frontrowindy.com",
    "wof:name":"Front Row Tickets",
    "wof:placetype":"venue"
},
  "geometry": {"coordinates":[-86.141693,39.86974],"type":"Point"}
}