{
  "type": "Feature",
  "properties": {
    "iso:country":"US",
    "sg:address":"120 W Washington St",
    "sg:city":"Shelbyville",
    "sg:classifiers":[
        {
            "category":"Social Services",
            "subcategory":"Adult Care",
            "type":"Services"
        }
    ],
    "sg:phone":"+1 317 398 0127",
    "sg:postcode":"46176",
    "sg:province":"IN",
    "sg:tags":[
        "organization",
        "senior",
        "citizen"
    ],
    "wof:name":"Shelby Senior Svc Inc",
    "wof:placetype":"venue"
},
  "geometry": {"coordinates":[-85.781324,39.524518],"type":"Point"}
}