{
  "type": "Feature",
  "properties": {
    "iso:country":"US",
    "sg:address":"2334 E 116th St",
    "sg:city":"Carmel",
    "sg:classifiers":[
        {
            "category":"Shopping",
            "type":"Retail Goods"
        }
    ],
    "sg:phone":"+1 317 844 8553",
    "sg:postcode":"46032",
    "sg:province":"IN",
    "sg:tags":[
        "telephone",
        "cellular"
    ],
    "wof:name":"Radio Shack",
    "wof:placetype":"venue"
},
  "geometry": {"coordinates":[-86.117498,39.956731],"type":"Point"}
}