{
  "type": "Feature",
  "properties": {
    "iso:country":"US",
    "sg:address":"4202 Charlestown Rd",
    "sg:city":"New Albany",
    "sg:classifiers":[
        {
            "category":"Education",
            "subcategory":"School",
            "type":"Public Place"
        }
    ],
    "sg:phone":"+1 812 949 4266",
    "sg:postcode":"47150",
    "sg:province":"IN",
    "sg:website":"www.prossertech.org",
    "wof:name":"Charles A Prosser Vocational",
    "wof:placetype":"venue"
},
  "geometry": {"coordinates":[-85.787666,38.357085],"type":"Point"}
}