{
  "type": "Feature",
  "properties": {
    "addr:full":"7949 Calumet Ave Munster IN 46321",
    "addr:housenumber":"7949",
    "addr:postcode":"46321",
    "addr:street":"Calumet Ave",
    "iso:country":"US",
    "sg:address":"7949 Calumet Ave",
    "sg:city":"Munster",
    "sg:classifiers":[
        {
            "category":"Restaurant",
            "type":"Food & Drink"
        }
    ],
    "sg:menulink":"http://www.allmenus.com/in/north/208096-taco-bell/menu/",
    "sg:phone":"+1 219 836 4102",
    "sg:postcode":"46321",
    "sg:province":"IN",
    "sg:tags":[
        "mexican"
    ],
    "wof:name":"Taco Bell",
    "wof:placetype":"venue"
},
  "geometry": {"coordinates":[-87.50896400000001,41.567805],"type":"Point"}
}