{
  "type": "Feature",
  "properties": {
    "iso:country":"US",
    "sg:address":"226 Windmill Trl S",
    "sg:city":"Greenwood",
    "sg:classifiers":[
        {
            "category":"Professional",
            "subcategory":"Art Services",
            "type":"Services"
        }
    ],
    "sg:phone":"+1 317 882 1744",
    "sg:postcode":"46142",
    "sg:province":"IN",
    "sg:tags":[
        "graphic",
        "designer"
    ],
    "wof:name":"J P Design LTD",
    "wof:placetype":"venue"
},
  "geometry": {"coordinates":[-86.18306200000001,39.61029],"type":"Point"}
}