{
  "type": "Feature",
  "properties": {
    "iso:country":"US",
    "sg:address":"8245 N Dog Trot Ln",
    "sg:city":"Morgantown",
    "sg:classifiers":[
        {
            "category":"Building & Trades",
            "subcategory":"Construction",
            "type":"Services"
        }
    ],
    "sg:phone":"+1 812 597 0432",
    "sg:postcode":"46160",
    "sg:province":"IN",
    "sg:tags":[
        "house",
        "nonresidential"
    ],
    "wof:name":"Embreys Construction",
    "wof:placetype":"venue"
},
  "geometry": {"coordinates":[-86.272628,39.312756],"type":"Point"}
}