{
  "type": "Feature",
  "properties": {
    "addr:full":"1432 Broad Ripple Ave Indianapolis IN 46220",
    "addr:housenumber":"1432",
    "addr:postcode":"46220",
    "addr:street":"Broad Ripple Ave",
    "iso:country":"US",
    "sg:address":"1432 Broad Ripple Ave",
    "sg:city":"Indianapolis",
    "sg:classifiers":[
        {
            "category":"Shopping",
            "subcategory":"Pets & Pet Supplies",
            "type":"Retail Goods"
        },
        {
            "category":"Retail",
            "subcategory":"Animal Services",
            "type":"Services"
        }
    ],
    "sg:phone":"+1 317 253 2672",
    "sg:postcode":"46220",
    "sg:province":"IN",
    "sg:tags":[
        "grooming",
        "dog",
        "cat"
    ],
    "wof:name":"Broad Ripple Canine Design",
    "wof:placetype":"venue"
},
  "geometry": {"coordinates":[-86.134615,39.868771],"type":"Point"}
}