{
  "type": "Feature",
  "properties": {
    "iso:country":"US",
    "sg:address":"252 N Main St",
    "sg:city":"Frankfort",
    "sg:classifiers":[
        {
            "category":"Professional",
            "subcategory":"Advertising",
            "type":"Services"
        }
    ],
    "sg:phone":"+1 765 659 5240",
    "sg:postcode":"46041",
    "sg:province":"IN",
    "sg:tags":[
        "counselor"
    ],
    "wof:name":"Daily Advertising",
    "wof:placetype":"venue"
},
  "geometry": {"coordinates":[-86.51205400000001,40.282176],"type":"Point"}
}