{
  "type": "Feature",
  "properties": {
    "iso:country":"US",
    "sg:address":"7560 N 1050 E",
    "sg:city":"Howe",
    "sg:classifiers":[
        {
            "category":"Manufacturing",
            "subcategory":"Pet Food",
            "type":"Manufacturing & Wholesale Goods"
        }
    ],
    "sg:phone":"+1 260 367 2394",
    "sg:postcode":"46746",
    "sg:province":"IN",
    "sg:tags":[
        "milling"
    ],
    "wof:name":"Greenfield Mills Inc",
    "wof:placetype":"venue"
},
  "geometry": {"coordinates":[-85.225455,41.751281],"type":"Point"}
}