{
  "type": "Feature",
  "properties": {
    "iso:country":"US",
    "sg:address":"71075 Co Rd 23",
    "sg:city":"New Paris",
    "sg:classifiers":[
        {
            "category":"Real Estate",
            "subcategory":"Real Estate Operator",
            "type":"Services"
        }
    ],
    "sg:phone":"+1 574 831 2697",
    "sg:postcode":"46553",
    "sg:province":"IN",
    "sg:tags":[
        "farm",
        "corn",
        "property",
        "soybean",
        "lessor"
    ],
    "wof:name":"Robert Lutes",
    "wof:placetype":"venue"
},
  "geometry": {"coordinates":[-85.838776,41.462984],"type":"Point"}
}