{
  "type": "Feature",
  "properties": {
    "addr:full":"1717 Hart St Vincennes IN 47591",
    "addr:housenumber":"1717",
    "addr:postcode":"47591",
    "addr:street":"Hart St",
    "iso:country":"US",
    "sg:address":"1717 Hart St",
    "sg:city":"Vincennes",
    "sg:classifiers":[
        {
            "category":"Restaurant",
            "type":"Food & Drink"
        }
    ],
    "sg:phone":"+1 812 886 3990",
    "sg:postcode":"47591",
    "sg:province":"IN",
    "wof:name":"La Fiesta Mexican Restaurant",
    "wof:placetype":"venue"
},
  "geometry": {"coordinates":[-87.515676,38.669582],"type":"Point"}
}