{
  "type": "Feature",
  "properties": {
    "iso:country":"US",
    "sg:address":"344 Clark Rd",
    "sg:city":"Charlestown",
    "sg:classifiers":[
        {
            "category":"Insurance",
            "subcategory":"Insurance Agent",
            "type":"Services"
        }
    ],
    "sg:phone":"+1 812 256 6575",
    "sg:postcode":"47111",
    "sg:province":"IN",
    "wof:name":"Crawford Enterprises",
    "wof:placetype":"venue"
},
  "geometry": {"coordinates":[-85.67511,38.44414],"type":"Point"}
}