{
  "type": "Feature",
  "properties": {
    "iso:country":"US",
    "sg:address":"9084 Technology Dr",
    "sg:city":"Fishers",
    "sg:classifiers":[
        {
            "category":"Real Estate",
            "subcategory":"Architect",
            "type":"Services"
        }
    ],
    "sg:phone":"+1 317 558 2822",
    "sg:postcode":"46038",
    "sg:province":"IN",
    "wof:name":"M D Architects",
    "wof:placetype":"venue"
},
  "geometry": {"coordinates":[-86.009875,39.961185],"type":"Point"}
}