{
  "type": "Feature",
  "properties": {
    "addr:full":"66485 State Rd 19 Wakarusa IN 46573",
    "addr:housenumber":"66485;19",
    "addr:postcode":"46573",
    "addr:street":"State Rd",
    "iso:country":"US",
    "sg:address":"66485 State Rd 19",
    "sg:city":"Wakarusa",
    "sg:classifiers":[
        {
            "category":"Freight",
            "type":"Transportation"
        }
    ],
    "sg:phone":"+1 574 862 2444",
    "sg:postcode":"46573",
    "sg:province":"IN",
    "sg:tags":[
        "trailer"
    ],
    "wof:name":"U S Rv Transport",
    "wof:placetype":"venue"
},
  "geometry": {"coordinates":[-86.001469,41.529432],"type":"Point"}
}