{
  "type": "Feature",
  "properties": {
    "iso:country":"US",
    "sg:address":"501 N 3rd St",
    "sg:city":"Lafayette",
    "sg:classifiers":[
        {
            "category":"Building & Trades",
            "subcategory":"Construction",
            "type":"Services"
        }
    ],
    "sg:phone":"+1 765 474 9184",
    "sg:postcode":"47901",
    "sg:province":"IN",
    "sg:tags":[
        "house"
    ],
    "wof:name":"Premier Contracting",
    "wof:placetype":"venue"
},
  "geometry": {"coordinates":[-86.894309,40.422708],"type":"Point"}
}