{
  "type": "Feature",
  "properties": {
    "addr:full":"872 S Meridian St Sunman IN 47041",
    "addr:housenumber":"872",
    "addr:postcode":"47041",
    "addr:street":"S Meridian St",
    "iso:country":"US",
    "sg:address":"872 S Meridian St",
    "sg:city":"Sunman",
    "sg:classifiers":[
        {
            "category":"Social Services",
            "subcategory":"Child Care",
            "type":"Services"
        }
    ],
    "sg:phone":"+1 812 623 5433",
    "sg:postcode":"47041",
    "sg:province":"IN",
    "wof:name":"Kreative Kids Learning Ctr",
    "wof:placetype":"venue"
},
  "geometry": {"coordinates":[-85.094684,39.226722],"type":"Point"}
}