{
  "type": "Feature",
  "properties": {
    "iso:country":"US",
    "sg:address":"25723 Freda Dr",
    "sg:city":"Elkhart",
    "sg:classifiers":[
        {
            "category":"Building & Trades",
            "subcategory":"Construction",
            "type":"Services"
        }
    ],
    "sg:phone":"+1 574 266 1224",
    "sg:postcode":"46514",
    "sg:province":"IN",
    "sg:tags":[
        "roofing",
        "contractor"
    ],
    "wof:name":"All Pro Roofing & Remodeling",
    "wof:placetype":"venue"
},
  "geometry": {"coordinates":[-85.961257,41.725465],"type":"Point"}
}