{
  "type": "Feature",
  "properties": {
    "iso:country":"US",
    "sg:address":"1510 E 77th St",
    "sg:city":"Indianapolis",
    "sg:classifiers":[
        {
            "category":"Communications",
            "subcategory":"Film & Video Production",
            "type":"Services"
        }
    ],
    "sg:phone":"+1 317 259 1350",
    "sg:postcode":"46240",
    "sg:province":"IN",
    "sg:tags":[
        "motion"
    ],
    "wof:name":"Wertzworks",
    "wof:placetype":"venue"
},
  "geometry": {"coordinates":[-86.134119,39.895265],"type":"Point"}
}