{
  "type": "Feature",
  "properties": {
    "iso:country":"US",
    "sg:address":"4008 S Maple Ln",
    "sg:city":"Muncie",
    "sg:classifiers":[
        {
            "category":"Real Estate",
            "subcategory":"Real Estate Agent",
            "type":"Services"
        }
    ],
    "sg:phone":"+1 765 284 9248",
    "sg:postcode":"47302",
    "sg:province":"IN",
    "wof:name":"JWT Properties Inc",
    "wof:placetype":"venue"
},
  "geometry": {"coordinates":[-85.372169,40.157659],"type":"Point"}
}