{
  "type": "Feature",
  "properties": {
    "iso:country":"US",
    "sg:address":"1374 S Range Line Rd",
    "sg:city":"Carmel",
    "sg:classifiers":[
        {
            "category":"Shopping",
            "subcategory":"Gifts & Souvenirs",
            "type":"Retail Goods"
        }
    ],
    "sg:phone":"+1 317 844 3474",
    "sg:postcode":"46032",
    "sg:province":"IN",
    "sg:tags":[
        "shop"
    ],
    "wof:name":"Pistachio Designs",
    "wof:placetype":"venue"
},
  "geometry": {"coordinates":[-86.126866,39.958807],"type":"Point"}
}