{
  "type": "Feature",
  "properties": {
    "iso:country":"US",
    "sg:address":"19969 Longview Dr",
    "sg:city":"Lawrenceburg",
    "sg:classifiers":[
        {
            "category":"Education",
            "subcategory":"Vocational School",
            "type":"Public Place"
        }
    ],
    "sg:phone":"+1 812 537 9738",
    "sg:postcode":"47025",
    "sg:province":"IN",
    "sg:tags":[
        "sales"
    ],
    "wof:name":"Plato Learning Inc",
    "wof:placetype":"venue"
},
  "geometry": {"coordinates":[-84.837233,39.160668],"type":"Point"}
}