{
  "type": "Feature",
  "properties": {
    "iso:country":"US",
    "sg:address":"7420 Sacramento Dr",
    "sg:city":"Greenfield",
    "sg:classifiers":[
        {
            "category":"Building & Trades",
            "subcategory":"Construction",
            "type":"Services"
        }
    ],
    "sg:phone":"+1 317 894 7360",
    "sg:postcode":"46140",
    "sg:province":"IN",
    "sg:tags":[
        "home",
        "builder"
    ],
    "wof:name":"Horsley Masonry Homes",
    "wof:placetype":"venue"
},
  "geometry": {"coordinates":[-85.940833,39.802401],"type":"Point"}
}