{
  "type": "Feature",
  "properties": {
    "iso:country":"US",
    "sg:address":"6559 Co Rd 7a",
    "sg:city":"Garrett",
    "sg:classifiers":[
        {
            "category":"Farming",
            "subcategory":"Farm",
            "type":"Manufacturing & Wholesale Goods"
        }
    ],
    "sg:phone":"+1 260 357 3669",
    "sg:postcode":"46738",
    "sg:province":"IN",
    "sg:tags":[
        "crop",
        "general"
    ],
    "wof:name":"Ted Thrush",
    "wof:placetype":"venue"
},
  "geometry": {"coordinates":[-85.14686,41.291609],"type":"Point"}
}