{
  "type": "Feature",
  "properties": {
    "iso:country":"US",
    "sg:address":"4120 N 1st Ave",
    "sg:city":"Evansville",
    "sg:classifiers":[
        {
            "category":"Shopping",
            "type":"Retail Goods"
        }
    ],
    "sg:phone":"+1 812 421 1357",
    "sg:postcode":"47710",
    "sg:province":"IN",
    "sg:tags":[
        "telephone",
        "cellular"
    ],
    "wof:name":"Spalding Communications",
    "wof:placetype":"venue"
},
  "geometry": {"coordinates":[-87.574163,38.016359],"type":"Point"}
}