{
  "type": "Feature",
  "properties": {
    "iso:country":"US",
    "sg:address":"320 E Linden Ave",
    "sg:city":"Logansport",
    "sg:classifiers":[
        {
            "category":"Personal",
            "subcategory":"Beauty Salon",
            "type":"Services"
        }
    ],
    "sg:phone":"+1 574 732 0391",
    "sg:postcode":"46947",
    "sg:province":"IN",
    "sg:tags":[
        "manicuring"
    ],
    "wof:name":"Puttin On The Nails",
    "wof:placetype":"venue"
},
  "geometry": {"coordinates":[-86.364621,40.758635],"type":"Point"}
}