{
  "type": "Feature",
  "properties": {
    "iso:country":"US",
    "sg:address":"14340 Whitworth Dr",
    "sg:city":"Carmel",
    "sg:classifiers":[
        {
            "category":"Building & Trades",
            "subcategory":"Construction",
            "type":"Services"
        }
    ],
    "sg:phone":"+1 317 848 4788",
    "sg:postcode":"46033",
    "sg:province":"IN",
    "sg:tags":[
        "contractor"
    ],
    "wof:name":"Lynch Douglas Builders",
    "wof:placetype":"venue"
},
  "geometry": {"coordinates":[-86.106655,39.997111],"type":"Point"}
}