{
  "type": "Feature",
  "properties": {
    "iso:country":"US",
    "sg:address":"6801 E 96th St",
    "sg:city":"Indianapolis",
    "sg:classifiers":[
        {
            "category":"Personal",
            "type":"Services"
        }
    ],
    "sg:phone":"+1 317 842 8260",
    "sg:postcode":"46038",
    "sg:province":"IN",
    "sg:tags":[
        "hair",
        "replacement"
    ],
    "wof:name":"C J's Hair TECHNOLOGIES",
    "wof:placetype":"venue"
},
  "geometry": {"coordinates":[-86.049648,39.927123],"type":"Point"}
}