{
  "type": "Feature",
  "properties": {
    "iso:country":"US",
    "sg:address":"733 Louisedale Dr",
    "sg:city":"Fort Wayne",
    "sg:classifiers":[
        {
            "category":"Building & Trades",
            "subcategory":"Construction",
            "type":"Services"
        }
    ],
    "sg:phone":"+1 260 483 1604",
    "sg:postcode":"46808",
    "sg:province":"IN",
    "sg:tags":[
        "general",
        "contractor"
    ],
    "wof:name":"Mc Comb Construction Inc",
    "wof:placetype":"venue"
},
  "geometry": {"coordinates":[-85.153899,41.113686],"type":"Point"}
}