{
  "type": "Feature",
  "properties": {
    "iso:country":"US",
    "sg:address":"8240 E 96th St",
    "sg:city":"Fishers",
    "sg:classifiers":[
        {
            "category":"Shopping",
            "subcategory":"Jewelry",
            "type":"Retail Goods"
        }
    ],
    "sg:phone":"+1 317 577 5584",
    "sg:postcode":"46037",
    "sg:province":"IN",
    "wof:name":"Jewelry Paradise",
    "wof:placetype":"venue"
},
  "geometry": {"coordinates":[-86.022853,39.927423],"type":"Point"}
}