{
  "type": "Feature",
  "properties": {
    "iso:country":"US",
    "sg:address":"5166 Treaty Line Rd",
    "sg:city":"Hagerstown",
    "sg:classifiers":[
        {
            "category":"Home & Garden",
            "subcategory":"Building Materials",
            "type":"Retail Goods"
        }
    ],
    "sg:phone":"+1 765 489 4119",
    "sg:postcode":"47346",
    "sg:province":"IN",
    "sg:tags":[
        "type",
        "door"
    ],
    "wof:name":"M D Door Svc",
    "wof:placetype":"venue"
},
  "geometry": {"coordinates":[-85.151681,39.903064],"type":"Point"}
}