{
  "type": "Feature",
  "properties": {
    "iso:country":"US",
    "sg:address":"2000 E 116th St",
    "sg:city":"Carmel",
    "sg:classifiers":[
        {
            "category":"Insurance",
            "subcategory":"Insurance Agent",
            "type":"Services"
        }
    ],
    "sg:phone":"+1 317 571 1661",
    "sg:postcode":"46032",
    "sg:province":"IN",
    "wof:name":"Covert Insurance Agency",
    "wof:placetype":"venue"
},
  "geometry": {"coordinates":[-86.118416,39.956657],"type":"Point"}
}