{
  "type": "Feature",
  "properties": {
    "iso:country":"US",
    "sg:address":"6620 Parkdale Pl",
    "sg:city":"Indianapolis",
    "sg:classifiers":[
        {
            "category":"Health Services",
            "subcategory":"Doctor",
            "type":"Services"
        }
    ],
    "sg:phone":"+1 317 297 7773",
    "sg:postcode":"46254",
    "sg:province":"IN",
    "sg:tags":[
        "physician",
        "surgeon"
    ],
    "wof:name":"I U Medical Group",
    "wof:placetype":"venue"
},
  "geometry": {"coordinates":[-86.27853899999999,39.825672],"type":"Point"}
}