{
  "type": "Feature",
  "properties": {
    "addr:full":"9720 Homestead Rd Roanoke IN 46783",
    "addr:housenumber":"9720",
    "addr:postcode":"46783",
    "addr:street":"Homestead Rd",
    "iso:country":"US",
    "sg:address":"9720 Homestead Rd",
    "sg:city":"Roanoke",
    "sg:classifiers":[
        {
            "category":"Professional",
            "subcategory":"Business Services",
            "type":"Services"
        }
    ],
    "sg:phone":"+1 260 672 1161",
    "sg:postcode":"46783",
    "sg:province":"IN",
    "wof:name":"Mam Family Limited Partnership",
    "wof:placetype":"venue"
},
  "geometry": {"coordinates":[-85.283646,40.993778],"type":"Point"}
}