{
  "type": "Feature",
  "properties": {
    "iso:country":"US",
    "sg:address":"1998 Deerfield Ln",
    "sg:city":"Kendallville",
    "sg:classifiers":[
        {
            "category":"Real Estate",
            "subcategory":"Real Estate Operator",
            "type":"Services"
        }
    ],
    "sg:phone":"+1 260 347 5600",
    "sg:postcode":"46755",
    "sg:province":"IN",
    "sg:tags":[
        "apartment"
    ],
    "wof:name":"Deerfield Village Apartments",
    "wof:placetype":"venue"
},
  "geometry": {"coordinates":[-85.231794,41.443221],"type":"Point"}
}