{
  "type": "Feature",
  "properties": {
    "iso:country":"US",
    "sg:address":"8857 N Co Rd 235 W",
    "sg:city":"Brazil",
    "sg:classifiers":[
        {
            "category":"Professional",
            "type":"Services"
        }
    ],
    "sg:phone":"+1 812 448 1432",
    "sg:postcode":"47834",
    "sg:province":"IN",
    "wof:name":"Designer Dog Mail Boxes",
    "wof:placetype":"venue"
},
  "geometry": {"coordinates":[-87.150774,39.516692],"type":"Point"}
}