{
  "type": "Feature",
  "properties": {
    "iso:country":"US",
    "sg:address":"1164 E Virginia St",
    "sg:city":"Evansville",
    "sg:classifiers":[
        {
            "category":"Food & Beverages",
            "subcategory":"Liquor & Beverages",
            "type":"Retail Goods"
        }
    ],
    "sg:phone":"+1 812 422 5499",
    "sg:postcode":"47711",
    "sg:province":"IN",
    "wof:name":"Wagon Wheel Liquors Inc",
    "wof:placetype":"venue"
},
  "geometry": {"coordinates":[-87.543346,37.981427],"type":"Point"}
}