{
  "type": "Feature",
  "properties": {
    "iso:country":"US",
    "sg:address":"11500 N 600 E",
    "sg:city":"Morristown",
    "sg:classifiers":[
        {
            "category":"Farming",
            "subcategory":"Farm",
            "type":"Manufacturing & Wholesale Goods"
        }
    ],
    "sg:phone":"+1 765 763 6453",
    "sg:postcode":"46161",
    "sg:province":"IN",
    "sg:tags":[
        "crop",
        "general"
    ],
    "wof:name":"Harry Ferris",
    "wof:placetype":"venue"
},
  "geometry": {"coordinates":[-85.67095500000001,39.685011],"type":"Point"}
}