{
  "type": "Feature",
  "properties": {
    "iso:country":"US",
    "sg:address":"2319 Cline Ave",
    "sg:city":"Gary",
    "sg:classifiers":[
        {
            "category":"Retail",
            "subcategory":"Auto Repair",
            "type":"Services"
        }
    ],
    "sg:phone":"+1 219 844 9743",
    "sg:postcode":"46406",
    "sg:province":"IN",
    "sg:tags":[
        "wrecker"
    ],
    "wof:name":"Oldenberg & Son Inc",
    "wof:placetype":"venue"
},
  "geometry": {"coordinates":[-87.432716,41.579868],"type":"Point"}
}