{
  "type": "Feature",
  "properties": {
    "addr:full":"1717 Gleneagles Dr Kokomo IN 46902",
    "addr:housenumber":"1717",
    "addr:postcode":"46902",
    "addr:street":"Gleneagles Dr",
    "iso:country":"US",
    "sg:address":"1717 Gleneagles Dr",
    "sg:city":"Kokomo",
    "sg:classifiers":[
        {
            "category":"Professional",
            "subcategory":"Engineering",
            "type":"Services"
        }
    ],
    "sg:phone":"+1 765 864 9249",
    "sg:postcode":"46902",
    "sg:province":"IN",
    "sg:tags":[
        "technical",
        "administrative",
        "contract"
    ],
    "wof:name":"ONeill and Associates",
    "wof:placetype":"venue"
},
  "geometry": {"coordinates":[-86.15267,40.455264],"type":"Point"}
}