{
  "type": "Feature",
  "properties": {
    "iso:country":"US",
    "sg:address":"4008 W 96th St",
    "sg:city":"Indianapolis",
    "sg:classifiers":[
        {
            "category":"Wholesale",
            "subcategory":"Groceries",
            "type":"Manufacturing & Wholesale Goods"
        }
    ],
    "sg:phone":"+1 317 334 0995",
    "sg:postcode":"46268",
    "sg:province":"IN",
    "sg:tags":[
        "food",
        "product",
        "mexican"
    ],
    "wof:name":"El Porton",
    "wof:placetype":"venue"
},
  "geometry": {"coordinates":[-86.231534,39.926215],"type":"Point"}
}