{
  "type": "Feature",
  "properties": {
    "addr:full":"4545 E Michigan St Indianapolis IN 46201",
    "addr:housenumber":"4545",
    "addr:postcode":"46201",
    "addr:street":"E Michigan St",
    "iso:country":"US",
    "sg:address":"4545 E Michigan St",
    "sg:city":"Indianapolis",
    "sg:classifiers":[
        {
            "category":"Autos & Motor Vehicles",
            "subcategory":"Automobile Sales",
            "type":"Retail Goods"
        }
    ],
    "sg:phone":"+1 317 357 8078",
    "sg:postcode":"46201",
    "sg:province":"IN",
    "sg:tags":[
        "car",
        "dealer"
    ],
    "wof:name":"United Auto Sales",
    "wof:placetype":"venue"
},
  "geometry": {"coordinates":[-86.091898,39.774732],"type":"Point"}
}