{
  "type": "Feature",
  "properties": {
    "addr:full":"8040 Clearvista Pkwy Indianapolis IN 46256",
    "addr:housenumber":"8040",
    "addr:postcode":"46256",
    "addr:street":"Clearvista Pkwy",
    "iso:country":"US",
    "sg:address":"8040 Clearvista Pkwy",
    "sg:city":"Indianapolis",
    "sg:classifiers":[
        {
            "category":"Health Services",
            "subcategory":"Doctor",
            "type":"Services"
        }
    ],
    "sg:phone":"+1 317 577 9411",
    "sg:postcode":"46256",
    "sg:province":"IN",
    "sg:tags":[
        "surgeon",
        "cosmetic"
    ],
    "wof:name":"University Plastic Surgery Associates Inc",
    "wof:placetype":"venue"
},
  "geometry": {"coordinates":[-86.03780399999999,39.901299],"type":"Point"}
}