{
  "type": "Feature",
  "properties": {
    "iso:country":"US",
    "sg:address":"2920 W Western Ave",
    "sg:city":"South Bend",
    "sg:classifiers":[
        {
            "category":"Restaurant",
            "type":"Food & Drink"
        }
    ],
    "sg:phone":"+1 574 234 6775",
    "sg:postcode":"46619",
    "sg:province":"IN",
    "wof:name":"Taquerie Chicago",
    "wof:placetype":"venue"
},
  "geometry": {"coordinates":[-86.290986,41.671914],"type":"Point"}
}