{
  "type": "Feature",
  "properties": {
    "iso:country":"US",
    "sg:address":"67 Woodacre Dr",
    "sg:city":"Carmel",
    "sg:classifiers":[
        {
            "category":"Education",
            "subcategory":"Special Training",
            "type":"Public Place"
        }
    ],
    "sg:phone":"+1 317 844 4444",
    "sg:postcode":"46032",
    "sg:province":"IN",
    "sg:tags":[
        "instruction",
        "music"
    ],
    "wof:name":"Music Man Studio",
    "wof:placetype":"venue"
},
  "geometry": {"coordinates":[-86.13538699999999,39.979958],"type":"Point"}
}