{
  "type": "Feature",
  "properties": {
    "iso:country":"US",
    "sg:address":"6860 State Rd 67",
    "sg:city":"Martinsville",
    "sg:classifiers":[
        {
            "category":"Personal",
            "subcategory":"Beauty Salon",
            "type":"Services"
        }
    ],
    "sg:phone":"+1 317 831 0730",
    "sg:postcode":"46151",
    "sg:province":"IN",
    "wof:name":"Hair Loft",
    "wof:placetype":"venue"
},
  "geometry": {"coordinates":[-86.393043,39.526409],"type":"Point"}
}