{
  "type": "Feature",
  "properties": {
    "iso:country":"US",
    "sg:address":"380 W 350 N",
    "sg:city":"Warsaw",
    "sg:classifiers":[
        {
            "category":"Shopping",
            "subcategory":"Computers & Home Electronics",
            "type":"Retail Goods"
        }
    ],
    "sg:phone":"+1 574 269 4088",
    "sg:postcode":"46582",
    "sg:province":"IN",
    "sg:tags":[
        "equipment",
        "electronic",
        "supply"
    ],
    "sg:website":"www.jelectronics.com",
    "wof:name":"Johnson Electronics",
    "wof:placetype":"venue"
},
  "geometry": {"coordinates":[-86.02793,41.282163],"type":"Point"}
}