{
  "type": "Feature",
  "properties": {
    "iso:country":"US",
    "sg:address":"1238 S 3rd St",
    "sg:city":"Terre Haute",
    "sg:classifiers":[
        {
            "category":"Retail",
            "subcategory":"Veterinary Services",
            "type":"Services"
        }
    ],
    "sg:phone":"+1 812 242 2273",
    "sg:postcode":"47802",
    "sg:province":"IN",
    "sg:tags":[
        "veterinarian"
    ],
    "wof:name":"Animal Emergency Clinic",
    "wof:placetype":"venue"
},
  "geometry": {"coordinates":[-87.413705,39.453891],"type":"Point"}
}