{
  "type": "Feature",
  "properties": {
    "iso:country":"US",
    "sg:address":"2728 N 6th St",
    "sg:city":"Vincennes",
    "sg:classifiers":[
        {
            "category":"Restaurant",
            "type":"Food & Drink"
        }
    ],
    "sg:phone":"+1 812 886 0169",
    "sg:postcode":"47591",
    "sg:province":"IN",
    "wof:name":"Denny's",
    "wof:placetype":"venue"
},
  "geometry": {"coordinates":[-87.50067,38.691502],"type":"Point"}
}