{
  "type": "Feature",
  "properties": {
    "iso:country":"US",
    "sg:address":"707 W Ludwig Rd",
    "sg:city":"Fort Wayne",
    "sg:classifiers":[
        {
            "category":"Professional",
            "subcategory":"Computer Services",
            "type":"Services"
        }
    ],
    "sg:phone":"+1 260 497 9716",
    "sg:postcode":"46825",
    "sg:province":"IN",
    "sg:tags":[
        "internet"
    ],
    "wof:name":"Tomsvision Inc",
    "wof:placetype":"venue"
},
  "geometry": {"coordinates":[-85.153953,41.139641],"type":"Point"}
}