{
  "type": "Feature",
  "properties": {
    "iso:country":"US",
    "sg:address":"1414 Monroe Dr",
    "sg:city":"Carmel",
    "sg:classifiers":[
        {
            "category":"Professional",
            "subcategory":"Business Services",
            "type":"Services"
        }
    ],
    "sg:phone":"+1 317 846 4798",
    "sg:postcode":"46032",
    "sg:province":"IN",
    "wof:name":"AEG Technologies Incorporated",
    "wof:placetype":"venue"
},
  "geometry": {"coordinates":[-86.123769,39.95747],"type":"Point"}
}