{
  "type": "Feature",
  "properties": {
    "iso:country":"US",
    "sg:address":"606 S Locke St",
    "sg:city":"Kokomo",
    "sg:classifiers":[
        {
            "category":"Retail",
            "subcategory":"Auto Repair",
            "type":"Services"
        }
    ],
    "sg:phone":"+1 765 457 8779",
    "sg:postcode":"46901",
    "sg:province":"IN",
    "sg:tags":[
        "body",
        "automobile",
        "painting"
    ],
    "wof:name":"B & B Body Shop",
    "wof:placetype":"venue"
},
  "geometry": {"coordinates":[-86.1215,40.480237],"type":"Point"}
}