{
  "type": "Feature",
  "properties": {
    "iso:country":"US",
    "sg:address":"10555 N State Rd 39",
    "sg:city":"Laporte",
    "sg:classifiers":[
        {
            "category":"Autos & Motor Vehicles",
            "subcategory":"Fuel & Gas Station",
            "type":"Retail Goods"
        }
    ],
    "sg:phone":"+1 219 324 4111",
    "sg:postcode":"46350",
    "sg:province":"IN",
    "sg:tags":[
        "oil"
    ],
    "wof:name":"Speedway",
    "wof:placetype":"venue"
},
  "geometry": {"coordinates":[-86.723151,41.757848],"type":"Point"}
}