{
  "type": "Feature",
  "properties": {
    "iso:country":"US",
    "sg:address":"1056 Alhambra Ave",
    "sg:city":"Frankfort",
    "sg:classifiers":[
        {
            "category":"Building & Trades",
            "subcategory":"Plumbing",
            "type":"Services"
        }
    ],
    "sg:phone":"+1 765 659 4442",
    "sg:postcode":"46041",
    "sg:province":"IN",
    "sg:tags":[
        "plumbing",
        "contractor"
    ],
    "wof:name":"M L Brittain Co",
    "wof:placetype":"venue"
},
  "geometry": {"coordinates":[-86.505961,40.266478],"type":"Point"}
}