{
  "type": "Feature",
  "properties": {
    "iso:country":"US",
    "sg:address":"1105 Shelby St",
    "sg:city":"Indianapolis",
    "sg:classifiers":[
        {
            "category":"Travel",
            "subcategory":"Hotels & Motels",
            "type":"Entertainment"
        }
    ],
    "sg:phone":"+1 317 686 6018",
    "sg:postcode":"46203",
    "sg:province":"IN",
    "sg:tags":[
        "breakfast",
        "accommodation",
        "bed"
    ],
    "wof:name":"Fountainview Inn",
    "wof:placetype":"venue"
},
  "geometry": {"coordinates":[-86.139708,39.752081],"type":"Point"}
}