{
  "type": "Feature",
  "properties": {
    "iso:country":"US",
    "sg:address":"9913 Heatherglen Ct",
    "sg:city":"Fishers",
    "sg:classifiers":[
        {
            "category":"Shopping",
            "subcategory":"Gifts & Souvenirs",
            "type":"Retail Goods"
        }
    ],
    "sg:phone":"+1 317 679 5893",
    "sg:postcode":"46037",
    "sg:province":"IN",
    "sg:tags":[
        "basket",
        "parcel"
    ],
    "wof:name":"Everything Indiana LLC",
    "wof:placetype":"venue"
},
  "geometry": {"coordinates":[-85.992454,39.937185],"type":"Point"}
}