{
  "type": "Feature",
  "properties": {
    "iso:country":"US",
    "sg:address":"4934 E 21st St",
    "sg:city":"Indianapolis",
    "sg:classifiers":[
        {
            "category":"Place Of Worship",
            "subcategory":"Church",
            "type":"Public Place"
        },
        {
            "category":"Place Of Worship",
            "type":"Public Place"
        },
        {
            "category":"Organizations",
            "subcategory":"Religious Organization",
            "type":"Services"
        }
    ],
    "sg:phone":"+1 317 322 5874",
    "sg:postcode":"46218",
    "sg:province":"IN",
    "sg:tags":[
        "churches-baptist-general",
        "churches-baptist"
    ],
    "wof:name":"Living Word",
    "wof:placetype":"venue"
},
  "geometry": {"coordinates":[-86.086884,39.7962],"type":"Point"}
}