{
  "type": "Feature",
  "properties": {
    "iso:country":"US",
    "sg:address":"111 W Rochester St",
    "sg:city":"Akron",
    "sg:classifiers":[
        {
            "category":"Bars & Pubs",
            "type":"Food & Drink"
        }
    ],
    "sg:phone":"+1 574 893 4367",
    "sg:postcode":"46910",
    "sg:province":"IN",
    "wof:name":"Den Tavern",
    "wof:placetype":"venue"
},
  "geometry": {"coordinates":[-86.02926100000001,41.038875],"type":"Point"}
}