{
  "type": "Feature",
  "properties": {
    "addr:full":"10137 Hatherly Way Fishers IN 46037",
    "addr:postcode":"10137;46037",
    "addr:street":"Hatherly Way",
    "iso:country":"US",
    "sg:address":"10137 Hatherly Way",
    "sg:city":"Fishers",
    "sg:classifiers":[
        {
            "category":"Real Estate",
            "subcategory":"Real Estate Agent",
            "type":"Services"
        }
    ],
    "sg:phone":"+1 317 577 1015",
    "sg:postcode":"46037",
    "sg:province":"IN",
    "wof:name":"Ramsey Property Group Inc",
    "wof:placetype":"venue"
},
  "geometry": {"coordinates":[-85.951666,39.938461],"type":"Point"}
}