{
  "type": "Feature",
  "properties": {
    "iso:country":"US",
    "sg:address":"4346 N US Hwy 231",
    "sg:city":"Jasper",
    "sg:classifiers":[
        {
            "category":"Building & Trades",
            "subcategory":"Construction",
            "type":"Services"
        }
    ],
    "sg:phone":"+1 812 482 3723",
    "sg:postcode":"47546",
    "sg:province":"IN",
    "sg:website":"www.mortonbuildings.com",
    "wof:name":"Morton Buildings",
    "wof:placetype":"venue"
},
  "geometry": {"coordinates":[-86.937818,38.438662],"type":"Point"}
}