{
  "type": "Feature",
  "properties": {
    "addr:full":"960 S Co Rd 75 W Danville IN 46122",
    "addr:housenumber":"960;75",
    "addr:postcode":"46122",
    "addr:street":"S Co Rd;W",
    "iso:country":"US",
    "sg:address":"960 S Co Rd 75 W",
    "sg:city":"Danville",
    "sg:classifiers":[
        {
            "category":"Retail",
            "subcategory":"Auto Repair",
            "type":"Services"
        }
    ],
    "sg:phone":"+1 317 745 6187",
    "sg:postcode":"46122",
    "sg:province":"IN",
    "sg:tags":[
        "general"
    ],
    "wof:name":"Hatcher Garage",
    "wof:placetype":"venue"
},
  "geometry": {"coordinates":[-86.537798,39.745815],"type":"Point"}
}