{
  "type": "Feature",
  "properties": {
    "iso:country":"US",
    "sg:address":"101 Agrico Ln",
    "sg:city":"Seymour",
    "sg:classifiers":[
        {
            "category":"Manufacturing",
            "subcategory":"Chemicals & Compounds",
            "type":"Manufacturing & Wholesale Goods"
        }
    ],
    "sg:phone":"+1 812 522 1786",
    "sg:postcode":"47274",
    "sg:province":"IN",
    "sg:tags":[
        "fertilizer"
    ],
    "sg:website":"www.ande.com",
    "wof:name":"Andersons",
    "wof:placetype":"venue"
},
  "geometry": {"coordinates":[-85.862571,38.959043],"type":"Point"}
}