{
  "type": "Feature",
  "properties": {
    "iso:country":"US",
    "sg:address":"817 Tennessee St",
    "sg:city":"Gary",
    "sg:classifiers":[
        {
            "category":"Professional",
            "subcategory":"Secretarial Services",
            "type":"Services"
        }
    ],
    "sg:phone":"+1 219 885 3628",
    "sg:postcode":"46402",
    "sg:province":"IN",
    "sg:tags":[
        "reporting",
        "court"
    ],
    "wof:name":"Mary Harris",
    "wof:placetype":"venue"
},
  "geometry": {"coordinates":[-87.322005,41.595371],"type":"Point"}
}