{
  "type": "Feature",
  "properties": {
    "iso:country":"US",
    "sg:address":"545 Country Club Rd SE",
    "sg:city":"Corydon",
    "sg:classifiers":[
        {
            "category":"Health Services",
            "subcategory":"Doctor",
            "type":"Services"
        }
    ],
    "sg:phone":"+1 812 738 2257",
    "sg:postcode":"47112",
    "sg:province":"IN",
    "sg:tags":[
        "dentist"
    ],
    "wof:name":"Mark Hall DDS",
    "wof:placetype":"venue"
},
  "geometry": {"coordinates":[-86.11512399999999,38.200658],"type":"Point"}
}