{
  "type": "Feature",
  "properties": {
    "iso:country":"US",
    "sg:address":"505 Carlisle Dr",
    "sg:city":"Huntington",
    "sg:classifiers":[
        {
            "category":"Shopping",
            "subcategory":"Beauty & Cosmetics",
            "type":"Retail Goods"
        }
    ],
    "sg:phone":"+1 260 356 8013",
    "sg:postcode":"46750",
    "sg:province":"IN",
    "sg:tags":[
        "merchandise"
    ],
    "wof:name":"Mary Kay",
    "wof:placetype":"venue"
},
  "geometry": {"coordinates":[-85.50641,40.905369],"type":"Point"}
}