{
  "type": "Feature",
  "properties": {
    "addr:full":"12805 North St Dillsboro IN 47018",
    "addr:housenumber":"12805",
    "addr:postcode":"47018",
    "addr:street":"North St",
    "iso:country":"US",
    "sg:address":"12805 North St",
    "sg:city":"Dillsboro",
    "sg:classifiers":[
        {
            "category":"Restaurant",
            "type":"Food & Drink"
        }
    ],
    "sg:phone":"+1 812 432 5410",
    "sg:postcode":"47018",
    "sg:province":"IN",
    "wof:name":"Dan & Deb's",
    "wof:placetype":"venue"
},
  "geometry": {"coordinates":[-85.05712200000001,39.017925],"type":"Point"}
}