{
  "type": "Feature",
  "properties": {
    "addr:full":"7013 E 173rd Ave Hebron IN 46341",
    "addr:housenumber":"7013",
    "addr:postcode":"46341",
    "addr:street":"E 173Rd Ave",
    "iso:country":"US",
    "sg:address":"7013 E 173rd Ave",
    "sg:city":"Hebron",
    "sg:classifiers":[
        {
            "category":"Real Estate",
            "subcategory":"Real Estate Operator",
            "type":"Services"
        }
    ],
    "sg:phone":"+1 219 996 6953",
    "sg:postcode":"46341",
    "sg:province":"IN",
    "sg:tags":[
        "property",
        "lessor"
    ],
    "wof:name":"Warren Lee Creekmur",
    "wof:placetype":"venue"
},
  "geometry": {"coordinates":[-87.248135,41.303869],"type":"Point"}
}