{
  "type": "Feature",
  "properties": {
    "iso:country":"US",
    "sg:address":"9413 E State Rd 164",
    "sg:city":"Celestine",
    "sg:classifiers":[
        {
            "category":"Wholesale",
            "subcategory":"Construction Materials",
            "type":"Manufacturing & Wholesale Goods"
        }
    ],
    "sg:phone":"+1 812 389 2716",
    "sg:postcode":"47513",
    "sg:province":"IN",
    "sg:tags":[
        "fence"
    ],
    "sg:website":"www.patokavinylco.com",
    "wof:name":"Patoka Vinyl Co",
    "wof:placetype":"venue"
},
  "geometry": {"coordinates":[-86.729951,38.371741],"type":"Point"}
}