{
  "type": "Feature",
  "properties": {
    "iso:country":"US",
    "sg:address":"179 W Main St",
    "sg:city":"Berne",
    "sg:classifiers":[
        {
            "category":"Insurance",
            "subcategory":"Insurance Agent",
            "type":"Services"
        }
    ],
    "sg:phone":"+1 260 589 2142",
    "sg:postcode":"46711",
    "sg:province":"IN",
    "sg:website":"www.bixlerinsurance.com",
    "wof:name":"Bixler Insurance Inc",
    "wof:placetype":"venue"
},
  "geometry": {"coordinates":[-84.951143,40.657908],"type":"Point"}
}