{
  "type": "Feature",
  "properties": {
    "iso:country":"US",
    "sg:address":"278 E Mander Rd",
    "sg:city":"Valparaiso",
    "sg:classifiers":[
        {
            "category":"Shopping",
            "subcategory":"Jewelry",
            "type":"Retail Goods"
        }
    ],
    "sg:phone":"+1 219 462 4440",
    "sg:postcode":"46383",
    "sg:province":"IN",
    "wof:name":"House Of Chimes",
    "wof:placetype":"venue"
},
  "geometry": {"coordinates":[-87.012593,41.551737],"type":"Point"}
}