{
  "type": "Feature",
  "properties": {
    "iso:country":"US",
    "sg:address":"971 E 300 N",
    "sg:city":"Hartford City",
    "sg:classifiers":[
        {
            "category":"Farming",
            "subcategory":"Farm",
            "type":"Manufacturing & Wholesale Goods"
        }
    ],
    "sg:phone":"+1 765 348 5251",
    "sg:postcode":"47348",
    "sg:province":"IN",
    "sg:tags":[
        "crop",
        "general"
    ],
    "wof:name":"Willmann Farm",
    "wof:placetype":"venue"
},
  "geometry": {"coordinates":[-85.352781,40.493984],"type":"Point"}
}