{
  "type": "Feature",
  "properties": {
    "iso:country":"US",
    "sg:address":"210 S Ironwood Dr",
    "sg:city":"South Bend",
    "sg:classifiers":[
        {
            "category":"Real Estate",
            "subcategory":"Real Estate Services",
            "type":"Services"
        }
    ],
    "sg:phone":"+1 574 233 8258",
    "sg:postcode":"46615",
    "sg:province":"IN",
    "sg:tags":[
        "company",
        "title"
    ],
    "wof:name":"Metropolitan Title Co",
    "wof:placetype":"venue"
},
  "geometry": {"coordinates":[-86.21590500000001,41.673043],"type":"Point"}
}