{
  "type": "Feature",
  "properties": {
    "iso:country":"US",
    "sg:address":"105 W 7th St",
    "sg:city":"Auburn",
    "sg:classifiers":[
        {
            "category":"Real Estate",
            "subcategory":"Real Estate Agent",
            "type":"Services"
        }
    ],
    "sg:phone":"+1 260 925 2422",
    "sg:postcode":"46706",
    "sg:province":"IN",
    "wof:name":"Habig Realty and Appraisal Svc",
    "wof:placetype":"venue"
},
  "geometry": {"coordinates":[-85.057119,41.3669],"type":"Point"}
}