{
  "type": "Feature",
  "properties": {
    "iso:country":"US",
    "sg:address":"300 Persimmon Trl",
    "sg:city":"Lafayette",
    "sg:classifiers":[
        {
            "category":"Building & Trades",
            "subcategory":"Landscaping Services",
            "type":"Services"
        }
    ],
    "sg:phone":"+1 765 471 9744",
    "sg:postcode":"47909",
    "sg:province":"IN",
    "wof:name":"Krintz Lawn Care",
    "wof:placetype":"venue"
},
  "geometry": {"coordinates":[-86.910754,40.377639],"type":"Point"}
}