{
  "type": "Feature",
  "properties": {
    "iso:country":"US",
    "sg:address":"1029 Broadway",
    "sg:city":"Gary",
    "sg:classifiers":[
        {
            "category":"Shopping",
            "subcategory":"Shoes",
            "type":"Retail Goods"
        }
    ],
    "sg:phone":"+1 219 886 1530",
    "sg:postcode":"46407",
    "sg:province":"IN",
    "wof:name":"Shoes For Less",
    "wof:placetype":"venue"
},
  "geometry": {"coordinates":[-87.337097,41.591806],"type":"Point"}
}