{
  "type": "Feature",
  "properties": {
    "iso:country":"US",
    "sg:address":"2650 Lake Circle Dr",
    "sg:city":"Indianapolis",
    "sg:classifiers":[
        {
            "category":"Restaurant",
            "type":"Food & Drink"
        }
    ],
    "sg:phone":"+1 317 879 1212",
    "sg:postcode":"46268",
    "sg:province":"IN",
    "wof:name":"Neon Johnny's Sports Bar",
    "wof:placetype":"venue"
},
  "geometry": {"coordinates":[-86.20759,39.913151],"type":"Point"}
}