{
  "type": "Feature",
  "properties": {
    "iso:country":"US",
    "sg:address":"4227 Bluffton Rd",
    "sg:city":"Fort Wayne",
    "sg:classifiers":[
        {
            "category":"Professional",
            "subcategory":"Detective & Security Services",
            "type":"Services"
        }
    ],
    "sg:phone":"+1 260 969 0077",
    "sg:postcode":"46809",
    "sg:province":"IN",
    "sg:tags":[
        "car",
        "armored"
    ],
    "wof:name":"APS Armored",
    "wof:placetype":"venue"
},
  "geometry": {"coordinates":[-85.167342,41.045422],"type":"Point"}
}