{
  "type": "Feature",
  "properties": {
    "iso:country":"US",
    "sg:address":"502 W National Ave",
    "sg:city":"Brazil",
    "sg:classifiers":[
        {
            "category":"Professional",
            "subcategory":"Accounting & Tax Preparation",
            "type":"Services"
        }
    ],
    "sg:phone":"+1 812 448 2021",
    "sg:postcode":"47834",
    "sg:province":"IN",
    "wof:name":"Gallatin Accounting",
    "wof:placetype":"venue"
},
  "geometry": {"coordinates":[-87.13332699999999,39.521739],"type":"Point"}
}