{
  "type": "Feature",
  "properties": {
    "iso:country":"US",
    "sg:address":"4053 S 650 W",
    "sg:city":"New Palestine",
    "sg:classifiers":[
        {
            "category":"Organizations",
            "subcategory":"Religious Organization",
            "type":"Services"
        }
    ],
    "sg:phone":"+1 317 861 4356",
    "sg:postcode":"46163",
    "sg:province":"IN",
    "sg:tags":[
        "church"
    ],
    "wof:name":"New Palestine Christian Church",
    "wof:placetype":"venue"
},
  "geometry": {"coordinates":[-85.923204,39.726714],"type":"Point"}
}