{
  "type": "Feature",
  "properties": {
    "iso:country":"US",
    "sg:address":"5495 Sinai Rd",
    "sg:city":"Bristow",
    "sg:classifiers":[
        {
            "category":"Organizations",
            "subcategory":"Religious Organization",
            "type":"Services"
        }
    ],
    "sg:phone":"+1 812 843 3126",
    "sg:postcode":"47515",
    "sg:province":"IN",
    "wof:name":"Calvary Ministries Outreach",
    "wof:placetype":"venue"
},
  "geometry": {"coordinates":[-86.706924,38.195158],"type":"Point"}
}