{
  "type": "Feature",
  "properties": {
    "iso:country":"US",
    "sg:address":"45 N Co Rd 200 E",
    "sg:city":"Danville",
    "sg:classifiers":[
        {
            "category":"Social Services",
            "subcategory":"Child Care",
            "type":"Services"
        }
    ],
    "sg:phone":"+1 317 745 4611",
    "sg:postcode":"46122",
    "sg:province":"IN",
    "wof:name":"Wee Friend's Child Care",
    "wof:placetype":"venue"
},
  "geometry": {"coordinates":[-86.486335,39.770019],"type":"Point"}
}