{
  "type": "Feature",
  "properties": {
    "iso:country":"US",
    "sg:address":"8650 Commerce Park Pl, Suite D",
    "sg:city":"Indianapolis",
    "sg:classifiers":[
        {
            "category":"Professional",
            "subcategory":"Computer Services",
            "type":"Services"
        }
    ],
    "sg:phone":"+1 317 808 5991",
    "sg:postcode":"46268",
    "sg:province":"IN",
    "sg:tags":[
        "designer",
        "network",
        "technical",
        "consultant",
        "assistance",
        "system",
        "design",
        "support"
    ],
    "wof:name":"Sourcient In",
    "wof:placetype":"venue"
},
  "geometry": {"coordinates":[-86.233231,39.91248],"type":"Point"}
}