{
  "type": "Feature",
  "properties": {
    "iso:country":"US",
    "sg:address":"3950 N High School Rd",
    "sg:city":"Indianapolis",
    "sg:classifiers":[
        {
            "category":"Food & Beverages",
            "subcategory":"Liquor & Beverages",
            "type":"Retail Goods"
        }
    ],
    "sg:phone":"+1 317 291 9518",
    "sg:postcode":"46254",
    "sg:province":"IN",
    "wof:name":"Liquorland",
    "wof:placetype":"venue"
},
  "geometry": {"coordinates":[-86.270414,39.828601],"type":"Point"}
}