{
  "type": "Feature",
  "properties": {
    "iso:country":"US",
    "sg:address":"3131 E 71st St",
    "sg:city":"Indianapolis",
    "sg:classifiers":[
        {
            "category":"Shopping",
            "subcategory":"Beauty & Cosmetics",
            "type":"Retail Goods"
        }
    ],
    "sg:phone":"+1 317 257 2204",
    "sg:postcode":"46220",
    "sg:province":"IN",
    "sg:tags":[
        "surgical",
        "appliance"
    ],
    "wof:name":"Creative Rheumatology Prod",
    "wof:placetype":"venue"
},
  "geometry": {"coordinates":[-86.114806,39.883177],"type":"Point"}
}