{
  "type": "Feature",
  "properties": {
    "iso:country":"US",
    "sg:address":"2442 Miracle Ln",
    "sg:city":"Mishawaka",
    "sg:classifiers":[
        {
            "category":"Food & Beverages",
            "subcategory":"Specialty",
            "type":"Retail Goods"
        }
    ],
    "sg:phone":"+1 574 255 1020",
    "sg:postcode":"46545",
    "sg:province":"IN",
    "sg:tags":[
        "herb"
    ],
    "wof:name":"Herbs 'n Such",
    "wof:placetype":"venue"
},
  "geometry": {"coordinates":[-86.192738,41.680349],"type":"Point"}
}