{
  "type": "Feature",
  "properties": {
    "addr:full":"1015 E Maplegrove Ave Fort Wayne IN 46806",
    "addr:housenumber":"1015",
    "addr:postcode":"46806",
    "addr:street":"E Maplegrove Ave",
    "iso:country":"US",
    "sg:address":"1015 E Maplegrove Ave",
    "sg:city":"Fort Wayne",
    "sg:classifiers":[
        {
            "category":"Organizations",
            "subcategory":"Religious Organization",
            "type":"Services"
        }
    ],
    "sg:phone":"+1 260 744 1683",
    "sg:postcode":"46806",
    "sg:province":"IN",
    "wof:name":"Church Fort Wyne Chrstn Acdemy",
    "wof:placetype":"venue"
},
  "geometry": {"coordinates":[-85.12123699999999,41.04038],"type":"Point"}
}