{
  "type": "Feature",
  "properties": {
    "addr:full":"1480 W Thunderbolt Ave Peru IN 46970",
    "addr:housenumber":"1480",
    "addr:postcode":"46970",
    "addr:street":"W Thunderbolt Ave",
    "iso:country":"US",
    "sg:address":"1480 W Thunderbolt Ave",
    "sg:city":"Peru",
    "sg:classifiers":[
        {
            "category":"Organizations",
            "subcategory":"Religious Organization",
            "type":"Services"
        }
    ],
    "sg:phone":"+1 765 689 9469",
    "sg:postcode":"46970",
    "sg:province":"IN",
    "sg:tags":[
        "church"
    ],
    "wof:name":"Church Of Christ At Grissom",
    "wof:placetype":"venue"
},
  "geometry": {"coordinates":[-86.142439,40.672091],"type":"Point"}
}