{
  "type": "Feature",
  "properties": {
    "iso:country":"US",
    "sg:address":"11020 Hillcrest Dr SW",
    "sg:city":"Mauckport",
    "sg:classifiers":[
        {
            "category":"Government",
            "subcategory":"Post Office",
            "type":"Public Place"
        }
    ],
    "sg:phone":"+1 812 732 4470",
    "sg:postcode":"47142",
    "sg:province":"IN",
    "wof:name":"US Post Office",
    "wof:placetype":"venue"
},
  "geometry": {"coordinates":[-86.191015,38.041879],"type":"Point"}
}