{
  "type": "Feature",
  "properties": {
    "iso:country":"US",
    "sg:address":"1105 23rd St",
    "sg:city":"Columbus",
    "sg:classifiers":[
        {
            "category":"Retail",
            "subcategory":"Repair Shop",
            "type":"Services"
        }
    ],
    "sg:phone":"+1 812 342 0000",
    "sg:postcode":"47201",
    "sg:province":"IN",
    "sg:tags":[
        "spa",
        "hot",
        "tub"
    ],
    "wof:name":"Thompson Pool & Spas",
    "wof:placetype":"venue"
},
  "geometry": {"coordinates":[-85.912863,39.221249],"type":"Point"}
}