{
  "type": "Feature",
  "properties": {
    "iso:country":"US",
    "sg:address":"803 S Reed Rd",
    "sg:city":"Kokomo",
    "sg:classifiers":[
        {
            "category":"Shopping",
            "type":"Retail Goods"
        }
    ],
    "sg:phone":"+1 765 452 1058",
    "sg:postcode":"46901",
    "sg:province":"IN",
    "sg:tags":[
        "pet",
        "food",
        "supply"
    ],
    "wof:name":"Pet Supplies Plus",
    "wof:placetype":"venue"
},
  "geometry": {"coordinates":[-86.107843,40.476687],"type":"Point"}
}