{
  "type": "Feature",
  "properties": {
    "iso:country":"US",
    "sg:address":"718 E Harris St",
    "sg:city":"Sullivan",
    "sg:classifiers":[
        {
            "category":"Organizations",
            "subcategory":"Religious Organization",
            "type":"Services"
        }
    ],
    "sg:phone":"+1 812 268 4316",
    "sg:postcode":"47882",
    "sg:province":"IN",
    "sg:tags":[
        "church"
    ],
    "wof:name":"Church Of The Bible Holiness",
    "wof:placetype":"venue"
},
  "geometry": {"coordinates":[-87.39742699999999,39.093333],"type":"Point"}
}