{
  "type": "Feature",
  "properties": {
    "iso:country":"US",
    "sg:address":"1528 NW 5th St",
    "sg:city":"Richmond",
    "sg:classifiers":[
        {
            "category":"Social Services",
            "type":"Services"
        }
    ],
    "sg:phone":"+1 765 935 0536",
    "sg:postcode":"47374",
    "sg:province":"IN",
    "sg:tags":[
        "organization",
        "welfare"
    ],
    "sg:website":"www.gac.com",
    "wof:name":"Achieva Resources",
    "wof:placetype":"venue"
},
  "geometry": {"coordinates":[-84.907938,39.847937],"type":"Point"}
}