{
  "type": "Feature",
  "properties": {
    "iso:country":"US",
    "sg:address":"1584 Miami Trl",
    "sg:city":"Bremen",
    "sg:phone":"+1 574 546 3912",
    "sg:postcode":"46506",
    "sg:province":"IN",
    "sg:tags":[
        "farm",
        "corn",
        "soybean"
    ],
    "wof:name":"Miami Hill Farms",
    "wof:placetype":"venue"
},
  "geometry": {"coordinates":[-86.192104,41.456222],"type":"Point"}
}