{
  "type": "Feature",
  "properties": {
    "addr:full":"3010 Allegany Ave Fort Wayne IN 46809",
    "addr:housenumber":"3010",
    "addr:postcode":"46809",
    "addr:street":"Allegany Ave",
    "iso:country":"US",
    "sg:address":"3010 Allegany Ave",
    "sg:city":"Fort Wayne",
    "sg:classifiers":[
        {
            "category":"Professional",
            "subcategory":"Computer Services",
            "type":"Services"
        }
    ],
    "sg:phone":"+1 260 478 8021",
    "sg:postcode":"46809",
    "sg:province":"IN",
    "sg:tags":[
        "related"
    ],
    "wof:name":"Technology Computer Consulting",
    "wof:placetype":"venue"
},
  "geometry": {"coordinates":[-85.174312,41.040423],"type":"Point"}
}