{
  "type": "Feature",
  "properties": {
    "iso:country":"US",
    "sg:address":"1315 Spring St",
    "sg:city":"Jeffersonville",
    "sg:classifiers":[
        {
            "category":"Personal",
            "subcategory":"Barber",
            "type":"Services"
        }
    ],
    "sg:phone":"+1 812 283 9677",
    "sg:postcode":"47130",
    "sg:province":"IN",
    "wof:name":"Brownie Townsend's Barber Shop",
    "wof:placetype":"venue"
},
  "geometry": {"coordinates":[-85.74820099999999,38.283497],"type":"Point"}
}