{
  "type": "Feature",
  "properties": {
    "iso:country":"US",
    "sg:address":"2212 White Oaks Dr",
    "sg:city":"Indianapolis",
    "sg:classifiers":[
        {
            "category":"Social Services",
            "subcategory":"Child Care",
            "type":"Services"
        }
    ],
    "sg:phone":"+1 317 244 9013",
    "sg:postcode":"46224",
    "sg:province":"IN",
    "wof:name":"Everist's Day Care",
    "wof:placetype":"venue"
},
  "geometry": {"coordinates":[-86.254386,39.796286],"type":"Point"}
}