{
  "type": "Feature",
  "properties": {
    "addr:full":"3330 State Rd 9 Anderson IN 46012",
    "addr:housenumber":"3330",
    "addr:postcode":"46012",
    "addr:street":"State Rd 9",
    "iso:country":"US",
    "sg:address":"3330 State Rd 9",
    "sg:city":"Anderson",
    "sg:classifiers":[
        {
            "category":"Health Services",
            "subcategory":"Optometrist",
            "type":"Services"
        }
    ],
    "sg:phone":"+1 765 644 3711",
    "sg:postcode":"46012",
    "sg:province":"IN",
    "wof:name":"Anderson Vision Care",
    "wof:placetype":"venue"
},
  "geometry": {"coordinates":[-85.671729,40.155194],"type":"Point"}
}