{
  "type": "Feature",
  "properties": {
    "iso:country":"US",
    "sg:address":"6616 N 500 W",
    "sg:city":"Winchester",
    "sg:phone":"+1 765 857 2006",
    "sg:postcode":"47394",
    "sg:province":"IN",
    "sg:tags":[
        "farm",
        "corn",
        "soybean"
    ],
    "wof:name":"Ronald Chalfant",
    "wof:placetype":"venue"
},
  "geometry": {"coordinates":[-85.074033,40.263927],"type":"Point"}
}