{
  "type": "Feature",
  "properties": {
    "iso:country":"US",
    "sg:address":"1780 W Epler Ave",
    "sg:city":"Indianapolis",
    "sg:classifiers":[
        {
            "category":"Retail",
            "subcategory":"Auto Repair",
            "type":"Services"
        }
    ],
    "sg:phone":"+1 317 791 1379",
    "sg:postcode":"46217",
    "sg:province":"IN",
    "sg:tags":[
        "repairing",
        "automobile"
    ],
    "wof:name":"Goldstar Automotive Svc",
    "wof:placetype":"venue"
},
  "geometry": {"coordinates":[-86.193038,39.685662],"type":"Point"}
}