{
  "type": "Feature",
  "properties": {
    "iso:country":"US",
    "sg:address":"6435 Castleway West Dr",
    "sg:city":"Indianapolis",
    "sg:classifiers":[
        {
            "category":"Insurance",
            "subcategory":"Insurance Agent",
            "type":"Services"
        }
    ],
    "sg:phone":"+1 317 849 5545",
    "sg:postcode":"46250",
    "sg:province":"IN",
    "wof:name":"Ail Special Risk Div",
    "wof:placetype":"venue"
},
  "geometry": {"coordinates":[-86.055899,39.900956],"type":"Point"}
}