{
  "type": "Feature",
  "properties": {
    "iso:country":"US",
    "sg:address":"2115 Lincoln Ave",
    "sg:city":"Evansville",
    "sg:classifiers":[
        {
            "category":"Retail",
            "subcategory":"Funeral Services",
            "type":"Services"
        }
    ],
    "sg:phone":"+1 812 476 1351",
    "sg:postcode":"47714",
    "sg:province":"IN",
    "sg:tags":[
        "director"
    ],
    "wof:name":"Alexander Funeral Homes Inc",
    "wof:placetype":"venue"
},
  "geometry": {"coordinates":[-87.538575,37.969978],"type":"Point"}
}