{
  "type": "Feature",
  "properties": {
    "iso:country":"US",
    "sg:address":"4235 Hazelhurst Dr",
    "sg:city":"Fort Wayne",
    "sg:classifiers":[
        {
            "category":"Freight",
            "type":"Transportation"
        }
    ],
    "sg:phone":"+1 260 459 6755",
    "sg:postcode":"46804",
    "sg:province":"IN",
    "sg:tags":[
        "mover"
    ],
    "wof:name":"Garrett Specialty Svc",
    "wof:placetype":"venue"
},
  "geometry": {"coordinates":[-85.22789899999999,41.046752],"type":"Point"}
}