{
  "type": "Feature",
  "properties": {
    "iso:country":"US",
    "sg:address":"5273 E 38th St",
    "sg:city":"Indianapolis",
    "sg:classifiers":[
        {
            "category":"Manufacturing",
            "subcategory":"Petroleum Products",
            "type":"Manufacturing & Wholesale Goods"
        }
    ],
    "sg:phone":"+1 317 543 2540",
    "sg:postcode":"46218",
    "sg:province":"IN",
    "wof:name":"PAR Petroleum",
    "wof:placetype":"venue"
},
  "geometry": {"coordinates":[-86.07916,39.8254],"type":"Point"}
}