{
  "type": "Feature",
  "properties": {
    "iso:country":"US",
    "sg:address":"1803 Lindenwood Ave",
    "sg:city":"Fort Wayne",
    "sg:classifiers":[
        {
            "category":"Building & Trades",
            "subcategory":"Construction",
            "type":"Services"
        }
    ],
    "sg:phone":"+1 260 436 2570",
    "sg:postcode":"46808",
    "sg:province":"IN",
    "sg:tags":[
        "painter"
    ],
    "wof:name":"Pro Joe's All-American Paintng",
    "wof:placetype":"venue"
},
  "geometry": {"coordinates":[-85.18065300000001,41.092093],"type":"Point"}
}