{
  "type": "Feature",
  "properties": {
    "iso:country":"US",
    "sg:address":"201 S Main St",
    "sg:city":"Kendallville",
    "sg:classifiers":[
        {
            "category":"Restaurant",
            "type":"Food & Drink"
        }
    ],
    "sg:phone":"+1 260 347 1274",
    "sg:postcode":"46755",
    "sg:province":"IN",
    "sg:tags":[
        "shop",
        "coffee"
    ],
    "wof:name":"Easy As Pie",
    "wof:placetype":"venue"
},
  "geometry": {"coordinates":[-85.265418,41.442617],"type":"Point"}
}