{
  "type": "Feature",
  "properties": {
    "iso:country":"US",
    "sg:address":"340 Tracy Rd",
    "sg:city":"Whiteland",
    "sg:classifiers":[
        {
            "category":"Health Services",
            "subcategory":"Doctor",
            "type":"Services"
        }
    ],
    "sg:phone":"+1 317 535 1577",
    "sg:postcode":"46184",
    "sg:province":"IN",
    "sg:tags":[
        "physician",
        "surgeon"
    ],
    "wof:name":"Family Physicians-Johnson Cnty",
    "wof:placetype":"venue"
},
  "geometry": {"coordinates":[-86.107191,39.56414],"type":"Point"}
}