{
  "type": "Feature",
  "properties": {
    "iso:country":"US",
    "sg:address":"2507 Ridgeway Dr",
    "sg:city":"Fort Wayne",
    "sg:classifiers":[
        {
            "category":"Professional",
            "type":"Services"
        }
    ],
    "sg:phone":"+1 260 447 1281",
    "sg:postcode":"46816",
    "sg:province":"IN",
    "wof:name":"John Mason Miller LP",
    "wof:placetype":"venue"
},
  "geometry": {"coordinates":[-85.10118199999999,41.018862],"type":"Point"}
}