{
  "type": "Feature",
  "properties": {
    "iso:country":"US",
    "sg:address":"1043 Castlebury Dr",
    "sg:city":"Greencastle",
    "sg:classifiers":[
        {
            "category":"Real Estate",
            "subcategory":"Real Estate Operator",
            "type":"Services"
        }
    ],
    "sg:phone":"+1 765 653 8011",
    "sg:postcode":"46135",
    "sg:province":"IN",
    "sg:tags":[
        "apartment"
    ],
    "wof:name":"Castlebury Apartments",
    "wof:placetype":"venue"
},
  "geometry": {"coordinates":[-86.83775900000001,39.648409],"type":"Point"}
}