{
  "type": "Feature",
  "properties": {
    "iso:country":"US",
    "sg:address":"2704 Washington Ave",
    "sg:city":"Vincennes",
    "sg:classifiers":[
        {
            "category":"Real Estate",
            "subcategory":"Surveying",
            "type":"Services"
        }
    ],
    "sg:phone":"+1 812 882 0476",
    "sg:postcode":"47591",
    "sg:province":"IN",
    "sg:tags":[
        "surveyor"
    ],
    "wof:name":"A To B Surveying LLC",
    "wof:placetype":"venue"
},
  "geometry": {"coordinates":[-87.499628,38.685036],"type":"Point"}
}