{
  "type": "Feature",
  "properties": {
    "iso:country":"US",
    "sg:address":"3417 E State Blvd",
    "sg:city":"Fort Wayne",
    "sg:classifiers":[
        {
            "category":"Real Estate",
            "subcategory":"Real Estate Agent",
            "type":"Services"
        }
    ],
    "sg:phone":"+1 260 471 3100",
    "sg:postcode":"46805",
    "sg:province":"IN",
    "wof:name":"Success Realtor Assoc",
    "wof:placetype":"venue"
},
  "geometry": {"coordinates":[-85.095737,41.097492],"type":"Point"}
}