{
  "type": "Feature",
  "properties": {
    "iso:country":"US",
    "sg:address":"4008 W Columbia St",
    "sg:city":"Evansville",
    "sg:classifiers":[
        {
            "category":"Building & Trades",
            "subcategory":"Construction",
            "type":"Services"
        }
    ],
    "sg:phone":"+1 812 425 7303",
    "sg:postcode":"47720",
    "sg:province":"IN",
    "sg:tags":[
        "general",
        "contractor"
    ],
    "wof:name":"Scott Lenfers Construction Inc",
    "wof:placetype":"venue"
},
  "geometry": {"coordinates":[-87.625215,37.986964],"type":"Point"}
}