{
  "type": "Feature",
  "properties": {
    "addr:full":"212 Grave St Patoka IN 47666",
    "addr:housenumber":"212",
    "addr:postcode":"47666",
    "addr:street":"Grave St",
    "iso:country":"US",
    "sg:address":"212 Grave St",
    "sg:city":"Patoka",
    "sg:classifiers":[
        {
            "category":"Wholesale",
            "subcategory":"Metals & Minerals",
            "type":"Manufacturing & Wholesale Goods"
        }
    ],
    "sg:phone":"+1 812 779 5656",
    "sg:postcode":"47666",
    "sg:province":"IN",
    "sg:tags":[
        "pipe"
    ],
    "wof:name":"J & J Municipal Supply Inc",
    "wof:placetype":"venue"
},
  "geometry": {"coordinates":[-87.587621,38.406199],"type":"Point"}
}