{
  "type": "Feature",
  "properties": {
    "iso:country":"US",
    "sg:address":"907 Washington St",
    "sg:city":"Michigan City",
    "sg:classifiers":[
        {
            "category":"Health Services",
            "subcategory":"Doctor",
            "type":"Services"
        }
    ],
    "sg:phone":"+1 219 872 9158",
    "sg:postcode":"46360",
    "sg:province":"IN",
    "sg:tags":[
        "physician",
        "surgeon"
    ],
    "wof:name":"Midwest Pain Clinic",
    "wof:placetype":"venue"
},
  "geometry": {"coordinates":[-86.90082700000001,41.711734],"type":"Point"}
}