{
  "type": "Feature",
  "properties": {
    "addr:full":"6150 Genevive Ln Bloomington IN 47408",
    "addr:postcode":"6150;47408",
    "addr:street":"Genevive Ln",
    "iso:country":"US",
    "sg:address":"6150 Genevive Ln",
    "sg:city":"Bloomington",
    "sg:classifiers":[
        {
            "category":"Health Services",
            "subcategory":"Nursing And Care Facility",
            "type":"Services"
        }
    ],
    "sg:phone":"+1 812 332 6421",
    "sg:postcode":"47408",
    "sg:province":"IN",
    "sg:tags":[
        "skilled",
        "employment",
        "agency"
    ],
    "wof:name":"Bailey Nursing Services Inc",
    "wof:placetype":"venue"
},
  "geometry": {"coordinates":[-86.449348,39.238921],"type":"Point"}
}