{
  "type": "Feature",
  "properties": {
    "iso:country":"US",
    "sg:address":"12990 W Co Rd 400 S",
    "sg:city":"Yorktown",
    "sg:classifiers":[
        {
            "category":"Retail",
            "subcategory":"Auto Repair",
            "type":"Services"
        }
    ],
    "sg:phone":"+1 765 378 3325",
    "sg:postcode":"47396",
    "sg:province":"IN",
    "sg:tags":[
        "vehicle",
        "recreational",
        "general"
    ],
    "wof:name":"Countyline Auto Body Specialis",
    "wof:placetype":"venue"
},
  "geometry": {"coordinates":[-85.540427,40.134698],"type":"Point"}
}