{
  "type": "Feature",
  "properties": {
    "iso:country":"US",
    "sg:address":"1700 Monticello Park Dr",
    "sg:city":"Valparaiso",
    "sg:classifiers":[
        {
            "category":"Social Services",
            "subcategory":"Child Care",
            "type":"Services"
        }
    ],
    "sg:phone":"+1 219 464 3427",
    "sg:postcode":"46383",
    "sg:province":"IN",
    "sg:tags":[
        "day"
    ],
    "wof:name":"Gloria Day",
    "wof:placetype":"venue"
},
  "geometry": {"coordinates":[-87.040475,41.485451],"type":"Point"}
}