{
  "type": "Feature",
  "properties": {
    "iso:country":"US",
    "sg:address":"116 Hamlet St",
    "sg:city":"Hamlet",
    "sg:classifiers":[
        {
            "category":"Organizations",
            "subcategory":"Religious Organization",
            "type":"Services"
        }
    ],
    "sg:phone":"+1 574 867 2843",
    "sg:postcode":"46532",
    "sg:province":"IN",
    "sg:tags":[
        "church"
    ],
    "wof:name":"New Life Pentecostal Church",
    "wof:placetype":"venue"
},
  "geometry": {"coordinates":[-86.585874,41.379979],"type":"Point"}
}