{
  "type": "Feature",
  "properties": {
    "iso:country":"US",
    "sg:address":"217 Dehart St",
    "sg:city":"West Lafayette",
    "sg:classifiers":[
        {
            "category":"Personal",
            "type":"Services"
        }
    ],
    "sg:phone":"+1 765 743 2755",
    "sg:postcode":"47906",
    "sg:province":"IN",
    "wof:name":"Duke Art",
    "wof:placetype":"venue"
},
  "geometry": {"coordinates":[-86.901677,40.432577],"type":"Point"}
}