{
  "type": "Feature",
  "properties": {
    "iso:country":"US",
    "sg:address":"2501 Madison Ave",
    "sg:city":"Indianapolis",
    "sg:classifiers":[
        {
            "category":"Professional",
            "subcategory":"Computer Services",
            "type":"Services"
        }
    ],
    "sg:phone":"+1 317 780 7716",
    "sg:postcode":"46225",
    "sg:province":"IN",
    "sg:tags":[
        "repair"
    ],
    "wof:name":"GDS Work Solutions",
    "wof:placetype":"venue"
},
  "geometry": {"coordinates":[-86.153926,39.729849],"type":"Point"}
}