{
  "type": "Feature",
  "properties": {
    "iso:country":"US",
    "sg:address":"1119 W Market St",
    "sg:city":"Logansport",
    "sg:classifiers":[
        {
            "category":"Shopping",
            "subcategory":"Bicycles & Sporting Goods",
            "type":"Retail Goods"
        }
    ],
    "sg:phone":"+1 574 753 5812",
    "sg:postcode":"46947",
    "sg:province":"IN",
    "sg:tags":[
        "tackle",
        "fishing"
    ],
    "wof:name":"Dick's Bait & Sporting Goods",
    "wof:placetype":"venue"
},
  "geometry": {"coordinates":[-86.381738,40.75234],"type":"Point"}
}