{
  "type": "Feature",
  "properties": {
    "iso:country":"US",
    "sg:address":"218 W Main St",
    "sg:city":"Economy",
    "sg:classifiers":[
        {
            "category":"Government",
            "subcategory":"Post Office",
            "type":"Public Place"
        }
    ],
    "sg:phone":"+1 765 886 5939",
    "sg:postcode":"47339",
    "sg:province":"IN",
    "wof:name":"US Post Office",
    "wof:placetype":"venue"
},
  "geometry": {"coordinates":[-85.088966,39.977847],"type":"Point"}
}