{
  "type": "Feature",
  "properties": {
    "addr:full":"4673 E 200 S Avilla IN 46710",
    "addr:housenumber":"4673",
    "addr:postcode":"46710",
    "addr:street":"E 200 S Avilla",
    "iso:country":"US",
    "sg:address":"4673 E 200 S",
    "sg:city":"Avilla",
    "sg:classifiers":[
        {
            "category":"Farming",
            "subcategory":"Livestock Farm",
            "type":"Manufacturing & Wholesale Goods"
        }
    ],
    "sg:phone":"+1 260 636 2479",
    "sg:postcode":"46710",
    "sg:province":"IN",
    "sg:tags":[
        "beef",
        "corn",
        "crop",
        "field",
        "cattle",
        "feedlot"
    ],
    "wof:name":"Robert McDowell",
    "wof:placetype":"venue"
},
  "geometry": {"coordinates":[-85.33037899999999,41.322481],"type":"Point"}
}