{
  "type": "Feature",
  "properties": {
    "addr:full":"5826 N Clinton St Fort Wayne IN 46825",
    "addr:housenumber":"5826",
    "addr:postcode":"46825",
    "addr:street":"N Clinton St",
    "iso:country":"US",
    "sg:address":"5826 N Clinton St",
    "sg:city":"Fort Wayne",
    "sg:classifiers":[
        {
            "category":"Professional",
            "type":"Services"
        }
    ],
    "sg:phone":"+1 260 484 6808",
    "sg:postcode":"46825",
    "sg:province":"IN",
    "wof:name":"Keefer Professional Svc",
    "wof:placetype":"venue"
},
  "geometry": {"coordinates":[-85.124045,41.12922],"type":"Point"}
}