{
  "type": "Feature",
  "properties": {
    "iso:country":"US",
    "sg:address":"7950 Allison Ave",
    "sg:city":"Indianapolis",
    "sg:classifiers":[
        {
            "category":"Manufacturing",
            "subcategory":"Chemicals & Compounds",
            "type":"Manufacturing & Wholesale Goods"
        }
    ],
    "sg:phone":"+1 317 876 4100",
    "sg:postcode":"46268",
    "sg:province":"IN",
    "sg:tags":[
        "plastic"
    ],
    "sg:website":"www.sealedair.com",
    "wof:name":"Cryovac Inc",
    "wof:placetype":"venue"
},
  "geometry": {"coordinates":[-86.250207,39.897457],"type":"Point"}
}