{
  "type": "Feature",
  "properties": {
    "iso:country":"US",
    "sg:address":"603 S Jackson St",
    "sg:city":"Auburn",
    "sg:classifiers":[
        {
            "category":"Education",
            "subcategory":"Library",
            "type":"Public Place"
        }
    ],
    "sg:phone":"+1 260 925 2414",
    "sg:postcode":"46706",
    "sg:province":"IN",
    "sg:website":"www.epl.lib.in.us",
    "wof:name":"Eckhart Public Library",
    "wof:placetype":"venue"
},
  "geometry": {"coordinates":[-85.057099,41.364163],"type":"Point"}
}