{
  "type": "Feature",
  "properties": {
    "iso:country":"US",
    "sg:address":"6955 Madison Ave",
    "sg:city":"Indianapolis",
    "sg:classifiers":[
        {
            "category":"Retail",
            "subcategory":"Veterinary Services",
            "type":"Services"
        }
    ],
    "sg:phone":"+1 317 786 1483",
    "sg:postcode":"46227",
    "sg:province":"IN",
    "sg:tags":[
        "hospital",
        "animal"
    ],
    "wof:name":"Southport Pet Hospital",
    "wof:placetype":"venue"
},
  "geometry": {"coordinates":[-86.12704,39.665138],"type":"Point"}
}