{
  "type": "Feature",
  "properties": {
    "iso:country":"US",
    "sg:address":"7442 Perrier Dr",
    "sg:city":"Indianapolis",
    "sg:classifiers":[
        {
            "category":"Building & Trades",
            "subcategory":"Cleaning & Sanitation",
            "type":"Services"
        }
    ],
    "sg:phone":"+1 317 870 0034",
    "sg:postcode":"46278",
    "sg:province":"IN",
    "sg:tags":[
        "house",
        "construction",
        "site-clean-up",
        "cleaners-interior"
    ],
    "wof:name":"PNC LLC Patty Newman Cleaning",
    "wof:placetype":"venue"
},
  "geometry": {"coordinates":[-86.28224299999999,39.88734],"type":"Point"}
}