{
  "type": "Feature",
  "properties": {
    "iso:country":"US",
    "sg:address":"62 Oak Tree Dr",
    "sg:city":"Brownsburg",
    "sg:classifiers":[
        {
            "category":"Restaurant",
            "type":"Food & Drink"
        }
    ],
    "sg:phone":"+1 317 852 2332",
    "sg:postcode":"46112",
    "sg:province":"IN",
    "wof:name":"Vineyard On The Square",
    "wof:placetype":"venue"
},
  "geometry": {"coordinates":[-86.435818,39.863915],"type":"Point"}
}