{
  "type": "Feature",
  "properties": {
    "addr:full":"501 Bloomingdale Dr Bristol IN 46507",
    "addr:housenumber":"501",
    "addr:postcode":"46507",
    "addr:street":"Bloomingdale Dr",
    "iso:country":"US",
    "sg:address":"501 Bloomingdale Dr",
    "sg:city":"Bristol",
    "sg:classifiers":[
        {
            "category":"Manufacturing",
            "subcategory":"Chemicals & Compounds",
            "type":"Manufacturing & Wholesale Goods"
        }
    ],
    "sg:phone":"+1 574 848 1001",
    "sg:postcode":"46507",
    "sg:province":"IN",
    "sg:tags":[
        "inorganic",
        "industrial"
    ],
    "wof:name":"Chem Tech Inc",
    "wof:placetype":"venue"
},
  "geometry": {"coordinates":[-85.81302700000001,41.711773],"type":"Point"}
}