{
  "type": "Feature",
  "properties": {
    "iso:country":"US",
    "sg:address":"8026 Mc Farland Ct",
    "sg:city":"Indianapolis",
    "sg:classifiers":[
        {
            "category":"Real Estate",
            "subcategory":"Real Estate Operator",
            "type":"Services"
        }
    ],
    "sg:phone":"+1 317 882 2734",
    "sg:postcode":"46227",
    "sg:province":"IN",
    "sg:tags":[
        "apartment"
    ],
    "wof:name":"Sherbrook Apartments",
    "wof:placetype":"venue"
},
  "geometry": {"coordinates":[-86.110475,39.649909],"type":"Point"}
}