{
  "type": "Feature",
  "properties": {
    "iso:country":"US",
    "sg:address":"1170 Wahl St",
    "sg:city":"Chesterton",
    "sg:classifiers":[
        {
            "category":"Freight",
            "type":"Transportation"
        }
    ],
    "sg:phone":"+1 219 787 8778",
    "sg:postcode":"46304",
    "sg:province":"IN",
    "sg:tags":[
        "commercial",
        "storage"
    ],
    "wof:name":"Burns Harbor Storage",
    "wof:placetype":"venue"
},
  "geometry": {"coordinates":[-87.12531199999999,41.602917],"type":"Point"}
}