{
  "type": "Feature",
  "properties": {
    "iso:country":"US",
    "sg:address":"200 S 6th St",
    "sg:city":"Vincennes",
    "sg:classifiers":[
        {
            "category":"Health Services",
            "subcategory":"Doctor",
            "type":"Services"
        }
    ],
    "sg:phone":"+1 812 882 4320",
    "sg:postcode":"47591",
    "sg:province":"IN",
    "sg:tags":[
        "physician",
        "surgeon"
    ],
    "sg:website":"www.urology-specialists.com",
    "wof:name":"Urology Specialists",
    "wof:placetype":"venue"
},
  "geometry": {"coordinates":[-87.53108400000001,38.67572],"type":"Point"}
}