{
  "type": "Feature",
  "properties": {
    "iso:country":"US",
    "sg:address":"1102 Gaiser Dr",
    "sg:city":"Seymour",
    "sg:classifiers":[
        {
            "category":"Manufacturing",
            "subcategory":"Printing",
            "type":"Manufacturing & Wholesale Goods"
        }
    ],
    "sg:phone":"+1 812 522 8675",
    "sg:postcode":"47274",
    "sg:province":"IN",
    "sg:tags":[
        "commercial"
    ],
    "wof:name":"R B's T's",
    "wof:placetype":"venue"
},
  "geometry": {"coordinates":[-85.886652,38.945945],"type":"Point"}
}