{
  "type": "Feature",
  "properties": {
    "iso:country":"US",
    "sg:address":"7766 N Bottom Rd",
    "sg:city":"Ellettsville",
    "sg:classifiers":[
        {
            "category":"Wholesale",
            "subcategory":"Chemicals & Plastics",
            "type":"Manufacturing & Wholesale Goods"
        }
    ],
    "sg:phone":"+1 812 876 1072",
    "sg:postcode":"47429",
    "sg:province":"IN",
    "wof:name":"Sexton Coatings",
    "wof:placetype":"venue"
},
  "geometry": {"coordinates":[-86.595602,39.295525],"type":"Point"}
}