{
  "type": "Feature",
  "properties": {
    "addr:full":"5640 E 38th St Indianapolis IN 46218",
    "addr:housenumber":"5640",
    "addr:postcode":"46218",
    "addr:street":"E 38Th St",
    "iso:country":"US",
    "sg:address":"5640 E 38th St",
    "sg:city":"Indianapolis",
    "sg:classifiers":[
        {
            "category":"Organizations",
            "subcategory":"Religious Organization",
            "type":"Services"
        }
    ],
    "sg:phone":"+1 317 568 1534",
    "sg:postcode":"46218",
    "sg:province":"IN",
    "sg:tags":[
        "church"
    ],
    "wof:name":"Messiah Missionary Baptist Chr",
    "wof:placetype":"venue"
},
  "geometry": {"coordinates":[-86.072828,39.825519],"type":"Point"}
}