{
  "type": "Feature",
  "properties": {
    "iso:country":"US",
    "sg:address":"184 Mallard Dr",
    "sg:city":"Valparaiso",
    "sg:classifiers":[
        {
            "category":"Building & Trades",
            "subcategory":"Construction",
            "type":"Services"
        }
    ],
    "sg:phone":"+1 219 531 1500",
    "sg:postcode":"46385",
    "sg:province":"IN",
    "sg:tags":[
        "contractor"
    ],
    "wof:name":"Creative Drywall Inc",
    "wof:placetype":"venue"
},
  "geometry": {"coordinates":[-87.100809,41.54439],"type":"Point"}
}