{
  "type": "Feature",
  "properties": {
    "iso:country":"US",
    "sg:address":"160 Stacey Hollow Ln",
    "sg:city":"Lafayette",
    "sg:classifiers":[
        {
            "category":"Professional",
            "subcategory":"Business Services",
            "type":"Services"
        }
    ],
    "sg:phone":"+1 765 589 8060",
    "sg:postcode":"47905",
    "sg:province":"IN",
    "sg:tags":[
        "interior",
        "consultant",
        "design",
        "decorator"
    ],
    "wof:name":"Anita L Goris Interior Design",
    "wof:placetype":"venue"
},
  "geometry": {"coordinates":[-86.785576,40.453175],"type":"Point"}
}