{
  "type": "Feature",
  "properties": {
    "addr:full":"5031 Broadway Gary IN 46409",
    "addr:housenumber":"5031",
    "addr:postcode":"46409",
    "addr:street":"Broadway",
    "iso:country":"US",
    "sg:address":"5031 Broadway",
    "sg:city":"Gary",
    "sg:classifiers":[
        {
            "category":"Professional",
            "subcategory":"Management & Consulting",
            "type":"Services"
        }
    ],
    "sg:phone":"+1 219 884 0520",
    "sg:postcode":"46409",
    "sg:province":"IN",
    "sg:tags":[
        "business",
        "general"
    ],
    "wof:name":"Spray Masters",
    "wof:placetype":"venue"
},
  "geometry": {"coordinates":[-87.33613,41.526401],"type":"Point"}
}