{
  "type": "Feature",
  "properties": {
    "iso:country":"US",
    "sg:address":"2004 Charlestown New Albany Rd",
    "sg:city":"Jeffersonville",
    "sg:classifiers":[
        {
            "category":"Professional",
            "subcategory":"Management & Consulting",
            "type":"Services"
        }
    ],
    "sg:phone":"+1 812 284 7292",
    "sg:postcode":"47130",
    "sg:province":"IN",
    "sg:tags":[
        "farm"
    ],
    "wof:name":"Clark County Farm Bureau Incorporated",
    "wof:placetype":"venue"
},
  "geometry": {"coordinates":[-85.740071,38.326256],"type":"Point"}
}