{
  "type": "Feature",
  "properties": {
    "iso:country":"US",
    "sg:address":"105 W Saddleback Trl",
    "sg:city":"Salem",
    "sg:classifiers":[
        {
            "category":"Retail",
            "subcategory":"Auto Rental",
            "type":"Services"
        }
    ],
    "sg:phone":"+1 812 883 0440",
    "sg:postcode":"47167",
    "sg:province":"IN",
    "sg:tags":[
        "renting",
        "automobile"
    ],
    "wof:name":"Enterprise Rent-A-Car",
    "wof:placetype":"venue"
},
  "geometry": {"coordinates":[-86.070319,38.586706],"type":"Point"}
}