{
  "type": "Feature",
  "properties": {
    "iso:country":"US",
    "sg:address":"425 W South St",
    "sg:city":"Indianapolis",
    "sg:classifiers":[
        {
            "category":"Manufacturing",
            "subcategory":"Printing",
            "type":"Manufacturing & Wholesale Goods"
        }
    ],
    "sg:phone":"+1 317 464 0261",
    "sg:postcode":"46225",
    "sg:province":"IN",
    "sg:tags":[
        "commercial"
    ],
    "sg:website":"www.rpsprinting.com",
    "wof:name":"RPS Printing Svc",
    "wof:placetype":"venue"
},
  "geometry": {"coordinates":[-86.166978,39.761572],"type":"Point"}
}