{
  "type": "Feature",
  "properties": {
    "iso:country":"US",
    "sg:address":"4223 Co Rd W 350 N",
    "sg:city":"Kokomo",
    "sg:classifiers":[
        {
            "category":"Education",
            "subcategory":"School",
            "type":"Public Place"
        }
    ],
    "sg:phone":"+1 765 457 8101",
    "sg:postcode":"46901",
    "sg:province":"IN",
    "wof:name":"Northwestern Elementary School",
    "wof:placetype":"venue"
},
  "geometry": {"coordinates":[-86.20722499999999,40.526171],"type":"Point"}
}