{
  "type": "Feature",
  "properties": {
    "iso:country":"US",
    "sg:address":"2031 W Michigan St",
    "sg:city":"Evansville",
    "sg:classifiers":[
        {
            "category":"Education",
            "subcategory":"School",
            "type":"Public Place"
        }
    ],
    "sg:phone":"+1 812 422 1014",
    "sg:postcode":"47712",
    "sg:province":"IN",
    "wof:name":"St Boniface Catholic School",
    "wof:placetype":"venue"
},
  "geometry": {"coordinates":[-87.595091,37.981548],"type":"Point"}
}