{
  "type": "Feature",
  "properties": {
    "iso:country":"US",
    "sg:address":"305 S Washington St",
    "sg:city":"Bloomington",
    "sg:classifiers":[
        {
            "category":"Health Services",
            "subcategory":"Health Practitioner",
            "type":"Services"
        }
    ],
    "sg:phone":"+1 812 333 1305",
    "sg:postcode":"47401",
    "sg:province":"IN",
    "sg:tags":[
        "hypnotist"
    ],
    "wof:name":"Gentle Mental",
    "wof:placetype":"venue"
},
  "geometry": {"coordinates":[-86.532312,39.1629],"type":"Point"}
}