{
  "type": "Feature",
  "properties": {
    "iso:country":"US",
    "sg:address":"9142 Nina Dr",
    "sg:city":"Georgetown",
    "sg:phone":"+1 812 951 3462",
    "sg:postcode":"47122",
    "sg:province":"IN",
    "sg:tags":[
        "electrical",
        "sign"
    ],
    "wof:name":"Information Display Systems",
    "wof:placetype":"venue"
},
  "geometry": {"coordinates":[-85.980571,38.301006],"type":"Point"}
}