{
  "type": "Feature",
  "properties": {
    "iso:country":"US",
    "sg:address":"12454 W Youth Camp Rd",
    "sg:city":"Columbus",
    "sg:classifiers":[
        {
            "category":"Travel",
            "subcategory":"Campground",
            "type":"Entertainment"
        }
    ],
    "sg:phone":"+1 812 342 3205",
    "sg:postcode":"47201",
    "sg:province":"IN",
    "sg:tags":[
        "camp"
    ],
    "wof:name":"Columbus Youth Camp",
    "wof:placetype":"venue"
},
  "geometry": {"coordinates":[-86.055734,39.173136],"type":"Point"}
}