{
  "type": "Feature",
  "properties": {
    "addr:full":"211 S 3rd St Logansport IN 46947",
    "addr:housenumber":"211",
    "addr:postcode":"46947",
    "addr:street":"S 3Rd St",
    "iso:country":"US",
    "sg:address":"211 S 3rd St",
    "sg:city":"Logansport",
    "sg:classifiers":[
        {
            "category":"Real Estate",
            "subcategory":"Real Estate Services",
            "type":"Services"
        }
    ],
    "sg:phone":"+1 574 735 6905",
    "sg:postcode":"46947",
    "sg:province":"IN",
    "sg:tags":[
        "company",
        "title"
    ],
    "sg:website":"www.casstitle.com",
    "wof:name":"Cass County Title Co",
    "wof:placetype":"venue"
},
  "geometry": {"coordinates":[-86.36769,40.754481],"type":"Point"}
}