{
  "type": "Feature",
  "properties": {
    "addr:full":"503 Pearl St Vevay IN 47043",
    "addr:housenumber":"503",
    "addr:postcode":"47043",
    "addr:street":"Pearl St",
    "iso:country":"US",
    "sg:address":"503 Pearl St",
    "sg:city":"Vevay",
    "sg:classifiers":[
        {
            "category":"Health Services",
            "subcategory":"Hospital",
            "type":"Services"
        }
    ],
    "sg:phone":"+1 812 427 2800",
    "sg:postcode":"47043",
    "sg:province":"IN",
    "sg:tags":[
        "mental"
    ],
    "wof:name":"Community Mental Health Ctr",
    "wof:placetype":"venue"
},
  "geometry": {"coordinates":[-85.06659000000001,38.752682],"type":"Point"}
}