{
  "type": "Feature",
  "properties": {
    "iso:country":"US",
    "sg:address":"1114 Prospect St",
    "sg:city":"Indianapolis",
    "sg:classifiers":[
        {
            "category":"Shopping",
            "subcategory":"Florist",
            "type":"Retail Goods"
        }
    ],
    "sg:phone":"+1 317 917 1888",
    "sg:postcode":"46203",
    "sg:province":"IN",
    "wof:name":"Flowers On The Square",
    "wof:placetype":"venue"
},
  "geometry": {"coordinates":[-86.138761,39.752412],"type":"Point"}
}