{
  "type": "Feature",
  "properties": {
    "iso:country":"US",
    "sg:address":"710 E Chicago Ave",
    "sg:city":"East Chicago",
    "sg:classifiers":[
        {
            "category":"Shopping",
            "type":"Retail Goods"
        }
    ],
    "sg:phone":"+1 219 397 3281",
    "sg:postcode":"46312",
    "sg:province":"IN",
    "sg:tags":[
        "ice"
    ],
    "wof:name":"Lang New City Ice",
    "wof:placetype":"venue"
},
  "geometry": {"coordinates":[-87.463156,41.629325],"type":"Point"}
}