{
  "type": "Feature",
  "properties": {
    "iso:country":"US",
    "sg:address":"1754 N Audubon Dr",
    "sg:city":"New Albany",
    "sg:classifiers":[
        {
            "category":"Wholesale",
            "subcategory":"Durable Goods & Equipment",
            "type":"Manufacturing & Wholesale Goods"
        }
    ],
    "sg:phone":"+1 812 948 0007",
    "sg:postcode":"47150",
    "sg:province":"IN",
    "sg:tags":[
        "fire",
        "extinguisher"
    ],
    "wof:name":"Metro Fire Equipment Co",
    "wof:placetype":"venue"
},
  "geometry": {"coordinates":[-85.807713,38.316832],"type":"Point"}
}