{
  "type": "Feature",
  "properties": {
    "addr:full":"302 W Superior St Fort Wayne IN 46802",
    "addr:housenumber":"302",
    "addr:postcode":"46802",
    "addr:street":"W Superior St",
    "iso:country":"US",
    "sg:address":"302 W Superior St",
    "sg:city":"Fort Wayne",
    "sg:classifiers":[
        {
            "category":"Wholesale",
            "subcategory":"Electrical",
            "type":"Manufacturing & Wholesale Goods"
        }
    ],
    "sg:phone":"+1 260 424 1901",
    "sg:postcode":"46802",
    "sg:province":"IN",
    "sg:tags":[
        "fire",
        "equipment",
        "protection"
    ],
    "wof:name":"Fire Protection Svc",
    "wof:placetype":"venue"
},
  "geometry": {"coordinates":[-85.144475,41.081793],"type":"Point"}
}