{
  "type": "Feature",
  "properties": {
    "iso:country":"US",
    "sg:address":"6425 N State Rd 25",
    "sg:city":"Rockfield",
    "sg:classifiers":[
        {
            "category":"Shopping",
            "subcategory":"Hobbies, Toys, & Games",
            "type":"Retail Goods"
        }
    ],
    "sg:phone":"+1 574 686 2750",
    "sg:postcode":"46923",
    "sg:province":"IN",
    "sg:tags":[
        "shop",
        "rock"
    ],
    "wof:name":"Bill's Rock Shop",
    "wof:placetype":"venue"
},
  "geometry": {"coordinates":[-86.577788,40.640487],"type":"Point"}
}