{
  "type": "Feature",
  "properties": {
    "iso:country":"US",
    "sg:address":"113 W 7th St",
    "sg:city":"Bloomington",
    "sg:classifiers":[
        {
            "category":"Shopping",
            "subcategory":"Clothing, Apparel, & Fashions",
            "type":"Retail Goods"
        }
    ],
    "sg:phone":"+1 812 330 0276",
    "sg:postcode":"47404",
    "sg:province":"IN",
    "sg:tags":[
        "designer"
    ],
    "wof:name":"Urban Stylz Inc",
    "wof:placetype":"venue"
},
  "geometry": {"coordinates":[-86.534735,39.168483],"type":"Point"}
}