{
  "type": "Feature",
  "properties": {
    "iso:country":"US",
    "sg:address":"3924 Pendleton Way",
    "sg:city":"Indianapolis",
    "sg:phone":"+1 317 547 2424",
    "sg:postcode":"46226",
    "sg:province":"IN",
    "wof:name":"Brickyard Gutter Systems",
    "wof:placetype":"venue"
},
  "geometry": {"coordinates":[-86.036708,39.831113],"type":"Point"}
}