{
  "type": "Feature",
  "properties": {
    "addr:full":"2801 S Michigan St South Bend IN 46614",
    "addr:housenumber":"2801",
    "addr:postcode":"46614",
    "addr:street":"S Michigan St",
    "iso:country":"US",
    "sg:address":"2801 S Michigan St",
    "sg:city":"South Bend",
    "sg:classifiers":[
        {
            "category":"Restaurant",
            "type":"Food & Drink"
        }
    ],
    "sg:phone":"+1 574 299 9126",
    "sg:postcode":"46614",
    "sg:province":"IN",
    "sg:tags":[
        "catering"
    ],
    "wof:name":"Landing Catering",
    "wof:placetype":"venue"
},
  "geometry": {"coordinates":[-86.24960799999999,41.644386],"type":"Point"}
}