{
  "type": "Feature",
  "properties": {
    "iso:country":"US",
    "sg:address":"2125 Bergdolt Rd",
    "sg:city":"Evansville",
    "sg:classifiers":[
        {
            "category":"Manufacturing",
            "subcategory":"Tools & Machinery",
            "type":"Manufacturing & Wholesale Goods"
        }
    ],
    "sg:phone":"+1 812 464 3650",
    "sg:postcode":"47711",
    "sg:province":"IN",
    "sg:tags":[
        "die",
        "maker"
    ],
    "wof:name":"A & A Metal Products Inc",
    "wof:placetype":"venue"
},
  "geometry": {"coordinates":[-87.526107,38.02058],"type":"Point"}
}