{
  "type": "Feature",
  "properties": {
    "iso:country":"US",
    "sg:address":"2002 N Pasadena St",
    "sg:city":"Indianapolis",
    "sg:classifiers":[
        {
            "category":"Wholesale",
            "subcategory":"Chemicals & Plastics",
            "type":"Manufacturing & Wholesale Goods"
        }
    ],
    "sg:phone":"+1 317 359 6725",
    "sg:postcode":"46219",
    "sg:province":"IN",
    "sg:tags":[
        "oil"
    ],
    "wof:name":"Amsoil Dealer",
    "wof:placetype":"venue"
},
  "geometry": {"coordinates":[-86.05381800000001,39.796337],"type":"Point"}
}