{
  "type": "Feature",
  "properties": {
    "iso:country":"US",
    "sg:address":"7869 S State Rd 63",
    "sg:city":"Terre Haute",
    "sg:classifiers":[
        {
            "category":"Retail",
            "subcategory":"Auto Repair",
            "type":"Services"
        }
    ],
    "sg:phone":"+1 812 299 1510",
    "sg:postcode":"47802",
    "sg:province":"IN",
    "sg:tags":[
        "body",
        "automobile",
        "painting"
    ],
    "wof:name":"A Z Auto Body",
    "wof:placetype":"venue"
},
  "geometry": {"coordinates":[-87.47309799999999,39.371741],"type":"Point"}
}