{
  "type": "Feature",
  "properties": {
    "addr:full":"3780 W Jonathan Moore Pike Columbus IN 47201",
    "addr:housenumber":"3780",
    "addr:postcode":"47201",
    "addr:street":"W Jonathan Moore Pike",
    "iso:country":"US",
    "sg:address":"3780 W Jonathan Moore Pike",
    "sg:city":"Columbus",
    "sg:classifiers":[
        {
            "category":"Personal",
            "subcategory":"Beauty Salon",
            "type":"Services"
        }
    ],
    "sg:phone":"+1 812 342 7100",
    "sg:postcode":"47201",
    "sg:province":"IN",
    "wof:name":"Serenities Salon & Day Spa",
    "wof:placetype":"venue"
},
  "geometry": {"coordinates":[-85.966399,39.200082],"type":"Point"}
}