{
  "type": "Feature",
  "properties": {
    "addr:full":"3401 S US Hwy 41 Terre Haute IN 47802",
    "addr:housenumber":"3401",
    "addr:postcode":"47802",
    "addr:street":"S Us Hwy 41",
    "iso:country":"US",
    "sg:address":"3401 S US Hwy 41",
    "sg:city":"Terre Haute",
    "sg:classifiers":[
        {
            "category":"Restaurant",
            "type":"Food & Drink"
        }
    ],
    "sg:phone":"+1 812 232 8444",
    "sg:postcode":"47802",
    "sg:province":"IN",
    "sg:website":"www.tgifridays.com",
    "wof:name":"TGI Friday's",
    "wof:placetype":"venue"
},
  "geometry": {"coordinates":[-87.416135,39.424134],"type":"Point"}
}