{
  "type": "Feature",
  "properties": {
    "addr:full":"1647 Presidential Dr New Haven IN 46774",
    "addr:housenumber":"1647",
    "addr:postcode":"46774",
    "addr:street":"Presidential Dr",
    "iso:country":"US",
    "sg:address":"1647 Presidential Dr",
    "sg:city":"New Haven",
    "sg:classifiers":[
        {
            "category":"Professional",
            "subcategory":"Management & Consulting",
            "type":"Services"
        }
    ],
    "sg:phone":"+1 260 493 4384",
    "sg:postcode":"46774",
    "sg:province":"IN",
    "sg:tags":[
        "business"
    ],
    "wof:name":"Janice Gfell Consultant",
    "wof:placetype":"venue"
},
  "geometry": {"coordinates":[-85.03570999999999,41.057281],"type":"Point"}
}