{
  "type": "Feature",
  "properties": {
    "iso:country":"US",
    "sg:address":"3101 W Co Rd 750 N",
    "sg:city":"Muncie",
    "sg:phone":"+1 765 286 2895",
    "sg:postcode":"47303",
    "sg:province":"IN",
    "sg:tags":[
        "farm",
        "corn",
        "soybean"
    ],
    "wof:name":"Bret Lancaster",
    "wof:placetype":"venue"
},
  "geometry": {"coordinates":[-85.42158499999999,40.298815],"type":"Point"}
}