{
  "type": "Feature",
  "properties": {
    "iso:country":"US",
    "sg:address":"259 S 3rd St",
    "sg:city":"Frankfort",
    "sg:classifiers":[
        {
            "category":"Organizations",
            "subcategory":"Community Association",
            "type":"Services"
        }
    ],
    "sg:phone":"+1 765 654 8082",
    "sg:postcode":"46041",
    "sg:province":"IN",
    "sg:tags":[
        "club"
    ],
    "wof:name":"Neighborhood Center",
    "wof:placetype":"venue"
},
  "geometry": {"coordinates":[-86.51678099999999,40.279081],"type":"Point"}
}