{
  "type": "Feature",
  "properties": {
    "iso:country":"US",
    "sg:address":"28343 Co Rd 10",
    "sg:city":"Elkhart",
    "sg:classifiers":[
        {
            "category":"Professional",
            "subcategory":"Lawyer & Legal Services",
            "type":"Services"
        }
    ],
    "sg:phone":"+1 574 266 6133",
    "sg:postcode":"46514",
    "sg:province":"IN",
    "wof:name":"Daniel Strahm",
    "wof:placetype":"venue"
},
  "geometry": {"coordinates":[-86.014535,41.705689],"type":"Point"}
}