{
  "type": "Feature",
  "properties": {
    "addr:full":"2963 E 725 N Dubois IN 47527",
    "addr:housenumber":"2963",
    "addr:postcode":"47527",
    "addr:street":"E 725 N Dubois",
    "iso:country":"US",
    "sg:address":"2963 E 725 N",
    "sg:city":"Dubois",
    "sg:classifiers":[
        {
            "category":"Farming",
            "subcategory":"Farm",
            "type":"Manufacturing & Wholesale Goods"
        }
    ],
    "sg:phone":"+1 812 678 5100",
    "sg:postcode":"47527",
    "sg:province":"IN",
    "wof:name":"Skyview Farms",
    "wof:placetype":"venue"
},
  "geometry": {"coordinates":[-86.862275,38.498305],"type":"Point"}
}