{
  "type": "Feature",
  "properties": {
    "iso:country":"US",
    "sg:address":"395 E Davis Dr",
    "sg:city":"Terre Haute",
    "sg:classifiers":[
        {
            "category":"Restaurant",
            "type":"Food & Drink"
        },
        {
            "category":"Ice Cream",
            "type":"Food & Drink"
        }
    ],
    "sg:menulink":"http://www.allmenus.com/in/honey-creek/161667-dairy-queen/menu/",
    "sg:phone":"+1 812 234 9653",
    "sg:postcode":"47802",
    "sg:province":"IN",
    "sg:tags":[
        "burger",
        "american",
        "ice",
        "cream"
    ],
    "wof:name":"Dairy Queen",
    "wof:placetype":"venue"
},
  "geometry": {"coordinates":[-87.412323,39.426877],"type":"Point"}
}