{
  "type": "Feature",
  "properties": {
    "addr:full":"200 W Franciscan Dr Crown Point IN 46307",
    "addr:housenumber":"200",
    "addr:postcode":"46307",
    "addr:street":"W Franciscan Dr",
    "iso:country":"US",
    "sg:address":"200 W Franciscan Dr",
    "sg:city":"Crown Point",
    "sg:classifiers":[
        {
            "category":"Food & Beverages",
            "subcategory":"Groceries & Convenience Stores",
            "type":"Retail Goods"
        }
    ],
    "sg:phone":"+1 219 663 3345",
    "sg:postcode":"46307",
    "sg:province":"IN",
    "sg:website":"strackandvantil.com",
    "wof:name":"Strack & Van Til Crown Point",
    "wof:placetype":"venue"
},
  "geometry": {"coordinates":[-87.366096,41.398399],"type":"Point"}
}