{
  "type": "Feature",
  "properties": {
    "addr:full":"9199 Old State Rd 3 Otisco IN 47163",
    "addr:housenumber":"9199",
    "addr:postcode":"47163",
    "addr:street":"Old State Rd 3 Otisco",
    "iso:country":"US",
    "sg:address":"9199 Old State Rd 3",
    "sg:city":"Otisco",
    "sg:classifiers":[
        {
            "category":"Organizations",
            "subcategory":"Religious Organization",
            "type":"Services"
        }
    ],
    "sg:phone":"+1 812 256 0486",
    "sg:postcode":"47163",
    "sg:province":"IN",
    "sg:tags":[
        "church"
    ],
    "wof:name":"Emmanuel United Methodist Chr",
    "wof:placetype":"venue"
},
  "geometry": {"coordinates":[-85.658022,38.573145],"type":"Point"}
}