{
  "type": "Feature",
  "properties": {
    "iso:country":"US",
    "sg:address":"216 E Washington St",
    "sg:city":"Fairmount",
    "sg:classifiers":[
        {
            "category":"Retail",
            "subcategory":"Auto Repair",
            "type":"Services"
        }
    ],
    "sg:phone":"+1 765 948 4185",
    "sg:postcode":"46928",
    "sg:province":"IN",
    "sg:tags":[
        "general"
    ],
    "wof:name":"Peters Garage",
    "wof:placetype":"venue"
},
  "geometry": {"coordinates":[-85.649358,40.415582],"type":"Point"}
}