{
  "type": "Feature",
  "properties": {
    "iso:country":"US",
    "sg:address":"25019 Underpass Rd",
    "sg:city":"Batesville",
    "sg:classifiers":[
        {
            "category":"Government",
            "subcategory":"Office",
            "type":"Public Place"
        }
    ],
    "sg:phone":"+1 812 934 5338",
    "sg:postcode":"47006",
    "sg:province":"IN",
    "sg:tags":[
        "village"
    ],
    "wof:name":"Batesville Wastewater Trtmnt",
    "wof:placetype":"venue"
},
  "geometry": {"coordinates":[-85.236199,39.299132],"type":"Point"}
}