{
  "type": "Feature",
  "properties": {
    "iso:country":"US",
    "sg:address":"12721 Kiawah Dr",
    "sg:city":"Carmel",
    "sg:classifiers":[
        {
            "category":"Health Services",
            "subcategory":"Doctor",
            "type":"Services"
        }
    ],
    "sg:phone":"+1 317 846 0674",
    "sg:postcode":"46033",
    "sg:province":"IN",
    "sg:tags":[
        "physician",
        "surgeon",
        "anesthesiology",
        "surgeons"
    ],
    "wof:name":"Riverview Anaestheologists Inc",
    "wof:placetype":"venue"
},
  "geometry": {"coordinates":[-86.066355,39.974985],"type":"Point"}
}