{
  "type": "Feature",
  "properties": {
    "iso:country":"US",
    "sg:address":"5770 E 226th St",
    "sg:city":"Cicero",
    "sg:phone":"+1 317 984 4336",
    "sg:postcode":"46034",
    "sg:province":"IN",
    "sg:tags":[
        "farm",
        "corn",
        "soybean"
    ],
    "wof:name":"Ron McGill",
    "wof:placetype":"venue"
},
  "geometry": {"coordinates":[-86.068479,40.116164],"type":"Point"}
}