{
  "type": "Feature",
  "properties": {
    "addr:full":"913 N Lasalle St Indianapolis IN 46201",
    "addr:housenumber":"913",
    "addr:postcode":"46201",
    "addr:street":"N Lasalle St",
    "iso:country":"US",
    "sg:address":"913 N Lasalle St",
    "sg:city":"Indianapolis",
    "sg:classifiers":[
        {
            "category":"Personal",
            "subcategory":"Barber",
            "type":"Services"
        }
    ],
    "sg:phone":"+1 317 636 7004",
    "sg:postcode":"46201",
    "sg:province":"IN",
    "sg:tags":[
        "shop",
        "beauty"
    ],
    "wof:name":"Susies Scissors Fabulous Hair",
    "wof:placetype":"venue"
},
  "geometry": {"coordinates":[-86.10968699999999,39.779702],"type":"Point"}
}