{
  "type": "Feature",
  "properties": {
    "iso:country":"US",
    "sg:address":"7320 Cape Cod Cir",
    "sg:city":"Indianapolis",
    "sg:classifiers":[
        {
            "category":"Professional",
            "subcategory":"Employment Agencies",
            "type":"Services"
        }
    ],
    "sg:phone":"+1 317 849 3544",
    "sg:postcode":"46250",
    "sg:province":"IN",
    "wof:name":"Insurance People",
    "wof:placetype":"venue"
},
  "geometry": {"coordinates":[-86.067486,39.889417],"type":"Point"}
}