{
  "type": "Feature",
  "properties": {
    "addr:full":"570 N Grandstaff Dr Auburn IN 46706",
    "addr:housenumber":"570",
    "addr:postcode":"46706",
    "addr:street":"N Grandstaff Dr",
    "iso:country":"US",
    "sg:address":"570 N Grandstaff Dr",
    "sg:city":"Auburn",
    "sg:classifiers":[
        {
            "category":"Personal",
            "subcategory":"Tanning Parlor",
            "type":"Services"
        }
    ],
    "sg:phone":"+1 260 925 3300",
    "sg:postcode":"46706",
    "sg:province":"IN",
    "sg:tags":[
        "salon"
    ],
    "wof:name":"Summer Illusions",
    "wof:placetype":"venue"
},
  "geometry": {"coordinates":[-85.07151399999999,41.366991],"type":"Point"}
}