{
  "type": "Feature",
  "properties": {
    "iso:country":"US",
    "sg:address":"58100 Pottawatomie St",
    "sg:city":"Osceola",
    "sg:classifiers":[
        {
            "category":"Organizations",
            "subcategory":"Religious Organization",
            "type":"Services"
        }
    ],
    "sg:phone":"+1 574 674 8199",
    "sg:postcode":"46561",
    "sg:province":"IN",
    "sg:tags":[
        "church"
    ],
    "wof:name":"Voice Ministries",
    "wof:placetype":"venue"
},
  "geometry": {"coordinates":[-86.058238,41.651236],"type":"Point"}
}