{
  "type": "Feature",
  "properties": {
    "addr:full":"1821 E 151st St Carmel IN 46033",
    "addr:housenumber":"1821",
    "addr:postcode":"46033",
    "addr:street":"E 151St St",
    "iso:country":"US",
    "sg:address":"1821 E 151st St",
    "sg:city":"Carmel",
    "sg:classifiers":[
        {
            "category":"Autos & Motor Vehicles",
            "subcategory":"Fuel & Gas Station",
            "type":"Retail Goods"
        }
    ],
    "sg:phone":"+1 317 844 9295",
    "sg:postcode":"46033",
    "sg:province":"IN",
    "sg:tags":[
        "oil"
    ],
    "wof:name":"Shell Convenience Stores",
    "wof:placetype":"venue"
},
  "geometry": {"coordinates":[-86.12716399999999,40.007438],"type":"Point"}
}