{
  "type": "Feature",
  "properties": {
    "iso:country":"US",
    "sg:address":"1324 19th St",
    "sg:city":"Bedford",
    "sg:classifiers":[
        {
            "category":"Organizations",
            "subcategory":"Religious Organization",
            "type":"Services"
        }
    ],
    "sg:phone":"+1 812 275 6732",
    "sg:postcode":"47421",
    "sg:province":"IN",
    "wof:name":"Midtown Church of Christ Inc",
    "wof:placetype":"venue"
},
  "geometry": {"coordinates":[-86.489752,38.857619],"type":"Point"}
}