{
  "type": "Feature",
  "properties": {
    "addr:full":"1 N Capitol Ave Indianapolis IN 46204",
    "addr:housenumber":"1",
    "addr:postcode":"46204",
    "addr:street":"N Capitol Ave",
    "iso:country":"US",
    "sg:address":"1 N Capitol Ave",
    "sg:city":"Indianapolis",
    "sg:classifiers":[
        {
            "category":"Government",
            "subcategory":"Office",
            "type":"Public Place"
        }
    ],
    "sg:phone":"+1 317 232 0159",
    "sg:postcode":"46204",
    "sg:province":"IN",
    "sg:tags":[
        "affairs",
        "state"
    ],
    "sg:website":"www.indianacommerce.com",
    "wof:name":"Business Development",
    "wof:placetype":"venue"
},
  "geometry": {"coordinates":[-86.16168999999999,39.767905],"type":"Point"}
}