{
  "type": "Feature",
  "properties": {
    "iso:country":"US",
    "sg:address":"2721 N Routiers Ave",
    "sg:city":"Indianapolis",
    "sg:classifiers":[
        {
            "category":"Building & Trades",
            "subcategory":"Construction",
            "type":"Services"
        }
    ],
    "sg:phone":"+1 317 898 5157",
    "sg:postcode":"46219",
    "sg:province":"IN",
    "sg:tags":[
        "home",
        "contractor",
        "remodeling",
        "residential"
    ],
    "wof:name":"Victor Chappelow Construction",
    "wof:placetype":"venue"
},
  "geometry": {"coordinates":[-86.01367500000001,39.807747],"type":"Point"}
}