{
  "type": "Feature",
  "properties": {
    "iso:country":"US",
    "sg:address":"14613 Lima Rd",
    "sg:city":"Fort Wayne",
    "sg:classifiers":[
        {
            "category":"Shopping",
            "type":"Retail Goods"
        },
        {
            "category":"Food & Beverages",
            "subcategory":"Bakery",
            "type":"Retail Goods"
        }
    ],
    "sg:phone":"+1 260 637 2253",
    "sg:postcode":"46818",
    "sg:province":"IN",
    "sg:tags":[
        "wedding",
        "supply"
    ],
    "wof:name":"Moments In Time Cakery",
    "wof:placetype":"venue"
},
  "geometry": {"coordinates":[-85.171948,41.218036],"type":"Point"}
}