{
  "type": "Feature",
  "properties": {
    "iso:country":"US",
    "sg:address":"1601 S Nebo Rd",
    "sg:city":"Yorktown",
    "sg:classifiers":[
        {
            "category":"Building & Trades",
            "subcategory":"Construction",
            "type":"Services"
        }
    ],
    "sg:phone":"+1 765 751 9990",
    "sg:postcode":"47396",
    "sg:province":"IN",
    "sg:tags":[
        "finishing",
        "wood",
        "refinishing"
    ],
    "wof:name":"Wood Truss Systems Inc",
    "wof:placetype":"venue"
},
  "geometry": {"coordinates":[-85.461845,40.176883],"type":"Point"}
}