{
  "type": "Feature",
  "properties": {
    "iso:country":"US",
    "sg:address":"11 Pine Lake Ave",
    "sg:city":"Laporte",
    "sg:classifiers":[
        {
            "category":"Manufacturing",
            "subcategory":"Tools & Machinery",
            "type":"Manufacturing & Wholesale Goods"
        }
    ],
    "sg:phone":"+1 219 326 9270",
    "sg:postcode":"46350",
    "sg:province":"IN",
    "sg:tags":[
        "metalworking"
    ],
    "wof:name":"Dynamic Metalworking Inc",
    "wof:placetype":"venue"
},
  "geometry": {"coordinates":[-86.72713,41.612756],"type":"Point"}
}