{
  "type": "Feature",
  "properties": {
    "addr:full":"3721 Charlestown Rd New Albany IN 47150",
    "addr:housenumber":"3721",
    "addr:postcode":"47150",
    "addr:street":"Charlestown Rd",
    "iso:country":"US",
    "sg:address":"3721 Charlestown Rd",
    "sg:city":"New Albany",
    "sg:classifiers":[
        {
            "category":"Retail",
            "subcategory":"Auto Repair",
            "type":"Services"
        }
    ],
    "sg:phone":"+1 812 944 5750",
    "sg:postcode":"47150",
    "sg:province":"IN",
    "sg:tags":[
        "automobile",
        "lubrication"
    ],
    "wof:name":"Pennzoil 10 Minute Oil Change",
    "wof:placetype":"venue"
},
  "geometry": {"coordinates":[-85.796618,38.348927],"type":"Point"}
}