{
  "type": "Feature",
  "properties": {
    "iso:country":"US",
    "sg:address":"2121 S Co Rd 600 W",
    "sg:city":"French Lick",
    "sg:classifiers":[
        {
            "category":"Retail",
            "subcategory":"Portrait Studio",
            "type":"Services"
        }
    ],
    "sg:phone":"+1 812 936 2295",
    "sg:postcode":"47432",
    "sg:province":"IN",
    "sg:tags":[
        "photo"
    ],
    "wof:name":"Natures Background Photography",
    "wof:placetype":"venue"
},
  "geometry": {"coordinates":[-86.570636,38.527118],"type":"Point"}
}