{
  "type": "Feature",
  "properties": {
    "iso:country":"US",
    "sg:address":"10570 N State Rd 9",
    "sg:city":"Fountaintown",
    "sg:classifiers":[
        {
            "category":"Farming",
            "subcategory":"Farm",
            "type":"Manufacturing & Wholesale Goods"
        }
    ],
    "sg:phone":"+1 317 861 1707",
    "sg:postcode":"46130",
    "sg:province":"IN",
    "sg:tags":[
        "crop",
        "general"
    ],
    "wof:name":"Roger Batton",
    "wof:placetype":"venue"
},
  "geometry": {"coordinates":[-85.773277,39.678067],"type":"Point"}
}