{
  "type": "Feature",
  "properties": {
    "iso:country":"US",
    "sg:address":"202 Luther Cir",
    "sg:city":"Jeffersonville",
    "sg:classifiers":[
        {
            "category":"Building & Trades",
            "subcategory":"Landscaping Services",
            "type":"Services"
        }
    ],
    "sg:phone":"+1 812 282 0010",
    "sg:postcode":"47130",
    "sg:province":"IN",
    "wof:name":"Jr Lawn Service",
    "wof:placetype":"venue"
},
  "geometry": {"coordinates":[-85.745309,38.284541],"type":"Point"}
}