{
  "type": "Feature",
  "properties": {
    "iso:country":"US",
    "sg:address":"128 N East St",
    "sg:city":"Crown Point",
    "sg:classifiers":[
        {
            "category":"Government",
            "subcategory":"Office",
            "type":"Public Place"
        }
    ],
    "sg:phone":"+1 219 662 3249",
    "sg:postcode":"46307",
    "sg:province":"IN",
    "sg:tags":[
        "village"
    ],
    "wof:name":"Crown Point Fire Rescue",
    "wof:placetype":"venue"
},
  "geometry": {"coordinates":[-87.363187,41.418009],"type":"Point"}
}