{
  "type": "Feature",
  "properties": {
    "addr:full":"217 W North St Indianapolis IN 46202",
    "addr:housenumber":"217",
    "addr:postcode":"46202",
    "addr:street":"W North St",
    "iso:country":"US",
    "sg:address":"217 W North St",
    "sg:city":"Indianapolis",
    "sg:classifiers":[
        {
            "category":"Food & Beverages",
            "subcategory":"Candy",
            "type":"Retail Goods"
        }
    ],
    "sg:phone":"+1 317 634 4216",
    "sg:postcode":"46202",
    "sg:province":"IN",
    "sg:tags":[
        "confectionery"
    ],
    "wof:name":"WYTE Chocolate",
    "wof:placetype":"venue"
},
  "geometry": {"coordinates":[-86.163095,39.775557],"type":"Point"}
}