{
  "type": "Feature",
  "properties": {
    "addr:full":"9553 Valparaiso Ct Indianapolis IN 46268",
    "addr:housenumber":"9553",
    "addr:postcode":"46268",
    "addr:street":"Valparaiso Ct",
    "iso:country":"US",
    "sg:address":"9553 Valparaiso Ct",
    "sg:city":"Indianapolis",
    "sg:classifiers":[
        {
            "category":"Government",
            "subcategory":"Office",
            "type":"Public Place"
        }
    ],
    "sg:phone":"+1 317 872 2356",
    "sg:postcode":"46268",
    "sg:province":"IN",
    "wof:name":"US Dept Of Agricultural",
    "wof:placetype":"venue"
},
  "geometry": {"coordinates":[-86.226361,39.925643],"type":"Point"}
}