{
  "type": "Feature",
  "properties": {
    "iso:country":"US",
    "sg:address":"1556 N State St",
    "sg:city":"Greenfield",
    "sg:classifiers":[
        {
            "category":"Shopping",
            "type":"Retail Goods"
        }
    ],
    "sg:phone":"+1 317 477 0053",
    "sg:postcode":"46140",
    "sg:province":"IN",
    "sg:tags":[
        "equipment",
        "care",
        "health",
        "home"
    ],
    "wof:name":"Home Med",
    "wof:placetype":"venue"
},
  "geometry": {"coordinates":[-85.769872,39.805443],"type":"Point"}
}