{
  "type": "Feature",
  "properties": {
    "iso:country":"US",
    "sg:address":"3607 Brooklyn Ave",
    "sg:city":"Fort Wayne",
    "sg:classifiers":[
        {
            "category":"Home & Garden",
            "subcategory":"Building Materials",
            "type":"Retail Goods"
        }
    ],
    "sg:phone":"+1 260 478 6676",
    "sg:postcode":"46809",
    "sg:province":"IN",
    "sg:tags":[
        "paint"
    ],
    "wof:name":"Norm's Paint Supply",
    "wof:placetype":"venue"
},
  "geometry": {"coordinates":[-85.164197,41.049873],"type":"Point"}
}