{
  "type": "Feature",
  "properties": {
    "addr:full":"201 E Main St Lebanon IN 46052",
    "addr:housenumber":"201",
    "addr:postcode":"46052",
    "addr:street":"E Main St",
    "iso:country":"US",
    "sg:address":"201 E Main St",
    "sg:city":"Lebanon",
    "sg:classifiers":[
        {
            "category":"Government",
            "subcategory":"Office",
            "type":"Public Place"
        }
    ],
    "sg:phone":"+1 765 482 1201",
    "sg:postcode":"46052",
    "sg:province":"IN",
    "sg:tags":[
        "city"
    ],
    "wof:name":"Mayors Office",
    "wof:placetype":"venue"
},
  "geometry": {"coordinates":[-86.46484,40.04756],"type":"Point"}
}