{
  "type": "Feature",
  "properties": {
    "iso:country":"US",
    "sg:address":"310 N Michigan St",
    "sg:city":"Plymouth",
    "sg:classifiers":[
        {
            "category":"Food & Beverages",
            "subcategory":"Candy",
            "type":"Retail Goods"
        }
    ],
    "sg:phone":"+1 574 936 9288",
    "sg:postcode":"46563",
    "sg:province":"IN",
    "sg:tags":[
        "confectionery"
    ],
    "wof:name":"Chocolate Isle",
    "wof:placetype":"venue"
},
  "geometry": {"coordinates":[-86.309327,41.342559],"type":"Point"}
}