{
  "type": "Feature",
  "properties": {
    "iso:country":"US",
    "sg:address":"3103 N 14th St",
    "sg:city":"Terre Haute",
    "sg:classifiers":[
        {
            "category":"Shopping",
            "subcategory":"Hobbies, Toys, & Games",
            "type":"Retail Goods"
        }
    ],
    "sg:phone":"+1 812 466 6234",
    "sg:postcode":"47804",
    "sg:province":"IN",
    "wof:name":"Mixer Amusement",
    "wof:placetype":"venue"
},
  "geometry": {"coordinates":[-87.39548600000001,39.505358],"type":"Point"}
}