{
  "type": "Feature",
  "properties": {
    "addr:full":"11952 Fishers Crossing Dr Fishers IN 46038",
    "addr:housenumber":"11952",
    "addr:postcode":"46038",
    "addr:street":"Fishers Crossing Dr",
    "iso:country":"US",
    "sg:address":"11952 Fishers Crossing Dr",
    "sg:city":"Fishers",
    "sg:classifiers":[
        {
            "category":"Insurance",
            "subcategory":"Life Insurance",
            "type":"Services"
        }
    ],
    "sg:phone":"+1 317 576 1987",
    "sg:postcode":"46038",
    "sg:province":"IN",
    "wof:name":"Indiana Title Svc",
    "wof:placetype":"venue"
},
  "geometry": {"coordinates":[-86.03932,39.962043],"type":"Point"}
}