{
  "type": "Feature",
  "properties": {
    "iso:country":"US",
    "sg:address":"3600 N Wheeling Ave",
    "sg:city":"Muncie",
    "sg:classifiers":[
        {
            "category":"Personal",
            "subcategory":"Beauty Salon",
            "type":"Services"
        }
    ],
    "sg:phone":"+1 765 282 4382",
    "sg:postcode":"47304",
    "sg:province":"IN",
    "wof:name":"Studio 2007 Hair Designers",
    "wof:placetype":"venue"
},
  "geometry": {"coordinates":[-85.40367000000001,40.220392],"type":"Point"}
}