{
  "type": "Feature",
  "properties": {
    "iso:country":"US",
    "sg:address":"1840 Randall Ct",
    "sg:city":"Indianapolis",
    "sg:classifiers":[
        {
            "category":"Retail",
            "subcategory":"Repair Shop",
            "type":"Services"
        }
    ],
    "sg:phone":"+1 317 257 9883",
    "sg:postcode":"46240",
    "sg:province":"IN",
    "wof:name":"Accepted Furniture Repair",
    "wof:placetype":"venue"
},
  "geometry": {"coordinates":[-86.12865600000001,39.889513],"type":"Point"}
}