{
  "type": "Feature",
  "properties": {
    "iso:country":"US",
    "sg:address":"8381 Bell Oaks Dr",
    "sg:city":"Newburgh",
    "sg:classifiers":[
        {
            "category":"Professional",
            "subcategory":"Accounting & Tax Preparation",
            "type":"Services"
        }
    ],
    "sg:phone":"+1 812 853 3232",
    "sg:postcode":"47630",
    "sg:province":"IN",
    "sg:tags":[
        "return",
        "filing"
    ],
    "wof:name":"H & R Block Tax Svc",
    "wof:placetype":"venue"
},
  "geometry": {"coordinates":[-87.403263,37.975886],"type":"Point"}
}