{
  "type": "Feature",
  "properties": {
    "iso:country":"US",
    "sg:address":"806 W 13th St",
    "sg:city":"Muncie",
    "sg:classifiers":[
        {
            "category":"Organizations",
            "subcategory":"Labor Organization",
            "type":"Services"
        }
    ],
    "sg:phone":"+1 765 286 1779",
    "sg:postcode":"47302",
    "sg:province":"IN",
    "wof:name":"APWU",
    "wof:placetype":"venue"
},
  "geometry": {"coordinates":[-85.395772,40.177491],"type":"Point"}
}