{
  "type": "Feature",
  "properties": {
    "iso:country":"US",
    "sg:address":"50 W Clinton St",
    "sg:city":"Frankfort",
    "sg:classifiers":[
        {
            "category":"Shopping",
            "subcategory":"Tobacco",
            "type":"Retail Goods"
        }
    ],
    "sg:phone":"+1 765 654 6055",
    "sg:postcode":"46041",
    "sg:province":"IN",
    "sg:tags":[
        "cigarette",
        "cigar",
        "dealer"
    ],
    "wof:name":"S & S Smoke Shop",
    "wof:placetype":"venue"
},
  "geometry": {"coordinates":[-86.513083,40.280706],"type":"Point"}
}