{
  "type": "Feature",
  "properties": {
    "iso:country":"US",
    "sg:address":"5306 S State Rd 13",
    "sg:city":"Pierceton",
    "sg:classifiers":[
        {
            "category":"Government",
            "subcategory":"Office",
            "type":"Public Place"
        }
    ],
    "sg:phone":"+1 574 594 5792",
    "sg:postcode":"46562",
    "sg:province":"IN",
    "sg:tags":[
        "village"
    ],
    "wof:name":"Monroe Township Trustee",
    "wof:placetype":"venue"
},
  "geometry": {"coordinates":[-85.73432699999999,41.157308],"type":"Point"}
}