{
  "type": "Feature",
  "properties": {
    "iso:country":"US",
    "sg:address":"16320 Fulton Pl",
    "sg:city":"Lowell",
    "sg:classifiers":[
        {
            "category":"Building & Trades",
            "subcategory":"Construction",
            "type":"Services"
        }
    ],
    "sg:phone":"+1 219 696 4325",
    "sg:postcode":"46356",
    "sg:province":"IN",
    "sg:tags":[
        "excavation",
        "contractor"
    ],
    "wof:name":"Thorn Meadows",
    "wof:placetype":"venue"
},
  "geometry": {"coordinates":[-87.423183,41.323324],"type":"Point"}
}