{
  "type": "Feature",
  "properties": {
    "iso:country":"US",
    "sg:address":"2000 Elkhart Rd",
    "sg:city":"Goshen",
    "sg:classifiers":[
        {
            "category":"Professional",
            "subcategory":"Employment Agencies",
            "type":"Services"
        }
    ],
    "sg:phone":"+1 574 533 7330",
    "sg:postcode":"46526",
    "sg:province":"IN",
    "sg:tags":[
        "help",
        "contractor"
    ],
    "wof:name":"Perry Personnel Plus",
    "wof:placetype":"venue"
},
  "geometry": {"coordinates":[-85.8647,41.600101],"type":"Point"}
}