{
  "type": "Feature",
  "properties": {
    "iso:country":"US",
    "sg:address":"403 E State Road 352",
    "sg:city":"Boswell",
    "sg:classifiers":[
        {
            "category":"Autos & Motor Vehicles",
            "subcategory":"Automobile Sales",
            "type":"Retail Goods"
        }
    ],
    "sg:phone":"+1 765 869 5211",
    "sg:postcode":"47921",
    "sg:province":"IN",
    "sg:tags":[
        "dealers-used",
        "car",
        "used",
        "cars-wholesale",
        "new"
    ],
    "wof:name":"Boswell Wheels",
    "wof:placetype":"venue"
},
  "geometry": {"coordinates":[-87.30967800000001,40.519291],"type":"Point"}
}