{
  "type": "Feature",
  "properties": {
    "iso:country":"US",
    "sg:address":"2301 N Spring St",
    "sg:city":"Otwell",
    "sg:classifiers":[
        {
            "category":"Government",
            "subcategory":"Office",
            "type":"Public Place"
        }
    ],
    "sg:phone":"+1 812 354 2878",
    "sg:postcode":"47564",
    "sg:province":"IN",
    "sg:tags":[
        "village"
    ],
    "wof:name":"Jefferson Township Community",
    "wof:placetype":"venue"
},
  "geometry": {"coordinates":[-87.091743,38.455607],"type":"Point"}
}