{
  "type": "Feature",
  "properties": {
    "addr:full":"957 Kenmore Dr Evansville IN 47714",
    "addr:housenumber":"957",
    "addr:postcode":"47714",
    "addr:street":"Kenmore Dr",
    "iso:country":"US",
    "sg:address":"957 Kenmore Dr",
    "sg:city":"Evansville",
    "sg:classifiers":[
        {
            "category":"Professional",
            "subcategory":"Accounting & Tax Preparation",
            "type":"Services"
        }
    ],
    "sg:phone":"+1 812 477 4927",
    "sg:postcode":"47714",
    "sg:province":"IN",
    "sg:tags":[
        "accountant"
    ],
    "wof:name":"Sanders & Co",
    "wof:placetype":"venue"
},
  "geometry": {"coordinates":[-87.496955,37.964694],"type":"Point"}
}