{
  "type": "Feature",
  "properties": {
    "iso:country":"US",
    "sg:address":"5626 Lawton Loop W Dr",
    "sg:city":"Indianapolis",
    "sg:classifiers":[
        {
            "category":"Education",
            "subcategory":"School",
            "type":"Public Place"
        }
    ],
    "sg:phone":"+1 317 546 4921",
    "sg:postcode":"46216",
    "sg:province":"IN",
    "wof:name":"MSD Lawrence Twp Foundation",
    "wof:placetype":"venue"
},
  "geometry": {"coordinates":[-86.016756,39.855231],"type":"Point"}
}