{
  "type": "Feature",
  "properties": {
    "iso:country":"US",
    "sg:address":"1275 State St",
    "sg:city":"Hammond",
    "sg:classifiers":[
        {
            "category":"Manufacturing",
            "subcategory":"Chemicals & Compounds",
            "type":"Manufacturing & Wholesale Goods"
        }
    ],
    "sg:phone":"+1 219 933 0877",
    "sg:postcode":"46320",
    "sg:province":"IN",
    "sg:tags":[
        "paint",
        "varnish",
        "allied",
        "product"
    ],
    "wof:name":"Davies Imperial Coatings",
    "wof:placetype":"venue"
},
  "geometry": {"coordinates":[-87.499137,41.611197],"type":"Point"}
}