{
  "type": "Feature",
  "properties": {
    "iso:country":"US",
    "sg:address":"1016 W Washington St",
    "sg:city":"Hartford City",
    "sg:classifiers":[
        {
            "category":"Personal",
            "subcategory":"Beauty Salon",
            "type":"Services"
        }
    ],
    "sg:phone":"+1 765 348 3842",
    "sg:postcode":"47348",
    "sg:province":"IN",
    "wof:name":"Classic Cuts",
    "wof:placetype":"venue"
},
  "geometry": {"coordinates":[-85.378164,40.451166],"type":"Point"}
}