{
  "type": "Feature",
  "properties": {
    "iso:country":"US",
    "sg:address":"524 N Section St",
    "sg:city":"Sullivan",
    "sg:classifiers":[
        {
            "category":"Retail",
            "subcategory":"Photofinishing",
            "type":"Services"
        }
    ],
    "sg:phone":"+1 812 268 3403",
    "sg:postcode":"47882",
    "sg:province":"IN",
    "sg:tags":[
        "photo",
        "finishing"
    ],
    "wof:name":"Trend Video/Photo Inc",
    "wof:placetype":"venue"
},
  "geometry": {"coordinates":[-87.409542,39.100744],"type":"Point"}
}