{
  "type": "Feature",
  "properties": {
    "iso:country":"US",
    "sg:address":"2550 Brandywine Ct",
    "sg:city":"Indianapolis",
    "sg:classifiers":[
        {
            "category":"Building & Trades",
            "subcategory":"Construction",
            "type":"Services"
        }
    ],
    "sg:phone":"+1 317 247 0737",
    "sg:postcode":"46241",
    "sg:province":"IN",
    "sg:tags":[
        "contractor"
    ],
    "wof:name":"Empire Contracting",
    "wof:placetype":"venue"
},
  "geometry": {"coordinates":[-86.247187,39.729617],"type":"Point"}
}