{
  "type": "Feature",
  "properties": {
    "iso:country":"US",
    "sg:address":"1214 N Meridian St",
    "sg:city":"Indianapolis",
    "sg:classifiers":[
        {
            "category":"Professional",
            "subcategory":"Secretarial Services",
            "type":"Services"
        }
    ],
    "sg:phone":"+1 317 686 3253",
    "sg:postcode":"46204",
    "sg:province":"IN",
    "sg:tags":[
        "transcription",
        "medical"
    ],
    "wof:name":"Meridian Healthcare Solutions",
    "wof:placetype":"venue"
},
  "geometry": {"coordinates":[-86.157507,39.784102],"type":"Point"}
}