{
  "type": "Feature",
  "properties": {
    "iso:country":"US",
    "sg:address":"305 E North St",
    "sg:city":"Kendallville",
    "sg:classifiers":[
        {
            "category":"Real Estate",
            "subcategory":"Real Estate Agent",
            "type":"Services"
        }
    ],
    "sg:phone":"+1 260 349 1304",
    "sg:postcode":"46755",
    "sg:province":"IN",
    "wof:name":"Coldwell Banker",
    "wof:placetype":"venue"
},
  "geometry": {"coordinates":[-85.26361300000001,41.452348],"type":"Point"}
}