{
  "type": "Feature",
  "properties": {
    "addr:full":"2510 Allison Ln Jeffersonville IN 47130",
    "addr:housenumber":"2510",
    "addr:postcode":"47130",
    "addr:street":"Allison Ln",
    "iso:country":"US",
    "sg:address":"2510 Allison Ln",
    "sg:city":"Jeffersonville",
    "sg:classifiers":[
        {
            "category":"Insurance",
            "subcategory":"Insurance Agent",
            "type":"Services"
        }
    ],
    "sg:phone":"+1 812 288 9393",
    "sg:postcode":"47130",
    "sg:province":"IN",
    "wof:name":"State Farm Insurance",
    "wof:placetype":"venue"
},
  "geometry": {"coordinates":[-85.71254399999999,38.322458],"type":"Point"}
}