{
  "type": "Feature",
  "properties": {
    "iso:country":"US",
    "sg:address":"4710 Industrial Hwy",
    "sg:city":"Gary",
    "sg:classifiers":[
        {
            "category":"Wholesale",
            "subcategory":"Scrap",
            "type":"Manufacturing & Wholesale Goods"
        }
    ],
    "sg:phone":"+1 219 977 9480",
    "sg:postcode":"46406",
    "sg:province":"IN",
    "sg:tags":[
        "waste"
    ],
    "wof:name":"Enterprise Waste Disposal",
    "wof:placetype":"venue"
},
  "geometry": {"coordinates":[-87.396338,41.611873],"type":"Point"}
}