{
  "type": "Feature",
  "properties": {
    "iso:country":"US",
    "sg:address":"107 W Washington St",
    "sg:city":"Fairland",
    "sg:classifiers":[
        {
            "category":"Insurance",
            "subcategory":"Insurance Agent",
            "type":"Services"
        }
    ],
    "sg:phone":"+1 317 398 4724",
    "sg:postcode":"46126",
    "sg:province":"IN",
    "wof:name":"Larkey Insurance & Real Estate",
    "wof:placetype":"venue"
},
  "geometry": {"coordinates":[-85.862725,39.585931],"type":"Point"}
}