{
  "type": "Feature",
  "properties": {
    "iso:country":"US",
    "sg:address":"3640 179th St",
    "sg:city":"Hammond",
    "sg:classifiers":[
        {
            "category":"Manufacturing",
            "subcategory":"Metals",
            "type":"Manufacturing & Wholesale Goods"
        }
    ],
    "sg:phone":"+1 219 923 1105",
    "sg:postcode":"46323",
    "sg:province":"IN",
    "sg:tags":[
        "treating",
        "heat"
    ],
    "sg:website":"www.thermalsolutions.com",
    "wof:name":"Thermal Solutions Inc",
    "wof:placetype":"venue"
},
  "geometry": {"coordinates":[-87.446703,41.573149],"type":"Point"}
}