{
  "type": "Feature",
  "properties": {
    "iso:country":"US",
    "sg:address":"304 N Jefferson St",
    "sg:city":"Converse",
    "sg:classifiers":[
        {
            "category":"Restaurant",
            "type":"Food & Drink"
        }
    ],
    "sg:phone":"+1 765 395 5442",
    "sg:postcode":"46919",
    "sg:province":"IN",
    "wof:name":"Marty's Pub",
    "wof:placetype":"venue"
},
  "geometry": {"coordinates":[-85.873249,40.580646],"type":"Point"}
}