{
  "type": "Feature",
  "properties": {
    "addr:full":"6137 Crawfordsville Rd Indianapolis IN 46224",
    "addr:housenumber":"6137",
    "addr:postcode":"46224",
    "addr:street":"Crawfordsville Rd",
    "iso:country":"US",
    "sg:address":"6137 Crawfordsville Rd",
    "sg:city":"Indianapolis",
    "sg:classifiers":[
        {
            "category":"Personal",
            "type":"Services"
        }
    ],
    "sg:phone":"+1 317 299 6814",
    "sg:postcode":"46224",
    "sg:province":"IN",
    "sg:tags":[
        "consultant",
        "program",
        "health",
        "fitness"
    ],
    "wof:name":"Jenny Craig Weight Loss Ctr",
    "wof:placetype":"venue"
},
  "geometry": {"coordinates":[-86.265677,39.798995],"type":"Point"}
}