{
  "type": "Feature",
  "properties": {
    "iso:country":"US",
    "sg:address":"2845 Guilford Ave",
    "sg:city":"Indianapolis",
    "sg:classifiers":[
        {
            "category":"Shopping",
            "subcategory":"Discount & Variety Stores",
            "type":"Retail Goods"
        }
    ],
    "sg:phone":"+1 317 924 6141",
    "sg:postcode":"46205",
    "sg:province":"IN",
    "wof:name":"Ashley's Variety",
    "wof:placetype":"venue"
},
  "geometry": {"coordinates":[-86.141543,39.808416],"type":"Point"}
}