{
  "type": "Feature",
  "properties": {
    "iso:country":"US",
    "sg:address":"210 N 7th St",
    "sg:city":"Terre Haute",
    "sg:classifiers":[
        {
            "category":"Education",
            "subcategory":"College",
            "type":"Public Place"
        }
    ],
    "sg:phone":"+1 812 237 2284",
    "sg:postcode":"47809",
    "sg:province":"IN",
    "sg:tags":[
        "academic",
        "school"
    ],
    "wof:name":"Indiana State University",
    "wof:placetype":"venue"
},
  "geometry": {"coordinates":[-87.407072,39.471565],"type":"Point"}
}