{
  "type": "Feature",
  "properties": {
    "addr:full":"215 45th St Munster IN 46321",
    "addr:housenumber":"215",
    "addr:postcode":"46321",
    "addr:street":"45Th St",
    "iso:country":"US",
    "sg:address":"215 45th St",
    "sg:city":"Munster",
    "sg:classifiers":[
        {
            "category":"Wholesale",
            "subcategory":"Machinery & Supplies",
            "type":"Manufacturing & Wholesale Goods"
        }
    ],
    "sg:phone":"+1 219 922 3660",
    "sg:postcode":"46321",
    "sg:province":"IN",
    "sg:tags":[
        "baker"
    ],
    "sg:website":"www.dawnfoods.com",
    "wof:name":"Dawn Food Products Inc",
    "wof:placetype":"venue"
},
  "geometry": {"coordinates":[-87.52466200000001,41.542987],"type":"Point"}
}