{
  "type": "Feature",
  "properties": {
    "iso:country":"US",
    "sg:address":"106 S Main St",
    "sg:city":"Culver",
    "sg:classifiers":[
        {
            "category":"Shopping",
            "subcategory":"Gifts & Souvenirs",
            "type":"Retail Goods"
        }
    ],
    "sg:phone":"+1 574 842 4870",
    "sg:postcode":"46511",
    "sg:province":"IN",
    "wof:name":"Town & Country Baskets",
    "wof:placetype":"venue"
},
  "geometry": {"coordinates":[-86.423629,41.216647],"type":"Point"}
}