{
  "type": "Feature",
  "properties": {
    "iso:country":"US",
    "sg:address":"4556 S 100 W",
    "sg:city":"Rochester",
    "sg:classifiers":[
        {
            "category":"Retail",
            "subcategory":"Auto Repair",
            "type":"Services"
        }
    ],
    "sg:phone":"+1 574 223 4352",
    "sg:postcode":"46975",
    "sg:province":"IN",
    "sg:tags":[
        "repairing",
        "automobile"
    ],
    "wof:name":"Gamble's Auto Repair",
    "wof:placetype":"venue"
},
  "geometry": {"coordinates":[-86.261488,40.988401],"type":"Point"}
}