{
  "type": "Feature",
  "properties": {
    "iso:country":"US",
    "sg:address":"249 Ivanhoe Ct",
    "sg:city":"Griffith",
    "sg:classifiers":[
        {
            "category":"Banks & Credit Unions",
            "subcategory":"Bank",
            "type":"Services"
        }
    ],
    "sg:phone":"+1 219 922 8304",
    "sg:postcode":"46319",
    "sg:province":"IN",
    "sg:tags":[
        "loan",
        "real estate"
    ],
    "wof:name":"Smart Mortgage",
    "wof:placetype":"venue"
},
  "geometry": {"coordinates":[-87.410646,41.519667],"type":"Point"}
}