{
  "type": "Feature",
  "properties": {
    "iso:country":"US",
    "sg:address":"4220 N 400 E",
    "sg:city":"Marion",
    "sg:classifiers":[
        {
            "category":"Professional",
            "subcategory":"Business Services",
            "type":"Services"
        }
    ],
    "sg:phone":"+1 765 662 8927",
    "sg:postcode":"46952",
    "sg:province":"IN",
    "sg:tags":[
        "farm",
        "diary"
    ],
    "wof:name":"Hix Diary Farm",
    "wof:placetype":"venue"
},
  "geometry": {"coordinates":[-85.598895,40.613166],"type":"Point"}
}