{
  "type": "Feature",
  "properties": {
    "iso:country":"US",
    "sg:address":"7714 Sunflower Dr",
    "sg:city":"Noblesville",
    "sg:classifiers":[
        {
            "category":"Arts & Performance",
            "subcategory":"Theater",
            "type":"Entertainment"
        }
    ],
    "sg:phone":"+1 317 770 9148",
    "sg:postcode":"46062",
    "sg:province":"IN",
    "sg:tags":[
        "group"
    ],
    "wof:name":"Prompt Inc",
    "wof:placetype":"venue"
},
  "geometry": {"coordinates":[-86.034548,40.065893],"type":"Point"}
}