{
  "type": "Feature",
  "properties": {
    "iso:country":"US",
    "sg:address":"17630 Briarcliff Ct",
    "sg:city":"South Bend",
    "sg:classifiers":[
        {
            "category":"Local Transit",
            "type":"Transportation"
        }
    ],
    "sg:phone":"+1 574 277 7171",
    "sg:postcode":"46635",
    "sg:province":"IN",
    "sg:tags":[
        "handicapped"
    ],
    "wof:name":"Road Runner",
    "wof:placetype":"venue"
},
  "geometry": {"coordinates":[-86.211259,41.732457],"type":"Point"}
}