{
  "type": "Feature",
  "properties": {
    "iso:country":"US",
    "sg:address":"135 N Harrison St",
    "sg:city":"Warsaw",
    "sg:classifiers":[
        {
            "category":"Education",
            "subcategory":"School",
            "type":"Public Place"
        }
    ],
    "sg:phone":"+1 574 267 5874",
    "sg:postcode":"46580",
    "sg:province":"IN",
    "wof:name":"Sacred Heart School",
    "wof:placetype":"venue"
},
  "geometry": {"coordinates":[-85.829038,41.239568],"type":"Point"}
}