{
  "type": "Feature",
  "properties": {
    "iso:country":"US",
    "sg:address":"2144 Wood Hollow",
    "sg:city":"Hammond",
    "sg:classifiers":[
        {
            "category":"Arts & Performance",
            "subcategory":"Theater",
            "type":"Entertainment"
        }
    ],
    "sg:phone":"+1 219 844 3063",
    "sg:postcode":"46323",
    "sg:province":"IN",
    "sg:tags":[
        "clown"
    ],
    "wof:name":"Jo Jo & Tudor The Clowns",
    "wof:placetype":"venue"
},
  "geometry": {"coordinates":[-87.474845,41.59336],"type":"Point"}
}