{
  "type": "Feature",
  "properties": {
    "iso:country":"US",
    "sg:address":"251 E Ohio St",
    "sg:city":"Indianapolis",
    "sg:classifiers":[
        {
            "category":"Government",
            "subcategory":"Office",
            "type":"Public Place"
        }
    ],
    "sg:phone":"+1 317 232 9154",
    "sg:postcode":"46204",
    "sg:province":"IN",
    "sg:tags":[
        "state",
        "program"
    ],
    "wof:name":"Education Department Pub",
    "wof:placetype":"venue"
},
  "geometry": {"coordinates":[-86.153204,39.769807],"type":"Point"}
}