{
  "type": "Feature",
  "properties": {
    "addr:full":"8602 S 100 W Union Mills IN 46382",
    "addr:housenumber":"8602;100",
    "addr:postcode":"46382",
    "addr:street":"S;W Union Mills",
    "iso:country":"US",
    "sg:address":"8602 S 100 W",
    "sg:city":"Union Mills",
    "sg:classifiers":[
        {
            "category":"Professional",
            "type":"Services"
        }
    ],
    "sg:phone":"+1 219 767 2984",
    "sg:postcode":"46382",
    "sg:province":"IN",
    "wof:name":"Reveille Inc",
    "wof:placetype":"venue"
},
  "geometry": {"coordinates":[-86.719522,41.482192],"type":"Point"}
}