{
  "type": "Feature",
  "properties": {
    "iso:country":"US",
    "sg:address":"4887 E 900 S",
    "sg:city":"La Fontaine",
    "sg:classifiers":[
        {
            "category":"Health Services",
            "subcategory":"Clinic",
            "type":"Services"
        }
    ],
    "sg:phone":"+1 765 981 4322",
    "sg:postcode":"46940",
    "sg:province":"IN",
    "sg:tags":[
        "education"
    ],
    "wof:name":"Health Education",
    "wof:placetype":"venue"
},
  "geometry": {"coordinates":[-85.703433,40.695969],"type":"Point"}
}