{
  "type": "Feature",
  "properties": {
    "iso:country":"US",
    "sg:address":"1715 W 37th Ave",
    "sg:city":"Gary",
    "sg:classifiers":[
        {
            "category":"Personal",
            "subcategory":"Beauty Salon",
            "type":"Services"
        }
    ],
    "sg:phone":"+1 219 980 0521",
    "sg:postcode":"46408",
    "sg:province":"IN",
    "wof:name":"Salon LA Chic",
    "wof:placetype":"venue"
},
  "geometry": {"coordinates":[-87.358103,41.551357],"type":"Point"}
}