{
  "type": "Feature",
  "properties": {
    "iso:country":"US",
    "sg:address":"8246 Allisonville Rd",
    "sg:city":"Indianapolis",
    "sg:classifiers":[
        {
            "category":"Autos & Motor Vehicles",
            "subcategory":"Auto Supplies",
            "type":"Retail Goods"
        },
        {
            "category":"Retail",
            "subcategory":"Auto Repair",
            "type":"Services"
        }
    ],
    "sg:phone":"+1 317 842 0800",
    "sg:postcode":"46250",
    "sg:province":"IN",
    "sg:tags":[
        "automobile",
        "part",
        "tire",
        "accessory"
    ],
    "wof:name":"Harris Tire & Automotive Service Inc",
    "wof:placetype":"venue"
},
  "geometry": {"coordinates":[-86.078102,39.9062],"type":"Point"}
}