{
  "type": "Feature",
  "properties": {
    "iso:country":"US",
    "sg:address":"365 E Co Rd 700 S",
    "sg:city":"Greensburg",
    "sg:phone":"+1 812 663 8607",
    "sg:postcode":"47240",
    "sg:province":"IN",
    "sg:tags":[
        "farm",
        "corn",
        "soybean"
    ],
    "wof:name":"Edward Huffmeyer",
    "wof:placetype":"venue"
},
  "geometry": {"coordinates":[-85.47873300000001,39.233801],"type":"Point"}
}