{
  "type": "Feature",
  "properties": {
    "addr:full":"7802 W Jefferson Blvd Fort Wayne IN 46804",
    "addr:housenumber":"7802",
    "addr:postcode":"46804",
    "addr:street":"W Jefferson Blvd",
    "iso:country":"US",
    "sg:address":"7802 W Jefferson Blvd",
    "sg:city":"Fort Wayne",
    "sg:classifiers":[
        {
            "category":"Health Services",
            "subcategory":"Doctor",
            "type":"Services"
        }
    ],
    "sg:phone":"+1 260 459 2113",
    "sg:postcode":"46804",
    "sg:province":"IN",
    "sg:tags":[
        "physician",
        "surgeon"
    ],
    "wof:name":"Obstetrics & Gynecology Assoc",
    "wof:placetype":"venue"
},
  "geometry": {"coordinates":[-85.243785,41.038925],"type":"Point"}
}