{
  "type": "Feature",
  "properties": {
    "iso:country":"US",
    "sg:address":"1555 E Main St",
    "sg:city":"Greenfield",
    "sg:classifiers":[
        {
            "category":"Building & Trades",
            "subcategory":"Construction",
            "type":"Services"
        }
    ],
    "sg:phone":"+1 317 462 1602",
    "sg:postcode":"46140",
    "sg:province":"IN",
    "sg:tags":[
        "insulation",
        "heat",
        "contractor"
    ],
    "wof:name":"Grace Insulation & Remodeling",
    "wof:placetype":"venue"
},
  "geometry": {"coordinates":[-85.74673300000001,39.786368],"type":"Point"}
}