{
  "type": "Feature",
  "properties": {
    "iso:country":"US",
    "sg:address":"10056 N Turkey Creek Rd",
    "sg:city":"Syracuse",
    "sg:classifiers":[
        {
            "category":"Real Estate",
            "subcategory":"Real Estate Operator",
            "type":"Services"
        }
    ],
    "sg:phone":"+1 260 856 2841",
    "sg:postcode":"46567",
    "sg:province":"IN",
    "sg:tags":[
        "mobile",
        "home",
        "community"
    ],
    "wof:name":"Wawasee Mobile Home Park",
    "wof:placetype":"venue"
},
  "geometry": {"coordinates":[-85.667484,41.38169],"type":"Point"}
}