{
  "type": "Feature",
  "properties": {
    "addr:full":"2999 E Business 30 Columbia City IN 46725",
    "addr:housenumber":"2999;30",
    "addr:postcode":"46725",
    "addr:street":"E Business",
    "iso:country":"US",
    "sg:address":"2999 E Business 30",
    "sg:city":"Columbia City",
    "sg:classifiers":[
        {
            "category":"Building & Trades",
            "subcategory":"Construction",
            "type":"Services"
        }
    ],
    "sg:phone":"+1 260 248 4995",
    "sg:postcode":"46725",
    "sg:province":"IN",
    "sg:tags":[
        "home",
        "builder"
    ],
    "wof:name":"GCI Homes",
    "wof:placetype":"venue"
},
  "geometry": {"coordinates":[-85.437663,41.140111],"type":"Point"}
}