{
  "type": "Feature",
  "properties": {
    "iso:country":"US",
    "sg:address":"16815 Lima Rd",
    "sg:city":"Huntertown",
    "sg:classifiers":[
        {
            "category":"Manufacturing",
            "subcategory":"Tools & Machinery",
            "type":"Manufacturing & Wholesale Goods"
        }
    ],
    "sg:phone":"+1 260 338 1100",
    "sg:postcode":"46748",
    "sg:province":"IN",
    "sg:tags":[
        "designed",
        "built"
    ],
    "wof:name":"Us Automation",
    "wof:placetype":"venue"
},
  "geometry": {"coordinates":[-85.174759,41.238106],"type":"Point"}
}