{
  "type": "Feature",
  "properties": {
    "addr:full":"535 N Memorial Dr New Castle IN 47362",
    "addr:housenumber":"535",
    "addr:postcode":"47362",
    "addr:street":"N Memorial Dr",
    "iso:country":"US",
    "sg:address":"535 N Memorial Dr",
    "sg:city":"New Castle",
    "sg:classifiers":[
        {
            "category":"Retail",
            "subcategory":"Auto Rental",
            "type":"Services"
        }
    ],
    "sg:phone":"+1 765 529 0450",
    "sg:postcode":"47362",
    "sg:province":"IN",
    "sg:tags":[
        "renting",
        "automobile"
    ],
    "wof:name":"Enterprise Rent-A-Car",
    "wof:placetype":"venue"
},
  "geometry": {"coordinates":[-85.383718,39.936857],"type":"Point"}
}