{
  "type": "Feature",
  "properties": {
    "addr:full":"500 S Capitol Ave Indianapolis IN 46225",
    "addr:housenumber":"500",
    "addr:postcode":"46225",
    "addr:street":"S Capitol Ave",
    "iso:country":"US",
    "sg:address":"500 S Capitol Ave",
    "sg:city":"Indianapolis",
    "sg:classifiers":[
        {
            "category":"Manufacturing",
            "subcategory":"Petroleum Products",
            "type":"Manufacturing & Wholesale Goods"
        },
        {
            "category":"Utilities",
            "subcategory":"Fuel Oil & Lpg",
            "type":"Services"
        }
    ],
    "sg:phone":"+1 317 262 8600",
    "sg:postcode":"46225",
    "sg:province":"IN",
    "sg:tags":[
        "oils-fuel",
        "marketer",
        "oils-petroleum"
    ],
    "wof:name":"Lucas Oil Stadium",
    "wof:placetype":"venue"
},
  "geometry": {"coordinates":[-86.16196600000001,39.760387],"type":"Point"}
}