{
  "type": "Feature",
  "properties": {
    "iso:country":"US",
    "sg:address":"1 E Main St",
    "sg:city":"Mooresville",
    "sg:classifiers":[
        {
            "category":"Shopping",
            "subcategory":"Used Merchandise",
            "type":"Retail Goods"
        }
    ],
    "sg:phone":"+1 317 831 7682",
    "sg:postcode":"46158",
    "sg:province":"IN",
    "sg:tags":[
        "antique"
    ],
    "wof:name":"Lizzard's Fly",
    "wof:placetype":"venue"
},
  "geometry": {"coordinates":[-86.37231199999999,39.612746],"type":"Point"}
}