{
  "type": "Feature",
  "properties": {
    "iso:country":"US",
    "sg:address":"4351 Sellers St",
    "sg:city":"Indianapolis",
    "sg:classifiers":[
        {
            "category":"Wholesale",
            "subcategory":"Machinery & Supplies",
            "type":"Manufacturing & Wholesale Goods"
        }
    ],
    "sg:phone":"+1 317 543 9100",
    "sg:postcode":"46226",
    "sg:province":"IN",
    "sg:tags":[
        "equipment",
        "industrial"
    ],
    "wof:name":"Industrial & Environ Sales LLC",
    "wof:placetype":"venue"
},
  "geometry": {"coordinates":[-86.034702,39.835715],"type":"Point"}
}