{
  "type": "Feature",
  "properties": {
    "iso:country":"US",
    "sg:address":"635 W 11th St",
    "sg:city":"Auburn",
    "sg:classifiers":[
        {
            "category":"Manufacturing",
            "subcategory":"Metals",
            "type":"Manufacturing & Wholesale Goods"
        }
    ],
    "sg:phone":"+1 260 925 0900",
    "sg:postcode":"46706",
    "sg:province":"IN",
    "sg:tags":[
        "casting"
    ],
    "sg:website":"www.auburnfoundry.com",
    "wof:name":"Auburn Foundry Inc",
    "wof:placetype":"venue"
},
  "geometry": {"coordinates":[-85.063969,41.364544],"type":"Point"}
}