{
  "type": "Feature",
  "properties": {
    "iso:country":"US",
    "sg:address":"249 68th Pl",
    "sg:city":"Schererville",
    "sg:classifiers":[
        {
            "category":"Retail",
            "subcategory":"Animal Services",
            "type":"Services"
        }
    ],
    "sg:phone":"+1 219 322 2225",
    "sg:postcode":"46375",
    "sg:province":"IN",
    "sg:tags":[
        "pet",
        "crematory",
        "cemetery"
    ],
    "wof:name":"Southlake Pet Cemetery",
    "wof:placetype":"venue"
},
  "geometry": {"coordinates":[-87.46008,41.494467],"type":"Point"}
}