{
  "type": "Feature",
  "properties": {
    "iso:country":"US",
    "sg:address":"3776 E Armstrong Rd",
    "sg:city":"Leesburg",
    "sg:classifiers":[
        {
            "category":"Professional",
            "subcategory":"Computer Services",
            "type":"Services"
        }
    ],
    "sg:phone":"+1 574 453 3560",
    "sg:postcode":"46538",
    "sg:province":"IN",
    "wof:name":"Azure Software Inc",
    "wof:placetype":"venue"
},
  "geometry": {"coordinates":[-85.772068,41.318127],"type":"Point"}
}