{
  "type": "Feature",
  "properties": {
    "addr:full":"715 S Tillotson Ave Muncie IN 47304",
    "addr:housenumber":"715",
    "addr:postcode":"47304",
    "addr:street":"S Tillotson Ave",
    "iso:country":"US",
    "sg:address":"715 S Tillotson Ave",
    "sg:city":"Muncie",
    "sg:classifiers":[
        {
            "category":"Food & Beverages",
            "subcategory":"Groceries & Convenience Stores",
            "type":"Retail Goods"
        }
    ],
    "sg:phone":"+1 765 213 1200",
    "sg:postcode":"47304",
    "sg:province":"IN",
    "sg:tags":[
        "grocer"
    ],
    "wof:name":"Marsh Supermarket",
    "wof:placetype":"venue"
},
  "geometry": {"coordinates":[-85.419203,40.188018],"type":"Point"}
}