{
  "type": "Feature",
  "properties": {
    "iso:country":"US",
    "sg:address":"4918 N College Ave",
    "sg:city":"Indianapolis",
    "sg:classifiers":[
        {
            "category":"Professional",
            "type":"Services"
        }
    ],
    "sg:phone":"+1 317 283 2221",
    "sg:postcode":"46205",
    "sg:province":"IN",
    "sg:tags":[
        "establishment"
    ],
    "wof:name":"Welty Custom Exteriors Inc",
    "wof:placetype":"venue"
},
  "geometry": {"coordinates":[-86.145791,39.843723],"type":"Point"}
}