{
  "type": "Feature",
  "properties": {
    "iso:country":"US",
    "sg:address":"6278 N 600 E",
    "sg:city":"Remington",
    "sg:phone":"+1 219 261 3205",
    "sg:postcode":"47977",
    "sg:province":"IN",
    "sg:tags":[
        "farm",
        "grain",
        "cash"
    ],
    "wof:name":"Larry Payne",
    "wof:placetype":"venue"
},
  "geometry": {"coordinates":[-87.210764,40.693194],"type":"Point"}
}