{
  "type": "Feature",
  "properties": {
    "addr:full":"210 W 7th St Connersville IN 47331",
    "addr:housenumber":"210",
    "addr:postcode":"47331",
    "addr:street":"W 7Th St",
    "iso:country":"US",
    "sg:address":"210 W 7th St",
    "sg:city":"Connersville",
    "sg:classifiers":[
        {
            "category":"Health Services",
            "subcategory":"Doctor",
            "type":"Services"
        }
    ],
    "sg:phone":"+1 765 825 5155",
    "sg:postcode":"47331",
    "sg:province":"IN",
    "sg:tags":[
        "dentist"
    ],
    "wof:name":"Brian Moore Family Dentistry",
    "wof:placetype":"venue"
},
  "geometry": {"coordinates":[-85.139703,39.644242],"type":"Point"}
}