{
  "type": "Feature",
  "properties": {
    "addr:full":"1750 E North St Crown Point IN 46307",
    "addr:housenumber":"1750",
    "addr:postcode":"46307",
    "addr:street":"E North St",
    "iso:country":"US",
    "sg:address":"1750 E North St",
    "sg:city":"Crown Point",
    "sg:classifiers":[
        {
            "category":"Building & Trades",
            "subcategory":"Construction",
            "type":"Services"
        }
    ],
    "sg:phone":"+1 219 662 0750",
    "sg:postcode":"46307",
    "sg:province":"IN",
    "sg:tags":[
        "contractor"
    ],
    "wof:name":"Woodbridge Construction & Carpentry Inc",
    "wof:placetype":"venue"
},
  "geometry": {"coordinates":[-87.341103,41.420101],"type":"Point"}
}