{
  "type": "Feature",
  "properties": {
    "addr:full":"2509 Saratoga Dr Evansville IN 47715",
    "addr:housenumber":"2509",
    "addr:postcode":"47715",
    "addr:street":"Saratoga Dr",
    "iso:country":"US",
    "sg:address":"2509 Saratoga Dr",
    "sg:city":"Evansville",
    "sg:classifiers":[
        {
            "category":"Building & Trades",
            "subcategory":"Landscaping Services",
            "type":"Services"
        }
    ],
    "sg:phone":"+1 812 483 5537",
    "sg:postcode":"47715",
    "sg:province":"IN",
    "sg:tags":[
        "lawn",
        "maintenance",
        "grounds"
    ],
    "wof:name":"Dorsey's Lawn Care & Landscape",
    "wof:placetype":"venue"
},
  "geometry": {"coordinates":[-87.497523,37.997755],"type":"Point"}
}