{
  "type": "Feature",
  "properties": {
    "iso:country":"US",
    "sg:address":"4008 N State Rd 15",
    "sg:city":"Warsaw",
    "sg:classifiers":[
        {
            "category":"Shopping",
            "subcategory":"Computers & Home Electronics",
            "type":"Retail Goods"
        }
    ],
    "sg:phone":"+1 574 269 5192",
    "sg:postcode":"46582",
    "sg:province":"IN",
    "sg:tags":[
        "satellite",
        "antenna",
        "installs",
        "television",
        "ant",
        "dish"
    ],
    "wof:name":"Kosciusko County Satellite",
    "wof:placetype":"venue"
},
  "geometry": {"coordinates":[-85.855716,41.295847],"type":"Point"}
}