{
  "type": "Feature",
  "properties": {
    "iso:country":"US",
    "sg:address":"417 Liberty St",
    "sg:city":"Covington",
    "sg:classifiers":[
        {
            "category":"Shopping",
            "subcategory":"Computers & Home Electronics",
            "type":"Retail Goods"
        }
    ],
    "sg:phone":"+1 765 793 4024",
    "sg:postcode":"47932",
    "sg:province":"IN",
    "sg:tags":[
        "software"
    ],
    "wof:name":"Computer Consulting Svc",
    "wof:placetype":"venue"
},
  "geometry": {"coordinates":[-87.395301,40.136949],"type":"Point"}
}