{
  "type": "Feature",
  "properties": {
    "addr:full":"13786 E 216th St Noblesville IN 46060",
    "addr:housenumber":"13786",
    "addr:postcode":"46060",
    "addr:street":"E 216Th St",
    "iso:country":"US",
    "sg:address":"13786 E 216th St",
    "sg:city":"Noblesville",
    "sg:classifiers":[
        {
            "category":"Organizations",
            "subcategory":"Religious Organization",
            "type":"Services"
        }
    ],
    "sg:phone":"+1 765 534 4682",
    "sg:postcode":"46060",
    "sg:province":"IN",
    "sg:tags":[
        "church"
    ],
    "wof:name":"Victory Chapel Parsonage",
    "wof:placetype":"venue"
},
  "geometry": {"coordinates":[-85.92226100000001,40.102926],"type":"Point"}
}