{
  "type": "Feature",
  "properties": {
    "addr:full":"4902 S Emerson Ave Indianapolis IN 46203",
    "addr:housenumber":"4902",
    "addr:postcode":"46203",
    "addr:street":"S Emerson Ave",
    "iso:country":"US",
    "sg:address":"4902 S Emerson Ave",
    "sg:city":"Indianapolis",
    "sg:classifiers":[
        {
            "category":"Autos & Motor Vehicles",
            "subcategory":"Auto Supplies",
            "type":"Retail Goods"
        }
    ],
    "sg:phone":"+1 317 781 6272",
    "sg:postcode":"46203",
    "sg:province":"IN",
    "sg:tags":[
        "automobile",
        "parts"
    ],
    "wof:name":"NAPA Auto Parts",
    "wof:placetype":"venue"
},
  "geometry": {"coordinates":[-86.082544,39.698899],"type":"Point"}
}