{
  "type": "Feature",
  "properties": {
    "iso:country":"US",
    "sg:address":"2606 W Washington St",
    "sg:city":"Indianapolis",
    "sg:classifiers":[
        {
            "category":"Manufacturing",
            "subcategory":"Printing",
            "type":"Manufacturing & Wholesale Goods"
        }
    ],
    "sg:phone":"+1 317 636 3489",
    "sg:postcode":"46222",
    "sg:province":"IN",
    "sg:tags":[
        "commercial"
    ],
    "wof:name":"Trinity Printing",
    "wof:placetype":"venue"
},
  "geometry": {"coordinates":[-86.205261,39.765482],"type":"Point"}
}