{
  "type": "Feature",
  "properties": {
    "iso:country":"US",
    "sg:address":"12196 N Bingham Rd",
    "sg:city":"Mooresville",
    "sg:classifiers":[
        {
            "category":"Real Estate",
            "subcategory":"Real Estate Operator",
            "type":"Services"
        }
    ],
    "sg:phone":"+1 317 831 1172",
    "sg:postcode":"46158",
    "sg:province":"IN",
    "sg:tags":[
        "building",
        "apartment"
    ],
    "wof:name":"Prescott I LLC",
    "wof:placetype":"venue"
},
  "geometry": {"coordinates":[-86.398677,39.602588],"type":"Point"}
}