{
  "type": "Feature",
  "properties": {
    "iso:country":"US",
    "sg:address":"2105 N Wells St",
    "sg:city":"Fort Wayne",
    "sg:classifiers":[
        {
            "category":"Building & Trades",
            "subcategory":"Electrical",
            "type":"Services"
        }
    ],
    "sg:phone":"+1 260 422 3318",
    "sg:postcode":"46808",
    "sg:province":"IN",
    "sg:tags":[
        "work",
        "electrical",
        "contractor"
    ],
    "wof:name":"Ed Walker Electric Inc",
    "wof:placetype":"venue"
},
  "geometry": {"coordinates":[-85.14631199999999,41.095073],"type":"Point"}
}