{
  "type": "Feature",
  "properties": {
    "addr:full":"6155 Guion Rd Indianapolis IN 46254",
    "addr:housenumber":"6155",
    "addr:postcode":"46254",
    "addr:street":"Guion Rd",
    "iso:country":"US",
    "sg:address":"6155 Guion Rd",
    "sg:city":"Indianapolis",
    "sg:classifiers":[
        {
            "category":"Home & Garden",
            "subcategory":"Furniture",
            "type":"Retail Goods"
        }
    ],
    "sg:phone":"+1 317 299 6000",
    "sg:postcode":"46254",
    "sg:province":"IN",
    "sg:tags":[
        "cabinet"
    ],
    "wof:name":"Mobelwerks Inc",
    "wof:placetype":"venue"
},
  "geometry": {"coordinates":[-86.231565,39.862714],"type":"Point"}
}