{
  "type": "Feature",
  "properties": {
    "iso:country":"US",
    "sg:address":"102 W Howard St",
    "sg:city":"Galveston",
    "sg:classifiers":[
        {
            "category":"Utilities",
            "subcategory":"Cable",
            "type":"Services"
        }
    ],
    "sg:phone":"+1 574 699 6434",
    "sg:postcode":"46932",
    "sg:province":"IN",
    "sg:tags":[
        "television"
    ],
    "wof:name":"CCS Satellite",
    "wof:placetype":"venue"
},
  "geometry": {"coordinates":[-86.189607,40.577984],"type":"Point"}
}