{
  "type": "Feature",
  "properties": {
    "addr:full":"2639 S 250 W Albion IN 46701",
    "addr:housenumber":"2639;250",
    "addr:postcode":"46701",
    "addr:street":"S;W Albion",
    "iso:country":"US",
    "sg:address":"2639 S 250 W",
    "sg:city":"Albion",
    "sg:classifiers":[
        {
            "category":"Government",
            "subcategory":"Office",
            "type":"Public Place"
        }
    ],
    "sg:phone":"+1 260 635 2049",
    "sg:postcode":"46701",
    "sg:province":"IN",
    "sg:tags":[
        "executive"
    ],
    "wof:name":"Noble Township Volunteer",
    "wof:placetype":"venue"
},
  "geometry": {"coordinates":[-85.47096500000001,41.313665],"type":"Point"}
}