{
  "type": "Feature",
  "properties": {
    "iso:country":"US",
    "sg:address":"105 south court",
    "sg:city":"Crown Point",
    "sg:classifiers":[
        {
            "category":"Restaurant",
            "type":"Food & Drink"
        },
        {
            "category":"Shopping",
            "type":"Retail Goods"
        }
    ],
    "sg:phone":"+1 219 662 8866",
    "sg:postcode":"46307",
    "sg:province":"IN",
    "sg:tags":[
        "flavor",
        "local"
    ],
    "wof:name":"sweeties",
    "wof:placetype":"venue"
},
  "geometry": {"coordinates":[-87.36554099999999,41.415535],"type":"Point"}
}