{
  "type": "Feature",
  "properties": {
    "iso:country":"US",
    "sg:address":"7741 Hohman Ave",
    "sg:city":"Munster",
    "sg:classifiers":[
        {
            "category":"Building & Trades",
            "subcategory":"Construction",
            "type":"Services"
        }
    ],
    "sg:phone":"+1 219 836 5104",
    "sg:postcode":"46321",
    "sg:province":"IN",
    "sg:tags":[
        "house"
    ],
    "wof:name":"Kish Construction Inc",
    "wof:placetype":"venue"
},
  "geometry": {"coordinates":[-87.52229,41.572209],"type":"Point"}
}