{
  "type": "Feature",
  "properties": {
    "iso:country":"US",
    "sg:address":"315 W 17th St",
    "sg:city":"Bloomington",
    "sg:classifiers":[
        {
            "category":"Organizations",
            "subcategory":"Membership Organization",
            "type":"Services"
        }
    ],
    "sg:phone":"+1 812 336 6110",
    "sg:postcode":"47404",
    "sg:province":"IN",
    "sg:tags":[
        "athletic"
    ],
    "sg:website":"www.swimbsc.com",
    "wof:name":"Bloomington Swim Club",
    "wof:placetype":"venue"
},
  "geometry": {"coordinates":[-86.537546,39.178936],"type":"Point"}
}