{
  "type": "Feature",
  "properties": {
    "addr:full":"2808 Bosworth Dr Fort Wayne IN 46805",
    "addr:housenumber":"2808",
    "addr:postcode":"46805",
    "addr:street":"Bosworth Dr",
    "iso:country":"US",
    "sg:address":"2808 Bosworth Dr",
    "sg:city":"Fort Wayne",
    "sg:classifiers":[
        {
            "category":"Insurance",
            "subcategory":"Insurance Agent",
            "type":"Services"
        }
    ],
    "sg:phone":"+1 260 471 3080",
    "sg:postcode":"46805",
    "sg:province":"IN",
    "wof:name":"Modern Woodmen Of America",
    "wof:placetype":"venue"
},
  "geometry": {"coordinates":[-85.091925,41.103925],"type":"Point"}
}