{
  "type": "Feature",
  "properties": {
    "addr:full":"511 S Madison St Bloomington IN 47403",
    "addr:housenumber":"511",
    "addr:postcode":"47403",
    "addr:street":"S Madison St",
    "iso:country":"US",
    "sg:address":"511 S Madison St",
    "sg:city":"Bloomington",
    "sg:classifiers":[
        {
            "category":"Professional",
            "subcategory":"Lawyer & Legal Services",
            "type":"Services"
        }
    ],
    "sg:phone":"+1 812 332 2167",
    "sg:postcode":"47403",
    "sg:province":"IN",
    "wof:name":"Turner Frederick",
    "wof:placetype":"venue"
},
  "geometry": {"coordinates":[-86.58260300000001,39.130901],"type":"Point"}
}