{
  "type": "Feature",
  "properties": {
    "iso:country":"US",
    "sg:address":"102 Lincoln Way E",
    "sg:city":"Mishawaka",
    "sg:classifiers":[
        {
            "category":"Shopping",
            "subcategory":"Used Merchandise",
            "type":"Retail Goods"
        }
    ],
    "sg:phone":"+1 574 255 9111",
    "sg:postcode":"46544",
    "sg:province":"IN",
    "sg:tags":[
        "shop",
        "consignment"
    ],
    "wof:name":"Fine Things",
    "wof:placetype":"venue"
},
  "geometry": {"coordinates":[-86.179289,41.661185],"type":"Point"}
}