{
  "type": "Feature",
  "properties": {
    "iso:country":"US",
    "sg:address":"10062 N 600 E",
    "sg:city":"Demotte",
    "sg:classifiers":[
        {
            "category":"Banks & Credit Unions",
            "subcategory":"Bank",
            "type":"Services"
        }
    ],
    "sg:phone":"+1 219 345 4646",
    "sg:postcode":"46310",
    "sg:province":"IN",
    "wof:name":"Kentland Bank",
    "wof:placetype":"venue"
},
  "geometry": {"coordinates":[-87.27579900000001,41.144534],"type":"Point"}
}