{
  "type": "Feature",
  "properties": {
    "iso:country":"US",
    "sg:address":"107 S Main St",
    "sg:city":"Sullivan",
    "sg:classifiers":[
        {
            "category":"Building & Trades",
            "subcategory":"Plumbing",
            "type":"Services"
        }
    ],
    "sg:phone":"+1 812 268 4068",
    "sg:postcode":"47882",
    "sg:province":"IN",
    "sg:tags":[
        "heating",
        "contractor"
    ],
    "wof:name":"Hilgediek Plumbing & Heating",
    "wof:placetype":"venue"
},
  "geometry": {"coordinates":[-87.407009,39.094303],"type":"Point"}
}