{
  "type": "Feature",
  "properties": {
    "addr:full":"217 N 15th St Terre Haute IN 47807",
    "addr:housenumber":"217",
    "addr:postcode":"47807",
    "addr:street":"N 15Th St",
    "iso:country":"US",
    "sg:address":"217 N 15th St",
    "sg:city":"Terre Haute",
    "sg:classifiers":[
        {
            "category":"Retail",
            "subcategory":"Car Wash",
            "type":"Services"
        }
    ],
    "sg:phone":"+1 812 232 8331",
    "sg:postcode":"47807",
    "sg:province":"IN",
    "sg:tags":[
        "automobile",
        "detail",
        "clean"
    ],
    "wof:name":"Darrell's Detail & Wash Shop",
    "wof:placetype":"venue"
},
  "geometry": {"coordinates":[-87.39259699999999,39.470869],"type":"Point"}
}