{
  "type": "Feature",
  "properties": {
    "iso:country":"US",
    "sg:address":"1905 S 13th St",
    "sg:city":"Terre Haute",
    "sg:classifiers":[
        {
            "category":"Wholesale",
            "subcategory":"Drugs",
            "type":"Manufacturing & Wholesale Goods"
        }
    ],
    "sg:phone":"+1 812 238 1490",
    "sg:postcode":"47802",
    "sg:province":"IN",
    "sg:tags":[
        "pharmaceutical",
        "product"
    ],
    "wof:name":"Amerisource Corp",
    "wof:placetype":"venue"
},
  "geometry": {"coordinates":[-87.397711,39.443844],"type":"Point"}
}