{
  "type": "Feature",
  "properties": {
    "iso:country":"US",
    "sg:address":"5920 Foolish Pleasure Ln",
    "sg:city":"Indianapolis",
    "sg:classifiers":[
        {
            "category":"Professional",
            "subcategory":"Accounting & Tax Preparation",
            "type":"Services"
        }
    ],
    "sg:phone":"+1 317 786 6945",
    "sg:postcode":"46237",
    "sg:province":"IN",
    "sg:tags":[
        "return"
    ],
    "wof:name":"Housecalls In Home Tax Prep",
    "wof:placetype":"venue"
},
  "geometry": {"coordinates":[-86.06483,39.680486],"type":"Point"}
}