{
  "type": "Feature",
  "properties": {
    "addr:full":"2449 E State Rd 44 Shelbyville IN 46176",
    "addr:housenumber":"2449;44",
    "addr:postcode":"46176",
    "addr:street":"E State Rd",
    "iso:country":"US",
    "sg:address":"2449 E State Rd 44",
    "sg:city":"Shelbyville",
    "sg:classifiers":[
        {
            "category":"Shopping",
            "subcategory":"Tobacco",
            "type":"Retail Goods"
        }
    ],
    "sg:phone":"+1 317 421 0357",
    "sg:postcode":"46176",
    "sg:province":"IN",
    "sg:tags":[
        "cigarette",
        "cigar",
        "dealer"
    ],
    "wof:name":"Low Bob's Discount Tobacco",
    "wof:placetype":"venue"
},
  "geometry": {"coordinates":[-85.744454,39.52264],"type":"Point"}
}