{
  "type": "Feature",
  "properties": {
    "iso:country":"US",
    "sg:address":"711 W Lincoln Ave",
    "sg:city":"Goshen",
    "sg:classifiers":[
        {
            "category":"Shopping",
            "subcategory":"Computers & Home Electronics",
            "type":"Retail Goods"
        }
    ],
    "sg:phone":"+1 574 534 1866",
    "sg:postcode":"46526",
    "sg:province":"IN",
    "sg:tags":[
        "equipment",
        "electronic",
        "supply"
    ],
    "wof:name":"Lots Of Sound Advice Inc",
    "wof:placetype":"venue"
},
  "geometry": {"coordinates":[-85.84594199999999,41.586459],"type":"Point"}
}