{
  "type": "Feature",
  "properties": {
    "addr:full":"1249 Miami Trl Bremen IN 46506",
    "addr:housenumber":"1249",
    "addr:postcode":"46506",
    "addr:street":"Miami Trl",
    "iso:country":"US",
    "sg:address":"1249 Miami Trl",
    "sg:city":"Bremen",
    "sg:classifiers":[
        {
            "category":"Building & Trades",
            "subcategory":"Construction",
            "type":"Services"
        }
    ],
    "sg:phone":"+1 574 546 3356",
    "sg:postcode":"46506",
    "sg:province":"IN",
    "sg:tags":[
        "general",
        "contractor"
    ],
    "wof:name":"Arndt Construction",
    "wof:placetype":"venue"
},
  "geometry": {"coordinates":[-86.19224800000001,41.460997],"type":"Point"}
}