{
  "type": "Feature",
  "properties": {
    "iso:country":"US",
    "sg:address":"4203 N Oxford St",
    "sg:city":"Indianapolis",
    "sg:classifiers":[
        {
            "category":"Building & Trades",
            "subcategory":"Construction",
            "type":"Services"
        }
    ],
    "sg:phone":"+1 317 546 1632",
    "sg:postcode":"46205",
    "sg:province":"IN",
    "sg:tags":[
        "contractor"
    ],
    "wof:name":"First Class Roofing",
    "wof:placetype":"venue"
},
  "geometry": {"coordinates":[-86.116339,39.834223],"type":"Point"}
}