{
  "type": "Feature",
  "properties": {
    "iso:country":"US",
    "sg:address":"122 S Park Blvd",
    "sg:city":"Greenwood",
    "sg:classifiers":[
        {
            "category":"Building & Trades",
            "subcategory":"Pest Control",
            "type":"Services"
        }
    ],
    "sg:phone":"+1 317 865 2501",
    "sg:postcode":"46143",
    "sg:province":"IN",
    "wof:name":"Steritech Group",
    "wof:placetype":"venue"
},
  "geometry": {"coordinates":[-86.077702,39.618743],"type":"Point"}
}