{
  "type": "Feature",
  "properties": {
    "iso:country":"US",
    "sg:address":"13 W US Hwy 30",
    "sg:city":"Schererville",
    "sg:classifiers":[
        {
            "category":"Health Services",
            "subcategory":"Health Practitioner",
            "type":"Services"
        }
    ],
    "sg:phone":"+1 219 865 4777",
    "sg:postcode":"46375",
    "sg:province":"IN",
    "sg:tags":[
        "surgery",
        "laser"
    ],
    "wof:name":"Laser Cosmetics & Aestetics",
    "wof:placetype":"venue"
},
  "geometry": {"coordinates":[-87.45053799999999,41.486118],"type":"Point"}
}