{
  "type": "Feature",
  "properties": {
    "iso:country":"US",
    "sg:address":"58005 Co Rd 105",
    "sg:city":"Elkhart",
    "sg:classifiers":[
        {
            "category":"Real Estate",
            "subcategory":"Real Estate Agent",
            "type":"Services"
        }
    ],
    "sg:phone":"+1 574 522 1187",
    "sg:postcode":"46517",
    "sg:province":"IN",
    "wof:name":"Stewart Realty",
    "wof:placetype":"venue"
},
  "geometry": {"coordinates":[-85.994428,41.650547],"type":"Point"}
}