{
  "type": "Feature",
  "properties": {
    "addr:full":"201 N 9th St Gosport IN 47433",
    "addr:housenumber":"201",
    "addr:postcode":"47433",
    "addr:street":"N 9Th St",
    "iso:country":"US",
    "sg:address":"201 N 9th St",
    "sg:city":"Gosport",
    "sg:classifiers":[
        {
            "category":"Education",
            "subcategory":"School",
            "type":"Public Place"
        }
    ],
    "sg:phone":"+1 812 879 4694",
    "sg:postcode":"47433",
    "sg:province":"IN",
    "wof:name":"Gosport Elementary School",
    "wof:placetype":"venue"
},
  "geometry": {"coordinates":[-86.669517,39.351267],"type":"Point"}
}