{
  "type": "Feature",
  "properties": {
    "addr:full":"6 S Main St Mooresville IN 46111",
    "addr:housenumber":"6",
    "addr:postcode":"46111",
    "addr:street":"S Main St",
    "iso:country":"US",
    "sg:address":"6 S Main St",
    "sg:city":"Mooresville",
    "sg:classifiers":[
        {
            "category":"Building & Trades",
            "subcategory":"Construction",
            "type":"Services"
        }
    ],
    "sg:phone":"+1 317 834 9079",
    "sg:postcode":"46111",
    "sg:province":"IN",
    "sg:tags":[
        "maker",
        "cabinet"
    ],
    "sg:website":"www.thewoodwiz.com",
    "wof:name":"Wood Wiz & Wizard Of Saws",
    "wof:placetype":"venue"
},
  "geometry": {"coordinates":[-86.370599,39.53751],"type":"Point"}
}