{
  "type": "Feature",
  "properties": {
    "iso:country":"US",
    "sg:address":"10 Cherry Tree Plz",
    "sg:city":"Washington",
    "sg:classifiers":[
        {
            "category":"Banks & Credit Unions",
            "subcategory":"Bank",
            "type":"Services"
        }
    ],
    "sg:phone":"+1 812 257 0837",
    "sg:postcode":"47501",
    "sg:province":"IN",
    "sg:tags":[
        "cashing",
        "check"
    ],
    "wof:name":"Advance America",
    "wof:placetype":"venue"
},
  "geometry": {"coordinates":[-87.15319100000001,38.652967],"type":"Point"}
}