{
  "type": "Feature",
  "properties": {
    "iso:country":"US",
    "sg:address":"6601 Bluff Rd",
    "sg:city":"Indianapolis",
    "sg:classifiers":[
        {
            "category":"Professional",
            "subcategory":"Business Services",
            "type":"Services"
        }
    ],
    "sg:phone":"+1 317 786 3433",
    "sg:postcode":"46217",
    "sg:province":"IN",
    "sg:tags":[
        "automobile",
        "appraiser"
    ],
    "wof:name":"Nostalgia Motors",
    "wof:placetype":"venue"
},
  "geometry": {"coordinates":[-86.180131,39.668409],"type":"Point"}
}