{
  "type": "Feature",
  "properties": {
    "iso:country":"US",
    "sg:address":"1681 Woodlawn Dr",
    "sg:city":"New Albany",
    "sg:classifiers":[
        {
            "category":"Arts & Performance",
            "subcategory":"Theater",
            "type":"Entertainment"
        }
    ],
    "sg:phone":"+1 812 941 9411",
    "sg:postcode":"47150",
    "sg:province":"IN",
    "sg:tags":[
        "live",
        "music"
    ],
    "wof:name":"A Class Act D J's",
    "wof:placetype":"venue"
},
  "geometry": {"coordinates":[-85.805595,38.313657],"type":"Point"}
}