{
  "type": "Feature",
  "properties": {
    "addr:full":"3706 Charlestown Rd New Albany IN 47150",
    "addr:housenumber":"3706",
    "addr:postcode":"47150",
    "addr:street":"Charlestown Rd",
    "iso:country":"US",
    "sg:address":"3706 Charlestown Rd",
    "sg:city":"New Albany",
    "sg:classifiers":[
        {
            "category":"Food & Beverages",
            "subcategory":"Groceries & Convenience Stores",
            "type":"Retail Goods"
        }
    ],
    "sg:phone":"+1 812 949 9329",
    "sg:postcode":"47150",
    "sg:province":"IN",
    "wof:name":"Mac's",
    "wof:placetype":"venue"
},
  "geometry": {"coordinates":[-85.796522,38.348783],"type":"Point"}
}