{
  "type": "Feature",
  "properties": {
    "addr:full":"700 Ohio St Terre Haute IN 47807",
    "addr:housenumber":"700",
    "addr:postcode":"47807",
    "addr:street":"Ohio St",
    "iso:country":"US",
    "sg:address":"700 Ohio St",
    "sg:city":"Terre Haute",
    "sg:classifiers":[
        {
            "category":"Banks & Credit Unions",
            "subcategory":"Bank",
            "type":"Services"
        }
    ],
    "sg:phone":"+1 812 462 7320",
    "sg:postcode":"47807",
    "sg:province":"IN",
    "wof:name":"Old National",
    "wof:placetype":"venue"
},
  "geometry": {"coordinates":[-87.40573500000001,39.465444],"type":"Point"}
}