{
  "type": "Feature",
  "properties": {
    "iso:country":"US",
    "sg:address":"255 N Capitol Ave",
    "sg:city":"Corydon",
    "sg:classifiers":[
        {
            "category":"Shopping",
            "subcategory":"Pharmacy",
            "type":"Retail Goods"
        }
    ],
    "sg:phone":"+1 812 738 7191",
    "sg:postcode":"47112",
    "sg:province":"IN",
    "sg:website":"www.cvs.com",
    "wof:name":"CVS Pharmacy",
    "wof:placetype":"venue"
},
  "geometry": {"coordinates":[-86.126397,38.211768],"type":"Point"}
}