{
  "type": "Feature",
  "properties": {
    "iso:country":"US",
    "sg:address":"300 E Tipton St",
    "sg:city":"Seymour",
    "sg:classifiers":[
        {
            "category":"Food & Beverages",
            "subcategory":"Groceries & Convenience Stores",
            "type":"Retail Goods"
        }
    ],
    "sg:phone":"+1 812 522 2229",
    "sg:postcode":"47274",
    "sg:province":"IN",
    "sg:tags":[
        "grocer"
    ],
    "wof:name":"Sunoco Fuel/Food Mart",
    "wof:placetype":"venue"
},
  "geometry": {"coordinates":[-85.884078,38.957786],"type":"Point"}
}