{
  "type": "Feature",
  "properties": {
    "addr:full":"900 Ridge Rd Munster IN 46321",
    "addr:housenumber":"900",
    "addr:postcode":"46321",
    "addr:street":"Ridge Rd",
    "iso:country":"US",
    "sg:address":"900 Ridge Rd",
    "sg:city":"Munster",
    "sg:classifiers":[
        {
            "category":"Banks & Credit Unions",
            "subcategory":"Investment Brokerage",
            "type":"Services"
        }
    ],
    "sg:phone":"+1 219 836 6134",
    "sg:postcode":"46321",
    "sg:province":"IN",
    "sg:tags":[
        "security"
    ],
    "wof:name":"Raymond James",
    "wof:placetype":"venue"
},
  "geometry": {"coordinates":[-87.508763,41.561178],"type":"Point"}
}