{
  "type": "Feature",
  "properties": {
    "iso:country":"US",
    "sg:address":"2900 E Walls Dr",
    "sg:city":"Bloomington",
    "sg:classifiers":[
        {
            "category":"Retail",
            "subcategory":"Auto Repair",
            "type":"Services"
        }
    ],
    "sg:phone":"+1 812 320 0630",
    "sg:postcode":"47403",
    "sg:province":"IN",
    "sg:tags":[
        "automobile",
        "top",
        "upholstery"
    ],
    "wof:name":"Mobile Quick Inc",
    "wof:placetype":"venue"
},
  "geometry": {"coordinates":[-86.53601999999999,39.135269],"type":"Point"}
}