{
  "type": "Feature",
  "properties": {
    "addr:full":"6070 Old Porter Rd Portage IN 46368",
    "addr:housenumber":"6070",
    "addr:postcode":"46368",
    "addr:street":"Old Porter Rd",
    "iso:country":"US",
    "sg:address":"6070 Old Porter Rd",
    "sg:city":"Portage",
    "sg:classifiers":[
        {
            "category":"Shopping",
            "subcategory":"Books",
            "type":"Retail Goods"
        }
    ],
    "sg:phone":"+1 219 762 2887",
    "sg:postcode":"46368",
    "sg:province":"IN",
    "wof:name":"Eagle Books",
    "wof:placetype":"venue"
},
  "geometry": {"coordinates":[-87.181642,41.594018],"type":"Point"}
}