{
  "type": "Feature",
  "properties": {
    "iso:country":"US",
    "sg:address":"5135 W Ridge Rd",
    "sg:city":"Gary",
    "sg:classifiers":[
        {
            "category":"Retail",
            "subcategory":"Auto Repair",
            "type":"Services"
        }
    ],
    "sg:phone":"+1 219 923 8000",
    "sg:postcode":"46408",
    "sg:province":"IN",
    "sg:tags":[
        "body",
        "automobile",
        "painting"
    ],
    "wof:name":"Broadway Auto Body Repair",
    "wof:placetype":"venue"
},
  "geometry": {"coordinates":[-87.394587,41.548282],"type":"Point"}
}