{
  "type": "Feature",
  "properties": {
    "addr:full":"1585 S 150 W Greenfield IN 46140",
    "addr:housenumber":"1585;150",
    "addr:postcode":"46140",
    "addr:street":"S;W Greenfield",
    "iso:country":"US",
    "sg:address":"1585 S 150 W",
    "sg:city":"Greenfield",
    "sg:classifiers":[
        {
            "category":"Building & Trades",
            "subcategory":"Construction",
            "type":"Services"
        }
    ],
    "sg:phone":"+1 317 462 6604",
    "sg:postcode":"46140",
    "sg:province":"IN",
    "sg:tags":[
        "contractor"
    ],
    "wof:name":"Lloyd Clark Fence Co",
    "wof:placetype":"venue"
},
  "geometry": {"coordinates":[-85.827367,39.761155],"type":"Point"}
}