{
  "type": "Feature",
  "properties": {
    "iso:country":"US",
    "sg:address":"25 E Park St",
    "sg:city":"Brazil",
    "sg:classifiers":[
        {
            "category":"Cinema",
            "subcategory":"Movie Rental",
            "type":"Entertainment"
        }
    ],
    "sg:phone":"+1 812 446 5033",
    "sg:postcode":"47834",
    "sg:province":"IN",
    "sg:tags":[
        "leasing",
        "video",
        "disc",
        "tape"
    ],
    "wof:name":"Movie Gallery",
    "wof:placetype":"venue"
},
  "geometry": {"coordinates":[-87.12794700000001,39.530635],"type":"Point"}
}