{
  "type": "Feature",
  "properties": {
    "iso:country":"US",
    "sg:address":"206 Cade Dr",
    "sg:city":"Chesterfield",
    "sg:classifiers":[
        {
            "category":"Building & Trades",
            "subcategory":"Electrical",
            "type":"Services"
        }
    ],
    "sg:phone":"+1 765 378 5656",
    "sg:postcode":"46017",
    "sg:province":"IN",
    "sg:tags":[
        "electric",
        "contractor"
    ],
    "wof:name":"Wilson Electric Co",
    "wof:placetype":"venue"
},
  "geometry": {"coordinates":[-85.59479899999999,40.111437],"type":"Point"}
}