{
  "type": "Feature",
  "properties": {
    "iso:country":"US",
    "sg:address":"1352 Evergreen Dr",
    "sg:city":"Greenfield",
    "sg:classifiers":[
        {
            "category":"Freight",
            "type":"Transportation"
        }
    ],
    "sg:phone":"+1 317 462 0689",
    "sg:postcode":"46140",
    "sg:province":"IN",
    "sg:tags":[
        "trucking"
    ],
    "wof:name":"Hobbs International Transport",
    "wof:placetype":"venue"
},
  "geometry": {"coordinates":[-85.748637,39.802876],"type":"Point"}
}