{
  "type": "Feature",
  "properties": {
    "iso:country":"US",
    "sg:address":"116 N 2nd St",
    "sg:city":"Decatur",
    "sg:classifiers":[
        {
            "category":"Shopping",
            "subcategory":"Gifts & Souvenirs",
            "type":"Retail Goods"
        }
    ],
    "sg:phone":"+1 260 724 7005",
    "sg:postcode":"46733",
    "sg:province":"IN",
    "sg:tags":[
        "collectible"
    ],
    "wof:name":"J B Collectables",
    "wof:placetype":"venue"
},
  "geometry": {"coordinates":[-84.924268,40.831154],"type":"Point"}
}