{
  "type": "Feature",
  "properties": {
    "addr:full":"6141 S Franklin Rd Acton IN 46259",
    "addr:housenumber":"6141",
    "addr:postcode":"46259",
    "addr:street":"S Franklin Rd",
    "iso:country":"US",
    "sg:address":"6141 S Franklin Rd",
    "sg:city":"Acton",
    "sg:classifiers":[
        {
            "category":"Professional",
            "subcategory":"Management & Consulting",
            "type":"Services"
        }
    ],
    "sg:phone":"+1 317 862 9599",
    "sg:postcode":"46259",
    "sg:province":"IN",
    "sg:tags":[
        "construction"
    ],
    "wof:name":"Freyn Brothers",
    "wof:placetype":"venue"
},
  "geometry": {"coordinates":[-86.018534,39.675862],"type":"Point"}
}