{
  "type": "Feature",
  "properties": {
    "iso:country":"US",
    "sg:address":"3217 S Madison St",
    "sg:city":"Muncie",
    "sg:classifiers":[
        {
            "category":"Professional",
            "subcategory":"Business Services",
            "type":"Services"
        }
    ],
    "sg:phone":"+1 765 289 0002",
    "sg:postcode":"47302",
    "sg:province":"IN",
    "sg:tags":[
        "license"
    ],
    "wof:name":"License Branch-Auto",
    "wof:placetype":"venue"
},
  "geometry": {"coordinates":[-85.381731,40.164042],"type":"Point"}
}