{
  "type": "Feature",
  "properties": {
    "iso:country":"US",
    "sg:address":"6304 W Harper Dr",
    "sg:city":"Yorktown",
    "sg:classifiers":[
        {
            "category":"Building & Trades",
            "subcategory":"Construction",
            "type":"Services"
        }
    ],
    "sg:phone":"+1 765 741 8808",
    "sg:postcode":"47396",
    "sg:province":"IN",
    "sg:tags":[
        "downspouts",
        "gutter"
    ],
    "wof:name":"Delaware Continuous Guttering",
    "wof:placetype":"venue"
},
  "geometry": {"coordinates":[-85.459339,40.168065],"type":"Point"}
}