{
  "type": "Feature",
  "properties": {
    "iso:country":"US",
    "sg:address":"10808 Deandra Dr",
    "sg:city":"Zionsville",
    "sg:classifiers":[
        {
            "category":"Retail",
            "subcategory":"Auto Repair",
            "type":"Services"
        }
    ],
    "sg:phone":"+1 317 873 9881",
    "sg:postcode":"46077",
    "sg:province":"IN",
    "sg:tags":[
        "transmission"
    ],
    "wof:name":"Midwest Transmission Exchange",
    "wof:placetype":"venue"
},
  "geometry": {"coordinates":[-86.239209,39.94255],"type":"Point"}
}