{
  "type": "Feature",
  "properties": {
    "addr:full":"7819 Darien Ct Indianapolis IN 46226",
    "addr:housenumber":"7819",
    "addr:postcode":"46226",
    "addr:street":"Darien Ct",
    "iso:country":"US",
    "sg:address":"7819 Darien Ct",
    "sg:city":"Indianapolis",
    "sg:classifiers":[
        {
            "category":"Personal",
            "subcategory":"Beauty Salon",
            "type":"Services"
        }
    ],
    "sg:phone":"+1 317 898 0785",
    "sg:postcode":"46226",
    "sg:province":"IN",
    "wof:name":"Unique Beauty",
    "wof:placetype":"venue"
},
  "geometry": {"coordinates":[-86.03125,39.829148],"type":"Point"}
}