{
  "type": "Feature",
  "properties": {
    "addr:full":"425 Joliet St Dyer IN 46311",
    "addr:housenumber":"425",
    "addr:postcode":"46311",
    "addr:street":"Joliet St",
    "iso:country":"US",
    "sg:address":"425 Joliet St",
    "sg:city":"Dyer",
    "sg:classifiers":[
        {
            "category":"Restaurant",
            "type":"Food & Drink"
        }
    ],
    "sg:menulink":"http://www.allmenus.com/in/st-john/69780-bellacinos-pizza--grinders/menu/",
    "sg:phone":"+1 219 864 3900",
    "sg:postcode":"46311",
    "sg:province":"IN",
    "sg:tags":[
        "wrap",
        "american",
        "sandwich",
        "pizza"
    ],
    "wof:name":"Bellacino's Pizza & Grinders",
    "wof:placetype":"venue"
},
  "geometry": {"coordinates":[-87.515676,41.493688],"type":"Point"}
}