{
  "type": "Feature",
  "properties": {
    "iso:country":"US",
    "sg:address":"265 W Water St",
    "sg:city":"Berne",
    "sg:classifiers":[
        {
            "category":"Health Services",
            "subcategory":"Nursing And Care Facility",
            "type":"Services"
        }
    ],
    "sg:phone":"+1 260 589 8598",
    "sg:postcode":"46711",
    "sg:province":"IN",
    "sg:tags":[
        "hospice"
    ],
    "wof:name":"Family Hospice Of Ne Indiana",
    "wof:placetype":"venue"
},
  "geometry": {"coordinates":[-84.952122,40.658835],"type":"Point"}
}