{
  "type": "Feature",
  "properties": {
    "addr:full":"3233 Teal Rd Lafayette IN 47905",
    "addr:housenumber":"3233",
    "addr:postcode":"47905",
    "addr:street":"Teal Rd",
    "iso:country":"US",
    "sg:address":"3233 Teal Rd",
    "sg:city":"Lafayette",
    "sg:classifiers":[
        {
            "category":"Recreation",
            "type":"Entertainment"
        }
    ],
    "sg:phone":"+1 765 477 9075",
    "sg:postcode":"47905",
    "sg:province":"IN",
    "sg:tags":[
        "bingo",
        "game"
    ],
    "wof:name":"Boot Scootin' Bingo",
    "wof:placetype":"venue"
},
  "geometry": {"coordinates":[-86.85947,40.39546],"type":"Point"}
}