{
  "type": "Feature",
  "properties": {
    "iso:country":"US",
    "sg:address":"1122 Winchester St",
    "sg:city":"Decatur",
    "sg:classifiers":[
        {
            "category":"Building & Trades",
            "subcategory":"Construction",
            "type":"Services"
        }
    ],
    "sg:phone":"+1 260 724 4344",
    "sg:postcode":"46733",
    "sg:province":"IN",
    "sg:tags":[
        "woodworker"
    ],
    "wof:name":"Midwest Prefinishing Inc",
    "wof:placetype":"venue"
},
  "geometry": {"coordinates":[-84.929609,40.816891],"type":"Point"}
}