{
  "type": "Feature",
  "properties": {
    "iso:country":"US",
    "sg:address":"1101 W Jefferson St",
    "sg:city":"Franklin",
    "sg:classifiers":[
        {
            "category":"Health Services",
            "subcategory":"Doctor",
            "type":"Services"
        }
    ],
    "sg:phone":"+1 317 736 7666",
    "sg:postcode":"46131",
    "sg:province":"IN",
    "sg:tags":[
        "physician",
        "surgeon"
    ],
    "wof:name":"Gerald C Walthall MD",
    "wof:placetype":"venue"
},
  "geometry": {"coordinates":[-86.073302,39.479685],"type":"Point"}
}