{
  "type": "Feature",
  "properties": {
    "iso:country":"US",
    "sg:address":"601 Jackson St",
    "sg:city":"La Porte",
    "sg:classifiers":[
        {
            "category":"Banks & Credit Unions",
            "subcategory":"Bank",
            "type":"Services"
        }
    ],
    "sg:phone":"+1 219 362 0404",
    "sg:postcode":"46350",
    "sg:province":"IN",
    "sg:tags":[
        "mortgage"
    ],
    "wof:name":"Wells Fargo",
    "wof:placetype":"venue"
},
  "geometry": {"coordinates":[-86.719219,41.613398],"type":"Point"}
}