{
  "type": "Feature",
  "properties": {
    "iso:country":"US",
    "sg:address":"3714 Main St",
    "sg:city":"East Chicago",
    "sg:classifiers":[
        {
            "category":"Government",
            "subcategory":"Office",
            "type":"Public Place"
        }
    ],
    "sg:phone":"+1 219 398 4163",
    "sg:postcode":"46312",
    "sg:province":"IN",
    "sg:tags":[
        "state",
        "resource"
    ],
    "wof:name":"Family & Social Svc Adm",
    "wof:placetype":"venue"
},
  "geometry": {"coordinates":[-87.445038,41.64464],"type":"Point"}
}