{
  "type": "Feature",
  "properties": {
    "iso:country":"US",
    "sg:address":"8446 N 100 E",
    "sg:city":"North Manchester",
    "sg:phone":"+1 260 982 4556",
    "sg:postcode":"46962",
    "sg:province":"IN",
    "sg:tags":[
        "farm",
        "corn",
        "soybean"
    ],
    "wof:name":"Lawrence Frieden",
    "wof:placetype":"venue"
},
  "geometry": {"coordinates":[-85.77928900000001,40.949523],"type":"Point"}
}