{
  "type": "Feature",
  "properties": {
    "iso:country":"US",
    "sg:address":"50 E 91st St",
    "sg:city":"Indianapolis",
    "sg:classifiers":[
        {
            "category":"Professional",
            "subcategory":"Management & Consulting",
            "type":"Services"
        }
    ],
    "sg:phone":"+1 317 581 9326",
    "sg:postcode":"46240",
    "sg:province":"IN",
    "sg:tags":[
        "personnel",
        "consultant"
    ],
    "sg:website":"www.ipsp.net",
    "wof:name":"Institute For Public Safety",
    "wof:placetype":"venue"
},
  "geometry": {"coordinates":[-86.155574,39.919778],"type":"Point"}
}