{
  "type": "Feature",
  "properties": {
    "iso:country":"US",
    "sg:address":"1420 Silver Slate Dr",
    "sg:city":"New Albany",
    "sg:classifiers":[
        {
            "category":"Insurance",
            "subcategory":"Insurance Agent",
            "type":"Services"
        }
    ],
    "sg:phone":"+1 812 944 6095",
    "sg:postcode":"47150",
    "sg:province":"IN",
    "sg:tags":[
        "agency"
    ],
    "wof:name":"Old Republic",
    "wof:placetype":"venue"
},
  "geometry": {"coordinates":[-85.796688,38.308121],"type":"Point"}
}