{
  "type": "Feature",
  "properties": {
    "iso:country":"US",
    "sg:address":"6508 E Washington St",
    "sg:city":"Indianapolis",
    "sg:classifiers":[
        {
            "category":"Professional",
            "subcategory":"Computer Services",
            "type":"Services"
        }
    ],
    "sg:phone":"+1 317 356 3622",
    "sg:postcode":"46219",
    "sg:province":"IN",
    "wof:name":"Tacs Inc",
    "wof:placetype":"venue"
},
  "geometry": {"coordinates":[-86.05477999999999,39.771682],"type":"Point"}
}