{
  "type": "Feature",
  "properties": {
    "iso:country":"US",
    "sg:address":"6294 E US Hwy 33",
    "sg:city":"Churubusco",
    "sg:classifiers":[
        {
            "category":"Building & Trades",
            "subcategory":"Landscaping Services",
            "type":"Services"
        }
    ],
    "sg:phone":"+1 260 705 6649",
    "sg:postcode":"46723",
    "sg:province":"IN",
    "sg:tags":[
        "landscape"
    ],
    "wof:name":"Prestige Services Inc",
    "wof:placetype":"venue"
},
  "geometry": {"coordinates":[-85.370513,41.257643],"type":"Point"}
}