{
  "type": "Feature",
  "properties": {
    "addr:full":"209 S Calumet Rd Chesterton IN 46304",
    "addr:housenumber":"209",
    "addr:postcode":"46304",
    "addr:street":"S Calumet Rd",
    "iso:country":"US",
    "sg:address":"209 S Calumet Rd",
    "sg:city":"Chesterton",
    "sg:classifiers":[
        {
            "category":"Banks & Credit Unions",
            "subcategory":"Bank",
            "type":"Services"
        }
    ],
    "sg:phone":"+1 219 926 4689",
    "sg:postcode":"46304",
    "sg:province":"IN",
    "sg:tags":[
        "loan",
        "real estate"
    ],
    "sg:website":"www.uniquehomeloans.com",
    "wof:name":"Alamo Services Inc",
    "wof:placetype":"venue"
},
  "geometry": {"coordinates":[-87.05191600000001,41.609651],"type":"Point"}
}