{
  "type": "Feature",
  "properties": {
    "iso:country":"US",
    "sg:address":"1080 Spartan Dr",
    "sg:city":"Columbia City",
    "sg:classifiers":[
        {
            "category":"Restaurant",
            "type":"Food & Drink"
        }
    ],
    "sg:menulink":"http://www.allmenus.com/in/columbia/67541-east-of-chicago-pizza/menu/",
    "sg:phone":"+1 260 248 2122",
    "sg:postcode":"46725",
    "sg:province":"IN",
    "sg:tags":[
        "sandwich",
        "salad",
        "soup",
        "american",
        "wrap",
        "pizza"
    ],
    "wof:name":"East of Chicago Pizza",
    "wof:placetype":"venue"
},
  "geometry": {"coordinates":[-85.485696,41.171152],"type":"Point"}
}