{
  "type": "Feature",
  "properties": {
    "iso:country":"US",
    "sg:address":"5150 E Stop 11 Rd",
    "sg:city":"Indianapolis",
    "sg:classifiers":[
        {
            "category":"Insurance",
            "subcategory":"Insurance Agent",
            "type":"Services"
        }
    ],
    "sg:phone":"+1 317 883 2100",
    "sg:postcode":"46237",
    "sg:province":"IN",
    "sg:website":"www.afponline.com",
    "wof:name":"Affiliated Financial Profs",
    "wof:placetype":"venue"
},
  "geometry": {"coordinates":[-86.07835300000001,39.651312],"type":"Point"}
}