{
  "type": "Feature",
  "properties": {
    "addr:full":"812 S Fleming St Indianapolis IN 46241",
    "addr:housenumber":"812",
    "addr:postcode":"46241",
    "addr:street":"S Fleming St",
    "iso:country":"US",
    "sg:address":"812 S Fleming St",
    "sg:city":"Indianapolis",
    "sg:classifiers":[
        {
            "category":"Building & Trades",
            "subcategory":"Construction",
            "type":"Services"
        }
    ],
    "sg:phone":"+1 317 244 5774",
    "sg:postcode":"46241",
    "sg:province":"IN",
    "sg:tags":[
        "downspouts",
        "gutter"
    ],
    "wof:name":"Howard's Gutters",
    "wof:placetype":"venue"
},
  "geometry": {"coordinates":[-86.23688,39.753822],"type":"Point"}
}