{
  "type": "Feature",
  "properties": {
    "addr:full":"6302 Rucker Rd Indianapolis IN 46220",
    "addr:housenumber":"6302",
    "addr:postcode":"46220",
    "addr:street":"Rucker Rd",
    "iso:country":"US",
    "sg:address":"6302 Rucker Rd",
    "sg:city":"Indianapolis",
    "sg:classifiers":[
        {
            "category":"Banks & Credit Unions",
            "subcategory":"Bank",
            "type":"Services"
        }
    ],
    "sg:phone":"+1 317 726 0955",
    "sg:postcode":"46220",
    "sg:province":"IN",
    "sg:tags":[
        "loan"
    ],
    "sg:website":"www.goldleafgroup.com",
    "wof:name":"Goldleaf Mortgage Group",
    "wof:placetype":"venue"
},
  "geometry": {"coordinates":[-86.079346,39.868726],"type":"Point"}
}