{
  "type": "Feature",
  "properties": {
    "iso:country":"US",
    "sg:address":"9435 Roberts Rd",
    "sg:city":"Woodburn",
    "sg:classifiers":[
        {
            "category":"Manufacturing",
            "subcategory":"Tools & Machinery",
            "type":"Manufacturing & Wholesale Goods"
        }
    ],
    "sg:phone":"+1 260 657 3346",
    "sg:postcode":"46797",
    "sg:province":"IN",
    "sg:tags":[
        "mfg",
        "industrial",
        "motor",
        "vehicle"
    ],
    "wof:name":"Unique Accessories Inc",
    "wof:placetype":"venue"
},
  "geometry": {"coordinates":[-84.92233,41.172437],"type":"Point"}
}