{
  "type": "Feature",
  "properties": {
    "iso:country":"US",
    "sg:address":"620 Washington St",
    "sg:city":"Rockport",
    "sg:classifiers":[
        {
            "category":"Government",
            "subcategory":"Office",
            "type":"Public Place"
        }
    ],
    "sg:phone":"+1 812 649 7431",
    "sg:postcode":"47635",
    "sg:province":"IN",
    "sg:tags":[
        "village"
    ],
    "wof:name":"Rockport City Garage",
    "wof:placetype":"venue"
},
  "geometry": {"coordinates":[-87.054788,37.886953],"type":"Point"}
}