{
  "type": "Feature",
  "properties": {
    "addr:full":"111 S Lake Ct Michigan City IN 46360",
    "addr:housenumber":"111",
    "addr:postcode":"46360",
    "addr:street":"S Lake Ct",
    "iso:country":"US",
    "sg:address":"111 S Lake Ct",
    "sg:city":"Michigan City",
    "sg:classifiers":[
        {
            "category":"Real Estate",
            "subcategory":"Surveying",
            "type":"Services"
        }
    ],
    "sg:phone":"+1 219 879 2504",
    "sg:postcode":"46360",
    "sg:province":"IN",
    "sg:tags":[
        "surveyor"
    ],
    "wof:name":"Sekerez Land Surveying",
    "wof:placetype":"venue"
},
  "geometry": {"coordinates":[-86.896918,41.670766],"type":"Point"}
}