{
  "type": "Feature",
  "properties": {
    "iso:country":"US",
    "sg:address":"1845 S Hunter Rd",
    "sg:city":"Indianapolis",
    "sg:classifiers":[
        {
            "category":"Building & Trades",
            "subcategory":"Construction",
            "type":"Services"
        }
    ],
    "sg:phone":"+1 317 291 1417",
    "sg:postcode":"46239",
    "sg:province":"IN",
    "sg:tags":[
        "excavating"
    ],
    "wof:name":"Ensley Excavating",
    "wof:placetype":"venue"
},
  "geometry": {"coordinates":[-86.049519,39.743024],"type":"Point"}
}