{
  "type": "Feature",
  "properties": {
    "iso:country":"US",
    "sg:address":"25855 Northwood Dr",
    "sg:city":"South Bend",
    "sg:classifiers":[
        {
            "category":"Manufacturing",
            "subcategory":"Tools & Machinery",
            "type":"Manufacturing & Wholesale Goods"
        }
    ],
    "sg:phone":"+1 574 289 2291",
    "sg:postcode":"46619",
    "sg:province":"IN",
    "sg:tags":[
        "machine",
        "shop"
    ],
    "wof:name":"Dkl Tool and Manufacturing",
    "wof:placetype":"venue"
},
  "geometry": {"coordinates":[-86.369884,41.645659],"type":"Point"}
}