{
  "type": "Feature",
  "properties": {
    "iso:country":"US",
    "sg:address":"520 S 10th St",
    "sg:city":"Lafayette",
    "sg:classifiers":[
        {
            "category":"Building & Trades",
            "subcategory":"Construction",
            "type":"Services"
        }
    ],
    "sg:phone":"+1 765 423 1453",
    "sg:postcode":"47905",
    "sg:province":"IN",
    "sg:tags":[
        "general",
        "contractor"
    ],
    "wof:name":"John Downey Builders",
    "wof:placetype":"venue"
},
  "geometry": {"coordinates":[-86.885429,40.411269],"type":"Point"}
}