{
  "type": "Feature",
  "properties": {
    "iso:country":"US",
    "sg:address":"218 Maple St",
    "sg:city":"Milan",
    "sg:classifiers":[
        {
            "category":"Social Services",
            "subcategory":"Adult Care",
            "type":"Services"
        }
    ],
    "sg:phone":"+1 812 744 6104",
    "sg:postcode":"47031",
    "sg:province":"IN",
    "sg:tags":[
        "senior",
        "housing",
        "citizen"
    ],
    "wof:name":"Milan Housing Inc",
    "wof:placetype":"venue"
},
  "geometry": {"coordinates":[-85.1288,39.12385],"type":"Point"}
}