{
  "type": "Feature",
  "properties": {
    "iso:country":"US",
    "sg:address":"130 E 11th St",
    "sg:city":"Brookville",
    "sg:classifiers":[
        {
            "category":"Insurance",
            "subcategory":"Insurance Agent",
            "type":"Services"
        }
    ],
    "sg:phone":"+1 765 647 6351",
    "sg:postcode":"47012",
    "sg:province":"IN",
    "wof:name":"State Farm Insurance",
    "wof:placetype":"venue"
},
  "geometry": {"coordinates":[-85.012223,39.426912],"type":"Point"}
}