{
  "type": "Feature",
  "properties": {
    "iso:country":"US",
    "sg:address":"402 Jaycee St",
    "sg:city":"Chandler",
    "sg:classifiers":[
        {
            "category":"Education",
            "subcategory":"Library",
            "type":"Public Place"
        }
    ],
    "sg:phone":"+1 812 925 7179",
    "sg:postcode":"47610",
    "sg:province":"IN",
    "wof:name":"Chandler Library",
    "wof:placetype":"venue"
},
  "geometry": {"coordinates":[-87.370126,38.04001],"type":"Point"}
}