{
  "type": "Feature",
  "properties": {
    "iso:country":"US",
    "sg:address":"9133 Bluestone Cir",
    "sg:city":"Indianapolis",
    "sg:classifiers":[
        {
            "category":"Shopping",
            "type":"Retail Goods"
        }
    ],
    "sg:phone":"+1 317 826 1406",
    "sg:postcode":"46236",
    "sg:province":"IN",
    "sg:tags":[
        "plastic"
    ],
    "wof:name":"Innovative Plastic Concepts",
    "wof:placetype":"venue"
},
  "geometry": {"coordinates":[-85.954645,39.920197],"type":"Point"}
}