{
  "type": "Feature",
  "properties": {
    "addr:full":"507 W Lois Ln Bloomington IN 47403",
    "addr:housenumber":"507",
    "addr:postcode":"47403",
    "addr:street":"W Lois Ln",
    "iso:country":"US",
    "sg:address":"507 W Lois Ln",
    "sg:city":"Bloomington",
    "sg:classifiers":[
        {
            "category":"Building & Trades",
            "subcategory":"Construction",
            "type":"Services"
        }
    ],
    "sg:phone":"+1 812 334 1766",
    "sg:postcode":"47403",
    "sg:province":"IN",
    "sg:tags":[
        "contractor"
    ],
    "wof:name":"Chandler Tile & Marble",
    "wof:placetype":"venue"
},
  "geometry": {"coordinates":[-86.54146,39.129566],"type":"Point"}
}