{
  "type": "Feature",
  "properties": {
    "addr:full":"2504 E 3rd St Bloomington IN 47401",
    "addr:housenumber":"2504",
    "addr:postcode":"47401",
    "addr:street":"E 3Rd St",
    "iso:country":"US",
    "sg:address":"2504 E 3rd St",
    "sg:city":"Bloomington",
    "sg:classifiers":[
        {
            "category":"Retail",
            "subcategory":"Laundry & Dry Cleaning",
            "type":"Services"
        }
    ],
    "sg:phone":"+1 812 333 6700",
    "sg:postcode":"47401",
    "sg:province":"IN",
    "sg:tags":[
        "cleaner"
    ],
    "wof:name":"CrossTown Cleaners",
    "wof:placetype":"venue"
},
  "geometry": {"coordinates":[-86.50239999999999,39.164239],"type":"Point"}
}