{
  "type": "Feature",
  "properties": {
    "iso:country":"US",
    "sg:address":"5332 Rockville Rd",
    "sg:city":"Indianapolis",
    "sg:classifiers":[
        {
            "category":"Home & Garden",
            "subcategory":"Building Materials",
            "type":"Retail Goods"
        }
    ],
    "sg:phone":"+1 317 244 5277",
    "sg:postcode":"46224",
    "sg:province":"IN",
    "sg:tags":[
        "glass",
        "window",
        "plate"
    ],
    "wof:name":"Speedway Auto Glass Co",
    "wof:placetype":"venue"
},
  "geometry": {"coordinates":[-86.252448,39.765243],"type":"Point"}
}