{
  "type": "Feature",
  "properties": {
    "addr:full":"6357 Rockville Rd Indianapolis IN 46214",
    "addr:housenumber":"6357",
    "addr:postcode":"46214",
    "addr:street":"Rockville Rd",
    "iso:country":"US",
    "sg:address":"6357 Rockville Rd",
    "sg:city":"Indianapolis",
    "sg:classifiers":[
        {
            "category":"Shopping",
            "type":"Retail Goods"
        }
    ],
    "sg:phone":"+1 317 243 2100",
    "sg:postcode":"46214",
    "sg:province":"IN",
    "sg:tags":[
        "hearing",
        "equipment",
        "supply",
        "impaired"
    ],
    "wof:name":"Physicians & Assoc",
    "wof:placetype":"venue"
},
  "geometry": {"coordinates":[-86.270516,39.764643],"type":"Point"}
}