{
  "type": "Feature",
  "properties": {
    "iso:country":"US",
    "sg:address":"704 E Locust St",
    "sg:city":"Fort Branch",
    "sg:classifiers":[
        {
            "category":"Shopping",
            "subcategory":"Bicycles & Sporting Goods",
            "type":"Retail Goods"
        }
    ],
    "sg:phone":"+1 812 753 9968",
    "sg:postcode":"47648",
    "sg:province":"IN",
    "sg:tags":[
        "equipment",
        "exercise"
    ],
    "wof:name":"Bigger Faster Stronger",
    "wof:placetype":"venue"
},
  "geometry": {"coordinates":[-87.571663,38.247338],"type":"Point"}
}