{
  "type": "Feature",
  "properties": {
    "iso:country":"US",
    "sg:address":"2570 S Co Rd 310 W",
    "sg:city":"Vallonia",
    "sg:classifiers":[
        {
            "category":"Building & Trades",
            "subcategory":"Construction",
            "type":"Services"
        }
    ],
    "sg:phone":"+1 812 358 5129",
    "sg:postcode":"47281",
    "sg:province":"IN",
    "sg:tags":[
        "excavating",
        "contractor"
    ],
    "wof:name":"Hauer Excavating",
    "wof:placetype":"venue"
},
  "geometry": {"coordinates":[-86.098117,38.843791],"type":"Point"}
}