{
  "type": "Feature",
  "properties": {
    "iso:country":"US",
    "sg:address":"4305 W 300 S",
    "sg:city":"New Palestine",
    "sg:classifiers":[
        {
            "category":"Building & Trades",
            "subcategory":"Construction",
            "type":"Services"
        }
    ],
    "sg:phone":"+1 317 861 4594",
    "sg:postcode":"46163",
    "sg:province":"IN",
    "sg:tags":[
        "contractor"
    ],
    "wof:name":"Hesterly Drywall",
    "wof:placetype":"venue"
},
  "geometry": {"coordinates":[-85.882256,39.742275],"type":"Point"}
}