{
  "type": "Feature",
  "properties": {
    "iso:country":"US",
    "sg:address":"705 S Noble St",
    "sg:city":"Shelbyville",
    "sg:classifiers":[
        {
            "category":"Home & Garden",
            "subcategory":"Household Appliances",
            "type":"Retail Goods"
        }
    ],
    "sg:phone":"+1 317 398 3111",
    "sg:postcode":"46176",
    "sg:province":"IN",
    "sg:tags":[
        "cleaners",
        "vacuum"
    ],
    "wof:name":"Quality Vacuum Sales & Svc",
    "wof:placetype":"venue"
},
  "geometry": {"coordinates":[-85.772825,39.518799],"type":"Point"}
}