{
  "type": "Feature",
  "properties": {
    "iso:country":"US",
    "sg:address":"6611 Bluff Rd",
    "sg:city":"Indianapolis",
    "sg:classifiers":[
        {
            "category":"Recreation",
            "type":"Entertainment"
        }
    ],
    "sg:phone":"+1 317 783 3660",
    "sg:postcode":"46217",
    "sg:province":"IN",
    "sg:tags":[
        "skating",
        "rink"
    ],
    "wof:name":"Southland Skate Ctr",
    "wof:placetype":"venue"
},
  "geometry": {"coordinates":[-86.180082,39.668552],"type":"Point"}
}