{
  "type": "Feature",
  "properties": {
    "addr:full":"113 Maryland St North Judson IN 46366",
    "addr:housenumber":"113",
    "addr:postcode":"judson;46366",
    "addr:street":"Maryland St",
    "iso:country":"US",
    "sg:address":"113 Maryland St",
    "sg:city":"North Judson",
    "sg:classifiers":[
        {
            "category":"Real Estate",
            "subcategory":"Real Estate Operator",
            "type":"Services"
        }
    ],
    "sg:phone":"+1 574 896 5013",
    "sg:postcode":"46366",
    "sg:province":"IN",
    "sg:tags":[
        "apartment"
    ],
    "wof:name":"Oak Manor Apartments",
    "wof:placetype":"venue"
},
  "geometry": {"coordinates":[-86.76740100000001,41.216175],"type":"Point"}
}