{
  "type": "Feature",
  "properties": {
    "addr:full":"6776 E State Rd 218 Camden IN 46917",
    "addr:housenumber":"6776;218",
    "addr:postcode":"46917",
    "addr:street":"E State Rd;Camden In",
    "iso:country":"US",
    "sg:address":"6776 E State Rd 218",
    "sg:city":"Camden",
    "sg:classifiers":[
        {
            "category":"Building & Trades",
            "subcategory":"Construction",
            "type":"Services"
        }
    ],
    "sg:phone":"+1 574 859 3200",
    "sg:postcode":"46917",
    "sg:province":"IN",
    "sg:tags":[
        "roofing",
        "contractor"
    ],
    "wof:name":"Myer Exteriors Inc",
    "wof:placetype":"venue"
},
  "geometry": {"coordinates":[-86.39448299999999,40.609697],"type":"Point"}
}