{
  "type": "Feature",
  "properties": {
    "iso:country":"US",
    "sg:address":"104 E Tate St",
    "sg:city":"Kokomo",
    "sg:classifiers":[
        {
            "category":"Building & Trades",
            "subcategory":"Cleaning & Sanitation",
            "type":"Services"
        }
    ],
    "sg:phone":"+1 765 452 5094",
    "sg:postcode":"46901",
    "sg:province":"IN",
    "sg:tags":[
        "janitor"
    ],
    "wof:name":"Sandy Janitorial Svc",
    "wof:placetype":"venue"
},
  "geometry": {"coordinates":[-86.129229,40.500092],"type":"Point"}
}