{
  "type": "Feature",
  "properties": {
    "iso:country":"US",
    "sg:address":"2810 E Jefferson Blvd",
    "sg:city":"South Bend",
    "sg:classifiers":[
        {
            "category":"Shopping",
            "subcategory":"Computers & Home Electronics",
            "type":"Retail Goods"
        }
    ],
    "sg:phone":"+1 574 232 5675",
    "sg:postcode":"46615",
    "sg:province":"IN",
    "sg:tags":[
        "software"
    ],
    "sg:website":"www.mis-group.com",
    "wof:name":"Manufacturing Information Sltn",
    "wof:placetype":"venue"
},
  "geometry": {"coordinates":[-86.20696599999999,41.672852],"type":"Point"}
}