{
  "type": "Feature",
  "properties": {
    "iso:country":"US",
    "sg:address":"4201 W US Hwy 40",
    "sg:city":"West Terre Haute",
    "sg:classifiers":[
        {
            "category":"Professional",
            "type":"Services"
        }
    ],
    "sg:phone":"+1 812 533 0444",
    "sg:postcode":"47885",
    "sg:province":"IN",
    "wof:name":"Great Vision Art Studio",
    "wof:placetype":"venue"
},
  "geometry": {"coordinates":[-87.480061,39.454788],"type":"Point"}
}