{
  "type": "Feature",
  "properties": {
    "iso:country":"US",
    "sg:address":"2246 N 1150 E",
    "sg:city":"Idaville",
    "sg:classifiers":[
        {
            "category":"Farming",
            "subcategory":"Farm",
            "type":"Manufacturing & Wholesale Goods"
        }
    ],
    "sg:phone":"+1 574 943 3204",
    "sg:postcode":"47950",
    "sg:province":"IN",
    "wof:name":"Sommers Farms Inc",
    "wof:placetype":"venue"
},
  "geometry": {"coordinates":[-86.648917,40.787733],"type":"Point"}
}