{
  "type": "Feature",
  "properties": {
    "addr:full":"314 State Rd 66 Tell City IN 47586",
    "addr:housenumber":"314;66",
    "addr:postcode":"47586",
    "addr:street":"State Rd",
    "iso:country":"US",
    "sg:address":"314 State Rd 66",
    "sg:city":"Tell City",
    "sg:classifiers":[
        {
            "category":"Retail",
            "subcategory":"Repair Shop",
            "type":"Services"
        }
    ],
    "sg:phone":"+1 812 547 8816",
    "sg:postcode":"47586",
    "sg:province":"IN",
    "sg:tags":[
        "telephone",
        "cellular"
    ],
    "wof:name":"Advanced Cellular Of Tell City",
    "wof:placetype":"venue"
},
  "geometry": {"coordinates":[-86.756592,37.935893],"type":"Point"}
}