{
  "type": "Feature",
  "properties": {
    "addr:full":"5029 N Lakeview Dr Bloomington IN 47404",
    "addr:housenumber":"5029",
    "addr:postcode":"47404",
    "addr:street":"N Lakeview Dr",
    "iso:country":"US",
    "sg:address":"5029 N Lakeview Dr",
    "sg:city":"Bloomington",
    "sg:classifiers":[
        {
            "category":"Building & Trades",
            "subcategory":"Plumbing",
            "type":"Services"
        }
    ],
    "sg:phone":"+1 812 876 2822",
    "sg:postcode":"47404",
    "sg:province":"IN",
    "sg:tags":[
        "contractor"
    ],
    "wof:name":"Grimes Plumbing Inc",
    "wof:placetype":"venue"
},
  "geometry": {"coordinates":[-86.60489699999999,39.223],"type":"Point"}
}