{
  "type": "Feature",
  "properties": {
    "addr:full":"4856 Bulla Rd Richmond IN 47374",
    "addr:housenumber":"4856",
    "addr:postcode":"47374",
    "addr:street":"Bulla Rd",
    "iso:country":"US",
    "sg:address":"4856 Bulla Rd",
    "sg:city":"Richmond",
    "sg:classifiers":[
        {
            "category":"Travel",
            "subcategory":"Campground",
            "type":"Entertainment"
        }
    ],
    "sg:phone":"+1 765 939 2500",
    "sg:postcode":"47374",
    "sg:province":"IN",
    "sg:tags":[
        "camp"
    ],
    "wof:name":"Dick Baumgartner's Basketball",
    "wof:placetype":"venue"
},
  "geometry": {"coordinates":[-84.836562,39.763089],"type":"Point"}
}