{
  "type": "Feature",
  "properties": {
    "iso:country":"US",
    "sg:address":"108 Cross St",
    "sg:city":"Waveland",
    "sg:classifiers":[
        {
            "category":"Food & Beverages",
            "subcategory":"Liquor & Beverages",
            "type":"Retail Goods"
        }
    ],
    "sg:phone":"+1 765 435 7289",
    "sg:postcode":"47989",
    "sg:province":"IN",
    "wof:name":"Hilltop Liquors",
    "wof:placetype":"venue"
},
  "geometry": {"coordinates":[-87.044456,39.87572],"type":"Point"}
}