{
  "type": "Feature",
  "properties": {
    "iso:country":"US",
    "sg:address":"2054 E Ireland Rd",
    "sg:city":"South Bend",
    "sg:classifiers":[
        {
            "category":"Personal",
            "subcategory":"Beauty Salon",
            "type":"Services"
        }
    ],
    "sg:phone":"+1 574 299 1399",
    "sg:postcode":"46614",
    "sg:province":"IN",
    "wof:name":"Creative Edge Hair Studio",
    "wof:placetype":"venue"
},
  "geometry": {"coordinates":[-86.21906,41.629411],"type":"Point"}
}