{
  "type": "Feature",
  "properties": {
    "addr:full":"1615 Western Ave Bluffton IN 46714",
    "addr:housenumber":"1615",
    "addr:postcode":"46714",
    "addr:street":"Western Ave",
    "iso:country":"US",
    "sg:address":"1615 Western Ave",
    "sg:city":"Bluffton",
    "sg:classifiers":[
        {
            "category":"Government",
            "subcategory":"Jail",
            "type":"Public Place"
        }
    ],
    "sg:phone":"+1 260 824 3426",
    "sg:postcode":"46714",
    "sg:province":"IN",
    "sg:tags":[
        "county",
        "govt",
        "institution"
    ],
    "wof:name":"County Jail",
    "wof:placetype":"venue"
},
  "geometry": {"coordinates":[-85.192947,40.733626],"type":"Point"}
}