{
  "type": "Feature",
  "properties": {
    "addr:full":"1848 N 225 E Attica IN 47918",
    "addr:housenumber":"1848",
    "addr:postcode":"in 47918",
    "addr:street":"N 225 E",
    "iso:country":"US",
    "sg:address":"1848 N 225 E",
    "sg:city":"Attica",
    "sg:classifiers":[
        {
            "category":"Manufacturing",
            "subcategory":"Buildings",
            "type":"Manufacturing & Wholesale Goods"
        },
        {
            "category":"Building & Trades",
            "subcategory":"Construction",
            "type":"Services"
        },
        {
            "category":"Utilities",
            "type":"Services"
        }
    ],
    "sg:phone":"+1 765 762 2977",
    "sg:postcode":"47918",
    "sg:province":"IN",
    "sg:tags":[
        "industrial",
        "builder",
        "system",
        "specialty",
        "heating",
        "contractor",
        "home",
        "air conditioning",
        "contractors-commercial"
    ],
    "wof:name":"Tanner Mark Construction",
    "wof:placetype":"venue"
},
  "geometry": {"coordinates":[-87.27714899999999,40.344798],"type":"Point"}
}