{
  "type": "Feature",
  "properties": {
    "iso:country":"US",
    "sg:address":"203 E Main St",
    "sg:city":"Henryville",
    "sg:classifiers":[
        {
            "category":"Professional",
            "subcategory":"Lawyer & Legal Services",
            "type":"Services"
        }
    ],
    "sg:phone":"+1 812 294 1410",
    "sg:postcode":"47126",
    "sg:province":"IN",
    "sg:tags":[
        "attorney"
    ],
    "wof:name":"Betty Hogue Carver Law Office",
    "wof:placetype":"venue"
},
  "geometry": {"coordinates":[-85.766179,38.540316],"type":"Point"}
}