{
  "type": "Feature",
  "properties": {
    "iso:country":"US",
    "sg:address":"2401 7th Ave",
    "sg:city":"Terre Haute",
    "sg:classifiers":[
        {
            "category":"Organizations",
            "subcategory":"Religious Organization",
            "type":"Services"
        }
    ],
    "sg:phone":"+1 812 231 1799",
    "sg:postcode":"47803",
    "sg:province":"IN",
    "wof:name":"Shiloh Baptist Church",
    "wof:placetype":"venue"
},
  "geometry": {"coordinates":[-87.380016,39.483584],"type":"Point"}
}