{
  "type": "Feature",
  "properties": {
    "iso:country":"US",
    "sg:address":"1650 W 81st Ave",
    "sg:city":"Merrillville",
    "sg:classifiers":[
        {
            "category":"Retail",
            "subcategory":"Auto Rental",
            "type":"Services"
        }
    ],
    "sg:phone":"+1 219 769 2444",
    "sg:postcode":"46410",
    "sg:province":"IN",
    "sg:tags":[
        "renting",
        "truck",
        "leasing"
    ],
    "wof:name":"U-Haul Co",
    "wof:placetype":"venue"
},
  "geometry": {"coordinates":[-87.353862,41.47118],"type":"Point"}
}