{
  "type": "Feature",
  "properties": {
    "iso:country":"US",
    "sg:address":"960 N Van Buren St",
    "sg:city":"Shipshewana",
    "sg:classifiers":[
        {
            "category":"Shopping",
            "subcategory":"Used Merchandise",
            "type":"Retail Goods"
        }
    ],
    "sg:phone":"+1 260 768 7070",
    "sg:postcode":"46565",
    "sg:province":"IN",
    "wof:name":"Shipshewana Antique Reprodctns",
    "wof:placetype":"venue"
},
  "geometry": {"coordinates":[-85.58057,41.66934],"type":"Point"}
}