{
  "type": "Feature",
  "properties": {
    "iso:country":"US",
    "sg:address":"213 S Washington St",
    "sg:city":"Swayzee",
    "sg:classifiers":[
        {
            "category":"Government",
            "subcategory":"Office",
            "type":"Public Place"
        }
    ],
    "sg:phone":"+1 765 922 7953",
    "sg:postcode":"46986",
    "sg:province":"IN",
    "sg:tags":[
        "city",
        "taxation"
    ],
    "wof:name":"Swayzee Clerk-Treasurer",
    "wof:placetype":"venue"
},
  "geometry": {"coordinates":[-85.825518,40.507326],"type":"Point"}
}