{
  "type": "Feature",
  "properties": {
    "iso:country":"US",
    "sg:address":"22918 Mule Barn Rd",
    "sg:city":"Sheridan",
    "sg:classifiers":[
        {
            "category":"Wholesale",
            "subcategory":"Machinery & Supplies",
            "type":"Manufacturing & Wholesale Goods"
        }
    ],
    "sg:phone":"+1 317 758 8000",
    "sg:postcode":"46069",
    "sg:province":"IN",
    "sg:tags":[
        "equipment",
        "irrigation",
        "system"
    ],
    "wof:name":"Irrigation Plus Inc",
    "wof:placetype":"venue"
},
  "geometry": {"coordinates":[-86.222695,40.114454],"type":"Point"}
}