{
  "type": "Feature",
  "properties": {
    "addr:full":"6109 E Co Rd 700 S Muncie IN 47302",
    "addr:housenumber":"6109;700",
    "addr:postcode":"47302",
    "addr:street":"E Co Rd;S Muncie",
    "iso:country":"US",
    "sg:address":"6109 E Co Rd 700 S",
    "sg:city":"Muncie",
    "sg:phone":"+1 765 774 4576",
    "sg:postcode":"47302",
    "sg:province":"IN",
    "sg:tags":[
        "farm",
        "corn",
        "soybean"
    ],
    "wof:name":"Bobbie Galbraith",
    "wof:placetype":"venue"
},
  "geometry": {"coordinates":[-85.326531,40.090982],"type":"Point"}
}