{
  "type": "Feature",
  "properties": {
    "addr:full":"7998 E 10th St Indianapolis IN 46219",
    "addr:housenumber":"7998",
    "addr:postcode":"46219",
    "addr:street":"E 10Th St",
    "iso:country":"US",
    "sg:address":"7998 E 10th St",
    "sg:city":"Indianapolis",
    "sg:classifiers":[
        {
            "category":"Place Of Worship",
            "subcategory":"Church",
            "type":"Public Place"
        }
    ],
    "sg:phone":"+1 317 356 2901",
    "sg:postcode":"46219",
    "sg:province":"IN",
    "sg:tags":[
        "affiliate",
        "churches-church",
        "god-anderson",
        "indiana"
    ],
    "wof:name":"East 10th St. Church of God Daycare Ministry",
    "wof:placetype":"venue"
},
  "geometry": {"coordinates":[-86.026314,39.78186],"type":"Point"}
}