{
  "type": "Feature",
  "properties": {
    "iso:country":"US",
    "sg:address":"1815 McDonald Ln",
    "sg:city":"New Albany",
    "sg:classifiers":[
        {
            "category":"Retail",
            "subcategory":"Repair Shop",
            "type":"Services"
        }
    ],
    "sg:phone":"+1 812 949 5046",
    "sg:postcode":"47150",
    "sg:province":"IN",
    "sg:tags":[
        "appliance"
    ],
    "wof:name":"PCS Appliance Repair",
    "wof:placetype":"venue"
},
  "geometry": {"coordinates":[-85.813442,38.319588],"type":"Point"}
}