{
  "type": "Feature",
  "properties": {
    "iso:country":"US",
    "sg:address":"10890 Andrade Dr",
    "sg:city":"Zionsville",
    "sg:classifiers":[
        {
            "category":"Building & Trades",
            "subcategory":"Construction",
            "type":"Services"
        }
    ],
    "sg:phone":"+1 317 873 5265",
    "sg:postcode":"46077",
    "sg:province":"IN",
    "sg:tags":[
        "excavating",
        "contractor"
    ],
    "wof:name":"Snider Group Inc",
    "wof:placetype":"venue"
},
  "geometry": {"coordinates":[-86.244001,39.94064],"type":"Point"}
}