{
  "type": "Feature",
  "properties": {
    "iso:country":"US",
    "sg:address":"8297 S 1100 W",
    "sg:city":"Francesville",
    "sg:classifiers":[
        {
            "category":"Retail",
            "subcategory":"Repair Shop",
            "type":"Services"
        }
    ],
    "sg:phone":"+1 219 567 9808",
    "sg:postcode":"47946",
    "sg:province":"IN",
    "sg:tags":[
        "welding"
    ],
    "wof:name":"Barlow & Sons Welding",
    "wof:placetype":"venue"
},
  "geometry": {"coordinates":[-86.815076,40.93443],"type":"Point"}
}