{
  "type": "Feature",
  "properties": {
    "iso:country":"US",
    "sg:address":"6318 W California Rd",
    "sg:city":"Fort Wayne",
    "sg:classifiers":[
        {
            "category":"Organizations",
            "subcategory":"Religious Organization",
            "type":"Services"
        }
    ],
    "sg:phone":"+1 260 484 7873",
    "sg:postcode":"46818",
    "sg:province":"IN",
    "sg:tags":[
        "church"
    ],
    "wof:name":"Suburban Bethlehem Lutheran",
    "wof:placetype":"venue"
},
  "geometry": {"coordinates":[-85.21146899999999,41.117604],"type":"Point"}
}