{
  "type": "Feature",
  "properties": {
    "iso:country":"US",
    "sg:address":"11915 E Washington St",
    "sg:city":"Indianapolis",
    "sg:classifiers":[
        {
            "category":"Recreation",
            "type":"Entertainment"
        }
    ],
    "sg:phone":"+1 317 890 0200",
    "sg:postcode":"46229",
    "sg:province":"IN",
    "sg:tags":[
        "martial",
        "arts",
        "instruction"
    ],
    "wof:name":"Impact Martial Arts",
    "wof:placetype":"venue"
},
  "geometry": {"coordinates":[-85.95511,39.776485],"type":"Point"}
}