{
  "type": "Feature",
  "properties": {
    "iso:country":"US",
    "sg:address":"3001 S 7th St",
    "sg:city":"Terre Haute",
    "sg:classifiers":[
        {
            "category":"Personal",
            "subcategory":"Barber",
            "type":"Services"
        }
    ],
    "sg:phone":"+1 812 234 3853",
    "sg:postcode":"47802",
    "sg:province":"IN",
    "sg:tags":[
        "shop"
    ],
    "wof:name":"Southland Barber Shop",
    "wof:placetype":"venue"
},
  "geometry": {"coordinates":[-87.406786,39.432808],"type":"Point"}
}