{
  "type": "Feature",
  "properties": {
    "addr:full":"3535 S Main St Elkhart IN 46517",
    "addr:housenumber":"3535",
    "addr:postcode":"46517",
    "addr:street":"S Main St",
    "iso:country":"US",
    "sg:address":"3535 S Main St",
    "sg:city":"Elkhart",
    "sg:classifiers":[
        {
            "category":"Restaurant",
            "type":"Food & Drink"
        }
    ],
    "sg:phone":"+1 574 293 8734",
    "sg:postcode":"46517",
    "sg:province":"IN",
    "wof:name":"Ponderosa Steakhouse",
    "wof:placetype":"venue"
},
  "geometry": {"coordinates":[-85.933831,41.645745],"type":"Point"}
}