{
  "type": "Feature",
  "properties": {
    "addr:full":"5320 Coldwater Rd Fort Wayne IN 46825",
    "addr:housenumber":"5320",
    "addr:postcode":"46825",
    "addr:street":"Coldwater Rd",
    "iso:country":"US",
    "sg:address":"5320 Coldwater Rd",
    "sg:city":"Fort Wayne",
    "sg:classifiers":[
        {
            "category":"Restaurant",
            "type":"Food & Drink"
        }
    ],
    "sg:phone":"+1 260 482 4040",
    "sg:postcode":"46825",
    "sg:province":"IN",
    "wof:name":"Yokohama Japanese Restaurant",
    "wof:placetype":"venue"
},
  "geometry": {"coordinates":[-85.135594,41.127299],"type":"Point"}
}