{
  "type": "Feature",
  "properties": {
    "iso:country":"US",
    "sg:address":"519 S Chestnut St",
    "sg:city":"Seymour",
    "sg:classifiers":[
        {
            "category":"Social Services",
            "subcategory":"Child Care",
            "type":"Services"
        }
    ],
    "sg:phone":"+1 812 523 7218",
    "sg:postcode":"47274",
    "sg:province":"IN",
    "sg:tags":[
        "day"
    ],
    "wof:name":"Home Child Care",
    "wof:placetype":"venue"
},
  "geometry": {"coordinates":[-85.88855599999999,38.952866],"type":"Point"}
}