{
  "type": "Feature",
  "properties": {
    "iso:country":"US",
    "sg:address":"1237 Northside Blvd",
    "sg:city":"South Bend",
    "sg:classifiers":[
        {
            "category":"Manufacturing",
            "subcategory":"Metals",
            "type":"Manufacturing & Wholesale Goods"
        }
    ],
    "sg:phone":"+1 574 234 3157",
    "sg:postcode":"46615",
    "sg:province":"IN",
    "sg:tags":[
        "valve"
    ],
    "sg:website":"www.sbcontrols.com",
    "wof:name":"South Bend Controls Inc",
    "wof:placetype":"venue"
},
  "geometry": {"coordinates":[-86.230944,41.662335],"type":"Point"}
}