{
  "type": "Feature",
  "properties": {
    "iso:country":"US",
    "sg:address":"3330 Vance Ave",
    "sg:city":"Fort Wayne",
    "sg:classifiers":[
        {
            "category":"Building & Trades",
            "subcategory":"Construction",
            "type":"Services"
        }
    ],
    "sg:phone":"+1 260 482 4026",
    "sg:postcode":"46805",
    "sg:province":"IN",
    "sg:tags":[
        "restoration",
        "cleaning",
        "patio",
        "deck"
    ],
    "wof:name":"S & R Pressurewashing",
    "wof:placetype":"venue"
},
  "geometry": {"coordinates":[-85.096912,41.104647],"type":"Point"}
}