{
  "type": "Feature",
  "properties": {
    "iso:country":"US",
    "sg:address":"4924 S Calhoun St",
    "sg:city":"Fort Wayne",
    "sg:classifiers":[
        {
            "category":"Food & Beverages",
            "subcategory":"Meat & Fish",
            "type":"Retail Goods"
        }
    ],
    "sg:phone":"+1 260 456 9009",
    "sg:postcode":"46807",
    "sg:province":"IN",
    "wof:name":"Albright's Meats & Deli",
    "wof:placetype":"venue"
},
  "geometry": {"coordinates":[-85.136951,41.039033],"type":"Point"}
}