{
  "type": "Feature",
  "properties": {
    "addr:full":"3 S Main St Whitestown IN 46075",
    "addr:housenumber":"3",
    "addr:postcode":"46075",
    "addr:street":"S Main St",
    "iso:country":"US",
    "sg:address":"3 S Main St",
    "sg:city":"Whitestown",
    "sg:classifiers":[
        {
            "category":"Government",
            "subcategory":"Fire Station",
            "type":"Public Place"
        }
    ],
    "sg:phone":"+1 317 769 3560",
    "sg:postcode":"46075",
    "sg:province":"IN",
    "sg:tags":[
        "department"
    ],
    "wof:name":"Worth Twp Fire Dept",
    "wof:placetype":"venue"
},
  "geometry": {"coordinates":[-86.34584700000001,39.99625],"type":"Point"}
}