{
  "type": "Feature",
  "properties": {
    "iso:country":"US",
    "sg:address":"810 S 17th St",
    "sg:city":"Vincennes",
    "sg:classifiers":[
        {
            "category":"Manufacturing",
            "subcategory":"Wood Products",
            "type":"Manufacturing & Wholesale Goods"
        }
    ],
    "sg:phone":"+1 812 882 2354",
    "sg:postcode":"47591",
    "sg:province":"IN",
    "wof:name":"Woodcraft Manufacturing Co",
    "wof:placetype":"venue"
},
  "geometry": {"coordinates":[-87.526385,38.662254],"type":"Point"}
}