{
  "type": "Feature",
  "properties": {
    "iso:country":"US",
    "sg:address":"1721 W Godfrey Ave",
    "sg:city":"Muncie",
    "sg:classifiers":[
        {
            "category":"Insurance",
            "subcategory":"Insurance Agent",
            "type":"Services"
        }
    ],
    "sg:phone":"+1 765 289 4177",
    "sg:postcode":"47304",
    "sg:province":"IN",
    "wof:name":"Rebco",
    "wof:placetype":"venue"
},
  "geometry": {"coordinates":[-85.407927,40.230345],"type":"Point"}
}