{
  "type": "Feature",
  "properties": {
    "iso:country":"US",
    "sg:address":"9443 N Aronson Rd",
    "sg:city":"Indianapolis",
    "sg:classifiers":[
        {
            "category":"Banks & Credit Unions",
            "subcategory":"Bank",
            "type":"Services"
        }
    ],
    "sg:phone":"+1 317 844 4601",
    "sg:postcode":"46240",
    "sg:province":"IN",
    "sg:tags":[
        "financing"
    ],
    "wof:name":"Beneficial Indiana Inc",
    "wof:placetype":"venue"
},
  "geometry": {"coordinates":[-86.110163,39.924876],"type":"Point"}
}