{
  "type": "Feature",
  "properties": {
    "addr:full":"19 S Washington St Knightstown IN 46148",
    "addr:housenumber":"19",
    "addr:postcode":"46148",
    "addr:street":"S Washington St",
    "iso:country":"US",
    "sg:address":"19 S Washington St",
    "sg:city":"Knightstown",
    "sg:classifiers":[
        {
            "category":"Professional",
            "subcategory":"Accounting & Tax Preparation",
            "type":"Services"
        }
    ],
    "sg:phone":"+1 765 345 7246",
    "sg:postcode":"46148",
    "sg:province":"IN",
    "sg:tags":[
        "return",
        "filing"
    ],
    "wof:name":"H & R Block Tax Svc",
    "wof:placetype":"venue"
},
  "geometry": {"coordinates":[-85.524716,39.795352],"type":"Point"}
}