{
  "type": "Feature",
  "properties": {
    "iso:country":"US",
    "sg:address":"50925 Clover Rd",
    "sg:city":"Granger",
    "sg:classifiers":[
        {
            "category":"Building & Trades",
            "subcategory":"Landscaping Services",
            "type":"Services"
        }
    ],
    "sg:phone":"+1 574 277 5774",
    "sg:postcode":"46530",
    "sg:province":"IN",
    "sg:tags":[
        "lawn",
        "maintenance",
        "grounds"
    ],
    "wof:name":"Labor Saver Lawn Svc Inc",
    "wof:placetype":"venue"
},
  "geometry": {"coordinates":[-86.156696,41.754491],"type":"Point"}
}