{
  "type": "Feature",
  "properties": {
    "addr:full":"2111 Main St Lafayette IN 47904",
    "addr:housenumber":"2111",
    "addr:postcode":"47904",
    "addr:street":"Main St",
    "iso:country":"US",
    "sg:address":"2111 Main St",
    "sg:city":"Lafayette",
    "sg:classifiers":[
        {
            "category":"Shopping",
            "subcategory":"Clothing, Apparel, & Fashions",
            "type":"Retail Goods"
        }
    ],
    "sg:phone":"+1 765 448 4744",
    "sg:postcode":"47904",
    "sg:province":"IN",
    "sg:tags":[
        "wig",
        "toupee",
        "hairpiece"
    ],
    "wof:name":"A Women's Place",
    "wof:placetype":"venue"
},
  "geometry": {"coordinates":[-86.87221700000001,40.411521],"type":"Point"}
}