{
  "type": "Feature",
  "properties": {
    "iso:country":"US",
    "sg:address":"806 E 66th St",
    "sg:city":"Indianapolis",
    "sg:classifiers":[
        {
            "category":"Personal",
            "subcategory":"Beauty Salon",
            "type":"Services"
        }
    ],
    "sg:phone":"+1 317 255 0147",
    "sg:postcode":"46220",
    "sg:province":"IN",
    "wof:name":"Face Place",
    "wof:placetype":"venue"
},
  "geometry": {"coordinates":[-86.14363899999999,39.876024],"type":"Point"}
}