{
  "type": "Feature",
  "properties": {
    "addr:full":"20011 Colfax St Lowell IN 46356",
    "addr:postcode":"20011;46356",
    "addr:street":"Colfax St",
    "iso:country":"US",
    "sg:address":"20011 Colfax St",
    "sg:city":"Lowell",
    "sg:classifiers":[
        {
            "category":"Government",
            "subcategory":"Office",
            "type":"Public Place"
        }
    ],
    "sg:phone":"+1 219 696 5050",
    "sg:postcode":"46356",
    "sg:province":"IN",
    "sg:tags":[
        "govt",
        "city"
    ],
    "wof:name":"Lowell Water Dept Pumping Plnt",
    "wof:placetype":"venue"
},
  "geometry": {"coordinates":[-87.41016,41.254983],"type":"Point"}
}