{
  "type": "Feature",
  "properties": {
    "iso:country":"US",
    "sg:address":"8624 South St",
    "sg:city":"Fishers",
    "sg:classifiers":[
        {
            "category":"Health Services",
            "subcategory":"Clinic",
            "type":"Services"
        }
    ],
    "sg:phone":"+1 317 842 0163",
    "sg:postcode":"46038",
    "sg:province":"IN",
    "sg:tags":[
        "home"
    ],
    "wof:name":"Mc Sherr Inc",
    "wof:placetype":"venue"
},
  "geometry": {"coordinates":[-86.016362,39.955755],"type":"Point"}
}