{
  "type": "Feature",
  "properties": {
    "iso:country":"US",
    "sg:address":"610 Main St",
    "sg:city":"Jasper",
    "sg:classifiers":[
        {
            "category":"Government",
            "subcategory":"Office",
            "type":"Public Place"
        }
    ],
    "sg:phone":"+1 812 482 9115",
    "sg:postcode":"47546",
    "sg:province":"IN",
    "sg:tags":[
        "county",
        "program",
        "adm"
    ],
    "wof:name":"Dubois County Tourism Comm",
    "wof:placetype":"venue"
},
  "geometry": {"coordinates":[-86.930728,38.392154],"type":"Point"}
}