{
  "type": "Feature",
  "properties": {
    "iso:country":"US",
    "sg:address":"154 W Hively Ave",
    "sg:city":"Elkhart",
    "sg:classifiers":[
        {
            "category":"Building & Trades",
            "subcategory":"Cleaning & Sanitation",
            "type":"Services"
        }
    ],
    "sg:phone":"+1 574 294 5834",
    "sg:postcode":"46517",
    "sg:province":"IN",
    "sg:tags":[
        "janitor"
    ],
    "wof:name":"Federal Cleaning Contractors",
    "wof:placetype":"venue"
},
  "geometry": {"coordinates":[-85.966352,41.659497],"type":"Point"}
}