{
  "type": "Feature",
  "properties": {
    "iso:country":"US",
    "sg:address":"1206 N Dearborn St",
    "sg:city":"Indianapolis",
    "sg:classifiers":[
        {
            "category":"Personal",
            "subcategory":"Beauty Salon",
            "type":"Services"
        }
    ],
    "sg:phone":"+1 317 638 4490",
    "sg:postcode":"46201",
    "sg:province":"IN",
    "wof:name":"Toni's Hair Salon",
    "wof:placetype":"venue"
},
  "geometry": {"coordinates":[-86.11114000000001,39.784866],"type":"Point"}
}