{
  "type": "Feature",
  "properties": {
    "iso:country":"US",
    "sg:address":"77 S Girls School Rd",
    "sg:city":"Indianapolis",
    "sg:classifiers":[
        {
            "category":"Health Services",
            "subcategory":"Optometrist",
            "type":"Services"
        }
    ],
    "sg:phone":"+1 317 486 9427",
    "sg:postcode":"46231",
    "sg:province":"IN",
    "wof:name":"Arnett Eye Ctr",
    "wof:placetype":"venue"
},
  "geometry": {"coordinates":[-86.288955,39.763372],"type":"Point"}
}