{
  "type": "Feature",
  "properties": {
    "iso:country":"US",
    "sg:address":"4946 W Willis Rd",
    "sg:city":"Georgetown",
    "sg:classifiers":[
        {
            "category":"Building & Trades",
            "subcategory":"Plumbing",
            "type":"Services"
        }
    ],
    "sg:phone":"+1 812 945 6185",
    "sg:postcode":"47122",
    "sg:province":"IN",
    "sg:tags":[
        "plumbing",
        "contractor"
    ],
    "wof:name":"D R Jones Plumbing Co",
    "wof:placetype":"venue"
},
  "geometry": {"coordinates":[-85.90294799999999,38.295822],"type":"Point"}
}