{
  "type": "Feature",
  "properties": {
    "iso:country":"US",
    "sg:address":"9529 Corporation Dr",
    "sg:city":"Indianapolis",
    "sg:classifiers":[
        {
            "category":"Shopping",
            "type":"Retail Goods"
        }
    ],
    "sg:phone":"+1 317 849 7727",
    "sg:postcode":"46256",
    "sg:province":"IN",
    "sg:tags":[
        "spa",
        "hot",
        "tub"
    ],
    "wof:name":"Carefree Spas",
    "wof:placetype":"venue"
},
  "geometry": {"coordinates":[-86.03567,39.918757],"type":"Point"}
}