{
  "type": "Feature",
  "properties": {
    "iso:country":"US",
    "sg:address":"303 State St",
    "sg:city":"Glenwood",
    "sg:classifiers":[
        {
            "category":"Organizations",
            "subcategory":"Religious Organization",
            "type":"Services"
        }
    ],
    "sg:phone":"+1 765 679 5437",
    "sg:postcode":"46133",
    "sg:province":"IN",
    "sg:tags":[
        "church"
    ],
    "wof:name":"Glenwood United Methodist Chr",
    "wof:placetype":"venue"
},
  "geometry": {"coordinates":[-85.307082,39.623573],"type":"Point"}
}