{
  "type": "Feature",
  "properties": {
    "iso:country":"US",
    "sg:address":"553 Erie Ave",
    "sg:city":"Logansport",
    "sg:classifiers":[
        {
            "category":"Personal",
            "subcategory":"Beauty Salon",
            "type":"Services"
        }
    ],
    "sg:phone":"+1 574 722 4030",
    "sg:postcode":"46947",
    "sg:province":"IN",
    "wof:name":"Secret Goddess Salon & Day Spa",
    "wof:placetype":"venue"
},
  "geometry": {"coordinates":[-86.363343,40.752653],"type":"Point"}
}