{
  "type": "Feature",
  "properties": {
    "addr:full":"18850 Calumet Ave Lowell IN 46356",
    "addr:housenumber":"18850",
    "addr:postcode":"46356",
    "addr:street":"Calumet Ave",
    "iso:country":"US",
    "sg:address":"18850 Calumet Ave",
    "sg:city":"Lowell",
    "sg:phone":"+1 219 696 7106",
    "sg:postcode":"46356",
    "sg:province":"IN",
    "sg:tags":[
        "farm",
        "corn"
    ],
    "wof:name":"Jerome Echterling",
    "wof:placetype":"venue"
},
  "geometry": {"coordinates":[-87.506381,41.27765],"type":"Point"}
}