{
  "type": "Feature",
  "properties": {
    "addr:full":"228 State Hwy 212 Michigan City IN 46360",
    "addr:housenumber":"228",
    "addr:postcode":"46360",
    "addr:street":"State Hwy 212",
    "iso:country":"US",
    "sg:address":"228 State Hwy 212",
    "sg:city":"Michigan City",
    "sg:classifiers":[
        {
            "category":"Retail",
            "subcategory":"Auto Repair",
            "type":"Services"
        }
    ],
    "sg:phone":"+1 219 874 6799",
    "sg:postcode":"46360",
    "sg:province":"IN",
    "sg:tags":[
        "repairing",
        "automobile"
    ],
    "wof:name":"Tony's Service Ctr",
    "wof:placetype":"venue"
},
  "geometry": {"coordinates":[-86.826402,41.741258],"type":"Point"}
}