{
  "type": "Feature",
  "properties": {
    "addr:full":"2350 Michigan Rd Madison IN 47250",
    "addr:housenumber":"2350",
    "addr:postcode":"47250",
    "addr:street":"Michigan Rd",
    "iso:country":"US",
    "sg:address":"2350 Michigan Rd",
    "sg:city":"Madison",
    "sg:classifiers":[
        {
            "category":"Autos & Motor Vehicles",
            "subcategory":"Auto Supplies",
            "type":"Retail Goods"
        }
    ],
    "sg:phone":"+1 812 265 3411",
    "sg:postcode":"47250",
    "sg:province":"IN",
    "sg:tags":[
        "tire"
    ],
    "wof:name":"Koehler Tire & Supply Inc",
    "wof:placetype":"venue"
},
  "geometry": {"coordinates":[-85.387266,38.771262],"type":"Point"}
}