{
  "type": "Feature",
  "properties": {
    "iso:country":"US",
    "sg:address":"15809 Westfield Blvd",
    "sg:city":"Carmel",
    "sg:classifiers":[
        {
            "category":"Food & Beverages",
            "subcategory":"Specialty",
            "type":"Retail Goods"
        }
    ],
    "sg:phone":"+1 317 896 5493",
    "sg:postcode":"46033",
    "sg:province":"IN",
    "wof:name":"Herbalife",
    "wof:placetype":"venue"
},
  "geometry": {"coordinates":[-86.127392,40.019309],"type":"Point"}
}