{
  "type": "Feature",
  "properties": {
    "iso:country":"US",
    "sg:address":"13102 W 500 N",
    "sg:city":"North Judson",
    "sg:classifiers":[
        {
            "category":"Farming",
            "subcategory":"Livestock Farm",
            "type":"Manufacturing & Wholesale Goods"
        }
    ],
    "sg:phone":"+1 219 843 7703",
    "sg:postcode":"46366",
    "sg:province":"IN",
    "sg:tags":[
        "feedlot",
        "hog",
        "corn",
        "or",
        "soybean"
    ],
    "wof:name":"James E Bogart",
    "wof:placetype":"venue"
},
  "geometry": {"coordinates":[-86.858373,41.128659],"type":"Point"}
}