{
  "type": "Feature",
  "properties": {
    "iso:country":"US",
    "sg:address":"6377 W 600 S",
    "sg:city":"Swayzee",
    "sg:classifiers":[
        {
            "category":"Wholesale",
            "subcategory":"Construction Materials",
            "type":"Manufacturing & Wholesale Goods"
        }
    ],
    "sg:phone":"+1 765 922 7285",
    "sg:postcode":"46986",
    "sg:province":"IN",
    "sg:tags":[
        "sand",
        "gravel"
    ],
    "wof:name":"IMI-North Accounting",
    "wof:placetype":"venue"
},
  "geometry": {"coordinates":[-85.796266,40.464949],"type":"Point"}
}