{
  "type": "Feature",
  "properties": {
    "addr:full":"207 N Sandy Creek Dr Seymour IN 47274",
    "addr:housenumber":"207",
    "addr:postcode":"47274",
    "addr:street":"N Sandy Creek Dr",
    "iso:country":"US",
    "sg:address":"207 N Sandy Creek Dr",
    "sg:city":"Seymour",
    "sg:classifiers":[
        {
            "category":"Travel",
            "subcategory":"Hotels & Motels",
            "type":"Entertainment"
        }
    ],
    "sg:phone":"+1 812 522 3523",
    "sg:postcode":"47274",
    "sg:province":"IN",
    "wof:name":"Knights Inn",
    "wof:placetype":"venue"
},
  "geometry": {"coordinates":[-85.848247,38.958477],"type":"Point"}
}