{
  "type": "Feature",
  "properties": {
    "addr:full":"8087 Randolph St Hobart IN 46342",
    "addr:housenumber":"8087",
    "addr:postcode":"46342",
    "addr:street":"Randolph St",
    "iso:country":"US",
    "sg:address":"8087 Randolph St",
    "sg:city":"Hobart",
    "sg:classifiers":[
        {
            "category":"Professional",
            "subcategory":"Accounting & Tax Preparation",
            "type":"Services"
        }
    ],
    "sg:phone":"+1 219 945 0462",
    "sg:postcode":"46342",
    "sg:province":"IN",
    "sg:tags":[
        "accountant"
    ],
    "wof:name":"Ramusack White CPA",
    "wof:placetype":"venue"
},
  "geometry": {"coordinates":[-87.23912300000001,41.476242],"type":"Point"}
}