{
  "type": "Feature",
  "properties": {
    "iso:country":"US",
    "sg:address":"7717 N 300 E",
    "sg:city":"Goodland",
    "sg:classifiers":[
        {
            "category":"Farming",
            "subcategory":"Livestock Farm",
            "type":"Manufacturing & Wholesale Goods"
        }
    ],
    "sg:phone":"+1 219 297 2273",
    "sg:postcode":"47948",
    "sg:province":"IN",
    "sg:tags":[
        "animal",
        "general"
    ],
    "wof:name":"Garrett Farms",
    "wof:placetype":"venue"
},
  "geometry": {"coordinates":[-87.267077,40.714613],"type":"Point"}
}