{
  "type": "Feature",
  "properties": {
    "iso:country":"US",
    "sg:address":"147 N 8th St",
    "sg:city":"Vincennes",
    "sg:classifiers":[
        {
            "category":"Government",
            "subcategory":"Office",
            "type":"Public Place"
        }
    ],
    "sg:phone":"+1 812 886 4094",
    "sg:postcode":"47591",
    "sg:province":"IN",
    "wof:name":"Wabash Valley Regl Community",
    "wof:placetype":"venue"
},
  "geometry": {"coordinates":[-87.526332,38.676048],"type":"Point"}
}