{
  "type": "Feature",
  "properties": {
    "iso:country":"US",
    "sg:address":"8410 Albert Dr",
    "sg:city":"Wadesville",
    "sg:classifiers":[
        {
            "category":"Manufacturing",
            "subcategory":"Apparel",
            "type":"Manufacturing & Wholesale Goods"
        }
    ],
    "sg:phone":"+1 812 985 9242",
    "sg:postcode":"47638",
    "sg:province":"IN",
    "sg:tags":[
        "building",
        "product",
        "exterior",
        "mfg"
    ],
    "wof:name":"Fashion Exterior Products",
    "wof:placetype":"venue"
},
  "geometry": {"coordinates":[-87.764517,38.07686],"type":"Point"}
}