{
  "type": "Feature",
  "properties": {
    "iso:country":"US",
    "sg:address":"1375 S State Rd 9",
    "sg:city":"Lagrange",
    "sg:classifiers":[
        {
            "category":"Autos & Motor Vehicles",
            "subcategory":"Automobile Sales",
            "type":"Retail Goods"
        }
    ],
    "sg:phone":"+1 260 463 3672",
    "sg:postcode":"46761",
    "sg:province":"IN",
    "sg:tags":[
        "car",
        "dealer"
    ],
    "wof:name":"Jamko Enterprises",
    "wof:placetype":"venue"
},
  "geometry": {"coordinates":[-85.415835,41.621364],"type":"Point"}
}