{
  "type": "Feature",
  "properties": {
    "addr:full":"3230 S Western Ave Marion IN 46953",
    "addr:housenumber":"3230",
    "addr:postcode":"46953",
    "addr:street":"S Western Ave",
    "iso:country":"US",
    "sg:address":"3230 S Western Ave",
    "sg:city":"Marion",
    "sg:classifiers":[
        {
            "category":"Wholesale",
            "subcategory":"Machinery & Supplies",
            "type":"Manufacturing & Wholesale Goods"
        }
    ],
    "sg:phone":"+1 765 662 3730",
    "sg:postcode":"46953",
    "sg:province":"IN",
    "sg:tags":[
        "salon",
        "beauty"
    ],
    "sg:website":"www.sallybeauty.com",
    "wof:name":"Sally Beauty Supply",
    "wof:placetype":"venue"
},
  "geometry": {"coordinates":[-85.67377,40.531524],"type":"Point"}
}