{
  "type": "Feature",
  "properties": {
    "iso:country":"US",
    "sg:address":"7983 E State Rd 28",
    "sg:city":"Elwood",
    "sg:classifiers":[
        {
            "category":"Building & Trades",
            "subcategory":"Landscaping Services",
            "type":"Services"
        }
    ],
    "sg:phone":"+1 765 552 6483",
    "sg:postcode":"46036",
    "sg:province":"IN",
    "sg:tags":[
        "tree"
    ],
    "wof:name":"Dukes Tree Svc",
    "wof:placetype":"venue"
},
  "geometry": {"coordinates":[-85.861106,40.276868],"type":"Point"}
}