{
  "type": "Feature",
  "properties": {
    "addr:full":"401 Sullivan St Hobart IN 46342",
    "addr:housenumber":"401",
    "addr:postcode":"46342",
    "addr:street":"Sullivan St",
    "iso:country":"US",
    "sg:address":"401 Sullivan St",
    "sg:city":"Hobart",
    "sg:classifiers":[
        {
            "category":"Retail",
            "subcategory":"Auto Repair",
            "type":"Services"
        }
    ],
    "sg:phone":"+1 219 942 8772",
    "sg:postcode":"46342",
    "sg:province":"IN",
    "sg:tags":[
        "truck"
    ],
    "wof:name":"Hobart Truck Svc",
    "wof:placetype":"venue"
},
  "geometry": {"coordinates":[-87.23315599999999,41.531002],"type":"Point"}
}