{
  "type": "Feature",
  "properties": {
    "iso:country":"US",
    "sg:address":"1619 E Markland Ave",
    "sg:city":"Kokomo",
    "sg:classifiers":[
        {
            "category":"Banks & Credit Unions",
            "subcategory":"Investment Brokerage",
            "type":"Services"
        }
    ],
    "sg:phone":"+1 765 868 7276",
    "sg:postcode":"46901",
    "sg:province":"IN",
    "sg:tags":[
        "funds",
        "mutual"
    ],
    "wof:name":"Edward Jones Co",
    "wof:placetype":"venue"
},
  "geometry": {"coordinates":[-86.11161,40.476575],"type":"Point"}
}