{
  "type": "Feature",
  "properties": {
    "iso:country":"US",
    "sg:address":"7775 State Rd 32 W",
    "sg:city":"Waynetown",
    "sg:classifiers":[
        {
            "category":"Restaurant",
            "type":"Food & Drink"
        }
    ],
    "sg:phone":"+1 765 234 2885",
    "sg:postcode":"47990",
    "sg:province":"IN",
    "wof:name":"A Country-A-Fair",
    "wof:placetype":"venue"
},
  "geometry": {"coordinates":[-87.047436,40.025124],"type":"Point"}
}