{
  "type": "Feature",
  "properties": {
    "iso:country":"US",
    "sg:address":"237 N 2nd St",
    "sg:city":"Decatur",
    "sg:classifiers":[
        {
            "category":"Organizations",
            "subcategory":"Religious Organization",
            "type":"Services"
        }
    ],
    "sg:phone":"+1 260 724 7777",
    "sg:postcode":"46733",
    "sg:province":"IN",
    "sg:tags":[
        "church"
    ],
    "wof:name":"Maranatha Baptist Church",
    "wof:placetype":"venue"
},
  "geometry": {"coordinates":[-84.924667,40.832142],"type":"Point"}
}