{
  "type": "Feature",
  "properties": {
    "addr:full":"303 Canal St Worthington IN 47471",
    "addr:housenumber":"303",
    "addr:postcode":"47471",
    "addr:street":"Canal St",
    "iso:country":"US",
    "sg:address":"303 Canal St",
    "sg:city":"Worthington",
    "sg:classifiers":[
        {
            "category":"Organizations",
            "subcategory":"Religious Organization",
            "type":"Services"
        }
    ],
    "sg:phone":"+1 812 875 2265",
    "sg:postcode":"47471",
    "sg:province":"IN",
    "sg:tags":[
        "church"
    ],
    "wof:name":"Assembly Of God Church",
    "wof:placetype":"venue"
},
  "geometry": {"coordinates":[-86.97489899999999,39.121606],"type":"Point"}
}