{
  "type": "Feature",
  "properties": {
    "iso:country":"US",
    "sg:address":"9567 Valparaiso Ct",
    "sg:city":"Indianapolis",
    "sg:classifiers":[
        {
            "category":"Banks & Credit Unions",
            "subcategory":"Bank",
            "type":"Services"
        }
    ],
    "sg:phone":"+1 317 871 4179",
    "sg:postcode":"46268",
    "sg:province":"IN",
    "sg:tags":[
        "loan",
        "real estate"
    ],
    "wof:name":"Horizon Mortgage",
    "wof:placetype":"venue"
},
  "geometry": {"coordinates":[-86.226366,39.925821],"type":"Point"}
}