{
  "type": "Feature",
  "properties": {
    "iso:country":"US",
    "sg:address":"3700 W Bethel Ave",
    "sg:city":"Muncie",
    "sg:classifiers":[
        {
            "category":"Banks & Credit Unions",
            "subcategory":"Bank",
            "type":"Services"
        }
    ],
    "sg:phone":"+1 765 289 2148",
    "sg:postcode":"47304",
    "sg:province":"IN",
    "sg:tags":[
        "loan"
    ],
    "sg:website":"www.wgefcu.org",
    "wof:name":"WGE Federal Credit Union",
    "wof:placetype":"venue"
},
  "geometry": {"coordinates":[-85.42900400000001,40.217727],"type":"Point"}
}