{
  "type": "Feature",
  "properties": {
    "iso:country":"US",
    "sg:address":"826 Lawrence Dr",
    "sg:city":"Fort Wayne",
    "sg:classifiers":[
        {
            "category":"Wholesale",
            "subcategory":"Painting Supplies",
            "type":"Manufacturing & Wholesale Goods"
        }
    ],
    "sg:phone":"+1 260 436 1854",
    "sg:postcode":"46804",
    "sg:province":"IN",
    "sg:tags":[
        "paint"
    ],
    "wof:name":"ICI Dulux Paint",
    "wof:placetype":"venue"
},
  "geometry": {"coordinates":[-85.207062,41.0775],"type":"Point"}
}