{
  "type": "Feature",
  "properties": {
    "iso:country":"US",
    "sg:address":"2118 Hamburg Pike",
    "sg:city":"Jeffersonville",
    "sg:classifiers":[
        {
            "category":"Organizations",
            "subcategory":"Religious Organization",
            "type":"Services"
        }
    ],
    "sg:phone":"+1 812 282 2453",
    "sg:postcode":"47130",
    "sg:province":"IN",
    "sg:tags":[
        "church"
    ],
    "wof:name":"Walnut Ridge Baptst Church SBC",
    "wof:placetype":"venue"
},
  "geometry": {"coordinates":[-85.746877,38.295783],"type":"Point"}
}