{
  "type": "Feature",
  "properties": {
    "iso:country":"US",
    "sg:address":"222 Bruceville Ave",
    "sg:city":"Bicknell",
    "sg:classifiers":[
        {
            "category":"Recreation",
            "type":"Entertainment"
        },
        {
            "category":"Social Services",
            "type":"Services"
        }
    ],
    "sg:phone":"+1 812 735 4382",
    "sg:postcode":"47512",
    "sg:province":"IN",
    "sg:tags":[
        "hall",
        "auditorium"
    ],
    "wof:name":"Wilson Community Center",
    "wof:placetype":"venue"
},
  "geometry": {"coordinates":[-87.31440000000001,38.771872],"type":"Point"}
}