{
  "type": "Feature",
  "properties": {
    "iso:country":"US",
    "sg:address":"6325 W 88th Pl",
    "sg:city":"Crown Point",
    "sg:classifiers":[
        {
            "category":"Building & Trades",
            "subcategory":"Construction",
            "type":"Services"
        }
    ],
    "sg:phone":"+1 219 365 7831",
    "sg:postcode":"46307",
    "sg:province":"IN",
    "sg:tags":[
        "roofing",
        "contractor"
    ],
    "wof:name":"Dillman Builder's",
    "wof:placetype":"venue"
},
  "geometry": {"coordinates":[-87.408625,41.45782],"type":"Point"}
}