{
  "type": "Feature",
  "properties": {
    "iso:country":"US",
    "sg:address":"4150 Edgemere Ct",
    "sg:city":"Indianapolis",
    "sg:classifiers":[
        {
            "category":"Professional",
            "type":"Services"
        }
    ],
    "sg:phone":"+1 317 542 1509",
    "sg:postcode":"46205",
    "sg:province":"IN",
    "sg:tags":[
        "establishment"
    ],
    "wof:name":"Stylin Divas",
    "wof:placetype":"venue"
},
  "geometry": {"coordinates":[-86.111299,39.832404],"type":"Point"}
}