{
  "type": "Feature",
  "properties": {
    "iso:country":"US",
    "sg:address":"1016 Country Club Rd",
    "sg:city":"Indianapolis",
    "sg:classifiers":[
        {
            "category":"Professional",
            "subcategory":"Lawyer & Legal Services",
            "type":"Services"
        }
    ],
    "sg:phone":"+1 317 273 6330",
    "sg:postcode":"46234",
    "sg:province":"IN",
    "sg:tags":[
        "attorney"
    ],
    "wof:name":"Ross & Kuhlman",
    "wof:placetype":"venue"
},
  "geometry": {"coordinates":[-86.30757199999999,39.780081],"type":"Point"}
}