{
  "type": "Feature",
  "properties": {
    "iso:country":"US",
    "sg:address":"7239 Fishers Landing",
    "sg:city":"Fishers",
    "sg:classifiers":[
        {
            "category":"Shopping",
            "subcategory":"Clothing, Apparel, & Fashions",
            "type":"Retail Goods"
        },
        {
            "category":"Shopping",
            "subcategory":"Bridal",
            "type":"Retail Goods"
        },
        {
            "category":"Shopping",
            "subcategory":"Discount & Variety Stores",
            "type":"Retail Goods"
        },
        {
            "category":"Shopping",
            "subcategory":"Used Merchandise",
            "type":"Retail Goods"
        }
    ],
    "sg:phone":"+1 317 570 4250",
    "sg:postcode":"46038",
    "sg:province":"IN",
    "sg:tags":[
        "wholesale",
        "clothing",
        "consignment",
        "vintage",
        "women's"
    ],
    "sg:website":"www.havilahsboutique.com",
    "wof:name":"Havilahs Resale Boutique",
    "wof:placetype":"venue"
},
  "geometry": {"coordinates":[-86.04343799999999,39.95605],"type":"Point"}
}