{
  "type": "Feature",
  "properties": {
    "addr:full":"6894 State Rd 56 Salem IN 47167",
    "addr:housenumber":"6894;56",
    "addr:postcode":"47167",
    "addr:street":"State Rd",
    "iso:country":"US",
    "sg:address":"6894 State Rd 56",
    "sg:city":"Salem",
    "sg:phone":"+1 812 883 2187",
    "sg:postcode":"47167",
    "sg:province":"IN",
    "sg:tags":[
        "farm",
        "corn",
        "soybean"
    ],
    "wof:name":"Brent Rosenbaum",
    "wof:placetype":"venue"
},
  "geometry": {"coordinates":[-86.21444,38.561397],"type":"Point"}
}