{
  "type": "Feature",
  "properties": {
    "iso:country":"US",
    "sg:address":"816 Mill Lake Rd",
    "sg:city":"Fort Wayne",
    "sg:classifiers":[
        {
            "category":"Health Services",
            "subcategory":"Chiropractor",
            "type":"Services"
        }
    ],
    "sg:phone":"+1 260 637 1548",
    "sg:postcode":"46845",
    "sg:province":"IN",
    "wof:name":"Health & Wellness Chiropractic",
    "wof:placetype":"venue"
},
  "geometry": {"coordinates":[-85.13195,41.180957],"type":"Point"}
}