{
  "type": "Feature",
  "properties": {
    "addr:full":"2300 E County Line Rd Indianapolis IN 46227",
    "addr:housenumber":"2300",
    "addr:postcode":"46227",
    "addr:street":"E County Line Rd",
    "iso:country":"US",
    "sg:address":"2300 E County Line Rd",
    "sg:city":"Indianapolis",
    "sg:classifiers":[
        {
            "category":"Banks & Credit Unions",
            "subcategory":"Bank",
            "type":"Services"
        }
    ],
    "sg:phone":"+1 317 859 6566",
    "sg:postcode":"46227",
    "sg:province":"IN",
    "sg:tags":[
        "cashing",
        "check"
    ],
    "wof:name":"Cash Quick Payday Loans",
    "wof:placetype":"venue"
},
  "geometry": {"coordinates":[-86.121112,39.635543],"type":"Point"}
}