{
  "type": "Feature",
  "properties": {
    "iso:country":"US",
    "sg:address":"400 N Maple St",
    "sg:city":"Martinsville",
    "sg:classifiers":[
        {
            "category":"Retail",
            "subcategory":"Animal Services",
            "type":"Services"
        }
    ],
    "sg:phone":"+1 765 349 1885",
    "sg:postcode":"46151",
    "sg:province":"IN",
    "wof:name":"Kritter Klipper",
    "wof:placetype":"venue"
},
  "geometry": {"coordinates":[-86.435232,39.43136],"type":"Point"}
}