{
  "type": "Feature",
  "properties": {
    "iso:country":"US",
    "sg:address":"1201 N Evans Ave",
    "sg:city":"Evansville",
    "sg:classifiers":[
        {
            "category":"Retail",
            "subcategory":"Repair Shop",
            "type":"Services"
        }
    ],
    "sg:phone":"+1 812 422 4491",
    "sg:postcode":"47711",
    "sg:province":"IN",
    "sg:tags":[
        "television",
        "radio"
    ],
    "wof:name":"J W Baize & Sons TV Sales",
    "wof:placetype":"venue"
},
  "geometry": {"coordinates":[-87.551973,37.99177],"type":"Point"}
}