{
  "type": "Feature",
  "properties": {
    "addr:full":"705 W Pike St Vevay IN 47043",
    "addr:housenumber":"705",
    "addr:postcode":"47043",
    "addr:street":"W Pike St",
    "iso:country":"US",
    "sg:address":"705 W Pike St",
    "sg:city":"Vevay",
    "sg:classifiers":[
        {
            "category":"Building & Trades",
            "subcategory":"Landscaping Services",
            "type":"Services"
        }
    ],
    "sg:phone":"+1 812 427 2418",
    "sg:postcode":"47043",
    "sg:province":"IN",
    "wof:name":"Pettits Mowing Service",
    "wof:placetype":"venue"
},
  "geometry": {"coordinates":[-85.073723,38.744615],"type":"Point"}
}