{
  "type": "Feature",
  "properties": {
    "iso:country":"US",
    "sg:address":"8150 Rockville Rd",
    "sg:city":"Indianapolis",
    "sg:classifiers":[
        {
            "category":"Banks & Credit Unions",
            "subcategory":"Bank",
            "type":"Services"
        }
    ],
    "sg:phone":"+1 317 271 7921",
    "sg:postcode":"46214",
    "sg:province":"IN",
    "wof:name":"Fifth Third Bank",
    "wof:placetype":"venue"
},
  "geometry": {"coordinates":[-86.30619,39.764209],"type":"Point"}
}