{
  "type": "Feature",
  "properties": {
    "iso:country":"US",
    "sg:address":"3326 E Main St",
    "sg:city":"Richmond",
    "sg:classifiers":[
        {
            "category":"Insurance",
            "subcategory":"Insurance Agent",
            "type":"Services"
        }
    ],
    "sg:phone":"+1 765 965 7800",
    "sg:postcode":"47374",
    "sg:province":"IN",
    "wof:name":"Western-Southern Life Ins Co",
    "wof:placetype":"venue"
},
  "geometry": {"coordinates":[-84.856348,39.830964],"type":"Point"}
}