{
  "type": "Feature",
  "properties": {
    "iso:country":"US",
    "sg:address":"406 Pearl St",
    "sg:city":"New Albany",
    "sg:classifiers":[
        {
            "category":"Insurance",
            "subcategory":"Insurance Agent",
            "type":"Services"
        }
    ],
    "sg:phone":"+1 812 945 6993",
    "sg:postcode":"47150",
    "sg:province":"IN",
    "wof:name":"Equitable Reserve",
    "wof:placetype":"venue"
},
  "geometry": {"coordinates":[-85.823478,38.287082],"type":"Point"}
}