{
  "type": "Feature",
  "properties": {
    "iso:country":"US",
    "sg:address":"10818 Coldwater Rd",
    "sg:city":"Fort Wayne",
    "sg:classifiers":[
        {
            "category":"Professional",
            "subcategory":"Management & Consulting",
            "type":"Services"
        }
    ],
    "sg:phone":"+1 260 637 9630",
    "sg:postcode":"46845",
    "sg:province":"IN",
    "wof:name":"Shippy Gary E",
    "wof:placetype":"venue"
},
  "geometry": {"coordinates":[-85.13218000000001,41.181738],"type":"Point"}
}