{
  "type": "Feature",
  "properties": {
    "iso:country":"US",
    "sg:address":"6354 State Rd 46",
    "sg:city":"Terre Haute",
    "sg:classifiers":[
        {
            "category":"Building & Trades",
            "subcategory":"Construction",
            "type":"Services"
        }
    ],
    "sg:phone":"+1 812 894 3209",
    "sg:postcode":"47802",
    "sg:province":"IN",
    "sg:tags":[
        "carpentry",
        "contractor"
    ],
    "wof:name":"Joshua Group Inc",
    "wof:placetype":"venue"
},
  "geometry": {"coordinates":[-87.313566,39.3969],"type":"Point"}
}