{
  "type": "Feature",
  "properties": {
    "iso:country":"US",
    "sg:address":"211 S Main St",
    "sg:city":"Zionsville",
    "sg:classifiers":[
        {
            "category":"Shopping",
            "type":"Retail Goods"
        }
    ],
    "sg:phone":"+1 317 733 8426",
    "sg:postcode":"46077",
    "sg:province":"IN",
    "sg:tags":[
        "art",
        "gallery",
        "dealer"
    ],
    "wof:name":"Art In Hand Gallery",
    "wof:placetype":"venue"
},
  "geometry": {"coordinates":[-86.261154,39.949181],"type":"Point"}
}