{
  "type": "Feature",
  "properties": {
    "iso:country":"US",
    "sg:address":"3112 Easy St",
    "sg:city":"Kokomo",
    "sg:classifiers":[
        {
            "category":"Home & Garden",
            "subcategory":"Building Materials",
            "type":"Retail Goods"
        }
    ],
    "sg:phone":"+1 765 453 0500",
    "sg:postcode":"46902",
    "sg:province":"IN",
    "sg:tags":[
        "paint"
    ],
    "wof:name":"Gooch & Co Distributing Inc",
    "wof:placetype":"venue"
},
  "geometry": {"coordinates":[-86.128743,40.450832],"type":"Point"}
}