{
  "type": "Feature",
  "properties": {
    "iso:country":"US",
    "sg:address":"1304 N Broadway Ave",
    "sg:city":"Muncie",
    "sg:classifiers":[
        {
            "category":"Manufacturing",
            "subcategory":"Printing",
            "type":"Manufacturing & Wholesale Goods"
        }
    ],
    "sg:phone":"+1 765 741 0037",
    "sg:postcode":"47303",
    "sg:province":"IN",
    "sg:tags":[
        "newspaper"
    ],
    "wof:name":"Muncie Times",
    "wof:placetype":"venue"
},
  "geometry": {"coordinates":[-85.37408000000001,40.205552],"type":"Point"}
}