{
  "type": "Feature",
  "properties": {
    "iso:country":"US",
    "sg:address":"39 W Mill Rd",
    "sg:city":"Shelbyville",
    "sg:classifiers":[
        {
            "category":"Professional",
            "subcategory":"Management & Consulting",
            "type":"Services"
        }
    ],
    "sg:phone":"+1 317 501 7290",
    "sg:postcode":"46176",
    "sg:province":"IN",
    "wof:name":"Design Rsurces Consulting Svcs",
    "wof:placetype":"venue"
},
  "geometry": {"coordinates":[-85.780498,39.624719],"type":"Point"}
}