{
  "type": "Feature",
  "properties": {
    "iso:country":"US",
    "sg:address":"8220 Brookville Rd",
    "sg:city":"Indianapolis",
    "sg:classifiers":[
        {
            "category":"Restaurant",
            "type":"Food & Drink"
        }
    ],
    "sg:phone":"+1 317 354 0690",
    "sg:postcode":"46239",
    "sg:province":"IN",
    "sg:tags":[
        "shop",
        "coffee"
    ],
    "wof:name":"Best Coffee For Miles",
    "wof:placetype":"venue"
},
  "geometry": {"coordinates":[-86.012227,39.747075],"type":"Point"}
}