{
  "type": "Feature",
  "properties": {
    "addr:full":"8708 Hunters Knoll Run Fort Wayne IN 46825",
    "addr:housenumber":"8708",
    "addr:postcode":"46825",
    "addr:street":"Hunters Knoll Run",
    "iso:country":"US",
    "sg:address":"8708 Hunters Knoll Run",
    "sg:city":"Fort Wayne",
    "sg:classifiers":[
        {
            "category":"Building & Trades",
            "subcategory":"Construction",
            "type":"Services"
        }
    ],
    "sg:phone":"+1 260 489 9287",
    "sg:postcode":"46825",
    "sg:province":"IN",
    "sg:tags":[
        "dry wall",
        "contractor"
    ],
    "wof:name":"H W Hartman Drywall",
    "wof:placetype":"venue"
},
  "geometry": {"coordinates":[-85.147542,41.159789],"type":"Point"}
}