{
  "type": "Feature",
  "properties": {
    "iso:country":"US",
    "sg:address":"4101 N Wheeling Ave",
    "sg:city":"Muncie",
    "sg:classifiers":[
        {
            "category":"Restaurant",
            "type":"Food & Drink"
        }
    ],
    "sg:phone":"+1 765 289 2366",
    "sg:postcode":"47304",
    "sg:province":"IN",
    "wof:name":"Pizza King",
    "wof:placetype":"venue"
},
  "geometry": {"coordinates":[-85.40773900000001,40.227731],"type":"Point"}
}