{
  "type": "Feature",
  "properties": {
    "iso:country":"US",
    "sg:address":"3506 N Main St",
    "sg:city":"Mishawaka",
    "sg:classifiers":[
        {
            "category":"Professional",
            "subcategory":"Secretarial Services",
            "type":"Services"
        }
    ],
    "sg:phone":"+1 574 257 4312",
    "sg:postcode":"46545",
    "sg:province":"IN",
    "sg:tags":[
        "transcription",
        "medical"
    ],
    "wof:name":"Datamed Transcription Inc",
    "wof:placetype":"venue"
},
  "geometry": {"coordinates":[-86.181736,41.691276],"type":"Point"}
}