{
  "type": "Feature",
  "properties": {
    "iso:country":"US",
    "sg:address":"5424 E US Hwy 20",
    "sg:city":"Rolling Prairie",
    "sg:classifiers":[
        {
            "category":"Retail",
            "subcategory":"Veterinary Services",
            "type":"Services"
        }
    ],
    "sg:phone":"+1 219 778 4458",
    "sg:postcode":"46371",
    "sg:province":"IN",
    "sg:tags":[
        "veterinarian"
    ],
    "wof:name":"New Prairie Veterinary Svc",
    "wof:placetype":"venue"
},
  "geometry": {"coordinates":[-86.593395,41.67274],"type":"Point"}
}