{
  "type": "Feature",
  "properties": {
    "iso:country":"US",
    "sg:address":"1510 N Cullen Ave",
    "sg:city":"Evansville",
    "sg:classifiers":[
        {
            "category":"Professional",
            "subcategory":"Advertising",
            "type":"Services"
        }
    ],
    "sg:phone":"+1 812 474 0795",
    "sg:postcode":"47715",
    "sg:province":"IN",
    "wof:name":"Evansville Cable Advertising",
    "wof:placetype":"venue"
},
  "geometry": {"coordinates":[-87.486183,37.989605],"type":"Point"}
}