{
  "type": "Feature",
  "properties": {
    "iso:country":"US",
    "sg:address":"10334 Springstone Rd",
    "sg:city":"Mc Cordsville",
    "sg:classifiers":[
        {
            "category":"Autos & Motor Vehicles",
            "subcategory":"Automobile Sales",
            "type":"Retail Goods"
        }
    ],
    "sg:phone":"+1 317 335 2479",
    "sg:postcode":"46055",
    "sg:province":"IN",
    "sg:tags":[
        "car",
        "dealer"
    ],
    "wof:name":"Gainey Inc",
    "wof:placetype":"venue"
},
  "geometry": {"coordinates":[-85.927515,39.937394],"type":"Point"}
}