{
  "type": "Feature",
  "properties": {
    "addr:full":"1424 N Salisbury St West Lafayette IN 47906",
    "addr:housenumber":"1424",
    "addr:postcode":"47906",
    "addr:street":"N Salisbury St",
    "iso:country":"US",
    "sg:address":"1424 N Salisbury St",
    "sg:city":"West Lafayette",
    "sg:classifiers":[
        {
            "category":"Professional",
            "subcategory":"Business Services",
            "type":"Services"
        }
    ],
    "sg:phone":"+1 765 463 3411",
    "sg:postcode":"47906",
    "sg:province":"IN",
    "wof:name":"Lynn Zachmanoglou Intr Design",
    "wof:placetype":"venue"
},
  "geometry": {"coordinates":[-86.908362,40.439727],"type":"Point"}
}