{
  "type": "Feature",
  "properties": {
    "iso:country":"US",
    "sg:address":"557 W Broadway St",
    "sg:city":"Shelburn",
    "sg:classifiers":[
        {
            "category":"Health Services",
            "subcategory":"Doctor",
            "type":"Services"
        }
    ],
    "sg:phone":"+1 812 397 2440",
    "sg:postcode":"47879",
    "sg:province":"IN",
    "sg:tags":[
        "physician",
        "surgeon"
    ],
    "wof:name":"Shelburn Medical Clinic",
    "wof:placetype":"venue"
},
  "geometry": {"coordinates":[-87.401678,39.181754],"type":"Point"}
}