{
  "type": "Feature",
  "properties": {
    "iso:country":"US",
    "sg:address":"5225 W 10th St",
    "sg:city":"Indianapolis",
    "sg:classifiers":[
        {
            "category":"Wholesale",
            "subcategory":"Office Equipment",
            "type":"Manufacturing & Wholesale Goods"
        }
    ],
    "sg:phone":"+1 317 248 1242",
    "sg:postcode":"46224",
    "sg:province":"IN",
    "sg:tags":[
        "register",
        "cash",
        "supply"
    ],
    "wof:name":"American Electronic Registers",
    "wof:placetype":"venue"
},
  "geometry": {"coordinates":[-86.250305,39.779899],"type":"Point"}
}