{
  "type": "Feature",
  "properties": {
    "iso:country":"US",
    "sg:address":"4179 Stellhorn Rd",
    "sg:city":"Fort Wayne",
    "sg:classifiers":[
        {
            "category":"Health Services",
            "subcategory":"Nursing And Care Facility",
            "type":"Services"
        }
    ],
    "sg:phone":"+1 260 485 2647",
    "sg:postcode":"46815",
    "sg:province":"IN",
    "sg:tags":[
        "adult"
    ],
    "wof:name":"Geoffrey's House",
    "wof:placetype":"venue"
},
  "geometry": {"coordinates":[-85.089305,41.119615],"type":"Point"}
}