{
  "type": "Feature",
  "properties": {
    "iso:country":"US",
    "sg:address":"620 W Huntington St",
    "sg:city":"Montpelier",
    "sg:classifiers":[
        {
            "category":"Food & Beverages",
            "subcategory":"Groceries & Convenience Stores",
            "type":"Retail Goods"
        }
    ],
    "sg:phone":"+1 765 728 2825",
    "sg:postcode":"47359",
    "sg:province":"IN",
    "wof:name":"Pit Stop Deli",
    "wof:placetype":"venue"
},
  "geometry": {"coordinates":[-85.287871,40.554848],"type":"Point"}
}