{
  "type": "Feature",
  "properties": {
    "iso:country":"US",
    "sg:address":"52200 Chatem Ct",
    "sg:city":"Granger",
    "sg:classifiers":[
        {
            "category":"Professional",
            "subcategory":"Business Services",
            "type":"Services"
        }
    ],
    "sg:phone":"+1 574 271 1380",
    "sg:postcode":"46530",
    "sg:province":"IN",
    "sg:tags":[
        "appraiser"
    ],
    "wof:name":"A A Antique Buyers",
    "wof:placetype":"venue"
},
  "geometry": {"coordinates":[-86.187167,41.73502],"type":"Point"}
}