{
  "type": "Feature",
  "properties": {
    "iso:country":"US",
    "sg:address":"1603 E Washington St",
    "sg:city":"Indianapolis",
    "sg:classifiers":[
        {
            "category":"Autos & Motor Vehicles",
            "subcategory":"Automobile Sales",
            "type":"Retail Goods"
        }
    ],
    "sg:phone":"+1 317 635 8179",
    "sg:postcode":"46201",
    "sg:province":"IN",
    "sg:tags":[
        "car",
        "used"
    ],
    "wof:name":"Indiana Auto Credit",
    "wof:placetype":"venue"
},
  "geometry": {"coordinates":[-86.13211,39.767222],"type":"Point"}
}