{
  "type": "Feature",
  "properties": {
    "iso:country":"US",
    "sg:address":"629 S West St",
    "sg:city":"Shelbyville",
    "sg:classifiers":[
        {
            "category":"Organizations",
            "subcategory":"Religious Organization",
            "type":"Services"
        }
    ],
    "sg:phone":"+1 317 398 4339",
    "sg:postcode":"46176",
    "sg:province":"IN",
    "sg:tags":[
        "church"
    ],
    "wof:name":"West St United Methodist Chr",
    "wof:placetype":"venue"
},
  "geometry": {"coordinates":[-85.781814,39.518554],"type":"Point"}
}