{
  "type": "Feature",
  "properties": {
    "iso:country":"US",
    "sg:address":"706 E 5th St",
    "sg:city":"Fowler",
    "sg:classifiers":[
        {
            "category":"Government",
            "subcategory":"Court House",
            "type":"Public Place"
        }
    ],
    "sg:phone":"+1 765 884 0370",
    "sg:postcode":"47944",
    "sg:province":"IN",
    "sg:tags":[
        "county"
    ],
    "wof:name":"Benton County Circuit Ct Judge",
    "wof:placetype":"venue"
},
  "geometry": {"coordinates":[-87.316361,40.617639],"type":"Point"}
}