{
  "type": "Feature",
  "properties": {
    "iso:country":"US",
    "sg:address":"2274 E 116th St",
    "sg:city":"Carmel",
    "sg:classifiers":[
        {
            "category":"Real Estate",
            "subcategory":"Real Estate Agent",
            "type":"Services"
        }
    ],
    "sg:phone":"+1 317 846 7751",
    "sg:postcode":"46032",
    "sg:province":"IN",
    "wof:name":"Marian A Hamaker",
    "wof:placetype":"venue"
},
  "geometry": {"coordinates":[-86.11696600000001,39.956731],"type":"Point"}
}