{
  "type": "Feature",
  "properties": {
    "addr:full":"110 N Main St Columbia City IN 46725",
    "addr:housenumber":"110",
    "addr:postcode":"46725",
    "addr:street":"N Main St",
    "iso:country":"US",
    "sg:address":"110 N Main St",
    "sg:city":"Columbia City",
    "sg:classifiers":[
        {
            "category":"Organizations",
            "subcategory":"Religious Organization",
            "type":"Services"
        }
    ],
    "sg:phone":"+1 260 244 4763",
    "sg:postcode":"46725",
    "sg:province":"IN",
    "sg:tags":[
        "church"
    ],
    "wof:name":"Church Of Jesus Christ Of Lds",
    "wof:placetype":"venue"
},
  "geometry": {"coordinates":[-85.488332,41.158024],"type":"Point"}
}