{
  "type": "Feature",
  "properties": {
    "addr:full":"1507 State Rd 68 New Harmony IN 47631",
    "addr:housenumber":"1507;68",
    "addr:postcode":"47631",
    "addr:street":"State Rd",
    "iso:country":"US",
    "sg:address":"1507 State Rd 68",
    "sg:city":"New Harmony",
    "sg:classifiers":[
        {
            "category":"Farming",
            "subcategory":"Livestock Farm",
            "type":"Manufacturing & Wholesale Goods"
        }
    ],
    "sg:phone":"+1 812 682 4078",
    "sg:postcode":"47631",
    "sg:province":"IN",
    "sg:tags":[
        "hog",
        "or",
        "feedlot"
    ],
    "wof:name":"Harry Crumbacher",
    "wof:placetype":"venue"
},
  "geometry": {"coordinates":[-87.89613300000001,38.139709],"type":"Point"}
}