{
  "type": "Feature",
  "properties": {
    "addr:full":"8202 Clearvista Pkwy Indianapolis IN 46256",
    "addr:housenumber":"8202",
    "addr:postcode":"46256",
    "addr:street":"Clearvista Pkwy",
    "iso:country":"US",
    "sg:address":"8202 Clearvista Pkwy",
    "sg:city":"Indianapolis",
    "sg:classifiers":[
        {
            "category":"Food & Beverages",
            "subcategory":"Groceries & Convenience Stores",
            "type":"Retail Goods"
        }
    ],
    "sg:phone":"+1 317 577 0035",
    "sg:postcode":"46256",
    "sg:province":"IN",
    "sg:tags":[
        "grocer"
    ],
    "wof:name":"Eighty Second Street Mrktplc",
    "wof:placetype":"venue"
},
  "geometry": {"coordinates":[-86.039659,39.906541],"type":"Point"}
}