{
  "type": "Feature",
  "properties": {
    "iso:country":"US",
    "sg:address":"508 E Main St",
    "sg:city":"Brownsburg",
    "sg:classifiers":[
        {
            "category":"Autos & Motor Vehicles",
            "subcategory":"Auto Supplies",
            "type":"Retail Goods"
        }
    ],
    "sg:phone":"+1 317 858 0775",
    "sg:postcode":"46112",
    "sg:province":"IN",
    "sg:tags":[
        "automobile",
        "parts"
    ],
    "wof:name":"Autozone",
    "wof:placetype":"venue"
},
  "geometry": {"coordinates":[-86.390005,39.841138],"type":"Point"}
}