{
  "type": "Feature",
  "properties": {
    "addr:full":"2236 S 225 W Franklin IN 46131",
    "addr:housenumber":"2236;225",
    "addr:postcode":"46131",
    "addr:street":"S;W Franklin",
    "iso:country":"US",
    "sg:address":"2236 S 225 W",
    "sg:city":"Franklin",
    "sg:classifiers":[
        {
            "category":"Banks & Credit Unions",
            "subcategory":"Bank",
            "type":"Services"
        }
    ],
    "sg:phone":"+1 317 878 5266",
    "sg:postcode":"46131",
    "sg:province":"IN",
    "sg:tags":[
        "mortgage"
    ],
    "wof:name":"First Republic Mortgage",
    "wof:placetype":"venue"
},
  "geometry": {"coordinates":[-86.14354299999999,39.441508],"type":"Point"}
}