{
  "type": "Feature",
  "properties": {
    "iso:country":"US",
    "sg:address":"1889 State Rd 128",
    "sg:city":"Alexandria",
    "sg:classifiers":[
        {
            "category":"Organizations",
            "subcategory":"Religious Organization",
            "type":"Services"
        }
    ],
    "sg:phone":"+1 765 754 8378",
    "sg:postcode":"46001",
    "sg:province":"IN",
    "wof:name":"Alexandria Church Of Christ",
    "wof:placetype":"venue"
},
  "geometry": {"coordinates":[-85.692624,40.21967],"type":"Point"}
}