{
  "type": "Feature",
  "properties": {
    "iso:country":"US",
    "sg:address":"902 E 66th St",
    "sg:city":"Indianapolis",
    "sg:classifiers":[
        {
            "category":"Professional",
            "subcategory":"Management & Consulting",
            "type":"Services"
        }
    ],
    "sg:phone":"+1 317 472 0931",
    "sg:postcode":"46220",
    "sg:province":"IN",
    "sg:tags":[
        "consultant"
    ],
    "wof:name":"NCB Consulting",
    "wof:placetype":"venue"
},
  "geometry": {"coordinates":[-86.142245,39.875958],"type":"Point"}
}