{
  "type": "Feature",
  "properties": {
    "iso:country":"US",
    "sg:address":"8030 Baptist Church Rd SE",
    "sg:city":"Elizabeth",
    "sg:classifiers":[
        {
            "category":"Organizations",
            "subcategory":"Religious Organization",
            "type":"Services"
        }
    ],
    "sg:phone":"+1 812 969 2536",
    "sg:postcode":"47117",
    "sg:province":"IN",
    "sg:tags":[
        "church"
    ],
    "wof:name":"First Baptist Church",
    "wof:placetype":"venue"
},
  "geometry": {"coordinates":[-85.965672,38.083872],"type":"Point"}
}