{
  "type": "Feature",
  "properties": {
    "iso:country":"US",
    "sg:address":"17776 State Rd 23",
    "sg:city":"South Bend",
    "sg:classifiers":[
        {
            "category":"Shopping",
            "subcategory":"Hobbies, Toys, & Games",
            "type":"Retail Goods"
        }
    ],
    "sg:phone":"+1 574 272 6792",
    "sg:postcode":"46635",
    "sg:province":"IN",
    "wof:name":"Eves Creations Inc",
    "wof:placetype":"venue"
},
  "geometry": {"coordinates":[-86.21114,41.702674],"type":"Point"}
}