{
  "type": "Feature",
  "properties": {
    "iso:country":"US",
    "sg:address":"8215 Pollack Ave",
    "sg:city":"Evansville",
    "sg:classifiers":[
        {
            "category":"Recreation",
            "type":"Entertainment"
        }
    ],
    "sg:phone":"+1 812 853 3956",
    "sg:postcode":"47715",
    "sg:province":"IN",
    "sg:tags":[
        "historical"
    ],
    "sg:website":"www.angelmounds.org",
    "wof:name":"Angel Mounds State Historic",
    "wof:placetype":"venue"
},
  "geometry": {"coordinates":[-87.453363,37.947695],"type":"Point"}
}