{
  "type": "Feature",
  "properties": {
    "iso:country":"US",
    "sg:address":"65201 Dogwood Rd",
    "sg:city":"Wakarusa",
    "sg:classifiers":[
        {
            "category":"Farming",
            "subcategory":"Farm",
            "type":"Manufacturing & Wholesale Goods"
        }
    ],
    "sg:phone":"+1 574 633 4777",
    "sg:postcode":"46573",
    "sg:province":"IN",
    "sg:tags":[
        "crop",
        "general"
    ],
    "wof:name":"Myers Orvil",
    "wof:placetype":"venue"
},
  "geometry": {"coordinates":[-86.11817600000001,41.538648],"type":"Point"}
}