{
  "type": "Feature",
  "properties": {
    "iso:country":"US",
    "sg:address":"323 W Graham St",
    "sg:city":"Kentland",
    "sg:classifiers":[
        {
            "category":"Manufacturing",
            "subcategory":"Rubber & Plastics",
            "type":"Manufacturing & Wholesale Goods"
        }
    ],
    "sg:phone":"+1 219 474 5709",
    "sg:postcode":"47951",
    "sg:province":"IN",
    "sg:website":"www.imageplastics.com",
    "wof:name":"Image Plastics LTD",
    "wof:placetype":"venue"
},
  "geometry": {"coordinates":[-87.45822800000001,40.769308],"type":"Point"}
}