{
  "type": "Feature",
  "properties": {
    "addr:full":"8760 Southeastern Ave Indianapolis IN 46239",
    "addr:housenumber":"8760",
    "addr:postcode":"46239",
    "addr:street":"Southeastern Ave",
    "iso:country":"US",
    "sg:address":"8760 Southeastern Ave",
    "sg:city":"Indianapolis",
    "sg:classifiers":[
        {
            "category":"Shopping",
            "subcategory":"Department Store",
            "type":"Retail Goods"
        }
    ],
    "sg:phone":"+1 317 862 7085",
    "sg:postcode":"46239",
    "sg:province":"IN",
    "sg:tags":[
        "variety"
    ],
    "sg:website":"http://www.dollargeneral.com",
    "wof:name":"Dollar General",
    "wof:placetype":"venue"
},
  "geometry": {"coordinates":[-86.011442,39.705483],"type":"Point"}
}