{
  "type": "Feature",
  "properties": {
    "iso:country":"US",
    "sg:address":"2444 S West St",
    "sg:city":"Indianapolis",
    "sg:classifiers":[
        {
            "category":"Freight",
            "type":"Transportation"
        }
    ],
    "sg:phone":"+1 317 788 8406",
    "sg:postcode":"46225",
    "sg:province":"IN",
    "sg:tags":[
        "trucking"
    ],
    "wof:name":"Werner Enterprises Inc",
    "wof:placetype":"venue"
},
  "geometry": {"coordinates":[-86.168498,39.737067],"type":"Point"}
}