{
  "type": "Feature",
  "properties": {
    "iso:country":"US",
    "sg:address":"315 E Market St",
    "sg:city":"Warsaw",
    "sg:classifiers":[
        {
            "category":"Autos & Motor Vehicles",
            "subcategory":"Automobile Sales",
            "type":"Retail Goods"
        }
    ],
    "sg:phone":"+1 574 267 3659",
    "sg:postcode":"46580",
    "sg:province":"IN",
    "sg:tags":[
        "car",
        "dealer"
    ],
    "wof:name":"N & J Auto Sales",
    "wof:placetype":"venue"
},
  "geometry": {"coordinates":[-85.85275799999999,41.237164],"type":"Point"}
}