{
  "type": "Feature",
  "properties": {
    "iso:country":"US",
    "sg:address":"120 N Maple St",
    "sg:city":"Orleans",
    "sg:classifiers":[
        {
            "category":"Retail",
            "subcategory":"Animal Services",
            "type":"Services"
        }
    ],
    "sg:phone":"+1 812 865 4494",
    "sg:postcode":"47452",
    "sg:province":"IN",
    "wof:name":"Dog Gone Salon",
    "wof:placetype":"venue"
},
  "geometry": {"coordinates":[-86.452691,38.663009],"type":"Point"}
}