{
  "type": "Feature",
  "properties": {
    "addr:full":"6106 Riverview Dr Indianapolis IN 46208",
    "addr:housenumber":"6106",
    "addr:postcode":"46208",
    "addr:street":"Riverview Dr",
    "iso:country":"US",
    "sg:address":"6106 Riverview Dr",
    "sg:city":"Indianapolis",
    "sg:classifiers":[
        {
            "category":"Real Estate",
            "subcategory":"Architect",
            "type":"Services"
        }
    ],
    "sg:phone":"+1 317 441 6964",
    "sg:postcode":"46208",
    "sg:province":"IN",
    "sg:tags":[
        "architects'",
        "specification",
        "builders'",
        "construction",
        "architectural"
    ],
    "wof:name":"Fusion By Design, Incorporated",
    "wof:placetype":"venue"
},
  "geometry": {"coordinates":[-86.159783,39.864976],"type":"Point"}
}