{
  "type": "Feature",
  "properties": {
    "iso:country":"US",
    "sg:address":"292 Watershed Ct",
    "sg:city":"Noblesville",
    "sg:classifiers":[
        {
            "category":"Health Services",
            "subcategory":"Medical Lab",
            "type":"Services"
        }
    ],
    "sg:phone":"+1 317 877 5938",
    "sg:postcode":"46062",
    "sg:province":"IN",
    "sg:tags":[
        "detection",
        "equipment",
        "drug"
    ],
    "wof:name":"Wolfe Data",
    "wof:placetype":"venue"
},
  "geometry": {"coordinates":[-86.044772,40.089863],"type":"Point"}
}