{
  "type": "Feature",
  "properties": {
    "iso:country":"US",
    "sg:address":"1011 Tulip St",
    "sg:city":"Mitchell",
    "sg:classifiers":[
        {
            "category":"Organizations",
            "subcategory":"Non-profit Organization",
            "type":"Services"
        }
    ],
    "sg:phone":"+1 812 849 6714",
    "sg:postcode":"47446",
    "sg:province":"IN",
    "sg:tags":[
        "information",
        "alcoholism",
        "treatment"
    ],
    "wof:name":"Alcoholics Anonymous",
    "wof:placetype":"venue"
},
  "geometry": {"coordinates":[-86.477243,38.728717],"type":"Point"}
}