{
  "type": "Feature",
  "properties": {
    "iso:country":"US",
    "sg:address":"617 S Sparling Ave",
    "sg:city":"Rensselaer",
    "sg:classifiers":[
        {
            "category":"Professional",
            "subcategory":"Management & Consulting",
            "type":"Services"
        }
    ],
    "sg:phone":"+1 219 866 5085",
    "sg:postcode":"47978",
    "sg:province":"IN",
    "sg:tags":[
        "consultant",
        "energy",
        "conservation"
    ],
    "wof:name":"CDC Resources Inc",
    "wof:placetype":"venue"
},
  "geometry": {"coordinates":[-87.161128,40.928682],"type":"Point"}
}