{
  "type": "Feature",
  "properties": {
    "iso:country":"US",
    "sg:address":"1802 Ridgefield Ave",
    "sg:city":"La Porte",
    "sg:classifiers":[
        {
            "category":"Professional",
            "type":"Services"
        }
    ],
    "sg:phone":"+1 219 324 4490",
    "sg:postcode":"46350",
    "sg:province":"IN",
    "sg:tags":[
        "editorial"
    ],
    "wof:name":"Boardman Edtrial Cnslting Svcs",
    "wof:placetype":"venue"
},
  "geometry": {"coordinates":[-86.707183,41.591184],"type":"Point"}
}