{
  "type": "Feature",
  "properties": {
    "iso:country":"US",
    "sg:address":"1900 S Co Rd 275 W",
    "sg:city":"New Castle",
    "sg:classifiers":[
        {
            "category":"Travel",
            "subcategory":"Campground",
            "type":"Entertainment"
        }
    ],
    "sg:phone":"+1 765 987 1232",
    "sg:postcode":"47362",
    "sg:province":"IN",
    "wof:name":"Westwood Park",
    "wof:placetype":"venue"
},
  "geometry": {"coordinates":[-85.438111,39.904189],"type":"Point"}
}