{
  "type": "Feature",
  "properties": {
    "iso:country":"US",
    "sg:address":"17190 N 600 E",
    "sg:city":"Dunkirk",
    "sg:phone":"+1 765 789 6259",
    "sg:postcode":"47336",
    "sg:province":"IN",
    "sg:tags":[
        "farm",
        "corn",
        "wheat",
        "soybean"
    ],
    "wof:name":"Doug Fisher",
    "wof:placetype":"venue"
},
  "geometry": {"coordinates":[-85.276571,40.343901],"type":"Point"}
}