{
  "type": "Feature",
  "properties": {
    "addr:full":"10392 S Co Rd 5 SE Carlisle IN 47838",
    "addr:housenumber":"10392",
    "addr:postcode":"47838",
    "addr:street":"S Co Rd 5 Se",
    "iso:country":"US",
    "sg:address":"10392 S Co Rd 5 SE",
    "sg:city":"Carlisle",
    "sg:classifiers":[
        {
            "category":"Real Estate",
            "subcategory":"Real Estate Operator",
            "type":"Services"
        }
    ],
    "sg:phone":"+1 812 398 5931",
    "sg:postcode":"47838",
    "sg:province":"IN",
    "sg:tags":[
        "property",
        "lessor"
    ],
    "wof:name":"Roy Volle",
    "wof:placetype":"venue"
},
  "geometry": {"coordinates":[-87.380619,38.932873],"type":"Point"}
}