{
  "type": "Feature",
  "properties": {
    "addr:full":"4977 S Co Rd 450 E Connersville IN 47331",
    "addr:housenumber":"4977",
    "addr:postcode":"47331",
    "addr:street":"S Co Rd 450 E",
    "iso:country":"US",
    "sg:address":"4977 S Co Rd 450 E",
    "sg:city":"Connersville",
    "sg:classifiers":[
        {
            "category":"Food & Beverages",
            "subcategory":"Fruits & Vegetables",
            "type":"Retail Goods"
        }
    ],
    "sg:phone":"+1 765 827 4241",
    "sg:postcode":"47331",
    "sg:province":"IN",
    "wof:name":"Connersville Produce",
    "wof:placetype":"venue"
},
  "geometry": {"coordinates":[-85.055283,39.569672],"type":"Point"}
}