{
  "type": "Feature",
  "properties": {
    "addr:full":"128 E Pettit Ave Fort Wayne IN 46806",
    "addr:housenumber":"128",
    "addr:postcode":"46806",
    "addr:street":"E Pettit Ave",
    "iso:country":"US",
    "sg:address":"128 E Pettit Ave",
    "sg:city":"Fort Wayne",
    "sg:classifiers":[
        {
            "category":"Manufacturing",
            "subcategory":"Printing",
            "type":"Manufacturing & Wholesale Goods"
        }
    ],
    "sg:phone":"+1 260 745 3028",
    "sg:postcode":"46806",
    "sg:province":"IN",
    "sg:tags":[
        "printer"
    ],
    "wof:name":"Advantage Printing & Packaging",
    "wof:placetype":"venue"
},
  "geometry": {"coordinates":[-85.136505,41.038752],"type":"Point"}
}