{
  "type": "Feature",
  "properties": {
    "addr:full":"3190 Mallard Cove Ln Fort Wayne IN 46804",
    "addr:housenumber":"3190",
    "addr:postcode":"46804",
    "addr:street":"Mallard Cove Ln",
    "iso:country":"US",
    "sg:address":"3190 Mallard Cove Ln",
    "sg:city":"Fort Wayne",
    "sg:classifiers":[
        {
            "category":"Airline",
            "type":"Transportation"
        }
    ],
    "sg:phone":"+1 260 436 3734",
    "sg:postcode":"46804",
    "sg:province":"IN",
    "sg:tags":[
        "a",
        "co",
        "operates",
        "as",
        "airplane",
        "rental"
    ],
    "wof:name":"Swanson Air LLC",
    "wof:placetype":"venue"
},
  "geometry": {"coordinates":[-85.23027999999999,41.054069],"type":"Point"}
}