{
  "type": "Feature",
  "properties": {
    "iso:country":"US",
    "sg:address":"1022 W McKinley Ave",
    "sg:city":"Mishawaka",
    "sg:classifiers":[
        {
            "category":"Cinema",
            "subcategory":"Movie Rental",
            "type":"Entertainment"
        }
    ],
    "sg:phone":"+1 574 257 0406",
    "sg:postcode":"46545",
    "sg:province":"IN",
    "sg:tags":[
        "leasing",
        "video",
        "disc",
        "tape"
    ],
    "wof:name":"Blockbuster Video",
    "wof:placetype":"venue"
},
  "geometry": {"coordinates":[-86.195506,41.680349],"type":"Point"}
}