{
  "type": "Feature",
  "properties": {
    "iso:country":"US",
    "sg:address":"7016 E Old 56",
    "sg:city":"Salem",
    "sg:classifiers":[
        {
            "category":"Manufacturing",
            "subcategory":"Lumber",
            "type":"Manufacturing & Wholesale Goods"
        }
    ],
    "sg:phone":"+1 812 883 8077",
    "sg:postcode":"47167",
    "sg:province":"IN",
    "sg:tags":[
        "sawmill"
    ],
    "sg:website":"www.frankmiller.com",
    "wof:name":"Frank Miller Lumber Co",
    "wof:placetype":"venue"
},
  "geometry": {"coordinates":[-85.975038,38.649716],"type":"Point"}
}