{
  "type": "Feature",
  "properties": {
    "iso:country":"US",
    "sg:address":"1506 Research Dr",
    "sg:city":"Jeffersonville",
    "sg:classifiers":[
        {
            "category":"Wholesale",
            "subcategory":"Vending Machines",
            "type":"Manufacturing & Wholesale Goods"
        }
    ],
    "sg:phone":"+1 812 282 0784",
    "sg:postcode":"47130",
    "sg:province":"IN",
    "wof:name":"Jeff Vending Svc",
    "wof:placetype":"venue"
},
  "geometry": {"coordinates":[-85.744738,38.309498],"type":"Point"}
}