{
  "type": "Feature",
  "properties": {
    "iso:country":"US",
    "sg:address":"7233 Enterprise Park Cir",
    "sg:city":"Evansville",
    "sg:classifiers":[
        {
            "category":"Retail",
            "subcategory":"Laundry & Dry Cleaning",
            "type":"Services"
        }
    ],
    "sg:phone":"+1 812 471 0870",
    "sg:postcode":"47715",
    "sg:province":"IN",
    "sg:tags":[
        "uniform",
        "supply"
    ],
    "wof:name":"Cintas The Uniform People",
    "wof:placetype":"venue"
},
  "geometry": {"coordinates":[-87.46325,37.996086],"type":"Point"}
}