{
  "type": "Feature",
  "properties": {
    "iso:country":"US",
    "sg:address":"358 Cmns Mall",
    "sg:city":"Columbus",
    "sg:classifiers":[
        {
            "category":"Shopping",
            "subcategory":"Books",
            "type":"Retail Goods"
        }
    ],
    "sg:phone":"+1 812 376 0778",
    "sg:postcode":"47201",
    "sg:province":"IN",
    "sg:tags":[
        "dealer"
    ],
    "sg:website":"www.viewpointbooks.com",
    "wof:name":"Viewpoint Books",
    "wof:placetype":"venue"
},
  "geometry": {"coordinates":[-85.92204700000001,39.202312],"type":"Point"}
}