{
  "type": "Feature",
  "properties": {
    "iso:country":"US",
    "sg:address":"1527 W Wilden Ave",
    "sg:city":"Goshen",
    "sg:classifiers":[
        {
            "category":"Building & Trades",
            "subcategory":"Construction",
            "type":"Services"
        }
    ],
    "sg:phone":"+1 574 533 1645",
    "sg:postcode":"46528",
    "sg:province":"IN",
    "sg:tags":[
        "general",
        "contractor"
    ],
    "sg:website":"www.djconstruction.com",
    "wof:name":"D J Construction Co Inc",
    "wof:placetype":"venue"
},
  "geometry": {"coordinates":[-85.85782,41.597326],"type":"Point"}
}