{
  "type": "Feature",
  "properties": {
    "iso:country":"US",
    "sg:address":"1511 Laporte Ave",
    "sg:city":"Valparaiso",
    "sg:classifiers":[
        {
            "category":"Organizations",
            "subcategory":"Religious Organization",
            "type":"Services"
        }
    ],
    "sg:phone":"+1 219 464 4042",
    "sg:postcode":"46383",
    "sg:province":"IN",
    "sg:tags":[
        "church"
    ],
    "sg:website":"www.valpo.edu/student/stt",
    "wof:name":"St Teresa Of Avila",
    "wof:placetype":"venue"
},
  "geometry": {"coordinates":[-87.041627,41.466629],"type":"Point"}
}