{
  "type": "Feature",
  "properties": {
    "iso:country":"US",
    "sg:address":"3425 N 550 W",
    "sg:city":"Angola",
    "sg:classifiers":[
        {
            "category":"Farming",
            "subcategory":"Orchard",
            "type":"Manufacturing & Wholesale Goods"
        }
    ],
    "sg:phone":"+1 260 833 1238",
    "sg:postcode":"46703",
    "sg:province":"IN",
    "sg:tags":[
        "fruit",
        "tree"
    ],
    "wof:name":"Gageview Orchards",
    "wof:placetype":"venue"
},
  "geometry": {"coordinates":[-85.093192,41.686137],"type":"Point"}
}