{
  "type": "Feature",
  "properties": {
    "iso:country":"US",
    "sg:address":"16 S Jefferson St",
    "sg:city":"Knightstown",
    "sg:classifiers":[
        {
            "category":"Insurance",
            "subcategory":"Insurance Agent",
            "type":"Services"
        }
    ],
    "sg:phone":"+1 765 345 5171",
    "sg:postcode":"46148",
    "sg:province":"IN",
    "sg:website":"www.leakeyinsurance.com",
    "wof:name":"Leakey Insurance Inc",
    "wof:placetype":"venue"
},
  "geometry": {"coordinates":[-85.526229,39.795246],"type":"Point"}
}