{
  "type": "Feature",
  "properties": {
    "iso:country":"US",
    "sg:address":"201 N Sherman St",
    "sg:city":"Brazil",
    "sg:classifiers":[
        {
            "category":"Mining & Drilling",
            "type":"Manufacturing & Wholesale Goods"
        }
    ],
    "sg:phone":"+1 812 446 6025",
    "sg:postcode":"47834",
    "sg:province":"IN",
    "sg:tags":[
        "stone"
    ],
    "sg:website":"www.mansfieldstone.com",
    "wof:name":"Mansfield Stone Co",
    "wof:placetype":"venue"
},
  "geometry": {"coordinates":[-87.133825,39.523198],"type":"Point"}
}