{
  "type": "Feature",
  "properties": {
    "iso:country":"US",
    "sg:address":"960 Alanwood Ln NW",
    "sg:city":"Corydon",
    "sg:classifiers":[
        {
            "category":"Manufacturing",
            "subcategory":"Tools & Machinery",
            "type":"Manufacturing & Wholesale Goods"
        }
    ],
    "sg:phone":"+1 812 734 0363",
    "sg:postcode":"47112",
    "sg:province":"IN",
    "sg:tags":[
        "mfg"
    ],
    "wof:name":"Race Mold Industrial Company",
    "wof:placetype":"venue"
},
  "geometry": {"coordinates":[-86.153434,38.216484],"type":"Point"}
}