{
  "type": "Feature",
  "properties": {
    "iso:country":"US",
    "sg:address":"1939 Lakeview Dr",
    "sg:city":"Fort Wayne",
    "sg:classifiers":[
        {
            "category":"Manufacturing",
            "subcategory":"Textiles",
            "type":"Manufacturing & Wholesale Goods"
        }
    ],
    "sg:phone":"+1 260 483 7394",
    "sg:postcode":"46808",
    "sg:province":"IN",
    "sg:tags":[
        "rug",
        "carpet"
    ],
    "wof:name":"Binding Inc",
    "wof:placetype":"venue"
},
  "geometry": {"coordinates":[-85.174373,41.093858],"type":"Point"}
}