{
  "type": "Feature",
  "properties": {
    "iso:country":"US",
    "sg:address":"348 W Main St",
    "sg:city":"Rossville",
    "sg:classifiers":[
        {
            "category":"Home & Garden",
            "subcategory":"Hardware",
            "type":"Retail Goods"
        }
    ],
    "sg:phone":"+1 765 379 9947",
    "sg:postcode":"46065",
    "sg:province":"IN",
    "wof:name":"Rossville Hardware & Paint",
    "wof:placetype":"venue"
},
  "geometry": {"coordinates":[-86.600831,40.417022],"type":"Point"}
}