{
  "type": "Feature",
  "properties": {
    "addr:full":"1820 N Purdum St Kokomo IN 46901",
    "addr:housenumber":"1820",
    "addr:postcode":"46901",
    "addr:street":"N Purdum St",
    "iso:country":"US",
    "sg:address":"1820 N Purdum St",
    "sg:city":"Kokomo",
    "sg:classifiers":[
        {
            "category":"Manufacturing",
            "subcategory":"Signs",
            "type":"Manufacturing & Wholesale Goods"
        }
    ],
    "sg:phone":"+1 765 457 6592",
    "sg:postcode":"46901",
    "sg:province":"IN",
    "wof:name":"Miller Sign & Design",
    "wof:placetype":"venue"
},
  "geometry": {"coordinates":[-86.124111,40.502596],"type":"Point"}
}