{
  "type": "Feature",
  "properties": {
    "iso:country":"US",
    "sg:address":"1650 Lake Park Dr",
    "sg:city":"Kendallville",
    "sg:classifiers":[
        {
            "category":"Travel",
            "subcategory":"Campground",
            "type":"Entertainment"
        }
    ],
    "sg:phone":"+1 260 347 9941",
    "sg:postcode":"46755",
    "sg:province":"IN",
    "wof:name":"Kendallville Park & Recreation",
    "wof:placetype":"venue"
},
  "geometry": {"coordinates":[-85.243382,41.443764],"type":"Point"}
}