{
  "type": "Feature",
  "properties": {
    "iso:country":"US",
    "sg:address":"3799 W State Rte 62",
    "sg:city":"Boonville",
    "sg:classifiers":[
        {
            "category":"Professional",
            "subcategory":"Accounting & Tax Preparation",
            "type":"Services"
        }
    ],
    "sg:phone":"+1 812 897 3159",
    "sg:postcode":"47601",
    "sg:province":"IN",
    "sg:tags":[
        "return",
        "filing"
    ],
    "wof:name":"Liberty Tax Svc",
    "wof:placetype":"venue"
},
  "geometry": {"coordinates":[-87.319964,38.048366],"type":"Point"}
}