{
  "type": "Feature",
  "properties": {
    "addr:full":"136 US Hwy 41 Schererville IN 46375",
    "addr:housenumber":"136",
    "addr:postcode":"46375",
    "addr:street":"Us Hwy 41",
    "iso:country":"US",
    "sg:address":"136 US Hwy 41",
    "sg:city":"Schererville",
    "sg:classifiers":[
        {
            "category":"Personal",
            "subcategory":"Beauty Salon",
            "type":"Services"
        }
    ],
    "sg:phone":"+1 219 864 8911",
    "sg:postcode":"46375",
    "sg:province":"IN",
    "wof:name":"Bo Rics Haircare",
    "wof:placetype":"venue"
},
  "geometry": {"coordinates":[-87.471361,41.519131],"type":"Point"}
}