{
  "type": "Feature",
  "properties": {
    "addr:full":"3828 Hamburg Pike Jeffersonville IN 47130",
    "addr:housenumber":"3828",
    "addr:postcode":"47130",
    "addr:street":"Hamburg Pike",
    "iso:country":"US",
    "sg:address":"3828 Hamburg Pike",
    "sg:city":"Jeffersonville",
    "sg:classifiers":[
        {
            "category":"Banks & Credit Unions",
            "subcategory":"Bank",
            "type":"Services"
        }
    ],
    "sg:phone":"+1 812 282 1188",
    "sg:postcode":"47130",
    "sg:province":"IN",
    "wof:name":"Pnc Bank",
    "wof:placetype":"venue"
},
  "geometry": {"coordinates":[-85.743149,38.322765],"type":"Point"}
}