{
  "type": "Feature",
  "properties": {
    "iso:country":"US",
    "sg:address":"5665 W 500 N",
    "sg:city":"Huntington",
    "sg:classifiers":[
        {
            "category":"Farming",
            "subcategory":"Farm",
            "type":"Manufacturing & Wholesale Goods"
        }
    ],
    "sg:phone":"+1 260 356 3959",
    "sg:postcode":"46750",
    "sg:province":"IN",
    "sg:tags":[
        "crop",
        "general"
    ],
    "wof:name":"Flint Ridge Farms",
    "wof:placetype":"venue"
},
  "geometry": {"coordinates":[-85.568861,40.904432],"type":"Point"}
}