{
  "type": "Feature",
  "properties": {
    "iso:country":"US",
    "sg:address":"500 S Maurer Dr",
    "sg:city":"Garrett",
    "sg:classifiers":[
        {
            "category":"Professional",
            "subcategory":"Accounting & Tax Preparation",
            "type":"Services"
        }
    ],
    "sg:phone":"+1 260 357 4130",
    "sg:postcode":"46738",
    "sg:province":"IN",
    "sg:tags":[
        "return"
    ],
    "wof:name":"Holiday Tax Service",
    "wof:placetype":"venue"
},
  "geometry": {"coordinates":[-85.14615000000001,41.346546],"type":"Point"}
}