{
  "type": "Feature",
  "properties": {
    "addr:full":"11943 S 630 W Remington IN 47977",
    "addr:housenumber":"11943;630",
    "addr:postcode":"47977",
    "addr:street":"S;W Remington",
    "iso:country":"US",
    "sg:address":"11943 S 630 W",
    "sg:city":"Remington",
    "sg:classifiers":[
        {
            "category":"Wholesale",
            "subcategory":"Farm Supplies",
            "type":"Manufacturing & Wholesale Goods"
        }
    ],
    "sg:phone":"+1 219 261 2900",
    "sg:postcode":"47977",
    "sg:province":"IN",
    "sg:tags":[
        "livestock"
    ],
    "wof:name":"Tip Top Pigs Inc",
    "wof:placetype":"venue"
},
  "geometry": {"coordinates":[-87.163944,40.838265],"type":"Point"}
}