{
  "type": "Feature",
  "properties": {
    "iso:country":"US",
    "sg:address":"6333 Lee Rd",
    "sg:city":"Indianapolis",
    "sg:classifiers":[
        {
            "category":"Education",
            "subcategory":"School",
            "type":"Public Place"
        }
    ],
    "sg:phone":"+1 317 823 5446",
    "sg:postcode":"46236",
    "sg:province":"IN",
    "sg:website":"www.ltschools.org",
    "wof:name":"Forest Glenn Elementary School",
    "wof:placetype":"venue"
},
  "geometry": {"coordinates":[-85.999977,39.880531],"type":"Point"}
}