{
  "type": "Feature",
  "properties": {
    "addr:full":"126 Market St Royal Center IN 46978",
    "addr:housenumber":"126",
    "addr:postcode":"46978",
    "addr:street":"Market St",
    "iso:country":"US",
    "sg:address":"126 Market St",
    "sg:city":"Royal Center",
    "sg:classifiers":[
        {
            "category":"Home & Garden",
            "subcategory":"Garden Supply",
            "type":"Retail Goods"
        }
    ],
    "sg:phone":"+1 574 643 5645",
    "sg:postcode":"46978",
    "sg:province":"IN",
    "sg:tags":[
        "fertilizer"
    ],
    "wof:name":"Traylor Chemical & Supply Co",
    "wof:placetype":"venue"
},
  "geometry": {"coordinates":[-86.50133,40.864353],"type":"Point"}
}