{
  "type": "Feature",
  "properties": {
    "iso:country":"US",
    "sg:address":"8145 Gwinnett Pl",
    "sg:city":"Indianapolis",
    "sg:classifiers":[
        {
            "category":"Real Estate",
            "subcategory":"Real Estate Services",
            "type":"Services"
        }
    ],
    "sg:phone":"+1 317 913 7933",
    "sg:postcode":"46250",
    "sg:province":"IN",
    "wof:name":"Alliance Real Estate",
    "wof:placetype":"venue"
},
  "geometry": {"coordinates":[-86.097801,39.903702],"type":"Point"}
}