{
  "type": "Feature",
  "properties": {
    "iso:country":"US",
    "sg:address":"1145 S Odell St",
    "sg:city":"Brownsburg",
    "sg:classifiers":[
        {
            "category":"Building & Trades",
            "subcategory":"Construction",
            "type":"Services"
        }
    ],
    "sg:phone":"+1 317 457 8120",
    "sg:postcode":"46112",
    "sg:province":"IN",
    "sg:tags":[
        "carpenter"
    ],
    "wof:name":"Tieken & Tieken Construction",
    "wof:placetype":"venue"
},
  "geometry": {"coordinates":[-86.386991,39.826455],"type":"Point"}
}