{
  "type": "Feature",
  "properties": {
    "addr:full":"368 Austin Dr Avon IN 46123",
    "addr:housenumber":"368",
    "addr:postcode":"46123",
    "addr:street":"Austin Dr",
    "iso:country":"US",
    "sg:address":"368 Austin Dr",
    "sg:city":"Avon",
    "sg:classifiers":[
        {
            "category":"Professional",
            "subcategory":"Engineering",
            "type":"Services"
        }
    ],
    "sg:phone":"+1 317 272 1023",
    "sg:postcode":"46123",
    "sg:province":"IN",
    "sg:tags":[
        "engineer"
    ],
    "wof:name":"Engineering & Fire Invstgtns",
    "wof:placetype":"venue"
},
  "geometry": {"coordinates":[-86.374893,39.769228],"type":"Point"}
}