{
  "type": "Feature",
  "properties": {
    "iso:country":"US",
    "sg:address":"525 Warren St",
    "sg:city":"Huntington",
    "sg:classifiers":[
        {
            "category":"Professional",
            "subcategory":"Accounting & Tax Preparation",
            "type":"Services"
        }
    ],
    "sg:phone":"+1 260 359 9190",
    "sg:postcode":"46750",
    "sg:province":"IN",
    "sg:tags":[
        "return",
        "filing"
    ],
    "wof:name":"R & L Tax Svc",
    "wof:placetype":"venue"
},
  "geometry": {"coordinates":[-85.494418,40.883063],"type":"Point"}
}