{
  "type": "Feature",
  "properties": {
    "iso:country":"US",
    "sg:address":"1512 W 96th Ave",
    "sg:city":"Crown Point",
    "sg:classifiers":[
        {
            "category":"Insurance",
            "subcategory":"Hazard Insurance",
            "type":"Services"
        }
    ],
    "sg:phone":"+1 219 661 1000",
    "sg:postcode":"46307",
    "sg:province":"IN",
    "sg:tags":[
        "warranty",
        "automobile",
        "processing"
    ],
    "wof:name":"Certified Dealer Svc Inc",
    "wof:placetype":"venue"
},
  "geometry": {"coordinates":[-87.351949,41.443879],"type":"Point"}
}