{
  "type": "Feature",
  "properties": {
    "iso:country":"US",
    "sg:address":"7805 Preservation Dr",
    "sg:city":"Indianapolis",
    "sg:classifiers":[
        {
            "category":"Building & Trades",
            "subcategory":"Construction",
            "type":"Services"
        }
    ],
    "sg:phone":"+1 317 919 7295",
    "sg:postcode":"46278",
    "sg:province":"IN",
    "sg:tags":[
        "home",
        "builder"
    ],
    "wof:name":"Executive Homes Inc Preserveat",
    "wof:placetype":"venue"
},
  "geometry": {"coordinates":[-86.31205,39.892471],"type":"Point"}
}