{
  "type": "Feature",
  "properties": {
    "iso:country":"US",
    "sg:address":"1510 Osolo Rd",
    "sg:city":"Elkhart",
    "sg:classifiers":[
        {
            "category":"Health Services",
            "subcategory":"Health Practitioner",
            "type":"Services"
        }
    ],
    "sg:phone":"+1 574 266 7747",
    "sg:postcode":"46514",
    "sg:province":"IN",
    "sg:tags":[
        "therapist",
        "physical"
    ],
    "wof:name":"SSIR Of Elkhart",
    "wof:placetype":"venue"
},
  "geometry": {"coordinates":[-85.9467,41.703821],"type":"Point"}
}