{
  "type": "Feature",
  "properties": {
    "addr:full":"7520 Highway 311 Sellersburg IN 47172",
    "addr:housenumber":"7520",
    "addr:postcode":"47172",
    "addr:street":"Highway 311",
    "iso:country":"US",
    "sg:address":"7520 Highway 311",
    "sg:city":"Sellersburg",
    "sg:classifiers":[
        {
            "category":"Banks & Credit Unions",
            "subcategory":"Bank",
            "type":"Services"
        }
    ],
    "sg:phone":"+1 812 246 4411",
    "sg:postcode":"47172",
    "sg:province":"IN",
    "wof:name":"Pnc Bank",
    "wof:placetype":"venue"
},
  "geometry": {"coordinates":[-85.768799,38.3801],"type":"Point"}
}