{
  "type": "Feature",
  "properties": {
    "iso:country":"US",
    "sg:address":"9102 E 325 N",
    "sg:city":"Buck Creek",
    "sg:classifiers":[
        {
            "category":"Wholesale",
            "subcategory":"Farm Supplies",
            "type":"Manufacturing & Wholesale Goods"
        }
    ],
    "sg:phone":"+1 765 589 8568",
    "sg:postcode":"47905",
    "sg:province":"IN",
    "sg:tags":[
        "feed"
    ],
    "wof:name":"Hunter Nutrition",
    "wof:placetype":"venue"
},
  "geometry": {"coordinates":[-86.728442,40.462805],"type":"Point"}
}