{
  "type": "Feature",
  "properties": {
    "iso:country":"US",
    "sg:address":"204 N Main St",
    "sg:city":"Columbia City",
    "sg:classifiers":[
        {
            "category":"Organizations",
            "subcategory":"Religious Organization",
            "type":"Services"
        }
    ],
    "sg:phone":"+1 260 244 7118",
    "sg:postcode":"46725",
    "sg:province":"IN",
    "sg:tags":[
        "church"
    ],
    "sg:website":"www.gracecolumbiacity.org",
    "wof:name":"Grace Lutheran Church",
    "wof:placetype":"venue"
},
  "geometry": {"coordinates":[-85.48836,41.15918],"type":"Point"}
}