{
  "type": "Feature",
  "properties": {
    "iso:country":"US",
    "sg:address":"78 E Park St",
    "sg:city":"Brazil",
    "sg:classifiers":[
        {
            "category":"Health Services",
            "subcategory":"Chiropractor",
            "type":"Services"
        }
    ],
    "sg:phone":"+1 812 443 2225",
    "sg:postcode":"47834",
    "sg:province":"IN",
    "wof:name":"Shaw Chiropractic",
    "wof:placetype":"venue"
},
  "geometry": {"coordinates":[-87.127573,39.530779],"type":"Point"}
}