{
  "type": "Feature",
  "properties": {
    "iso:country":"US",
    "sg:address":"1516 W 86th St",
    "sg:city":"Indianapolis",
    "sg:classifiers":[
        {
            "category":"Personal",
            "subcategory":"Nail Salon",
            "type":"Services"
        }
    ],
    "sg:phone":"+1 317 337 0098",
    "sg:postcode":"46260",
    "sg:province":"IN",
    "wof:name":"Elain Nail Spa",
    "wof:placetype":"venue"
},
  "geometry": {"coordinates":[-86.18713200000001,39.91223],"type":"Point"}
}