{
  "type": "Feature",
  "properties": {
    "iso:country":"US",
    "sg:address":"10928 Oak Wind Ct",
    "sg:city":"Fort Wayne",
    "sg:classifiers":[
        {
            "category":"Professional",
            "subcategory":"Business Services",
            "type":"Services"
        }
    ],
    "sg:phone":"+1 260 482 3988",
    "sg:postcode":"46845",
    "sg:province":"IN",
    "wof:name":"Lightning Group Inc",
    "wof:placetype":"venue"
},
  "geometry": {"coordinates":[-85.072988,41.184339],"type":"Point"}
}