{
  "type": "Feature",
  "properties": {
    "addr:full":"2670 N Morton St Franklin IN 46131",
    "addr:housenumber":"2670",
    "addr:postcode":"46131",
    "addr:street":"N Morton St",
    "iso:country":"US",
    "sg:address":"2670 N Morton St",
    "sg:city":"Franklin",
    "sg:classifiers":[
        {
            "category":"Freight",
            "type":"Transportation"
        }
    ],
    "sg:phone":"+1 317 736 5999",
    "sg:postcode":"46131",
    "sg:province":"IN",
    "sg:tags":[
        "commercial",
        "storage"
    ],
    "wof:name":"Randy's U-Store It",
    "wof:placetype":"venue"
},
  "geometry": {"coordinates":[-86.072067,39.511338],"type":"Point"}
}