{
  "type": "Feature",
  "properties": {
    "iso:country":"US",
    "sg:address":"2407 S 14th St",
    "sg:city":"New Castle",
    "sg:classifiers":[
        {
            "category":"Building & Trades",
            "subcategory":"Construction",
            "type":"Services"
        }
    ],
    "sg:phone":"+1 765 529 1352",
    "sg:postcode":"47362",
    "sg:province":"IN",
    "sg:tags":[
        "tile",
        "dealer"
    ],
    "wof:name":"Saunders Flooring Ctr",
    "wof:placetype":"venue"
},
  "geometry": {"coordinates":[-85.363152,39.909543],"type":"Point"}
}