{
  "type": "Feature",
  "properties": {
    "iso:country":"US",
    "sg:address":"4377 W County Line Rd",
    "sg:city":"Greenwood",
    "sg:classifiers":[
        {
            "category":"Real Estate",
            "subcategory":"Real Estate Operator",
            "type":"Services"
        }
    ],
    "sg:phone":"+1 317 888 1841",
    "sg:postcode":"46142",
    "sg:province":"IN",
    "sg:tags":[
        "mobile",
        "home",
        "community"
    ],
    "wof:name":"Friendly Village-Greenwood",
    "wof:placetype":"venue"
},
  "geometry": {"coordinates":[-86.186562,39.634511],"type":"Point"}
}