{
  "type": "Feature",
  "properties": {
    "addr:full":"3115 W 16th St Indianapolis IN 46222",
    "addr:housenumber":"3115",
    "addr:postcode":"46222",
    "addr:street":"W 16Th St",
    "iso:country":"US",
    "sg:address":"3115 W 16th St",
    "sg:city":"Indianapolis",
    "sg:classifiers":[
        {
            "category":"Retail",
            "subcategory":"Auto Rental",
            "type":"Services"
        }
    ],
    "sg:phone":"+1 317 632 2214",
    "sg:postcode":"46222",
    "sg:province":"IN",
    "sg:tags":[
        "renting",
        "automobile"
    ],
    "wof:name":"Enterprise Rent-A-Car",
    "wof:placetype":"venue"
},
  "geometry": {"coordinates":[-86.21257300000001,39.787858],"type":"Point"}
}