{
  "type": "Feature",
  "properties": {
    "iso:country":"US",
    "sg:address":"6505 Miramar Ct",
    "sg:city":"Indianapolis",
    "sg:classifiers":[
        {
            "category":"Banks & Credit Unions",
            "subcategory":"Investment Brokerage",
            "type":"Services"
        }
    ],
    "sg:phone":"+1 317 570 9515",
    "sg:postcode":"46250",
    "sg:province":"IN",
    "sg:tags":[
        "consultant",
        "financing"
    ],
    "wof:name":"Morton Harris & Co",
    "wof:placetype":"venue"
},
  "geometry": {"coordinates":[-86.054634,39.926423],"type":"Point"}
}