{
  "type": "Feature",
  "properties": {
    "iso:country":"US",
    "sg:address":"210 George St",
    "sg:city":"Aurora",
    "sg:classifiers":[
        {
            "category":"Freight",
            "type":"Transportation"
        }
    ],
    "sg:phone":"+1 812 926 0740",
    "sg:postcode":"47001",
    "sg:province":"IN",
    "sg:tags":[
        "terminal",
        "line",
        "barge"
    ],
    "wof:name":"Aurora Terminal Co Inc",
    "wof:placetype":"venue"
},
  "geometry": {"coordinates":[-84.898856,39.059306],"type":"Point"}
}