{
  "type": "Feature",
  "properties": {
    "addr:full":"556 N Clark Blvd Clarksville IN 47129",
    "addr:housenumber":"556",
    "addr:postcode":"47129",
    "addr:street":"N Clark Blvd",
    "iso:country":"US",
    "sg:address":"556 N Clark Blvd",
    "sg:city":"Clarksville",
    "sg:classifiers":[
        {
            "category":"Autos & Motor Vehicles",
            "subcategory":"Auto Supplies",
            "type":"Retail Goods"
        }
    ],
    "sg:phone":"+1 812 288 6910",
    "sg:postcode":"47129",
    "sg:province":"IN",
    "sg:tags":[
        "equipment",
        "racing",
        "car",
        "automobile"
    ],
    "wof:name":"Bill Kimmel & Sons Auto Parts",
    "wof:placetype":"venue"
},
  "geometry": {"coordinates":[-85.769052,38.293674],"type":"Point"}
}