{
  "type": "Feature",
  "properties": {
    "iso:country":"US",
    "sg:address":"18 Blvd Motif",
    "sg:city":"Brownsburg",
    "sg:classifiers":[
        {
            "category":"Health Services",
            "subcategory":"Doctor",
            "type":"Services"
        }
    ],
    "sg:phone":"+1 317 852 5566",
    "sg:postcode":"46112",
    "sg:province":"IN",
    "sg:tags":[
        "dentist"
    ],
    "sg:website":"www.embraceme.com",
    "wof:name":"Central Indiana Orthodontics",
    "wof:placetype":"venue"
},
  "geometry": {"coordinates":[-86.394455,39.85245],"type":"Point"}
}