{
  "type": "Feature",
  "properties": {
    "iso:country":"US",
    "sg:address":"90 Executive Dr",
    "sg:city":"Carmel",
    "sg:classifiers":[
        {
            "category":"Shopping",
            "subcategory":"Used Merchandise",
            "type":"Retail Goods"
        }
    ],
    "sg:phone":"+1 317 848 4755",
    "sg:postcode":"46032",
    "sg:province":"IN",
    "sg:tags":[
        "shop",
        "thrift"
    ],
    "wof:name":"Thompson Thrift Development",
    "wof:placetype":"venue"
},
  "geometry": {"coordinates":[-86.123514,39.963392],"type":"Point"}
}