{
  "type": "Feature",
  "properties": {
    "iso:country":"US",
    "sg:address":"5344 S Yankeetown Rd",
    "sg:city":"Boonville",
    "sg:classifiers":[
        {
            "category":"Building & Trades",
            "subcategory":"Construction",
            "type":"Services"
        }
    ],
    "sg:phone":"+1 812 853 5007",
    "sg:postcode":"47601",
    "sg:province":"IN",
    "sg:tags":[
        "excavating",
        "contractor"
    ],
    "wof:name":"L & M Excavating",
    "wof:placetype":"venue"
},
  "geometry": {"coordinates":[-87.285205,37.955847],"type":"Point"}
}