{
  "type": "Feature",
  "properties": {
    "iso:country":"US",
    "sg:address":"11428 Grabill Rd",
    "sg:city":"Leo",
    "sg:classifiers":[
        {
            "category":"Wholesale",
            "subcategory":"Non-durable Goods",
            "type":"Manufacturing & Wholesale Goods"
        }
    ],
    "sg:phone":"+1 260 627 6332",
    "sg:postcode":"46765",
    "sg:province":"IN",
    "sg:tags":[
        "shop",
        "coffee",
        "art",
        "custom",
        "framing",
        "print"
    ],
    "wof:name":"Prints of Peace Galleries",
    "wof:placetype":"venue"
},
  "geometry": {"coordinates":[-85.002825,41.22135],"type":"Point"}
}