{
  "type": "Feature",
  "properties": {
    "iso:country":"US",
    "sg:address":"2506 Willowbrook Pkwy",
    "sg:city":"Indianapolis",
    "sg:classifiers":[
        {
            "category":"Health Services",
            "subcategory":"Health Practitioner",
            "type":"Services"
        }
    ],
    "sg:phone":"+1 317 252 2620",
    "sg:postcode":"46205",
    "sg:province":"IN",
    "sg:tags":[
        "psychologist"
    ],
    "wof:name":"PAI Inc",
    "wof:placetype":"venue"
},
  "geometry": {"coordinates":[-86.11927,39.842424],"type":"Point"}
}