{
  "type": "Feature",
  "properties": {
    "iso:country":"US",
    "sg:address":"442 E Line St",
    "sg:city":"Geneva",
    "sg:classifiers":[
        {
            "category":"Bars & Pubs",
            "type":"Food & Drink"
        }
    ],
    "sg:phone":"+1 260 368 7441",
    "sg:postcode":"46740",
    "sg:province":"IN",
    "wof:name":"Jack's Pub",
    "wof:placetype":"venue"
},
  "geometry": {"coordinates":[-84.957384,40.591996],"type":"Point"}
}