{
  "type": "Feature",
  "properties": {
    "iso:country":"US",
    "sg:address":"7672 Wickfield Way",
    "sg:city":"Indianapolis",
    "sg:classifiers":[
        {
            "category":"Professional",
            "subcategory":"Business Services",
            "type":"Services"
        }
    ],
    "sg:phone":"+1 317 849 4167",
    "sg:postcode":"46256",
    "sg:province":"IN",
    "wof:name":"Alderman Financial Service",
    "wof:placetype":"venue"
},
  "geometry": {"coordinates":[-86.030427,39.894082],"type":"Point"}
}