{
  "type": "Feature",
  "properties": {
    "iso:country":"US",
    "sg:address":"3801 S Co Rd 575 E",
    "sg:city":"Selma",
    "sg:classifiers":[
        {
            "category":"Manufacturing",
            "subcategory":"Musical Instruments",
            "type":"Manufacturing & Wholesale Goods"
        }
    ],
    "sg:phone":"+1 765 287 1757",
    "sg:postcode":"47383",
    "sg:province":"IN",
    "sg:tags":[
        "mfg"
    ],
    "wof:name":"Shekinah Rhythm Instrument",
    "wof:placetype":"venue"
},
  "geometry": {"coordinates":[-85.277666,40.149968],"type":"Point"}
}