{
  "type": "Feature",
  "properties": {
    "iso:country":"US",
    "sg:address":"118 E 8th St",
    "sg:city":"Rochester",
    "sg:classifiers":[
        {
            "category":"Manufacturing",
            "subcategory":"Printing",
            "type":"Manufacturing & Wholesale Goods"
        }
    ],
    "sg:phone":"+1 574 223 2111",
    "sg:postcode":"46975",
    "sg:province":"IN",
    "sg:tags":[
        "newspaper"
    ],
    "sg:website":"www.rochsent.com",
    "wof:name":"Rochester Sentinel",
    "wof:placetype":"venue"
},
  "geometry": {"coordinates":[-86.215728,41.066123],"type":"Point"}
}