{
  "type": "Feature",
  "properties": {
    "iso:country":"US",
    "sg:address":"515 S Curry Pike",
    "sg:city":"Bloomington",
    "sg:classifiers":[
        {
            "category":"Organizations",
            "subcategory":"Religious Organization",
            "type":"Services"
        }
    ],
    "sg:phone":"+1 812 336 7224",
    "sg:postcode":"47403",
    "sg:province":"IN",
    "sg:website":"www.highlandvillagechurch.com",
    "wof:name":"United Pentecostal Church of Highland Village",
    "wof:placetype":"venue"
},
  "geometry": {"coordinates":[-86.58260300000001,39.162399],"type":"Point"}
}