{
  "type": "Feature",
  "properties": {
    "iso:country":"US",
    "sg:address":"5355 N Co Rd 600 E",
    "sg:city":"Brownsburg",
    "sg:classifiers":[
        {
            "category":"Manufacturing",
            "subcategory":"Apparel",
            "type":"Manufacturing & Wholesale Goods"
        }
    ],
    "sg:phone":"+1 317 852 2968",
    "sg:postcode":"46112",
    "sg:province":"IN",
    "sg:tags":[
        "canvas",
        "product",
        "related"
    ],
    "wof:name":"Fabricraft",
    "wof:placetype":"venue"
},
  "geometry": {"coordinates":[-86.420387,39.839404],"type":"Point"}
}