{
  "type": "Feature",
  "properties": {
    "iso:country":"US",
    "sg:address":"225 Clay St",
    "sg:city":"Jasper",
    "sg:classifiers":[
        {
            "category":"Professional",
            "type":"Services"
        }
    ],
    "sg:phone":"+1 812 482 3204",
    "sg:postcode":"47546",
    "sg:province":"IN",
    "sg:tags":[
        "establishment"
    ],
    "wof:name":"Community Division-Jasper",
    "wof:placetype":"venue"
},
  "geometry": {"coordinates":[-86.932823,38.388877],"type":"Point"}
}