{
  "type": "Feature",
  "properties": {
    "iso:country":"US",
    "sg:address":"317 Winesap Dr",
    "sg:city":"Lafayette",
    "sg:classifiers":[
        {
            "category":"Building & Trades",
            "subcategory":"Landscaping Services",
            "type":"Services"
        }
    ],
    "sg:phone":"+1 765 446 0156",
    "sg:postcode":"47905",
    "sg:province":"IN",
    "sg:tags":[
        "landscape"
    ],
    "wof:name":"Landcraft Design",
    "wof:placetype":"venue"
},
  "geometry": {"coordinates":[-86.837549,40.423351],"type":"Point"}
}