{
  "type": "Feature",
  "properties": {
    "iso:country":"US",
    "sg:address":"435 N Lynhurst Dr",
    "sg:city":"Indianapolis",
    "sg:classifiers":[
        {
            "category":"Organizations",
            "subcategory":"Religious Organization",
            "type":"Services"
        }
    ],
    "sg:phone":"+1 317 241 8884",
    "sg:postcode":"46224",
    "sg:province":"IN",
    "wof:name":"First Assembly Of God",
    "wof:placetype":"venue"
},
  "geometry": {"coordinates":[-86.250405,39.773624],"type":"Point"}
}