{
  "type": "Feature",
  "properties": {
    "iso:country":"US",
    "sg:address":"850 W Michigan St",
    "sg:city":"Indianapolis",
    "sg:classifiers":[
        {
            "category":"Restaurant",
            "type":"Food & Drink"
        }
    ],
    "sg:phone":"+1 317 638 2264",
    "sg:postcode":"46202",
    "sg:province":"IN",
    "sg:tags":[
        "pizza"
    ],
    "wof:name":"Luca Pizza Iupui",
    "wof:placetype":"venue"
},
  "geometry": {"coordinates":[-86.17334,39.774479],"type":"Point"}
}