{
  "type": "Feature",
  "properties": {
    "iso:country":"US",
    "sg:address":"3327 E North St",
    "sg:city":"Indianapolis",
    "sg:classifiers":[
        {
            "category":"Building & Trades",
            "subcategory":"Construction",
            "type":"Services"
        }
    ],
    "sg:phone":"+1 317 945 1801",
    "sg:postcode":"46201",
    "sg:province":"IN",
    "sg:tags":[
        "house"
    ],
    "wof:name":"Carter & Burgess",
    "wof:placetype":"venue"
},
  "geometry": {"coordinates":[-86.108524,39.775816],"type":"Point"}
}