{
  "type": "Feature",
  "properties": {
    "iso:country":"US",
    "sg:address":"4516 Brittany Rd",
    "sg:city":"Indianapolis",
    "sg:classifiers":[
        {
            "category":"Building & Trades",
            "subcategory":"Construction",
            "type":"Services"
        }
    ],
    "sg:phone":"+1 317 752 7639",
    "sg:postcode":"46222",
    "sg:province":"IN",
    "sg:tags":[
        "roofing",
        "contractor"
    ],
    "wof:name":"Restoration Today",
    "wof:placetype":"venue"
},
  "geometry": {"coordinates":[-86.237903,39.811869],"type":"Point"}
}