{
  "type": "Feature",
  "properties": {
    "iso:country":"US",
    "sg:address":"835 Spear St",
    "sg:city":"Logansport",
    "sg:classifiers":[
        {
            "category":"Professional",
            "subcategory":"Computer Services",
            "type":"Services"
        }
    ],
    "sg:phone":"+1 574 722 3038",
    "sg:postcode":"46947",
    "sg:province":"IN",
    "wof:name":"Cosby Inc",
    "wof:placetype":"venue"
},
  "geometry": {"coordinates":[-86.358333,40.752879],"type":"Point"}
}