{
  "type": "Feature",
  "properties": {
    "iso:country":"US",
    "sg:address":"1265 E 150 N",
    "sg:city":"Lagrange",
    "sg:classifiers":[
        {
            "category":"Retail",
            "subcategory":"Auto Repair",
            "type":"Services"
        }
    ],
    "sg:phone":"+1 260 463 8900",
    "sg:postcode":"46761",
    "sg:province":"IN",
    "sg:tags":[
        "body"
    ],
    "wof:name":"Hippenhammer Body Shop",
    "wof:placetype":"venue"
},
  "geometry": {"coordinates":[-85.387778,41.663441],"type":"Point"}
}