{
  "type": "Feature",
  "properties": {
    "iso:country":"US",
    "sg:address":"5235 Elmwood Ave",
    "sg:city":"Indianapolis",
    "sg:classifiers":[
        {
            "category":"Building & Trades",
            "subcategory":"Construction",
            "type":"Services"
        },
        {
            "category":"Building & Trades",
            "subcategory":"Electrical",
            "type":"Services"
        },
        {
            "category":"Home & Garden",
            "subcategory":"Household Appliances",
            "type":"Retail Goods"
        },
        {
            "category":"Home & Garden",
            "subcategory":"Building Materials",
            "type":"Retail Goods"
        },
        {
            "category":"Professional",
            "subcategory":"Engineering",
            "type":"Services"
        },
        {
            "category":"Building & Trades",
            "subcategory":"Cleaning & Sanitation",
            "type":"Services"
        }
    ],
    "sg:phone":"+1 317 781 2580",
    "sg:postcode":"46203",
    "sg:province":"IN",
    "sg:tags":[
        "repair",
        "purifying",
        "specialty",
        "quality-indoor",
        "duct",
        "systems-repairing",
        "system",
        "contractor",
        "equipment",
        "furnaces-heating",
        "furnaces-repairing",
        "pump",
        "insulation",
        "heating",
        "heat",
        "air conditioning"
    ],
    "sg:website":"http://www.IndySE.biz",
    "wof:name":"Service Experts of Indianapolis",
    "wof:placetype":"venue"
},
  "geometry": {"coordinates":[-86.08008,39.705573],"type":"Point"}
}