{
  "type": "Feature",
  "properties": {
    "iso:country":"US",
    "sg:address":"440 3rd St",
    "sg:city":"Columbus",
    "sg:classifiers":[
        {
            "category":"Government",
            "subcategory":"Office",
            "type":"Public Place"
        }
    ],
    "sg:phone":"+1 812 379 1560",
    "sg:postcode":"47201",
    "sg:province":"IN",
    "wof:name":"Maintenance Supervisor",
    "wof:placetype":"venue"
},
  "geometry": {"coordinates":[-85.920165,39.201508],"type":"Point"}
}