{
  "type": "Feature",
  "properties": {
    "addr:full":"330 W US Hwy 30 Valparaiso IN 46385",
    "addr:housenumber":"330",
    "addr:postcode":"46385",
    "addr:street":"W Us Hwy 30",
    "iso:country":"US",
    "sg:address":"330 W US Hwy 30",
    "sg:city":"Valparaiso",
    "sg:classifiers":[
        {
            "category":"Education",
            "subcategory":"Special Training",
            "type":"Public Place"
        }
    ],
    "sg:phone":"+1 219 476 9224",
    "sg:postcode":"46385",
    "sg:province":"IN",
    "sg:tags":[
        "craft"
    ],
    "wof:name":"Golden Seal",
    "wof:placetype":"venue"
},
  "geometry": {"coordinates":[-87.11847400000001,41.464916],"type":"Point"}
}