{
  "type": "Feature",
  "properties": {
    "iso:country":"US",
    "sg:address":"809 State St",
    "sg:city":"Laporte",
    "sg:classifiers":[
        {
            "category":"Government",
            "subcategory":"Jail",
            "type":"Public Place"
        }
    ],
    "sg:phone":"+1 219 326 7700",
    "sg:postcode":"46350",
    "sg:province":"IN",
    "sg:tags":[
        "county",
        "govt",
        "institution"
    ],
    "wof:name":"LA Porte County Jail",
    "wof:placetype":"venue"
},
  "geometry": {"coordinates":[-86.722081,41.611942],"type":"Point"}
}