{
  "type": "Feature",
  "properties": {
    "iso:country":"US",
    "sg:address":"700 S Center St",
    "sg:city":"Fort Branch",
    "sg:classifiers":[
        {
            "category":"Shopping",
            "subcategory":"Bicycles & Sporting Goods",
            "type":"Retail Goods"
        }
    ],
    "sg:phone":"+1 812 753 5977",
    "sg:postcode":"47648",
    "sg:province":"IN",
    "sg:tags":[
        "gun",
        "gunsmith"
    ],
    "wof:name":"Bill's Gun Shop",
    "wof:placetype":"venue"
},
  "geometry": {"coordinates":[-87.576133,38.24193],"type":"Point"}
}