{
  "type": "Feature",
  "properties": {
    "iso:country":"US",
    "sg:address":"3319 South St",
    "sg:city":"Lafayette",
    "sg:classifiers":[
        {
            "category":"Manufacturing",
            "subcategory":"Motor Vehicles & Parts",
            "type":"Manufacturing & Wholesale Goods"
        }
    ],
    "sg:phone":"+1 765 583 4392",
    "sg:postcode":"47904",
    "sg:province":"IN",
    "sg:tags":[
        "shaft",
        "drive",
        "mfg"
    ],
    "wof:name":"Wilkinson Custom Drive Shaft",
    "wof:placetype":"venue"
},
  "geometry": {"coordinates":[-86.858202,40.417471],"type":"Point"}
}