{
  "type": "Feature",
  "properties": {
    "addr:full":"3127 W 22nd St Anderson IN 46011",
    "addr:housenumber":"3127",
    "addr:postcode":"46011",
    "addr:street":"W 22Nd St",
    "iso:country":"US",
    "sg:address":"3127 W 22nd St",
    "sg:city":"Anderson",
    "sg:classifiers":[
        {
            "category":"Social Services",
            "subcategory":"Child Care",
            "type":"Services"
        }
    ],
    "sg:phone":"+1 765 642 2059",
    "sg:postcode":"46011",
    "sg:province":"IN",
    "sg:tags":[
        "day"
    ],
    "wof:name":"Lisa Brown",
    "wof:placetype":"venue"
},
  "geometry": {"coordinates":[-85.726297,40.094588],"type":"Point"}
}