{
  "type": "Feature",
  "properties": {
    "iso:country":"US",
    "sg:address":"230 Main St W",
    "sg:city":"Greenwood",
    "sg:classifiers":[
        {
            "category":"Restaurant",
            "type":"Food & Drink"
        }
    ],
    "sg:phone":"+1 317 887 6631",
    "sg:postcode":"46142",
    "sg:province":"IN",
    "sg:tags":[
        "banquet",
        "rooms"
    ],
    "sg:website":"www.columnsballroom.com",
    "wof:name":"Columns",
    "wof:placetype":"venue"
},
  "geometry": {"coordinates":[-86.108025,39.613764],"type":"Point"}
}