{
  "type": "Feature",
  "properties": {
    "iso:country":"US",
    "sg:address":"401 S Deer Creek St",
    "sg:city":"Galveston",
    "sg:classifiers":[
        {
            "category":"Real Estate",
            "subcategory":"Real Estate Operator",
            "type":"Services"
        }
    ],
    "sg:phone":"+1 574 699 6327",
    "sg:postcode":"46932",
    "sg:province":"IN",
    "sg:tags":[
        "mobile",
        "home",
        "community"
    ],
    "wof:name":"Deer Creek Village",
    "wof:placetype":"venue"
},
  "geometry": {"coordinates":[-86.184691,40.576007],"type":"Point"}
}