{
  "type": "Feature",
  "properties": {
    "iso:country":"US",
    "sg:address":"9401 Skyhill Dr",
    "sg:city":"Fort Wayne",
    "sg:classifiers":[
        {
            "category":"Professional",
            "subcategory":"Engineering",
            "type":"Services"
        }
    ],
    "sg:phone":"+1 260 432 5262",
    "sg:postcode":"46804",
    "sg:province":"IN",
    "sg:tags":[
        "engineer"
    ],
    "wof:name":"J D Bishop Engineering & Dev",
    "wof:placetype":"venue"
},
  "geometry": {"coordinates":[-85.264501,41.034799],"type":"Point"}
}