{
  "type": "Feature",
  "properties": {
    "iso:country":"US",
    "sg:address":"1240 Orchard St",
    "sg:city":"Mitchell",
    "sg:classifiers":[
        {
            "category":"Social Services",
            "subcategory":"Child Care",
            "type":"Services"
        }
    ],
    "sg:phone":"+1 812 849 4448",
    "sg:postcode":"47446",
    "sg:province":"IN",
    "sg:website":"www.hoosieruplands.org",
    "wof:name":"Hoosier Uplands Child Care Ctr",
    "wof:placetype":"venue"
},
  "geometry": {"coordinates":[-86.480062,38.72768],"type":"Point"}
}