{
  "type": "Feature",
  "properties": {
    "iso:country":"US",
    "sg:address":"238 W Main St",
    "sg:city":"Cambridge City",
    "sg:classifiers":[
        {
            "category":"Organizations",
            "subcategory":"Religious Organization",
            "type":"Services"
        }
    ],
    "sg:phone":"+1 765 478 3731",
    "sg:postcode":"47327",
    "sg:province":"IN",
    "sg:tags":[
        "church"
    ],
    "wof:name":"First United Methodist Church",
    "wof:placetype":"venue"
},
  "geometry": {"coordinates":[-85.173833,39.812376],"type":"Point"}
}