{
  "type": "Feature",
  "properties": {
    "addr:full":"2754 E Paulding Rd Fort Wayne IN 46816",
    "addr:housenumber":"2754",
    "addr:postcode":"46816",
    "addr:street":"E Paulding Rd",
    "iso:country":"US",
    "sg:address":"2754 E Paulding Rd",
    "sg:city":"Fort Wayne",
    "sg:classifiers":[
        {
            "category":"Real Estate",
            "subcategory":"Real Estate Operator",
            "type":"Services"
        }
    ],
    "sg:phone":"+1 260 447 4541",
    "sg:postcode":"46816",
    "sg:province":"IN",
    "sg:tags":[
        "apartment"
    ],
    "wof:name":"Village Park Apartments",
    "wof:placetype":"venue"
},
  "geometry": {"coordinates":[-85.10079399999999,41.032237],"type":"Point"}
}