{
  "type": "Feature",
  "properties": {
    "iso:country":"US",
    "sg:address":"2102 S Dixon Rd",
    "sg:city":"Kokomo",
    "sg:classifiers":[
        {
            "category":"Food & Beverages",
            "subcategory":"Groceries & Convenience Stores",
            "type":"Retail Goods"
        }
    ],
    "sg:phone":"+1 765 455 0025",
    "sg:postcode":"46902",
    "sg:province":"IN",
    "wof:name":"Marsh",
    "wof:placetype":"venue"
},
  "geometry": {"coordinates":[-86.165043,40.459527],"type":"Point"}
}