{
  "type": "Feature",
  "properties": {
    "iso:country":"US",
    "sg:address":"180 US Hwy 20",
    "sg:city":"Lagrange",
    "sg:classifiers":[
        {
            "category":"Retail",
            "subcategory":"Auto Repair",
            "type":"Services"
        }
    ],
    "sg:phone":"+1 260 463 5066",
    "sg:postcode":"46761",
    "sg:province":"IN",
    "sg:tags":[
        "body",
        "automobile",
        "painting"
    ],
    "wof:name":"Hite's Auto Body",
    "wof:placetype":"venue"
},
  "geometry": {"coordinates":[-85.428279,41.641357],"type":"Point"}
}