{
  "type": "Feature",
  "properties": {
    "iso:country":"US",
    "sg:address":"1822 Arthur Rd",
    "sg:city":"Paragon",
    "sg:classifiers":[
        {
            "category":"Building & Trades",
            "subcategory":"Construction",
            "type":"Services"
        }
    ],
    "sg:phone":"+1 765 537 2845",
    "sg:postcode":"46166",
    "sg:province":"IN",
    "sg:tags":[
        "downspouts",
        "gutter"
    ],
    "wof:name":"Rhude & Son Guttering",
    "wof:placetype":"venue"
},
  "geometry": {"coordinates":[-86.605141,39.404872],"type":"Point"}
}