{
  "type": "Feature",
  "properties": {
    "iso:country":"US",
    "sg:address":"415 Vigo St",
    "sg:city":"Vincennes",
    "sg:classifiers":[
        {
            "category":"Wholesale",
            "subcategory":"Medical Equipment & Supplies",
            "type":"Manufacturing & Wholesale Goods"
        }
    ],
    "sg:phone":"+1 812 882 3636",
    "sg:postcode":"47591",
    "sg:province":"IN",
    "sg:tags":[
        "hospital"
    ],
    "wof:name":"Harmon Medical Supply",
    "wof:placetype":"venue"
},
  "geometry": {"coordinates":[-87.53186,38.677514],"type":"Point"}
}