{
  "type": "Feature",
  "properties": {
    "iso:country":"US",
    "sg:address":"11514 N US Hwy 41",
    "sg:city":"Farmersburg",
    "sg:classifiers":[
        {
            "category":"Restaurant",
            "type":"Food & Drink"
        }
    ],
    "sg:phone":"+1 812 696 2074",
    "sg:postcode":"47850",
    "sg:province":"IN",
    "wof:name":"Oasis Restaurant & Lounge",
    "wof:placetype":"venue"
},
  "geometry": {"coordinates":[-87.388998,39.25167],"type":"Point"}
}