{
  "type": "Feature",
  "properties": {
    "iso:country":"US",
    "sg:address":"300 S 4th St",
    "sg:city":"Jeffersonville",
    "sg:classifiers":[
        {
            "category":"Organizations",
            "subcategory":"Religious Organization",
            "type":"Services"
        }
    ],
    "sg:phone":"+1 812 283 9372",
    "sg:postcode":"47130",
    "sg:province":"IN",
    "sg:tags":[
        "church"
    ],
    "wof:name":"Church Of Christ",
    "wof:placetype":"venue"
},
  "geometry": {"coordinates":[-85.653815,38.333659],"type":"Point"}
}