{
  "type": "Feature",
  "properties": {
    "iso:country":"US",
    "sg:address":"1003 W McGalliard Rd",
    "sg:city":"Muncie",
    "sg:classifiers":[
        {
            "category":"Insurance",
            "subcategory":"Insurance Agent",
            "type":"Services"
        }
    ],
    "sg:phone":"+1 765 284 9767",
    "sg:postcode":"47303",
    "sg:province":"IN",
    "wof:name":"Equitable Life Assurance",
    "wof:placetype":"venue"
},
  "geometry": {"coordinates":[-85.398207,40.218861],"type":"Point"}
}