{
  "type": "Feature",
  "properties": {
    "addr:full":"6045 Calumet Ave Hammond IN 46320",
    "addr:housenumber":"6045",
    "addr:postcode":"46320",
    "addr:street":"Calumet Ave",
    "iso:country":"US",
    "sg:address":"6045 Calumet Ave",
    "sg:city":"Hammond",
    "sg:classifiers":[
        {
            "category":"Food & Beverages",
            "subcategory":"Liquor & Beverages",
            "type":"Retail Goods"
        }
    ],
    "sg:phone":"+1 219 937 4957",
    "sg:postcode":"46320",
    "sg:province":"IN",
    "sg:tags":[
        "beer",
        "spirit",
        "wine"
    ],
    "wof:name":"Dynasty Liquors",
    "wof:placetype":"venue"
},
  "geometry": {"coordinates":[-87.508735,41.60347],"type":"Point"}
}