{
  "type": "Feature",
  "properties": {
    "iso:country":"US",
    "sg:address":"114 W Michigan St",
    "sg:city":"Lagrange",
    "sg:classifiers":[
        {
            "category":"Government",
            "subcategory":"Office",
            "type":"Public Place"
        }
    ],
    "sg:phone":"+1 260 499 6300",
    "sg:postcode":"46761",
    "sg:province":"IN",
    "sg:website":"www.lagrangecounty.org",
    "wof:name":"LA Grange County Office Bldg",
    "wof:placetype":"venue"
},
  "geometry": {"coordinates":[-85.419127,41.644962],"type":"Point"}
}