{
  "type": "Feature",
  "properties": {
    "iso:country":"US",
    "sg:address":"4614 Buena Vista Dr",
    "sg:city":"Indianapolis",
    "sg:classifiers":[
        {
            "category":"Building & Trades",
            "subcategory":"Equipment Rental",
            "type":"Services"
        }
    ],
    "sg:phone":"+1 317 926 5939",
    "sg:postcode":"46228",
    "sg:province":"IN",
    "wof:name":"Kangai Rentals",
    "wof:placetype":"venue"
},
  "geometry": {"coordinates":[-86.191506,39.83943],"type":"Point"}
}