{
  "type": "Feature",
  "properties": {
    "iso:country":"US",
    "sg:address":"6860 Kennedy Ave",
    "sg:city":"Hammond",
    "sg:classifiers":[
        {
            "category":"Autos & Motor Vehicles",
            "subcategory":"Fuel & Gas Station",
            "type":"Retail Goods"
        }
    ],
    "sg:phone":"+1 219 844 0648",
    "sg:postcode":"46323",
    "sg:province":"IN",
    "sg:tags":[
        "oil"
    ],
    "wof:name":"A & R Petroleum",
    "wof:placetype":"venue"
},
  "geometry": {"coordinates":[-87.461713,41.589344],"type":"Point"}
}