{
  "type": "Feature",
  "properties": {
    "iso:country":"US",
    "sg:address":"3565 State Rd 9",
    "sg:city":"Albion",
    "sg:phone":"+1 260 636 2199",
    "sg:postcode":"46701",
    "sg:province":"IN",
    "sg:tags":[
        "gas"
    ],
    "wof:name":"Hoosier Propane",
    "wof:placetype":"venue"
},
  "geometry": {"coordinates":[-85.423219,41.298862],"type":"Point"}
}