{
  "type": "Feature",
  "properties": {
    "iso:country":"US",
    "sg:address":"405 Carpenter St",
    "sg:city":"Evansville",
    "sg:classifiers":[
        {
            "category":"Communications",
            "subcategory":"Television Station",
            "type":"Services"
        }
    ],
    "sg:phone":"+1 812 423 2973",
    "sg:postcode":"47708",
    "sg:province":"IN",
    "sg:tags":[
        "broadcasting",
        "co"
    ],
    "sg:website":"www.wnin.org",
    "wof:name":"WNIN",
    "wof:placetype":"venue"
},
  "geometry": {"coordinates":[-87.576511,37.974718],"type":"Point"}
}