{
  "type": "Feature",
  "properties": {
    "iso:country":"US",
    "sg:address":"8808 Frontenac Rd",
    "sg:city":"Indianapolis",
    "sg:classifiers":[
        {
            "category":"Freight",
            "type":"Transportation"
        }
    ],
    "sg:phone":"+1 317 899 1832",
    "sg:postcode":"46226",
    "sg:province":"IN",
    "sg:tags":[
        "mover"
    ],
    "wof:name":"Plan B",
    "wof:placetype":"venue"
},
  "geometry": {"coordinates":[-86.012886,39.819064],"type":"Point"}
}