{
  "type": "Feature",
  "properties": {
    "addr:full":"618 Beech Dr W Plainfield IN 46168",
    "addr:housenumber":"618",
    "addr:postcode":"46168",
    "addr:street":"Beech Dr W",
    "iso:country":"US",
    "sg:address":"618 Beech Dr W",
    "sg:city":"Plainfield",
    "sg:classifiers":[
        {
            "category":"Banks & Credit Unions",
            "subcategory":"Investment Brokerage",
            "type":"Services"
        },
        {
            "category":"Insurance",
            "subcategory":"Hazard Insurance",
            "type":"Services"
        }
    ],
    "sg:phone":"+1 317 837 0264",
    "sg:postcode":"46168",
    "sg:province":"IN",
    "sg:tags":[
        "agent",
        "resume"
    ],
    "sg:website":"http://www.kinneyassoc.com",
    "wof:name":"Kinney",
    "wof:placetype":"venue"
},
  "geometry": {"coordinates":[-86.379704,39.699411],"type":"Point"}
}