{
  "type": "Feature",
  "properties": {
    "iso:country":"US",
    "sg:address":"2536 Waterbridge Way",
    "sg:city":"Evansville",
    "sg:classifiers":[
        {
            "category":"Social Services",
            "subcategory":"Child Care",
            "type":"Services"
        }
    ],
    "sg:phone":"+1 812 424 7749",
    "sg:postcode":"47710",
    "sg:province":"IN",
    "wof:name":"Bright Beginnings Child Care",
    "wof:placetype":"venue"
},
  "geometry": {"coordinates":[-87.57189,38.00194],"type":"Point"}
}