{
  "type": "Feature",
  "properties": {
    "iso:country":"US",
    "sg:address":"408 Salt Creek Pkwy",
    "sg:city":"Valparaiso",
    "sg:classifiers":[
        {
            "category":"Organizations",
            "subcategory":"Professional Association",
            "type":"Services"
        }
    ],
    "sg:phone":"+1 219 759 4326",
    "sg:postcode":"46385",
    "sg:province":"IN",
    "wof:name":"La Societe Voiture Des 40",
    "wof:placetype":"venue"
},
  "geometry": {"coordinates":[-87.139848,41.510097],"type":"Point"}
}