{
  "type": "Feature",
  "properties": {
    "iso:country":"US",
    "sg:address":"931 6th St",
    "sg:city":"West Lafayette",
    "sg:classifiers":[
        {
            "category":"Organizations",
            "subcategory":"Community Association",
            "type":"Services"
        }
    ],
    "sg:phone":"+1 765 743 6672",
    "sg:postcode":"47906",
    "sg:province":"IN",
    "sg:tags":[
        "sorority",
        "fraternity"
    ],
    "wof:name":"Lambda Chi Alpha",
    "wof:placetype":"venue"
},
  "geometry": {"coordinates":[-86.91760499999999,40.430185],"type":"Point"}
}