{
  "type": "Feature",
  "properties": {
    "iso:country":"US",
    "sg:address":"5545 Farnsley Knob Rd",
    "sg:city":"Elizabeth",
    "sg:classifiers":[
        {
            "category":"Manufacturing",
            "subcategory":"Buildings",
            "type":"Manufacturing & Wholesale Goods"
        }
    ],
    "sg:phone":"+1 812 944 9507",
    "sg:postcode":"47117",
    "sg:province":"IN",
    "sg:tags":[
        "home",
        "log",
        "cabin"
    ],
    "wof:name":"Barna Log Homes Of The Ohio",
    "wof:placetype":"venue"
},
  "geometry": {"coordinates":[-85.91036200000001,38.195987],"type":"Point"}
}