{
  "type": "Feature",
  "properties": {
    "iso:country":"US",
    "sg:address":"420 E Main St",
    "sg:city":"Cambridge City",
    "sg:classifiers":[
        {
            "category":"Home & Garden",
            "subcategory":"Furniture",
            "type":"Retail Goods"
        }
    ],
    "sg:phone":"+1 765 478 4720",
    "sg:postcode":"47327",
    "sg:province":"IN",
    "wof:name":"M & M Furniture Co",
    "wof:placetype":"venue"
},
  "geometry": {"coordinates":[-85.16278,39.81286],"type":"Point"}
}