{
  "type": "Feature",
  "properties": {
    "iso:country":"US",
    "sg:address":"10 Oakview Dr",
    "sg:city":"Monticello",
    "sg:classifiers":[
        {
            "category":"Real Estate",
            "subcategory":"Real Estate Operator",
            "type":"Services"
        }
    ],
    "sg:phone":"+1 574 583 4638",
    "sg:postcode":"47960",
    "sg:province":"IN",
    "sg:tags":[
        "apartment"
    ],
    "wof:name":"Oakview Apartment Co",
    "wof:placetype":"venue"
},
  "geometry": {"coordinates":[-86.769075,40.760252],"type":"Point"}
}