{
  "type": "Feature",
  "properties": {
    "iso:country":"US",
    "sg:address":"5833 Smith Rd",
    "sg:city":"Fort Wayne",
    "sg:classifiers":[
        {
            "category":"Wholesale",
            "subcategory":"Construction Materials",
            "type":"Manufacturing & Wholesale Goods"
        }
    ],
    "sg:phone":"+1 260 747 9141",
    "sg:postcode":"46809",
    "sg:province":"IN",
    "sg:tags":[
        "sand",
        "gravel"
    ],
    "wof:name":"Old Prairie Products Inc",
    "wof:placetype":"venue"
},
  "geometry": {"coordinates":[-85.20781100000001,41.028288],"type":"Point"}
}