{
  "type": "Feature",
  "properties": {
    "iso:country":"US",
    "sg:address":"3508 Stellhorn Rd",
    "sg:city":"Fort Wayne",
    "sg:classifiers":[
        {
            "category":"Wholesale",
            "subcategory":"Stationery",
            "type":"Manufacturing & Wholesale Goods"
        }
    ],
    "sg:phone":"+1 260 637 5490",
    "sg:postcode":"46815",
    "sg:province":"IN",
    "sg:tags":[
        "business",
        "form",
        "system"
    ],
    "wof:name":"Graphic 2000 Forms & Labels",
    "wof:placetype":"venue"
},
  "geometry": {"coordinates":[-85.096613,41.119227],"type":"Point"}
}