{
  "type": "Feature",
  "properties": {
    "addr:full":"1502 S Huntington St Syracuse IN 46567",
    "addr:housenumber":"1502",
    "addr:postcode":"46567",
    "addr:street":"S Huntington St",
    "iso:country":"US",
    "sg:address":"1502 S Huntington St",
    "sg:city":"Syracuse",
    "sg:classifiers":[
        {
            "category":"Farming",
            "subcategory":"Farm",
            "type":"Manufacturing & Wholesale Goods"
        }
    ],
    "sg:phone":"+1 574 457 5528",
    "sg:postcode":"46567",
    "sg:province":"IN",
    "sg:tags":[
        "crop",
        "general"
    ],
    "wof:name":"List Farm LLC",
    "wof:placetype":"venue"
},
  "geometry": {"coordinates":[-85.744286,41.403722],"type":"Point"}
}