{
  "type": "Feature",
  "properties": {
    "addr:full":"305 S Main St Salem IN 47167",
    "addr:housenumber":"305",
    "addr:postcode":"47167",
    "addr:street":"S Main St",
    "iso:country":"US",
    "sg:address":"305 S Main St",
    "sg:city":"Salem",
    "sg:classifiers":[
        {
            "category":"Restaurant",
            "type":"Food & Drink"
        }
    ],
    "sg:phone":"+1 812 883 5744",
    "sg:postcode":"47167",
    "sg:province":"IN",
    "wof:name":"Dinner Bell",
    "wof:placetype":"venue"
},
  "geometry": {"coordinates":[-86.10078,38.603659],"type":"Point"}
}