{
  "type": "Feature",
  "properties": {
    "iso:country":"US",
    "sg:address":"324 N 24th St",
    "sg:city":"Lafayette",
    "sg:classifiers":[
        {
            "category":"Social Services",
            "subcategory":"Child Care",
            "type":"Services"
        }
    ],
    "sg:phone":"+1 765 448 6071",
    "sg:postcode":"47904",
    "sg:province":"IN",
    "sg:tags":[
        "day"
    ],
    "wof:name":"Teresa Remaly",
    "wof:placetype":"venue"
},
  "geometry": {"coordinates":[-86.870093,40.419632],"type":"Point"}
}