{
  "type": "Feature",
  "properties": {
    "iso:country":"US",
    "sg:address":"1050 US Hwy 20",
    "sg:city":"Lagrange",
    "sg:classifiers":[
        {
            "category":"Organizations",
            "subcategory":"Religious Organization",
            "type":"Services"
        }
    ],
    "sg:phone":"+1 260 367 2625",
    "sg:postcode":"46761",
    "sg:province":"IN",
    "wof:name":"East Springfield Untd Methdst",
    "wof:placetype":"venue"
},
  "geometry": {"coordinates":[-85.444435,41.641184],"type":"Point"}
}