{
  "type": "Feature",
  "properties": {
    "iso:country":"US",
    "sg:address":"1913 Melody Ln",
    "sg:city":"Greenfield",
    "sg:classifiers":[
        {
            "category":"Restaurant",
            "type":"Food & Drink"
        }
    ],
    "sg:phone":"+1 317 462 6307",
    "sg:postcode":"46140",
    "sg:province":"IN",
    "wof:name":"Tim's Bakery & Deli",
    "wof:placetype":"venue"
},
  "geometry": {"coordinates":[-85.767951,39.808054],"type":"Point"}
}