{
  "type": "Feature",
  "properties": {
    "iso:country":"US",
    "sg:address":"2234 N Knighthood Grove Rd",
    "sg:city":"Shelbyville",
    "sg:classifiers":[
        {
            "category":"Real Estate",
            "subcategory":"Real Estate Agent",
            "type":"Services"
        }
    ],
    "sg:phone":"+1 317 398 3229",
    "sg:postcode":"46176",
    "sg:province":"IN",
    "wof:name":"American Dream Realty Inc",
    "wof:placetype":"venue"
},
  "geometry": {"coordinates":[-85.75676,39.558173],"type":"Point"}
}