{
  "type": "Feature",
  "properties": {
    "iso:country":"US",
    "sg:address":"8900 Mississippi St",
    "sg:city":"Merrillville",
    "sg:classifiers":[
        {
            "category":"Retail",
            "subcategory":"Repair Shop",
            "type":"Services"
        }
    ],
    "sg:phone":"+1 219 769 9040",
    "sg:postcode":"46410",
    "sg:province":"IN",
    "sg:tags":[
        "valve"
    ],
    "wof:name":"Furmanite America",
    "wof:placetype":"venue"
},
  "geometry": {"coordinates":[-87.316329,41.454975],"type":"Point"}
}