{
  "type": "Feature",
  "properties": {
    "iso:country":"US",
    "sg:address":"608 N Main St",
    "sg:city":"Frankfort",
    "sg:classifiers":[
        {
            "category":"Retail",
            "subcategory":"Funeral Services",
            "type":"Services"
        }
    ],
    "sg:phone":"+1 765 659 3356",
    "sg:postcode":"46041",
    "sg:province":"IN",
    "sg:tags":[
        "director"
    ],
    "wof:name":"Genda Funeral Home",
    "wof:placetype":"venue"
},
  "geometry": {"coordinates":[-86.512124,40.28618],"type":"Point"}
}