{
  "type": "Feature",
  "properties": {
    "iso:country":"US",
    "sg:address":"55807 Cedar Rd",
    "sg:city":"Mishawaka",
    "sg:classifiers":[
        {
            "category":"Building & Trades",
            "subcategory":"Electrical",
            "type":"Services"
        }
    ],
    "sg:phone":"+1 574 256 2403",
    "sg:postcode":"46545",
    "sg:province":"IN",
    "sg:tags":[
        "electric",
        "contractor"
    ],
    "wof:name":"C & K Electric Co",
    "wof:placetype":"venue"
},
  "geometry": {"coordinates":[-86.100139,41.683422],"type":"Point"}
}