{
  "type": "Feature",
  "properties": {
    "iso:country":"US",
    "sg:address":"4299 W 96th St",
    "sg:city":"Indianapolis",
    "sg:classifiers":[
        {
            "category":"Professional",
            "subcategory":"Testing Lab",
            "type":"Services"
        }
    ],
    "sg:phone":"+1 317 228 9400",
    "sg:postcode":"46268",
    "sg:province":"IN",
    "sg:tags":[
        "laboratory"
    ],
    "wof:name":"Severn Trent Labs",
    "wof:placetype":"venue"
},
  "geometry": {"coordinates":[-86.23244699999999,39.926071],"type":"Point"}
}