{
  "type": "Feature",
  "properties": {
    "iso:country":"US",
    "sg:address":"16411 Foxcross Dr",
    "sg:city":"Granger",
    "sg:classifiers":[
        {
            "category":"Retail",
            "subcategory":"Repair Shop",
            "type":"Services"
        }
    ],
    "sg:phone":"+1 574 247 9495",
    "sg:postcode":"46530",
    "sg:province":"IN",
    "sg:tags":[
        "repairing",
        "piano",
        "refinishing"
    ],
    "wof:name":"Kanta Kahn Piano Svc",
    "wof:placetype":"venue"
},
  "geometry": {"coordinates":[-86.189249,41.758604],"type":"Point"}
}