{
  "type": "Feature",
  "properties": {
    "iso:country":"US",
    "sg:address":"9158 N 250 E",
    "sg:city":"Roanoke",
    "sg:classifiers":[
        {
            "category":"Retail",
            "subcategory":"Animal Services",
            "type":"Services"
        }
    ],
    "sg:phone":"+1 260 672 8272",
    "sg:postcode":"46783",
    "sg:province":"IN",
    "sg:tags":[
        "pet",
        "grooming",
        "washing"
    ],
    "wof:name":"Countryside Kennel",
    "wof:placetype":"venue"
},
  "geometry": {"coordinates":[-85.403875,40.965796],"type":"Point"}
}