{
  "type": "Feature",
  "properties": {
    "iso:country":"US",
    "sg:address":"5510 W State Rd 67",
    "sg:city":"Portland",
    "sg:classifiers":[
        {
            "category":"Retail",
            "subcategory":"Auto Repair",
            "type":"Services"
        }
    ],
    "sg:phone":"+1 260 726 2225",
    "sg:postcode":"47371",
    "sg:province":"IN",
    "sg:tags":[
        "repairing",
        "automobile"
    ],
    "wof:name":"Como Service",
    "wof:placetype":"venue"
},
  "geometry": {"coordinates":[-85.083694,40.3859],"type":"Point"}
}