{
  "type": "Feature",
  "properties": {
    "iso:country":"US",
    "sg:address":"335 N Wayne St",
    "sg:city":"Waterloo",
    "sg:classifiers":[
        {
            "category":"Retail",
            "subcategory":"Animal Services",
            "type":"Services"
        }
    ],
    "sg:phone":"+1 260 837 3090",
    "sg:postcode":"46793",
    "sg:province":"IN",
    "sg:tags":[
        "pet",
        "grooming",
        "washing"
    ],
    "wof:name":"Waggin Tails Pet Salon",
    "wof:placetype":"venue"
},
  "geometry": {"coordinates":[-85.02005200000001,41.432889],"type":"Point"}
}