{
  "type": "Feature",
  "properties": {
    "addr:full":"802 Spring Mill Ln Indianapolis IN 46260",
    "addr:housenumber":"802",
    "addr:postcode":"46260",
    "addr:street":"Spring Mill Ln",
    "iso:country":"US",
    "sg:address":"802 Spring Mill Ln",
    "sg:city":"Indianapolis",
    "sg:classifiers":[
        {
            "category":"Professional",
            "type":"Services"
        }
    ],
    "sg:phone":"+1 317 251 0756",
    "sg:postcode":"46260",
    "sg:province":"IN",
    "wof:name":"Broad Rpple Alnce For Progress",
    "wof:placetype":"venue"
},
  "geometry": {"coordinates":[-86.172631,39.89109],"type":"Point"}
}