{
  "type": "Feature",
  "properties": {
    "iso:country":"US",
    "sg:address":"2220 Spear St",
    "sg:city":"Logansport",
    "sg:classifiers":[
        {
            "category":"Professional",
            "subcategory":"Computer Services",
            "type":"Services"
        }
    ],
    "sg:phone":"+1 574 753 9494",
    "sg:postcode":"46947",
    "sg:province":"IN",
    "sg:tags":[
        "repair"
    ],
    "wof:name":"Computer Doctor",
    "wof:placetype":"venue"
},
  "geometry": {"coordinates":[-86.338759,40.756348],"type":"Point"}
}