{
  "type": "Feature",
  "properties": {
    "iso:country":"US",
    "sg:address":"539 Broadway",
    "sg:city":"Chesterton",
    "sg:classifiers":[
        {
            "category":"Building & Trades",
            "subcategory":"Construction",
            "type":"Services"
        }
    ],
    "sg:phone":"+1 219 929 6492",
    "sg:postcode":"46304",
    "sg:province":"IN",
    "sg:tags":[
        "insulation",
        "heat",
        "contractor"
    ],
    "wof:name":"Coleman's Insulation Co",
    "wof:placetype":"venue"
},
  "geometry": {"coordinates":[-87.058376,41.611176],"type":"Point"}
}