{
  "type": "Feature",
  "properties": {
    "addr:full":"1530 N Co Rd 1050 E Indianapolis IN 46234",
    "addr:housenumber":"1530;1050 e",
    "addr:postcode":"46234",
    "addr:street":"N Co Rd",
    "iso:country":"US",
    "sg:address":"1530 N Co Rd 1050 E",
    "sg:city":"Indianapolis",
    "sg:classifiers":[
        {
            "category":"Wholesale",
            "subcategory":"Machinery & Supplies",
            "type":"Manufacturing & Wholesale Goods"
        }
    ],
    "sg:phone":"+1 317 894 0666",
    "sg:postcode":"46234",
    "sg:province":"IN",
    "sg:tags":[
        "vacuum",
        "system",
        "cleaning"
    ],
    "wof:name":"Consolidated Central Vacuum",
    "wof:placetype":"venue"
},
  "geometry": {"coordinates":[-86.336061,39.785952],"type":"Point"}
}