{
  "type": "Feature",
  "properties": {
    "iso:country":"US",
    "sg:address":"4702 Calumet Ave",
    "sg:city":"Hammond",
    "sg:classifiers":[
        {
            "category":"Food & Beverages",
            "subcategory":"Liquor & Beverages",
            "type":"Retail Goods"
        }
    ],
    "sg:phone":"+1 219 933 4702",
    "sg:postcode":"46327",
    "sg:province":"IN",
    "wof:name":"Nick's Liquor Mart",
    "wof:placetype":"venue"
},
  "geometry": {"coordinates":[-87.508872,41.626566],"type":"Point"}
}