{
  "type": "Feature",
  "properties": {
    "addr:full":"13490 N 100 W Perrysville IN 47974",
    "addr:housenumber":"13490",
    "addr:postcode":"47974",
    "addr:street":"N 100 W",
    "iso:country":"US",
    "sg:address":"13490 N 100 W",
    "sg:city":"Perrysville",
    "sg:classifiers":[
        {
            "category":"Manufacturing",
            "subcategory":"Food",
            "type":"Manufacturing & Wholesale Goods"
        },
        {
            "category":"Farming",
            "subcategory":"Farm",
            "type":"Manufacturing & Wholesale Goods"
        }
    ],
    "sg:phone":"+1 765 793 4160",
    "sg:postcode":"47974",
    "sg:province":"IN",
    "sg:tags":[
        "corn",
        "product"
    ],
    "wof:name":"Kevin Barnes",
    "wof:placetype":"venue"
},
  "geometry": {"coordinates":[-87.490211,40.079849],"type":"Point"}
}