{
  "type": "Feature",
  "properties": {
    "iso:country":"US",
    "sg:address":"5501 W 86th St",
    "sg:city":"Indianapolis",
    "sg:classifiers":[
        {
            "category":"Sports & Exercise",
            "subcategory":"Swimming Pool",
            "type":"Entertainment"
        }
    ],
    "sg:phone":"+1 317 297 2822",
    "sg:postcode":"46268",
    "sg:province":"IN",
    "sg:tags":[
        "diving",
        "instruction"
    ],
    "wof:name":"Diver's Supply Indy",
    "wof:placetype":"venue"
},
  "geometry": {"coordinates":[-86.257594,39.910713],"type":"Point"}
}