{
  "type": "Feature",
  "properties": {
    "iso:country":"US",
    "sg:address":"814 Development Dr",
    "sg:city":"Tipton",
    "sg:classifiers":[
        {
            "category":"Freight",
            "type":"Transportation"
        }
    ],
    "sg:phone":"+1 765 675 2975",
    "sg:postcode":"46072",
    "sg:province":"IN",
    "sg:tags":[
        "hauling",
        "trucking"
    ],
    "wof:name":"Weismiller Trucking",
    "wof:placetype":"venue"
},
  "geometry": {"coordinates":[-86.050758,40.294701],"type":"Point"}
}