{
  "type": "Feature",
  "properties": {
    "iso:country":"US",
    "sg:address":"1305 N Delaware St",
    "sg:city":"Indianapolis",
    "sg:classifiers":[
        {
            "category":"Organizations",
            "subcategory":"Community Association",
            "type":"Services"
        }
    ],
    "sg:phone":"+1 317 631 4373",
    "sg:postcode":"46202",
    "sg:province":"IN",
    "sg:tags":[
        "fraternal"
    ],
    "wof:name":"Knights Of Columbus",
    "wof:placetype":"venue"
},
  "geometry": {"coordinates":[-86.15389500000001,39.785344],"type":"Point"}
}