{
  "type": "Feature",
  "properties": {
    "iso:country":"US",
    "sg:address":"14299 Clay Terrace Blvd",
    "sg:city":"Carmel",
    "sg:classifiers":[
        {
            "category":"Shopping",
            "subcategory":"Gifts & Souvenirs",
            "type":"Retail Goods"
        }
    ],
    "sg:phone":"+1 317 846 8250",
    "sg:postcode":"46032",
    "sg:province":"IN",
    "sg:tags":[
        "shop"
    ],
    "wof:name":"Eclectic Corner",
    "wof:placetype":"venue"
},
  "geometry": {"coordinates":[-86.12863299999999,39.995279],"type":"Point"}
}