{
  "type": "Feature",
  "properties": {
    "iso:country":"US",
    "sg:address":"325 E Main St",
    "sg:city":"Brownsburg",
    "sg:classifiers":[
        {
            "category":"Social Services",
            "subcategory":"Child Care",
            "type":"Services"
        }
    ],
    "sg:phone":"+1 317 852 2273",
    "sg:postcode":"46112",
    "sg:province":"IN",
    "sg:website":"www.knowledgelearning.com",
    "wof:name":"Learning Universe",
    "wof:placetype":"venue"
},
  "geometry": {"coordinates":[-86.392027,39.841654],"type":"Point"}
}