{
  "type": "Feature",
  "properties": {
    "addr:full":"501 S 9th St Noblesville IN 46060",
    "addr:housenumber":"501",
    "addr:postcode":"46060",
    "addr:street":"S 9Th St",
    "iso:country":"US",
    "sg:address":"501 S 9th St",
    "sg:city":"Noblesville",
    "sg:classifiers":[
        {
            "category":"Organizations",
            "subcategory":"Professional Association",
            "type":"Services"
        }
    ],
    "sg:phone":"+1 317 776 1519",
    "sg:postcode":"46060",
    "sg:province":"IN",
    "wof:name":"Cancer Service",
    "wof:placetype":"venue"
},
  "geometry": {"coordinates":[-86.013453,40.041604],"type":"Point"}
}