{
  "type": "Feature",
  "properties": {
    "addr:full":"2010 W 86th St Suite 105 Indianapolis IN 46260",
    "addr:housenumber":"2010",
    "addr:postcode":"46260",
    "addr:street":"W 86Th St Suite 105",
    "iso:country":"US",
    "sg:address":"2010 W 86th St Suite 105",
    "sg:city":"Indianapolis",
    "sg:classifiers":[
        {
            "category":"Health Services",
            "subcategory":"Hospital",
            "type":"Services"
        },
        {
            "category":"Health Services",
            "subcategory":"Dentist",
            "type":"Services"
        }
    ],
    "sg:phone":"+1 317 329 7667",
    "sg:postcode":"46260",
    "sg:province":"IN",
    "sg:tags":[
        "dental",
        "clinic",
        "sleep",
        "treatment",
        "disorders-information"
    ],
    "sg:website":"http://www.indysmiles.com",
    "wof:name":"Dr Llewellyn/ Indy Smiles",
    "wof:placetype":"venue"
},
  "geometry": {"coordinates":[-86.19644599999999,39.912108],"type":"Point"}
}