{
  "type": "Feature",
  "properties": {
    "iso:country":"US",
    "sg:address":"153 W Gould St",
    "sg:city":"Nashville",
    "sg:classifiers":[
        {
            "category":"Real Estate",
            "subcategory":"Real Estate Agent",
            "type":"Services"
        }
    ],
    "sg:phone":"+1 812 988 6216",
    "sg:postcode":"47448",
    "sg:province":"IN",
    "sg:tags":[
        "appraiser"
    ],
    "wof:name":"South Central Appraisal Assoc",
    "wof:placetype":"venue"
},
  "geometry": {"coordinates":[-86.249389,39.208361],"type":"Point"}
}