{
  "type": "Feature",
  "properties": {
    "iso:country":"US",
    "sg:address":"2305 Rolling Hill Dr",
    "sg:city":"Dyer",
    "sg:classifiers":[
        {
            "category":"Education",
            "subcategory":"Special Training",
            "type":"Public Place"
        }
    ],
    "sg:phone":"+1 219 864 9282",
    "sg:postcode":"46311",
    "sg:province":"IN",
    "wof:name":"Esi Continuing Education",
    "wof:placetype":"venue"
},
  "geometry": {"coordinates":[-87.504661,41.487789],"type":"Point"}
}