{
  "type": "Feature",
  "properties": {
    "iso:country":"US",
    "sg:address":"11234 E Washington St",
    "sg:city":"Indianapolis",
    "sg:classifiers":[
        {
            "category":"Retail",
            "subcategory":"Laundry & Dry Cleaning",
            "type":"Services"
        }
    ],
    "sg:phone":"+1 317 891 0520",
    "sg:postcode":"46229",
    "sg:province":"IN",
    "sg:tags":[
        "cleaners"
    ],
    "wof:name":"Deering Cleaners",
    "wof:placetype":"venue"
},
  "geometry": {"coordinates":[-85.967455,39.775974],"type":"Point"}
}