{
  "type": "Feature",
  "properties": {
    "iso:country":"US",
    "sg:address":"800 E Dallas Dr",
    "sg:city":"Terre Haute",
    "sg:classifiers":[
        {
            "category":"Government",
            "subcategory":"Fire Station",
            "type":"Public Place"
        }
    ],
    "sg:phone":"+1 812 298 1966",
    "sg:postcode":"47802",
    "sg:province":"IN",
    "sg:tags":[
        "department"
    ],
    "wof:name":"Honey Creek Fire Dept",
    "wof:placetype":"venue"
},
  "geometry": {"coordinates":[-87.40293,39.361505],"type":"Point"}
}