{
  "type": "Feature",
  "properties": {
    "iso:country":"US",
    "sg:address":"7022 State Rd 311",
    "sg:city":"Sellersburg",
    "sg:classifiers":[
        {
            "category":"Freight",
            "type":"Transportation"
        }
    ],
    "sg:phone":"+1 812 246 8948",
    "sg:postcode":"47172",
    "sg:province":"IN",
    "sg:tags":[
        "commercial",
        "storage"
    ],
    "sg:website":"www.thestoragestation.com",
    "wof:name":"Storage Station",
    "wof:placetype":"venue"
},
  "geometry": {"coordinates":[-85.772819,38.373696],"type":"Point"}
}