{
  "type": "Feature",
  "properties": {
    "iso:country":"US",
    "sg:address":"2001 N Hunt St",
    "sg:city":"Terre Haute",
    "sg:classifiers":[
        {
            "category":"Manufacturing",
            "subcategory":"Printing",
            "type":"Manufacturing & Wholesale Goods"
        }
    ],
    "sg:phone":"+1 812 877 3764",
    "sg:postcode":"47805",
    "sg:province":"IN",
    "sg:tags":[
        "commercial"
    ],
    "wof:name":"Discount Labels Inc",
    "wof:placetype":"venue"
},
  "geometry": {"coordinates":[-87.31425,39.490661],"type":"Point"}
}