{
  "type": "Feature",
  "properties": {
    "iso:country":"US",
    "sg:address":"2219 Oak Ln",
    "sg:city":"Gary",
    "sg:classifiers":[
        {
            "category":"Professional",
            "subcategory":"Business Services",
            "type":"Services"
        }
    ],
    "sg:phone":"+1 219 980 2608",
    "sg:postcode":"46408",
    "sg:province":"IN",
    "sg:tags":[
        "financial"
    ],
    "wof:name":"Tight Corp",
    "wof:placetype":"venue"
},
  "geometry": {"coordinates":[-87.363002,41.542389],"type":"Point"}
}