{
  "type": "Feature",
  "properties": {
    "iso:country":"US",
    "sg:address":"2728 Westlane Rd",
    "sg:city":"Indianapolis",
    "sg:classifiers":[
        {
            "category":"Professional",
            "subcategory":"Employment Agencies",
            "type":"Services"
        }
    ],
    "sg:phone":"+1 317 329 0829",
    "sg:postcode":"46268",
    "sg:province":"IN",
    "sg:tags":[
        "opportunity"
    ],
    "wof:name":"Labor Ready Inc",
    "wof:placetype":"venue"
},
  "geometry": {"coordinates":[-86.204184,39.886139],"type":"Point"}
}