{
  "type": "Feature",
  "properties": {
    "iso:country":"US",
    "sg:address":"4787 N Post Rd",
    "sg:city":"Indianapolis",
    "sg:classifiers":[
        {
            "category":"Personal",
            "subcategory":"Beauty Salon",
            "type":"Services"
        }
    ],
    "sg:phone":"+1 317 890 0365",
    "sg:postcode":"46226",
    "sg:province":"IN",
    "wof:name":"Hana Salon Hair Care-Men Woman",
    "wof:placetype":"venue"
},
  "geometry": {"coordinates":[-86.010216,39.842165],"type":"Point"}
}