{
  "type": "Feature",
  "properties": {
    "iso:country":"US",
    "sg:address":"1370 Nealon Dr",
    "sg:city":"Portage",
    "sg:classifiers":[
        {
            "category":"Professional",
            "subcategory":"Business Services",
            "type":"Services"
        }
    ],
    "sg:phone":"+1 219 764 4787",
    "sg:postcode":"46368",
    "sg:province":"IN",
    "wof:name":"Ppsa Inc",
    "wof:placetype":"venue"
},
  "geometry": {"coordinates":[-87.172487,41.611077],"type":"Point"}
}