{
  "type": "Feature",
  "properties": {
    "iso:country":"US",
    "sg:address":"108 Eastshore Ct",
    "sg:city":"Laporte",
    "sg:classifiers":[
        {
            "category":"Home & Garden",
            "subcategory":"Garden Supply",
            "type":"Retail Goods"
        }
    ],
    "sg:phone":"+1 219 362 6000",
    "sg:postcode":"46350",
    "sg:province":"IN",
    "sg:tags":[
        "landscaping",
        "equipment"
    ],
    "wof:name":"Rigg's Mowers & More",
    "wof:placetype":"venue"
},
  "geometry": {"coordinates":[-86.73564500000001,41.629992],"type":"Point"}
}