{
  "type": "Feature",
  "properties": {
    "addr:full":"4101 Alden Ave Indianapolis IN 46221",
    "addr:housenumber":"4101",
    "addr:postcode":"46221",
    "addr:street":"Alden Ave",
    "iso:country":"US",
    "sg:address":"4101 Alden Ave",
    "sg:city":"Indianapolis",
    "sg:classifiers":[
        {
            "category":"Wholesale",
            "subcategory":"Toys & Hobbies",
            "type":"Manufacturing & Wholesale Goods"
        }
    ],
    "sg:phone":"+1 317 486 1676",
    "sg:postcode":"46221",
    "sg:province":"IN",
    "sg:tags":[
        "firework"
    ],
    "wof:name":"Circle City Pyrotechnics Inc",
    "wof:placetype":"venue"
},
  "geometry": {"coordinates":[-86.231874,39.710703],"type":"Point"}
}