{
  "type": "Feature",
  "properties": {
    "iso:country":"US",
    "sg:address":"8235 Lafayette Rd",
    "sg:city":"Indianapolis",
    "sg:classifiers":[
        {
            "category":"Freight",
            "type":"Transportation"
        }
    ],
    "sg:phone":"+1 317 291 5260",
    "sg:postcode":"46278",
    "sg:province":"IN",
    "sg:tags":[
        "trucking"
    ],
    "wof:name":"Goodwin Express Inc",
    "wof:placetype":"venue"
},
  "geometry": {"coordinates":[-86.307395,39.904646],"type":"Point"}
}