{
  "type": "Feature",
  "properties": {
    "addr:full":"3502 Washington Ave Evansville IN 47714",
    "addr:housenumber":"3502",
    "addr:postcode":"47714",
    "addr:street":"Washington Ave",
    "iso:country":"US",
    "sg:address":"3502 Washington Ave",
    "sg:city":"Evansville",
    "sg:classifiers":[
        {
            "category":"Health Services",
            "subcategory":"Doctor",
            "type":"Services"
        }
    ],
    "sg:phone":"+1 812 477 0323",
    "sg:postcode":"47714",
    "sg:province":"IN",
    "sg:tags":[
        "dentist"
    ],
    "wof:name":"Joseph L Fox DDS LTD",
    "wof:placetype":"venue"
},
  "geometry": {"coordinates":[-87.50421,37.962462],"type":"Point"}
}