{
  "type": "Feature",
  "properties": {
    "iso:country":"US",
    "sg:address":"2814 E 38th St",
    "sg:city":"Indianapolis",
    "sg:classifiers":[
        {
            "category":"Personal",
            "subcategory":"Beauty Salon",
            "type":"Services"
        },
        {
            "category":"Personal",
            "subcategory":"Barber",
            "type":"Services"
        },
        {
            "category":"Shopping",
            "subcategory":"Beauty & Cosmetics",
            "type":"Retail Goods"
        }
    ],
    "sg:phone":"+1 317 543 2888",
    "sg:postcode":"46218",
    "sg:province":"IN",
    "sg:tags":[
        "equipment",
        "salons-equipment",
        "supply"
    ],
    "wof:name":"King's Fashions",
    "wof:placetype":"venue"
},
  "geometry": {"coordinates":[-86.116699,39.82534],"type":"Point"}
}