{
  "type": "Feature",
  "properties": {
    "iso:country":"US",
    "sg:address":"520 N Main St",
    "sg:city":"Tipton",
    "sg:classifiers":[
        {
            "category":"Utilities",
            "subcategory":"Refuse",
            "type":"Services"
        }
    ],
    "sg:phone":"+1 765 675 3985",
    "sg:postcode":"46072",
    "sg:province":"IN",
    "sg:tags":[
        "system"
    ],
    "wof:name":"Tipton Yard",
    "wof:placetype":"venue"
},
  "geometry": {"coordinates":[-86.041146,40.289739],"type":"Point"}
}