{
  "type": "Feature",
  "properties": {
    "iso:country":"US",
    "sg:address":"4440 N 750 W",
    "sg:city":"Rochester",
    "sg:classifiers":[
        {
            "category":"Home & Garden",
            "subcategory":"Building Materials",
            "type":"Retail Goods"
        }
    ],
    "sg:phone":"+1 574 542 4411",
    "sg:postcode":"46975",
    "sg:province":"IN",
    "sg:tags":[
        "mixed",
        "concrete"
    ],
    "wof:name":"Aggregate Industrys",
    "wof:placetype":"venue"
},
  "geometry": {"coordinates":[-86.385902,41.121538],"type":"Point"}
}