{
  "type": "Feature",
  "properties": {
    "iso:country":"US",
    "sg:address":"3201 W Western Ave",
    "sg:city":"South Bend",
    "sg:classifiers":[
        {
            "category":"Autos & Motor Vehicles",
            "subcategory":"Automobile Sales",
            "type":"Retail Goods"
        }
    ],
    "sg:phone":"+1 574 288 8875",
    "sg:postcode":"46619",
    "sg:province":"IN",
    "sg:tags":[
        "car",
        "dealer"
    ],
    "wof:name":"Hot Wheels",
    "wof:placetype":"venue"
},
  "geometry": {"coordinates":[-86.294822,41.671963],"type":"Point"}
}