{
  "type": "Feature",
  "properties": {
    "addr:full":"320 Indianapolis Blvd Schererville IN 46375",
    "addr:housenumber":"320",
    "addr:postcode":"46375",
    "addr:street":"Indianapolis Blvd",
    "iso:country":"US",
    "sg:address":"320 Indianapolis Blvd",
    "sg:city":"Schererville",
    "sg:classifiers":[
        {
            "category":"Food & Beverages",
            "subcategory":"Bakery",
            "type":"Retail Goods"
        }
    ],
    "sg:phone":"+1 219 322 0800",
    "sg:postcode":"46375",
    "sg:province":"IN",
    "sg:tags":[
        "doughnut"
    ],
    "sg:website":"www.sweettradition.com",
    "wof:name":"Krispy Kreme Doughnuts",
    "wof:placetype":"venue"
},
  "geometry": {"coordinates":[-87.471312,41.516015],"type":"Point"}
}