{
  "type": "Feature",
  "properties": {
    "iso:country":"US",
    "sg:address":"3360 Louise Ave",
    "sg:city":"Indianapolis",
    "sg:classifiers":[
        {
            "category":"Real Estate",
            "subcategory":"Real Estate Agent",
            "type":"Services"
        }
    ],
    "sg:phone":"+1 317 329 7704",
    "sg:postcode":"46234",
    "sg:province":"IN",
    "wof:name":"Eagle Eye Building Inspection",
    "wof:placetype":"venue"
},
  "geometry": {"coordinates":[-86.31511500000001,39.81516],"type":"Point"}
}