{
  "type": "Feature",
  "properties": {
    "iso:country":"US",
    "sg:address":"2700 US Hwy 231 S",
    "sg:city":"Lafayette",
    "sg:classifiers":[
        {
            "category":"Food & Beverages",
            "subcategory":"Groceries & Convenience Stores",
            "type":"Retail Goods"
        }
    ],
    "sg:phone":"+1 765 474 9578",
    "sg:postcode":"47909",
    "sg:province":"IN",
    "wof:name":"Goodnight Southside Shell",
    "wof:placetype":"venue"
},
  "geometry": {"coordinates":[-86.918992,40.38783],"type":"Point"}
}