{
  "type": "Feature",
  "properties": {
    "iso:country":"US",
    "sg:address":"2746 E 1400 North Rd",
    "sg:city":"Sheldon",
    "sg:phone":"+1 815 429 3150",
    "sg:postcode":"60966",
    "sg:province":"IN",
    "sg:tags":[
        "farm",
        "corn",
        "soybean"
    ],
    "wof:name":"Ronald Kollman",
    "wof:placetype":"venue"
},
  "geometry": {"coordinates":[-87.609972,40.717318],"type":"Point"}
}