{
  "type": "Feature",
  "properties": {
    "iso:country":"US",
    "sg:address":"17 S Vine St",
    "sg:city":"Greencastle",
    "sg:classifiers":[
        {
            "category":"Shopping",
            "subcategory":"Florist",
            "type":"Retail Goods"
        }
    ],
    "sg:phone":"+1 765 653 3171",
    "sg:postcode":"46135",
    "sg:province":"IN",
    "sg:website":"www.eitelsflowers.com",
    "wof:name":"Eitel Flowers & Gifts",
    "wof:placetype":"venue"
},
  "geometry": {"coordinates":[-86.863411,39.64388],"type":"Point"}
}