{
  "type": "Feature",
  "properties": {
    "iso:country":"US",
    "sg:address":"18140 State Rd 331",
    "sg:city":"Tippecanoe",
    "sg:classifiers":[
        {
            "category":"Home & Garden",
            "subcategory":"Building Materials",
            "type":"Retail Goods"
        }
    ],
    "sg:phone":"+1 574 498 6022",
    "sg:postcode":"46570",
    "sg:province":"IN",
    "sg:tags":[
        "truss"
    ],
    "wof:name":"Premier Truss & Lumber Co",
    "wof:placetype":"venue"
},
  "geometry": {"coordinates":[-86.114929,41.213609],"type":"Point"}
}