{
  "type": "Feature",
  "properties": {
    "iso:country":"US",
    "sg:address":"1702 Fairfield Ave",
    "sg:city":"Fort Wayne",
    "sg:classifiers":[
        {
            "category":"Retail",
            "subcategory":"Repair Shop",
            "type":"Services"
        }
    ],
    "sg:phone":"+1 260 744 2151",
    "sg:postcode":"46802",
    "sg:province":"IN",
    "sg:tags":[
        "equipment",
        "heating",
        "system"
    ],
    "wof:name":"Rolf & Griffin",
    "wof:placetype":"venue"
},
  "geometry": {"coordinates":[-85.145445,41.06955],"type":"Point"}
}