{
  "type": "Feature",
  "properties": {
    "addr:full":"1299 E Morgan St Kokomo IN 46901",
    "addr:housenumber":"1299",
    "addr:postcode":"46901",
    "addr:street":"E Morgan St",
    "iso:country":"US",
    "sg:address":"1299 E Morgan St",
    "sg:city":"Kokomo",
    "sg:classifiers":[
        {
            "category":"Shopping",
            "subcategory":"Tobacco",
            "type":"Retail Goods"
        }
    ],
    "sg:phone":"+1 765 457 4056",
    "sg:postcode":"46901",
    "sg:province":"IN",
    "sg:tags":[
        "cigarette",
        "cigar",
        "dealer"
    ],
    "wof:name":"Bob Low Tobacco Central",
    "wof:placetype":"venue"
},
  "geometry": {"coordinates":[-86.11568200000001,40.505579],"type":"Point"}
}