{
  "type": "Feature",
  "properties": {
    "addr:full":"411 S Range Line Rd Carmel IN 46032",
    "addr:housenumber":"411",
    "addr:postcode":"46032",
    "addr:street":"S Range Line Rd",
    "iso:country":"US",
    "sg:address":"411 S Range Line Rd",
    "sg:city":"Carmel",
    "sg:classifiers":[
        {
            "category":"Real Estate",
            "subcategory":"Real Estate Agent",
            "type":"Services"
        }
    ],
    "sg:phone":"+1 317 848 2670",
    "sg:postcode":"46032",
    "sg:province":"IN",
    "sg:tags":[
        "consultant"
    ],
    "wof:name":"Land Inc",
    "wof:placetype":"venue"
},
  "geometry": {"coordinates":[-86.126977,39.974461],"type":"Point"}
}