{
  "type": "Feature",
  "properties": {
    "iso:country":"US",
    "sg:address":"9732 S 550 W",
    "sg:city":"Lafayette",
    "sg:classifiers":[
        {
            "category":"Retail",
            "subcategory":"Repair Shop",
            "type":"Services"
        }
    ],
    "sg:phone":"+1 765 538 2090",
    "sg:postcode":"47909",
    "sg:province":"IN",
    "sg:tags":[
        "welding"
    ],
    "wof:name":"Moffett's Welding",
    "wof:placetype":"venue"
},
  "geometry": {"coordinates":[-87.008314,40.276397],"type":"Point"}
}