{
  "type": "Feature",
  "properties": {
    "addr:full":"11107 Thiel Saint John IN 46373",
    "addr:housenumber":"11107",
    "addr:postcode":"46373",
    "addr:street":"Thiel Saint",
    "iso:country":"US",
    "sg:address":"11107 Thiel",
    "sg:city":"Saint John",
    "sg:classifiers":[
        {
            "category":"Arts & Performance",
            "subcategory":"Art Gallery",
            "type":"Entertainment"
        }
    ],
    "sg:phone":"+1 219 365 1014",
    "sg:postcode":"46373",
    "sg:province":"IN",
    "wof:name":"Steeple Gallery the",
    "wof:placetype":"venue"
},
  "geometry": {"coordinates":[-87.47399900000001,41.4394],"type":"Point"}
}