{
  "type": "Feature",
  "properties": {
    "addr:full":"320 Lone Oak Dr New Albany IN 47150",
    "addr:housenumber":"320",
    "addr:postcode":"47150",
    "addr:street":"Lone Oak Dr",
    "iso:country":"US",
    "sg:address":"320 Lone Oak Dr",
    "sg:city":"New Albany",
    "sg:classifiers":[
        {
            "category":"Professional",
            "subcategory":"Management & Consulting",
            "type":"Services"
        }
    ],
    "sg:phone":"+1 812 944 5532",
    "sg:postcode":"47150",
    "sg:province":"IN",
    "sg:tags":[
        "business"
    ],
    "wof:name":"Sentinel Safety Consulting LLC",
    "wof:placetype":"venue"
},
  "geometry": {"coordinates":[-85.852555,38.269944],"type":"Point"}
}