{
  "type": "Feature",
  "properties": {
    "addr:full":"6111 Shelby St Indianapolis IN 46227",
    "addr:housenumber":"6111",
    "addr:postcode":"46227",
    "addr:street":"Shelby St",
    "iso:country":"US",
    "sg:address":"6111 Shelby St",
    "sg:city":"Indianapolis",
    "sg:classifiers":[
        {
            "category":"Organizations",
            "subcategory":"Religious Organization",
            "type":"Services"
        }
    ],
    "sg:phone":"+1 317 783 2000",
    "sg:postcode":"46227",
    "sg:province":"IN",
    "sg:tags":[
        "church"
    ],
    "sg:website":"www.clcs.org",
    "wof:name":"Calvary Lutheran Church",
    "wof:placetype":"venue"
},
  "geometry": {"coordinates":[-86.139383,39.678107],"type":"Point"}
}