{
  "type": "Feature",
  "properties": {
    "iso:country":"US",
    "sg:address":"701 Portage Ct",
    "sg:city":"South Bend",
    "sg:classifiers":[
        {
            "category":"Arts & Performance",
            "subcategory":"Theater",
            "type":"Entertainment"
        }
    ],
    "sg:phone":"+1 574 234 1112",
    "sg:postcode":"46616",
    "sg:province":"IN",
    "wof:name":"South Bend Civic Theatre",
    "wof:placetype":"venue"
},
  "geometry": {"coordinates":[-86.259836,41.686568],"type":"Point"}
}