{
  "type": "Feature",
  "properties": {
    "addr:full":"7201 Mill Run Rd Fort Wayne IN 46819",
    "addr:housenumber":"7201",
    "addr:postcode":"46819",
    "addr:street":"Mill Run Rd",
    "iso:country":"US",
    "sg:address":"7201 Mill Run Rd",
    "sg:city":"Fort Wayne",
    "sg:classifiers":[
        {
            "category":"Banks & Credit Unions",
            "subcategory":"Investment Brokerage",
            "type":"Services"
        }
    ],
    "sg:phone":"+1 260 478 7060",
    "sg:postcode":"46819",
    "sg:province":"IN",
    "sg:tags":[
        "advisory",
        "financial"
    ],
    "wof:name":"Fort Wayne Financial Svc",
    "wof:placetype":"venue"
},
  "geometry": {"coordinates":[-85.151427,41.01748],"type":"Point"}
}