{
  "type": "Feature",
  "properties": {
    "iso:country":"US",
    "sg:address":"180 S West St",
    "sg:city":"Crown Point",
    "sg:classifiers":[
        {
            "category":"Banks & Credit Unions",
            "subcategory":"Bank",
            "type":"Services"
        }
    ],
    "sg:phone":"+1 219 662 2074",
    "sg:postcode":"46307",
    "sg:province":"IN",
    "sg:tags":[
        "financing"
    ],
    "wof:name":"MSC Financial Inc",
    "wof:placetype":"venue"
},
  "geometry": {"coordinates":[-87.366545,41.417091],"type":"Point"}
}