{
  "type": "Feature",
  "properties": {
    "addr:full":"1640 E Sycamore St Kokomo IN 46901",
    "addr:housenumber":"1640",
    "addr:postcode":"46901",
    "addr:street":"E Sycamore St",
    "iso:country":"US",
    "sg:address":"1640 E Sycamore St",
    "sg:city":"Kokomo",
    "sg:classifiers":[
        {
            "category":"Banks & Credit Unions",
            "subcategory":"Bank",
            "type":"Services"
        }
    ],
    "sg:phone":"+1 765 459 3911",
    "sg:postcode":"46901",
    "sg:province":"IN",
    "wof:name":"First National Bank & Trust",
    "wof:placetype":"venue"
},
  "geometry": {"coordinates":[-86.103095,40.490742],"type":"Point"}
}