{
  "type": "Feature",
  "properties": {
    "iso:country":"US",
    "sg:address":"302 N Main St",
    "sg:city":"Goshen",
    "sg:classifiers":[
        {
            "category":"Professional",
            "subcategory":"Computer Services",
            "type":"Services"
        }
    ],
    "sg:phone":"+1 574 533 5588",
    "sg:postcode":"46528",
    "sg:province":"IN",
    "sg:tags":[
        "internet"
    ],
    "wof:name":"Cash Cow",
    "wof:placetype":"venue"
},
  "geometry": {"coordinates":[-85.834508,41.590074],"type":"Point"}
}