{
  "type": "Feature",
  "properties": {
    "iso:country":"US",
    "sg:address":"230 N Main St",
    "sg:city":"Elkhart",
    "sg:classifiers":[
        {
            "category":"Professional",
            "subcategory":"Lawyer & Legal Services",
            "type":"Services"
        }
    ],
    "sg:phone":"+1 574 296 1515",
    "sg:postcode":"46516",
    "sg:province":"IN",
    "sg:tags":[
        "attorney"
    ],
    "sg:website":"www.chesterlawoffice.com",
    "wof:name":"Edward J Chester Law Office",
    "wof:placetype":"venue"
},
  "geometry": {"coordinates":[-85.974046,41.688421],"type":"Point"}
}