{
  "type": "Feature",
  "properties": {
    "iso:country":"US",
    "sg:address":"1231 Roosevelt Ave",
    "sg:city":"Indianapolis",
    "sg:classifiers":[
        {
            "category":"Retail",
            "subcategory":"Repair Shop",
            "type":"Services"
        }
    ],
    "sg:phone":"+1 317 383 1000",
    "sg:postcode":"46202",
    "sg:province":"IN",
    "sg:tags":[
        "refinishing",
        "furniture"
    ],
    "wof:name":"AFC Blackwell Restoration",
    "wof:placetype":"venue"
},
  "geometry": {"coordinates":[-86.13689,39.783651],"type":"Point"}
}