{
  "type": "Feature",
  "properties": {
    "addr:full":"302 W Jefferson St Albion IN 46701",
    "addr:housenumber":"302",
    "addr:postcode":"46701",
    "addr:street":"W Jefferson St",
    "iso:country":"US",
    "sg:address":"302 W Jefferson St",
    "sg:city":"Albion",
    "sg:classifiers":[
        {
            "category":"Insurance",
            "subcategory":"Hazard Insurance",
            "type":"Services"
        }
    ],
    "sg:phone":"+1 260 636 2755",
    "sg:postcode":"46701",
    "sg:province":"IN",
    "sg:tags":[
        "bond"
    ],
    "wof:name":"A A Agents Bail Bonding Inc",
    "wof:placetype":"venue"
},
  "geometry": {"coordinates":[-85.42676299999999,41.3965],"type":"Point"}
}