{
  "type": "Feature",
  "properties": {
    "iso:country":"US",
    "sg:address":"971 Haugh St",
    "sg:city":"Indianapolis",
    "sg:classifiers":[
        {
            "category":"Building & Trades",
            "subcategory":"Construction",
            "type":"Services"
        }
    ],
    "sg:phone":"+1 317 917 1693",
    "sg:postcode":"46222",
    "sg:province":"IN",
    "sg:tags":[
        "general",
        "contractor"
    ],
    "wof:name":"BHB Construction",
    "wof:placetype":"venue"
},
  "geometry": {"coordinates":[-86.207507,39.779195],"type":"Point"}
}