{
  "type": "Feature",
  "properties": {
    "iso:country":"US",
    "sg:address":"5152 Lacy Pl",
    "sg:city":"Greenwood",
    "sg:classifiers":[
        {
            "category":"Building & Trades",
            "subcategory":"Construction",
            "type":"Services"
        }
    ],
    "sg:phone":"+1 317 895 7437",
    "sg:postcode":"46142",
    "sg:province":"IN",
    "sg:tags":[
        "contractor"
    ],
    "wof:name":"Construction Specialist Group",
    "wof:placetype":"venue"
},
  "geometry": {"coordinates":[-86.201861,39.623117],"type":"Point"}
}