{
  "type": "Feature",
  "properties": {
    "iso:country":"US",
    "sg:address":"840 Broadway",
    "sg:city":"Gary",
    "sg:classifiers":[
        {
            "category":"Government",
            "subcategory":"Office",
            "type":"Public Place"
        }
    ],
    "sg:phone":"+1 219 883 1027",
    "sg:postcode":"46402",
    "sg:province":"IN",
    "sg:tags":[
        "village"
    ],
    "wof:name":"Customer Service & User Charge",
    "wof:placetype":"venue"
},
  "geometry": {"coordinates":[-87.33719000000001,41.595928],"type":"Point"}
}