{
  "type": "Feature",
  "properties": {
    "iso:country":"US",
    "sg:address":"335 Churchman Pl",
    "sg:city":"Beech Grove",
    "sg:classifiers":[
        {
            "category":"Real Estate",
            "subcategory":"Real Estate Operator",
            "type":"Services"
        }
    ],
    "sg:phone":"+1 317 788 4596",
    "sg:postcode":"46107",
    "sg:province":"IN",
    "sg:tags":[
        "building",
        "apartment"
    ],
    "wof:name":"Cambridge Square Beach Grove",
    "wof:placetype":"venue"
},
  "geometry": {"coordinates":[-86.079773,39.715775],"type":"Point"}
}