{
  "type": "Feature",
  "properties": {
    "addr:full":"316 E Lincoln St Kentland IN 47951",
    "addr:housenumber":"316",
    "addr:postcode":"47951",
    "addr:street":"E Lincoln St",
    "iso:country":"US",
    "sg:address":"316 E Lincoln St",
    "sg:city":"Kentland",
    "sg:classifiers":[
        {
            "category":"Building & Trades",
            "subcategory":"Construction",
            "type":"Services"
        }
    ],
    "sg:phone":"+1 219 474 5006",
    "sg:postcode":"47951",
    "sg:province":"IN",
    "sg:tags":[
        "general",
        "contractor"
    ],
    "wof:name":"I Q Construction Corp",
    "wof:placetype":"venue"
},
  "geometry": {"coordinates":[-87.444712,40.773342],"type":"Point"}
}