{
  "type": "Feature",
  "properties": {
    "iso:country":"US",
    "sg:address":"215 N 2nd St",
    "sg:city":"Mt Ayr",
    "sg:classifiers":[
        {
            "category":"Organizations",
            "subcategory":"Religious Organization",
            "type":"Services"
        }
    ],
    "sg:phone":"+1 219 394 2864",
    "sg:postcode":"47964",
    "sg:province":"IN",
    "sg:tags":[
        "church"
    ],
    "wof:name":"Apostolic Faith Assembly",
    "wof:placetype":"venue"
},
  "geometry": {"coordinates":[-87.298882,40.954205],"type":"Point"}
}