{
  "type": "Feature",
  "properties": {
    "iso:country":"US",
    "sg:address":"7602 Broadway",
    "sg:city":"Merrillville",
    "sg:classifiers":[
        {
            "category":"Food & Beverages",
            "subcategory":"Liquor & Beverages",
            "type":"Retail Goods"
        }
    ],
    "sg:phone":"+1 219 769 7821",
    "sg:postcode":"46410",
    "sg:province":"IN",
    "wof:name":"Broadway Liquors",
    "wof:placetype":"venue"
},
  "geometry": {"coordinates":[-87.336075,41.480452],"type":"Point"}
}