{
  "type": "Feature",
  "properties": {
    "iso:country":"US",
    "sg:address":"4626 S Strawtown Pike",
    "sg:city":"Peru",
    "sg:classifiers":[
        {
            "category":"Manufacturing",
            "subcategory":"Food",
            "type":"Manufacturing & Wholesale Goods"
        }
    ],
    "sg:phone":"+1 765 472 0095",
    "sg:postcode":"46970",
    "sg:province":"IN",
    "sg:tags":[
        "rendering",
        "company"
    ],
    "wof:name":"Endsley Rendering Svc",
    "wof:placetype":"venue"
},
  "geometry": {"coordinates":[-86.062715,40.698331],"type":"Point"}
}