{
  "type": "Feature",
  "properties": {
    "addr:full":"601 W Market St Logansport IN 46947",
    "addr:housenumber":"601",
    "addr:postcode":"46947",
    "addr:street":"W Market St",
    "iso:country":"US",
    "sg:address":"601 W Market St",
    "sg:city":"Logansport",
    "sg:classifiers":[
        {
            "category":"Retail",
            "subcategory":"Auto Repair",
            "type":"Services"
        }
    ],
    "sg:phone":"+1 574 722 6677",
    "sg:postcode":"46947",
    "sg:province":"IN",
    "sg:tags":[
        "repairing",
        "automobile"
    ],
    "wof:name":"A-1 Thrifty Car Care Ctr",
    "wof:placetype":"venue"
},
  "geometry": {"coordinates":[-86.37821599999999,40.751729],"type":"Point"}
}