{
  "type": "Feature",
  "properties": {
    "iso:country":"US",
    "sg:address":"380 Main Cross St",
    "sg:city":"Charlestown",
    "sg:classifiers":[
        {
            "category":"Food & Beverages",
            "subcategory":"Liquor & Beverages",
            "type":"Retail Goods"
        }
    ],
    "sg:phone":"+1 812 256 3913",
    "sg:postcode":"47111",
    "sg:province":"IN",
    "wof:name":"Four Seasons Package Store",
    "wof:placetype":"venue"
},
  "geometry": {"coordinates":[-85.661833,38.444392],"type":"Point"}
}