{
  "type": "Feature",
  "properties": {
    "iso:country":"US",
    "sg:address":"8914 Belle Union Dr",
    "sg:city":"Camby",
    "sg:classifiers":[
        {
            "category":"Building & Trades",
            "subcategory":"Construction",
            "type":"Services"
        }
    ],
    "sg:phone":"+1 317 856 3423",
    "sg:postcode":"46113",
    "sg:province":"IN",
    "sg:tags":[
        "home",
        "builder"
    ],
    "wof:name":"Heartland Crossing",
    "wof:placetype":"venue"
},
  "geometry": {"coordinates":[-86.318572,39.637132],"type":"Point"}
}