{
  "type": "Feature",
  "properties": {
    "iso:country":"US",
    "sg:address":"2317 Sycamore St",
    "sg:city":"Columbus",
    "sg:classifiers":[
        {
            "category":"Organizations",
            "subcategory":"Non-profit Organization",
            "type":"Services"
        }
    ],
    "sg:phone":"+1 812 372 9095",
    "sg:postcode":"47201",
    "sg:province":"IN",
    "sg:tags":[
        "breastfeeding",
        "information",
        "supply"
    ],
    "wof:name":"LA Leche League Of Columbus",
    "wof:placetype":"venue"
},
  "geometry": {"coordinates":[-85.916787,39.22184],"type":"Point"}
}