{
  "type": "Feature",
  "properties": {
    "iso:country":"US",
    "sg:address":"2153 E Mulberry St",
    "sg:city":"Evansville",
    "sg:classifiers":[
        {
            "category":"Organizations",
            "subcategory":"Religious Organization",
            "type":"Services"
        }
    ],
    "sg:phone":"+1 812 479 7109",
    "sg:postcode":"47714",
    "sg:province":"IN",
    "sg:tags":[
        "church"
    ],
    "wof:name":"Jehovah's Witnesses Hall",
    "wof:placetype":"venue"
},
  "geometry": {"coordinates":[-87.52585,37.968868],"type":"Point"}
}