{
  "type": "Feature",
  "properties": {
    "iso:country":"US",
    "sg:address":"2013 S Yost Ave",
    "sg:city":"Bloomington",
    "sg:classifiers":[
        {
            "category":"Freight",
            "type":"Transportation"
        }
    ],
    "sg:phone":"+1 812 336 3256",
    "sg:postcode":"47403",
    "sg:province":"IN",
    "sg:tags":[
        "mover"
    ],
    "sg:website":"www.bushmoving.com",
    "wof:name":"Don Bush Moving",
    "wof:placetype":"venue"
},
  "geometry": {"coordinates":[-86.580843,39.144035],"type":"Point"}
}