{
  "type": "Feature",
  "properties": {
    "iso:country":"US",
    "sg:address":"5560 N Washington Blvd",
    "sg:city":"Indianapolis",
    "sg:classifiers":[
        {
            "category":"Professional",
            "subcategory":"Business Services",
            "type":"Services"
        }
    ],
    "sg:phone":"+1 317 253 1865",
    "sg:postcode":"46220",
    "sg:province":"IN",
    "wof:name":"Charles R Oehrle Inc",
    "wof:placetype":"venue"
},
  "geometry": {"coordinates":[-86.152542,39.853036],"type":"Point"}
}