{
  "type": "Feature",
  "properties": {
    "addr:full":"2118 Inwood Dr Fort Wayne IN 46815",
    "addr:housenumber":"2118",
    "addr:postcode":"46815",
    "addr:street":"Inwood Dr",
    "iso:country":"US",
    "sg:address":"2118 Inwood Dr",
    "sg:city":"Fort Wayne",
    "sg:classifiers":[
        {
            "category":"Organizations",
            "subcategory":"Non-profit Organization",
            "type":"Services"
        }
    ],
    "sg:phone":"+1 260 471 6262",
    "sg:postcode":"46815",
    "sg:province":"IN",
    "sg:tags":[
        "information",
        "alcoholism",
        "treatment"
    ],
    "wof:name":"Alcoholics Anonymous",
    "wof:placetype":"venue"
},
  "geometry": {"coordinates":[-85.08662,41.098623],"type":"Point"}
}