{
  "type": "Feature",
  "properties": {
    "iso:country":"US",
    "sg:address":"1620 US Hwy 41",
    "sg:city":"Schererville",
    "sg:classifiers":[
        {
            "category":"Shopping",
            "subcategory":"Discount & Variety Stores",
            "type":"Retail Goods"
        }
    ],
    "sg:phone":"+1 219 322 7871",
    "sg:postcode":"46375",
    "sg:province":"IN",
    "wof:name":"Buck Stop",
    "wof:placetype":"venue"
},
  "geometry": {"coordinates":[-87.470984,41.49354],"type":"Point"}
}