{
  "type": "Feature",
  "properties": {
    "iso:country":"US",
    "sg:address":"30 N Van Buren St",
    "sg:city":"Nashville",
    "sg:classifiers":[
        {
            "category":"Wholesale",
            "subcategory":"Machinery & Supplies",
            "type":"Manufacturing & Wholesale Goods"
        }
    ],
    "sg:phone":"+1 812 988 7597",
    "sg:postcode":"47448",
    "sg:province":"IN",
    "wof:name":"Red Engine Shop",
    "wof:placetype":"venue"
},
  "geometry": {"coordinates":[-86.246871,39.208175],"type":"Point"}
}