{
  "type": "Feature",
  "properties": {
    "addr:full":"11199 W State Rd 2 Westville IN 46391",
    "addr:housenumber":"11199",
    "addr:postcode":"46391",
    "addr:street":"W State Rd 2",
    "iso:country":"US",
    "sg:address":"11199 W State Rd 2",
    "sg:city":"Westville",
    "sg:classifiers":[
        {
            "category":"Real Estate",
            "subcategory":"Developer",
            "type":"Services"
        }
    ],
    "sg:phone":"+1 219 785 2221",
    "sg:postcode":"46391",
    "sg:province":"IN",
    "sg:tags":[
        "mobile",
        "home"
    ],
    "wof:name":"Westville Estates",
    "wof:placetype":"venue"
},
  "geometry": {"coordinates":[-86.917402,41.53836],"type":"Point"}
}