{
  "type": "Feature",
  "properties": {
    "iso:country":"US",
    "sg:address":"5009 Bellemeade Ave",
    "sg:city":"Evansville",
    "sg:classifiers":[
        {
            "category":"Autos & Motor Vehicles",
            "subcategory":"Auto Supplies",
            "type":"Retail Goods"
        }
    ],
    "sg:phone":"+1 812 479 0846",
    "sg:postcode":"47715",
    "sg:province":"IN",
    "sg:tags":[
        "automobile",
        "parts"
    ],
    "wof:name":"Carquest Auto Parts",
    "wof:placetype":"venue"
},
  "geometry": {"coordinates":[-87.491851,37.967884],"type":"Point"}
}