{
  "type": "Feature",
  "properties": {
    "addr:full":"146 N Rosenberger Ave Evansville IN 47712",
    "addr:housenumber":"146",
    "addr:postcode":"47712",
    "addr:street":"N Rosenberger Ave",
    "iso:country":"US",
    "sg:address":"146 N Rosenberger Ave",
    "sg:city":"Evansville",
    "sg:classifiers":[
        {
            "category":"Personal",
            "subcategory":"Beauty Salon",
            "type":"Services"
        }
    ],
    "sg:phone":"+1 812 423 8868",
    "sg:postcode":"47712",
    "sg:province":"IN",
    "wof:name":"Salon WOW",
    "wof:placetype":"venue"
},
  "geometry": {"coordinates":[-87.627702,37.98104],"type":"Point"}
}