{
  "type": "Feature",
  "properties": {
    "iso:country":"US",
    "sg:address":"6019 Brookshire Dr",
    "sg:city":"Pittsboro",
    "sg:classifiers":[
        {
            "category":"Professional",
            "subcategory":"Business Services",
            "type":"Services"
        },
        {
            "category":"Recreation",
            "type":"Entertainment"
        }
    ],
    "sg:phone":"+1 317 892 4244",
    "sg:postcode":"46167",
    "sg:province":"IN",
    "sg:tags":[
        "aquarium"
    ],
    "wof:name":"Allen Herring Aquarium Service",
    "wof:placetype":"venue"
},
  "geometry": {"coordinates":[-86.438872,39.850796],"type":"Point"}
}