{
  "type": "Feature",
  "properties": {
    "iso:country":"US",
    "sg:address":"147 Diplomat Ct",
    "sg:city":"Beech Grove",
    "sg:classifiers":[
        {
            "category":"Real Estate",
            "subcategory":"Real Estate Operator",
            "type":"Services"
        }
    ],
    "sg:phone":"+1 317 788 1535",
    "sg:postcode":"46107",
    "sg:province":"IN",
    "sg:tags":[
        "apartment"
    ],
    "wof:name":"Beech Meadow Apartments",
    "wof:placetype":"venue"
},
  "geometry": {"coordinates":[-86.079241,39.713879],"type":"Point"}
}