{
  "type": "Feature",
  "properties": {
    "iso:country":"US",
    "sg:address":"4760 Jordan Rd",
    "sg:city":"Martinsville",
    "sg:classifiers":[
        {
            "category":"Building & Trades",
            "subcategory":"Construction",
            "type":"Services"
        }
    ],
    "sg:phone":"+1 765 349 9187",
    "sg:postcode":"46151",
    "sg:province":"IN",
    "sg:tags":[
        "maintenance",
        "contractor"
    ],
    "wof:name":"Broyer Maintenance Shop",
    "wof:placetype":"venue"
},
  "geometry": {"coordinates":[-86.45589,39.375268],"type":"Point"}
}