{
  "type": "Feature",
  "properties": {
    "addr:full":"805 Baker St Plymouth IN 46563",
    "addr:housenumber":"805",
    "addr:postcode":"46563",
    "addr:street":"Baker St",
    "iso:country":"US",
    "sg:address":"805 Baker St",
    "sg:city":"Plymouth",
    "sg:classifiers":[
        {
            "category":"Real Estate",
            "subcategory":"Real Estate Operator",
            "type":"Services"
        }
    ],
    "sg:phone":"+1 574 936 2535",
    "sg:postcode":"46563",
    "sg:province":"IN",
    "sg:tags":[
        "mobile",
        "home",
        "community"
    ],
    "wof:name":"Riverpark",
    "wof:placetype":"venue"
},
  "geometry": {"coordinates":[-86.296645,41.349848],"type":"Point"}
}