{
  "type": "Feature",
  "properties": {
    "iso:country":"US",
    "sg:address":"4516 Old State Rd 46",
    "sg:city":"Nashville",
    "sg:classifiers":[
        {
            "category":"Manufacturing",
            "subcategory":"Tools & Machinery",
            "type":"Manufacturing & Wholesale Goods"
        }
    ],
    "sg:phone":"+1 812 988 8726",
    "sg:postcode":"47448",
    "sg:province":"IN",
    "sg:tags":[
        "transformer"
    ],
    "wof:name":"Intranco Inc",
    "wof:placetype":"venue"
},
  "geometry": {"coordinates":[-86.166186,39.18795],"type":"Point"}
}