{
  "type": "Feature",
  "properties": {
    "addr:full":"16302 Hand Rd Huntertown IN 46748",
    "addr:housenumber":"16302",
    "addr:postcode":"46748",
    "addr:street":"Hand Rd",
    "iso:country":"US",
    "sg:address":"16302 Hand Rd",
    "sg:city":"Huntertown",
    "sg:classifiers":[
        {
            "category":"Building & Trades",
            "subcategory":"Construction",
            "type":"Services"
        }
    ],
    "sg:phone":"+1 260 338 0959",
    "sg:postcode":"46748",
    "sg:province":"IN",
    "sg:tags":[
        "equipment",
        "installation"
    ],
    "wof:name":"Keck Services",
    "wof:placetype":"venue"
},
  "geometry": {"coordinates":[-85.210517,41.23401],"type":"Point"}
}