{
  "type": "Feature",
  "properties": {
    "iso:country":"US",
    "sg:address":"2401 Charlestown Rd",
    "sg:city":"New Albany",
    "sg:classifiers":[
        {
            "category":"Autos & Motor Vehicles",
            "subcategory":"Auto Supplies",
            "type":"Retail Goods"
        }
    ],
    "sg:phone":"+1 812 944 8569",
    "sg:postcode":"47150",
    "sg:province":"IN",
    "sg:tags":[
        "automobile",
        "parts"
    ],
    "wof:name":"New Albany Auto Parts Machine",
    "wof:placetype":"venue"
},
  "geometry": {"coordinates":[-85.808172,38.30914],"type":"Point"}
}