{
  "type": "Feature",
  "properties": {
    "iso:country":"US",
    "sg:address":"6930 Atrium Boardwalk S",
    "sg:city":"Indianapolis",
    "sg:classifiers":[
        {
            "category":"Professional",
            "subcategory":"Accounting & Tax Preparation",
            "type":"Services"
        }
    ],
    "sg:phone":"+1 317 577 7720",
    "sg:postcode":"46250",
    "sg:province":"IN",
    "sg:tags":[
        "accountant"
    ],
    "sg:website":"www.kempercpa.com",
    "wof:name":"Kemper CPA Group LLC",
    "wof:placetype":"venue"
},
  "geometry": {"coordinates":[-86.0473,39.891504],"type":"Point"}
}