{
  "type": "Feature",
  "properties": {
    "addr:full":"3622 State Rd 38 E Lafayette IN 47905",
    "addr:housenumber":"3622;38 e",
    "addr:postcode":"47905",
    "addr:street":"State Rd",
    "iso:country":"US",
    "sg:address":"3622 State Rd 38 E",
    "sg:city":"Lafayette",
    "sg:classifiers":[
        {
            "category":"Restaurant",
            "type":"Food & Drink"
        }
    ],
    "sg:phone":"+1 765 447 3766",
    "sg:postcode":"47905",
    "sg:province":"IN",
    "wof:name":"Blimpie Subs & Salads",
    "wof:placetype":"venue"
},
  "geometry": {"coordinates":[-86.84772599999999,40.393799],"type":"Point"}
}