{
  "type": "Feature",
  "properties": {
    "iso:country":"US",
    "sg:address":"6750 E 75th St",
    "sg:city":"Indianapolis",
    "sg:classifiers":[
        {
            "category":"Professional",
            "subcategory":"Business Services",
            "type":"Services"
        }
    ],
    "sg:phone":"+1 317 594 5151",
    "sg:postcode":"46250",
    "sg:province":"IN",
    "sg:tags":[
        "broker"
    ],
    "sg:website":"www.beaconbiz.biz",
    "wof:name":"Beacon Business EXCHANGE",
    "wof:placetype":"venue"
},
  "geometry": {"coordinates":[-86.04988,39.890771],"type":"Point"}
}