{
  "type": "Feature",
  "properties": {
    "iso:country":"US",
    "sg:address":"227 N Main St",
    "sg:city":"New Castle",
    "sg:classifiers":[
        {
            "category":"Government",
            "subcategory":"Police Station",
            "type":"Public Place"
        }
    ],
    "sg:phone":"+1 765 529 4890",
    "sg:postcode":"47362",
    "sg:province":"IN",
    "sg:tags":[
        "department"
    ],
    "wof:name":"New Castle City Police Dept",
    "wof:placetype":"venue"
},
  "geometry": {"coordinates":[-85.370322,39.932977],"type":"Point"}
}