{
  "type": "Feature",
  "properties": {
    "addr:full":"14939 Wheatfield Ln Carmel IN 46032",
    "addr:housenumber":"14939",
    "addr:postcode":"46032",
    "addr:street":"Wheatfield Ln",
    "iso:country":"US",
    "sg:address":"14939 Wheatfield Ln",
    "sg:city":"Carmel",
    "sg:classifiers":[
        {
            "category":"Personal",
            "subcategory":"Beauty Salon",
            "type":"Services"
        }
    ],
    "sg:phone":"+1 317 844 7191",
    "sg:postcode":"46032",
    "sg:province":"IN",
    "wof:name":"Bella's Hair & Nail Salon",
    "wof:placetype":"venue"
},
  "geometry": {"coordinates":[-86.137401,40.005306],"type":"Point"}
}