{
  "type": "Feature",
  "properties": {
    "addr:full":"142 S Olive St South Bend IN 46619",
    "addr:housenumber":"142",
    "addr:postcode":"46619",
    "addr:street":"S Olive St",
    "iso:country":"US",
    "sg:address":"142 S Olive St",
    "sg:city":"South Bend",
    "sg:classifiers":[
        {
            "category":"Government",
            "subcategory":"Office",
            "type":"Public Place"
        }
    ],
    "sg:phone":"+1 574 235 9751",
    "sg:postcode":"46619",
    "sg:province":"IN",
    "wof:name":"St Joseph Weights & Measures",
    "wof:placetype":"venue"
},
  "geometry": {"coordinates":[-86.283304,41.675822],"type":"Point"}
}