{
  "type": "Feature",
  "properties": {
    "iso:country":"US",
    "sg:address":"236 N State Rd 135",
    "sg:city":"Bargersville",
    "sg:classifiers":[
        {
            "category":"Freight",
            "type":"Transportation"
        }
    ],
    "sg:phone":"+1 317 422 3757",
    "sg:postcode":"46106",
    "sg:province":"IN",
    "sg:tags":[
        "commercial",
        "storage"
    ],
    "wof:name":"Trafalgar Mini Storage",
    "wof:placetype":"venue"
},
  "geometry": {"coordinates":[-86.157919,39.486799],"type":"Point"}
}