{
  "type": "Feature",
  "properties": {
    "iso:country":"US",
    "sg:address":"206 N 3rd St",
    "sg:city":"Wolcott",
    "sg:classifiers":[
        {
            "category":"Freight",
            "type":"Transportation"
        }
    ],
    "sg:phone":"+1 219 279 2632",
    "sg:postcode":"47995",
    "sg:province":"IN",
    "sg:tags":[
        "operator",
        "local",
        "trucking"
    ],
    "wof:name":"Kenny Burns Trucking",
    "wof:placetype":"venue"
},
  "geometry": {"coordinates":[-87.04377,40.76031],"type":"Point"}
}