{
  "type": "Feature",
  "properties": {
    "iso:country":"US",
    "sg:address":"855 Starkey Rd",
    "sg:city":"Zionsville",
    "sg:classifiers":[
        {
            "category":"Utilities",
            "subcategory":"Sewage",
            "type":"Services"
        }
    ],
    "sg:phone":"+1 317 873 2332",
    "sg:postcode":"46077",
    "sg:province":"IN",
    "sg:tags":[
        "equipment",
        "treatment"
    ],
    "wof:name":"Zionsville Sewage Plant",
    "wof:placetype":"venue"
},
  "geometry": {"coordinates":[-86.270013,39.946608],"type":"Point"}
}