{
  "type": "Feature",
  "properties": {
    "iso:country":"US",
    "sg:address":"5619 W 38th St",
    "sg:city":"Indianapolis",
    "sg:classifiers":[
        {
            "category":"Restaurant",
            "type":"Food & Drink"
        }
    ],
    "sg:phone":"+1 317 387 0118",
    "sg:postcode":"46254",
    "sg:province":"IN",
    "wof:name":"Happy Dragon",
    "wof:placetype":"venue"
},
  "geometry": {"coordinates":[-86.258349,39.82371],"type":"Point"}
}