{
  "type": "Feature",
  "properties": {
    "iso:country":"US",
    "sg:address":"704 S Burlington Dr",
    "sg:city":"Muncie",
    "sg:classifiers":[
        {
            "category":"Manufacturing",
            "subcategory":"Tools & Machinery",
            "type":"Manufacturing & Wholesale Goods"
        }
    ],
    "sg:phone":"+1 765 282 0522",
    "sg:postcode":"47302",
    "sg:province":"IN",
    "sg:tags":[
        "die",
        "maker"
    ],
    "wof:name":"Muncie Mold & Engineering",
    "wof:placetype":"venue"
},
  "geometry": {"coordinates":[-85.366356,40.188068],"type":"Point"}
}