{
  "type": "Feature",
  "properties": {
    "iso:country":"US",
    "sg:address":"1931 Locust St",
    "sg:city":"Terre Haute",
    "sg:classifiers":[
        {
            "category":"Cinema",
            "subcategory":"Movie Rental",
            "type":"Entertainment"
        }
    ],
    "sg:phone":"+1 812 234 0575",
    "sg:postcode":"47807",
    "sg:province":"IN",
    "sg:tags":[
        "leasing",
        "video",
        "disc",
        "tape"
    ],
    "wof:name":"U B's Video",
    "wof:placetype":"venue"
},
  "geometry": {"coordinates":[-87.387776,39.477444],"type":"Point"}
}