{
  "type": "Feature",
  "properties": {
    "iso:country":"US",
    "sg:address":"302 W Lake St",
    "sg:city":"Topeka",
    "sg:classifiers":[
        {
            "category":"Food & Beverages",
            "subcategory":"Groceries & Convenience Stores",
            "type":"Retail Goods"
        }
    ],
    "sg:phone":"+1 260 593 2433",
    "sg:postcode":"46571",
    "sg:province":"IN",
    "wof:name":"Fast Lane",
    "wof:placetype":"venue"
},
  "geometry": {"coordinates":[-85.541392,41.539454],"type":"Point"}
}