{
  "type": "Feature",
  "properties": {
    "iso:country":"US",
    "sg:address":"1091 Hospital Rd",
    "sg:city":"Franklin",
    "sg:classifiers":[
        {
            "category":"Government",
            "subcategory":"Police Station",
            "type":"Public Place"
        }
    ],
    "sg:phone":"+1 317 736 9155",
    "sg:postcode":"46131",
    "sg:province":"IN",
    "sg:tags":[
        "sheriff"
    ],
    "wof:name":"Johnson County Sheriff's Ofc",
    "wof:placetype":"venue"
},
  "geometry": {"coordinates":[-86.086251,39.477604],"type":"Point"}
}