{
  "type": "Feature",
  "properties": {
    "iso:country":"US",
    "sg:address":"2350 S State Rd 1",
    "sg:city":"Bluffton",
    "sg:classifiers":[
        {
            "category":"Organizations",
            "subcategory":"Religious Organization",
            "type":"Services"
        }
    ],
    "sg:phone":"+1 260 824 0068",
    "sg:postcode":"46714",
    "sg:province":"IN",
    "sg:tags":[
        "church"
    ],
    "sg:website":"www.sonlightwesleyan.com",
    "wof:name":"Sonlight Wesleyan Church",
    "wof:placetype":"venue"
},
  "geometry": {"coordinates":[-85.167572,40.708582],"type":"Point"}
}