{
  "type": "Feature",
  "properties": {
    "iso:country":"US",
    "sg:address":"1109 Hawthorne Ave",
    "sg:city":"Frankfort",
    "sg:classifiers":[
        {
            "category":"Shopping",
            "subcategory":"Bicycles & Sporting Goods",
            "type":"Retail Goods"
        }
    ],
    "sg:phone":"+1 765 654 8275",
    "sg:postcode":"46041",
    "sg:province":"IN",
    "wof:name":"Mike's Bikes",
    "wof:placetype":"venue"
},
  "geometry": {"coordinates":[-86.528188,40.290788],"type":"Point"}
}