{
  "type": "Feature",
  "properties": {
    "iso:country":"US",
    "sg:address":"3105 W Sample St",
    "sg:city":"South Bend",
    "sg:classifiers":[
        {
            "category":"Retail",
            "subcategory":"Auto Repair",
            "type":"Services"
        }
    ],
    "sg:phone":"+1 574 287 4945",
    "sg:postcode":"46619",
    "sg:province":"IN",
    "sg:tags":[
        "body",
        "automobile",
        "painting"
    ],
    "wof:name":"Floyd's Body Shop",
    "wof:placetype":"venue"
},
  "geometry": {"coordinates":[-86.293487,41.664794],"type":"Point"}
}