{
  "type": "Feature",
  "properties": {
    "iso:country":"US",
    "sg:address":"2141 E 52nd St",
    "sg:city":"Indianapolis",
    "sg:classifiers":[
        {
            "category":"Professional",
            "subcategory":"Accounting & Tax Preparation",
            "type":"Services"
        }
    ],
    "sg:phone":"+1 317 253 3910",
    "sg:postcode":"46205",
    "sg:province":"IN",
    "sg:tags":[
        "accountant"
    ],
    "wof:name":"Abbs Int",
    "wof:placetype":"venue"
},
  "geometry": {"coordinates":[-86.123671,39.847587],"type":"Point"}
}