{
  "type": "Feature",
  "properties": {
    "addr:full":"2651 Carmen St Portage IN 46368",
    "addr:housenumber":"2651",
    "addr:postcode":"46368",
    "addr:street":"Carmen St",
    "iso:country":"US",
    "sg:address":"2651 Carmen St",
    "sg:city":"Portage",
    "sg:classifiers":[
        {
            "category":"Professional",
            "subcategory":"Accounting & Tax Preparation",
            "type":"Services"
        }
    ],
    "sg:phone":"+1 219 763 3971",
    "sg:postcode":"46368",
    "sg:province":"IN",
    "sg:tags":[
        "accountant"
    ],
    "wof:name":"Brenda Ames CPA",
    "wof:placetype":"venue"
},
  "geometry": {"coordinates":[-87.175028,41.574307],"type":"Point"}
}