{
  "type": "Feature",
  "properties": {
    "iso:country":"US",
    "sg:address":"5448 State Rd 132",
    "sg:city":"Pendleton",
    "sg:classifiers":[
        {
            "category":"Building & Trades",
            "subcategory":"Construction",
            "type":"Services"
        }
    ],
    "sg:phone":"+1 765 642 1660",
    "sg:postcode":"46064",
    "sg:province":"IN",
    "sg:tags":[
        "general",
        "contractor"
    ],
    "sg:website":"www.fredericksinc.com",
    "wof:name":"Frederick's Inc",
    "wof:placetype":"venue"
},
  "geometry": {"coordinates":[-85.77739,40.024552],"type":"Point"}
}