{
  "type": "Feature",
  "properties": {
    "iso:country":"US",
    "sg:address":"3505 S Lafountain St",
    "sg:city":"Kokomo",
    "sg:classifiers":[
        {
            "category":"Insurance",
            "subcategory":"Insurance Agent",
            "type":"Services"
        }
    ],
    "sg:phone":"+1 765 453 0110",
    "sg:postcode":"46902",
    "sg:province":"IN",
    "wof:name":"Farm Bureau Insurance",
    "wof:placetype":"venue"
},
  "geometry": {"coordinates":[-86.12716399999999,40.446648],"type":"Point"}
}