{
  "type": "Feature",
  "properties": {
    "addr:full":"1424 W Carmel Dr Carmel IN 46032",
    "addr:housenumber":"1424",
    "addr:postcode":"46032",
    "addr:street":"W Carmel Dr",
    "iso:country":"US",
    "sg:address":"1424 W Carmel Dr",
    "sg:city":"Carmel",
    "sg:classifiers":[
        {
            "category":"Utilities",
            "subcategory":"Mobile Phone",
            "type":"Services"
        }
    ],
    "sg:phone":"+1 317 571 1948",
    "sg:postcode":"46032",
    "sg:province":"IN",
    "sg:tags":[
        "telephone",
        "cellular"
    ],
    "wof:name":"Cingular Wireless",
    "wof:placetype":"venue"
},
  "geometry": {"coordinates":[-86.13882099999999,39.965072],"type":"Point"}
}