{
  "type": "Feature",
  "properties": {
    "addr:full":"229 N Main St Monticello IN 47960",
    "addr:housenumber":"229",
    "addr:postcode":"47960",
    "addr:street":"N Main St",
    "iso:country":"US",
    "sg:address":"229 N Main St",
    "sg:city":"Monticello",
    "sg:classifiers":[
        {
            "category":"Government",
            "subcategory":"Police Station",
            "type":"Public Place"
        }
    ],
    "sg:phone":"+1 574 583 7131",
    "sg:postcode":"47960",
    "sg:province":"IN",
    "sg:tags":[
        "department"
    ],
    "wof:name":"Monticello Chief Of Police",
    "wof:placetype":"venue"
},
  "geometry": {"coordinates":[-86.76186199999999,40.746548],"type":"Point"}
}