{
  "type": "Feature",
  "properties": {
    "iso:country":"US",
    "sg:address":"1020 N Main St",
    "sg:city":"Huntingburg",
    "sg:classifiers":[
        {
            "category":"Communications",
            "type":"Services"
        }
    ],
    "sg:phone":"+1 812 683 5410",
    "sg:postcode":"47542",
    "sg:province":"IN",
    "wof:name":"Tri State Communications",
    "wof:placetype":"venue"
},
  "geometry": {"coordinates":[-86.955467,38.304547],"type":"Point"}
}