{
  "type": "Feature",
  "properties": {
    "addr:full":"969 N Range Line Rd Carmel IN 46032",
    "addr:housenumber":"969",
    "addr:postcode":"46032",
    "addr:street":"N Range Line Rd",
    "iso:country":"US",
    "sg:address":"969 N Range Line Rd",
    "sg:city":"Carmel",
    "sg:classifiers":[
        {
            "category":"Autos & Motor Vehicles",
            "subcategory":"Recreational Vehicle Sales",
            "type":"Retail Goods"
        }
    ],
    "sg:phone":"+1 317 846 5839",
    "sg:postcode":"46032",
    "sg:province":"IN",
    "sg:tags":[
        "parts",
        "trailer"
    ],
    "sg:website":"www.northsidetrailer.com",
    "wof:name":"Northside Trailer Sales & Svc",
    "wof:placetype":"venue"
},
  "geometry": {"coordinates":[-86.12702400000001,39.985674],"type":"Point"}
}