{
  "type": "Feature",
  "properties": {
    "iso:country":"US",
    "sg:address":"1919 E Jefferson St",
    "sg:city":"Kokomo",
    "sg:classifiers":[
        {
            "category":"Retail",
            "subcategory":"Auto Repair",
            "type":"Services"
        }
    ],
    "sg:phone":"+1 765 457 7754",
    "sg:postcode":"46901",
    "sg:province":"IN",
    "sg:tags":[
        "body",
        "automobile",
        "painting"
    ],
    "wof:name":"Padfield's Auto Body & Paint",
    "wof:placetype":"venue"
},
  "geometry": {"coordinates":[-86.103996,40.49115],"type":"Point"}
}