{
  "type": "Feature",
  "properties": {
    "addr:full":"225 S 11th St New Castle IN 47362",
    "addr:housenumber":"225",
    "addr:postcode":"47362",
    "addr:street":"S 11Th St",
    "iso:country":"US",
    "sg:address":"225 S 11th St",
    "sg:city":"New Castle",
    "sg:classifiers":[
        {
            "category":"Insurance",
            "subcategory":"Hazard Insurance",
            "type":"Services"
        }
    ],
    "sg:phone":"+1 765 529 0000",
    "sg:postcode":"47362",
    "sg:province":"IN",
    "sg:tags":[
        "bond"
    ],
    "wof:name":"Goodwin Bail Bonding",
    "wof:placetype":"venue"
},
  "geometry": {"coordinates":[-85.37307699999999,39.930138],"type":"Point"}
}