{
  "type": "Feature",
  "properties": {
    "iso:country":"US",
    "sg:address":"67507 Beech Rd",
    "sg:city":"Wakarusa",
    "sg:classifiers":[
        {
            "category":"Freight",
            "type":"Transportation"
        }
    ],
    "sg:phone":"+1 574 633 4509",
    "sg:postcode":"46573",
    "sg:province":"IN",
    "sg:tags":[
        "operator",
        "local",
        "trucking"
    ],
    "wof:name":"Jay Conrad",
    "wof:placetype":"venue"
},
  "geometry": {"coordinates":[-86.07922,41.511095],"type":"Point"}
}