{
  "type": "Feature",
  "properties": {
    "addr:full":"104 E Main St Albion IN 46701",
    "addr:housenumber":"104",
    "addr:postcode":"46701",
    "addr:street":"E Main St",
    "iso:country":"US",
    "sg:address":"104 E Main St",
    "sg:city":"Albion",
    "sg:classifiers":[
        {
            "category":"Professional",
            "subcategory":"Lawyer & Legal Services",
            "type":"Services"
        }
    ],
    "sg:phone":"+1 260 636 2141",
    "sg:postcode":"46701",
    "sg:province":"IN",
    "sg:tags":[
        "attorney"
    ],
    "wof:name":"Hagen & Hagen Professional",
    "wof:placetype":"venue"
},
  "geometry": {"coordinates":[-85.42269400000001,41.395648],"type":"Point"}
}