{
  "type": "Feature",
  "properties": {
    "iso:country":"US",
    "sg:address":"2401 S Gharkey St",
    "sg:city":"Muncie",
    "sg:classifiers":[
        {
            "category":"Government",
            "subcategory":"Office",
            "type":"Public Place"
        }
    ],
    "sg:phone":"+1 765 747 4851",
    "sg:postcode":"47302",
    "sg:province":"IN",
    "sg:tags":[
        "village"
    ],
    "wof:name":"Muncie Animal Shelter",
    "wof:placetype":"venue"
},
  "geometry": {"coordinates":[-85.393676,40.171935],"type":"Point"}
}