{
  "type": "Feature",
  "properties": {
    "iso:country":"US",
    "sg:address":"504 Eastwood Rd",
    "sg:city":"Michigan City",
    "sg:classifiers":[
        {
            "category":"Home & Garden",
            "subcategory":"Garden Supply",
            "type":"Retail Goods"
        }
    ],
    "sg:phone":"+1 219 879 0089",
    "sg:postcode":"46360",
    "sg:province":"IN",
    "sg:tags":[
        "center"
    ],
    "wof:name":"Clark's Secret Garden",
    "wof:placetype":"venue"
},
  "geometry": {"coordinates":[-86.836271,41.73666],"type":"Point"}
}