{
  "type": "Feature",
  "properties": {
    "iso:country":"US",
    "sg:address":"12033 Cheyenne Ct",
    "sg:city":"Granger",
    "sg:classifiers":[
        {
            "category":"Professional",
            "subcategory":"Management & Consulting",
            "type":"Services"
        }
    ],
    "sg:phone":"+1 219 271 0325",
    "sg:postcode":"46530",
    "sg:province":"IN",
    "sg:tags":[
        "business"
    ],
    "wof:name":"Corona Consulting LLC",
    "wof:placetype":"venue"
},
  "geometry": {"coordinates":[-86.102123,41.758637],"type":"Point"}
}