{
  "type": "Feature",
  "properties": {
    "iso:country":"US",
    "sg:address":"121 Commerce Dr",
    "sg:city":"Danville",
    "sg:classifiers":[
        {
            "category":"Manufacturing",
            "subcategory":"Printing",
            "type":"Manufacturing & Wholesale Goods"
        }
    ],
    "sg:phone":"+1 317 487 6035",
    "sg:postcode":"46122",
    "sg:province":"IN",
    "sg:tags":[
        "printer",
        "form"
    ],
    "wof:name":"Teuteberg Business Forms Inc",
    "wof:placetype":"venue"
},
  "geometry": {"coordinates":[-86.471768,39.760438],"type":"Point"}
}