{
  "type": "Feature",
  "properties": {
    "iso:country":"US",
    "sg:address":"2505 N Arlington Ave",
    "sg:city":"Indianapolis",
    "sg:classifiers":[
        {
            "category":"Health Services",
            "subcategory":"Hospital",
            "type":"Services"
        }
    ],
    "sg:phone":"+1 317 554 5200",
    "sg:postcode":"46218",
    "sg:province":"IN",
    "wof:name":"North Arlington Community Hlth",
    "wof:placetype":"venue"
},
  "geometry": {"coordinates":[-86.064483,39.804417],"type":"Point"}
}