{
  "type": "Feature",
  "properties": {
    "addr:full":"2206 N Main St Mishawaka IN 46545",
    "addr:housenumber":"2206",
    "addr:postcode":"46545",
    "addr:street":"N Main St",
    "iso:country":"US",
    "sg:address":"2206 N Main St",
    "sg:city":"Mishawaka",
    "sg:classifiers":[
        {
            "category":"Wholesale",
            "subcategory":"Office Equipment",
            "type":"Manufacturing & Wholesale Goods"
        }
    ],
    "sg:phone":"+1 574 254 5055",
    "sg:postcode":"46545",
    "sg:province":"IN",
    "sg:tags":[
        "register",
        "cash",
        "supply"
    ],
    "sg:website":"www.crsgroup.com",
    "wof:name":"CRS",
    "wof:placetype":"venue"
},
  "geometry": {"coordinates":[-86.181319,41.680355],"type":"Point"}
}