{
  "type": "Feature",
  "properties": {
    "addr:full":"6941 State Line Ave Hammond IN 46324",
    "addr:housenumber":"6941",
    "addr:postcode":"46324",
    "addr:street":"State Line Ave",
    "iso:country":"US",
    "sg:address":"6941 State Line Ave",
    "sg:city":"Hammond",
    "sg:classifiers":[
        {
            "category":"Manufacturing",
            "subcategory":"Printing",
            "type":"Manufacturing & Wholesale Goods"
        }
    ],
    "sg:phone":"+1 219 933 1809",
    "sg:postcode":"46324",
    "sg:province":"IN",
    "sg:tags":[
        "broker"
    ],
    "wof:name":"Maximum Business Solutions",
    "wof:placetype":"venue"
},
  "geometry": {"coordinates":[-87.525356,41.587151],"type":"Point"}
}