{
  "type": "Feature",
  "properties": {
    "iso:country":"US",
    "sg:address":"4557 W 100 S",
    "sg:city":"New Palestine",
    "sg:classifiers":[
        {
            "category":"Wholesale",
            "subcategory":"Office Equipment",
            "type":"Manufacturing & Wholesale Goods"
        }
    ],
    "sg:phone":"+1 317 861 0226",
    "sg:postcode":"46163",
    "sg:province":"IN",
    "sg:tags":[
        "chalkboard"
    ],
    "wof:name":"Claridge Products Inc",
    "wof:placetype":"venue"
},
  "geometry": {"coordinates":[-85.887958,39.771645],"type":"Point"}
}