{
  "type": "Feature",
  "properties": {
    "addr:full":"6453 Graham Rd Indianapolis IN 46220",
    "addr:housenumber":"6453",
    "addr:postcode":"46220",
    "addr:street":"Graham Rd",
    "iso:country":"US",
    "sg:address":"6453 Graham Rd",
    "sg:city":"Indianapolis",
    "sg:classifiers":[
        {
            "category":"Sports & Exercise",
            "subcategory":"Golf",
            "type":"Entertainment"
        }
    ],
    "sg:phone":"+1 317 251 0480",
    "sg:postcode":"46220",
    "sg:province":"IN",
    "sg:tags":[
        "course"
    ],
    "wof:name":"Advantage Golf",
    "wof:placetype":"venue"
},
  "geometry": {"coordinates":[-86.070256,39.86983],"type":"Point"}
}