{
  "type": "Feature",
  "properties": {
    "iso:country":"US",
    "sg:address":"5381 E 82nd St",
    "sg:city":"Indianapolis",
    "sg:classifiers":[
        {
            "category":"Professional",
            "subcategory":"Employment Agencies",
            "type":"Services"
        }
    ],
    "sg:phone":"+1 317 570 6080",
    "sg:postcode":"46250",
    "sg:province":"IN",
    "sg:tags":[
        "opportunity"
    ],
    "wof:name":"Reserves Network",
    "wof:placetype":"venue"
},
  "geometry": {"coordinates":[-86.076946,39.905052],"type":"Point"}
}