{
  "type": "Feature",
  "properties": {
    "addr:full":"101 N Tucker Mentone IN 46539",
    "addr:housenumber":"101",
    "addr:postcode":"in 46539",
    "addr:street":"N",
    "iso:country":"US",
    "sg:address":"101 N Tucker",
    "sg:city":"Mentone",
    "sg:classifiers":[
        {
            "category":"Retail",
            "subcategory":"Funeral Services",
            "type":"Services"
        }
    ],
    "sg:phone":"+1 574 353 7975",
    "sg:postcode":"46539",
    "sg:province":"IN",
    "sg:tags":[
        "cemetery"
    ],
    "wof:name":"King Memorial Funeral Home",
    "wof:placetype":"venue"
},
  "geometry": {"coordinates":[-86.004501,41.166],"type":"Point"}
}