{
  "type": "Feature",
  "properties": {
    "iso:country":"US",
    "sg:address":"113 E Jackson St",
    "sg:city":"Monroe",
    "sg:classifiers":[
        {
            "category":"Personal",
            "subcategory":"Beauty Salon",
            "type":"Services"
        }
    ],
    "sg:phone":"+1 260 692 1444",
    "sg:postcode":"46772",
    "sg:province":"IN",
    "wof:name":"Style & Tan Central",
    "wof:placetype":"venue"
},
  "geometry": {"coordinates":[-84.938814,40.744155],"type":"Point"}
}