{
  "type": "Feature",
  "properties": {
    "iso:country":"US",
    "sg:address":"1411 E Market St",
    "sg:city":"Indianapolis",
    "sg:classifiers":[
        {
            "category":"Real Estate",
            "subcategory":"Real Estate Operator",
            "type":"Services"
        }
    ],
    "sg:phone":"+1 317 632 7204",
    "sg:postcode":"46201",
    "sg:province":"IN",
    "sg:tags":[
        "apartment"
    ],
    "wof:name":"Byrne Court Apartments",
    "wof:placetype":"venue"
},
  "geometry": {"coordinates":[-86.133575,39.768048],"type":"Point"}
}