{
  "type": "Feature",
  "properties": {
    "iso:country":"US",
    "sg:address":"10123 US Hwy 36",
    "sg:city":"Avon",
    "sg:classifiers":[
        {
            "category":"Wholesale",
            "subcategory":"Apparel",
            "type":"Manufacturing & Wholesale Goods"
        }
    ],
    "sg:phone":"+1 317 273 8369",
    "sg:postcode":"46123",
    "sg:province":"IN",
    "sg:tags":[
        "fabric"
    ],
    "wof:name":"Jo-Ann Etc",
    "wof:placetype":"venue"
},
  "geometry": {"coordinates":[-86.34411799999999,39.763628],"type":"Point"}
}