{
  "type": "Feature",
  "properties": {
    "iso:country":"US",
    "sg:address":"2059 State Rd 8",
    "sg:city":"Auburn",
    "sg:classifiers":[
        {
            "category":"Wholesale",
            "subcategory":"Construction Materials",
            "type":"Manufacturing & Wholesale Goods"
        }
    ],
    "sg:phone":"+1 260 927 0935",
    "sg:postcode":"46706",
    "sg:province":"IN",
    "sg:tags":[
        "sand",
        "gravel"
    ],
    "wof:name":"Irving Gravel Co Inc",
    "wof:placetype":"venue"
},
  "geometry": {"coordinates":[-85.095274,41.366778],"type":"Point"}
}