{
  "type": "Feature",
  "properties": {
    "addr:full":"1502 W Market St Salem IN 47167",
    "addr:housenumber":"1502",
    "addr:postcode":"47167",
    "addr:street":"W Market St",
    "iso:country":"US",
    "sg:address":"1502 W Market St",
    "sg:city":"Salem",
    "sg:classifiers":[
        {
            "category":"Home & Garden",
            "subcategory":"Garden Supply",
            "type":"Retail Goods"
        }
    ],
    "sg:phone":"+1 812 883 4165",
    "sg:postcode":"47167",
    "sg:province":"IN",
    "sg:tags":[
        "fertilizer"
    ],
    "wof:name":"Salem Fertilizer Co",
    "wof:placetype":"venue"
},
  "geometry": {"coordinates":[-86.1199,38.602543],"type":"Point"}
}