{
  "type": "Feature",
  "properties": {
    "iso:country":"US",
    "sg:address":"10762 Randolph St",
    "sg:city":"Crown Point",
    "sg:classifiers":[
        {
            "category":"Restaurant",
            "type":"Food & Drink"
        }
    ],
    "sg:menulink":"http://www.allmenus.com/in/winfield/88285-aurelios-pizza/menu/",
    "sg:phone":"+1 219 661 2900",
    "sg:postcode":"46307",
    "sg:province":"IN",
    "sg:tags":[
        "american",
        "pizza"
    ],
    "wof:name":"Aurelio's Pizza",
    "wof:placetype":"venue"
},
  "geometry": {"coordinates":[-87.23901499999999,41.421484],"type":"Point"}
}