{
  "type": "Feature",
  "properties": {
    "iso:country":"US",
    "sg:address":"8300 Broadway",
    "sg:city":"Merrillville",
    "sg:classifiers":[
        {
            "category":"Utilities",
            "subcategory":"Telephone",
            "type":"Services"
        }
    ],
    "sg:phone":"+1 219 736 2268",
    "sg:postcode":"46410",
    "sg:province":"IN",
    "sg:tags":[
        "company"
    ],
    "wof:name":"G 3 Technology Partners",
    "wof:placetype":"venue"
},
  "geometry": {"coordinates":[-87.335933,41.467521],"type":"Point"}
}