{
  "type": "Feature",
  "properties": {
    "addr:full":"221 Newsom Ave Columbus IN 47201",
    "addr:housenumber":"221",
    "addr:postcode":"47201",
    "addr:street":"Newsom Ave",
    "iso:country":"US",
    "sg:address":"221 Newsom Ave",
    "sg:city":"Columbus",
    "sg:classifiers":[
        {
            "category":"Organizations",
            "subcategory":"Membership Organization",
            "type":"Services"
        }
    ],
    "sg:phone":"+1 812 376 6402",
    "sg:postcode":"47201",
    "sg:province":"IN",
    "wof:name":"Daughters of Isabella Inc",
    "wof:placetype":"venue"
},
  "geometry": {"coordinates":[-85.92378600000001,39.216989],"type":"Point"}
}