{
  "type": "Feature",
  "properties": {
    "iso:country":"US",
    "sg:address":"716 3rd St",
    "sg:city":"Columbus",
    "sg:classifiers":[
        {
            "category":"Real Estate",
            "subcategory":"Real Estate Agent",
            "type":"Services"
        }
    ],
    "sg:phone":"+1 812 372 8445",
    "sg:postcode":"47201",
    "sg:province":"IN",
    "wof:name":"Wagner Realtors",
    "wof:placetype":"venue"
},
  "geometry": {"coordinates":[-85.915915,39.201652],"type":"Point"}
}