{
  "type": "Feature",
  "properties": {
    "iso:country":"US",
    "sg:address":"2210 Beacon St",
    "sg:city":"Fort Wayne",
    "sg:classifiers":[
        {
            "category":"Real Estate",
            "subcategory":"Real Estate Agent",
            "type":"Services"
        }
    ],
    "sg:phone":"+1 260 449 7832",
    "sg:postcode":"46805",
    "sg:province":"IN",
    "sg:tags":[
        "management"
    ],
    "wof:name":"Beacon Heights",
    "wof:placetype":"venue"
},
  "geometry": {"coordinates":[-85.103274,41.096155],"type":"Point"}
}