{
  "type": "Feature",
  "properties": {
    "addr:full":"300 W State St Albany IN 47320",
    "addr:housenumber":"300",
    "addr:postcode":"47320",
    "addr:street":"W State St",
    "iso:country":"US",
    "sg:address":"300 W State St",
    "sg:city":"Albany",
    "sg:classifiers":[
        {
            "category":"Social Services",
            "subcategory":"Job Training",
            "type":"Services"
        }
    ],
    "sg:phone":"+1 765 789 6335",
    "sg:postcode":"47320",
    "sg:province":"IN",
    "sg:tags":[
        "apprenticeship",
        "program"
    ],
    "wof:name":"IUBAX State Apprentice Fun",
    "wof:placetype":"venue"
},
  "geometry": {"coordinates":[-85.240337,40.299738],"type":"Point"}
}