{
  "type": "Feature",
  "properties": {
    "addr:full":"15150 W Commerce Rd Daleville IN 47334",
    "addr:housenumber":"15150",
    "addr:postcode":"47334",
    "addr:street":"W Commerce Rd",
    "iso:country":"US",
    "sg:address":"15150 W Commerce Rd",
    "sg:city":"Daleville",
    "sg:classifiers":[
        {
            "category":"Autos & Motor Vehicles",
            "subcategory":"Fuel & Gas Station",
            "type":"Retail Goods"
        }
    ],
    "sg:phone":"+1 765 378 7460",
    "sg:postcode":"47334",
    "sg:province":"IN",
    "sg:tags":[
        "oil"
    ],
    "wof:name":"Daleville Shell",
    "wof:placetype":"venue"
},
  "geometry": {"coordinates":[-85.56475,40.113813],"type":"Point"}
}