{
  "type": "Feature",
  "properties": {
    "iso:country":"US",
    "sg:address":"7748 S 300 E",
    "sg:city":"Oxford",
    "sg:classifiers":[
        {
            "category":"Farming",
            "subcategory":"Livestock Farm",
            "type":"Manufacturing & Wholesale Goods"
        }
    ],
    "sg:phone":"+1 765 385 5119",
    "sg:postcode":"47971",
    "sg:province":"IN",
    "sg:tags":[
        "beef",
        "feedlot",
        "cattle"
    ],
    "wof:name":"Daniel Winger",
    "wof:placetype":"venue"
},
  "geometry": {"coordinates":[-87.264567,40.495073],"type":"Point"}
}