{
  "type": "Feature",
  "properties": {
    "addr:full":"1542 S Monroe City Rd Vincennes IN 47591",
    "addr:housenumber":"1542",
    "addr:postcode":"47591",
    "addr:street":"S Monroe City Rd",
    "iso:country":"US",
    "sg:address":"1542 S Monroe City Rd",
    "sg:city":"Vincennes",
    "sg:classifiers":[
        {
            "category":"Shopping",
            "type":"Retail Goods"
        }
    ],
    "sg:phone":"+1 812 726 5215",
    "sg:postcode":"47591",
    "sg:province":"IN",
    "sg:tags":[
        "merchandise"
    ],
    "wof:name":"Sandee Global Marketing",
    "wof:placetype":"venue"
},
  "geometry": {"coordinates":[-87.384109,38.656567],"type":"Point"}
}