{
  "type": "Feature",
  "properties": {
    "iso:country":"US",
    "sg:address":"13926 S US Hwy 41",
    "sg:city":"Terre Haute",
    "sg:classifiers":[
        {
            "category":"Farming",
            "subcategory":"Orchard",
            "type":"Manufacturing & Wholesale Goods"
        }
    ],
    "sg:phone":"+1 812 696 0543",
    "sg:postcode":"47802",
    "sg:province":"IN",
    "sg:tags":[
        "grove",
        "management"
    ],
    "wof:name":"Swanee Orchards",
    "wof:placetype":"venue"
},
  "geometry": {"coordinates":[-87.388233,39.29745],"type":"Point"}
}