{
  "type": "Feature",
  "properties": {
    "iso:country":"US",
    "sg:address":"27144 US Hwy 52",
    "sg:city":"Rushville",
    "sg:classifiers":[
        {
            "category":"Government",
            "subcategory":"Fire Station",
            "type":"Public Place"
        }
    ],
    "sg:phone":"+1 765 679 1611",
    "sg:postcode":"46173",
    "sg:province":"IN",
    "sg:tags":[
        "department"
    ],
    "wof:name":"Laurel Fire Dept",
    "wof:placetype":"venue"
},
  "geometry": {"coordinates":[-85.26584200000001,39.492127],"type":"Point"}
}