{
  "type": "Feature",
  "properties": {
    "addr:full":"3655 S Snoddy Rd Bloomington IN 47401",
    "addr:housenumber":"3655",
    "addr:postcode":"47401",
    "addr:street":"S Snoddy Rd",
    "iso:country":"US",
    "sg:address":"3655 S Snoddy Rd",
    "sg:city":"Bloomington",
    "sg:classifiers":[
        {
            "category":"Organizations",
            "subcategory":"Religious Organization",
            "type":"Services"
        }
    ],
    "sg:phone":"+1 812 336 6807",
    "sg:postcode":"47401",
    "sg:province":"IN",
    "sg:website":"www.tmbcc.net",
    "wof:name":"Tibetan Mongolian Buddhist Cultural Center",
    "wof:placetype":"venue"
},
  "geometry": {"coordinates":[-86.489403,39.1264],"type":"Point"}
}