{
  "type": "Feature",
  "properties": {
    "iso:country":"US",
    "sg:address":"615 Pine St",
    "sg:city":"Michigan City",
    "sg:classifiers":[
        {
            "category":"Manufacturing",
            "subcategory":"Metals",
            "type":"Manufacturing & Wholesale Goods"
        }
    ],
    "sg:phone":"+1 219 872 8237",
    "sg:postcode":"46360",
    "sg:province":"IN",
    "sg:tags":[
        "steel"
    ],
    "wof:name":"Ideal Railing Co",
    "wof:placetype":"venue"
},
  "geometry": {"coordinates":[-86.899419,41.715572],"type":"Point"}
}