{
  "type": "Feature",
  "properties": {
    "iso:country":"US",
    "sg:address":"950 Co Rd 60",
    "sg:city":"Garrett",
    "sg:classifiers":[
        {
            "category":"Wholesale",
            "subcategory":"Electrical",
            "type":"Manufacturing & Wholesale Goods"
        }
    ],
    "sg:phone":"+1 260 357 4476",
    "sg:postcode":"46738",
    "sg:province":"IN",
    "sg:tags":[
        "electric",
        "motor"
    ],
    "wof:name":"M & M Distributors Inc",
    "wof:placetype":"venue"
},
  "geometry": {"coordinates":[-85.151706,41.308001],"type":"Point"}
}