{
  "type": "Feature",
  "properties": {
    "addr:full":"10940 W Mount Healthy Rd Columbus IN 47201",
    "addr:housenumber":"10940",
    "addr:postcode":"47201",
    "addr:street":"W Mount Healthy Rd",
    "iso:country":"US",
    "sg:address":"10940 W Mount Healthy Rd",
    "sg:city":"Columbus",
    "sg:classifiers":[
        {
            "category":"Farming",
            "subcategory":"Farm",
            "type":"Manufacturing & Wholesale Goods"
        }
    ],
    "sg:phone":"+1 812 342 3197",
    "sg:postcode":"47201",
    "sg:province":"IN",
    "sg:tags":[
        "crop",
        "general"
    ],
    "wof:name":"Charles Spurgeon",
    "wof:placetype":"venue"
},
  "geometry": {"coordinates":[-86.038944,39.080197],"type":"Point"}
}