{
  "type": "Feature",
  "properties": {
    "addr:full":"2015 E Carter St Kokomo IN 46901",
    "addr:housenumber":"2015",
    "addr:postcode":"46901",
    "addr:street":"E Carter St",
    "iso:country":"US",
    "sg:address":"2015 E Carter St",
    "sg:city":"Kokomo",
    "sg:classifiers":[
        {
            "category":"Organizations",
            "subcategory":"Religious Organization",
            "type":"Services"
        }
    ],
    "sg:phone":"+1 765 452 4018",
    "sg:postcode":"46901",
    "sg:province":"IN",
    "sg:tags":[
        "church"
    ],
    "wof:name":"Church Of One Accord",
    "wof:placetype":"venue"
},
  "geometry": {"coordinates":[-86.102217,40.48393],"type":"Point"}
}