{
  "type": "Feature",
  "properties": {
    "iso:country":"US",
    "sg:address":"2958 Kessler Blvd North Dr",
    "sg:city":"Indianapolis",
    "sg:classifiers":[
        {
            "category":"Sports & Exercise",
            "subcategory":"Gym",
            "type":"Entertainment"
        }
    ],
    "sg:phone":"+1 317 925 0516",
    "sg:postcode":"46222",
    "sg:province":"IN",
    "sg:tags":[
        "club",
        "health",
        "studio",
        "gymnasium"
    ],
    "wof:name":"Awesome Bodies Fitness",
    "wof:placetype":"venue"
},
  "geometry": {"coordinates":[-86.211175,39.809461],"type":"Point"}
}