{
  "type": "Feature",
  "properties": {
    "iso:country":"US",
    "sg:address":"232 W Van Buren St",
    "sg:city":"Columbia City",
    "sg:classifiers":[
        {
            "category":"Banks & Credit Unions",
            "subcategory":"Investment Brokerage",
            "type":"Services"
        }
    ],
    "sg:phone":"+1 260 244 2856",
    "sg:postcode":"46725",
    "sg:province":"IN",
    "sg:tags":[
        "advisory",
        "financial"
    ],
    "wof:name":"Thrivent Financial-Lutherans",
    "wof:placetype":"venue"
},
  "geometry": {"coordinates":[-85.49084499999999,41.157092],"type":"Point"}
}