{
  "type": "Feature",
  "properties": {
    "iso:country":"US",
    "sg:address":"4275 E 30th Dr",
    "sg:city":"Terre Haute",
    "sg:classifiers":[
        {
            "category":"Professional",
            "type":"Services"
        }
    ],
    "sg:phone":"+1 812 478 0016",
    "sg:postcode":"47802",
    "sg:province":"IN",
    "sg:tags":[
        "establishment"
    ],
    "wof:name":"Edgemaster",
    "wof:placetype":"venue"
},
  "geometry": {"coordinates":[-87.358712,39.430327],"type":"Point"}
}