{
  "type": "Feature",
  "properties": {
    "iso:country":"US",
    "sg:address":"9440 W 400 S",
    "sg:city":"Topeka",
    "sg:classifiers":[
        {
            "category":"Shopping",
            "subcategory":"Used Merchandise",
            "type":"Retail Goods"
        }
    ],
    "sg:phone":"+1 260 593 3851",
    "sg:postcode":"46571",
    "sg:province":"IN",
    "sg:tags":[
        "antique"
    ],
    "wof:name":"White Swan",
    "wof:placetype":"venue"
},
  "geometry": {"coordinates":[-85.603684,41.582062],"type":"Point"}
}