{
  "type": "Feature",
  "properties": {
    "addr:full":"316 N Point Cir Danville IN 46122",
    "addr:housenumber":"316",
    "addr:postcode":"46122",
    "addr:street":"N Point Cir",
    "iso:country":"US",
    "sg:address":"316 N Point Cir",
    "sg:city":"Danville",
    "sg:classifiers":[
        {
            "category":"Building & Trades",
            "subcategory":"Construction",
            "type":"Services"
        }
    ],
    "sg:phone":"+1 317 745 5613",
    "sg:postcode":"46122",
    "sg:province":"IN",
    "sg:tags":[
        "residential"
    ],
    "wof:name":"Ja Owens Construction",
    "wof:placetype":"venue"
},
  "geometry": {"coordinates":[-86.533181,39.766828],"type":"Point"}
}