{
  "type": "Feature",
  "properties": {
    "iso:country":"US",
    "sg:address":"1809 W Clinton St",
    "sg:city":"Goshen",
    "sg:classifiers":[
        {
            "category":"Autos & Motor Vehicles",
            "subcategory":"Fuel & Gas Station",
            "type":"Retail Goods"
        }
    ],
    "sg:phone":"+1 574 533 1585",
    "sg:postcode":"46526",
    "sg:province":"IN",
    "sg:tags":[
        "oil"
    ],
    "wof:name":"Steve's Marathon",
    "wof:placetype":"venue"
},
  "geometry": {"coordinates":[-85.862243,41.587958],"type":"Point"}
}