{
  "type": "Feature",
  "properties": {
    "addr:full":"1402 N Park Ave Alexandria IN 46001",
    "addr:housenumber":"1402",
    "addr:postcode":"46001",
    "addr:street":"N Park Ave",
    "iso:country":"US",
    "sg:address":"1402 N Park Ave",
    "sg:city":"Alexandria",
    "sg:classifiers":[
        {
            "category":"Food & Beverages",
            "subcategory":"Liquor & Beverages",
            "type":"Retail Goods"
        }
    ],
    "sg:phone":"+1 765 724 7444",
    "sg:postcode":"46001",
    "sg:province":"IN",
    "wof:name":"Bottle Shop",
    "wof:placetype":"venue"
},
  "geometry": {"coordinates":[-85.670794,40.275589],"type":"Point"}
}