{
  "type": "Feature",
  "properties": {
    "iso:country":"US",
    "sg:address":"1600 23th St",
    "sg:city":"Bedford",
    "sg:classifiers":[
        {
            "category":"Health Services",
            "subcategory":"Hospital",
            "type":"Services"
        }
    ],
    "sg:phone":"+1 812 275 3331",
    "sg:postcode":"47421",
    "sg:province":"IN",
    "wof:name":"Dunn Memorial Hospital",
    "wof:placetype":"venue"
},
  "geometry": {"coordinates":[-86.493175,38.853477],"type":"Point"}
}