{
  "type": "Feature",
  "properties": {
    "iso:country":"US",
    "sg:address":"10621 Orchard Ln",
    "sg:city":"Evansville",
    "sg:classifiers":[
        {
            "category":"Professional",
            "subcategory":"Computer Services",
            "type":"Services"
        }
    ],
    "sg:phone":"+1 812 963 5701",
    "sg:postcode":"47720",
    "sg:province":"IN",
    "sg:tags":[
        "datum"
    ],
    "wof:name":"Phyllis Buente",
    "wof:placetype":"venue"
},
  "geometry": {"coordinates":[-87.631833,38.076371],"type":"Point"}
}