{
  "type": "Feature",
  "properties": {
    "iso:country":"US",
    "sg:address":"365 Tanger Blvd",
    "sg:city":"Seymour",
    "sg:classifiers":[
        {
            "category":"Travel",
            "subcategory":"Hotels & Motels",
            "type":"Entertainment"
        }
    ],
    "sg:phone":"+1 812 524 7443",
    "sg:postcode":"47274",
    "sg:province":"IN",
    "wof:name":"Motel 6",
    "wof:placetype":"venue"
},
  "geometry": {"coordinates":[-85.841252,38.960897],"type":"Point"}
}