{
  "type": "Feature",
  "properties": {
    "iso:country":"US",
    "sg:address":"19419 N Raceway Rd",
    "sg:city":"Indianapolis",
    "sg:classifiers":[
        {
            "category":"Professional",
            "subcategory":"Art Services",
            "type":"Services"
        }
    ],
    "sg:phone":"+1 317 293 1826",
    "sg:postcode":"46234",
    "sg:province":"IN",
    "sg:tags":[
        "faux",
        "finishing",
        "painting"
    ],
    "wof:name":"Hughes / Hughes",
    "wof:placetype":"venue"
},
  "geometry": {"coordinates":[-86.326427,39.781496],"type":"Point"}
}