{
  "type": "Feature",
  "properties": {
    "iso:country":"US",
    "sg:address":"245 W 38th St",
    "sg:city":"Indianapolis",
    "sg:classifiers":[
        {
            "category":"Real Estate",
            "subcategory":"Real Estate Operator",
            "type":"Services"
        }
    ],
    "sg:phone":"+1 317 920 1893",
    "sg:postcode":"46208",
    "sg:province":"IN",
    "sg:tags":[
        "apartment"
    ],
    "wof:name":"Meridian Mart Apartments",
    "wof:placetype":"venue"
},
  "geometry": {"coordinates":[-86.161553,39.824856],"type":"Point"}
}