{
  "type": "Feature",
  "properties": {
    "iso:country":"US",
    "sg:address":"7899 Austin Ct",
    "sg:city":"Plainfield",
    "sg:classifiers":[
        {
            "category":"Real Estate",
            "subcategory":"Real Estate Agent",
            "type":"Services"
        }
    ],
    "sg:phone":"+1 317 839 6925",
    "sg:postcode":"46168",
    "sg:province":"IN",
    "wof:name":"Lifeline Home Buyers",
    "wof:placetype":"venue"
},
  "geometry": {"coordinates":[-86.383872,39.670046],"type":"Point"}
}