{
  "type": "Feature",
  "properties": {
    "iso:country":"US",
    "sg:address":"926 W 29th St",
    "sg:city":"Indianapolis",
    "sg:classifiers":[
        {
            "category":"Place Of Worship",
            "subcategory":"Church",
            "type":"Public Place"
        },
        {
            "category":"Place Of Worship",
            "type":"Public Place"
        }
    ],
    "sg:phone":"+1 317 924 6549",
    "sg:postcode":"46208",
    "sg:province":"IN",
    "sg:tags":[
        "christ",
        "churches-community",
        "churches-baptist-general",
        "denomination",
        "churches-baptist",
        "churches-interdenominational",
        "churches-various"
    ],
    "wof:name":"Freedom Full Gospel Community Church",
    "wof:placetype":"venue"
},
  "geometry": {"coordinates":[-86.17636899999999,39.808287],"type":"Point"}
}