{
  "type": "Feature",
  "properties": {
    "iso:country":"US",
    "sg:address":"710 Madison St",
    "sg:city":"Elkhart",
    "sg:classifiers":[
        {
            "category":"Social Services",
            "subcategory":"Child Care",
            "type":"Services"
        }
    ],
    "sg:phone":"+1 574 293 9149",
    "sg:postcode":"46516",
    "sg:province":"IN",
    "wof:name":"Rave Daycare",
    "wof:placetype":"venue"
},
  "geometry": {"coordinates":[-85.964172,41.682941],"type":"Point"}
}