{
  "type": "Feature",
  "properties": {
    "iso:country":"US",
    "sg:address":"4008 W 79th St",
    "sg:city":"Indianapolis",
    "sg:classifiers":[
        {
            "category":"Professional",
            "subcategory":"Detective & Security Services",
            "type":"Services"
        }
    ],
    "sg:phone":"+1 317 299 1219",
    "sg:postcode":"46268",
    "sg:province":"IN",
    "wof:name":"Vandermoere & Macke",
    "wof:placetype":"venue"
},
  "geometry": {"coordinates":[-86.228305,39.897025],"type":"Point"}
}