{
  "type": "Feature",
  "properties": {
    "iso:country":"US",
    "sg:address":"1124 Main St",
    "sg:city":"Vincennes",
    "sg:classifiers":[
        {
            "category":"Wholesale",
            "subcategory":"Vending Machines",
            "type":"Manufacturing & Wholesale Goods"
        }
    ],
    "sg:phone":"+1 812 882 3500",
    "sg:postcode":"47591",
    "sg:province":"IN",
    "wof:name":"Canteen Service Co",
    "wof:placetype":"venue"
},
  "geometry": {"coordinates":[-87.524659,38.672218],"type":"Point"}
}