{
  "type": "Feature",
  "properties": {
    "addr:full":"301 Indiana Ave Jeffersonville IN 47130",
    "addr:housenumber":"301",
    "addr:postcode":"47130",
    "addr:street":"Indiana Ave",
    "iso:country":"US",
    "sg:address":"301 Indiana Ave",
    "sg:city":"Jeffersonville",
    "sg:classifiers":[
        {
            "category":"Restaurant",
            "type":"Food & Drink"
        }
    ],
    "sg:phone":"+1 812 280 8500",
    "sg:postcode":"47130",
    "sg:province":"IN",
    "sg:tags":[
        "sushi",
        "bar"
    ],
    "sg:website":"http://www.kobesteakhouse.net",
    "wof:name":"KOBE Japanese Steak House",
    "wof:placetype":"venue"
},
  "geometry": {"coordinates":[-85.746368,38.27804],"type":"Point"}
}