{
  "type": "Feature",
  "properties": {
    "iso:country":"US",
    "sg:address":"1079 W 200 N",
    "sg:city":"Peru",
    "sg:classifiers":[
        {
            "category":"Recreation",
            "type":"Entertainment"
        }
    ],
    "sg:phone":"+1 765 473 9656",
    "sg:postcode":"46970",
    "sg:province":"IN",
    "sg:tags":[
        "fairground"
    ],
    "wof:name":"Miami County Four-H Fairground",
    "wof:placetype":"venue"
},
  "geometry": {"coordinates":[-86.093988,40.793126],"type":"Point"}
}