{
  "type": "Feature",
  "properties": {
    "addr:full":"1201 N Weinbach Ave Evansville IN 47711",
    "addr:housenumber":"1201",
    "addr:postcode":"47711",
    "addr:street":"N Weinbach Ave",
    "iso:country":"US",
    "sg:address":"1201 N Weinbach Ave",
    "sg:city":"Evansville",
    "sg:classifiers":[
        {
            "category":"Wholesale",
            "subcategory":"Electrical",
            "type":"Manufacturing & Wholesale Goods"
        }
    ],
    "sg:phone":"+1 812 473 9555",
    "sg:postcode":"47711",
    "sg:province":"IN",
    "sg:tags":[
        "alarm",
        "burglar",
        "system"
    ],
    "wof:name":"ABK Alarms",
    "wof:placetype":"venue"
},
  "geometry": {"coordinates":[-87.529235,37.988743],"type":"Point"}
}