{
  "type": "Feature",
  "properties": {
    "iso:country":"US",
    "sg:address":"2509 S Michigan St",
    "sg:city":"South Bend",
    "sg:classifiers":[
        {
            "category":"Restaurant",
            "type":"Food & Drink"
        }
    ],
    "sg:phone":"+1 574 287 1034",
    "sg:postcode":"46614",
    "sg:province":"IN",
    "sg:tags":[
        "eating"
    ],
    "wof:name":"Julio's Pizza & Ribs",
    "wof:placetype":"venue"
},
  "geometry": {"coordinates":[-86.24975,41.648422],"type":"Point"}
}