{
  "type": "Feature",
  "properties": {
    "addr:full":"7243 Tresa Dr Indianapolis IN 46239",
    "addr:housenumber":"7243",
    "addr:postcode":"46239",
    "addr:street":"Tresa Dr",
    "iso:country":"US",
    "sg:address":"7243 Tresa Dr",
    "sg:city":"Indianapolis",
    "sg:classifiers":[
        {
            "category":"Professional",
            "type":"Services"
        }
    ],
    "sg:phone":"+1 317 862 5810",
    "sg:postcode":"46239",
    "sg:province":"IN",
    "sg:tags":[
        "establishment"
    ],
    "wof:name":"Quality Technical Support LLC",
    "wof:placetype":"venue"
},
  "geometry": {"coordinates":[-86.039332,39.691367],"type":"Point"}
}