{
  "type": "Feature",
  "properties": {
    "iso:country":"US",
    "sg:address":"7255 State Rd 7",
    "sg:city":"Columbus",
    "sg:classifiers":[
        {
            "category":"Autos & Motor Vehicles",
            "subcategory":"Auto Supplies",
            "type":"Retail Goods"
        }
    ],
    "sg:phone":"+1 812 579 9653",
    "sg:postcode":"47203",
    "sg:province":"IN",
    "sg:tags":[
        "equipment",
        "racing",
        "car",
        "automobile"
    ],
    "wof:name":"Black Wolf Performance",
    "wof:placetype":"venue"
},
  "geometry": {"coordinates":[-85.84101800000001,39.166488],"type":"Point"}
}