{
  "type": "Feature",
  "properties": {
    "addr:full":"704 Vigo St Vincennes IN 47591",
    "addr:housenumber":"704",
    "addr:postcode":"47591",
    "addr:street":"Vigo St",
    "iso:country":"US",
    "sg:address":"704 Vigo St",
    "sg:city":"Vincennes",
    "sg:classifiers":[
        {
            "category":"Professional",
            "subcategory":"Accounting & Tax Preparation",
            "type":"Services"
        }
    ],
    "sg:phone":"+1 812 882 6398",
    "sg:postcode":"47591",
    "sg:province":"IN",
    "sg:tags":[
        "accountant"
    ],
    "wof:name":"Richard L Shanklin CPA",
    "wof:placetype":"venue"
},
  "geometry": {"coordinates":[-87.529577,38.675361],"type":"Point"}
}