{
  "type": "Feature",
  "properties": {
    "iso:country":"US",
    "sg:address":"1321 N Shadeland Ave",
    "sg:city":"Indianapolis",
    "sg:classifiers":[
        {
            "category":"Retail",
            "subcategory":"Auto Rental",
            "type":"Services"
        }
    ],
    "sg:phone":"+1 317 353 2173",
    "sg:postcode":"46219",
    "sg:province":"IN",
    "sg:tags":[
        "renting",
        "automobile"
    ],
    "wof:name":"Hertz Rent A Car",
    "wof:placetype":"venue"
},
  "geometry": {"coordinates":[-86.045355,39.787081],"type":"Point"}
}