{
  "type": "Feature",
  "properties": {
    "addr:full":"3210 E 96th St Indianapolis IN 46240",
    "addr:housenumber":"3210",
    "addr:postcode":"46240",
    "addr:street":"E 96Th St",
    "iso:country":"US",
    "sg:address":"3210 E 96th St",
    "sg:city":"Indianapolis",
    "sg:classifiers":[
        {
            "category":"Professional",
            "type":"Services"
        }
    ],
    "sg:phone":"+1 317 566 8170",
    "sg:postcode":"46240",
    "sg:province":"IN",
    "sg:tags":[
        "establishment"
    ],
    "wof:name":"Universal",
    "wof:placetype":"venue"
},
  "geometry": {"coordinates":[-86.111589,39.926899],"type":"Point"}
}