{
  "type": "Feature",
  "properties": {
    "addr:full":"1362 S Range Line Rd Carmel IN 46032",
    "addr:housenumber":"1362",
    "addr:postcode":"46032",
    "addr:street":"S Range Line Rd",
    "iso:country":"US",
    "sg:address":"1362 S Range Line Rd",
    "sg:city":"Carmel",
    "sg:classifiers":[
        {
            "category":"Shopping",
            "subcategory":"Gifts & Souvenirs",
            "type":"Retail Goods"
        }
    ],
    "sg:phone":"+1 317 574 2273",
    "sg:postcode":"46032",
    "sg:province":"IN",
    "wof:name":"Authentic Sports",
    "wof:placetype":"venue"
},
  "geometry": {"coordinates":[-86.126862,39.958628],"type":"Point"}
}