{
  "type": "Feature",
  "properties": {
    "iso:country":"US",
    "sg:address":"522 E 246th St",
    "sg:city":"Sheridan",
    "sg:classifiers":[
        {
            "category":"Retail",
            "subcategory":"Auto Repair",
            "type":"Services"
        }
    ],
    "sg:phone":"+1 317 758 6616",
    "sg:postcode":"46069",
    "sg:province":"IN",
    "sg:tags":[
        "body"
    ],
    "wof:name":"Parkers Body Shop",
    "wof:placetype":"venue"
},
  "geometry": {"coordinates":[-86.13750400000001,40.14552],"type":"Point"}
}