{
  "type": "Feature",
  "properties": {
    "iso:country":"US",
    "sg:address":"1001 W 10th St",
    "sg:city":"Hobart",
    "sg:classifiers":[
        {
            "category":"Real Estate",
            "subcategory":"Real Estate Agent",
            "type":"Services"
        }
    ],
    "sg:phone":"+1 219 947 2886",
    "sg:postcode":"46342",
    "sg:province":"IN",
    "wof:name":"Adele M Cuadra",
    "wof:placetype":"venue"
},
  "geometry": {"coordinates":[-87.27539,41.521868],"type":"Point"}
}