{
  "type": "Feature",
  "properties": {
    "addr:full":"6429 N Keystone Ave Indianapolis IN 46220",
    "addr:housenumber":"6429",
    "addr:postcode":"46220",
    "addr:street":"N Keystone Ave",
    "iso:country":"US",
    "sg:address":"6429 N Keystone Ave",
    "sg:city":"Indianapolis",
    "sg:classifiers":[
        {
            "category":"Personal",
            "type":"Services"
        },
        {
            "category":"Retail",
            "subcategory":"Storage",
            "type":"Services"
        }
    ],
    "sg:phone":"+1 877 258 8230",
    "sg:postcode":"46220",
    "sg:province":"IN",
    "sg:tags":[
        "self",
        "full",
        "commercial",
        "mover",
        "household"
    ],
    "sg:website":"http://www.publicstorage.com/?pid=ypcomCPCingenio",
    "wof:name":"Public Storage",
    "wof:placetype":"venue"
},
  "geometry": {"coordinates":[-86.122068,39.874156],"type":"Point"}
}