{
  "type": "Feature",
  "properties": {
    "iso:country":"US",
    "sg:address":"8213 Pendleton Pike",
    "sg:city":"Indianapolis",
    "sg:classifiers":[
        {
            "category":"Insurance",
            "subcategory":"Insurance Agent",
            "type":"Services"
        },
        {
            "category":"Insurance",
            "subcategory":"Hazard Insurance",
            "type":"Services"
        }
    ],
    "sg:phone":"+1 317 898 1866",
    "sg:postcode":"46226",
    "sg:province":"IN",
    "sg:tags":[
        "auto",
        "marine",
        "motorcycle",
        "boat"
    ],
    "wof:name":"Titan Auto Insurance - & Boat Insurance",
    "wof:placetype":"venue"
},
  "geometry": {"coordinates":[-86.023566,39.838068],"type":"Point"}
}