{
  "type": "Feature",
  "properties": {
    "iso:country":"US",
    "sg:address":"615 Touby Pike",
    "sg:city":"Kokomo",
    "sg:classifiers":[
        {
            "category":"Manufacturing",
            "subcategory":"Signs",
            "type":"Manufacturing & Wholesale Goods"
        }
    ],
    "sg:phone":"+1 765 457 5966",
    "sg:postcode":"46901",
    "sg:province":"IN",
    "wof:name":"Kinder Sign Svc",
    "wof:placetype":"venue"
},
  "geometry": {"coordinates":[-86.103183,40.493529],"type":"Point"}
}