{
  "type": "Feature",
  "properties": {
    "iso:country":"US",
    "sg:address":"3739 N Shadeland Ave",
    "sg:city":"Indianapolis",
    "sg:classifiers":[
        {
            "category":"Food & Beverages",
            "subcategory":"Liquor & Beverages",
            "type":"Retail Goods"
        }
    ],
    "sg:phone":"+1 317 541 8355",
    "sg:postcode":"46226",
    "sg:province":"IN",
    "wof:name":"Payless Liquors",
    "wof:placetype":"venue"
},
  "geometry": {"coordinates":[-86.04579200000001,39.823259],"type":"Point"}
}