{
  "type": "Feature",
  "properties": {
    "addr:full":"217 W North St Indianapolis IN 46202",
    "addr:housenumber":"217",
    "addr:postcode":"46202",
    "addr:street":"W North St",
    "iso:country":"US",
    "sg:address":"217 W North St",
    "sg:city":"Indianapolis",
    "sg:classifiers":[
        {
            "category":"Restaurant",
            "type":"Food & Drink"
        }
    ],
    "sg:phone":"+1 317 635 6808",
    "sg:postcode":"46202",
    "sg:province":"IN",
    "wof:name":"Dimples Chop Shop",
    "wof:placetype":"venue"
},
  "geometry": {"coordinates":[-86.163095,39.775557],"type":"Point"}
}