{
  "type": "Feature",
  "properties": {
    "iso:country":"US",
    "sg:address":"2107 N 900 E",
    "sg:city":"Avilla",
    "sg:classifiers":[
        {
            "category":"Freight",
            "type":"Transportation"
        }
    ],
    "sg:phone":"+1 260 897 2115",
    "sg:postcode":"46710",
    "sg:province":"IN",
    "sg:tags":[
        "commercial",
        "storage"
    ],
    "wof:name":"Double A Svc",
    "wof:placetype":"venue"
},
  "geometry": {"coordinates":[-85.250694,41.380559],"type":"Point"}
}