{
  "type": "Feature",
  "properties": {
    "iso:country":"US",
    "sg:address":"20 E Washington St",
    "sg:city":"Whiteland",
    "sg:classifiers":[
        {
            "category":"Insurance",
            "subcategory":"Insurance Agent",
            "type":"Services"
        }
    ],
    "sg:phone":"+1 317 535 2076",
    "sg:postcode":"46140",
    "sg:province":"IN",
    "wof:name":"American Family Insurance",
    "wof:placetype":"venue"
},
  "geometry": {"coordinates":[-85.768764,39.855862],"type":"Point"}
}