{
  "type": "Feature",
  "properties": {
    "iso:country":"US",
    "sg:address":"6045 E 86th St",
    "sg:city":"Indianapolis",
    "sg:classifiers":[
        {
            "category":"Restaurant",
            "type":"Food & Drink"
        }
    ],
    "sg:menulink":"http://www.allmenus.com/in/lawrence/20835-buca-di-beppo/menu/",
    "sg:phone":"+1 317 842 8666",
    "sg:postcode":"46250",
    "sg:province":"IN",
    "sg:tags":[
        "italian"
    ],
    "wof:name":"Buca Di Beppo",
    "wof:placetype":"venue"
},
  "geometry": {"coordinates":[-86.066226,39.91239],"type":"Point"}
}