{
  "type": "Feature",
  "properties": {
    "iso:country":"US",
    "sg:address":"6127 E Washington St",
    "sg:city":"Indianapolis",
    "sg:classifiers":[
        {
            "category":"Personal",
            "subcategory":"Barber",
            "type":"Services"
        }
    ],
    "sg:phone":"+1 317 353 2603",
    "sg:postcode":"46219",
    "sg:province":"IN",
    "wof:name":"Sheridan Barber Shop",
    "wof:placetype":"venue"
},
  "geometry": {"coordinates":[-86.060345,39.771227],"type":"Point"}
}