{
  "type": "Feature",
  "properties": {
    "addr:full":"235 N Vine St Muncie IN 47305",
    "addr:housenumber":"235",
    "addr:postcode":"47305",
    "addr:street":"N Vine St",
    "iso:country":"US",
    "sg:address":"235 N Vine St",
    "sg:city":"Muncie",
    "sg:classifiers":[
        {
            "category":"Organizations",
            "subcategory":"Professional Association",
            "type":"Services"
        }
    ],
    "sg:phone":"+1 765 288 6041",
    "sg:postcode":"47305",
    "sg:province":"IN",
    "wof:name":"Indiana Towing & Recker Assc",
    "wof:placetype":"venue"
},
  "geometry": {"coordinates":[-85.379555,40.195216],"type":"Point"}
}