{
  "type": "Feature",
  "properties": {
    "iso:country":"US",
    "sg:address":"5015 W State Road 46",
    "sg:city":"Bloomington",
    "sg:classifiers":[
        {
            "category":"Professional",
            "subcategory":"Accounting & Tax Preparation",
            "type":"Services"
        }
    ],
    "sg:phone":"+1 812 876 2100",
    "sg:postcode":"47404",
    "sg:province":"IN",
    "sg:tags":[
        "accountant"
    ],
    "wof:name":"Lanny Schlamp CPA",
    "wof:placetype":"venue"
},
  "geometry": {"coordinates":[-86.585999,39.2117],"type":"Point"}
}