{
  "type": "Feature",
  "properties": {
    "iso:country":"US",
    "sg:address":"7318 W 300 S",
    "sg:city":"Kewanna",
    "sg:phone":"+1 574 653 2167",
    "sg:postcode":"46939",
    "sg:province":"IN",
    "sg:tags":[
        "farm",
        "corn",
        "soybean"
    ],
    "wof:name":"Kerry Newman Farm",
    "wof:placetype":"venue"
},
  "geometry": {"coordinates":[-86.385457,41.011106],"type":"Point"}
}