{
  "type": "Feature",
  "properties": {
    "addr:full":"2003 E 1000 N Laporte IN 46350",
    "addr:housenumber":"2003",
    "addr:postcode":"46350",
    "addr:street":"E 1000 N",
    "iso:country":"US",
    "sg:address":"2003 E 1000 N",
    "sg:city":"Laporte",
    "sg:classifiers":[
        {
            "category":"Restaurant",
            "type":"Food & Drink"
        }
    ],
    "sg:phone":"+1 219 778 2938",
    "sg:postcode":"46350",
    "sg:province":"IN",
    "sg:website":"www.hestoninc.com",
    "wof:name":"Heston Bar",
    "wof:placetype":"venue"
},
  "geometry": {"coordinates":[-86.656068,41.752899],"type":"Point"}
}