{
  "type": "Feature",
  "properties": {
    "iso:country":"US",
    "sg:address":"147 W Ripley St",
    "sg:city":"Osgood",
    "sg:classifiers":[
        {
            "category":"Government",
            "subcategory":"Office",
            "type":"Public Place"
        }
    ],
    "sg:phone":"+1 812 689 4240",
    "sg:postcode":"47037",
    "sg:province":"IN",
    "sg:tags":[
        "city"
    ],
    "wof:name":"Osgood Town Hall",
    "wof:placetype":"venue"
},
  "geometry": {"coordinates":[-85.291728,39.128942],"type":"Point"}
}