{
  "type": "Feature",
  "properties": {
    "addr:full":"105 Royal Pine Ln Cicero IN 46034",
    "addr:housenumber":"105",
    "addr:postcode":"46034",
    "addr:street":"Royal Pine Ln",
    "iso:country":"US",
    "sg:address":"105 Royal Pine Ln",
    "sg:city":"Cicero",
    "sg:classifiers":[
        {
            "category":"Organizations",
            "subcategory":"Professional Association",
            "type":"Services"
        }
    ],
    "sg:phone":"+1 317 877 8147",
    "sg:postcode":"46034",
    "sg:province":"IN",
    "sg:tags":[
        "business"
    ],
    "wof:name":"Jim Jung Sales Inc",
    "wof:placetype":"venue"
},
  "geometry": {"coordinates":[-86.047664,40.103614],"type":"Point"}
}