{
  "type": "Feature",
  "properties": {
    "iso:country":"US",
    "sg:address":"2011 W Morris St",
    "sg:city":"Indianapolis",
    "sg:classifiers":[
        {
            "category":"Personal",
            "subcategory":"Beauty Salon",
            "type":"Services"
        }
    ],
    "sg:phone":"+1 317 631 8961",
    "sg:postcode":"46221",
    "sg:province":"IN",
    "sg:tags":[
        "shop"
    ],
    "wof:name":"Wilma's Beauty Shop",
    "wof:placetype":"venue"
},
  "geometry": {"coordinates":[-86.196615,39.750917],"type":"Point"}
}