{
  "type": "Feature",
  "properties": {
    "iso:country":"US",
    "sg:address":"520 Hayden St",
    "sg:city":"Fort Wayne",
    "sg:classifiers":[
        {
            "category":"Manufacturing",
            "subcategory":"Signs",
            "type":"Manufacturing & Wholesale Goods"
        }
    ],
    "sg:phone":"+1 260 424 8766",
    "sg:postcode":"46802",
    "sg:province":"IN",
    "wof:name":"A-1 Sign Solutions",
    "wof:placetype":"venue"
},
  "geometry": {"coordinates":[-85.130258,41.072124],"type":"Point"}
}