{
  "type": "Feature",
  "properties": {
    "iso:country":"US",
    "sg:address":"3551 N Banta Rd",
    "sg:city":"Bargersville",
    "sg:classifiers":[
        {
            "category":"Wholesale",
            "subcategory":"Farm Supplies",
            "type":"Manufacturing & Wholesale Goods"
        }
    ],
    "sg:phone":"+1 317 422 9191",
    "sg:postcode":"46106",
    "sg:province":"IN",
    "sg:tags":[
        "beekeeper"
    ],
    "wof:name":"Banta General Store",
    "wof:placetype":"venue"
},
  "geometry": {"coordinates":[-86.25030700000001,39.524095],"type":"Point"}
}