{
  "type": "Feature",
  "properties": {
    "addr:full":"3404 S Adams St Marion IN 46953",
    "addr:housenumber":"3404",
    "addr:postcode":"46953",
    "addr:street":"S Adams St",
    "iso:country":"US",
    "sg:address":"3404 S Adams St",
    "sg:city":"Marion",
    "sg:classifiers":[
        {
            "category":"Restaurant",
            "type":"Food & Drink"
        }
    ],
    "sg:menulink":"http://www.allmenus.com/in/marion/237609-pizza-king/menu/",
    "sg:phone":"+1 765 674 6966",
    "sg:postcode":"46953",
    "sg:province":"IN",
    "sg:tags":[
        "american",
        "pizza"
    ],
    "wof:name":"Pizza King",
    "wof:placetype":"venue"
},
  "geometry": {"coordinates":[-85.658524,40.529162],"type":"Point"}
}