{
  "type": "Feature",
  "properties": {
    "iso:country":"US",
    "sg:address":"1855 Shoshone Dr",
    "sg:city":"Lafayette",
    "sg:classifiers":[
        {
            "category":"Real Estate",
            "subcategory":"Real Estate Operator",
            "type":"Services"
        }
    ],
    "sg:phone":"+1 765 474 9221",
    "sg:postcode":"47909",
    "sg:province":"IN",
    "sg:tags":[
        "apartment"
    ],
    "sg:website":"www.gt-south.com",
    "wof:name":"Georgetown South Apartments",
    "wof:placetype":"venue"
},
  "geometry": {"coordinates":[-86.872048,40.392824],"type":"Point"}
}