{
  "type": "Feature",
  "properties": {
    "iso:country":"US",
    "sg:address":"134 N Broad St",
    "sg:city":"Griffith",
    "sg:classifiers":[
        {
            "category":"Manufacturing",
            "subcategory":"Printing",
            "type":"Manufacturing & Wholesale Goods"
        }
    ],
    "sg:phone":"+1 219 924 6499",
    "sg:postcode":"46319",
    "sg:province":"IN",
    "sg:tags":[
        "screen"
    ],
    "wof:name":"Premier Screenprinting",
    "wof:placetype":"venue"
},
  "geometry": {"coordinates":[-87.427734,41.523888],"type":"Point"}
}