{
  "type": "Feature",
  "properties": {
    "iso:country":"US",
    "sg:address":"18536 US Hwy 20",
    "sg:city":"Goshen",
    "sg:classifiers":[
        {
            "category":"Professional",
            "subcategory":"Business Services",
            "type":"Services"
        }
    ],
    "sg:phone":"+1 574 266 1809",
    "sg:postcode":"46528",
    "sg:province":"IN",
    "sg:tags":[
        "embroidery"
    ],
    "wof:name":"OBE Co",
    "wof:placetype":"venue"
},
  "geometry": {"coordinates":[-85.822033,41.667323],"type":"Point"}
}