{
  "type": "Feature",
  "properties": {
    "addr:full":"5626 E Virginia St Evansville IN 47715",
    "addr:housenumber":"5626",
    "addr:postcode":"47715",
    "addr:street":"E Virginia St",
    "iso:country":"US",
    "sg:address":"5626 E Virginia St",
    "sg:city":"Evansville",
    "sg:classifiers":[
        {
            "category":"Building & Trades",
            "subcategory":"Construction",
            "type":"Services"
        }
    ],
    "sg:phone":"+1 812 858 3887",
    "sg:postcode":"47715",
    "sg:province":"IN",
    "sg:tags":[
        "resurfacing",
        "laying",
        "refinishing",
        "floor"
    ],
    "wof:name":"Professional Hardwood Floors",
    "wof:placetype":"venue"
},
  "geometry": {"coordinates":[-87.487832,37.981261],"type":"Point"}
}