{
  "type": "Feature",
  "properties": {
    "iso:country":"US",
    "sg:address":"100 W Center St",
    "sg:city":"Warsaw",
    "sg:classifiers":[
        {
            "category":"Government",
            "subcategory":"Office",
            "type":"Public Place"
        }
    ],
    "sg:phone":"+1 574 267 4444",
    "sg:postcode":"46580",
    "sg:province":"IN",
    "sg:tags":[
        "executive"
    ],
    "wof:name":"County of Kosciusko",
    "wof:placetype":"venue"
},
  "geometry": {"coordinates":[-85.857961,41.238098],"type":"Point"}
}