{
  "type": "Feature",
  "properties": {
    "iso:country":"US",
    "sg:address":"6695 E 34th St",
    "sg:city":"Indianapolis",
    "sg:classifiers":[
        {
            "category":"Professional",
            "subcategory":"Engineering",
            "type":"Services"
        }
    ],
    "sg:phone":"+1 317 549 2082",
    "sg:postcode":"46226",
    "sg:province":"IN",
    "sg:tags":[
        "general",
        "contractor"
    ],
    "wof:name":"Scott Engineering",
    "wof:placetype":"venue"
},
  "geometry": {"coordinates":[-86.05849600000001,39.818274],"type":"Point"}
}