{
  "type": "Feature",
  "properties": {
    "addr:full":"10415 Gratis Jacksonburg Rd Somerville IN 45311",
    "addr:housenumber":"10415",
    "addr:postcode":"45311",
    "addr:street":"Gratis Jacksonburg Rd",
    "iso:country":"US",
    "sg:address":"10415 Gratis Jacksonburg Rd",
    "sg:city":"Somerville",
    "sg:classifiers":[
        {
            "category":"Building & Trades",
            "subcategory":"Construction",
            "type":"Services"
        }
    ],
    "sg:phone":"+1 513 787 9161",
    "sg:postcode":"45311",
    "sg:province":"IN",
    "sg:tags":[
        "builder",
        "stair",
        "contractor"
    ],
    "wof:name":"R & B Stairs",
    "wof:placetype":"venue"
},
  "geometry": {"coordinates":[-84.531792,39.592797],"type":"Point"}
}