{
  "type": "Feature",
  "properties": {
    "iso:country":"US",
    "sg:address":"744 W Main St",
    "sg:city":"Mitchell",
    "sg:classifiers":[
        {
            "category":"Home & Garden",
            "subcategory":"Building Materials",
            "type":"Retail Goods"
        }
    ],
    "sg:phone":"+1 812 849 2069",
    "sg:postcode":"47446",
    "sg:province":"IN",
    "wof:name":"Crawford-Morris Lumber Ctr",
    "wof:placetype":"venue"
},
  "geometry": {"coordinates":[-86.473911,38.732586],"type":"Point"}
}