{
  "type": "Feature",
  "properties": {
    "iso:country":"US",
    "sg:address":"6325 Echo Ct",
    "sg:city":"Indianapolis",
    "sg:classifiers":[
        {
            "category":"Banks & Credit Unions",
            "subcategory":"Investment Brokerage",
            "type":"Services"
        }
    ],
    "sg:phone":"+1 317 293 7836",
    "sg:postcode":"46278",
    "sg:province":"IN",
    "sg:tags":[
        "advisory",
        "consulting",
        "management"
    ],
    "wof:name":"Cost Reduction Specialists",
    "wof:placetype":"venue"
},
  "geometry": {"coordinates":[-86.26272899999999,39.870492],"type":"Point"}
}