{
  "type": "Feature",
  "properties": {
    "iso:country":"US",
    "sg:address":"5173 Boulder Ave",
    "sg:city":"Portage",
    "sg:classifiers":[
        {
            "category":"Freight",
            "type":"Transportation"
        }
    ],
    "sg:phone":"+1 219 762 2270",
    "sg:postcode":"46368",
    "sg:province":"IN",
    "sg:tags":[
        "operator",
        "local",
        "trucking"
    ],
    "wof:name":"Daves Hauling",
    "wof:placetype":"venue"
},
  "geometry": {"coordinates":[-87.21661899999999,41.556415],"type":"Point"}
}