{
  "type": "Feature",
  "properties": {
    "iso:country":"US",
    "sg:address":"9597 W Mount Carmel Rd",
    "sg:city":"Gosport",
    "sg:classifiers":[
        {
            "category":"Building & Trades",
            "subcategory":"Construction",
            "type":"Services"
        }
    ],
    "sg:phone":"+1 812 876 5431",
    "sg:postcode":"47433",
    "sg:province":"IN",
    "sg:tags":[
        "house"
    ],
    "wof:name":"Beckman Construction Inc",
    "wof:placetype":"venue"
},
  "geometry": {"coordinates":[-86.679136,39.296266],"type":"Point"}
}