{
  "type": "Feature",
  "properties": {
    "iso:country":"US",
    "sg:address":"1715 Stringtown Pike",
    "sg:city":"Cicero",
    "sg:classifiers":[
        {
            "category":"Organizations",
            "subcategory":"Religious Organization",
            "type":"Services"
        }
    ],
    "sg:phone":"+1 317 984 4653",
    "sg:postcode":"46034",
    "sg:province":"IN",
    "sg:tags":[
        "church"
    ],
    "wof:name":"Cicero Christian Church",
    "wof:placetype":"venue"
},
  "geometry": {"coordinates":[-86.02347899999999,40.119923],"type":"Point"}
}