{
  "type": "Feature",
  "properties": {
    "addr:full":"4701 N Superior Dr Muncie IN 47303",
    "addr:housenumber":"4701",
    "addr:postcode":"47303",
    "addr:street":"N Superior Dr",
    "iso:country":"US",
    "sg:address":"4701 N Superior Dr",
    "sg:city":"Muncie",
    "sg:classifiers":[
        {
            "category":"Home & Garden",
            "subcategory":"Building Materials",
            "type":"Retail Goods"
        }
    ],
    "sg:phone":"+1 765 284 0386",
    "sg:postcode":"47303",
    "sg:province":"IN",
    "sg:tags":[
        "door"
    ],
    "wof:name":"Overhead Door Corp",
    "wof:placetype":"venue"
},
  "geometry": {"coordinates":[-85.39454000000001,40.23195],"type":"Point"}
}