{
  "type": "Feature",
  "properties": {
    "iso:country":"US",
    "sg:address":"10107 N Harmony Pendleton St",
    "sg:city":"Brazil",
    "sg:classifiers":[
        {
            "category":"Building & Trades",
            "subcategory":"Construction",
            "type":"Services"
        }
    ],
    "sg:phone":"+1 812 448 8932",
    "sg:postcode":"47834",
    "sg:province":"IN",
    "sg:tags":[
        "hanging",
        "contractor"
    ],
    "wof:name":"Mekee Painting",
    "wof:placetype":"venue"
},
  "geometry": {"coordinates":[-87.076471,39.534071],"type":"Point"}
}