{
  "type": "Feature",
  "properties": {
    "addr:full":"1180 W 5th St Peru IN 46970",
    "addr:housenumber":"1180",
    "addr:postcode":"46970",
    "addr:street":"W 5Th St",
    "iso:country":"US",
    "sg:address":"1180 W 5th St",
    "sg:city":"Peru",
    "sg:classifiers":[
        {
            "category":"Government",
            "subcategory":"Office",
            "type":"Public Place"
        }
    ],
    "sg:phone":"+1 765 473 6753",
    "sg:postcode":"46970",
    "sg:province":"IN",
    "sg:tags":[
        "federal"
    ],
    "wof:name":"US Consolidated Farm Svc Agcy",
    "wof:placetype":"venue"
},
  "geometry": {"coordinates":[-86.102508,40.745799],"type":"Point"}
}