{
  "type": "Feature",
  "properties": {
    "iso:country":"US",
    "sg:address":"202 E John St",
    "sg:city":"Alexandria",
    "sg:classifiers":[
        {
            "category":"Organizations",
            "subcategory":"Community Association",
            "type":"Services"
        }
    ],
    "sg:phone":"+1 765 724 7095",
    "sg:postcode":"46001",
    "sg:province":"IN",
    "wof:name":"Delta Theta Tau Sorority",
    "wof:placetype":"venue"
},
  "geometry": {"coordinates":[-85.673087,40.264564],"type":"Point"}
}