{
  "type": "Feature",
  "properties": {
    "iso:country":"US",
    "sg:address":"1087 Broad Ripple Ave",
    "sg:city":"Indianapolis",
    "sg:classifiers":[
        {
            "category":"Restaurant",
            "type":"Food & Drink"
        }
    ],
    "sg:phone":"+1 317 722 1090",
    "sg:postcode":"46220",
    "sg:province":"IN",
    "sg:tags":[
        "eating"
    ],
    "wof:name":"Side Wok Cafe",
    "wof:placetype":"venue"
},
  "geometry": {"coordinates":[-86.140476,39.869644],"type":"Point"}
}