{
  "type": "Feature",
  "properties": {
    "addr:full":"3671 Lauren Ln Bloomington IN 47404",
    "addr:housenumber":"3671",
    "addr:postcode":"47404",
    "addr:street":"Lauren Ln",
    "iso:country":"US",
    "sg:address":"3671 Lauren Ln",
    "sg:city":"Bloomington",
    "sg:classifiers":[
        {
            "category":"Professional",
            "subcategory":"Management & Consulting",
            "type":"Services"
        }
    ],
    "sg:phone":"+1 812 935 6896",
    "sg:postcode":"47404",
    "sg:province":"IN",
    "wof:name":"Hic",
    "wof:placetype":"venue"
},
  "geometry": {"coordinates":[-86.576382,39.220692],"type":"Point"}
}