{
  "type": "Feature",
  "properties": {
    "addr:full":"300 S Green River Rd Evansville IN 47715",
    "addr:housenumber":"300",
    "addr:postcode":"47715",
    "addr:street":"S Green River Rd",
    "iso:country":"US",
    "sg:address":"300 S Green River Rd",
    "sg:city":"Evansville",
    "sg:classifiers":[
        {
            "category":"Food & Beverages",
            "subcategory":"Groceries & Convenience Stores",
            "type":"Retail Goods"
        }
    ],
    "sg:phone":"+1 812 477 4332",
    "sg:postcode":"47715",
    "sg:province":"IN",
    "wof:name":"Big Foot Food Store",
    "wof:placetype":"venue"
},
  "geometry": {"coordinates":[-87.49262299999999,37.973192],"type":"Point"}
}