{
  "type": "Feature",
  "properties": {
    "iso:country":"US",
    "sg:address":"10 N Depot St",
    "sg:city":"New Palestine",
    "sg:classifiers":[
        {
            "category":"Professional",
            "subcategory":"Accounting & Tax Preparation",
            "type":"Services"
        }
    ],
    "sg:phone":"+1 317 861 8742",
    "sg:postcode":"46163",
    "sg:province":"IN",
    "sg:tags":[
        "return",
        "filing"
    ],
    "wof:name":"Income Tax Specialists",
    "wof:placetype":"venue"
},
  "geometry": {"coordinates":[-85.889425,39.721905],"type":"Point"}
}