{
  "type": "Feature",
  "properties": {
    "addr:full":"719 W McKinley Ave Mishawaka IN 46545",
    "addr:housenumber":"719",
    "addr:postcode":"46545",
    "addr:street":"W Mckinley Ave",
    "iso:country":"US",
    "sg:address":"719 W McKinley Ave",
    "sg:city":"Mishawaka",
    "sg:classifiers":[
        {
            "category":"Restaurant",
            "type":"Food & Drink"
        }
    ],
    "sg:phone":"+1 574 255 3122",
    "sg:postcode":"46545",
    "sg:province":"IN",
    "sg:tags":[
        "shop",
        "coffee",
        "eating"
    ],
    "wof:name":"Sufficient Grounds Coffee Hous",
    "wof:placetype":"venue"
},
  "geometry": {"coordinates":[-86.192655,41.680211],"type":"Point"}
}