{
  "type": "Feature",
  "properties": {
    "iso:country":"US",
    "sg:address":"61857 Co Rd 1",
    "sg:city":"Elkhart",
    "sg:classifiers":[
        {
            "category":"Health Services",
            "subcategory":"Health Practitioner",
            "type":"Services"
        }
    ],
    "sg:phone":"+1 574 533 4717",
    "sg:postcode":"46517",
    "sg:province":"IN",
    "sg:tags":[
        "therapist",
        "physical"
    ],
    "wof:name":"Wolff Therapy & Wellness Inc",
    "wof:placetype":"venue"
},
  "geometry": {"coordinates":[-86.041228,41.595966],"type":"Point"}
}