{
  "type": "Feature",
  "properties": {
    "iso:country":"US",
    "sg:address":"907 Eastern Blvd",
    "sg:city":"Clarksville",
    "sg:classifiers":[
        {
            "category":"Health Services",
            "subcategory":"Doctor",
            "type":"Services"
        }
    ],
    "sg:phone":"+1 812 284 0077",
    "sg:postcode":"47129",
    "sg:province":"IN",
    "sg:tags":[
        "physician",
        "surgeon"
    ],
    "wof:name":"Bennett & Bloom Eye Ctr",
    "wof:placetype":"venue"
},
  "geometry": {"coordinates":[-85.765548,38.303933],"type":"Point"}
}