{
  "type": "Feature",
  "properties": {
    "iso:country":"US",
    "sg:address":"95 Chesterfield Dr",
    "sg:city":"Noblesville",
    "sg:classifiers":[
        {
            "category":"Professional",
            "subcategory":"Computer Services",
            "type":"Services"
        }
    ],
    "sg:phone":"+1 317 773 4088",
    "sg:postcode":"46060",
    "sg:province":"IN",
    "sg:tags":[
        "programing",
        "custom"
    ],
    "wof:name":"Ics Consulting Inc",
    "wof:placetype":"venue"
},
  "geometry": {"coordinates":[-86.005809,40.021575],"type":"Point"}
}