{
  "type": "Feature",
  "properties": {
    "iso:country":"US",
    "sg:address":"1601 US Hwy 231 S",
    "sg:city":"Crawfordsville",
    "sg:classifiers":[
        {
            "category":"Utilities",
            "subcategory":"Mobile Phone",
            "type":"Services"
        }
    ],
    "sg:phone":"+1 765 361 8500",
    "sg:postcode":"47933",
    "sg:province":"IN",
    "sg:tags":[
        "telephone",
        "cellular"
    ],
    "wof:name":"Grant Communications",
    "wof:placetype":"venue"
},
  "geometry": {"coordinates":[-86.904074,40.020438],"type":"Point"}
}