{
  "type": "Feature",
  "properties": {
    "iso:country":"US",
    "sg:address":"1335 Eliza St",
    "sg:city":"Fort Wayne",
    "sg:classifiers":[
        {
            "category":"Autos & Motor Vehicles",
            "subcategory":"Automobile Sales",
            "type":"Retail Goods"
        }
    ],
    "sg:phone":"+1 260 420 9494",
    "sg:postcode":"46803",
    "sg:province":"IN",
    "sg:tags":[
        "car",
        "dealer"
    ],
    "wof:name":"Chapman's Auto & Diagnostic",
    "wof:placetype":"venue"
},
  "geometry": {"coordinates":[-85.118386,41.073189],"type":"Point"}
}