{
  "type": "Feature",
  "properties": {
    "iso:country":"US",
    "sg:address":"751 N Cherry St",
    "sg:city":"Ladoga",
    "sg:classifiers":[
        {
            "category":"Organizations",
            "subcategory":"Religious Organization",
            "type":"Services"
        }
    ],
    "sg:phone":"+1 765 942 2460",
    "sg:postcode":"47954",
    "sg:province":"IN",
    "sg:tags":[
        "church"
    ],
    "wof:name":"Ladoga Baptist Church",
    "wof:placetype":"venue"
},
  "geometry": {"coordinates":[-86.799064,39.922945],"type":"Point"}
}