{
  "type": "Feature",
  "properties": {
    "addr:full":"122 Timberbrook Run Westfield IN 46074",
    "addr:housenumber":"122",
    "addr:postcode":"46074",
    "addr:street":"Timberbrook Run",
    "iso:country":"US",
    "sg:address":"122 Timberbrook Run",
    "sg:city":"Westfield",
    "sg:classifiers":[
        {
            "category":"Professional",
            "subcategory":"Engineering",
            "type":"Services"
        }
    ],
    "sg:phone":"+1 317 867 4611",
    "sg:postcode":"46074",
    "sg:province":"IN",
    "sg:tags":[
        "engineer"
    ],
    "wof:name":"Noble Consulting Engineers",
    "wof:placetype":"venue"
},
  "geometry": {"coordinates":[-86.120848,40.040952],"type":"Point"}
}