{
  "type": "Feature",
  "properties": {
    "iso:country":"US",
    "sg:address":"220 Kennedy Ave",
    "sg:city":"Schererville",
    "sg:classifiers":[
        {
            "category":"Retail",
            "subcategory":"Repair Shop",
            "type":"Services"
        }
    ],
    "sg:phone":"+1 219 322 1476",
    "sg:postcode":"46375",
    "sg:province":"IN",
    "sg:tags":[
        "equipment",
        "hydraulic"
    ],
    "wof:name":"Keystone Industrial Resources",
    "wof:placetype":"venue"
},
  "geometry": {"coordinates":[-87.461765,41.522291],"type":"Point"}
}