{
  "type": "Feature",
  "properties": {
    "iso:country":"US",
    "sg:address":"13 E Main St",
    "sg:city":"Peru",
    "sg:classifiers":[
        {
            "category":"Social Services",
            "type":"Services"
        }
    ],
    "sg:phone":"+1 765 473 4240",
    "sg:postcode":"46970",
    "sg:province":"IN",
    "sg:tags":[
        "organization",
        "welfare"
    ],
    "wof:name":"United Way",
    "wof:placetype":"venue"
},
  "geometry": {"coordinates":[-86.06859300000001,40.753801],"type":"Point"}
}