{
  "type": "Feature",
  "properties": {
    "iso:country":"US",
    "sg:address":"2414 Kotter Ave",
    "sg:city":"Evansville",
    "sg:classifiers":[
        {
            "category":"Professional",
            "subcategory":"Engineering",
            "type":"Services"
        }
    ],
    "sg:phone":"+1 812 471 7800",
    "sg:postcode":"47715",
    "sg:province":"IN",
    "sg:tags":[
        "engineer"
    ],
    "sg:website":"www.donan.com",
    "wof:name":"Donan Engineering Co",
    "wof:placetype":"venue"
},
  "geometry": {"coordinates":[-87.481585,38.000894],"type":"Point"}
}