{
  "type": "Feature",
  "properties": {
    "iso:country":"US",
    "sg:address":"2174 E 100 S",
    "sg:city":"Lebanon",
    "sg:classifiers":[
        {
            "category":"Building & Trades",
            "subcategory":"Construction",
            "type":"Services"
        }
    ],
    "sg:phone":"+1 317 769 3318",
    "sg:postcode":"46052",
    "sg:province":"IN",
    "sg:tags":[
        "house"
    ],
    "wof:name":"Montgomery Construction Inc",
    "wof:placetype":"venue"
},
  "geometry": {"coordinates":[-86.428272,40.025587],"type":"Point"}
}