{
  "type": "Feature",
  "properties": {
    "iso:country":"US",
    "sg:address":"3014 Bashor Rd",
    "sg:city":"Goshen",
    "sg:classifiers":[
        {
            "category":"Health Services",
            "subcategory":"Chiropractor",
            "type":"Services"
        }
    ],
    "sg:phone":"+1 574 533 2531",
    "sg:postcode":"46526",
    "sg:province":"IN",
    "wof:name":"Goshen Chiropractic Ctr",
    "wof:placetype":"venue"
},
  "geometry": {"coordinates":[-85.886375,41.594948],"type":"Point"}
}