{
  "type": "Feature",
  "properties": {
    "iso:country":"US",
    "sg:address":"6075 Lakeside Blvd",
    "sg:city":"Indianapolis",
    "sg:classifiers":[
        {
            "category":"Social Services",
            "type":"Services"
        }
    ],
    "sg:phone":"+1 317 234 1931",
    "sg:postcode":"46278",
    "sg:province":"IN",
    "sg:tags":[
        "probation"
    ],
    "wof:name":"Parole Office",
    "wof:placetype":"venue"
},
  "geometry": {"coordinates":[-86.265392,39.876715],"type":"Point"}
}