{
  "type": "Feature",
  "properties": {
    "iso:country":"US",
    "sg:address":"1260 W 700 S",
    "sg:city":"Pendleton",
    "sg:classifiers":[
        {
            "category":"Professional",
            "subcategory":"Business Services",
            "type":"Services"
        }
    ],
    "sg:phone":"+1 765 778 9427",
    "sg:postcode":"46064",
    "sg:province":"IN",
    "wof:name":"Kistler Design",
    "wof:placetype":"venue"
},
  "geometry": {"coordinates":[-85.695885,40.004104],"type":"Point"}
}