{
  "type": "Feature",
  "properties": {
    "iso:country":"US",
    "sg:address":"11590 N Meridian St",
    "sg:city":"Carmel",
    "sg:classifiers":[
        {
            "category":"Restaurant",
            "type":"Food & Drink"
        }
    ],
    "sg:phone":"+1 317 545 3678",
    "sg:postcode":"46032",
    "sg:province":"IN",
    "wof:name":"Meridian Crossing Cafe",
    "wof:placetype":"venue"
},
  "geometry": {"coordinates":[-86.157998,39.956122],"type":"Point"}
}