{
  "type": "Feature",
  "properties": {
    "iso:country":"US",
    "sg:address":"8118 N 1000 E",
    "sg:city":"Sheridan",
    "sg:phone":"+1 317 758 6116",
    "sg:postcode":"46069",
    "sg:province":"IN",
    "sg:tags":[
        "farm",
        "corn",
        "soybean"
    ],
    "wof:name":"Randy Rawlings",
    "wof:placetype":"venue"
},
  "geometry": {"coordinates":[-86.280271,40.15551],"type":"Point"}
}