{
  "type": "Feature",
  "properties": {
    "addr:full":"231 E Linden Ave Logansport IN 46947",
    "addr:housenumber":"231",
    "addr:postcode":"46947",
    "addr:street":"E Linden Ave",
    "iso:country":"US",
    "sg:address":"231 E Linden Ave",
    "sg:city":"Logansport",
    "sg:classifiers":[
        {
            "category":"Organizations",
            "subcategory":"Religious Organization",
            "type":"Services"
        }
    ],
    "sg:phone":"+1 574 735 0000",
    "sg:postcode":"46947",
    "sg:province":"IN",
    "sg:tags":[
        "church"
    ],
    "wof:name":"Logansport Riverview Wslyn Ch",
    "wof:placetype":"venue"
},
  "geometry": {"coordinates":[-86.36579399999999,40.758026],"type":"Point"}
}