{
  "type": "Feature",
  "properties": {
    "iso:country":"US",
    "sg:address":"872 Broadway S Dr",
    "sg:city":"Plainfield",
    "sg:classifiers":[
        {
            "category":"Professional",
            "type":"Services"
        }
    ],
    "sg:phone":"+1 317 445 1096",
    "sg:postcode":"46168",
    "sg:province":"IN",
    "wof:name":"James E Welch Inc",
    "wof:placetype":"venue"
},
  "geometry": {"coordinates":[-86.393282,39.688145],"type":"Point"}
}