{
  "type": "Feature",
  "properties": {
    "iso:country":"US",
    "sg:address":"1139 Shelby St",
    "sg:city":"Indianapolis",
    "sg:classifiers":[
        {
            "category":"Real Estate",
            "subcategory":"Architect",
            "type":"Services"
        }
    ],
    "sg:phone":"+1 317 684 1431",
    "sg:postcode":"46203",
    "sg:province":"IN",
    "wof:name":"Halstead Architects",
    "wof:placetype":"venue"
},
  "geometry": {"coordinates":[-86.139708,39.751527],"type":"Point"}
}