{
  "type": "Feature",
  "properties": {
    "iso:country":"US",
    "sg:address":"3335 Kayenta Ct",
    "sg:city":"Indianapolis",
    "sg:classifiers":[
        {
            "category":"Retail",
            "subcategory":"Auto Repair",
            "type":"Services"
        }
    ],
    "sg:phone":"+1 317 898 7444",
    "sg:postcode":"46226",
    "sg:province":"IN",
    "sg:tags":[
        "muffler",
        "exhaust",
        "system"
    ],
    "wof:name":"Exhaust Products Warehouse Inc",
    "wof:placetype":"venue"
},
  "geometry": {"coordinates":[-86.01285,39.817259],"type":"Point"}
}