{
  "type": "Feature",
  "properties": {
    "iso:country":"US",
    "sg:address":"7235 E 116th St",
    "sg:city":"Fishers",
    "sg:classifiers":[
        {
            "category":"Autos & Motor Vehicles",
            "subcategory":"Fuel & Gas Station",
            "type":"Retail Goods"
        }
    ],
    "sg:phone":"+1 317 578 8092",
    "sg:postcode":"46038",
    "sg:province":"IN",
    "wof:name":"Gas America Services Inc",
    "wof:placetype":"venue"
},
  "geometry": {"coordinates":[-86.043503,39.956799],"type":"Point"}
}