{
  "type": "Feature",
  "properties": {
    "iso:country":"US",
    "sg:address":"1111 Broad St",
    "sg:city":"New Castle",
    "sg:classifiers":[
        {
            "category":"Real Estate",
            "subcategory":"Real Estate Services",
            "type":"Services"
        }
    ],
    "sg:phone":"+1 765 521 2990",
    "sg:postcode":"47362",
    "sg:province":"IN",
    "sg:tags":[
        "company",
        "title"
    ],
    "sg:website":"www.kingstitle.com",
    "wof:name":"Kings Title & Abstract",
    "wof:placetype":"venue"
},
  "geometry": {"coordinates":[-85.372676,39.931138],"type":"Point"}
}