{
  "type": "Feature",
  "properties": {
    "addr:full":"325 Main St Evansville IN 47708",
    "addr:housenumber":"325",
    "addr:postcode":"47708",
    "addr:street":"Main St",
    "iso:country":"US",
    "sg:address":"325 Main St",
    "sg:city":"Evansville",
    "sg:classifiers":[
        {
            "category":"Shopping",
            "type":"Retail Goods"
        }
    ],
    "sg:phone":"+1 812 867 3584",
    "sg:postcode":"47708",
    "sg:province":"IN",
    "sg:tags":[
        "art",
        "gallery",
        "dealer"
    ],
    "wof:name":"Artwork Unlimited Inc",
    "wof:placetype":"venue"
},
  "geometry": {"coordinates":[-87.571288,37.971361],"type":"Point"}
}