{
  "type": "Feature",
  "properties": {
    "iso:country":"US",
    "sg:address":"311 16th St",
    "sg:city":"Logansport",
    "sg:classifiers":[
        {
            "category":"Building & Trades",
            "subcategory":"Electrical",
            "type":"Services"
        }
    ],
    "sg:phone":"+1 574 753 3659",
    "sg:postcode":"46947",
    "sg:province":"IN",
    "sg:tags":[
        "electrical",
        "contractor"
    ],
    "wof:name":"Gingrich Service",
    "wof:placetype":"venue"
},
  "geometry": {"coordinates":[-86.349338,40.756722],"type":"Point"}
}