{
  "type": "Feature",
  "properties": {
    "iso:country":"US",
    "sg:address":"1101 Windsor St",
    "sg:city":"Indianapolis",
    "sg:classifiers":[
        {
            "category":"Shopping",
            "subcategory":"Department Store",
            "type":"Retail Goods"
        }
    ],
    "sg:phone":"+1 317 423 1220",
    "sg:postcode":"46201",
    "sg:province":"IN",
    "wof:name":"Sam's Club",
    "wof:placetype":"venue"
},
  "geometry": {"coordinates":[-86.130017,39.782752],"type":"Point"}
}