{
  "type": "Feature",
  "properties": {
    "iso:country":"US",
    "sg:address":"118 N Perry St",
    "sg:city":"Attica",
    "sg:classifiers":[
        {
            "category":"Building & Trades",
            "subcategory":"Equipment Rental",
            "type":"Services"
        }
    ],
    "sg:phone":"+1 765 764 4521",
    "sg:postcode":"47918",
    "sg:province":"IN",
    "sg:tags":[
        "leasing",
        "furniture"
    ],
    "wof:name":"Circle H Discount Ctr",
    "wof:placetype":"venue"
},
  "geometry": {"coordinates":[-87.248209,40.295115],"type":"Point"}
}