{
  "type": "Feature",
  "properties": {
    "iso:country":"US",
    "sg:address":"46 N Main St",
    "sg:city":"Bargersville",
    "sg:classifiers":[
        {
            "category":"Manufacturing",
            "subcategory":"Tools & Machinery",
            "type":"Manufacturing & Wholesale Goods"
        }
    ],
    "sg:phone":"+1 317 422 5105",
    "sg:postcode":"46106",
    "sg:province":"IN",
    "sg:tags":[
        "machine",
        "shop"
    ],
    "wof:name":"Baker Machine Shop",
    "wof:placetype":"venue"
},
  "geometry": {"coordinates":[-86.168037,39.522161],"type":"Point"}
}