{
  "type": "Feature",
  "properties": {
    "iso:country":"US",
    "sg:address":"1712 Calumet Ave",
    "sg:city":"Whiting",
    "sg:classifiers":[
        {
            "category":"Utilities",
            "subcategory":"Mobile Phone",
            "type":"Services"
        }
    ],
    "sg:phone":"+1 219 659 4000",
    "sg:postcode":"46394",
    "sg:province":"IN",
    "sg:tags":[
        "equipment",
        "paging",
        "signaling",
        "system"
    ],
    "wof:name":"Wireless One",
    "wof:placetype":"venue"
},
  "geometry": {"coordinates":[-87.508624,41.681255],"type":"Point"}
}