{
  "type": "Feature",
  "properties": {
    "iso:country":"US",
    "sg:address":"2809 E 38th St",
    "sg:city":"Indianapolis",
    "sg:classifiers":[
        {
            "category":"Restaurant",
            "type":"Food & Drink"
        }
    ],
    "sg:menulink":"http://www.allmenus.com/in/indianapolis/208047-taco-bell/menu/",
    "sg:phone":"+1 317 591 9241",
    "sg:postcode":"46218",
    "sg:province":"IN",
    "sg:tags":[
        "mexican"
    ],
    "wof:name":"Taco Bell",
    "wof:placetype":"venue"
},
  "geometry": {"coordinates":[-86.11638000000001,39.824984],"type":"Point"}
}