{
  "type": "Feature",
  "properties": {
    "addr:full":"1059 Ransom Rd Valparaiso IN 46385",
    "addr:housenumber":"1059",
    "addr:postcode":"46385",
    "addr:street":"Ransom Rd",
    "iso:country":"US",
    "sg:address":"1059 Ransom Rd",
    "sg:city":"Valparaiso",
    "sg:classifiers":[
        {
            "category":"Real Estate",
            "subcategory":"Architect",
            "type":"Services"
        }
    ],
    "sg:phone":"+1 219 462 2791",
    "sg:postcode":"46385",
    "sg:province":"IN",
    "sg:tags":[
        "architectural"
    ],
    "wof:name":"Feltgen Ronald E & Assoc Inc",
    "wof:placetype":"venue"
},
  "geometry": {"coordinates":[-87.073933,41.499878],"type":"Point"}
}