{
  "type": "Feature",
  "properties": {
    "iso:country":"US",
    "sg:address":"3510 S US Hwy 41",
    "sg:city":"Terre Haute",
    "sg:classifiers":[
        {
            "category":"Sports & Exercise",
            "subcategory":"Gym",
            "type":"Entertainment"
        }
    ],
    "sg:phone":"+1 812 231 1234",
    "sg:postcode":"47802",
    "sg:province":"IN",
    "sg:tags":[
        "club",
        "health",
        "studio",
        "gymnasium"
    ],
    "wof:name":"Club Fit For Women",
    "wof:placetype":"venue"
},
  "geometry": {"coordinates":[-87.415983,39.422689],"type":"Point"}
}