{
  "type": "Feature",
  "properties": {
    "iso:country":"US",
    "sg:address":"7169 Rockville Rd",
    "sg:city":"Indianapolis",
    "sg:classifiers":[
        {
            "category":"Autos & Motor Vehicles",
            "subcategory":"Fuel & Gas Station",
            "type":"Retail Goods"
        },
        {
            "category":"Manufacturing",
            "subcategory":"Petroleum Products",
            "type":"Manufacturing & Wholesale Goods"
        },
        {
            "category":"Food & Beverages",
            "subcategory":"Groceries & Convenience Stores",
            "type":"Retail Goods"
        }
    ],
    "sg:phone":"+1 317 244 0979",
    "sg:postcode":"46214",
    "sg:province":"IN",
    "sg:tags":[
        "oil",
        "refiner"
    ],
    "sg:website":"http://www.speedway.com",
    "wof:name":"Speedway 6124",
    "wof:placetype":"venue"
},
  "geometry": {"coordinates":[-86.287983,39.764307],"type":"Point"}
}