{
  "type": "Feature",
  "properties": {
    "iso:country":"US",
    "sg:address":"2624 Turley Rd",
    "sg:city":"Vincennes",
    "sg:phone":"+1 812 882 4699",
    "sg:postcode":"47591",
    "sg:province":"IN",
    "sg:tags":[
        "farm",
        "corn",
        "soybean"
    ],
    "wof:name":"Mosher Reid",
    "wof:placetype":"venue"
},
  "geometry": {"coordinates":[-87.495487,38.669078],"type":"Point"}
}