{
  "type": "Feature",
  "properties": {
    "iso:country":"US",
    "sg:address":"212 N Main St",
    "sg:city":"Goshen",
    "sg:classifiers":[
        {
            "category":"Real Estate",
            "subcategory":"Real Estate Agent",
            "type":"Services"
        }
    ],
    "sg:phone":"+1 574 534 0827",
    "sg:postcode":"46526",
    "sg:province":"IN",
    "wof:name":"Las Americas Financial Svc",
    "wof:placetype":"venue"
},
  "geometry": {"coordinates":[-85.834471,41.588339],"type":"Point"}
}