{
  "type": "Feature",
  "properties": {
    "iso:country":"US",
    "sg:address":"1535 S State Rd 19",
    "sg:city":"Akron",
    "sg:classifiers":[
        {
            "category":"Freight",
            "type":"Transportation"
        }
    ],
    "sg:phone":"+1 574 893 1513",
    "sg:postcode":"46910",
    "sg:province":"IN",
    "sg:tags":[
        "trucking"
    ],
    "wof:name":"Landair Corp",
    "wof:placetype":"venue"
},
  "geometry": {"coordinates":[-86.02563,41.033892],"type":"Point"}
}