{
  "type": "Feature",
  "properties": {
    "iso:country":"US",
    "sg:address":"5213 State Rd 45",
    "sg:city":"Nashville",
    "sg:classifiers":[
        {
            "category":"Building & Trades",
            "subcategory":"Construction",
            "type":"Services"
        }
    ],
    "sg:phone":"+1 812 988 4442",
    "sg:postcode":"47448",
    "sg:province":"IN",
    "sg:tags":[
        "resurfacing",
        "laying",
        "refinishing",
        "floor"
    ],
    "wof:name":"Distinctive Hardwood Floors",
    "wof:placetype":"venue"
},
  "geometry": {"coordinates":[-86.344171,39.247925],"type":"Point"}
}