{
  "type": "Feature",
  "properties": {
    "iso:country":"US",
    "sg:address":"6 Oak Dr",
    "sg:city":"Chesterton",
    "sg:classifiers":[
        {
            "category":"Health Services",
            "subcategory":"Doctor",
            "type":"Services"
        }
    ],
    "sg:phone":"+1 219 787 8777",
    "sg:postcode":"46304",
    "sg:province":"IN",
    "sg:tags":[
        "physician",
        "surgeon"
    ],
    "wof:name":"Morton Millman MD",
    "wof:placetype":"venue"
},
  "geometry": {"coordinates":[-87.091373,41.652754],"type":"Point"}
}