{
  "type": "Feature",
  "properties": {
    "iso:country":"US",
    "sg:address":"47 W Marion St",
    "sg:city":"Danville",
    "sg:classifiers":[
        {
            "category":"Professional",
            "subcategory":"Lawyer & Legal Services",
            "type":"Services"
        }
    ],
    "sg:phone":"+1 317 745 0135",
    "sg:postcode":"46122",
    "sg:province":"IN",
    "sg:tags":[
        "attorney"
    ],
    "wof:name":"John E Pierce",
    "wof:placetype":"venue"
},
  "geometry": {"coordinates":[-86.524642,39.759792],"type":"Point"}
}