{
  "type": "Feature",
  "properties": {
    "iso:country":"US",
    "sg:address":"6240 Amber Valley Ln",
    "sg:city":"Indianapolis",
    "sg:classifiers":[
        {
            "category":"Building & Trades",
            "subcategory":"Construction",
            "type":"Services"
        }
    ],
    "sg:phone":"+1 317 577 2814",
    "sg:postcode":"46237",
    "sg:province":"IN",
    "sg:tags":[
        "roofing",
        "contractor"
    ],
    "wof:name":"Indianapolis Contracting",
    "wof:placetype":"venue"
},
  "geometry": {"coordinates":[-86.046777,39.677529],"type":"Point"}
}