{
  "type": "Feature",
  "properties": {
    "addr:full":"119 NW 4th St Evansville IN 47708",
    "addr:housenumber":"119",
    "addr:postcode":"47708",
    "addr:street":"Nw 4Th St",
    "iso:country":"US",
    "sg:address":"119 NW 4th St",
    "sg:city":"Evansville",
    "sg:classifiers":[
        {
            "category":"Restaurant",
            "type":"Food & Drink"
        }
    ],
    "sg:phone":"+1 812 422 6667",
    "sg:postcode":"47708",
    "sg:province":"IN",
    "wof:name":"Jaya's Authentic Foods",
    "wof:placetype":"venue"
},
  "geometry": {"coordinates":[-87.572295,37.973135],"type":"Point"}
}