{
  "type": "Feature",
  "properties": {
    "iso:country":"US",
    "sg:address":"3401 Prestwick Square Dr",
    "sg:city":"Jeffersonville",
    "sg:classifiers":[
        {
            "category":"Real Estate",
            "subcategory":"Real Estate Operator",
            "type":"Services"
        }
    ],
    "sg:phone":"+1 812 280 7888",
    "sg:postcode":"47130",
    "sg:province":"IN",
    "sg:tags":[
        "apartment"
    ],
    "wof:name":"Prestwick Square Apartments",
    "wof:placetype":"venue"
},
  "geometry": {"coordinates":[-85.713028,38.32962],"type":"Point"}
}