{
  "type": "Feature",
  "properties": {
    "addr:full":"777 Beachway Dr Indianapolis IN 46224",
    "addr:housenumber":"777",
    "addr:postcode":"46224",
    "addr:street":"Beachway Dr",
    "iso:country":"US",
    "sg:address":"777 Beachway Dr",
    "sg:city":"Indianapolis",
    "sg:classifiers":[
        {
            "category":"Banks & Credit Unions",
            "subcategory":"Bank",
            "type":"Services"
        }
    ],
    "sg:phone":"+1 317 887 0499",
    "sg:postcode":"46224",
    "sg:province":"IN",
    "sg:tags":[
        "loan",
        "broker",
        "real estate"
    ],
    "sg:website":"www.acerefi.com",
    "wof:name":"Ace Mortgage Funding Inc",
    "wof:placetype":"venue"
},
  "geometry": {"coordinates":[-86.26783500000001,39.778604],"type":"Point"}
}