{
  "type": "Feature",
  "properties": {
    "addr:full":"14981 S Willow Grove Ave Clinton IN 47842",
    "addr:housenumber":"14981",
    "addr:postcode":"47842",
    "addr:street":"S Willow Grove Ave",
    "iso:country":"US",
    "sg:address":"14981 S Willow Grove Ave",
    "sg:city":"Clinton",
    "sg:classifiers":[
        {
            "category":"Real Estate",
            "subcategory":"Developer",
            "type":"Services"
        }
    ],
    "sg:phone":"+1 765 832 7884",
    "sg:postcode":"47842",
    "sg:province":"IN",
    "sg:tags":[
        "mobile",
        "home"
    ],
    "wof:name":"Sycamore Mobile Home Park",
    "wof:placetype":"venue"
},
  "geometry": {"coordinates":[-87.413539,39.666026],"type":"Point"}
}