{
  "type": "Feature",
  "properties": {
    "iso:country":"US",
    "sg:address":"7377 Edgewater Dr",
    "sg:city":"Indianapolis",
    "sg:classifiers":[
        {
            "category":"Professional",
            "subcategory":"Computer Services",
            "type":"Services"
        }
    ],
    "sg:phone":"+1 317 253 5432",
    "sg:postcode":"46240",
    "sg:province":"IN",
    "sg:tags":[
        "related"
    ],
    "wof:name":"C R Spencer Co Inc",
    "wof:placetype":"venue"
},
  "geometry": {"coordinates":[-86.13833200000001,39.888685],"type":"Point"}
}