{
  "type": "Feature",
  "properties": {
    "iso:country":"US",
    "sg:address":"1766 US Hwy 231 N",
    "sg:city":"Crawfordsville",
    "sg:classifiers":[
        {
            "category":"Autos & Motor Vehicles",
            "subcategory":"Auto Supplies",
            "type":"Retail Goods"
        }
    ],
    "sg:phone":"+1 765 362 8304",
    "sg:postcode":"47933",
    "sg:province":"IN",
    "wof:name":"Stevenson Automotive",
    "wof:placetype":"venue"
},
  "geometry": {"coordinates":[-86.90804900000001,40.065673],"type":"Point"}
}