{
  "type": "Feature",
  "properties": {
    "iso:country":"US",
    "sg:address":"11133 Rockaway Dr",
    "sg:city":"Fort Wayne",
    "sg:classifiers":[
        {
            "category":"Professional",
            "type":"Services"
        }
    ],
    "sg:phone":"+1 260 637 9198",
    "sg:postcode":"46845",
    "sg:province":"IN",
    "sg:tags":[
        "establishment"
    ],
    "wof:name":"Accuride Corp",
    "wof:placetype":"venue"
},
  "geometry": {"coordinates":[-85.145506,41.186035],"type":"Point"}
}