{
  "type": "Feature",
  "properties": {
    "iso:country":"US",
    "sg:address":"319 S Walnut St",
    "sg:city":"Crawfordsville",
    "sg:classifiers":[
        {
            "category":"Wholesale",
            "subcategory":"Sporting Goods",
            "type":"Manufacturing & Wholesale Goods"
        }
    ],
    "sg:phone":"+1 765 364 9408",
    "sg:postcode":"47933",
    "sg:province":"IN",
    "wof:name":"Ele Tennis Inc",
    "wof:placetype":"venue"
},
  "geometry": {"coordinates":[-86.902975,40.039243],"type":"Point"}
}