{
  "type": "Feature",
  "properties": {
    "addr:full":"320 SW D St Richmond IN 47374",
    "addr:housenumber":"320",
    "addr:postcode":"47374",
    "addr:street":"Sw D St",
    "iso:country":"US",
    "sg:address":"320 SW D St",
    "sg:city":"Richmond",
    "sg:classifiers":[
        {
            "category":"Shopping",
            "subcategory":"Gifts & Souvenirs",
            "type":"Retail Goods"
        }
    ],
    "sg:phone":"+1 765 966 7155",
    "sg:postcode":"47374",
    "sg:province":"IN",
    "wof:name":"From Heart By SIS",
    "wof:placetype":"venue"
},
  "geometry": {"coordinates":[-84.90692,39.823792],"type":"Point"}
}