{
  "type": "Feature",
  "properties": {
    "iso:country":"US",
    "sg:address":"1 Farabee Dr",
    "sg:city":"Lafayette",
    "sg:classifiers":[
        {
            "category":"Building & Trades",
            "subcategory":"Plumbing",
            "type":"Services"
        }
    ],
    "sg:phone":"+1 765 448 1443",
    "sg:postcode":"47905",
    "sg:province":"IN",
    "sg:tags":[
        "septic"
    ],
    "wof:name":"Ike's Sewer Svc",
    "wof:placetype":"venue"
},
  "geometry": {"coordinates":[-86.851908,40.410256],"type":"Point"}
}