{
  "type": "Feature",
  "properties": {
    "iso:country":"US",
    "sg:address":"6411 E 16th St",
    "sg:city":"Indianapolis",
    "sg:classifiers":[
        {
            "category":"Retail",
            "subcategory":"Animal Services",
            "type":"Services"
        }
    ],
    "sg:phone":"+1 317 351 8066",
    "sg:postcode":"46219",
    "sg:province":"IN",
    "wof:name":"Doggy Duty",
    "wof:placetype":"venue"
},
  "geometry": {"coordinates":[-86.054792,39.78896],"type":"Point"}
}