{
  "type": "Feature",
  "properties": {
    "iso:country":"US",
    "sg:address":"2523 W Lincoln Hwy",
    "sg:city":"Merrillville",
    "sg:classifiers":[
        {
            "category":"Shopping",
            "type":"Retail Goods"
        }
    ],
    "sg:phone":"+1 219 865 6838",
    "sg:postcode":"46410",
    "sg:province":"IN",
    "sg:tags":[
        "picture",
        "frame"
    ],
    "wof:name":"Family Tree Gallery",
    "wof:placetype":"venue"
},
  "geometry": {"coordinates":[-87.367464,41.471045],"type":"Point"}
}