{
  "type": "Feature",
  "properties": {
    "addr:full":"3685 Grant St Gary IN 46408",
    "addr:housenumber":"3685",
    "addr:postcode":"46408",
    "addr:street":"Grant St Gary",
    "iso:country":"US",
    "sg:address":"3685 Grant St",
    "sg:city":"Gary",
    "sg:classifiers":[
        {
            "category":"Personal",
            "subcategory":"Beauty Salon",
            "type":"Services"
        }
    ],
    "sg:phone":"+1 219 949 1785",
    "sg:postcode":"46408",
    "sg:province":"IN",
    "wof:name":"Salon Eboni",
    "wof:placetype":"venue"
},
  "geometry": {"coordinates":[-87.355807,41.552964],"type":"Point"}
}