{
  "type": "Feature",
  "properties": {
    "iso:country":"US",
    "sg:address":"925 S 13th St",
    "sg:city":"Decatur",
    "sg:classifiers":[
        {
            "category":"Restaurant",
            "type":"Food & Drink"
        }
    ],
    "sg:phone":"+1 260 724 7407",
    "sg:postcode":"46733",
    "sg:province":"IN",
    "wof:name":"Peking",
    "wof:placetype":"venue"
},
  "geometry": {"coordinates":[-84.93733,40.819421],"type":"Point"}
}