{
  "type": "Feature",
  "properties": {
    "iso:country":"US",
    "sg:address":"569 Tyler St",
    "sg:city":"Gary",
    "sg:classifiers":[
        {
            "category":"Health Services",
            "subcategory":"Doctor",
            "type":"Services"
        }
    ],
    "sg:phone":"+1 219 885 3300",
    "sg:postcode":"46402",
    "sg:province":"IN",
    "sg:tags":[
        "physician",
        "surgeon"
    ],
    "wof:name":"Northwest In Dialysis",
    "wof:placetype":"venue"
},
  "geometry": {"coordinates":[-87.348365,41.600906],"type":"Point"}
}