{
  "type": "Feature",
  "properties": {
    "iso:country":"US",
    "sg:address":"6301 Hollingsworth Dr",
    "sg:city":"Indianapolis",
    "sg:classifiers":[
        {
            "category":"Building & Trades",
            "subcategory":"Cleaning & Sanitation",
            "type":"Services"
        }
    ],
    "sg:phone":"+1 317 387 0798",
    "sg:postcode":"46268",
    "sg:province":"IN",
    "sg:tags":[
        "janitorial"
    ],
    "wof:name":"Grahams Janitorial Service",
    "wof:placetype":"venue"
},
  "geometry": {"coordinates":[-86.215526,39.871392],"type":"Point"}
}