{
  "type": "Feature",
  "properties": {
    "iso:country":"US",
    "sg:address":"531 Winston Ct",
    "sg:city":"Schererville",
    "sg:classifiers":[
        {
            "category":"Building & Trades",
            "subcategory":"Construction",
            "type":"Services"
        }
    ],
    "sg:phone":"+1 219 322 2300",
    "sg:postcode":"46375",
    "sg:province":"IN",
    "sg:tags":[
        "sewer",
        "contractor"
    ],
    "wof:name":"B & D Sewer & Backhoe Svc",
    "wof:placetype":"venue"
},
  "geometry": {"coordinates":[-87.462175,41.516941],"type":"Point"}
}