{
  "type": "Feature",
  "properties": {
    "iso:country":"US",
    "sg:address":"3141 Willowcreek Rd",
    "sg:city":"Portage",
    "sg:classifiers":[
        {
            "category":"Insurance",
            "subcategory":"Insurance Agent",
            "type":"Services"
        }
    ],
    "sg:phone":"+1 219 763 2200",
    "sg:postcode":"46368",
    "sg:province":"IN",
    "sg:website":"www.statefarm.com",
    "wof:name":"State Farm Insurance",
    "wof:placetype":"venue"
},
  "geometry": {"coordinates":[-87.182698,41.561326],"type":"Point"}
}