{
  "type": "Feature",
  "properties": {
    "iso:country":"US",
    "sg:address":"330 E Windsor Ave",
    "sg:city":"Elkhart",
    "sg:classifiers":[
        {
            "category":"Building & Trades",
            "subcategory":"Construction",
            "type":"Services"
        }
    ],
    "sg:phone":"+1 574 262 2540",
    "sg:postcode":"46514",
    "sg:province":"IN",
    "sg:tags":[
        "house"
    ],
    "wof:name":"Jack of All Trades Services",
    "wof:placetype":"venue"
},
  "geometry": {"coordinates":[-85.974146,41.726918],"type":"Point"}
}