{
  "type": "Feature",
  "properties": {
    "iso:country":"US",
    "sg:address":"306 N Main St",
    "sg:city":"Salem",
    "sg:classifiers":[
        {
            "category":"Autos & Motor Vehicles",
            "subcategory":"Fuel & Gas Station",
            "type":"Retail Goods"
        }
    ],
    "sg:phone":"+1 812 883 6548",
    "sg:postcode":"47167",
    "sg:province":"IN",
    "sg:tags":[
        "oil"
    ],
    "wof:name":"Swifty Oil Co",
    "wof:placetype":"venue"
},
  "geometry": {"coordinates":[-86.100906,38.6082],"type":"Point"}
}