{
  "type": "Feature",
  "properties": {
    "iso:country":"US",
    "sg:address":"2400 Roosevelt Ave",
    "sg:city":"Indianapolis",
    "sg:classifiers":[
        {
            "category":"Manufacturing",
            "subcategory":"Tools & Machinery",
            "type":"Manufacturing & Wholesale Goods"
        }
    ],
    "sg:phone":"+1 317 263 9160",
    "sg:postcode":"46218",
    "sg:province":"IN",
    "sg:tags":[
        "apparatus"
    ],
    "sg:website":"www.tst-corp.com",
    "wof:name":"Transportation Safety Tech",
    "wof:placetype":"venue"
},
  "geometry": {"coordinates":[-86.120787,39.793557],"type":"Point"}
}