{
  "type": "Feature",
  "properties": {
    "iso:country":"US",
    "sg:address":"6345 Sunnyside Rd",
    "sg:city":"Indianapolis",
    "sg:classifiers":[
        {
            "category":"Education",
            "subcategory":"School",
            "type":"Public Place"
        },
        {
            "category":"Government",
            "subcategory":"Office",
            "type":"Public Place"
        }
    ],
    "sg:phone":"+1 317 964 4500",
    "sg:postcode":"46236",
    "sg:province":"IN",
    "sg:website":"http://www.msdlt.k12.in.us",
    "wof:name":"Sunnyside Elementary School",
    "wof:placetype":"venue"
},
  "geometry": {"coordinates":[-85.97315999999999,39.87413],"type":"Point"}
}