{
  "type": "Feature",
  "properties": {
    "iso:country":"US",
    "sg:address":"200 S Gardener St",
    "sg:city":"Scottsburg",
    "sg:classifiers":[
        {
            "category":"Cinema",
            "subcategory":"Movie Rental",
            "type":"Entertainment"
        }
    ],
    "sg:phone":"+1 812 752 0720",
    "sg:postcode":"47170",
    "sg:province":"IN",
    "sg:tags":[
        "leasing",
        "video",
        "disc",
        "tape"
    ],
    "wof:name":"Movie Gallery",
    "wof:placetype":"venue"
},
  "geometry": {"coordinates":[-85.778384,38.683916],"type":"Point"}
}