{
  "type": "Feature",
  "properties": {
    "iso:country":"US",
    "sg:address":"415 W Main St",
    "sg:city":"Portland",
    "sg:classifiers":[
        {
            "category":"Personal",
            "subcategory":"Barber",
            "type":"Services"
        }
    ],
    "sg:phone":"+1 260 726 8667",
    "sg:postcode":"47371",
    "sg:province":"IN",
    "sg:tags":[
        "shop"
    ],
    "wof:name":"Eads Barber Shop",
    "wof:placetype":"venue"
},
  "geometry": {"coordinates":[-84.981847,40.433176],"type":"Point"}
}