{
  "type": "Feature",
  "properties": {
    "iso:country":"US",
    "sg:address":"1003 Hartzell Rd",
    "sg:city":"New Haven",
    "sg:classifiers":[
        {
            "category":"Manufacturing",
            "subcategory":"Tools & Machinery",
            "type":"Manufacturing & Wholesale Goods"
        }
    ],
    "sg:phone":"+1 260 749 9789",
    "sg:postcode":"46774",
    "sg:province":"IN",
    "sg:tags":[
        "bulb",
        "lamp",
        "electric",
        "tube"
    ],
    "sg:website":"www.uniquelamp.com",
    "wof:name":"Unique Lamp Co Inc",
    "wof:placetype":"venue"
},
  "geometry": {"coordinates":[-85.03005400000001,41.067014],"type":"Point"}
}