{
  "type": "Feature",
  "properties": {
    "iso:country":"US",
    "sg:address":"4000 W 10th St",
    "sg:city":"Indianapolis",
    "sg:classifiers":[
        {
            "category":"Wholesale",
            "subcategory":"Scrap",
            "type":"Manufacturing & Wholesale Goods"
        }
    ],
    "sg:phone":"+1 317 247 7160",
    "sg:postcode":"46222",
    "sg:province":"IN",
    "sg:tags":[
        "waste"
    ],
    "wof:name":"EQ Transfer & Processing",
    "wof:placetype":"venue"
},
  "geometry": {"coordinates":[-86.231218,39.780274],"type":"Point"}
}