{
  "type": "Feature",
  "properties": {
    "iso:country":"US",
    "sg:address":"2704 W Dunes Hwy",
    "sg:city":"Michigan City",
    "sg:classifiers":[
        {
            "category":"Food & Beverages",
            "subcategory":"Groceries & Convenience Stores",
            "type":"Retail Goods"
        }
    ],
    "sg:phone":"+1 219 872 2301",
    "sg:postcode":"46360",
    "sg:province":"IN",
    "sg:tags":[
        "grocer"
    ],
    "wof:name":"Spotlite",
    "wof:placetype":"venue"
},
  "geometry": {"coordinates":[-86.932576,41.695453],"type":"Point"}
}