{
  "type": "Feature",
  "properties": {
    "addr:full":"1014 N Sheffield Ave Indianapolis IN 46222",
    "addr:housenumber":"1014",
    "addr:postcode":"46222",
    "addr:street":"N Sheffield Ave",
    "iso:country":"US",
    "sg:address":"1014 N Sheffield Ave",
    "sg:city":"Indianapolis",
    "sg:classifiers":[
        {
            "category":"Social Services",
            "subcategory":"Child Care",
            "type":"Services"
        }
    ],
    "sg:phone":"+1 317 685 2838",
    "sg:postcode":"46222",
    "sg:province":"IN",
    "wof:name":"Ebony's Daycare",
    "wof:placetype":"venue"
},
  "geometry": {"coordinates":[-86.19819,39.782247],"type":"Point"}
}