{
  "type": "Feature",
  "properties": {
    "iso:country":"US",
    "sg:address":"247 Webb St",
    "sg:city":"Hammond",
    "sg:classifiers":[
        {
            "category":"Professional",
            "subcategory":"Management & Consulting",
            "type":"Services"
        }
    ],
    "sg:phone":"+1 219 937 2371",
    "sg:postcode":"46320",
    "sg:province":"IN",
    "wof:name":"B & B Management Svc",
    "wof:placetype":"venue"
},
  "geometry": {"coordinates":[-87.519493,41.609533],"type":"Point"}
}