{
  "type": "Feature",
  "properties": {
    "iso:country":"US",
    "sg:address":"106 S 5th St",
    "sg:city":"Middletown",
    "sg:classifiers":[
        {
            "category":"Wholesale",
            "subcategory":"Office Equipment",
            "type":"Manufacturing & Wholesale Goods"
        }
    ],
    "sg:phone":"+1 765 354 9890",
    "sg:postcode":"47356",
    "sg:province":"IN",
    "sg:tags":[
        "machine",
        "duplicating",
        "copying"
    ],
    "wof:name":"SOS Sales & Svc Inc",
    "wof:placetype":"venue"
},
  "geometry": {"coordinates":[-85.53349300000001,40.054157],"type":"Point"}
}