{
  "type": "Feature",
  "properties": {
    "iso:country":"US",
    "sg:address":"6964 Hillsdale Ct",
    "sg:city":"Indianapolis",
    "sg:classifiers":[
        {
            "category":"Professional",
            "subcategory":"Testing Lab",
            "type":"Services"
        }
    ],
    "sg:phone":"+1 317 842 4261",
    "sg:postcode":"46250",
    "sg:province":"IN",
    "sg:tags":[
        "laboratory"
    ],
    "sg:website":"www.testamericainc.com",
    "wof:name":"Testamerica Inc",
    "wof:placetype":"venue"
},
  "geometry": {"coordinates":[-86.046925,39.896237],"type":"Point"}
}