{
  "type": "Feature",
  "properties": {
    "iso:country":"US",
    "sg:address":"10515 King Rd",
    "sg:city":"Plymouth",
    "sg:classifiers":[
        {
            "category":"Building & Trades",
            "subcategory":"Cleaning & Sanitation",
            "type":"Services"
        }
    ],
    "sg:phone":"+1 574 935 5257",
    "sg:postcode":"46563",
    "sg:province":"IN",
    "sg:tags":[
        "maintenance"
    ],
    "wof:name":"Smith Janitorial & Carpet Svc",
    "wof:placetype":"venue"
},
  "geometry": {"coordinates":[-86.26118099999999,41.323429],"type":"Point"}
}