{
  "type": "Feature",
  "properties": {
    "addr:full":"502 Wall St Valparaiso IN 46383",
    "addr:housenumber":"502",
    "addr:postcode":"46383",
    "addr:street":"Wall St",
    "iso:country":"US",
    "sg:address":"502 Wall St",
    "sg:city":"Valparaiso",
    "sg:classifiers":[
        {
            "category":"Banks & Credit Unions",
            "subcategory":"Investment Brokerage",
            "type":"Services"
        }
    ],
    "sg:phone":"+1 219 465 6192",
    "sg:postcode":"46383",
    "sg:province":"IN",
    "sg:tags":[
        "advisory",
        "financial"
    ],
    "wof:name":"Raymond James Financial Svc",
    "wof:placetype":"venue"
},
  "geometry": {"coordinates":[-87.053901,41.488699],"type":"Point"}
}