{
  "type": "Feature",
  "properties": {
    "iso:country":"US",
    "sg:address":"210 N Meridian St",
    "sg:city":"Portland",
    "sg:classifiers":[
        {
            "category":"Social Services",
            "type":"Services"
        }
    ],
    "sg:phone":"+1 260 726 3880",
    "sg:postcode":"47371",
    "sg:province":"IN",
    "sg:tags":[
        "organization",
        "welfare"
    ],
    "wof:name":"Aids Task Force-E Central In",
    "wof:placetype":"venue"
},
  "geometry": {"coordinates":[-84.97798299999999,40.435253],"type":"Point"}
}