{
  "type": "Feature",
  "properties": {
    "iso:country":"US",
    "sg:address":"7330 State Rd 256",
    "sg:city":"Madison",
    "sg:classifiers":[
        {
            "category":"Farming",
            "subcategory":"Aquatic Farm",
            "type":"Manufacturing & Wholesale Goods"
        }
    ],
    "sg:phone":"+1 812 866 3474",
    "sg:postcode":"47250",
    "sg:province":"IN",
    "sg:tags":[
        "fish"
    ],
    "wof:name":"Tri-State Fish",
    "wof:placetype":"venue"
},
  "geometry": {"coordinates":[-85.52285000000001,38.737896],"type":"Point"}
}