{
  "type": "Feature",
  "properties": {
    "iso:country":"US",
    "sg:address":"824 S 9th St",
    "sg:city":"Noblesville",
    "sg:classifiers":[
        {
            "category":"Building & Trades",
            "subcategory":"Construction",
            "type":"Services"
        }
    ],
    "sg:phone":"+1 317 849 9496",
    "sg:postcode":"46060",
    "sg:province":"IN",
    "sg:tags":[
        "contractor"
    ],
    "wof:name":"John A Dell Enterprises Inc",
    "wof:placetype":"venue"
},
  "geometry": {"coordinates":[-86.01334300000001,40.038841],"type":"Point"}
}