{
  "type": "Feature",
  "properties": {
    "addr:full":"3148 S Holt Rd Indianapolis IN 46221",
    "addr:housenumber":"3148",
    "addr:postcode":"46221",
    "addr:street":"S Holt Rd",
    "iso:country":"US",
    "sg:address":"3148 S Holt Rd",
    "sg:city":"Indianapolis",
    "sg:classifiers":[
        {
            "category":"Manufacturing",
            "subcategory":"Metals",
            "type":"Manufacturing & Wholesale Goods"
        },
        {
            "category":"Manufacturing",
            "subcategory":"Tools & Machinery",
            "type":"Manufacturing & Wholesale Goods"
        }
    ],
    "sg:phone":"+1 317 244 5889",
    "sg:postcode":"46221",
    "sg:province":"IN",
    "sg:tags":[
        "shop",
        "machine",
        "industrial",
        "weld",
        "mfg"
    ],
    "wof:name":"Denver Stone Machine Shop Co",
    "wof:placetype":"venue"
},
  "geometry": {"coordinates":[-86.225172,39.717722],"type":"Point"}
}