{
  "type": "Feature",
  "properties": {
    "iso:country":"US",
    "sg:address":"5278 E 32nd St",
    "sg:city":"Indianapolis",
    "sg:classifiers":[
        {
            "category":"Professional",
            "type":"Services"
        }
    ],
    "sg:phone":"+1 317 541 0658",
    "sg:postcode":"46218",
    "sg:province":"IN",
    "sg:tags":[
        "establishment"
    ],
    "wof:name":"Miss Tyler's",
    "wof:placetype":"venue"
},
  "geometry": {"coordinates":[-86.082484,39.814751],"type":"Point"}
}