{
  "type": "Feature",
  "properties": {
    "iso:country":"US",
    "sg:address":"803 S Main St",
    "sg:city":"Bluffton",
    "sg:classifiers":[
        {
            "category":"Insurance",
            "subcategory":"Insurance Agent",
            "type":"Services"
        }
    ],
    "sg:phone":"+1 260 824 1814",
    "sg:postcode":"46714",
    "sg:province":"IN",
    "wof:name":"Barton Insurance",
    "wof:placetype":"venue"
},
  "geometry": {"coordinates":[-85.171334,40.732317],"type":"Point"}
}