{
  "type": "Feature",
  "properties": {
    "iso:country":"US",
    "sg:address":"7414 Campfire Run",
    "sg:city":"Indianapolis",
    "sg:classifiers":[
        {
            "category":"Wholesale",
            "subcategory":"Durable Goods & Equipment",
            "type":"Manufacturing & Wholesale Goods"
        }
    ],
    "sg:phone":"+1 317 834 6430",
    "sg:postcode":"46236",
    "sg:province":"IN",
    "sg:tags":[
        "representative",
        "manufacturer"
    ],
    "wof:name":"Precision Marketing Co",
    "wof:placetype":"venue"
},
  "geometry": {"coordinates":[-85.977397,39.88921],"type":"Point"}
}