{
  "type": "Feature",
  "properties": {
    "iso:country":"US",
    "sg:address":"734 S 300 W",
    "sg:city":"Hebron",
    "sg:classifiers":[
        {
            "category":"Farming",
            "subcategory":"Farm",
            "type":"Manufacturing & Wholesale Goods"
        }
    ],
    "sg:phone":"+1 219 996 6077",
    "sg:postcode":"46341",
    "sg:province":"IN",
    "wof:name":"Hallberg Brothers",
    "wof:placetype":"venue"
},
  "geometry": {"coordinates":[-87.127852,41.330593],"type":"Point"}
}