{
  "type": "Feature",
  "properties": {
    "addr:full":"1222 E State Rd 164 Jasper IN 47546",
    "addr:housenumber":"1222;164",
    "addr:postcode":"47546",
    "addr:street":"E State Rd",
    "iso:country":"US",
    "sg:address":"1222 E State Rd 164",
    "sg:city":"Jasper",
    "sg:classifiers":[
        {
            "category":"Manufacturing",
            "subcategory":"Tools & Machinery",
            "type":"Manufacturing & Wholesale Goods"
        }
    ],
    "sg:phone":"+1 812 482 5489",
    "sg:postcode":"47546",
    "sg:province":"IN",
    "sg:tags":[
        "food",
        "product",
        "mfg"
    ],
    "wof:name":"Elmer Buechler",
    "wof:placetype":"venue"
},
  "geometry": {"coordinates":[-86.882071,38.388923],"type":"Point"}
}