{
  "type": "Feature",
  "properties": {
    "iso:country":"US",
    "sg:address":"3023 E 500 S",
    "sg:city":"Waldron",
    "sg:phone":"+1 765 525 4802",
    "sg:postcode":"46182",
    "sg:province":"IN",
    "sg:tags":[
        "farm",
        "corn",
        "wheat",
        "soybean"
    ],
    "wof:name":"Dennis Hartman",
    "wof:placetype":"venue"
},
  "geometry": {"coordinates":[-85.722274,39.453168],"type":"Point"}
}