{
  "type": "Feature",
  "properties": {
    "iso:country":"US",
    "sg:address":"509 Calhoun St",
    "sg:city":"Mishawaka",
    "sg:classifiers":[
        {
            "category":"Real Estate",
            "subcategory":"Real Estate Agent",
            "type":"Services"
        }
    ],
    "sg:phone":"+1 574 259 6936",
    "sg:postcode":"46545",
    "sg:province":"IN",
    "wof:name":"Samuel & Assoc",
    "wof:placetype":"venue"
},
  "geometry": {"coordinates":[-86.195218,41.665448],"type":"Point"}
}