{
  "type": "Feature",
  "properties": {
    "iso:country":"US",
    "sg:address":"6207 W Taylor Rd",
    "sg:city":"Muncie",
    "sg:classifiers":[
        {
            "category":"Organizations",
            "subcategory":"Religious Organization",
            "type":"Services"
        }
    ],
    "sg:phone":"+1 765 282 7666",
    "sg:postcode":"47304",
    "sg:province":"IN",
    "sg:tags":[
        "church"
    ],
    "wof:name":"New Testament Christian",
    "wof:placetype":"venue"
},
  "geometry": {"coordinates":[-85.46172,40.182093],"type":"Point"}
}