{
  "type": "Feature",
  "properties": {
    "iso:country":"US",
    "sg:address":"227 Virginia Ave",
    "sg:city":"Sellersburg",
    "sg:classifiers":[
        {
            "category":"Freight",
            "type":"Transportation"
        }
    ],
    "sg:phone":"+1 812 246 3954",
    "sg:postcode":"47172",
    "sg:province":"IN",
    "sg:tags":[
        "trucking"
    ],
    "wof:name":"Mc Kinley Trucking Inc",
    "wof:placetype":"venue"
},
  "geometry": {"coordinates":[-85.754186,38.409833],"type":"Point"}
}