{
  "type": "Feature",
  "properties": {
    "iso:country":"US",
    "sg:address":"8197 N 700 E",
    "sg:city":"Falmouth",
    "sg:classifiers":[
        {
            "category":"Manufacturing",
            "subcategory":"Toys & Sporting Goods",
            "type":"Manufacturing & Wholesale Goods"
        }
    ],
    "sg:phone":"+1 765 679 5842",
    "sg:postcode":"46127",
    "sg:province":"IN",
    "sg:tags":[
        "mfg"
    ],
    "wof:name":"Gwinnup Farms",
    "wof:placetype":"venue"
},
  "geometry": {"coordinates":[-85.32032599999999,39.731044],"type":"Point"}
}