{
  "type": "Feature",
  "properties": {
    "iso:country":"US",
    "sg:address":"52361 Co Rd 13",
    "sg:city":"Elkhart",
    "sg:classifiers":[
        {
            "category":"Professional",
            "subcategory":"Business Services",
            "type":"Services"
        }
    ],
    "sg:phone":"+1 574 264 5640",
    "sg:postcode":"46514",
    "sg:province":"IN",
    "wof:name":"Fair Assoc Inc",
    "wof:placetype":"venue"
},
  "geometry": {"coordinates":[-85.92763100000001,41.73255],"type":"Point"}
}