{
  "type": "Feature",
  "properties": {
    "iso:country":"US",
    "sg:address":"340 S Main St",
    "sg:city":"Montpelier",
    "sg:classifiers":[
        {
            "category":"Personal",
            "subcategory":"Beauty Salon",
            "type":"Services"
        }
    ],
    "sg:phone":"+1 765 728 5464",
    "sg:postcode":"47359",
    "sg:province":"IN",
    "sg:tags":[
        "shop"
    ],
    "wof:name":"Shears Hair Design",
    "wof:placetype":"venue"
},
  "geometry": {"coordinates":[-85.278407,40.552666],"type":"Point"}
}