{
  "type": "Feature",
  "properties": {
    "iso:country":"US",
    "sg:address":"3750 E 400 N",
    "sg:city":"Knox",
    "sg:classifiers":[
        {
            "category":"Personal",
            "subcategory":"Beauty Salon",
            "type":"Services"
        }
    ],
    "sg:phone":"+1 574 772 5789",
    "sg:postcode":"46534",
    "sg:province":"IN",
    "wof:name":"New Creation Hair Salon",
    "wof:placetype":"venue"
},
  "geometry": {"coordinates":[-86.620944,41.360668],"type":"Point"}
}