{
  "type": "Feature",
  "properties": {
    "iso:country":"US",
    "sg:address":"1216 Fairview Dr",
    "sg:city":"Greenfield",
    "sg:classifiers":[
        {
            "category":"Real Estate",
            "subcategory":"Real Estate Operator",
            "type":"Services"
        }
    ],
    "sg:phone":"+1 317 462 1670",
    "sg:postcode":"46140",
    "sg:province":"IN",
    "sg:tags":[
        "apartment"
    ],
    "wof:name":"Scroggham Rentals",
    "wof:placetype":"venue"
},
  "geometry": {"coordinates":[-85.778752,39.800559],"type":"Point"}
}