{
  "type": "Feature",
  "properties": {
    "iso:country":"US",
    "sg:address":"2324 Hunter St",
    "sg:city":"Huntertown",
    "sg:classifiers":[
        {
            "category":"Retail",
            "subcategory":"Laundry & Dry Cleaning",
            "type":"Services"
        }
    ],
    "sg:phone":"+1 260 637 3332",
    "sg:postcode":"46748",
    "sg:province":"IN",
    "sg:tags":[
        "drycleaning",
        "plant"
    ],
    "wof:name":"Enterprise Cleaners MBL Valet",
    "wof:placetype":"venue"
},
  "geometry": {"coordinates":[-85.17555299999999,41.228046],"type":"Point"}
}