{
  "type": "Feature",
  "properties": {
    "iso:country":"US",
    "sg:address":"2347 N Union Rd",
    "sg:city":"Walkerton",
    "sg:classifiers":[
        {
            "category":"Personal",
            "subcategory":"Beauty Salon",
            "type":"Services"
        }
    ],
    "sg:phone":"+1 574 586 3034",
    "sg:postcode":"46574",
    "sg:province":"IN",
    "sg:tags":[
        "cosmetologist"
    ],
    "wof:name":"Linda D Bella",
    "wof:placetype":"venue"
},
  "geometry": {"coordinates":[-86.444497,41.442783],"type":"Point"}
}