{
  "type": "Feature",
  "properties": {
    "iso:country":"US",
    "sg:address":"5410 S High School Rd",
    "sg:city":"Indianapolis",
    "sg:classifiers":[
        {
            "category":"Government",
            "subcategory":"Fire Station",
            "type":"Public Place"
        },
        {
            "category":"Government",
            "subcategory":"Office",
            "type":"Public Place"
        }
    ],
    "sg:phone":"+1 317 856 5400",
    "sg:postcode":"46221",
    "sg:province":"IN",
    "sg:tags":[
        "department",
        "township",
        "protection",
        "government-city",
        "village"
    ],
    "sg:website":"http://www.indfirechiefs.org",
    "wof:name":"Decatur Township Fire Dept",
    "wof:placetype":"venue"
},
  "geometry": {"coordinates":[-86.26933,39.685809],"type":"Point"}
}