{
  "type": "Feature",
  "properties": {
    "iso:country":"US",
    "sg:address":"3101 Mount Vernon Ave",
    "sg:city":"Evansville",
    "sg:classifiers":[
        {
            "category":"Food & Beverages",
            "subcategory":"Groceries & Convenience Stores",
            "type":"Retail Goods"
        }
    ],
    "sg:phone":"+1 812 464 3079",
    "sg:postcode":"47712",
    "sg:province":"IN",
    "wof:name":"Kiel Brothers Oil Co Inc",
    "wof:placetype":"venue"
},
  "geometry": {"coordinates":[-87.61559099999999,37.983664],"type":"Point"}
}