{
  "type": "Feature",
  "properties": {
    "addr:full":"12123 Donnington Ln Fishers IN 46037",
    "addr:housenumber":"12123",
    "addr:postcode":"46037",
    "addr:street":"Donnington Ln",
    "iso:country":"US",
    "sg:address":"12123 Donnington Ln",
    "sg:city":"Fishers",
    "sg:classifiers":[
        {
            "category":"Professional",
            "subcategory":"Management & Consulting",
            "type":"Services"
        }
    ],
    "sg:phone":"+1 317 915 9408",
    "sg:postcode":"46037",
    "sg:province":"IN",
    "sg:tags":[
        "business"
    ],
    "wof:name":"Braun Real Estate Consulting I",
    "wof:placetype":"venue"
},
  "geometry": {"coordinates":[-85.92700499999999,39.964413],"type":"Point"}
}