{
  "type": "Feature",
  "properties": {
    "iso:country":"US",
    "sg:address":"3839 Timothy Trl",
    "sg:city":"Lafayette",
    "sg:classifiers":[
        {
            "category":"Professional",
            "subcategory":"Computer Services",
            "type":"Services"
        }
    ],
    "sg:phone":"+1 765 446 2646",
    "sg:postcode":"47905",
    "sg:province":"IN",
    "sg:tags":[
        "repair"
    ],
    "sg:website":"www.upgrade1.com",
    "wof:name":"Upgrade Computer Svc",
    "wof:placetype":"venue"
},
  "geometry": {"coordinates":[-86.836029,40.407848],"type":"Point"}
}