{
  "type": "Feature",
  "properties": {
    "iso:country":"US",
    "sg:address":"1108 US Hwy 27 N",
    "sg:city":"Berne",
    "sg:classifiers":[
        {
            "category":"Shopping",
            "subcategory":"Department Store",
            "type":"Retail Goods"
        }
    ],
    "sg:phone":"+1 260 589 8447",
    "sg:postcode":"46711",
    "sg:province":"IN",
    "sg:tags":[
        "shop"
    ],
    "wof:name":"Family Dollar Store",
    "wof:placetype":"venue"
},
  "geometry": {"coordinates":[-84.95567,40.668056],"type":"Point"}
}