{
  "type": "Feature",
  "properties": {
    "addr:full":"1409 E Virginia St Evansville IN 47711",
    "addr:housenumber":"1409",
    "addr:postcode":"47711",
    "addr:street":"E Virginia St",
    "iso:country":"US",
    "sg:address":"1409 E Virginia St",
    "sg:city":"Evansville",
    "sg:classifiers":[
        {
            "category":"Shopping",
            "subcategory":"Pharmacy",
            "type":"Retail Goods"
        }
    ],
    "sg:phone":"+1 812 421 1002",
    "sg:postcode":"47711",
    "sg:province":"IN",
    "sg:website":"www.radiopharmacy.com",
    "wof:name":"Radiopharmacy",
    "wof:placetype":"venue"
},
  "geometry": {"coordinates":[-87.541479,37.981256],"type":"Point"}
}