{
  "type": "Feature",
  "properties": {
    "iso:country":"US",
    "sg:address":"8657 E Diane Dr",
    "sg:city":"Ossian",
    "sg:classifiers":[
        {
            "category":"Utilities",
            "subcategory":"Telephone",
            "type":"Services"
        }
    ],
    "sg:phone":"+1 260 622 2222",
    "sg:postcode":"46777",
    "sg:province":"IN",
    "sg:tags":[
        "messaging",
        "voice",
        "equipment"
    ],
    "wof:name":"Info Net Voice Mail Svc",
    "wof:placetype":"venue"
},
  "geometry": {"coordinates":[-85.165552,40.870064],"type":"Point"}
}