{
  "type": "Feature",
  "properties": {
    "iso:country":"US",
    "sg:address":"407 W 30th St",
    "sg:city":"Connersville",
    "sg:classifiers":[
        {
            "category":"Restaurant",
            "type":"Food & Drink"
        }
    ],
    "sg:menulink":"http://www.allmenus.com/in/harrison/237745-rax/menu/",
    "sg:phone":"+1 765 825 6666",
    "sg:postcode":"47331",
    "sg:province":"IN",
    "sg:tags":[
        "wrap",
        "american",
        "sandwich"
    ],
    "wof:name":"Rax",
    "wof:placetype":"venue"
},
  "geometry": {"coordinates":[-85.133443,39.671631],"type":"Point"}
}