{
  "type": "Feature",
  "properties": {
    "addr:full":"811 W Main St Ste 100 Carmel IN 46032",
    "addr:housenumber":"811",
    "addr:postcode":"46032",
    "addr:street":"W Main St Ste 100",
    "iso:country":"US",
    "sg:address":"811 W Main St Ste 100",
    "sg:city":"Carmel",
    "sg:classifiers":[
        {
            "category":"Autos & Motor Vehicles",
            "subcategory":"Automobile Sales",
            "type":"Retail Goods"
        },
        {
            "category":"Autos & Motor Vehicles",
            "subcategory":"Auto Supplies",
            "type":"Retail Goods"
        },
        {
            "category":"Retail",
            "subcategory":"Auto Repair",
            "type":"Services"
        }
    ],
    "sg:phone":"+1 317 846 3216",
    "sg:postcode":"46032",
    "sg:province":"IN",
    "sg:tags":[
        "oil",
        "tire",
        "automotive",
        "equipment",
        "lube",
        "brake",
        "equipment-service",
        "air conditioning",
        "tune"
    ],
    "sg:website":"www.joesautoservice.net",
    "wof:name":"Joe's Auto Service",
    "wof:placetype":"venue"
},
  "geometry": {"coordinates":[-86.141513,39.97812],"type":"Point"}
}