{
  "type": "Feature",
  "properties": {
    "addr:full":"1603 Lynch Ln Clarksville IN 47129",
    "addr:housenumber":"1603",
    "addr:postcode":"47129",
    "addr:street":"Lynch Ln",
    "iso:country":"US",
    "sg:address":"1603 Lynch Ln",
    "sg:city":"Clarksville",
    "sg:classifiers":[
        {
            "category":"Insurance",
            "subcategory":"Insurance Agent",
            "type":"Services"
        }
    ],
    "sg:phone":"+1 812 288 8874",
    "sg:postcode":"47129",
    "sg:province":"IN",
    "wof:name":"American Family Insurance",
    "wof:placetype":"venue"
},
  "geometry": {"coordinates":[-85.769077,38.316644],"type":"Point"}
}