{
  "type": "Feature",
  "properties": {
    "iso:country":"US",
    "sg:address":"409 Indianapolis Ave",
    "sg:city":"Lebanon",
    "sg:classifiers":[
        {
            "category":"Wholesale",
            "subcategory":"Hardware",
            "type":"Manufacturing & Wholesale Goods"
        }
    ],
    "sg:phone":"+1 765 482 7000",
    "sg:postcode":"46052",
    "sg:province":"IN",
    "sg:tags":[
        "heating"
    ],
    "sg:website":"www.perezsteele.com",
    "wof:name":"USA Manufacturing Corp",
    "wof:placetype":"venue"
},
  "geometry": {"coordinates":[-86.46191,40.04429],"type":"Point"}
}