{
  "type": "Feature",
  "properties": {
    "iso:country":"US",
    "sg:address":"1314 N Anderson St",
    "sg:city":"Greensburg",
    "sg:classifiers":[
        {
            "category":"Building & Trades",
            "subcategory":"Plumbing",
            "type":"Services"
        }
    ],
    "sg:phone":"+1 812 662 7344",
    "sg:postcode":"47240",
    "sg:province":"IN",
    "sg:tags":[
        "contractor"
    ],
    "wof:name":"Bailey Plumbing",
    "wof:placetype":"venue"
},
  "geometry": {"coordinates":[-85.490279,39.350282],"type":"Point"}
}