{
  "type": "Feature",
  "properties": {
    "iso:country":"US",
    "sg:address":"901 N Main St",
    "sg:city":"Franklin",
    "sg:classifiers":[
        {
            "category":"Health Services",
            "subcategory":"Podiatrist",
            "type":"Services"
        }
    ],
    "sg:phone":"+1 317 736 8717",
    "sg:postcode":"46131",
    "sg:province":"IN",
    "wof:name":"Franklin Foot Clinic",
    "wof:placetype":"venue"
},
  "geometry": {"coordinates":[-86.058979,39.489589],"type":"Point"}
}