{
  "type": "Feature",
  "properties": {
    "iso:country":"US",
    "sg:address":"195 S 5th St",
    "sg:city":"Noblesville",
    "sg:classifiers":[
        {
            "category":"Education",
            "subcategory":"Special Training",
            "type":"Public Place"
        }
    ],
    "sg:phone":"+1 317 776 2278",
    "sg:postcode":"46060",
    "sg:province":"IN",
    "sg:tags":[
        "school",
        "art"
    ],
    "wof:name":"Hamilton County Art Center",
    "wof:placetype":"venue"
},
  "geometry": {"coordinates":[-86.01728900000001,40.043789],"type":"Point"}
}