{
  "type": "Feature",
  "properties": {
    "iso:country":"US",
    "sg:address":"306 River Bend Ct",
    "sg:city":"Fort Wayne",
    "sg:classifiers":[
        {
            "category":"Wholesale",
            "subcategory":"Groceries",
            "type":"Manufacturing & Wholesale Goods"
        }
    ],
    "sg:phone":"+1 260 426 3564",
    "sg:postcode":"46803",
    "sg:province":"IN",
    "sg:tags":[
        "confectionery",
        "chips",
        "potato"
    ],
    "wof:name":"Mike Sells Potato Chips",
    "wof:placetype":"venue"
},
  "geometry": {"coordinates":[-85.120358,41.084002],"type":"Point"}
}