{
  "type": "Feature",
  "properties": {
    "iso:country":"US",
    "sg:address":"928 N Meridian St",
    "sg:city":"Portland",
    "sg:classifiers":[
        {
            "category":"Banks & Credit Unions",
            "subcategory":"Investment Brokerage",
            "type":"Services"
        }
    ],
    "sg:phone":"+1 260 726 8596",
    "sg:postcode":"47371",
    "sg:province":"IN",
    "sg:tags":[
        "security"
    ],
    "wof:name":"Raymond James & Assoc Inc",
    "wof:placetype":"venue"
},
  "geometry": {"coordinates":[-84.97815900000001,40.442027],"type":"Point"}
}