{
  "type": "Feature",
  "properties": {
    "iso:country":"US",
    "sg:address":"8424 Naab Rd Ste 1E",
    "sg:city":"Indianapolis",
    "sg:classifiers":[
        {
            "category":"Health Services",
            "subcategory":"Doctor",
            "type":"Services"
        }
    ],
    "sg:phone":"+1 317 872 5591",
    "sg:postcode":"46260",
    "sg:province":"IN",
    "sg:tags":[
        "cardiologist"
    ],
    "wof:name":"Shapiro Michael I MD Fccp",
    "wof:placetype":"venue"
},
  "geometry": {"coordinates":[-86.19849600000001,39.909411],"type":"Point"}
}