{
  "type": "Feature",
  "properties": {
    "iso:country":"US",
    "sg:address":"20 N Main St",
    "sg:city":"Knox",
    "sg:classifiers":[
        {
            "category":"Banks & Credit Unions",
            "subcategory":"Bank",
            "type":"Services"
        }
    ],
    "sg:phone":"+1 574 772 2144",
    "sg:postcode":"46534",
    "sg:province":"IN",
    "wof:name":"Key Bank",
    "wof:placetype":"venue"
},
  "geometry": {"coordinates":[-86.623187,41.298208],"type":"Point"}
}