{
  "type": "Feature",
  "properties": {
    "iso:country":"US",
    "sg:address":"203 W 6th St",
    "sg:city":"Jasper",
    "sg:classifiers":[
        {
            "category":"Organizations",
            "subcategory":"Professional Association",
            "type":"Services"
        }
    ],
    "sg:phone":"+1 812 482 6977",
    "sg:postcode":"47546",
    "sg:province":"IN",
    "wof:name":"Girl Scouts",
    "wof:placetype":"venue"
},
  "geometry": {"coordinates":[-86.932727,38.391347],"type":"Point"}
}