{
  "type": "Feature",
  "properties": {
    "addr:full":"4075 Hwy 64 NW Depauw IN 47115",
    "addr:housenumber":"4075",
    "addr:postcode":"depauw;47115",
    "addr:street":"Hwy 64 Nw",
    "iso:country":"US",
    "sg:address":"4075 Hwy 64 NW",
    "sg:city":"Depauw",
    "sg:classifiers":[
        {
            "category":"Farming",
            "subcategory":"Farm",
            "type":"Manufacturing & Wholesale Goods"
        }
    ],
    "sg:phone":"+1 812 347 3486",
    "sg:postcode":"47115",
    "sg:province":"IN",
    "sg:tags":[
        "crop",
        "general"
    ],
    "wof:name":"Countryside Farm",
    "wof:placetype":"venue"
},
  "geometry": {"coordinates":[-86.210222,38.333101],"type":"Point"}
}