{
  "type": "Feature",
  "properties": {
    "iso:country":"US",
    "sg:address":"2818 S River Rd",
    "sg:city":"Wabash",
    "sg:classifiers":[
        {
            "category":"Personal",
            "subcategory":"Beauty Salon",
            "type":"Services"
        }
    ],
    "sg:phone":"+1 260 569 1050",
    "sg:postcode":"46992",
    "sg:province":"IN",
    "sg:tags":[
        "shop"
    ],
    "wof:name":"Cutting Edge",
    "wof:placetype":"venue"
},
  "geometry": {"coordinates":[-85.85656899999999,40.78039],"type":"Point"}
}