{
  "type": "Feature",
  "properties": {
    "iso:country":"US",
    "sg:address":"525 Main St",
    "sg:city":"Ferdinand",
    "sg:classifiers":[
        {
            "category":"Retail",
            "subcategory":"Auto Repair",
            "type":"Services"
        }
    ],
    "sg:phone":"+1 812 367 1651",
    "sg:postcode":"47532",
    "sg:province":"IN",
    "sg:tags":[
        "repairing",
        "automobile"
    ],
    "wof:name":"Bolte's Service Ctr",
    "wof:placetype":"venue"
},
  "geometry": {"coordinates":[-86.86293499999999,38.221267],"type":"Point"}
}