{
  "type": "Feature",
  "properties": {
    "iso:country":"US",
    "sg:address":"616 W Stadium Ave",
    "sg:city":"West Lafayette",
    "sg:classifiers":[
        {
            "category":"Shopping",
            "subcategory":"Books",
            "type":"Retail Goods"
        }
    ],
    "sg:phone":"+1 765 743 9696",
    "sg:postcode":"47906",
    "sg:province":"IN",
    "sg:tags":[
        "dealer"
    ],
    "wof:name":"Follett's Boiler Book Store",
    "wof:placetype":"venue"
},
  "geometry": {"coordinates":[-86.91305,40.431439],"type":"Point"}
}