{
  "type": "Feature",
  "properties": {
    "addr:full":"11720 W 250 N Middlebury IN 46540",
    "addr:housenumber":"11720",
    "addr:postcode":"46540",
    "addr:street":"W 250 N",
    "iso:country":"US",
    "sg:address":"11720 W 250 N",
    "sg:city":"Middlebury",
    "sg:classifiers":[
        {
            "category":"Home & Garden",
            "subcategory":"Garden Supply",
            "type":"Retail Goods"
        }
    ],
    "sg:phone":"+1 574 825 7281",
    "sg:postcode":"46540",
    "sg:province":"IN",
    "sg:tags":[
        "lawn",
        "mower"
    ],
    "wof:name":"Crystal Valley Power Equipment",
    "wof:placetype":"venue"
},
  "geometry": {"coordinates":[-85.65242000000001,41.675627],"type":"Point"}
}