{
  "type": "Feature",
  "properties": {
    "iso:country":"US",
    "sg:address":"714 Fair Ave",
    "sg:city":"Shelbyville",
    "sg:classifiers":[
        {
            "category":"Organizations",
            "subcategory":"Religious Organization",
            "type":"Services"
        }
    ],
    "sg:phone":"+1 317 392 1294",
    "sg:postcode":"46176",
    "sg:province":"IN",
    "sg:tags":[
        "church"
    ],
    "wof:name":"Trinity United Methodist Chr",
    "wof:placetype":"venue"
},
  "geometry": {"coordinates":[-85.763639,39.529115],"type":"Point"}
}