{
  "type": "Feature",
  "properties": {
    "iso:country":"US",
    "sg:address":"135 E Sycamore St",
    "sg:city":"Zionsville",
    "sg:classifiers":[
        {
            "category":"Health Services",
            "subcategory":"Doctor",
            "type":"Services"
        }
    ],
    "sg:phone":"+1 317 733 1596",
    "sg:postcode":"46077",
    "sg:province":"IN",
    "sg:tags":[
        "physician",
        "surgeon"
    ],
    "wof:name":"Ron Stachler MD",
    "wof:placetype":"venue"
},
  "geometry": {"coordinates":[-86.26047199999999,39.948223],"type":"Point"}
}