{
  "type": "Feature",
  "properties": {
    "addr:full":"402 S Heaton St Knox IN 46534",
    "addr:housenumber":"402",
    "addr:postcode":"46534",
    "addr:street":"S Heaton St",
    "iso:country":"US",
    "sg:address":"402 S Heaton St",
    "sg:city":"Knox",
    "sg:classifiers":[
        {
            "category":"Insurance",
            "subcategory":"Insurance Agent",
            "type":"Services"
        }
    ],
    "sg:phone":"+1 574 772 6291",
    "sg:postcode":"46534",
    "sg:province":"IN",
    "wof:name":"1ST Source Insurance",
    "wof:placetype":"venue"
},
  "geometry": {"coordinates":[-86.620619,41.293945],"type":"Point"}
}