{
  "type": "Feature",
  "properties": {
    "iso:country":"US",
    "sg:address":"1670 E North St",
    "sg:city":"Crown Point",
    "sg:classifiers":[
        {
            "category":"Retail",
            "subcategory":"Auto Repair",
            "type":"Services"
        }
    ],
    "sg:phone":"+1 219 663 0045",
    "sg:postcode":"46307",
    "sg:province":"IN",
    "sg:website":"www.proautoinc.com",
    "wof:name":"Pro Auto Service",
    "wof:placetype":"venue"
},
  "geometry": {"coordinates":[-87.341797,41.420101],"type":"Point"}
}