{
  "type": "Feature",
  "properties": {
    "iso:country":"US",
    "sg:address":"16 W Washington St",
    "sg:city":"Indianapolis",
    "sg:classifiers":[
        {
            "category":"Organizations",
            "subcategory":"Religious Organization",
            "type":"Services"
        }
    ],
    "sg:phone":"+1 765 345 5023",
    "sg:postcode":"46204",
    "sg:province":"IN",
    "sg:tags":[
        "church"
    ],
    "wof:name":"Truth Apostolic Tabernacle",
    "wof:placetype":"venue"
},
  "geometry": {"coordinates":[-86.15966,39.767186],"type":"Point"}
}