{
  "type": "Feature",
  "properties": {
    "iso:country":"US",
    "sg:address":"4652 W US Hwy 6",
    "sg:city":"Union Mills",
    "sg:classifiers":[
        {
            "category":"Professional",
            "subcategory":"Business Services",
            "type":"Services"
        }
    ],
    "sg:phone":"+1 219 767 3171",
    "sg:postcode":"46382",
    "sg:province":"IN",
    "wof:name":"Eagle Express Enterprises Inc",
    "wof:placetype":"venue"
},
  "geometry": {"coordinates":[-86.790172,41.517431],"type":"Point"}
}