{
  "type": "Feature",
  "properties": {
    "addr:full":"754 McCool Rd Valparaiso IN 46385",
    "addr:housenumber":"754",
    "addr:postcode":"46385",
    "addr:street":"Mccool Rd",
    "iso:country":"US",
    "sg:address":"754 McCool Rd",
    "sg:city":"Valparaiso",
    "sg:classifiers":[
        {
            "category":"Health Services",
            "subcategory":"Doctor",
            "type":"Services"
        }
    ],
    "sg:phone":"+1 219 759 5500",
    "sg:postcode":"46385",
    "sg:province":"IN",
    "sg:tags":[
        "medical"
    ],
    "wof:name":"Philip Nowzaradan MD",
    "wof:placetype":"venue"
},
  "geometry": {"coordinates":[-87.143396,41.543219],"type":"Point"}
}