{
  "type": "Feature",
  "properties": {
    "iso:country":"US",
    "sg:address":"1027 W 7th St",
    "sg:city":"Auburn",
    "sg:classifiers":[
        {
            "category":"Shopping",
            "subcategory":"Optical Goods",
            "type":"Retail Goods"
        }
    ],
    "sg:phone":"+1 260 925 5950",
    "sg:postcode":"46706",
    "sg:province":"IN",
    "wof:name":"Pearle Vision Center",
    "wof:placetype":"venue"
},
  "geometry": {"coordinates":[-85.072419,41.366608],"type":"Point"}
}