{
  "type": "Feature",
  "properties": {
    "iso:country":"US",
    "sg:address":"4205 E State Blvd",
    "sg:city":"Fort Wayne",
    "sg:classifiers":[
        {
            "category":"Wholesale",
            "subcategory":"Electrical",
            "type":"Manufacturing & Wholesale Goods"
        }
    ],
    "sg:phone":"+1 260 422 1290",
    "sg:postcode":"46815",
    "sg:province":"IN",
    "sg:tags":[
        "alarm",
        "burglar",
        "system"
    ],
    "wof:name":"Alarm Security Integration",
    "wof:placetype":"venue"
},
  "geometry": {"coordinates":[-85.081585,41.098003],"type":"Point"}
}