{
  "type": "Feature",
  "properties": {
    "addr:full":"4900 W 16th St Indianapolis IN 46224",
    "addr:housenumber":"4900",
    "addr:postcode":"46224",
    "addr:street":"W 16Th St",
    "iso:country":"US",
    "sg:address":"4900 W 16th St",
    "sg:city":"Indianapolis",
    "sg:classifiers":[
        {
            "category":"Deli",
            "type":"Food & Drink"
        },
        {
            "category":"Restaurant",
            "type":"Food & Drink"
        }
    ],
    "sg:phone":"+1 317 243 3354",
    "sg:postcode":"46224",
    "sg:province":"IN",
    "sg:tags":[
        "delicatessen"
    ],
    "wof:name":"Olde Village Deli",
    "wof:placetype":"venue"
},
  "geometry": {"coordinates":[-86.241058,39.787392],"type":"Point"}
}