{
  "type": "Feature",
  "properties": {
    "iso:country":"US",
    "sg:address":"4459 E 625 S",
    "sg:city":"Waldron",
    "sg:classifiers":[
        {
            "category":"Manufacturing",
            "subcategory":"Rubber & Plastics",
            "type":"Manufacturing & Wholesale Goods"
        }
    ],
    "sg:phone":"+1 765 525 4248",
    "sg:postcode":"46182",
    "sg:province":"IN",
    "wof:name":"Rrb Plastics Inc",
    "wof:placetype":"venue"
},
  "geometry": {"coordinates":[-85.69449400000001,39.434608],"type":"Point"}
}