{
  "type": "Feature",
  "properties": {
    "iso:country":"US",
    "sg:address":"509 Shamrock Ln",
    "sg:city":"Valparaiso",
    "sg:classifiers":[
        {
            "category":"Building & Trades",
            "subcategory":"Construction",
            "type":"Services"
        }
    ],
    "sg:phone":"+1 219 462 8371",
    "sg:postcode":"46385",
    "sg:province":"IN",
    "sg:tags":[
        "contractor"
    ],
    "wof:name":"Shamrock Subdivision",
    "wof:placetype":"venue"
},
  "geometry": {"coordinates":[-87.097267,41.473795],"type":"Point"}
}