{
  "type": "Feature",
  "properties": {
    "iso:country":"US",
    "sg:address":"821 E Lincolnway",
    "sg:city":"Valparaiso",
    "sg:classifiers":[
        {
            "category":"Health Services",
            "subcategory":"Clinic",
            "type":"Services"
        }
    ],
    "sg:phone":"+1 219 465 4151",
    "sg:postcode":"46383",
    "sg:province":"IN",
    "sg:tags":[
        "wellness",
        "program"
    ],
    "wof:name":"National Wellness Svc",
    "wof:placetype":"venue"
},
  "geometry": {"coordinates":[-87.047573,41.467865],"type":"Point"}
}