{
  "type": "Feature",
  "properties": {
    "iso:country":"US",
    "sg:address":"434 Massachusetts Ave",
    "sg:city":"Indianapolis",
    "sg:classifiers":[
        {
            "category":"Shopping",
            "subcategory":"Jewelry",
            "type":"Retail Goods"
        }
    ],
    "sg:phone":"+1 317 955 9925",
    "sg:postcode":"46204",
    "sg:province":"IN",
    "sg:tags":[
        "jeweler"
    ],
    "wof:name":"Silver In The City 925",
    "wof:placetype":"venue"
},
  "geometry": {"coordinates":[-86.151125,39.773527],"type":"Point"}
}