{
  "type": "Feature",
  "properties": {
    "addr:full":"8859 E Schnellville Rd Birdseye IN 47513",
    "addr:housenumber":"8859",
    "addr:postcode":"47513",
    "addr:street":"E Schnellville Rd",
    "iso:country":"US",
    "sg:address":"8859 E Schnellville Rd",
    "sg:city":"Birdseye",
    "sg:classifiers":[
        {
            "category":"Farming",
            "subcategory":"Farm",
            "type":"Manufacturing & Wholesale Goods"
        }
    ],
    "sg:phone":"+1 812 389 2522",
    "sg:postcode":"47513",
    "sg:province":"IN",
    "wof:name":"Schnell Farms",
    "wof:placetype":"venue"
},
  "geometry": {"coordinates":[-86.738124,38.336195],"type":"Point"}
}