{
  "type": "Feature",
  "properties": {
    "iso:country":"US",
    "sg:address":"13 Sand Ct",
    "sg:city":"Batesville",
    "sg:classifiers":[
        {
            "category":"Organizations",
            "subcategory":"Religious Organization",
            "type":"Services"
        }
    ],
    "sg:phone":"+1 812 934 3204",
    "sg:postcode":"47006",
    "sg:province":"IN",
    "sg:tags":[
        "church"
    ],
    "sg:website":"www.stlouis-batesville.org",
    "wof:name":"St Louis Catholic Church",
    "wof:placetype":"venue"
},
  "geometry": {"coordinates":[-85.224111,39.290914],"type":"Point"}
}