{
  "type": "Feature",
  "properties": {
    "iso:country":"US",
    "sg:address":"11842 Sea Star Dr",
    "sg:city":"Indianapolis",
    "sg:classifiers":[
        {
            "category":"Professional",
            "subcategory":"Business Services",
            "type":"Services"
        }
    ],
    "sg:phone":"+1 317 576 9888",
    "sg:postcode":"46256",
    "sg:province":"IN",
    "sg:tags":[
        "interior",
        "consultant",
        "design",
        "decorator"
    ],
    "wof:name":"Impressions Decorative Paint",
    "wof:placetype":"venue"
},
  "geometry": {"coordinates":[-85.952274,39.933417],"type":"Point"}
}