{
  "type": "Feature",
  "properties": {
    "iso:country":"US",
    "sg:address":"2175 E Wabash St",
    "sg:city":"Frankfort",
    "sg:classifiers":[
        {
            "category":"Social Services",
            "subcategory":"Child Care",
            "type":"Services"
        }
    ],
    "sg:phone":"+1 765 659 2755",
    "sg:postcode":"46041",
    "sg:province":"IN",
    "sg:tags":[
        "day"
    ],
    "wof:name":"Teddy Bear Day Care",
    "wof:placetype":"venue"
},
  "geometry": {"coordinates":[-86.48713,40.278916],"type":"Point"}
}