{
  "type": "Feature",
  "properties": {
    "iso:country":"US",
    "sg:address":"601 E Maple Ave",
    "sg:city":"La Porte",
    "sg:classifiers":[
        {
            "category":"Personal",
            "subcategory":"Beauty Salon",
            "type":"Services"
        }
    ],
    "sg:phone":"+1 219 362 5396",
    "sg:postcode":"46350",
    "sg:province":"IN",
    "sg:tags":[
        "cosmetologist"
    ],
    "wof:name":"Paula K Ayres",
    "wof:placetype":"venue"
},
  "geometry": {"coordinates":[-86.707962,41.612937],"type":"Point"}
}