{
  "type": "Feature",
  "properties": {
    "iso:country":"US",
    "sg:address":"3665 N 950 W",
    "sg:city":"Michigan City",
    "sg:classifiers":[
        {
            "category":"Retail",
            "subcategory":"Repair Shop",
            "type":"Services"
        }
    ],
    "sg:phone":"+1 219 874 7735",
    "sg:postcode":"46360",
    "sg:province":"IN",
    "sg:tags":[
        "plumbing",
        "drain",
        "cleaning",
        "sewer"
    ],
    "wof:name":"Siuda Steve Sewer & Septic Svc",
    "wof:placetype":"venue"
},
  "geometry": {"coordinates":[-86.88433000000001,41.660913],"type":"Point"}
}