{
  "type": "Feature",
  "properties": {
    "iso:country":"US",
    "sg:address":"3647 S Co Rd 400 E",
    "sg:city":"Brownstown",
    "sg:classifiers":[
        {
            "category":"Wholesale",
            "subcategory":"Farm Supplies",
            "type":"Manufacturing & Wholesale Goods"
        }
    ],
    "sg:phone":"+1 812 358 5149",
    "sg:postcode":"47220",
    "sg:province":"IN",
    "sg:tags":[
        "feed"
    ],
    "wof:name":"Hackman Brothers Feed Svc",
    "wof:placetype":"venue"
},
  "geometry": {"coordinates":[-85.961213,38.82826],"type":"Point"}
}