{
  "type": "Feature",
  "properties": {
    "addr:full":"2801 Mount Vernon Ave Evansville IN 47712",
    "addr:housenumber":"2801",
    "addr:postcode":"47712",
    "addr:street":"Mount Vernon Ave",
    "iso:country":"US",
    "sg:address":"2801 Mount Vernon Ave",
    "sg:city":"Evansville",
    "sg:classifiers":[
        {
            "category":"Autos & Motor Vehicles",
            "subcategory":"Fuel & Gas Station",
            "type":"Retail Goods"
        }
    ],
    "sg:phone":"+1 812 422 8127",
    "sg:postcode":"47712",
    "sg:province":"IN",
    "sg:tags":[
        "oil"
    ],
    "wof:name":"West Side Shell",
    "wof:placetype":"venue"
},
  "geometry": {"coordinates":[-87.609596,37.983301],"type":"Point"}
}