{
  "type": "Feature",
  "properties": {
    "addr:full":"7800 E Ridge Rd Hobart IN 46342",
    "addr:housenumber":"7800",
    "addr:postcode":"46342",
    "addr:street":"E Ridge Rd",
    "iso:country":"US",
    "sg:address":"7800 E Ridge Rd",
    "sg:city":"Hobart",
    "sg:classifiers":[
        {
            "category":"Restaurant",
            "type":"Food & Drink"
        }
    ],
    "sg:menulink":"http://www.allmenus.com/in/hobart/159657-arbys/menu/",
    "sg:phone":"+1 219 962 7008",
    "sg:postcode":"46342",
    "sg:province":"IN",
    "sg:tags":[
        "burger",
        "american"
    ],
    "wof:name":"Arby's",
    "wof:placetype":"venue"
},
  "geometry": {"coordinates":[-87.227037,41.550611],"type":"Point"}
}