{
  "type": "Feature",
  "properties": {
    "iso:country":"US",
    "sg:address":"214 E Monroe St",
    "sg:city":"Decatur",
    "sg:classifiers":[
        {
            "category":"Freight",
            "type":"Transportation"
        }
    ],
    "sg:phone":"+1 260 728 4077",
    "sg:postcode":"46733",
    "sg:province":"IN",
    "sg:tags":[
        "trucking"
    ],
    "wof:name":"Mitchel Enterprises Corp",
    "wof:placetype":"venue"
},
  "geometry": {"coordinates":[-84.919061,40.832042],"type":"Point"}
}