{
  "type": "Feature",
  "properties": {
    "addr:full":"2307 E 10th St Anderson IN 46012",
    "addr:housenumber":"2307",
    "addr:postcode":"46012",
    "addr:street":"E 10Th St",
    "iso:country":"US",
    "sg:address":"2307 E 10th St",
    "sg:city":"Anderson",
    "sg:classifiers":[
        {
            "category":"Personal",
            "subcategory":"Beauty Salon",
            "type":"Services"
        }
    ],
    "sg:phone":"+1 765 649 5528",
    "sg:postcode":"46012",
    "sg:province":"IN",
    "wof:name":"Mystique Designs",
    "wof:placetype":"venue"
},
  "geometry": {"coordinates":[-85.650623,40.105771],"type":"Point"}
}