{
  "type": "Feature",
  "properties": {
    "iso:country":"US",
    "sg:address":"7267 Jessman Road E Dr",
    "sg:city":"Indianapolis",
    "sg:classifiers":[
        {
            "category":"Professional",
            "subcategory":"Employment Agencies",
            "type":"Services"
        }
    ],
    "sg:phone":"+1 317 841 7575",
    "sg:postcode":"46256",
    "sg:province":"IN",
    "sg:tags":[
        "opportunity"
    ],
    "wof:name":"Quiring Associates Inc",
    "wof:placetype":"venue"
},
  "geometry": {"coordinates":[-86.038499,39.885641],"type":"Point"}
}