{
  "type": "Feature",
  "properties": {
    "iso:country":"US",
    "sg:address":"9 S Walnut St",
    "sg:city":"Brazil",
    "sg:classifiers":[
        {
            "category":"Personal",
            "subcategory":"Beauty Salon",
            "type":"Services"
        }
    ],
    "sg:phone":"+1 812 446 2484",
    "sg:postcode":"47834",
    "sg:province":"IN",
    "wof:name":"Hair Productions",
    "wof:placetype":"venue"
},
  "geometry": {"coordinates":[-87.127915,39.522947],"type":"Point"}
}