{
  "type": "Feature",
  "properties": {
    "iso:country":"US",
    "sg:address":"9407 Stouffer Ct",
    "sg:city":"Indianapolis",
    "sg:classifiers":[
        {
            "category":"Manufacturing",
            "subcategory":"Tools & Machinery",
            "type":"Manufacturing & Wholesale Goods"
        }
    ],
    "sg:phone":"+1 317 899 0877",
    "sg:postcode":"46235",
    "sg:province":"IN",
    "sg:tags":[
        "cleaners",
        "household",
        "vacuum"
    ],
    "wof:name":"R G Vacuum & Co",
    "wof:placetype":"venue"
},
  "geometry": {"coordinates":[-86.00193400000001,39.835295],"type":"Point"}
}