{
  "type": "Feature",
  "properties": {
    "iso:country":"US",
    "sg:address":"115 E Market St",
    "sg:city":"New Albany",
    "sg:classifiers":[
        {
            "category":"Building & Trades",
            "subcategory":"Construction",
            "type":"Services"
        }
    ],
    "sg:phone":"+1 812 941 9990",
    "sg:postcode":"47150",
    "sg:province":"IN",
    "sg:tags":[
        "designer",
        "marine",
        "contractor"
    ],
    "wof:name":"Hornblower Marine Svc",
    "wof:placetype":"venue"
},
  "geometry": {"coordinates":[-85.823017,38.284779],"type":"Point"}
}