{
  "type": "Feature",
  "properties": {
    "iso:country":"US",
    "sg:address":"93 Salem Ct E",
    "sg:city":"Otisco",
    "sg:classifiers":[
        {
            "category":"Professional",
            "subcategory":"Management & Consulting",
            "type":"Services"
        }
    ],
    "sg:phone":"+1 812 256 6856",
    "sg:postcode":"47163",
    "sg:province":"IN",
    "wof:name":"TS Services",
    "wof:placetype":"venue"
},
  "geometry": {"coordinates":[-85.67656100000001,38.516249],"type":"Point"}
}