{
  "type": "Feature",
  "properties": {
    "iso:country":"US",
    "sg:address":"2655 Knob View Ave",
    "sg:city":"New Albany",
    "sg:classifiers":[
        {
            "category":"Building & Trades",
            "subcategory":"Cleaning & Sanitation",
            "type":"Services"
        }
    ],
    "sg:phone":"+1 812 542 1815",
    "sg:postcode":"47150",
    "sg:province":"IN",
    "wof:name":"Sparkling Image",
    "wof:placetype":"venue"
},
  "geometry": {"coordinates":[-85.81053799999999,38.32053],"type":"Point"}
}