{
  "type": "Feature",
  "properties": {
    "iso:country":"US",
    "sg:address":"8500 Keystone Xing",
    "sg:city":"Indianapolis",
    "sg:classifiers":[
        {
            "category":"Professional",
            "type":"Services"
        }
    ],
    "sg:phone":"+1 317 580 0460",
    "sg:postcode":"46240",
    "sg:province":"IN",
    "sg:tags":[
        "establishment"
    ],
    "wof:name":"Credit Data-Indiana",
    "wof:placetype":"venue"
},
  "geometry": {"coordinates":[-86.113976,39.910415],"type":"Point"}
}