{
  "type": "Feature",
  "properties": {
    "iso:country":"US",
    "sg:address":"2130 Research Dr",
    "sg:city":"Fort Wayne",
    "sg:classifiers":[
        {
            "category":"Freight",
            "type":"Transportation"
        }
    ],
    "sg:phone":"+1 260 471 8800",
    "sg:postcode":"46808",
    "sg:province":"IN",
    "sg:tags":[
        "commercial",
        "storage"
    ],
    "wof:name":"All Seasons Climate Self Stge",
    "wof:placetype":"venue"
},
  "geometry": {"coordinates":[-85.168085,41.127657],"type":"Point"}
}