{
  "type": "Feature",
  "properties": {
    "iso:country":"US",
    "sg:address":"1172 N Main St",
    "sg:city":"Franklin",
    "sg:classifiers":[
        {
            "category":"Restaurant",
            "type":"Food & Drink"
        }
    ],
    "sg:menulink":"http://www.allmenus.com/in/franklin/77316-papa-murphys/menu/",
    "sg:phone":"+1 317 346 9929",
    "sg:postcode":"46131",
    "sg:province":"IN",
    "sg:tags":[
        "american",
        "pizza"
    ],
    "wof:name":"Papa Murphy's",
    "wof:placetype":"venue"
},
  "geometry": {"coordinates":[-86.06270600000001,39.493267],"type":"Point"}
}