{
  "type": "Feature",
  "properties": {
    "iso:country":"US",
    "sg:address":"2905 E Morgan Ave",
    "sg:city":"Evansville",
    "sg:classifiers":[
        {
            "category":"Sports & Exercise",
            "subcategory":"Golf",
            "type":"Entertainment"
        }
    ],
    "sg:phone":"+1 812 479 7339",
    "sg:postcode":"47711",
    "sg:province":"IN",
    "sg:tags":[
        "course"
    ],
    "wof:name":"Wesselman PAR 3 Golf Course",
    "wof:placetype":"venue"
},
  "geometry": {"coordinates":[-87.515445,37.991445],"type":"Point"}
}