{
  "type": "Feature",
  "properties": {
    "iso:country":"US",
    "sg:address":"1223 N Harbour Pointe Rd",
    "sg:city":"Peru",
    "sg:classifiers":[
        {
            "category":"Health Services",
            "subcategory":"Optometrist",
            "type":"Services"
        }
    ],
    "sg:phone":"+1 765 472 3825",
    "sg:postcode":"46970",
    "sg:province":"IN",
    "wof:name":"James Mulis OD",
    "wof:placetype":"venue"
},
  "geometry": {"coordinates":[-86.103731,40.785208],"type":"Point"}
}