{
  "type": "Feature",
  "properties": {
    "iso:country":"US",
    "sg:address":"527 Sheridan St",
    "sg:city":"Crown Point",
    "sg:classifiers":[
        {
            "category":"Shopping",
            "subcategory":"Stationery & Office Supplies",
            "type":"Retail Goods"
        }
    ],
    "sg:phone":"+1 219 662 2860",
    "sg:postcode":"46307",
    "sg:province":"IN",
    "sg:tags":[
        "equipment"
    ],
    "sg:website":"www.tiboffice.com",
    "wof:name":"Tib Office",
    "wof:placetype":"venue"
},
  "geometry": {"coordinates":[-87.358498,41.423801],"type":"Point"}
}