{
  "type": "Feature",
  "properties": {
    "iso:country":"US",
    "sg:address":"259 S County Line Rd",
    "sg:city":"Cumberland",
    "sg:classifiers":[
        {
            "category":"Manufacturing",
            "subcategory":"Tools & Machinery",
            "type":"Manufacturing & Wholesale Goods"
        }
    ],
    "sg:phone":"+1 317 891 0559",
    "sg:postcode":"46229",
    "sg:province":"IN",
    "sg:tags":[
        "photographic",
        "supply"
    ],
    "wof:name":"Noble Silver Co",
    "wof:placetype":"venue"
},
  "geometry": {"coordinates":[-85.952412,39.773869],"type":"Point"}
}