{
  "type": "Feature",
  "properties": {
    "iso:country":"US",
    "sg:address":"2303 W State Rd 2",
    "sg:city":"Laporte",
    "sg:classifiers":[
        {
            "category":"Retail",
            "subcategory":"Veterinary Services",
            "type":"Services"
        }
    ],
    "sg:phone":"+1 219 362 2612",
    "sg:postcode":"46350",
    "sg:province":"IN",
    "sg:tags":[
        "veterinarian"
    ],
    "wof:name":"LA Porte Animal Hospital Inc",
    "wof:placetype":"venue"
},
  "geometry": {"coordinates":[-86.745403,41.595262],"type":"Point"}
}