{
  "type": "Feature",
  "properties": {
    "iso:country":"US",
    "sg:address":"2225 Hulman St",
    "sg:city":"Terre Haute",
    "sg:classifiers":[
        {
            "category":"Real Estate",
            "subcategory":"Real Estate Agent",
            "type":"Services"
        }
    ],
    "sg:phone":"+1 812 235 3235",
    "sg:postcode":"47803",
    "sg:province":"IN",
    "sg:tags":[
        "inspection"
    ],
    "wof:name":"Lewis Home Inspections LLC",
    "wof:placetype":"venue"
},
  "geometry": {"coordinates":[-87.383754,39.448315],"type":"Point"}
}