{
  "type": "Feature",
  "properties": {
    "iso:country":"US",
    "sg:address":"9715 E Washington St",
    "sg:city":"Indianapolis",
    "sg:classifiers":[
        {
            "category":"Restaurant",
            "type":"Food & Drink"
        }
    ],
    "sg:phone":"+1 317 898 1679",
    "sg:postcode":"46229",
    "sg:province":"IN",
    "wof:name":"Mi Amigos",
    "wof:placetype":"venue"
},
  "geometry": {"coordinates":[-85.993039,39.774636],"type":"Point"}
}