{
  "type": "Feature",
  "properties": {
    "iso:country":"US",
    "sg:address":"703 E Washington St",
    "sg:city":"Greencastle",
    "sg:classifiers":[
        {
            "category":"Retail",
            "subcategory":"Funeral Services",
            "type":"Services"
        }
    ],
    "sg:phone":"+1 765 653 6262",
    "sg:postcode":"46135",
    "sg:province":"IN",
    "sg:tags":[
        "director"
    ],
    "wof:name":"Hopkins-Rector Funeral Home",
    "wof:placetype":"venue"
},
  "geometry": {"coordinates":[-86.853608,39.644058],"type":"Point"}
}