{
  "type": "Feature",
  "properties": {
    "addr:full":"204 N Vine St Greencastle IN 46135",
    "addr:housenumber":"204",
    "addr:postcode":"46135",
    "addr:street":"N Vine St",
    "iso:country":"US",
    "sg:address":"204 N Vine St",
    "sg:city":"Greencastle",
    "sg:classifiers":[
        {
            "category":"Wholesale",
            "subcategory":"Office Equipment",
            "type":"Manufacturing & Wholesale Goods"
        }
    ],
    "sg:phone":"+1 765 364 8292",
    "sg:postcode":"46135",
    "sg:province":"IN",
    "sg:tags":[
        "machine",
        "duplicating",
        "copying"
    ],
    "wof:name":"Copiers Plus",
    "wof:placetype":"venue"
},
  "geometry": {"coordinates":[-86.86354799999999,39.646174],"type":"Point"}
}