{
  "type": "Feature",
  "properties": {
    "iso:country":"US",
    "sg:address":"1202 Broad St",
    "sg:city":"New Castle",
    "sg:classifiers":[
        {
            "category":"Retail",
            "subcategory":"Funeral Services",
            "type":"Services"
        }
    ],
    "sg:phone":"+1 765 521 0997",
    "sg:postcode":"47362",
    "sg:province":"IN",
    "sg:tags":[
        "director"
    ],
    "wof:name":"New Era Funeral Supply",
    "wof:placetype":"venue"
},
  "geometry": {"coordinates":[-85.371615,39.931288],"type":"Point"}
}