{
  "type": "Feature",
  "properties": {
    "iso:country":"US",
    "sg:address":"51070 Bittersweet Rd",
    "sg:city":"Granger",
    "sg:classifiers":[
        {
            "category":"Professional",
            "subcategory":"Business Services",
            "type":"Services"
        }
    ],
    "sg:phone":"+1 574 287 7550",
    "sg:postcode":"46530",
    "sg:province":"IN",
    "wof:name":"Vegh Vendel",
    "wof:placetype":"venue"
},
  "geometry": {"coordinates":[-86.110918,41.752285],"type":"Point"}
}