{
  "type": "Feature",
  "properties": {
    "iso:country":"US",
    "sg:address":"6201 State Rd 218",
    "sg:city":"Walton",
    "sg:phone":"+1 574 626 2157",
    "sg:postcode":"46994",
    "sg:province":"IN",
    "sg:tags":[
        "farm",
        "corn",
        "soybean"
    ],
    "wof:name":"Gene Hines",
    "wof:placetype":"venue"
},
  "geometry": {"coordinates":[-86.256445,40.66389],"type":"Point"}
}