{
  "type": "Feature",
  "properties": {
    "addr:full":"999 Progress Blvd New Albany IN 47150",
    "addr:housenumber":"999",
    "addr:postcode":"47150",
    "addr:street":"Progress Blvd",
    "iso:country":"US",
    "sg:address":"999 Progress Blvd",
    "sg:city":"New Albany",
    "sg:classifiers":[
        {
            "category":"Wholesale",
            "subcategory":"Groceries",
            "type":"Manufacturing & Wholesale Goods"
        }
    ],
    "sg:phone":"+1 812 945 6042",
    "sg:postcode":"47150",
    "sg:province":"IN",
    "sg:tags":[
        "food"
    ],
    "wof:name":"Compass Group-Canteen",
    "wof:placetype":"venue"
},
  "geometry": {"coordinates":[-85.831941,38.335572],"type":"Point"}
}