{
  "type": "Feature",
  "properties": {
    "iso:country":"US",
    "sg:address":"3625 Nichol Ave",
    "sg:city":"Anderson",
    "sg:classifiers":[
        {
            "category":"Personal",
            "subcategory":"Beauty Salon",
            "type":"Services"
        }
    ],
    "sg:phone":"+1 765 642 4177",
    "sg:postcode":"46011",
    "sg:province":"IN",
    "wof:name":"Edgewood Beauty Salon",
    "wof:placetype":"venue"
},
  "geometry": {"coordinates":[-85.73434899999999,40.101456],"type":"Point"}
}