{
  "type": "Feature",
  "properties": {
    "iso:country":"US",
    "sg:address":"902 Main St",
    "sg:city":"Memphis",
    "sg:classifiers":[
        {
            "category":"Building & Trades",
            "subcategory":"Construction",
            "type":"Services"
        }
    ],
    "sg:phone":"+1 812 294 1772",
    "sg:postcode":"47143",
    "sg:province":"IN",
    "sg:tags":[
        "tile",
        "dealer"
    ],
    "wof:name":"Floors & More",
    "wof:placetype":"venue"
},
  "geometry": {"coordinates":[-85.75891799999999,38.482777],"type":"Point"}
}