{
  "type": "Feature",
  "properties": {
    "iso:country":"US",
    "sg:address":"611 S Higbee St",
    "sg:city":"Milford",
    "sg:classifiers":[
        {
            "category":"Retail",
            "subcategory":"Auto Repair",
            "type":"Services"
        }
    ],
    "sg:phone":"+1 574 658 4880",
    "sg:postcode":"46542",
    "sg:province":"IN",
    "sg:tags":[
        "body",
        "automobile",
        "painting"
    ],
    "wof:name":"Medina's Body Repair",
    "wof:placetype":"venue"
},
  "geometry": {"coordinates":[-85.85362600000001,41.40295],"type":"Point"}
}