{
  "type": "Feature",
  "properties": {
    "iso:country":"US",
    "sg:address":"417 W 6th St",
    "sg:city":"Bloomington",
    "sg:classifiers":[
        {
            "category":"Banks & Credit Unions",
            "subcategory":"Bank",
            "type":"Services"
        }
    ],
    "sg:phone":"+1 812 331 7000",
    "sg:postcode":"47404",
    "sg:province":"IN",
    "sg:tags":[
        "loan",
        "real estate"
    ],
    "wof:name":"American Home Mortgage",
    "wof:placetype":"venue"
},
  "geometry": {"coordinates":[-86.538515,39.167519],"type":"Point"}
}