{
  "type": "Feature",
  "properties": {
    "iso:country":"US",
    "sg:address":"1663 3rd Ave",
    "sg:city":"Terre Haute",
    "sg:classifiers":[
        {
            "category":"Retail",
            "subcategory":"Car Wash",
            "type":"Services"
        }
    ],
    "sg:phone":"+1 812 232 7065",
    "sg:postcode":"47807",
    "sg:province":"IN",
    "sg:tags":[
        "carwash"
    ],
    "wof:name":"Port A Wash",
    "wof:placetype":"venue"
},
  "geometry": {"coordinates":[-87.388872,39.480161],"type":"Point"}
}