{
  "type": "Feature",
  "properties": {
    "addr:full":"6220 N College Ave Indianapolis IN 46220",
    "addr:housenumber":"6220",
    "addr:postcode":"46220",
    "addr:street":"N College Ave",
    "iso:country":"US",
    "sg:address":"6220 N College Ave",
    "sg:city":"Indianapolis",
    "sg:classifiers":[
        {
            "category":"Professional",
            "subcategory":"Detective & Security Services",
            "type":"Services"
        }
    ],
    "sg:phone":"+1 317 251 8000",
    "sg:postcode":"46220",
    "sg:province":"IN",
    "wof:name":"Innovative Investigative",
    "wof:placetype":"venue"
},
  "geometry": {"coordinates":[-86.14619,39.869262],"type":"Point"}
}