{
  "type": "Feature",
  "properties": {
    "iso:country":"US",
    "sg:address":"2415 Sagamore Pkwy S",
    "sg:city":"Lafayette",
    "sg:classifiers":[
        {
            "category":"Shopping",
            "subcategory":"Department Store",
            "type":"Retail Goods"
        }
    ],
    "sg:phone":"+1 765 449 7703",
    "sg:postcode":"47905",
    "sg:province":"IN",
    "sg:tags":[
        "electronic",
        "component",
        "mfg"
    ],
    "wof:name":"Sears Home Electronic Dept",
    "wof:placetype":"venue"
},
  "geometry": {"coordinates":[-86.855665,40.394737],"type":"Point"}
}