{
  "type": "Feature",
  "properties": {
    "iso:country":"US",
    "sg:address":"6595 S 125 W",
    "sg:city":"Trafalgar",
    "sg:classifiers":[
        {
            "category":"Restaurant",
            "type":"Food & Drink"
        }
    ],
    "sg:phone":"+1 317 878 5464",
    "sg:postcode":"46181",
    "sg:province":"IN",
    "sg:tags":[
        "banquet",
        "rooms"
    ],
    "wof:name":"Indiana FFA Ctr",
    "wof:placetype":"venue"
},
  "geometry": {"coordinates":[-86.127919,39.377963],"type":"Point"}
}