{
  "type": "Feature",
  "properties": {
    "iso:country":"US",
    "sg:address":"4681 S 300 E",
    "sg:city":"Chesterfield",
    "sg:classifiers":[
        {
            "category":"Professional",
            "subcategory":"Business Services",
            "type":"Services"
        }
    ],
    "sg:phone":"+1 765 649 8104",
    "sg:postcode":"46017",
    "sg:province":"IN",
    "wof:name":"Shreves Emergency Vehicles Sls",
    "wof:placetype":"venue"
},
  "geometry": {"coordinates":[-85.61506300000001,40.038058],"type":"Point"}
}