{
  "type": "Feature",
  "properties": {
    "iso:country":"US",
    "sg:address":"1342 W State Rd 2",
    "sg:city":"Laporte",
    "sg:classifiers":[
        {
            "category":"Shopping",
            "subcategory":"Discount & Variety Stores",
            "type":"Retail Goods"
        }
    ],
    "sg:phone":"+1 219 326 6663",
    "sg:postcode":"46350",
    "sg:province":"IN",
    "wof:name":"Buck Stop",
    "wof:placetype":"venue"
},
  "geometry": {"coordinates":[-86.734414,41.600952],"type":"Point"}
}