{
  "type": "Feature",
  "properties": {
    "iso:country":"US",
    "sg:address":"1611 W Maryland St",
    "sg:city":"Evansville",
    "sg:classifiers":[
        {
            "category":"Building & Trades",
            "subcategory":"Construction",
            "type":"Services"
        }
    ],
    "sg:phone":"+1 812 425 7663",
    "sg:postcode":"47710",
    "sg:province":"IN",
    "sg:tags":[
        "roofing",
        "contractor"
    ],
    "wof:name":"AAA Roofing & Construction",
    "wof:placetype":"venue"
},
  "geometry": {"coordinates":[-87.587699,37.985595],"type":"Point"}
}