{
  "type": "Feature",
  "properties": {
    "iso:country":"US",
    "sg:address":"8727 Lawrenceburg Rd",
    "sg:city":"Harrison",
    "sg:classifiers":[
        {
            "category":"Building & Trades",
            "subcategory":"Construction",
            "type":"Services"
        }
    ],
    "sg:phone":"+1 513 367 0700",
    "sg:postcode":"45030",
    "sg:province":"IN",
    "sg:tags":[
        "house"
    ],
    "wof:name":"Wb Const Services",
    "wof:placetype":"venue"
},
  "geometry": {"coordinates":[-84.814182,39.238375],"type":"Point"}
}