{
  "type": "Feature",
  "properties": {
    "iso:country":"US",
    "sg:address":"225 Aberdeen Dr",
    "sg:city":"Valparaiso",
    "sg:classifiers":[
        {
            "category":"Personal",
            "subcategory":"Beauty Salon",
            "type":"Services"
        }
    ],
    "sg:phone":"+1 219 462 7883",
    "sg:postcode":"46385",
    "sg:province":"IN",
    "wof:name":"Spa Medica",
    "wof:placetype":"venue"
},
  "geometry": {"coordinates":[-87.107944,41.43917],"type":"Point"}
}