{
  "type": "Feature",
  "properties": {
    "iso:country":"US",
    "sg:address":"529 E State Road 250",
    "sg:city":"Brownstown",
    "sg:classifiers":[
        {
            "category":"Animal Shelter",
            "type":"Public Place"
        },
        {
            "category":"Shopping",
            "subcategory":"Pets & Pet Supplies",
            "type":"Retail Goods"
        },
        {
            "category":"Retail",
            "subcategory":"Animal Services",
            "type":"Services"
        },
        {
            "category":"Retail",
            "subcategory":"Pet Boarding",
            "type":"Services"
        }
    ],
    "sg:phone":"+1 812 358 1827",
    "sg:postcode":"47220",
    "sg:province":"IN",
    "sg:tags":[
        "grooming",
        "dog",
        "kennel",
        "cat"
    ],
    "sg:website":"http://www.allaboutpawz.com",
    "wof:name":"All About Pawz",
    "wof:placetype":"venue"
},
  "geometry": {"coordinates":[-86.031552,38.866615],"type":"Point"}
}