{
  "type": "Feature",
  "properties": {
    "addr:full":"410 N Detroit St Lagrange IN 46761",
    "addr:housenumber":"410",
    "addr:postcode":"46761",
    "addr:street":"N Detroit St",
    "iso:country":"US",
    "sg:address":"410 N Detroit St",
    "sg:city":"Lagrange",
    "sg:classifiers":[
        {
            "category":"Travel",
            "subcategory":"Hotels & Motels",
            "type":"Entertainment"
        }
    ],
    "sg:phone":"+1 260 463 3555",
    "sg:postcode":"46761",
    "sg:province":"IN",
    "wof:name":"Budget Motel",
    "wof:placetype":"venue"
},
  "geometry": {"coordinates":[-85.41791000000001,41.647659],"type":"Point"}
}