{
  "type": "Feature",
  "properties": {
    "iso:country":"US",
    "sg:address":"7734 S 500 E",
    "sg:city":"Frankfort",
    "sg:phone":"+1 765 258 3156",
    "sg:postcode":"46041",
    "sg:province":"IN",
    "sg:tags":[
        "farm",
        "corn",
        "soybean"
    ],
    "wof:name":"Richard Harness",
    "wof:placetype":"venue"
},
  "geometry": {"coordinates":[-86.430677,40.436246],"type":"Point"}
}