{
  "type": "Feature",
  "properties": {
    "iso:country":"US",
    "sg:address":"7214 Hohman Ave",
    "sg:city":"Hammond",
    "sg:classifiers":[
        {
            "category":"Home & Garden",
            "subcategory":"Building Materials",
            "type":"Retail Goods"
        }
    ],
    "sg:phone":"+1 219 931 0617",
    "sg:postcode":"46324",
    "sg:province":"IN",
    "wof:name":"D L & Son Enterprises",
    "wof:placetype":"venue"
},
  "geometry": {"coordinates":[-87.52214,41.582634],"type":"Point"}
}