{
  "type": "Feature",
  "properties": {
    "addr:full":"8100 US Hwy 20 Shipshewana IN 46565",
    "addr:housenumber":"8100",
    "addr:postcode":"46565",
    "addr:street":"Us Hwy 20",
    "iso:country":"US",
    "sg:address":"8100 US Hwy 20",
    "sg:city":"Shipshewana",
    "sg:classifiers":[
        {
            "category":"Health Services",
            "subcategory":"Chiropractor",
            "type":"Services"
        }
    ],
    "sg:phone":"+1 260 768 7806",
    "sg:postcode":"46565",
    "sg:province":"IN",
    "wof:name":"Meyer Chiropractic Offices",
    "wof:placetype":"venue"
},
  "geometry": {"coordinates":[-85.581883,41.654495],"type":"Point"}
}