{
  "type": "Feature",
  "properties": {
    "iso:country":"US",
    "sg:address":"906 N 10th St",
    "sg:city":"Gas City",
    "sg:classifiers":[
        {
            "category":"Organizations",
            "subcategory":"Religious Organization",
            "type":"Services"
        }
    ],
    "sg:phone":"+1 765 674 1017",
    "sg:postcode":"46933",
    "sg:province":"IN",
    "sg:tags":[
        "church"
    ],
    "wof:name":"Church Of God Of Prophecy",
    "wof:placetype":"venue"
},
  "geometry": {"coordinates":[-85.595814,40.495511],"type":"Point"}
}