{
  "type": "Feature",
  "properties": {
    "iso:country":"US",
    "sg:address":"4315 W Co Rd 650 N",
    "sg:city":"North Salem",
    "sg:phone":"+1 765 676 6607",
    "sg:postcode":"46165",
    "sg:province":"IN",
    "sg:tags":[
        "farm",
        "soybean"
    ],
    "wof:name":"Alvin Brunes",
    "wof:placetype":"venue"
},
  "geometry": {"coordinates":[-86.597341,39.855559],"type":"Point"}
}