{
  "type": "Feature",
  "properties": {
    "iso:country":"US",
    "sg:address":"21 E Main St",
    "sg:city":"Brownsburg",
    "sg:classifiers":[
        {
            "category":"Shopping",
            "subcategory":"Pharmacy",
            "type":"Retail Goods"
        }
    ],
    "sg:phone":"+1 317 858 2954",
    "sg:postcode":"46112",
    "sg:province":"IN",
    "sg:website":"www.cvs.com",
    "wof:name":"CVS Pharmacy",
    "wof:placetype":"venue"
},
  "geometry": {"coordinates":[-86.39771,39.84319],"type":"Point"}
}