{
  "type": "Feature",
  "properties": {
    "addr:full":"5451 E 42nd St Indianapolis IN 46226",
    "addr:housenumber":"5451",
    "addr:postcode":"46226",
    "addr:street":"E 42Nd St",
    "iso:country":"US",
    "sg:address":"5451 E 42nd St",
    "sg:city":"Indianapolis",
    "sg:classifiers":[
        {
            "category":"Food & Beverages",
            "subcategory":"Bakery",
            "type":"Retail Goods"
        },
        {
            "category":"Wholesale",
            "subcategory":"Groceries",
            "type":"Manufacturing & Wholesale Goods"
        }
    ],
    "sg:phone":"+1 317 541 9223",
    "sg:postcode":"46226",
    "sg:province":"IN",
    "sg:tags":[
        "cooky",
        "crackers-wholesale",
        "bakers-wholesale",
        "manufacturer"
    ],
    "wof:name":"Cookie Crumb Corporation",
    "wof:placetype":"venue"
},
  "geometry": {"coordinates":[-86.075653,39.833038],"type":"Point"}
}