{
  "type": "Feature",
  "properties": {
    "iso:country":"US",
    "sg:address":"6401 Hemlock Ave",
    "sg:city":"Gary",
    "sg:classifiers":[
        {
            "category":"Education",
            "subcategory":"School",
            "type":"Public Place"
        }
    ],
    "sg:phone":"+1 219 938 1191",
    "sg:postcode":"46403",
    "sg:province":"IN",
    "wof:name":"Jacques Marquette School",
    "wof:placetype":"venue"
},
  "geometry": {"coordinates":[-87.262629,41.613441],"type":"Point"}
}