{
  "type": "Feature",
  "properties": {
    "iso:country":"US",
    "sg:address":"1601 W Indiana Ave",
    "sg:city":"South Bend",
    "sg:classifiers":[
        {
            "category":"Retail",
            "subcategory":"Auto Repair",
            "type":"Services"
        }
    ],
    "sg:phone":"+1 574 251 0524",
    "sg:postcode":"46613",
    "sg:province":"IN",
    "sg:tags":[
        "repairing",
        "automobile"
    ],
    "wof:name":"California Auto Repair",
    "wof:placetype":"venue"
},
  "geometry": {"coordinates":[-86.273263,41.657208],"type":"Point"}
}