{
  "type": "Feature",
  "properties": {
    "addr:full":"3570 Newton St Jasper IN 47546",
    "addr:housenumber":"3570",
    "addr:postcode":"47546",
    "addr:street":"Newton St",
    "iso:country":"US",
    "sg:address":"3570 Newton St",
    "sg:city":"Jasper",
    "sg:classifiers":[
        {
            "category":"Bars & Pubs",
            "type":"Food & Drink"
        },
        {
            "category":"Restaurant",
            "type":"Food & Drink"
        }
    ],
    "sg:menulink":"http://www.allmenus.com/in/bainbridge/224329-garfields-restaurant--pub/menu/",
    "sg:phone":"+1 812 471 2806",
    "sg:postcode":"47546",
    "sg:province":"IN",
    "sg:tags":[
        "food",
        "american",
        "pub"
    ],
    "wof:name":"Garfield's Restaurant & Pub",
    "wof:placetype":"venue"
},
  "geometry": {"coordinates":[-86.937811,38.421855],"type":"Point"}
}