{
  "type": "Feature",
  "properties": {
    "iso:country":"US",
    "sg:address":"6060 Castleway West Dr",
    "sg:city":"Indianapolis",
    "sg:classifiers":[
        {
            "category":"Social Services",
            "subcategory":"Job Training",
            "type":"Services"
        },
        {
            "category":"Education",
            "subcategory":"Special Training",
            "type":"Public Place"
        },
        {
            "category":"Education",
            "subcategory":"Vocational School",
            "type":"Public Place"
        },
        {
            "category":"Education",
            "subcategory":"University",
            "type":"Public Place"
        }
    ],
    "sg:phone":"+1 317 755 4287",
    "sg:postcode":"46250",
    "sg:province":"IN",
    "sg:tags":[
        "business",
        "assistant",
        "dental",
        "computer",
        "college",
        "technician",
        "technology",
        "medical"
    ],
    "sg:website":"http://www.national-college.edu",
    "wof:name":"National College",
    "wof:placetype":"venue"
},
  "geometry": {"coordinates":[-86.066672,39.903462],"type":"Point"}
}