{
  "type": "Feature",
  "properties": {
    "iso:country":"US",
    "sg:address":"635 W 49th Ave",
    "sg:city":"Gary",
    "sg:classifiers":[
        {
            "category":"Organizations",
            "subcategory":"Religious Organization",
            "type":"Services"
        }
    ],
    "sg:phone":"+1 219 887 7613",
    "sg:postcode":"46408",
    "sg:province":"IN",
    "sg:tags":[
        "church"
    ],
    "wof:name":"Carter Memorial CME",
    "wof:placetype":"venue"
},
  "geometry": {"coordinates":[-87.344294,41.529454],"type":"Point"}
}