{
  "type": "Feature",
  "properties": {
    "addr:full":"110 S Main St Advance IN 46102",
    "addr:housenumber":"110",
    "addr:postcode":"46102",
    "addr:street":"S Main St",
    "iso:country":"US",
    "sg:address":"110 S Main St",
    "sg:city":"Advance",
    "sg:classifiers":[
        {
            "category":"Government",
            "subcategory":"Post Office",
            "type":"Public Place"
        }
    ],
    "sg:phone":"+1 765 676 6477",
    "sg:postcode":"46102",
    "sg:province":"IN",
    "wof:name":"US Post Office",
    "wof:placetype":"venue"
},
  "geometry": {"coordinates":[-86.619775,39.995669],"type":"Point"}
}