{
  "type": "Feature",
  "properties": {
    "iso:country":"US",
    "sg:address":"5 Hoosier Ave",
    "sg:city":"Oolitic",
    "sg:classifiers":[
        {
            "category":"Government",
            "subcategory":"Fire Station",
            "type":"Public Place"
        }
    ],
    "sg:phone":"+1 812 279 0477",
    "sg:postcode":"47451",
    "sg:province":"IN",
    "sg:tags":[
        "department"
    ],
    "wof:name":"Oolitic Fire Dept Non Emrgncy",
    "wof:placetype":"venue"
},
  "geometry": {"coordinates":[-86.52724499999999,38.903623],"type":"Point"}
}