{
  "type": "Feature",
  "properties": {
    "iso:country":"US",
    "sg:address":"309 N Main St",
    "sg:city":"Frankfort",
    "sg:classifiers":[
        {
            "category":"Organizations",
            "subcategory":"Community Association",
            "type":"Services"
        }
    ],
    "sg:phone":"+1 765 654 7624",
    "sg:postcode":"46041",
    "sg:province":"IN",
    "wof:name":"Veterans Of Foreign Wars",
    "wof:placetype":"venue"
},
  "geometry": {"coordinates":[-86.51196400000001,40.28162],"type":"Point"}
}