{
  "type": "Feature",
  "properties": {
    "addr:full":"4974 Scottsville Rd Floyds Knobs IN 47119",
    "addr:housenumber":"4974",
    "addr:postcode":"in 47119",
    "addr:street":"Scottsville Rd",
    "iso:country":"US",
    "sg:address":"4974 Scottsville Rd",
    "sg:city":"Floyds Knobs",
    "sg:classifiers":[
        {
            "category":"Building & Trades",
            "subcategory":"Construction",
            "type":"Services"
        }
    ],
    "sg:phone":"+1 812 923 1452",
    "sg:postcode":"47119",
    "sg:province":"IN",
    "sg:tags":[
        "general",
        "contractor"
    ],
    "sg:website":"www.aje-builders.com",
    "wof:name":"Absolute Builders",
    "wof:placetype":"venue"
},
  "geometry": {"coordinates":[-85.876869,38.346009],"type":"Point"}
}