{
  "type": "Feature",
  "properties": {
    "addr:full":"3483 W 3rd St Bloomington IN 47404",
    "addr:housenumber":"3483",
    "addr:postcode":"47404",
    "addr:street":"W 3Rd St",
    "iso:country":"US",
    "sg:address":"3483 W 3rd St",
    "sg:city":"Bloomington",
    "sg:classifiers":[
        {
            "category":"Home & Garden",
            "subcategory":"Household Appliances",
            "type":"Retail Goods"
        }
    ],
    "sg:phone":"+1 812 323 0302",
    "sg:postcode":"47404",
    "sg:province":"IN",
    "sg:tags":[
        "machine",
        "sewing"
    ],
    "wof:name":"Abbey Sewing Ctr",
    "wof:placetype":"venue"
},
  "geometry": {"coordinates":[-86.577972,39.164512],"type":"Point"}
}