{
  "type": "Feature",
  "properties": {
    "iso:country":"US",
    "sg:address":"541 S Lake St",
    "sg:city":"Gary",
    "sg:classifiers":[
        {
            "category":"Wholesale",
            "subcategory":"Machinery & Supplies",
            "type":"Manufacturing & Wholesale Goods"
        }
    ],
    "sg:phone":"+1 219 939 3870",
    "sg:postcode":"46403",
    "sg:province":"IN",
    "sg:tags":[
        "mason",
        "contractor"
    ],
    "wof:name":"Mortar Net",
    "wof:placetype":"venue"
},
  "geometry": {"coordinates":[-87.267431,41.600548],"type":"Point"}
}