{
  "type": "Feature",
  "properties": {
    "addr:full":"424 S Sycamore St Syracuse IN 46567",
    "addr:housenumber":"424",
    "addr:postcode":"46567",
    "addr:street":"S Sycamore St",
    "iso:country":"US",
    "sg:address":"424 S Sycamore St",
    "sg:city":"Syracuse",
    "sg:classifiers":[
        {
            "category":"Manufacturing",
            "subcategory":"Chemicals & Compounds",
            "type":"Manufacturing & Wholesale Goods"
        }
    ],
    "sg:phone":"+1 574 457 4133",
    "sg:postcode":"46567",
    "sg:province":"IN",
    "sg:tags":[
        "polish"
    ],
    "wof:name":"Tekonsha Corp-Custom Div",
    "wof:placetype":"venue"
},
  "geometry": {"coordinates":[-85.749426,41.418678],"type":"Point"}
}