{
  "type": "Feature",
  "properties": {
    "iso:country":"US",
    "sg:address":"424 Heltonville Rd W",
    "sg:city":"Bedford",
    "sg:classifiers":[
        {
            "category":"Communications",
            "subcategory":"Radio Station",
            "type":"Services"
        }
    ],
    "sg:phone":"+1 812 333 1050",
    "sg:postcode":"47421",
    "sg:province":"IN",
    "sg:tags":[
        "company",
        "broadcasting"
    ],
    "sg:website":"www.wqrk.com",
    "wof:name":"WQRK",
    "wof:placetype":"venue"
},
  "geometry": {"coordinates":[-86.474833,38.874691],"type":"Point"}
}