{
  "type": "Feature",
  "properties": {
    "iso:country":"US",
    "sg:address":"862 E 125 S",
    "sg:city":"Franklin",
    "sg:classifiers":[
        {
            "category":"Real Estate",
            "subcategory":"Real Estate Operator",
            "type":"Services"
        }
    ],
    "sg:phone":"+1 317 738 2134",
    "sg:postcode":"46131",
    "sg:province":"IN",
    "sg:tags":[
        "farm",
        "corn",
        "property",
        "soybean",
        "lessor"
    ],
    "wof:name":"Ralph Duckworth",
    "wof:placetype":"venue"
},
  "geometry": {"coordinates":[-86.086497,39.459126],"type":"Point"}
}