{
  "type": "Feature",
  "properties": {
    "iso:country":"US",
    "sg:address":"2923 Broad St",
    "sg:city":"New Castle",
    "sg:classifiers":[
        {
            "category":"Retail",
            "subcategory":"Auto Rental",
            "type":"Services"
        }
    ],
    "sg:phone":"+1 765 529 7966",
    "sg:postcode":"47362",
    "sg:province":"IN",
    "sg:tags":[
        "renting",
        "truck",
        "leasing"
    ],
    "wof:name":"U-Haul Co",
    "wof:placetype":"venue"
},
  "geometry": {"coordinates":[-85.34921900000001,39.928411],"type":"Point"}
}