{
  "type": "Feature",
  "properties": {
    "iso:country":"US",
    "sg:address":"510 Lincoln Way E",
    "sg:city":"Mishawaka",
    "sg:classifiers":[
        {
            "category":"Real Estate",
            "subcategory":"Architect",
            "type":"Services"
        }
    ],
    "sg:phone":"+1 574 257 1843",
    "sg:postcode":"46544",
    "sg:province":"IN",
    "wof:name":"CTG & Assoc",
    "wof:placetype":"venue"
},
  "geometry": {"coordinates":[-86.173676,41.661213],"type":"Point"}
}