{
  "type": "Feature",
  "properties": {
    "addr:full":"3850 S Emerson Ave Indianapolis IN 46203",
    "addr:housenumber":"3850",
    "addr:postcode":"46203",
    "addr:street":"S Emerson Ave",
    "iso:country":"US",
    "sg:address":"3850 S Emerson Ave",
    "sg:city":"Indianapolis",
    "sg:classifiers":[
        {
            "category":"Banks & Credit Unions",
            "subcategory":"Bank",
            "type":"Services"
        }
    ],
    "sg:phone":"+1 317 784 6692",
    "sg:postcode":"46203",
    "sg:province":"IN",
    "sg:tags":[
        "financing"
    ],
    "wof:name":"American General Finance Inc",
    "wof:placetype":"venue"
},
  "geometry": {"coordinates":[-86.082666,39.710414],"type":"Point"}
}