{
  "type": "Feature",
  "properties": {
    "iso:country":"US",
    "sg:address":"9511 W State Rte 662",
    "sg:city":"Newburgh",
    "sg:classifiers":[
        {
            "category":"Recreation",
            "type":"Entertainment"
        }
    ],
    "sg:phone":"+1 812 858 5152",
    "sg:postcode":"47630",
    "sg:province":"IN",
    "sg:tags":[
        "club",
        "baseball"
    ],
    "wof:name":"Newburgh Junior Baseball",
    "wof:placetype":"venue"
},
  "geometry": {"coordinates":[-87.422669,37.9505],"type":"Point"}
}