{
  "type": "Feature",
  "properties": {
    "iso:country":"US",
    "sg:address":"1650 W Oak St",
    "sg:city":"Zionsville",
    "sg:classifiers":[
        {
            "category":"Health Services",
            "subcategory":"Doctor",
            "type":"Services"
        }
    ],
    "sg:phone":"+1 317 873 8807",
    "sg:postcode":"46077",
    "sg:province":"IN",
    "sg:tags":[
        "physician",
        "surgeon"
    ],
    "wof:name":"C Layton Elliott MD",
    "wof:placetype":"venue"
},
  "geometry": {"coordinates":[-86.282516,39.95012],"type":"Point"}
}