{
  "type": "Feature",
  "properties": {
    "iso:country":"US",
    "sg:address":"516 N Line St",
    "sg:city":"Columbia City",
    "sg:classifiers":[
        {
            "category":"Health Services",
            "subcategory":"Doctor",
            "type":"Services"
        }
    ],
    "sg:phone":"+1 260 244 4007",
    "sg:postcode":"46725",
    "sg:province":"IN",
    "sg:tags":[
        "dentist"
    ],
    "wof:name":"Midwest Oral & Maxillofacial",
    "wof:placetype":"venue"
},
  "geometry": {"coordinates":[-85.49145300000001,41.165687],"type":"Point"}
}