{
  "type": "Feature",
  "properties": {
    "addr:full":"1629 Co Rd 950 S Clinton IN 47842",
    "addr:housenumber":"1629;950",
    "addr:postcode":"47842",
    "addr:street":"Co Rd;S Clinton",
    "iso:country":"US",
    "sg:address":"1629 Co Rd 950 S",
    "sg:city":"Clinton",
    "sg:phone":"+1 765 665 3320",
    "sg:postcode":"47842",
    "sg:province":"IN",
    "sg:tags":[
        "farm",
        "corn"
    ],
    "wof:name":"James Chambers",
    "wof:placetype":"venue"
},
  "geometry": {"coordinates":[-87.50027799999999,39.745707],"type":"Point"}
}