{
  "type": "Feature",
  "properties": {
    "addr:full":"234 E Main St Plainfield IN 46168",
    "addr:housenumber":"234",
    "addr:postcode":"46168",
    "addr:street":"E Main St",
    "iso:country":"US",
    "sg:address":"234 E Main St",
    "sg:city":"Plainfield",
    "sg:classifiers":[
        {
            "category":"Shopping",
            "subcategory":"Clothing, Apparel, & Fashions",
            "type":"Retail Goods"
        }
    ],
    "sg:phone":"+1 317 838 7244",
    "sg:postcode":"46168",
    "sg:province":"IN",
    "sg:tags":[
        "infant",
        "consignment",
        "wear"
    ],
    "wof:name":"Kids Corner",
    "wof:placetype":"venue"
},
  "geometry": {"coordinates":[-86.40044,39.703564],"type":"Point"}
}