{
  "type": "Feature",
  "properties": {
    "iso:country":"US",
    "sg:address":"8750 E Windsor Rd",
    "sg:city":"Selma",
    "sg:classifiers":[
        {
            "category":"Professional",
            "subcategory":"Business Services",
            "type":"Services"
        }
    ],
    "sg:phone":"+1 765 288 4313",
    "sg:postcode":"47383",
    "sg:province":"IN",
    "sg:tags":[
        "promotional"
    ],
    "wof:name":"Total Marketing Concepts",
    "wof:placetype":"venue"
},
  "geometry": {"coordinates":[-85.28836200000001,40.149339],"type":"Point"}
}