{
  "type": "Feature",
  "properties": {
    "iso:country":"US",
    "sg:address":"302 Elm St",
    "sg:city":"Clinton",
    "sg:classifiers":[
        {
            "category":"Insurance",
            "subcategory":"Insurance Agent",
            "type":"Services"
        }
    ],
    "sg:phone":"+1 765 832 3493",
    "sg:postcode":"47842",
    "sg:province":"IN",
    "wof:name":"Wilson Insurance",
    "wof:placetype":"venue"
},
  "geometry": {"coordinates":[-87.39970099999999,39.657055],"type":"Point"}
}