{
  "type": "Feature",
  "properties": {
    "addr:full":"421 Jefferson St Covington IN 47932",
    "addr:housenumber":"421",
    "addr:postcode":"47932",
    "addr:street":"Jefferson St",
    "iso:country":"US",
    "sg:address":"421 Jefferson St",
    "sg:city":"Covington",
    "sg:classifiers":[
        {
            "category":"Shopping",
            "subcategory":"Department Store",
            "type":"Retail Goods"
        }
    ],
    "sg:phone":"+1 765 793 2571",
    "sg:postcode":"47932",
    "sg:province":"IN",
    "sg:tags":[
        "shop",
        "discount"
    ],
    "sg:website":"http://www.dollargeneral.com",
    "wof:name":"Dollar General",
    "wof:placetype":"venue"
},
  "geometry": {"coordinates":[-87.396595,40.13857],"type":"Point"}
}