{
  "type": "Feature",
  "properties": {
    "addr:full":"1405 Berwick Ln New Haven IN 46774",
    "addr:housenumber":"1405",
    "addr:postcode":"46774",
    "addr:street":"Berwick Ln",
    "iso:country":"US",
    "sg:address":"1405 Berwick Ln",
    "sg:city":"New Haven",
    "sg:classifiers":[
        {
            "category":"Retail",
            "subcategory":"Portrait Studio",
            "type":"Services"
        }
    ],
    "sg:phone":"+1 260 493 2882",
    "sg:postcode":"46774",
    "sg:province":"IN",
    "sg:tags":[
        "photo"
    ],
    "wof:name":"Justin Vaugh",
    "wof:placetype":"venue"
},
  "geometry": {"coordinates":[-85.009619,41.061863],"type":"Point"}
}