{
  "type": "Feature",
  "properties": {
    "addr:full":"1003 W 3rd St Rushville IN 46173",
    "addr:housenumber":"1003",
    "addr:postcode":"46173",
    "addr:street":"W 3Rd St",
    "iso:country":"US",
    "sg:address":"1003 W 3rd St",
    "sg:city":"Rushville",
    "sg:classifiers":[
        {
            "category":"Shopping",
            "subcategory":"Hobbies, Toys, & Games",
            "type":"Retail Goods"
        }
    ],
    "sg:phone":"+1 765 938 3524",
    "sg:postcode":"46173",
    "sg:province":"IN",
    "sg:tags":[
        "craft"
    ],
    "wof:name":"Mindy's",
    "wof:placetype":"venue"
},
  "geometry": {"coordinates":[-85.459897,39.611309],"type":"Point"}
}