{
  "type": "Feature",
  "properties": {
    "iso:country":"US",
    "sg:address":"334 N Halleck St",
    "sg:city":"Demotte",
    "sg:classifiers":[
        {
            "category":"Shopping",
            "subcategory":"Department Store",
            "type":"Retail Goods"
        }
    ],
    "sg:phone":"+1 219 987 3755",
    "sg:postcode":"46310",
    "sg:province":"IN",
    "sg:tags":[
        "shop"
    ],
    "wof:name":"ALCO",
    "wof:placetype":"venue"
},
  "geometry": {"coordinates":[-87.198911,41.206973],"type":"Point"}
}