{
  "type": "Feature",
  "properties": {
    "iso:country":"US",
    "sg:address":"109 14th St",
    "sg:city":"Middlebury",
    "sg:classifiers":[
        {
            "category":"Manufacturing",
            "subcategory":"Buildings",
            "type":"Manufacturing & Wholesale Goods"
        }
    ],
    "sg:phone":"+1 574 825 8400",
    "sg:postcode":"46540",
    "sg:province":"IN",
    "sg:tags":[
        "mobile",
        "home"
    ],
    "sg:website":"www.patriothomes.com",
    "wof:name":"Victorian Homes Inc",
    "wof:placetype":"venue"
},
  "geometry": {"coordinates":[-85.69906899999999,41.687094],"type":"Point"}
}