{
  "type": "Feature",
  "properties": {
    "iso:country":"US",
    "sg:address":"201 S Capitol Ave",
    "sg:city":"Indianapolis",
    "sg:classifiers":[
        {
            "category":"Manufacturing",
            "subcategory":"Printing",
            "type":"Manufacturing & Wholesale Goods"
        }
    ],
    "sg:phone":"+1 317 925 1099",
    "sg:postcode":"46225",
    "sg:province":"IN",
    "sg:tags":[
        "printer",
        "form"
    ],
    "wof:name":"Moore Wallace North America",
    "wof:placetype":"venue"
},
  "geometry": {"coordinates":[-86.161859,39.763185],"type":"Point"}
}