{
  "type": "Feature",
  "properties": {
    "iso:country":"US",
    "sg:address":"2631 Belle Vista Blvd",
    "sg:city":"Fort Wayne",
    "sg:classifiers":[
        {
            "category":"Building & Trades",
            "subcategory":"Construction",
            "type":"Services"
        }
    ],
    "sg:phone":"+1 260 747 0112",
    "sg:postcode":"46809",
    "sg:province":"IN",
    "sg:tags":[
        "floor",
        "laying",
        "contractor"
    ],
    "wof:name":"Todd C Rees Installation",
    "wof:placetype":"venue"
},
  "geometry": {"coordinates":[-85.171399,41.03146],"type":"Point"}
}