{
  "type": "Feature",
  "properties": {
    "iso:country":"US",
    "sg:address":"514 Drover St",
    "sg:city":"Indianapolis",
    "sg:classifiers":[
        {
            "category":"Organizations",
            "subcategory":"Labor Organization",
            "type":"Services"
        }
    ],
    "sg:phone":"+1 317 636 0730",
    "sg:postcode":"46221",
    "sg:province":"IN",
    "wof:name":"UAW",
    "wof:placetype":"venue"
},
  "geometry": {"coordinates":[-86.176496,39.758839],"type":"Point"}
}