{
  "type": "Feature",
  "properties": {
    "iso:country":"US",
    "sg:address":"1931 S Weinbach Ave",
    "sg:city":"Evansville",
    "sg:classifiers":[
        {
            "category":"Shopping",
            "subcategory":"Used Merchandise",
            "type":"Retail Goods"
        }
    ],
    "sg:phone":"+1 812 473 3886",
    "sg:postcode":"47714",
    "sg:province":"IN",
    "sg:tags":[
        "shop",
        "thrift"
    ],
    "wof:name":"Salvation Army",
    "wof:placetype":"venue"
},
  "geometry": {"coordinates":[-87.5299,37.948174],"type":"Point"}
}