{
  "type": "Feature",
  "properties": {
    "iso:country":"US",
    "sg:address":"314 W Cleveland Rd",
    "sg:city":"Granger",
    "sg:classifiers":[
        {
            "category":"Personal",
            "subcategory":"Tanning Parlor",
            "type":"Services"
        },
        {
            "category":"Personal",
            "type":"Services"
        }
    ],
    "sg:phone":"+1 574 271 2924",
    "sg:postcode":"46530",
    "sg:province":"IN",
    "sg:tags":[
        "salon"
    ],
    "wof:name":"Marcels Tanning Salons Inc",
    "wof:placetype":"venue"
},
  "geometry": {"coordinates":[-86.18543,41.723979],"type":"Point"}
}