{
  "type": "Feature",
  "properties": {
    "iso:country":"US",
    "sg:address":"631 N College Ave",
    "sg:city":"Bloomington",
    "sg:classifiers":[
        {
            "category":"Health Services",
            "subcategory":"Doctor",
            "type":"Services"
        },
        {
            "category":"Health Services",
            "subcategory":"Clinic",
            "type":"Services"
        }
    ],
    "sg:phone":"+1 812 332 5289",
    "sg:postcode":"47404",
    "sg:province":"IN",
    "sg:tags":[
        "counseling",
        "mental"
    ],
    "wof:name":"Weller Donald PHD",
    "wof:placetype":"venue"
},
  "geometry": {"coordinates":[-86.535004,39.172199],"type":"Point"}
}