{
  "type": "Feature",
  "properties": {
    "iso:country":"US",
    "sg:address":"1200 Madison Ave",
    "sg:city":"Indianapolis",
    "sg:classifiers":[
        {
            "category":"Retail",
            "subcategory":"Repair Shop",
            "type":"Services"
        }
    ],
    "sg:phone":"+1 317 331 1608",
    "sg:postcode":"46225",
    "sg:province":"IN",
    "sg:tags":[
        "ironwork"
    ],
    "wof:name":"Apple Ironworks",
    "wof:placetype":"venue"
},
  "geometry": {"coordinates":[-86.154236,39.75069],"type":"Point"}
}