{
  "type": "Feature",
  "properties": {
    "iso:country":"US",
    "sg:address":"112 S Main St",
    "sg:city":"Churubusco",
    "sg:classifiers":[
        {
            "category":"Shopping",
            "subcategory":"Computers & Home Electronics",
            "type":"Retail Goods"
        }
    ],
    "sg:phone":"+1 260 693 3334",
    "sg:postcode":"46723",
    "sg:province":"IN",
    "sg:tags":[
        "equipment",
        "dealer"
    ],
    "wof:name":"Accurasource Computers",
    "wof:placetype":"venue"
},
  "geometry": {"coordinates":[-85.319228,41.230576],"type":"Point"}
}