{
  "type": "Feature",
  "properties": {
    "iso:country":"US",
    "sg:address":"7036 Goshen Rd",
    "sg:city":"Fort Wayne",
    "sg:classifiers":[
        {
            "category":"Arts & Performance",
            "subcategory":"Theater",
            "type":"Entertainment"
        }
    ],
    "sg:phone":"+1 260 459 0568",
    "sg:postcode":"46818",
    "sg:province":"IN",
    "sg:tags":[
        "group"
    ],
    "wof:name":"A Strip O Gram",
    "wof:placetype":"venue"
},
  "geometry": {"coordinates":[-85.226966,41.156888],"type":"Point"}
}