{
  "type": "Feature",
  "properties": {
    "iso:country":"US",
    "sg:address":"8137 Pendleton Pike",
    "sg:city":"Indianapolis",
    "sg:classifiers":[
        {
            "category":"Cinema",
            "subcategory":"Movie Rental",
            "type":"Entertainment"
        }
    ],
    "sg:phone":"+1 317 869 0144",
    "sg:postcode":"46226",
    "sg:province":"IN",
    "sg:tags":[
        "leasing",
        "video",
        "disc",
        "tape"
    ],
    "wof:name":"Dave's Video",
    "wof:placetype":"venue"
},
  "geometry": {"coordinates":[-86.022823,39.838279],"type":"Point"}
}