{
  "type": "Feature",
  "properties": {
    "iso:country":"US",
    "sg:address":"8383 Craig St",
    "sg:city":"Indianapolis",
    "sg:classifiers":[
        {
            "category":"Insurance",
            "subcategory":"Insurance Agent",
            "type":"Services"
        }
    ],
    "sg:phone":"+1 317 849 6620",
    "sg:postcode":"46250",
    "sg:province":"IN",
    "wof:name":"Luxor Insurance Group",
    "wof:placetype":"venue"
},
  "geometry": {"coordinates":[-86.05291699999999,39.906909],"type":"Point"}
}