{
  "type": "Feature",
  "properties": {
    "addr:full":"11339 Calumet Ave Dyer IN 46311",
    "addr:housenumber":"11339",
    "addr:postcode":"46311",
    "addr:street":"Calumet Ave",
    "iso:country":"US",
    "sg:address":"11339 Calumet Ave",
    "sg:city":"Dyer",
    "sg:classifiers":[
        {
            "category":"Building & Trades",
            "subcategory":"Construction",
            "type":"Services"
        }
    ],
    "sg:phone":"+1 219 365 8879",
    "sg:postcode":"46311",
    "sg:province":"IN",
    "sg:tags":[
        "roofing",
        "contractor"
    ],
    "wof:name":"Eenigenburg Roofing",
    "wof:placetype":"venue"
},
  "geometry": {"coordinates":[-87.50823200000001,41.413159],"type":"Point"}
}