{
  "type": "Feature",
  "properties": {
    "iso:country":"US",
    "sg:address":"134 N Walnut St",
    "sg:city":"Bloomington",
    "sg:classifiers":[
        {
            "category":"Professional",
            "subcategory":"Management & Consulting",
            "type":"Services"
        }
    ],
    "sg:phone":"+1 812 332 3329",
    "sg:postcode":"47404",
    "sg:province":"IN",
    "sg:tags":[
        "marketing",
        "consultant"
    ],
    "wof:name":"Sage Marketing Communications",
    "wof:placetype":"venue"
},
  "geometry": {"coordinates":[-86.533533,39.167214],"type":"Point"}
}