{
  "type": "Feature",
  "properties": {
    "addr:full":"6742 E 82nd St Indianapolis IN 46250",
    "addr:housenumber":"6742",
    "addr:postcode":"46250",
    "addr:street":"E 82Nd St",
    "iso:country":"US",
    "sg:address":"6742 E 82nd St",
    "sg:city":"Indianapolis",
    "sg:classifiers":[
        {
            "category":"Restaurant",
            "type":"Food & Drink"
        }
    ],
    "sg:menulink":"http://www.allmenus.com/in/lawrence/163402-rallys/menu/",
    "sg:phone":"+1 317 585 9546",
    "sg:postcode":"46250",
    "sg:province":"IN",
    "sg:tags":[
        "sandwich",
        "dog",
        "burger",
        "hot",
        "wrap",
        "american"
    ],
    "wof:name":"Rally's",
    "wof:placetype":"venue"
},
  "geometry": {"coordinates":[-86.050523,39.905262],"type":"Point"}
}