{
  "type": "Feature",
  "properties": {
    "addr:full":"8040 Clearvista Pkwy Indianapolis IN 46256",
    "addr:housenumber":"8040",
    "addr:postcode":"46256",
    "addr:street":"Clearvista Pkwy",
    "iso:country":"US",
    "sg:address":"8040 Clearvista Pkwy",
    "sg:city":"Indianapolis",
    "sg:classifiers":[
        {
            "category":"Health Services",
            "subcategory":"Medical Lab",
            "type":"Services"
        }
    ],
    "sg:phone":"+1 317 598 8525",
    "sg:postcode":"46256",
    "sg:province":"IN",
    "sg:tags":[
        "laboratory"
    ],
    "wof:name":"Quest Diagnostics Inc",
    "wof:placetype":"venue"
},
  "geometry": {"coordinates":[-86.037823,39.901419],"type":"Point"}
}