{
  "type": "Feature",
  "properties": {
    "iso:country":"US",
    "sg:address":"490 W Plaza Dr",
    "sg:city":"Columbia City",
    "sg:classifiers":[
        {
            "category":"Banks & Credit Unions",
            "subcategory":"Bank",
            "type":"Services"
        }
    ],
    "sg:phone":"+1 260 244 4165",
    "sg:postcode":"46725",
    "sg:province":"IN",
    "sg:tags":[
        "cashing",
        "check"
    ],
    "wof:name":"Check 'n Go",
    "wof:placetype":"venue"
},
  "geometry": {"coordinates":[-85.491747,41.17011],"type":"Point"}
}