{
  "type": "Feature",
  "properties": {
    "addr:full":"600 Tracy Rd Whiteland IN 46184",
    "addr:housenumber":"600",
    "addr:postcode":"46184",
    "addr:street":"Tracy Rd",
    "iso:country":"US",
    "sg:address":"600 Tracy Rd",
    "sg:city":"Whiteland",
    "sg:classifiers":[
        {
            "category":"Retail",
            "subcategory":"Repair Shop",
            "type":"Services"
        },
        {
            "category":"Wholesale",
            "subcategory":"Construction Materials",
            "type":"Manufacturing & Wholesale Goods"
        },
        {
            "category":"Manufacturing",
            "subcategory":"Furniture",
            "type":"Manufacturing & Wholesale Goods"
        }
    ],
    "sg:phone":"+1 317 535 9070",
    "sg:postcode":"46184",
    "sg:province":"IN",
    "sg:tags":[
        "designer",
        "upholsterer",
        "supply",
        "builder",
        "caning",
        "custom",
        "refinish"
    ],
    "wof:name":"Second Chance",
    "wof:placetype":"venue"
},
  "geometry": {"coordinates":[-86.08837800000001,39.564667],"type":"Point"}
}