{
  "type": "Feature",
  "properties": {
    "addr:full":"6516 Glen Lake Ct Fort Wayne IN 46814",
    "addr:housenumber":"6516",
    "addr:postcode":"46814",
    "addr:street":"Glen Lake Ct",
    "iso:country":"US",
    "sg:address":"6516 Glen Lake Ct",
    "sg:city":"Fort Wayne",
    "sg:classifiers":[
        {
            "category":"Personal",
            "subcategory":"Tanning Parlor",
            "type":"Services"
        }
    ],
    "sg:phone":"+1 260 432 8848",
    "sg:postcode":"46814",
    "sg:province":"IN",
    "sg:tags":[
        "salon"
    ],
    "wof:name":"Mist N' Go Tan",
    "wof:placetype":"venue"
},
  "geometry": {"coordinates":[-85.302537,41.023735],"type":"Point"}
}