{
  "type": "Feature",
  "properties": {
    "iso:country":"US",
    "sg:address":"1550 E County Line Rd S",
    "sg:city":"Indianapolis",
    "sg:classifiers":[
        {
            "category":"Social Services",
            "type":"Services"
        }
    ],
    "sg:phone":"+1 317 883 2220",
    "sg:postcode":"46227",
    "sg:province":"IN",
    "sg:tags":[
        "instruction",
        "health",
        "care"
    ],
    "wof:name":"American Health Network",
    "wof:placetype":"venue"
},
  "geometry": {"coordinates":[-86.134811,39.635469],"type":"Point"}
}