{
  "type": "Feature",
  "properties": {
    "iso:country":"US",
    "sg:address":"907 Indiana Ave",
    "sg:city":"Indianapolis",
    "sg:classifiers":[
        {
            "category":"Restaurant",
            "type":"Food & Drink"
        }
    ],
    "sg:menulink":"http://www.allmenus.com/in/indianapolis/98235-qdoba/menu/",
    "sg:phone":"+1 317 423 3932",
    "sg:postcode":"46202",
    "sg:province":"IN",
    "sg:tags":[
        "mexican"
    ],
    "wof:name":"Qdoba",
    "wof:placetype":"venue"
},
  "geometry": {"coordinates":[-86.173109,39.779478],"type":"Point"}
}