{
  "type": "Feature",
  "properties": {
    "addr:full":"9052 E Garrison Hollow Rd Salem IN 47167",
    "addr:housenumber":"9052",
    "addr:postcode":"47167",
    "addr:street":"E Garrison Hollow Rd",
    "iso:country":"US",
    "sg:address":"9052 E Garrison Hollow Rd",
    "sg:city":"Salem",
    "sg:classifiers":[
        {
            "category":"Professional",
            "subcategory":"Research",
            "type":"Services"
        }
    ],
    "sg:phone":"+1 812 967 5048",
    "sg:postcode":"47167",
    "sg:province":"IN",
    "sg:tags":[
        "market",
        "analysis"
    ],
    "wof:name":"Garrison Hollow Mktng",
    "wof:placetype":"venue"
},
  "geometry": {"coordinates":[-85.938151,38.597564],"type":"Point"}
}