{
  "type": "Feature",
  "properties": {
    "iso:country":"US",
    "sg:address":"1317 E 10th St",
    "sg:city":"Jeffersonville",
    "sg:classifiers":[
        {
            "category":"Autos & Motor Vehicles",
            "subcategory":"Fuel & Gas Station",
            "type":"Retail Goods"
        }
    ],
    "sg:phone":"+1 812 283 0759",
    "sg:postcode":"47130",
    "sg:province":"IN",
    "sg:tags":[
        "oil"
    ],
    "wof:name":"Jeffersonville Marathon",
    "wof:placetype":"venue"
},
  "geometry": {"coordinates":[-85.730391,38.287289],"type":"Point"}
}