{
  "type": "Feature",
  "properties": {
    "iso:country":"US",
    "sg:address":"518 E Hendricks St",
    "sg:city":"Shelbyville",
    "sg:classifiers":[
        {
            "category":"Professional",
            "type":"Services"
        }
    ],
    "sg:phone":"+1 317 392 8713",
    "sg:postcode":"46176",
    "sg:province":"IN",
    "sg:tags":[
        "establishment"
    ],
    "wof:name":"Technology/Network Specialist",
    "wof:placetype":"venue"
},
  "geometry": {"coordinates":[-85.769949,39.52202],"type":"Point"}
}