{
  "type": "Feature",
  "properties": {
    "iso:country":"US",
    "sg:address":"121 W Liberty Ave",
    "sg:city":"Bourbon",
    "sg:classifiers":[
        {
            "category":"Health Services",
            "subcategory":"Doctor",
            "type":"Services"
        }
    ],
    "sg:phone":"+1 765 732 3114",
    "sg:postcode":"46504",
    "sg:province":"IN",
    "sg:tags":[
        "physician",
        "surgeon"
    ],
    "wof:name":"Oxford Internal Medicine",
    "wof:placetype":"venue"
},
  "geometry": {"coordinates":[-86.117244,41.298889],"type":"Point"}
}