{
  "type": "Feature",
  "properties": {
    "iso:country":"US",
    "sg:address":"9041 W 700 S",
    "sg:city":"Columbus",
    "sg:phone":"+1 812 342 3865",
    "sg:postcode":"47201",
    "sg:province":"IN",
    "sg:tags":[
        "farm",
        "corn",
        "soybean"
    ],
    "wof:name":"Denny Cottongim",
    "wof:placetype":"venue"
},
  "geometry": {"coordinates":[-86.018762,39.095625],"type":"Point"}
}