{
  "type": "Feature",
  "properties": {
    "iso:country":"US",
    "sg:address":"676 Main St",
    "sg:city":"Lafayette",
    "sg:classifiers":[
        {
            "category":"Retail",
            "subcategory":"Repair Shop",
            "type":"Services"
        }
    ],
    "sg:phone":"+1 765 423 4488",
    "sg:postcode":"47901",
    "sg:province":"IN",
    "sg:tags":[
        "bicycle"
    ],
    "wof:name":"Project Bike Shop",
    "wof:placetype":"venue"
},
  "geometry": {"coordinates":[-86.888273,40.419204],"type":"Point"}
}