{
  "type": "Feature",
  "properties": {
    "addr:full":"1640 E Morgan St Martinsville IN 46151",
    "addr:housenumber":"1640",
    "addr:postcode":"46151",
    "addr:street":"E Morgan St",
    "iso:country":"US",
    "sg:address":"1640 E Morgan St",
    "sg:city":"Martinsville",
    "sg:classifiers":[
        {
            "category":"Retail",
            "subcategory":"Auto Repair",
            "type":"Services"
        }
    ],
    "sg:phone":"+1 765 342 2176",
    "sg:postcode":"46151",
    "sg:province":"IN",
    "sg:tags":[
        "wrecker"
    ],
    "wof:name":"Across Town Transporting Svc",
    "wof:placetype":"venue"
},
  "geometry": {"coordinates":[-86.40767200000001,39.428658],"type":"Point"}
}