{
  "type": "Feature",
  "properties": {
    "iso:country":"US",
    "sg:address":"1585 E 86th St",
    "sg:city":"Indianapolis",
    "sg:classifiers":[
        {
            "category":"Government",
            "subcategory":"Fire Station",
            "type":"Public Place"
        }
    ],
    "sg:phone":"+1 317 252 5200",
    "sg:postcode":"46240",
    "sg:province":"IN",
    "sg:tags":[
        "department"
    ],
    "wof:name":"Washington Twp Fire Dept",
    "wof:placetype":"venue"
},
  "geometry": {"coordinates":[-86.132237,39.912442],"type":"Point"}
}