{
  "type": "Feature",
  "properties": {
    "addr:full":"311 N Green River Rd Evansville IN 47715",
    "addr:housenumber":"311",
    "addr:postcode":"47715",
    "addr:street":"N Green River Rd",
    "iso:country":"US",
    "sg:address":"311 N Green River Rd",
    "sg:city":"Evansville",
    "sg:classifiers":[
        {
            "category":"Restaurant",
            "type":"Food & Drink"
        }
    ],
    "sg:menulink":"http://www.allmenus.com/in/knight/100730-captain-ds-seafood/menu/",
    "sg:phone":"+1 812 476 3865",
    "sg:postcode":"47715",
    "sg:province":"IN",
    "sg:tags":[
        "seafood",
        "american"
    ],
    "wof:name":"Captain D's Seafood",
    "wof:placetype":"venue"
},
  "geometry": {"coordinates":[-87.492541,37.979302],"type":"Point"}
}