{
  "type": "Feature",
  "properties": {
    "iso:country":"US",
    "sg:address":"8018 W 950 S",
    "sg:city":"Kewanna",
    "sg:classifiers":[
        {
            "category":"Farming",
            "subcategory":"Farm",
            "type":"Manufacturing & Wholesale Goods"
        }
    ],
    "sg:phone":"+1 574 653 2518",
    "sg:postcode":"46939",
    "sg:province":"IN",
    "sg:tags":[
        "crop",
        "general"
    ],
    "wof:name":"Ryan Townsand",
    "wof:placetype":"venue"
},
  "geometry": {"coordinates":[-86.398692,40.916819],"type":"Point"}
}