{
  "type": "Feature",
  "properties": {
    "iso:country":"US",
    "sg:address":"2736 E Paulding Rd",
    "sg:city":"Fort Wayne",
    "sg:classifiers":[
        {
            "category":"Arts & Performance",
            "subcategory":"Theater",
            "type":"Entertainment"
        }
    ],
    "sg:phone":"+1 260 441 0445",
    "sg:postcode":"46816",
    "sg:province":"IN",
    "sg:tags":[
        "live",
        "music"
    ],
    "wof:name":"Hot Vocals",
    "wof:placetype":"venue"
},
  "geometry": {"coordinates":[-85.100568,41.032236],"type":"Point"}
}