{
  "type": "Feature",
  "properties": {
    "iso:country":"US",
    "sg:address":"2455 W 1000 S",
    "sg:city":"Keystone",
    "sg:classifiers":[
        {
            "category":"Organizations",
            "subcategory":"Religious Organization",
            "type":"Services"
        }
    ],
    "sg:phone":"+1 765 728 2154",
    "sg:postcode":"46759",
    "sg:province":"IN",
    "sg:tags":[
        "church"
    ],
    "wof:name":"Southern Wells Community Chr",
    "wof:placetype":"venue"
},
  "geometry": {"coordinates":[-85.265603,40.596211],"type":"Point"}
}