{
  "type": "Feature",
  "properties": {
    "iso:country":"US",
    "sg:address":"2620 N Riley Rd",
    "sg:city":"Columbia City",
    "sg:phone":"+1 260 244 5572",
    "sg:postcode":"46725",
    "sg:province":"IN",
    "sg:tags":[
        "farm",
        "corn",
        "wheat",
        "soybean"
    ],
    "wof:name":"Roy Pontzius",
    "wof:placetype":"venue"
},
  "geometry": {"coordinates":[-85.427567,41.202714],"type":"Point"}
}