{
  "type": "Feature",
  "properties": {
    "addr:full":"1970 N Wabash Rd Marion IN 46952",
    "addr:housenumber":"1970",
    "addr:postcode":"46952",
    "addr:street":"N Wabash Rd",
    "iso:country":"US",
    "sg:address":"1970 N Wabash Rd",
    "sg:city":"Marion",
    "sg:classifiers":[
        {
            "category":"Organizations",
            "subcategory":"Religious Organization",
            "type":"Services"
        }
    ],
    "sg:phone":"+1 765 664 1221",
    "sg:postcode":"46952",
    "sg:province":"IN",
    "sg:tags":[
        "church"
    ],
    "wof:name":"First Christian Church",
    "wof:placetype":"venue"
},
  "geometry": {"coordinates":[-85.68177900000001,40.583996],"type":"Point"}
}