{
  "type": "Feature",
  "properties": {
    "iso:country":"US",
    "sg:address":"11740 Sweeping Ridge Dr",
    "sg:city":"Zionsville",
    "sg:classifiers":[
        {
            "category":"Manufacturing",
            "subcategory":"Aerospace",
            "type":"Manufacturing & Wholesale Goods"
        }
    ],
    "sg:phone":"+1 317 557 1352",
    "sg:postcode":"46077",
    "sg:province":"IN",
    "sg:tags":[
        "supply",
        "equipment",
        "aircraft",
        "part",
        "supplies-wholesale",
        "manufacturer"
    ],
    "wof:name":"Iat Manufacturing",
    "wof:placetype":"venue"
},
  "geometry": {"coordinates":[-86.23007800000001,39.957932],"type":"Point"}
}