{
  "type": "Feature",
  "properties": {
    "iso:country":"US",
    "sg:address":"709 N Illinois St",
    "sg:city":"Indianapolis",
    "sg:classifiers":[
        {
            "category":"Recreation",
            "type":"Entertainment"
        },
        {
            "category":"Organizations",
            "subcategory":"Community Association",
            "type":"Services"
        }
    ],
    "sg:phone":"+1 317 631 3535",
    "sg:postcode":"46204",
    "sg:province":"IN",
    "sg:tags":[
        "club",
        "membership",
        "drinking"
    ],
    "wof:name":"Gatling Gun Club Inc",
    "wof:placetype":"venue"
},
  "geometry": {"coordinates":[-86.159417,39.777942],"type":"Point"}
}