{
  "type": "Feature",
  "properties": {
    "iso:country":"US",
    "sg:address":"3738 Allen Ave",
    "sg:city":"Fort Wayne",
    "sg:classifiers":[
        {
            "category":"Wholesale",
            "subcategory":"Electrical",
            "type":"Manufacturing & Wholesale Goods"
        }
    ],
    "sg:phone":"+1 260 471 7100",
    "sg:postcode":"46805",
    "sg:province":"IN",
    "sg:tags":[
        "electronic",
        "representative"
    ],
    "sg:website":"www.jgireps.com",
    "wof:name":"Johnson Group Inc",
    "wof:placetype":"venue"
},
  "geometry": {"coordinates":[-85.134236,41.111308],"type":"Point"}
}