{
  "type": "Feature",
  "properties": {
    "iso:country":"US",
    "sg:address":"510 E 96th St",
    "sg:city":"Indianapolis",
    "sg:classifiers":[
        {
            "category":"Manufacturing",
            "subcategory":"Printing",
            "type":"Manufacturing & Wholesale Goods"
        }
    ],
    "sg:phone":"+1 317 566 0525",
    "sg:postcode":"46240",
    "sg:province":"IN",
    "sg:tags":[
        "newspaper"
    ],
    "wof:name":"Inquisitive Kids",
    "wof:placetype":"venue"
},
  "geometry": {"coordinates":[-86.148962,39.927202],"type":"Point"}
}