{
  "type": "Feature",
  "properties": {
    "iso:country":"US",
    "sg:address":"5250 Broadway",
    "sg:city":"Merrillville",
    "sg:classifiers":[
        {
            "category":"Organizations",
            "subcategory":"Religious Organization",
            "type":"Services"
        }
    ],
    "sg:phone":"+1 219 887 3855",
    "sg:postcode":"46410",
    "sg:province":"IN",
    "wof:name":"Christ Is Knigchurch Of God",
    "wof:placetype":"venue"
},
  "geometry": {"coordinates":[-87.336258,41.523147],"type":"Point"}
}