{
  "type": "Feature",
  "properties": {
    "addr:full":"391 Newman Ave Clarksville IN 47129",
    "addr:housenumber":"391",
    "addr:postcode":"47129",
    "addr:street":"Newman Ave",
    "iso:country":"US",
    "sg:address":"391 Newman Ave",
    "sg:city":"Clarksville",
    "sg:classifiers":[
        {
            "category":"Professional",
            "subcategory":"Testing Lab",
            "type":"Services"
        }
    ],
    "sg:phone":"+1 812 282 8481",
    "sg:postcode":"47129",
    "sg:province":"IN",
    "sg:tags":[
        "laboratory"
    ],
    "wof:name":"Environmental Consultants Inc",
    "wof:placetype":"venue"
},
  "geometry": {"coordinates":[-85.761196,38.283826],"type":"Point"}
}