{
  "type": "Feature",
  "properties": {
    "iso:country":"US",
    "sg:address":"19201 Promise Rd",
    "sg:city":"Noblesville",
    "sg:classifiers":[
        {
            "category":"Organizations",
            "subcategory":"Religious Organization",
            "type":"Services"
        }
    ],
    "sg:phone":"+1 317 770 9920",
    "sg:postcode":"46060",
    "sg:province":"IN",
    "sg:tags":[
        "church"
    ],
    "sg:website":"www.faithcomm.com",
    "wof:name":"Faith Community Church",
    "wof:placetype":"venue"
},
  "geometry": {"coordinates":[-85.971973,40.068395],"type":"Point"}
}