{
  "type": "Feature",
  "properties": {
    "iso:country":"US",
    "sg:address":"1792 N Riley Hwy",
    "sg:city":"Shelbyville",
    "sg:classifiers":[
        {
            "category":"Autos & Motor Vehicles",
            "subcategory":"Fuel & Gas Station",
            "type":"Retail Goods"
        }
    ],
    "sg:phone":"+1 317 392 3746",
    "sg:postcode":"46176",
    "sg:province":"IN",
    "sg:tags":[
        "oil"
    ],
    "wof:name":"Shell Car Wash",
    "wof:placetype":"venue"
},
  "geometry": {"coordinates":[-85.775491,39.546078],"type":"Point"}
}