{
  "type": "Feature",
  "properties": {
    "iso:country":"US",
    "sg:address":"6840 Eagle Highlands Way",
    "sg:city":"Indianapolis",
    "sg:classifiers":[
        {
            "category":"Professional",
            "subcategory":"Accounting & Tax Preparation",
            "type":"Services"
        }
    ],
    "sg:phone":"+1 317 347 5200",
    "sg:postcode":"46254",
    "sg:province":"IN",
    "sg:tags":[
        "accountant"
    ],
    "sg:website":"www.kbparrish.com",
    "wof:name":"K B Parrish & Co",
    "wof:placetype":"venue"
},
  "geometry": {"coordinates":[-86.282705,39.828049],"type":"Point"}
}