{
  "type": "Feature",
  "properties": {
    "iso:country":"US",
    "sg:address":"110 N Franklin St",
    "sg:city":"Fairland",
    "sg:classifiers":[
        {
            "category":"Health Services",
            "subcategory":"Doctor",
            "type":"Services"
        }
    ],
    "sg:phone":"+1 317 835 7892",
    "sg:postcode":"46126",
    "sg:province":"IN",
    "sg:tags":[
        "dentist"
    ],
    "wof:name":"Robert Judah II LLC",
    "wof:placetype":"venue"
},
  "geometry": {"coordinates":[-85.859814,39.587648],"type":"Point"}
}