{
  "type": "Feature",
  "properties": {
    "iso:country":"US",
    "sg:address":"5726 Roxbury Cir",
    "sg:city":"Indianapolis",
    "sg:classifiers":[
        {
            "category":"Professional",
            "subcategory":"Management & Consulting",
            "type":"Services"
        }
    ],
    "sg:phone":"+1 317 545 9222",
    "sg:postcode":"46226",
    "sg:province":"IN",
    "sg:tags":[
        "consultant",
        "business"
    ],
    "wof:name":"Beavers Limited Part",
    "wof:placetype":"venue"
},
  "geometry": {"coordinates":[-86.070768,39.85288],"type":"Point"}
}