{
  "type": "Feature",
  "properties": {
    "iso:country":"US",
    "sg:address":"103 E Broadway St",
    "sg:city":"Shelbyville",
    "sg:classifiers":[
        {
            "category":"Retail",
            "subcategory":"Auto Repair",
            "type":"Services"
        }
    ],
    "sg:phone":"+1 317 398 2841",
    "sg:postcode":"46176",
    "sg:province":"IN",
    "sg:tags":[
        "automobile",
        "lubrication"
    ],
    "wof:name":"Mr Lubie",
    "wof:placetype":"venue"
},
  "geometry": {"coordinates":[-85.774811,39.522854],"type":"Point"}
}