{
  "type": "Feature",
  "properties": {
    "iso:country":"US",
    "sg:address":"5340 Julian Ave",
    "sg:city":"Indianapolis",
    "sg:classifiers":[
        {
            "category":"Arts & Performance",
            "subcategory":"Theater",
            "type":"Entertainment"
        }
    ],
    "sg:phone":"+1 317 926 2492",
    "sg:postcode":"46219",
    "sg:province":"IN",
    "sg:tags":[
        "live",
        "music"
    ],
    "wof:name":"Mystro's Entertainment Mobile",
    "wof:placetype":"venue"
},
  "geometry": {"coordinates":[-86.07726,39.768841],"type":"Point"}
}