{
  "type": "Feature",
  "properties": {
    "iso:country":"US",
    "sg:address":"13265 N Eastshore Dr",
    "sg:city":"Syracuse",
    "sg:classifiers":[
        {
            "category":"Real Estate",
            "subcategory":"Architect",
            "type":"Services"
        }
    ],
    "sg:phone":"+1 574 457 4454",
    "sg:postcode":"46567",
    "sg:province":"IN",
    "sg:tags":[
        "architectural"
    ],
    "wof:name":"Harwood Harwood Inc",
    "wof:placetype":"venue"
},
  "geometry": {"coordinates":[-85.725155,41.428488],"type":"Point"}
}