{
  "type": "Feature",
  "properties": {
    "iso:country":"US",
    "sg:address":"1824 E Main St",
    "sg:city":"Plainfield",
    "sg:classifiers":[
        {
            "category":"Insurance",
            "subcategory":"Insurance Agent",
            "type":"Services"
        }
    ],
    "sg:phone":"+1 317 839 5433",
    "sg:postcode":"46168",
    "sg:province":"IN",
    "wof:name":"Rick A Shaw Agency",
    "wof:placetype":"venue"
},
  "geometry": {"coordinates":[-86.376144,39.710749],"type":"Point"}
}