{
  "type": "Feature",
  "properties": {
    "iso:country":"US",
    "sg:address":"2421 Wilson Ave",
    "sg:city":"Madison",
    "sg:classifiers":[
        {
            "category":"Education",
            "subcategory":"School",
            "type":"Public Place"
        }
    ],
    "sg:phone":"+1 812 273 8511",
    "sg:postcode":"47250",
    "sg:province":"IN",
    "wof:name":"Madison Consolidated Schools",
    "wof:placetype":"venue"
},
  "geometry": {"coordinates":[-85.40599899999999,38.771934],"type":"Point"}
}