{
  "type": "Feature",
  "properties": {
    "iso:country":"US",
    "sg:address":"2010 N Lincoln St",
    "sg:city":"Greensburg",
    "sg:classifiers":[
        {
            "category":"Autos & Motor Vehicles",
            "subcategory":"Automobile Sales",
            "type":"Retail Goods"
        }
    ],
    "sg:phone":"+1 812 663 7621",
    "sg:postcode":"47240",
    "sg:province":"IN",
    "sg:tags":[
        "car",
        "dealer"
    ],
    "sg:website":"www.donmeyerford.com",
    "wof:name":"Don Meyer Ford Mercury Inc",
    "wof:placetype":"venue"
},
  "geometry": {"coordinates":[-85.479752,39.353551],"type":"Point"}
}