{
  "type": "Feature",
  "properties": {
    "addr:full":"550 S Indiana St Waterloo IN 46793",
    "addr:housenumber":"550",
    "addr:postcode":"46793",
    "addr:street":"S Indiana St",
    "iso:country":"US",
    "sg:address":"550 S Indiana St",
    "sg:city":"Waterloo",
    "sg:classifiers":[
        {
            "category":"Personal",
            "subcategory":"Beauty Salon",
            "type":"Services"
        }
    ],
    "sg:phone":"+1 260 238 4610",
    "sg:postcode":"46793",
    "sg:province":"IN",
    "wof:name":"Shear Country",
    "wof:placetype":"venue"
},
  "geometry": {"coordinates":[-85.014177,41.427722],"type":"Point"}
}