{
  "type": "Feature",
  "properties": {
    "iso:country":"US",
    "sg:address":"530 Indiana Ave",
    "sg:city":"Richmond",
    "sg:classifiers":[
        {
            "category":"Retail",
            "subcategory":"Auto Repair",
            "type":"Services"
        }
    ],
    "sg:phone":"+1 765 962 8736",
    "sg:postcode":"47374",
    "sg:province":"IN",
    "sg:tags":[
        "repairing",
        "automobile"
    ],
    "wof:name":"Christopher's Automotive Rpr",
    "wof:placetype":"venue"
},
  "geometry": {"coordinates":[-84.909846,39.838392],"type":"Point"}
}