{
  "type": "Feature",
  "properties": {
    "iso:country":"US",
    "sg:address":"109 N Mulberry St",
    "sg:city":"Fairland",
    "sg:classifiers":[
        {
            "category":"Organizations",
            "subcategory":"Religious Organization",
            "type":"Services"
        }
    ],
    "sg:phone":"+1 317 835 2984",
    "sg:postcode":"46126",
    "sg:province":"IN",
    "sg:tags":[
        "church"
    ],
    "wof:name":"Fairland Christian Church",
    "wof:placetype":"venue"
},
  "geometry": {"coordinates":[-85.863663,39.587837],"type":"Point"}
}