{
  "type": "Feature",
  "properties": {
    "iso:country":"US",
    "sg:address":"921 E Washington St",
    "sg:city":"Indianapolis",
    "sg:classifiers":[
        {
            "category":"Restaurant",
            "type":"Food & Drink"
        }
    ],
    "sg:menulink":"http://www.allmenus.com/in/indianapolis/155827-hardees/menu/",
    "sg:phone":"+1 317 631 8890",
    "sg:postcode":"46202",
    "sg:province":"IN",
    "sg:tags":[
        "burger",
        "american"
    ],
    "wof:name":"Hardee's",
    "wof:placetype":"venue"
},
  "geometry": {"coordinates":[-86.14146700000001,39.766521],"type":"Point"}
}