{
  "type": "Feature",
  "properties": {
    "iso:country":"US",
    "sg:address":"525 Michigan Ave",
    "sg:city":"Auburn",
    "sg:classifiers":[
        {
            "category":"Insurance",
            "subcategory":"Insurance Agent",
            "type":"Services"
        }
    ],
    "sg:phone":"+1 260 925 2668",
    "sg:postcode":"46706",
    "sg:province":"IN",
    "wof:name":"De Kalb Farm Mutual Insurance",
    "wof:placetype":"venue"
},
  "geometry": {"coordinates":[-85.06134299999999,41.370573],"type":"Point"}
}