{
  "type": "Feature",
  "properties": {
    "iso:country":"US",
    "sg:address":"366 Main Cross St",
    "sg:city":"Charlestown",
    "sg:classifiers":[
        {
            "category":"Banks & Credit Unions",
            "subcategory":"Bank",
            "type":"Services"
        }
    ],
    "sg:phone":"+1 812 256 6785",
    "sg:postcode":"47111",
    "sg:province":"IN",
    "sg:tags":[
        "loan",
        "mortgage",
        "real estate"
    ],
    "wof:name":"Hallmark Mortgage Co",
    "wof:placetype":"venue"
},
  "geometry": {"coordinates":[-85.66188200000001,38.444465],"type":"Point"}
}