{
  "type": "Feature",
  "properties": {
    "iso:country":"US",
    "sg:address":"109 N Broad St",
    "sg:city":"Griffith",
    "sg:classifiers":[
        {
            "category":"Shopping",
            "type":"Retail Goods"
        }
    ],
    "sg:phone":"+1 219 924 9399",
    "sg:postcode":"46319",
    "sg:province":"IN",
    "sg:tags":[
        "merchandise"
    ],
    "wof:name":"Lynch Custom Shop",
    "wof:placetype":"venue"
},
  "geometry": {"coordinates":[-87.427588,41.52444],"type":"Point"}
}