{
  "type": "Feature",
  "properties": {
    "iso:country":"US",
    "sg:address":"10700 N 750 E",
    "sg:city":"Ossian",
    "sg:classifiers":[
        {
            "category":"Manufacturing",
            "subcategory":"Tools & Machinery",
            "type":"Manufacturing & Wholesale Goods"
        }
    ],
    "sg:phone":"+1 260 639 6541",
    "sg:postcode":"46777",
    "sg:province":"IN",
    "sg:tags":[
        "mold",
        "special"
    ],
    "wof:name":"Kamco Inc",
    "wof:placetype":"venue"
},
  "geometry": {"coordinates":[-85.083161,40.898995],"type":"Point"}
}