{
  "type": "Feature",
  "properties": {
    "iso:country":"US",
    "sg:address":"750 Drexel Pkwy",
    "sg:city":"Rensselaer",
    "sg:classifiers":[
        {
            "category":"Manufacturing",
            "subcategory":"Food",
            "type":"Manufacturing & Wholesale Goods"
        }
    ],
    "sg:phone":"+1 219 866 3020",
    "sg:postcode":"47978",
    "sg:province":"IN",
    "sg:tags":[
        "popcorn",
        "supply"
    ],
    "sg:website":"www.conagrafoods.com",
    "wof:name":"Con Agra Snack Foods",
    "wof:placetype":"venue"
},
  "geometry": {"coordinates":[-87.155343,40.922894],"type":"Point"}
}