{
  "type": "Feature",
  "properties": {
    "iso:country":"US",
    "sg:address":"8000 N Mt Tabor Rd",
    "sg:city":"Ellettsville",
    "sg:classifiers":[
        {
            "category":"Freight",
            "type":"Transportation"
        }
    ],
    "sg:phone":"+1 812 935 8988",
    "sg:postcode":"47429",
    "sg:province":"IN",
    "sg:tags":[
        "trucking"
    ],
    "wof:name":"Itd Transport Inc",
    "wof:placetype":"venue"
},
  "geometry": {"coordinates":[-86.623903,39.280004],"type":"Point"}
}