{
  "type": "Feature",
  "properties": {
    "iso:country":"US",
    "sg:address":"210 N Meridian St",
    "sg:city":"Portland",
    "sg:classifiers":[
        {
            "category":"Professional",
            "type":"Services"
        }
    ],
    "sg:phone":"+1 260 726 8805",
    "sg:postcode":"47371",
    "sg:province":"IN",
    "wof:name":"Myron Julie",
    "wof:placetype":"venue"
},
  "geometry": {"coordinates":[-84.977983,40.435253],"type":"Point"}
}