{
  "type": "Feature",
  "properties": {
    "iso:country":"US",
    "sg:address":"14 Lakeshore Dr",
    "sg:city":"Clarksville",
    "sg:classifiers":[
        {
            "category":"Retail",
            "subcategory":"Car Wash",
            "type":"Services"
        }
    ],
    "sg:phone":"+1 812 284 4394",
    "sg:postcode":"47129",
    "sg:province":"IN",
    "sg:tags":[
        "automobile",
        "detail",
        "clean"
    ],
    "wof:name":"Dusters Detail Cleaning",
    "wof:placetype":"venue"
},
  "geometry": {"coordinates":[-85.755564,38.28237],"type":"Point"}
}