{
  "type": "Feature",
  "properties": {
    "addr:full":"6418 E State Blvd Fort Wayne IN 46815",
    "addr:housenumber":"6418",
    "addr:postcode":"46815",
    "addr:street":"E State Blvd",
    "iso:country":"US",
    "sg:address":"6418 E State Blvd",
    "sg:city":"Fort Wayne",
    "sg:classifiers":[
        {
            "category":"Shopping",
            "subcategory":"Florist",
            "type":"Retail Goods"
        }
    ],
    "sg:phone":"+1 260 493 1581",
    "sg:postcode":"46815",
    "sg:province":"IN",
    "sg:website":"www.lopshire.com",
    "wof:name":"Lopshire Flowers Inc",
    "wof:placetype":"venue"
},
  "geometry": {"coordinates":[-85.059076,41.101168],"type":"Point"}
}