{
  "type": "Feature",
  "properties": {
    "iso:country":"US",
    "sg:address":"2715 Cassopolis St",
    "sg:city":"Elkhart",
    "sg:classifiers":[
        {
            "category":"Restaurant",
            "type":"Food & Drink"
        }
    ],
    "sg:menulink":"http://www.allmenus.com/in/osolo/167297-burger-king/menu/",
    "sg:phone":"+1 219 262 4898",
    "sg:postcode":"46514",
    "sg:province":"IN",
    "sg:tags":[
        "burger",
        "american"
    ],
    "wof:name":"Burger King",
    "wof:placetype":"venue"
},
  "geometry": {"coordinates":[-85.97294599999999,41.723104],"type":"Point"}
}