{
  "type": "Feature",
  "properties": {
    "iso:country":"US",
    "sg:address":"1420 Central Ave",
    "sg:city":"Columbus",
    "sg:classifiers":[
        {
            "category":"Autos & Motor Vehicles",
            "subcategory":"Automobile Sales",
            "type":"Retail Goods"
        }
    ],
    "sg:phone":"+1 812 376 6414",
    "sg:postcode":"47201",
    "sg:province":"IN",
    "sg:tags":[
        "car",
        "dealer"
    ],
    "wof:name":"Graham-Todd Motor Co Inc",
    "wof:placetype":"venue"
},
  "geometry": {"coordinates":[-85.904125,39.21274],"type":"Point"}
}