{
  "type": "Feature",
  "properties": {
    "addr:full":"11156 N Milhon West Dr Mooresville IN 46158",
    "addr:housenumber":"11156",
    "addr:postcode":"46158",
    "addr:street":"N Milhon West Dr",
    "iso:country":"US",
    "sg:address":"11156 N Milhon West Dr",
    "sg:city":"Mooresville",
    "sg:classifiers":[
        {
            "category":"Home & Garden",
            "subcategory":"Carpets & Floor Coverings",
            "type":"Retail Goods"
        }
    ],
    "sg:phone":"+1 317 996 4260",
    "sg:postcode":"46158",
    "sg:province":"IN",
    "wof:name":"Carpet Artist Installatio",
    "wof:placetype":"venue"
},
  "geometry": {"coordinates":[-86.43511599999999,39.587756],"type":"Point"}
}