{
  "type": "Feature",
  "properties": {
    "iso:country":"US",
    "sg:address":"210 N Front St",
    "sg:city":"Syracuse",
    "sg:classifiers":[
        {
            "category":"Building & Trades",
            "subcategory":"Cleaning & Sanitation",
            "type":"Services"
        }
    ],
    "sg:phone":"+1 574 457 3077",
    "sg:postcode":"46567",
    "sg:province":"IN",
    "wof:name":"Price's Mobile Powerwash",
    "wof:placetype":"venue"
},
  "geometry": {"coordinates":[-85.745307,41.424129],"type":"Point"}
}