{
  "type": "Feature",
  "properties": {
    "addr:full":"208 Lake Point Ln S Greenwood IN 46142",
    "addr:housenumber":"208",
    "addr:postcode":"46142",
    "addr:street":"Lake Point Ln S",
    "iso:country":"US",
    "sg:address":"208 Lake Point Ln S",
    "sg:city":"Greenwood",
    "sg:classifiers":[
        {
            "category":"Professional",
            "subcategory":"Business Services",
            "type":"Services"
        }
    ],
    "sg:phone":"+1 317 313 7666",
    "sg:postcode":"46142",
    "sg:province":"IN",
    "sg:tags":[
        "information",
        "technology",
        "specialist"
    ],
    "wof:name":"Citadel Consulting LLC",
    "wof:placetype":"venue"
},
  "geometry": {"coordinates":[-86.14981299999999,39.616439],"type":"Point"}
}