{
  "type": "Feature",
  "properties": {
    "iso:country":"US",
    "sg:address":"4293 S 50 W",
    "sg:city":"Albion",
    "sg:classifiers":[
        {
            "category":"Wholesale",
            "subcategory":"Farm Supplies",
            "type":"Manufacturing & Wholesale Goods"
        }
    ],
    "sg:phone":"+1 260 636 2945",
    "sg:postcode":"46701",
    "sg:province":"IN",
    "sg:tags":[
        "feed"
    ],
    "wof:name":"Diller's Merrian Feed Mill",
    "wof:placetype":"venue"
},
  "geometry": {"coordinates":[-85.433884,41.289983],"type":"Point"}
}