{
  "type": "Feature",
  "properties": {
    "addr:full":"1010 S Mc Gill St Knox IN 46534",
    "addr:housenumber":"1010",
    "addr:postcode":"46534",
    "addr:street":"S Mc Gill St",
    "iso:country":"US",
    "sg:address":"1010 S Mc Gill St",
    "sg:city":"Knox",
    "sg:classifiers":[
        {
            "category":"Building & Trades",
            "subcategory":"Construction",
            "type":"Services"
        }
    ],
    "sg:phone":"+1 574 772 6966",
    "sg:postcode":"46534",
    "sg:province":"IN",
    "sg:tags":[
        "insulation",
        "heat",
        "contractor"
    ],
    "wof:name":"Elvis Cole Construction",
    "wof:placetype":"venue"
},
  "geometry": {"coordinates":[-86.61593499999999,41.286708],"type":"Point"}
}