{
  "type": "Feature",
  "properties": {
    "iso:country":"US",
    "sg:address":"2090 Virginia St",
    "sg:city":"Gary",
    "sg:classifiers":[
        {
            "category":"Food & Beverages",
            "subcategory":"Liquor & Beverages",
            "type":"Retail Goods"
        }
    ],
    "sg:phone":"+1 219 882 9654",
    "sg:postcode":"46407",
    "sg:province":"IN",
    "wof:name":"Discount Liquors",
    "wof:placetype":"venue"
},
  "geometry": {"coordinates":[-87.32969,41.580656],"type":"Point"}
}