{
  "type": "Feature",
  "properties": {
    "iso:country":"US",
    "sg:address":"14331 E Jackson St",
    "sg:city":"Parker City",
    "sg:classifiers":[
        {
            "category":"Health Services",
            "subcategory":"Doctor",
            "type":"Services"
        }
    ],
    "sg:phone":"+1 765 468 6814",
    "sg:postcode":"47368",
    "sg:province":"IN",
    "sg:tags":[
        "dentist"
    ],
    "wof:name":"Terry W Davis DDS",
    "wof:placetype":"venue"
},
  "geometry": {"coordinates":[-85.218628,40.193006],"type":"Point"}
}