{
  "type": "Feature",
  "properties": {
    "iso:country":"US",
    "sg:address":"335 High St",
    "sg:city":"Winchester",
    "sg:classifiers":[
        {
            "category":"Social Services",
            "type":"Services"
        }
    ],
    "sg:phone":"+1 765 584 1856",
    "sg:postcode":"47394",
    "sg:province":"IN",
    "sg:tags":[
        "organization",
        "welfare"
    ],
    "wof:name":"Chapter 1 Parent Resource Ctr",
    "wof:placetype":"venue"
},
  "geometry": {"coordinates":[-84.977577,40.170149],"type":"Point"}
}