{
  "type": "Feature",
  "properties": {
    "addr:full":"116 W Main St Fort Wayne IN 46802",
    "addr:housenumber":"116",
    "addr:postcode":"46802",
    "addr:street":"W Main St",
    "iso:country":"US",
    "sg:address":"116 W Main St",
    "sg:city":"Fort Wayne",
    "sg:classifiers":[
        {
            "category":"Autos & Motor Vehicles",
            "subcategory":"Automobile Sales",
            "type":"Retail Goods"
        }
    ],
    "sg:phone":"+1 260 623 3679",
    "sg:postcode":"46802",
    "sg:province":"IN",
    "sg:tags":[
        "car",
        "dealer"
    ],
    "sg:website":"www.meyer.fivestardealers.com",
    "wof:name":"Meyer Auto Sales Inc",
    "wof:placetype":"venue"
},
  "geometry": {"coordinates":[-85.14046999999999,41.080318],"type":"Point"}
}