{
  "type": "Feature",
  "properties": {
    "iso:country":"US",
    "sg:address":"5524 N Co Rd 600 E",
    "sg:city":"Twelve Mile",
    "sg:classifiers":[
        {
            "category":"Personal",
            "subcategory":"Beauty Salon",
            "type":"Services"
        }
    ],
    "sg:phone":"+1 574 664 4664",
    "sg:postcode":"46988",
    "sg:province":"IN",
    "wof:name":"Images",
    "wof:placetype":"venue"
},
  "geometry": {"coordinates":[-86.260989,40.845431],"type":"Point"}
}