{
  "type": "Feature",
  "properties": {
    "addr:full":"440 N Morton St Franklin IN 46131",
    "addr:housenumber":"440",
    "addr:postcode":"46131",
    "addr:street":"N Morton St",
    "iso:country":"US",
    "sg:address":"440 N Morton St",
    "sg:city":"Franklin",
    "sg:classifiers":[
        {
            "category":"Restaurant",
            "type":"Food & Drink"
        }
    ],
    "sg:menulink":"http://www.allmenus.com/in/franklin/79403-pizza-hut/menu/",
    "sg:phone":"+1 317 738 5444",
    "sg:postcode":"46131",
    "sg:province":"IN",
    "sg:tags":[
        "american",
        "pizza"
    ],
    "wof:name":"Pizza Hut",
    "wof:placetype":"venue"
},
  "geometry": {"coordinates":[-86.06419099999999,39.485432],"type":"Point"}
}