{
  "type": "Feature",
  "properties": {
    "addr:full":"603 W Main St Mitchell IN 47446",
    "addr:housenumber":"603",
    "addr:postcode":"47446",
    "addr:street":"W Main St",
    "iso:country":"US",
    "sg:address":"603 W Main St",
    "sg:city":"Mitchell",
    "sg:classifiers":[
        {
            "category":"Shopping",
            "subcategory":"Florist",
            "type":"Retail Goods"
        }
    ],
    "sg:phone":"+1 812 849 9595",
    "sg:postcode":"47446",
    "sg:province":"IN",
    "wof:name":"Three Hearts Flower & Gift Shp",
    "wof:placetype":"venue"
},
  "geometry": {"coordinates":[-86.47230500000001,38.733149],"type":"Point"}
}