{
  "type": "Feature",
  "properties": {
    "iso:country":"US",
    "sg:address":"2201 N Grand Ave",
    "sg:city":"Connersville",
    "sg:classifiers":[
        {
            "category":"Health Services",
            "subcategory":"Medical Lab",
            "type":"Services"
        }
    ],
    "sg:phone":"+1 765 825 5944",
    "sg:postcode":"47331",
    "sg:province":"IN",
    "sg:tags":[
        "laboratory"
    ],
    "wof:name":"Don's Dental Lab",
    "wof:placetype":"venue"
},
  "geometry": {"coordinates":[-85.134782,39.662539],"type":"Point"}
}