{
  "type": "Feature",
  "properties": {
    "addr:full":"10295 State Rd 335 Pekin IN 47165",
    "addr:housenumber":"10295;335",
    "addr:postcode":"47165",
    "addr:street":"State Rd",
    "iso:country":"US",
    "sg:address":"10295 State Rd 335",
    "sg:city":"Pekin",
    "sg:classifiers":[
        {
            "category":"Home & Garden",
            "subcategory":"Household Appliances",
            "type":"Retail Goods"
        }
    ],
    "sg:phone":"+1 812 967 3997",
    "sg:postcode":"47165",
    "sg:province":"IN",
    "wof:name":"Billy Martin Store Inc",
    "wof:placetype":"venue"
},
  "geometry": {"coordinates":[-86.026014,38.443814],"type":"Point"}
}