{
  "type": "Feature",
  "properties": {
    "addr:full":"3950 Meadows Dr Indianapolis IN 46205",
    "addr:housenumber":"3950",
    "addr:postcode":"46205",
    "addr:street":"Meadows Dr",
    "iso:country":"US",
    "sg:address":"3950 Meadows Dr",
    "sg:city":"Indianapolis",
    "sg:classifiers":[
        {
            "category":"Banks & Credit Unions",
            "subcategory":"Bank",
            "type":"Services"
        }
    ],
    "sg:phone":"+1 317 266 6360",
    "sg:postcode":"46205",
    "sg:province":"IN",
    "wof:name":"Bank One",
    "wof:placetype":"venue"
},
  "geometry": {"coordinates":[-86.11204499999999,39.828528],"type":"Point"}
}