{
  "type": "Feature",
  "properties": {
    "addr:full":"4625 S State Rd 162 Huntingburg IN 47542",
    "addr:housenumber":"4625",
    "addr:postcode":"47542",
    "addr:street":"S State Rd 162",
    "iso:country":"US",
    "sg:address":"4625 S State Rd 162",
    "sg:city":"Huntingburg",
    "sg:classifiers":[
        {
            "category":"Shopping",
            "subcategory":"Hobbies, Toys, & Games",
            "type":"Retail Goods"
        }
    ],
    "sg:phone":"+1 812 482 2099",
    "sg:postcode":"47542",
    "sg:province":"IN",
    "sg:tags":[
        "doll"
    ],
    "wof:name":"Voo Doo Dolls",
    "wof:placetype":"venue"
},
  "geometry": {"coordinates":[-86.87215,38.310762],"type":"Point"}
}