{
  "type": "Feature",
  "properties": {
    "iso:country":"US",
    "sg:address":"444 Thurston Dr",
    "sg:city":"Noblesville",
    "sg:classifiers":[
        {
            "category":"Professional",
            "type":"Services"
        }
    ],
    "sg:phone":"+1 317 773 5286",
    "sg:postcode":"46060",
    "sg:province":"IN",
    "sg:tags":[
        "establishment"
    ],
    "wof:name":"Rivers Edge",
    "wof:placetype":"venue"
},
  "geometry": {"coordinates":[-85.968173,40.058141],"type":"Point"}
}