{
  "type": "Feature",
  "properties": {
    "addr:full":"305 Cherry St Westfield IN 46074",
    "addr:housenumber":"305",
    "addr:postcode":"46074",
    "addr:street":"Cherry St",
    "iso:country":"US",
    "sg:address":"305 Cherry St",
    "sg:city":"Westfield",
    "sg:classifiers":[
        {
            "category":"Building & Trades",
            "subcategory":"Construction",
            "type":"Services"
        }
    ],
    "sg:phone":"+1 317 867 3227",
    "sg:postcode":"46074",
    "sg:province":"IN",
    "sg:tags":[
        "concrete",
        "contractor"
    ],
    "wof:name":"Firm Foundation LLC",
    "wof:placetype":"venue"
},
  "geometry": {"coordinates":[-86.12502499999999,40.040235],"type":"Point"}
}