{
  "type": "Feature",
  "properties": {
    "iso:country":"US",
    "sg:address":"470 E Morse St",
    "sg:city":"Markle",
    "sg:classifiers":[
        {
            "category":"Organizations",
            "subcategory":"Religious Organization",
            "type":"Services"
        }
    ],
    "sg:phone":"+1 260 758 2920",
    "sg:postcode":"46770",
    "sg:province":"IN",
    "sg:tags":[
        "church"
    ],
    "wof:name":"Seventh-Day Adventist Church",
    "wof:placetype":"venue"
},
  "geometry": {"coordinates":[-85.332414,40.822304],"type":"Point"}
}