{
  "type": "Feature",
  "properties": {
    "iso:country":"US",
    "sg:address":"12833 S 1000 E",
    "sg:city":"Converse",
    "sg:classifiers":[
        {
            "category":"Manufacturing",
            "subcategory":"Tools & Machinery",
            "type":"Manufacturing & Wholesale Goods"
        }
    ],
    "sg:phone":"+1 765 395 7949",
    "sg:postcode":"46919",
    "sg:province":"IN",
    "sg:tags":[
        "machine",
        "shop"
    ],
    "wof:name":"Rencor Tool & Die Inc",
    "wof:placetype":"venue"
},
  "geometry": {"coordinates":[-85.88292199999999,40.582253],"type":"Point"}
}