{
  "type": "Feature",
  "properties": {
    "iso:country":"US",
    "sg:address":"1642 US Hwy 41",
    "sg:city":"Schererville",
    "sg:classifiers":[
        {
            "category":"Sports & Exercise",
            "subcategory":"Gym",
            "type":"Entertainment"
        }
    ],
    "sg:phone":"+1 219 322 2424",
    "sg:postcode":"46375",
    "sg:province":"IN",
    "sg:tags":[
        "club",
        "health",
        "studio",
        "gymnasium"
    ],
    "wof:name":"Cardinal Fitness",
    "wof:placetype":"venue"
},
  "geometry": {"coordinates":[-87.470988,41.49391],"type":"Point"}
}