{
  "type": "Feature",
  "properties": {
    "iso:country":"US",
    "sg:address":"712 Industries Rd",
    "sg:city":"Richmond",
    "sg:classifiers":[
        {
            "category":"Building & Trades",
            "subcategory":"Construction",
            "type":"Services"
        }
    ],
    "sg:phone":"+1 765 939 2287",
    "sg:postcode":"47374",
    "sg:province":"IN",
    "sg:tags":[
        "excavating",
        "contractor"
    ],
    "wof:name":"Buckley Excavating",
    "wof:placetype":"venue"
},
  "geometry": {"coordinates":[-84.910434,39.86253],"type":"Point"}
}