{
  "type": "Feature",
  "properties": {
    "iso:country":"US",
    "sg:address":"715 S 22nd St",
    "sg:city":"Elwood",
    "sg:classifiers":[
        {
            "category":"Shopping",
            "subcategory":"Computers & Home Electronics",
            "type":"Retail Goods"
        }
    ],
    "sg:phone":"+1 765 552 7250",
    "sg:postcode":"46036",
    "sg:province":"IN",
    "sg:tags":[
        "equipment",
        "electronic",
        "supply"
    ],
    "wof:name":"Loy's Custom Audio Video",
    "wof:placetype":"venue"
},
  "geometry": {"coordinates":[-85.832397,40.271463],"type":"Point"}
}