{
  "type": "Feature",
  "properties": {
    "iso:country":"US",
    "sg:address":"7680 E 500 N",
    "sg:city":"Wilkinson",
    "sg:classifiers":[
        {
            "category":"Retail",
            "subcategory":"Repair Shop",
            "type":"Services"
        }
    ],
    "sg:phone":"+1 317 462 4637",
    "sg:postcode":"46186",
    "sg:province":"IN",
    "sg:tags":[
        "appliance"
    ],
    "wof:name":"Rockey's Appliance Svc",
    "wof:placetype":"venue"
},
  "geometry": {"coordinates":[-85.664654,39.858993],"type":"Point"}
}