{
  "type": "Feature",
  "properties": {
    "iso:country":"US",
    "sg:address":"1419 Country Club Rd",
    "sg:city":"Indianapolis",
    "sg:classifiers":[
        {
            "category":"Retail",
            "subcategory":"Repair Shop",
            "type":"Services"
        }
    ],
    "sg:phone":"+1 317 273 9353",
    "sg:postcode":"46234",
    "sg:province":"IN",
    "sg:tags":[
        "welding"
    ],
    "wof:name":"Dynamite Welding",
    "wof:placetype":"venue"
},
  "geometry": {"coordinates":[-86.307477,39.78582],"type":"Point"}
}