{
  "type": "Feature",
  "properties": {
    "iso:country":"US",
    "sg:address":"4201 Washington St",
    "sg:city":"Gary",
    "sg:classifiers":[
        {
            "category":"Organizations",
            "subcategory":"Religious Organization",
            "type":"Services"
        }
    ],
    "sg:phone":"+1 219 884 1837",
    "sg:postcode":"46408",
    "sg:province":"IN",
    "sg:tags":[
        "church"
    ],
    "wof:name":"Christ Temple Church Of Christ",
    "wof:placetype":"venue"
},
  "geometry": {"coordinates":[-87.337508,41.540389],"type":"Point"}
}