{
  "type": "Feature",
  "properties": {
    "iso:country":"US",
    "sg:address":"5955 Central Ave",
    "sg:city":"Portage",
    "sg:classifiers":[
        {
            "category":"Insurance",
            "subcategory":"Insurance Agent",
            "type":"Services"
        }
    ],
    "sg:phone":"+1 219 764 3560",
    "sg:postcode":"46368",
    "sg:province":"IN",
    "wof:name":"Paul Marsh Agency",
    "wof:placetype":"venue"
},
  "geometry": {"coordinates":[-87.186074,41.575752],"type":"Point"}
}