{
  "type": "Feature",
  "properties": {
    "addr:full":"945 W Lake St Topeka IN 46571",
    "addr:housenumber":"945",
    "addr:postcode":"46571",
    "addr:street":"W Lake St",
    "iso:country":"US",
    "sg:address":"945 W Lake St",
    "sg:city":"Topeka",
    "sg:classifiers":[
        {
            "category":"Retail",
            "subcategory":"Repair Shop",
            "type":"Services"
        }
    ],
    "sg:phone":"+1 260 593 2181",
    "sg:postcode":"46571",
    "sg:province":"IN",
    "sg:tags":[
        "sharpening"
    ],
    "wof:name":"O K Saw & Tool",
    "wof:placetype":"venue"
},
  "geometry": {"coordinates":[-85.54495300000001,41.539255],"type":"Point"}
}