{
  "type": "Feature",
  "properties": {
    "iso:country":"US",
    "sg:address":"922 Massachusetts Ave",
    "sg:city":"Indianapolis",
    "sg:classifiers":[
        {
            "category":"Shopping",
            "subcategory":"Used Merchandise",
            "type":"Retail Goods"
        }
    ],
    "sg:phone":"+1 317 687 8768",
    "sg:postcode":"46204",
    "sg:province":"IN",
    "sg:tags":[
        "flea",
        "market"
    ],
    "wof:name":"Teapots N Treasures",
    "wof:placetype":"venue"
},
  "geometry": {"coordinates":[-86.142295,39.77976],"type":"Point"}
}