{
  "type": "Feature",
  "properties": {
    "addr:full":"1728 S Riverview Rd Peru IN 46970",
    "addr:housenumber":"1728",
    "addr:postcode":"46970",
    "addr:street":"S Riverview Rd",
    "iso:country":"US",
    "sg:address":"1728 S Riverview Rd",
    "sg:city":"Peru",
    "sg:phone":"+1 765 473 7739",
    "sg:postcode":"46970",
    "sg:province":"IN",
    "sg:tags":[
        "farm",
        "corn",
        "soybean"
    ],
    "wof:name":"William L McMinn",
    "wof:placetype":"venue"
},
  "geometry": {"coordinates":[-86.122911,40.741502],"type":"Point"}
}