{
  "type": "Feature",
  "properties": {
    "iso:country":"US",
    "sg:address":"3047 Grandma Barnes Rd",
    "sg:city":"Nashville",
    "sg:classifiers":[
        {
            "category":"Manufacturing",
            "subcategory":"Tools & Machinery",
            "type":"Manufacturing & Wholesale Goods"
        }
    ],
    "sg:phone":"+1 812 988 7649",
    "sg:postcode":"47448",
    "sg:province":"IN",
    "sg:tags":[
        "machine",
        "shop"
    ],
    "wof:name":"Orbit Machine & Tool",
    "wof:placetype":"venue"
},
  "geometry": {"coordinates":[-86.262167,39.239476],"type":"Point"}
}