{
  "type": "Feature",
  "properties": {
    "addr:full":"2802 E State Blvd Fort Wayne IN 46805",
    "addr:housenumber":"2802",
    "addr:postcode":"46805",
    "addr:street":"E State Blvd",
    "iso:country":"US",
    "sg:address":"2802 E State Blvd",
    "sg:city":"Fort Wayne",
    "sg:classifiers":[
        {
            "category":"Shopping",
            "subcategory":"Pharmacy",
            "type":"Retail Goods"
        }
    ],
    "sg:phone":"+1 260 471 7641",
    "sg:postcode":"46805",
    "sg:province":"IN",
    "wof:name":"CVS Pharmacy",
    "wof:placetype":"venue"
},
  "geometry": {"coordinates":[-85.102163,41.097166],"type":"Point"}
}