{
  "type": "Feature",
  "properties": {
    "iso:country":"US",
    "sg:address":"779 N 100 W",
    "sg:city":"Fowler",
    "sg:classifiers":[
        {
            "category":"Wholesale",
            "subcategory":"Machinery & Supplies",
            "type":"Manufacturing & Wholesale Goods"
        }
    ],
    "sg:phone":"+1 765 884 8935",
    "sg:postcode":"47944",
    "sg:province":"IN",
    "sg:tags":[
        "farm",
        "equipment"
    ],
    "sg:website":"www.turnersequipment.com",
    "wof:name":"Turner's Equipment",
    "wof:placetype":"venue"
},
  "geometry": {"coordinates":[-87.342493,40.616565],"type":"Point"}
}