{
  "type": "Feature",
  "properties": {
    "addr:full":"6445 Kennedy Ave Hammond IN 46323",
    "addr:housenumber":"6445",
    "addr:postcode":"46323",
    "addr:street":"Kennedy Ave",
    "iso:country":"US",
    "sg:address":"6445 Kennedy Ave",
    "sg:city":"Hammond",
    "sg:classifiers":[
        {
            "category":"Professional",
            "subcategory":"Accounting & Tax Preparation",
            "type":"Services"
        }
    ],
    "sg:phone":"+1 219 844 3434",
    "sg:postcode":"46323",
    "sg:province":"IN",
    "sg:tags":[
        "accountant"
    ],
    "wof:name":"Robert S Zurad CPA",
    "wof:placetype":"venue"
},
  "geometry": {"coordinates":[-87.46154,41.595798],"type":"Point"}
}