{
  "type": "Feature",
  "properties": {
    "addr:full":"405 NE 3rd St Washington IN 47501",
    "addr:housenumber":"405",
    "addr:postcode":"in 47501",
    "addr:street":"Ne 3Rd St",
    "iso:country":"US",
    "sg:address":"405 NE 3rd St",
    "sg:city":"Washington",
    "sg:classifiers":[
        {
            "category":"Social Services",
            "type":"Services"
        }
    ],
    "sg:phone":"+1 812 254 4481",
    "sg:postcode":"47501",
    "sg:province":"IN",
    "sg:tags":[
        "organization",
        "welfare"
    ],
    "sg:website":"www.dcymca.org",
    "wof:name":"YMCA",
    "wof:placetype":"venue"
},
  "geometry": {"coordinates":[-87.172442,38.661288],"type":"Point"}
}