{
  "type": "Feature",
  "properties": {
    "addr:full":"2501 E Business 30 Columbia City IN 46725",
    "addr:housenumber":"2501;30",
    "addr:postcode":"46725",
    "addr:street":"E Business",
    "iso:country":"US",
    "sg:address":"2501 E Business 30",
    "sg:city":"Columbia City",
    "sg:classifiers":[
        {
            "category":"Social Services",
            "subcategory":"Child Care",
            "type":"Services"
        }
    ],
    "sg:phone":"+1 260 244 3874",
    "sg:postcode":"46725",
    "sg:province":"IN",
    "sg:tags":[
        "day"
    ],
    "wof:name":"Marcia Leininger",
    "wof:placetype":"venue"
},
  "geometry": {"coordinates":[-85.440056,41.140116],"type":"Point"}
}