{
  "type": "Feature",
  "properties": {
    "iso:country":"US",
    "sg:address":"4433 Broadway",
    "sg:city":"Gary",
    "sg:classifiers":[
        {
            "category":"Social Services",
            "type":"Services"
        }
    ],
    "sg:phone":"+1 219 980 4636",
    "sg:postcode":"46409",
    "sg:province":"IN",
    "sg:tags":[
        "organization",
        "welfare"
    ],
    "wof:name":"International Institute",
    "wof:placetype":"venue"
},
  "geometry": {"coordinates":[-87.3362,41.537343],"type":"Point"}
}