{
  "type": "Feature",
  "properties": {
    "iso:country":"US",
    "sg:address":"14141 Esprit Dr",
    "sg:city":"Westfield",
    "sg:classifiers":[
        {
            "category":"Building & Trades",
            "subcategory":"Construction",
            "type":"Services"
        }
    ],
    "sg:phone":"+1 317 571 9860",
    "sg:postcode":"46074",
    "sg:province":"IN",
    "sg:tags":[
        "home",
        "builder"
    ],
    "wof:name":"Pulte Homes Corp",
    "wof:placetype":"venue"
},
  "geometry": {"coordinates":[-86.185089,39.992187],"type":"Point"}
}