{
  "type": "Feature",
  "properties": {
    "iso:country":"US",
    "sg:address":"801 Chestnut St",
    "sg:city":"Evansville",
    "sg:classifiers":[
        {
            "category":"Restaurant",
            "type":"Food & Drink"
        }
    ],
    "sg:phone":"+1 812 435 8258",
    "sg:postcode":"47713",
    "sg:province":"IN",
    "sg:tags":[
        "retail",
        "eating",
        "direct",
        "sales"
    ],
    "wof:name":"Evsc Food Service",
    "wof:placetype":"venue"
},
  "geometry": {"coordinates":[-87.563664,37.971786],"type":"Point"}
}