{
  "type": "Feature",
  "properties": {
    "addr:full":"2530 S 300 W Tipton IN 46072",
    "addr:housenumber":"2530;300",
    "addr:postcode":"46072",
    "addr:street":"S;W Tipton",
    "iso:country":"US",
    "sg:address":"2530 S 300 W",
    "sg:city":"Tipton",
    "sg:classifiers":[
        {
            "category":"Farming",
            "subcategory":"Farm",
            "type":"Manufacturing & Wholesale Goods"
        }
    ],
    "sg:phone":"+1 765 675 6394",
    "sg:postcode":"46072",
    "sg:province":"IN",
    "sg:tags":[
        "crop",
        "general"
    ],
    "wof:name":"Earl Sottong",
    "wof:placetype":"venue"
},
  "geometry": {"coordinates":[-86.069149,40.267905],"type":"Point"}
}