{
  "type": "Feature",
  "properties": {
    "iso:country":"US",
    "sg:address":"6910 N Main St",
    "sg:city":"Granger",
    "sg:classifiers":[
        {
            "category":"Professional",
            "subcategory":"Accounting & Tax Preparation",
            "type":"Services"
        }
    ],
    "sg:phone":"+1 574 277 8700",
    "sg:postcode":"46530",
    "sg:province":"IN",
    "sg:tags":[
        "return"
    ],
    "wof:name":"Buczynski Tim C P A and Conslt",
    "wof:placetype":"venue"
},
  "geometry": {"coordinates":[-86.17803,41.722915],"type":"Point"}
}