{
  "type": "Feature",
  "properties": {
    "iso:country":"US",
    "sg:address":"7147 W Co Rd 100 N",
    "sg:city":"West Baden Springs",
    "sg:classifiers":[
        {
            "category":"Farming",
            "subcategory":"Livestock Farm",
            "type":"Manufacturing & Wholesale Goods"
        }
    ],
    "sg:phone":"+1 812 936 2270",
    "sg:postcode":"47469",
    "sg:province":"IN",
    "sg:tags":[
        "beef",
        "feedlot",
        "cattle"
    ],
    "wof:name":"Walter Freeman",
    "wof:placetype":"venue"
},
  "geometry": {"coordinates":[-86.57656,38.570729],"type":"Point"}
}