{
  "type": "Feature",
  "properties": {
    "iso:country":"US",
    "sg:address":"1315 Misty River Dr",
    "sg:city":"Fort Wayne",
    "sg:classifiers":[
        {
            "category":"Professional",
            "subcategory":"Business Services",
            "type":"Services"
        }
    ],
    "sg:phone":"+1 260 459 2726",
    "sg:postcode":"46808",
    "sg:province":"IN",
    "wof:name":"Indiana Home Inspections Inc",
    "wof:placetype":"venue"
},
  "geometry": {"coordinates":[-85.188148,41.085628],"type":"Point"}
}