{
  "type": "Feature",
  "properties": {
    "iso:country":"US",
    "sg:address":"502 Grant Ave",
    "sg:city":"Chesterton",
    "sg:classifiers":[
        {
            "category":"Professional",
            "subcategory":"Management & Consulting",
            "type":"Services"
        }
    ],
    "sg:phone":"+1 219 983 1224",
    "sg:postcode":"46304",
    "sg:province":"IN",
    "sg:tags":[
        "marketing",
        "consultant"
    ],
    "wof:name":"Corporate Image",
    "wof:placetype":"venue"
},
  "geometry": {"coordinates":[-87.06048,41.612687],"type":"Point"}
}