{
  "type": "Feature",
  "properties": {
    "iso:country":"US",
    "sg:address":"6708 N Co Rd 700 E",
    "sg:city":"Clarksburg",
    "sg:classifiers":[
        {
            "category":"Organizations",
            "subcategory":"Religious Organization",
            "type":"Services"
        }
    ],
    "sg:phone":"+1 812 527 2845",
    "sg:postcode":"47246",
    "sg:province":"IN",
    "sg:tags":[
        "clergy"
    ],
    "wof:name":"Clarksburg Christian Church",
    "wof:placetype":"venue"
},
  "geometry": {"coordinates":[-85.780994,39.270363],"type":"Point"}
}