{
  "type": "Feature",
  "properties": {
    "addr:full":"220 N Elm St Corydon IN 47112",
    "addr:housenumber":"220",
    "addr:postcode":"47112",
    "addr:street":"N Elm St",
    "iso:country":"US",
    "sg:address":"220 N Elm St",
    "sg:city":"Corydon",
    "sg:classifiers":[
        {
            "category":"Shopping",
            "subcategory":"Musical Instruments",
            "type":"Retail Goods"
        }
    ],
    "sg:phone":"+1 812 738 2111",
    "sg:postcode":"47112",
    "sg:province":"IN",
    "wof:name":"Conrad Music",
    "wof:placetype":"venue"
},
  "geometry": {"coordinates":[-86.12531300000001,38.21161],"type":"Point"}
}