{
  "type": "Feature",
  "properties": {
    "addr:full":"15 S Boeke Rd Evansville IN 47714",
    "addr:housenumber":"15",
    "addr:postcode":"47714",
    "addr:street":"S Boeke Rd",
    "iso:country":"US",
    "sg:address":"15 S Boeke Rd",
    "sg:city":"Evansville",
    "sg:classifiers":[
        {
            "category":"Arts & Performance",
            "subcategory":"Theater",
            "type":"Entertainment"
        }
    ],
    "sg:phone":"+1 812 473 8915",
    "sg:postcode":"47714",
    "sg:province":"IN",
    "sg:tags":[
        "entertainer",
        "business"
    ],
    "wof:name":"Mad Science Of Evansville",
    "wof:placetype":"venue"
},
  "geometry": {"coordinates":[-87.52023199999999,37.976642],"type":"Point"}
}