{
  "type": "Feature",
  "properties": {
    "iso:country":"US",
    "sg:address":"3721 S 700 W",
    "sg:city":"Mentone",
    "sg:classifiers":[
        {
            "category":"Freight",
            "type":"Transportation"
        }
    ],
    "sg:phone":"+1 574 491 4408",
    "sg:postcode":"46539",
    "sg:province":"IN",
    "sg:tags":[
        "trucking"
    ],
    "wof:name":"Yates Trucking Inc",
    "wof:placetype":"venue"
},
  "geometry": {"coordinates":[-85.97573,41.174067],"type":"Point"}
}