{
  "type": "Feature",
  "properties": {
    "iso:country":"US",
    "sg:address":"7183 S 100 E",
    "sg:city":"Portland",
    "sg:phone":"+1 260 726 6747",
    "sg:postcode":"47371",
    "sg:province":"IN",
    "sg:tags":[
        "farm",
        "corn",
        "soybean"
    ],
    "wof:name":"Lyons Family Farm",
    "wof:placetype":"venue"
},
  "geometry": {"coordinates":[-84.95815399999999,40.335879],"type":"Point"}
}