{
  "type": "Feature",
  "properties": {
    "iso:country":"US",
    "sg:address":"1522 SE Riverside Dr",
    "sg:city":"Evansville",
    "sg:classifiers":[
        {
            "category":"Social Services",
            "type":"Services"
        }
    ],
    "sg:phone":"+1 812 434 2956",
    "sg:postcode":"47713",
    "sg:province":"IN",
    "sg:tags":[
        "agency",
        "adoption"
    ],
    "sg:website":"www.villages.org",
    "wof:name":"Villages",
    "wof:placetype":"venue"
},
  "geometry": {"coordinates":[-87.565486,37.956514],"type":"Point"}
}