{
  "type": "Feature",
  "properties": {
    "iso:country":"US",
    "sg:address":"1139 E 4th St",
    "sg:city":"Mishawaka",
    "sg:classifiers":[
        {
            "category":"Organizations",
            "subcategory":"Religious Organization",
            "type":"Services"
        }
    ],
    "sg:phone":"+1 574 256 0713",
    "sg:postcode":"46544",
    "sg:province":"IN",
    "wof:name":"Wesley Helfenbein",
    "wof:placetype":"venue"
},
  "geometry": {"coordinates":[-86.161785,41.659903],"type":"Point"}
}