{
  "type": "Feature",
  "properties": {
    "iso:country":"US",
    "sg:address":"122 E Market St",
    "sg:city":"Wolcott",
    "sg:classifiers":[
        {
            "category":"Retail",
            "subcategory":"Auto Repair",
            "type":"Services"
        }
    ],
    "sg:phone":"+1 219 279 2124",
    "sg:postcode":"47995",
    "sg:province":"IN",
    "sg:tags":[
        "repairing",
        "automobile"
    ],
    "wof:name":"Rex's Auto Svc",
    "wof:placetype":"venue"
},
  "geometry": {"coordinates":[-87.041315,40.758585],"type":"Point"}
}