{
  "type": "Feature",
  "properties": {
    "addr:full":"1033 E Mount Pleasant Rd Evansville IN 47725",
    "addr:housenumber":"1033",
    "addr:postcode":"47725",
    "addr:street":"E Mount Pleasant Rd",
    "iso:country":"US",
    "sg:address":"1033 E Mount Pleasant Rd",
    "sg:city":"Evansville",
    "sg:classifiers":[
        {
            "category":"Professional",
            "type":"Services"
        }
    ],
    "sg:phone":"+1 812 867 0047",
    "sg:postcode":"47725",
    "sg:province":"IN",
    "wof:name":"Americoal Services Inc",
    "wof:placetype":"venue"
},
  "geometry": {"coordinates":[-87.550043,38.057737],"type":"Point"}
}