{
  "type": "Feature",
  "properties": {
    "addr:full":"113 W 6th St Ferdinand IN 47532",
    "addr:housenumber":"113",
    "addr:postcode":"47532",
    "addr:street":"W 6Th St Ferdinand In",
    "iso:country":"US",
    "sg:address":"113 W 6th St",
    "sg:city":"Ferdinand",
    "sg:classifiers":[
        {
            "category":"Manufacturing",
            "subcategory":"Printing",
            "type":"Manufacturing & Wholesale Goods"
        }
    ],
    "sg:phone":"+1 812 367 2041",
    "sg:postcode":"47532",
    "sg:province":"IN",
    "sg:tags":[
        "newspaper"
    ],
    "wof:name":"Ferdinand News",
    "wof:placetype":"venue"
},
  "geometry": {"coordinates":[-86.86364399999999,38.221477],"type":"Point"}
}