{
  "type": "Feature",
  "properties": {
    "iso:country":"US",
    "sg:address":"2605 S Main St",
    "sg:city":"South Bend",
    "sg:classifiers":[
        {
            "category":"Organizations",
            "subcategory":"Labor Organization",
            "type":"Services"
        }
    ],
    "sg:phone":"+1 574 287 8728",
    "sg:postcode":"46614",
    "sg:province":"IN",
    "wof:name":"Sheet Metal Workers Joint",
    "wof:placetype":"venue"
},
  "geometry": {"coordinates":[-86.251335,41.646605],"type":"Point"}
}