{
  "type": "Feature",
  "properties": {
    "iso:country":"US",
    "sg:address":"8721 Shetland Ln",
    "sg:city":"Indianapolis",
    "sg:classifiers":[
        {
            "category":"Building & Trades",
            "subcategory":"Construction",
            "type":"Services"
        }
    ],
    "sg:phone":"+1 317 291 1659",
    "sg:postcode":"46278",
    "sg:province":"IN",
    "sg:tags":[
        "general",
        "contractor"
    ],
    "wof:name":"Design Construction Management",
    "wof:placetype":"venue"
},
  "geometry": {"coordinates":[-86.32234699999999,39.912352],"type":"Point"}
}