{
  "type": "Feature",
  "properties": {
    "iso:country":"US",
    "sg:address":"3602 Northgate Ct",
    "sg:city":"New Albany",
    "sg:classifiers":[
        {
            "category":"Building & Trades",
            "subcategory":"Equipment Rental",
            "type":"Services"
        }
    ],
    "sg:phone":"+1 812 949 2200",
    "sg:postcode":"47150",
    "sg:province":"IN",
    "sg:tags":[
        "leasing"
    ],
    "wof:name":"Develco Properties",
    "wof:placetype":"venue"
},
  "geometry": {"coordinates":[-85.81619600000001,38.332007],"type":"Point"}
}