{
  "type": "Feature",
  "properties": {
    "iso:country":"US",
    "sg:address":"106 Lincoln Way E",
    "sg:city":"Mishawaka",
    "sg:classifiers":[
        {
            "category":"Social Services",
            "type":"Services"
        }
    ],
    "sg:phone":"+1 574 259 5207",
    "sg:postcode":"46544",
    "sg:province":"IN",
    "sg:tags":[
        "organization",
        "welfare"
    ],
    "wof:name":"Special Olympics-St Joseph Co",
    "wof:placetype":"venue"
},
  "geometry": {"coordinates":[-86.17933,41.661185],"type":"Point"}
}