{
  "type": "Feature",
  "properties": {
    "addr:full":"2301 W Michigan St Evansville IN 47712",
    "addr:housenumber":"2301",
    "addr:postcode":"47712",
    "addr:street":"W Michigan St",
    "iso:country":"US",
    "sg:address":"2301 W Michigan St",
    "sg:city":"Evansville",
    "sg:classifiers":[
        {
            "category":"Social Services",
            "type":"Services"
        }
    ],
    "sg:phone":"+1 812 484 0782",
    "sg:postcode":"47712",
    "sg:province":"IN",
    "sg:tags":[
        "counselor",
        "marriage",
        "family"
    ],
    "wof:name":"Gibault Counseling Inc",
    "wof:placetype":"venue"
},
  "geometry": {"coordinates":[-87.600532,37.981528],"type":"Point"}
}