{
  "type": "Feature",
  "properties": {
    "iso:country":"US",
    "sg:address":"418 Mulberry St",
    "sg:city":"Madison",
    "sg:classifiers":[
        {
            "category":"Personal",
            "subcategory":"Beauty Salon",
            "type":"Services"
        }
    ],
    "sg:phone":"+1 812 265 6915",
    "sg:postcode":"47250",
    "sg:province":"IN",
    "wof:name":"Body Works",
    "wof:placetype":"venue"
},
  "geometry": {"coordinates":[-85.378715,38.73662],"type":"Point"}
}