{
  "type": "Feature",
  "properties": {
    "iso:country":"US",
    "sg:address":"1444 W 18th St",
    "sg:city":"Rochester",
    "sg:classifiers":[
        {
            "category":"Shopping",
            "subcategory":"Used Merchandise",
            "type":"Retail Goods"
        }
    ],
    "sg:phone":"+1 574 224 2200",
    "sg:postcode":"46975",
    "sg:province":"IN",
    "sg:tags":[
        "antique"
    ],
    "wof:name":"A & S Penny Pinchers Inc",
    "wof:placetype":"venue"
},
  "geometry": {"coordinates":[-86.23528,41.054255],"type":"Point"}
}