{
  "type": "Feature",
  "properties": {
    "iso:country":"US",
    "sg:address":"308 W Ridge Rd",
    "sg:city":"Gary",
    "sg:classifiers":[
        {
            "category":"Banks & Credit Unions",
            "subcategory":"Bank",
            "type":"Services"
        }
    ],
    "sg:phone":"+1 219 981 9600",
    "sg:postcode":"46408",
    "sg:province":"IN",
    "sg:tags":[
        "loan",
        "real estate"
    ],
    "wof:name":"A & W Investment LTD",
    "wof:placetype":"venue"
},
  "geometry": {"coordinates":[-87.341242,41.549491],"type":"Point"}
}