{
  "type": "Feature",
  "properties": {
    "iso:country":"US",
    "sg:address":"5525 S Meridian St",
    "sg:city":"Indianapolis",
    "sg:classifiers":[
        {
            "category":"Shopping",
            "type":"Retail Goods"
        }
    ],
    "sg:phone":"+1 317 783 2721",
    "sg:postcode":"46217",
    "sg:province":"IN",
    "sg:tags":[
        "wedding",
        "supply"
    ],
    "wof:name":"Clark's Petals",
    "wof:placetype":"venue"
},
  "geometry": {"coordinates":[-86.15846000000001,39.684199],"type":"Point"}
}