{
  "type": "Feature",
  "properties": {
    "iso:country":"US",
    "sg:address":"1 Lupine Ln",
    "sg:city":"Chesterton",
    "sg:classifiers":[
        {
            "category":"Professional",
            "subcategory":"Management & Consulting",
            "type":"Services"
        }
    ],
    "sg:phone":"+1 219 787 8263",
    "sg:postcode":"46304",
    "sg:province":"IN",
    "sg:tags":[
        "business"
    ],
    "wof:name":"Rob Carstens",
    "wof:placetype":"venue"
},
  "geometry": {"coordinates":[-86.987032,41.664639],"type":"Point"}
}