{
  "type": "Feature",
  "properties": {
    "iso:country":"US",
    "sg:address":"3123 E Thompson Rd",
    "sg:city":"Indianapolis",
    "sg:classifiers":[
        {
            "category":"Retail",
            "subcategory":"Portrait Studio",
            "type":"Services"
        }
    ],
    "sg:phone":"+1 317 791 0510",
    "sg:postcode":"46227",
    "sg:province":"IN",
    "sg:tags":[
        "photographer"
    ],
    "wof:name":"Conley Photography",
    "wof:placetype":"venue"
},
  "geometry": {"coordinates":[-86.111108,39.693943],"type":"Point"}
}