{
  "type": "Feature",
  "properties": {
    "iso:country":"US",
    "sg:address":"14527 State Rd 350",
    "sg:city":"Moores Hill",
    "sg:classifiers":[
        {
            "category":"Retail",
            "subcategory":"Auto Repair",
            "type":"Services"
        }
    ],
    "sg:phone":"+1 812 744 3088",
    "sg:postcode":"47032",
    "sg:province":"IN",
    "sg:tags":[
        "body",
        "automobile",
        "painting"
    ],
    "wof:name":"Berry's Body Shop",
    "wof:placetype":"venue"
},
  "geometry": {"coordinates":[-85.08858600000001,39.119888],"type":"Point"}
}