{
  "type": "Feature",
  "properties": {
    "addr:full":"5609 Ensenada Ave Indianapolis IN 46237",
    "addr:housenumber":"5609",
    "addr:postcode":"46237",
    "addr:street":"Ensenada Ave",
    "iso:country":"US",
    "sg:address":"5609 Ensenada Ave",
    "sg:city":"Indianapolis",
    "sg:classifiers":[
        {
            "category":"Professional",
            "subcategory":"Business Services",
            "type":"Services"
        }
    ],
    "sg:phone":"+1 317 782 9948",
    "sg:postcode":"46237",
    "sg:province":"IN",
    "sg:tags":[
        "motion",
        "production"
    ],
    "wof:name":"Rappers Resource",
    "wof:placetype":"venue"
},
  "geometry": {"coordinates":[-86.07157599999999,39.694228],"type":"Point"}
}