{
  "type": "Feature",
  "properties": {
    "addr:full":"6732 E State Blvd Fort Wayne IN 46815",
    "addr:housenumber":"6732",
    "addr:postcode":"46815",
    "addr:street":"E State Blvd",
    "iso:country":"US",
    "sg:address":"6732 E State Blvd",
    "sg:city":"Fort Wayne",
    "sg:classifiers":[
        {
            "category":"Professional",
            "subcategory":"Advertising",
            "type":"Services"
        }
    ],
    "sg:phone":"+1 260 749 0369",
    "sg:postcode":"46815",
    "sg:province":"IN",
    "sg:tags":[
        "mailing",
        "shipping"
    ],
    "wof:name":"UPS Store",
    "wof:placetype":"venue"
},
  "geometry": {"coordinates":[-85.054862,41.103767],"type":"Point"}
}