{
  "type": "Feature",
  "properties": {
    "iso:country":"US",
    "sg:address":"1202 N Hoosier Blvd",
    "sg:city":"Peru",
    "sg:classifiers":[
        {
            "category":"Professional",
            "type":"Services"
        }
    ],
    "sg:phone":"+1 765 689 8533",
    "sg:postcode":"46970",
    "sg:province":"IN",
    "sg:tags":[
        "establishment"
    ],
    "wof:name":"North Central Indiana Law",
    "wof:placetype":"venue"
},
  "geometry": {"coordinates":[-86.143478,40.663174],"type":"Point"}
}