{
  "type": "Feature",
  "properties": {
    "iso:country":"US",
    "sg:address":"901 E Troy Ave",
    "sg:city":"Indianapolis",
    "sg:classifiers":[
        {
            "category":"Manufacturing",
            "subcategory":"Glass & Minerals",
            "type":"Manufacturing & Wholesale Goods"
        }
    ],
    "sg:phone":"+1 317 787 3201",
    "sg:postcode":"46203",
    "sg:province":"IN",
    "sg:tags":[
        "concrete",
        "brick"
    ],
    "sg:website":"www.schusters.com",
    "wof:name":"Schuster's Building Products",
    "wof:placetype":"venue"
},
  "geometry": {"coordinates":[-86.141939,39.722691],"type":"Point"}
}