{
  "type": "Feature",
  "properties": {
    "iso:country":"US",
    "sg:address":"2045 W Packard Ave",
    "sg:city":"Fort Wayne",
    "sg:classifiers":[
        {
            "category":"Building & Trades",
            "subcategory":"Construction",
            "type":"Services"
        }
    ],
    "sg:phone":"+1 260 478 1360",
    "sg:postcode":"46809",
    "sg:province":"IN",
    "sg:tags":[
        "hanging",
        "contractor"
    ],
    "wof:name":"Allspray Painting Inc",
    "wof:placetype":"venue"
},
  "geometry": {"coordinates":[-85.166718,41.054619],"type":"Point"}
}