{
  "type": "Feature",
  "properties": {
    "iso:country":"US",
    "sg:address":"1611 US Hwy 231 S",
    "sg:city":"Crawfordsville",
    "sg:classifiers":[
        {
            "category":"Shopping",
            "type":"Retail Goods"
        }
    ],
    "sg:phone":"+1 765 362 7226",
    "sg:postcode":"47933",
    "sg:province":"IN",
    "sg:tags":[
        "telephone",
        "cellular"
    ],
    "sg:website":"www.radioshack.com",
    "wof:name":"Radio Shack",
    "wof:placetype":"venue"
},
  "geometry": {"coordinates":[-86.904073,40.020367],"type":"Point"}
}