{
  "type": "Feature",
  "properties": {
    "iso:country":"US",
    "sg:address":"425 N 9th St",
    "sg:city":"Decatur",
    "sg:classifiers":[
        {
            "category":"Organizations",
            "subcategory":"Community Association",
            "type":"Services"
        }
    ],
    "sg:phone":"+1 260 724 2736",
    "sg:postcode":"46733",
    "sg:province":"IN",
    "sg:tags":[
        "club"
    ],
    "wof:name":"Kiwanis Club Of Decatur",
    "wof:placetype":"venue"
},
  "geometry": {"coordinates":[-84.933145,40.833207],"type":"Point"}
}