{
  "type": "Feature",
  "properties": {
    "iso:country":"US",
    "sg:address":"10253 E 150 N",
    "sg:city":"Darlington",
    "sg:phone":"+1 765 794 4196",
    "sg:postcode":"47940",
    "sg:province":"IN",
    "sg:tags":[
        "farm",
        "soybean"
    ],
    "wof:name":"Denny Roberts",
    "wof:placetype":"venue"
},
  "geometry": {"coordinates":[-86.71968099999999,40.061985],"type":"Point"}
}