{
  "type": "Feature",
  "properties": {
    "addr:full":"730 W Eads Pkwy Lawrenceburg IN 47025",
    "addr:housenumber":"730",
    "addr:postcode":"47025",
    "addr:street":"W Eads Pkwy",
    "iso:country":"US",
    "sg:address":"730 W Eads Pkwy",
    "sg:city":"Lawrenceburg",
    "sg:classifiers":[
        {
            "category":"Retail",
            "subcategory":"Auto Repair",
            "type":"Services"
        }
    ],
    "sg:phone":"+1 812 537 1999",
    "sg:postcode":"47025",
    "sg:province":"IN",
    "sg:tags":[
        "repairing",
        "automobile"
    ],
    "wof:name":"Quikstop Oilube",
    "wof:placetype":"venue"
},
  "geometry": {"coordinates":[-84.868566,39.093386],"type":"Point"}
}