{
  "type": "Feature",
  "properties": {
    "iso:country":"US",
    "sg:address":"514 S Elliott Acres Dr",
    "sg:city":"Muncie",
    "sg:classifiers":[
        {
            "category":"Professional",
            "subcategory":"Management & Consulting",
            "type":"Services"
        }
    ],
    "sg:phone":"+1 765 281 9577",
    "sg:postcode":"47302",
    "sg:province":"IN",
    "wof:name":"W F Smith LLC",
    "wof:placetype":"venue"
},
  "geometry": {"coordinates":[-85.331537,40.187672],"type":"Point"}
}