{
  "type": "Feature",
  "properties": {
    "iso:country":"US",
    "sg:address":"5510 Utica Pike",
    "sg:city":"Jeffersonville",
    "sg:classifiers":[
        {
            "category":"Professional",
            "subcategory":"Advertising",
            "type":"Services"
        }
    ],
    "sg:phone":"+1 812 283 5750",
    "sg:postcode":"47130",
    "sg:province":"IN",
    "sg:tags":[
        "counselor"
    ],
    "wof:name":"5510",
    "wof:placetype":"venue"
},
  "geometry": {"coordinates":[-85.661507,38.325444],"type":"Point"}
}