{
  "type": "Feature",
  "properties": {
    "iso:country":"US",
    "sg:address":"9050 Louisiana St",
    "sg:city":"Merrillville",
    "sg:classifiers":[
        {
            "category":"Home & Garden",
            "subcategory":"Building Materials",
            "type":"Retail Goods"
        }
    ],
    "sg:phone":"+1 219 793 1500",
    "sg:postcode":"46410",
    "sg:province":"IN",
    "sg:tags":[
        "windows"
    ],
    "sg:website":"www.alliedbuilding.com",
    "wof:name":"Allied Building Products Corp",
    "wof:placetype":"venue"
},
  "geometry": {"coordinates":[-87.319582,41.455672],"type":"Point"}
}