{
  "type": "Feature",
  "properties": {
    "iso:country":"US",
    "sg:address":"320 S Bloomington St",
    "sg:city":"Greencastle",
    "sg:classifiers":[
        {
            "category":"Freight",
            "type":"Transportation"
        }
    ],
    "sg:phone":"+1 765 653 8585",
    "sg:postcode":"46135",
    "sg:province":"IN",
    "sg:tags":[
        "commercial",
        "storage"
    ],
    "wof:name":"Attic Self Stor Storage",
    "wof:placetype":"venue"
},
  "geometry": {"coordinates":[-86.856432,39.639968],"type":"Point"}
}