{
  "type": "Feature",
  "properties": {
    "iso:country":"US",
    "sg:address":"225 Adams St",
    "sg:city":"Decatur",
    "sg:classifiers":[
        {
            "category":"Retail",
            "subcategory":"Funeral Services",
            "type":"Services"
        }
    ],
    "sg:phone":"+1 260 724 7167",
    "sg:postcode":"46733",
    "sg:province":"IN",
    "sg:tags":[
        "director"
    ],
    "wof:name":"Haggard & Sefton Funeral Home",
    "wof:placetype":"venue"
},
  "geometry": {"coordinates":[-84.923588,40.827379],"type":"Point"}
}