{
  "type": "Feature",
  "properties": {
    "iso:country":"US",
    "sg:address":"316 S 9th St",
    "sg:city":"Richmond",
    "sg:classifiers":[
        {
            "category":"Building & Trades",
            "subcategory":"Construction",
            "type":"Services"
        }
    ],
    "sg:phone":"+1 765 966 2114",
    "sg:postcode":"47374",
    "sg:province":"IN",
    "sg:tags":[
        "home",
        "improvement"
    ],
    "wof:name":"Bowman & Son Home Improvement",
    "wof:placetype":"venue"
},
  "geometry": {"coordinates":[-84.890341,39.824434],"type":"Point"}
}