{
  "type": "Feature",
  "properties": {
    "iso:country":"US",
    "sg:address":"4335 Shady View Dr",
    "sg:city":"Indianapolis",
    "sg:classifiers":[
        {
            "category":"Utilities",
            "subcategory":"Electric",
            "type":"Services"
        },
        {
            "category":"Manufacturing",
            "subcategory":"Electronics",
            "type":"Manufacturing & Wholesale Goods"
        }
    ],
    "sg:phone":"+1 317 546 5071",
    "sg:postcode":"46226",
    "sg:province":"IN",
    "sg:tags":[
        "equipment-testing"
    ],
    "wof:name":"Solar Century Of Indiana",
    "wof:placetype":"venue"
},
  "geometry": {"coordinates":[-86.050079,39.835673],"type":"Point"}
}