{
  "type": "Feature",
  "properties": {
    "iso:country":"US",
    "sg:address":"141 E South St",
    "sg:city":"Mooresville",
    "sg:classifiers":[
        {
            "category":"Building & Trades",
            "subcategory":"Construction",
            "type":"Services"
        }
    ],
    "sg:phone":"+1 317 834 2416",
    "sg:postcode":"46158",
    "sg:province":"IN",
    "sg:tags":[
        "home",
        "improvement"
    ],
    "wof:name":"Tim Morris Construction",
    "wof:placetype":"venue"
},
  "geometry": {"coordinates":[-86.37184999999999,39.608466],"type":"Point"}
}