{
  "type": "Feature",
  "properties": {
    "iso:country":"US",
    "sg:address":"214 S Indiana Ave",
    "sg:city":"Goshen",
    "sg:classifiers":[
        {
            "category":"Professional",
            "subcategory":"Testing Lab",
            "type":"Services"
        }
    ],
    "sg:phone":"+1 574 534 5756",
    "sg:postcode":"46526",
    "sg:province":"IN",
    "sg:tags":[
        "correction",
        "radon"
    ],
    "wof:name":"Radon-X",
    "wof:placetype":"venue"
},
  "geometry": {"coordinates":[-85.848114,41.581908],"type":"Point"}
}