{
  "type": "Feature",
  "properties": {
    "addr:full":"6240 Exeter Ct South Bend IN 46614",
    "addr:housenumber":"6240",
    "addr:postcode":"46614",
    "addr:street":"Exeter Ct",
    "iso:country":"US",
    "sg:address":"6240 Exeter Ct",
    "sg:city":"South Bend",
    "sg:classifiers":[
        {
            "category":"Organizations",
            "subcategory":"Religious Organization",
            "type":"Services"
        }
    ],
    "sg:phone":"+1 574 299 0236",
    "sg:postcode":"46614",
    "sg:province":"IN",
    "wof:name":"Hope Community Church",
    "wof:placetype":"venue"
},
  "geometry": {"coordinates":[-86.23186099999999,41.608917],"type":"Point"}
}