{
  "type": "Feature",
  "properties": {
    "iso:country":"US",
    "sg:address":"1905 N Ritter Ave",
    "sg:city":"Indianapolis",
    "sg:classifiers":[
        {
            "category":"Shopping",
            "subcategory":"Department Store",
            "type":"Retail Goods"
        }
    ],
    "sg:phone":"+1 317 356 3619",
    "sg:postcode":"46218",
    "sg:province":"IN",
    "sg:tags":[
        "shop"
    ],
    "sg:website":"www.cooldiscounts.net",
    "wof:name":"COOLDISCOUNTS.NET",
    "wof:placetype":"venue"
},
  "geometry": {"coordinates":[-86.073802,39.793958],"type":"Point"}
}