{
  "type": "Feature",
  "properties": {
    "iso:country":"US",
    "sg:address":"7515 W Lane Rd",
    "sg:city":"Mc Cordsville",
    "sg:classifiers":[
        {
            "category":"Freight",
            "type":"Transportation"
        }
    ],
    "sg:phone":"+1 317 335 2477",
    "sg:postcode":"46055",
    "sg:province":"IN",
    "sg:tags":[
        "operator",
        "trucking"
    ],
    "wof:name":"Gerald Phares",
    "wof:placetype":"venue"
},
  "geometry": {"coordinates":[-85.942695,39.847725],"type":"Point"}
}