{
  "type": "Feature",
  "properties": {
    "addr:full":"5377 Grimm Rd Newburgh IN 47630",
    "addr:housenumber":"5377",
    "addr:postcode":"47630",
    "addr:street":"Grimm Rd",
    "iso:country":"US",
    "sg:address":"5377 Grimm Rd",
    "sg:city":"Newburgh",
    "sg:classifiers":[
        {
            "category":"Recreation",
            "type":"Entertainment"
        }
    ],
    "sg:phone":"+1 812 490 4001",
    "sg:postcode":"47630",
    "sg:province":"IN",
    "sg:tags":[
        "stable"
    ],
    "wof:name":"Riverwind Stable",
    "wof:placetype":"venue"
},
  "geometry": {"coordinates":[-87.432434,37.955285],"type":"Point"}
}