{
  "type": "Feature",
  "properties": {
    "iso:country":"US",
    "sg:address":"5621 Autumn Ridge Dr",
    "sg:city":"Newburgh",
    "sg:classifiers":[
        {
            "category":"Real Estate",
            "subcategory":"Real Estate Agent",
            "type":"Services"
        }
    ],
    "sg:phone":"+1 812 853 6915",
    "sg:postcode":"47630",
    "sg:province":"IN",
    "sg:tags":[
        "investment"
    ],
    "wof:name":"Rivertown Prop Invest",
    "wof:placetype":"venue"
},
  "geometry": {"coordinates":[-87.38997500000001,37.952128],"type":"Point"}
}