{
  "type": "Feature",
  "properties": {
    "iso:country":"US",
    "sg:address":"6214 Covington Rd",
    "sg:city":"Fort Wayne",
    "sg:classifiers":[
        {
            "category":"Travel",
            "subcategory":"Travel Agent",
            "type":"Entertainment"
        }
    ],
    "sg:phone":"+1 260 432 5995",
    "sg:postcode":"46804",
    "sg:province":"IN",
    "sg:tags":[
        "agency",
        "bureau"
    ],
    "sg:website":"www.covingtontravelinc.com",
    "wof:name":"Covington Travel",
    "wof:placetype":"venue"
},
  "geometry": {"coordinates":[-85.221946,41.059804],"type":"Point"}
}