{
  "type": "Feature",
  "properties": {
    "addr:full":"330 Harrison St Troy IN 47588",
    "addr:housenumber":"330",
    "addr:postcode":"47588",
    "addr:street":"Harrison St",
    "iso:country":"US",
    "sg:address":"330 Harrison St",
    "sg:city":"Troy",
    "sg:classifiers":[
        {
            "category":"Government",
            "subcategory":"Office",
            "type":"Public Place"
        }
    ],
    "sg:phone":"+1 812 547 7501",
    "sg:postcode":"47588",
    "sg:province":"IN",
    "sg:tags":[
        "govt",
        "city"
    ],
    "wof:name":"Troy Utility Dept",
    "wof:placetype":"venue"
},
  "geometry": {"coordinates":[-86.80289500000001,37.995466],"type":"Point"}
}