{
  "type": "Feature",
  "properties": {
    "iso:country":"US",
    "sg:address":"832 W 5th Ave",
    "sg:city":"Gary",
    "sg:classifiers":[
        {
            "category":"Retail",
            "subcategory":"Laundry & Dry Cleaning",
            "type":"Services"
        }
    ],
    "sg:phone":"+1 219 883 1808",
    "sg:postcode":"46402",
    "sg:province":"IN",
    "sg:tags":[
        "cleaners"
    ],
    "wof:name":"5th Ave Coin/Op Laundry",
    "wof:placetype":"venue"
},
  "geometry": {"coordinates":[-87.347478,41.602094],"type":"Point"}
}