{
  "type": "Feature",
  "properties": {
    "addr:full":"207 S 8th St Richmond IN 47374",
    "addr:housenumber":"207",
    "addr:postcode":"47374",
    "addr:street":"S 8Th St",
    "iso:country":"US",
    "sg:address":"207 S 8th St",
    "sg:city":"Richmond",
    "sg:classifiers":[
        {
            "category":"Personal",
            "subcategory":"Beauty Salon",
            "type":"Services"
        }
    ],
    "sg:phone":"+1 765 962 3945",
    "sg:postcode":"47374",
    "sg:province":"IN",
    "sg:tags":[
        "shop",
        "tanning"
    ],
    "wof:name":"Rod N Roll Beauty Salon",
    "wof:placetype":"venue"
},
  "geometry": {"coordinates":[-84.891548,39.825828],"type":"Point"}
}