{
  "type": "Feature",
  "properties": {
    "iso:country":"US",
    "sg:address":"11680 Jefferson Blvd",
    "sg:city":"Osceola",
    "sg:classifiers":[
        {
            "category":"Freight",
            "type":"Transportation"
        }
    ],
    "sg:phone":"+1 574 679 4744",
    "sg:postcode":"46561",
    "sg:province":"IN",
    "sg:tags":[
        "commercial",
        "storage"
    ],
    "wof:name":"Mc Kinley Penn Self-Lock Stge",
    "wof:placetype":"venue"
},
  "geometry": {"coordinates":[-86.09141,41.677209],"type":"Point"}
}