{
  "type": "Feature",
  "properties": {
    "iso:country":"US",
    "sg:address":"111 W Main St",
    "sg:city":"Odon",
    "sg:classifiers":[
        {
            "category":"Shopping",
            "subcategory":"Books",
            "type":"Retail Goods"
        }
    ],
    "sg:phone":"+1 812 636 2326",
    "sg:postcode":"47562",
    "sg:province":"IN",
    "sg:tags":[
        "dealer"
    ],
    "wof:name":"Lighthouse On Main",
    "wof:placetype":"venue"
},
  "geometry": {"coordinates":[-86.991326,38.842583],"type":"Point"}
}