{
  "type": "Feature",
  "properties": {
    "iso:country":"US",
    "sg:address":"3701 N Stoneybrook Blvd",
    "sg:city":"Bloomington",
    "sg:classifiers":[
        {
            "category":"Organizations",
            "subcategory":"Religious Organization",
            "type":"Services"
        }
    ],
    "sg:phone":"+1 812 339 6062",
    "sg:postcode":"47404",
    "sg:province":"IN",
    "sg:website":"www.churchofgod.cc",
    "wof:name":"Stoneybrook Community Church of God",
    "wof:placetype":"venue"
},
  "geometry": {"coordinates":[-86.56240099999999,39.2006],"type":"Point"}
}