{
  "type": "Feature",
  "properties": {
    "iso:country":"US",
    "sg:address":"113 S Water St",
    "sg:city":"Crawfordsville",
    "sg:classifiers":[
        {
            "category":"Organizations",
            "subcategory":"Professional Association",
            "type":"Services"
        }
    ],
    "sg:phone":"+1 765 362 3103",
    "sg:postcode":"47933",
    "sg:province":"IN",
    "sg:website":"www.redcross.org/mont/in",
    "wof:name":"American Red Cross",
    "wof:placetype":"venue"
},
  "geometry": {"coordinates":[-86.89848600000001,40.041603],"type":"Point"}
}