{
  "type": "Feature",
  "properties": {
    "addr:full":"200 Elm St Modoc IN 47358",
    "addr:housenumber":"200",
    "addr:postcode":"47358",
    "addr:street":"Elm St",
    "iso:country":"US",
    "sg:address":"200 Elm St",
    "sg:city":"Modoc",
    "sg:classifiers":[
        {
            "category":"Autos & Motor Vehicles",
            "subcategory":"Auto Supplies",
            "type":"Retail Goods"
        }
    ],
    "sg:phone":"+1 765 468 6834",
    "sg:postcode":"47358",
    "sg:province":"IN",
    "wof:name":"Kennard Shaffer",
    "wof:placetype":"venue"
},
  "geometry": {"coordinates":[-85.128002,40.046339],"type":"Point"}
}