{
  "type": "Feature",
  "properties": {
    "addr:full":"1516 Lafayette St Valparaiso IN 46383",
    "addr:housenumber":"1516",
    "addr:postcode":"46383",
    "addr:street":"Lafayette St",
    "iso:country":"US",
    "sg:address":"1516 Lafayette St",
    "sg:city":"Valparaiso",
    "sg:classifiers":[
        {
            "category":"Health Services",
            "subcategory":"Doctor",
            "type":"Services"
        }
    ],
    "sg:phone":"+1 219 462 6827",
    "sg:postcode":"46383",
    "sg:province":"IN",
    "sg:tags":[
        "dentist"
    ],
    "wof:name":"Family Dental Care",
    "wof:placetype":"venue"
},
  "geometry": {"coordinates":[-87.06219900000001,41.482009],"type":"Point"}
}