{
  "type": "Feature",
  "properties": {
    "iso:country":"US",
    "sg:address":"7901 Crawfordsville Rd",
    "sg:city":"Indianapolis",
    "sg:classifiers":[
        {
            "category":"Health Services",
            "subcategory":"Doctor",
            "type":"Services"
        }
    ],
    "sg:phone":"+1 317 293 0965",
    "sg:postcode":"46214",
    "sg:province":"IN",
    "sg:tags":[
        "dentist"
    ],
    "wof:name":"Karl Gossweiler DDS",
    "wof:placetype":"venue"
},
  "geometry": {"coordinates":[-86.299025,39.807257],"type":"Point"}
}