{
  "type": "Feature",
  "properties": {
    "iso:country":"US",
    "sg:address":"11182 W 900 S",
    "sg:city":"Francesville",
    "sg:classifiers":[
        {
            "category":"Professional",
            "subcategory":"Management & Consulting",
            "type":"Services"
        }
    ],
    "sg:phone":"+1 219 567 9755",
    "sg:postcode":"47946",
    "sg:province":"IN",
    "sg:tags":[
        "consultant",
        "training"
    ],
    "wof:name":"Dosier Training Ctr Horse",
    "wof:placetype":"venue"
},
  "geometry": {"coordinates":[-86.819196,40.927069],"type":"Point"}
}