{
  "type": "Feature",
  "properties": {
    "iso:country":"US",
    "sg:address":"5397 E 900 N",
    "sg:city":"Syracuse",
    "sg:classifiers":[
        {
            "category":"Building & Trades",
            "subcategory":"Construction",
            "type":"Services"
        }
    ],
    "sg:phone":"+1 574 834 3544",
    "sg:postcode":"46567",
    "sg:province":"IN",
    "sg:tags":[
        "mobile",
        "home"
    ],
    "wof:name":"Gary's Rv & Mobile Home Repair",
    "wof:placetype":"venue"
},
  "geometry": {"coordinates":[-85.745194,41.364384],"type":"Point"}
}