{
  "type": "Feature",
  "properties": {
    "addr:full":"410 Silver St New Albany IN 47150",
    "addr:housenumber":"410",
    "addr:postcode":"47150",
    "addr:street":"Silver St",
    "iso:country":"US",
    "sg:address":"410 Silver St",
    "sg:city":"New Albany",
    "sg:classifiers":[
        {
            "category":"Insurance",
            "subcategory":"Insurance Agent",
            "type":"Services"
        }
    ],
    "sg:phone":"+1 812 945 1144",
    "sg:postcode":"47150",
    "sg:province":"IN",
    "wof:name":"State Farm Insurance",
    "wof:placetype":"venue"
},
  "geometry": {"coordinates":[-85.800826,38.297557],"type":"Point"}
}