{
  "type": "Feature",
  "properties": {
    "iso:country":"US",
    "sg:address":"4313 E Morgan Ave",
    "sg:city":"Evansville",
    "sg:classifiers":[
        {
            "category":"Banks & Credit Unions",
            "subcategory":"Bank",
            "type":"Services"
        }
    ],
    "sg:phone":"+1 812 474 1642",
    "sg:postcode":"47715",
    "sg:province":"IN",
    "sg:tags":[
        "financing"
    ],
    "wof:name":"Beneficial Indiana Inc",
    "wof:placetype":"venue"
},
  "geometry": {"coordinates":[-87.496471,37.991175],"type":"Point"}
}