{
  "type": "Feature",
  "properties": {
    "iso:country":"US",
    "sg:address":"4545 S Cross St",
    "sg:city":"St Anthony",
    "sg:classifiers":[
        {
            "category":"Organizations",
            "subcategory":"Community Association",
            "type":"Services"
        }
    ],
    "sg:phone":"+1 812 326 2866",
    "sg:postcode":"47575",
    "sg:province":"IN",
    "sg:tags":[
        "military"
    ],
    "wof:name":"American Legion",
    "wof:placetype":"venue"
},
  "geometry": {"coordinates":[-86.827437,38.313697],"type":"Point"}
}