{
  "type": "Feature",
  "properties": {
    "iso:country":"US",
    "sg:address":"5603 Mineral Springs Rd",
    "sg:city":"Greens Fork",
    "sg:classifiers":[
        {
            "category":"Farming",
            "subcategory":"Farm",
            "type":"Manufacturing & Wholesale Goods"
        }
    ],
    "sg:phone":"+1 765 886 5579",
    "sg:postcode":"47345",
    "sg:province":"IN",
    "sg:tags":[
        "crop",
        "general"
    ],
    "wof:name":"Bill Gamber",
    "wof:placetype":"venue"
},
  "geometry": {"coordinates":[-85.040356,39.904586],"type":"Point"}
}