{
  "type": "Feature",
  "properties": {
    "addr:full":"823 Ohio St Terre Haute IN 47807",
    "addr:housenumber":"823",
    "addr:postcode":"47807",
    "addr:street":"Ohio St",
    "iso:country":"US",
    "sg:address":"823 Ohio St",
    "sg:city":"Terre Haute",
    "sg:classifiers":[
        {
            "category":"Health Services",
            "subcategory":"Doctor",
            "type":"Services"
        }
    ],
    "sg:phone":"+1 812 232 5774",
    "sg:postcode":"47807",
    "sg:province":"IN",
    "sg:tags":[
        "dentist"
    ],
    "wof:name":"Peter Van Horn DDS",
    "wof:placetype":"venue"
},
  "geometry": {"coordinates":[-87.404726,39.465369],"type":"Point"}
}