{
  "type": "Feature",
  "properties": {
    "iso:country":"US",
    "sg:address":"5324 W 38th St",
    "sg:city":"Indianapolis",
    "sg:classifiers":[
        {
            "category":"Food & Beverages",
            "subcategory":"Groceries & Convenience Stores",
            "type":"Retail Goods"
        }
    ],
    "sg:phone":"+1 317 299 9610",
    "sg:postcode":"46254",
    "sg:province":"IN",
    "sg:tags":[
        "grocer"
    ],
    "wof:name":"Tienda Morelos",
    "wof:placetype":"venue"
},
  "geometry": {"coordinates":[-86.25350299999999,39.823928],"type":"Point"}
}