{
  "type": "Feature",
  "properties": {
    "addr:full":"282 E Paul Revere Ct Chesterton IN 46304",
    "addr:housenumber":"282",
    "addr:postcode":"46304",
    "addr:street":"E Paul Revere Ct",
    "iso:country":"US",
    "sg:address":"282 E Paul Revere Ct",
    "sg:city":"Chesterton",
    "sg:classifiers":[
        {
            "category":"Professional",
            "subcategory":"Research",
            "type":"Services"
        }
    ],
    "sg:phone":"+1 219 929 4435",
    "sg:postcode":"46304",
    "sg:province":"IN",
    "sg:tags":[
        "environmental",
        "ecological"
    ],
    "wof:name":"Onyx Environmental Co",
    "wof:placetype":"venue"
},
  "geometry": {"coordinates":[-87.014368,41.59448],"type":"Point"}
}