{
  "type": "Feature",
  "properties": {
    "iso:country":"US",
    "sg:address":"5555 Epworth Rd",
    "sg:city":"Newburgh",
    "sg:classifiers":[
        {
            "category":"Food & Beverages",
            "subcategory":"Groceries & Convenience Stores",
            "type":"Retail Goods"
        }
    ],
    "sg:phone":"+1 812 853 0347",
    "sg:postcode":"47630",
    "sg:province":"IN",
    "wof:name":"Circle S",
    "wof:placetype":"venue"
},
  "geometry": {"coordinates":[-87.44151,37.954754],"type":"Point"}
}