{
  "type": "Feature",
  "properties": {
    "iso:country":"US",
    "sg:address":"800 W Johnson Dr",
    "sg:city":"Terre Haute",
    "sg:classifiers":[
        {
            "category":"Education",
            "subcategory":"Dance Studio",
            "type":"Public Place"
        }
    ],
    "sg:phone":"+1 812 234 1233",
    "sg:postcode":"47802",
    "sg:province":"IN",
    "sg:tags":[
        "instruction",
        "dancing"
    ],
    "wof:name":"World Of Dance",
    "wof:placetype":"venue"
},
  "geometry": {"coordinates":[-87.428253,39.423778],"type":"Point"}
}