{
  "type": "Feature",
  "properties": {
    "iso:country":"US",
    "sg:address":"225 E 300 S",
    "sg:city":"Lafayette",
    "sg:classifiers":[
        {
            "category":"Travel",
            "subcategory":"Campground",
            "type":"Entertainment"
        }
    ],
    "sg:phone":"+1 765 474 5030",
    "sg:postcode":"47909",
    "sg:province":"IN",
    "wof:name":"AOK Campgrounds Of Lafayette",
    "wof:placetype":"venue"
},
  "geometry": {"coordinates":[-86.898286,40.374345],"type":"Point"}
}