{
  "type": "Feature",
  "properties": {
    "iso:country":"US",
    "sg:address":"2360 Prospect St",
    "sg:city":"Indianapolis",
    "sg:classifiers":[
        {
            "category":"Retail",
            "subcategory":"Auto Repair",
            "type":"Services"
        }
    ],
    "sg:phone":"+1 317 631 7656",
    "sg:postcode":"46203",
    "sg:province":"IN",
    "sg:tags":[
        "brake"
    ],
    "wof:name":"Mike's Auto Sales Inc",
    "wof:placetype":"venue"
},
  "geometry": {"coordinates":[-86.12153,39.752514],"type":"Point"}
}