{
  "type": "Feature",
  "properties": {
    "iso:country":"US",
    "sg:address":"1755 Country Club Rd",
    "sg:city":"Indianapolis",
    "sg:classifiers":[
        {
            "category":"Retail",
            "subcategory":"Auto Repair",
            "type":"Services"
        }
    ],
    "sg:phone":"+1 317 209 1506",
    "sg:postcode":"46234",
    "sg:province":"IN",
    "sg:tags":[
        "body",
        "automobile",
        "painting"
    ],
    "wof:name":"Kane's Pit Stop",
    "wof:placetype":"venue"
},
  "geometry": {"coordinates":[-86.30752099999999,39.788307],"type":"Point"}
}