{
  "type": "Feature",
  "properties": {
    "iso:country":"US",
    "sg:address":"305 Washington St",
    "sg:city":"Columbus",
    "sg:classifiers":[
        {
            "category":"Insurance",
            "subcategory":"Insurance Agent",
            "type":"Services"
        }
    ],
    "sg:phone":"+1 812 372 0841",
    "sg:postcode":"47201",
    "sg:province":"IN",
    "wof:name":"Marvin Johnson & Assoc",
    "wof:placetype":"venue"
},
  "geometry": {"coordinates":[-85.920977,39.202416],"type":"Point"}
}