{
  "type": "Feature",
  "properties": {
    "iso:country":"US",
    "sg:address":"1901 Senate Blvd",
    "sg:city":"Indianapolis",
    "sg:classifiers":[
        {
            "category":"Health Services",
            "subcategory":"Hospital",
            "type":"Services"
        }
    ],
    "sg:phone":"+1 317 931 5220",
    "sg:postcode":"46202",
    "sg:province":"IN",
    "wof:name":"Select Specialty Hospital",
    "wof:placetype":"venue"
},
  "geometry": {"coordinates":[-86.16293,39.791368],"type":"Point"}
}