{
  "type": "Feature",
  "properties": {
    "iso:country":"US",
    "sg:address":"5940 Madison Ave",
    "sg:city":"Anderson",
    "sg:classifiers":[
        {
            "category":"Organizations",
            "subcategory":"Religious Organization",
            "type":"Services"
        }
    ],
    "sg:phone":"+1 765 643 7800",
    "sg:postcode":"46013",
    "sg:province":"IN",
    "sg:tags":[
        "ch",
        "united",
        "reformed",
        "christ"
    ],
    "wof:name":"Whetson Church of Christ",
    "wof:placetype":"venue"
},
  "geometry": {"coordinates":[-85.69205599999999,40.054668],"type":"Point"}
}