{
  "type": "Feature",
  "properties": {
    "addr:full":"620 S Wayne St Gary IN 46403",
    "addr:housenumber":"620",
    "addr:postcode":"46403",
    "addr:street":"S Wayne St Gary",
    "iso:country":"US",
    "sg:address":"620 S Wayne St",
    "sg:city":"Gary",
    "sg:classifiers":[
        {
            "category":"Retail",
            "subcategory":"Repair Shop",
            "type":"Services"
        }
    ],
    "sg:phone":"+1 219 364 0402",
    "sg:postcode":"46403",
    "sg:province":"IN",
    "sg:tags":[
        "related"
    ],
    "wof:name":"Quality Smart Carts",
    "wof:placetype":"venue"
},
  "geometry": {"coordinates":[-87.224423,41.597427],"type":"Point"}
}