{
  "type": "Feature",
  "properties": {
    "iso:country":"US",
    "sg:address":"107 S East St",
    "sg:city":"Crown Point",
    "sg:classifiers":[
        {
            "category":"Wholesale",
            "subcategory":"Machinery & Supplies",
            "type":"Manufacturing & Wholesale Goods"
        }
    ],
    "sg:phone":"+1 219 661 0313",
    "sg:postcode":"46307",
    "sg:province":"IN",
    "sg:tags":[
        "equipment",
        "industrial"
    ],
    "wof:name":"Brookside Industrial Sales",
    "wof:placetype":"venue"
},
  "geometry": {"coordinates":[-87.363262,41.417924],"type":"Point"}
}