{
  "type": "Feature",
  "properties": {
    "addr:full":"4620 Bull Rapids Rd Woodburn IN 46797",
    "addr:housenumber":"4620",
    "addr:postcode":"46797",
    "addr:street":"Bull Rapids Rd",
    "iso:country":"US",
    "sg:address":"4620 Bull Rapids Rd",
    "sg:city":"Woodburn",
    "sg:classifiers":[
        {
            "category":"Retail",
            "subcategory":"Veterinary Services",
            "type":"Services"
        }
    ],
    "sg:phone":"+1 260 632 4612",
    "sg:postcode":"46797",
    "sg:province":"IN",
    "sg:tags":[
        "veterinarian"
    ],
    "wof:name":"Woodburn Veterinary Clinic",
    "wof:placetype":"venue"
},
  "geometry": {"coordinates":[-84.854653,41.126573],"type":"Point"}
}