{
  "type": "Feature",
  "properties": {
    "iso:country":"US",
    "sg:address":"6083 S 500 W",
    "sg:city":"North Judson",
    "sg:classifiers":[
        {
            "category":"Communications",
            "type":"Services"
        }
    ],
    "sg:phone":"+1 574 896 5504",
    "sg:postcode":"46366",
    "sg:province":"IN",
    "wof:name":"Pinnacle Towers Inc",
    "wof:placetype":"venue"
},
  "geometry": {"coordinates":[-86.795001,41.213903],"type":"Point"}
}