{
  "type": "Feature",
  "properties": {
    "addr:full":"63760 US Hwy 31 South Bend IN 46614",
    "addr:postcode":"63760;46614",
    "addr:street":"Us Hwy 31",
    "iso:country":"US",
    "sg:address":"63760 US Hwy 31",
    "sg:city":"South Bend",
    "sg:classifiers":[
        {
            "category":"Shopping",
            "subcategory":"Used Merchandise",
            "type":"Retail Goods"
        }
    ],
    "sg:phone":"+1 574 291 3931",
    "sg:postcode":"46614",
    "sg:province":"IN",
    "wof:name":"Dixie Way South Antiques",
    "wof:placetype":"venue"
},
  "geometry": {"coordinates":[-86.264608,41.569468],"type":"Point"}
}