{
  "type": "Feature",
  "properties": {
    "iso:country":"US",
    "sg:address":"1624 E 950 S",
    "sg:city":"La Fontaine",
    "sg:classifiers":[
        {
            "category":"Farming",
            "subcategory":"Farm",
            "type":"Manufacturing & Wholesale Goods"
        }
    ],
    "sg:phone":"+1 765 981 4079",
    "sg:postcode":"46940",
    "sg:province":"IN",
    "sg:tags":[
        "crop",
        "general"
    ],
    "wof:name":"Well Mac Farms Inc",
    "wof:placetype":"venue"
},
  "geometry": {"coordinates":[-85.75702,40.688405],"type":"Point"}
}