{
  "type": "Feature",
  "properties": {
    "iso:country":"US",
    "sg:address":"2509 W 2nd St",
    "sg:city":"Marion",
    "sg:classifiers":[
        {
            "category":"Communications",
            "type":"Services"
        }
    ],
    "sg:phone":"+1 765 651 2001",
    "sg:postcode":"46952",
    "sg:province":"IN",
    "sg:website":"www.mooreheadcomm.com",
    "wof:name":"Moorehead Communications",
    "wof:placetype":"venue"
},
  "geometry": {"coordinates":[-85.70286299999999,40.559791],"type":"Point"}
}