{
  "type": "Feature",
  "properties": {
    "iso:country":"US",
    "sg:address":"342 N Senate Ave",
    "sg:city":"Indianapolis",
    "sg:classifiers":[
        {
            "category":"Professional",
            "subcategory":"Research",
            "type":"Services"
        }
    ],
    "sg:phone":"+1 317 261 3004",
    "sg:postcode":"46204",
    "sg:province":"IN",
    "wof:name":"Center For Urban Policy",
    "wof:placetype":"venue"
},
  "geometry": {"coordinates":[-86.163367,39.771435],"type":"Point"}
}