{
  "type": "Feature",
  "properties": {
    "iso:country":"US",
    "sg:address":"725 W Jackson St",
    "sg:city":"Parker City",
    "sg:classifiers":[
        {
            "category":"Professional",
            "type":"Services"
        }
    ],
    "sg:phone":"+1 765 468 8581",
    "sg:postcode":"47368",
    "sg:province":"IN",
    "sg:tags":[
        "establishment"
    ],
    "wof:name":"Boomers Fire Works",
    "wof:placetype":"venue"
},
  "geometry": {"coordinates":[-85.21247700000001,40.193208],"type":"Point"}
}