{
  "type": "Feature",
  "properties": {
    "iso:country":"US",
    "sg:address":"2927 Lake Valley Dr",
    "sg:city":"Evansville",
    "sg:classifiers":[
        {
            "category":"Organizations",
            "subcategory":"Non-profit Organization",
            "type":"Services"
        }
    ],
    "sg:phone":"+1 812 401 9230",
    "sg:postcode":"47711",
    "sg:province":"IN",
    "sg:tags":[
        "fund",
        "counselor",
        "raising"
    ],
    "wof:name":"Michael J Effinger Inc",
    "wof:placetype":"venue"
},
  "geometry": {"coordinates":[-87.51149599999999,38.002949],"type":"Point"}
}