{
  "type": "Feature",
  "properties": {
    "iso:country":"US",
    "sg:address":"214 W Depot St",
    "sg:city":"Bainbridge",
    "sg:classifiers":[
        {
            "category":"Arts & Performance",
            "subcategory":"Theater",
            "type":"Entertainment"
        }
    ],
    "sg:phone":"+1 765 522 6878",
    "sg:postcode":"46105",
    "sg:province":"IN",
    "sg:tags":[
        "group"
    ],
    "wof:name":"Sound Investment Productions",
    "wof:placetype":"venue"
},
  "geometry": {"coordinates":[-86.813388,39.759793],"type":"Point"}
}