{
  "type": "Feature",
  "properties": {
    "iso:country":"US",
    "sg:address":"109 N Jackson St",
    "sg:city":"Crothersville",
    "sg:classifiers":[
        {
            "category":"Freight",
            "type":"Transportation"
        }
    ],
    "sg:phone":"+1 812 793 3630",
    "sg:postcode":"47229",
    "sg:province":"IN",
    "sg:tags":[
        "courier"
    ],
    "wof:name":"J T Courier Svc",
    "wof:placetype":"venue"
},
  "geometry": {"coordinates":[-85.838245,38.79707],"type":"Point"}
}