{
  "type": "Feature",
  "properties": {
    "iso:country":"US",
    "sg:address":"2602 Oakwood Ave",
    "sg:city":"Valparaiso",
    "sg:classifiers":[
        {
            "category":"Home & Garden",
            "subcategory":"Home Furnishings",
            "type":"Retail Goods"
        }
    ],
    "sg:phone":"+1 219 464 2924",
    "sg:postcode":"46383",
    "sg:province":"IN",
    "sg:tags":[
        "equipment",
        "fireplace"
    ],
    "wof:name":"Fireside Specialties",
    "wof:placetype":"venue"
},
  "geometry": {"coordinates":[-87.029867,41.505117],"type":"Point"}
}