{
  "type": "Feature",
  "properties": {
    "iso:country":"US",
    "sg:address":"5155 E 116th St",
    "sg:city":"Carmel",
    "sg:classifiers":[
        {
            "category":"Organizations",
            "subcategory":"Religious Organization",
            "type":"Services"
        }
    ],
    "sg:phone":"+1 317 846 6322",
    "sg:postcode":"46033",
    "sg:province":"IN",
    "sg:tags":[
        "church"
    ],
    "wof:name":"White Chapel Church",
    "wof:placetype":"venue"
},
  "geometry": {"coordinates":[-86.083271,39.956605],"type":"Point"}
}