{
  "type": "Feature",
  "properties": {
    "iso:country":"US",
    "sg:address":"7492 E 200 N",
    "sg:city":"Grovertown",
    "sg:classifiers":[
        {
            "category":"Food & Beverages",
            "subcategory":"Meat & Fish",
            "type":"Retail Goods"
        }
    ],
    "sg:phone":"+1 574 867 5287",
    "sg:postcode":"46531",
    "sg:province":"IN",
    "wof:name":"Pork Shop",
    "wof:placetype":"venue"
},
  "geometry": {"coordinates":[-86.553362,41.331602],"type":"Point"}
}