{
  "type": "Feature",
  "properties": {
    "iso:country":"US",
    "sg:address":"1805 Kentucky Ave",
    "sg:city":"Indianapolis",
    "sg:classifiers":[
        {
            "category":"Building & Trades",
            "subcategory":"Plumbing",
            "type":"Services"
        }
    ],
    "sg:phone":"+1 317 264 9124",
    "sg:postcode":"46221",
    "sg:province":"IN",
    "sg:tags":[
        "mechanical",
        "contractor"
    ],
    "wof:name":"Pyramid Development & Constr",
    "wof:placetype":"venue"
},
  "geometry": {"coordinates":[-86.19589999999999,39.737175],"type":"Point"}
}