{
  "type": "Feature",
  "properties": {
    "addr:full":"214 W 4th St Bloomington IN 47408",
    "addr:housenumber":"214",
    "addr:postcode":"47408",
    "addr:street":"W 4Th St",
    "iso:country":"US",
    "sg:address":"214 W 4th St",
    "sg:city":"Bloomington",
    "sg:classifiers":[
        {
            "category":"Shopping",
            "subcategory":"Used Merchandise",
            "type":"Retail Goods"
        }
    ],
    "sg:phone":"+1 812 333 0408",
    "sg:postcode":"47408",
    "sg:province":"IN",
    "sg:tags":[
        "vintage",
        "consignment"
    ],
    "wof:name":"Material Plane",
    "wof:placetype":"venue"
},
  "geometry": {"coordinates":[-86.535083,39.165606],"type":"Point"}
}