{
  "type": "Feature",
  "properties": {
    "addr:full":"11903 E Welland St Indianapolis IN 46229",
    "addr:housenumber":"11903",
    "addr:postcode":"46229",
    "addr:street":"E Welland St",
    "iso:country":"US",
    "sg:address":"11903 E Welland St",
    "sg:city":"Indianapolis",
    "sg:classifiers":[
        {
            "category":"Insurance",
            "subcategory":"Insurance Agent",
            "type":"Services"
        }
    ],
    "sg:phone":"+1 317 894 1717",
    "sg:postcode":"46229",
    "sg:province":"IN",
    "wof:name":"Midwest Life Specialists",
    "wof:placetype":"venue"
},
  "geometry": {"coordinates":[-85.955153,39.778691],"type":"Point"}
}