{
  "type": "Feature",
  "properties": {
    "iso:country":"US",
    "sg:address":"11130 W 93rd Ave",
    "sg:city":"St John",
    "sg:classifiers":[
        {
            "category":"Building & Trades",
            "subcategory":"Construction",
            "type":"Services"
        }
    ],
    "sg:phone":"+1 219 365 9398",
    "sg:postcode":"46373",
    "sg:province":"IN",
    "sg:tags":[
        "general",
        "contractor"
    ],
    "wof:name":"Boller Construction",
    "wof:placetype":"venue"
},
  "geometry": {"coordinates":[-87.46834800000001,41.45002],"type":"Point"}
}