{
  "type": "Feature",
  "properties": {
    "iso:country":"US",
    "sg:address":"1819 N Lincoln St",
    "sg:city":"Greensburg",
    "sg:classifiers":[
        {
            "category":"Personal",
            "subcategory":"Beauty Salon",
            "type":"Services"
        }
    ],
    "sg:phone":"+1 812 663 9711",
    "sg:postcode":"47240",
    "sg:province":"IN",
    "wof:name":"Cut-Up's Barber & Beauty Shop",
    "wof:placetype":"venue"
},
  "geometry": {"coordinates":[-85.479866,39.35502],"type":"Point"}
}