{
  "type": "Feature",
  "properties": {
    "iso:country":"US",
    "sg:address":"201 S Emerson Ave",
    "sg:city":"Greenwood",
    "sg:classifiers":[
        {
            "category":"Health Services",
            "subcategory":"Doctor",
            "type":"Services"
        }
    ],
    "sg:phone":"+1 317 888 4044",
    "sg:postcode":"46143",
    "sg:province":"IN",
    "sg:tags":[
        "dentist"
    ],
    "wof:name":"Gentle Dentist",
    "wof:placetype":"venue"
},
  "geometry": {"coordinates":[-86.082544,39.613005],"type":"Point"}
}