{
  "type": "Feature",
  "properties": {
    "iso:country":"US",
    "sg:address":"64 Oakden Ct",
    "sg:city":"Whiteland",
    "sg:classifiers":[
        {
            "category":"Professional",
            "subcategory":"Art Services",
            "type":"Services"
        }
    ],
    "sg:phone":"+1 317 535 7742",
    "sg:postcode":"46184",
    "sg:province":"IN",
    "sg:tags":[
        "graphic",
        "designer"
    ],
    "wof:name":"Jam Graphix Inc",
    "wof:placetype":"venue"
},
  "geometry": {"coordinates":[-86.09553099999999,39.569919],"type":"Point"}
}