{
  "type": "Feature",
  "properties": {
    "iso:country":"US",
    "sg:address":"4256 S 800 E",
    "sg:city":"Greenfield",
    "sg:classifiers":[
        {
            "category":"Real Estate",
            "subcategory":"Real Estate Operator",
            "type":"Services"
        }
    ],
    "sg:phone":"+1 317 462 6486",
    "sg:postcode":"46140",
    "sg:province":"IN",
    "sg:tags":[
        "property",
        "lessor"
    ],
    "wof:name":"Wallace Roberts",
    "wof:placetype":"venue"
},
  "geometry": {"coordinates":[-85.65205,39.721454],"type":"Point"}
}