{
  "type": "Feature",
  "properties": {
    "addr:full":"151 N Senate Ave Indianapolis IN 46202",
    "addr:housenumber":"151",
    "addr:postcode":"46202",
    "addr:street":"N Senate Ave",
    "iso:country":"US",
    "sg:address":"151 N Senate Ave",
    "sg:city":"Indianapolis",
    "sg:classifiers":[
        {
            "category":"Professional",
            "subcategory":"Management & Consulting",
            "type":"Services"
        }
    ],
    "sg:phone":"+1 317 634 2020",
    "sg:postcode":"46202",
    "sg:province":"IN",
    "sg:tags":[
        "life",
        "carrier",
        "insurance"
    ],
    "wof:name":"Financial Service Corporation",
    "wof:placetype":"venue"
},
  "geometry": {"coordinates":[-86.163477,39.76934],"type":"Point"}
}