{
  "type": "Feature",
  "properties": {
    "iso:country":"US",
    "sg:address":"940 W Miami Ave",
    "sg:city":"Logansport",
    "sg:classifiers":[
        {
            "category":"Freight",
            "type":"Transportation"
        }
    ],
    "sg:phone":"+1 574 753 6161",
    "sg:postcode":"46947",
    "sg:province":"IN",
    "sg:tags":[
        "commercial",
        "storage"
    ],
    "wof:name":"Wolf Office & Mini Storage",
    "wof:placetype":"venue"
},
  "geometry": {"coordinates":[-86.381844,40.755971],"type":"Point"}
}