{
  "type": "Feature",
  "properties": {
    "iso:country":"US",
    "sg:address":"5071 E Hopewell Rd",
    "sg:city":"Avilla",
    "sg:classifiers":[
        {
            "category":"Personal",
            "subcategory":"Beauty Salon",
            "type":"Services"
        }
    ],
    "sg:phone":"+1 260 636 1208",
    "sg:postcode":"46710",
    "sg:province":"IN",
    "sg:tags":[
        "shop"
    ],
    "wof:name":"Wagon Wheel",
    "wof:placetype":"venue"
},
  "geometry": {"coordinates":[-85.282465,41.323664],"type":"Point"}
}