{
  "type": "Feature",
  "properties": {
    "iso:country":"US",
    "sg:address":"2646 Lois St",
    "sg:city":"Portage",
    "sg:classifiers":[
        {
            "category":"Health Services",
            "subcategory":"Doctor",
            "type":"Services"
        }
    ],
    "sg:phone":"+1 219 762 3010",
    "sg:postcode":"46368",
    "sg:province":"IN",
    "sg:tags":[
        "dentist"
    ],
    "wof:name":"Family Dentistry",
    "wof:placetype":"venue"
},
  "geometry": {"coordinates":[-87.179996,41.574149],"type":"Point"}
}