{
  "type": "Feature",
  "properties": {
    "addr:full":"4387 W 5th Ave Gary IN 46406",
    "addr:housenumber":"4387",
    "addr:postcode":"46406",
    "addr:street":"W 5Th Ave",
    "iso:country":"US",
    "sg:address":"4387 W 5th Ave",
    "sg:city":"Gary",
    "sg:classifiers":[
        {
            "category":"Personal",
            "subcategory":"Beauty Salon",
            "type":"Services"
        }
    ],
    "sg:phone":"+1 219 977 9180",
    "sg:postcode":"46406",
    "sg:province":"IN",
    "sg:tags":[
        "nail",
        "manicuring"
    ],
    "wof:name":"Tammy Nails",
    "wof:placetype":"venue"
},
  "geometry": {"coordinates":[-87.39313900000001,41.601896],"type":"Point"}
}