{
  "type": "Feature",
  "properties": {
    "iso:country":"US",
    "sg:address":"401 W Jackson St",
    "sg:city":"Muncie",
    "sg:classifiers":[
        {
            "category":"Social Services",
            "type":"Services"
        }
    ],
    "sg:phone":"+1 765 284 9063",
    "sg:postcode":"47305",
    "sg:province":"IN",
    "sg:tags":[
        "organization",
        "welfare"
    ],
    "wof:name":"Cancer Services Of Delaware",
    "wof:placetype":"venue"
},
  "geometry": {"coordinates":[-85.391,40.192892],"type":"Point"}
}