{
  "type": "Feature",
  "properties": {
    "iso:country":"US",
    "sg:address":"2359 E Wabash St",
    "sg:city":"Frankfort",
    "sg:classifiers":[
        {
            "category":"Real Estate",
            "subcategory":"Real Estate Agent",
            "type":"Services"
        }
    ],
    "sg:phone":"+1 765 659 1828",
    "sg:postcode":"46041",
    "sg:province":"IN",
    "sg:website":"www.rodkey.com",
    "wof:name":"Dave Rodkey Realtors",
    "wof:placetype":"venue"
},
  "geometry": {"coordinates":[-86.48329,40.2788],"type":"Point"}
}