{
  "type": "Feature",
  "properties": {
    "iso:country":"US",
    "sg:address":"25119 Chapel Rd",
    "sg:city":"Laurel",
    "sg:classifiers":[
        {
            "category":"Building & Trades",
            "subcategory":"Landscaping Services",
            "type":"Services"
        }
    ],
    "sg:phone":"+1 765 698 2273",
    "sg:postcode":"47024",
    "sg:province":"IN",
    "sg:tags":[
        "tree"
    ],
    "wof:name":"Maggard Tree Svc",
    "wof:placetype":"venue"
},
  "geometry": {"coordinates":[-85.24579,39.466784],"type":"Point"}
}