{
  "type": "Feature",
  "properties": {
    "iso:country":"US",
    "sg:address":"2040 Chartwell Dr",
    "sg:city":"Fort Wayne",
    "sg:classifiers":[
        {
            "category":"Social Services",
            "subcategory":"Child Care",
            "type":"Services"
        }
    ],
    "sg:phone":"+1 260 447 9423",
    "sg:postcode":"46816",
    "sg:province":"IN",
    "wof:name":"Deonna's Daycare",
    "wof:placetype":"venue"
},
  "geometry": {"coordinates":[-85.107935,41.030235],"type":"Point"}
}