{
  "type": "Feature",
  "properties": {
    "iso:country":"US",
    "sg:address":"1214 Washington Ave",
    "sg:city":"Vincennes",
    "sg:classifiers":[
        {
            "category":"Building & Trades",
            "subcategory":"Construction",
            "type":"Services"
        }
    ],
    "sg:phone":"+1 812 882 4277",
    "sg:postcode":"47591",
    "sg:province":"IN",
    "sg:tags":[
        "general",
        "contractor"
    ],
    "wof:name":"Fisher Construction",
    "wof:placetype":"venue"
},
  "geometry": {"coordinates":[-87.515883,38.681684],"type":"Point"}
}