{
  "type": "Feature",
  "properties": {
    "iso:country":"US",
    "sg:address":"1744 W Morris St",
    "sg:city":"Indianapolis",
    "sg:classifiers":[
        {
            "category":"Building & Trades",
            "subcategory":"Construction",
            "type":"Services"
        }
    ],
    "sg:phone":"+1 317 917 8810",
    "sg:postcode":"46221",
    "sg:province":"IN",
    "sg:tags":[
        "roofing",
        "contractor"
    ],
    "wof:name":"Randy's Roofing & Remodeling",
    "wof:placetype":"venue"
},
  "geometry": {"coordinates":[-86.192007,39.751202],"type":"Point"}
}