{
  "type": "Feature",
  "properties": {
    "iso:country":"US",
    "sg:address":"8005 Calumet Avenue",
    "sg:city":"Munster",
    "sg:classifiers":[
        {
            "category":"Shopping",
            "subcategory":"Department Store",
            "type":"Retail Goods"
        },
        {
            "category":"Shopping",
            "subcategory":"Beauty & Cosmetics",
            "type":"Retail Goods"
        },
        {
            "category":"Home & Garden",
            "subcategory":"Home Furnishings",
            "type":"Retail Goods"
        },
        {
            "category":"Home & Garden",
            "subcategory":"Furniture",
            "type":"Retail Goods"
        },
        {
            "category":"Home & Garden",
            "subcategory":"Carpets & Floor Coverings",
            "type":"Retail Goods"
        },
        {
            "category":"Food & Beverages",
            "subcategory":"Groceries & Convenience Stores",
            "type":"Retail Goods"
        }
    ],
    "sg:phone":"+1 219 836 2489",
    "sg:postcode":"46321",
    "sg:province":"IN",
    "sg:tags":[
        "decor",
        "mattress",
        "supply"
    ],
    "wof:name":"Target",
    "wof:placetype":"venue"
},
  "geometry": {"coordinates":[-87.508797,41.568298],"type":"Point"}
}