{
  "type": "Feature",
  "properties": {
    "iso:country":"US",
    "sg:address":"458 S 450 E",
    "sg:city":"Valparaiso",
    "sg:classifiers":[
        {
            "category":"Building & Trades",
            "subcategory":"Cleaning & Sanitation",
            "type":"Services"
        }
    ],
    "sg:phone":"+1 219 548 1329",
    "sg:postcode":"46383",
    "sg:province":"IN",
    "sg:tags":[
        "window"
    ],
    "wof:name":"Hoosier Window Washer",
    "wof:placetype":"venue"
},
  "geometry": {"coordinates":[-86.978706,41.375934],"type":"Point"}
}