{
  "type": "Feature",
  "properties": {
    "addr:full":"619 N Burkhardt Rd Evansville IN 47715",
    "addr:housenumber":"619",
    "addr:postcode":"47715",
    "addr:street":"N Burkhardt Rd",
    "iso:country":"US",
    "sg:address":"619 N Burkhardt Rd",
    "sg:city":"Evansville",
    "sg:classifiers":[
        {
            "category":"Personal",
            "subcategory":"Beauty Salon",
            "type":"Services"
        }
    ],
    "sg:phone":"+1 812 491 2583",
    "sg:postcode":"47715",
    "sg:province":"IN",
    "wof:name":"Blue Duck Salon",
    "wof:placetype":"venue"
},
  "geometry": {"coordinates":[-87.473957,37.981541],"type":"Point"}
}