{
  "type": "Feature",
  "properties": {
    "iso:country":"US",
    "sg:address":"6624 Monument Ave",
    "sg:city":"Portage",
    "sg:classifiers":[
        {
            "category":"Building & Trades",
            "subcategory":"Construction",
            "type":"Services"
        }
    ],
    "sg:phone":"+1 219 764 2033",
    "sg:postcode":"46368",
    "sg:province":"IN",
    "sg:tags":[
        "house"
    ],
    "wof:name":"Action Const",
    "wof:placetype":"venue"
},
  "geometry": {"coordinates":[-87.16231,41.591888],"type":"Point"}
}