{
  "type": "Feature",
  "properties": {
    "iso:country":"US",
    "sg:address":"14020 Buena Vista Rd",
    "sg:city":"Laurel",
    "sg:classifiers":[
        {
            "category":"Freight",
            "type":"Transportation"
        }
    ],
    "sg:phone":"+1 765 679 5128",
    "sg:postcode":"47024",
    "sg:province":"IN",
    "sg:tags":[
        "operator",
        "local",
        "trucking"
    ],
    "wof:name":"John D Byrd",
    "wof:placetype":"venue"
},
  "geometry": {"coordinates":[-85.289006,39.498939],"type":"Point"}
}