{
  "type": "Feature",
  "properties": {
    "iso:country":"US",
    "sg:address":"2832 Edwardsville Galena Rd",
    "sg:city":"Georgetown",
    "sg:classifiers":[
        {
            "category":"Wholesale",
            "subcategory":"Non-durable Goods",
            "type":"Manufacturing & Wholesale Goods"
        }
    ],
    "sg:phone":"+1 812 923 7955",
    "sg:postcode":"47122",
    "sg:province":"IN",
    "wof:name":"Apparel Plus Inc",
    "wof:placetype":"venue"
},
  "geometry": {"coordinates":[-85.93128900000001,38.314484],"type":"Point"}
}