{
  "type": "Feature",
  "properties": {
    "iso:country":"US",
    "sg:address":"300 S Fairview St",
    "sg:city":"Bloomington",
    "sg:classifiers":[
        {
            "category":"Professional",
            "subcategory":"Management & Consulting",
            "type":"Services"
        }
    ],
    "sg:phone":"+1 812 334 3718",
    "sg:postcode":"47403",
    "sg:province":"IN",
    "sg:tags":[
        "administrative"
    ],
    "wof:name":"Wildthings",
    "wof:placetype":"venue"
},
  "geometry": {"coordinates":[-86.540933,39.162883],"type":"Point"}
}