{
  "type": "Feature",
  "properties": {
    "iso:country":"US",
    "sg:address":"1825 N Kinser Pike",
    "sg:city":"Bloomington",
    "sg:classifiers":[
        {
            "category":"Banks & Credit Unions",
            "subcategory":"Bank",
            "type":"Services"
        }
    ],
    "sg:phone":"+1 812 331 3518",
    "sg:postcode":"47404",
    "sg:province":"IN",
    "wof:name":"Monroe Bank",
    "wof:placetype":"venue"
},
  "geometry": {"coordinates":[-86.537887,39.186942],"type":"Point"}
}