{
  "type": "Feature",
  "properties": {
    "iso:country":"US",
    "sg:address":"404 N Jefferson St",
    "sg:city":"Ossian",
    "sg:classifiers":[
        {
            "category":"Food & Beverages",
            "subcategory":"Groceries & Convenience Stores",
            "type":"Retail Goods"
        }
    ],
    "sg:phone":"+1 260 622 7499",
    "sg:postcode":"46777",
    "sg:province":"IN",
    "wof:name":"Ossian Deli Inc",
    "wof:placetype":"venue"
},
  "geometry": {"coordinates":[-85.166557,40.882968],"type":"Point"}
}