{
  "type": "Feature",
  "properties": {
    "iso:country":"US",
    "sg:address":"620 Norris Dr",
    "sg:city":"Anderson",
    "sg:classifiers":[
        {
            "category":"Organizations",
            "subcategory":"Religious Organization",
            "type":"Services"
        }
    ],
    "sg:phone":"+1 765 644 2058",
    "sg:postcode":"46013",
    "sg:province":"IN",
    "sg:tags":[
        "church"
    ],
    "wof:name":"Faith Baptist Church",
    "wof:placetype":"venue"
},
  "geometry": {"coordinates":[-85.668178,40.038419],"type":"Point"}
}