{
  "type": "Feature",
  "properties": {
    "addr:full":"1500 N Detroit St Lagrange IN 46761",
    "addr:housenumber":"1500",
    "addr:postcode":"46761",
    "addr:street":"N Detroit St",
    "iso:country":"US",
    "sg:address":"1500 N Detroit St",
    "sg:city":"Lagrange",
    "sg:classifiers":[
        {
            "category":"Manufacturing",
            "subcategory":"Buildings",
            "type":"Manufacturing & Wholesale Goods"
        }
    ],
    "sg:phone":"+1 260 463 3199",
    "sg:postcode":"46761",
    "sg:province":"IN",
    "sg:tags":[
        "mobile",
        "home"
    ],
    "sg:website":"www.dutch-housing.com",
    "wof:name":"Dutch Housing Inc",
    "wof:placetype":"venue"
},
  "geometry": {"coordinates":[-85.425264,41.663191],"type":"Point"}
}