{
  "type": "Feature",
  "properties": {
    "addr:full":"8232 Allisonville Rd Indianapolis IN 46250",
    "addr:housenumber":"8232",
    "addr:postcode":"46250",
    "addr:street":"Allisonville Rd",
    "iso:country":"US",
    "sg:address":"8232 Allisonville Rd",
    "sg:city":"Indianapolis",
    "sg:classifiers":[
        {
            "category":"Shopping",
            "subcategory":"Bicycles & Sporting Goods",
            "type":"Retail Goods"
        }
    ],
    "sg:phone":"+1 317 570 9811",
    "sg:postcode":"46250",
    "sg:province":"IN",
    "wof:name":"Flymasters",
    "wof:placetype":"venue"
},
  "geometry": {"coordinates":[-86.07820100000001,39.905899],"type":"Point"}
}