{
  "type": "Feature",
  "properties": {
    "addr:full":"2170 N Park Rd Connersville IN 47331",
    "addr:housenumber":"2170",
    "addr:postcode":"47331",
    "addr:street":"N Park Rd",
    "iso:country":"US",
    "sg:address":"2170 N Park Rd",
    "sg:city":"Connersville",
    "sg:classifiers":[
        {
            "category":"Restaurant",
            "type":"Food & Drink"
        }
    ],
    "sg:menulink":"http://www.allmenus.com/in/harrison/120046-subway/menu/",
    "sg:phone":"+1 765 825 7031",
    "sg:postcode":"47331",
    "sg:province":"IN",
    "sg:tags":[
        "american",
        "sandwich"
    ],
    "wof:name":"Subway",
    "wof:placetype":"venue"
},
  "geometry": {"coordinates":[-85.12909000000001,39.660267],"type":"Point"}
}