{
  "type": "Feature",
  "properties": {
    "addr:full":"600 S Georgia St Sheridan IN 46069",
    "addr:housenumber":"600",
    "addr:postcode":"46069",
    "addr:street":"S Georgia St",
    "iso:country":"US",
    "sg:address":"600 S Georgia St",
    "sg:city":"Sheridan",
    "sg:classifiers":[
        {
            "category":"Professional",
            "subcategory":"Computer Services",
            "type":"Services"
        }
    ],
    "sg:phone":"+1 317 758 0027",
    "sg:postcode":"46069",
    "sg:province":"IN",
    "sg:tags":[
        "programing",
        "custom"
    ],
    "wof:name":"Tsarquest Corporation",
    "wof:placetype":"venue"
},
  "geometry": {"coordinates":[-86.21939999999999,40.133469],"type":"Point"}
}