{
  "type": "Feature",
  "properties": {
    "addr:full":"6758 Bear Creek Rd Morgantown IN 46160",
    "addr:housenumber":"6758",
    "addr:postcode":"46160",
    "addr:street":"Bear Creek Rd",
    "iso:country":"US",
    "sg:address":"6758 Bear Creek Rd",
    "sg:city":"Morgantown",
    "sg:classifiers":[
        {
            "category":"Travel",
            "subcategory":"Campground",
            "type":"Entertainment"
        }
    ],
    "sg:phone":"+1 812 597 4692",
    "sg:postcode":"46160",
    "sg:province":"IN",
    "sg:tags":[
        "camp"
    ],
    "wof:name":"Dudley Gallahue Valley Camps",
    "wof:placetype":"venue"
},
  "geometry": {"coordinates":[-86.34553200000001,39.295343],"type":"Point"}
}