{
  "type": "Feature",
  "properties": {
    "addr:full":"2122 State Rd 56 Vevay IN 47043",
    "addr:housenumber":"2122;56",
    "addr:postcode":"vevay;47043",
    "addr:street":"State Rd",
    "iso:country":"US",
    "sg:address":"2122 State Rd 56",
    "sg:city":"Vevay",
    "sg:classifiers":[
        {
            "category":"Wholesale",
            "subcategory":"Farm Supplies",
            "type":"Manufacturing & Wholesale Goods"
        }
    ],
    "sg:phone":"+1 812 534 9655",
    "sg:postcode":"47043",
    "sg:province":"IN",
    "sg:tags":[
        "feed"
    ],
    "wof:name":"Flecher Feed & Supply Inc",
    "wof:placetype":"venue"
},
  "geometry": {"coordinates":[-84.98777,38.88807],"type":"Point"}
}