{
  "type": "Feature",
  "properties": {
    "iso:country":"US",
    "sg:address":"1905 McDonald Ln",
    "sg:city":"New Albany",
    "sg:classifiers":[
        {
            "category":"Wholesale",
            "subcategory":"Durable Goods & Equipment",
            "type":"Manufacturing & Wholesale Goods"
        }
    ],
    "sg:phone":"+1 812 948 0757",
    "sg:postcode":"47150",
    "sg:province":"IN",
    "sg:tags":[
        "fire",
        "extinguisher"
    ],
    "wof:name":"National Fire Equipment Co Inc",
    "wof:placetype":"venue"
},
  "geometry": {"coordinates":[-85.815507,38.322821],"type":"Point"}
}