{
  "type": "Feature",
  "properties": {
    "iso:country":"US",
    "sg:address":"5639 E Greenfield Ave",
    "sg:city":"Indianapolis",
    "sg:classifiers":[
        {
            "category":"Building & Trades",
            "subcategory":"Construction",
            "type":"Services"
        }
    ],
    "sg:phone":"+1 317 353 8417",
    "sg:postcode":"46219",
    "sg:province":"IN",
    "sg:tags":[
        "concrete",
        "contractor"
    ],
    "wof:name":"Vaughn Enterprises Inc",
    "wof:placetype":"venue"
},
  "geometry": {"coordinates":[-86.072083,39.761153],"type":"Point"}
}