{
  "type": "Feature",
  "properties": {
    "addr:full":"2908 165th St Hammond IN 46323",
    "addr:housenumber":"2908",
    "addr:postcode":"46323",
    "addr:street":"165Th St",
    "iso:country":"US",
    "sg:address":"2908 165th St",
    "sg:city":"Hammond",
    "sg:classifiers":[
        {
            "category":"Retail",
            "subcategory":"Auto Repair",
            "type":"Services"
        }
    ],
    "sg:phone":"+1 219 844 4554",
    "sg:postcode":"46323",
    "sg:province":"IN",
    "wof:name":"J R's Automotive Service",
    "wof:placetype":"venue"
},
  "geometry": {"coordinates":[-87.4589,41.595501],"type":"Point"}
}