{
  "type": "Feature",
  "properties": {
    "iso:country":"US",
    "sg:address":"2503 S Sunrise Dr",
    "sg:city":"New Palestine",
    "sg:classifiers":[
        {
            "category":"Building & Trades",
            "subcategory":"Cleaning & Sanitation",
            "type":"Services"
        }
    ],
    "sg:phone":"+1 317 971 2458",
    "sg:postcode":"46163",
    "sg:province":"IN",
    "sg:tags":[
        "janitor"
    ],
    "wof:name":"C & C Cleaning Svc",
    "wof:placetype":"venue"
},
  "geometry": {"coordinates":[-85.94621600000001,39.744806],"type":"Point"}
}