{
  "type": "Feature",
  "properties": {
    "addr:full":"7124 E Centenary Rd Mooresville IN 46158",
    "addr:housenumber":"7124",
    "addr:postcode":"46158",
    "addr:street":"E Centenary Rd",
    "iso:country":"US",
    "sg:address":"7124 E Centenary Rd",
    "sg:city":"Mooresville",
    "sg:classifiers":[
        {
            "category":"Manufacturing",
            "subcategory":"Glass & Minerals",
            "type":"Manufacturing & Wholesale Goods"
        }
    ],
    "sg:phone":"+1 317 834 8415",
    "sg:postcode":"46158",
    "sg:province":"IN",
    "sg:tags":[
        "abrasive",
        "product",
        "mfg"
    ],
    "wof:name":"Saint-Gobain Abrasives Inc",
    "wof:placetype":"venue"
},
  "geometry": {"coordinates":[-86.293133,39.5665],"type":"Point"}
}