{
  "type": "Feature",
  "properties": {
    "addr:full":"973 W 6th Ave Gary IN 46402",
    "addr:housenumber":"973",
    "addr:postcode":"46402",
    "addr:street":"W 6Th Ave",
    "iso:country":"US",
    "sg:address":"973 W 6th Ave",
    "sg:city":"Gary",
    "sg:classifiers":[
        {
            "category":"Organizations",
            "subcategory":"Non-profit Organization",
            "type":"Services"
        }
    ],
    "sg:phone":"+1 219 882 2737",
    "sg:postcode":"46402",
    "sg:province":"IN",
    "wof:name":"Retired Senior Volunteer Prog",
    "wof:placetype":"venue"
},
  "geometry": {"coordinates":[-87.348966,41.600058],"type":"Point"}
}