{
  "type": "Feature",
  "properties": {
    "iso:country":"US",
    "sg:address":"1125 E Walnut St",
    "sg:city":"Boonville",
    "sg:classifiers":[
        {
            "category":"Health Services",
            "subcategory":"Doctor",
            "type":"Services"
        }
    ],
    "sg:phone":"+1 812 897 3506",
    "sg:postcode":"47601",
    "sg:province":"IN",
    "sg:tags":[
        "physician",
        "surgeon"
    ],
    "wof:name":"W H Lee MD",
    "wof:placetype":"venue"
},
  "geometry": {"coordinates":[-87.263671,38.047479],"type":"Point"}
}