{
  "type": "Feature",
  "properties": {
    "addr:full":"430 N Illinois St Monticello IN 47960",
    "addr:housenumber":"430",
    "addr:postcode":"47960",
    "addr:street":"N Illinois St",
    "iso:country":"US",
    "sg:address":"430 N Illinois St",
    "sg:city":"Monticello",
    "sg:classifiers":[
        {
            "category":"Home & Garden",
            "subcategory":"Building Materials",
            "type":"Retail Goods"
        }
    ],
    "sg:phone":"+1 574 583 4191",
    "sg:postcode":"47960",
    "sg:province":"IN",
    "sg:tags":[
        "center"
    ],
    "wof:name":"Monticello Lumber & Tool Rntl",
    "wof:placetype":"venue"
},
  "geometry": {"coordinates":[-86.76354499999999,40.748484],"type":"Point"}
}