{
  "type": "Feature",
  "properties": {
    "iso:country":"US",
    "sg:address":"1918 Elkhart Rd",
    "sg:city":"Goshen",
    "sg:classifiers":[
        {
            "category":"Shopping",
            "subcategory":"Jewelry",
            "type":"Retail Goods"
        }
    ],
    "sg:phone":"+1 574 537 9606",
    "sg:postcode":"46526",
    "sg:province":"IN",
    "sg:tags":[
        "jeweler"
    ],
    "wof:name":"Diamond Outlet",
    "wof:placetype":"venue"
},
  "geometry": {"coordinates":[-85.865691,41.600705],"type":"Point"}
}