{
  "type": "Feature",
  "properties": {
    "iso:country":"US",
    "sg:address":"3114 W Mishawaka Ave",
    "sg:city":"South Bend",
    "sg:classifiers":[
        {
            "category":"Banks & Credit Unions",
            "subcategory":"Bank",
            "type":"Services"
        }
    ],
    "sg:phone":"+1 574 232 5500",
    "sg:postcode":"46615",
    "sg:province":"IN",
    "sg:tags":[
        "loan",
        "real estate"
    ],
    "wof:name":"North Star Mortgage",
    "wof:placetype":"venue"
},
  "geometry": {"coordinates":[-86.20336500000001,41.665647],"type":"Point"}
}