{
  "type": "Feature",
  "properties": {
    "iso:country":"US",
    "sg:address":"2900 Mitchell Rd",
    "sg:city":"Bedford",
    "sg:classifiers":[
        {
            "category":"Wholesale",
            "subcategory":"Hardware",
            "type":"Manufacturing & Wholesale Goods"
        }
    ],
    "sg:phone":"+1 812 275 4473",
    "sg:postcode":"47421",
    "sg:province":"IN",
    "sg:tags":[
        "plumbing",
        "fixture",
        "supply"
    ],
    "sg:website":"www.cpisupply.com",
    "wof:name":"CPI Supply",
    "wof:placetype":"venue"
},
  "geometry": {"coordinates":[-86.54746299999999,38.868639],"type":"Point"}
}