{
  "type": "Feature",
  "properties": {
    "iso:country":"US",
    "sg:address":"249 E Rudisill Blvd",
    "sg:city":"Fort Wayne",
    "sg:classifiers":[
        {
            "category":"Autos & Motor Vehicles",
            "subcategory":"Fuel & Gas Station",
            "type":"Retail Goods"
        }
    ],
    "sg:phone":"+1 260 744 1951",
    "sg:postcode":"46806",
    "sg:province":"IN",
    "sg:tags":[
        "oil"
    ],
    "wof:name":"Clark",
    "wof:placetype":"venue"
},
  "geometry": {"coordinates":[-85.133992,41.050168],"type":"Point"}
}