{
  "type": "Feature",
  "properties": {
    "iso:country":"US",
    "sg:address":"52124 Fir Rd",
    "sg:city":"Granger",
    "sg:classifiers":[
        {
            "category":"Building & Trades",
            "subcategory":"Construction",
            "type":"Services"
        }
    ],
    "sg:phone":"+1 574 243 4910",
    "sg:postcode":"46530",
    "sg:province":"IN",
    "sg:tags":[
        "contractor"
    ],
    "wof:name":"Sharp Tile",
    "wof:placetype":"venue"
},
  "geometry": {"coordinates":[-86.15876299999999,41.734845],"type":"Point"}
}