{
  "type": "Feature",
  "properties": {
    "addr:full":"222 E Market St Indianapolis IN 46204",
    "addr:housenumber":"222",
    "addr:postcode":"46204",
    "addr:street":"E Market St",
    "iso:country":"US",
    "sg:address":"222 E Market St",
    "sg:city":"Indianapolis",
    "sg:classifiers":[
        {
            "category":"Restaurant",
            "type":"Food & Drink"
        }
    ],
    "sg:phone":"+1 317 638 3354",
    "sg:postcode":"46204",
    "sg:province":"IN",
    "wof:name":"LA Cucina",
    "wof:placetype":"venue"
},
  "geometry": {"coordinates":[-86.152914,39.768481],"type":"Point"}
}