{
  "type": "Feature",
  "properties": {
    "iso:country":"US",
    "sg:address":"114 S Meridian St",
    "sg:city":"Goldsmith",
    "sg:classifiers":[
        {
            "category":"Building & Trades",
            "subcategory":"Electrical",
            "type":"Services"
        }
    ],
    "sg:phone":"+1 765 963 5650",
    "sg:postcode":"46072",
    "sg:province":"IN",
    "sg:tags":[
        "electrical",
        "electric",
        "contractor"
    ],
    "wof:name":"Connection Residential & Comm",
    "wof:placetype":"venue"
},
  "geometry": {"coordinates":[-86.1493,40.288433],"type":"Point"}
}