{
  "type": "Feature",
  "properties": {
    "iso:country":"US",
    "sg:address":"6411 W 11th St",
    "sg:city":"Indianapolis",
    "sg:classifiers":[
        {
            "category":"Building & Trades",
            "subcategory":"Construction",
            "type":"Services"
        }
    ],
    "sg:phone":"+1 317 243 7140",
    "sg:postcode":"46214",
    "sg:province":"IN",
    "sg:tags":[
        "general",
        "contractor"
    ],
    "wof:name":"White Oak Construction",
    "wof:placetype":"venue"
},
  "geometry": {"coordinates":[-86.273353,39.780634],"type":"Point"}
}