{
  "type": "Feature",
  "properties": {
    "iso:country":"US",
    "sg:address":"1915 Toledo Rd",
    "sg:city":"Elkhart",
    "sg:classifiers":[
        {
            "category":"Building & Trades",
            "subcategory":"Construction",
            "type":"Services"
        }
    ],
    "sg:phone":"+1 574 293 1126",
    "sg:postcode":"46516",
    "sg:province":"IN",
    "sg:tags":[
        "designer",
        "dealer",
        "pool",
        "swimming"
    ],
    "wof:name":"Backyard Pools",
    "wof:placetype":"venue"
},
  "geometry": {"coordinates":[-85.932741,41.677549],"type":"Point"}
}