{
  "type": "Feature",
  "properties": {
    "addr:full":"1500 W Markland Ave Kokomo IN 46901",
    "addr:housenumber":"1500",
    "addr:postcode":"46901",
    "addr:street":"W Markland Ave",
    "iso:country":"US",
    "sg:address":"1500 W Markland Ave",
    "sg:city":"Kokomo",
    "sg:classifiers":[
        {
            "category":"Freight",
            "type":"Transportation"
        }
    ],
    "sg:phone":"+1 765 868 9960",
    "sg:postcode":"46901",
    "sg:province":"IN",
    "sg:tags":[
        "hauling",
        "trucking"
    ],
    "wof:name":"Edward's Hauling",
    "wof:placetype":"venue"
},
  "geometry": {"coordinates":[-86.14976900000001,40.476333],"type":"Point"}
}