{
  "type": "Feature",
  "properties": {
    "addr:full":"8666 Ruffian Ln Newburgh IN 47630",
    "addr:housenumber":"8666",
    "addr:postcode":"47630",
    "addr:street":"Ruffian Ln",
    "iso:country":"US",
    "sg:address":"8666 Ruffian Ln",
    "sg:city":"Newburgh",
    "sg:classifiers":[
        {
            "category":"Shopping",
            "subcategory":"Florist",
            "type":"Retail Goods"
        }
    ],
    "sg:phone":"+1 812 853 2900",
    "sg:postcode":"47630",
    "sg:province":"IN",
    "sg:website":"www.zeidlers.com",
    "wof:name":"Zeidler's Flowers Garden & Gifts",
    "wof:placetype":"venue"
},
  "geometry": {"coordinates":[-87.408661,37.97572],"type":"Point"}
}