{
  "type": "Feature",
  "properties": {
    "addr:full":"2717 Gay St Fort Wayne IN 46806",
    "addr:housenumber":"2717",
    "addr:postcode":"46806",
    "addr:street":"Gay St",
    "iso:country":"US",
    "sg:address":"2717 Gay St",
    "sg:city":"Fort Wayne",
    "sg:classifiers":[
        {
            "category":"Organizations",
            "subcategory":"Religious Organization",
            "type":"Services"
        }
    ],
    "sg:phone":"+1 260 456 5063",
    "sg:postcode":"46806",
    "sg:province":"IN",
    "wof:name":"Faith Missionary Bapt Church",
    "wof:placetype":"venue"
},
  "geometry": {"coordinates":[-85.124143,41.05919],"type":"Point"}
}