{
  "type": "Feature",
  "properties": {
    "iso:country":"US",
    "sg:address":"2503 S Main St",
    "sg:city":"Elkhart",
    "sg:classifiers":[
        {
            "category":"Retail",
            "subcategory":"Laundry & Dry Cleaning",
            "type":"Services"
        }
    ],
    "sg:phone":"+1 574 294 7241",
    "sg:postcode":"46517",
    "sg:province":"IN",
    "wof:name":"Russells Alteration Shop",
    "wof:placetype":"venue"
},
  "geometry": {"coordinates":[-85.950368,41.662204],"type":"Point"}
}