{
  "type": "Feature",
  "properties": {
    "iso:country":"US",
    "sg:address":"50648 Glen Meadow Ln",
    "sg:city":"Granger",
    "sg:classifiers":[
        {
            "category":"Manufacturing",
            "subcategory":"Textiles",
            "type":"Manufacturing & Wholesale Goods"
        }
    ],
    "sg:phone":"+1 574 277 6160",
    "sg:postcode":"46530",
    "sg:province":"IN",
    "sg:tags":[
        "mill",
        "fabric",
        "cotton"
    ],
    "wof:name":"Cynthia Bergstrand",
    "wof:placetype":"venue"
},
  "geometry": {"coordinates":[-86.17215299999999,41.757345],"type":"Point"}
}