{
  "type": "Feature",
  "properties": {
    "iso:country":"US",
    "sg:address":"5729 W Minnesota St",
    "sg:city":"Indianapolis",
    "sg:classifiers":[
        {
            "category":"Building & Trades",
            "subcategory":"Construction",
            "type":"Services"
        }
    ],
    "sg:phone":"+1 317 227 8060",
    "sg:postcode":"46241",
    "sg:province":"IN",
    "sg:tags":[
        "floor",
        "laying",
        "contractor"
    ],
    "wof:name":"Carpet Decorators Inc",
    "wof:placetype":"venue"
},
  "geometry": {"coordinates":[-86.257838,39.742955],"type":"Point"}
}