{
  "type": "Feature",
  "properties": {
    "addr:full":"1802 N Tibbs Ave Indianapolis IN 46222",
    "addr:housenumber":"1802",
    "addr:postcode":"46222",
    "addr:street":"N Tibbs Ave",
    "iso:country":"US",
    "sg:address":"1802 N Tibbs Ave",
    "sg:city":"Indianapolis",
    "sg:classifiers":[
        {
            "category":"Building & Trades",
            "subcategory":"Plumbing",
            "type":"Services"
        }
    ],
    "sg:phone":"+1 317 631 5941",
    "sg:postcode":"46222",
    "sg:province":"IN",
    "sg:tags":[
        "heating",
        "contractor"
    ],
    "sg:website":"www.smithandsonheating.com",
    "wof:name":"Smith & Son Inc Heating & AC",
    "wof:placetype":"venue"
},
  "geometry": {"coordinates":[-86.21592,39.79329],"type":"Point"}
}