{
  "type": "Feature",
  "properties": {
    "iso:country":"US",
    "sg:address":"6380 Rockville Rd",
    "sg:city":"Indianapolis",
    "sg:classifiers":[
        {
            "category":"Shopping",
            "subcategory":"Florist",
            "type":"Retail Goods"
        }
    ],
    "sg:phone":"+1 317 243 4245",
    "sg:postcode":"46214",
    "sg:province":"IN",
    "wof:name":"Berkshire Florists",
    "wof:placetype":"venue"
},
  "geometry": {"coordinates":[-86.272826,39.764733],"type":"Point"}
}