{
  "type": "Feature",
  "properties": {
    "iso:country":"US",
    "sg:address":"540 W 30th St",
    "sg:city":"Connersville",
    "sg:classifiers":[
        {
            "category":"Shopping",
            "subcategory":"Department Store",
            "type":"Retail Goods"
        }
    ],
    "sg:phone":"+1 765 825 1603",
    "sg:postcode":"47331",
    "sg:province":"IN",
    "sg:tags":[
        "shop"
    ],
    "wof:name":"Dollar General",
    "wof:placetype":"venue"
},
  "geometry": {"coordinates":[-85.135586,39.671717],"type":"Point"}
}