{
  "type": "Feature",
  "properties": {
    "addr:full":"4373 N 900 E Wilkinson IN 46186",
    "addr:housenumber":"4373",
    "addr:postcode":"46186",
    "addr:street":"N 900 E",
    "iso:country":"US",
    "sg:address":"4373 N 900 E",
    "sg:city":"Wilkinson",
    "sg:classifiers":[
        {
            "category":"Wholesale",
            "subcategory":"Drugs",
            "type":"Manufacturing & Wholesale Goods"
        }
    ],
    "sg:phone":"+1 765 785 9370",
    "sg:postcode":"46186",
    "sg:province":"IN",
    "sg:tags":[
        "pharmaceutical",
        "product"
    ],
    "wof:name":"Eli Lilly & Co",
    "wof:placetype":"venue"
},
  "geometry": {"coordinates":[-85.63544899999999,39.847627],"type":"Point"}
}