{
  "type": "Feature",
  "properties": {
    "iso:country":"US",
    "sg:address":"111 W 10th St",
    "sg:city":"Hobart",
    "sg:classifiers":[
        {
            "category":"Insurance",
            "subcategory":"Title Insurance",
            "type":"Services"
        }
    ],
    "sg:phone":"+1 219 942 4959",
    "sg:postcode":"46342",
    "sg:province":"IN",
    "wof:name":"Ticor Title Insurance",
    "wof:placetype":"venue"
},
  "geometry": {"coordinates":[-87.26275,41.521731],"type":"Point"}
}