{
  "type": "Feature",
  "properties": {
    "addr:full":"2125 N 25th St Terre Haute IN 47804",
    "addr:housenumber":"2125",
    "addr:postcode":"47804",
    "addr:street":"N 25Th St",
    "iso:country":"US",
    "sg:address":"2125 N 25th St",
    "sg:city":"Terre Haute",
    "sg:classifiers":[
        {
            "category":"Restaurant",
            "type":"Food & Drink"
        }
    ],
    "sg:phone":"+1 812 235 7990",
    "sg:postcode":"47804",
    "sg:province":"IN",
    "wof:name":"Rosselli's Club 70 Restaurant",
    "wof:placetype":"venue"
},
  "geometry": {"coordinates":[-87.379014,39.491253],"type":"Point"}
}