{
  "type": "Feature",
  "properties": {
    "addr:full":"530 S Main St Churubusco IN 46723",
    "addr:housenumber":"530",
    "addr:postcode":"46723",
    "addr:street":"S Main St",
    "iso:country":"US",
    "sg:address":"530 S Main St",
    "sg:city":"Churubusco",
    "sg:classifiers":[
        {
            "category":"Sports & Exercise",
            "subcategory":"Gym",
            "type":"Entertainment"
        }
    ],
    "sg:phone":"+1 260 693 3838",
    "sg:postcode":"46723",
    "sg:province":"IN",
    "sg:tags":[
        "club",
        "health",
        "studio",
        "gymnasium"
    ],
    "wof:name":"Curves For Women",
    "wof:placetype":"venue"
},
  "geometry": {"coordinates":[-85.31809699999999,41.228185],"type":"Point"}
}