{
  "type": "Feature",
  "properties": {
    "iso:country":"US",
    "sg:address":"2974 US Hwy 27",
    "sg:city":"Richmond",
    "sg:classifiers":[
        {
            "category":"Retail",
            "subcategory":"Repair Shop",
            "type":"Services"
        }
    ],
    "sg:phone":"+1 765 966 0076",
    "sg:postcode":"47374",
    "sg:province":"IN",
    "sg:tags":[
        "television",
        "radio"
    ],
    "wof:name":"Bill's TV Svc",
    "wof:placetype":"venue"
},
  "geometry": {"coordinates":[-84.901493,39.787381],"type":"Point"}
}