{
  "type": "Feature",
  "properties": {
    "iso:country":"US",
    "sg:address":"12414 Parrish Ave",
    "sg:city":"Cedar Lake",
    "sg:classifiers":[
        {
            "category":"Professional",
            "subcategory":"Business Services",
            "type":"Services"
        }
    ],
    "sg:phone":"+1 219 374 6701",
    "sg:postcode":"46303",
    "sg:province":"IN",
    "wof:name":"Tgm Enterprises Inc",
    "wof:placetype":"venue"
},
  "geometry": {"coordinates":[-87.451241,41.393502],"type":"Point"}
}