{
  "type": "Feature",
  "properties": {
    "addr:full":"10333 N Meridian St Indianapolis IN 46290",
    "addr:housenumber":"10333",
    "addr:postcode":"46290",
    "addr:street":"N Meridian St",
    "iso:country":"US",
    "sg:address":"10333 N Meridian St",
    "sg:city":"Indianapolis",
    "sg:classifiers":[
        {
            "category":"Communications",
            "type":"Services"
        }
    ],
    "sg:phone":"+1 317 569 6781",
    "sg:postcode":"46290",
    "sg:province":"IN",
    "wof:name":"Connect Communications",
    "wof:placetype":"venue"
},
  "geometry": {"coordinates":[-86.157833,39.92873],"type":"Point"}
}