{
  "type": "Feature",
  "properties": {
    "iso:country":"US",
    "sg:address":"3706 E Tamarron Dr",
    "sg:city":"Bloomington",
    "sg:classifiers":[
        {
            "category":"Professional",
            "subcategory":"Management & Consulting",
            "type":"Services"
        }
    ],
    "sg:phone":"+1 812 323 9244",
    "sg:postcode":"47408",
    "sg:province":"IN",
    "sg:tags":[
        "economic"
    ],
    "wof:name":"Michael Alexeev",
    "wof:placetype":"venue"
},
  "geometry": {"coordinates":[-86.484505,39.17575],"type":"Point"}
}