{
  "type": "Feature",
  "properties": {
    "iso:country":"US",
    "sg:address":"7806 State Rd 311",
    "sg:city":"Sellersburg",
    "sg:classifiers":[
        {
            "category":"Retail",
            "subcategory":"Funeral Services",
            "type":"Services"
        }
    ],
    "sg:phone":"+1 812 246 3344",
    "sg:postcode":"47172",
    "sg:province":"IN",
    "sg:tags":[
        "director"
    ],
    "wof:name":"Garr Funeral Home",
    "wof:placetype":"venue"
},
  "geometry": {"coordinates":[-85.767314,38.384344],"type":"Point"}
}