{
  "type": "Feature",
  "properties": {
    "iso:country":"US",
    "sg:address":"322 W 3rd St",
    "sg:city":"Bloomington",
    "sg:classifiers":[
        {
            "category":"Autos & Motor Vehicles",
            "subcategory":"Motorcycle Sales",
            "type":"Retail Goods"
        }
    ],
    "sg:phone":"+1 812 332 5262",
    "sg:postcode":"47404",
    "sg:province":"IN",
    "sg:tags":[
        "scooter"
    ],
    "wof:name":"Fox's Cycle Sales",
    "wof:placetype":"venue"
},
  "geometry": {"coordinates":[-86.536697,39.1647],"type":"Point"}
}