{
  "type": "Feature",
  "properties": {
    "iso:country":"US",
    "sg:address":"52051 Glen Arbor Ct",
    "sg:city":"Granger",
    "sg:classifiers":[
        {
            "category":"Organizations",
            "subcategory":"Religious Organization",
            "type":"Services"
        }
    ],
    "sg:phone":"+1 574 243 0227",
    "sg:postcode":"46530",
    "sg:province":"IN",
    "sg:tags":[
        "clergy"
    ],
    "wof:name":"James B Miller",
    "wof:placetype":"venue"
},
  "geometry": {"coordinates":[-86.169571,41.737591],"type":"Point"}
}