{
  "type": "Feature",
  "properties": {
    "iso:country":"US",
    "sg:address":"12120 Chase St",
    "sg:city":"Crown Point",
    "sg:classifiers":[
        {
            "category":"Building & Trades",
            "subcategory":"Construction",
            "type":"Services"
        }
    ],
    "sg:phone":"+1 219 662 7275",
    "sg:postcode":"46307",
    "sg:province":"IN",
    "sg:tags":[
        "woodworker"
    ],
    "wof:name":"MDM Woddworking Svc",
    "wof:placetype":"venue"
},
  "geometry": {"coordinates":[-87.370942,41.376445],"type":"Point"}
}