{
  "type": "Feature",
  "properties": {
    "iso:country":"US",
    "sg:address":"2124 Elkhart Rd",
    "sg:city":"Goshen",
    "sg:classifiers":[
        {
            "category":"Restaurant",
            "type":"Food & Drink"
        }
    ],
    "sg:phone":"+1 574 533 3858",
    "sg:postcode":"46526",
    "sg:province":"IN",
    "sg:tags":[
        "mexican"
    ],
    "wof:name":"Mi Casita",
    "wof:placetype":"venue"
},
  "geometry": {"coordinates":[-85.86441000000001,41.600014],"type":"Point"}
}