{
  "type": "Feature",
  "properties": {
    "iso:country":"US",
    "sg:address":"921 S 4th St",
    "sg:city":"Gas City",
    "sg:classifiers":[
        {
            "category":"Freight",
            "type":"Transportation"
        }
    ],
    "sg:phone":"+1 765 674 9354",
    "sg:postcode":"46933",
    "sg:province":"IN",
    "sg:tags":[
        "trucking"
    ],
    "wof:name":"T C Trucking Of Marion Inc",
    "wof:placetype":"venue"
},
  "geometry": {"coordinates":[-85.608726,40.480008],"type":"Point"}
}