{
  "type": "Feature",
  "properties": {
    "iso:country":"US",
    "sg:address":"405 S Poplar St",
    "sg:city":"Seymour",
    "sg:classifiers":[
        {
            "category":"Shopping",
            "subcategory":"Bicycles & Sporting Goods",
            "type":"Retail Goods"
        }
    ],
    "sg:phone":"+1 812 522 4008",
    "sg:postcode":"47274",
    "sg:province":"IN",
    "sg:tags":[
        "gun",
        "gunsmith"
    ],
    "wof:name":"Acme Sports",
    "wof:placetype":"venue"
},
  "geometry": {"coordinates":[-85.89169200000001,38.954475],"type":"Point"}
}