{
  "type": "Feature",
  "properties": {
    "iso:country":"US",
    "sg:address":"7752 Cobblesprings Dr",
    "sg:city":"Avon",
    "sg:classifiers":[
        {
            "category":"Retail",
            "subcategory":"Car Wash",
            "type":"Services"
        }
    ],
    "sg:phone":"+1 317 272 2660",
    "sg:postcode":"46123",
    "sg:province":"IN",
    "sg:tags":[
        "polishing",
        "washing"
    ],
    "wof:name":"Splash Car Wash",
    "wof:placetype":"venue"
},
  "geometry": {"coordinates":[-86.384166,39.76799],"type":"Point"}
}