{
  "type": "Feature",
  "properties": {
    "iso:country":"US",
    "sg:address":"23986 State Line Rd",
    "sg:city":"Lawrenceburg",
    "sg:classifiers":[
        {
            "category":"Personal",
            "subcategory":"Beauty Salon",
            "type":"Services"
        }
    ],
    "sg:phone":"+1 812 637 9222",
    "sg:postcode":"47025",
    "sg:province":"IN",
    "wof:name":"Nassau Beauty Salon",
    "wof:placetype":"venue"
},
  "geometry": {"coordinates":[-84.85587,39.218494],"type":"Point"}
}