{
  "type": "Feature",
  "properties": {
    "iso:country":"US",
    "sg:address":"811 W Main St",
    "sg:city":"North Manchester",
    "sg:classifiers":[
        {
            "category":"Autos & Motor Vehicles",
            "subcategory":"Automobile Sales",
            "type":"Retail Goods"
        }
    ],
    "sg:phone":"+1 260 982 4405",
    "sg:postcode":"46962",
    "sg:province":"IN",
    "sg:tags":[
        "car",
        "dealer"
    ],
    "wof:name":"Village Auto Sales",
    "wof:placetype":"venue"
},
  "geometry": {"coordinates":[-85.778896,40.998866],"type":"Point"}
}