{
  "type": "Feature",
  "properties": {
    "iso:country":"US",
    "sg:address":"10203 E Washington St",
    "sg:city":"Indianapolis",
    "sg:classifiers":[
        {
            "category":"Shopping",
            "subcategory":"Shoes",
            "type":"Retail Goods"
        }
    ],
    "sg:phone":"+1 317 895 2400",
    "sg:postcode":"46229",
    "sg:province":"IN",
    "wof:name":"Shoe Carnival",
    "wof:placetype":"venue"
},
  "geometry": {"coordinates":[-85.985395,39.775035],"type":"Point"}
}