{
  "type": "Feature",
  "properties": {
    "iso:country":"US",
    "sg:address":"6832 Kentland Dr",
    "sg:city":"Indianapolis",
    "sg:classifiers":[
        {
            "category":"Professional",
            "subcategory":"Management & Consulting",
            "type":"Services"
        }
    ],
    "sg:phone":"+1 317 783 4197",
    "sg:postcode":"46237",
    "sg:province":"IN",
    "sg:tags":[
        "consultant",
        "safety"
    ],
    "wof:name":"Pro Train",
    "wof:placetype":"venue"
},
  "geometry": {"coordinates":[-86.048103,39.669251],"type":"Point"}
}