{
  "type": "Feature",
  "properties": {
    "iso:country":"US",
    "sg:address":"1019 W Sycamore St",
    "sg:city":"Kokomo",
    "sg:classifiers":[
        {
            "category":"Personal",
            "subcategory":"Beauty Salon",
            "type":"Services"
        }
    ],
    "sg:phone":"+1 765 868 9420",
    "sg:postcode":"46901",
    "sg:province":"IN",
    "sg:tags":[
        "cosmetologist"
    ],
    "wof:name":"Anne Schaeffer",
    "wof:placetype":"venue"
},
  "geometry": {"coordinates":[-86.14227,40.486296],"type":"Point"}
}