{
  "type": "Feature",
  "properties": {
    "iso:country":"US",
    "sg:address":"6327 Constitution Dr",
    "sg:city":"Fort Wayne",
    "sg:classifiers":[
        {
            "category":"Freight",
            "type":"Transportation"
        }
    ],
    "sg:phone":"+1 260 969 2201",
    "sg:postcode":"46804",
    "sg:province":"IN",
    "sg:tags":[
        "broker",
        "trucking"
    ],
    "wof:name":"P S Transport",
    "wof:placetype":"venue"
},
  "geometry": {"coordinates":[-85.226387,41.067863],"type":"Point"}
}