{
  "type": "Feature",
  "properties": {
    "iso:country":"US",
    "sg:address":"2804 N 1st Ave",
    "sg:city":"Evansville",
    "sg:classifiers":[
        {
            "category":"Professional",
            "subcategory":"Lawyer & Legal Services",
            "type":"Services"
        }
    ],
    "sg:phone":"+1 812 423 1500",
    "sg:postcode":"47710",
    "sg:province":"IN",
    "sg:tags":[
        "attorney"
    ],
    "wof:name":"Glenn A Deig",
    "wof:placetype":"venue"
},
  "geometry": {"coordinates":[-87.574442,38.005044],"type":"Point"}
}