{
  "type": "Feature",
  "properties": {
    "addr:full":"302 E Washington St Waynetown IN 47990",
    "addr:housenumber":"302",
    "addr:postcode":"47990",
    "addr:street":"E Washington St",
    "iso:country":"US",
    "sg:address":"302 E Washington St",
    "sg:city":"Waynetown",
    "sg:classifiers":[
        {
            "category":"Food & Beverages",
            "subcategory":"Groceries & Convenience Stores",
            "type":"Retail Goods"
        }
    ],
    "sg:phone":"+1 765 234 2700",
    "sg:postcode":"47990",
    "sg:province":"IN",
    "wof:name":"F & F Mart",
    "wof:placetype":"venue"
},
  "geometry": {"coordinates":[-87.060534,40.08786],"type":"Point"}
}