{
  "type": "Feature",
  "properties": {
    "iso:country":"US",
    "sg:address":"1214 S State Ave",
    "sg:city":"Indianapolis",
    "sg:classifiers":[
        {
            "category":"Building & Trades",
            "subcategory":"Construction",
            "type":"Services"
        }
    ],
    "sg:phone":"+1 317 636 3356",
    "sg:postcode":"46203",
    "sg:province":"IN",
    "sg:tags":[
        "general",
        "contractor"
    ],
    "wof:name":"Zimmer's Contractors",
    "wof:placetype":"venue"
},
  "geometry": {"coordinates":[-86.130737,39.751288],"type":"Point"}
}