{
  "type": "Feature",
  "properties": {
    "iso:country":"US",
    "sg:address":"6897 E Co Rd 1150 N",
    "sg:city":"Sunman",
    "sg:classifiers":[
        {
            "category":"Farming",
            "subcategory":"Livestock Farm",
            "type":"Manufacturing & Wholesale Goods"
        }
    ],
    "sg:phone":"+1 812 623 3522",
    "sg:postcode":"47041",
    "sg:province":"IN",
    "sg:tags":[
        "c",
        "wheat",
        "beef",
        "corn",
        "field",
        "cattle",
        "feedlot"
    ],
    "wof:name":"Orville Kunkel",
    "wof:placetype":"venue"
},
  "geometry": {"coordinates":[-85.142012,39.243752],"type":"Point"}
}