{
  "type": "Feature",
  "properties": {
    "addr:full":"2100 Market St Charlestown IN 47111",
    "addr:housenumber":"2100",
    "addr:postcode":"47111",
    "addr:street":"Market St",
    "iso:country":"US",
    "sg:address":"2100 Market St",
    "sg:city":"Charlestown",
    "sg:classifiers":[
        {
            "category":"Health Services",
            "subcategory":"Doctor",
            "type":"Services"
        }
    ],
    "sg:phone":"+1 812 256 6167",
    "sg:postcode":"47111",
    "sg:province":"IN",
    "sg:tags":[
        "physician",
        "surgeon"
    ],
    "wof:name":"Henry Byrum MD",
    "wof:placetype":"venue"
},
  "geometry": {"coordinates":[-85.669071,38.471199],"type":"Point"}
}