{
  "type": "Feature",
  "properties": {
    "iso:country":"US",
    "sg:address":"3906 S State Rd 3",
    "sg:city":"New Castle",
    "sg:classifiers":[
        {
            "category":"Government",
            "subcategory":"Office",
            "type":"Public Place"
        }
    ],
    "sg:phone":"+1 765 529 6520",
    "sg:postcode":"47362",
    "sg:province":"IN",
    "sg:tags":[
        "state",
        "program"
    ],
    "wof:name":"Transportation Dept",
    "wof:placetype":"venue"
},
  "geometry": {"coordinates":[-85.38861199999999,39.874657],"type":"Point"}
}