{
  "type": "Feature",
  "properties": {
    "addr:full":"435 Eastern Blvd Clarksville IN 47129",
    "addr:housenumber":"435",
    "addr:postcode":"47129",
    "addr:street":"Eastern Blvd",
    "iso:country":"US",
    "sg:address":"435 Eastern Blvd",
    "sg:city":"Clarksville",
    "sg:classifiers":[
        {
            "category":"Organizations",
            "subcategory":"Religious Organization",
            "type":"Services"
        }
    ],
    "sg:phone":"+1 812 283 0776",
    "sg:postcode":"47129",
    "sg:province":"IN",
    "sg:tags":[
        "church"
    ],
    "sg:website":"www.mortonchurch.org",
    "wof:name":"Morton Meml United Methodist",
    "wof:placetype":"venue"
},
  "geometry": {"coordinates":[-85.756187,38.294258],"type":"Point"}
}