{
  "type": "Feature",
  "properties": {
    "iso:country":"US",
    "sg:address":"4624 Walker St",
    "sg:city":"Greenwood",
    "sg:classifiers":[
        {
            "category":"Education",
            "subcategory":"Vocational School",
            "type":"Public Place"
        }
    ],
    "sg:phone":"+1 317 887 3107",
    "sg:postcode":"46143",
    "sg:province":"IN",
    "sg:tags":[
        "contract"
    ],
    "wof:name":"Donald Young Owner",
    "wof:placetype":"venue"
},
  "geometry": {"coordinates":[-86.19220300000001,39.604262],"type":"Point"}
}