{
  "type": "Feature",
  "properties": {
    "iso:country":"US",
    "sg:address":"1417 S Walnut St",
    "sg:city":"Muncie",
    "sg:classifiers":[
        {
            "category":"Recreation",
            "type":"Entertainment"
        }
    ],
    "sg:phone":"+1 765 282 8376",
    "sg:postcode":"47302",
    "sg:province":"IN",
    "sg:tags":[
        "parlor",
        "billiard"
    ],
    "wof:name":"Jimmy's Recreation",
    "wof:placetype":"venue"
},
  "geometry": {"coordinates":[-85.386513,40.18211],"type":"Point"}
}