{
  "type": "Feature",
  "properties": {
    "addr:full":"701 Henry St North Vernon IN 47265",
    "addr:housenumber":"701",
    "addr:postcode":"47265",
    "addr:street":"Henry St",
    "iso:country":"US",
    "sg:address":"701 Henry St",
    "sg:city":"North Vernon",
    "sg:classifiers":[
        {
            "category":"Health Services",
            "subcategory":"Clinic",
            "type":"Services"
        },
        {
            "category":"Social Services",
            "subcategory":"Job Training",
            "type":"Services"
        }
    ],
    "sg:phone":"+1 812 352 9723",
    "sg:postcode":"47265",
    "sg:province":"IN",
    "sg:tags":[
        "rehabilitation",
        "outpatient",
        "specialty"
    ],
    "wof:name":"Paragon Rehab Inc",
    "wof:placetype":"venue"
},
  "geometry": {"coordinates":[-85.641222,39.011242],"type":"Point"}
}