{
  "type": "Feature",
  "properties": {
    "iso:country":"US",
    "sg:address":"1130 S Lynhurst Dr",
    "sg:city":"Indianapolis",
    "sg:classifiers":[
        {
            "category":"Retail",
            "subcategory":"Auto Repair",
            "type":"Services"
        }
    ],
    "sg:phone":"+1 317 247 5599",
    "sg:postcode":"46241",
    "sg:province":"IN",
    "sg:tags":[
        "repairing",
        "automobile"
    ],
    "wof:name":"Eddie's Auto Svc",
    "wof:placetype":"venue"
},
  "geometry": {"coordinates":[-86.25018300000001,39.752851],"type":"Point"}
}