{
  "type": "Feature",
  "properties": {
    "iso:country":"US",
    "sg:address":"2106 Clark Rd",
    "sg:city":"Gary",
    "sg:classifiers":[
        {
            "category":"Professional",
            "subcategory":"Accounting & Tax Preparation",
            "type":"Services"
        }
    ],
    "sg:phone":"+1 219 949 0100",
    "sg:postcode":"46404",
    "sg:province":"IN",
    "sg:tags":[
        "return",
        "filing"
    ],
    "wof:name":"Dungy's Accounting & Tax Svc",
    "wof:placetype":"venue"
},
  "geometry": {"coordinates":[-87.393883,41.578947],"type":"Point"}
}