{
  "type": "Feature",
  "properties": {
    "addr:full":"1780 E US Hwy 40 Greencastle IN 46135",
    "addr:housenumber":"1780",
    "addr:postcode":"46135",
    "addr:street":"E Us Hwy 40 Greencastle",
    "iso:country":"US",
    "sg:address":"1780 E US Hwy 40",
    "sg:city":"Greencastle",
    "sg:classifiers":[
        {
            "category":"Education",
            "subcategory":"School",
            "type":"Public Place"
        }
    ],
    "sg:phone":"+1 765 653 3148",
    "sg:postcode":"46135",
    "sg:province":"IN",
    "sg:website":"www.sputnam.k12.in.us",
    "wof:name":"South Putman High School",
    "wof:placetype":"venue"
},
  "geometry": {"coordinates":[-86.81744399999999,39.585204],"type":"Point"}
}