{
  "type": "Feature",
  "properties": {
    "iso:country":"US",
    "sg:address":"921 N Willow St",
    "sg:city":"Rushville",
    "sg:classifiers":[
        {
            "category":"Organizations",
            "subcategory":"Religious Organization",
            "type":"Services"
        }
    ],
    "sg:phone":"+1 765 938 5581",
    "sg:postcode":"46173",
    "sg:province":"IN",
    "wof:name":"Christian Sexton Church",
    "wof:placetype":"venue"
},
  "geometry": {"coordinates":[-85.441998,39.616345],"type":"Point"}
}