{
  "type": "Feature",
  "properties": {
    "iso:country":"US",
    "sg:address":"1025 N State St",
    "sg:city":"Greenfield",
    "sg:classifiers":[
        {
            "category":"Banks & Credit Unions",
            "subcategory":"Bank",
            "type":"Services"
        }
    ],
    "sg:phone":"+1 317 467 5626",
    "sg:postcode":"46140",
    "sg:province":"IN",
    "sg:tags":[
        "cashing",
        "check"
    ],
    "wof:name":"Cash Today",
    "wof:placetype":"venue"
},
  "geometry": {"coordinates":[-85.76968599999999,39.799437],"type":"Point"}
}