{
  "type": "Feature",
  "properties": {
    "iso:country":"US",
    "sg:address":"2804 Dawnlake Dr",
    "sg:city":"Indianapolis",
    "sg:classifiers":[
        {
            "category":"Freight",
            "type":"Transportation"
        }
    ],
    "sg:phone":"+1 317 889 1449",
    "sg:postcode":"46217",
    "sg:province":"IN",
    "sg:tags":[
        "operator",
        "local",
        "trucking"
    ],
    "wof:name":"Bryan Road Trucking Company",
    "wof:placetype":"venue"
},
  "geometry": {"coordinates":[-86.20601600000001,39.657159],"type":"Point"}
}