{
  "type": "Feature",
  "properties": {
    "iso:country":"US",
    "sg:address":"101 N Blish St",
    "sg:city":"Seymour",
    "sg:classifiers":[
        {
            "category":"Manufacturing",
            "subcategory":"Metals",
            "type":"Manufacturing & Wholesale Goods"
        },
        {
            "category":"Building & Trades",
            "subcategory":"Construction",
            "type":"Services"
        }
    ],
    "sg:phone":"+1 812 522 6468",
    "sg:postcode":"47274",
    "sg:province":"IN",
    "sg:tags":[
        "mfg",
        "fabricator",
        "metalwork",
        "structural"
    ],
    "wof:name":"High Value Metal Inc",
    "wof:placetype":"venue"
},
  "geometry": {"coordinates":[-85.88246,38.960958],"type":"Point"}
}