{
  "type": "Feature",
  "properties": {
    "iso:country":"US",
    "sg:address":"3512 S Tudor Ln",
    "sg:city":"Bloomington",
    "sg:classifiers":[
        {
            "category":"Building & Trades",
            "subcategory":"Cleaning & Sanitation",
            "type":"Services"
        }
    ],
    "sg:phone":"+1 812 336 2489",
    "sg:postcode":"47401",
    "sg:province":"IN",
    "sg:tags":[
        "janitor"
    ],
    "wof:name":"City Systems",
    "wof:placetype":"venue"
},
  "geometry": {"coordinates":[-86.523886,39.130781],"type":"Point"}
}