{
  "type": "Feature",
  "properties": {
    "iso:country":"US",
    "sg:address":"1020 W Buena Vista Rd",
    "sg:city":"Evansville",
    "sg:classifiers":[
        {
            "category":"Shopping",
            "subcategory":"Optical Goods",
            "type":"Retail Goods"
        }
    ],
    "sg:phone":"+1 812 422 6977",
    "sg:postcode":"47710",
    "sg:province":"IN",
    "wof:name":"Envision Optical",
    "wof:placetype":"venue"
},
  "geometry": {"coordinates":[-87.575571,38.014133],"type":"Point"}
}