{
  "type": "Feature",
  "properties": {
    "iso:country":"US",
    "sg:address":"4181 E 96th St",
    "sg:city":"Indianapolis",
    "sg:classifiers":[
        {
            "category":"Professional",
            "subcategory":"Lawyer & Legal Services",
            "type":"Services"
        }
    ],
    "sg:phone":"+1 317 574 9113",
    "sg:postcode":"46240",
    "sg:province":"IN",
    "sg:tags":[
        "attorney"
    ],
    "wof:name":"Sarah L Nagy Law Offices",
    "wof:placetype":"venue"
},
  "geometry": {"coordinates":[-86.094559,39.926957],"type":"Point"}
}