{
  "type": "Feature",
  "properties": {
    "iso:country":"US",
    "sg:address":"504 Colonial Ct",
    "sg:city":"Plymouth",
    "sg:classifiers":[
        {
            "category":"Health Services",
            "subcategory":"Podiatrist",
            "type":"Services"
        }
    ],
    "sg:phone":"+1 574 935 5563",
    "sg:postcode":"46563",
    "sg:province":"IN",
    "wof:name":"Northern Indiana Foot Care",
    "wof:placetype":"venue"
},
  "geometry": {"coordinates":[-86.305981,41.343958],"type":"Point"}
}