{
  "type": "Feature",
  "properties": {
    "iso:country":"US",
    "sg:address":"6401 S East St",
    "sg:city":"Indianapolis",
    "sg:classifiers":[
        {
            "category":"Professional",
            "subcategory":"Credit Reporting & Collection",
            "type":"Services"
        }
    ],
    "sg:phone":"+1 317 780 5353",
    "sg:postcode":"46227",
    "sg:province":"IN",
    "sg:tags":[
        "agency"
    ],
    "sg:website":"www.getmetro.com",
    "wof:name":"Metro Asset Management",
    "wof:placetype":"venue"
},
  "geometry": {"coordinates":[-86.14913900000001,39.673273],"type":"Point"}
}