{
  "type": "Feature",
  "properties": {
    "iso:country":"US",
    "sg:address":"2612 Mounds Rd",
    "sg:city":"Anderson",
    "sg:classifiers":[
        {
            "category":"Building & Trades",
            "subcategory":"Equipment Rental",
            "type":"Services"
        }
    ],
    "sg:phone":"+1 765 649 2213",
    "sg:postcode":"46016",
    "sg:province":"IN",
    "sg:tags":[
        "contractor"
    ],
    "wof:name":"Mounds Road Rental Svc",
    "wof:placetype":"venue"
},
  "geometry": {"coordinates":[-85.646443,40.090829],"type":"Point"}
}