{
  "type": "Feature",
  "properties": {
    "iso:country":"US",
    "sg:address":"144 N Delaware St",
    "sg:city":"Indianapolis",
    "sg:classifiers":[
        {
            "category":"Professional",
            "subcategory":"Lawyer & Legal Services",
            "type":"Services"
        }
    ],
    "sg:phone":"+1 317 264 3628",
    "sg:postcode":"46204",
    "sg:province":"IN",
    "sg:tags":[
        "attorney"
    ],
    "wof:name":"Ronald D Casey",
    "wof:placetype":"venue"
},
  "geometry": {"coordinates":[-86.154439,39.769709],"type":"Point"}
}