{
  "type": "Feature",
  "properties": {
    "iso:country":"US",
    "sg:address":"581 W Cross St",
    "sg:city":"Austin",
    "sg:classifiers":[
        {
            "category":"Food & Beverages",
            "subcategory":"Groceries & Convenience Stores",
            "type":"Retail Goods"
        }
    ],
    "sg:phone":"+1 812 794 2430",
    "sg:postcode":"47102",
    "sg:province":"IN",
    "sg:tags":[
        "grocer"
    ],
    "wof:name":"Campbell's Grocery",
    "wof:placetype":"venue"
},
  "geometry": {"coordinates":[-85.811656,38.738713],"type":"Point"}
}