{
  "type": "Feature",
  "properties": {
    "iso:country":"US",
    "sg:address":"28 E 3rd St",
    "sg:city":"Hobart",
    "sg:classifiers":[
        {
            "category":"Shopping",
            "subcategory":"Hobbies, Toys, & Games",
            "type":"Retail Goods"
        }
    ],
    "sg:phone":"+1 219 947 3808",
    "sg:postcode":"46342",
    "sg:province":"IN",
    "sg:tags":[
        "product",
        "ceramic"
    ],
    "wof:name":"Mina's Clay Party",
    "wof:placetype":"venue"
},
  "geometry": {"coordinates":[-87.258409,41.531294],"type":"Point"}
}