{
  "type": "Feature",
  "properties": {
    "addr:full":"1506 N McKinley Ave Rensselaer IN 47978",
    "addr:housenumber":"1506",
    "addr:postcode":"47978",
    "addr:street":"N Mckinley Ave",
    "iso:country":"US",
    "sg:address":"1506 N McKinley Ave",
    "sg:city":"Rensselaer",
    "sg:classifiers":[
        {
            "category":"Home & Garden",
            "subcategory":"Furniture",
            "type":"Retail Goods"
        }
    ],
    "sg:phone":"+1 219 866 2782",
    "sg:postcode":"47978",
    "sg:province":"IN",
    "sg:tags":[
        "cabinet"
    ],
    "wof:name":"Mgt Cabinets Inc",
    "wof:placetype":"venue"
},
  "geometry": {"coordinates":[-87.151447,40.953023],"type":"Point"}
}