{
  "type": "Feature",
  "properties": {
    "iso:country":"US",
    "sg:address":"18 S Franklin St",
    "sg:city":"Bloomfield",
    "sg:classifiers":[
        {
            "category":"Professional",
            "subcategory":"Lawyer & Legal Services",
            "type":"Services"
        }
    ],
    "sg:phone":"+1 812 384 3531",
    "sg:postcode":"47424",
    "sg:province":"IN",
    "sg:tags":[
        "attorney"
    ],
    "wof:name":"Riester & Strueh",
    "wof:placetype":"venue"
},
  "geometry": {"coordinates":[-86.93856,39.026611],"type":"Point"}
}