{
  "type": "Feature",
  "properties": {
    "addr:full":"3623 E State Road 16 Brook IN 47922",
    "addr:housenumber":"3623",
    "addr:postcode":"47922",
    "addr:street":"E State Road 16 Brook",
    "iso:country":"US",
    "sg:address":"3623 E State Road 16",
    "sg:city":"Brook",
    "sg:classifiers":[
        {
            "category":"Social Services",
            "subcategory":"Job Training",
            "type":"Services"
        },
        {
            "category":"Social Services",
            "subcategory":"Retirement Home",
            "type":"Services"
        },
        {
            "category":"Health Services",
            "subcategory":"Clinic",
            "type":"Services"
        }
    ],
    "sg:phone":"+1 219 275 2531",
    "sg:postcode":"47922",
    "sg:province":"IN",
    "sg:tags":[
        "medical",
        "convalescent",
        "nursing",
        "homes-skilled",
        "facility"
    ],
    "sg:website":"http://www.georgeade.org",
    "wof:name":"George Ade Memorial Health Care Center Inc",
    "wof:placetype":"venue"
},
  "geometry": {"coordinates":[-87.322799,40.864561],"type":"Point"}
}