{
  "type": "Feature",
  "properties": {
    "iso:country":"US",
    "sg:address":"5101 E 38th St",
    "sg:city":"Indianapolis",
    "sg:classifiers":[
        {
            "category":"Shopping",
            "subcategory":"Used Merchandise",
            "type":"Retail Goods"
        }
    ],
    "sg:phone":"+1 317 541 1824",
    "sg:postcode":"46218",
    "sg:province":"IN",
    "sg:tags":[
        "pawnbroker"
    ],
    "wof:name":"Cash-N-Pawn",
    "wof:placetype":"venue"
},
  "geometry": {"coordinates":[-86.082002,39.825492],"type":"Point"}
}