{
  "type": "Feature",
  "properties": {
    "iso:country":"US",
    "sg:address":"279 W 80th Pl",
    "sg:city":"Merrillville",
    "sg:classifiers":[
        {
            "category":"Health Services",
            "subcategory":"Optometrist",
            "type":"Services"
        }
    ],
    "sg:phone":"+1 219 738 2180",
    "sg:postcode":"46410",
    "sg:province":"IN",
    "wof:name":"Eye Care Plus",
    "wof:placetype":"venue"
},
  "geometry": {"coordinates":[-87.338604,41.473309],"type":"Point"}
}