{
  "type": "Feature",
  "properties": {
    "iso:country":"US",
    "sg:address":"619 Main St",
    "sg:city":"Jasper",
    "sg:classifiers":[
        {
            "category":"Professional",
            "subcategory":"Accounting & Tax Preparation",
            "type":"Services"
        }
    ],
    "sg:phone":"+1 812 482 3181",
    "sg:postcode":"47546",
    "sg:province":"IN",
    "sg:tags":[
        "return",
        "filing"
    ],
    "wof:name":"Hamilton Accounting & Tax",
    "wof:placetype":"venue"
},
  "geometry": {"coordinates":[-86.93087800000001,38.392117],"type":"Point"}
}