{
  "type": "Feature",
  "properties": {
    "iso:country":"US",
    "sg:address":"202 N Center St",
    "sg:city":"Bremen",
    "sg:classifiers":[
        {
            "category":"Organizations",
            "subcategory":"Religious Organization",
            "type":"Services"
        }
    ],
    "sg:phone":"+1 574 546 0393",
    "sg:postcode":"46506",
    "sg:province":"IN",
    "sg:tags":[
        "church"
    ],
    "sg:website":"www.horizonministries.com",
    "wof:name":"Horizon Ministries",
    "wof:placetype":"venue"
},
  "geometry": {"coordinates":[-86.146429,41.448209],"type":"Point"}
}