{
  "type": "Feature",
  "properties": {
    "addr:full":"70 E 91st St Indianapolis IN 46240",
    "addr:housenumber":"70",
    "addr:postcode":"46240",
    "addr:street":"E 91St St",
    "iso:country":"US",
    "sg:address":"70 E 91st St",
    "sg:city":"Indianapolis",
    "sg:classifiers":[
        {
            "category":"Health Services",
            "subcategory":"Doctor",
            "type":"Services"
        }
    ],
    "sg:phone":"+1 317 581 1911",
    "sg:postcode":"46240",
    "sg:province":"IN",
    "sg:tags":[
        "medical",
        "imaging"
    ],
    "wof:name":"Medical Physics Consultants",
    "wof:placetype":"venue"
},
  "geometry": {"coordinates":[-86.155794,39.919775],"type":"Point"}
}