{
  "type": "Feature",
  "properties": {
    "iso:country":"US",
    "sg:address":"841 S Union St",
    "sg:city":"Warsaw",
    "sg:classifiers":[
        {
            "category":"Health Services",
            "subcategory":"Doctor",
            "type":"Services"
        }
    ],
    "sg:phone":"+1 574 267 1490",
    "sg:postcode":"46580",
    "sg:province":"IN",
    "sg:tags":[
        "dentist"
    ],
    "sg:website":"www.oss-orthodontics.com",
    "wof:name":"Orthodontic Specialty Svc",
    "wof:placetype":"venue"
},
  "geometry": {"coordinates":[-85.861727,41.230027],"type":"Point"}
}