{
  "type": "Feature",
  "properties": {
    "iso:country":"US",
    "sg:address":"5999 Crawfordsville Rd",
    "sg:city":"Indianapolis",
    "sg:classifiers":[
        {
            "category":"Recreation",
            "type":"Entertainment"
        }
    ],
    "sg:phone":"+1 317 244 3600",
    "sg:postcode":"46224",
    "sg:province":"IN",
    "sg:tags":[
        "martial",
        "arts",
        "instruction"
    ],
    "wof:name":"A-1 Masters Martial Arts",
    "wof:placetype":"venue"
},
  "geometry": {"coordinates":[-86.266363,39.799368],"type":"Point"}
}