{
  "type": "Feature",
  "properties": {
    "addr:full":"5865 US Hwy 6 Portage IN 46368",
    "addr:housenumber":"5865",
    "addr:postcode":"46368",
    "addr:street":"Us Hwy 6",
    "iso:country":"US",
    "sg:address":"5865 US Hwy 6",
    "sg:city":"Portage",
    "sg:classifiers":[
        {
            "category":"Retail",
            "subcategory":"Car Wash",
            "type":"Services"
        }
    ],
    "sg:phone":"+1 219 762 1999",
    "sg:postcode":"46368",
    "sg:province":"IN",
    "sg:tags":[
        "polishing",
        "washing"
    ],
    "wof:name":"Portage Car Wash",
    "wof:placetype":"venue"
},
  "geometry": {"coordinates":[-87.18612299999999,41.550498],"type":"Point"}
}