{
  "type": "Feature",
  "properties": {
    "iso:country":"US",
    "sg:address":"2125 N Morton St",
    "sg:city":"Franklin",
    "sg:classifiers":[
        {
            "category":"Retail",
            "subcategory":"Portrait Studio",
            "type":"Services"
        }
    ],
    "sg:phone":"+1 317 736 0207",
    "sg:postcode":"46131",
    "sg:province":"IN",
    "sg:tags":[
        "photo"
    ],
    "wof:name":"PCA International LLC",
    "wof:placetype":"venue"
},
  "geometry": {"coordinates":[-86.06769,39.500183],"type":"Point"}
}