{
  "type": "Feature",
  "properties": {
    "iso:country":"US",
    "sg:address":"2001 Musicland Dr",
    "sg:city":"Franklin",
    "sg:classifiers":[
        {
            "category":"Shopping",
            "subcategory":"Computers & Home Electronics",
            "type":"Retail Goods"
        }
    ],
    "sg:phone":"+1 317 736 1000",
    "sg:postcode":"46131",
    "sg:province":"IN",
    "sg:tags":[
        "equipment",
        "electronic",
        "supply"
    ],
    "wof:name":"Best Buy",
    "wof:placetype":"venue"
},
  "geometry": {"coordinates":[-86.04561200000001,39.505096],"type":"Point"}
}