{
  "type": "Feature",
  "properties": {
    "iso:country":"US",
    "sg:address":"5947 E 82nd St",
    "sg:city":"Indianapolis",
    "sg:classifiers":[
        {
            "category":"Utilities",
            "subcategory":"Mobile Phone",
            "type":"Services"
        }
    ],
    "sg:phone":"+1 317 595 8800",
    "sg:postcode":"46250",
    "sg:province":"IN",
    "sg:tags":[
        "telephone",
        "cellular"
    ],
    "wof:name":"Cellular Warehouse Of America",
    "wof:placetype":"venue"
},
  "geometry": {"coordinates":[-86.065952,39.905183],"type":"Point"}
}