{
  "type": "Feature",
  "properties": {
    "iso:country":"US",
    "sg:address":"506 Leisure Ln",
    "sg:city":"Greenwood",
    "sg:classifiers":[
        {
            "category":"Wholesale",
            "subcategory":"Drugs",
            "type":"Manufacturing & Wholesale Goods"
        }
    ],
    "sg:phone":"+1 317 859 8668",
    "sg:postcode":"46142",
    "sg:province":"IN",
    "sg:tags":[
        "support",
        "abdominal"
    ],
    "wof:name":"Corinthian Consulting LLC",
    "wof:placetype":"venue"
},
  "geometry": {"coordinates":[-86.168594,39.62271],"type":"Point"}
}