{
  "type": "Feature",
  "properties": {
    "iso:country":"US",
    "sg:address":"315 S Chestnut St",
    "sg:city":"Seymour",
    "sg:classifiers":[
        {
            "category":"Education",
            "subcategory":"School",
            "type":"Public Place"
        }
    ],
    "sg:phone":"+1 812 522 2686",
    "sg:postcode":"47274",
    "sg:province":"IN",
    "wof:name":"Religious Education Office",
    "wof:placetype":"venue"
},
  "geometry": {"coordinates":[-85.88905800000001,38.9557],"type":"Point"}
}