{
  "type": "Feature",
  "properties": {
    "addr:full":"5556 S State Rd 162 Huntingburg IN 47542",
    "addr:housenumber":"5556",
    "addr:postcode":"47542",
    "addr:street":"S State Rd 162",
    "iso:country":"US",
    "sg:address":"5556 S State Rd 162",
    "sg:city":"Huntingburg",
    "sg:classifiers":[
        {
            "category":"Utilities",
            "subcategory":"Refuse",
            "type":"Services"
        }
    ],
    "sg:phone":"+1 812 683 5569",
    "sg:postcode":"47542",
    "sg:province":"IN",
    "sg:tags":[
        "disposal",
        "waste"
    ],
    "wof:name":"Advantage Sanitation",
    "wof:placetype":"venue"
},
  "geometry": {"coordinates":[-86.873541,38.29887],"type":"Point"}
}