{
  "type": "Feature",
  "properties": {
    "iso:country":"US",
    "sg:address":"628 James St",
    "sg:city":"Elkhart",
    "sg:classifiers":[
        {
            "category":"Building & Trades",
            "subcategory":"Construction",
            "type":"Services"
        }
    ],
    "sg:phone":"+1 574 295 1555",
    "sg:postcode":"46516",
    "sg:province":"IN",
    "sg:tags":[
        "painter"
    ],
    "wof:name":"Baldwin Painting Inc",
    "wof:placetype":"venue"
},
  "geometry": {"coordinates":[-85.948004,41.682508],"type":"Point"}
}