{
  "type": "Feature",
  "properties": {
    "iso:country":"US",
    "sg:address":"1168 Keystone Way",
    "sg:city":"Carmel",
    "sg:classifiers":[
        {
            "category":"Restaurant",
            "type":"Food & Drink"
        }
    ],
    "sg:phone":"+1 317 844 4766",
    "sg:postcode":"46032",
    "sg:province":"IN",
    "sg:tags":[
        "deli"
    ],
    "wof:name":"Yorkshire Rose Pub",
    "wof:placetype":"venue"
},
  "geometry": {"coordinates":[-86.115402,39.959599],"type":"Point"}
}