{
  "type": "Feature",
  "properties": {
    "iso:country":"US",
    "sg:address":"106 W Catherine St",
    "sg:city":"Milford",
    "sg:classifiers":[
        {
            "category":"Building & Trades",
            "subcategory":"Plumbing",
            "type":"Services"
        }
    ],
    "sg:phone":"+1 574 658 4509",
    "sg:postcode":"46542",
    "sg:province":"IN",
    "sg:tags":[
        "plumbing",
        "contractor"
    ],
    "wof:name":"Wayne Plumbing Installations",
    "wof:placetype":"venue"
},
  "geometry": {"coordinates":[-85.846079,41.409738],"type":"Point"}
}