{
  "type": "Feature",
  "properties": {
    "iso:country":"US",
    "sg:address":"11096 Co Rd 16",
    "sg:city":"Middlebury",
    "sg:classifiers":[
        {
            "category":"Wholesale",
            "subcategory":"Poultry",
            "type":"Manufacturing & Wholesale Goods"
        }
    ],
    "sg:phone":"+1 574 825 2177",
    "sg:postcode":"46540",
    "sg:province":"IN",
    "wof:name":"Middlebury Produce Inc",
    "wof:placetype":"venue"
},
  "geometry": {"coordinates":[-85.689918,41.676052],"type":"Point"}
}