{
  "type": "Feature",
  "properties": {
    "addr:full":"203 E 6th St Jasper IN 47546",
    "addr:housenumber":"203",
    "addr:postcode":"47546",
    "addr:street":"E 6Th St",
    "iso:country":"US",
    "sg:address":"203 E 6th St",
    "sg:city":"Jasper",
    "sg:classifiers":[
        {
            "category":"Health Services",
            "subcategory":"Optometrist",
            "type":"Services"
        }
    ],
    "sg:phone":"+1 812 482 4868",
    "sg:postcode":"47546",
    "sg:province":"IN",
    "wof:name":"Ronald C Exkert OD",
    "wof:placetype":"venue"
},
  "geometry": {"coordinates":[-86.928926,38.391316],"type":"Point"}
}