{
  "type": "Feature",
  "properties": {
    "iso:country":"US",
    "sg:address":"1501 E Main St",
    "sg:city":"Richmond",
    "sg:classifiers":[
        {
            "category":"Shopping",
            "subcategory":"Pharmacy",
            "type":"Retail Goods"
        }
    ],
    "sg:phone":"+1 765 962 8822",
    "sg:postcode":"47374",
    "sg:province":"IN",
    "wof:name":"CVS Pharmacy",
    "wof:placetype":"venue"
},
  "geometry": {"coordinates":[-84.88048999999999,39.829636],"type":"Point"}
}