{
  "type": "Feature",
  "properties": {
    "addr:full":"2264 S 600 W-1 Bluffton IN 46714",
    "addr:housenumber":"2264;600 w-1",
    "addr:postcode":"46714",
    "addr:street":"S",
    "iso:country":"US",
    "sg:address":"2264 S 600 W-1",
    "sg:city":"Bluffton",
    "sg:classifiers":[
        {
            "category":"Real Estate",
            "subcategory":"Real Estate Agent",
            "type":"Services"
        }
    ],
    "sg:phone":"+1 260 565 3940",
    "sg:postcode":"46714",
    "sg:province":"IN",
    "wof:name":"Stoller Farms",
    "wof:placetype":"venue"
},
  "geometry": {"coordinates":[-85.05079600000001,40.709787],"type":"Point"}
}