{
  "type": "Feature",
  "properties": {
    "addr:full":"137 W Washington St Galveston IN 46932",
    "addr:housenumber":"137",
    "addr:postcode":"46932",
    "addr:street":"W Washington St",
    "iso:country":"US",
    "sg:address":"137 W Washington St",
    "sg:city":"Galveston",
    "sg:classifiers":[
        {
            "category":"Insurance",
            "subcategory":"Insurance Agent",
            "type":"Services"
        }
    ],
    "sg:phone":"+1 574 699 6560",
    "sg:postcode":"46932",
    "sg:province":"IN",
    "wof:name":"Lyle Brown Agency",
    "wof:placetype":"venue"
},
  "geometry": {"coordinates":[-86.19176400000001,40.5769],"type":"Point"}
}