{
  "type": "Feature",
  "properties": {
    "iso:country":"US",
    "sg:address":"2200 Smith St",
    "sg:city":"Fort Wayne",
    "sg:classifiers":[
        {
            "category":"Organizations",
            "subcategory":"Community Association",
            "type":"Services"
        }
    ],
    "sg:phone":"+1 260 456 5111",
    "sg:postcode":"46803",
    "sg:province":"IN",
    "wof:name":"Project Impact",
    "wof:placetype":"venue"
},
  "geometry": {"coordinates":[-85.123154,41.064786],"type":"Point"}
}