{
  "type": "Feature",
  "properties": {
    "iso:country":"US",
    "sg:address":"211 N High St",
    "sg:city":"Hartford City",
    "sg:classifiers":[
        {
            "category":"Professional",
            "subcategory":"Lawyer & Legal Services",
            "type":"Services"
        }
    ],
    "sg:phone":"+1 765 348 1142",
    "sg:postcode":"47348",
    "sg:province":"IN",
    "sg:tags":[
        "attorney"
    ],
    "wof:name":"Barry Basey & Barry",
    "wof:placetype":"venue"
},
  "geometry": {"coordinates":[-85.36859,40.452924],"type":"Point"}
}