{
  "type": "Feature",
  "properties": {
    "iso:country":"US",
    "sg:address":"3721 Westfield Dr",
    "sg:city":"Anderson",
    "sg:classifiers":[
        {
            "category":"Insurance",
            "subcategory":"Life Insurance",
            "type":"Services"
        }
    ],
    "sg:phone":"+1 765 649 1029",
    "sg:postcode":"46011",
    "sg:province":"IN",
    "sg:tags":[
        "carrier"
    ],
    "wof:name":"Rdw Marketing",
    "wof:placetype":"venue"
},
  "geometry": {"coordinates":[-85.736413,40.097256],"type":"Point"}
}