{
  "type": "Feature",
  "properties": {
    "iso:country":"US",
    "sg:address":"4525 Bell Hollow Rd",
    "sg:city":"Cannelton",
    "sg:classifiers":[
        {
            "category":"Building & Trades",
            "subcategory":"Plumbing",
            "type":"Services"
        }
    ],
    "sg:phone":"+1 812 547 4441",
    "sg:postcode":"47520",
    "sg:province":"IN",
    "sg:tags":[
        "conditioning",
        "air",
        "system",
        "contractor"
    ],
    "wof:name":"East's Refrigeration Heating",
    "wof:placetype":"venue"
},
  "geometry": {"coordinates":[-86.722464,37.906981],"type":"Point"}
}