{
  "type": "Feature",
  "properties": {
    "iso:country":"US",
    "sg:address":"9252 E 75 S",
    "sg:city":"Mill Creek",
    "sg:classifiers":[
        {
            "category":"Manufacturing",
            "subcategory":"Toys & Sporting Goods",
            "type":"Manufacturing & Wholesale Goods"
        }
    ],
    "sg:phone":"+1 219 369 9185",
    "sg:postcode":"46365",
    "sg:province":"IN",
    "sg:tags":[
        "mfg"
    ],
    "wof:name":"Lempke Heirlooms",
    "wof:placetype":"venue"
},
  "geometry": {"coordinates":[-86.519277,41.596045],"type":"Point"}
}