{
  "type": "Feature",
  "properties": {
    "iso:country":"US",
    "sg:address":"801 Indiana Ave",
    "sg:city":"Laporte",
    "sg:classifiers":[
        {
            "category":"Travel",
            "subcategory":"Travel Agent",
            "type":"Entertainment"
        }
    ],
    "sg:phone":"+1 219 362 8502",
    "sg:postcode":"46350",
    "sg:province":"IN",
    "sg:tags":[
        "agency",
        "bureau"
    ],
    "wof:name":"Edgerton's Travel Svc",
    "wof:placetype":"venue"
},
  "geometry": {"coordinates":[-86.721706,41.609898],"type":"Point"}
}