{
  "type": "Feature",
  "properties": {
    "iso:country":"US",
    "sg:address":"2965 E US Hwy 41",
    "sg:city":"Attica",
    "sg:classifiers":[
        {
            "category":"Wholesale",
            "subcategory":"Farm Supplies",
            "type":"Manufacturing & Wholesale Goods"
        }
    ],
    "sg:phone":"+1 765 764 4247",
    "sg:postcode":"47918",
    "sg:province":"IN",
    "wof:name":"Country Feed & Farm Supply",
    "wof:placetype":"venue"
},
  "geometry": {"coordinates":[-87.264322,40.303798],"type":"Point"}
}