{
  "type": "Feature",
  "properties": {
    "iso:country":"US",
    "sg:address":"303 Greenwich St",
    "sg:city":"Valparaiso",
    "sg:classifiers":[
        {
            "category":"Professional",
            "subcategory":"Business Services",
            "type":"Services"
        }
    ],
    "sg:phone":"+1 219 462 9552",
    "sg:postcode":"46383",
    "sg:province":"IN",
    "wof:name":"Deimar Gross and Associates",
    "wof:placetype":"venue"
},
  "geometry": {"coordinates":[-87.05256,41.470684],"type":"Point"}
}