{
  "type": "Feature",
  "properties": {
    "iso:country":"US",
    "sg:address":"6925 Shore Ter",
    "sg:city":"Indianapolis",
    "sg:classifiers":[
        {
            "category":"Health Services",
            "subcategory":"Doctor",
            "type":"Services"
        }
    ],
    "sg:phone":"+1 317 329 7470",
    "sg:postcode":"46254",
    "sg:province":"IN",
    "sg:tags":[
        "physician",
        "surgeon"
    ],
    "wof:name":"Indiana Oncology Hematology",
    "wof:placetype":"venue"
},
  "geometry": {"coordinates":[-86.281673,39.829814],"type":"Point"}
}