{
  "type": "Feature",
  "properties": {
    "addr:full":"840 Richard Rd Dyer IN 46311",
    "addr:housenumber":"840",
    "addr:postcode":"46311",
    "addr:street":"Richard Rd",
    "iso:country":"US",
    "sg:address":"840 Richard Rd",
    "sg:city":"Dyer",
    "sg:classifiers":[
        {
            "category":"Health Services",
            "subcategory":"Doctor",
            "type":"Services"
        }
    ],
    "sg:phone":"+1 219 322 7171",
    "sg:postcode":"46311",
    "sg:province":"IN",
    "sg:tags":[
        "physician",
        "surgeon"
    ],
    "wof:name":"Dyer Pediatric Svc",
    "wof:placetype":"venue"
},
  "geometry": {"coordinates":[-87.508785,41.491355],"type":"Point"}
}