{
  "type": "Feature",
  "properties": {
    "iso:country":"US",
    "sg:address":"1120 W Ridge Rd",
    "sg:city":"Rochester",
    "sg:classifiers":[
        {
            "category":"Building & Trades",
            "subcategory":"Landscaping Services",
            "type":"Services"
        }
    ],
    "sg:phone":"+1 574 223 2451",
    "sg:postcode":"46975",
    "sg:province":"IN",
    "sg:tags":[
        "landscape",
        "contractor"
    ],
    "wof:name":"Green Jeans Gdn & Landscaping",
    "wof:placetype":"venue"
},
  "geometry": {"coordinates":[-86.232651,41.072428],"type":"Point"}
}