{
  "type": "Feature",
  "properties": {
    "iso:country":"US",
    "sg:address":"4713 US Hwy 31",
    "sg:city":"Seymour",
    "sg:classifiers":[
        {
            "category":"Shopping",
            "subcategory":"Gifts & Souvenirs",
            "type":"Retail Goods"
        }
    ],
    "sg:phone":"+1 812 523 7505",
    "sg:postcode":"47274",
    "sg:province":"IN",
    "wof:name":"Longaberger",
    "wof:placetype":"venue"
},
  "geometry": {"coordinates":[-85.834376,38.947729],"type":"Point"}
}