{
  "type": "Feature",
  "properties": {
    "iso:country":"US",
    "sg:address":"2209 John R Wooden Dr",
    "sg:city":"Martinsville",
    "sg:classifiers":[
        {
            "category":"Health Services",
            "subcategory":"Doctor",
            "type":"Services"
        }
    ],
    "sg:phone":"+1 765 342 3686",
    "sg:postcode":"46151",
    "sg:province":"IN",
    "sg:tags":[
        "physician",
        "surgeon"
    ],
    "wof:name":"Central Indiana Proctology",
    "wof:placetype":"venue"
},
  "geometry": {"coordinates":[-86.40596499999999,39.425845],"type":"Point"}
}