{
  "type": "Feature",
  "properties": {
    "iso:country":"US",
    "sg:address":"9654 N Highgate Cir",
    "sg:city":"Indianapolis",
    "sg:classifiers":[
        {
            "category":"Professional",
            "subcategory":"Business Services",
            "type":"Services"
        }
    ],
    "sg:phone":"+1 317 576 9447",
    "sg:postcode":"46250",
    "sg:province":"IN",
    "wof:name":"Berengaria Intl LLC",
    "wof:placetype":"venue"
},
  "geometry": {"coordinates":[-86.061275,39.927626],"type":"Point"}
}