{
  "type": "Feature",
  "properties": {
    "iso:country":"US",
    "sg:address":"315 Main St",
    "sg:city":"Brookville",
    "sg:classifiers":[
        {
            "category":"Food & Beverages",
            "subcategory":"Specialty",
            "type":"Retail Goods"
        }
    ],
    "sg:phone":"+1 765 647 1328",
    "sg:postcode":"47012",
    "sg:province":"IN",
    "wof:name":"Herbalistic Ways",
    "wof:placetype":"venue"
},
  "geometry": {"coordinates":[-85.01284099999999,39.417932],"type":"Point"}
}