{
  "type": "Feature",
  "properties": {
    "iso:country":"US",
    "sg:address":"316 N Line St",
    "sg:city":"Columbia City",
    "sg:classifiers":[
        {
            "category":"Organizations",
            "subcategory":"Religious Organization",
            "type":"Services"
        }
    ],
    "sg:phone":"+1 260 248 2032",
    "sg:postcode":"46725",
    "sg:province":"IN",
    "wof:name":"Living Word Bible Church",
    "wof:placetype":"venue"
},
  "geometry": {"coordinates":[-85.491335,41.163093],"type":"Point"}
}