{
  "type": "Feature",
  "properties": {
    "addr:full":"4411 S Adams St Marion IN 46953",
    "addr:housenumber":"4411",
    "addr:postcode":"46953",
    "addr:street":"S Adams St",
    "iso:country":"US",
    "sg:address":"4411 S Adams St",
    "sg:city":"Marion",
    "sg:classifiers":[
        {
            "category":"Health Services",
            "subcategory":"Health Practitioner",
            "type":"Services"
        }
    ],
    "sg:phone":"+1 765 674 4455",
    "sg:postcode":"46953",
    "sg:province":"IN",
    "sg:tags":[
        "therapist",
        "physical"
    ],
    "wof:name":"Center For Sports & Physical",
    "wof:placetype":"venue"
},
  "geometry": {"coordinates":[-85.655357,40.516852],"type":"Point"}
}