{
  "type": "Feature",
  "properties": {
    "iso:country":"US",
    "sg:address":"407 N 5th St",
    "sg:city":"Attica",
    "sg:classifiers":[
        {
            "category":"Building & Trades",
            "subcategory":"Construction",
            "type":"Services"
        }
    ],
    "sg:phone":"+1 765 762 6433",
    "sg:postcode":"47918",
    "sg:province":"IN",
    "sg:tags":[
        "house"
    ],
    "wof:name":"Tahitiannoni International",
    "wof:placetype":"venue"
},
  "geometry": {"coordinates":[-87.245054,40.29623],"type":"Point"}
}