{
  "type": "Feature",
  "properties": {
    "iso:country":"US",
    "sg:address":"5103 E Washington St",
    "sg:city":"Indianapolis",
    "sg:classifiers":[
        {
            "category":"Autos & Motor Vehicles",
            "subcategory":"Fuel & Gas Station",
            "type":"Retail Goods"
        }
    ],
    "sg:phone":"+1 317 356 2155",
    "sg:postcode":"46219",
    "sg:province":"IN",
    "sg:tags":[
        "oil"
    ],
    "sg:website":"www.speedway.com",
    "wof:name":"Speedway",
    "wof:placetype":"venue"
},
  "geometry": {"coordinates":[-86.082257,39.770137],"type":"Point"}
}