{
  "type": "Feature",
  "properties": {
    "iso:country":"US",
    "sg:address":"5011 Lafayette Rd",
    "sg:city":"Indianapolis",
    "sg:classifiers":[
        {
            "category":"Travel",
            "subcategory":"Hotels & Motels",
            "type":"Entertainment"
        }
    ],
    "sg:phone":"+1 317 297 0721",
    "sg:postcode":"46254",
    "sg:province":"IN",
    "wof:name":"Lee's Inn",
    "wof:placetype":"venue"
},
  "geometry": {"coordinates":[-86.254911,39.844475],"type":"Point"}
}