{
  "type": "Feature",
  "properties": {
    "addr:full":"14501 W Commerce Rd Daleville IN 47334",
    "addr:housenumber":"14501",
    "addr:postcode":"47334",
    "addr:street":"W Commerce Rd",
    "iso:country":"US",
    "sg:address":"14501 W Commerce Rd",
    "sg:city":"Daleville",
    "sg:classifiers":[
        {
            "category":"Bars & Pubs",
            "type":"Food & Drink"
        }
    ],
    "sg:phone":"+1 765 378 1053",
    "sg:postcode":"47334",
    "sg:province":"IN",
    "wof:name":"Lonnie's Sports Bar",
    "wof:placetype":"venue"
},
  "geometry": {"coordinates":[-85.55730699999999,40.113482],"type":"Point"}
}