{
  "type": "Feature",
  "properties": {
    "iso:country":"US",
    "sg:address":"3258 N Co Rd 700 E",
    "sg:city":"Michigantown",
    "sg:phone":"+1 765 249 2517",
    "sg:postcode":"46057",
    "sg:province":"IN",
    "sg:tags":[
        "farm",
        "corn"
    ],
    "wof:name":"Neil Kirkendall",
    "wof:placetype":"venue"
},
  "geometry": {"coordinates":[-86.375416,40.336222],"type":"Point"}
}