{
  "type": "Feature",
  "properties": {
    "iso:country":"US",
    "sg:address":"5112 S Delaware Dr",
    "sg:city":"Muncie",
    "sg:classifiers":[
        {
            "category":"Insurance",
            "subcategory":"Hazard Insurance",
            "type":"Services"
        }
    ],
    "sg:phone":"+1 765 282 2115",
    "sg:postcode":"47302",
    "sg:province":"IN",
    "sg:tags":[
        "bond"
    ],
    "wof:name":"Scott's Bail Bonds",
    "wof:placetype":"venue"
},
  "geometry": {"coordinates":[-85.421106,40.148782],"type":"Point"}
}