{
  "type": "Feature",
  "properties": {
    "iso:country":"US",
    "sg:address":"1712 Broad St",
    "sg:city":"New Castle",
    "sg:classifiers":[
        {
            "category":"Food & Beverages",
            "subcategory":"Groceries & Convenience Stores",
            "type":"Retail Goods"
        }
    ],
    "sg:phone":"+1 765 529 7177",
    "sg:postcode":"47362",
    "sg:province":"IN",
    "sg:tags":[
        "grocer"
    ],
    "wof:name":"Harvest Supermarkets Inc",
    "wof:placetype":"venue"
},
  "geometry": {"coordinates":[-85.363867,39.931269],"type":"Point"}
}