{
  "type": "Feature",
  "properties": {
    "iso:country":"US",
    "sg:address":"10855 E State Rd 8",
    "sg:city":"Culver",
    "sg:classifiers":[
        {
            "category":"Wholesale",
            "subcategory":"Auto Parts",
            "type":"Manufacturing & Wholesale Goods"
        }
    ],
    "sg:phone":"+1 574 772 5727",
    "sg:postcode":"46511",
    "sg:province":"IN",
    "sg:tags":[
        "automobile",
        "rebuilt",
        "used"
    ],
    "wof:name":"Allen Sidney Auto Parts",
    "wof:placetype":"venue"
},
  "geometry": {"coordinates":[-86.488616,41.287686],"type":"Point"}
}