{
  "type": "Feature",
  "properties": {
    "addr:full":"110 W Washington St Indianapolis IN 46204",
    "addr:housenumber":"110",
    "addr:postcode":"46204",
    "addr:street":"W Washington St",
    "iso:country":"US",
    "sg:address":"110 W Washington St",
    "sg:city":"Indianapolis",
    "sg:classifiers":[
        {
            "category":"Personal",
            "subcategory":"Beauty Salon",
            "type":"Services"
        }
    ],
    "sg:phone":"+1 317 951 8610",
    "sg:postcode":"46204",
    "sg:province":"IN",
    "sg:tags":[
        "manicuring"
    ],
    "wof:name":"Luxury Nail",
    "wof:placetype":"venue"
},
  "geometry": {"coordinates":[-86.161721,39.767162],"type":"Point"}
}