{
  "type": "Feature",
  "properties": {
    "iso:country":"US",
    "sg:address":"315 Lankford St",
    "sg:city":"Clay City",
    "sg:classifiers":[
        {
            "category":"Health Services",
            "subcategory":"Doctor",
            "type":"Services"
        }
    ],
    "sg:phone":"+1 812 939 2126",
    "sg:postcode":"47841",
    "sg:province":"IN",
    "sg:tags":[
        "physician",
        "surgeon"
    ],
    "sg:website":"www.uhhg.org",
    "wof:name":"Clay City Ctr-Family Medicine",
    "wof:placetype":"venue"
},
  "geometry": {"coordinates":[-87.110465,39.281329],"type":"Point"}
}