{
  "type": "Feature",
  "properties": {
    "addr:full":"342 E Center St Dunkirk IN 47336",
    "addr:housenumber":"342",
    "addr:postcode":"47336",
    "addr:street":"E Center St",
    "iso:country":"US",
    "sg:address":"342 E Center St",
    "sg:city":"Dunkirk",
    "sg:classifiers":[
        {
            "category":"Shopping",
            "subcategory":"Used Merchandise",
            "type":"Retail Goods"
        }
    ],
    "sg:phone":"+1 260 726 4767",
    "sg:postcode":"47336",
    "sg:province":"IN",
    "sg:tags":[
        "flea",
        "market"
    ],
    "wof:name":"Grouchs Flea Market",
    "wof:placetype":"venue"
},
  "geometry": {"coordinates":[-85.20617799999999,40.374092],"type":"Point"}
}