{
  "type": "Feature",
  "properties": {
    "iso:country":"US",
    "sg:address":"604 N 15th 1/2 St",
    "sg:city":"Vincennes",
    "sg:classifiers":[
        {
            "category":"Insurance",
            "subcategory":"Insurance Agent",
            "type":"Services"
        },
        {
            "category":"Insurance",
            "subcategory":"Hazard Insurance",
            "type":"Services"
        },
        {
            "category":"Insurance",
            "subcategory":"Title Insurance",
            "type":"Services"
        },
        {
            "category":"Insurance",
            "subcategory":"Life Insurance",
            "type":"Services"
        }
    ],
    "sg:phone":"+1 812 886 0200",
    "sg:postcode":"47591",
    "sg:province":"IN",
    "sg:tags":[
        "business",
        "auto",
        "commercial",
        "homeowner",
        "motorcycle",
        "renter"
    ],
    "wof:name":"Allstate Insurance Company - Pete Barry",
    "wof:placetype":"venue"
},
  "geometry": {"coordinates":[-87.51722599999999,38.67151],"type":"Point"}
}