{
  "type": "Feature",
  "properties": {
    "iso:country":"US",
    "sg:address":"225 N High St",
    "sg:city":"Muncie",
    "sg:classifiers":[
        {
            "category":"Social Services",
            "type":"Services"
        }
    ],
    "sg:phone":"+1 765 747 5567",
    "sg:postcode":"47305",
    "sg:province":"IN",
    "sg:tags":[
        "probation"
    ],
    "wof:name":"US Probation & Parole Office",
    "wof:placetype":"venue"
},
  "geometry": {"coordinates":[-85.387731,40.195222],"type":"Point"}
}