{
  "type": "Feature",
  "properties": {
    "iso:country":"US",
    "sg:address":"320 W Willard St",
    "sg:city":"Muncie",
    "sg:classifiers":[
        {
            "category":"Home & Garden",
            "subcategory":"Hardware",
            "type":"Retail Goods"
        }
    ],
    "sg:phone":"+1 765 282 2259",
    "sg:postcode":"47302",
    "sg:province":"IN",
    "wof:name":"All-Phase Electric Supply Co",
    "wof:placetype":"venue"
},
  "geometry": {"coordinates":[-85.389756,40.185671],"type":"Point"}
}