{
  "type": "Feature",
  "properties": {
    "iso:country":"US",
    "sg:address":"516 Main St",
    "sg:city":"Tell City",
    "sg:classifiers":[
        {
            "category":"Health Services",
            "subcategory":"Medical Lab",
            "type":"Services"
        }
    ],
    "sg:phone":"+1 812 548 0521",
    "sg:postcode":"47586",
    "sg:province":"IN",
    "sg:tags":[
        "laboratory"
    ],
    "wof:name":"Riverside Cytology Lab Inc",
    "wof:placetype":"venue"
},
  "geometry": {"coordinates":[-86.769728,37.949036],"type":"Point"}
}