{
  "type": "Feature",
  "properties": {
    "iso:country":"US",
    "sg:address":"11235 N 460 W",
    "sg:city":"New Palestine",
    "sg:classifiers":[
        {
            "category":"Building & Trades",
            "subcategory":"Construction",
            "type":"Services"
        }
    ],
    "sg:phone":"+1 317 861 6872",
    "sg:postcode":"46163",
    "sg:province":"IN",
    "sg:tags":[
        "consulting",
        "hanging",
        "s",
        "business",
        "contractor"
    ],
    "wof:name":"Jbm Painting",
    "wof:placetype":"venue"
},
  "geometry": {"coordinates":[-85.868619,39.68643],"type":"Point"}
}