{
  "type": "Feature",
  "properties": {
    "iso:country":"US",
    "sg:address":"3857 State Rd 38 E",
    "sg:city":"Lafayette",
    "sg:classifiers":[
        {
            "category":"Autos & Motor Vehicles",
            "subcategory":"Automobile Sales",
            "type":"Retail Goods"
        }
    ],
    "sg:phone":"+1 765 446 9204",
    "sg:postcode":"47905",
    "sg:province":"IN",
    "sg:tags":[
        "car",
        "dealer"
    ],
    "sg:website":"www.delrealauto.com",
    "wof:name":"Delreal Auto Sales",
    "wof:placetype":"venue"
},
  "geometry": {"coordinates":[-86.83911000000001,40.389052],"type":"Point"}
}