{
  "type": "Feature",
  "properties": {
    "iso:country":"US",
    "sg:address":"316 N 7th St",
    "sg:city":"Decatur",
    "sg:classifiers":[
        {
            "category":"Organizations",
            "subcategory":"Religious Organization",
            "type":"Services"
        }
    ],
    "sg:phone":"+1 260 724 2332",
    "sg:postcode":"46733",
    "sg:province":"IN",
    "sg:tags":[
        "church"
    ],
    "wof:name":"Church Of The Nazarene",
    "wof:placetype":"venue"
},
  "geometry": {"coordinates":[-84.930395,40.833352],"type":"Point"}
}