{
  "type": "Feature",
  "properties": {
    "iso:country":"US",
    "sg:address":"111 E 12th St",
    "sg:city":"Anderson",
    "sg:classifiers":[
        {
            "category":"Education",
            "subcategory":"Library",
            "type":"Public Place"
        }
    ],
    "sg:phone":"+1 765 641 2450",
    "sg:postcode":"46016",
    "sg:province":"IN",
    "sg:website":"www.andersonlibrary.net",
    "wof:name":"Anderson Public Library",
    "wof:placetype":"venue"
},
  "geometry": {"coordinates":[-85.676945,40.104074],"type":"Point"}
}