{
  "type": "Feature",
  "properties": {
    "addr:full":"6210 W 5th Ave Gary IN 46406",
    "addr:housenumber":"6210",
    "addr:postcode":"46406",
    "addr:street":"W 5Th Ave",
    "iso:country":"US",
    "sg:address":"6210 W 5th Ave",
    "sg:city":"Gary",
    "sg:classifiers":[
        {
            "category":"Restaurant",
            "type":"Food & Drink"
        }
    ],
    "sg:phone":"+1 219 944 8155",
    "sg:postcode":"46406",
    "sg:province":"IN",
    "wof:name":"Elio's Hot Dogs & Mexican Food",
    "wof:placetype":"venue"
},
  "geometry": {"coordinates":[-87.41443099999999,41.601954],"type":"Point"}
}