{
  "type": "Feature",
  "properties": {
    "iso:country":"US",
    "sg:address":"12441 W State Rd 28",
    "sg:city":"Gaston",
    "sg:classifiers":[
        {
            "category":"Autos & Motor Vehicles",
            "subcategory":"Automobile Sales",
            "type":"Retail Goods"
        }
    ],
    "sg:phone":"+1 765 358 4865",
    "sg:postcode":"47342",
    "sg:province":"IN",
    "sg:tags":[
        "used"
    ],
    "wof:name":"G & G Auto Sales",
    "wof:placetype":"venue"
},
  "geometry": {"coordinates":[-85.533676,40.276741],"type":"Point"}
}