{
  "type": "Feature",
  "properties": {
    "iso:country":"US",
    "sg:address":"6337 Hollister Dr",
    "sg:city":"Indianapolis",
    "sg:classifiers":[
        {
            "category":"Social Services",
            "type":"Services"
        }
    ],
    "sg:phone":"+1 317 290 1610",
    "sg:postcode":"46224",
    "sg:province":"IN",
    "sg:tags":[
        "counselor",
        "marriage",
        "family"
    ],
    "wof:name":"Donald L Fox",
    "wof:placetype":"venue"
},
  "geometry": {"coordinates":[-86.270916,39.807337],"type":"Point"}
}