{
  "type": "Feature",
  "properties": {
    "addr:full":"5045 Stagecoach Rd Portage IN 46368",
    "addr:housenumber":"5045",
    "addr:postcode":"46368",
    "addr:street":"Stagecoach Rd",
    "iso:country":"US",
    "sg:address":"5045 Stagecoach Rd",
    "sg:city":"Portage",
    "sg:classifiers":[
        {
            "category":"Shopping",
            "subcategory":"Florist",
            "type":"Retail Goods"
        }
    ],
    "sg:phone":"+1 219 762 0834",
    "sg:postcode":"46368",
    "sg:province":"IN",
    "wof:name":"Susan J Eikman Floral Dctr",
    "wof:placetype":"venue"
},
  "geometry": {"coordinates":[-87.222188,41.596518],"type":"Point"}
}