{
  "type": "Feature",
  "properties": {
    "iso:country":"US",
    "sg:address":"600 E Columbia St",
    "sg:city":"Evansville",
    "sg:classifiers":[
        {
            "category":"Food & Beverages",
            "subcategory":"Fruits & Vegetables",
            "type":"Retail Goods"
        }
    ],
    "sg:phone":"+1 812 423 4869",
    "sg:postcode":"47711",
    "sg:province":"IN",
    "sg:tags":[
        "produce"
    ],
    "wof:name":"Variety Village",
    "wof:placetype":"venue"
},
  "geometry": {"coordinates":[-87.554975,37.984702],"type":"Point"}
}