{
  "type": "Feature",
  "properties": {
    "iso:country":"US",
    "sg:address":"7676 Zionsville Rd",
    "sg:city":"Indianapolis",
    "sg:classifiers":[
        {
            "category":"Building & Trades",
            "subcategory":"Construction",
            "type":"Services"
        }
    ],
    "sg:phone":"+1 317 613 1300",
    "sg:postcode":"46268",
    "sg:province":"IN",
    "sg:tags":[
        "general",
        "contractor"
    ],
    "wof:name":"Dallman Industrial Corp",
    "wof:placetype":"venue"
},
  "geometry": {"coordinates":[-86.259924,39.89176],"type":"Point"}
}