{
  "type": "Feature",
  "properties": {
    "iso:country":"US",
    "sg:address":"340 S Main St",
    "sg:city":"Zionsville",
    "sg:classifiers":[
        {
            "category":"Retail",
            "subcategory":"Repair Shop",
            "type":"Services"
        }
    ],
    "sg:phone":"+1 317 873 1703",
    "sg:postcode":"46077",
    "sg:province":"IN",
    "sg:tags":[
        "lock",
        "locksmith"
    ],
    "wof:name":"Zionsville Lock & Safe Inc",
    "wof:placetype":"venue"
},
  "geometry": {"coordinates":[-86.261251,39.948975],"type":"Point"}
}