{
  "type": "Feature",
  "properties": {
    "iso:country":"US",
    "sg:address":"3531 W 800 N",
    "sg:city":"Huntington",
    "sg:classifiers":[
        {
            "category":"Organizations",
            "subcategory":"Religious Organization",
            "type":"Services"
        }
    ],
    "sg:phone":"+1 260 356 7814",
    "sg:postcode":"46750",
    "sg:province":"IN",
    "sg:tags":[
        "church"
    ],
    "wof:name":"Sugar Creek Brethren Church",
    "wof:placetype":"venue"
},
  "geometry": {"coordinates":[-85.520252,40.945865],"type":"Point"}
}