{
  "type": "Feature",
  "properties": {
    "addr:full":"6818 Littleton Dr Indianapolis IN 46221",
    "addr:housenumber":"6818",
    "addr:postcode":"46221",
    "addr:street":"Littleton Dr",
    "iso:country":"US",
    "sg:address":"6818 Littleton Dr",
    "sg:city":"Indianapolis",
    "sg:classifiers":[
        {
            "category":"Professional",
            "type":"Services"
        },
        {
            "category":"Food & Beverages",
            "subcategory":"Bakery",
            "type":"Retail Goods"
        }
    ],
    "sg:phone":"+1 317 821 8214",
    "sg:postcode":"46221",
    "sg:province":"IN",
    "sg:tags":[
        "baker"
    ],
    "wof:name":"Brenda's Cakes Custom Design",
    "wof:placetype":"venue"
},
  "geometry": {"coordinates":[-86.263964,39.665527],"type":"Point"}
}