{
  "type": "Feature",
  "properties": {
    "iso:country":"US",
    "sg:address":"625 Stadium Dr",
    "sg:city":"Decatur",
    "sg:classifiers":[
        {
            "category":"Education",
            "subcategory":"School",
            "type":"Public Place"
        }
    ],
    "sg:phone":"+1 260 724 7146",
    "sg:postcode":"46733",
    "sg:province":"IN",
    "sg:website":"www.nadams.k12.in.us",
    "wof:name":"North Adams Community Schools",
    "wof:placetype":"venue"
},
  "geometry": {"coordinates":[-84.912079,40.835324],"type":"Point"}
}