{
  "type": "Feature",
  "properties": {
    "addr:full":"800 Northwestern Ave West Lafayette IN 47906",
    "addr:housenumber":"800",
    "addr:postcode":"47906",
    "addr:street":"Northwestern Ave",
    "iso:country":"US",
    "sg:address":"800 Northwestern Ave",
    "sg:city":"West Lafayette",
    "sg:classifiers":[
        {
            "category":"Organizations",
            "subcategory":"Community Association",
            "type":"Services"
        }
    ],
    "sg:phone":"+1 765 743 8979",
    "sg:postcode":"47906",
    "sg:province":"IN",
    "sg:tags":[
        "sorority",
        "fraternity"
    ],
    "wof:name":"Stewart House",
    "wof:placetype":"venue"
},
  "geometry": {"coordinates":[-86.91519599999999,40.434196],"type":"Point"}
}