{
  "type": "Feature",
  "properties": {
    "iso:country":"US",
    "sg:address":"5064 US Hwy 40",
    "sg:city":"Centerville",
    "sg:classifiers":[
        {
            "category":"Wholesale",
            "subcategory":"Machinery & Supplies",
            "type":"Manufacturing & Wholesale Goods"
        }
    ],
    "sg:phone":"+1 765 962 7724",
    "sg:postcode":"47330",
    "sg:province":"IN",
    "sg:tags":[
        "tractor"
    ],
    "sg:website":"www.bensonequip.com",
    "wof:name":"Benson Equipment Inc",
    "wof:placetype":"venue"
},
  "geometry": {"coordinates":[-84.97138200000001,39.81967],"type":"Point"}
}