{
  "type": "Feature",
  "properties": {
    "addr:full":"28 W 9th St Anderson IN 46016",
    "addr:housenumber":"28",
    "addr:postcode":"46016",
    "addr:street":"W 9Th St",
    "iso:country":"US",
    "sg:address":"28 W 9th St",
    "sg:city":"Anderson",
    "sg:classifiers":[
        {
            "category":"Real Estate",
            "subcategory":"Real Estate Services",
            "type":"Services"
        }
    ],
    "sg:phone":"+1 765 683 9601",
    "sg:postcode":"46016",
    "sg:province":"IN",
    "sg:tags":[
        "company",
        "title"
    ],
    "wof:name":"Title Express Inc",
    "wof:placetype":"venue"
},
  "geometry": {"coordinates":[-85.680267,40.107167],"type":"Point"}
}