{
  "type": "Feature",
  "properties": {
    "addr:full":"101 N Washington St Crawfordsville IN 47933",
    "addr:housenumber":"101",
    "addr:postcode":"47933",
    "addr:street":"N Washington St",
    "iso:country":"US",
    "sg:address":"101 N Washington St",
    "sg:city":"Crawfordsville",
    "sg:classifiers":[
        {
            "category":"Shopping",
            "subcategory":"Clothing, Apparel, & Fashions",
            "type":"Retail Goods"
        }
    ],
    "sg:phone":"+1 765 362 0888",
    "sg:postcode":"47933",
    "sg:province":"IN",
    "wof:name":"Heathcliff",
    "wof:placetype":"venue"
},
  "geometry": {"coordinates":[-86.901414,40.042887],"type":"Point"}
}