{
  "type": "Feature",
  "properties": {
    "iso:country":"US",
    "sg:address":"1330 S 15th St",
    "sg:city":"Vincennes",
    "sg:classifiers":[
        {
            "category":"Building & Trades",
            "subcategory":"Construction",
            "type":"Services"
        }
    ],
    "sg:phone":"+1 812 886 0360",
    "sg:postcode":"47591",
    "sg:province":"IN",
    "sg:tags":[
        "general",
        "contractor"
    ],
    "wof:name":"CLR Inc",
    "wof:placetype":"venue"
},
  "geometry": {"coordinates":[-87.532685,38.661772],"type":"Point"}
}