{
  "type": "Feature",
  "properties": {
    "addr:full":"4983 W 87th Ln Crown Point IN 46307",
    "addr:housenumber":"4983",
    "addr:postcode":"46307",
    "addr:street":"W 87Th Ln",
    "iso:country":"US",
    "sg:address":"4983 W 87th Ln",
    "sg:city":"Crown Point",
    "sg:classifiers":[
        {
            "category":"Building & Trades",
            "subcategory":"Plumbing",
            "type":"Services"
        }
    ],
    "sg:phone":"+1 219 769 2605",
    "sg:postcode":"46307",
    "sg:province":"IN",
    "sg:tags":[
        "contractor"
    ],
    "wof:name":"Air Mgmt Group",
    "wof:placetype":"venue"
},
  "geometry": {"coordinates":[-87.393933,41.459194],"type":"Point"}
}