{
  "type": "Feature",
  "properties": {
    "iso:country":"US",
    "sg:address":"207 W Pearl St",
    "sg:city":"Batesville",
    "sg:classifiers":[
        {
            "category":"Personal",
            "subcategory":"Beauty Salon",
            "type":"Services"
        }
    ],
    "sg:phone":"+1 812 934 2221",
    "sg:postcode":"47006",
    "sg:province":"IN",
    "wof:name":"Headlines-Family Hair Design",
    "wof:placetype":"venue"
},
  "geometry": {"coordinates":[-85.225675,39.300096],"type":"Point"}
}