{
  "type": "Feature",
  "properties": {
    "addr:full":"6293 S State Rd 3 Spiceland IN 47385",
    "addr:housenumber":"6293",
    "addr:postcode":"47385",
    "addr:street":"S State Rd 3",
    "iso:country":"US",
    "sg:address":"6293 S State Rd 3",
    "sg:city":"Spiceland",
    "sg:classifiers":[
        {
            "category":"Organizations",
            "subcategory":"Religious Organization",
            "type":"Services"
        }
    ],
    "sg:phone":"+1 765 987 7672",
    "sg:postcode":"47385",
    "sg:province":"IN",
    "sg:tags":[
        "church"
    ],
    "sg:website":"www.spicelandnazarene.com",
    "wof:name":"Spiceland Church Of Nazarene",
    "wof:placetype":"venue"
},
  "geometry": {"coordinates":[-85.427324,39.841044],"type":"Point"}
}