{
  "type": "Feature",
  "properties": {
    "iso:country":"US",
    "sg:address":"1549 Co Rd 800 N",
    "sg:city":"Alexandria",
    "sg:classifiers":[
        {
            "category":"Professional",
            "type":"Services"
        }
    ],
    "sg:phone":"+1 765 724 3181",
    "sg:postcode":"46001",
    "sg:province":"IN",
    "wof:name":"Accountability Inc",
    "wof:placetype":"venue"
},
  "geometry": {"coordinates":[-85.655096,40.219471],"type":"Point"}
}