{
  "type": "Feature",
  "properties": {
    "iso:country":"US",
    "sg:address":"913 N 7th St",
    "sg:city":"Terre Haute",
    "sg:classifiers":[
        {
            "category":"Shopping",
            "subcategory":"Clothing, Apparel, & Fashions",
            "type":"Retail Goods"
        }
    ],
    "sg:phone":"+1 812 234 8085",
    "sg:postcode":"47807",
    "sg:province":"IN",
    "sg:tags":[
        "shop",
        "bridal"
    ],
    "wof:name":"Delialah's Designs",
    "wof:placetype":"venue"
},
  "geometry": {"coordinates":[-87.407042,39.478218],"type":"Point"}
}