{
  "type": "Feature",
  "properties": {
    "iso:country":"US",
    "sg:address":"7855 Mount St",
    "sg:city":"Schererville",
    "sg:classifiers":[
        {
            "category":"Building & Trades",
            "subcategory":"Plumbing",
            "type":"Services"
        }
    ],
    "sg:phone":"+1 219 864 8796",
    "sg:postcode":"46375",
    "sg:province":"IN",
    "sg:tags":[
        "plumbing",
        "contractor"
    ],
    "wof:name":"Withers Plumbing",
    "wof:placetype":"venue"
},
  "geometry": {"coordinates":[-87.396454,41.475768],"type":"Point"}
}