{
  "type": "Feature",
  "properties": {
    "iso:country":"US",
    "sg:address":"139 E South St",
    "sg:city":"Mooresville",
    "sg:classifiers":[
        {
            "category":"Personal",
            "subcategory":"Beauty Salon",
            "type":"Services"
        }
    ],
    "sg:phone":"+1 317 831 1171",
    "sg:postcode":"46158",
    "sg:province":"IN",
    "wof:name":"Shear Illusions",
    "wof:placetype":"venue"
},
  "geometry": {"coordinates":[-86.371825,39.608466],"type":"Point"}
}