{
  "type": "Feature",
  "properties": {
    "iso:country":"US",
    "sg:address":"2625 N Meridian St",
    "sg:city":"Indianapolis",
    "sg:classifiers":[
        {
            "category":"Banks & Credit Unions",
            "subcategory":"Investment Brokerage",
            "type":"Services"
        }
    ],
    "sg:phone":"+1 317 925 5433",
    "sg:postcode":"46208",
    "sg:province":"IN",
    "sg:tags":[
        "consultant",
        "planning",
        "financial"
    ],
    "wof:name":"PACE",
    "wof:placetype":"venue"
},
  "geometry": {"coordinates":[-86.156579,39.805444],"type":"Point"}
}