{
  "type": "Feature",
  "properties": {
    "iso:country":"US",
    "sg:address":"11110 Scipio Rd",
    "sg:city":"Harlan",
    "sg:classifiers":[
        {
            "category":"Retail",
            "subcategory":"Repair Shop",
            "type":"Services"
        }
    ],
    "sg:phone":"+1 260 632 4800",
    "sg:postcode":"46743",
    "sg:province":"IN",
    "sg:tags":[
        "equipment",
        "hydraulic"
    ],
    "wof:name":"Cummins Repair Inc",
    "wof:placetype":"venue"
},
  "geometry": {"coordinates":[-84.819563,41.191728],"type":"Point"}
}