{
  "type": "Feature",
  "properties": {
    "iso:country":"US",
    "sg:address":"1301 Lafayette Ave",
    "sg:city":"Lebanon",
    "sg:classifiers":[
        {
            "category":"Building & Trades",
            "subcategory":"Construction",
            "type":"Services"
        }
    ],
    "sg:phone":"+1 765 482 8870",
    "sg:postcode":"46052",
    "sg:province":"IN",
    "sg:tags":[
        "marking",
        "maintenance",
        "parking"
    ],
    "wof:name":"Street Dept",
    "wof:placetype":"venue"
},
  "geometry": {"coordinates":[-86.485398,40.058579],"type":"Point"}
}