{
  "type": "Feature",
  "properties": {
    "addr:full":"11 E Pearl St Greens Fork IN 47345",
    "addr:housenumber":"11",
    "addr:postcode":"47345",
    "addr:street":"E Pearl St",
    "iso:country":"US",
    "sg:address":"11 E Pearl St",
    "sg:city":"Greens Fork",
    "sg:classifiers":[
        {
            "category":"Retail",
            "subcategory":"Auto Repair",
            "type":"Services"
        }
    ],
    "sg:phone":"+1 765 886 4142",
    "sg:postcode":"47345",
    "sg:province":"IN",
    "sg:tags":[
        "repairing",
        "automobile"
    ],
    "wof:name":"Charles Garage",
    "wof:placetype":"venue"
},
  "geometry": {"coordinates":[-85.042739,39.89285],"type":"Point"}
}