{
  "type": "Feature",
  "properties": {
    "addr:full":"4050 Zinfandel Way Indianapolis IN 46254",
    "addr:housenumber":"4050",
    "addr:postcode":"46254",
    "addr:street":"Zinfandel Way",
    "iso:country":"US",
    "sg:address":"4050 Zinfandel Way",
    "sg:city":"Indianapolis",
    "sg:classifiers":[
        {
            "category":"Professional",
            "subcategory":"Lawyer & Legal Services",
            "type":"Services"
        }
    ],
    "sg:phone":"+1 317 299 8763",
    "sg:postcode":"46254",
    "sg:province":"IN",
    "wof:name":"Donald W Crider",
    "wof:placetype":"venue"
},
  "geometry": {"coordinates":[-86.285613,39.827881],"type":"Point"}
}