{
  "type": "Feature",
  "properties": {
    "iso:country":"US",
    "sg:address":"308 W 11th St",
    "sg:city":"Lapel",
    "sg:classifiers":[
        {
            "category":"Freight",
            "type":"Transportation"
        }
    ],
    "sg:phone":"+1 765 534 3718",
    "sg:postcode":"46051",
    "sg:province":"IN",
    "sg:tags":[
        "trucking"
    ],
    "wof:name":"D C Transportation",
    "wof:placetype":"venue"
},
  "geometry": {"coordinates":[-85.852243,40.070255],"type":"Point"}
}