{
  "type": "Feature",
  "properties": {
    "iso:country":"US",
    "sg:address":"3990 State Rd 26",
    "sg:city":"Hartford City",
    "sg:classifiers":[
        {
            "category":"Real Estate",
            "subcategory":"Real Estate Operator",
            "type":"Services"
        }
    ],
    "sg:phone":"+1 765 348 1216",
    "sg:postcode":"47348",
    "sg:province":"IN",
    "sg:tags":[
        "property",
        "lessor"
    ],
    "wof:name":"Leroy Stallsmith",
    "wof:placetype":"venue"
},
  "geometry": {"coordinates":[-85.295459,40.449731],"type":"Point"}
}