{
  "type": "Feature",
  "properties": {
    "iso:country":"US",
    "sg:address":"644 Wernsing Rd",
    "sg:city":"Jasper",
    "sg:classifiers":[
        {
            "category":"Retail",
            "subcategory":"Auto Rental",
            "type":"Services"
        }
    ],
    "sg:phone":"+1 812 481 1886",
    "sg:postcode":"47546",
    "sg:province":"IN",
    "sg:tags":[
        "automobile",
        "leasing"
    ],
    "wof:name":"Autoplex-Ryder & Budget Truck",
    "wof:placetype":"venue"
},
  "geometry": {"coordinates":[-86.942213,38.379898],"type":"Point"}
}