{
  "type": "Feature",
  "properties": {
    "iso:country":"US",
    "sg:address":"10744 Club Chase",
    "sg:city":"Fishers",
    "sg:classifiers":[
        {
            "category":"Real Estate",
            "subcategory":"Real Estate Agent",
            "type":"Services"
        }
    ],
    "sg:phone":"+1 317 464 8254",
    "sg:postcode":"46037",
    "sg:province":"IN",
    "wof:name":"Mansur Investment Real Estate",
    "wof:placetype":"venue"
},
  "geometry": {"coordinates":[-85.948235,39.943674],"type":"Point"}
}