{
  "type": "Feature",
  "properties": {
    "iso:country":"US",
    "sg:address":"3208 N Bolton Ave",
    "sg:city":"Indianapolis",
    "sg:classifiers":[
        {
            "category":"Professional",
            "subcategory":"Management & Consulting",
            "type":"Services"
        }
    ],
    "sg:phone":"+1 317 377 0612",
    "sg:postcode":"46218",
    "sg:province":"IN",
    "sg:tags":[
        "business"
    ],
    "wof:name":"Complete Cad Solutions",
    "wof:placetype":"venue"
},
  "geometry": {"coordinates":[-86.067216,39.816608],"type":"Point"}
}