{
  "type": "Feature",
  "properties": {
    "iso:country":"US",
    "sg:address":"220 N Main St",
    "sg:city":"Churubusco",
    "sg:classifiers":[
        {
            "category":"Organizations",
            "subcategory":"Religious Organization",
            "type":"Services"
        }
    ],
    "sg:phone":"+1 260 693 9578",
    "sg:postcode":"46723",
    "sg:province":"IN",
    "sg:tags":[
        "church"
    ],
    "wof:name":"St John Bosco Catholic Church",
    "wof:placetype":"venue"
},
  "geometry": {"coordinates":[-85.320365,41.23208],"type":"Point"}
}