{
  "type": "Feature",
  "properties": {
    "iso:country":"US",
    "sg:address":"14842 Sulky Way",
    "sg:city":"Carmel",
    "sg:classifiers":[
        {
            "category":"Professional",
            "subcategory":"Business Services",
            "type":"Services"
        }
    ],
    "sg:phone":"+1 317 575 8761",
    "sg:postcode":"46032",
    "sg:province":"IN",
    "wof:name":"Time By Design LLC",
    "wof:placetype":"venue"
},
  "geometry": {"coordinates":[-86.15685999999999,40.002918],"type":"Point"}
}