{
  "type": "Feature",
  "properties": {
    "iso:country":"US",
    "sg:address":"324 W Jackson St",
    "sg:city":"Muncie",
    "sg:classifiers":[
        {
            "category":"Professional",
            "subcategory":"Lawyer & Legal Services",
            "type":"Services"
        }
    ],
    "sg:phone":"+1 765 288 8950",
    "sg:postcode":"47305",
    "sg:province":"IN",
    "sg:tags":[
        "attorney"
    ],
    "wof:name":"Dennis Wenger & Abrell Pro",
    "wof:placetype":"venue"
},
  "geometry": {"coordinates":[-85.38969,40.192939],"type":"Point"}
}