{
  "type": "Feature",
  "properties": {
    "iso:country":"US",
    "sg:address":"1395 W 13th St",
    "sg:city":"Rochester",
    "sg:classifiers":[
        {
            "category":"Building & Trades",
            "subcategory":"Landscaping Services",
            "type":"Services"
        }
    ],
    "sg:phone":"+1 574 223 2769",
    "sg:postcode":"46975",
    "sg:province":"IN",
    "sg:tags":[
        "landscape",
        "contractor"
    ],
    "wof:name":"Sroufe Landscape Nurseries",
    "wof:placetype":"venue"
},
  "geometry": {"coordinates":[-86.23611699999999,41.061341],"type":"Point"}
}