{
  "type": "Feature",
  "properties": {
    "iso:country":"US",
    "sg:address":"2021 N Michigan St",
    "sg:city":"Plymouth",
    "sg:classifiers":[
        {
            "category":"Restaurant",
            "type":"Food & Drink"
        }
    ],
    "sg:menulink":"http://www.allmenus.com/in/plymouth/167409-burger-king/menu/",
    "sg:phone":"+1 574 936 5859",
    "sg:postcode":"46563",
    "sg:province":"IN",
    "sg:tags":[
        "burger",
        "american"
    ],
    "wof:name":"Burger King",
    "wof:placetype":"venue"
},
  "geometry": {"coordinates":[-86.311763,41.360707],"type":"Point"}
}