{
  "type": "Feature",
  "properties": {
    "iso:country":"US",
    "sg:address":"2128 N 1st Ave",
    "sg:city":"Evansville",
    "sg:classifiers":[
        {
            "category":"Food & Beverages",
            "subcategory":"Bakery",
            "type":"Retail Goods"
        }
    ],
    "sg:phone":"+1 812 426 2311",
    "sg:postcode":"47710",
    "sg:province":"IN",
    "sg:tags":[
        "baker"
    ],
    "wof:name":"Donut Bank Bakery & Coffee Shp",
    "wof:placetype":"venue"
},
  "geometry": {"coordinates":[-87.57462,37.998325],"type":"Point"}
}