{
  "type": "Feature",
  "properties": {
    "iso:country":"US",
    "sg:address":"5111 Northern Hills Dr",
    "sg:city":"Fort Wayne",
    "sg:classifiers":[
        {
            "category":"Retail",
            "subcategory":"Auto Repair",
            "type":"Services"
        }
    ],
    "sg:phone":"+1 260 471 8579",
    "sg:postcode":"46825",
    "sg:province":"IN",
    "sg:tags":[
        "repairing",
        "engine"
    ],
    "wof:name":"Wells Small Engine Repair",
    "wof:placetype":"venue"
},
  "geometry": {"coordinates":[-85.080332,41.179067],"type":"Point"}
}