{
  "type": "Feature",
  "properties": {
    "iso:country":"US",
    "sg:address":"8025 S 250 W",
    "sg:city":"Shelbyville",
    "sg:classifiers":[
        {
            "category":"Government",
            "subcategory":"Office",
            "type":"Public Place"
        }
    ],
    "sg:phone":"+1 812 587 5607",
    "sg:postcode":"46176",
    "sg:province":"IN",
    "sg:tags":[
        "village"
    ],
    "wof:name":"Washington Twp Trustee",
    "wof:placetype":"venue"
},
  "geometry": {"coordinates":[-85.826806,39.407837],"type":"Point"}
}