{
  "type": "Feature",
  "properties": {
    "iso:country":"US",
    "sg:address":"4903 Seville Ct",
    "sg:city":"Indianapolis",
    "sg:classifiers":[
        {
            "category":"Professional",
            "subcategory":"Research",
            "type":"Services"
        }
    ],
    "sg:phone":"+1 317 298 9612",
    "sg:postcode":"46228",
    "sg:province":"IN",
    "sg:tags":[
        "development",
        "laboratory"
    ],
    "wof:name":"Analytical Systems Research",
    "wof:placetype":"venue"
},
  "geometry": {"coordinates":[-86.209663,39.843319],"type":"Point"}
}