{
  "type": "Feature",
  "properties": {
    "iso:country":"US",
    "sg:address":"2611 E Jackson St",
    "sg:city":"Muncie",
    "sg:classifiers":[
        {
            "category":"Home & Garden",
            "subcategory":"Furniture",
            "type":"Retail Goods"
        }
    ],
    "sg:phone":"+1 765 529 6025",
    "sg:postcode":"47303",
    "sg:province":"IN",
    "wof:name":"Delk's Furniture",
    "wof:placetype":"venue"
},
  "geometry": {"coordinates":[-85.35599999999999,40.192843],"type":"Point"}
}