{
  "type": "Feature",
  "properties": {
    "iso:country":"US",
    "sg:address":"8048 Preidt Pl",
    "sg:city":"Indianapolis",
    "sg:classifiers":[
        {
            "category":"Real Estate",
            "subcategory":"Real Estate Operator",
            "type":"Services"
        }
    ],
    "sg:phone":"+1 317 885 7155",
    "sg:postcode":"46237",
    "sg:province":"IN",
    "sg:tags":[
        "apartment"
    ],
    "wof:name":"Encore Apartments",
    "wof:placetype":"venue"
},
  "geometry": {"coordinates":[-86.086237,39.649306],"type":"Point"}
}