{
  "type": "Feature",
  "properties": {
    "addr:full":"106 Eastwood Dr Vincennes IN 47591",
    "addr:housenumber":"106",
    "addr:postcode":"47591",
    "addr:street":"Eastwood Dr",
    "iso:country":"US",
    "sg:address":"106 Eastwood Dr",
    "sg:city":"Vincennes",
    "sg:classifiers":[
        {
            "category":"Building & Trades",
            "subcategory":"Electrical",
            "type":"Services"
        }
    ],
    "sg:phone":"+1 812 886 6305",
    "sg:postcode":"47591",
    "sg:province":"IN",
    "sg:tags":[
        "electric",
        "industrial",
        "contractors-commercial",
        "contractor"
    ],
    "wof:name":"Cardinal Electric",
    "wof:placetype":"venue"
},
  "geometry": {"coordinates":[-87.48481700000001,38.688015],"type":"Point"}
}