{
  "type": "Feature",
  "properties": {
    "addr:full":"2640 Cold Spring Rd Indianapolis IN 46222",
    "addr:housenumber":"2640",
    "addr:postcode":"46222",
    "addr:street":"Cold Spring Rd",
    "iso:country":"US",
    "sg:address":"2640 Cold Spring Rd",
    "sg:city":"Indianapolis",
    "sg:classifiers":[
        {
            "category":"Organizations",
            "subcategory":"Non-profit Organization",
            "type":"Services"
        }
    ],
    "sg:phone":"+1 317 923 1518",
    "sg:postcode":"46222",
    "sg:province":"IN",
    "wof:name":"Alpha Home",
    "wof:placetype":"venue"
},
  "geometry": {"coordinates":[-86.203236,39.804306],"type":"Point"}
}