{
  "type": "Feature",
  "properties": {
    "iso:country":"US",
    "sg:address":"481 E Chicago Ave",
    "sg:city":"East Chicago",
    "sg:classifiers":[
        {
            "category":"Manufacturing",
            "subcategory":"Chemicals & Compounds",
            "type":"Manufacturing & Wholesale Goods"
        }
    ],
    "sg:phone":"+1 219 397 8248",
    "sg:postcode":"46312",
    "sg:province":"IN",
    "sg:tags":[
        "product",
        "polyurethane"
    ],
    "wof:name":"Pinder Polyurethane & Plastics",
    "wof:placetype":"venue"
},
  "geometry": {"coordinates":[-87.465929,41.629209],"type":"Point"}
}