{
  "type": "Feature",
  "properties": {
    "addr:full":"2715 S Airport Rd Monticello IN 47960",
    "addr:housenumber":"2715",
    "addr:postcode":"47960",
    "addr:street":"S Airport Rd",
    "iso:country":"US",
    "sg:address":"2715 S Airport Rd",
    "sg:city":"Monticello",
    "sg:classifiers":[
        {
            "category":"Building & Trades",
            "subcategory":"Plumbing",
            "type":"Services"
        }
    ],
    "sg:phone":"+1 574 583 2881",
    "sg:postcode":"47960",
    "sg:province":"IN",
    "sg:tags":[
        "mechanical",
        "contractor"
    ],
    "wof:name":"Quality Mechanical Inc",
    "wof:placetype":"venue"
},
  "geometry": {"coordinates":[-86.763651,40.710416],"type":"Point"}
}