{
  "type": "Feature",
  "properties": {
    "addr:full":"7730 Blackthorn Cir Indianapolis IN 46236",
    "addr:housenumber":"7730",
    "addr:postcode":"46236",
    "addr:street":"Blackthorn Cir",
    "iso:country":"US",
    "sg:address":"7730 Blackthorn Cir",
    "sg:city":"Indianapolis",
    "sg:classifiers":[
        {
            "category":"Building & Trades",
            "subcategory":"Cleaning & Sanitation",
            "type":"Services"
        }
    ],
    "sg:phone":"+1 317 823 9158",
    "sg:postcode":"46236",
    "sg:province":"IN",
    "sg:tags":[
        "maintenance"
    ],
    "wof:name":"True Reflections Cleaning Svc",
    "wof:placetype":"venue"
},
  "geometry": {"coordinates":[-85.950655,39.895671],"type":"Point"}
}