{
  "type": "Feature",
  "properties": {
    "iso:country":"US",
    "sg:address":"314 Massachusetts Ave",
    "sg:city":"Indianapolis",
    "sg:classifiers":[
        {
            "category":"Restaurant",
            "type":"Food & Drink"
        }
    ],
    "sg:phone":"+1 317 624 9533",
    "sg:postcode":"46204",
    "sg:province":"IN",
    "wof:name":"Chez Jean Bakery Cafe Inc",
    "wof:placetype":"venue"
},
  "geometry": {"coordinates":[-86.152664,39.772482],"type":"Point"}
}