{
  "type": "Feature",
  "properties": {
    "iso:country":"US",
    "sg:address":"968 S Center St",
    "sg:city":"French Lick",
    "sg:classifiers":[
        {
            "category":"Retail",
            "subcategory":"Repair Shop",
            "type":"Services"
        }
    ],
    "sg:phone":"+1 812 936 4914",
    "sg:postcode":"47432",
    "sg:province":"IN",
    "sg:tags":[
        "lock",
        "locksmith"
    ],
    "wof:name":"Springs Valley Locksmith",
    "wof:placetype":"venue"
},
  "geometry": {"coordinates":[-86.622578,38.541035],"type":"Point"}
}