{
  "type": "Feature",
  "properties": {
    "iso:country":"US",
    "sg:address":"2801 Lafayette Rd",
    "sg:city":"Indianapolis",
    "sg:classifiers":[
        {
            "category":"Food & Beverages",
            "subcategory":"Bakery",
            "type":"Retail Goods"
        }
    ],
    "sg:phone":"+1 317 926 4441",
    "sg:postcode":"46222",
    "sg:province":"IN",
    "sg:tags":[
        "baker"
    ],
    "wof:name":"Wonder Bread & Hostess Cakes",
    "wof:placetype":"venue"
},
  "geometry": {"coordinates":[-86.21935499999999,39.808159],"type":"Point"}
}