{
  "type": "Feature",
  "properties": {
    "iso:country":"US",
    "sg:address":"1818 Jeanwood Dr",
    "sg:city":"Elkhart",
    "sg:classifiers":[
        {
            "category":"Building & Trades",
            "subcategory":"Construction",
            "type":"Services"
        }
    ],
    "sg:phone":"+1 574 262 2400",
    "sg:postcode":"46514",
    "sg:province":"IN",
    "sg:tags":[
        "painter"
    ],
    "wof:name":"Tom's Painting",
    "wof:placetype":"venue"
},
  "geometry": {"coordinates":[-85.927299,41.711085],"type":"Point"}
}