{
  "type": "Feature",
  "properties": {
    "iso:country":"US",
    "sg:address":"720 N Gardner St",
    "sg:city":"Scottsburg",
    "sg:classifiers":[
        {
            "category":"Shopping",
            "type":"Retail Goods"
        }
    ],
    "sg:phone":"+1 812 752 9449",
    "sg:postcode":"47170",
    "sg:province":"IN",
    "sg:tags":[
        "equipment",
        "care",
        "health",
        "home"
    ],
    "wof:name":"Premier Home Care Inc",
    "wof:placetype":"venue"
},
  "geometry": {"coordinates":[-85.781559,38.695508],"type":"Point"}
}