{
  "type": "Feature",
  "properties": {
    "iso:country":"US",
    "sg:address":"8475 E US Hwy 33",
    "sg:city":"Churubusco",
    "sg:classifiers":[
        {
            "category":"Sports & Exercise",
            "subcategory":"Gym",
            "type":"Entertainment"
        }
    ],
    "sg:phone":"+1 260 693 1188",
    "sg:postcode":"46723",
    "sg:province":"IN",
    "sg:tags":[
        "club",
        "health",
        "studio",
        "gymnasium"
    ],
    "wof:name":"Inches-A-Weigh Fitness-Women",
    "wof:placetype":"venue"
},
  "geometry": {"coordinates":[-85.330095,41.240337],"type":"Point"}
}