{
  "type": "Feature",
  "properties": {
    "iso:country":"US",
    "sg:address":"3300 N Everbrook Ln",
    "sg:city":"Muncie",
    "sg:classifiers":[
        {
            "category":"Banks & Credit Unions",
            "subcategory":"Bank",
            "type":"Services"
        }
    ],
    "sg:phone":"+1 765 751 3566",
    "sg:postcode":"47304",
    "sg:province":"IN",
    "wof:name":"Star Financial Bank",
    "wof:placetype":"venue"
},
  "geometry": {"coordinates":[-85.426573,40.216632],"type":"Point"}
}