{
  "type": "Feature",
  "properties": {
    "addr:full":"2000 Ridge Rd Highland IN 46322",
    "addr:housenumber":"2000",
    "addr:postcode":"46322",
    "addr:street":"Ridge Rd",
    "iso:country":"US",
    "sg:address":"2000 Ridge Rd",
    "sg:city":"Highland",
    "sg:classifiers":[
        {
            "category":"Restaurant",
            "type":"Food & Drink"
        }
    ],
    "sg:phone":"+1 219 838 1510",
    "sg:postcode":"46322",
    "sg:province":"IN",
    "sg:tags":[
        "banquet",
        "rooms"
    ],
    "wof:name":"Unique Events Inc",
    "wof:placetype":"venue"
},
  "geometry": {"coordinates":[-87.476089,41.556664],"type":"Point"}
}