{
  "type": "Feature",
  "properties": {
    "iso:country":"US",
    "sg:address":"5022 Binford Ln",
    "sg:city":"Fort Wayne",
    "sg:classifiers":[
        {
            "category":"Professional",
            "subcategory":"Accounting & Tax Preparation",
            "type":"Services"
        }
    ],
    "sg:phone":"+1 260 432 2631",
    "sg:postcode":"46804",
    "sg:province":"IN",
    "wof:name":"Larry L Puls CPA",
    "wof:placetype":"venue"
},
  "geometry": {"coordinates":[-85.261177,41.036555],"type":"Point"}
}