{
  "type": "Feature",
  "properties": {
    "iso:country":"US",
    "sg:address":"3757 N Capitol Ave",
    "sg:city":"Indianapolis",
    "sg:classifiers":[
        {
            "category":"Food & Beverages",
            "subcategory":"Liquor & Beverages",
            "type":"Retail Goods"
        }
    ],
    "sg:phone":"+1 317 923 1683",
    "sg:postcode":"46208",
    "sg:province":"IN",
    "wof:name":"Community Spirits",
    "wof:placetype":"venue"
},
  "geometry": {"coordinates":[-86.161446,39.823755],"type":"Point"}
}