{
  "type": "Feature",
  "properties": {
    "iso:country":"US",
    "sg:address":"1616 N Section St",
    "sg:city":"Sullivan",
    "sg:phone":"+1 812 268 3389",
    "sg:postcode":"47882",
    "sg:province":"IN",
    "wof:name":"Patrick's Restaurant",
    "wof:placetype":"venue"
},
  "geometry": {"coordinates":[-87.409285,39.111711],"type":"Point"}
}