{
  "type": "Feature",
  "properties": {
    "iso:country":"US",
    "sg:address":"71 Hadley Woodland St",
    "sg:city":"Mooresville",
    "sg:classifiers":[
        {
            "category":"Manufacturing",
            "subcategory":"Aerospace",
            "type":"Manufacturing & Wholesale Goods"
        }
    ],
    "sg:phone":"+1 317 831 1144",
    "sg:postcode":"46158",
    "sg:province":"IN",
    "sg:tags":[
        "instrument",
        "aircraft",
        "avionics"
    ],
    "wof:name":"Voelz Avionics, Inc",
    "wof:placetype":"venue"
},
  "geometry": {"coordinates":[-86.376104,39.623133],"type":"Point"}
}