{
  "type": "Feature",
  "properties": {
    "addr:full":"2802 E 38th St Indianapolis IN 46218",
    "addr:housenumber":"2802",
    "addr:postcode":"46218",
    "addr:street":"E 38Th St",
    "iso:country":"US",
    "sg:address":"2802 E 38th St",
    "sg:city":"Indianapolis",
    "sg:classifiers":[
        {
            "category":"Cinema",
            "subcategory":"Movie Rental",
            "type":"Entertainment"
        }
    ],
    "sg:phone":"+1 317 541 0240",
    "sg:postcode":"46218",
    "sg:province":"IN",
    "sg:tags":[
        "leasing",
        "video",
        "disc",
        "tape"
    ],
    "wof:name":"Blockbuster Video",
    "wof:placetype":"venue"
},
  "geometry": {"coordinates":[-86.1168,39.825395],"type":"Point"}
}