{
  "type": "Feature",
  "properties": {
    "addr:full":"8737 State Rd 114 Rensselaer IN 47978",
    "addr:housenumber":"8737;114",
    "addr:postcode":"47978",
    "addr:street":"State Rd",
    "iso:country":"US",
    "sg:address":"8737 State Rd 114",
    "sg:city":"Rensselaer",
    "sg:classifiers":[
        {
            "category":"Restaurant",
            "type":"Food & Drink"
        }
    ],
    "sg:phone":"+1 219 866 8700",
    "sg:postcode":"47978",
    "sg:province":"IN",
    "wof:name":"KFC",
    "wof:placetype":"venue"
},
  "geometry": {"coordinates":[-87.22072,40.940651],"type":"Point"}
}