{
  "type": "Feature",
  "properties": {
    "addr:full":"407 Clay St Jasper IN 47546",
    "addr:housenumber":"407",
    "addr:postcode":"47546",
    "addr:street":"Clay St",
    "iso:country":"US",
    "sg:address":"407 Clay St",
    "sg:city":"Jasper",
    "sg:classifiers":[
        {
            "category":"Wholesale",
            "subcategory":"Medical Equipment & Supplies",
            "type":"Manufacturing & Wholesale Goods"
        }
    ],
    "sg:phone":"+1 812 482 5570",
    "sg:postcode":"47546",
    "sg:province":"IN",
    "wof:name":"K M T Motion Medical Inc",
    "wof:placetype":"venue"
},
  "geometry": {"coordinates":[-86.932805,38.390238],"type":"Point"}
}