{
  "type": "Feature",
  "properties": {
    "addr:full":"4020 Earnings Way New Albany IN 47150",
    "addr:housenumber":"4020",
    "addr:postcode":"47150",
    "addr:street":"Earnings Way",
    "iso:country":"US",
    "sg:address":"4020 Earnings Way",
    "sg:city":"New Albany",
    "sg:classifiers":[
        {
            "category":"Wholesale",
            "subcategory":"Medical Equipment & Supplies",
            "type":"Manufacturing & Wholesale Goods"
        }
    ],
    "sg:phone":"+1 812 949 3400",
    "sg:postcode":"47150",
    "sg:province":"IN",
    "sg:tags":[
        "optical"
    ],
    "wof:name":"D O Kentuckiana",
    "wof:placetype":"venue"
},
  "geometry": {"coordinates":[-85.835719,38.339994],"type":"Point"}
}