{
  "type": "Feature",
  "properties": {
    "iso:country":"US",
    "sg:address":"616 E Pearl St",
    "sg:city":"Batesville",
    "sg:classifiers":[
        {
            "category":"Professional",
            "subcategory":"Lawyer & Legal Services",
            "type":"Services"
        }
    ],
    "sg:phone":"+1 812 934 4851",
    "sg:postcode":"47006",
    "sg:province":"IN",
    "sg:tags":[
        "attorney"
    ],
    "wof:name":"Jones & Dorenbusch",
    "wof:placetype":"venue"
},
  "geometry": {"coordinates":[-85.217807,39.296224],"type":"Point"}
}