{
  "type": "Feature",
  "properties": {
    "iso:country":"US",
    "sg:address":"151 W Ohio St",
    "sg:city":"Indianapolis",
    "sg:classifiers":[
        {
            "category":"Government",
            "subcategory":"Office",
            "type":"Public Place"
        }
    ],
    "sg:phone":"+1 317 232 0506",
    "sg:postcode":"46204",
    "sg:province":"IN",
    "sg:tags":[
        "state",
        "program"
    ],
    "sg:website":"www.doe.state.in.us",
    "wof:name":"Indiana Department-Education",
    "wof:placetype":"venue"
},
  "geometry": {"coordinates":[-86.160898,39.769905],"type":"Point"}
}