{
  "type": "Feature",
  "properties": {
    "iso:country":"US",
    "sg:address":"48 Cottonwood Dr",
    "sg:city":"Garrett",
    "sg:classifiers":[
        {
            "category":"Restaurant",
            "type":"Food & Drink"
        }
    ],
    "sg:phone":"+1 260 637 4308",
    "sg:postcode":"46738",
    "sg:province":"IN",
    "sg:tags":[
        "eating"
    ],
    "wof:name":"Traxside Bar & Grill Inc",
    "wof:placetype":"venue"
},
  "geometry": {"coordinates":[-85.13179700000001,41.283809],"type":"Point"}
}