{
  "type": "Feature",
  "properties": {
    "iso:country":"US",
    "sg:address":"523 Polaris Dr",
    "sg:city":"Indianapolis",
    "sg:classifiers":[
        {
            "category":"Retail",
            "subcategory":"Laundry & Dry Cleaning",
            "type":"Services"
        },
        {
            "category":"Building & Trades",
            "subcategory":"Cleaning & Sanitation",
            "type":"Services"
        }
    ],
    "sg:phone":"+1 317 313 0457",
    "sg:postcode":"46241",
    "sg:province":"IN",
    "sg:tags":[
        "cleaner",
        "house"
    ],
    "sg:website":"http://www.mrcleancleaningservice.com",
    "wof:name":"Mr. Clean Cleaning Service",
    "wof:placetype":"venue"
},
  "geometry": {"coordinates":[-86.284712,39.757718],"type":"Point"}
}