{
  "type": "Feature",
  "properties": {
    "iso:country":"US",
    "sg:address":"217 E Southway Blvd",
    "sg:city":"Kokomo",
    "sg:classifiers":[
        {
            "category":"Banks & Credit Unions",
            "subcategory":"Bank",
            "type":"Services"
        }
    ],
    "sg:phone":"+1 765 455 5210",
    "sg:postcode":"46902",
    "sg:province":"IN",
    "sg:tags":[
        "loan",
        "real estate"
    ],
    "wof:name":"Walton Mortgage",
    "wof:placetype":"venue"
},
  "geometry": {"coordinates":[-86.126186,40.444197],"type":"Point"}
}