{
  "type": "Feature",
  "properties": {
    "iso:country":"US",
    "sg:address":"1133 E Perry St",
    "sg:city":"Indianapolis",
    "sg:classifiers":[
        {
            "category":"Building & Trades",
            "subcategory":"Plumbing",
            "type":"Services"
        }
    ],
    "sg:phone":"+1 317 245 8770",
    "sg:postcode":"46227",
    "sg:province":"IN",
    "sg:tags":[
        "plumbing-drain",
        "cleaning",
        "sewer"
    ],
    "wof:name":"Larry Stokes Plumbing",
    "wof:placetype":"venue"
},
  "geometry": {"coordinates":[-86.13909099999999,39.720504],"type":"Point"}
}