{
  "type": "Feature",
  "properties": {
    "iso:country":"US",
    "sg:address":"5231 N Park Ave",
    "sg:city":"Indianapolis",
    "sg:classifiers":[
        {
            "category":"Professional",
            "type":"Services"
        }
    ],
    "sg:phone":"+1 317 283 1192",
    "sg:postcode":"46220",
    "sg:province":"IN",
    "sg:tags":[
        "editorial"
    ],
    "wof:name":"Susan Christopherson",
    "wof:placetype":"venue"
},
  "geometry": {"coordinates":[-86.148481,39.848333],"type":"Point"}
}