{
  "type": "Feature",
  "properties": {
    "addr:full":"2900 E Co Rd 600 N Frankfort IN 46041",
    "addr:housenumber":"2900;600",
    "addr:postcode":"46041",
    "addr:street":"E Co Rd;N",
    "iso:country":"US",
    "sg:address":"2900 E Co Rd 600 N",
    "sg:city":"Frankfort",
    "sg:classifiers":[
        {
            "category":"Farming",
            "subcategory":"Farm & Veterinary Services",
            "type":"Manufacturing & Wholesale Goods"
        }
    ],
    "sg:phone":"+1 765 650 8722",
    "sg:postcode":"46041",
    "sg:province":"IN",
    "sg:tags":[
        "crop",
        "harvesting"
    ],
    "wof:name":"Bixler Bradley G",
    "wof:placetype":"venue"
},
  "geometry": {"coordinates":[-86.452147,40.373719],"type":"Point"}
}