{
  "type": "Feature",
  "properties": {
    "iso:country":"US",
    "sg:address":"3150 N 750 E",
    "sg:city":"Lebanon",
    "sg:classifiers":[
        {
            "category":"Farming",
            "subcategory":"Farm",
            "type":"Manufacturing & Wholesale Goods"
        }
    ],
    "sg:phone":"+1 317 769 4656",
    "sg:postcode":"46052",
    "sg:province":"IN",
    "sg:tags":[
        "crop",
        "general"
    ],
    "wof:name":"William Padgett",
    "wof:placetype":"venue"
},
  "geometry": {"coordinates":[-86.32756000000001,40.096432],"type":"Point"}
}