{
  "type": "Feature",
  "properties": {
    "iso:country":"US",
    "sg:address":"29235 US Hwy 33",
    "sg:city":"Elkhart",
    "sg:classifiers":[
        {
            "category":"Professional",
            "subcategory":"Advertising",
            "type":"Services"
        }
    ],
    "sg:phone":"+1 574 294 5535",
    "sg:postcode":"46516",
    "sg:province":"IN",
    "sg:tags":[
        "distribution"
    ],
    "wof:name":"Alco Tool Supply Inc",
    "wof:placetype":"venue"
},
  "geometry": {"coordinates":[-86.021648,41.668108],"type":"Point"}
}