{
  "type": "Feature",
  "properties": {
    "iso:country":"US",
    "sg:address":"522 Liberty St",
    "sg:city":"Covington",
    "sg:classifiers":[
        {
            "category":"Personal",
            "subcategory":"Beauty Salon",
            "type":"Services"
        }
    ],
    "sg:phone":"+1 765 793 1822",
    "sg:postcode":"47932",
    "sg:province":"IN",
    "sg:tags":[
        "shop"
    ],
    "wof:name":"Utopia Styling Salon",
    "wof:placetype":"venue"
},
  "geometry": {"coordinates":[-87.394199,40.136982],"type":"Point"}
}