{
  "type": "Feature",
  "properties": {
    "iso:country":"US",
    "sg:address":"6620 Scatterfield Rd",
    "sg:city":"Anderson",
    "sg:classifiers":[
        {
            "category":"Restaurant",
            "type":"Food & Drink"
        }
    ],
    "sg:phone":"+1 765 643 8343",
    "sg:postcode":"46013",
    "sg:province":"IN",
    "wof:name":"A & W Family Restaurant",
    "wof:placetype":"venue"
},
  "geometry": {"coordinates":[-85.65270700000001,40.049],"type":"Point"}
}