{
  "type": "Feature",
  "properties": {
    "iso:country":"US",
    "sg:address":"2425 Southeastern Ave",
    "sg:city":"Indianapolis",
    "sg:classifiers":[
        {
            "category":"Organizations",
            "subcategory":"Religious Organization",
            "type":"Services"
        }
    ],
    "sg:phone":"+1 317 231 9771",
    "sg:postcode":"46201",
    "sg:province":"IN",
    "sg:tags":[
        "church"
    ],
    "wof:name":"Philippi Inner City Baptist",
    "wof:placetype":"venue"
},
  "geometry": {"coordinates":[-86.120177,39.760978],"type":"Point"}
}