{
  "type": "Feature",
  "properties": {
    "iso:country":"US",
    "sg:address":"5158 S State Rd 116",
    "sg:city":"Bluffton",
    "sg:classifiers":[
        {
            "category":"Farming",
            "subcategory":"Livestock Farm",
            "type":"Manufacturing & Wholesale Goods"
        }
    ],
    "sg:phone":"+1 260 334 5320",
    "sg:postcode":"46714",
    "sg:province":"IN",
    "sg:tags":[
        "hog",
        "or",
        "feedlot"
    ],
    "wof:name":"Ault Farms",
    "wof:placetype":"venue"
},
  "geometry": {"coordinates":[-85.059558,40.668674],"type":"Point"}
}