{
  "type": "Feature",
  "properties": {
    "iso:country":"US",
    "sg:address":"2334 Davis Rd",
    "sg:city":"Indianapolis",
    "sg:classifiers":[
        {
            "category":"Food & Beverages",
            "subcategory":"Specialty",
            "type":"Retail Goods"
        }
    ],
    "sg:phone":"+1 317 862 2116",
    "sg:postcode":"46239",
    "sg:province":"IN",
    "sg:tags":[
        "spice"
    ],
    "wof:name":"Watkins Products",
    "wof:placetype":"venue"
},
  "geometry": {"coordinates":[-85.989727,39.73648],"type":"Point"}
}