{
  "type": "Feature",
  "properties": {
    "iso:country":"US",
    "sg:address":"130 Hunter Station Way Ste 201",
    "sg:city":"Sellersburg",
    "sg:classifiers":[
        {
            "category":"Health Services",
            "subcategory":"Doctor",
            "type":"Services"
        }
    ],
    "sg:phone":"+1 812 941 7232",
    "sg:postcode":"47172",
    "sg:province":"IN",
    "sg:tags":[
        "orthopedist"
    ],
    "sg:website":"www.shoulderandelbowcenter.com",
    "wof:name":"Moskal Michael Dr",
    "wof:placetype":"venue"
},
  "geometry": {"coordinates":[-85.77207900000001,38.382884],"type":"Point"}
}