{
  "type": "Feature",
  "properties": {
    "iso:country":"US",
    "sg:address":"10790 Calumet Ave",
    "sg:city":"Dyer",
    "sg:classifiers":[
        {
            "category":"Education",
            "subcategory":"School",
            "type":"Public Place"
        },
        {
            "category":"Organizations",
            "subcategory":"Religious Organization",
            "type":"Services"
        }
    ],
    "sg:phone":"+1 219 558 2660",
    "sg:postcode":"46311",
    "sg:province":"IN",
    "wof:name":"Protestant Reformed Christian School",
    "wof:placetype":"venue"
},
  "geometry": {"coordinates":[-87.508441,41.420522],"type":"Point"}
}