{
  "type": "Feature",
  "properties": {
    "iso:country":"US",
    "sg:address":"14626 Flatrock Rd",
    "sg:city":"Monroeville",
    "sg:classifiers":[
        {
            "category":"Retail",
            "subcategory":"Repair Shop",
            "type":"Services"
        }
    ],
    "sg:phone":"+1 260 639 0321",
    "sg:postcode":"46773",
    "sg:province":"IN",
    "wof:name":"Stephen Hetler",
    "wof:placetype":"venue"
},
  "geometry": {"coordinates":[-84.947594,40.963574],"type":"Point"}
}