{
  "type": "Feature",
  "properties": {
    "addr:full":"8177 Covington Ct Newburgh IN 47630",
    "addr:housenumber":"8177",
    "addr:postcode":"47630",
    "addr:street":"Covington Ct",
    "iso:country":"US",
    "sg:address":"8177 Covington Ct",
    "sg:city":"Newburgh",
    "sg:classifiers":[
        {
            "category":"Professional",
            "subcategory":"Business Services",
            "type":"Services"
        }
    ],
    "sg:phone":"+1 812 858 8451",
    "sg:postcode":"47630",
    "sg:province":"IN",
    "wof:name":"Floors & Decor Inc",
    "wof:placetype":"venue"
},
  "geometry": {"coordinates":[-87.399655,37.981356],"type":"Point"}
}