{
  "type": "Feature",
  "properties": {
    "addr:full":"11529 N 400 E Demotte IN 46310",
    "addr:housenumber":"11529",
    "addr:postcode":"46310",
    "addr:street":"N 400 E",
    "iso:country":"US",
    "sg:address":"11529 N 400 E",
    "sg:city":"Demotte",
    "sg:phone":"+1 219 345 2267",
    "sg:postcode":"46310",
    "sg:province":"IN",
    "sg:tags":[
        "farm",
        "corn"
    ],
    "wof:name":"Cornelius Sekema",
    "wof:placetype":"venue"
},
  "geometry": {"coordinates":[-87.314657,41.163686],"type":"Point"}
}