{
  "type": "Feature",
  "properties": {
    "iso:country":"US",
    "sg:address":"803 Lincoln Ave",
    "sg:city":"Evansville",
    "sg:classifiers":[
        {
            "category":"Retail",
            "subcategory":"Auto Repair",
            "type":"Services"
        }
    ],
    "sg:phone":"+1 812 423 6499",
    "sg:postcode":"47713",
    "sg:province":"IN",
    "sg:tags":[
        "repairing",
        "automobile"
    ],
    "wof:name":"Midwest Auto Repair",
    "wof:placetype":"venue"
},
  "geometry": {"coordinates":[-87.553814,37.970085],"type":"Point"}
}