{
  "type": "Feature",
  "properties": {
    "iso:country":"US",
    "sg:address":"3012 Claremont Ave",
    "sg:city":"Evansville",
    "sg:classifiers":[
        {
            "category":"Building & Trades",
            "subcategory":"Plumbing",
            "type":"Services"
        }
    ],
    "sg:phone":"+1 812 425 5211",
    "sg:postcode":"47712",
    "sg:province":"IN",
    "sg:tags":[
        "heating",
        "contractor"
    ],
    "wof:name":"Moose Lewis Contracting Inc",
    "wof:placetype":"venue"
},
  "geometry": {"coordinates":[-87.613044,37.971249],"type":"Point"}
}