{
  "type": "Feature",
  "properties": {
    "addr:full":"2130 W Sycamore St Kokomo IN 46901",
    "addr:housenumber":"2130",
    "addr:postcode":"46901",
    "addr:street":"W Sycamore St",
    "iso:country":"US",
    "sg:address":"2130 W Sycamore St",
    "sg:city":"Kokomo",
    "sg:classifiers":[
        {
            "category":"Personal",
            "subcategory":"Barber",
            "type":"Services"
        }
    ],
    "sg:phone":"+1 765 452 9594",
    "sg:postcode":"46901",
    "sg:province":"IN",
    "sg:website":"www.forestparkhobby.com",
    "wof:name":"Forest Park Barber Salon",
    "wof:placetype":"venue"
},
  "geometry": {"coordinates":[-86.158404,40.487343],"type":"Point"}
}