{
  "type": "Feature",
  "properties": {
    "iso:country":"US",
    "sg:address":"728 W US Hwy 20",
    "sg:city":"Michigan City",
    "sg:classifiers":[
        {
            "category":"Wholesale",
            "subcategory":"Auto Parts",
            "type":"Manufacturing & Wholesale Goods"
        }
    ],
    "sg:phone":"+1 219 872 5567",
    "sg:postcode":"46360",
    "sg:province":"IN",
    "sg:tags":[
        "automobile",
        "rebuilt"
    ],
    "wof:name":"LKQ Great Lakes",
    "wof:placetype":"venue"
},
  "geometry": {"coordinates":[-86.904616,41.680346],"type":"Point"}
}