{
  "type": "Feature",
  "properties": {
    "iso:country":"US",
    "sg:address":"654 E Market St",
    "sg:city":"Nappanee",
    "sg:classifiers":[
        {
            "category":"Personal",
            "subcategory":"Beauty Salon",
            "type":"Services"
        }
    ],
    "sg:phone":"+1 574 773 3625",
    "sg:postcode":"46550",
    "sg:province":"IN",
    "sg:tags":[
        "shop"
    ],
    "wof:name":"Helens Beauty Shoppe",
    "wof:placetype":"venue"
},
  "geometry": {"coordinates":[-85.994579,41.44271],"type":"Point"}
}