{
  "type": "Feature",
  "properties": {
    "iso:country":"US",
    "sg:address":"9513 E Washington St",
    "sg:city":"Indianapolis",
    "sg:classifiers":[
        {
            "category":"Shopping",
            "subcategory":"Clothing, Apparel, & Fashions",
            "type":"Retail Goods"
        }
    ],
    "sg:phone":"+1 317 897 9028",
    "sg:postcode":"46229",
    "sg:province":"IN",
    "sg:tags":[
        "theatrical",
        "costume"
    ],
    "wof:name":"Ron's Halloween",
    "wof:placetype":"venue"
},
  "geometry": {"coordinates":[-85.990509,39.774799],"type":"Point"}
}