{
  "type": "Feature",
  "properties": {
    "iso:country":"US",
    "sg:address":"12117 E 75th St",
    "sg:city":"Indianapolis",
    "sg:classifiers":[
        {
            "category":"Restaurant",
            "type":"Food & Drink"
        }
    ],
    "sg:phone":"+1 317 335 2567",
    "sg:postcode":"46236",
    "sg:province":"IN",
    "sg:tags":[
        "eating"
    ],
    "wof:name":"TGI Fridays",
    "wof:placetype":"venue"
},
  "geometry": {"coordinates":[-85.948802,39.891249],"type":"Point"}
}