{
  "type": "Feature",
  "properties": {
    "addr:full":"7301 W 10th St Indianapolis IN 46214",
    "addr:housenumber":"7301",
    "addr:postcode":"46214",
    "addr:street":"W 10Th St",
    "iso:country":"US",
    "sg:address":"7301 W 10th St",
    "sg:city":"Indianapolis",
    "sg:classifiers":[
        {
            "category":"Banks & Credit Unions",
            "subcategory":"Financial Services",
            "type":"Services"
        }
    ],
    "sg:phone":"+1 317 209 8385",
    "sg:postcode":"46214",
    "sg:province":"IN",
    "sg:tags":[
        "cashing",
        "loan",
        "payday",
        "alternative",
        "check"
    ],
    "sg:website":"http://www.acecashexpress.com",
    "wof:name":"ACE Cash Express",
    "wof:placetype":"venue"
},
  "geometry": {"coordinates":[-86.289192,39.779148],"type":"Point"}
}