{
  "type": "Feature",
  "properties": {
    "iso:country":"US",
    "sg:address":"4765 N US Hwy 24 E",
    "sg:city":"Huntington",
    "sg:classifiers":[
        {
            "category":"Retail",
            "subcategory":"Animal Services",
            "type":"Services"
        }
    ],
    "sg:phone":"+1 260 356 0355",
    "sg:postcode":"46750",
    "sg:province":"IN",
    "sg:tags":[
        "shelter"
    ],
    "wof:name":"Huntington County Humane Scty",
    "wof:placetype":"venue"
},
  "geometry": {"coordinates":[-85.440827,40.900251],"type":"Point"}
}