{
  "type": "Feature",
  "properties": {
    "iso:country":"US",
    "sg:address":"1280 Lafayette Ave",
    "sg:city":"Terre Haute",
    "sg:classifiers":[
        {
            "category":"Food & Beverages",
            "subcategory":"Groceries & Convenience Stores",
            "type":"Retail Goods"
        }
    ],
    "sg:phone":"+1 812 242 2960",
    "sg:postcode":"47804",
    "sg:province":"IN",
    "wof:name":"Mac's",
    "wof:placetype":"venue"
},
  "geometry": {"coordinates":[-87.398787,39.491717],"type":"Point"}
}