{
  "type": "Feature",
  "properties": {
    "iso:country":"US",
    "sg:address":"5650 Harrison St",
    "sg:city":"Merrillville",
    "sg:classifiers":[
        {
            "category":"Real Estate",
            "subcategory":"Real Estate Agent",
            "type":"Services"
        }
    ],
    "sg:phone":"+1 219 836 5626",
    "sg:postcode":"46410",
    "sg:province":"IN",
    "wof:name":"Collins Barksdale",
    "wof:placetype":"venue"
},
  "geometry": {"coordinates":[-87.345742,41.515609],"type":"Point"}
}