{
  "type": "Feature",
  "properties": {
    "addr:full":"1570 S 650 W Rensselaer IN 47978",
    "addr:housenumber":"1570;650",
    "addr:postcode":"47978",
    "addr:street":"S;W",
    "iso:country":"US",
    "sg:address":"1570 S 650 W",
    "sg:city":"Rensselaer",
    "sg:phone":"+1 219 866 5294",
    "sg:postcode":"47978",
    "sg:province":"IN",
    "sg:tags":[
        "farm",
        "corn",
        "soybean"
    ],
    "wof:name":"Dan Alson",
    "wof:placetype":"venue"
},
  "geometry": {"coordinates":[-87.17103400000001,40.982257],"type":"Point"}
}