{
  "type": "Feature",
  "properties": {
    "iso:country":"US",
    "sg:address":"11619 Edison Rd",
    "sg:city":"Osceola",
    "sg:classifiers":[
        {
            "category":"Wholesale",
            "subcategory":"Construction Materials",
            "type":"Manufacturing & Wholesale Goods"
        }
    ],
    "sg:phone":"+1 574 259 2441",
    "sg:postcode":"46561",
    "sg:province":"IN",
    "sg:tags":[
        "fence"
    ],
    "wof:name":"Everett Fence Corp",
    "wof:placetype":"venue"
},
  "geometry": {"coordinates":[-86.088842,41.695532],"type":"Point"}
}