{
  "type": "Feature",
  "properties": {
    "addr:full":"8109 W State Rd 47 Thorntown IN 46071",
    "addr:housenumber":"8109;47",
    "addr:postcode":"thorntown;46071",
    "addr:street":"W State Rd",
    "iso:country":"US",
    "sg:address":"8109 W State Rd 47",
    "sg:city":"Thorntown",
    "sg:classifiers":[
        {
            "category":"Organizations",
            "subcategory":"Professional Association",
            "type":"Services"
        }
    ],
    "sg:phone":"+1 765 436 7381",
    "sg:postcode":"46071",
    "sg:province":"IN",
    "wof:name":"F & A Masons",
    "wof:placetype":"venue"
},
  "geometry": {"coordinates":[-86.622195,40.129544],"type":"Point"}
}