{
  "type": "Feature",
  "properties": {
    "iso:country":"US",
    "sg:address":"4004 US Hwy 421",
    "sg:city":"Madison",
    "sg:classifiers":[
        {
            "category":"Manufacturing",
            "subcategory":"Metals",
            "type":"Manufacturing & Wholesale Goods"
        }
    ],
    "sg:phone":"+1 812 265 9255",
    "sg:postcode":"47250",
    "sg:province":"IN",
    "sg:tags":[
        "tubing"
    ],
    "wof:name":"Century Tube Corp",
    "wof:placetype":"venue"
},
  "geometry": {"coordinates":[-85.385131,38.798994],"type":"Point"}
}