{
  "type": "Feature",
  "properties": {
    "iso:country":"US",
    "sg:address":"4808 Ashbrook Dr",
    "sg:city":"Noblesville",
    "sg:classifiers":[
        {
            "category":"Professional",
            "subcategory":"Employment Agencies",
            "type":"Services"
        }
    ],
    "sg:phone":"+1 317 867 1867",
    "sg:postcode":"46062",
    "sg:province":"IN",
    "sg:tags":[
        "contractor"
    ],
    "wof:name":"Jewelry Careers Unlimited",
    "wof:placetype":"venue"
},
  "geometry": {"coordinates":[-86.087576,40.052541],"type":"Point"}
}