{
  "type": "Feature",
  "properties": {
    "addr:full":"10211 E 116th St Fishers IN 46037",
    "addr:housenumber":"10211",
    "addr:postcode":"46037",
    "addr:street":"E 116Th St",
    "iso:country":"US",
    "sg:address":"10211 E 116th St",
    "sg:city":"Fishers",
    "sg:classifiers":[
        {
            "category":"Manufacturing",
            "subcategory":"Tools & Machinery",
            "type":"Manufacturing & Wholesale Goods"
        },
        {
            "category":"Utilities",
            "subcategory":"Water",
            "type":"Services"
        },
        {
            "category":"Wholesale",
            "subcategory":"Machinery & Supplies",
            "type":"Manufacturing & Wholesale Goods"
        },
        {
            "category":"Utilities",
            "subcategory":"Fuel Oil & Lpg",
            "type":"Services"
        }
    ],
    "sg:phone":"+1 317 849 2535",
    "sg:postcode":"46037",
    "sg:province":"IN",
    "sg:tags":[
        "control",
        "equipment",
        "well",
        "contractor",
        "flood",
        "pump",
        "drilling"
    ],
    "wof:name":"Beechler Well Drilling & Pump Service",
    "wof:placetype":"venue"
},
  "geometry": {"coordinates":[-85.987399,39.957041],"type":"Point"}
}