{
  "type": "Feature",
  "properties": {
    "addr:full":"10999 Stahl Rd Newburgh IN 47630",
    "addr:housenumber":"10999",
    "addr:postcode":"47630",
    "addr:street":"Stahl Rd",
    "iso:country":"US",
    "sg:address":"10999 Stahl Rd",
    "sg:city":"Newburgh",
    "sg:classifiers":[
        {
            "category":"Education",
            "subcategory":"University",
            "type":"Public Place"
        }
    ],
    "sg:phone":"+1 812 858 1600",
    "sg:postcode":"47630",
    "sg:province":"IN",
    "sg:tags":[
        "college"
    ],
    "sg:website":"www.itt-tech.edu",
    "wof:name":"ITT Technical Institute",
    "wof:placetype":"venue"
},
  "geometry": {"coordinates":[-87.44940200000001,37.980301],"type":"Point"}
}