{
  "type": "Feature",
  "properties": {
    "addr:full":"2057 N 150 E Laporte IN 46350",
    "addr:housenumber":"2057",
    "addr:postcode":"46350",
    "addr:street":"N 150 E Laporte",
    "iso:country":"US",
    "sg:address":"2057 N 150 E",
    "sg:city":"Laporte",
    "sg:classifiers":[
        {
            "category":"Building & Trades",
            "subcategory":"Plumbing",
            "type":"Services"
        }
    ],
    "sg:phone":"+1 219 362 0488",
    "sg:postcode":"46350",
    "sg:province":"IN",
    "sg:tags":[
        "plumbing",
        "contractor"
    ],
    "wof:name":"D S Plumbing Inc",
    "wof:placetype":"venue"
},
  "geometry": {"coordinates":[-86.67012800000001,41.640869],"type":"Point"}
}