{
  "type": "Feature",
  "properties": {
    "addr:full":"1020 N 18th St Lafayette IN 47904",
    "addr:housenumber":"1020",
    "addr:postcode":"47904",
    "addr:street":"N 18Th St",
    "iso:country":"US",
    "sg:address":"1020 N 18th St",
    "sg:city":"Lafayette",
    "sg:classifiers":[
        {
            "category":"Health Services",
            "subcategory":"Clinic",
            "type":"Services"
        }
    ],
    "sg:phone":"+1 765 423 6011",
    "sg:postcode":"47904",
    "sg:province":"IN",
    "sg:tags":[
        "dialysis"
    ],
    "wof:name":"Dialysis Center-Greter Lfytt",
    "wof:placetype":"venue"
},
  "geometry": {"coordinates":[-86.87751,40.427986],"type":"Point"}
}