{
  "type": "Feature",
  "properties": {
    "addr:full":"5182 W Pike Plaza Rd Indianapolis IN 46254",
    "addr:housenumber":"5182",
    "addr:postcode":"46254",
    "addr:street":"W Pike Plaza Rd",
    "iso:country":"US",
    "sg:address":"5182 W Pike Plaza Rd",
    "sg:city":"Indianapolis",
    "sg:classifiers":[
        {
            "category":"Government",
            "subcategory":"Office",
            "type":"Public Place"
        }
    ],
    "sg:phone":"+1 317 298 7207",
    "sg:postcode":"46254",
    "sg:province":"IN",
    "sg:tags":[
        "armed",
        "force",
        "recruiting"
    ],
    "wof:name":"US Marine Corps Recruiting",
    "wof:placetype":"venue"
},
  "geometry": {"coordinates":[-86.25225,39.830785],"type":"Point"}
}