{
  "type": "Feature",
  "properties": {
    "iso:country":"US",
    "sg:address":"115 E Water St",
    "sg:city":"Portland",
    "sg:classifiers":[
        {
            "category":"Organizations",
            "subcategory":"Professional Association",
            "type":"Services"
        }
    ],
    "sg:phone":"+1 260 726 6477",
    "sg:postcode":"47371",
    "sg:province":"IN",
    "wof:name":"Jay County Boys Community Ctr",
    "wof:placetype":"venue"
},
  "geometry": {"coordinates":[-84.976184,40.432295],"type":"Point"}
}