{
  "type": "Feature",
  "properties": {
    "iso:country":"US",
    "sg:address":"718 Hulman St",
    "sg:city":"Terre Haute",
    "sg:classifiers":[
        {
            "category":"Professional",
            "type":"Services"
        }
    ],
    "sg:phone":"+1 812 234 3845",
    "sg:postcode":"47802",
    "sg:province":"IN",
    "sg:tags":[
        "establishment"
    ],
    "wof:name":"Guppy Inc",
    "wof:placetype":"venue"
},
  "geometry": {"coordinates":[-87.40691700000001,39.448254],"type":"Point"}
}