{
  "type": "Feature",
  "properties": {
    "iso:country":"US",
    "sg:address":"6250 W Smith Valley Rd",
    "sg:city":"Greenwood",
    "sg:classifiers":[
        {
            "category":"Social Services",
            "type":"Services"
        }
    ],
    "sg:phone":"+1 317 881 6704",
    "sg:postcode":"46142",
    "sg:province":"IN",
    "sg:tags":[
        "youth",
        "organization",
        "center"
    ],
    "wof:name":"Center Grove Little League",
    "wof:placetype":"venue"
},
  "geometry": {"coordinates":[-86.215892,39.604924],"type":"Point"}
}