{
  "type": "Feature",
  "properties": {
    "iso:country":"US",
    "sg:address":"8013 W Washington St",
    "sg:city":"Indianapolis",
    "sg:classifiers":[
        {
            "category":"Bars & Pubs",
            "type":"Food & Drink"
        }
    ],
    "sg:phone":"+1 317 244 1989",
    "sg:postcode":"46231",
    "sg:province":"IN",
    "sg:website":"www.dancersshowclub.com",
    "wof:name":"Dancers Show Club",
    "wof:placetype":"venue"
},
  "geometry": {"coordinates":[-86.299798,39.737501],"type":"Point"}
}