{
  "type": "Feature",
  "properties": {
    "iso:country":"US",
    "sg:address":"3147 Northview Dr",
    "sg:city":"Elkhart",
    "sg:classifiers":[
        {
            "category":"Shopping",
            "subcategory":"Clothing, Apparel, & Fashions",
            "type":"Retail Goods"
        }
    ],
    "sg:phone":"+1 574 264 9994",
    "sg:postcode":"46514",
    "sg:province":"IN",
    "wof:name":"Fashion Bug",
    "wof:placetype":"venue"
},
  "geometry": {"coordinates":[-85.97731,41.73431],"type":"Point"}
}