{
  "type": "Feature",
  "properties": {
    "addr:full":"640 N Sherman Dr Indianapolis IN 46201",
    "addr:housenumber":"640",
    "addr:postcode":"46201",
    "addr:street":"N Sherman Dr",
    "iso:country":"US",
    "sg:address":"640 N Sherman Dr",
    "sg:city":"Indianapolis",
    "sg:classifiers":[
        {
            "category":"Manufacturing",
            "subcategory":"Tools & Machinery",
            "type":"Manufacturing & Wholesale Goods"
        }
    ],
    "sg:phone":"+1 317 916 4274",
    "sg:postcode":"46201",
    "sg:province":"IN",
    "sg:tags":[
        "control",
        "repair",
        "electric",
        "mfg",
        "pump",
        "electrical",
        "motor"
    ],
    "wof:name":"Horner Electric Inc",
    "wof:placetype":"venue"
},
  "geometry": {"coordinates":[-86.102345,39.776046],"type":"Point"}
}