{
  "type": "Feature",
  "properties": {
    "addr:full":"457 N Summit St Nappanee IN 46550",
    "addr:housenumber":"457",
    "addr:postcode":"46550",
    "addr:street":"N Summit St",
    "iso:country":"US",
    "sg:address":"457 N Summit St",
    "sg:city":"Nappanee",
    "sg:classifiers":[
        {
            "category":"Restaurant",
            "type":"Food & Drink"
        }
    ],
    "sg:phone":"+1 574 773 7104",
    "sg:postcode":"46550",
    "sg:province":"IN",
    "wof:name":"Mc Donald's",
    "wof:placetype":"venue"
},
  "geometry": {"coordinates":[-85.99526,41.445931],"type":"Point"}
}