{
  "type": "Feature",
  "properties": {
    "iso:country":"US",
    "sg:address":"10680 Rosewood Rd SE",
    "sg:city":"Elizabeth",
    "sg:classifiers":[
        {
            "category":"Freight",
            "type":"Transportation"
        }
    ],
    "sg:phone":"+1 812 969 3770",
    "sg:postcode":"47117",
    "sg:province":"IN",
    "sg:tags":[
        "operator",
        "local",
        "trucking"
    ],
    "wof:name":"HLS Trucking",
    "wof:placetype":"venue"
},
  "geometry": {"coordinates":[-85.948553,38.049806],"type":"Point"}
}