{
  "type": "Feature",
  "properties": {
    "iso:country":"US",
    "sg:address":"2006 Allison Ln",
    "sg:city":"Jeffersonville",
    "sg:classifiers":[
        {
            "category":"Government",
            "subcategory":"Fire Station",
            "type":"Public Place"
        }
    ],
    "sg:phone":"+1 812 283 5541",
    "sg:postcode":"47130",
    "sg:province":"IN",
    "sg:tags":[
        "protection"
    ],
    "wof:name":"McCullough Fire Dept",
    "wof:placetype":"venue"
},
  "geometry": {"coordinates":[-85.70507600000001,38.314202],"type":"Point"}
}