{
  "type": "Feature",
  "properties": {
    "iso:country":"US",
    "sg:address":"10304 E Co Rd 1600 N",
    "sg:city":"Santa Claus",
    "sg:classifiers":[
        {
            "category":"Personal",
            "type":"Services"
        }
    ],
    "sg:phone":"+1 812 544 2475",
    "sg:postcode":"47579",
    "sg:province":"IN",
    "sg:tags":[
        "therapist",
        "massage"
    ],
    "wof:name":"Cindy's Massage Ctr",
    "wof:placetype":"venue"
},
  "geometry": {"coordinates":[-86.88984000000001,38.118203],"type":"Point"}
}