{
  "type": "Feature",
  "properties": {
    "iso:country":"US",
    "sg:address":"6326 Covington Rd",
    "sg:city":"Fort Wayne",
    "sg:classifiers":[
        {
            "category":"Retail",
            "subcategory":"Laundry & Dry Cleaning",
            "type":"Services"
        }
    ],
    "sg:phone":"+1 260 432 7358",
    "sg:postcode":"46804",
    "sg:province":"IN",
    "sg:tags":[
        "cleaners"
    ],
    "wof:name":"Allen County Dry Cleaners",
    "wof:placetype":"venue"
},
  "geometry": {"coordinates":[-85.220586,41.059804],"type":"Point"}
}