{
  "type": "Feature",
  "properties": {
    "addr:full":"1545 W US Hwy 30 Schererville IN 46375",
    "addr:housenumber":"1545",
    "addr:postcode":"46375",
    "addr:street":"W Us Hwy 30",
    "iso:country":"US",
    "sg:address":"1545 W US Hwy 30",
    "sg:city":"Schererville",
    "sg:classifiers":[
        {
            "category":"Restaurant",
            "type":"Food & Drink"
        }
    ],
    "sg:phone":"+1 219 322 3439",
    "sg:postcode":"46375",
    "sg:province":"IN",
    "wof:name":"Paragon Family Restaurant",
    "wof:placetype":"venue"
},
  "geometry": {"coordinates":[-87.48479399999999,41.490952],"type":"Point"}
}