{
  "type": "Feature",
  "properties": {
    "iso:country":"US",
    "sg:address":"17 N Pennsylvania St",
    "sg:city":"Indianapolis",
    "sg:classifiers":[
        {
            "category":"Restaurant",
            "type":"Food & Drink"
        }
    ],
    "sg:phone":"+1 317 635 6112",
    "sg:postcode":"46204",
    "sg:province":"IN",
    "sg:website":"www.jimmyjohns.com",
    "wof:name":"Jimmy John's Gourmet Sandwich",
    "wof:placetype":"venue"
},
  "geometry": {"coordinates":[-86.156194,39.767318],"type":"Point"}
}