{
  "type": "Feature",
  "properties": {
    "addr:full":"1711 Country Club Rd Mt Vernon IN 47620",
    "addr:housenumber":"1711",
    "addr:postcode":"47620",
    "addr:street":"Country Club Rd",
    "iso:country":"US",
    "sg:address":"1711 Country Club Rd",
    "sg:city":"Mt Vernon",
    "sg:classifiers":[
        {
            "category":"Recreation",
            "type":"Entertainment"
        }
    ],
    "sg:phone":"+1 812 838 3148",
    "sg:postcode":"47620",
    "sg:province":"IN",
    "sg:tags":[
        "course",
        "golf"
    ],
    "wof:name":"Western Hills Country Club",
    "wof:placetype":"venue"
},
  "geometry": {"coordinates":[-87.919984,37.929],"type":"Point"}
}