{
  "type": "Feature",
  "properties": {
    "addr:full":"2336 Washington Ave Evansville IN 47714",
    "addr:housenumber":"2336",
    "addr:postcode":"47714",
    "addr:street":"Washington Ave",
    "iso:country":"US",
    "sg:address":"2336 Washington Ave",
    "sg:city":"Evansville",
    "sg:classifiers":[
        {
            "category":"Professional",
            "subcategory":"Accounting & Tax Preparation",
            "type":"Services"
        }
    ],
    "sg:phone":"+1 812 474 2324",
    "sg:postcode":"47714",
    "sg:province":"IN",
    "sg:tags":[
        "accountant"
    ],
    "wof:name":"Rick Goelz CPA",
    "wof:placetype":"venue"
},
  "geometry": {"coordinates":[-87.51756899999999,37.96261],"type":"Point"}
}