{
  "type": "Feature",
  "properties": {
    "addr:full":"5510 S 150 W Lafayette IN 47909",
    "addr:housenumber":"5510;150",
    "addr:postcode":"47909",
    "addr:street":"S;W Lafayette",
    "iso:country":"US",
    "sg:address":"5510 S 150 W",
    "sg:city":"Lafayette",
    "sg:classifiers":[
        {
            "category":"Building & Trades",
            "subcategory":"Construction",
            "type":"Services"
        }
    ],
    "sg:phone":"+1 765 538 2770",
    "sg:postcode":"47909",
    "sg:province":"IN",
    "sg:tags":[
        "contractor"
    ],
    "wof:name":"J & S Well Drilling",
    "wof:placetype":"venue"
},
  "geometry": {"coordinates":[-86.932862,40.326809],"type":"Point"}
}