{
  "type": "Feature",
  "properties": {
    "iso:country":"US",
    "sg:address":"107 N Court St",
    "sg:city":"Sullivan",
    "sg:classifiers":[
        {
            "category":"Organizations",
            "subcategory":"Religious Organization",
            "type":"Services"
        }
    ],
    "sg:phone":"+1 812 268 4498",
    "sg:postcode":"47882",
    "sg:province":"IN",
    "sg:tags":[
        "church"
    ],
    "wof:name":"First United Methodist Church",
    "wof:placetype":"venue"
},
  "geometry": {"coordinates":[-87.408267,39.096783],"type":"Point"}
}