{
  "type": "Feature",
  "properties": {
    "iso:country":"US",
    "sg:address":"8075 S US Hwy 421",
    "sg:city":"San Pierre",
    "sg:classifiers":[
        {
            "category":"Freight",
            "type":"Transportation"
        }
    ],
    "sg:phone":"+1 219 828 4761",
    "sg:postcode":"46374",
    "sg:province":"IN",
    "sg:tags":[
        "commercial",
        "storage"
    ],
    "wof:name":"Gibson's Storage",
    "wof:placetype":"venue"
},
  "geometry": {"coordinates":[-86.891171,41.185493],"type":"Point"}
}