{
  "type": "Feature",
  "properties": {
    "addr:full":"1915 E 86th St Indianapolis IN 46240",
    "addr:housenumber":"1915",
    "addr:postcode":"46240",
    "addr:street":"E 86Th St",
    "iso:country":"US",
    "sg:address":"1915 E 86th St",
    "sg:city":"Indianapolis",
    "sg:classifiers":[
        {
            "category":"Education",
            "subcategory":"School",
            "type":"Public Place"
        }
    ],
    "sg:phone":"+1 317 259 5458",
    "sg:postcode":"46240",
    "sg:province":"IN",
    "sg:tags":[
        "high",
        "middle",
        "elementary"
    ],
    "wof:name":"Hilltop Learning Center Adult Education",
    "wof:placetype":"venue"
},
  "geometry": {"coordinates":[-86.127098,39.912498],"type":"Point"}
}