{
  "type": "Feature",
  "properties": {
    "iso:country":"US",
    "sg:address":"120 W Market St",
    "sg:city":"Warsaw",
    "sg:classifiers":[
        {
            "category":"Insurance",
            "subcategory":"Insurance Agent",
            "type":"Services"
        }
    ],
    "sg:phone":"+1 574 267 3587",
    "sg:postcode":"46580",
    "sg:province":"IN",
    "wof:name":"Allstate Insurance",
    "wof:placetype":"venue"
},
  "geometry": {"coordinates":[-85.857765,41.237176],"type":"Point"}
}