{
  "type": "Feature",
  "properties": {
    "iso:country":"US",
    "sg:address":"419 S 8th St",
    "sg:city":"Goshen",
    "sg:classifiers":[
        {
            "category":"Education",
            "subcategory":"School",
            "type":"Public Place"
        }
    ],
    "sg:phone":"+1 574 533 5085",
    "sg:postcode":"46526",
    "sg:province":"IN",
    "wof:name":"Chandler Elementary",
    "wof:placetype":"venue"
},
  "geometry": {"coordinates":[-85.828168,41.581885],"type":"Point"}
}