{
  "type": "Feature",
  "properties": {
    "iso:country":"US",
    "sg:address":"32 Waterfall Rd",
    "sg:city":"Richmond",
    "sg:classifiers":[
        {
            "category":"Wholesale",
            "subcategory":"Computers",
            "type":"Manufacturing & Wholesale Goods"
        }
    ],
    "sg:phone":"+1 765 939 6862",
    "sg:postcode":"47374",
    "sg:province":"IN",
    "sg:tags":[
        "datum"
    ],
    "wof:name":"World Central Computers",
    "wof:placetype":"venue"
},
  "geometry": {"coordinates":[-84.892914,39.848481],"type":"Point"}
}