{
  "type": "Feature",
  "properties": {
    "addr:full":"11540 Fishers Dr Fishers IN 46038",
    "addr:housenumber":"11540",
    "addr:postcode":"46038",
    "addr:street":"Fishers Dr",
    "iso:country":"US",
    "sg:address":"11540 Fishers Dr",
    "sg:city":"Fishers",
    "sg:classifiers":[
        {
            "category":"Social Services",
            "subcategory":"Child Care",
            "type":"Services"
        }
    ],
    "sg:phone":"+1 317 841 9771",
    "sg:postcode":"46038",
    "sg:province":"IN",
    "sg:tags":[
        "elementary",
        "school"
    ],
    "sg:website":"www.lapetite.com",
    "wof:name":"La Petite Academy",
    "wof:placetype":"venue"
},
  "geometry": {"coordinates":[-86.038152,39.95579],"type":"Point"}
}