{
  "type": "Feature",
  "properties": {
    "iso:country":"US",
    "sg:address":"7432 W 140th Ave",
    "sg:city":"Cedar Lake",
    "sg:classifiers":[
        {
            "category":"Building & Trades",
            "subcategory":"Plumbing",
            "type":"Services"
        }
    ],
    "sg:phone":"+1 219 374 9087",
    "sg:postcode":"46303",
    "sg:province":"IN",
    "sg:tags":[
        "contractor"
    ],
    "wof:name":"Murray Plumbing Inc",
    "wof:placetype":"venue"
},
  "geometry": {"coordinates":[-87.42598,41.364136],"type":"Point"}
}