{
  "type": "Feature",
  "properties": {
    "iso:country":"US",
    "sg:address":"3521 W Alto Rd",
    "sg:city":"Kokomo",
    "sg:classifiers":[
        {
            "category":"Organizations",
            "subcategory":"Religious Organization",
            "type":"Services"
        }
    ],
    "sg:phone":"+1 765 453 7966",
    "sg:postcode":"46902",
    "sg:province":"IN",
    "sg:tags":[
        "church"
    ],
    "wof:name":"Centro De Adoracion-Getsemani",
    "wof:placetype":"venue"
},
  "geometry": {"coordinates":[-86.19395,40.439535],"type":"Point"}
}