{
  "type": "Feature",
  "properties": {
    "addr:full":"1430 N Baldwin Ave Marion IN 46952",
    "addr:housenumber":"1430",
    "addr:postcode":"46952",
    "addr:street":"N Baldwin Ave",
    "iso:country":"US",
    "sg:address":"1430 N Baldwin Ave",
    "sg:city":"Marion",
    "sg:classifiers":[
        {
            "category":"Retail",
            "subcategory":"Auto Repair",
            "type":"Services"
        }
    ],
    "sg:phone":"+1 765 668 3258",
    "sg:postcode":"46952",
    "sg:province":"IN",
    "sg:tags":[
        "body",
        "automobile",
        "painting"
    ],
    "wof:name":"Southworth Collision Ctr",
    "wof:placetype":"venue"
},
  "geometry": {"coordinates":[-85.66804399999999,40.579442],"type":"Point"}
}