{
  "type": "Feature",
  "properties": {
    "addr:full":"2043 Southlake Mall Merrillville IN 46410",
    "addr:housenumber":"2043",
    "addr:postcode":"46410",
    "addr:street":"Southlake Mall",
    "iso:country":"US",
    "sg:address":"2043 Southlake Mall",
    "sg:city":"Merrillville",
    "sg:classifiers":[
        {
            "category":"Bakery",
            "type":"Food & Drink"
        }
    ],
    "sg:menulink":"http://www.allmenus.com/in/ross/239329-wetzels-pretzels/menu/",
    "sg:phone":"+1 219 736 9882",
    "sg:postcode":"46410",
    "sg:province":"IN",
    "sg:tags":[
        "american",
        "pastry"
    ],
    "wof:name":"Wetzel's Pretzels",
    "wof:placetype":"venue"
},
  "geometry": {"coordinates":[-87.306867,41.470284],"type":"Point"}
}