{
  "type": "Feature",
  "properties": {
    "addr:full":"4405 W Washington Center Rd Fort Wayne IN 46818",
    "addr:housenumber":"4405",
    "addr:postcode":"46818",
    "addr:street":"W Washington Center Rd",
    "iso:country":"US",
    "sg:address":"4405 W Washington Center Rd",
    "sg:city":"Fort Wayne",
    "sg:classifiers":[
        {
            "category":"Bus Charters",
            "type":"Transportation"
        }
    ],
    "sg:phone":"+1 260 489 1059",
    "sg:postcode":"46818",
    "sg:province":"IN",
    "sg:tags":[
        "rental"
    ],
    "wof:name":"Landmark Charter Coach",
    "wof:placetype":"venue"
},
  "geometry": {"coordinates":[-85.200311,41.131929],"type":"Point"}
}