{
  "type": "Feature",
  "properties": {
    "iso:country":"US",
    "sg:address":"5515 Hanna St",
    "sg:city":"Fort Wayne",
    "sg:classifiers":[
        {
            "category":"Organizations",
            "subcategory":"Religious Organization",
            "type":"Services"
        }
    ],
    "sg:phone":"+1 260 744 9600",
    "sg:postcode":"46806",
    "sg:province":"IN",
    "wof:name":"Renaissance Baptist Church",
    "wof:placetype":"venue"
},
  "geometry": {"coordinates":[-85.127591,41.03349],"type":"Point"}
}