{
  "type": "Feature",
  "properties": {
    "iso:country":"US",
    "sg:address":"317 S Wayne St",
    "sg:city":"Angola",
    "sg:classifiers":[
        {
            "category":"Government",
            "subcategory":"Office",
            "type":"Public Place"
        }
    ],
    "sg:phone":"+1 260 665 3713",
    "sg:postcode":"46703",
    "sg:province":"IN",
    "sg:tags":[
        "county",
        "resource"
    ],
    "wof:name":"Steuben County Welfare Dept",
    "wof:placetype":"venue"
},
  "geometry": {"coordinates":[-84.999155,41.632932],"type":"Point"}
}