{
  "type": "Feature",
  "properties": {
    "addr:full":"110 Main St Aurora IN 47001",
    "addr:housenumber":"110",
    "addr:postcode":"47001",
    "addr:street":"Main St",
    "iso:country":"US",
    "sg:address":"110 Main St",
    "sg:city":"Aurora",
    "sg:classifiers":[
        {
            "category":"Government",
            "subcategory":"Office",
            "type":"Public Place"
        }
    ],
    "sg:phone":"+1 812 926 1777",
    "sg:postcode":"47001",
    "sg:province":"IN",
    "sg:tags":[
        "village"
    ],
    "wof:name":"Aurora Clerk",
    "wof:placetype":"venue"
},
  "geometry": {"coordinates":[-84.899534,39.057301],"type":"Point"}
}