{
  "type": "Feature",
  "properties": {
    "iso:country":"US",
    "sg:address":"615 Hillcrest Rd",
    "sg:city":"West Lafayette",
    "sg:classifiers":[
        {
            "category":"Health Services",
            "subcategory":"Clinic",
            "type":"Services"
        }
    ],
    "sg:phone":"+1 765 463 9520",
    "sg:postcode":"47906",
    "sg:province":"IN",
    "wof:name":"Animal Human Health Aternative",
    "wof:placetype":"venue"
},
  "geometry": {"coordinates":[-86.915237,40.440126],"type":"Point"}
}