{
  "type": "Feature",
  "properties": {
    "iso:country":"US",
    "sg:address":"10416 US Hwy 36",
    "sg:city":"Avon",
    "sg:classifiers":[
        {
            "category":"Restaurant",
            "type":"Food & Drink"
        }
    ],
    "sg:phone":"+1 317 209 9245",
    "sg:postcode":"46123",
    "sg:province":"IN",
    "wof:name":"O'Charley's",
    "wof:placetype":"venue"
},
  "geometry": {"coordinates":[-86.33932799999999,39.763861],"type":"Point"}
}