{
  "type": "Feature",
  "properties": {
    "iso:country":"US",
    "sg:address":"113 S 2nd St",
    "sg:city":"Boonville",
    "sg:classifiers":[
        {
            "category":"Retail",
            "subcategory":"Portrait Studio",
            "type":"Services"
        }
    ],
    "sg:phone":"+1 812 897 1986",
    "sg:postcode":"47601",
    "sg:province":"IN",
    "sg:tags":[
        "photographer"
    ],
    "wof:name":"Memories At Home",
    "wof:placetype":"venue"
},
  "geometry": {"coordinates":[-87.275626,38.049914],"type":"Point"}
}