{
  "type": "Feature",
  "properties": {
    "iso:country":"US",
    "sg:address":"11017 Sedlak Ln",
    "sg:city":"Indianapolis",
    "sg:classifiers":[
        {
            "category":"Wholesale",
            "subcategory":"Vending Machines",
            "type":"Manufacturing & Wholesale Goods"
        }
    ],
    "sg:phone":"+1 317 891 1976",
    "sg:postcode":"46229",
    "sg:province":"IN",
    "sg:tags":[
        "operator"
    ],
    "wof:name":"Master Vending Produ",
    "wof:placetype":"venue"
},
  "geometry": {"coordinates":[-85.970436,39.788431],"type":"Point"}
}