{
  "type": "Feature",
  "properties": {
    "addr:full":"2001 E Greyhound Pass Carmel IN 46033",
    "addr:housenumber":"2001",
    "addr:postcode":"46033",
    "addr:street":"E Greyhound Pass",
    "iso:country":"US",
    "sg:address":"2001 E Greyhound Pass",
    "sg:city":"Carmel",
    "sg:classifiers":[
        {
            "category":"Restaurant",
            "type":"Food & Drink"
        }
    ],
    "sg:menulink":"http://www.allmenus.com/in/westfield/120023-subway/menu/",
    "sg:phone":"+1 317 575 9547",
    "sg:postcode":"46033",
    "sg:province":"IN",
    "sg:tags":[
        "american",
        "sandwich"
    ],
    "wof:name":"Subway",
    "wof:placetype":"venue"
},
  "geometry": {"coordinates":[-86.122625,40.002442],"type":"Point"}
}