{
  "type": "Feature",
  "properties": {
    "iso:country":"US",
    "sg:address":"652 Van Ave",
    "sg:city":"Shelbyville",
    "sg:classifiers":[
        {
            "category":"Manufacturing",
            "subcategory":"Electronics",
            "type":"Manufacturing & Wholesale Goods"
        }
    ],
    "sg:phone":"+1 317 512 1026",
    "sg:postcode":"46176",
    "sg:province":"IN",
    "sg:tags":[
        "electronic",
        "component",
        "mfg"
    ],
    "wof:name":"Circuits Repair LLC",
    "wof:placetype":"venue"
},
  "geometry": {"coordinates":[-85.767305,39.518152],"type":"Point"}
}