{
  "type": "Feature",
  "properties": {
    "iso:country":"US",
    "sg:address":"3748 Lafayette Rd",
    "sg:city":"Indianapolis",
    "sg:classifiers":[
        {
            "category":"Restaurant",
            "type":"Food & Drink"
        }
    ],
    "sg:phone":"+1 317 924 1455",
    "sg:postcode":"46222",
    "sg:province":"IN",
    "wof:name":"Jean's Kitchen",
    "wof:placetype":"venue"
},
  "geometry": {"coordinates":[-86.227966,39.816833],"type":"Point"}
}