{
  "type": "Feature",
  "properties": {
    "iso:country":"US",
    "sg:address":"630 3rd Ave",
    "sg:city":"Jasper",
    "sg:classifiers":[
        {
            "category":"Manufacturing",
            "subcategory":"Tools & Machinery",
            "type":"Manufacturing & Wholesale Goods"
        }
    ],
    "sg:phone":"+1 812 482 3644",
    "sg:postcode":"47546",
    "sg:province":"IN",
    "sg:tags":[
        "industry",
        "special"
    ],
    "sg:website":"www.duboisequipment.com",
    "wof:name":"Dubois Machine Co Inc",
    "wof:placetype":"venue"
},
  "geometry": {"coordinates":[-86.919082,38.3802],"type":"Point"}
}