{
  "type": "Feature",
  "properties": {
    "iso:country":"US",
    "sg:address":"1010 W National Ave",
    "sg:city":"West Terre Haute",
    "sg:classifiers":[
        {
            "category":"Banks & Credit Unions",
            "subcategory":"Bank",
            "type":"Services"
        }
    ],
    "sg:phone":"+1 812 462 7360",
    "sg:postcode":"47885",
    "sg:province":"IN",
    "wof:name":"Old National Bank",
    "wof:placetype":"venue"
},
  "geometry": {"coordinates":[-87.457696,39.462828],"type":"Point"}
}