{
  "type": "Feature",
  "properties": {
    "iso:country":"US",
    "sg:address":"8650 Woodbluff Ct",
    "sg:city":"Indianapolis",
    "sg:classifiers":[
        {
            "category":"Professional",
            "subcategory":"Business Services",
            "type":"Services"
        }
    ],
    "sg:phone":"+1 317 328 2628",
    "sg:postcode":"46234",
    "sg:province":"IN",
    "wof:name":"Personal Tuch Dsigns Interiors",
    "wof:placetype":"venue"
},
  "geometry": {"coordinates":[-86.31550799999999,39.797422],"type":"Point"}
}