{
  "type": "Feature",
  "properties": {
    "iso:country":"US",
    "sg:address":"601 N College Ave",
    "sg:city":"Bloomington",
    "sg:classifiers":[
        {
            "category":"Coffee & Tea",
            "type":"Food & Drink"
        }
    ],
    "sg:menulink":"http://www.allmenus.com/in/bloomington/248269-mixed-greens/menu/",
    "sg:phone":"+1 812 323 8500",
    "sg:postcode":"47404",
    "sg:province":"IN",
    "sg:tags":[
        "smoothy",
        "sandwich",
        "salad",
        "juice",
        "soup",
        "american",
        "wrap"
    ],
    "wof:name":"Mixed Greens",
    "wof:placetype":"venue"
},
  "geometry": {"coordinates":[-86.534831,39.171691],"type":"Point"}
}