{
  "type": "Feature",
  "properties": {
    "iso:country":"US",
    "sg:address":"146 S 23rd St",
    "sg:city":"Terre Haute",
    "sg:classifiers":[
        {
            "category":"Wholesale",
            "subcategory":"Non-durable Goods",
            "type":"Manufacturing & Wholesale Goods"
        }
    ],
    "sg:phone":"+1 812 232 5954",
    "sg:postcode":"47803",
    "sg:province":"IN",
    "wof:name":"Bob Corey Advertising",
    "wof:placetype":"venue"
},
  "geometry": {"coordinates":[-87.38118900000001,39.468191],"type":"Point"}
}