{
  "type": "Feature",
  "properties": {
    "iso:country":"US",
    "sg:address":"60663 Orange Rd",
    "sg:city":"South Bend",
    "sg:classifiers":[
        {
            "category":"Freight",
            "type":"Transportation"
        }
    ],
    "sg:phone":"+1 574 287 3133",
    "sg:postcode":"46614",
    "sg:province":"IN",
    "sg:tags":[
        "trucking"
    ],
    "wof:name":"Indian Trucking Co",
    "wof:placetype":"venue"
},
  "geometry": {"coordinates":[-86.340755,41.616427],"type":"Point"}
}