{
  "type": "Feature",
  "properties": {
    "iso:country":"US",
    "sg:address":"3551 E Main St",
    "sg:city":"Richmond",
    "sg:classifiers":[
        {
            "category":"Food & Beverages",
            "subcategory":"Specialty",
            "type":"Retail Goods"
        }
    ],
    "sg:phone":"+1 765 965 7010",
    "sg:postcode":"47374",
    "sg:province":"IN",
    "sg:tags":[
        "control",
        "preparation",
        "weight"
    ],
    "wof:name":"LA Weight Loss Ctr Inc",
    "wof:placetype":"venue"
},
  "geometry": {"coordinates":[-84.853166,39.830894],"type":"Point"}
}