{
  "type": "Feature",
  "properties": {
    "iso:country":"US",
    "sg:address":"8369 Castleton Corner Dr",
    "sg:city":"Indianapolis",
    "sg:classifiers":[
        {
            "category":"Home & Garden",
            "subcategory":"Carpets & Floor Coverings",
            "type":"Retail Goods"
        }
    ],
    "sg:phone":"+1 317 849 8037",
    "sg:postcode":"46250",
    "sg:province":"IN",
    "sg:tags":[
        "mattress"
    ],
    "wof:name":"Mattress Firm Inc",
    "wof:placetype":"venue"
},
  "geometry": {"coordinates":[-86.071297,39.908501],"type":"Point"}
}