{
  "type": "Feature",
  "properties": {
    "iso:country":"US",
    "sg:address":"2714 John St",
    "sg:city":"Fort Wayne",
    "sg:classifiers":[
        {
            "category":"Personal",
            "subcategory":"Beauty Salon",
            "type":"Services"
        }
    ],
    "sg:phone":"+1 260 456 4121",
    "sg:postcode":"46806",
    "sg:province":"IN",
    "sg:tags":[
        "cosmetologist"
    ],
    "wof:name":"Ethel Lee Brewer",
    "wof:placetype":"venue"
},
  "geometry": {"coordinates":[-85.125529,41.059173],"type":"Point"}
}