{
  "type": "Feature",
  "properties": {
    "iso:country":"US",
    "sg:address":"4502 W 900 S",
    "sg:city":"Union Mills",
    "sg:classifiers":[
        {
            "category":"Building & Trades",
            "subcategory":"Landscaping Services",
            "type":"Services"
        }
    ],
    "sg:phone":"+1 219 575 1734",
    "sg:postcode":"46382",
    "sg:province":"IN",
    "sg:tags":[
        "landscape",
        "contractor"
    ],
    "wof:name":"Professional Lawncare",
    "wof:placetype":"venue"
},
  "geometry": {"coordinates":[-86.791123,41.476639],"type":"Point"}
}