{
  "type": "Feature",
  "properties": {
    "iso:country":"US",
    "sg:address":"1100 W 116th St",
    "sg:city":"Carmel",
    "sg:classifiers":[
        {
            "category":"Professional",
            "type":"Services"
        }
    ],
    "sg:phone":"+1 317 819 0320",
    "sg:postcode":"46032",
    "sg:province":"IN",
    "sg:tags":[
        "establishment"
    ],
    "wof:name":"Mc Namara",
    "wof:placetype":"venue"
},
  "geometry": {"coordinates":[-86.174703,39.955999],"type":"Point"}
}