{
  "type": "Feature",
  "properties": {
    "iso:country":"US",
    "sg:address":"1737 E 900 S",
    "sg:city":"Fairmount",
    "sg:classifiers":[
        {
            "category":"Autos & Motor Vehicles",
            "subcategory":"Automobile Sales",
            "type":"Retail Goods"
        }
    ],
    "sg:phone":"+1 765 948 5566",
    "sg:postcode":"46928",
    "sg:province":"IN",
    "sg:tags":[
        "car",
        "dealer"
    ],
    "wof:name":"J & S Motors",
    "wof:placetype":"venue"
},
  "geometry": {"coordinates":[-85.641105,40.423005],"type":"Point"}
}