{
  "type": "Feature",
  "properties": {
    "iso:country":"US",
    "sg:address":"7303 Winchester Rd",
    "sg:city":"Fort Wayne",
    "sg:classifiers":[
        {
            "category":"Restaurant",
            "type":"Food & Drink"
        }
    ],
    "sg:menulink":"http://www.allmenus.com/in/indian-village/233363-penguin-point/menu/",
    "sg:phone":"+1 260 747 2586",
    "sg:postcode":"46819",
    "sg:province":"IN",
    "sg:tags":[
        "burger",
        "american"
    ],
    "wof:name":"Penguin Point",
    "wof:placetype":"venue"
},
  "geometry": {"coordinates":[-85.14571100000001,41.018469],"type":"Point"}
}