{
  "type": "Feature",
  "properties": {
    "addr:full":"1811 E 38th Pl Hobart IN 46342",
    "addr:housenumber":"1811",
    "addr:postcode":"46342",
    "addr:street":"E 38Th Pl",
    "iso:country":"US",
    "sg:address":"1811 E 38th Pl",
    "sg:city":"Hobart",
    "sg:classifiers":[
        {
            "category":"Professional",
            "subcategory":"Computer Services",
            "type":"Services"
        }
    ],
    "sg:phone":"+1 219 947 2749",
    "sg:postcode":"46342",
    "sg:province":"IN",
    "sg:tags":[
        "datum"
    ],
    "wof:name":"Tom Kowalisyn",
    "wof:placetype":"venue"
},
  "geometry": {"coordinates":[-87.238833,41.548267],"type":"Point"}
}