{
  "type": "Feature",
  "properties": {
    "iso:country":"US",
    "sg:address":"1217 W Lakeview Dr",
    "sg:city":"Peru",
    "sg:classifiers":[
        {
            "category":"Health Services",
            "subcategory":"Doctor",
            "type":"Services"
        }
    ],
    "sg:phone":"+1 765 472 7000",
    "sg:postcode":"46970",
    "sg:province":"IN",
    "sg:tags":[
        "medical"
    ],
    "wof:name":"Mark S Hartinger PC",
    "wof:placetype":"venue"
},
  "geometry": {"coordinates":[-86.09302,40.781438],"type":"Point"}
}