{
  "type": "Feature",
  "properties": {
    "iso:country":"US",
    "sg:address":"3415 N Clinton St",
    "sg:city":"Fort Wayne",
    "sg:classifiers":[
        {
            "category":"Autos & Motor Vehicles",
            "subcategory":"Automobile Sales",
            "type":"Retail Goods"
        }
    ],
    "sg:phone":"+1 260 482 2513",
    "sg:postcode":"46805",
    "sg:province":"IN",
    "sg:tags":[
        "car",
        "dealer"
    ],
    "wof:name":"Garcia Auto Sales",
    "wof:placetype":"venue"
},
  "geometry": {"coordinates":[-85.137313,41.108453],"type":"Point"}
}