{
  "type": "Feature",
  "properties": {
    "iso:country":"US",
    "sg:address":"1721 W Lincoln Rd",
    "sg:city":"Kokomo",
    "sg:classifiers":[
        {
            "category":"Personal",
            "subcategory":"Beauty Salon",
            "type":"Services"
        }
    ],
    "sg:phone":"+1 765 453 2613",
    "sg:postcode":"46902",
    "sg:province":"IN",
    "wof:name":"Innovations Salon",
    "wof:placetype":"venue"
},
  "geometry": {"coordinates":[-86.152526,40.45466],"type":"Point"}
}