{
  "type": "Feature",
  "properties": {
    "iso:country":"US",
    "sg:address":"1811 Fairhill Rd",
    "sg:city":"Fort Wayne",
    "sg:classifiers":[
        {
            "category":"Organizations",
            "subcategory":"Religious Organization",
            "type":"Services"
        }
    ],
    "sg:phone":"+1 260 426 4712",
    "sg:postcode":"46808",
    "sg:province":"IN",
    "sg:tags":[
        "church"
    ],
    "wof:name":"Grace Presbyterian Church",
    "wof:placetype":"venue"
},
  "geometry": {"coordinates":[-85.162999,41.092376],"type":"Point"}
}