{
  "type": "Feature",
  "properties": {
    "iso:country":"US",
    "sg:address":"2456 E State Hwy 2",
    "sg:city":"Rolling Prairie",
    "sg:classifiers":[
        {
            "category":"Organizations",
            "subcategory":"Religious Organization",
            "type":"Services"
        }
    ],
    "sg:phone":"+1 219 324 8401",
    "sg:postcode":"46371",
    "sg:province":"IN",
    "sg:tags":[
        "church"
    ],
    "wof:name":"First Free Will Baptist Church",
    "wof:placetype":"venue"
},
  "geometry": {"coordinates":[-86.665138,41.63606],"type":"Point"}
}