{
  "type": "Feature",
  "properties": {
    "iso:country":"US",
    "sg:address":"200 N Walnut St",
    "sg:city":"Batesville",
    "sg:classifiers":[
        {
            "category":"Retail",
            "subcategory":"Repair Shop",
            "type":"Services"
        }
    ],
    "sg:phone":"+1 812 934 6161",
    "sg:postcode":"47006",
    "sg:province":"IN",
    "sg:tags":[
        "picture",
        "framing"
    ],
    "wof:name":"Concepts Frame Art & Gifts",
    "wof:placetype":"venue"
},
  "geometry": {"coordinates":[-85.22169100000001,39.301164],"type":"Point"}
}