{
  "type": "Feature",
  "properties": {
    "iso:country":"US",
    "sg:address":"301 S Walnut St",
    "sg:city":"Ridgeville",
    "sg:classifiers":[
        {
            "category":"Government",
            "subcategory":"Post Office",
            "type":"Public Place"
        }
    ],
    "sg:phone":"+1 765 857 2041",
    "sg:postcode":"47380",
    "sg:province":"IN",
    "wof:name":"US Post Office",
    "wof:placetype":"venue"
},
  "geometry": {"coordinates":[-85.029111,40.287245],"type":"Point"}
}