{
  "type": "Feature",
  "properties": {
    "iso:country":"US",
    "sg:address":"2450 Co Rd 32",
    "sg:city":"Waterloo",
    "sg:classifiers":[
        {
            "category":"Retail",
            "subcategory":"Repair Shop",
            "type":"Services"
        }
    ],
    "sg:phone":"+1 260 925 2086",
    "sg:postcode":"46793",
    "sg:province":"IN",
    "sg:tags":[
        "welding"
    ],
    "wof:name":"Lockwood Welding Inc",
    "wof:placetype":"venue"
},
  "geometry": {"coordinates":[-85.064768,41.410667],"type":"Point"}
}