{
  "type": "Feature",
  "properties": {
    "iso:country":"US",
    "sg:address":"3360 Irvington Dr",
    "sg:city":"Fort Wayne",
    "sg:classifiers":[
        {
            "category":"Professional",
            "subcategory":"Engineering",
            "type":"Services"
        }
    ],
    "sg:phone":"+1 260 483 6343",
    "sg:postcode":"46805",
    "sg:province":"IN",
    "wof:name":"R A Chambers",
    "wof:placetype":"venue"
},
  "geometry": {"coordinates":[-85.143342,41.105629],"type":"Point"}
}