{
  "type": "Feature",
  "properties": {
    "iso:country":"US",
    "sg:address":"16 E Washington St",
    "sg:city":"Greencastle",
    "sg:classifiers":[
        {
            "category":"Health Services",
            "subcategory":"Doctor",
            "type":"Services"
        }
    ],
    "sg:phone":"+1 765 653 9449",
    "sg:postcode":"46135",
    "sg:province":"IN",
    "sg:tags":[
        "physician",
        "surgeon"
    ],
    "wof:name":"Uptown Medical Family Practice",
    "wof:placetype":"venue"
},
  "geometry": {"coordinates":[-86.86441000000001,39.643927],"type":"Point"}
}