{
  "type": "Feature",
  "properties": {
    "addr:full":"1301 Prospect St Indianapolis IN 46203",
    "addr:housenumber":"1301",
    "addr:postcode":"46203",
    "addr:street":"Prospect St",
    "iso:country":"US",
    "sg:address":"1301 Prospect St",
    "sg:city":"Indianapolis",
    "sg:classifiers":[
        {
            "category":"Organizations",
            "subcategory":"Religious Organization",
            "type":"Services"
        }
    ],
    "sg:phone":"+1 317 632 2167",
    "sg:postcode":"46203",
    "sg:province":"IN",
    "sg:tags":[
        "church"
    ],
    "wof:name":"St Mark's Lutheran Church",
    "wof:placetype":"venue"
},
  "geometry": {"coordinates":[-86.135808,39.752365],"type":"Point"}
}