{
  "type": "Feature",
  "properties": {
    "addr:full":"3565 State Rd 62 Mt Vernon IN 47620",
    "addr:housenumber":"3565;62",
    "addr:postcode":"in 47620",
    "addr:street":"State Rd",
    "iso:country":"US",
    "sg:address":"3565 State Rd 62",
    "sg:city":"Mt Vernon",
    "sg:classifiers":[
        {
            "category":"Utilities",
            "subcategory":"Refuse",
            "type":"Services"
        }
    ],
    "sg:phone":"+1 812 833 0777",
    "sg:postcode":"47620",
    "sg:province":"IN",
    "sg:tags":[
        "equipment",
        "recycling",
        "system"
    ],
    "wof:name":"Plastic Reclaiming",
    "wof:placetype":"venue"
},
  "geometry": {"coordinates":[-87.98166399999999,37.929018],"type":"Point"}
}