{
  "type": "Feature",
  "properties": {
    "iso:country":"US",
    "sg:address":"710 W 5th St",
    "sg:city":"New Albany",
    "sg:classifiers":[
        {
            "category":"Building & Trades",
            "subcategory":"Construction",
            "type":"Services"
        }
    ],
    "sg:phone":"+1 812 949 8182",
    "sg:postcode":"47150",
    "sg:province":"IN",
    "sg:tags":[
        "house"
    ],
    "wof:name":"Robb Construction",
    "wof:placetype":"venue"
},
  "geometry": {"coordinates":[-85.833887,38.288239],"type":"Point"}
}