{
  "type": "Feature",
  "properties": {
    "addr:full":"325 Hovan Dr Fort Wayne IN 46825",
    "addr:housenumber":"325",
    "addr:postcode":"46825",
    "addr:street":"Hovan Dr",
    "iso:country":"US",
    "sg:address":"325 Hovan Dr",
    "sg:city":"Fort Wayne",
    "sg:classifiers":[
        {
            "category":"Home & Garden",
            "subcategory":"Furniture",
            "type":"Retail Goods"
        }
    ],
    "sg:phone":"+1 260 484 4534",
    "sg:postcode":"46825",
    "sg:province":"IN",
    "sg:website":"www.cherishedagain.com",
    "wof:name":"Fort Wayne Wood & Metal Spec",
    "wof:placetype":"venue"
},
  "geometry": {"coordinates":[-85.143632,41.12025],"type":"Point"}
}