{
  "type": "Feature",
  "properties": {
    "addr:full":"1001 Wayne St Bluffton IN 46714",
    "addr:housenumber":"1001",
    "addr:postcode":"46714",
    "addr:street":"Wayne St",
    "iso:country":"US",
    "sg:address":"1001 Wayne St",
    "sg:city":"Bluffton",
    "sg:classifiers":[
        {
            "category":"Professional",
            "subcategory":"Business Services",
            "type":"Services"
        }
    ],
    "sg:phone":"+1 260 824 4345",
    "sg:postcode":"46714",
    "sg:province":"IN",
    "sg:tags":[
        "industry",
        "machinery",
        "mfg"
    ],
    "wof:name":"Cales Soft Water Service",
    "wof:placetype":"venue"
},
  "geometry": {"coordinates":[-85.16492700000001,40.730412],"type":"Point"}
}