{
  "type": "Feature",
  "properties": {
    "addr:full":"2494 One Mile Rd Lawrenceburg IN 47025",
    "addr:housenumber":"2494",
    "addr:postcode":"47025",
    "addr:street":"One Mile Rd",
    "iso:country":"US",
    "sg:address":"2494 One Mile Rd",
    "sg:city":"Lawrenceburg",
    "sg:classifiers":[
        {
            "category":"Utilities",
            "type":"Services"
        }
    ],
    "sg:phone":"+1 812 637 0219",
    "sg:postcode":"47025",
    "sg:province":"IN",
    "sg:tags":[
        "combination"
    ],
    "wof:name":"Lmh Utilities Plant",
    "wof:placetype":"venue"
},
  "geometry": {"coordinates":[-84.865892,39.213342],"type":"Point"}
}