{
  "type": "Feature",
  "properties": {
    "iso:country":"US",
    "sg:address":"425 Joliet St",
    "sg:city":"Dyer",
    "sg:classifiers":[
        {
            "category":"Home & Garden",
            "subcategory":"Home Furnishings",
            "type":"Retail Goods"
        }
    ],
    "sg:phone":"+1 219 864 9688",
    "sg:postcode":"46311",
    "sg:province":"IN",
    "sg:tags":[
        "curtain",
        "made",
        "drapery"
    ],
    "wof:name":"Namco Draperies & Installation",
    "wof:placetype":"venue"
},
  "geometry": {"coordinates":[-87.51403500000001,41.493522],"type":"Point"}
}