{
  "type": "Feature",
  "properties": {
    "iso:country":"US",
    "sg:address":"705 Putnam St",
    "sg:city":"Terre Haute",
    "sg:classifiers":[
        {
            "category":"Organizations",
            "subcategory":"Professional Association",
            "type":"Services"
        }
    ],
    "sg:phone":"+1 812 232 2679",
    "sg:postcode":"47802",
    "sg:province":"IN",
    "wof:name":"American Cancer Society",
    "wof:placetype":"venue"
},
  "geometry": {"coordinates":[-87.406317,39.450271],"type":"Point"}
}