{
  "type": "Feature",
  "properties": {
    "iso:country":"US",
    "sg:address":"4824 Ossington Ct",
    "sg:city":"Indianapolis",
    "sg:classifiers":[
        {
            "category":"Building & Trades",
            "subcategory":"Cleaning & Sanitation",
            "type":"Services"
        }
    ],
    "sg:phone":"+1 317 280 9727",
    "sg:postcode":"46254",
    "sg:province":"IN",
    "sg:tags":[
        "window"
    ],
    "wof:name":"Fish Window Cleaning",
    "wof:placetype":"venue"
},
  "geometry": {"coordinates":[-86.278647,39.841021],"type":"Point"}
}