{
  "type": "Feature",
  "properties": {
    "addr:full":"3030 State Rd 62 Jeffersonville IN 47130",
    "addr:housenumber":"3030;62",
    "addr:postcode":"47130",
    "addr:street":"State Rd",
    "iso:country":"US",
    "sg:address":"3030 State Rd 62",
    "sg:city":"Jeffersonville",
    "sg:classifiers":[
        {
            "category":"Restaurant",
            "type":"Food & Drink"
        }
    ],
    "sg:phone":"+1 812 218 8400",
    "sg:postcode":"47130",
    "sg:province":"IN",
    "sg:tags":[
        "out"
    ],
    "wof:name":"Penn Station",
    "wof:placetype":"venue"
},
  "geometry": {"coordinates":[-85.712469,38.323942],"type":"Point"}
}