{
  "type": "Feature",
  "properties": {
    "iso:country":"US",
    "sg:address":"304 E 700 N",
    "sg:city":"Huntington",
    "sg:classifiers":[
        {
            "category":"Manufacturing",
            "subcategory":"Rubber & Plastics",
            "type":"Manufacturing & Wholesale Goods"
        }
    ],
    "sg:phone":"+1 260 356 7609",
    "sg:postcode":"46750",
    "sg:province":"IN",
    "sg:tags":[
        "product",
        "mfg"
    ],
    "wof:name":"Eiler Window & Door",
    "wof:placetype":"venue"
},
  "geometry": {"coordinates":[-85.445813,40.932113],"type":"Point"}
}