{
  "type": "Feature",
  "properties": {
    "iso:country":"US",
    "sg:address":"8095 W 400 S",
    "sg:city":"Fowler",
    "sg:phone":"+1 765 869 4063",
    "sg:postcode":"47944",
    "sg:province":"IN",
    "sg:tags":[
        "farm",
        "corn",
        "soybean"
    ],
    "wof:name":"Brian Geswein",
    "wof:placetype":"venue"
},
  "geometry": {"coordinates":[-87.471648,40.5494],"type":"Point"}
}