{
  "type": "Feature",
  "properties": {
    "iso:country":"US",
    "sg:address":"804 N Huntington St",
    "sg:city":"Syracuse",
    "sg:classifiers":[
        {
            "category":"Personal",
            "subcategory":"Beauty Salon",
            "type":"Services"
        }
    ],
    "sg:phone":"+1 574 457 4155",
    "sg:postcode":"46567",
    "sg:province":"IN",
    "wof:name":"Uptown Salon & Gift Shop LLC",
    "wof:placetype":"venue"
},
  "geometry": {"coordinates":[-85.753263,41.42846],"type":"Point"}
}