{
  "type": "Feature",
  "properties": {
    "iso:country":"US",
    "sg:address":"8504 N Troy Rd",
    "sg:city":"Greenfield",
    "sg:classifiers":[
        {
            "category":"Retail",
            "subcategory":"Animal Services",
            "type":"Services"
        }
    ],
    "sg:phone":"+1 317 326 2099",
    "sg:postcode":"46140",
    "sg:province":"IN",
    "sg:tags":[
        "pet",
        "grooming",
        "washing"
    ],
    "wof:name":"Anita's Pet Grooming & Supls",
    "wof:placetype":"venue"
},
  "geometry": {"coordinates":[-85.73919,39.911068],"type":"Point"}
}