{
  "type": "Feature",
  "properties": {
    "addr:full":"423 E Oak St Boonville IN 47601",
    "addr:housenumber":"423",
    "addr:postcode":"47601",
    "addr:street":"E Oak St",
    "iso:country":"US",
    "sg:address":"423 E Oak St",
    "sg:city":"Boonville",
    "sg:classifiers":[
        {
            "category":"Organizations",
            "subcategory":"Religious Organization",
            "type":"Services"
        }
    ],
    "sg:phone":"+1 812 897 4684",
    "sg:postcode":"47601",
    "sg:province":"IN",
    "wof:name":"Kingdom Hall Jhovahs Witnesses",
    "wof:placetype":"venue"
},
  "geometry": {"coordinates":[-87.270695,38.043026],"type":"Point"}
}