{
  "type": "Feature",
  "properties": {
    "addr:full":"231 E McKinley Ave Mishawaka IN 46545",
    "addr:housenumber":"231",
    "addr:postcode":"46545",
    "addr:street":"E Mckinley Ave",
    "iso:country":"US",
    "sg:address":"231 E McKinley Ave",
    "sg:city":"Mishawaka",
    "sg:classifiers":[
        {
            "category":"Restaurant",
            "type":"Food & Drink"
        }
    ],
    "sg:phone":"+1 574 257 2727",
    "sg:postcode":"46545",
    "sg:province":"IN",
    "wof:name":"Tailgate BBQ",
    "wof:placetype":"venue"
},
  "geometry": {"coordinates":[-86.178284,41.680363],"type":"Point"}
}