{
  "type": "Feature",
  "properties": {
    "iso:country":"US",
    "sg:address":"1221 E 100 S",
    "sg:city":"Winchester",
    "sg:classifiers":[
        {
            "category":"Real Estate",
            "subcategory":"Real Estate Agent",
            "type":"Services"
        }
    ],
    "sg:phone":"+1 765 584 1783",
    "sg:postcode":"47394",
    "sg:province":"IN",
    "wof:name":"Halderman Farm Management",
    "wof:placetype":"venue"
},
  "geometry": {"coordinates":[-84.953576,40.150172],"type":"Point"}
}