{
  "type": "Feature",
  "properties": {
    "iso:country":"US",
    "sg:address":"1695 W Lake St",
    "sg:city":"Warsaw",
    "sg:classifiers":[
        {
            "category":"Food & Beverages",
            "subcategory":"Groceries & Convenience Stores",
            "type":"Retail Goods"
        }
    ],
    "sg:phone":"+1 574 269 6121",
    "sg:postcode":"46580",
    "sg:province":"IN",
    "wof:name":"Wilby's Gas & Goodies",
    "wof:placetype":"venue"
},
  "geometry": {"coordinates":[-85.881751,41.248191],"type":"Point"}
}