{
  "type": "Feature",
  "properties": {
    "addr:full":"3454 US Hwy 6 Waterloo IN 46793",
    "addr:housenumber":"3454",
    "addr:postcode":"46793",
    "addr:street":"Us Hwy 6",
    "iso:country":"US",
    "sg:address":"3454 US Hwy 6",
    "sg:city":"Waterloo",
    "sg:classifiers":[
        {
            "category":"Travel",
            "subcategory":"Hotels & Motels",
            "type":"Entertainment"
        }
    ],
    "sg:phone":"+1 260 837 2414",
    "sg:postcode":"46793",
    "sg:province":"IN",
    "wof:name":"Lighthouse Inn",
    "wof:placetype":"venue"
},
  "geometry": {"coordinates":[-85.03185999999999,41.43533],"type":"Point"}
}