{
  "type": "Feature",
  "properties": {
    "iso:country":"US",
    "sg:address":"964 S Kentucky Ave",
    "sg:city":"Evansville",
    "sg:classifiers":[
        {
            "category":"Shopping",
            "subcategory":"Computers & Home Electronics",
            "type":"Retail Goods"
        }
    ],
    "sg:phone":"+1 812 464 2443",
    "sg:postcode":"47714",
    "sg:province":"IN",
    "sg:tags":[
        "equipment",
        "electronic",
        "supply"
    ],
    "wof:name":"Big E's Electronics",
    "wof:placetype":"venue"
},
  "geometry": {"coordinates":[-87.54769,37.963066],"type":"Point"}
}