{
  "type": "Feature",
  "properties": {
    "iso:country":"US",
    "sg:address":"501 S 7th St",
    "sg:city":"Richmond",
    "sg:classifiers":[
        {
            "category":"Social Services",
            "type":"Services"
        }
    ],
    "sg:phone":"+1 765 939 1808",
    "sg:postcode":"47374",
    "sg:province":"IN",
    "sg:tags":[
        "youth",
        "organization",
        "center"
    ],
    "wof:name":"Youth As Resources-Wayne",
    "wof:placetype":"venue"
},
  "geometry": {"coordinates":[-84.892881,39.821669],"type":"Point"}
}