{
  "type": "Feature",
  "properties": {
    "iso:country":"US",
    "sg:address":"6020 E Isgrigg Pl",
    "sg:city":"Pekin",
    "sg:classifiers":[
        {
            "category":"Building & Trades",
            "subcategory":"Construction",
            "type":"Services"
        }
    ],
    "sg:phone":"+1 812 967 3379",
    "sg:postcode":"47165",
    "sg:province":"IN",
    "sg:tags":[
        "house"
    ],
    "wof:name":"Isgrigg Cstm Bldg & Design LLC",
    "wof:placetype":"venue"
},
  "geometry": {"coordinates":[-85.993183,38.489947],"type":"Point"}
}