{
  "type": "Feature",
  "properties": {
    "iso:country":"US",
    "sg:address":"9001 State Rd 262",
    "sg:city":"Dillsboro",
    "sg:classifiers":[
        {
            "category":"Building & Trades",
            "subcategory":"Construction",
            "type":"Services"
        }
    ],
    "sg:phone":"+1 812 438 9255",
    "sg:postcode":"47018",
    "sg:province":"IN",
    "sg:tags":[
        "excavating",
        "contractor"
    ],
    "wof:name":"Roark & Son Excavating",
    "wof:placetype":"venue"
},
  "geometry": {"coordinates":[-85.038769,39.005178],"type":"Point"}
}