{
  "type": "Feature",
  "properties": {
    "iso:country":"US",
    "sg:address":"1320 S Jackson St",
    "sg:city":"Salem",
    "sg:classifiers":[
        {
            "category":"Insurance",
            "subcategory":"Insurance Agent",
            "type":"Services"
        }
    ],
    "sg:phone":"+1 812 883 6991",
    "sg:postcode":"47167",
    "sg:province":"IN",
    "wof:name":"State Farm Insurance",
    "wof:placetype":"venue"
},
  "geometry": {"coordinates":[-86.084031,38.597686],"type":"Point"}
}