{
  "type": "Feature",
  "properties": {
    "addr:full":"115 E 6th St Connersville IN 47331",
    "addr:housenumber":"115",
    "addr:postcode":"47331",
    "addr:street":"E 6Th St",
    "iso:country":"US",
    "sg:address":"115 E 6th St",
    "sg:city":"Connersville",
    "sg:classifiers":[
        {
            "category":"Professional",
            "subcategory":"Research",
            "type":"Services"
        }
    ],
    "sg:phone":"+1 765 827 1366",
    "sg:postcode":"47331",
    "sg:province":"IN",
    "sg:tags":[
        "economic",
        "analysis"
    ],
    "sg:website":"www.edgconnersville.com",
    "wof:name":"Economic Development Group",
    "wof:placetype":"venue"
},
  "geometry": {"coordinates":[-85.13851099999999,39.642185],"type":"Point"}
}