{
  "type": "Feature",
  "properties": {
    "iso:country":"US",
    "sg:address":"912 N Delaware St",
    "sg:city":"Indianapolis",
    "sg:classifiers":[
        {
            "category":"Wholesale",
            "subcategory":"Electrical",
            "type":"Manufacturing & Wholesale Goods"
        }
    ],
    "sg:phone":"+1 317 636 6540",
    "sg:postcode":"46202",
    "sg:province":"IN",
    "sg:tags":[
        "alarm",
        "burglar",
        "system"
    ],
    "wof:name":"American Alarm Honeywell",
    "wof:placetype":"venue"
},
  "geometry": {"coordinates":[-86.154065,39.779495],"type":"Point"}
}