{
  "type": "Feature",
  "properties": {
    "iso:country":"US",
    "sg:address":"500 E Washington St",
    "sg:city":"Muncie",
    "sg:classifiers":[
        {
            "category":"Insurance",
            "subcategory":"Insurance Agent",
            "type":"Services"
        }
    ],
    "sg:phone":"+1 765 284 5664",
    "sg:postcode":"47305",
    "sg:province":"IN",
    "wof:name":"Dan Hutcheson & Co",
    "wof:placetype":"venue"
},
  "geometry": {"coordinates":[-85.380602,40.194457],"type":"Point"}
}