{
  "type": "Feature",
  "properties": {
    "iso:country":"US",
    "sg:address":"526 E Edwards Ave",
    "sg:city":"Indianapolis",
    "sg:classifiers":[
        {
            "category":"Shopping",
            "subcategory":"Florist",
            "type":"Retail Goods"
        }
    ],
    "sg:phone":"+1 317 786 0816",
    "sg:postcode":"46227",
    "sg:province":"IN",
    "wof:name":"Weddings By Anne",
    "wof:placetype":"venue"
},
  "geometry": {"coordinates":[-86.146755,39.705461],"type":"Point"}
}