{
  "type": "Feature",
  "properties": {
    "addr:full":"802 Ahrens Rd Chesterton IN 46304",
    "addr:housenumber":"802",
    "addr:postcode":"46304",
    "addr:street":"Ahrens Rd",
    "iso:country":"US",
    "sg:address":"802 Ahrens Rd",
    "sg:city":"Chesterton",
    "sg:classifiers":[
        {
            "category":"Retail",
            "subcategory":"Auto Repair",
            "type":"Services"
        }
    ],
    "sg:phone":"+1 219 926 3636",
    "sg:postcode":"46304",
    "sg:province":"IN",
    "sg:tags":[
        "automobile",
        "lubrication"
    ],
    "wof:name":"Jiffy Lube",
    "wof:placetype":"venue"
},
  "geometry": {"coordinates":[-87.034927,41.615884],"type":"Point"}
}