{
  "type": "Feature",
  "properties": {
    "addr:full":"1334 Field St Hammond IN 46320",
    "addr:housenumber":"1334",
    "addr:postcode":"46320",
    "addr:street":"Field St",
    "iso:country":"US",
    "sg:address":"1334 Field St",
    "sg:city":"Hammond",
    "sg:classifiers":[
        {
            "category":"Building & Trades",
            "subcategory":"Construction",
            "type":"Services"
        }
    ],
    "sg:phone":"+1 219 852 9323",
    "sg:postcode":"46320",
    "sg:province":"IN",
    "sg:tags":[
        "roofing",
        "contractor"
    ],
    "sg:website":"www.greatlakesroof.com",
    "wof:name":"Great Lakes Roofing",
    "wof:placetype":"venue"
},
  "geometry": {"coordinates":[-87.496623,41.601469],"type":"Point"}
}