{
  "type": "Feature",
  "properties": {
    "iso:country":"US",
    "sg:address":"1145 E 3rd St",
    "sg:city":"Mishawaka",
    "sg:classifiers":[
        {
            "category":"Social Services",
            "subcategory":"Child Care",
            "type":"Services"
        }
    ],
    "sg:phone":"+1 574 255 4968",
    "sg:postcode":"46544",
    "sg:province":"IN",
    "wof:name":"ABC Learn & Play Inc",
    "wof:placetype":"venue"
},
  "geometry": {"coordinates":[-86.161678,41.660808],"type":"Point"}
}