{
  "type": "Feature",
  "properties": {
    "addr:full":"8018 N 925 E Dubois IN 47527",
    "addr:housenumber":"8018",
    "addr:postcode":"47527",
    "addr:street":"N 925 E Dubois",
    "iso:country":"US",
    "sg:address":"8018 N 925 E",
    "sg:city":"Dubois",
    "sg:classifiers":[
        {
            "category":"Home & Garden",
            "subcategory":"Garden Supply",
            "type":"Retail Goods"
        }
    ],
    "sg:phone":"+1 812 678 3706",
    "sg:postcode":"47527",
    "sg:province":"IN",
    "sg:tags":[
        "lawn",
        "mower"
    ],
    "wof:name":"Hagen's Repair Shop",
    "wof:placetype":"venue"
},
  "geometry": {"coordinates":[-86.733012,38.498432],"type":"Point"}
}