{
  "type": "Feature",
  "properties": {
    "iso:country":"US",
    "sg:address":"8805 Indianapolis Blvd",
    "sg:city":"Highland",
    "sg:classifiers":[
        {
            "category":"Professional",
            "type":"Services"
        }
    ],
    "sg:phone":"+1 219 923 4290",
    "sg:postcode":"46322",
    "sg:province":"IN",
    "wof:name":"Smoke Ring Corporation",
    "wof:placetype":"venue"
},
  "geometry": {"coordinates":[-87.47025600000001,41.460552],"type":"Point"}
}