{
  "type": "Feature",
  "properties": {
    "iso:country":"US",
    "sg:address":"7230 Engle Rd",
    "sg:city":"Fort Wayne",
    "sg:classifiers":[
        {
            "category":"Health Services",
            "subcategory":"Doctor",
            "type":"Services"
        }
    ],
    "sg:phone":"+1 260 436 9696",
    "sg:postcode":"46804",
    "sg:province":"IN",
    "sg:tags":[
        "physician",
        "surgeon"
    ],
    "wof:name":"Three Rivers Dermatology",
    "wof:placetype":"venue"
},
  "geometry": {"coordinates":[-85.237383,41.044554],"type":"Point"}
}