{
  "type": "Feature",
  "properties": {
    "addr:full":"315 W 350 N Warsaw IN 46582",
    "addr:housenumber":"315",
    "addr:postcode":"46582",
    "addr:street":"W 350 N",
    "iso:country":"US",
    "sg:address":"315 W 350 N",
    "sg:city":"Warsaw",
    "sg:classifiers":[
        {
            "category":"Professional",
            "type":"Services"
        }
    ],
    "sg:phone":"+1 574 269 4520",
    "sg:postcode":"46582",
    "sg:province":"IN",
    "sg:tags":[
        "establishment"
    ],
    "wof:name":"USPFO For Indiana",
    "wof:placetype":"venue"
},
  "geometry": {"coordinates":[-86.027902,41.282177],"type":"Point"}
}