{
  "type": "Feature",
  "properties": {
    "iso:country":"US",
    "sg:address":"2124 Broadway St",
    "sg:city":"Anderson",
    "sg:classifiers":[
        {
            "category":"Food & Beverages",
            "subcategory":"Liquor & Beverages",
            "type":"Retail Goods"
        }
    ],
    "sg:phone":"+1 765 644 0555",
    "sg:postcode":"46012",
    "sg:province":"IN",
    "wof:name":"Keg-N-Bottle Package",
    "wof:placetype":"venue"
},
  "geometry": {"coordinates":[-85.67753,40.137425],"type":"Point"}
}