{
  "type": "Feature",
  "properties": {
    "iso:country":"US",
    "sg:address":"913 W Park Dr",
    "sg:city":"Huntington",
    "sg:classifiers":[
        {
            "category":"Shopping",
            "type":"Retail Goods"
        }
    ],
    "sg:phone":"+1 260 356 0064",
    "sg:postcode":"46750",
    "sg:province":"IN",
    "sg:tags":[
        "wedding",
        "supply"
    ],
    "wof:name":"Julliart Video Prods",
    "wof:placetype":"venue"
},
  "geometry": {"coordinates":[-85.503783,40.879125],"type":"Point"}
}