{
  "type": "Feature",
  "properties": {
    "iso:country":"US",
    "sg:address":"7398 E State Rd 66",
    "sg:city":"Cannelton",
    "sg:classifiers":[
        {
            "category":"Home & Garden",
            "subcategory":"Furniture",
            "type":"Retail Goods"
        }
    ],
    "sg:phone":"+1 812 547 7782",
    "sg:postcode":"47520",
    "sg:province":"IN",
    "wof:name":"ABC Loft",
    "wof:placetype":"venue"
},
  "geometry": {"coordinates":[-86.659536,37.929726],"type":"Point"}
}