{
  "type": "Feature",
  "properties": {
    "iso:country":"US",
    "sg:address":"3937 N Keystone Ave",
    "sg:city":"Indianapolis",
    "sg:classifiers":[
        {
            "category":"Shopping",
            "subcategory":"Clothing, Apparel, & Fashions",
            "type":"Retail Goods"
        }
    ],
    "sg:phone":"+1 317 542 7101",
    "sg:postcode":"46205",
    "sg:province":"IN",
    "sg:tags":[
        "handbag"
    ],
    "wof:name":"Chante's Boutique",
    "wof:placetype":"venue"
},
  "geometry": {"coordinates":[-86.121758,39.827515],"type":"Point"}
}