{
  "type": "Feature",
  "properties": {
    "iso:country":"US",
    "sg:address":"540 Broadway St",
    "sg:city":"New Haven",
    "sg:classifiers":[
        {
            "category":"Retail",
            "subcategory":"Auto Repair",
            "type":"Services"
        }
    ],
    "sg:phone":"+1 260 749 5274",
    "sg:postcode":"46774",
    "sg:province":"IN",
    "sg:tags":[
        "repairing",
        "automobile"
    ],
    "wof:name":"Lash Auto Svc",
    "wof:placetype":"venue"
},
  "geometry": {"coordinates":[-85.016866,41.071665],"type":"Point"}
}