{
  "type": "Feature",
  "properties": {
    "iso:country":"US",
    "sg:address":"5822 Rahke Rd",
    "sg:city":"Indianapolis",
    "sg:classifiers":[
        {
            "category":"Manufacturing",
            "subcategory":"Rubber & Plastics",
            "type":"Manufacturing & Wholesale Goods"
        }
    ],
    "sg:phone":"+1 317 446 4409",
    "sg:postcode":"46217",
    "sg:province":"IN",
    "sg:tags":[
        "gaskets-manufacturers"
    ],
    "wof:name":"Hoosier Sealing Supply Company",
    "wof:placetype":"venue"
},
  "geometry": {"coordinates":[-86.168037,39.681651],"type":"Point"}
}