{
  "type": "Feature",
  "properties": {
    "iso:country":"US",
    "sg:address":"7504 Crews Dr",
    "sg:city":"Indianapolis",
    "sg:classifiers":[
        {
            "category":"Wholesale",
            "subcategory":"Machinery & Supplies",
            "type":"Manufacturing & Wholesale Goods"
        }
    ],
    "sg:phone":"+1 317 547 0727",
    "sg:postcode":"46226",
    "sg:province":"IN",
    "sg:tags":[
        "equipment",
        "foundry"
    ],
    "wof:name":"John M Glass Co Inc",
    "wof:placetype":"venue"
},
  "geometry": {"coordinates":[-86.035798,39.835435],"type":"Point"}
}