{
  "type": "Feature",
  "properties": {
    "addr:full":"9200 Keystone Xing Ste 500 Indianapolis IN 46240",
    "addr:housenumber":"9200",
    "addr:postcode":"46240",
    "addr:street":"Keystone Xing Ste 500",
    "iso:country":"US",
    "sg:address":"9200 Keystone Xing Ste 500",
    "sg:city":"Indianapolis",
    "sg:classifiers":[
        {
            "category":"Real Estate",
            "subcategory":"Real Estate Services",
            "type":"Services"
        },
        {
            "category":"Real Estate",
            "subcategory":"Real Estate Operator",
            "type":"Services"
        }
    ],
    "sg:phone":"+1 317 817 7500",
    "sg:postcode":"46240",
    "sg:province":"IN",
    "sg:tags":[
        "apartment",
        "property",
        "management"
    ],
    "wof:name":"Aimco Management Co",
    "wof:placetype":"venue"
},
  "geometry": {"coordinates":[-86.109497,39.9179],"type":"Point"}
}