{
  "type": "Feature",
  "properties": {
    "iso:country":"US",
    "sg:address":"7145 MICHIGAN RD",
    "sg:city":"INDIANAPOLIS",
    "sg:classifiers":[
        {
            "category":"Home & Garden",
            "subcategory":"Household Appliances",
            "type":"Retail Goods"
        },
        {
            "category":"Communications",
            "subcategory":"Radio Station",
            "type":"Services"
        },
        {
            "category":"Shopping",
            "subcategory":"Computers & Home Electronics",
            "type":"Retail Goods"
        },
        {
            "category":"Home & Garden",
            "subcategory":"Furniture",
            "type":"Retail Goods"
        }
    ],
    "sg:phone":"+1 317 285 0609",
    "sg:postcode":"46268",
    "sg:province":"IN",
    "sg:tags":[
        "renting",
        "television",
        "leasing",
        "radio-renting",
        "equipment",
        "rental"
    ],
    "sg:website":"http://www.rentacenter.com/",
    "wof:name":"Rent-A-Center",
    "wof:placetype":"venue"
},
  "geometry": {"coordinates":[-86.209266,39.883711],"type":"Point"}
}