{
  "type": "Feature",
  "properties": {
    "iso:country":"US",
    "sg:address":"12522 Rockridge Pl",
    "sg:city":"Fort Wayne",
    "sg:classifiers":[
        {
            "category":"Manufacturing",
            "subcategory":"Tools & Machinery",
            "type":"Manufacturing & Wholesale Goods"
        }
    ],
    "sg:phone":"+1 260 672 8995",
    "sg:postcode":"46814",
    "sg:province":"IN",
    "sg:tags":[
        "equipment",
        "system",
        "automation"
    ],
    "wof:name":"Midpro",
    "wof:placetype":"venue"
},
  "geometry": {"coordinates":[-85.30622,41.027604],"type":"Point"}
}