{
  "type": "Feature",
  "properties": {
    "iso:country":"US",
    "sg:address":"1114 Horseshoe Bend Rd",
    "sg:city":"Sunman",
    "sg:classifiers":[
        {
            "category":"Farming",
            "subcategory":"Livestock Farm",
            "type":"Manufacturing & Wholesale Goods"
        }
    ],
    "sg:phone":"+1 812 623 3231",
    "sg:postcode":"47041",
    "sg:province":"IN",
    "sg:tags":[
        "feedlot",
        "corn",
        "soybean",
        "beef",
        "cattle"
    ],
    "wof:name":"Edward Windhotlz",
    "wof:placetype":"venue"
},
  "geometry": {"coordinates":[-85.076292,39.309993],"type":"Point"}
}