{
  "type": "Feature",
  "properties": {
    "iso:country":"US",
    "sg:address":"3487 W 86th St",
    "sg:city":"Indianapolis",
    "sg:classifiers":[
        {
            "category":"Shopping",
            "type":"Retail Goods"
        }
    ],
    "sg:phone":"+1 317 876 3140",
    "sg:postcode":"46268",
    "sg:province":"IN",
    "sg:tags":[
        "pet",
        "shop"
    ],
    "sg:website":"www.petsmart.com",
    "wof:name":"Petsmart",
    "wof:placetype":"venue"
},
  "geometry": {"coordinates":[-86.221272,39.911606],"type":"Point"}
}