{
  "type": "Feature",
  "properties": {
    "iso:country":"US",
    "sg:address":"608 Waldron St",
    "sg:city":"West Lafayette",
    "sg:classifiers":[
        {
            "category":"Travel",
            "subcategory":"Hotels & Motels",
            "type":"Entertainment"
        }
    ],
    "sg:phone":"+1 765 743 1886",
    "sg:postcode":"47906",
    "sg:province":"IN",
    "sg:tags":[
        "membership",
        "association",
        "lodging"
    ],
    "wof:name":"Acacia Fraternity",
    "wof:placetype":"venue"
},
  "geometry": {"coordinates":[-86.917886,40.431287],"type":"Point"}
}