{
  "type": "Feature",
  "properties": {
    "iso:country":"US",
    "sg:address":"1305 Edwardsville Galena Rd",
    "sg:city":"Georgetown",
    "sg:classifiers":[
        {
            "category":"Social Services",
            "subcategory":"Child Care",
            "type":"Services"
        }
    ],
    "sg:phone":"+1 812 923 8518",
    "sg:postcode":"47122",
    "sg:province":"IN",
    "wof:name":"Highland Baptist Church",
    "wof:placetype":"venue"
},
  "geometry": {"coordinates":[-85.91990699999999,38.29221],"type":"Point"}
}