{
  "type": "Feature",
  "properties": {
    "iso:country":"US",
    "sg:address":"295 N 600 W",
    "sg:city":"Angola",
    "sg:classifiers":[
        {
            "category":"Farming",
            "subcategory":"Farm",
            "type":"Manufacturing & Wholesale Goods"
        }
    ],
    "sg:phone":"+1 260 668 7700",
    "sg:postcode":"46703",
    "sg:province":"IN",
    "sg:tags":[
        "crop",
        "general"
    ],
    "wof:name":"Rocky Delancey",
    "wof:placetype":"venue"
},
  "geometry": {"coordinates":[-85.102296,41.642233],"type":"Point"}
}