{
  "type": "Feature",
  "properties": {
    "iso:country":"US",
    "sg:address":"4221 W Washington Center Rd",
    "sg:city":"Fort Wayne",
    "sg:classifiers":[
        {
            "category":"Food & Beverages",
            "subcategory":"Groceries & Convenience Stores",
            "type":"Retail Goods"
        }
    ],
    "sg:phone":"+1 260 490 8015",
    "sg:postcode":"46818",
    "sg:province":"IN",
    "wof:name":"Old Fort Travel Plaza",
    "wof:placetype":"venue"
},
  "geometry": {"coordinates":[-85.202098,41.131984],"type":"Point"}
}