{
  "type": "Feature",
  "properties": {
    "iso:country":"US",
    "sg:address":"344 Walnut St",
    "sg:city":"Lawrenceburg",
    "sg:classifiers":[
        {
            "category":"Social Services",
            "type":"Services"
        }
    ],
    "sg:phone":"+1 812 537 0556",
    "sg:postcode":"47025",
    "sg:province":"IN",
    "sg:tags":[
        "counselor",
        "marriage",
        "family"
    ],
    "wof:name":"Center For Christian Cnslng",
    "wof:placetype":"venue"
},
  "geometry": {"coordinates":[-84.8505,39.094834],"type":"Point"}
}