{
  "type": "Feature",
  "properties": {
    "iso:country":"US",
    "sg:address":"9608 Sycamore Rd",
    "sg:city":"Carmel",
    "sg:classifiers":[
        {
            "category":"Organizations",
            "subcategory":"Religious Organization",
            "type":"Services"
        }
    ],
    "sg:phone":"+1 317 875 5899",
    "sg:postcode":"46032",
    "sg:province":"IN",
    "sg:tags":[
        "clergy"
    ],
    "wof:name":"Blanche Fiscus",
    "wof:placetype":"venue"
},
  "geometry": {"coordinates":[-86.21964800000001,39.927981],"type":"Point"}
}