{
  "type": "Feature",
  "properties": {
    "iso:country":"US",
    "sg:address":"51146 Co Rd 5",
    "sg:city":"Elkhart",
    "sg:classifiers":[
        {
            "category":"Insurance",
            "subcategory":"Insurance Agent",
            "type":"Services"
        }
    ],
    "sg:phone":"+1 574 262 1806",
    "sg:postcode":"46514",
    "sg:province":"IN",
    "wof:name":"Evie's Insurance",
    "wof:placetype":"venue"
},
  "geometry": {"coordinates":[-86.033152,41.751662],"type":"Point"}
}