{
  "type": "Feature",
  "properties": {
    "addr:full":"1345 125th St Whiting IN 46394",
    "addr:housenumber":"1345",
    "addr:postcode":"46394",
    "addr:street":"125Th St",
    "iso:country":"US",
    "sg:address":"1345 125th St",
    "sg:city":"Whiting",
    "sg:classifiers":[
        {
            "category":"Manufacturing",
            "subcategory":"Rubber & Plastics",
            "type":"Manufacturing & Wholesale Goods"
        }
    ],
    "sg:phone":"+1 219 659 1152",
    "sg:postcode":"46394",
    "sg:province":"IN",
    "sg:tags":[
        "toilet",
        "portable",
        "mfg"
    ],
    "wof:name":"Polyjohn Enterprises Corp",
    "wof:placetype":"venue"
},
  "geometry": {"coordinates":[-87.500747,41.668433],"type":"Point"}
}