{
  "type": "Feature",
  "properties": {
    "iso:country":"US",
    "sg:address":"428 E 5th St",
    "sg:city":"Connersville",
    "sg:classifiers":[
        {
            "category":"Restaurant",
            "type":"Food & Drink"
        }
    ],
    "sg:phone":"+1 765 825 9049",
    "sg:postcode":"47331",
    "sg:province":"IN",
    "wof:name":"Chrome Grill",
    "wof:placetype":"venue"
},
  "geometry": {"coordinates":[-85.134343,39.639883],"type":"Point"}
}