{
  "type": "Feature",
  "properties": {
    "iso:country":"US",
    "sg:address":"18710 US Hwy 31",
    "sg:city":"Westfield",
    "sg:classifiers":[
        {
            "category":"Retail",
            "subcategory":"Animal Services",
            "type":"Services"
        }
    ],
    "sg:phone":"+1 317 896 2942",
    "sg:postcode":"46074",
    "sg:province":"IN",
    "sg:tags":[
        "pet",
        "boarding",
        "sitting"
    ],
    "wof:name":"Almost Home Boarding Kennel",
    "wof:placetype":"venue"
},
  "geometry": {"coordinates":[-86.13220200000001,40.053667],"type":"Point"}
}