{
  "type": "Feature",
  "properties": {
    "addr:full":"14 W Washington St Knightstown IN 46148",
    "addr:housenumber":"14",
    "addr:postcode":"46148",
    "addr:street":"W Washington St",
    "iso:country":"US",
    "sg:address":"14 W Washington St",
    "sg:city":"Knightstown",
    "sg:classifiers":[
        {
            "category":"Shopping",
            "subcategory":"Music",
            "type":"Retail Goods"
        }
    ],
    "sg:phone":"+1 765 345 5850",
    "sg:postcode":"46148",
    "sg:province":"IN",
    "sg:tags":[
        "video",
        "disc",
        "tape",
        "cassette"
    ],
    "wof:name":"Top Ten Video's & Tanning Sln",
    "wof:placetype":"venue"
},
  "geometry": {"coordinates":[-85.52496499999999,39.795955],"type":"Point"}
}