{
  "type": "Feature",
  "properties": {
    "iso:country":"US",
    "sg:address":"1228 S Bend Ave",
    "sg:city":"South Bend",
    "sg:classifiers":[
        {
            "category":"Shopping",
            "subcategory":"Computers & Home Electronics",
            "type":"Retail Goods"
        }
    ],
    "sg:phone":"+1 574 288 8967",
    "sg:postcode":"46617",
    "sg:province":"IN",
    "sg:tags":[
        "equipment",
        "dealer"
    ],
    "wof:name":"TCD Computer Svc",
    "wof:placetype":"venue"
},
  "geometry": {"coordinates":[-86.232241,41.689192],"type":"Point"}
}