{
  "type": "Feature",
  "properties": {
    "addr:full":"3208 Beech Rd Bremen IN 46506",
    "addr:housenumber":"3208",
    "addr:postcode":"46506",
    "addr:street":"Beech Rd",
    "iso:country":"US",
    "sg:address":"3208 Beech Rd",
    "sg:city":"Bremen",
    "sg:classifiers":[
        {
            "category":"Retail",
            "subcategory":"Repair Shop",
            "type":"Services"
        }
    ],
    "sg:phone":"+1 574 773 2883",
    "sg:postcode":"46506",
    "sg:province":"IN",
    "sg:tags":[
        "welding"
    ],
    "wof:name":"Schmucker Welding",
    "wof:placetype":"venue"
},
  "geometry": {"coordinates":[-86.07807099999999,41.429906],"type":"Point"}
}