{
  "type": "Feature",
  "properties": {
    "iso:country":"US",
    "sg:address":"720 W US Hwy 20",
    "sg:city":"Michigan City",
    "sg:classifiers":[
        {
            "category":"Manufacturing",
            "subcategory":"Petroleum Products",
            "type":"Manufacturing & Wholesale Goods"
        }
    ],
    "sg:phone":"+1 219 872 8618",
    "sg:postcode":"46360",
    "sg:province":"IN",
    "sg:tags":[
        "asphalt"
    ],
    "wof:name":"Brown Inc",
    "wof:placetype":"venue"
},
  "geometry": {"coordinates":[-86.90472,41.680347],"type":"Point"}
}