{
  "type": "Feature",
  "properties": {
    "addr:full":"113 S Washington St Sims IN 46986",
    "addr:housenumber":"113",
    "addr:postcode":"46986",
    "addr:street":"S Washington St",
    "iso:country":"US",
    "sg:address":"113 S Washington St",
    "sg:city":"Sims",
    "sg:classifiers":[
        {
            "category":"Building & Trades",
            "subcategory":"Plumbing",
            "type":"Services"
        }
    ],
    "sg:phone":"+1 765 922 7950",
    "sg:postcode":"46986",
    "sg:province":"IN",
    "sg:tags":[
        "plumbing",
        "contractor"
    ],
    "wof:name":"Howard Plumbing Htg & Hdwr",
    "wof:placetype":"venue"
},
  "geometry": {"coordinates":[-85.855116,40.498885],"type":"Point"}
}