{
  "type": "Feature",
  "properties": {
    "iso:country":"US",
    "sg:address":"268 W 600 S",
    "sg:city":"Winchester",
    "sg:classifiers":[
        {
            "category":"Farming",
            "subcategory":"Farm",
            "type":"Manufacturing & Wholesale Goods"
        }
    ],
    "sg:phone":"+1 765 584 9850",
    "sg:postcode":"47394",
    "sg:province":"IN",
    "sg:tags":[
        "crop",
        "general"
    ],
    "wof:name":"Sickels Farm",
    "wof:placetype":"venue"
},
  "geometry": {"coordinates":[-84.982891,40.077663],"type":"Point"}
}