{
  "type": "Feature",
  "properties": {
    "iso:country":"US",
    "sg:address":"1058 S Ewing St",
    "sg:city":"Indianapolis",
    "sg:classifiers":[
        {
            "category":"Manufacturing",
            "subcategory":"Tools & Machinery",
            "type":"Manufacturing & Wholesale Goods"
        }
    ],
    "sg:phone":"+1 317 357 8491",
    "sg:postcode":"46203",
    "sg:province":"IN",
    "sg:tags":[
        "machine",
        "shop"
    ],
    "wof:name":"Accurate Machine Co",
    "wof:placetype":"venue"
},
  "geometry": {"coordinates":[-86.104388,39.753414],"type":"Point"}
}