{
  "type": "Feature",
  "properties": {
    "iso:country":"US",
    "sg:address":"3504 Cardinal Ln",
    "sg:city":"Fort Wayne",
    "sg:classifiers":[
        {
            "category":"Professional",
            "type":"Services"
        }
    ],
    "sg:phone":"+1 260 493 1733",
    "sg:postcode":"46815",
    "sg:province":"IN",
    "wof:name":"Jjmc LLP",
    "wof:placetype":"venue"
},
  "geometry": {"coordinates":[-85.028092,41.111236],"type":"Point"}
}