{
  "type": "Feature",
  "properties": {
    "iso:country":"US",
    "sg:address":"11044 Co Rd 2",
    "sg:city":"Middlebury",
    "sg:classifiers":[
        {
            "category":"Home & Garden",
            "subcategory":"Garden Supply",
            "type":"Retail Goods"
        }
    ],
    "sg:phone":"+1 574 825 5000",
    "sg:postcode":"46540",
    "sg:province":"IN",
    "sg:tags":[
        "landscaping",
        "equipment"
    ],
    "wof:name":"Indian Prairie Materials Inc",
    "wof:placetype":"venue"
},
  "geometry": {"coordinates":[-85.680912,41.754879],"type":"Point"}
}