{
  "type": "Feature",
  "properties": {
    "addr:full":"509 S Locust St Greencastle IN 46135",
    "addr:housenumber":"509",
    "addr:postcode":"46135",
    "addr:street":"S Locust St",
    "iso:country":"US",
    "sg:address":"509 S Locust St",
    "sg:city":"Greencastle",
    "sg:classifiers":[
        {
            "category":"Organizations",
            "subcategory":"Community Association",
            "type":"Services"
        }
    ],
    "sg:phone":"+1 765 653 9751",
    "sg:postcode":"46135",
    "sg:province":"IN",
    "sg:tags":[
        "sorority",
        "fraternity"
    ],
    "wof:name":"Sigma Alpha Epsilon",
    "wof:placetype":"venue"
},
  "geometry": {"coordinates":[-86.860591,39.639047],"type":"Point"}
}