{
  "type": "Feature",
  "properties": {
    "iso:country":"US",
    "sg:address":"6060 Hardegan St",
    "sg:city":"Indianapolis",
    "sg:classifiers":[
        {
            "category":"Insurance",
            "subcategory":"Insurance Agent",
            "type":"Services"
        }
    ],
    "sg:phone":"+1 317 783 4004",
    "sg:postcode":"46227",
    "sg:province":"IN",
    "wof:name":"BFK Assoc",
    "wof:placetype":"venue"
},
  "geometry": {"coordinates":[-86.125644,39.676711],"type":"Point"}
}