{
  "type": "Feature",
  "properties": {
    "addr:full":"651 S Clarizz Blvd Bloomington IN 47401",
    "addr:housenumber":"651",
    "addr:postcode":"47401",
    "addr:street":"S Clarizz Blvd",
    "iso:country":"US",
    "sg:address":"651 S Clarizz Blvd",
    "sg:city":"Bloomington",
    "sg:classifiers":[
        {
            "category":"Health Services",
            "subcategory":"Doctor",
            "type":"Services"
        }
    ],
    "sg:phone":"+1 812 333 2304",
    "sg:postcode":"47401",
    "sg:province":"IN",
    "sg:website":"www.sipdocs.com",
    "wof:name":"Malone Richard K MD",
    "wof:placetype":"venue"
},
  "geometry": {"coordinates":[-86.478996,39.1642],"type":"Point"}
}