{
  "type": "Feature",
  "properties": {
    "addr:full":"215 N 2nd St Terre Haute IN 47807",
    "addr:housenumber":"215",
    "addr:postcode":"47807",
    "addr:street":"N 2Nd St",
    "iso:country":"US",
    "sg:address":"215 N 2nd St",
    "sg:city":"Terre Haute",
    "sg:classifiers":[
        {
            "category":"Restaurant",
            "type":"Food & Drink"
        }
    ],
    "sg:menulink":"http://www.allmenus.com/in/harrison/273048-pizza-city/menu/",
    "sg:phone":"+1 812 232 5253",
    "sg:postcode":"47807",
    "sg:province":"IN",
    "sg:tags":[
        "american",
        "pizza"
    ],
    "wof:name":"Pizza City",
    "wof:placetype":"venue"
},
  "geometry": {"coordinates":[-87.415178,39.468851],"type":"Point"}
}