{
  "type": "Feature",
  "properties": {
    "iso:country":"US",
    "sg:address":"459 N 9th St",
    "sg:city":"Clinton",
    "sg:classifiers":[
        {
            "category":"Organizations",
            "subcategory":"Religious Organization",
            "type":"Services"
        }
    ],
    "sg:phone":"+1 765 828 9067",
    "sg:postcode":"47842",
    "sg:province":"IN",
    "sg:tags":[
        "church"
    ],
    "wof:name":"New Life Family Four Square",
    "wof:placetype":"venue"
},
  "geometry": {"coordinates":[-87.40816700000001,39.664131],"type":"Point"}
}