{
  "type": "Feature",
  "properties": {
    "addr:full":"160 N Washington St Hartsville IN 47244",
    "addr:housenumber":"160",
    "addr:postcode":"47244",
    "addr:street":"N Washington St",
    "iso:country":"US",
    "sg:address":"160 N Washington St",
    "sg:city":"Hartsville",
    "sg:classifiers":[
        {
            "category":"Organizations",
            "subcategory":"Religious Organization",
            "type":"Services"
        }
    ],
    "sg:phone":"+1 812 546 5517",
    "sg:postcode":"47244",
    "sg:province":"IN",
    "sg:tags":[
        "church"
    ],
    "wof:name":"Hartsville Church Of Christ",
    "wof:placetype":"venue"
},
  "geometry": {"coordinates":[-85.699124,39.267978],"type":"Point"}
}