{
  "type": "Feature",
  "properties": {
    "iso:country":"US",
    "sg:address":"957 Ironwood Dr W",
    "sg:city":"Carmel",
    "sg:classifiers":[
        {
            "category":"Professional",
            "subcategory":"Accounting & Tax Preparation",
            "type":"Services"
        }
    ],
    "sg:phone":"+1 317 846 7881",
    "sg:postcode":"46033",
    "sg:province":"IN",
    "wof:name":"William C Kennedy CPA",
    "wof:placetype":"venue"
},
  "geometry": {"coordinates":[-86.100312,39.99058],"type":"Point"}
}