{
  "type": "Feature",
  "properties": {
    "iso:country":"US",
    "sg:address":"2823 N Oakwood Ave",
    "sg:city":"Muncie",
    "sg:classifiers":[
        {
            "category":"Personal",
            "subcategory":"Barber",
            "type":"Services"
        }
    ],
    "sg:phone":"+1 765 747 9888",
    "sg:postcode":"47304",
    "sg:province":"IN",
    "wof:name":"Joe's Barber Shop",
    "wof:placetype":"venue"
},
  "geometry": {"coordinates":[-85.40965,40.218798],"type":"Point"}
}