{
  "type": "Feature",
  "properties": {
    "addr:full":"907 Lincoln Hwy W New Haven IN 46774",
    "addr:housenumber":"907",
    "addr:postcode":"46774",
    "addr:street":"Lincoln Hwy W;Haven",
    "iso:country":"US",
    "sg:address":"907 Lincoln Hwy W",
    "sg:city":"New Haven",
    "sg:classifiers":[
        {
            "category":"Shopping",
            "subcategory":"Pharmacy",
            "type":"Retail Goods"
        }
    ],
    "sg:phone":"+1 260 493 3538",
    "sg:postcode":"46774",
    "sg:province":"IN",
    "wof:name":"Walgreens",
    "wof:placetype":"venue"
},
  "geometry": {"coordinates":[-85.03892999999999,41.069958],"type":"Point"}
}