{
  "type": "Feature",
  "properties": {
    "iso:country":"US",
    "sg:address":"3 N Broadway",
    "sg:city":"Peru",
    "sg:classifiers":[
        {
            "category":"Utilities",
            "subcategory":"Mobile Phone",
            "type":"Services"
        }
    ],
    "sg:phone":"+1 765 473 8284",
    "sg:postcode":"46970",
    "sg:province":"IN",
    "sg:tags":[
        "telephone",
        "cellular"
    ],
    "wof:name":"Us Cellular Inc",
    "wof:placetype":"venue"
},
  "geometry": {"coordinates":[-86.06965,40.754593],"type":"Point"}
}