{
  "type": "Feature",
  "properties": {
    "iso:country":"US",
    "sg:address":"1231 Meridian St",
    "sg:city":"Anderson",
    "sg:classifiers":[
        {
            "category":"Shopping",
            "subcategory":"Used Merchandise",
            "type":"Retail Goods"
        }
    ],
    "sg:phone":"+1 765 642 8016",
    "sg:postcode":"46016",
    "sg:province":"IN",
    "wof:name":"Abbys",
    "wof:placetype":"venue"
},
  "geometry": {"coordinates":[-85.679278,40.103434],"type":"Point"}
}