{
  "type": "Feature",
  "properties": {
    "addr:full":"4450 N State Rd 29 Camden IN 46917",
    "addr:housenumber":"4450;29",
    "addr:postcode":"46917",
    "addr:street":"N State Rd",
    "iso:country":"US",
    "sg:address":"4450 N State Rd 29",
    "sg:city":"Camden",
    "sg:classifiers":[
        {
            "category":"Organizations",
            "subcategory":"Religious Organization",
            "type":"Services"
        }
    ],
    "sg:phone":"+1 574 859 3671",
    "sg:postcode":"46917",
    "sg:province":"IN",
    "sg:tags":[
        "church"
    ],
    "wof:name":"Deer Creek Presbyterian Church",
    "wof:placetype":"venue"
},
  "geometry": {"coordinates":[-86.39130400000001,40.613577],"type":"Point"}
}