{
  "type": "Feature",
  "properties": {
    "iso:country":"US",
    "sg:address":"425 S Wabash St",
    "sg:city":"Wabash",
    "sg:classifiers":[
        {
            "category":"Real Estate",
            "subcategory":"Real Estate Agent",
            "type":"Services"
        }
    ],
    "sg:phone":"+1 260 563 4962",
    "sg:postcode":"46992",
    "sg:province":"IN",
    "wof:name":"Wabash Realty LLC",
    "wof:placetype":"venue"
},
  "geometry": {"coordinates":[-85.820306,40.794876],"type":"Point"}
}