{
  "type": "Feature",
  "properties": {
    "iso:country":"US",
    "sg:address":"2367 Untalulti Dr",
    "sg:city":"Monticello",
    "sg:classifiers":[
        {
            "category":"Travel",
            "subcategory":"Hotels & Motels",
            "type":"Entertainment"
        }
    ],
    "sg:phone":"+1 574 583 8918",
    "sg:postcode":"47960",
    "sg:province":"IN",
    "sg:tags":[
        "operation"
    ],
    "wof:name":"Beach Vue Resorts Inc",
    "wof:placetype":"venue"
},
  "geometry": {"coordinates":[-86.77488,40.787828],"type":"Point"}
}