{
  "type": "Feature",
  "properties": {
    "iso:country":"US",
    "sg:address":"3836 Lodi Ln",
    "sg:city":"Lafayette",
    "sg:classifiers":[
        {
            "category":"Organizations",
            "subcategory":"Non-profit Organization",
            "type":"Services"
        }
    ],
    "sg:phone":"+1 765 447 4603",
    "sg:postcode":"47905",
    "sg:province":"IN",
    "wof:name":"Sheltie Rescue",
    "wof:placetype":"venue"
},
  "geometry": {"coordinates":[-86.83768999999999,40.423645],"type":"Point"}
}