{
  "type": "Feature",
  "properties": {
    "iso:country":"US",
    "sg:address":"273 Larkspur Ct",
    "sg:city":"Zionsville",
    "sg:classifiers":[
        {
            "category":"Banks & Credit Unions",
            "subcategory":"Investment Brokerage",
            "type":"Services"
        }
    ],
    "sg:phone":"+1 317 873 9581",
    "sg:postcode":"46077",
    "sg:province":"IN",
    "sg:tags":[
        "consultant",
        "planning",
        "financial"
    ],
    "wof:name":"Zionsville Financial Planning",
    "wof:placetype":"venue"
},
  "geometry": {"coordinates":[-86.26302,40.00263],"type":"Point"}
}