{
  "type": "Feature",
  "properties": {
    "iso:country":"US",
    "sg:address":"1907 N Greensburg Xing",
    "sg:city":"Greensburg",
    "sg:classifiers":[
        {
            "category":"Shopping",
            "subcategory":"Tobacco",
            "type":"Retail Goods"
        }
    ],
    "sg:phone":"+1 812 662 6974",
    "sg:postcode":"47240",
    "sg:province":"IN",
    "sg:tags":[
        "cigarette",
        "cigar",
        "dealer"
    ],
    "wof:name":"Low Bobs Discount Tobacco Town",
    "wof:placetype":"venue"
},
  "geometry": {"coordinates":[-85.61994300000001,39.351988],"type":"Point"}
}