{
  "type": "Feature",
  "properties": {
    "iso:country":"US",
    "sg:address":"6544 E State Blvd",
    "sg:city":"Fort Wayne",
    "sg:classifiers":[
        {
            "category":"Shopping",
            "subcategory":"Gifts & Souvenirs",
            "type":"Retail Goods"
        }
    ],
    "sg:phone":"+1 260 749 2072",
    "sg:postcode":"46815",
    "sg:province":"IN",
    "sg:tags":[
        "shop"
    ],
    "sg:website":"www.rustichutch.com",
    "wof:name":"Rustic Hutch",
    "wof:placetype":"venue"
},
  "geometry": {"coordinates":[-85.057851,41.101899],"type":"Point"}
}