{
  "type": "Feature",
  "properties": {
    "iso:country":"US",
    "sg:address":"101 Connie Ave",
    "sg:city":"Salem",
    "sg:classifiers":[
        {
            "category":"Local Transit",
            "type":"Transportation"
        }
    ],
    "sg:phone":"+1 812 883 2994",
    "sg:postcode":"47167",
    "sg:province":"IN",
    "sg:tags":[
        "ambulance"
    ],
    "wof:name":"Hedrick's Transport Inc",
    "wof:placetype":"venue"
},
  "geometry": {"coordinates":[-86.10895600000001,38.615235],"type":"Point"}
}