{
  "type": "Feature",
  "properties": {
    "iso:country":"US",
    "sg:address":"4122 State Rd 331",
    "sg:city":"Bremen",
    "sg:classifiers":[
        {
            "category":"Building & Trades",
            "subcategory":"Construction",
            "type":"Services"
        }
    ],
    "sg:phone":"+1 574 546 2774",
    "sg:postcode":"46506",
    "sg:province":"IN",
    "sg:tags":[
        "concrete",
        "contractor"
    ],
    "wof:name":"Graverson Concrete",
    "wof:placetype":"venue"
},
  "geometry": {"coordinates":[-86.117251,41.417983],"type":"Point"}
}