{
  "type": "Feature",
  "properties": {
    "iso:country":"US",
    "sg:address":"111 Division Way",
    "sg:city":"Decatur",
    "sg:classifiers":[
        {
            "category":"Professional",
            "subcategory":"Management & Consulting",
            "type":"Services"
        }
    ],
    "sg:phone":"+1 260 368 9950",
    "sg:postcode":"46733",
    "sg:province":"IN",
    "sg:tags":[
        "consultant",
        "business"
    ],
    "wof:name":"Continuous Improvement Systems",
    "wof:placetype":"venue"
},
  "geometry": {"coordinates":[-84.938661,40.796094],"type":"Point"}
}