{
  "type": "Feature",
  "properties": {
    "iso:country":"US",
    "sg:address":"801 S Bend Ave",
    "sg:city":"South Bend",
    "sg:classifiers":[
        {
            "category":"Banks & Credit Unions",
            "subcategory":"Bank",
            "type":"Services"
        }
    ],
    "sg:phone":"+1 574 237 7288",
    "sg:postcode":"46617",
    "sg:province":"IN",
    "sg:tags":[
        "federal"
    ],
    "wof:name":"Notre Dame Federal Credit Un",
    "wof:placetype":"venue"
},
  "geometry": {"coordinates":[-86.239126,41.685027],"type":"Point"}
}