{
  "type": "Feature",
  "properties": {
    "iso:country":"US",
    "sg:address":"1927 E Co Rd 525 S",
    "sg:city":"Brownstown",
    "sg:classifiers":[
        {
            "category":"Retail",
            "subcategory":"Auto Repair",
            "type":"Services"
        }
    ],
    "sg:phone":"+1 812 358 3019",
    "sg:postcode":"47220",
    "sg:province":"IN",
    "sg:tags":[
        "farm",
        "corn",
        "soybean",
        "general"
    ],
    "wof:name":"Miller Electric",
    "wof:placetype":"venue"
},
  "geometry": {"coordinates":[-86.000068,38.804576],"type":"Point"}
}