{
  "type": "Feature",
  "properties": {
    "iso:country":"US",
    "sg:address":"2344 S Tibbs Ave",
    "sg:city":"Indianapolis",
    "sg:classifiers":[
        {
            "category":"Organizations",
            "subcategory":"Labor Organization",
            "type":"Services"
        }
    ],
    "sg:phone":"+1 317 241 0756",
    "sg:postcode":"46241",
    "sg:province":"IN",
    "wof:name":"Uawaft Local 9212",
    "wof:placetype":"venue"
},
  "geometry": {"coordinates":[-86.215954,39.733923],"type":"Point"}
}