{
  "type": "Feature",
  "properties": {
    "iso:country":"US",
    "sg:address":"5792 E Landersdale Rd",
    "sg:city":"Camby",
    "sg:classifiers":[
        {
            "category":"Retail",
            "subcategory":"Repair Shop",
            "type":"Services"
        }
    ],
    "sg:phone":"+1 317 831 2424",
    "sg:postcode":"46113",
    "sg:province":"IN",
    "wof:name":"Maintenance Masters Clg Svc",
    "wof:placetype":"venue"
},
  "geometry": {"coordinates":[-86.319371,39.617774],"type":"Point"}
}