{
  "type": "Feature",
  "properties": {
    "iso:country":"US",
    "sg:address":"115 S Obrien St",
    "sg:city":"Seymour",
    "sg:classifiers":[
        {
            "category":"Real Estate",
            "subcategory":"Real Estate Operator",
            "type":"Services"
        }
    ],
    "sg:phone":"+1 812 522 5239",
    "sg:postcode":"47274",
    "sg:province":"IN",
    "sg:tags":[
        "mobile",
        "home",
        "community"
    ],
    "wof:name":"Hilltop Mobile Home Park",
    "wof:placetype":"venue"
},
  "geometry": {"coordinates":[-85.881315,38.959241],"type":"Point"}
}