{
  "type": "Feature",
  "properties": {
    "iso:country":"US",
    "sg:address":"4200 Alder St",
    "sg:city":"East Chicago",
    "sg:classifiers":[
        {
            "category":"Organizations",
            "subcategory":"Religious Organization",
            "type":"Services"
        }
    ],
    "sg:phone":"+1 219 398 4653",
    "sg:postcode":"46312",
    "sg:province":"IN",
    "sg:tags":[
        "church"
    ],
    "wof:name":"St Mark AME Zion",
    "wof:placetype":"venue"
},
  "geometry": {"coordinates":[-87.44249,41.636371],"type":"Point"}
}