{
  "type": "Feature",
  "properties": {
    "iso:country":"US",
    "sg:address":"106 N Spring St",
    "sg:city":"Odon",
    "sg:classifiers":[
        {
            "category":"Banks & Credit Unions",
            "subcategory":"Bank",
            "type":"Services"
        }
    ],
    "sg:phone":"+1 812 636 7378",
    "sg:postcode":"47562",
    "sg:province":"IN",
    "wof:name":"Integra Bank",
    "wof:placetype":"venue"
},
  "geometry": {"coordinates":[-86.991348,38.843158],"type":"Point"}
}