{
  "type": "Feature",
  "properties": {
    "addr:full":"1018 N Central Ave Connersville IN 47331",
    "addr:housenumber":"1018",
    "addr:postcode":"47331",
    "addr:street":"N Central Ave",
    "iso:country":"US",
    "sg:address":"1018 N Central Ave",
    "sg:city":"Connersville",
    "sg:classifiers":[
        {
            "category":"Real Estate",
            "subcategory":"Real Estate Agent",
            "type":"Services"
        }
    ],
    "sg:phone":"+1 765 825 8513",
    "sg:postcode":"47331",
    "sg:province":"IN",
    "wof:name":"Southern Cross Development",
    "wof:placetype":"venue"
},
  "geometry": {"coordinates":[-85.13543799999999,39.646332],"type":"Point"}
}