{
  "type": "Feature",
  "properties": {
    "iso:country":"US",
    "sg:address":"2577 Bear Wallow Hill Rd",
    "sg:city":"Nashville",
    "sg:classifiers":[
        {
            "category":"Building & Trades",
            "subcategory":"Construction",
            "type":"Services"
        }
    ],
    "sg:phone":"+1 812 988 0620",
    "sg:postcode":"47448",
    "sg:province":"IN",
    "sg:tags":[
        "concrete",
        "contractor"
    ],
    "wof:name":"Price-Sullivan Concrete",
    "wof:placetype":"venue"
},
  "geometry": {"coordinates":[-86.225596,39.234651],"type":"Point"}
}