{
  "type": "Feature",
  "properties": {
    "iso:country":"US",
    "sg:address":"224 Extension St",
    "sg:city":"Worthington",
    "sg:classifiers":[
        {
            "category":"Freight",
            "type":"Transportation"
        }
    ],
    "sg:phone":"+1 812 875 2687",
    "sg:postcode":"47471",
    "sg:province":"IN",
    "sg:tags":[
        "operator",
        "local",
        "trucking"
    ],
    "wof:name":"Driscol Trucking",
    "wof:placetype":"venue"
},
  "geometry": {"coordinates":[-86.97623,39.116176],"type":"Point"}
}