{
  "type": "Feature",
  "properties": {
    "iso:country":"US",
    "sg:address":"94 N 1st Ave",
    "sg:city":"Beech Grove",
    "sg:classifiers":[
        {
            "category":"Retail",
            "subcategory":"Auto Repair",
            "type":"Services"
        }
    ],
    "sg:phone":"+1 317 787 2116",
    "sg:postcode":"46107",
    "sg:province":"IN",
    "sg:tags":[
        "repairing",
        "automobile"
    ],
    "wof:name":"Beech Grove Auto Svc Inc",
    "wof:placetype":"venue"
},
  "geometry": {"coordinates":[-86.082511,39.721642],"type":"Point"}
}