{
  "type": "Feature",
  "properties": {
    "iso:country":"US",
    "sg:address":"506 W Main St",
    "sg:city":"Austin",
    "sg:classifiers":[
        {
            "category":"Shopping",
            "subcategory":"Discount & Variety Stores",
            "type":"Retail Goods"
        }
    ],
    "sg:phone":"+1 812 794 9416",
    "sg:postcode":"47102",
    "sg:province":"IN",
    "wof:name":"Linda's This & That Shop",
    "wof:placetype":"venue"
},
  "geometry": {"coordinates":[-85.812263,38.741462],"type":"Point"}
}