{
  "type": "Feature",
  "properties": {
    "iso:country":"US",
    "sg:address":"227 E Jefferson St",
    "sg:city":"Tipton",
    "sg:classifiers":[
        {
            "category":"Government",
            "subcategory":"Fire Station",
            "type":"Public Place"
        }
    ],
    "sg:phone":"+1 765 675 4633",
    "sg:postcode":"46072",
    "sg:province":"IN",
    "sg:tags":[
        "department"
    ],
    "wof:name":"Tipton Fire Dept",
    "wof:placetype":"venue"
},
  "geometry": {"coordinates":[-86.038247,40.28224],"type":"Point"}
}