{
  "type": "Feature",
  "properties": {
    "addr:full":"9311 S Ferdinand Rd NW Ferdinand IN 47532",
    "addr:housenumber":"9311",
    "addr:postcode":"ferdinand;47532",
    "addr:street":"S Ferdinand Rd Nw",
    "iso:country":"US",
    "sg:address":"9311 S Ferdinand Rd NW",
    "sg:city":"Ferdinand",
    "sg:classifiers":[
        {
            "category":"Farming",
            "subcategory":"Farm",
            "type":"Manufacturing & Wholesale Goods"
        }
    ],
    "sg:phone":"+1 812 367 2241",
    "sg:postcode":"47532",
    "sg:province":"IN",
    "sg:tags":[
        "general"
    ],
    "wof:name":"Gehlhausen Farms",
    "wof:placetype":"venue"
},
  "geometry": {"coordinates":[-86.89599200000001,38.243862],"type":"Point"}
}