{
  "type": "Feature",
  "properties": {
    "iso:country":"US",
    "sg:address":"412 W Co Rd 500 N",
    "sg:city":"Frankfort",
    "sg:classifiers":[
        {
            "category":"Farming",
            "subcategory":"Farm",
            "type":"Manufacturing & Wholesale Goods"
        }
    ],
    "sg:phone":"+1 765 258 2340",
    "sg:postcode":"46041",
    "sg:province":"IN",
    "sg:tags":[
        "crop",
        "general"
    ],
    "wof:name":"James Chezem",
    "wof:placetype":"venue"
},
  "geometry": {"coordinates":[-86.51063499999999,40.358595],"type":"Point"}
}