{
  "type": "Feature",
  "properties": {
    "iso:country":"US",
    "sg:address":"8945 Classic View Dr",
    "sg:city":"Indianapolis",
    "sg:classifiers":[
        {
            "category":"Health Services",
            "subcategory":"Doctor",
            "type":"Services"
        }
    ],
    "sg:phone":"+1 317 887 7700",
    "sg:postcode":"46217",
    "sg:province":"IN",
    "sg:tags":[
        "physician",
        "surgeon"
    ],
    "wof:name":"Ibad U Ansari MD",
    "wof:placetype":"venue"
},
  "geometry": {"coordinates":[-86.16371700000001,39.635955],"type":"Point"}
}