{
  "type": "Feature",
  "properties": {
    "iso:country":"US",
    "sg:address":"2269 E 151st St",
    "sg:city":"Carmel",
    "sg:classifiers":[
        {
            "category":"Professional",
            "subcategory":"Management & Consulting",
            "type":"Services"
        }
    ],
    "sg:phone":"+1 317 575 6136",
    "sg:postcode":"46033",
    "sg:province":"IN",
    "sg:tags":[
        "consultant"
    ],
    "wof:name":"Carmel Consulting",
    "wof:placetype":"venue"
},
  "geometry": {"coordinates":[-86.120737,40.007434],"type":"Point"}
}