{
  "type": "Feature",
  "properties": {
    "iso:country":"US",
    "sg:address":"10501 Heartland Blvd",
    "sg:city":"Camby",
    "sg:classifiers":[
        {
            "category":"Autos & Motor Vehicles",
            "subcategory":"Fuel & Gas Station",
            "type":"Retail Goods"
        },
        {
            "category":"Food & Beverages",
            "subcategory":"Groceries & Convenience Stores",
            "type":"Retail Goods"
        }
    ],
    "sg:phone":"+1 317 821 6829",
    "sg:postcode":"46113",
    "sg:province":"IN",
    "wof:name":"Meijer",
    "wof:placetype":"venue"
},
  "geometry": {"coordinates":[-86.322152,39.635104],"type":"Point"}
}