{
  "type": "Feature",
  "properties": {
    "addr:full":"3015 S B St Richmond IN 47374",
    "addr:housenumber":"3015",
    "addr:postcode":"47374",
    "addr:street":"S B St",
    "iso:country":"US",
    "sg:address":"3015 S B St",
    "sg:city":"Richmond",
    "sg:classifiers":[
        {
            "category":"Organizations",
            "subcategory":"Religious Organization",
            "type":"Services"
        }
    ],
    "sg:phone":"+1 765 966 4654",
    "sg:postcode":"47374",
    "sg:province":"IN",
    "sg:tags":[
        "church"
    ],
    "wof:name":"Ravina Park Baptist Church",
    "wof:placetype":"venue"
},
  "geometry": {"coordinates":[-84.86138099999999,39.825953],"type":"Point"}
}