{
  "type": "Feature",
  "properties": {
    "addr:full":"4822 S 1075 E New Ross IN 47905",
    "addr:housenumber":"4822",
    "addr:postcode":"47905",
    "addr:street":"S 1075 E",
    "iso:country":"US",
    "sg:address":"4822 S 1075 E",
    "sg:city":"New Ross",
    "sg:phone":"+1 765 723 1750",
    "sg:postcode":"47905",
    "sg:province":"IN",
    "sg:tags":[
        "farm",
        "corn",
        "soybean"
    ],
    "wof:name":"Henry Farms",
    "wof:placetype":"venue"
},
  "geometry": {"coordinates":[-86.699788,40.349716],"type":"Point"}
}