{
  "type": "Feature",
  "properties": {
    "iso:country":"US",
    "sg:address":"6 S Main St",
    "sg:city":"Fortville",
    "sg:classifiers":[
        {
            "category":"Organizations",
            "subcategory":"Professional Association",
            "type":"Services"
        }
    ],
    "sg:phone":"+1 317 485 5253",
    "sg:postcode":"46040",
    "sg:province":"IN",
    "wof:name":"Masonic Lodge",
    "wof:placetype":"venue"
},
  "geometry": {"coordinates":[-85.849816,39.933958],"type":"Point"}
}