{
  "type": "Feature",
  "properties": {
    "iso:country":"US",
    "sg:address":"1519 N Post Rd",
    "sg:city":"Indianapolis",
    "sg:classifiers":[
        {
            "category":"Health Services",
            "subcategory":"Health Practitioner",
            "type":"Services"
        }
    ],
    "sg:phone":"+1 317 890 0117",
    "sg:postcode":"46219",
    "sg:province":"IN",
    "sg:tags":[
        "therapist",
        "physical"
    ],
    "wof:name":"St Vincent Physical Therapy",
    "wof:placetype":"venue"
},
  "geometry": {"coordinates":[-86.009238,39.78856],"type":"Point"}
}