{
  "type": "Feature",
  "properties": {
    "iso:country":"US",
    "sg:address":"5757 Kopetsky Dr",
    "sg:city":"Indianapolis",
    "sg:classifiers":[
        {
            "category":"Recreation",
            "type":"Entertainment"
        }
    ],
    "sg:phone":"+1 317 780 5757",
    "sg:postcode":"46217",
    "sg:province":"IN",
    "sg:tags":[
        "amusement"
    ],
    "sg:website":"www.softballltd.com",
    "wof:name":"Softball LTD",
    "wof:placetype":"venue"
},
  "geometry": {"coordinates":[-86.192614,39.682068],"type":"Point"}
}