{
  "type": "Feature",
  "properties": {
    "iso:country":"US",
    "sg:address":"7503 S 350 W",
    "sg:city":"Jonesboro",
    "sg:phone":"+1 765 948 5787",
    "sg:postcode":"46938",
    "sg:province":"IN",
    "sg:tags":[
        "farm",
        "corn",
        "soybean"
    ],
    "wof:name":"Loren Brookshire",
    "wof:placetype":"venue"
},
  "geometry": {"coordinates":[-85.73849300000001,40.443742],"type":"Point"}
}