{
  "type": "Feature",
  "properties": {
    "iso:country":"US",
    "sg:address":"12720 Ford Dr",
    "sg:city":"Fishers",
    "sg:classifiers":[
        {
            "category":"Building & Trades",
            "subcategory":"Construction",
            "type":"Services"
        }
    ],
    "sg:phone":"+1 317 596 6371",
    "sg:postcode":"46038",
    "sg:province":"IN",
    "sg:tags":[
        "general",
        "contractor"
    ],
    "sg:website":"www.mpconstr.com",
    "wof:name":"Mac Dougall Pierce Constr Inc",
    "wof:placetype":"venue"
},
  "geometry": {"coordinates":[-86.006295,39.97185],"type":"Point"}
}