{
  "type": "Feature",
  "properties": {
    "iso:country":"US",
    "sg:address":"8038 S Edinburgh Rd",
    "sg:city":"Edinburgh",
    "sg:classifiers":[
        {
            "category":"Retail",
            "subcategory":"Animal Services",
            "type":"Services"
        }
    ],
    "sg:phone":"+1 812 526 7297",
    "sg:postcode":"46124",
    "sg:province":"IN",
    "sg:tags":[
        "pet",
        "grooming",
        "washing"
    ],
    "wof:name":"Pampered Pets",
    "wof:placetype":"venue"
},
  "geometry": {"coordinates":[-85.913156,39.407268],"type":"Point"}
}