{
  "type": "Feature",
  "properties": {
    "addr:full":"8249 Dean Rd Indianapolis IN 46240",
    "addr:housenumber":"8249",
    "addr:postcode":"46240",
    "addr:street":"Dean Rd",
    "iso:country":"US",
    "sg:address":"8249 Dean Rd",
    "sg:city":"Indianapolis",
    "sg:classifiers":[
        {
            "category":"Sports & Exercise",
            "subcategory":"Tennis Court",
            "type":"Entertainment"
        }
    ],
    "sg:phone":"+1 317 849 2531",
    "sg:postcode":"46240",
    "sg:province":"IN",
    "wof:name":"Indianapolis Racquet Club",
    "wof:placetype":"venue"
},
  "geometry": {"coordinates":[-86.09839599999999,39.9063],"type":"Point"}
}