{
  "type": "Feature",
  "properties": {
    "iso:country":"US",
    "sg:address":"5520 W 10th St",
    "sg:city":"Indianapolis",
    "sg:classifiers":[
        {
            "category":"Retail",
            "subcategory":"Funeral Services",
            "type":"Services"
        }
    ],
    "sg:phone":"+1 317 247 4493",
    "sg:postcode":"46224",
    "sg:province":"IN",
    "sg:tags":[
        "director"
    ],
    "wof:name":"Stevens Mortuary",
    "wof:placetype":"venue"
},
  "geometry": {"coordinates":[-86.254321,39.779989],"type":"Point"}
}