{
  "type": "Feature",
  "properties": {
    "iso:country":"US",
    "sg:address":"106 W Pearl St",
    "sg:city":"Trafalgar",
    "sg:classifiers":[
        {
            "category":"Restaurant",
            "type":"Food & Drink"
        }
    ],
    "sg:phone":"+1 317 878 9988",
    "sg:postcode":"46181",
    "sg:province":"IN",
    "wof:name":"Small Town Pizza & Subs",
    "wof:placetype":"venue"
},
  "geometry": {"coordinates":[-86.152124,39.416172],"type":"Point"}
}