{
  "type": "Feature",
  "properties": {
    "iso:country":"US",
    "sg:address":"3805 Franklin St",
    "sg:city":"Michigan City",
    "sg:classifiers":[
        {
            "category":"Retail",
            "subcategory":"Auto Repair",
            "type":"Services"
        }
    ],
    "sg:phone":"+1 219 879 4618",
    "sg:postcode":"46360",
    "sg:province":"IN",
    "sg:tags":[
        "muffler",
        "exhaust",
        "system"
    ],
    "wof:name":"Midas Auto Svc Experts",
    "wof:placetype":"venue"
},
  "geometry": {"coordinates":[-86.894026,41.684016],"type":"Point"}
}