{
  "type": "Feature",
  "properties": {
    "iso:country":"US",
    "sg:address":"6322 Peachtree Cir",
    "sg:city":"Portage",
    "sg:classifiers":[
        {
            "category":"Organizations",
            "subcategory":"Professional Association",
            "type":"Services"
        }
    ],
    "sg:phone":"+1 219 736 4098",
    "sg:postcode":"46368",
    "sg:province":"IN",
    "wof:name":"American Assoc of Neurosc",
    "wof:placetype":"venue"
},
  "geometry": {"coordinates":[-87.169984,41.556901],"type":"Point"}
}