{
  "type": "Feature",
  "properties": {
    "addr:full":"1791 W Lincoln Rd Kokomo IN 46902",
    "addr:housenumber":"1791",
    "addr:postcode":"46902",
    "addr:street":"W Lincoln Rd",
    "iso:country":"US",
    "sg:address":"1791 W Lincoln Rd",
    "sg:city":"Kokomo",
    "sg:classifiers":[
        {
            "category":"Health Services",
            "subcategory":"Doctor",
            "type":"Services"
        }
    ],
    "sg:phone":"+1 765 453 8922",
    "sg:postcode":"46902",
    "sg:province":"IN",
    "sg:tags":[
        "physician",
        "surgeon"
    ],
    "wof:name":"Indiana Hand Ctr",
    "wof:placetype":"venue"
},
  "geometry": {"coordinates":[-86.151742,40.454634],"type":"Point"}
}