{
  "type": "Feature",
  "properties": {
    "iso:country":"US",
    "sg:address":"6105 Southeastern Ave",
    "sg:city":"Indianapolis",
    "sg:classifiers":[
        {
            "category":"Freight",
            "type":"Transportation"
        }
    ],
    "sg:phone":"+1 317 357 2444",
    "sg:postcode":"46203",
    "sg:province":"IN",
    "sg:tags":[
        "commercial",
        "storage",
        "general"
    ],
    "wof:name":"Southeastern Self Storage",
    "wof:placetype":"venue"
},
  "geometry": {"coordinates":[-86.059147,39.732376],"type":"Point"}
}