{
  "type": "Feature",
  "properties": {
    "iso:country":"US",
    "sg:address":"1625 Tilden Ave",
    "sg:city":"Fort Wayne",
    "sg:classifiers":[
        {
            "category":"Building & Trades",
            "subcategory":"Construction",
            "type":"Services"
        }
    ],
    "sg:phone":"+1 260 420 3535",
    "sg:postcode":"46805",
    "sg:province":"IN",
    "sg:tags":[
        "plastering",
        "contractor"
    ],
    "wof:name":"Steve Helmuth Plastering",
    "wof:placetype":"venue"
},
  "geometry": {"coordinates":[-85.116913,41.088632],"type":"Point"}
}