{
  "type": "Feature",
  "properties": {
    "iso:country":"US",
    "sg:address":"4573 S Fagin St",
    "sg:city":"Terre Haute",
    "sg:classifiers":[
        {
            "category":"Retail",
            "subcategory":"Auto Repair",
            "type":"Services"
        }
    ],
    "sg:phone":"+1 812 299 0199",
    "sg:postcode":"47802",
    "sg:province":"IN",
    "sg:tags":[
        "body",
        "automobile",
        "painting"
    ],
    "wof:name":"Autoworks Body Shop",
    "wof:placetype":"venue"
},
  "geometry": {"coordinates":[-87.369191,39.411751],"type":"Point"}
}