{
  "type": "Feature",
  "properties": {
    "iso:country":"US",
    "sg:address":"4160 Woodland Streams Dr",
    "sg:city":"Greenwood",
    "sg:classifiers":[
        {
            "category":"Manufacturing",
            "subcategory":"Chemicals & Compounds",
            "type":"Manufacturing & Wholesale Goods"
        }
    ],
    "sg:phone":"+1 317 535 7177",
    "sg:postcode":"46143",
    "sg:province":"IN",
    "sg:tags":[
        "agricultural",
        "mfg"
    ],
    "wof:name":"Bill Bland",
    "wof:placetype":"venue"
},
  "geometry": {"coordinates":[-86.183172,39.566395],"type":"Point"}
}