{
  "type": "Feature",
  "properties": {
    "iso:country":"US",
    "sg:address":"2113 Yorktowne Dr",
    "sg:city":"Valparaiso",
    "sg:classifiers":[
        {
            "category":"Building & Trades",
            "subcategory":"Construction",
            "type":"Services"
        }
    ],
    "sg:phone":"+1 219 465 3122",
    "sg:postcode":"46383",
    "sg:province":"IN",
    "sg:tags":[
        "house"
    ],
    "wof:name":"Gibbs Construction Inc",
    "wof:placetype":"venue"
},
  "geometry": {"coordinates":[-87.03562,41.485041],"type":"Point"}
}