{
  "type": "Feature",
  "properties": {
    "iso:country":"US",
    "sg:address":"10596 Greenway Dr",
    "sg:city":"Fishers",
    "sg:classifiers":[
        {
            "category":"Wholesale",
            "subcategory":"Non-durable Goods",
            "type":"Manufacturing & Wholesale Goods"
        }
    ],
    "sg:phone":"+1 317 842 8161",
    "sg:postcode":"46037",
    "sg:province":"IN",
    "sg:tags":[
        "advertising"
    ],
    "wof:name":"Livtech Inc",
    "wof:placetype":"venue"
},
  "geometry": {"coordinates":[-85.983948,39.931916],"type":"Point"}
}