{
  "type": "Feature",
  "properties": {
    "iso:country":"US",
    "sg:address":"639 N 13th St",
    "sg:city":"Decatur",
    "sg:classifiers":[
        {
            "category":"Restaurant",
            "type":"Food & Drink"
        }
    ],
    "sg:menulink":"http://www.allmenus.com/in/decatur/208005-taco-bell/menu/",
    "sg:phone":"+1 260 724 4700",
    "sg:postcode":"46733",
    "sg:province":"IN",
    "sg:tags":[
        "mexican"
    ],
    "wof:name":"Taco Bell",
    "wof:placetype":"venue"
},
  "geometry": {"coordinates":[-84.937724,40.834574],"type":"Point"}
}