{
  "type": "Feature",
  "properties": {
    "iso:country":"US",
    "sg:address":"7074 Kiesler Rd",
    "sg:city":"Greenville",
    "sg:classifiers":[
        {
            "category":"Building & Trades",
            "subcategory":"Construction",
            "type":"Services"
        }
    ],
    "sg:phone":"+1 812 923 6296",
    "sg:postcode":"47124",
    "sg:province":"IN",
    "sg:tags":[
        "contractor"
    ],
    "wof:name":"Lawmakers Roofing Inc",
    "wof:placetype":"venue"
},
  "geometry": {"coordinates":[-86.014548,38.372827],"type":"Point"}
}