{
  "type": "Feature",
  "properties": {
    "iso:country":"US",
    "sg:address":"4719 Roosevelt St",
    "sg:city":"Gary",
    "sg:classifiers":[
        {
            "category":"Wholesale",
            "subcategory":"Machinery & Supplies",
            "type":"Manufacturing & Wholesale Goods"
        }
    ],
    "sg:phone":"+1 219 884 7963",
    "sg:postcode":"46408",
    "sg:province":"IN",
    "sg:tags":[
        "filter"
    ],
    "sg:website":"www.envirofiltration.com",
    "wof:name":"Enviro Filtration Inc",
    "wof:placetype":"venue"
},
  "geometry": {"coordinates":[-87.362775,41.53184],"type":"Point"}
}