{
  "type": "Feature",
  "properties": {
    "iso:country":"US",
    "sg:address":"1517 Avco Blvd",
    "sg:city":"Sellersburg",
    "sg:classifiers":[
        {
            "category":"Freight",
            "type":"Transportation"
        }
    ],
    "sg:phone":"+1 812 246 6306",
    "sg:postcode":"47172",
    "sg:province":"IN",
    "sg:tags":[
        "trucking"
    ],
    "wof:name":"National Distributors Inc",
    "wof:placetype":"venue"
},
  "geometry": {"coordinates":[-85.761639,38.371454],"type":"Point"}
}