{
  "type": "Feature",
  "properties": {
    "addr:full":"5500 S Hohman Ave Ste 2E Hammond IN 46320",
    "addr:housenumber":"5500",
    "addr:postcode":"46320",
    "addr:street":"S Hohman Ave Ste 2E",
    "iso:country":"US",
    "sg:address":"5500 S Hohman Ave Ste 2E",
    "sg:city":"Hammond",
    "sg:classifiers":[
        {
            "category":"Health Services",
            "subcategory":"Doctor",
            "type":"Services"
        }
    ],
    "sg:phone":"+1 219 933 6757",
    "sg:postcode":"46320",
    "sg:province":"IN",
    "wof:name":"Lee Oh J",
    "wof:placetype":"venue"
},
  "geometry": {"coordinates":[-87.522003,41.613899],"type":"Point"}
}