{
  "type": "Feature",
  "properties": {
    "iso:country":"US",
    "sg:address":"197 W Adams St",
    "sg:city":"Perrysville",
    "sg:classifiers":[
        {
            "category":"Organizations",
            "subcategory":"Community Association",
            "type":"Services"
        }
    ],
    "sg:phone":"+1 765 793 2563",
    "sg:postcode":"47974",
    "sg:province":"IN",
    "sg:tags":[
        "military"
    ],
    "wof:name":"American Legion",
    "wof:placetype":"venue"
},
  "geometry": {"coordinates":[-87.43338900000001,40.052247],"type":"Point"}
}