{
  "type": "Feature",
  "properties": {
    "iso:country":"US",
    "sg:address":"55 S Raceway Rd Ste 1000",
    "sg:city":"Indianapolis",
    "sg:classifiers":[
        {
            "category":"Personal",
            "subcategory":"Beauty Salon",
            "type":"Services"
        }
    ],
    "sg:phone":"+1 317 271 5500",
    "sg:postcode":"46231",
    "sg:province":"IN",
    "sg:tags":[
        "hair",
        "accessory",
        "supply"
    ],
    "wof:name":"Indy Laser",
    "wof:placetype":"venue"
},
  "geometry": {"coordinates":[-86.326854,39.763027],"type":"Point"}
}