{
  "type": "Feature",
  "properties": {
    "addr:full":"156 S Lombardy Dr South Bend IN 46619",
    "addr:housenumber":"156",
    "addr:postcode":"46619",
    "addr:street":"S Lombardy Dr",
    "iso:country":"US",
    "sg:address":"156 S Lombardy Dr",
    "sg:city":"South Bend",
    "sg:classifiers":[
        {
            "category":"Organizations",
            "subcategory":"Religious Organization",
            "type":"Services"
        }
    ],
    "sg:phone":"+1 574 233 9589",
    "sg:postcode":"46619",
    "sg:province":"IN",
    "sg:tags":[
        "church"
    ],
    "wof:name":"Southbend Seventh Day Advntst",
    "wof:placetype":"venue"
},
  "geometry": {"coordinates":[-86.31017199999999,41.672155],"type":"Point"}
}