{
  "type": "Feature",
  "properties": {
    "iso:country":"US",
    "sg:address":"518 Hoffman St",
    "sg:city":"Hammond",
    "sg:classifiers":[
        {
            "category":"Wholesale",
            "subcategory":"Construction Materials",
            "type":"Manufacturing & Wholesale Goods"
        }
    ],
    "sg:phone":"+1 219 932 5308",
    "sg:postcode":"46327",
    "sg:province":"IN",
    "sg:tags":[
        "pallet",
        "skid"
    ],
    "wof:name":"Geo C Meyer & Co",
    "wof:placetype":"venue"
},
  "geometry": {"coordinates":[-87.515857,41.626537],"type":"Point"}
}