{
  "type": "Feature",
  "properties": {
    "addr:full":"1415 Douglas Dr Carmel IN 46033",
    "addr:housenumber":"1415",
    "addr:postcode":"46033",
    "addr:street":"Douglas Dr",
    "iso:country":"US",
    "sg:address":"1415 Douglas Dr",
    "sg:city":"Carmel",
    "sg:classifiers":[
        {
            "category":"Organizations",
            "subcategory":"Religious Organization",
            "type":"Services"
        }
    ],
    "sg:phone":"+1 317 844 2321",
    "sg:postcode":"46033",
    "sg:province":"IN",
    "wof:name":"Randall J Worland Rev",
    "wof:placetype":"venue"
},
  "geometry": {"coordinates":[-86.102925,39.972284],"type":"Point"}
}