{
  "type": "Feature",
  "properties": {
    "addr:full":"53465 Ada Dr Elkhart IN 46514",
    "addr:housenumber":"53465",
    "addr:postcode":"46514",
    "addr:street":"Ada Dr",
    "iso:country":"US",
    "sg:address":"53465 Ada Dr",
    "sg:city":"Elkhart",
    "sg:classifiers":[
        {
            "category":"Manufacturing",
            "subcategory":"Printing",
            "type":"Manufacturing & Wholesale Goods"
        }
    ],
    "sg:phone":"+1 574 264 9695",
    "sg:postcode":"46514",
    "sg:province":"IN",
    "sg:tags":[
        "commercial"
    ],
    "sg:website":"www.kellmark.net",
    "wof:name":"Kellmark Corp",
    "wof:placetype":"venue"
},
  "geometry": {"coordinates":[-85.92287899999999,41.718426],"type":"Point"}
}