{
  "type": "Feature",
  "properties": {
    "iso:country":"US",
    "sg:address":"222 Pearl St",
    "sg:city":"New Albany",
    "sg:classifiers":[
        {
            "category":"Professional",
            "subcategory":"Business Services",
            "type":"Services"
        }
    ],
    "sg:phone":"+1 812 949 9200",
    "sg:postcode":"47150",
    "sg:province":"IN",
    "sg:tags":[
        "trade",
        "exposition",
        "fair",
        "show"
    ],
    "wof:name":"Sellers Exposition",
    "wof:placetype":"venue"
},
  "geometry": {"coordinates":[-85.822294,38.284683],"type":"Point"}
}