{
  "type": "Feature",
  "properties": {
    "iso:country":"US",
    "sg:address":"5995 US Hwy 6",
    "sg:city":"Portage",
    "sg:classifiers":[
        {
            "category":"Retail",
            "subcategory":"Photofinishing",
            "type":"Services"
        }
    ],
    "sg:phone":"+1 219 763 2341",
    "sg:postcode":"46368",
    "sg:province":"IN",
    "sg:tags":[
        "photo",
        "finishing"
    ],
    "wof:name":"Qualex Osp",
    "wof:placetype":"venue"
},
  "geometry": {"coordinates":[-87.182891,41.550406],"type":"Point"}
}