{
  "type": "Feature",
  "properties": {
    "addr:full":"1342 Tishman Ln Indianapolis IN 46260",
    "addr:housenumber":"1342",
    "addr:postcode":"46260",
    "addr:street":"Tishman Ln",
    "iso:country":"US",
    "sg:address":"1342 Tishman Ln",
    "sg:city":"Indianapolis",
    "sg:classifiers":[
        {
            "category":"Shopping",
            "type":"Retail Goods"
        },
        {
            "category":"Organizations",
            "subcategory":"Non-profit Organization",
            "type":"Services"
        }
    ],
    "sg:phone":"+1 317 445 8932",
    "sg:postcode":"46260",
    "sg:province":"IN",
    "sg:tags":[
        "supply",
        "fund",
        "games",
        "merchandise",
        "raising"
    ],
    "wof:name":"Brewer & Associates, Incorporated",
    "wof:placetype":"venue"
},
  "geometry": {"coordinates":[-86.182451,39.889611],"type":"Point"}
}