{
  "type": "Feature",
  "properties": {
    "addr:full":"425 Norfolk Rd Valparaiso IN 46385",
    "addr:housenumber":"425",
    "addr:postcode":"46385",
    "addr:street":"Norfolk Rd",
    "iso:country":"US",
    "sg:address":"425 Norfolk Rd",
    "sg:city":"Valparaiso",
    "sg:classifiers":[
        {
            "category":"Professional",
            "subcategory":"Accounting & Tax Preparation",
            "type":"Services"
        }
    ],
    "sg:phone":"+1 219 759 3256",
    "sg:postcode":"46385",
    "sg:province":"IN",
    "sg:tags":[
        "return"
    ],
    "wof:name":"Kathys Tax & Financial Svcs",
    "wof:placetype":"venue"
},
  "geometry": {"coordinates":[-87.14654299999999,41.524369],"type":"Point"}
}