{
  "type": "Feature",
  "properties": {
    "iso:country":"US",
    "sg:address":"930 Crown Ct",
    "sg:city":"Crown Point",
    "sg:classifiers":[
        {
            "category":"Restaurant",
            "type":"Food & Drink"
        }
    ],
    "sg:phone":"+1 219 663 6551",
    "sg:postcode":"46307",
    "sg:province":"IN",
    "sg:tags":[
        "pizza"
    ],
    "wof:name":"Carriage Court Pizza",
    "wof:placetype":"venue"
},
  "geometry": {"coordinates":[-87.353709,41.431278],"type":"Point"}
}