{
  "type": "Feature",
  "properties": {
    "iso:country":"US",
    "sg:address":"3035 N Shadeland Ave",
    "sg:city":"Indianapolis",
    "sg:classifiers":[
        {
            "category":"Manufacturing",
            "subcategory":"Metals",
            "type":"Manufacturing & Wholesale Goods"
        }
    ],
    "sg:phone":"+1 317 543 5980",
    "sg:postcode":"46226",
    "sg:province":"IN",
    "sg:tags":[
        "fabricated",
        "structural"
    ],
    "sg:website":"www.micrometl.com",
    "wof:name":"Micro Metal Corp",
    "wof:placetype":"venue"
},
  "geometry": {"coordinates":[-86.045686,39.815039],"type":"Point"}
}