{
  "type": "Feature",
  "properties": {
    "iso:country":"US",
    "sg:address":"5645 N Post Rd",
    "sg:city":"Indianapolis",
    "sg:classifiers":[
        {
            "category":"Insurance",
            "subcategory":"Insurance Agent",
            "type":"Services"
        },
        {
            "category":"Insurance",
            "subcategory":"Hazard Insurance",
            "type":"Services"
        },
        {
            "category":"Insurance",
            "subcategory":"Health Insurance",
            "type":"Services"
        }
    ],
    "sg:phone":"+1 317 591 0958",
    "sg:postcode":"46216",
    "sg:province":"IN",
    "sg:tags":[
        "auto",
        "commercial",
        "business",
        "flood"
    ],
    "sg:website":"http://www.vanessamarinleonard.com",
    "wof:name":"State Farm Insurance Vanessa Marin Leonard",
    "wof:placetype":"venue"
},
  "geometry": {"coordinates":[-86.010379,39.855624],"type":"Point"}
}