{
  "type": "Feature",
  "properties": {
    "iso:country":"US",
    "sg:address":"2528 State St",
    "sg:city":"Lafayette",
    "sg:classifiers":[
        {
            "category":"Mining & Drilling",
            "type":"Manufacturing & Wholesale Goods"
        }
    ],
    "sg:phone":"+1 765 742 7144",
    "sg:postcode":"47905",
    "sg:province":"IN",
    "sg:tags":[
        "construction"
    ],
    "wof:name":"Vulcan Materials Company",
    "wof:placetype":"venue"
},
  "geometry": {"coordinates":[-86.868464,40.400923],"type":"Point"}
}