{
  "type": "Feature",
  "properties": {
    "iso:country":"US",
    "sg:address":"120 Sylvan Dr",
    "sg:city":"Valparaiso",
    "sg:classifiers":[
        {
            "category":"Manufacturing",
            "subcategory":"Musical Instruments",
            "type":"Manufacturing & Wholesale Goods"
        }
    ],
    "sg:phone":"+1 219 464 3390",
    "sg:postcode":"46385",
    "sg:province":"IN",
    "sg:tags":[
        "mfg"
    ],
    "wof:name":"Stradella String Instruments",
    "wof:placetype":"venue"
},
  "geometry": {"coordinates":[-87.106432,41.453303],"type":"Point"}
}