{
  "type": "Feature",
  "properties": {
    "addr:full":"58418 Hilly Ln Elkhart IN 46517",
    "addr:postcode":"58418;46517",
    "addr:street":"Hilly Ln",
    "iso:country":"US",
    "sg:address":"58418 Hilly Ln",
    "sg:city":"Elkhart",
    "sg:classifiers":[
        {
            "category":"Retail",
            "subcategory":"Laundry & Dry Cleaning",
            "type":"Services"
        }
    ],
    "sg:phone":"+1 574 294 7357",
    "sg:postcode":"46517",
    "sg:province":"IN",
    "wof:name":"Freedom Carpet Cleaning",
    "wof:placetype":"venue"
},
  "geometry": {"coordinates":[-85.97017099999999,41.648149],"type":"Point"}
}