{
  "type": "Feature",
  "properties": {
    "iso:country":"US",
    "sg:address":"955 E Diamond Ave",
    "sg:city":"Evansville",
    "sg:classifiers":[
        {
            "category":"Manufacturing",
            "subcategory":"Rubber & Plastics",
            "type":"Manufacturing & Wholesale Goods"
        }
    ],
    "sg:phone":"+1 812 867 2447",
    "sg:postcode":"47711",
    "sg:province":"IN",
    "sg:tags":[
        "product",
        "mfg"
    ],
    "wof:name":"Wabash Plastics Inc",
    "wof:placetype":"venue"
},
  "geometry": {"coordinates":[-87.547504,37.999121],"type":"Point"}
}