{
  "type": "Feature",
  "properties": {
    "addr:full":"22111 Jackson Rd South Bend IN 46614",
    "addr:housenumber":"22111",
    "addr:postcode":"46614",
    "addr:street":"Jackson Rd",
    "iso:country":"US",
    "sg:address":"22111 Jackson Rd",
    "sg:city":"South Bend",
    "sg:classifiers":[
        {
            "category":"Building & Trades",
            "subcategory":"Construction",
            "type":"Services"
        }
    ],
    "sg:phone":"+1 574 291 2750",
    "sg:postcode":"46614",
    "sg:province":"IN",
    "sg:tags":[
        "water",
        "well",
        "drilling"
    ],
    "wof:name":"M L Fall Well Svc",
    "wof:placetype":"venue"
},
  "geometry": {"coordinates":[-86.286376,41.62145],"type":"Point"}
}