{
  "type": "Feature",
  "properties": {
    "iso:country":"US",
    "sg:address":"6091 W State Rd 18",
    "sg:city":"Brookston",
    "sg:phone":"+1 765 563 3342",
    "sg:postcode":"47923",
    "sg:province":"IN",
    "sg:tags":[
        "farm",
        "corn",
        "electric",
        "soybean",
        "mfg"
    ],
    "wof:name":"Dunbar Heating & Cooling",
    "wof:placetype":"venue"
},
  "geometry": {"coordinates":[-86.99236399999999,40.605797],"type":"Point"}
}