{
  "type": "Feature",
  "properties": {
    "addr:full":"1704 S Heaton St Knox IN 46534",
    "addr:housenumber":"1704",
    "addr:postcode":"46534",
    "addr:street":"S Heaton St",
    "iso:country":"US",
    "sg:address":"1704 S Heaton St",
    "sg:city":"Knox",
    "sg:classifiers":[
        {
            "category":"Restaurant",
            "type":"Food & Drink"
        }
    ],
    "sg:phone":"+1 574 772 4800",
    "sg:postcode":"46534",
    "sg:province":"IN",
    "wof:name":"Big Dipper Ice Cream Parlor",
    "wof:placetype":"venue"
},
  "geometry": {"coordinates":[-86.620726,41.281653],"type":"Point"}
}