{
  "type": "Feature",
  "properties": {
    "iso:country":"US",
    "sg:address":"107 S Broadway St",
    "sg:city":"Greensburg",
    "sg:classifiers":[
        {
            "category":"Professional",
            "subcategory":"Business Services",
            "type":"Services"
        }
    ],
    "sg:phone":"+1 812 663 0700",
    "sg:postcode":"47240",
    "sg:province":"IN",
    "sg:tags":[
        "appraiser"
    ],
    "wof:name":"Appraisal Research Corp",
    "wof:placetype":"venue"
},
  "geometry": {"coordinates":[-85.484288,39.33652],"type":"Point"}
}