{
  "type": "Feature",
  "properties": {
    "iso:country":"US",
    "sg:address":"401 N Foster Ave",
    "sg:city":"Albany",
    "sg:classifiers":[
        {
            "category":"Building & Trades",
            "subcategory":"Construction",
            "type":"Services"
        }
    ],
    "sg:phone":"+1 765 789 8950",
    "sg:postcode":"47320",
    "sg:province":"IN",
    "sg:tags":[
        "excavation",
        "contractor"
    ],
    "wof:name":"Lewis Backhoe & Dump Truck Svc",
    "wof:placetype":"venue"
},
  "geometry": {"coordinates":[-85.22917700000001,40.303474],"type":"Point"}
}