{
  "type": "Feature",
  "properties": {
    "iso:country":"US",
    "sg:address":"1 Broadway",
    "sg:city":"Gary",
    "sg:classifiers":[
        {
            "category":"Wholesale",
            "subcategory":"Machinery & Supplies",
            "type":"Manufacturing & Wholesale Goods"
        }
    ],
    "sg:phone":"+1 219 882 8090",
    "sg:postcode":"46407",
    "sg:province":"IN",
    "sg:tags":[
        "equipment",
        "safety",
        "clothing"
    ],
    "wof:name":"Hagemeyer Valen Safety",
    "wof:placetype":"venue"
},
  "geometry": {"coordinates":[-87.337207,41.608314],"type":"Point"}
}