{
  "type": "Feature",
  "properties": {
    "iso:country":"US",
    "sg:address":"601 E Race St",
    "sg:city":"Odon",
    "sg:classifiers":[
        {
            "category":"Organizations",
            "subcategory":"Non-profit Organization",
            "type":"Services"
        }
    ],
    "sg:phone":"+1 812 636 8232",
    "sg:postcode":"47562",
    "sg:province":"IN",
    "wof:name":"Ketcham Memorial Ctr",
    "wof:placetype":"venue"
},
  "geometry": {"coordinates":[-86.982866,38.841204],"type":"Point"}
}