{
  "type": "Feature",
  "properties": {
    "iso:country":"US",
    "sg:address":"10812 Coldwater Rd",
    "sg:city":"Fort Wayne",
    "sg:classifiers":[
        {
            "category":"Retail",
            "subcategory":"Animal Services",
            "type":"Services"
        }
    ],
    "sg:phone":"+1 260 637 9445",
    "sg:postcode":"46845",
    "sg:province":"IN",
    "sg:tags":[
        "pet",
        "grooming",
        "washing"
    ],
    "wof:name":"Joanna's Animal Grooming Salon",
    "wof:placetype":"venue"
},
  "geometry": {"coordinates":[-85.132182,41.181795],"type":"Point"}
}