{
  "type": "Feature",
  "properties": {
    "iso:country":"US",
    "sg:address":"525 E Center St",
    "sg:city":"Warsaw",
    "sg:classifiers":[
        {
            "category":"Real Estate",
            "subcategory":"Real Estate Agent",
            "type":"Services"
        }
    ],
    "sg:phone":"+1 574 267 2239",
    "sg:postcode":"46580",
    "sg:province":"IN",
    "sg:website":"www.lucasrealtorsgmac.com",
    "wof:name":"Lucas Realtors",
    "wof:placetype":"venue"
},
  "geometry": {"coordinates":[-85.851684,41.238147],"type":"Point"}
}