{
  "type": "Feature",
  "properties": {
    "addr:full":"8071 Hopkins Ln Indianapolis IN 46250",
    "addr:housenumber":"8071",
    "addr:postcode":"46250",
    "addr:street":"Hopkins Ln",
    "iso:country":"US",
    "sg:address":"8071 Hopkins Ln",
    "sg:city":"Indianapolis",
    "sg:classifiers":[
        {
            "category":"Health Services",
            "subcategory":"Health Practitioner",
            "type":"Services"
        }
    ],
    "sg:phone":"+1 317 205 9020",
    "sg:postcode":"46250",
    "sg:province":"IN",
    "sg:tags":[
        "therapist",
        "physical"
    ],
    "wof:name":"Julia L Moses",
    "wof:placetype":"venue"
},
  "geometry": {"coordinates":[-86.09484500000001,39.902637],"type":"Point"}
}