{
  "type": "Feature",
  "properties": {
    "iso:country":"US",
    "sg:address":"444 N Keystone Ave",
    "sg:city":"Indianapolis",
    "sg:classifiers":[
        {
            "category":"Retail",
            "subcategory":"Auto Repair",
            "type":"Services"
        }
    ],
    "sg:phone":"+1 317 637 0361",
    "sg:postcode":"46201",
    "sg:province":"IN",
    "sg:tags":[
        "repairing",
        "automobile"
    ],
    "wof:name":"Crystal Clear",
    "wof:placetype":"venue"
},
  "geometry": {"coordinates":[-86.12195199999999,39.773117],"type":"Point"}
}