{
  "type": "Feature",
  "properties": {
    "addr:full":"3540 State Rd 38 E Lafayette IN 47905",
    "addr:housenumber":"3540;38 e",
    "addr:postcode":"47905",
    "addr:street":"State Rd",
    "iso:country":"US",
    "sg:address":"3540 State Rd 38 E",
    "sg:city":"Lafayette",
    "sg:classifiers":[
        {
            "category":"Real Estate",
            "subcategory":"Real Estate Agent",
            "type":"Services"
        }
    ],
    "sg:phone":"+1 765 446 0461",
    "sg:postcode":"47905",
    "sg:province":"IN",
    "sg:tags":[
        "agency",
        "rental"
    ],
    "wof:name":"Rent Way",
    "wof:placetype":"venue"
},
  "geometry": {"coordinates":[-86.849093,40.394794],"type":"Point"}
}