{
  "type": "Feature",
  "properties": {
    "iso:country":"US",
    "sg:address":"749 Lincoln Hwy E",
    "sg:city":"New Haven",
    "sg:classifiers":[
        {
            "category":"Shopping",
            "type":"Retail Goods"
        }
    ],
    "sg:phone":"+1 260 493 2300",
    "sg:postcode":"46774",
    "sg:province":"IN",
    "sg:tags":[
        "monument"
    ],
    "wof:name":"Allen County's Tri State",
    "wof:placetype":"venue"
},
  "geometry": {"coordinates":[-85.018854,41.070239],"type":"Point"}
}