{
  "type": "Feature",
  "properties": {
    "addr:full":"530 E Broadway St Shelbyville IN 46176",
    "addr:housenumber":"530",
    "addr:postcode":"46176",
    "addr:street":"E Broadway St",
    "iso:country":"US",
    "sg:address":"530 E Broadway St",
    "sg:city":"Shelbyville",
    "sg:classifiers":[
        {
            "category":"Personal",
            "subcategory":"Beauty Salon",
            "type":"Services"
        }
    ],
    "sg:phone":"+1 317 398 9440",
    "sg:postcode":"46176",
    "sg:province":"IN",
    "wof:name":"Off Broadway Salon",
    "wof:placetype":"venue"
},
  "geometry": {"coordinates":[-85.76702299999999,39.522824],"type":"Point"}
}