{
  "type": "Feature",
  "properties": {
    "iso:country":"US",
    "sg:address":"6200 State Rd 62",
    "sg:city":"Jeffersonville",
    "sg:classifiers":[
        {
            "category":"Freight",
            "type":"Transportation"
        }
    ],
    "sg:phone":"+1 812 280 7795",
    "sg:postcode":"47130",
    "sg:province":"IN",
    "sg:tags":[
        "trucking"
    ],
    "wof:name":"W T Express",
    "wof:placetype":"venue"
},
  "geometry": {"coordinates":[-85.697898,38.366806],"type":"Point"}
}