{
  "type": "Feature",
  "properties": {
    "iso:country":"US",
    "sg:address":"8554 E Hendricks County Rd",
    "sg:city":"Mooresville",
    "sg:classifiers":[
        {
            "category":"Organizations",
            "subcategory":"Religious Organization",
            "type":"Services"
        }
    ],
    "sg:phone":"+1 317 831 1012",
    "sg:postcode":"46158",
    "sg:province":"IN",
    "sg:tags":[
        "church"
    ],
    "wof:name":"Eternal Life Baptist Church",
    "wof:placetype":"venue"
},
  "geometry": {"coordinates":[-86.366085,39.631063],"type":"Point"}
}