{
  "type": "Feature",
  "properties": {
    "addr:full":"2318 E State Rd 14 Rochester IN 46975",
    "addr:housenumber":"2318;14",
    "addr:postcode":"46975",
    "addr:street":"E State Rd",
    "iso:country":"US",
    "sg:address":"2318 E State Rd 14",
    "sg:city":"Rochester",
    "sg:classifiers":[
        {
            "category":"Freight",
            "type":"Transportation"
        }
    ],
    "sg:phone":"+1 574 224 3434",
    "sg:postcode":"46975",
    "sg:province":"IN",
    "sg:tags":[
        "commercial",
        "storage"
    ],
    "wof:name":"Airport Mini Storage-Rochester",
    "wof:placetype":"venue"
},
  "geometry": {"coordinates":[-86.18138500000001,41.06221],"type":"Point"}
}