{
  "type": "Feature",
  "properties": {
    "iso:country":"US",
    "sg:address":"205 E Rochester St",
    "sg:city":"Akron",
    "sg:classifiers":[
        {
            "category":"Education",
            "subcategory":"Library",
            "type":"Public Place"
        }
    ],
    "sg:phone":"+1 574 893 4113",
    "sg:postcode":"46910",
    "sg:province":"IN",
    "wof:name":"Akron Public Library",
    "wof:placetype":"venue"
},
  "geometry": {"coordinates":[-86.02720100000001,41.038625],"type":"Point"}
}