{
  "type": "Feature",
  "properties": {
    "iso:country":"US",
    "sg:address":"52241 Co Rd 7",
    "sg:city":"Elkhart",
    "sg:classifiers":[
        {
            "category":"Building & Trades",
            "subcategory":"Construction",
            "type":"Services"
        }
    ],
    "sg:phone":"+1 574 262 9295",
    "sg:postcode":"46514",
    "sg:province":"IN",
    "sg:tags":[
        "painter"
    ],
    "wof:name":"Haselrick & Cross Fine Pntng",
    "wof:placetype":"venue"
},
  "geometry": {"coordinates":[-85.988619,41.736075],"type":"Point"}
}