{
  "type": "Feature",
  "properties": {
    "iso:country":"US",
    "sg:address":"2405 US Hwy 30",
    "sg:city":"Valparaiso",
    "sg:classifiers":[
        {
            "category":"Restaurant",
            "type":"Food & Drink"
        }
    ],
    "sg:phone":"+1 219 462 5121",
    "sg:postcode":"46383",
    "sg:province":"IN",
    "sg:website":"www.strongbowinn.com",
    "wof:name":"Strongbow Inn",
    "wof:placetype":"venue"
},
  "geometry": {"coordinates":[-87.031576,41.45766],"type":"Point"}
}