{
  "type": "Feature",
  "properties": {
    "iso:country":"US",
    "sg:address":"3791 National Rd E",
    "sg:city":"Richmond",
    "sg:classifiers":[
        {
            "category":"Social Services",
            "type":"Services"
        }
    ],
    "sg:phone":"+1 765 966 4108",
    "sg:postcode":"47374",
    "sg:province":"IN",
    "sg:tags":[
        "organization",
        "welfare"
    ],
    "sg:website":"www.goodwill.com",
    "wof:name":"Goodwill Industries",
    "wof:placetype":"venue"
},
  "geometry": {"coordinates":[-84.847922,39.830979],"type":"Point"}
}