{
  "type": "Feature",
  "properties": {
    "iso:country":"US",
    "sg:address":"16612 Monroeville Rd",
    "sg:city":"Monroeville",
    "sg:classifiers":[
        {
            "category":"Organizations",
            "subcategory":"Religious Organization",
            "type":"Services"
        }
    ],
    "sg:phone":"+1 260 623 3273",
    "sg:postcode":"46773",
    "sg:province":"IN",
    "wof:name":"Foursquare Solution Inc",
    "wof:placetype":"venue"
},
  "geometry": {"coordinates":[-84.929312,40.978575],"type":"Point"}
}