{
  "type": "Feature",
  "properties": {
    "iso:country":"US",
    "sg:address":"229 Port Sylvia Dr",
    "sg:city":"Indianapolis",
    "sg:classifiers":[
        {
            "category":"Social Services",
            "subcategory":"Child Care",
            "type":"Services"
        }
    ],
    "sg:phone":"+1 317 241 4695",
    "sg:postcode":"46224",
    "sg:province":"IN",
    "wof:name":"Kay's Daycare",
    "wof:placetype":"venue"
},
  "geometry": {"coordinates":[-86.262119,39.770312],"type":"Point"}
}