{
  "type": "Feature",
  "properties": {
    "iso:country":"US",
    "sg:address":"3829 Harper Dr",
    "sg:city":"Lafayette",
    "sg:classifiers":[
        {
            "category":"Real Estate",
            "subcategory":"Real Estate Agent",
            "type":"Services"
        }
    ],
    "sg:phone":"+1 765 448 4663",
    "sg:postcode":"47905",
    "sg:province":"IN",
    "wof:name":"Kelly Real Estate & Auction",
    "wof:placetype":"venue"
},
  "geometry": {"coordinates":[-86.835315,40.406292],"type":"Point"}
}