{
  "type": "Feature",
  "properties": {
    "iso:country":"US",
    "sg:address":"13930 Royalwood Dr",
    "sg:city":"Fishers",
    "sg:classifiers":[
        {
            "category":"Building & Trades",
            "subcategory":"Construction",
            "type":"Services"
        }
    ],
    "sg:phone":"+1 317 598 9049",
    "sg:postcode":"46037",
    "sg:province":"IN",
    "sg:tags":[
        "home",
        "builder"
    ],
    "wof:name":"Centex Homes",
    "wof:placetype":"venue"
},
  "geometry": {"coordinates":[-85.916377,39.961749],"type":"Point"}
}