{
  "type": "Feature",
  "properties": {
    "addr:full":"3003 S Hackley St Muncie IN 47302",
    "addr:housenumber":"3003",
    "addr:postcode":"47302",
    "addr:street":"S Hackley St",
    "iso:country":"US",
    "sg:address":"3003 S Hackley St",
    "sg:city":"Muncie",
    "sg:classifiers":[
        {
            "category":"Manufacturing",
            "subcategory":"Electronics",
            "type":"Manufacturing & Wholesale Goods"
        }
    ],
    "sg:phone":"+1 765 284 3486",
    "sg:postcode":"47302",
    "sg:province":"IN",
    "sg:tags":[
        "equipment",
        "mfg",
        "communication"
    ],
    "wof:name":"Satellite Services",
    "wof:placetype":"venue"
},
  "geometry": {"coordinates":[-85.37724799999999,40.166265],"type":"Point"}
}