{
  "type": "Feature",
  "properties": {
    "iso:country":"US",
    "sg:address":"1396 Eastern Blvd",
    "sg:city":"Clarksville",
    "sg:classifiers":[
        {
            "category":"Retail",
            "subcategory":"Laundry & Dry Cleaning",
            "type":"Services"
        }
    ],
    "sg:phone":"+1 812 282 4263",
    "sg:postcode":"47129",
    "sg:province":"IN",
    "sg:tags":[
        "cleaners"
    ],
    "wof:name":"Clarksville Cleaners",
    "wof:placetype":"venue"
},
  "geometry": {"coordinates":[-85.76767700000001,38.306384],"type":"Point"}
}