{
  "type": "Feature",
  "properties": {
    "iso:country":"US",
    "sg:address":"1917 E 116th St",
    "sg:city":"Carmel",
    "sg:classifiers":[
        {
            "category":"Real Estate",
            "subcategory":"Real Estate Services",
            "type":"Services"
        }
    ],
    "sg:phone":"+1 317 581 1143",
    "sg:postcode":"46032",
    "sg:province":"IN",
    "sg:tags":[
        "management",
        "property"
    ],
    "wof:name":"Ind Society of Public Accountants",
    "wof:placetype":"venue"
},
  "geometry": {"coordinates":[-86.11979700000001,39.956799],"type":"Point"}
}