{
  "type": "Feature",
  "properties": {
    "iso:country":"US",
    "sg:address":"512 Randle St",
    "sg:city":"Valparaiso",
    "sg:classifiers":[
        {
            "category":"Personal",
            "type":"Services"
        }
    ],
    "sg:phone":"+1 219 465 7287",
    "sg:postcode":"46383",
    "sg:province":"IN",
    "sg:tags":[
        "therapist",
        "massage"
    ],
    "wof:name":"Balance A Therapeutic Touch",
    "wof:placetype":"venue"
},
  "geometry": {"coordinates":[-87.05515699999999,41.482169],"type":"Point"}
}