{
  "type": "Feature",
  "properties": {
    "iso:country":"US",
    "sg:address":"10136 S County Line Rd",
    "sg:city":"Clarks Hill",
    "sg:phone":"+1 765 523 2389",
    "sg:postcode":"47930",
    "sg:province":"IN",
    "sg:tags":[
        "farm",
        "corn",
        "soybean"
    ],
    "wof:name":"Gary Monjon",
    "wof:placetype":"venue"
},
  "geometry": {"coordinates":[-86.712114,40.214533],"type":"Point"}
}