{
  "type": "Feature",
  "properties": {
    "iso:country":"US",
    "sg:address":"301 N 25th St",
    "sg:city":"New Castle",
    "sg:classifiers":[
        {
            "category":"Retail",
            "subcategory":"Auto Repair",
            "type":"Services"
        }
    ],
    "sg:phone":"+1 765 521 0381",
    "sg:postcode":"47362",
    "sg:province":"IN",
    "sg:tags":[
        "repairing",
        "automobile"
    ],
    "wof:name":"WERT Auto Repair",
    "wof:placetype":"venue"
},
  "geometry": {"coordinates":[-85.354102,39.932663],"type":"Point"}
}