{
  "type": "Feature",
  "properties": {
    "addr:full":"4717 W Washington St Indianapolis IN 46241",
    "addr:housenumber":"4717",
    "addr:postcode":"46241",
    "addr:street":"W Washington St",
    "iso:country":"US",
    "sg:address":"4717 W Washington St",
    "sg:city":"Indianapolis",
    "sg:classifiers":[
        {
            "category":"Autos & Motor Vehicles",
            "subcategory":"Automobile Sales",
            "type":"Retail Goods"
        }
    ],
    "sg:phone":"+1 317 248 1604",
    "sg:postcode":"46241",
    "sg:province":"IN",
    "sg:tags":[
        "dealers-used",
        "car",
        "used",
        "cars-wholesale",
        "new"
    ],
    "wof:name":"Hoosier Car Truck Sales",
    "wof:placetype":"venue"
},
  "geometry": {"coordinates":[-86.240402,39.755852],"type":"Point"}
}