{
  "type": "Feature",
  "properties": {
    "addr:full":"7410 Bluffton Rd Fort Wayne IN 46809",
    "addr:housenumber":"7410",
    "addr:postcode":"46809",
    "addr:street":"Bluffton Rd",
    "iso:country":"US",
    "sg:address":"7410 Bluffton Rd",
    "sg:city":"Fort Wayne",
    "sg:classifiers":[
        {
            "category":"Insurance",
            "subcategory":"Insurance Agent",
            "type":"Services"
        }
    ],
    "sg:phone":"+1 260 747 5373",
    "sg:postcode":"46809",
    "sg:province":"IN",
    "wof:name":"Wise Insurance",
    "wof:placetype":"venue"
},
  "geometry": {"coordinates":[-85.169299,41.013965],"type":"Point"}
}