{
  "type": "Feature",
  "properties": {
    "iso:country":"US",
    "sg:address":"6445 W Washington St",
    "sg:city":"Indianapolis",
    "sg:classifiers":[
        {
            "category":"Shopping",
            "subcategory":"Used Merchandise",
            "type":"Retail Goods"
        }
    ],
    "sg:phone":"+1 317 244 0941",
    "sg:postcode":"46241",
    "sg:province":"IN",
    "sg:tags":[
        "flea",
        "market"
    ],
    "wof:name":"West Washington Flea Market",
    "wof:placetype":"venue"
},
  "geometry": {"coordinates":[-86.27290499999999,39.745829],"type":"Point"}
}