{
  "type": "Feature",
  "properties": {
    "addr:full":"218 N Harrison St Alexandria IN 46001",
    "addr:housenumber":"218",
    "addr:postcode":"46001",
    "addr:street":"N Harrison St",
    "iso:country":"US",
    "sg:address":"218 N Harrison St",
    "sg:city":"Alexandria",
    "sg:classifiers":[
        {
            "category":"Social Services",
            "subcategory":"Child Care",
            "type":"Services"
        }
    ],
    "sg:phone":"+1 765 724 2974",
    "sg:postcode":"46001",
    "sg:province":"IN",
    "sg:tags":[
        "kindergarten",
        "academic",
        "school"
    ],
    "wof:name":"Alexandria Christian Academy",
    "wof:placetype":"venue"
},
  "geometry": {"coordinates":[-85.67455200000001,40.264308],"type":"Point"}
}