{
  "type": "Feature",
  "properties": {
    "iso:country":"US",
    "sg:address":"907 N Oxford St",
    "sg:city":"Indianapolis",
    "sg:classifiers":[
        {
            "category":"Retail",
            "subcategory":"Auto Repair",
            "type":"Services"
        }
    ],
    "sg:phone":"+1 317 917 1871",
    "sg:postcode":"46201",
    "sg:province":"IN",
    "sg:tags":[
        "repairing",
        "automobile"
    ],
    "wof:name":"Tez Car Care & Wash",
    "wof:placetype":"venue"
},
  "geometry": {"coordinates":[-86.115349,39.777471],"type":"Point"}
}