{
  "type": "Feature",
  "properties": {
    "iso:country":"US",
    "sg:address":"2016 S 22nd St",
    "sg:city":"Lafayette",
    "sg:classifiers":[
        {
            "category":"Education",
            "subcategory":"School",
            "type":"Public Place"
        }
    ],
    "sg:phone":"+1 765 772 4735",
    "sg:postcode":"47905",
    "sg:province":"IN",
    "wof:name":"Lafayette School Corp Altrntv",
    "wof:placetype":"venue"
},
  "geometry": {"coordinates":[-86.871781,40.397858],"type":"Point"}
}