{
  "type": "Feature",
  "properties": {
    "iso:country":"US",
    "sg:address":"3832 E 38th St",
    "sg:city":"Indianapolis",
    "sg:classifiers":[
        {
            "category":"Personal",
            "subcategory":"Beauty Salon",
            "type":"Services"
        }
    ],
    "sg:phone":"+1 317 377 1370",
    "sg:postcode":"46218",
    "sg:province":"IN",
    "wof:name":"Elegance Braiding",
    "wof:placetype":"venue"
},
  "geometry": {"coordinates":[-86.101761,39.825418],"type":"Point"}
}