{
  "type": "Feature",
  "properties": {
    "iso:country":"US",
    "sg:address":"11961 S State Rd 42",
    "sg:city":"Cloverdale",
    "sg:classifiers":[
        {
            "category":"Organizations",
            "subcategory":"Religious Organization",
            "type":"Services"
        }
    ],
    "sg:phone":"+1 765 795 3373",
    "sg:postcode":"46120",
    "sg:province":"IN",
    "sg:tags":[
        "church"
    ],
    "wof:name":"Cloverdale Christian Church",
    "wof:placetype":"venue"
},
  "geometry": {"coordinates":[-86.803022,39.486385],"type":"Point"}
}