{
  "type": "Feature",
  "properties": {
    "iso:country":"US",
    "sg:address":"2010 E US Hwy 20",
    "sg:city":"Michigan City",
    "sg:classifiers":[
        {
            "category":"Shopping",
            "subcategory":"Bicycles & Sporting Goods",
            "type":"Retail Goods"
        }
    ],
    "sg:phone":"+1 219 872 9191",
    "sg:postcode":"46360",
    "sg:province":"IN",
    "wof:name":"Mike's Sporting Goods Inc",
    "wof:placetype":"venue"
},
  "geometry": {"coordinates":[-86.851856,41.687457],"type":"Point"}
}