{
  "type": "Feature",
  "properties": {
    "iso:country":"US",
    "sg:address":"136 E Washington St",
    "sg:city":"Shelbyville",
    "sg:classifiers":[
        {
            "category":"Organizations",
            "subcategory":"Religious Organization",
            "type":"Services"
        }
    ],
    "sg:phone":"+1 317 398 7421",
    "sg:postcode":"46176",
    "sg:province":"IN",
    "sg:tags":[
        "church"
    ],
    "wof:name":"Salvation Army",
    "wof:placetype":"venue"
},
  "geometry": {"coordinates":[-85.77274199999999,39.524432],"type":"Point"}
}