{
  "type": "Feature",
  "properties": {
    "iso:country":"US",
    "sg:address":"3025 State Rd 9",
    "sg:city":"Anderson",
    "sg:classifiers":[
        {
            "category":"Autos & Motor Vehicles",
            "subcategory":"Automobile Sales",
            "type":"Retail Goods"
        }
    ],
    "sg:phone":"+1 765 649 3333",
    "sg:postcode":"46012",
    "sg:province":"IN",
    "sg:tags":[
        "car",
        "dealer"
    ],
    "sg:website":"www.paytonwells.com",
    "wof:name":"Payton Wells Preowned Ctr",
    "wof:placetype":"venue"
},
  "geometry": {"coordinates":[-85.671946,40.151767],"type":"Point"}
}