{
  "type": "Feature",
  "properties": {
    "iso:country":"US",
    "sg:address":"8037 S Meridian St",
    "sg:city":"Indianapolis",
    "sg:classifiers":[
        {
            "category":"Retail",
            "subcategory":"Self-service Laundry",
            "type":"Services"
        }
    ],
    "sg:phone":"+1 317 887 9828",
    "sg:postcode":"46217",
    "sg:province":"IN",
    "wof:name":"Laundry & Tan Express",
    "wof:placetype":"venue"
},
  "geometry": {"coordinates":[-86.158336,39.648949],"type":"Point"}
}