{
  "type": "Feature",
  "properties": {
    "iso:country":"US",
    "sg:address":"425 State St",
    "sg:city":"New Albany",
    "sg:classifiers":[
        {
            "category":"Shopping",
            "subcategory":"Used Merchandise",
            "type":"Retail Goods"
        }
    ],
    "sg:phone":"+1 812 949 5232",
    "sg:postcode":"47150",
    "sg:province":"IN",
    "sg:tags":[
        "antique"
    ],
    "wof:name":"Debbie's Yesterday & Tomorrow",
    "wof:placetype":"venue"
},
  "geometry": {"coordinates":[-85.824607,38.286489],"type":"Point"}
}