{
  "type": "Feature",
  "properties": {
    "addr:full":"3100 S Hill Rd Mitchell IN 47421",
    "addr:housenumber":"3100",
    "addr:postcode":"47421",
    "addr:street":"S Hill Rd",
    "iso:country":"US",
    "sg:address":"3100 S Hill Rd",
    "sg:city":"Mitchell",
    "sg:classifiers":[
        {
            "category":"Autos & Motor Vehicles",
            "subcategory":"Auto Supplies",
            "type":"Retail Goods"
        }
    ],
    "sg:phone":"+1 812 849 6431",
    "sg:postcode":"47421",
    "sg:province":"IN",
    "sg:tags":[
        "tire"
    ],
    "wof:name":"Tieman Tire Co",
    "wof:placetype":"venue"
},
  "geometry": {"coordinates":[-86.547843,38.868549],"type":"Point"}
}