{
  "type": "Feature",
  "properties": {
    "iso:country":"US",
    "sg:address":"1581 Churchill Rd",
    "sg:city":"Franklin",
    "sg:classifiers":[
        {
            "category":"Organizations",
            "subcategory":"Religious Organization",
            "type":"Services"
        }
    ],
    "sg:phone":"+1 317 736 9208",
    "sg:postcode":"46131",
    "sg:province":"IN",
    "sg:tags":[
        "clergy"
    ],
    "wof:name":"John G Williams",
    "wof:placetype":"venue"
},
  "geometry": {"coordinates":[-86.060724,39.49467],"type":"Point"}
}