{
  "type": "Feature",
  "properties": {
    "iso:country":"US",
    "sg:address":"4972 Co Rd 56",
    "sg:city":"Auburn",
    "sg:classifiers":[
        {
            "category":"Recreation",
            "type":"Entertainment"
        }
    ],
    "sg:phone":"+1 260 482 8891",
    "sg:postcode":"46706",
    "sg:province":"IN",
    "sg:tags":[
        "aquarium"
    ],
    "wof:name":"Sea Dwellers",
    "wof:placetype":"venue"
},
  "geometry": {"coordinates":[-84.957533,41.325721],"type":"Point"}
}