{
  "type": "Feature",
  "properties": {
    "iso:country":"US",
    "sg:address":"7847 Calumet Ave",
    "sg:city":"Munster",
    "sg:classifiers":[
        {
            "category":"Health Services",
            "subcategory":"Doctor",
            "type":"Services"
        }
    ],
    "sg:phone":"+1 219 836 5102",
    "sg:postcode":"46321",
    "sg:province":"IN",
    "sg:tags":[
        "clinic"
    ],
    "wof:name":"Calumet Surgery Ctr",
    "wof:placetype":"venue"
},
  "geometry": {"coordinates":[-87.508961,41.571414],"type":"Point"}
}