{
  "type": "Feature",
  "properties": {
    "iso:country":"US",
    "sg:address":"4321 Fir St",
    "sg:city":"East Chicago",
    "sg:classifiers":[
        {
            "category":"Education",
            "subcategory":"Library",
            "type":"Public Place"
        }
    ],
    "sg:phone":"+1 219 392 7230",
    "sg:postcode":"46312",
    "sg:province":"IN",
    "sg:tags":[
        "special",
        "interest"
    ],
    "wof:name":"Mcguire Memorial Library",
    "wof:placetype":"venue"
},
  "geometry": {"coordinates":[-87.448752,41.633905],"type":"Point"}
}