{
  "type": "Feature",
  "properties": {
    "iso:country":"US",
    "sg:address":"614 W 11th St",
    "sg:city":"Winamac",
    "sg:classifiers":[
        {
            "category":"Government",
            "subcategory":"Office",
            "type":"Public Place"
        }
    ],
    "sg:phone":"+1 574 946 3312",
    "sg:postcode":"46996",
    "sg:province":"IN",
    "wof:name":"Pulaski County Family & Child",
    "wof:placetype":"venue"
},
  "geometry": {"coordinates":[-86.610683,41.055316],"type":"Point"}
}