{
  "type": "Feature",
  "properties": {
    "iso:country":"US",
    "sg:address":"1502 Willow St",
    "sg:city":"Vincennes",
    "sg:classifiers":[
        {
            "category":"Food & Beverages",
            "subcategory":"Liquor & Beverages",
            "type":"Retail Goods"
        }
    ],
    "sg:phone":"+1 812 882 7081",
    "sg:postcode":"47591",
    "sg:province":"IN",
    "wof:name":"PAR T Pac",
    "wof:placetype":"venue"
},
  "geometry": {"coordinates":[-87.5325,38.661881],"type":"Point"}
}