{
  "type": "Feature",
  "properties": {
    "iso:country":"US",
    "sg:address":"1271 N Finlandia Way",
    "sg:city":"Albion",
    "sg:classifiers":[
        {
            "category":"Manufacturing",
            "subcategory":"Buildings",
            "type":"Manufacturing & Wholesale Goods"
        }
    ],
    "sg:phone":"+1 260 636 7180",
    "sg:postcode":"46701",
    "sg:province":"IN",
    "sg:tags":[
        "home",
        "log",
        "cabin"
    ],
    "wof:name":"Winebrenner Real Log Homes",
    "wof:placetype":"venue"
},
  "geometry": {"coordinates":[-85.491546,41.371513],"type":"Point"}
}