{
  "type": "Feature",
  "properties": {
    "iso:country":"US",
    "sg:address":"15 W Vincennes St",
    "sg:city":"Linton",
    "sg:classifiers":[
        {
            "category":"Organizations",
            "subcategory":"Religious Organization",
            "type":"Services"
        }
    ],
    "sg:phone":"+1 812 847 7704",
    "sg:postcode":"47441",
    "sg:province":"IN",
    "sg:tags":[
        "church"
    ],
    "wof:name":"New Jerusalem Christian Ctr",
    "wof:placetype":"venue"
},
  "geometry": {"coordinates":[-87.166257,39.034],"type":"Point"}
}