{
  "type": "Feature",
  "properties": {
    "addr:full":"811 Crown Ct Crown Point IN 46307",
    "addr:housenumber":"811",
    "addr:postcode":"46307",
    "addr:street":"Crown Ct",
    "iso:country":"US",
    "sg:address":"811 Crown Ct",
    "sg:city":"Crown Point",
    "sg:classifiers":[
        {
            "category":"Retail",
            "subcategory":"Funeral Services",
            "type":"Services"
        }
    ],
    "sg:phone":"+1 219 663 4302",
    "sg:postcode":"46307",
    "sg:province":"IN",
    "sg:tags":[
        "director"
    ],
    "wof:name":"Pruzin & Little Funeral Svc",
    "wof:placetype":"venue"
},
  "geometry": {"coordinates":[-87.352531,41.431124],"type":"Point"}
}