{
  "type": "Feature",
  "properties": {
    "iso:country":"US",
    "sg:address":"1701 Library Blvd",
    "sg:city":"Greenwood",
    "sg:classifiers":[
        {
            "category":"Health Services",
            "subcategory":"Health Practitioner",
            "type":"Services"
        }
    ],
    "sg:phone":"+1 317 889 5612",
    "sg:postcode":"46142",
    "sg:province":"IN",
    "sg:tags":[
        "psychologist"
    ],
    "wof:name":"Russ A Rasmussen",
    "wof:placetype":"venue"
},
  "geometry": {"coordinates":[-86.15752999999999,39.60773],"type":"Point"}
}