{
  "type": "Feature",
  "properties": {
    "iso:country":"US",
    "sg:address":"187 E Cherry St",
    "sg:city":"Scottsburg",
    "sg:classifiers":[
        {
            "category":"Home & Garden",
            "subcategory":"Furniture",
            "type":"Retail Goods"
        }
    ],
    "sg:phone":"+1 812 752 0850",
    "sg:postcode":"47170",
    "sg:province":"IN",
    "wof:name":"Amick Appliance & Furniture",
    "wof:placetype":"venue"
},
  "geometry": {"coordinates":[-85.768068,38.684007],"type":"Point"}
}