{
  "type": "Feature",
  "properties": {
    "iso:country":"US",
    "sg:address":"109 E Chestnut St",
    "sg:city":"Corydon",
    "sg:classifiers":[
        {
            "category":"Autos & Motor Vehicles",
            "subcategory":"Auto Supplies",
            "type":"Retail Goods"
        }
    ],
    "sg:phone":"+1 812 738 8296",
    "sg:postcode":"47112",
    "sg:province":"IN",
    "sg:tags":[
        "automobile",
        "parts"
    ],
    "wof:name":"Southern Indiana Automotive",
    "wof:placetype":"venue"
},
  "geometry": {"coordinates":[-86.126272,38.21049],"type":"Point"}
}