{
  "type": "Feature",
  "properties": {
    "iso:country":"US",
    "sg:address":"1003 W Mill St",
    "sg:city":"Middletown",
    "sg:classifiers":[
        {
            "category":"Autos & Motor Vehicles",
            "subcategory":"Fuel & Gas Station",
            "type":"Retail Goods"
        }
    ],
    "sg:phone":"+1 765 354 4388",
    "sg:postcode":"47356",
    "sg:province":"IN",
    "sg:tags":[
        "oil"
    ],
    "wof:name":"Phil's Phillips 66",
    "wof:placetype":"venue"
},
  "geometry": {"coordinates":[-85.542153,40.062334],"type":"Point"}
}