{
  "type": "Feature",
  "properties": {
    "addr:full":"1547 N 400 E Winchester IN 47394",
    "addr:housenumber":"1547",
    "addr:postcode":"47394",
    "addr:street":"N 400 E",
    "iso:country":"US",
    "sg:address":"1547 N 400 E",
    "sg:city":"Winchester",
    "sg:classifiers":[
        {
            "category":"Real Estate",
            "subcategory":"Real Estate Operator",
            "type":"Services"
        }
    ],
    "sg:phone":"+1 765 584 2001",
    "sg:postcode":"47394",
    "sg:province":"IN",
    "sg:tags":[
        "property",
        "lessor"
    ],
    "wof:name":"David Carpenter",
    "wof:placetype":"venue"
},
  "geometry": {"coordinates":[-84.90038300000001,40.188465],"type":"Point"}
}