{
  "type": "Feature",
  "properties": {
    "iso:country":"US",
    "sg:address":"1650 Ohio Ave",
    "sg:city":"Anderson",
    "sg:classifiers":[
        {
            "category":"Personal",
            "subcategory":"Beauty Salon",
            "type":"Services"
        }
    ],
    "sg:phone":"+1 765 649 3212",
    "sg:postcode":"46016",
    "sg:province":"IN",
    "sg:tags":[
        "cosmetologist"
    ],
    "wof:name":"Stacey L Vaughn",
    "wof:placetype":"venue"
},
  "geometry": {"coordinates":[-85.668731,40.099815],"type":"Point"}
}