{
  "type": "Feature",
  "properties": {
    "addr:full":"1846 Holloway Ave Indianapolis IN 46218",
    "addr:housenumber":"1846",
    "addr:postcode":"46218",
    "addr:street":"Holloway Ave",
    "iso:country":"US",
    "sg:address":"1846 Holloway Ave",
    "sg:city":"Indianapolis",
    "sg:classifiers":[
        {
            "category":"Social Services",
            "subcategory":"Child Care",
            "type":"Services"
        }
    ],
    "sg:phone":"+1 317 634 0477",
    "sg:postcode":"46218",
    "sg:province":"IN",
    "wof:name":"Davis Daycare",
    "wof:placetype":"venue"
},
  "geometry": {"coordinates":[-86.128024,39.792011],"type":"Point"}
}