{
  "type": "Feature",
  "properties": {
    "iso:country":"US",
    "sg:address":"2951 W Avon Ave",
    "sg:city":"Marion",
    "sg:classifiers":[
        {
            "category":"Professional",
            "subcategory":"Accounting & Tax Preparation",
            "type":"Services"
        }
    ],
    "sg:phone":"+1 765 662 3521",
    "sg:postcode":"46953",
    "sg:province":"IN",
    "sg:tags":[
        "bookkeeping",
        "general"
    ],
    "wof:name":"Rainbow Bookkeeping System",
    "wof:placetype":"venue"
},
  "geometry": {"coordinates":[-85.716235,40.539047],"type":"Point"}
}