{
  "type": "Feature",
  "properties": {
    "addr:full":"5219 E 500 N Leesburg IN 46538",
    "addr:housenumber":"5219",
    "addr:postcode":"46538",
    "addr:street":"E 500 N",
    "iso:country":"US",
    "sg:address":"5219 E 500 N",
    "sg:city":"Leesburg",
    "sg:classifiers":[
        {
            "category":"Real Estate",
            "subcategory":"Real Estate Operator",
            "type":"Services"
        }
    ],
    "sg:phone":"+1 574 834 7060",
    "sg:postcode":"46538",
    "sg:province":"IN",
    "sg:tags":[
        "mobile",
        "home",
        "community"
    ],
    "wof:name":"Lakeview Mobile Home Park",
    "wof:placetype":"venue"
},
  "geometry": {"coordinates":[-85.745097,41.308008],"type":"Point"}
}