{
  "type": "Feature",
  "properties": {
    "addr:full":"1408 Arles Dr Noblesville IN 46060",
    "addr:housenumber":"1408",
    "addr:postcode":"46060",
    "addr:street":"Arles Dr",
    "iso:country":"US",
    "sg:address":"1408 Arles Dr",
    "sg:city":"Noblesville",
    "sg:classifiers":[
        {
            "category":"Real Estate",
            "subcategory":"Real Estate Operator",
            "type":"Services"
        }
    ],
    "sg:phone":"+1 317 776 0166",
    "sg:postcode":"46060",
    "sg:province":"IN",
    "sg:tags":[
        "building",
        "nonresidential"
    ],
    "wof:name":"Five Star Properties LLC",
    "wof:placetype":"venue"
},
  "geometry": {"coordinates":[-86.006846,40.063124],"type":"Point"}
}