{
  "type": "Feature",
  "properties": {
    "addr:full":"55 Pawling St Wabash IN 46992",
    "addr:housenumber":"55",
    "addr:postcode":"46992",
    "addr:street":"Pawling St",
    "iso:country":"US",
    "sg:address":"55 Pawling St",
    "sg:city":"Wabash",
    "sg:classifiers":[
        {
            "category":"Home & Garden",
            "subcategory":"Building Materials",
            "type":"Retail Goods"
        },
        {
            "category":"Wholesale",
            "subcategory":"Home Furnishings",
            "type":"Manufacturing & Wholesale Goods"
        }
    ],
    "sg:phone":"+1 260 563 8670",
    "sg:postcode":"46992",
    "sg:province":"IN",
    "sg:tags":[
        "wallpaper",
        "drapery",
        "business"
    ],
    "wof:name":"Rhoades Window Shop",
    "wof:placetype":"venue"
},
  "geometry": {"coordinates":[-85.82270800000001,40.803178],"type":"Point"}
}