{
  "type": "Feature",
  "properties": {
    "iso:country":"US",
    "sg:address":"1929 Hwy 337 NW",
    "sg:city":"Corydon",
    "sg:classifiers":[
        {
            "category":"Insurance",
            "subcategory":"Insurance Agent",
            "type":"Services"
        }
    ],
    "sg:phone":"+1 812 738 3276",
    "sg:postcode":"47112",
    "sg:province":"IN",
    "wof:name":"Farmers Insurance Group",
    "wof:placetype":"venue"
},
  "geometry": {"coordinates":[-86.137112,38.23011],"type":"Point"}
}