{
  "type": "Feature",
  "properties": {
    "iso:country":"US",
    "sg:address":"4401 S Delaware Dr",
    "sg:city":"Muncie",
    "sg:classifiers":[
        {
            "category":"Retail",
            "subcategory":"Repair Shop",
            "type":"Services"
        }
    ],
    "sg:phone":"+1 765 741 2760",
    "sg:postcode":"47302",
    "sg:province":"IN",
    "sg:tags":[
        "welding"
    ],
    "wof:name":"Diamond Welding",
    "wof:placetype":"venue"
},
  "geometry": {"coordinates":[-85.421237,40.153926],"type":"Point"}
}