{
  "type": "Feature",
  "properties": {
    "iso:country":"US",
    "sg:address":"3425 Hobson Rd",
    "sg:city":"Fort Wayne",
    "sg:classifiers":[
        {
            "category":"Banks & Credit Unions",
            "subcategory":"Bank",
            "type":"Services"
        }
    ],
    "sg:phone":"+1 260 471 8198",
    "sg:postcode":"46805",
    "sg:province":"IN",
    "wof:name":"Indiana Postal & Federal Cu",
    "wof:placetype":"venue"
},
  "geometry": {"coordinates":[-85.099397,41.108859],"type":"Point"}
}