{
  "type": "Feature",
  "properties": {
    "iso:country":"US",
    "sg:address":"13720 Main St",
    "sg:city":"Grabill",
    "sg:classifiers":[
        {
            "category":"Manufacturing",
            "subcategory":"Printing",
            "type":"Manufacturing & Wholesale Goods"
        }
    ],
    "sg:phone":"+1 260 627 2728",
    "sg:postcode":"46741",
    "sg:province":"IN",
    "sg:tags":[
        "commercial"
    ],
    "wof:name":"Courier Printing Co-Allen Cnty",
    "wof:placetype":"venue"
},
  "geometry": {"coordinates":[-84.965829,41.212731],"type":"Point"}
}