{
  "type": "Feature",
  "properties": {
    "iso:country":"US",
    "sg:address":"11420 Middle Mount Vernon Rd",
    "sg:city":"Evansville",
    "sg:classifiers":[
        {
            "category":"Organizations",
            "subcategory":"Religious Organization",
            "type":"Services"
        }
    ],
    "sg:phone":"+1 812 985 5288",
    "sg:postcode":"47712",
    "sg:province":"IN",
    "sg:tags":[
        "church"
    ],
    "sg:website":"www.nbcfcampus.org",
    "wof:name":"New Beginnings Christian",
    "wof:placetype":"venue"
},
  "geometry": {"coordinates":[-87.709703,37.967588],"type":"Point"}
}