{
  "type": "Feature",
  "properties": {
    "addr:full":"1829 S Curry Pike Bloomington IN 47403",
    "addr:housenumber":"1829",
    "addr:postcode":"47403",
    "addr:street":"S Curry Pike",
    "iso:country":"US",
    "sg:address":"1829 S Curry Pike",
    "sg:city":"Bloomington",
    "sg:classifiers":[
        {
            "category":"Utilities",
            "subcategory":"Natural Gas",
            "type":"Services"
        }
    ],
    "sg:phone":"+1 812 336 3931",
    "sg:postcode":"47403",
    "sg:province":"IN",
    "sg:tags":[
        "transmission",
        "distribution"
    ],
    "wof:name":"Ameri Gas Inc",
    "wof:placetype":"venue"
},
  "geometry": {"coordinates":[-86.58255200000001,39.150471],"type":"Point"}
}