{
  "type": "Feature",
  "properties": {
    "addr:full":"2304 Lincolnway E Goshen IN 46526",
    "addr:housenumber":"2304;e",
    "addr:postcode":"46526",
    "addr:street":"Lincolnway",
    "iso:country":"US",
    "sg:address":"2304 Lincolnway E",
    "sg:city":"Goshen",
    "sg:classifiers":[
        {
            "category":"Personal",
            "subcategory":"Beauty Salon",
            "type":"Services"
        }
    ],
    "sg:phone":"+1 574 534 7865",
    "sg:postcode":"46526",
    "sg:province":"IN",
    "sg:tags":[
        "manicuring"
    ],
    "wof:name":"Regal Nails",
    "wof:placetype":"venue"
},
  "geometry": {"coordinates":[-85.797659,41.562169],"type":"Point"}
}