{
  "type": "Feature",
  "properties": {
    "addr:full":"4207 Lake Ave Fort Wayne IN 46815",
    "addr:housenumber":"4207",
    "addr:postcode":"46815",
    "addr:street":"Lake Ave",
    "iso:country":"US",
    "sg:address":"4207 Lake Ave",
    "sg:city":"Fort Wayne",
    "sg:classifiers":[
        {
            "category":"Health Services",
            "subcategory":"Doctor",
            "type":"Services"
        }
    ],
    "sg:phone":"+1 260 424 3007",
    "sg:postcode":"46815",
    "sg:province":"IN",
    "sg:tags":[
        "dentist"
    ],
    "wof:name":"Denture Clinic",
    "wof:placetype":"venue"
},
  "geometry": {"coordinates":[-85.087293,41.090589],"type":"Point"}
}