{
  "type": "Feature",
  "properties": {
    "iso:country":"US",
    "sg:address":"53163 Sylvan Ct",
    "sg:city":"Bristol",
    "sg:classifiers":[
        {
            "category":"Health Services",
            "subcategory":"Doctor",
            "type":"Services"
        }
    ],
    "sg:phone":"+1 574 848 1229",
    "sg:postcode":"46507",
    "sg:province":"IN",
    "sg:tags":[
        "medical"
    ],
    "wof:name":"Jeffery A Mark P C",
    "wof:placetype":"venue"
},
  "geometry": {"coordinates":[-85.879671,41.722041],"type":"Point"}
}