{
  "type": "Feature",
  "properties": {
    "iso:country":"US",
    "sg:address":"800 Adams St",
    "sg:city":"Decatur",
    "sg:classifiers":[
        {
            "category":"Freight",
            "type":"Transportation"
        }
    ],
    "sg:phone":"+1 260 728 9789",
    "sg:postcode":"46733",
    "sg:province":"IN",
    "sg:tags":[
        "warehouse",
        "self",
        "storage"
    ],
    "wof:name":"Continental Lumber",
    "wof:placetype":"venue"
},
  "geometry": {"coordinates":[-84.931587,40.826606],"type":"Point"}
}