{
  "type": "Feature",
  "properties": {
    "iso:country":"US",
    "sg:address":"320 W 8th St",
    "sg:city":"Bloomington",
    "sg:classifiers":[
        {
            "category":"Social Services",
            "type":"Services"
        }
    ],
    "sg:phone":"+1 812 336 7814",
    "sg:postcode":"47404",
    "sg:province":"IN",
    "sg:tags":[
        "organization",
        "welfare"
    ],
    "sg:website":"www.lifeserviceseap.com",
    "wof:name":"Lifeservices Eap",
    "wof:placetype":"venue"
},
  "geometry": {"coordinates":[-86.537464,39.169606],"type":"Point"}
}