{
  "type": "Feature",
  "properties": {
    "iso:country":"US",
    "sg:address":"414 W High St",
    "sg:city":"Elkhart",
    "sg:classifiers":[
        {
            "category":"Professional",
            "subcategory":"Lawyer & Legal Services",
            "type":"Services"
        }
    ],
    "sg:phone":"+1 574 293 2014",
    "sg:postcode":"46516",
    "sg:province":"IN",
    "sg:tags":[
        "attorney"
    ],
    "wof:name":"Gordon G Mac Kenzie",
    "wof:placetype":"venue"
},
  "geometry": {"coordinates":[-85.97731,41.683959],"type":"Point"}
}