{
  "type": "Feature",
  "properties": {
    "iso:country":"US",
    "sg:address":"9000 Keystone Xing",
    "sg:city":"Nora",
    "sg:classifiers":[
        {
            "category":"Professional",
            "subcategory":"Lawyer & Legal Services",
            "type":"Services"
        }
    ],
    "sg:phone":"+1 317 972 9999",
    "sg:postcode":"46240",
    "sg:province":"IN",
    "wof:name":"Charles Carlock",
    "wof:placetype":"venue"
},
  "geometry": {"coordinates":[-86.109497,39.916698],"type":"Point"}
}