{
  "type": "Feature",
  "properties": {
    "addr:full":"2572 US Hwy 31 Seymour IN 47274",
    "addr:housenumber":"2572",
    "addr:postcode":"47274",
    "addr:street":"Us Hwy 31",
    "iso:country":"US",
    "sg:address":"2572 US Hwy 31",
    "sg:city":"Seymour",
    "sg:classifiers":[
        {
            "category":"Wholesale",
            "subcategory":"Toys & Hobbies",
            "type":"Manufacturing & Wholesale Goods"
        }
    ],
    "sg:phone":"+1 812 523 3473",
    "sg:postcode":"47274",
    "sg:province":"IN",
    "sg:tags":[
        "firework"
    ],
    "wof:name":"Patriotic Fireworks",
    "wof:placetype":"venue"
},
  "geometry": {"coordinates":[-85.83356999999999,38.919428],"type":"Point"}
}