{
  "type": "Feature",
  "properties": {
    "iso:country":"US",
    "sg:address":"5606 Maplewood Dr",
    "sg:city":"Indianapolis",
    "sg:classifiers":[
        {
            "category":"Professional",
            "subcategory":"Computer Services",
            "type":"Services"
        }
    ],
    "sg:phone":"+1 317 299 5084",
    "sg:postcode":"46224",
    "sg:province":"IN",
    "sg:tags":[
        "programing",
        "custom"
    ],
    "wof:name":"Computer Automation & Tech",
    "wof:placetype":"venue"
},
  "geometry": {"coordinates":[-86.259845,39.803716],"type":"Point"}
}