{
  "type": "Feature",
  "properties": {
    "iso:country":"US",
    "sg:address":"4850 N 250 W",
    "sg:city":"West Lafayette",
    "sg:classifiers":[
        {
            "category":"Farming",
            "subcategory":"Farm",
            "type":"Manufacturing & Wholesale Goods"
        }
    ],
    "sg:phone":"+1 765 463 6161",
    "sg:postcode":"47906",
    "sg:province":"IN",
    "sg:tags":[
        "crop",
        "general"
    ],
    "wof:name":"Farm Directors Inc",
    "wof:placetype":"venue"
},
  "geometry": {"coordinates":[-86.953172,40.482769],"type":"Point"}
}