{
  "type": "Feature",
  "properties": {
    "addr:full":"112 E Alto Rd Kokomo IN 46902",
    "addr:housenumber":"112",
    "addr:postcode":"46902",
    "addr:street":"E Alto Rd",
    "iso:country":"US",
    "sg:address":"112 E Alto Rd",
    "sg:city":"Kokomo",
    "sg:classifiers":[
        {
            "category":"Health Services",
            "subcategory":"Doctor",
            "type":"Services"
        }
    ],
    "sg:phone":"+1 765 455 2505",
    "sg:postcode":"46902",
    "sg:province":"IN",
    "sg:tags":[
        "dentist"
    ],
    "wof:name":"Kokomo Endodontics",
    "wof:placetype":"venue"
},
  "geometry": {"coordinates":[-86.13345200000001,40.44061],"type":"Point"}
}