{
  "type": "Feature",
  "properties": {
    "iso:country":"US",
    "sg:address":"10585 N Meridian St Ste 201",
    "sg:city":"Indianapolis",
    "sg:classifiers":[
        {
            "category":"Professional",
            "subcategory":"Employment Agencies",
            "type":"Services"
        }
    ],
    "sg:phone":"+1 317 815 0778",
    "sg:postcode":"46290",
    "sg:province":"IN",
    "wof:name":"Careerstaff Unlimited-Therapists Unlimited",
    "wof:placetype":"venue"
},
  "geometry": {"coordinates":[-86.157501,39.941502],"type":"Point"}
}