{
  "type": "Feature",
  "properties": {
    "addr:full":"1435 Brookville Way Indianapolis IN 46239",
    "addr:housenumber":"1435",
    "addr:postcode":"46239",
    "addr:street":"Brookville Way",
    "iso:country":"US",
    "sg:address":"1435 Brookville Way",
    "sg:city":"Indianapolis",
    "sg:classifiers":[
        {
            "category":"Freight",
            "type":"Transportation"
        }
    ],
    "sg:phone":"+1 317 375 1651",
    "sg:postcode":"46239",
    "sg:province":"IN",
    "sg:tags":[
        "delivery"
    ],
    "wof:name":"Velocity Express Inc",
    "wof:placetype":"venue"
},
  "geometry": {"coordinates":[-86.046211,39.753955],"type":"Point"}
}