{
  "type": "Feature",
  "properties": {
    "iso:country":"US",
    "sg:address":"4257 W Hunters Ridge Ln",
    "sg:city":"Greenwood",
    "sg:classifiers":[
        {
            "category":"Wholesale",
            "subcategory":"Home Furnishings",
            "type":"Manufacturing & Wholesale Goods"
        }
    ],
    "sg:phone":"+1 317 422 1775",
    "sg:postcode":"46143",
    "sg:province":"IN",
    "sg:tags":[
        "window",
        "covering"
    ],
    "wof:name":"Discount Blinds & Verticals",
    "wof:placetype":"venue"
},
  "geometry": {"coordinates":[-86.183365,39.591154],"type":"Point"}
}