{
  "type": "Feature",
  "properties": {
    "iso:country":"US",
    "sg:address":"6813 Kennedy Ave",
    "sg:city":"Hammond",
    "sg:classifiers":[
        {
            "category":"Insurance",
            "subcategory":"Insurance Agent",
            "type":"Services"
        }
    ],
    "sg:phone":"+1 219 845 7100",
    "sg:postcode":"46323",
    "sg:province":"IN",
    "wof:name":"Silcox Insurance Svc",
    "wof:placetype":"venue"
},
  "geometry": {"coordinates":[-87.461638,41.589105],"type":"Point"}
}