{
  "type": "Feature",
  "properties": {
    "iso:country":"US",
    "sg:address":"3786 S 500 W",
    "sg:city":"New Palestine",
    "sg:classifiers":[
        {
            "category":"Building & Trades",
            "subcategory":"Construction",
            "type":"Services"
        }
    ],
    "sg:phone":"+1 317 861 4903",
    "sg:postcode":"46163",
    "sg:province":"IN",
    "sg:tags":[
        "contractor"
    ],
    "wof:name":"Harting Farms",
    "wof:placetype":"venue"
},
  "geometry": {"coordinates":[-85.895571,39.729917],"type":"Point"}
}