{
  "type": "Feature",
  "properties": {
    "addr:full":"875 W State Rd 144 Franklin IN 46131",
    "addr:housenumber":"875;144",
    "addr:postcode":"46131",
    "addr:street":"W State Rd",
    "iso:country":"US",
    "sg:address":"875 W State Rd 144",
    "sg:city":"Franklin",
    "sg:classifiers":[
        {
            "category":"Real Estate",
            "subcategory":"Real Estate Operator",
            "type":"Services"
        }
    ],
    "sg:phone":"+1 317 736 4134",
    "sg:postcode":"46131",
    "sg:province":"IN",
    "sg:tags":[
        "property",
        "lessor"
    ],
    "wof:name":"David Ditmard",
    "wof:placetype":"venue"
},
  "geometry": {"coordinates":[-86.065787,39.479948],"type":"Point"}
}