{
  "type": "Feature",
  "properties": {
    "addr:full":"9201 Valley View Dr Evansville IN 47711",
    "addr:housenumber":"9201",
    "addr:postcode":"47711",
    "addr:street":"Valley View Dr",
    "iso:country":"US",
    "sg:address":"9201 Valley View Dr",
    "sg:city":"Evansville",
    "sg:classifiers":[
        {
            "category":"Professional",
            "subcategory":"Business Services",
            "type":"Services"
        }
    ],
    "sg:phone":"+1 812 473 0064",
    "sg:postcode":"47711",
    "sg:province":"IN",
    "sg:tags":[
        "appraiser"
    ],
    "wof:name":"Deig Appraisal Co",
    "wof:placetype":"venue"
},
  "geometry": {"coordinates":[-87.55548,38.062219],"type":"Point"}
}