{
  "type": "Feature",
  "properties": {
    "iso:country":"US",
    "sg:address":"418 E Jefferson St",
    "sg:city":"Tipton",
    "sg:classifiers":[
        {
            "category":"Personal",
            "subcategory":"Beauty Salon",
            "type":"Services"
        }
    ],
    "sg:phone":"+1 765 675 2762",
    "sg:postcode":"46072",
    "sg:province":"IN",
    "wof:name":"Rob's Hair Studio",
    "wof:placetype":"venue"
},
  "geometry": {"coordinates":[-86.035372,40.282478],"type":"Point"}
}