{
  "type": "Feature",
  "properties": {
    "iso:country":"US",
    "sg:address":"2020 E Chicago Ave",
    "sg:city":"East Chicago",
    "sg:classifiers":[
        {
            "category":"Retail",
            "subcategory":"Laundry & Dry Cleaning",
            "type":"Services"
        }
    ],
    "sg:phone":"+1 219 397 1265",
    "sg:postcode":"46312",
    "sg:province":"IN",
    "sg:tags":[
        "cleaners"
    ],
    "wof:name":"Nu-Method Cleaners",
    "wof:placetype":"venue"
},
  "geometry": {"coordinates":[-87.451994,41.629188],"type":"Point"}
}