{
  "type": "Feature",
  "properties": {
    "iso:country":"US",
    "sg:address":"10025 Chatodd Ct",
    "sg:city":"Evansville",
    "sg:classifiers":[
        {
            "category":"Professional",
            "subcategory":"Computer Services",
            "type":"Services"
        }
    ],
    "sg:phone":"+1 812 474 2324",
    "sg:postcode":"47712",
    "sg:province":"IN",
    "sg:tags":[
        "internet"
    ],
    "wof:name":"Intra-Data Link Inc",
    "wof:placetype":"venue"
},
  "geometry": {"coordinates":[-87.69176400000001,37.971337],"type":"Point"}
}