{
  "type": "Feature",
  "properties": {
    "iso:country":"US",
    "sg:address":"303 W Main St",
    "sg:city":"Hagerstown",
    "sg:classifiers":[
        {
            "category":"Manufacturing",
            "subcategory":"Toys & Sporting Goods",
            "type":"Manufacturing & Wholesale Goods"
        }
    ],
    "sg:phone":"+1 765 489 5807",
    "sg:postcode":"47346",
    "sg:province":"IN",
    "wof:name":"TEDCO Inc",
    "wof:placetype":"venue"
},
  "geometry": {"coordinates":[-85.16512899999999,39.910742],"type":"Point"}
}