{
  "type": "Feature",
  "properties": {
    "iso:country":"US",
    "sg:address":"4705 S Meridian Rd",
    "sg:city":"Greenfield",
    "sg:phone":"+1 317 462 9798",
    "sg:postcode":"46140",
    "sg:province":"IN",
    "sg:tags":[
        "farm",
        "corn",
        "wheat",
        "soybean"
    ],
    "wof:name":"Dismore Farms",
    "wof:placetype":"venue"
},
  "geometry": {"coordinates":[-85.800468,39.717954],"type":"Point"}
}