{
  "type": "Feature",
  "properties": {
    "iso:country":"US",
    "sg:address":"200 E Swayzee St",
    "sg:city":"Marion",
    "sg:classifiers":[
        {
            "category":"Organizations",
            "subcategory":"Religious Organization",
            "type":"Services"
        }
    ],
    "sg:phone":"+1 765 664 3039",
    "sg:postcode":"46952",
    "sg:province":"IN",
    "sg:tags":[
        "church"
    ],
    "wof:name":"Swayzee Street United Meth",
    "wof:placetype":"venue"
},
  "geometry": {"coordinates":[-85.657349,40.564185],"type":"Point"}
}