{
  "type": "Feature",
  "properties": {
    "iso:country":"US",
    "sg:address":"8600 E Co Rd 1100 N",
    "sg:city":"Eaton",
    "sg:classifiers":[
        {
            "category":"Shopping",
            "subcategory":"Gifts & Souvenirs",
            "type":"Retail Goods"
        }
    ],
    "sg:phone":"+1 765 396 3877",
    "sg:postcode":"47338",
    "sg:province":"IN",
    "wof:name":"Home Interior Gifts",
    "wof:placetype":"venue"
},
  "geometry": {"coordinates":[-85.292231,40.349537],"type":"Point"}
}