{
  "type": "Feature",
  "properties": {
    "iso:country":"US",
    "sg:address":"624 W Main St",
    "sg:city":"New Albany",
    "sg:classifiers":[
        {
            "category":"Food & Beverages",
            "subcategory":"Groceries & Convenience Stores",
            "type":"Retail Goods"
        }
    ],
    "sg:phone":"+1 812 944 1040",
    "sg:postcode":"47150",
    "sg:province":"IN",
    "sg:tags":[
        "grocer"
    ],
    "wof:name":"Service Plus",
    "wof:placetype":"venue"
},
  "geometry": {"coordinates":[-85.829183,38.280806],"type":"Point"}
}