{
  "type": "Feature",
  "properties": {
    "iso:country":"US",
    "sg:address":"2248 W US Hwy 40",
    "sg:city":"Greenfield",
    "sg:classifiers":[
        {
            "category":"Real Estate",
            "subcategory":"Real Estate Agent",
            "type":"Services"
        }
    ],
    "sg:phone":"+1 317 216 4080",
    "sg:postcode":"46140",
    "sg:province":"IN",
    "wof:name":"Real Estate",
    "wof:placetype":"venue"
},
  "geometry": {"coordinates":[-85.844441,39.781765],"type":"Point"}
}