{
  "type": "Feature",
  "properties": {
    "iso:country":"US",
    "sg:address":"1000 Axe Ave",
    "sg:city":"Valparaiso",
    "sg:classifiers":[
        {
            "category":"Manufacturing",
            "subcategory":"Motor Vehicles & Parts",
            "type":"Manufacturing & Wholesale Goods"
        }
    ],
    "sg:phone":"+1 219 462 5181",
    "sg:postcode":"46383",
    "sg:province":"IN",
    "sg:tags":[
        "automobile",
        "supply"
    ],
    "sg:website":"www.classychassistrucks.com",
    "wof:name":"Kennelly's Auto Body Inc",
    "wof:placetype":"venue"
},
  "geometry": {"coordinates":[-87.055415,41.458275],"type":"Point"}
}