{
  "type": "Feature",
  "properties": {
    "addr:full":"696 W Eads Pkwy Lawrenceburg IN 47025",
    "addr:housenumber":"696",
    "addr:postcode":"47025",
    "addr:street":"W Eads Pkwy",
    "iso:country":"US",
    "sg:address":"696 W Eads Pkwy",
    "sg:city":"Lawrenceburg",
    "sg:classifiers":[
        {
            "category":"Professional",
            "subcategory":"Employment Agencies",
            "type":"Services"
        }
    ],
    "sg:phone":"+1 812 537 9420",
    "sg:postcode":"47025",
    "sg:province":"IN",
    "sg:tags":[
        "help",
        "contractor"
    ],
    "wof:name":"CBS Personnel Svc",
    "wof:placetype":"venue"
},
  "geometry": {"coordinates":[-84.867656,39.093743],"type":"Point"}
}