{
  "type": "Feature",
  "properties": {
    "iso:country":"US",
    "sg:address":"903 Bison Ridge",
    "sg:city":"Nappanee",
    "sg:classifiers":[
        {
            "category":"Real Estate",
            "subcategory":"Real Estate Operator",
            "type":"Services"
        }
    ],
    "sg:phone":"+1 574 773 2353",
    "sg:postcode":"46550",
    "sg:province":"IN",
    "sg:tags":[
        "building",
        "apartment"
    ],
    "wof:name":"Bison Ridge Apartments",
    "wof:placetype":"venue"
},
  "geometry": {"coordinates":[-85.997297,41.455997],"type":"Point"}
}