{
  "type": "Feature",
  "properties": {
    "iso:country":"US",
    "sg:address":"710 W Lincoln Ave",
    "sg:city":"Goshen",
    "sg:classifiers":[
        {
            "category":"Food & Beverages",
            "subcategory":"Bakery",
            "type":"Retail Goods"
        }
    ],
    "sg:phone":"+1 574 533 3525",
    "sg:postcode":"46526",
    "sg:province":"IN",
    "sg:tags":[
        "baker"
    ],
    "wof:name":"Everett's Suger-N-Spice Bakery",
    "wof:placetype":"venue"
},
  "geometry": {"coordinates":[-85.845941,41.586309],"type":"Point"}
}