{
  "type": "Feature",
  "properties": {
    "addr:full":"119 S Anderson St Elwood IN 46036",
    "addr:housenumber":"119",
    "addr:postcode":"46036",
    "addr:street":"S Anderson St",
    "iso:country":"US",
    "sg:address":"119 S Anderson St",
    "sg:city":"Elwood",
    "sg:classifiers":[
        {
            "category":"Shopping",
            "subcategory":"Gifts & Souvenirs",
            "type":"Retail Goods"
        }
    ],
    "sg:phone":"+1 765 552 3855",
    "sg:postcode":"46036",
    "sg:province":"IN",
    "sg:tags":[
        "shop"
    ],
    "wof:name":"Young's Country Cottage",
    "wof:placetype":"venue"
},
  "geometry": {"coordinates":[-85.84179399999999,40.276806],"type":"Point"}
}