{
  "type": "Feature",
  "properties": {
    "iso:country":"US",
    "sg:address":"1449 E 84th Pl",
    "sg:city":"Merrillville",
    "sg:classifiers":[
        {
            "category":"Insurance",
            "subcategory":"Insurance Agent",
            "type":"Services"
        }
    ],
    "sg:phone":"+1 219 769 3658",
    "sg:postcode":"46410",
    "sg:province":"IN",
    "wof:name":"Allstate Insurance",
    "wof:placetype":"venue"
},
  "geometry": {"coordinates":[-87.318817,41.464769],"type":"Point"}
}