{
  "type": "Feature",
  "properties": {
    "iso:country":"US",
    "sg:address":"4514 E 79th St",
    "sg:city":"Indianapolis",
    "sg:classifiers":[
        {
            "category":"Professional",
            "type":"Services"
        }
    ],
    "sg:phone":"+1 317 842 6521",
    "sg:postcode":"46250",
    "sg:province":"IN",
    "sg:tags":[
        "establishment"
    ],
    "wof:name":"Crews Sturtz Inc",
    "wof:placetype":"venue"
},
  "geometry": {"coordinates":[-86.087546,39.897775],"type":"Point"}
}