{
  "type": "Feature",
  "properties": {
    "addr:full":"1605 N Home St Mishawaka IN 46545",
    "addr:housenumber":"1605",
    "addr:postcode":"46545",
    "addr:street":"N Home St",
    "iso:country":"US",
    "sg:address":"1605 N Home St",
    "sg:city":"Mishawaka",
    "sg:classifiers":[
        {
            "category":"Manufacturing",
            "subcategory":"Printing",
            "type":"Manufacturing & Wholesale Goods"
        }
    ],
    "sg:phone":"+1 574 255 9800",
    "sg:postcode":"46545",
    "sg:province":"IN",
    "sg:tags":[
        "newspaper"
    ],
    "sg:website":"www.blueandgold.com",
    "wof:name":"Blue & Gold Illustrated",
    "wof:placetype":"venue"
},
  "geometry": {"coordinates":[-86.14819799999999,41.678698],"type":"Point"}
}