{
  "type": "Feature",
  "properties": {
    "addr:full":"1260 W 150 S Knox IN 46534",
    "addr:housenumber":"1260",
    "addr:postcode":"46534",
    "addr:street":"W 150 S",
    "iso:country":"US",
    "sg:address":"1260 W 150 S",
    "sg:city":"Knox",
    "sg:classifiers":[
        {
            "category":"Manufacturing",
            "subcategory":"Building Materials",
            "type":"Manufacturing & Wholesale Goods"
        }
    ],
    "sg:phone":"+1 574 772 2296",
    "sg:postcode":"46534",
    "sg:province":"IN",
    "sg:tags":[
        "mfg"
    ],
    "wof:name":"Interior World",
    "wof:placetype":"venue"
},
  "geometry": {"coordinates":[-86.722103,41.28096],"type":"Point"}
}