{
  "type": "Feature",
  "properties": {
    "iso:country":"US",
    "sg:address":"604 E Hackberry St",
    "sg:city":"Salem",
    "sg:classifiers":[
        {
            "category":"Autos & Motor Vehicles",
            "subcategory":"Fuel & Gas Station",
            "type":"Retail Goods"
        }
    ],
    "sg:phone":"+1 812 883 1902",
    "sg:postcode":"47167",
    "sg:province":"IN",
    "sg:tags":[
        "oil"
    ],
    "wof:name":"Collett Gas",
    "wof:placetype":"venue"
},
  "geometry": {"coordinates":[-86.094584,38.609766],"type":"Point"}
}