{
  "type": "Feature",
  "properties": {
    "addr:full":"3520 E 96th St Indianapolis IN 46240",
    "addr:housenumber":"3520",
    "addr:postcode":"46240",
    "addr:street":"E 96Th St",
    "iso:country":"US",
    "sg:address":"3520 E 96th St",
    "sg:city":"Indianapolis",
    "sg:classifiers":[
        {
            "category":"Real Estate",
            "subcategory":"Real Estate Agent",
            "type":"Services"
        }
    ],
    "sg:phone":"+1 317 574 9035",
    "sg:postcode":"46240",
    "sg:province":"IN",
    "sg:tags":[
        "appraiser"
    ],
    "wof:name":"Keystone Appraisal Svc",
    "wof:placetype":"venue"
},
  "geometry": {"coordinates":[-86.107316,39.926828],"type":"Point"}
}