{
  "type": "Feature",
  "properties": {
    "iso:country":"US",
    "sg:address":"316 S 3rd St",
    "sg:city":"Goshen",
    "sg:classifiers":[
        {
            "category":"Banks & Credit Unions",
            "subcategory":"Bank",
            "type":"Services"
        }
    ],
    "sg:phone":"+1 574 533 7785",
    "sg:postcode":"46526",
    "sg:province":"IN",
    "sg:tags":[
        "loan",
        "real estate"
    ],
    "wof:name":"Pioneer Mortgage",
    "wof:placetype":"venue"
},
  "geometry": {"coordinates":[-85.835961,41.583226],"type":"Point"}
}