{
  "type": "Feature",
  "properties": {
    "iso:country":"US",
    "sg:address":"13861 Co Rd 4",
    "sg:city":"Middlebury",
    "sg:classifiers":[
        {
            "category":"Autos & Motor Vehicles",
            "subcategory":"Automobile Sales",
            "type":"Retail Goods"
        }
    ],
    "sg:phone":"+1 574 825 6775",
    "sg:postcode":"46540",
    "sg:province":"IN",
    "sg:tags":[
        "trailer"
    ],
    "wof:name":"Bomar Racing LTD",
    "wof:placetype":"venue"
},
  "geometry": {"coordinates":[-85.736129,41.739966],"type":"Point"}
}