{
  "type": "Feature",
  "properties": {
    "addr:full":"2023 Ekin Ave New Albany IN 47150",
    "addr:housenumber":"2023",
    "addr:postcode":"47150",
    "addr:street":"Ekin Ave",
    "iso:country":"US",
    "sg:address":"2023 Ekin Ave",
    "sg:city":"New Albany",
    "sg:classifiers":[
        {
            "category":"Education",
            "subcategory":"School",
            "type":"Public Place"
        }
    ],
    "sg:phone":"+1 812 949 4309",
    "sg:postcode":"47150",
    "sg:province":"IN",
    "sg:website":"www.nafcs.k12.in.us",
    "wof:name":"Silver Street Elementary Schl",
    "wof:placetype":"venue"
},
  "geometry": {"coordinates":[-85.803378,38.299981],"type":"Point"}
}