{
  "type": "Feature",
  "properties": {
    "iso:country":"US",
    "sg:address":"815 W Michigan St",
    "sg:city":"Indianapolis",
    "sg:classifiers":[
        {
            "category":"Education",
            "subcategory":"College",
            "type":"Public Place"
        }
    ],
    "sg:phone":"+1 317 274 2237",
    "sg:postcode":"46202",
    "sg:province":"IN",
    "sg:tags":[
        "academic",
        "school"
    ],
    "sg:website":"www.universitycollege.iupui.edu",
    "wof:name":"Iupui University",
    "wof:placetype":"venue"
},
  "geometry": {"coordinates":[-86.172198,39.774457],"type":"Point"}
}