{
  "type": "Feature",
  "properties": {
    "iso:country":"US",
    "sg:address":"16575 Carey Rd",
    "sg:city":"Westfield",
    "sg:classifiers":[
        {
            "category":"Social Services",
            "type":"Services"
        }
    ],
    "sg:phone":"+1 317 867 5877",
    "sg:postcode":"46074",
    "sg:province":"IN",
    "sg:tags":[
        "youth",
        "organization",
        "center"
    ],
    "sg:website":"www.hhyf.org",
    "wof:name":"Harness Horse Youth Foundation",
    "wof:placetype":"venue"
},
  "geometry": {"coordinates":[-86.108758,40.027341],"type":"Point"}
}