{
  "type": "Feature",
  "properties": {
    "iso:country":"US",
    "sg:address":"314 Metropolis Mile",
    "sg:city":"Plainfield",
    "sg:classifiers":[
        {
            "category":"Personal",
            "subcategory":"Nail Salon",
            "type":"Services"
        }
    ],
    "sg:phone":"+1 317 406 2558",
    "sg:postcode":"46168",
    "sg:province":"IN",
    "wof:name":"Glace' Nails",
    "wof:placetype":"venue"
},
  "geometry": {"coordinates":[-86.358599,39.712702],"type":"Point"}
}