{
  "type": "Feature",
  "properties": {
    "iso:country":"US",
    "sg:address":"333 E Berwyn St",
    "sg:city":"Indianapolis",
    "sg:classifiers":[
        {
            "category":"Building & Trades",
            "subcategory":"Construction",
            "type":"Services"
        }
    ],
    "sg:phone":"+1 317 788 8627",
    "sg:postcode":"46225",
    "sg:province":"IN",
    "sg:tags":[
        "carpenter"
    ],
    "wof:name":"Mills Custom Carpentry",
    "wof:placetype":"venue"
},
  "geometry": {"coordinates":[-86.15304399999999,39.72424],"type":"Point"}
}