{
  "type": "Feature",
  "properties": {
    "iso:country":"US",
    "sg:address":"2027 Westgate Ave",
    "sg:city":"Plymouth",
    "sg:classifiers":[
        {
            "category":"Building & Trades",
            "subcategory":"Construction",
            "type":"Services"
        }
    ],
    "sg:phone":"+1 574 935 9922",
    "sg:postcode":"46563",
    "sg:province":"IN",
    "sg:tags":[
        "house",
        "contractor"
    ],
    "wof:name":"B & R Builders",
    "wof:placetype":"venue"
},
  "geometry": {"coordinates":[-86.334383,41.336941],"type":"Point"}
}