{
  "type": "Feature",
  "properties": {
    "iso:country":"US",
    "sg:address":"4326 Winston Dr",
    "sg:city":"Fort Wayne",
    "sg:classifiers":[
        {
            "category":"Building & Trades",
            "subcategory":"Construction",
            "type":"Services"
        }
    ],
    "sg:phone":"+1 260 744 1362",
    "sg:postcode":"46806",
    "sg:province":"IN",
    "sg:tags":[
        "hanging",
        "contractor"
    ],
    "wof:name":"Kimber Painting",
    "wof:placetype":"venue"
},
  "geometry": {"coordinates":[-85.099594,41.042839],"type":"Point"}
}