{
  "type": "Feature",
  "properties": {
    "iso:country":"US",
    "sg:address":"213 W Van Buren St",
    "sg:city":"Columbia City",
    "sg:classifiers":[
        {
            "category":"Organizations",
            "subcategory":"Religious Organization",
            "type":"Services"
        },
        {
            "category":"Education",
            "subcategory":"Vocational School",
            "type":"Public Place"
        }
    ],
    "sg:phone":"+1 260 248 8264",
    "sg:postcode":"46725",
    "sg:province":"IN",
    "sg:tags":[
        "correspondence"
    ],
    "wof:name":"United Christian Ministry Inst",
    "wof:placetype":"venue"
},
  "geometry": {"coordinates":[-85.491141,41.156941],"type":"Point"}
}