{
  "type": "Feature",
  "properties": {
    "addr:full":"521 State St Newburgh IN 47630",
    "addr:housenumber":"521",
    "addr:postcode":"47630",
    "addr:street":"State St",
    "iso:country":"US",
    "sg:address":"521 State St",
    "sg:city":"Newburgh",
    "sg:classifiers":[
        {
            "category":"Restaurant",
            "type":"Food & Drink"
        }
    ],
    "sg:phone":"+1 812 853 5840",
    "sg:postcode":"47630",
    "sg:province":"IN",
    "wof:name":"Rivertown Ice Cream & Grill",
    "wof:placetype":"venue"
},
  "geometry": {"coordinates":[-87.405135,37.948511],"type":"Point"}
}