{
  "type": "Feature",
  "properties": {
    "iso:country":"US",
    "sg:address":"5921 Vogel Rd",
    "sg:city":"Evansville",
    "sg:classifiers":[
        {
            "category":"Shopping",
            "type":"Retail Goods"
        }
    ],
    "sg:phone":"+1 812 479 7577",
    "sg:postcode":"47715",
    "sg:province":"IN",
    "sg:tags":[
        "limb",
        "artificial"
    ],
    "wof:name":"Riverside Orthotics & Prsthtcs",
    "wof:placetype":"venue"
},
  "geometry": {"coordinates":[-87.479874,37.987554],"type":"Point"}
}