{
  "type": "Feature",
  "properties": {
    "addr:full":"10866 Spry Rd Newburgh IN 47630",
    "addr:housenumber":"10866",
    "addr:postcode":"47630",
    "addr:street":"Spry Rd",
    "iso:country":"US",
    "sg:address":"10866 Spry Rd",
    "sg:city":"Newburgh",
    "sg:classifiers":[
        {
            "category":"Real Estate",
            "subcategory":"Real Estate Operator",
            "type":"Services"
        }
    ],
    "sg:phone":"+1 812 853 8936",
    "sg:postcode":"47630",
    "sg:province":"IN",
    "sg:tags":[
        "apartment"
    ],
    "wof:name":"Henson Enterprises",
    "wof:placetype":"venue"
},
  "geometry": {"coordinates":[-87.44866399999999,37.951459],"type":"Point"}
}