{
  "type": "Feature",
  "properties": {
    "iso:country":"US",
    "sg:address":"875 Ln 200 Lake James",
    "sg:city":"Angola",
    "sg:classifiers":[
        {
            "category":"Wholesale",
            "subcategory":"Machinery & Supplies",
            "type":"Manufacturing & Wholesale Goods"
        }
    ],
    "sg:phone":"+1 260 833 2851",
    "sg:postcode":"46703",
    "sg:province":"IN",
    "sg:tags":[
        "rope"
    ],
    "wof:name":"Alexander Rope & Twine Co",
    "wof:placetype":"venue"
},
  "geometry": {"coordinates":[-85.011891,41.689434],"type":"Point"}
}