{
  "type": "Feature",
  "properties": {
    "iso:country":"US",
    "sg:address":"735 E Water St",
    "sg:city":"Hartford City",
    "sg:classifiers":[
        {
            "category":"Home & Garden",
            "subcategory":"Home Furnishings",
            "type":"Retail Goods"
        }
    ],
    "sg:phone":"+1 765 348 1282",
    "sg:postcode":"47348",
    "sg:province":"IN",
    "sg:tags":[
        "mirror"
    ],
    "sg:website":"www.hartfordglass.com",
    "wof:name":"Hartford Glass Co",
    "wof:placetype":"venue"
},
  "geometry": {"coordinates":[-85.360293,40.450341],"type":"Point"}
}