{
  "type": "Feature",
  "properties": {
    "iso:country":"US",
    "sg:address":"1034 E New York St",
    "sg:city":"Indianapolis",
    "sg:classifiers":[
        {
            "category":"Shopping",
            "subcategory":"Hobbies, Toys, & Games",
            "type":"Retail Goods"
        }
    ],
    "sg:phone":"+1 317 955 8444",
    "sg:postcode":"46202",
    "sg:province":"IN",
    "sg:tags":[
        "equipment",
        "ceramic",
        "supply"
    ],
    "wof:name":"Indiana Ceramic Supply",
    "wof:placetype":"venue"
},
  "geometry": {"coordinates":[-86.139708,39.771103],"type":"Point"}
}