{
  "type": "Feature",
  "properties": {
    "iso:country":"US",
    "sg:address":"16806 Co Rd 46",
    "sg:city":"New Paris",
    "sg:classifiers":[
        {
            "category":"Sports & Exercise",
            "subcategory":"Race Track",
            "type":"Entertainment"
        }
    ],
    "sg:phone":"+1 574 831 3050",
    "sg:postcode":"46553",
    "sg:province":"IN",
    "wof:name":"New Paris Speedway",
    "wof:placetype":"venue"
},
  "geometry": {"coordinates":[-85.770116,41.496533],"type":"Point"}
}