{
  "type": "Feature",
  "properties": {
    "iso:country":"US",
    "sg:address":"5133 N Starnes Rd",
    "sg:city":"Bloomington",
    "sg:classifiers":[
        {
            "category":"Insurance",
            "subcategory":"Insurance Agent",
            "type":"Services"
        }
    ],
    "sg:phone":"+1 812 876 8436",
    "sg:postcode":"47404",
    "sg:province":"IN",
    "wof:name":"Insurance Forum",
    "wof:placetype":"venue"
},
  "geometry": {"coordinates":[-86.658869,39.222258],"type":"Point"}
}