{
  "type": "Feature",
  "properties": {
    "addr:full":"425 W Main St Peru IN 46970",
    "addr:housenumber":"425",
    "addr:postcode":"46970",
    "addr:street":"W Main St",
    "iso:country":"US",
    "sg:address":"425 W Main St",
    "sg:city":"Peru",
    "sg:classifiers":[
        {
            "category":"Education",
            "subcategory":"School",
            "type":"Public Place"
        }
    ],
    "sg:phone":"+1 765 473 7605",
    "sg:postcode":"46970",
    "sg:province":"IN",
    "wof:name":"Holman Elementary School",
    "wof:placetype":"venue"
},
  "geometry": {"coordinates":[-86.081485,40.748196],"type":"Point"}
}