{
  "type": "Feature",
  "properties": {
    "iso:country":"US",
    "sg:address":"114 W Franklin St",
    "sg:city":"Hartford City",
    "sg:classifiers":[
        {
            "category":"Personal",
            "subcategory":"Beauty Salon",
            "type":"Services"
        }
    ],
    "sg:phone":"+1 765 348 3673",
    "sg:postcode":"47348",
    "sg:province":"IN",
    "wof:name":"May's Beauty Shop",
    "wof:placetype":"venue"
},
  "geometry": {"coordinates":[-85.367834,40.453082],"type":"Point"}
}