{
  "type": "Feature",
  "properties": {
    "iso:country":"US",
    "sg:address":"1260 W 400 N",
    "sg:city":"Howe",
    "sg:classifiers":[
        {
            "category":"Education",
            "subcategory":"Dance Studio",
            "type":"Public Place"
        }
    ],
    "sg:phone":"+1 260 562 2683",
    "sg:postcode":"46746",
    "sg:province":"IN",
    "sg:tags":[
        "instruction",
        "dancing"
    ],
    "wof:name":"Dance Etc",
    "wof:placetype":"venue"
},
  "geometry": {"coordinates":[-85.448526,41.699252],"type":"Point"}
}