{
  "type": "Feature",
  "properties": {
    "iso:country":"US",
    "sg:address":"4308 Bertrand Rd",
    "sg:city":"Indianapolis",
    "sg:classifiers":[
        {
            "category":"Retail",
            "subcategory":"Repair Shop",
            "type":"Services"
        }
    ],
    "sg:phone":"+1 317 216 0748",
    "sg:postcode":"46222",
    "sg:province":"IN",
    "sg:tags":[
        "related"
    ],
    "wof:name":"David Upholstry Repair",
    "wof:placetype":"venue"
},
  "geometry": {"coordinates":[-86.23806,39.812245],"type":"Point"}
}