{
  "type": "Feature",
  "properties": {
    "iso:country":"US",
    "sg:address":"1259 N Etna Rd",
    "sg:city":"Huntington",
    "sg:classifiers":[
        {
            "category":"Food & Beverages",
            "subcategory":"Fruits & Vegetables",
            "type":"Retail Goods"
        }
    ],
    "sg:phone":"+1 260 356 4622",
    "sg:postcode":"46750",
    "sg:province":"IN",
    "sg:tags":[
        "produce"
    ],
    "wof:name":"Huntington Orchards",
    "wof:placetype":"venue"
},
  "geometry": {"coordinates":[-85.520774,40.849571],"type":"Point"}
}