{
  "type": "Feature",
  "properties": {
    "iso:country":"US",
    "sg:address":"120 E 200 S",
    "sg:city":"Warsaw",
    "sg:classifiers":[
        {
            "category":"Professional",
            "subcategory":"Management & Consulting",
            "type":"Services"
        }
    ],
    "sg:phone":"+1 574 267 6553",
    "sg:postcode":"46580",
    "sg:province":"IN",
    "sg:tags":[
        "business"
    ],
    "wof:name":"Morris R G & Associates",
    "wof:placetype":"venue"
},
  "geometry": {"coordinates":[-85.834323,41.205532],"type":"Point"}
}