{
  "type": "Feature",
  "properties": {
    "iso:country":"US",
    "sg:address":"8997 S Snow Rd",
    "sg:city":"Bloomington",
    "sg:classifiers":[
        {
            "category":"Freight",
            "type":"Transportation"
        }
    ],
    "sg:phone":"+1 812 825 7356",
    "sg:postcode":"47403",
    "sg:province":"IN",
    "sg:tags":[
        "trucking"
    ],
    "wof:name":"Keith Webster Trucking",
    "wof:placetype":"venue"
},
  "geometry": {"coordinates":[-86.654055,39.021352],"type":"Point"}
}