{
  "type": "Feature",
  "properties": {
    "iso:country":"US",
    "sg:address":"7820 Scarborough Blvd S Dr S",
    "sg:city":"Indianapolis",
    "sg:classifiers":[
        {
            "category":"Professional",
            "subcategory":"Engineering",
            "type":"Services"
        }
    ],
    "sg:phone":"+1 317 842 1906",
    "sg:postcode":"46256",
    "sg:province":"IN",
    "sg:tags":[
        "engineer"
    ],
    "wof:name":"Karl E Muszar PE",
    "wof:placetype":"venue"
},
  "geometry": {"coordinates":[-86.03111699999999,39.888441],"type":"Point"}
}