{
  "type": "Feature",
  "properties": {
    "iso:country":"US",
    "sg:address":"608 S Main St",
    "sg:city":"Burnettsville",
    "sg:classifiers":[
        {
            "category":"Wholesale",
            "subcategory":"Stationery",
            "type":"Manufacturing & Wholesale Goods"
        }
    ],
    "sg:phone":"+1 574 826 4195",
    "sg:postcode":"47926",
    "sg:province":"IN",
    "sg:tags":[
        "product",
        "paper"
    ],
    "wof:name":"J H Saylor Co",
    "wof:placetype":"venue"
},
  "geometry": {"coordinates":[-86.593613,40.759264],"type":"Point"}
}