{
  "type": "Feature",
  "properties": {
    "addr:full":"1135 Suncrest Cir Indianapolis IN 46241",
    "addr:housenumber":"1135",
    "addr:postcode":"46241",
    "addr:street":"Suncrest Cir",
    "iso:country":"US",
    "sg:address":"1135 Suncrest Cir",
    "sg:city":"Indianapolis",
    "sg:classifiers":[
        {
            "category":"Real Estate",
            "subcategory":"Real Estate Operator",
            "type":"Services"
        }
    ],
    "sg:phone":"+1 317 248 1880",
    "sg:postcode":"46241",
    "sg:province":"IN",
    "sg:tags":[
        "apartment"
    ],
    "wof:name":"Suncrest Apartments",
    "wof:placetype":"venue"
},
  "geometry": {"coordinates":[-86.26186800000001,39.751951],"type":"Point"}
}