{
  "type": "Feature",
  "properties": {
    "iso:country":"US",
    "sg:address":"1937 S Foundry St",
    "sg:city":"Cambridge City",
    "sg:classifiers":[
        {
            "category":"Professional",
            "subcategory":"Management & Consulting",
            "type":"Services"
        }
    ],
    "sg:phone":"+1 765 478 9807",
    "sg:postcode":"47327",
    "sg:province":"IN",
    "sg:tags":[
        "marketing",
        "consultant"
    ],
    "wof:name":"MVP Sports Marketing",
    "wof:placetype":"venue"
},
  "geometry": {"coordinates":[-85.202128,39.805659],"type":"Point"}
}