{
  "type": "Feature",
  "properties": {
    "addr:full":"202 W Daisy Ln New Albany IN 47150",
    "addr:housenumber":"202",
    "addr:postcode":"47150",
    "addr:street":"W Daisy Ln",
    "iso:country":"US",
    "sg:address":"202 W Daisy Ln",
    "sg:city":"New Albany",
    "sg:classifiers":[
        {
            "category":"Building & Trades",
            "subcategory":"Landscaping Services",
            "type":"Services"
        }
    ],
    "sg:phone":"+1 812 948 0846",
    "sg:postcode":"47150",
    "sg:province":"IN",
    "wof:name":"Trees Unilimited",
    "wof:placetype":"venue"
},
  "geometry": {"coordinates":[-85.838578,38.310129],"type":"Point"}
}