{
  "type": "Feature",
  "properties": {
    "iso:country":"US",
    "sg:address":"3733 N 400 W",
    "sg:city":"Anderson",
    "sg:classifiers":[
        {
            "category":"Farming",
            "subcategory":"Livestock Farm",
            "type":"Manufacturing & Wholesale Goods"
        }
    ],
    "sg:phone":"+1 765 644 0141",
    "sg:postcode":"46011",
    "sg:province":"IN",
    "sg:tags":[
        "beef",
        "feedlot",
        "cattle"
    ],
    "wof:name":"Brad Clevenger",
    "wof:placetype":"venue"
},
  "geometry": {"coordinates":[-85.74761599999999,40.160325],"type":"Point"}
}