{
  "type": "Feature",
  "properties": {
    "iso:country":"US",
    "sg:address":"1410 W 86th St",
    "sg:city":"Indianapolis",
    "sg:classifiers":[
        {
            "category":"Banks & Credit Unions",
            "subcategory":"Investment Brokerage",
            "type":"Services"
        },
        {
            "category":"Cinema",
            "subcategory":"Movie Rental",
            "type":"Entertainment"
        },
        {
            "category":"Shopping",
            "subcategory":"Computers & Home Electronics",
            "type":"Retail Goods"
        }
    ],
    "sg:phone":"+1 317 228 0011",
    "sg:postcode":"46260",
    "sg:province":"IN",
    "sg:tags":[
        "dvd",
        "sale",
        "dvds-rental",
        "game",
        "tape",
        "video"
    ],
    "sg:website":"http://www.blockbuster.com",
    "wof:name":"Blockbuster Video",
    "wof:placetype":"venue"
},
  "geometry": {"coordinates":[-86.18409699999999,39.912399],"type":"Point"}
}