{
  "type": "Feature",
  "properties": {
    "iso:country":"US",
    "sg:address":"137 Ulen Blvd",
    "sg:city":"Lebanon",
    "sg:classifiers":[
        {
            "category":"Banks & Credit Unions",
            "subcategory":"Investment Brokerage",
            "type":"Services"
        }
    ],
    "sg:phone":"+1 765 482 0924",
    "sg:postcode":"46052",
    "sg:province":"IN",
    "sg:tags":[
        "advisory",
        "financial"
    ],
    "wof:name":"Erskine Investments LLC",
    "wof:placetype":"venue"
},
  "geometry": {"coordinates":[-86.462631,40.066792],"type":"Point"}
}