{
  "type": "Feature",
  "properties": {
    "iso:country":"US",
    "sg:address":"7616 Freedom Woods Dr",
    "sg:city":"Acton",
    "sg:classifiers":[
        {
            "category":"Education",
            "subcategory":"Vocational School",
            "type":"Public Place"
        },
        {
            "category":"Professional",
            "subcategory":"Computer Services",
            "type":"Services"
        }
    ],
    "sg:phone":"+1 317 862 0945",
    "sg:postcode":"46259",
    "sg:province":"IN",
    "sg:tags":[
        "consultant",
        "designer",
        "datum",
        "processing"
    ],
    "wof:name":"Complete Software Solutions",
    "wof:placetype":"venue"
},
  "geometry": {"coordinates":[-86.031035,39.66076],"type":"Point"}
}