{
  "type": "Feature",
  "properties": {
    "iso:country":"US",
    "sg:address":"2922 Coal Mine Rd",
    "sg:city":"Newburgh",
    "sg:classifiers":[
        {
            "category":"Social Services",
            "subcategory":"Child Care",
            "type":"Services"
        }
    ],
    "sg:phone":"+1 812 853 0048",
    "sg:postcode":"47630",
    "sg:province":"IN",
    "wof:name":"Caring Hands",
    "wof:placetype":"venue"
},
  "geometry": {"coordinates":[-87.391097,37.991049],"type":"Point"}
}