{
  "type": "Feature",
  "properties": {
    "iso:country":"US",
    "sg:address":"548 Main St",
    "sg:city":"Brookville",
    "sg:classifiers":[
        {
            "category":"Bars & Pubs",
            "type":"Food & Drink"
        }
    ],
    "sg:phone":"+1 765 647 7994",
    "sg:postcode":"47012",
    "sg:province":"IN",
    "sg:tags":[
        "drinking"
    ],
    "wof:name":"Midtown Tavern",
    "wof:placetype":"venue"
},
  "geometry": {"coordinates":[-85.01280199999999,39.419653],"type":"Point"}
}