{
  "type": "Feature",
  "properties": {
    "iso:country":"US",
    "sg:address":"7213 Locust Ave",
    "sg:city":"Gary",
    "sg:classifiers":[
        {
            "category":"Education",
            "subcategory":"Special Training",
            "type":"Public Place"
        }
    ],
    "sg:phone":"+1 219 938 8105",
    "sg:postcode":"46403",
    "sg:province":"IN",
    "sg:tags":[
        "center"
    ],
    "wof:name":"Edu Care Plaza Substitute Div",
    "wof:placetype":"venue"
},
  "geometry": {"coordinates":[-87.249198,41.618124],"type":"Point"}
}