{
  "type": "Feature",
  "properties": {
    "addr:full":"3015 US Hwy 35 Richmond IN 47374",
    "addr:housenumber":"3015",
    "addr:postcode":"47374",
    "addr:street":"Us Hwy 35",
    "iso:country":"US",
    "sg:address":"3015 US Hwy 35",
    "sg:city":"Richmond",
    "sg:classifiers":[
        {
            "category":"Autos & Motor Vehicles",
            "subcategory":"Automobile Sales",
            "type":"Retail Goods"
        }
    ],
    "sg:phone":"+1 765 962 1445",
    "sg:postcode":"47374",
    "sg:province":"IN",
    "sg:tags":[
        "used"
    ],
    "wof:name":"Reliable Motors",
    "wof:placetype":"venue"
},
  "geometry": {"coordinates":[-84.932044,39.871288],"type":"Point"}
}