{
  "type": "Feature",
  "properties": {
    "iso:country":"US",
    "sg:address":"5930 Staughton Dr",
    "sg:city":"Indianapolis",
    "sg:classifiers":[
        {
            "category":"Shopping",
            "subcategory":"Discount & Variety Stores",
            "type":"Retail Goods"
        }
    ],
    "sg:phone":"+1 317 541 9501",
    "sg:postcode":"46226",
    "sg:province":"IN",
    "wof:name":"Rosie Variety",
    "wof:placetype":"venue"
},
  "geometry": {"coordinates":[-86.065635,39.842333],"type":"Point"}
}