{
  "type": "Feature",
  "properties": {
    "iso:country":"US",
    "sg:address":"10814 Coldwater Rd",
    "sg:city":"Fort Wayne",
    "sg:classifiers":[
        {
            "category":"Insurance",
            "subcategory":"Insurance Agent",
            "type":"Services"
        }
    ],
    "sg:phone":"+1 260 637 7877",
    "sg:postcode":"46845",
    "sg:province":"IN",
    "wof:name":"Swing Insurance",
    "wof:placetype":"venue"
},
  "geometry": {"coordinates":[-85.132181,41.181776],"type":"Point"}
}