{
  "type": "Feature",
  "properties": {
    "addr:full":"8211 Stacy Rd Charlestown IN 47111",
    "addr:housenumber":"8211",
    "addr:postcode":"47111",
    "addr:street":"Stacy Rd",
    "iso:country":"US",
    "sg:address":"8211 Stacy Rd",
    "sg:city":"Charlestown",
    "sg:classifiers":[
        {
            "category":"Organizations",
            "subcategory":"Religious Organization",
            "type":"Services"
        }
    ],
    "sg:phone":"+1 812 256 5339",
    "sg:postcode":"47111",
    "sg:province":"IN",
    "wof:name":"Pleasant Grove Methodist Church",
    "wof:placetype":"venue"
},
  "geometry": {"coordinates":[-85.719398,38.425999],"type":"Point"}
}