{
  "type": "Feature",
  "properties": {
    "iso:country":"US",
    "sg:address":"1359 W Armstrong St",
    "sg:city":"Frankfort",
    "sg:classifiers":[
        {
            "category":"Building & Trades",
            "subcategory":"Plumbing",
            "type":"Services"
        }
    ],
    "sg:phone":"+1 765 659 3622",
    "sg:postcode":"46041",
    "sg:province":"IN",
    "sg:tags":[
        "plumbing",
        "contractor"
    ],
    "wof:name":"AAA Plumbing Of Frankfort",
    "wof:placetype":"venue"
},
  "geometry": {"coordinates":[-86.522744,40.275919],"type":"Point"}
}