{
  "type": "Feature",
  "properties": {
    "iso:country":"US",
    "sg:address":"4177 Jenner Rd",
    "sg:city":"Boonville",
    "sg:classifiers":[
        {
            "category":"Freight",
            "type":"Transportation"
        }
    ],
    "sg:phone":"+1 812 897 2991",
    "sg:postcode":"47601",
    "sg:province":"IN",
    "sg:tags":[
        "carriage"
    ],
    "wof:name":"Crofts Carriage Svc",
    "wof:placetype":"venue"
},
  "geometry": {"coordinates":[-87.321834,38.012126],"type":"Point"}
}