{
  "type": "Feature",
  "properties": {
    "iso:country":"US",
    "sg:address":"263 E Crowe St",
    "sg:city":"Hanover",
    "sg:classifiers":[
        {
            "category":"Real Estate",
            "subcategory":"Real Estate Agent",
            "type":"Services"
        },
        {
            "category":"Professional",
            "subcategory":"Business Services",
            "type":"Services"
        }
    ],
    "sg:phone":"+1 812 866 3300",
    "sg:postcode":"47243",
    "sg:province":"IN",
    "sg:tags":[
        "building",
        "laboratory",
        "s",
        "testing",
        "inspection"
    ],
    "wof:name":"Guardian Inspection Services",
    "wof:placetype":"venue"
},
  "geometry": {"coordinates":[-85.468758,38.714866],"type":"Point"}
}