{
  "type": "Feature",
  "properties": {
    "addr:full":"56605 Woodbine Ln Elkhart IN 46516",
    "addr:housenumber":"56605",
    "addr:postcode":"46516",
    "addr:street":"Woodbine Ln",
    "iso:country":"US",
    "sg:address":"56605 Woodbine Ln",
    "sg:city":"Elkhart",
    "sg:classifiers":[
        {
            "category":"Real Estate",
            "subcategory":"Real Estate Agent",
            "type":"Services"
        }
    ],
    "sg:phone":"+1 574 523 1963",
    "sg:postcode":"46516",
    "sg:province":"IN",
    "wof:name":"Lane Realty Inc",
    "wof:placetype":"venue"
},
  "geometry": {"coordinates":[-85.921306,41.672573],"type":"Point"}
}