{
  "type": "Feature",
  "properties": {
    "iso:country":"US",
    "sg:address":"1243 Summer St",
    "sg:city":"Hammond",
    "sg:classifiers":[
        {
            "category":"Retail",
            "subcategory":"Auto Repair",
            "type":"Services"
        }
    ],
    "sg:phone":"+1 219 931 0721",
    "sg:postcode":"46320",
    "sg:province":"IN",
    "sg:tags":[
        "body",
        "shop"
    ],
    "wof:name":"State Auto Body Inc",
    "wof:placetype":"venue"
},
  "geometry": {"coordinates":[-87.497096,41.608832],"type":"Point"}
}