{
  "type": "Feature",
  "properties": {
    "iso:country":"US",
    "sg:address":"2010 Franklin St",
    "sg:city":"South Bend",
    "sg:classifiers":[
        {
            "category":"Recreation",
            "subcategory":"Arcade",
            "type":"Entertainment"
        }
    ],
    "sg:phone":"+1 574 237 1853",
    "sg:postcode":"46613",
    "sg:province":"IN",
    "sg:tags":[
        "amusement",
        "devices"
    ],
    "wof:name":"Marroni Inc & Dart Shop",
    "wof:placetype":"venue"
},
  "geometry": {"coordinates":[-86.254484,41.653887],"type":"Point"}
}