{
  "type": "Feature",
  "properties": {
    "iso:country":"US",
    "sg:address":"11347 E 900 S",
    "sg:city":"Otterbein",
    "sg:classifiers":[
        {
            "category":"Farming",
            "subcategory":"Farm",
            "type":"Manufacturing & Wholesale Goods"
        }
    ],
    "sg:phone":"+1 765 583 4164",
    "sg:postcode":"47970",
    "sg:province":"IN",
    "sg:tags":[
        "crop",
        "general"
    ],
    "wof:name":"David Gephart",
    "wof:placetype":"venue"
},
  "geometry": {"coordinates":[-87.113152,40.475656],"type":"Point"}
}