{
  "type": "Feature",
  "properties": {
    "iso:country":"US",
    "sg:address":"909 Main St",
    "sg:city":"New Haven",
    "sg:classifiers":[
        {
            "category":"Personal",
            "subcategory":"Beauty Salon",
            "type":"Services"
        }
    ],
    "sg:phone":"+1 260 749 8111",
    "sg:postcode":"46774",
    "sg:province":"IN",
    "wof:name":"Grapevine",
    "wof:placetype":"venue"
},
  "geometry": {"coordinates":[-85.016685,41.073405],"type":"Point"}
}