{
  "type": "Feature",
  "properties": {
    "addr:full":"10412 Allisonville Rd Suite 100 Fishers IN 46038",
    "addr:housenumber":"10412",
    "addr:postcode":"46038",
    "addr:street":"Allisonville Rd Suite 100",
    "iso:country":"US",
    "sg:address":"10412 Allisonville Rd Suite 100",
    "sg:city":"Fishers",
    "sg:classifiers":[
        {
            "category":"Manufacturing",
            "subcategory":"Buildings",
            "type":"Manufacturing & Wholesale Goods"
        },
        {
            "category":"Building & Trades",
            "subcategory":"Construction",
            "type":"Services"
        }
    ],
    "sg:phone":"+1 317 574 5488",
    "sg:postcode":"46038",
    "sg:province":"IN",
    "sg:tags":[
        "home",
        "builder",
        "management",
        "contractor"
    ],
    "wof:name":"Capitol Construction Services Inc.",
    "wof:placetype":"venue"
},
  "geometry": {"coordinates":[-86.05252,39.938495],"type":"Point"}
}