{
  "type": "Feature",
  "properties": {
    "iso:country":"US",
    "sg:address":"7733 E Co Rd 750 N",
    "sg:city":"Twelve Mile",
    "sg:classifiers":[
        {
            "category":"Shopping",
            "subcategory":"Bicycles & Sporting Goods",
            "type":"Retail Goods"
        }
    ],
    "sg:phone":"+1 574 664 5852",
    "sg:postcode":"46988",
    "sg:province":"IN",
    "sg:tags":[
        "gun",
        "gunsmith"
    ],
    "wof:name":"Gun Room Indiana",
    "wof:placetype":"venue"
},
  "geometry": {"coordinates":[-86.228168,40.873722],"type":"Point"}
}