{
  "type": "Feature",
  "properties": {
    "addr:full":"2600 E Willard St Muncie IN 47302",
    "addr:housenumber":"2600",
    "addr:postcode":"47302",
    "addr:street":"E Willard St",
    "iso:country":"US",
    "sg:address":"2600 E Willard St",
    "sg:city":"Muncie",
    "sg:classifiers":[
        {
            "category":"Organizations",
            "subcategory":"Religious Organization",
            "type":"Services"
        }
    ],
    "sg:phone":"+1 765 288 1410",
    "sg:postcode":"47302",
    "sg:province":"IN",
    "sg:tags":[
        "church"
    ],
    "wof:name":"Riverview Church-The Nazarene",
    "wof:placetype":"venue"
},
  "geometry": {"coordinates":[-85.355422,40.18565],"type":"Point"}
}