{
  "type": "Feature",
  "properties": {
    "iso:country":"US",
    "sg:address":"3867 N Aviation Way",
    "sg:city":"Greenfield",
    "sg:classifiers":[
        {
            "category":"Airline",
            "type":"Transportation"
        }
    ],
    "sg:phone":"+1 800 433 7300",
    "sg:postcode":"46140",
    "sg:province":"IN",
    "sg:website":"http://indianapolis.citysearch.com/profile/external/603459292/greenfield_in/american_airlines.html?publisher=yellowpages&reference_id=1&placement=ypwebsitemip",
    "wof:name":"American Airlines",
    "wof:placetype":"venue"
},
  "geometry": {"coordinates":[-85.903915,39.844913],"type":"Point"}
}