{
  "type": "Feature",
  "properties": {
    "iso:country":"US",
    "sg:address":"118 W Clark St",
    "sg:city":"Crown Point",
    "sg:classifiers":[
        {
            "category":"Bars & Pubs",
            "subcategory":"Lounge",
            "type":"Food & Drink"
        }
    ],
    "sg:phone":"+1 219 662 8272",
    "sg:postcode":"46307",
    "sg:province":"IN",
    "sg:website":"www.zombie-club.com",
    "wof:name":"Zombie Club",
    "wof:placetype":"venue"
},
  "geometry": {"coordinates":[-87.36453899999999,41.417942],"type":"Point"}
}