{
  "type": "Feature",
  "properties": {
    "iso:country":"US",
    "sg:address":"1505 E Lincolnway",
    "sg:city":"Laporte",
    "sg:classifiers":[
        {
            "category":"Restaurant",
            "type":"Food & Drink"
        }
    ],
    "sg:phone":"+1 219 362 0200",
    "sg:postcode":"46350",
    "sg:province":"IN",
    "wof:name":"Ma Z's Pizza",
    "wof:placetype":"venue"
},
  "geometry": {"coordinates":[-86.691638,41.624604],"type":"Point"}
}