{
  "type": "Feature",
  "properties": {
    "iso:country":"US",
    "sg:address":"1049 E Lakeshore Dr",
    "sg:city":"Greensburg",
    "sg:classifiers":[
        {
            "category":"Building & Trades",
            "subcategory":"Plumbing",
            "type":"Services"
        }
    ],
    "sg:phone":"+1 812 663 5670",
    "sg:postcode":"47240",
    "sg:province":"IN",
    "sg:tags":[
        "plumbing",
        "air",
        "heating",
        "contractor"
    ],
    "wof:name":"Foster George Plumbing & Htg",
    "wof:placetype":"venue"
},
  "geometry": {"coordinates":[-85.469582,39.328474],"type":"Point"}
}