{
  "type": "Feature",
  "properties": {
    "addr:full":"1435 A St NE Linton IN 47441",
    "addr:housenumber":"1435",
    "addr:postcode":"47441",
    "addr:street":"A St Ne",
    "iso:country":"US",
    "sg:address":"1435 A St NE",
    "sg:city":"Linton",
    "sg:classifiers":[
        {
            "category":"Food & Beverages",
            "subcategory":"Groceries & Convenience Stores",
            "type":"Retail Goods"
        }
    ],
    "sg:phone":"+1 812 847 4826",
    "sg:postcode":"47441",
    "sg:province":"IN",
    "wof:name":"Taylor Bp",
    "wof:placetype":"venue"
},
  "geometry": {"coordinates":[-87.14783300000001,39.037349],"type":"Point"}
}