{
  "type": "Feature",
  "properties": {
    "iso:country":"US",
    "sg:address":"216 N Cleveland St",
    "sg:city":"Indianapolis",
    "sg:classifiers":[
        {
            "category":"Real Estate",
            "subcategory":"Real Estate Operator",
            "type":"Services"
        }
    ],
    "sg:phone":"+1 317 916 2928",
    "sg:postcode":"46204",
    "sg:province":"IN",
    "sg:tags":[
        "condominium"
    ],
    "wof:name":"Clevelander Condominium Assoc",
    "wof:placetype":"venue"
},
  "geometry": {"coordinates":[-86.149776,39.771128],"type":"Point"}
}