{
  "type": "Feature",
  "properties": {
    "iso:country":"US",
    "sg:address":"10702 W 141st Ave",
    "sg:city":"Cedar Lake",
    "sg:classifiers":[
        {
            "category":"Wholesale",
            "subcategory":"Machinery & Supplies",
            "type":"Manufacturing & Wholesale Goods"
        }
    ],
    "sg:phone":"+1 219 374 6856",
    "sg:postcode":"46303",
    "sg:province":"IN",
    "sg:tags":[
        "farm",
        "equipment"
    ],
    "wof:name":"Kretz Equipment",
    "wof:placetype":"venue"
},
  "geometry": {"coordinates":[-87.467997,41.363427],"type":"Point"}
}