{
  "type": "Feature",
  "properties": {
    "iso:country":"US",
    "sg:address":"3138 Broadway St",
    "sg:city":"Fort Wayne",
    "sg:classifiers":[
        {
            "category":"Shopping",
            "subcategory":"Tobacco",
            "type":"Retail Goods"
        }
    ],
    "sg:phone":"+1 260 458 9449",
    "sg:postcode":"46807",
    "sg:province":"IN",
    "sg:tags":[
        "cigarette",
        "product",
        "cigar",
        "dealer"
    ],
    "wof:name":"Twenty Past Four Inc",
    "wof:placetype":"venue"
},
  "geometry": {"coordinates":[-85.154689,41.056508],"type":"Point"}
}