{
  "type": "Feature",
  "properties": {
    "addr:full":"5966 N State Rd 55 Fowler IN 47944",
    "addr:housenumber":"5966;55",
    "addr:postcode":"47944",
    "addr:street":"N State Rd",
    "iso:country":"US",
    "sg:address":"5966 N State Rd 55",
    "sg:city":"Fowler",
    "sg:classifiers":[
        {
            "category":"Real Estate",
            "subcategory":"Real Estate Operator",
            "type":"Services"
        }
    ],
    "sg:phone":"+1 765 884 1539",
    "sg:postcode":"47944",
    "sg:province":"IN",
    "sg:tags":[
        "property",
        "lessor"
    ],
    "wof:name":"Morris Wetli",
    "wof:placetype":"venue"
},
  "geometry": {"coordinates":[-87.324431,40.690743],"type":"Point"}
}