{
  "type": "Feature",
  "properties": {
    "iso:country":"US",
    "sg:address":"310 Pine Dr",
    "sg:city":"Indianapolis",
    "sg:classifiers":[
        {
            "category":"Real Estate",
            "subcategory":"Real Estate Agent",
            "type":"Services"
        }
    ],
    "sg:phone":"+1 317 844 0399",
    "sg:postcode":"46260",
    "sg:province":"IN",
    "wof:name":"Robert B Hollander Co",
    "wof:placetype":"venue"
},
  "geometry": {"coordinates":[-86.16492599999999,39.924157],"type":"Point"}
}