{
  "type": "Feature",
  "properties": {
    "iso:country":"US",
    "sg:address":"1055 Bear Cub Dr",
    "sg:city":"Cicero",
    "sg:classifiers":[
        {
            "category":"Banks & Credit Unions",
            "subcategory":"Bank",
            "type":"Services"
        }
    ],
    "sg:phone":"+1 317 984 7681",
    "sg:postcode":"46034",
    "sg:province":"IN",
    "sg:tags":[
        "broker",
        "mortgage"
    ],
    "wof:name":"Allen-Reid Mortgage Group Inc",
    "wof:placetype":"venue"
},
  "geometry": {"coordinates":[-86.05800600000001,40.124736],"type":"Point"}
}