{
  "type": "Feature",
  "properties": {
    "addr:full":"6336 Travis Rd Greenwood IN 46143",
    "addr:housenumber":"6336",
    "addr:postcode":"46143",
    "addr:street":"Travis Rd",
    "iso:country":"US",
    "sg:address":"6336 Travis Rd",
    "sg:city":"Greenwood",
    "sg:classifiers":[
        {
            "category":"Manufacturing",
            "subcategory":"Printing",
            "type":"Manufacturing & Wholesale Goods"
        }
    ],
    "sg:phone":"+1 317 422 8231",
    "sg:postcode":"46143",
    "sg:province":"IN",
    "sg:tags":[
        "screen"
    ],
    "wof:name":"Hoosier Screen Printer",
    "wof:placetype":"venue"
},
  "geometry": {"coordinates":[-86.21966,39.569285],"type":"Point"}
}