{
  "type": "Feature",
  "properties": {
    "iso:country":"US",
    "sg:address":"1602 W Smith Valley Rd",
    "sg:city":"Greenwood",
    "sg:classifiers":[
        {
            "category":"Building & Trades",
            "subcategory":"Construction",
            "type":"Services"
        }
    ],
    "sg:phone":"+1 317 881 6275",
    "sg:postcode":"46142",
    "sg:province":"IN",
    "sg:tags":[
        "contractor"
    ],
    "wof:name":"Prestige Homes Inc",
    "wof:placetype":"venue"
},
  "geometry": {"coordinates":[-86.155248,39.606016],"type":"Point"}
}