{
  "type": "Feature",
  "properties": {
    "iso:country":"US",
    "sg:address":"5207 E 38th St",
    "sg:city":"Indianapolis",
    "sg:classifiers":[
        {
            "category":"Shopping",
            "type":"Retail Goods"
        }
    ],
    "sg:phone":"+1 317 549 3880",
    "sg:postcode":"46218",
    "sg:province":"IN",
    "sg:tags":[
        "incense"
    ],
    "wof:name":"Magnifiscents",
    "wof:placetype":"venue"
},
  "geometry": {"coordinates":[-86.08044700000001,39.825409],"type":"Point"}
}