{
  "type": "Feature",
  "properties": {
    "iso:country":"US",
    "sg:address":"4950 W Washington St",
    "sg:city":"Indianapolis",
    "sg:classifiers":[
        {
            "category":"Personal",
            "subcategory":"Beauty Salon",
            "type":"Services"
        }
    ],
    "sg:phone":"+1 317 484 8280",
    "sg:postcode":"46241",
    "sg:province":"IN",
    "sg:tags":[
        "manicuring"
    ],
    "wof:name":"Nice Nails",
    "wof:placetype":"venue"
},
  "geometry": {"coordinates":[-86.243939,39.754835],"type":"Point"}
}