{
  "type": "Feature",
  "properties": {
    "iso:country":"US",
    "sg:address":"260 Ln 120F Hamilton Lake",
    "sg:city":"Hamilton",
    "sg:classifiers":[
        {
            "category":"Travel",
            "subcategory":"Hotels & Motels",
            "type":"Entertainment"
        }
    ],
    "sg:phone":"+1 260 488 2920",
    "sg:postcode":"46742",
    "sg:province":"IN",
    "sg:tags":[
        "resort"
    ],
    "sg:website":"www.cold-springs-resort.com",
    "wof:name":"Cold Springs Golf Course",
    "wof:placetype":"venue"
},
  "geometry": {"coordinates":[-84.910234,41.55669],"type":"Point"}
}