{
  "type": "Feature",
  "properties": {
    "iso:country":"US",
    "sg:address":"553 S 1100 E",
    "sg:city":"Greentown",
    "sg:classifiers":[
        {
            "category":"Wholesale",
            "subcategory":"Groceries",
            "type":"Manufacturing & Wholesale Goods"
        }
    ],
    "sg:phone":"+1 765 628 2282",
    "sg:postcode":"46970",
    "sg:province":"IN",
    "sg:tags":[
        "honey"
    ],
    "wof:name":"Larry's Honey",
    "wof:placetype":"venue"
},
  "geometry": {"coordinates":[-86.165933,40.722038],"type":"Point"}
}