{
  "type": "Feature",
  "properties": {
    "iso:country":"US",
    "sg:address":"2160 Cottage Ave",
    "sg:city":"Columbus",
    "sg:classifiers":[
        {
            "category":"Retail",
            "subcategory":"Repair Shop",
            "type":"Services"
        }
    ],
    "sg:phone":"+1 812 378 1967",
    "sg:postcode":"47201",
    "sg:province":"IN",
    "sg:tags":[
        "antique",
        "restoring"
    ],
    "wof:name":"B W Restorations",
    "wof:placetype":"venue"
},
  "geometry": {"coordinates":[-85.905479,39.219607],"type":"Point"}
}