{
  "type": "Feature",
  "properties": {
    "iso:country":"US",
    "sg:address":"911 N State Rd 135",
    "sg:city":"Greenwood",
    "sg:classifiers":[
        {
            "category":"Restaurant",
            "type":"Food & Drink"
        }
    ],
    "sg:phone":"+1 317 889 1200",
    "sg:postcode":"46142",
    "sg:province":"IN",
    "wof:name":"Stone Creek Dining Co",
    "wof:placetype":"venue"
},
  "geometry": {"coordinates":[-86.158336,39.62919],"type":"Point"}
}