{
  "type": "Feature",
  "properties": {
    "iso:country":"US",
    "sg:address":"2820 Main St",
    "sg:city":"Elwood",
    "sg:classifiers":[
        {
            "category":"Restaurant",
            "type":"Food & Drink"
        }
    ],
    "sg:menulink":"http://www.allmenus.com/in/pipe-creek/155796-hardees/menu/",
    "sg:phone":"+1 765 552 2345",
    "sg:postcode":"46036",
    "sg:province":"IN",
    "sg:tags":[
        "burger",
        "american"
    ],
    "wof:name":"Hardee's",
    "wof:placetype":"venue"
},
  "geometry": {"coordinates":[-85.824406,40.277043],"type":"Point"}
}