{
  "type": "Feature",
  "properties": {
    "iso:country":"US",
    "sg:address":"6629 Frito Lay Dr",
    "sg:city":"Evansville",
    "sg:classifiers":[
        {
            "category":"Home & Garden",
            "subcategory":"Carpets & Floor Coverings",
            "type":"Retail Goods"
        }
    ],
    "sg:phone":"+1 812 479 8066",
    "sg:postcode":"47715",
    "sg:province":"IN",
    "sg:tags":[
        "dealer",
        "rug"
    ],
    "wof:name":"Mc Millen Carpet Receivers Inc",
    "wof:placetype":"venue"
},
  "geometry": {"coordinates":[-87.471339,38.007661],"type":"Point"}
}