{
  "type": "Feature",
  "properties": {
    "iso:country":"US",
    "sg:address":"2960 Covert Ave",
    "sg:city":"Evansville",
    "sg:classifiers":[
        {
            "category":"Restaurant",
            "type":"Food & Drink"
        }
    ],
    "sg:menulink":"http://www.allmenus.com/in/knight/186319-mcdonalds/menu/",
    "sg:postcode":"47714",
    "sg:province":"IN",
    "sg:tags":[
        "burger",
        "american"
    ],
    "wof:name":"McDonald's",
    "wof:placetype":"venue"
},
  "geometry": {"coordinates":[-87.513965,37.955531],"type":"Point"}
}