{
  "type": "Feature",
  "properties": {
    "addr:full":"1 E National Ave Brazil IN 47834",
    "addr:housenumber":"1",
    "addr:postcode":"47834",
    "addr:street":"E National Ave",
    "iso:country":"US",
    "sg:address":"1 E National Ave",
    "sg:city":"Brazil",
    "sg:classifiers":[
        {
            "category":"Banks & Credit Unions",
            "subcategory":"Financial Services",
            "type":"Services"
        }
    ],
    "sg:phone":"+1 812 448 2611",
    "sg:postcode":"47834",
    "sg:province":"IN",
    "sg:tags":[
        "company",
        "holding"
    ],
    "wof:name":"R N B Bancorp",
    "wof:placetype":"venue"
},
  "geometry": {"coordinates":[-87.12706799999999,39.523202],"type":"Point"}
}