{
  "type": "Feature",
  "properties": {
    "iso:country":"US",
    "sg:address":"1535 Blue Grass Pkwy",
    "sg:city":"Greenwood",
    "sg:classifiers":[
        {
            "category":"Building & Trades",
            "subcategory":"Construction",
            "type":"Services"
        }
    ],
    "sg:phone":"+1 317 887 1555",
    "sg:postcode":"46143",
    "sg:province":"IN",
    "sg:tags":[
        "home",
        "builder"
    ],
    "wof:name":"Beazer Homes",
    "wof:placetype":"venue"
},
  "geometry": {"coordinates":[-86.090113,39.594903],"type":"Point"}
}