{
  "type": "Feature",
  "properties": {
    "iso:country":"US",
    "sg:address":"6898 N Clinton St",
    "sg:city":"Terre Haute",
    "sg:classifiers":[
        {
            "category":"Education",
            "subcategory":"Special Training",
            "type":"Public Place"
        }
    ],
    "sg:phone":"+1 812 466 2229",
    "sg:postcode":"47805",
    "sg:province":"IN",
    "sg:tags":[
        "aircraft",
        "school"
    ],
    "wof:name":"Brown Flying School Inc",
    "wof:placetype":"venue"
},
  "geometry": {"coordinates":[-87.370024,39.549682],"type":"Point"}
}