{
  "type": "Feature",
  "properties": {
    "addr:full":"1015 W 15th St Anderson IN 46016",
    "addr:housenumber":"1015",
    "addr:postcode":"46016",
    "addr:street":"W 15Th St",
    "iso:country":"US",
    "sg:address":"1015 W 15th St",
    "sg:city":"Anderson",
    "sg:classifiers":[
        {
            "category":"Organizations",
            "subcategory":"Membership Organization",
            "type":"Services"
        }
    ],
    "sg:phone":"+1 765 649 4231",
    "sg:postcode":"46016",
    "sg:province":"IN",
    "wof:name":"NAACP Headquarters",
    "wof:placetype":"venue"
},
  "geometry": {"coordinates":[-85.692978,40.100918],"type":"Point"}
}