{
  "type": "Feature",
  "properties": {
    "iso:country":"US",
    "sg:address":"313 N Mulberry St",
    "sg:city":"Muncie",
    "sg:classifiers":[
        {
            "category":"Organizations",
            "subcategory":"Labor Organization",
            "type":"Services"
        }
    ],
    "sg:phone":"+1 765 289 4321",
    "sg:postcode":"47305",
    "sg:province":"IN",
    "wof:name":"UAW",
    "wof:placetype":"venue"
},
  "geometry": {"coordinates":[-85.385391,40.196128],"type":"Point"}
}