{
  "type": "Feature",
  "properties": {
    "iso:country":"US",
    "sg:address":"10600 Old State Rd",
    "sg:city":"Evansville",
    "sg:classifiers":[
        {
            "category":"Organizations",
            "subcategory":"Professional Association",
            "type":"Services"
        }
    ],
    "sg:phone":"+1 812 867 2433",
    "sg:postcode":"47711",
    "sg:province":"IN",
    "sg:website":"www.sinfonia.net",
    "wof:name":"Phi Mu Alpha Fraternity",
    "wof:placetype":"venue"
},
  "geometry": {"coordinates":[-87.561139,38.077423],"type":"Point"}
}