{
  "type": "Feature",
  "properties": {
    "iso:country":"US",
    "sg:address":"103 E Union St",
    "sg:city":"Liberty",
    "sg:classifiers":[
        {
            "category":"Organizations",
            "subcategory":"Religious Organization",
            "type":"Services"
        }
    ],
    "sg:phone":"+1 765 458 7349",
    "sg:postcode":"47353",
    "sg:province":"IN",
    "sg:tags":[
        "church"
    ],
    "wof:name":"First Presbyterian Church",
    "wof:placetype":"venue"
},
  "geometry": {"coordinates":[-84.928482,39.635514],"type":"Point"}
}