{
  "type": "Feature",
  "properties": {
    "addr:full":"4102 Robinwood Dr Fort Wayne IN 46806",
    "addr:housenumber":"4102",
    "addr:postcode":"46806",
    "addr:street":"Robinwood Dr",
    "iso:country":"US",
    "sg:address":"4102 Robinwood Dr",
    "sg:city":"Fort Wayne",
    "sg:classifiers":[
        {
            "category":"Personal",
            "subcategory":"Beauty Salon",
            "type":"Services"
        }
    ],
    "sg:phone":"+1 260 744 2645",
    "sg:postcode":"46806",
    "sg:province":"IN",
    "wof:name":"Lady's First",
    "wof:placetype":"venue"
},
  "geometry": {"coordinates":[-85.11869,41.046218],"type":"Point"}
}