{
  "type": "Feature",
  "properties": {
    "addr:full":"285 John St Noblesville IN 46060",
    "addr:housenumber":"285",
    "addr:postcode":"46060",
    "addr:street":"John St",
    "iso:country":"US",
    "sg:address":"285 John St",
    "sg:city":"Noblesville",
    "sg:classifiers":[
        {
            "category":"Building & Trades",
            "subcategory":"Cleaning & Sanitation",
            "type":"Services"
        }
    ],
    "sg:phone":"+1 317 356 9073",
    "sg:postcode":"46060",
    "sg:province":"IN",
    "sg:tags":[
        "maintenance"
    ],
    "wof:name":"A One Spotless Window Clg 2000",
    "wof:placetype":"venue"
},
  "geometry": {"coordinates":[-86.02195399999999,40.048957],"type":"Point"}
}