{
  "type": "Feature",
  "properties": {
    "iso:country":"US",
    "sg:address":"1550 Linda Ln",
    "sg:city":"Bloomington",
    "sg:classifiers":[
        {
            "category":"Building & Trades",
            "subcategory":"Construction",
            "type":"Services"
        }
    ],
    "sg:phone":"+1 812 824 4146",
    "sg:postcode":"47401",
    "sg:province":"IN",
    "sg:tags":[
        "downspouts",
        "gutter",
        "contractor"
    ],
    "wof:name":"Jerry's Seamless Gutter",
    "wof:placetype":"venue"
},
  "geometry": {"coordinates":[-86.51797000000001,39.09678],"type":"Point"}
}