{
  "type": "Feature",
  "properties": {
    "iso:country":"US",
    "sg:address":"3343 Central Ave",
    "sg:city":"Indianapolis",
    "sg:classifiers":[
        {
            "category":"Manufacturing",
            "subcategory":"Buildings",
            "type":"Manufacturing & Wholesale Goods"
        },
        {
            "category":"Building & Trades",
            "subcategory":"Construction",
            "type":"Services"
        }
    ],
    "sg:phone":"+1 317 924 4180",
    "sg:postcode":"46205",
    "sg:province":"IN",
    "sg:tags":[
        "home",
        "builder",
        "contractor"
    ],
    "wof:name":"Minority Construction Group",
    "wof:placetype":"venue"
},
  "geometry": {"coordinates":[-86.14966800000001,39.816511],"type":"Point"}
}