{
  "type": "Feature",
  "properties": {
    "iso:country":"US",
    "sg:address":"7955 N Co Rd 1000 E",
    "sg:city":"Hope",
    "sg:classifiers":[
        {
            "category":"Farming",
            "subcategory":"Livestock Farm",
            "type":"Manufacturing & Wholesale Goods"
        }
    ],
    "sg:phone":"+1 812 546 4078",
    "sg:postcode":"47246",
    "sg:province":"IN",
    "sg:tags":[
        "hog",
        "or",
        "feedlot"
    ],
    "wof:name":"Steven Nading",
    "wof:placetype":"venue"
},
  "geometry": {"coordinates":[-85.723964,39.286937],"type":"Point"}
}