{
  "type": "Feature",
  "properties": {
    "iso:country":"US",
    "sg:address":"402 W Jasper St",
    "sg:city":"Goodland",
    "sg:classifiers":[
        {
            "category":"Restaurant",
            "type":"Food & Drink"
        }
    ],
    "sg:phone":"+1 219 297 3090",
    "sg:postcode":"47948",
    "sg:province":"IN",
    "wof:name":"Catch 24",
    "wof:placetype":"venue"
},
  "geometry": {"coordinates":[-87.301039,40.765693],"type":"Point"}
}