{
  "type": "Feature",
  "properties": {
    "iso:country":"US",
    "sg:address":"400 W 250 S",
    "sg:city":"Peru",
    "sg:classifiers":[
        {
            "category":"Freight",
            "type":"Transportation"
        }
    ],
    "sg:phone":"+1 765 472 4600",
    "sg:postcode":"46970",
    "sg:province":"IN",
    "sg:tags":[
        "trucking"
    ],
    "wof:name":"Diamond Trucking Inc",
    "wof:placetype":"venue"
},
  "geometry": {"coordinates":[-86.077824,40.728992],"type":"Point"}
}