{
  "type": "Feature",
  "properties": {
    "iso:country":"US",
    "sg:address":"5920 Warnke Rd",
    "sg:city":"Michigan City",
    "sg:classifiers":[
        {
            "category":"Wholesale",
            "subcategory":"Non-durable Goods",
            "type":"Manufacturing & Wholesale Goods"
        }
    ],
    "sg:phone":"+1 219 874 7971",
    "sg:postcode":"46360",
    "sg:province":"IN",
    "sg:tags":[
        "advertising"
    ],
    "wof:name":"Direct Impact Marketing Group",
    "wof:placetype":"venue"
},
  "geometry": {"coordinates":[-86.814595,41.708603],"type":"Point"}
}