{
  "type": "Feature",
  "properties": {
    "addr:full":"1700 Wabash Ave Lafayette IN 47909",
    "addr:housenumber":"1700",
    "addr:postcode":"47909",
    "addr:street":"Wabash Ave",
    "iso:country":"US",
    "sg:address":"1700 Wabash Ave",
    "sg:city":"Lafayette",
    "sg:classifiers":[
        {
            "category":"Government",
            "subcategory":"Office",
            "type":"Public Place"
        }
    ],
    "sg:phone":"+1 765 476 4550",
    "sg:postcode":"47909",
    "sg:province":"IN",
    "sg:tags":[
        "city",
        "program"
    ],
    "wof:name":"Lafayette Water Pollution Ctrl",
    "wof:placetype":"venue"
},
  "geometry": {"coordinates":[-86.91126199999999,40.400618],"type":"Point"}
}