{
  "type": "Feature",
  "properties": {
    "iso:country":"US",
    "sg:address":"8506 E Ryerson Rd",
    "sg:city":"Pierceton",
    "sg:classifiers":[
        {
            "category":"Building & Trades",
            "subcategory":"Construction",
            "type":"Services"
        }
    ],
    "sg:phone":"+1 574 594 2142",
    "sg:postcode":"46562",
    "sg:province":"IN",
    "sg:tags":[
        "company"
    ],
    "wof:name":"Dale Wilcoxson Construction",
    "wof:placetype":"venue"
},
  "geometry": {"coordinates":[-85.682815,41.182832],"type":"Point"}
}