{
  "type": "Feature",
  "properties": {
    "iso:country":"US",
    "sg:address":"210 S Lake St",
    "sg:city":"South Bend",
    "sg:classifiers":[
        {
            "category":"Wholesale",
            "subcategory":"Groceries",
            "type":"Manufacturing & Wholesale Goods"
        }
    ],
    "sg:phone":"+1 574 234 3600",
    "sg:postcode":"46619",
    "sg:province":"IN",
    "sg:tags":[
        "food"
    ],
    "wof:name":"Too Much-A Good",
    "wof:placetype":"venue"
},
  "geometry": {"coordinates":[-86.295943,41.672713],"type":"Point"}
}