{
  "type": "Feature",
  "properties": {
    "iso:country":"US",
    "sg:address":"1105 W State Rd 2",
    "sg:city":"Laporte",
    "sg:classifiers":[
        {
            "category":"Wholesale",
            "subcategory":"Hardware",
            "type":"Manufacturing & Wholesale Goods"
        }
    ],
    "sg:phone":"+1 219 325 3556",
    "sg:postcode":"46350",
    "sg:province":"IN",
    "sg:tags":[
        "air",
        "parts",
        "conditioning",
        "supply"
    ],
    "wof:name":"K & L Supply",
    "wof:placetype":"venue"
},
  "geometry": {"coordinates":[-86.731547,41.600834],"type":"Point"}
}