{
  "type": "Feature",
  "properties": {
    "iso:country":"US",
    "sg:address":"1400 S Broad St",
    "sg:city":"Griffith",
    "sg:classifiers":[
        {
            "category":"Organizations",
            "subcategory":"Community Association",
            "type":"Services"
        }
    ],
    "sg:phone":"+1 219 865 8542",
    "sg:postcode":"46319",
    "sg:province":"IN",
    "sg:tags":[
        "social"
    ],
    "wof:name":"Knights Of Columbus",
    "wof:placetype":"venue"
},
  "geometry": {"coordinates":[-87.427573,41.500649],"type":"Point"}
}