{
  "type": "Feature",
  "properties": {
    "iso:country":"US",
    "sg:address":"10 Coronado Rd",
    "sg:city":"Indianapolis",
    "sg:classifiers":[
        {
            "category":"Professional",
            "subcategory":"Credit Reporting & Collection",
            "type":"Services"
        }
    ],
    "sg:phone":"+1 317 273 1200",
    "sg:postcode":"46234",
    "sg:province":"IN",
    "sg:tags":[
        "agency"
    ],
    "wof:name":"Creditors' Service Of Indiana",
    "wof:placetype":"venue"
},
  "geometry": {"coordinates":[-86.319771,39.765069],"type":"Point"}
}