{
  "type": "Feature",
  "properties": {
    "iso:country":"US",
    "sg:address":"5115 Monroe Ave",
    "sg:city":"Evansville",
    "sg:classifiers":[
        {
            "category":"Restaurant",
            "type":"Food & Drink"
        }
    ],
    "sg:phone":"+1 812 479 6388",
    "sg:postcode":"47715",
    "sg:province":"IN",
    "wof:name":"Carousel",
    "wof:placetype":"venue"
},
  "geometry": {"coordinates":[-87.487008,37.958617],"type":"Point"}
}