{
  "type": "Feature",
  "properties": {
    "iso:country":"US",
    "sg:address":"8923 S Meridian St",
    "sg:city":"Indianapolis",
    "sg:classifiers":[
        {
            "category":"Food & Beverages",
            "subcategory":"Bakery",
            "type":"Retail Goods"
        }
    ],
    "sg:phone":"+1 317 881 9010",
    "sg:postcode":"46217",
    "sg:province":"IN",
    "sg:tags":[
        "baker"
    ],
    "wof:name":"Chezjean Bakery & Deli",
    "wof:placetype":"venue"
},
  "geometry": {"coordinates":[-86.158321,39.635652],"type":"Point"}
}