{
  "type": "Feature",
  "properties": {
    "iso:country":"US",
    "sg:address":"3829 Union St",
    "sg:city":"Lafayette",
    "sg:classifiers":[
        {
            "category":"Shopping",
            "subcategory":"Optical Goods",
            "type":"Retail Goods"
        }
    ],
    "sg:phone":"+1 765 447 4951",
    "sg:postcode":"47905",
    "sg:province":"IN",
    "sg:tags":[
        "contact",
        "lense"
    ],
    "wof:name":"Evans Eye Care",
    "wof:placetype":"venue"
},
  "geometry": {"coordinates":[-86.837417,40.424913],"type":"Point"}
}