{
  "type": "Feature",
  "properties": {
    "iso:country":"US",
    "sg:address":"1149 W 3rd St",
    "sg:city":"Rushville",
    "sg:classifiers":[
        {
            "category":"Shopping",
            "subcategory":"Tobacco",
            "type":"Retail Goods"
        }
    ],
    "sg:phone":"+1 765 932 4587",
    "sg:postcode":"46173",
    "sg:province":"IN",
    "sg:tags":[
        "cigarette",
        "cigar",
        "dealer"
    ],
    "wof:name":"Save On Tobacco",
    "wof:placetype":"venue"
},
  "geometry": {"coordinates":[-85.460982,39.611737],"type":"Point"}
}