{
  "type": "Feature",
  "properties": {
    "iso:country":"US",
    "sg:address":"2312 Sycamore Hills Dr",
    "sg:city":"Fort Wayne",
    "sg:classifiers":[
        {
            "category":"Wholesale",
            "subcategory":"Durable Goods & Equipment",
            "type":"Manufacturing & Wholesale Goods"
        }
    ],
    "sg:phone":"+1 260 625 3311",
    "sg:postcode":"46814",
    "sg:province":"IN",
    "sg:tags":[
        "representative",
        "manufacturer"
    ],
    "wof:name":"Jacon Equipment Co",
    "wof:placetype":"venue"
},
  "geometry": {"coordinates":[-85.282005,41.062366],"type":"Point"}
}