{
  "type": "Feature",
  "properties": {
    "addr:full":"6810 Shore Ter Indianapolis IN 46254",
    "addr:housenumber":"6810",
    "addr:postcode":"46254",
    "addr:street":"Shore Ter",
    "iso:country":"US",
    "sg:address":"6810 Shore Ter",
    "sg:city":"Indianapolis",
    "sg:classifiers":[
        {
            "category":"Health Services",
            "subcategory":"Health Practitioner",
            "type":"Services"
        }
    ],
    "sg:phone":"+1 317 290 1177",
    "sg:postcode":"46254",
    "sg:province":"IN",
    "sg:tags":[
        "therapist",
        "physical"
    ],
    "wof:name":"Advanced Physical Therapy",
    "wof:placetype":"venue"
},
  "geometry": {"coordinates":[-86.280092,39.830006],"type":"Point"}
}