{
  "type": "Feature",
  "properties": {
    "iso:country":"US",
    "sg:address":"10850 S Washington Rd",
    "sg:city":"Columbia City",
    "sg:classifiers":[
        {
            "category":"Retail",
            "subcategory":"Repair Shop",
            "type":"Services"
        }
    ],
    "sg:phone":"+1 260 344 1692",
    "sg:postcode":"46725",
    "sg:province":"IN",
    "sg:tags":[
        "farm",
        "equipment",
        "parts"
    ],
    "wof:name":"Rupley Farm Equipment",
    "wof:placetype":"venue"
},
  "geometry": {"coordinates":[-85.509541,41.006298],"type":"Point"}
}