{
  "type": "Feature",
  "properties": {
    "iso:country":"US",
    "sg:address":"9001 N Kentucky Ave",
    "sg:city":"Evansville",
    "sg:classifiers":[
        {
            "category":"Organizations",
            "subcategory":"Labor Organization",
            "type":"Services"
        }
    ],
    "sg:phone":"+1 812 867 9670",
    "sg:postcode":"47725",
    "sg:province":"IN",
    "wof:name":"IBEW",
    "wof:placetype":"venue"
},
  "geometry": {"coordinates":[-87.545244,38.060145],"type":"Point"}
}