{
  "type": "Feature",
  "properties": {
    "iso:country":"US",
    "sg:address":"300 W 2nd St",
    "sg:city":"Seymour",
    "sg:classifiers":[
        {
            "category":"Health Services",
            "subcategory":"Optometrist",
            "type":"Services"
        }
    ],
    "sg:phone":"+1 812 523 6100",
    "sg:postcode":"47274",
    "sg:province":"IN",
    "wof:name":"Seymour Eye Clinic",
    "wof:placetype":"venue"
},
  "geometry": {"coordinates":[-85.89182,38.958819],"type":"Point"}
}