{
  "type": "Feature",
  "properties": {
    "iso:country":"US",
    "sg:address":"415 E Havens St",
    "sg:city":"Kokomo",
    "sg:classifiers":[
        {
            "category":"Farming",
            "subcategory":"Aquatic Farm",
            "type":"Manufacturing & Wholesale Goods"
        }
    ],
    "sg:phone":"+1 765 457 9291",
    "sg:postcode":"46901",
    "sg:province":"IN",
    "sg:tags":[
        "fish"
    ],
    "wof:name":"Gowdy's Fishery",
    "wof:placetype":"venue"
},
  "geometry": {"coordinates":[-86.127593,40.494268],"type":"Point"}
}