{
  "type": "Feature",
  "properties": {
    "iso:country":"US",
    "sg:address":"101 W Royerton Rd",
    "sg:city":"Muncie",
    "sg:classifiers":[
        {
            "category":"Farming",
            "subcategory":"Nursery",
            "type":"Manufacturing & Wholesale Goods"
        }
    ],
    "sg:phone":"+1 765 747 5126",
    "sg:postcode":"47303",
    "sg:province":"IN",
    "sg:tags":[
        "greenhouse"
    ],
    "wof:name":"G & M Pet & Garden Ctr Inc",
    "wof:placetype":"venue"
},
  "geometry": {"coordinates":[-85.386602,40.26248],"type":"Point"}
}