{
  "type": "Feature",
  "properties": {
    "iso:country":"US",
    "sg:address":"119 W Mitchell St",
    "sg:city":"Kendallville",
    "sg:classifiers":[
        {
            "category":"Insurance",
            "subcategory":"Insurance Agent",
            "type":"Services"
        }
    ],
    "sg:phone":"+1 260 347 5597",
    "sg:postcode":"46755",
    "sg:province":"IN",
    "wof:name":"Thrivent Financial-Lutherans",
    "wof:placetype":"venue"
},
  "geometry": {"coordinates":[-85.265929,41.443807],"type":"Point"}
}