{
  "type": "Feature",
  "properties": {
    "iso:country":"US",
    "sg:address":"712 W Broadway St",
    "sg:city":"Fortville",
    "sg:classifiers":[
        {
            "category":"Wholesale",
            "subcategory":"Auto Parts",
            "type":"Manufacturing & Wholesale Goods"
        }
    ],
    "sg:phone":"+1 317 485 5133",
    "sg:postcode":"46040",
    "sg:province":"IN",
    "sg:tags":[
        "automobile",
        "supply"
    ],
    "sg:website":"www.americanracetires.com",
    "wof:name":"Dayton Enterprises Inc",
    "wof:placetype":"venue"
},
  "geometry": {"coordinates":[-85.853354,39.928753],"type":"Point"}
}