{
  "type": "Feature",
  "properties": {
    "addr:full":"602 N High School Rd Indianapolis IN 46214",
    "addr:housenumber":"602",
    "addr:postcode":"46214",
    "addr:street":"N High School Rd",
    "iso:country":"US",
    "sg:address":"602 N High School Rd",
    "sg:city":"Indianapolis",
    "sg:classifiers":[
        {
            "category":"Health Services",
            "subcategory":"Health Practitioner",
            "type":"Services"
        }
    ],
    "sg:phone":"+1 317 484 5380",
    "sg:postcode":"46214",
    "sg:province":"IN",
    "sg:tags":[
        "psychologist"
    ],
    "wof:name":"Hamilton Center Inc",
    "wof:placetype":"venue"
},
  "geometry": {"coordinates":[-86.27342400000001,39.778838],"type":"Point"}
}