{
  "type": "Feature",
  "properties": {
    "iso:country":"US",
    "sg:address":"11767 W Lake Bluff Rd",
    "sg:city":"Monticello",
    "sg:classifiers":[
        {
            "category":"Building & Trades",
            "subcategory":"Construction",
            "type":"Services"
        }
    ],
    "sg:phone":"+1 574 965 4861",
    "sg:postcode":"47960",
    "sg:province":"IN",
    "sg:tags":[
        "house"
    ],
    "wof:name":"Danny W Thompson Construc",
    "wof:placetype":"venue"
},
  "geometry": {"coordinates":[-86.750508,40.70772],"type":"Point"}
}