{
  "type": "Feature",
  "properties": {
    "iso:country":"US",
    "sg:address":"2336 W Airport Rd",
    "sg:city":"Peru",
    "sg:classifiers":[
        {
            "category":"Insurance",
            "subcategory":"Insurance Agent",
            "type":"Services"
        }
    ],
    "sg:phone":"+1 765 472 4853",
    "sg:postcode":"46970",
    "sg:province":"IN",
    "wof:name":"Duckwall & Assoc",
    "wof:placetype":"venue"
},
  "geometry": {"coordinates":[-86.120177,40.731471],"type":"Point"}
}