{
  "type": "Feature",
  "properties": {
    "iso:country":"US",
    "sg:address":"116 Hillcrest Rd",
    "sg:city":"Portage",
    "sg:classifiers":[
        {
            "category":"Organizations",
            "subcategory":"Religious Organization",
            "type":"Services"
        }
    ],
    "sg:phone":"+1 219 762 1184",
    "sg:postcode":"46368",
    "sg:province":"IN",
    "sg:tags":[
        "church"
    ],
    "wof:name":"Ogden Dunes Community Church",
    "wof:placetype":"venue"
},
  "geometry": {"coordinates":[-87.189995,41.61967],"type":"Point"}
}