{
  "type": "Feature",
  "properties": {
    "addr:full":"5630 Brookville Rd Indianapolis IN 46219",
    "addr:housenumber":"5630",
    "addr:postcode":"46219",
    "addr:street":"Brookville Rd",
    "iso:country":"US",
    "sg:address":"5630 Brookville Rd",
    "sg:city":"Indianapolis",
    "sg:classifiers":[
        {
            "category":"Manufacturing",
            "subcategory":"Retail Goods",
            "type":"Manufacturing & Wholesale Goods"
        }
    ],
    "sg:phone":"+1 317 322 8590",
    "sg:postcode":"46219",
    "sg:province":"IN",
    "sg:tags":[
        "manufacturer"
    ],
    "wof:name":"Mccallisters Industries",
    "wof:placetype":"venue"
},
  "geometry": {"coordinates":[-86.072498,39.75994],"type":"Point"}
}