{
  "type": "Feature",
  "properties": {
    "iso:country":"US",
    "sg:address":"1396 Benham Ave",
    "sg:city":"Elkhart",
    "sg:classifiers":[
        {
            "category":"Real Estate",
            "subcategory":"Real Estate Agent",
            "type":"Services"
        }
    ],
    "sg:phone":"+1 574 295 8392",
    "sg:postcode":"46516",
    "sg:province":"IN",
    "sg:tags":[
        "authorities",
        "housing"
    ],
    "sg:website":"www.ehai.org",
    "wof:name":"Elkhart Housing Authority",
    "wof:placetype":"venue"
},
  "geometry": {"coordinates":[-85.970342,41.675813],"type":"Point"}
}