{
  "type": "Feature",
  "properties": {
    "iso:country":"US",
    "sg:address":"5738 N Ewing St",
    "sg:city":"Indianapolis",
    "sg:classifiers":[
        {
            "category":"Professional",
            "subcategory":"Management & Consulting",
            "type":"Services"
        }
    ],
    "sg:phone":"+1 317 257 5990",
    "sg:postcode":"46220",
    "sg:province":"IN",
    "wof:name":"Better Way Marketing",
    "wof:placetype":"venue"
},
  "geometry": {"coordinates":[-86.106089,39.859637],"type":"Point"}
}