{
  "type": "Feature",
  "properties": {
    "iso:country":"US",
    "sg:address":"224 S Baldwin Ave",
    "sg:city":"Marion",
    "sg:classifiers":[
        {
            "category":"Retail",
            "subcategory":"Auto Repair",
            "type":"Services"
        }
    ],
    "sg:phone":"+1 765 662 3948",
    "sg:postcode":"46952",
    "sg:province":"IN",
    "sg:tags":[
        "muffler",
        "exhaust",
        "system"
    ],
    "wof:name":"Midas Auto Svc Experts",
    "wof:placetype":"venue"
},
  "geometry": {"coordinates":[-85.67581800000001,40.559083],"type":"Point"}
}