{
  "type": "Feature",
  "properties": {
    "addr:full":"215 E Pearl St Portland IN 47371",
    "addr:housenumber":"215",
    "addr:postcode":"47371",
    "addr:street":"E Pearl St",
    "iso:country":"US",
    "sg:address":"215 E Pearl St",
    "sg:city":"Portland",
    "sg:classifiers":[
        {
            "category":"Professional",
            "subcategory":"Accounting & Tax Preparation",
            "type":"Services"
        }
    ],
    "sg:phone":"+1 260 726 4207",
    "sg:postcode":"47371",
    "sg:province":"IN",
    "sg:tags":[
        "accountant"
    ],
    "wof:name":"Honegger Ringger & Co",
    "wof:placetype":"venue"
},
  "geometry": {"coordinates":[-84.975257,40.440368],"type":"Point"}
}