{
  "type": "Feature",
  "properties": {
    "iso:country":"US",
    "sg:address":"2717 S 500 W",
    "sg:city":"New Palestine",
    "sg:classifiers":[
        {
            "category":"Professional",
            "subcategory":"Accounting & Tax Preparation",
            "type":"Services"
        }
    ],
    "sg:phone":"+1 317 861 5379",
    "sg:postcode":"46163",
    "sg:province":"IN",
    "wof:name":"Accounting Partners Inc",
    "wof:placetype":"venue"
},
  "geometry": {"coordinates":[-85.89580599999999,39.75295],"type":"Point"}
}