{
  "type": "Feature",
  "properties": {
    "iso:country":"US",
    "sg:address":"366 W Tansey Xing",
    "sg:city":"Westfield",
    "sg:classifiers":[
        {
            "category":"Building & Trades",
            "subcategory":"Cleaning & Sanitation",
            "type":"Services"
        }
    ],
    "sg:phone":"+1 317 844 7851",
    "sg:postcode":"46074",
    "sg:province":"IN",
    "sg:tags":[
        "maintenance"
    ],
    "wof:name":"Gdh Rainbow Inc",
    "wof:placetype":"venue"
},
  "geometry": {"coordinates":[-86.163652,40.011633],"type":"Point"}
}