{
  "type": "Feature",
  "properties": {
    "iso:country":"US",
    "sg:address":"9939 S State Rd 63",
    "sg:city":"Terre Haute",
    "sg:classifiers":[
        {
            "category":"Real Estate",
            "subcategory":"Developer",
            "type":"Services"
        }
    ],
    "sg:phone":"+1 812 299 5125",
    "sg:postcode":"47802",
    "sg:province":"IN",
    "sg:tags":[
        "cemetery"
    ],
    "sg:website":"www.debaunfuneralhomes.com",
    "wof:name":"New Harmony Cemetery",
    "wof:placetype":"venue"
},
  "geometry": {"coordinates":[-87.49631100000001,39.346331],"type":"Point"}
}