{
  "type": "Feature",
  "properties": {
    "addr:full":"11785 Lawndale Ave Plymouth IN 46563",
    "addr:housenumber":"11785",
    "addr:postcode":"46563",
    "addr:street":"Lawndale Ave",
    "iso:country":"US",
    "sg:address":"11785 Lawndale Ave",
    "sg:city":"Plymouth",
    "sg:classifiers":[
        {
            "category":"Retail",
            "subcategory":"Repair Shop",
            "type":"Services"
        }
    ],
    "sg:phone":"+1 574 936 3016",
    "sg:postcode":"46563",
    "sg:province":"IN",
    "sg:tags":[
        "appliance"
    ],
    "wof:name":"Bruce Cook Appliance Repair",
    "wof:placetype":"venue"
},
  "geometry": {"coordinates":[-86.283929,41.338926],"type":"Point"}
}