{
  "type": "Feature",
  "properties": {
    "iso:country":"US",
    "sg:address":"115 W Main Cross St",
    "sg:city":"Edinburgh",
    "sg:classifiers":[
        {
            "category":"Personal",
            "subcategory":"Beauty Salon",
            "type":"Services"
        }
    ],
    "sg:phone":"+1 812 526 2114",
    "sg:postcode":"46124",
    "sg:province":"IN",
    "wof:name":"Magic Mirror",
    "wof:placetype":"venue"
},
  "geometry": {"coordinates":[-85.967009,39.354215],"type":"Point"}
}