{
  "type": "Feature",
  "properties": {
    "iso:country":"US",
    "sg:address":"1764 E 86th St",
    "sg:city":"Indianapolis",
    "sg:classifiers":[
        {
            "category":"Shopping",
            "subcategory":"Antiques",
            "type":"Retail Goods"
        }
    ],
    "sg:phone":"+1 317 574 1777",
    "sg:postcode":"46240",
    "sg:province":"IN",
    "wof:name":"Smith-Hill Antiques",
    "wof:placetype":"venue"
},
  "geometry": {"coordinates":[-86.130227,39.912597],"type":"Point"}
}