{
  "type": "Feature",
  "properties": {
    "iso:country":"US",
    "sg:address":"1 Industrial Rd",
    "sg:city":"Kingsbury",
    "sg:classifiers":[
        {
            "category":"Professional",
            "subcategory":"Business Services",
            "type":"Services"
        }
    ],
    "sg:phone":"+1 219 393 1908",
    "sg:postcode":"46320",
    "sg:province":"IN",
    "sg:tags":[
        "paper"
    ],
    "wof:name":"Kimedic Technologies",
    "wof:placetype":"venue"
},
  "geometry": {"coordinates":[-87.52116100000001,41.621429],"type":"Point"}
}