{
  "type": "Feature",
  "properties": {
    "addr:full":"6110 Broadway Merrillville IN 46410",
    "addr:housenumber":"6110",
    "addr:postcode":"46410",
    "addr:street":"Broadway",
    "iso:country":"US",
    "sg:address":"6110 Broadway",
    "sg:city":"Merrillville",
    "sg:classifiers":[
        {
            "category":"Professional",
            "subcategory":"Accounting & Tax Preparation",
            "type":"Services"
        }
    ],
    "sg:phone":"+1 219 985 8545",
    "sg:postcode":"46410",
    "sg:province":"IN",
    "sg:tags":[
        "return",
        "filing"
    ],
    "wof:name":"Jackson Hewitt Tax Svc",
    "wof:placetype":"venue"
},
  "geometry": {"coordinates":[-87.336128,41.504721],"type":"Point"}
}