{
  "type": "Feature",
  "properties": {
    "addr:full":"2424 Franklin St Michigan City IN 46360",
    "addr:housenumber":"2424",
    "addr:postcode":"46360",
    "addr:street":"Franklin St",
    "iso:country":"US",
    "sg:address":"2424 Franklin St",
    "sg:city":"Michigan City",
    "sg:classifiers":[
        {
            "category":"Shopping",
            "subcategory":"Computers & Home Electronics",
            "type":"Retail Goods"
        }
    ],
    "sg:phone":"+1 219 874 5600",
    "sg:postcode":"46360",
    "sg:province":"IN",
    "sg:tags":[
        "equipment",
        "dealer"
    ],
    "sg:website":"www.pcdepotmc.com",
    "wof:name":"P C Repair Depot",
    "wof:placetype":"venue"
},
  "geometry": {"coordinates":[-86.894154,41.701917],"type":"Point"}
}