{
  "type": "Feature",
  "properties": {
    "addr:full":"165 S Gardener St Scottsburg IN 47170",
    "addr:housenumber":"165",
    "addr:postcode":"47170",
    "addr:street":"S Gardener St",
    "iso:country":"US",
    "sg:address":"165 S Gardener St",
    "sg:city":"Scottsburg",
    "sg:classifiers":[
        {
            "category":"Personal",
            "subcategory":"Tattoo Parlor",
            "type":"Services"
        }
    ],
    "sg:phone":"+1 812 752 1000",
    "sg:postcode":"47170",
    "sg:province":"IN",
    "sg:tags":[
        "tattooing"
    ],
    "wof:name":"Artistry In Motion",
    "wof:placetype":"venue"
},
  "geometry": {"coordinates":[-85.778325,38.68419],"type":"Point"}
}