{
  "type": "Feature",
  "properties": {
    "iso:country":"US",
    "sg:address":"1579 E Elkhorn Rd",
    "sg:city":"Vincennes",
    "sg:classifiers":[
        {
            "category":"Real Estate",
            "subcategory":"Real Estate Services",
            "type":"Services"
        },
        {
            "category":"Real Estate",
            "subcategory":"Real Estate Agent",
            "type":"Services"
        }
    ],
    "sg:phone":"+1 812 882 5353",
    "sg:postcode":"47591",
    "sg:province":"IN",
    "sg:tags":[
        "buyer",
        "broker"
    ],
    "wof:name":"Mary Kocher Realtor",
    "wof:placetype":"venue"
},
  "geometry": {"coordinates":[-87.510015,38.637642],"type":"Point"}
}