{
  "type": "Feature",
  "properties": {
    "iso:country":"US",
    "sg:address":"2910 Horse Hill West Dr",
    "sg:city":"Indianapolis",
    "sg:classifiers":[
        {
            "category":"Professional",
            "type":"Services"
        }
    ],
    "sg:phone":"+1 317 298 8867",
    "sg:postcode":"46214",
    "sg:province":"IN",
    "wof:name":"Review Servs Co",
    "wof:placetype":"venue"
},
  "geometry": {"coordinates":[-86.297384,39.808386],"type":"Point"}
}