{
  "type": "Feature",
  "properties": {
    "iso:country":"US",
    "sg:address":"1572 S Co Rd 125 W",
    "sg:city":"New Castle",
    "sg:classifiers":[
        {
            "category":"Wholesale",
            "subcategory":"Electrical",
            "type":"Manufacturing & Wholesale Goods"
        }
    ],
    "sg:phone":"+1 765 529 7078",
    "sg:postcode":"47362",
    "sg:province":"IN",
    "sg:tags":[
        "light",
        "tube",
        "bulb"
    ],
    "wof:name":"Maintenance Research",
    "wof:placetype":"venue"
},
  "geometry": {"coordinates":[-85.40911,39.907147],"type":"Point"}
}