{
  "type": "Feature",
  "properties": {
    "iso:country":"US",
    "sg:address":"6345 Carrollton Ave",
    "sg:city":"Indianapolis",
    "sg:classifiers":[
        {
            "category":"Professional",
            "subcategory":"Business Services",
            "type":"Services"
        }
    ],
    "sg:phone":"+1 317 259 5800",
    "sg:postcode":"46220",
    "sg:province":"IN",
    "sg:tags":[
        "water",
        "treatment"
    ],
    "wof:name":"Ideal Water Treatment Inc",
    "wof:placetype":"venue"
},
  "geometry": {"coordinates":[-86.144757,39.871316],"type":"Point"}
}