{
  "type": "Feature",
  "properties": {
    "iso:country":"US",
    "sg:address":"3607 State Rd 337",
    "sg:city":"Orleans",
    "sg:classifiers":[
        {
            "category":"Building & Trades",
            "subcategory":"Electrical",
            "type":"Services"
        }
    ],
    "sg:phone":"+1 812 967 4470",
    "sg:postcode":"47452",
    "sg:province":"IN",
    "sg:tags":[
        "electrical",
        "contractor"
    ],
    "wof:name":"Franks Electric",
    "wof:placetype":"venue"
},
  "geometry": {"coordinates":[-86.344819,38.606039],"type":"Point"}
}