{
  "type": "Feature",
  "properties": {
    "iso:country":"US",
    "sg:address":"405 S Walnut St",
    "sg:city":"Muncie",
    "sg:classifiers":[
        {
            "category":"Recreation",
            "type":"Entertainment"
        }
    ],
    "sg:phone":"+1 765 289 9767",
    "sg:postcode":"47305",
    "sg:province":"IN",
    "sg:tags":[
        "psychic",
        "medium"
    ],
    "wof:name":"Tarot By Sherita",
    "wof:placetype":"venue"
},
  "geometry": {"coordinates":[-85.386622,40.190406],"type":"Point"}
}