{
  "type": "Feature",
  "properties": {
    "iso:country":"US",
    "sg:address":"3573 N Co Rd 450 E",
    "sg:city":"Logansport",
    "sg:classifiers":[
        {
            "category":"Organizations",
            "subcategory":"Religious Organization",
            "type":"Services"
        }
    ],
    "sg:phone":"+1 574 722 2863",
    "sg:postcode":"46947",
    "sg:province":"IN",
    "sg:tags":[
        "church"
    ],
    "wof:name":"Spring Creek Christian Church",
    "wof:placetype":"venue"
},
  "geometry": {"coordinates":[-86.290319,40.816814],"type":"Point"}
}