{
  "type": "Feature",
  "properties": {
    "addr:full":"1900 Kingsbury Ave La Porte IN 46350",
    "addr:housenumber":"1900",
    "addr:postcode":"porte;46350",
    "addr:street":"Kingsbury Ave",
    "iso:country":"US",
    "sg:address":"1900 Kingsbury Ave",
    "sg:city":"La Porte",
    "sg:classifiers":[
        {
            "category":"Restaurant",
            "type":"Food & Drink"
        }
    ],
    "sg:phone":"+1 219 325 3248",
    "sg:postcode":"46350",
    "sg:province":"IN",
    "sg:tags":[
        "eating"
    ],
    "wof:name":"Master Caterers Inc",
    "wof:placetype":"venue"
},
  "geometry": {"coordinates":[-86.70921300000001,41.590381],"type":"Point"}
}