{
  "type": "Feature",
  "properties": {
    "iso:country":"US",
    "sg:address":"1904 K St",
    "sg:city":"Laporte",
    "sg:classifiers":[
        {
            "category":"Building & Trades",
            "subcategory":"Landscaping Services",
            "type":"Services"
        }
    ],
    "sg:phone":"+1 219 324 0454",
    "sg:postcode":"46350",
    "sg:province":"IN",
    "sg:tags":[
        "landscape",
        "contractor"
    ],
    "wof:name":"Noe Landscape & Nursery Inc",
    "wof:placetype":"venue"
},
  "geometry": {"coordinates":[-86.731899,41.589848],"type":"Point"}
}