{
  "type": "Feature",
  "properties": {
    "iso:country":"US",
    "sg:address":"17 E 950 N",
    "sg:city":"Chesterton",
    "sg:classifiers":[
        {
            "category":"Farming",
            "subcategory":"Farm",
            "type":"Manufacturing & Wholesale Goods"
        }
    ],
    "sg:phone":"+1 219 926 7251",
    "sg:postcode":"46304",
    "sg:province":"IN",
    "sg:tags":[
        "crop",
        "general"
    ],
    "wof:name":"Tom Slont",
    "wof:placetype":"venue"
},
  "geometry": {"coordinates":[-87.065329,41.571792],"type":"Point"}
}