{
  "type": "Feature",
  "properties": {
    "iso:country":"US",
    "sg:address":"5942 W US Hwy 36",
    "sg:city":"Greencastle",
    "sg:classifiers":[
        {
            "category":"Retail",
            "subcategory":"Repair Shop",
            "type":"Services"
        }
    ],
    "sg:phone":"+1 765 739 6250",
    "sg:postcode":"46135",
    "sg:province":"IN",
    "sg:tags":[
        "welding"
    ],
    "wof:name":"Stultz Welding",
    "wof:placetype":"venue"
},
  "geometry": {"coordinates":[-86.939453,39.763004],"type":"Point"}
}