{
  "type": "Feature",
  "properties": {
    "addr:full":"1500 N Delaware St Indianapolis IN 46202",
    "addr:housenumber":"1500",
    "addr:postcode":"46202",
    "addr:street":"N Delaware St",
    "iso:country":"US",
    "sg:address":"1500 N Delaware St",
    "sg:city":"Indianapolis",
    "sg:classifiers":[
        {
            "category":"Professional",
            "type":"Services"
        }
    ],
    "sg:phone":"+1 317 283 2514",
    "sg:postcode":"46202",
    "sg:province":"IN",
    "sg:tags":[
        "establishment"
    ],
    "wof:name":"International Center",
    "wof:placetype":"venue"
},
  "geometry": {"coordinates":[-86.15391,39.788427],"type":"Point"}
}