{
  "type": "Feature",
  "properties": {
    "iso:country":"US",
    "sg:address":"1494 N Brick Church Rd",
    "sg:city":"Cambridge City",
    "sg:classifiers":[
        {
            "category":"Real Estate",
            "subcategory":"Real Estate Operator",
            "type":"Services"
        }
    ],
    "sg:phone":"+1 765 478 5488",
    "sg:postcode":"47327",
    "sg:province":"IN",
    "sg:tags":[
        "farm",
        "property",
        "lessor",
        "soybean"
    ],
    "wof:name":"Howard Study",
    "wof:placetype":"venue"
},
  "geometry": {"coordinates":[-85.183219,39.850675],"type":"Point"}
}