{
  "type": "Feature",
  "properties": {
    "iso:country":"US",
    "sg:address":"309 E Jefferson St",
    "sg:city":"Plymouth",
    "sg:classifiers":[
        {
            "category":"Building & Trades",
            "subcategory":"Construction",
            "type":"Services"
        }
    ],
    "sg:phone":"+1 574 936 2513",
    "sg:postcode":"46563",
    "sg:province":"IN",
    "sg:tags":[
        "general",
        "contractor"
    ],
    "wof:name":"Dewitt Construction",
    "wof:placetype":"venue"
},
  "geometry": {"coordinates":[-86.30641799999999,41.34374],"type":"Point"}
}