{
  "type": "Feature",
  "properties": {
    "iso:country":"US",
    "sg:address":"3712 S Lafountain St",
    "sg:city":"Kokomo",
    "sg:classifiers":[
        {
            "category":"Shopping",
            "subcategory":"Crafts & Fabrics",
            "type":"Retail Goods"
        }
    ],
    "sg:phone":"+1 765 453 4652",
    "sg:postcode":"46902",
    "sg:province":"IN",
    "sg:tags":[
        "sewing"
    ],
    "wof:name":"Khadija Yarn Shop",
    "wof:placetype":"venue"
},
  "geometry": {"coordinates":[-86.127071,40.440888],"type":"Point"}
}