{
  "type": "Feature",
  "properties": {
    "addr:full":"2650 E 100 S Lagrange IN 46761",
    "addr:housenumber":"2650",
    "addr:postcode":"46761",
    "addr:street":"E 100 S Lagrange",
    "iso:country":"US",
    "sg:address":"2650 E 100 S",
    "sg:city":"Lagrange",
    "sg:phone":"+1 260 463 2591",
    "sg:postcode":"46761",
    "sg:province":"IN",
    "sg:tags":[
        "farm",
        "corn",
        "beef",
        "feedlot",
        "cattle"
    ],
    "wof:name":"Grossman Buryl",
    "wof:placetype":"venue"
},
  "geometry": {"coordinates":[-85.374606,41.627158],"type":"Point"}
}