{
  "type": "Feature",
  "properties": {
    "addr:full":"1001 Evans Rd Gas City IN 46933",
    "addr:housenumber":"1001",
    "addr:postcode":"46933",
    "addr:street":"Evans Rd",
    "iso:country":"US",
    "sg:address":"1001 Evans Rd",
    "sg:city":"Gas City",
    "sg:classifiers":[
        {
            "category":"Wholesale",
            "subcategory":"Toys & Hobbies",
            "type":"Manufacturing & Wholesale Goods"
        }
    ],
    "sg:phone":"+1 765 674 8571",
    "sg:postcode":"46933",
    "sg:province":"IN",
    "sg:tags":[
        "firework"
    ],
    "sg:website":"www.tntfireworks.com",
    "wof:name":"TNT Fireworks",
    "wof:placetype":"venue"
},
  "geometry": {"coordinates":[-85.616257,40.479771],"type":"Point"}
}