{
  "type": "Feature",
  "properties": {
    "addr:full":"4990 Kessler Boulevard East Dr Indianapolis IN 46220",
    "addr:housenumber":"4990",
    "addr:postcode":"46220",
    "addr:street":"Kessler Boulevard East Dr",
    "iso:country":"US",
    "sg:address":"4990 Kessler Boulevard East Dr",
    "sg:city":"Indianapolis",
    "sg:classifiers":[
        {
            "category":"Social Services",
            "type":"Services"
        },
        {
            "category":"Education",
            "subcategory":"College",
            "type":"Public Place"
        },
        {
            "category":"Organizations",
            "subcategory":"Community Association",
            "type":"Services"
        },
        {
            "category":"Organizations",
            "subcategory":"Membership Organization",
            "type":"Services"
        }
    ],
    "sg:phone":"+1 317 251 4900",
    "sg:postcode":"46220",
    "sg:province":"IN",
    "sg:tags":[
        "fraternal",
        "sorority",
        "housing",
        "student",
        "fraternity"
    ],
    "wof:name":"Millersville Masonic Lodge",
    "wof:placetype":"venue"
},
  "geometry": {"coordinates":[-86.08635099999999,39.858082],"type":"Point"}
}