{
  "type": "Feature",
  "properties": {
    "iso:country":"US",
    "sg:address":"225 W Commercial Ave",
    "sg:city":"Lowell",
    "sg:classifiers":[
        {
            "category":"Freight",
            "type":"Transportation"
        }
    ],
    "sg:phone":"+1 219 808 7221",
    "sg:postcode":"46356",
    "sg:province":"IN",
    "sg:tags":[
        "operator",
        "local",
        "trucking"
    ],
    "wof:name":"Tsm Co",
    "wof:placetype":"venue"
},
  "geometry": {"coordinates":[-87.429091,41.289826],"type":"Point"}
}