{
  "type": "Feature",
  "properties": {
    "iso:country":"US",
    "sg:address":"6150 W Evans Dr",
    "sg:city":"Terre Haute",
    "sg:classifiers":[
        {
            "category":"Food & Beverages",
            "subcategory":"Meat & Fish",
            "type":"Retail Goods"
        }
    ],
    "sg:phone":"+1 812 898 2090",
    "sg:postcode":"47802",
    "sg:province":"IN",
    "sg:tags":[
        "personal"
    ],
    "wof:name":"Pohlman Custom Killing & Proc",
    "wof:placetype":"venue"
},
  "geometry": {"coordinates":[-87.500092,39.303006],"type":"Point"}
}