{
  "type": "Feature",
  "properties": {
    "iso:country":"US",
    "sg:address":"3860 W 3rd St",
    "sg:city":"Bloomington",
    "sg:classifiers":[
        {
            "category":"Restaurant",
            "type":"Food & Drink"
        }
    ],
    "sg:phone":"+1 812 339 4846",
    "sg:postcode":"47404",
    "sg:province":"IN",
    "wof:name":"Pammy's Diner",
    "wof:placetype":"venue"
},
  "geometry": {"coordinates":[-86.581464,39.164714],"type":"Point"}
}