{
  "type": "Feature",
  "properties": {
    "addr:full":"1908 W Lincoln Ave Goshen IN 46526",
    "addr:housenumber":"1908",
    "addr:postcode":"46526",
    "addr:street":"W Lincoln Ave",
    "iso:country":"US",
    "sg:address":"1908 W Lincoln Ave",
    "sg:city":"Goshen",
    "sg:classifiers":[
        {
            "category":"Social Services",
            "type":"Services"
        }
    ],
    "sg:phone":"+1 574 534 2161",
    "sg:postcode":"46526",
    "sg:province":"IN",
    "sg:tags":[
        "counseling"
    ],
    "wof:name":"Jennifer Miller",
    "wof:placetype":"venue"
},
  "geometry": {"coordinates":[-85.866975,41.58655],"type":"Point"}
}