{
  "type": "Feature",
  "properties": {
    "iso:country":"US",
    "sg:address":"691 N 700 W",
    "sg:city":"Hobart",
    "sg:classifiers":[
        {
            "category":"Restaurant",
            "type":"Food & Drink"
        }
    ],
    "sg:phone":"+1 219 759 0087",
    "sg:postcode":"46342",
    "sg:province":"IN",
    "sg:tags":[
        "caterer"
    ],
    "wof:name":"Piggin' Out Catering Co",
    "wof:placetype":"venue"
},
  "geometry": {"coordinates":[-87.201547,41.53473],"type":"Point"}
}