{
  "type": "Feature",
  "properties": {
    "iso:country":"US",
    "sg:address":"109 Gasoline Aly",
    "sg:city":"Indianapolis",
    "sg:classifiers":[
        {
            "category":"Local Transit",
            "type":"Transportation"
        }
    ],
    "sg:phone":"+1 317 484 2273",
    "sg:postcode":"46222",
    "sg:province":"IN",
    "sg:tags":[
        "ambulance"
    ],
    "wof:name":"Care Ambulance Svc",
    "wof:placetype":"venue"
},
  "geometry": {"coordinates":[-86.234236,39.768223],"type":"Point"}
}