{
  "type": "Feature",
  "properties": {
    "iso:country":"US",
    "sg:address":"1100 E Poplar St",
    "sg:city":"Terre Haute",
    "sg:classifiers":[
        {
            "category":"Organizations",
            "subcategory":"Labor Organization",
            "type":"Services"
        }
    ],
    "sg:phone":"+1 812 232 4384",
    "sg:postcode":"47807",
    "sg:province":"IN",
    "wof:name":"Mid Central Operating Engnrs",
    "wof:placetype":"venue"
},
  "geometry": {"coordinates":[-87.39928399999999,39.462922],"type":"Point"}
}