{
  "type": "Feature",
  "properties": {
    "addr:full":"1150 W 150 N Columbia City IN 46725",
    "addr:housenumber":"1150",
    "addr:postcode":"46725",
    "addr:street":"W 150 N",
    "iso:country":"US",
    "sg:address":"1150 W 150 N",
    "sg:city":"Columbia City",
    "sg:classifiers":[
        {
            "category":"Shopping",
            "subcategory":"Bicycles & Sporting Goods",
            "type":"Retail Goods"
        }
    ],
    "sg:phone":"+1 260 244 5903",
    "sg:postcode":"46725",
    "sg:province":"IN",
    "wof:name":"Sportsworld",
    "wof:placetype":"venue"
},
  "geometry": {"coordinates":[-85.51360099999999,41.18514],"type":"Point"}
}