{
  "type": "Feature",
  "properties": {
    "iso:country":"US",
    "sg:address":"100 High St",
    "sg:city":"Geneva",
    "sg:classifiers":[
        {
            "category":"Health Services",
            "subcategory":"Hospital",
            "type":"Services"
        }
    ],
    "sg:phone":"+1 260 368 7113",
    "sg:postcode":"46740",
    "sg:province":"IN",
    "wof:name":"Adams County Memorial Hospital",
    "wof:placetype":"venue"
},
  "geometry": {"coordinates":[-84.958098,40.592991],"type":"Point"}
}