{
  "type": "Feature",
  "properties": {
    "iso:country":"US",
    "sg:address":"9481 E Backwater Rd",
    "sg:city":"North Webster",
    "sg:classifiers":[
        {
            "category":"Travel",
            "subcategory":"Campground",
            "type":"Entertainment"
        }
    ],
    "sg:phone":"+1 574 834 1200",
    "sg:postcode":"46555",
    "sg:province":"IN",
    "sg:tags":[
        "camp"
    ],
    "wof:name":"Good News Camp",
    "wof:placetype":"venue"
},
  "geometry": {"coordinates":[-85.664693,41.322252],"type":"Point"}
}