{
  "type": "Feature",
  "properties": {
    "iso:country":"US",
    "sg:address":"606 Green Blvd",
    "sg:city":"Aurora",
    "sg:classifiers":[
        {
            "category":"Autos & Motor Vehicles",
            "subcategory":"Fuel & Gas Station",
            "type":"Retail Goods"
        }
    ],
    "sg:phone":"+1 812 926 0651",
    "sg:postcode":"47001",
    "sg:province":"IN",
    "sg:tags":[
        "oil"
    ],
    "sg:website":"www.duncanoil.com",
    "wof:name":"Aurora Citgo",
    "wof:placetype":"venue"
},
  "geometry": {"coordinates":[-84.897723,39.062114],"type":"Point"}
}