{
  "type": "Feature",
  "properties": {
    "iso:country":"US",
    "sg:address":"2300 N Co Rd 250 W",
    "sg:city":"Greensburg",
    "sg:classifiers":[
        {
            "category":"Building & Trades",
            "subcategory":"Equipment Rental",
            "type":"Services"
        }
    ],
    "sg:phone":"+1 812 663 8589",
    "sg:postcode":"47240",
    "sg:province":"IN",
    "sg:tags":[
        "yard"
    ],
    "wof:name":"Recommend Tent Rental",
    "wof:placetype":"venue"
},
  "geometry": {"coordinates":[-85.52229699999999,39.380034],"type":"Point"}
}