{
  "type": "Feature",
  "properties": {
    "iso:country":"US",
    "sg:address":"10698 W US Hwy 30",
    "sg:city":"Wanatah",
    "sg:classifiers":[
        {
            "category":"Freight",
            "type":"Transportation"
        }
    ],
    "sg:phone":"+1 219 733 2871",
    "sg:postcode":"46390",
    "sg:province":"IN",
    "sg:tags":[
        "general"
    ],
    "wof:name":"Bjss Stor & Deluxe Rvs & Boat",
    "wof:placetype":"venue"
},
  "geometry": {"coordinates":[-86.904564,41.434074],"type":"Point"}
}