{
  "type": "Feature",
  "properties": {
    "iso:country":"US",
    "sg:address":"929 Ridge Rd",
    "sg:city":"Munster",
    "sg:classifiers":[
        {
            "category":"Health Services",
            "subcategory":"Doctor",
            "type":"Services"
        }
    ],
    "sg:phone":"+1 219 836 3086",
    "sg:postcode":"46321",
    "sg:province":"IN",
    "sg:tags":[
        "physician",
        "surgeon"
    ],
    "wof:name":"Medina Mecdevitt Patricia MD",
    "wof:placetype":"venue"
},
  "geometry": {"coordinates":[-87.50614899999999,41.560992],"type":"Point"}
}