{
  "type": "Feature",
  "properties": {
    "addr:full":"100 S Main St Ligonier IN 46767",
    "addr:housenumber":"100",
    "addr:postcode":"46767",
    "addr:street":"S Main St",
    "iso:country":"US",
    "sg:address":"100 S Main St",
    "sg:city":"Ligonier",
    "sg:classifiers":[
        {
            "category":"Organizations",
            "subcategory":"Community Association",
            "type":"Services"
        }
    ],
    "sg:phone":"+1 260 894 3430",
    "sg:postcode":"46767",
    "sg:province":"IN",
    "sg:tags":[
        "military"
    ],
    "wof:name":"American Legion",
    "wof:placetype":"venue"
},
  "geometry": {"coordinates":[-85.589184,41.465548],"type":"Point"}
}