{
  "type": "Feature",
  "properties": {
    "iso:country":"US",
    "sg:address":"1201 Oriole Dr",
    "sg:city":"Munster",
    "sg:classifiers":[
        {
            "category":"Manufacturing",
            "subcategory":"Textiles",
            "type":"Manufacturing & Wholesale Goods"
        }
    ],
    "sg:phone":"+1 219 937 9540",
    "sg:postcode":"46321",
    "sg:province":"IN",
    "sg:tags":[
        "finishing"
    ],
    "wof:name":"Philley Manufacturing",
    "wof:placetype":"venue"
},
  "geometry": {"coordinates":[-87.498123,41.544774],"type":"Point"}
}