{
  "type": "Feature",
  "properties": {
    "iso:country":"US",
    "sg:address":"4122 Alabama St",
    "sg:city":"Hobart",
    "sg:classifiers":[
        {
            "category":"Building & Trades",
            "subcategory":"Electrical",
            "type":"Services"
        }
    ],
    "sg:phone":"+1 219 942 1871",
    "sg:postcode":"46342",
    "sg:province":"IN",
    "sg:tags":[
        "electric",
        "contractor"
    ],
    "wof:name":"Stimack & Popov Electric",
    "wof:placetype":"venue"
},
  "geometry": {"coordinates":[-87.314621,41.543017],"type":"Point"}
}