{
  "type": "Feature",
  "properties": {
    "addr:full":"1707 E Market St Huntington IN 46750",
    "addr:housenumber":"1707",
    "addr:postcode":"46750",
    "addr:street":"E Market St",
    "iso:country":"US",
    "sg:address":"1707 E Market St",
    "sg:city":"Huntington",
    "sg:classifiers":[
        {
            "category":"Building & Trades",
            "subcategory":"Construction",
            "type":"Services"
        }
    ],
    "sg:phone":"+1 260 356 2135",
    "sg:postcode":"46750",
    "sg:province":"IN",
    "sg:tags":[
        "hanging",
        "contractor"
    ],
    "wof:name":"D & H Painting",
    "wof:placetype":"venue"
},
  "geometry": {"coordinates":[-85.477169,40.886364],"type":"Point"}
}