{
  "type": "Feature",
  "properties": {
    "iso:country":"US",
    "sg:address":"6374 W Jefferson Blvd",
    "sg:city":"Fort Wayne",
    "sg:classifiers":[
        {
            "category":"Home & Garden",
            "subcategory":"Furniture",
            "type":"Retail Goods"
        }
    ],
    "sg:phone":"+1 260 436 3777",
    "sg:postcode":"46804",
    "sg:province":"IN",
    "wof:name":"Hoffman Collection",
    "wof:placetype":"venue"
},
  "geometry": {"coordinates":[-85.225363,41.055645],"type":"Point"}
}