{
  "type": "Feature",
  "properties": {
    "iso:country":"US",
    "sg:address":"919 Ridge Rd",
    "sg:city":"Munster",
    "sg:classifiers":[
        {
            "category":"Government",
            "subcategory":"Office",
            "type":"Public Place"
        }
    ],
    "sg:phone":"+1 219 836 1594",
    "sg:postcode":"46321",
    "sg:province":"IN",
    "sg:tags":[
        "department",
        "transportation"
    ],
    "wof:name":"Munster License Branch 237",
    "wof:placetype":"venue"
},
  "geometry": {"coordinates":[-87.506011,41.560966],"type":"Point"}
}