{
  "type": "Feature",
  "properties": {
    "iso:country":"US",
    "sg:address":"1027 Morrow Way",
    "sg:city":"Fort Wayne",
    "sg:classifiers":[
        {
            "category":"Building & Trades",
            "subcategory":"Construction",
            "type":"Services"
        }
    ],
    "sg:phone":"+1 260 483 0038",
    "sg:postcode":"46808",
    "sg:province":"IN",
    "sg:tags":[
        "insulation",
        "plastering",
        "drywall"
    ],
    "wof:name":"Bobay Terry Remodeling Contr",
    "wof:placetype":"venue"
},
  "geometry": {"coordinates":[-85.154944,41.11227],"type":"Point"}
}