{
  "type": "Feature",
  "properties": {
    "iso:country":"US",
    "sg:address":"2308 N Old Towne Ln",
    "sg:city":"Muncie",
    "sg:classifiers":[
        {
            "category":"Wholesale",
            "subcategory":"Stationery",
            "type":"Manufacturing & Wholesale Goods"
        }
    ],
    "sg:phone":"+1 765 284 2106",
    "sg:postcode":"47304",
    "sg:province":"IN",
    "sg:tags":[
        "business",
        "form",
        "system"
    ],
    "wof:name":"Safeguard Business Systems",
    "wof:placetype":"venue"
},
  "geometry": {"coordinates":[-85.44588,40.214048],"type":"Point"}
}