{
  "type": "Feature",
  "properties": {
    "iso:country":"US",
    "sg:address":"3431 Arlington Manor",
    "sg:city":"Vincennes",
    "sg:classifiers":[
        {
            "category":"Health Services",
            "subcategory":"Clinic",
            "type":"Services"
        }
    ],
    "sg:phone":"+1 812 882 2696",
    "sg:postcode":"47591",
    "sg:province":"IN",
    "sg:tags":[
        "record",
        "medical",
        "auditing",
        "coding"
    ],
    "wof:name":"Hospital Physcn Cding Svcs LLC",
    "wof:placetype":"venue"
},
  "geometry": {"coordinates":[-87.479749,38.692644],"type":"Point"}
}