{
  "type": "Feature",
  "properties": {
    "iso:country":"US",
    "sg:address":"205 E North St",
    "sg:city":"Goodland",
    "sg:classifiers":[
        {
            "category":"Building & Trades",
            "subcategory":"Electrical",
            "type":"Services"
        }
    ],
    "sg:phone":"+1 219 297 3538",
    "sg:postcode":"47948",
    "sg:province":"IN",
    "sg:tags":[
        "electric",
        "contractor"
    ],
    "wof:name":"Sheets Electrical Svc",
    "wof:placetype":"venue"
},
  "geometry": {"coordinates":[-87.291212,40.758308],"type":"Point"}
}