{
  "type": "Feature",
  "properties": {
    "iso:country":"US",
    "sg:address":"5200 Melton Rd",
    "sg:city":"Gary",
    "sg:classifiers":[
        {
            "category":"Autos & Motor Vehicles",
            "subcategory":"Automobile Sales",
            "type":"Retail Goods"
        }
    ],
    "sg:phone":"+1 219 939 1960",
    "sg:postcode":"46403",
    "sg:province":"IN",
    "sg:tags":[
        "car",
        "dealer"
    ],
    "wof:name":"C & G Auto Sales",
    "wof:placetype":"venue"
},
  "geometry": {"coordinates":[-87.275182,41.596187],"type":"Point"}
}