{
  "type": "Feature",
  "properties": {
    "iso:country":"US",
    "sg:address":"4947 S 450 W",
    "sg:city":"New Palestine",
    "sg:classifiers":[
        {
            "category":"Health Services",
            "subcategory":"Clinic",
            "type":"Services"
        }
    ],
    "sg:phone":"+1 317 861 4898",
    "sg:postcode":"46163",
    "sg:province":"IN",
    "sg:tags":[
        "wellness",
        "program"
    ],
    "wof:name":"Nikken Independent Wellness",
    "wof:placetype":"venue"
},
  "geometry": {"coordinates":[-85.88546100000001,39.707158],"type":"Point"}
}