{
  "type": "Feature",
  "properties": {
    "addr:full":"390 Hwy 64 NE New Salisbury IN 47161",
    "addr:housenumber":"390",
    "addr:postcode":"47161",
    "addr:street":"Hwy 64 Ne New",
    "iso:country":"US",
    "sg:address":"390 Hwy 64 NE",
    "sg:city":"New Salisbury",
    "sg:classifiers":[
        {
            "category":"Shopping",
            "subcategory":"Florist",
            "type":"Retail Goods"
        }
    ],
    "sg:phone":"+1 812 347 2485",
    "sg:postcode":"47161",
    "sg:province":"IN",
    "wof:name":"Creative Design",
    "wof:placetype":"venue"
},
  "geometry": {"coordinates":[-86.117761,38.317064],"type":"Point"}
}