{
  "type": "Feature",
  "properties": {
    "iso:country":"US",
    "sg:address":"897 N Co Rd 550 W",
    "sg:city":"Danville",
    "sg:classifiers":[
        {
            "category":"Retail",
            "subcategory":"Repair Shop",
            "type":"Services"
        }
    ],
    "sg:phone":"+1 317 539 7133",
    "sg:postcode":"46122",
    "sg:province":"IN",
    "sg:tags":[
        "repairing",
        "picture",
        "frame",
        "merchandise"
    ],
    "wof:name":"Frames By Laura Inc",
    "wof:placetype":"venue"
},
  "geometry": {"coordinates":[-86.623157,39.760579],"type":"Point"}
}