{
  "type": "Feature",
  "properties": {
    "iso:country":"US",
    "sg:address":"9770 Grant Pl",
    "sg:city":"Crown Point",
    "sg:classifiers":[
        {
            "category":"Retail",
            "subcategory":"Repair Shop",
            "type":"Services"
        }
    ],
    "sg:phone":"+1 219 662 0677",
    "sg:postcode":"46307",
    "sg:province":"IN",
    "wof:name":"Rons Piano Service",
    "wof:placetype":"venue"
},
  "geometry": {"coordinates":[-87.355647,41.441513],"type":"Point"}
}