{
  "type": "Feature",
  "properties": {
    "addr:full":"1308 Dearborn St Huntington IN 46750",
    "addr:housenumber":"1308",
    "addr:postcode":"46750",
    "addr:street":"Dearborn St",
    "iso:country":"US",
    "sg:address":"1308 Dearborn St",
    "sg:city":"Huntington",
    "sg:classifiers":[
        {
            "category":"Social Services",
            "subcategory":"Child Care",
            "type":"Services"
        }
    ],
    "sg:phone":"+1 260 356 0617",
    "sg:postcode":"46750",
    "sg:province":"IN",
    "sg:tags":[
        "day"
    ],
    "wof:name":"Susies Wee Care Day Care",
    "wof:placetype":"venue"
},
  "geometry": {"coordinates":[-85.498262,40.868691],"type":"Point"}
}