{
  "type": "Feature",
  "properties": {
    "iso:country":"US",
    "sg:address":"5699 W State Rd 45",
    "sg:city":"Bloomington",
    "sg:classifiers":[
        {
            "category":"Wholesale",
            "subcategory":"Medical Equipment & Supplies",
            "type":"Manufacturing & Wholesale Goods"
        }
    ],
    "sg:phone":"+1 812 825 6252",
    "sg:postcode":"47403",
    "sg:province":"IN",
    "sg:tags":[
        "hospital"
    ],
    "wof:name":"A C Warehouse",
    "wof:placetype":"venue"
},
  "geometry": {"coordinates":[-86.610191,39.125508],"type":"Point"}
}