{
  "type": "Feature",
  "properties": {
    "iso:country":"US",
    "sg:address":"6528 Ferguson St",
    "sg:city":"Indianapolis",
    "sg:classifiers":[
        {
            "category":"Professional",
            "subcategory":"Management & Consulting",
            "type":"Services"
        }
    ],
    "sg:phone":"+1 317 255 5111",
    "sg:postcode":"46220",
    "sg:province":"IN",
    "sg:tags":[
        "consultant",
        "business"
    ],
    "wof:name":"Management System Consultants",
    "wof:placetype":"venue"
},
  "geometry": {"coordinates":[-86.143662,39.875721],"type":"Point"}
}