{
  "type": "Feature",
  "properties": {
    "iso:country":"US",
    "sg:address":"438 E Lynnwood Dr N",
    "sg:city":"Warsaw",
    "sg:classifiers":[
        {
            "category":"Professional",
            "subcategory":"Computer Services",
            "type":"Services"
        }
    ],
    "sg:phone":"+1 574 269 5066",
    "sg:postcode":"46580",
    "sg:province":"IN",
    "sg:tags":[
        "website",
        "design"
    ],
    "wof:name":"Technical Imprint Inc",
    "wof:placetype":"venue"
},
  "geometry": {"coordinates":[-85.835185,41.20755],"type":"Point"}
}