{
  "type": "Feature",
  "properties": {
    "iso:country":"US",
    "sg:address":"3110 E Wabash St",
    "sg:city":"Frankfort",
    "sg:classifiers":[
        {
            "category":"Retail",
            "subcategory":"Veterinary Services",
            "type":"Services"
        }
    ],
    "sg:phone":"+1 765 654 8686",
    "sg:postcode":"46041",
    "sg:province":"IN",
    "sg:tags":[
        "veterinarian"
    ],
    "wof:name":"Town & Country Veterinary",
    "wof:placetype":"venue"
},
  "geometry": {"coordinates":[-86.465815,40.278844],"type":"Point"}
}