{
  "type": "Feature",
  "properties": {
    "iso:country":"US",
    "sg:address":"620 S Range Line Rd Unit M",
    "sg:city":"Carmel",
    "sg:classifiers":[
        {
            "category":"Arts & Performance",
            "subcategory":"Art Gallery",
            "type":"Entertainment"
        },
        {
            "category":"Coffee & Tea",
            "type":"Food & Drink"
        }
    ],
    "sg:postcode":"46032",
    "sg:province":"IN",
    "sg:website":"www.sohocafecarmel.com",
    "wof:name":"SoHo Cafe & Gallery",
    "wof:placetype":"venue"
},
  "geometry": {"coordinates":[-86.128384,39.971932],"type":"Point"}
}