{
  "type": "Feature",
  "properties": {
    "iso:country":"US",
    "sg:address":"5740 Rolling Ridge Rd",
    "sg:city":"Indianapolis",
    "sg:classifiers":[
        {
            "category":"Professional",
            "type":"Services"
        }
    ],
    "sg:phone":"+1 317 255 1836",
    "sg:postcode":"46220",
    "sg:province":"IN",
    "wof:name":"Playful Dragon Inc",
    "wof:placetype":"venue"
},
  "geometry": {"coordinates":[-86.099925,39.86001],"type":"Point"}
}