{
  "type": "Feature",
  "properties": {
    "addr:full":"2153 W Co Rd 250 S Greensburg IN 47240",
    "addr:housenumber":"2153",
    "addr:postcode":"47240",
    "addr:street":"W Co Rd 250 S",
    "iso:country":"US",
    "sg:address":"2153 W Co Rd 250 S",
    "sg:city":"Greensburg",
    "sg:phone":"+1 812 663 6765",
    "sg:postcode":"47240",
    "sg:province":"IN",
    "sg:tags":[
        "farm",
        "corn"
    ],
    "wof:name":"Charles Kramer",
    "wof:placetype":"venue"
},
  "geometry": {"coordinates":[-85.519845,39.299332],"type":"Point"}
}