{
  "type": "Feature",
  "properties": {
    "iso:country":"US",
    "sg:address":"9205 Avionics Dr",
    "sg:city":"Fort Wayne",
    "sg:classifiers":[
        {
            "category":"Building & Trades",
            "subcategory":"Construction",
            "type":"Services"
        }
    ],
    "sg:phone":"+1 260 478 1492",
    "sg:postcode":"46809",
    "sg:province":"IN",
    "sg:tags":[
        "designer"
    ],
    "wof:name":"Design Facts Inc",
    "wof:placetype":"venue"
},
  "geometry": {"coordinates":[-85.194997,41.002072],"type":"Point"}
}