{
  "type": "Feature",
  "properties": {
    "iso:country":"US",
    "sg:address":"1450 NW 11th St",
    "sg:city":"Richmond",
    "sg:classifiers":[
        {
            "category":"Wholesale",
            "subcategory":"Electrical",
            "type":"Manufacturing & Wholesale Goods"
        }
    ],
    "sg:phone":"+1 765 935 7781",
    "sg:postcode":"47374",
    "sg:province":"IN",
    "sg:tags":[
        "fire",
        "equipment",
        "protection"
    ],
    "sg:website":"www.koorsen.com",
    "wof:name":"Koorsen Fire & Security",
    "wof:placetype":"venue"
},
  "geometry": {"coordinates":[-84.91717,39.846206],"type":"Point"}
}