{
  "type": "Feature",
  "properties": {
    "iso:country":"US",
    "sg:address":"520 Gerber St",
    "sg:city":"Ligonier",
    "sg:classifiers":[
        {
            "category":"Manufacturing",
            "subcategory":"Paper Products",
            "type":"Manufacturing & Wholesale Goods"
        }
    ],
    "sg:phone":"+1 260 894 3136",
    "sg:postcode":"46767",
    "sg:province":"IN",
    "sg:tags":[
        "converted",
        "prod"
    ],
    "sg:website":"www.superiorsample.com",
    "wof:name":"Superior Sample Co",
    "wof:placetype":"venue"
},
  "geometry": {"coordinates":[-85.595885,41.46861],"type":"Point"}
}