{
  "type": "Feature",
  "properties": {
    "iso:country":"US",
    "sg:address":"1980 Lockerbie Dr",
    "sg:city":"Columbus",
    "sg:classifiers":[
        {
            "category":"Building & Trades",
            "subcategory":"Construction",
            "type":"Services"
        }
    ],
    "sg:phone":"+1 812 372 1898",
    "sg:postcode":"47203",
    "sg:province":"IN",
    "sg:tags":[
        "home",
        "improvement"
    ],
    "wof:name":"Richardson's Home Imprvmt Inc",
    "wof:placetype":"venue"
},
  "geometry": {"coordinates":[-85.865723,39.22127],"type":"Point"}
}