{
  "type": "Feature",
  "properties": {
    "iso:country":"US",
    "sg:address":"315 W Main St",
    "sg:city":"Berne",
    "sg:classifiers":[
        {
            "category":"Organizations",
            "subcategory":"Religious Organization",
            "type":"Services"
        }
    ],
    "sg:phone":"+1 260 589 2752",
    "sg:postcode":"46711",
    "sg:province":"IN",
    "sg:tags":[
        "church"
    ],
    "wof:name":"Cross United Church Of Christ",
    "wof:placetype":"venue"
},
  "geometry": {"coordinates":[-84.952847,40.657872],"type":"Point"}
}