{
  "type": "Feature",
  "properties": {
    "addr:full":"6511 Indian Meadow Ln West Lafayette IN 47906",
    "addr:housenumber":"6511",
    "addr:postcode":"47906",
    "addr:street":"Indian Meadow Ln",
    "iso:country":"US",
    "sg:address":"6511 Indian Meadow Ln",
    "sg:city":"West Lafayette",
    "sg:classifiers":[
        {
            "category":"Professional",
            "subcategory":"Engineering",
            "type":"Services"
        }
    ],
    "sg:phone":"+1 765 463 4276",
    "sg:postcode":"47906",
    "sg:province":"IN",
    "sg:tags":[
        "consulting",
        "general"
    ],
    "wof:name":"A F Grandt Consulting",
    "wof:placetype":"venue"
},
  "geometry": {"coordinates":[-86.90151400000001,40.517095],"type":"Point"}
}