{
  "type": "Feature",
  "properties": {
    "iso:country":"US",
    "sg:address":"3510 Pendleton Ave",
    "sg:city":"Anderson",
    "sg:classifiers":[
        {
            "category":"Freight",
            "type":"Transportation"
        }
    ],
    "sg:phone":"+1 765 643 8722",
    "sg:postcode":"46013",
    "sg:province":"IN",
    "sg:tags":[
        "commercial",
        "storage"
    ],
    "wof:name":"Community Storage",
    "wof:placetype":"venue"
},
  "geometry": {"coordinates":[-85.70823300000001,40.076814],"type":"Point"}
}