{
  "type": "Feature",
  "properties": {
    "addr:full":"820 S Adams St Versailles IN 47042",
    "addr:housenumber":"820",
    "addr:postcode":"47042",
    "addr:street":"S Adams St",
    "iso:country":"US",
    "sg:address":"820 S Adams St",
    "sg:city":"Versailles",
    "sg:classifiers":[
        {
            "category":"Real Estate",
            "subcategory":"Real Estate Agent",
            "type":"Services"
        }
    ],
    "sg:phone":"+1 812 689 3808",
    "sg:postcode":"47042",
    "sg:province":"IN",
    "wof:name":"Remax Genisis Realty Group",
    "wof:placetype":"venue"
},
  "geometry": {"coordinates":[-85.25577,39.063086],"type":"Point"}
}