{
  "type": "Feature",
  "properties": {
    "iso:country":"US",
    "sg:address":"2176 N Meridian St",
    "sg:city":"Indianapolis",
    "sg:classifiers":[
        {
            "category":"Government",
            "subcategory":"Fire Station",
            "type":"Public Place"
        },
        {
            "category":"Retail",
            "subcategory":"Laundry & Dry Cleaning",
            "type":"Services"
        },
        {
            "category":"Building & Trades",
            "subcategory":"Cleaning & Sanitation",
            "type":"Services"
        }
    ],
    "sg:phone":"+1 317 920 0016",
    "sg:postcode":"46202",
    "sg:province":"IN",
    "sg:tags":[
        "cleaner",
        "disaster",
        "house",
        "rug",
        "damage",
        "water",
        "restoration",
        "relief",
        "carpet",
        "recovery"
    ],
    "sg:website":"http://www.kleanrestoration.com",
    "wof:name":"Klean Restoration",
    "wof:placetype":"venue"
},
  "geometry": {"coordinates":[-86.157275,39.796859],"type":"Point"}
}