{
  "type": "Feature",
  "properties": {
    "iso:country":"US",
    "sg:address":"105 W Washington St",
    "sg:city":"South Bend",
    "sg:classifiers":[
        {
            "category":"Shopping",
            "subcategory":"Jewelry",
            "type":"Retail Goods"
        }
    ],
    "sg:phone":"+1 574 234 2919",
    "sg:postcode":"46601",
    "sg:province":"IN",
    "sg:tags":[
        "jeweler"
    ],
    "sg:website":"www.golfersgold.com",
    "wof:name":"Van Horne & Co",
    "wof:placetype":"venue"
},
  "geometry": {"coordinates":[-86.25103300000001,41.67645],"type":"Point"}
}