{
  "type": "Feature",
  "properties": {
    "iso:country":"US",
    "sg:address":"10592 Cedar Dr",
    "sg:city":"Fishers",
    "sg:classifiers":[
        {
            "category":"Food & Beverages",
            "subcategory":"Specialty",
            "type":"Retail Goods"
        }
    ],
    "sg:phone":"+1 317 570 1577",
    "sg:postcode":"46037",
    "sg:province":"IN",
    "sg:tags":[
        "health",
        "diet"
    ],
    "wof:name":"Smartbody Nutrition",
    "wof:placetype":"venue"
},
  "geometry": {"coordinates":[-85.979067,39.96145],"type":"Point"}
}