{
  "type": "Feature",
  "properties": {
    "iso:country":"US",
    "sg:address":"275 W 68th Pl",
    "sg:city":"Merrillville",
    "sg:classifiers":[
        {
            "category":"Building & Trades",
            "subcategory":"Plumbing",
            "type":"Services"
        }
    ],
    "sg:phone":"+1 219 769 2716",
    "sg:postcode":"46410",
    "sg:province":"IN",
    "sg:tags":[
        "plumbing",
        "contractor"
    ],
    "wof:name":"Carl & Sons Plumbing",
    "wof:placetype":"venue"
},
  "geometry": {"coordinates":[-87.338438,41.493294],"type":"Point"}
}