{
  "type": "Feature",
  "properties": {
    "addr:full":"10078 Summerlakes Dr Carmel IN 46032",
    "addr:housenumber":"10078",
    "addr:postcode":"46032",
    "addr:street":"Summerlakes Dr",
    "iso:country":"US",
    "sg:address":"10078 Summerlakes Dr",
    "sg:city":"Carmel",
    "sg:classifiers":[
        {
            "category":"Insurance",
            "subcategory":"Insurance Agent",
            "type":"Services"
        }
    ],
    "sg:phone":"+1 317 569 1111",
    "sg:postcode":"46032",
    "sg:province":"IN",
    "wof:name":"Landmark Insurance Co",
    "wof:placetype":"venue"
},
  "geometry": {"coordinates":[-86.190577,39.92939],"type":"Point"}
}