{
  "type": "Feature",
  "properties": {
    "iso:country":"US",
    "sg:address":"435 Harrison St",
    "sg:city":"Charlestown",
    "sg:classifiers":[
        {
            "category":"Organizations",
            "subcategory":"Religious Organization",
            "type":"Services"
        }
    ],
    "sg:phone":"+1 812 256 6178",
    "sg:postcode":"47111",
    "sg:province":"IN",
    "wof:name":"United Church Ministries Inc",
    "wof:placetype":"venue"
},
  "geometry": {"coordinates":[-85.66126800000001,38.445515],"type":"Point"}
}