{
  "type": "Feature",
  "properties": {
    "iso:country":"US",
    "sg:address":"206 W Maumee St",
    "sg:city":"Angola",
    "sg:classifiers":[
        {
            "category":"Shopping",
            "subcategory":"Used Merchandise",
            "type":"Retail Goods"
        },
        {
            "category":"Shopping",
            "subcategory":"Books",
            "type":"Retail Goods"
        }
    ],
    "sg:phone":"+1 260 665 2392",
    "sg:postcode":"46703",
    "sg:province":"IN",
    "sg:tags":[
        "rare",
        "dealer"
    ],
    "wof:name":"Sam's Half Price Book Store",
    "wof:placetype":"venue"
},
  "geometry": {"coordinates":[-85.001584,41.63482],"type":"Point"}
}