{
  "type": "Feature",
  "properties": {
    "iso:country":"US",
    "sg:address":"3715 Washington St",
    "sg:city":"Gary",
    "sg:classifiers":[
        {
            "category":"Real Estate",
            "subcategory":"Real Estate Agent",
            "type":"Services"
        }
    ],
    "sg:phone":"+1 219 887 4300",
    "sg:postcode":"46408",
    "sg:province":"IN",
    "wof:name":"Property Liquidators Inc",
    "wof:placetype":"venue"
},
  "geometry": {"coordinates":[-87.337616,41.549909],"type":"Point"}
}