{
  "type": "Feature",
  "properties": {
    "iso:country":"US",
    "sg:address":"9490 S 600 E-92",
    "sg:city":"Roanoke",
    "sg:classifiers":[
        {
            "category":"Building & Trades",
            "subcategory":"Landscaping Services",
            "type":"Services"
        }
    ],
    "sg:phone":"+1 260 396 2970",
    "sg:postcode":"46783",
    "sg:province":"IN",
    "sg:tags":[
        "landscape",
        "contractor"
    ],
    "wof:name":"Renaissance Management Svc",
    "wof:placetype":"venue"
},
  "geometry": {"coordinates":[-85.374676,41.033244],"type":"Point"}
}