{
  "type": "Feature",
  "properties": {
    "iso:country":"US",
    "sg:address":"5670 Sohl Ave",
    "sg:city":"Hammond",
    "sg:classifiers":[
        {
            "category":"Organizations",
            "subcategory":"Religious Organization",
            "type":"Services"
        }
    ],
    "sg:phone":"+1 219 933 7013",
    "sg:postcode":"46320",
    "sg:province":"IN",
    "sg:tags":[
        "church"
    ],
    "sg:website":"www.hammondfirst.org",
    "wof:name":"First Assembly Of God Hammond",
    "wof:placetype":"venue"
},
  "geometry": {"coordinates":[-87.513822,41.610645],"type":"Point"}
}