{
  "type": "Feature",
  "properties": {
    "iso:country":"US",
    "sg:address":"6451 Pierson Dr",
    "sg:city":"Indianapolis",
    "sg:classifiers":[
        {
            "category":"Autos & Motor Vehicles",
            "subcategory":"Automobile Sales",
            "type":"Retail Goods"
        }
    ],
    "sg:phone":"+1 317 484 2783",
    "sg:postcode":"46241",
    "sg:province":"IN",
    "sg:tags":[
        "aircraft"
    ],
    "wof:name":"Raytheon Aircraft Co",
    "wof:placetype":"venue"
},
  "geometry": {"coordinates":[-86.273861,39.738027],"type":"Point"}
}