{
  "type": "Feature",
  "properties": {
    "iso:country":"US",
    "sg:address":"218 E Lincolnway",
    "sg:city":"Valparaiso",
    "sg:classifiers":[
        {
            "category":"Restaurant",
            "type":"Food & Drink"
        }
    ],
    "sg:phone":"+1 219 464 1018",
    "sg:postcode":"46383",
    "sg:province":"IN",
    "wof:name":"Tony's Place",
    "wof:placetype":"venue"
},
  "geometry": {"coordinates":[-87.057189,41.467791],"type":"Point"}
}