{
  "type": "Feature",
  "properties": {
    "iso:country":"US",
    "sg:address":"3005 N Washington St",
    "sg:city":"Kokomo",
    "sg:classifiers":[
        {
            "category":"Shopping",
            "subcategory":"Tobacco",
            "type":"Retail Goods"
        }
    ],
    "sg:phone":"+1 765 854 3050",
    "sg:postcode":"46901",
    "sg:province":"IN",
    "sg:tags":[
        "cigarette",
        "cigar",
        "dealer"
    ],
    "wof:name":"Little Bobs Discount Tobacco",
    "wof:placetype":"venue"
},
  "geometry": {"coordinates":[-86.130752,40.517179],"type":"Point"}
}