{
  "type": "Feature",
  "properties": {
    "addr:full":"6312 S Flatwood Rd Pekin IN 47165",
    "addr:housenumber":"6312",
    "addr:postcode":"47165",
    "addr:street":"S Flatwood Rd",
    "iso:country":"US",
    "sg:address":"6312 S Flatwood Rd",
    "sg:city":"Pekin",
    "sg:classifiers":[
        {
            "category":"Home & Garden",
            "subcategory":"Hardware",
            "type":"Retail Goods"
        }
    ],
    "sg:phone":"+1 812 967 3322",
    "sg:postcode":"47165",
    "sg:province":"IN",
    "sg:tags":[
        "saw"
    ],
    "wof:name":"Mount Outdoor Power Equipment",
    "wof:placetype":"venue"
},
  "geometry": {"coordinates":[-85.867609,38.519299],"type":"Point"}
}