{
  "type": "Feature",
  "properties": {
    "iso:country":"US",
    "sg:address":"7509 Eagle Crest Blvd",
    "sg:city":"Evansville",
    "sg:classifiers":[
        {
            "category":"Insurance",
            "subcategory":"Insurance Agent",
            "type":"Services"
        }
    ],
    "sg:phone":"+1 812 469 7576",
    "sg:postcode":"47715",
    "sg:province":"IN",
    "wof:name":"Acordia",
    "wof:placetype":"venue"
},
  "geometry": {"coordinates":[-87.462233,37.975521],"type":"Point"}
}