{
  "type": "Feature",
  "properties": {
    "addr:full":"4301 W Clara Ln Muncie IN 47304",
    "addr:housenumber":"4301",
    "addr:postcode":"47304",
    "addr:street":"W Clara Ln",
    "iso:country":"US",
    "sg:address":"4301 W Clara Ln",
    "sg:city":"Muncie",
    "sg:classifiers":[
        {
            "category":"Home & Garden",
            "subcategory":"Household Appliances",
            "type":"Retail Goods"
        }
    ],
    "sg:phone":"+1 765 286 3800",
    "sg:postcode":"47304",
    "sg:province":"IN",
    "sg:website":"www.hhgregg.com",
    "wof:name":"H H Gregg Appliances",
    "wof:placetype":"venue"
},
  "geometry": {"coordinates":[-85.44205599999999,40.217304],"type":"Point"}
}