{
  "type": "Feature",
  "properties": {
    "iso:country":"US",
    "sg:address":"502 Gilmore Ave",
    "sg:city":"Jeffersonville",
    "sg:classifiers":[
        {
            "category":"Shopping",
            "subcategory":"Computers & Home Electronics",
            "type":"Retail Goods"
        }
    ],
    "sg:phone":"+1 812 284 1656",
    "sg:postcode":"47130",
    "sg:province":"IN",
    "sg:tags":[
        "software"
    ],
    "wof:name":"S S & C Technologies Inc",
    "wof:placetype":"venue"
},
  "geometry": {"coordinates":[-85.718055,38.286173],"type":"Point"}
}