{
  "type": "Feature",
  "properties": {
    "iso:country":"US",
    "sg:address":"3270 Grassland Hills Rd",
    "sg:city":"Jasper",
    "sg:classifiers":[
        {
            "category":"Restaurant",
            "type":"Food & Drink"
        }
    ],
    "sg:phone":"+1 812 481 2441",
    "sg:postcode":"47546",
    "sg:province":"IN",
    "wof:name":"Ja Mel Food's Inc",
    "wof:placetype":"venue"
},
  "geometry": {"coordinates":[-86.956793,38.4163],"type":"Point"}
}