{
  "type": "Feature",
  "properties": {
    "iso:country":"US",
    "sg:address":"9275 E US Hwy 40",
    "sg:city":"Terre Haute",
    "sg:classifiers":[
        {
            "category":"Personal",
            "subcategory":"Beauty Salon",
            "type":"Services"
        }
    ],
    "sg:phone":"+1 812 877 2214",
    "sg:postcode":"47803",
    "sg:province":"IN",
    "wof:name":"Shear Madness II",
    "wof:placetype":"venue"
},
  "geometry": {"coordinates":[-87.27473999999999,39.492546],"type":"Point"}
}