{
  "type": "Feature",
  "properties": {
    "iso:country":"US",
    "sg:address":"232 W High St",
    "sg:city":"Lawrenceburg",
    "sg:classifiers":[
        {
            "category":"Shopping",
            "subcategory":"Used Merchandise",
            "type":"Retail Goods"
        }
    ],
    "sg:phone":"+1 812 537 1709",
    "sg:postcode":"47025",
    "sg:province":"IN",
    "sg:tags":[
        "antique",
        "dealer"
    ],
    "wof:name":"Collins Family Antiques",
    "wof:placetype":"venue"
},
  "geometry": {"coordinates":[-84.84966,39.090999],"type":"Point"}
}