{
  "type": "Feature",
  "properties": {
    "iso:country":"US",
    "sg:address":"6920 Parkdale Pl",
    "sg:city":"Indianapolis",
    "sg:classifiers":[
        {
            "category":"Health Services",
            "subcategory":"Podiatrist",
            "type":"Services"
        }
    ],
    "sg:phone":"+1 317 297 0661",
    "sg:postcode":"46254",
    "sg:province":"IN",
    "wof:name":"Foot & Ankle Institute",
    "wof:placetype":"venue"
},
  "geometry": {"coordinates":[-86.280646,39.826137],"type":"Point"}
}