{
  "type": "Feature",
  "properties": {
    "iso:country":"US",
    "sg:address":"2380 25th St",
    "sg:city":"Columbus",
    "sg:classifiers":[
        {
            "category":"Professional",
            "type":"Services"
        }
    ],
    "sg:phone":"+1 812 376 8239",
    "sg:postcode":"47201",
    "sg:province":"IN",
    "sg:tags":[
        "establishment"
    ],
    "wof:name":"Digital Universe",
    "wof:placetype":"venue"
},
  "geometry": {"coordinates":[-85.897938,39.223108],"type":"Point"}
}