{
  "type": "Feature",
  "properties": {
    "addr:full":"1204 Greenbush St Lafayette IN 47904",
    "addr:housenumber":"1204",
    "addr:postcode":"47904",
    "addr:street":"Greenbush St",
    "iso:country":"US",
    "sg:address":"1204 Greenbush St",
    "sg:city":"Lafayette",
    "sg:classifiers":[
        {
            "category":"Food & Beverages",
            "subcategory":"Groceries & Convenience Stores",
            "type":"Retail Goods"
        }
    ],
    "sg:phone":"+1 765 429 5346",
    "sg:postcode":"47904",
    "sg:province":"IN",
    "sg:tags":[
        "product"
    ],
    "wof:name":"Sheppards Table Food Pantry",
    "wof:placetype":"venue"
},
  "geometry": {"coordinates":[-86.884649,40.432102],"type":"Point"}
}