{
  "type": "Feature",
  "properties": {
    "iso:country":"US",
    "sg:address":"134 E Elm St",
    "sg:city":"New Albany",
    "sg:classifiers":[
        {
            "category":"Banks & Credit Unions",
            "subcategory":"Investment Brokerage",
            "type":"Services"
        }
    ],
    "sg:phone":"+1 812 945 0727",
    "sg:postcode":"47150",
    "sg:province":"IN",
    "sg:tags":[
        "consultant",
        "planning",
        "financial"
    ],
    "wof:name":"B & M Walker Enterprises",
    "wof:placetype":"venue"
},
  "geometry": {"coordinates":[-85.822683,38.287323],"type":"Point"}
}