{
  "type": "Feature",
  "properties": {
    "iso:country":"US",
    "sg:address":"937 W Walnut St",
    "sg:city":"Albany",
    "sg:classifiers":[
        {
            "category":"Banks & Credit Unions",
            "subcategory":"Bank",
            "type":"Services"
        }
    ],
    "sg:phone":"+1 765 789 4426",
    "sg:postcode":"47320",
    "sg:province":"IN",
    "wof:name":"First Merchants Bank",
    "wof:placetype":"venue"
},
  "geometry": {"coordinates":[-85.247828,40.300554],"type":"Point"}
}