{
  "type": "Feature",
  "properties": {
    "iso:country":"US",
    "sg:address":"110 W Logan St",
    "sg:city":"Markle",
    "sg:classifiers":[
        {
            "category":"Food & Beverages",
            "subcategory":"Groceries & Convenience Stores",
            "type":"Retail Goods"
        }
    ],
    "sg:phone":"+1 260 758 2600",
    "sg:postcode":"46770",
    "sg:province":"IN",
    "wof:name":"Markle Quick Stop",
    "wof:placetype":"venue"
},
  "geometry": {"coordinates":[-85.335518,40.829208],"type":"Point"}
}