{
  "type": "Feature",
  "properties": {
    "addr:full":"4405 Old Mill Rd Fort Wayne IN 46807",
    "addr:housenumber":"4405",
    "addr:postcode":"46807",
    "addr:street":"Old Mill Rd",
    "iso:country":"US",
    "sg:address":"4405 Old Mill Rd",
    "sg:city":"Fort Wayne",
    "sg:classifiers":[
        {
            "category":"Health Services",
            "subcategory":"Doctor",
            "type":"Services"
        }
    ],
    "sg:phone":"+1 260 456 2808",
    "sg:postcode":"46807",
    "sg:province":"IN",
    "sg:tags":[
        "medical"
    ],
    "wof:name":"Pamela M Kelly MD",
    "wof:placetype":"venue"
},
  "geometry": {"coordinates":[-85.15657,41.046347],"type":"Point"}
}