{
  "type": "Feature",
  "properties": {
    "addr:full":"1026 W 2nd St Mount Vernon IN 47620",
    "addr:housenumber":"1026",
    "addr:postcode":"47620",
    "addr:street":"W 2Nd St",
    "iso:country":"US",
    "sg:address":"1026 W 2nd St",
    "sg:city":"Mount Vernon",
    "sg:classifiers":[
        {
            "category":"Sports & Exercise",
            "subcategory":"Bowling",
            "type":"Entertainment"
        }
    ],
    "sg:phone":"+1 812 838 3818",
    "sg:postcode":"47620",
    "sg:province":"IN",
    "sg:tags":[
        "center"
    ],
    "wof:name":"Mount Vernon Bowling Assn",
    "wof:placetype":"venue"
},
  "geometry": {"coordinates":[-87.906003,37.927355],"type":"Point"}
}