{
  "type": "Feature",
  "properties": {
    "iso:country":"US",
    "sg:address":"825 E Markland Ave",
    "sg:city":"Kokomo",
    "sg:classifiers":[
        {
            "category":"Professional",
            "type":"Services"
        }
    ],
    "sg:phone":"+1 765 457 3254",
    "sg:postcode":"46901",
    "sg:province":"IN",
    "sg:tags":[
        "establishment"
    ],
    "wof:name":"Check With Cheek",
    "wof:placetype":"venue"
},
  "geometry": {"coordinates":[-86.12217,40.476547],"type":"Point"}
}