{
  "type": "Feature",
  "properties": {
    "iso:country":"US",
    "sg:address":"12538 N 350 W",
    "sg:city":"Wheatfield",
    "sg:phone":"+1 219 956 3324",
    "sg:postcode":"46392",
    "sg:province":"IN",
    "sg:tags":[
        "farm",
        "grain",
        "cash"
    ],
    "wof:name":"Harold Duttlinger",
    "wof:placetype":"venue"
},
  "geometry": {"coordinates":[-87.11248399999999,41.201997],"type":"Point"}
}