{
  "type": "Feature",
  "properties": {
    "iso:country":"US",
    "sg:address":"1626 Connemara Rd",
    "sg:city":"Indianapolis",
    "sg:classifiers":[
        {
            "category":"Building & Trades",
            "subcategory":"Construction",
            "type":"Services"
        }
    ],
    "sg:phone":"+1 317 883 2970",
    "sg:postcode":"46217",
    "sg:province":"IN",
    "sg:tags":[
        "house"
    ],
    "wof:name":"Custom Homes & Remodeling",
    "wof:placetype":"venue"
},
  "geometry": {"coordinates":[-86.188969,39.649889],"type":"Point"}
}