{
  "type": "Feature",
  "properties": {
    "iso:country":"US",
    "sg:address":"1733 Dr Andrew J Brown Ave",
    "sg:city":"Indianapolis",
    "sg:classifiers":[
        {
            "category":"Organizations",
            "subcategory":"Religious Organization",
            "type":"Services"
        }
    ],
    "sg:phone":"+1 317 632 9349",
    "sg:postcode":"46202",
    "sg:province":"IN",
    "wof:name":"St Rita Church",
    "wof:placetype":"venue"
},
  "geometry": {"coordinates":[-86.135321,39.791893],"type":"Point"}
}