{
  "type": "Feature",
  "properties": {
    "iso:country":"US",
    "sg:address":"461 Towle Ct",
    "sg:city":"Hammond",
    "sg:classifiers":[
        {
            "category":"Communications",
            "subcategory":"Television Station",
            "type":"Services"
        }
    ],
    "sg:phone":"+1 708 217 1789",
    "sg:postcode":"46320",
    "sg:province":"IN",
    "wof:name":"Diva Television",
    "wof:placetype":"venue"
},
  "geometry": {"coordinates":[-87.51633099999999,41.622303],"type":"Point"}
}