{
  "type": "Feature",
  "properties": {
    "iso:country":"US",
    "sg:address":"1320 Goshen Ave",
    "sg:city":"Fort Wayne",
    "sg:classifiers":[
        {
            "category":"Retail",
            "subcategory":"Car Wash",
            "type":"Services"
        }
    ],
    "sg:phone":"+1 260 471 4523",
    "sg:postcode":"46808",
    "sg:province":"IN",
    "sg:tags":[
        "polishing",
        "washing"
    ],
    "wof:name":"Fort Wayne Super Wash",
    "wof:placetype":"venue"
},
  "geometry": {"coordinates":[-85.157199,41.100567],"type":"Point"}
}