{
  "type": "Feature",
  "properties": {
    "iso:country":"US",
    "sg:address":"5519 Alcott Ln",
    "sg:city":"Indianapolis",
    "sg:classifiers":[
        {
            "category":"Building & Trades",
            "subcategory":"Construction",
            "type":"Services"
        }
    ],
    "sg:phone":"+1 317 714 1415",
    "sg:postcode":"46221",
    "sg:province":"IN",
    "sg:tags":[
        "hanging",
        "contractor"
    ],
    "wof:name":"Million S Custom Painting",
    "wof:placetype":"venue"
},
  "geometry": {"coordinates":[-86.25812500000001,39.665861],"type":"Point"}
}