{
  "type": "Feature",
  "properties": {
    "iso:country":"US",
    "sg:address":"214 N Mishawaka St",
    "sg:city":"Akron",
    "sg:classifiers":[
        {
            "category":"Personal",
            "subcategory":"Beauty Salon",
            "type":"Services"
        }
    ],
    "sg:phone":"+1 574 893 7051",
    "sg:postcode":"46910",
    "sg:province":"IN",
    "wof:name":"Pam's New Image Styling Salon",
    "wof:placetype":"venue"
},
  "geometry": {"coordinates":[-86.028391,41.040405],"type":"Point"}
}