{
  "type": "Feature",
  "properties": {
    "addr:full":"1119 N Madison Ave Anderson IN 46011",
    "addr:housenumber":"1119",
    "addr:postcode":"46011",
    "addr:street":"N Madison Ave",
    "iso:country":"US",
    "sg:address":"1119 N Madison Ave",
    "sg:city":"Anderson",
    "sg:classifiers":[
        {
            "category":"Professional",
            "subcategory":"Management & Consulting",
            "type":"Services"
        }
    ],
    "sg:phone":"+1 765 643 4154",
    "sg:postcode":"46011",
    "sg:province":"IN",
    "wof:name":"Autrey",
    "wof:placetype":"venue"
},
  "geometry": {"coordinates":[-85.69174099999999,40.123859],"type":"Point"}
}