{
  "type": "Feature",
  "properties": {
    "iso:country":"US",
    "sg:address":"1160 W Bristol St",
    "sg:city":"Elkhart",
    "sg:classifiers":[
        {
            "category":"Restaurant",
            "type":"Food & Drink"
        }
    ],
    "sg:phone":"+1 574 262 3305",
    "sg:postcode":"46514",
    "sg:province":"IN",
    "sg:tags":[
        "pizza"
    ],
    "wof:name":"Original Vesuvio Pizza",
    "wof:placetype":"venue"
},
  "geometry": {"coordinates":[-85.989237,41.702689],"type":"Point"}
}