{
  "type": "Feature",
  "properties": {
    "iso:country":"US",
    "sg:address":"45 Rose St",
    "sg:city":"Martinsville",
    "sg:classifiers":[
        {
            "category":"Wholesale",
            "subcategory":"Scrap",
            "type":"Manufacturing & Wholesale Goods"
        }
    ],
    "sg:phone":"+1 765 349 9175",
    "sg:postcode":"46151",
    "sg:province":"IN",
    "sg:tags":[
        "waste"
    ],
    "wof:name":"Martinsville Transfer",
    "wof:placetype":"venue"
},
  "geometry": {"coordinates":[-86.428607,39.440286],"type":"Point"}
}