{
  "type": "Feature",
  "properties": {
    "iso:country":"US",
    "sg:address":"1136 Washington Sq",
    "sg:city":"Evansville",
    "sg:classifiers":[
        {
            "category":"Real Estate",
            "subcategory":"Real Estate Agent",
            "type":"Services"
        }
    ],
    "sg:phone":"+1 812 423 4640",
    "sg:postcode":"47715",
    "sg:province":"IN",
    "sg:website":"www.hahnrealtycorp.com",
    "wof:name":"Hahn Realty Corp",
    "wof:placetype":"venue"
},
  "geometry": {"coordinates":[-87.491771,37.963592],"type":"Point"}
}