{
  "type": "Feature",
  "properties": {
    "iso:country":"US",
    "sg:address":"1021 N Main St",
    "sg:city":"Mishawaka",
    "sg:classifiers":[
        {
            "category":"Wholesale",
            "subcategory":"Durable Goods & Equipment",
            "type":"Manufacturing & Wholesale Goods"
        }
    ],
    "sg:phone":"+1 574 259 2459",
    "sg:postcode":"46545",
    "sg:province":"IN",
    "sg:tags":[
        "room",
        "drafting"
    ],
    "wof:name":"Triangle Digital Printing Inc",
    "wof:placetype":"venue"
},
  "geometry": {"coordinates":[-86.18141300000001,41.670076],"type":"Point"}
}