{
  "type": "Feature",
  "properties": {
    "addr:full":"709 W Oakley Ave Lowell IN 46356",
    "addr:housenumber":"709",
    "addr:postcode":"46356",
    "addr:street":"W Oakley Ave",
    "iso:country":"US",
    "sg:address":"709 W Oakley Ave",
    "sg:city":"Lowell",
    "sg:classifiers":[
        {
            "category":"Autos & Motor Vehicles",
            "subcategory":"Automobile Sales",
            "type":"Retail Goods"
        }
    ],
    "sg:phone":"+1 219 838 9454",
    "sg:postcode":"46356",
    "sg:province":"IN",
    "sg:tags":[
        "limo"
    ],
    "wof:name":"Fred's Limo",
    "wof:placetype":"venue"
},
  "geometry": {"coordinates":[-87.436048,41.288445],"type":"Point"}
}