{
  "type": "Feature",
  "properties": {
    "addr:full":"601 S Main St Elkhart IN 46516",
    "addr:housenumber":"601",
    "addr:postcode":"46516",
    "addr:street":"S Main St",
    "iso:country":"US",
    "sg:address":"601 S Main St",
    "sg:city":"Elkhart",
    "sg:classifiers":[
        {
            "category":"Government",
            "subcategory":"Post Office",
            "type":"Public Place"
        }
    ],
    "sg:phone":"+1 574 000 1111",
    "sg:postcode":"46516",
    "sg:province":"IN",
    "wof:name":"US Post Office",
    "wof:placetype":"venue"
},
  "geometry": {"coordinates":[-85.970568,41.681454],"type":"Point"}
}