{
  "type": "Feature",
  "properties": {
    "iso:country":"US",
    "sg:address":"544 N Jefferson St",
    "sg:city":"Huntington",
    "sg:classifiers":[
        {
            "category":"Retail",
            "subcategory":"Portrait Studio",
            "type":"Services"
        }
    ],
    "sg:phone":"+1 260 356 2660",
    "sg:postcode":"46750",
    "sg:province":"IN",
    "sg:tags":[
        "photographer"
    ],
    "wof:name":"Portraits By Jolene",
    "wof:placetype":"venue"
},
  "geometry": {"coordinates":[-85.495949,40.882899],"type":"Point"}
}