{
  "type": "Feature",
  "properties": {
    "addr:full":"10821 W Division Rd Westville IN 46391",
    "addr:housenumber":"10821",
    "addr:postcode":"46391",
    "addr:street":"W Division Rd",
    "iso:country":"US",
    "sg:address":"10821 W Division Rd",
    "sg:city":"Westville",
    "sg:classifiers":[
        {
            "category":"Building & Trades",
            "subcategory":"Construction",
            "type":"Services"
        }
    ],
    "sg:phone":"+1 219 871 1587",
    "sg:postcode":"46391",
    "sg:province":"IN",
    "sg:tags":[
        "excavation",
        "contractor"
    ],
    "wof:name":"Phelps Construction",
    "wof:placetype":"venue"
},
  "geometry": {"coordinates":[-86.880444,41.607243],"type":"Point"}
}