{
  "type": "Feature",
  "properties": {
    "iso:country":"US",
    "sg:address":"3705 S Madison St",
    "sg:city":"Muncie",
    "sg:classifiers":[
        {
            "category":"Food & Beverages",
            "subcategory":"Groceries & Convenience Stores",
            "type":"Retail Goods"
        }
    ],
    "sg:phone":"+1 765 284 2466",
    "sg:postcode":"47302",
    "sg:province":"IN",
    "sg:tags":[
        "grocer"
    ],
    "wof:name":"Lo Bill Foods",
    "wof:placetype":"venue"
},
  "geometry": {"coordinates":[-85.382442,40.157337],"type":"Point"}
}