{
  "type": "Feature",
  "properties": {
    "iso:country":"US",
    "sg:address":"137 S Main St",
    "sg:city":"Clinton",
    "sg:classifiers":[
        {
            "category":"Sports & Exercise",
            "subcategory":"Bowling",
            "type":"Entertainment"
        }
    ],
    "sg:phone":"+1 765 832 9010",
    "sg:postcode":"47842",
    "sg:province":"IN",
    "sg:tags":[
        "center"
    ],
    "wof:name":"Lucky Strike Bowl",
    "wof:placetype":"venue"
},
  "geometry": {"coordinates":[-87.39838,39.660083],"type":"Point"}
}