{
  "type": "Feature",
  "properties": {
    "iso:country":"US",
    "sg:address":"750 Co Rd 15",
    "sg:city":"Elkhart",
    "sg:classifiers":[
        {
            "category":"Retail",
            "subcategory":"Auto Rental",
            "type":"Services"
        }
    ],
    "sg:phone":"+1 574 295 1285",
    "sg:postcode":"46516",
    "sg:province":"IN",
    "sg:tags":[
        "renting",
        "truck",
        "leasing"
    ],
    "wof:name":"Old Dominion Truck Leasing Inc",
    "wof:placetype":"venue"
},
  "geometry": {"coordinates":[-85.907328,41.684421],"type":"Point"}
}