{
  "type": "Feature",
  "properties": {
    "iso:country":"US",
    "sg:address":"1403 W Lusher Ave",
    "sg:city":"Elkhart",
    "sg:classifiers":[
        {
            "category":"Wholesale",
            "subcategory":"Machinery & Supplies",
            "type":"Manufacturing & Wholesale Goods"
        }
    ],
    "sg:phone":"+1 574 293 5641",
    "sg:postcode":"46517",
    "sg:province":"IN",
    "sg:tags":[
        "janitor"
    ],
    "wof:name":"Harter Supply",
    "wof:placetype":"venue"
},
  "geometry": {"coordinates":[-85.990262,41.666859],"type":"Point"}
}