{
  "type": "Feature",
  "properties": {
    "iso:country":"US",
    "sg:address":"1120 S Arlington Ave",
    "sg:city":"Indianapolis",
    "sg:classifiers":[
        {
            "category":"Organizations",
            "subcategory":"Religious Organization",
            "type":"Services"
        }
    ],
    "sg:phone":"+1 317 357 2971",
    "sg:postcode":"46203",
    "sg:province":"IN",
    "sg:tags":[
        "church"
    ],
    "wof:name":"Crossroads Baptist Temple",
    "wof:placetype":"venue"
},
  "geometry": {"coordinates":[-86.06393799999999,39.750016],"type":"Point"}
}