{
  "type": "Feature",
  "properties": {
    "iso:country":"US",
    "sg:address":"1631 W Bristol St",
    "sg:city":"Elkhart",
    "sg:classifiers":[
        {
            "category":"Home & Garden",
            "subcategory":"Mobile Homes",
            "type":"Retail Goods"
        }
    ],
    "sg:phone":"+1 574 262 3546",
    "sg:postcode":"46514",
    "sg:province":"IN",
    "sg:tags":[
        "parts"
    ],
    "wof:name":"Ntp Distribution",
    "wof:placetype":"venue"
},
  "geometry": {"coordinates":[-85.996693,41.702537],"type":"Point"}
}