{
  "type": "Feature",
  "properties": {
    "iso:country":"US",
    "sg:address":"820 Pleasant St",
    "sg:city":"Charlestown",
    "sg:classifiers":[
        {
            "category":"Organizations",
            "subcategory":"Religious Organization",
            "type":"Services"
        }
    ],
    "sg:phone":"+1 812 256 5833",
    "sg:postcode":"47111",
    "sg:province":"IN",
    "sg:tags":[
        "church"
    ],
    "wof:name":"Charlestown Full Gospel Church",
    "wof:placetype":"venue"
},
  "geometry": {"coordinates":[-85.663942,38.446439],"type":"Point"}
}