{
  "type": "Feature",
  "properties": {
    "iso:country":"US",
    "sg:address":"6467 N 1200 W",
    "sg:city":"Monticello",
    "sg:phone":"+1 574 965 2727",
    "sg:postcode":"47960",
    "sg:province":"IN",
    "sg:tags":[
        "farm",
        "field",
        "crop"
    ],
    "wof:name":"Gary Burt",
    "wof:placetype":"venue"
},
  "geometry": {"coordinates":[-86.75699,40.645866],"type":"Point"}
}