{
  "type": "Feature",
  "properties": {
    "iso:country":"US",
    "sg:address":"6389 W May Rd",
    "sg:city":"Bloomington",
    "sg:classifiers":[
        {
            "category":"Building & Trades",
            "subcategory":"Construction",
            "type":"Services"
        }
    ],
    "sg:phone":"+1 812 825 1972",
    "sg:postcode":"47403",
    "sg:province":"IN",
    "sg:tags":[
        "excavating",
        "contractor"
    ],
    "wof:name":"Johnson Excavating",
    "wof:placetype":"venue"
},
  "geometry": {"coordinates":[-86.632469,39.093529],"type":"Point"}
}