{
  "type": "Feature",
  "properties": {
    "iso:country":"US",
    "sg:address":"414 S Sherman Dr",
    "sg:city":"Indianapolis",
    "sg:classifiers":[
        {
            "category":"Retail",
            "subcategory":"Repair Shop",
            "type":"Services"
        }
    ],
    "sg:phone":"+1 317 356 0880",
    "sg:postcode":"46201",
    "sg:province":"IN",
    "sg:tags":[
        "cleaners",
        "parts",
        "vacuum"
    ],
    "wof:name":"Mr Fix-It Shop",
    "wof:placetype":"venue"
},
  "geometry": {"coordinates":[-86.102096,39.760165],"type":"Point"}
}