{
  "type": "Feature",
  "properties": {
    "iso:country":"US",
    "sg:address":"1501 Wabash St",
    "sg:city":"Michigan City",
    "sg:classifiers":[
        {
            "category":"Health Services",
            "subcategory":"Doctor",
            "type":"Services"
        }
    ],
    "sg:phone":"+1 219 877 1965",
    "sg:postcode":"46360",
    "sg:province":"IN",
    "sg:tags":[
        "physician",
        "surgeon"
    ],
    "wof:name":"St Anthony Memorial Health Ctr",
    "wof:placetype":"venue"
},
  "geometry": {"coordinates":[-86.900086,41.706991],"type":"Point"}
}