{
  "type": "Feature",
  "properties": {
    "iso:country":"US",
    "sg:address":"30729 State Rd 2",
    "sg:city":"New Carlisle",
    "sg:classifiers":[
        {
            "category":"Shopping",
            "subcategory":"Bicycles & Sporting Goods",
            "type":"Retail Goods"
        }
    ],
    "sg:phone":"+1 574 654 7388",
    "sg:postcode":"46552",
    "sg:province":"IN",
    "wof:name":"Stony Ridge Horse Wear",
    "wof:placetype":"venue"
},
  "geometry": {"coordinates":[-86.453874,41.67214],"type":"Point"}
}