{
  "type": "Feature",
  "properties": {
    "addr:full":"409 Market Plz Greenwood IN 46142",
    "addr:housenumber":"409",
    "addr:postcode":"46142",
    "addr:street":"Market Plz",
    "iso:country":"US",
    "sg:address":"409 Market Plz",
    "sg:city":"Greenwood",
    "sg:classifiers":[
        {
            "category":"Autos & Motor Vehicles",
            "subcategory":"Auto Supplies",
            "type":"Retail Goods"
        }
    ],
    "sg:phone":"+1 317 881 9361",
    "sg:postcode":"46142",
    "sg:province":"IN",
    "sg:tags":[
        "automobile",
        "parts"
    ],
    "wof:name":"NAPA Auto Parts",
    "wof:placetype":"venue"
},
  "geometry": {"coordinates":[-86.10957999999999,39.611155],"type":"Point"}
}