{
  "type": "Feature",
  "properties": {
    "addr:full":"223 Washington St Columbus IN 47201",
    "addr:housenumber":"223",
    "addr:postcode":"47201",
    "addr:street":"Washington St",
    "iso:country":"US",
    "sg:address":"223 Washington St",
    "sg:city":"Columbus",
    "sg:classifiers":[
        {
            "category":"Real Estate",
            "subcategory":"Real Estate Services",
            "type":"Services"
        }
    ],
    "sg:phone":"+1 812 376 3313",
    "sg:postcode":"47201",
    "sg:province":"IN",
    "sg:tags":[
        "company",
        "title"
    ],
    "wof:name":"Royal Title Svc-Bartholomew",
    "wof:placetype":"venue"
},
  "geometry": {"coordinates":[-85.920929,39.201165],"type":"Point"}
}