{
  "type": "Feature",
  "properties": {
    "addr:full":"6158 Co Rd 1675 N Dale IN 47579",
    "addr:housenumber":"6158",
    "addr:postcode":"47579",
    "addr:street":"Co Rd 1675 N Dale In",
    "iso:country":"US",
    "sg:address":"6158 Co Rd 1675 N",
    "sg:city":"Dale",
    "sg:classifiers":[
        {
            "category":"Professional",
            "subcategory":"Business Services",
            "type":"Services"
        }
    ],
    "sg:phone":"+1 812 937 2338",
    "sg:postcode":"47579",
    "sg:province":"IN",
    "wof:name":"Brummel Sales",
    "wof:placetype":"venue"
},
  "geometry": {"coordinates":[-86.950262,38.129355],"type":"Point"}
}