{
  "type": "Feature",
  "properties": {
    "iso:country":"US",
    "sg:address":"2808 N 1st Ave",
    "sg:city":"Evansville",
    "sg:classifiers":[
        {
            "category":"Banks & Credit Unions",
            "subcategory":"Bank",
            "type":"Services"
        }
    ],
    "sg:phone":"+1 812 421 0200",
    "sg:postcode":"47710",
    "sg:province":"IN",
    "sg:tags":[
        "loan",
        "real estate"
    ],
    "wof:name":"H & H Financial Group",
    "wof:placetype":"venue"
},
  "geometry": {"coordinates":[-87.574444,38.00499],"type":"Point"}
}