{
  "type": "Feature",
  "properties": {
    "addr:full":"11811 Yale Dr Carmel IN 46032",
    "addr:housenumber":"11811",
    "addr:postcode":"46032",
    "addr:street":"Yale Dr",
    "iso:country":"US",
    "sg:address":"11811 Yale Dr",
    "sg:city":"Carmel",
    "sg:classifiers":[
        {
            "category":"Professional",
            "subcategory":"Advertising",
            "type":"Services"
        }
    ],
    "sg:phone":"+1 317 442 3908",
    "sg:postcode":"46032",
    "sg:province":"IN",
    "sg:tags":[
        "distributing",
        "sample",
        "service-circular"
    ],
    "wof:name":"United Marketing Solutions",
    "wof:placetype":"venue"
},
  "geometry": {"coordinates":[-86.141954,39.960117],"type":"Point"}
}