{
  "type": "Feature",
  "properties": {
    "iso:country":"US",
    "sg:address":"1322 Garfield St",
    "sg:city":"Fort Wayne",
    "sg:classifiers":[
        {
            "category":"Mining & Drilling",
            "type":"Manufacturing & Wholesale Goods"
        }
    ],
    "sg:phone":"+1 260 432 4756",
    "sg:postcode":"46805",
    "sg:province":"IN",
    "sg:tags":[
        "rigger"
    ],
    "sg:website":"www.wendtrigging.com",
    "wof:name":"Wendt & Sons",
    "wof:placetype":"venue"
},
  "geometry": {"coordinates":[-85.116478,41.088338],"type":"Point"}
}