{
  "type": "Feature",
  "properties": {
    "iso:country":"US",
    "sg:address":"622 S Range Line Rd Ste Q",
    "sg:city":"Carmel",
    "sg:classifiers":[
        {
            "category":"Farming",
            "subcategory":"Fish & Marine Products",
            "type":"Manufacturing & Wholesale Goods"
        },
        {
            "category":"Retail",
            "subcategory":"Repair Shop",
            "type":"Services"
        },
        {
            "category":"Professional",
            "subcategory":"Art Services",
            "type":"Services"
        },
        {
            "category":"Shopping",
            "subcategory":"Antiques",
            "type":"Retail Goods"
        }
    ],
    "sg:phone":"+1 317 566 8216",
    "sg:postcode":"46032",
    "sg:province":"IN",
    "sg:tags":[
        "picture",
        "frame",
        "restoration",
        "framing",
        "reproduction"
    ],
    "wof:name":"Angelica's Gold Frame",
    "wof:placetype":"venue"
},
  "geometry": {"coordinates":[-86.127015,39.972153],"type":"Point"}
}