{
  "type": "Feature",
  "properties": {
    "iso:country":"US",
    "sg:address":"101 Saint John Rd",
    "sg:city":"Michigan City",
    "sg:classifiers":[
        {
            "category":"Organizations",
            "subcategory":"Religious Organization",
            "type":"Services"
        }
    ],
    "sg:phone":"+1 219 872 9121",
    "sg:postcode":"46360",
    "sg:province":"IN",
    "sg:tags":[
        "church"
    ],
    "sg:website":"www.stjohnsmc.org",
    "wof:name":"St John's United Church-Christ",
    "wof:placetype":"venue"
},
  "geometry": {"coordinates":[-86.90361900000001,41.683752],"type":"Point"}
}