{
  "type": "Feature",
  "properties": {
    "iso:country":"US",
    "sg:address":"333 S Highland Ave",
    "sg:city":"Bloomington",
    "sg:classifiers":[
        {
            "category":"Organizations",
            "subcategory":"Religious Organization",
            "type":"Services"
        }
    ],
    "sg:phone":"+1 812 330 9081",
    "sg:postcode":"47401",
    "sg:province":"IN",
    "wof:name":"Bloomington Third Branch",
    "wof:placetype":"venue"
},
  "geometry": {"coordinates":[-86.517653,39.163463],"type":"Point"}
}