{
  "type": "Feature",
  "properties": {
    "iso:country":"US",
    "sg:address":"309 S Prairie St",
    "sg:city":"Brookston",
    "sg:classifiers":[
        {
            "category":"Banks & Credit Unions",
            "subcategory":"Bank",
            "type":"Services"
        }
    ],
    "sg:phone":"+1 765 563 3135",
    "sg:postcode":"47923",
    "sg:province":"IN",
    "wof:name":"Farmers State Bank",
    "wof:placetype":"venue"
},
  "geometry": {"coordinates":[-86.86879999999999,40.602675],"type":"Point"}
}