{
  "type": "Feature",
  "properties": {
    "iso:country":"US",
    "sg:address":"55659 Currant Rd",
    "sg:city":"Mishawaka",
    "sg:classifiers":[
        {
            "category":"Retail",
            "subcategory":"Animal Services",
            "type":"Services"
        }
    ],
    "sg:phone":"+1 574 256 2227",
    "sg:postcode":"46545",
    "sg:province":"IN",
    "sg:tags":[
        "pet",
        "grooming",
        "washing"
    ],
    "wof:name":"Sue's Small Stuff Dog Grooming",
    "wof:placetype":"venue"
},
  "geometry": {"coordinates":[-86.12906599999999,41.681496],"type":"Point"}
}