{
  "type": "Feature",
  "properties": {
    "iso:country":"US",
    "sg:address":"801 N East St",
    "sg:city":"Lebanon",
    "sg:classifiers":[
        {
            "category":"Government",
            "subcategory":"Office",
            "type":"Public Place"
        }
    ],
    "sg:phone":"+1 765 482 6447",
    "sg:postcode":"46052",
    "sg:province":"IN",
    "sg:tags":[
        "state",
        "security"
    ],
    "sg:website":"www.inarng.org",
    "wof:name":"National Guard",
    "wof:placetype":"venue"
},
  "geometry": {"coordinates":[-86.46682,40.054624],"type":"Point"}
}