{
  "type": "Feature",
  "properties": {
    "iso:country":"US",
    "sg:address":"1624 N Webster St",
    "sg:city":"Kokomo",
    "sg:classifiers":[
        {
            "category":"Recreation",
            "type":"Entertainment"
        }
    ],
    "sg:phone":"+1 765 457 3619",
    "sg:postcode":"46901",
    "sg:province":"IN",
    "wof:name":"Islas Ceramic",
    "wof:placetype":"venue"
},
  "geometry": {"coordinates":[-86.136143,40.501502],"type":"Point"}
}