{
  "type": "Feature",
  "properties": {
    "iso:country":"US",
    "sg:address":"10162 E 500 S",
    "sg:city":"Windfall",
    "sg:classifiers":[
        {
            "category":"Travel",
            "subcategory":"Campground",
            "type":"Entertainment"
        }
    ],
    "sg:phone":"+1 765 945 7815",
    "sg:postcode":"46076",
    "sg:province":"IN",
    "wof:name":"Beaver Point Campground",
    "wof:placetype":"venue"
},
  "geometry": {"coordinates":[-85.935347,40.406525],"type":"Point"}
}