{
  "type": "Feature",
  "properties": {
    "iso:country":"US",
    "sg:address":"1007 W Mill St",
    "sg:city":"Middletown",
    "sg:classifiers":[
        {
            "category":"Restaurant",
            "type":"Food & Drink"
        }
    ],
    "sg:phone":"+1 765 354 9284",
    "sg:postcode":"47356",
    "sg:province":"IN",
    "wof:name":"Middletown Diner",
    "wof:placetype":"venue"
},
  "geometry": {"coordinates":[-85.54219399999999,40.062333],"type":"Point"}
}