{
  "type": "Feature",
  "properties": {
    "iso:country":"US",
    "sg:address":"7754 Shady Hills Dr W",
    "sg:city":"Indianapolis",
    "sg:classifiers":[
        {
            "category":"Personal",
            "subcategory":"Beauty Salon",
            "type":"Services"
        }
    ],
    "sg:phone":"+1 317 481 1600",
    "sg:postcode":"46278",
    "sg:province":"IN",
    "wof:name":"Almost Gucci",
    "wof:placetype":"venue"
},
  "geometry": {"coordinates":[-86.304895,39.893627],"type":"Point"}
}