{
  "type": "Feature",
  "properties": {
    "iso:country":"US",
    "sg:address":"429 N Pennsylvania St",
    "sg:city":"Indianapolis",
    "sg:classifiers":[
        {
            "category":"Government",
            "subcategory":"Office",
            "type":"Public Place"
        }
    ],
    "sg:phone":"+1 317 226 5860",
    "sg:postcode":"46204",
    "sg:province":"IN",
    "sg:tags":[
        "federal"
    ],
    "wof:name":"US Labor Dept",
    "wof:placetype":"venue"
},
  "geometry": {"coordinates":[-86.15609600000001,39.773669],"type":"Point"}
}