{
  "type": "Feature",
  "properties": {
    "addr:full":"3813 E Winston St Bloomington IN 47401",
    "addr:housenumber":"3813",
    "addr:postcode":"47401",
    "addr:street":"E Winston St",
    "iso:country":"US",
    "sg:address":"3813 E Winston St",
    "sg:city":"Bloomington",
    "sg:classifiers":[
        {
            "category":"Professional",
            "subcategory":"Art Services",
            "type":"Services"
        }
    ],
    "sg:phone":"+1 812 333 9307",
    "sg:postcode":"47401",
    "sg:province":"IN",
    "sg:tags":[
        "commercial",
        "design"
    ],
    "wof:name":"Rsn Ltd",
    "wof:placetype":"venue"
},
  "geometry": {"coordinates":[-86.48280099999999,39.14581],"type":"Point"}
}