{
  "type": "Feature",
  "properties": {
    "addr:full":"9892 E 1310 S Converse IN 46919",
    "addr:housenumber":"9892",
    "addr:postcode":"46919",
    "addr:street":"E 1310 S Converse",
    "iso:country":"US",
    "sg:address":"9892 E 1310 S",
    "sg:city":"Converse",
    "sg:classifiers":[
        {
            "category":"Freight",
            "type":"Transportation"
        }
    ],
    "sg:phone":"+1 765 395 3465",
    "sg:postcode":"46919",
    "sg:province":"IN",
    "sg:tags":[
        "hauling",
        "trucking"
    ],
    "wof:name":"Warnock Trucking Inc",
    "wof:placetype":"venue"
},
  "geometry": {"coordinates":[-85.887039,40.577758],"type":"Point"}
}