{
  "type": "Feature",
  "properties": {
    "iso:country":"US",
    "sg:address":"5971 N Centerville Rd",
    "sg:city":"Richmond",
    "sg:classifiers":[
        {
            "category":"Building & Trades",
            "subcategory":"Electrical",
            "type":"Services"
        }
    ],
    "sg:phone":"+1 765 886 5442",
    "sg:postcode":"47374",
    "sg:province":"IN",
    "sg:tags":[
        "electric",
        "contractor"
    ],
    "wof:name":"Canon Electric",
    "wof:placetype":"venue"
},
  "geometry": {"coordinates":[-84.996103,39.916511],"type":"Point"}
}