{
  "type": "Feature",
  "properties": {
    "iso:country":"US",
    "sg:address":"2807 Stringtown Rd",
    "sg:city":"Evansville",
    "sg:classifiers":[
        {
            "category":"Organizations",
            "subcategory":"Religious Organization",
            "type":"Services"
        }
    ],
    "sg:phone":"+1 812 468 8394",
    "sg:postcode":"47711",
    "sg:province":"IN",
    "sg:tags":[
        "church"
    ],
    "wof:name":"New Horizon Fellowship Church",
    "wof:placetype":"venue"
},
  "geometry": {"coordinates":[-87.554609,38.007252],"type":"Point"}
}