{
  "type": "Feature",
  "properties": {
    "iso:country":"US",
    "sg:address":"8345 E 48th St",
    "sg:city":"Indianapolis",
    "sg:classifiers":[
        {
            "category":"Personal",
            "type":"Services"
        }
    ],
    "sg:phone":"+1 317 731 4321",
    "sg:postcode":"46226",
    "sg:province":"IN",
    "sg:tags":[
        "towing"
    ],
    "wof:name":"American Pride Recker Services",
    "wof:placetype":"venue"
},
  "geometry": {"coordinates":[-86.021333,39.8429],"type":"Point"}
}