{
  "type": "Feature",
  "properties": {
    "iso:country":"US",
    "sg:address":"1404 W Cowing Dr",
    "sg:city":"Muncie",
    "sg:classifiers":[
        {
            "category":"Organizations",
            "subcategory":"Religious Organization",
            "type":"Services"
        }
    ],
    "sg:phone":"+1 765 288 6433",
    "sg:postcode":"47304",
    "sg:province":"IN",
    "wof:name":"Muncie SDA Church",
    "wof:placetype":"venue"
},
  "geometry": {"coordinates":[-85.403456,40.21376],"type":"Point"}
}