{
  "type": "Feature",
  "properties": {
    "addr:full":"301 E Linden Ave Logansport IN 46947",
    "addr:housenumber":"301",
    "addr:postcode":"46947",
    "addr:street":"E Linden Ave",
    "iso:country":"US",
    "sg:address":"301 E Linden Ave",
    "sg:city":"Logansport",
    "sg:classifiers":[
        {
            "category":"Organizations",
            "subcategory":"Religious Organization",
            "type":"Services"
        }
    ],
    "sg:phone":"+1 574 753 8316",
    "sg:postcode":"46947",
    "sg:province":"IN",
    "sg:tags":[
        "church"
    ],
    "wof:name":"Riverview Wesleyan Church Inc",
    "wof:placetype":"venue"
},
  "geometry": {"coordinates":[-86.36441499999999,40.758652],"type":"Point"}
}