{
  "type": "Feature",
  "properties": {
    "iso:country":"US",
    "sg:address":"1813 N Shadeland Ave",
    "sg:city":"Indianapolis",
    "sg:classifiers":[
        {
            "category":"Professional",
            "subcategory":"Employment Agencies",
            "type":"Services"
        }
    ],
    "sg:phone":"+1 317 917 0803",
    "sg:postcode":"46219",
    "sg:province":"IN",
    "sg:tags":[
        "help",
        "contractor"
    ],
    "wof:name":"CTI Personnel",
    "wof:placetype":"venue"
},
  "geometry": {"coordinates":[-86.045427,39.793378],"type":"Point"}
}