{
  "type": "Feature",
  "properties": {
    "iso:country":"US",
    "sg:address":"1098 State Rd 25",
    "sg:city":"Logansport",
    "sg:classifiers":[
        {
            "category":"Government",
            "subcategory":"Office",
            "type":"Public Place"
        }
    ],
    "sg:phone":"+1 574 753 0517",
    "sg:postcode":"46947",
    "sg:province":"IN",
    "sg:tags":[
        "state",
        "program"
    ],
    "wof:name":"Transportation Dept",
    "wof:placetype":"venue"
},
  "geometry": {"coordinates":[-86.351258,40.78251],"type":"Point"}
}