{
  "type": "Feature",
  "properties": {
    "addr:full":"3615 N Main St Mishawaka IN 46545",
    "addr:housenumber":"3615",
    "addr:postcode":"46545",
    "addr:street":"N Main St",
    "iso:country":"US",
    "sg:address":"3615 N Main St",
    "sg:city":"Mishawaka",
    "sg:classifiers":[
        {
            "category":"Recreation",
            "type":"Entertainment"
        }
    ],
    "sg:phone":"+1 574 259 4171",
    "sg:postcode":"46545",
    "sg:province":"IN",
    "sg:tags":[
        "course",
        "golf"
    ],
    "sg:website":"www.puttputt.com",
    "wof:name":"Putt Putt Golf & Games",
    "wof:placetype":"venue"
},
  "geometry": {"coordinates":[-86.181833,41.691925],"type":"Point"}
}