{
  "type": "Feature",
  "properties": {
    "iso:country":"US",
    "sg:address":"130 Conwell St",
    "sg:city":"Laurel",
    "sg:classifiers":[
        {
            "category":"Organizations",
            "subcategory":"Religious Organization",
            "type":"Services"
        }
    ],
    "sg:phone":"+1 765 698 2588",
    "sg:postcode":"47024",
    "sg:province":"IN",
    "sg:tags":[
        "church"
    ],
    "wof:name":"Laurel-Metamora United Meth",
    "wof:placetype":"venue"
},
  "geometry": {"coordinates":[-85.184545,39.501702],"type":"Point"}
}