{
  "type": "Feature",
  "properties": {
    "iso:country":"US",
    "sg:address":"102 E Washington St",
    "sg:city":"Roachdale",
    "sg:classifiers":[
        {
            "category":"Retail",
            "subcategory":"Funeral Services",
            "type":"Services"
        }
    ],
    "sg:phone":"+1 765 522 1311",
    "sg:postcode":"46172",
    "sg:province":"IN",
    "sg:tags":[
        "director"
    ],
    "wof:name":"Servies & Morgan Funeral Home",
    "wof:placetype":"venue"
},
  "geometry": {"coordinates":[-86.800914,39.85206],"type":"Point"}
}