{
  "type": "Feature",
  "properties": {
    "iso:country":"US",
    "sg:address":"1302 W State Rd 2",
    "sg:city":"Laporte",
    "sg:classifiers":[
        {
            "category":"Shopping",
            "subcategory":"Pharmacy",
            "type":"Retail Goods"
        }
    ],
    "sg:phone":"+1 219 362 7008",
    "sg:postcode":"46350",
    "sg:province":"IN",
    "wof:name":"Walgreens",
    "wof:placetype":"venue"
},
  "geometry": {"coordinates":[-86.733974,41.600946],"type":"Point"}
}