{
  "type": "Feature",
  "properties": {
    "iso:country":"US",
    "sg:address":"8395 Keystone Xing",
    "sg:city":"Indianapolis",
    "sg:classifiers":[
        {
            "category":"Real Estate",
            "subcategory":"Real Estate Services",
            "type":"Services"
        }
    ],
    "sg:phone":"+1 317 254 5454",
    "sg:postcode":"46240",
    "sg:province":"IN",
    "sg:tags":[
        "company",
        "title"
    ],
    "sg:website":"www.firsttitlein.com",
    "wof:name":"First Title Of Indiana Inc",
    "wof:placetype":"venue"
},
  "geometry": {"coordinates":[-86.117175,39.907207],"type":"Point"}
}