{
  "type": "Feature",
  "properties": {
    "iso:country":"US",
    "sg:address":"17335 US Highway 31 N",
    "sg:city":"Westfield",
    "sg:classifiers":[
        {
            "category":"Retail",
            "subcategory":"Laundry & Dry Cleaning",
            "type":"Services"
        }
    ],
    "sg:phone":"+1 317 896 2531",
    "sg:postcode":"46074",
    "sg:province":"IN",
    "sg:website":"www.airemate.com",
    "wof:name":"Aire-Mate Inc",
    "wof:placetype":"venue"
},
  "geometry": {"coordinates":[-86.135498,40.039398],"type":"Point"}
}