{
  "type": "Feature",
  "properties": {
    "iso:country":"US",
    "sg:address":"5330 W 38th St",
    "sg:city":"Indianapolis",
    "sg:classifiers":[
        {
            "category":"Recreation",
            "type":"Entertainment"
        }
    ],
    "sg:phone":"+1 317 297 1000",
    "sg:postcode":"46254",
    "sg:province":"IN",
    "wof:name":"Oriental Marshal Arts College",
    "wof:placetype":"venue"
},
  "geometry": {"coordinates":[-86.253383,39.82393],"type":"Point"}
}