{
  "type": "Feature",
  "properties": {
    "addr:full":"8935 N Meridian St Ste 107 Indianapolis IN 46260",
    "addr:housenumber":"8935",
    "addr:postcode":"46260",
    "addr:street":"N Meridian St Ste 107",
    "iso:country":"US",
    "sg:address":"8935 N Meridian St Ste 107",
    "sg:city":"Indianapolis",
    "sg:classifiers":[
        {
            "category":"Health Services",
            "subcategory":"Doctor",
            "type":"Services"
        }
    ],
    "sg:phone":"+1 317 571 0170",
    "sg:postcode":"46260",
    "sg:province":"IN",
    "wof:name":"Conway Gary Lmhc",
    "wof:placetype":"venue"
},
  "geometry": {"coordinates":[-86.157641,39.917662],"type":"Point"}
}