{
  "type": "Feature",
  "properties": {
    "iso:country":"US",
    "sg:address":"8680 Champions Dr",
    "sg:city":"Indianapolis",
    "sg:classifiers":[
        {
            "category":"Insurance",
            "subcategory":"Insurance Agent",
            "type":"Services"
        }
    ],
    "sg:phone":"+1 317 849 7795",
    "sg:postcode":"46256",
    "sg:province":"IN",
    "wof:name":"Prudential",
    "wof:placetype":"venue"
},
  "geometry": {"coordinates":[-86.022806,39.913685],"type":"Point"}
}