{
  "type": "Feature",
  "properties": {
    "addr:full":"2030 Moscow Rd Greensburg IN 47240",
    "addr:postcode":"2030;47240",
    "addr:street":"Moscow Rd",
    "iso:country":"US",
    "sg:address":"2030 Moscow Rd",
    "sg:city":"Greensburg",
    "sg:classifiers":[
        {
            "category":"Social Services",
            "subcategory":"Adult Care",
            "type":"Services"
        }
    ],
    "sg:phone":"+1 812 663 5770",
    "sg:postcode":"47240",
    "sg:province":"IN",
    "sg:tags":[
        "home",
        "group"
    ],
    "wof:name":"Res-Care Group Home",
    "wof:placetype":"venue"
},
  "geometry": {"coordinates":[-85.49868600000001,39.354357],"type":"Point"}
}