{
  "type": "Feature",
  "properties": {
    "iso:country":"US",
    "sg:address":"8145 Bash St",
    "sg:city":"Indianapolis",
    "sg:classifiers":[
        {
            "category":"Restaurant",
            "type":"Food & Drink"
        }
    ],
    "sg:phone":"+1 317 570 0383",
    "sg:postcode":"46250",
    "sg:province":"IN",
    "wof:name":"Sonic Drive-In",
    "wof:placetype":"venue"
},
  "geometry": {"coordinates":[-86.04963600000001,39.903862],"type":"Point"}
}