{
  "type": "Feature",
  "properties": {
    "addr:full":"16584 Co Rd 34 Goshen IN 46528",
    "addr:housenumber":"16584;34",
    "addr:postcode":"46528",
    "addr:street":"Co Rd",
    "iso:country":"US",
    "sg:address":"16584 Co Rd 34",
    "sg:city":"Goshen",
    "sg:classifiers":[
        {
            "category":"Freight",
            "type":"Transportation"
        }
    ],
    "sg:phone":"+1 574 534 0289",
    "sg:postcode":"46528",
    "sg:province":"IN",
    "sg:tags":[
        "trucking"
    ],
    "wof:name":"Estrich Trucking",
    "wof:placetype":"venue"
},
  "geometry": {"coordinates":[-85.78166299999999,41.580846],"type":"Point"}
}