{
  "type": "Feature",
  "properties": {
    "iso:country":"US",
    "sg:address":"19 Woodland Dr",
    "sg:city":"Carmel",
    "sg:classifiers":[
        {
            "category":"Local Transit",
            "type":"Transportation"
        }
    ],
    "sg:phone":"+1 317 846 2395",
    "sg:postcode":"46032",
    "sg:province":"IN",
    "sg:tags":[
        "bus",
        "line"
    ],
    "wof:name":"John E Morley Company",
    "wof:placetype":"venue"
},
  "geometry": {"coordinates":[-86.123959,39.956413],"type":"Point"}
}