{
  "type": "Feature",
  "properties": {
    "iso:country":"US",
    "sg:address":"11334 Gatch Hill Rd",
    "sg:city":"Aurora",
    "sg:classifiers":[
        {
            "category":"Building & Trades",
            "subcategory":"Electrical",
            "type":"Services"
        }
    ],
    "sg:phone":"+1 812 926 0240",
    "sg:postcode":"47001",
    "sg:province":"IN",
    "sg:tags":[
        "electric",
        "contractor"
    ],
    "wof:name":"Aurora Lites",
    "wof:placetype":"venue"
},
  "geometry": {"coordinates":[-84.95389400000001,39.041738],"type":"Point"}
}