{
  "type": "Feature",
  "properties": {
    "addr:full":"3800 N 300 W Angola IN 46703",
    "addr:housenumber":"3800",
    "addr:postcode":"46703",
    "addr:street":"N 300 W",
    "iso:country":"US",
    "sg:address":"3800 N 300 W",
    "sg:city":"Angola",
    "sg:classifiers":[
        {
            "category":"Building & Trades",
            "subcategory":"Landscaping Services",
            "type":"Services"
        }
    ],
    "sg:phone":"+1 260 833 8804",
    "sg:postcode":"46703",
    "sg:province":"IN",
    "sg:tags":[
        "landscape",
        "contractor"
    ],
    "wof:name":"Rice Tree Svc",
    "wof:placetype":"venue"
},
  "geometry": {"coordinates":[-85.04804900000001,41.692017],"type":"Point"}
}