{
  "type": "Feature",
  "properties": {
    "addr:full":"2020 N Meridian St Indianapolis IN 46202",
    "addr:housenumber":"2020",
    "addr:postcode":"46202",
    "addr:street":"N Meridian St",
    "iso:country":"US",
    "sg:address":"2020 N Meridian St",
    "sg:city":"Indianapolis",
    "sg:classifiers":[
        {
            "category":"Professional",
            "subcategory":"Business Services",
            "type":"Services"
        }
    ],
    "sg:phone":"+1 317 927 6001",
    "sg:postcode":"46202",
    "sg:province":"IN",
    "sg:tags":[
        "development",
        "plan"
    ],
    "wof:name":"Crdc",
    "wof:placetype":"venue"
},
  "geometry": {"coordinates":[-86.157338,39.793618],"type":"Point"}
}