{
  "type": "Feature",
  "properties": {
    "iso:country":"US",
    "sg:address":"202 W Commerce St",
    "sg:city":"Brownstown",
    "sg:classifiers":[
        {
            "category":"Food & Beverages",
            "subcategory":"Liquor & Beverages",
            "type":"Retail Goods"
        }
    ],
    "sg:phone":"+1 812 358 3233",
    "sg:postcode":"47220",
    "sg:province":"IN",
    "wof:name":"Happy Herman's Package Store",
    "wof:placetype":"venue"
},
  "geometry": {"coordinates":[-86.045919,38.877104],"type":"Point"}
}