{
  "type": "Feature",
  "properties": {
    "iso:country":"US",
    "sg:address":"205 E Main St",
    "sg:city":"Loogootee",
    "sg:classifiers":[
        {
            "category":"Organizations",
            "subcategory":"Religious Organization",
            "type":"Services"
        }
    ],
    "sg:phone":"+1 812 295 4024",
    "sg:postcode":"47553",
    "sg:province":"IN",
    "sg:tags":[
        "church"
    ],
    "wof:name":"Faith Baptist Churches",
    "wof:placetype":"venue"
},
  "geometry": {"coordinates":[-86.91246,38.678094],"type":"Point"}
}