{
  "type": "Feature",
  "properties": {
    "iso:country":"US",
    "sg:address":"2060 Clark Rd",
    "sg:city":"Gary",
    "sg:classifiers":[
        {
            "category":"Organizations",
            "subcategory":"Non-profit Organization",
            "type":"Services"
        }
    ],
    "sg:phone":"+1 219 944 0823",
    "sg:postcode":"46404",
    "sg:province":"IN",
    "wof:name":"Amvets",
    "wof:placetype":"venue"
},
  "geometry": {"coordinates":[-87.393812,41.582112],"type":"Point"}
}