{
  "type": "Feature",
  "properties": {
    "iso:country":"US",
    "sg:address":"5921 W 25th Ave",
    "sg:city":"Gary",
    "sg:classifiers":[
        {
            "category":"Education",
            "subcategory":"Library",
            "type":"Public Place"
        }
    ],
    "sg:phone":"+1 219 844 8809",
    "sg:postcode":"46406",
    "sg:province":"IN",
    "wof:name":"Lake County Public Library",
    "wof:placetype":"venue"
},
  "geometry": {"coordinates":[-87.410347,41.573454],"type":"Point"}
}