{
  "type": "Feature",
  "properties": {
    "iso:country":"US",
    "sg:address":"128 W State St",
    "sg:city":"Pendleton",
    "sg:classifiers":[
        {
            "category":"Professional",
            "subcategory":"Art Services",
            "type":"Services"
        }
    ],
    "sg:phone":"+1 765 778 2612",
    "sg:postcode":"46064",
    "sg:province":"IN",
    "sg:tags":[
        "photographer"
    ],
    "wof:name":"Bow Tie Photography",
    "wof:placetype":"venue"
},
  "geometry": {"coordinates":[-85.746468,40.002547],"type":"Point"}
}