{
  "type": "Feature",
  "properties": {
    "iso:country":"US",
    "sg:address":"443 N Detroit St",
    "sg:city":"Warsaw",
    "sg:classifiers":[
        {
            "category":"Food & Beverages",
            "subcategory":"Groceries & Convenience Stores",
            "type":"Retail Goods"
        }
    ],
    "sg:phone":"+1 574 267 5221",
    "sg:postcode":"46580",
    "sg:province":"IN",
    "wof:name":"Gas America",
    "wof:placetype":"venue"
},
  "geometry": {"coordinates":[-85.852861,41.240564],"type":"Point"}
}