{
  "type": "Feature",
  "properties": {
    "iso:country":"US",
    "sg:address":"4602 W Richland Plz",
    "sg:city":"Bloomington",
    "sg:classifiers":[
        {
            "category":"Restaurant",
            "type":"Food & Drink"
        }
    ],
    "sg:phone":"+1 812 876 1106",
    "sg:postcode":"47404",
    "sg:province":"IN",
    "sg:tags":[
        "diner"
    ],
    "wof:name":"Wee Willie's West",
    "wof:placetype":"venue"
},
  "geometry": {"coordinates":[-86.59320099999999,39.215302],"type":"Point"}
}