{
  "type": "Feature",
  "properties": {
    "addr:full":"2001 W Washington St Indianapolis IN 46222",
    "addr:housenumber":"2001",
    "addr:postcode":"46222",
    "addr:street":"W Washington St",
    "iso:country":"US",
    "sg:address":"2001 W Washington St",
    "sg:city":"Indianapolis",
    "sg:classifiers":[
        {
            "category":"Bakery",
            "type":"Food & Drink"
        }
    ],
    "sg:phone":"+1 317 955 7399",
    "sg:postcode":"46222",
    "sg:province":"IN",
    "wof:name":"Mexican Bakery Mama Ines",
    "wof:placetype":"venue"
},
  "geometry": {"coordinates":[-86.19551800000001,39.76638],"type":"Point"}
}