{
  "type": "Feature",
  "properties": {
    "iso:country":"US",
    "sg:address":"11152 Oaktree Rd W",
    "sg:city":"Brookville",
    "sg:classifiers":[
        {
            "category":"Freight",
            "type":"Transportation"
        }
    ],
    "sg:phone":"+1 765 647 3864",
    "sg:postcode":"47012",
    "sg:province":"IN",
    "sg:tags":[
        "operator",
        "local",
        "trucking"
    ],
    "wof:name":"Don Kocher Trucking",
    "wof:placetype":"venue"
},
  "geometry": {"coordinates":[-85.006919,39.372225],"type":"Point"}
}