{
  "type": "Feature",
  "properties": {
    "iso:country":"US",
    "sg:address":"2101 W Washington St",
    "sg:city":"Indianapolis",
    "sg:classifiers":[
        {
            "category":"Restaurant",
            "type":"Food & Drink"
        }
    ],
    "sg:phone":"+1 317 687 8020",
    "sg:postcode":"46222",
    "sg:province":"IN",
    "sg:tags":[
        "pizza"
    ],
    "wof:name":"Jack's Pizza",
    "wof:placetype":"venue"
},
  "geometry": {"coordinates":[-86.19689200000001,39.766251],"type":"Point"}
}