{
  "type": "Feature",
  "properties": {
    "addr:full":"305 N Briant St Huntington IN 46750",
    "addr:housenumber":"305",
    "addr:postcode":"46750",
    "addr:street":"N Briant St",
    "iso:country":"US",
    "sg:address":"305 N Briant St",
    "sg:city":"Huntington",
    "sg:classifiers":[
        {
            "category":"Professional",
            "subcategory":"Art Services",
            "type":"Services"
        }
    ],
    "sg:phone":"+1 260 359 1101",
    "sg:postcode":"46750",
    "sg:province":"IN",
    "sg:tags":[
        "graphic",
        "designer"
    ],
    "wof:name":"Innovative Edge",
    "wof:placetype":"venue"
},
  "geometry": {"coordinates":[-85.485404,40.883428],"type":"Point"}
}