{
  "type": "Feature",
  "properties": {
    "iso:country":"US",
    "sg:address":"10002 Columbia Ave",
    "sg:city":"Munster",
    "sg:classifiers":[
        {
            "category":"Social Services",
            "subcategory":"Adult Care",
            "type":"Services"
        }
    ],
    "sg:phone":"+1 219 934 0580",
    "sg:postcode":"46321",
    "sg:province":"IN",
    "sg:tags":[
        "home",
        "residential"
    ],
    "sg:website":"www.hartsfield.com",
    "wof:name":"Commons",
    "wof:placetype":"venue"
},
  "geometry": {"coordinates":[-87.512054,41.531889],"type":"Point"}
}