{
  "type": "Feature",
  "properties": {
    "addr:full":"812 W Auman Dr Carmel IN 46032",
    "addr:housenumber":"812",
    "addr:postcode":"46032",
    "addr:street":"W Auman Dr",
    "iso:country":"US",
    "sg:address":"812 W Auman Dr",
    "sg:city":"Carmel",
    "sg:classifiers":[
        {
            "category":"Building & Trades",
            "subcategory":"Cleaning & Sanitation",
            "type":"Services"
        }
    ],
    "sg:phone":"+1 317 575 8707",
    "sg:postcode":"46032",
    "sg:province":"IN",
    "sg:tags":[
        "carpet"
    ],
    "wof:name":"Mike's Carpet and Upholstery Cleaning",
    "wof:placetype":"venue"
},
  "geometry": {"coordinates":[-86.12190200000001,39.9688],"type":"Point"}
}