{
  "type": "Feature",
  "properties": {
    "iso:country":"US",
    "sg:address":"6105 Brockworth Dr",
    "sg:city":"Indianapolis",
    "sg:classifiers":[
        {
            "category":"Personal",
            "subcategory":"Nail Salon",
            "type":"Services"
        }
    ],
    "sg:phone":"+1 317 351 0985",
    "sg:postcode":"46203",
    "sg:province":"IN",
    "wof:name":"Keona's Nail Care",
    "wof:placetype":"venue"
},
  "geometry": {"coordinates":[-86.06176600000001,39.720526],"type":"Point"}
}