{
  "type": "Feature",
  "properties": {
    "iso:country":"US",
    "sg:address":"7600 Williamsburg St",
    "sg:city":"Terre Haute",
    "sg:classifiers":[
        {
            "category":"Professional",
            "subcategory":"Business Services",
            "type":"Services"
        }
    ],
    "sg:phone":"+1 812 299 9511",
    "sg:postcode":"47802",
    "sg:province":"IN",
    "wof:name":"Rebel Enterprises",
    "wof:placetype":"venue"
},
  "geometry": {"coordinates":[-87.40216,39.373096],"type":"Point"}
}