{
  "type": "Feature",
  "properties": {
    "iso:country":"US",
    "sg:address":"351 E Lincolnway",
    "sg:city":"Valparaiso",
    "sg:classifiers":[
        {
            "category":"Real Estate",
            "subcategory":"Surveying",
            "type":"Services"
        }
    ],
    "sg:phone":"+1 219 462 7452",
    "sg:postcode":"46383",
    "sg:province":"IN",
    "sg:tags":[
        "surveyor"
    ],
    "wof:name":"Emil Beeg Land Surveyor Inc",
    "wof:placetype":"venue"
},
  "geometry": {"coordinates":[-87.056716,41.467869],"type":"Point"}
}