{
  "type": "Feature",
  "properties": {
    "iso:country":"US",
    "sg:address":"205 Wilmer St",
    "sg:city":"Osgood",
    "sg:classifiers":[
        {
            "category":"Real Estate",
            "subcategory":"Real Estate Operator",
            "type":"Services"
        }
    ],
    "sg:phone":"+1 812 689 4334",
    "sg:postcode":"47037",
    "sg:province":"IN",
    "sg:tags":[
        "property",
        "lessor"
    ],
    "wof:name":"Russell Stephens",
    "wof:placetype":"venue"
},
  "geometry": {"coordinates":[-85.296699,39.135823],"type":"Point"}
}