{
  "type": "Feature",
  "properties": {
    "iso:country":"US",
    "sg:address":"408 Countryside Dr",
    "sg:city":"Ossian",
    "sg:classifiers":[
        {
            "category":"Real Estate",
            "subcategory":"Real Estate Operator",
            "type":"Services"
        }
    ],
    "sg:phone":"+1 260 622 6429",
    "sg:postcode":"46777",
    "sg:province":"IN",
    "sg:tags":[
        "apartment"
    ],
    "wof:name":"Country Place Apartments",
    "wof:placetype":"venue"
},
  "geometry": {"coordinates":[-85.17526100000001,40.875829],"type":"Point"}
}