{
  "type": "Feature",
  "properties": {
    "iso:country":"US",
    "sg:address":"1508 Massachusetts St",
    "sg:city":"Gary",
    "sg:classifiers":[
        {
            "category":"Local Transit",
            "type":"Transportation"
        }
    ],
    "sg:phone":"+1 219 886 2582",
    "sg:postcode":"46407",
    "sg:province":"IN",
    "sg:tags":[
        "handicapped"
    ],
    "wof:name":"Right On Time Transportation",
    "wof:placetype":"venue"
},
  "geometry": {"coordinates":[-87.335706,41.587017],"type":"Point"}
}