{
  "type": "Feature",
  "properties": {
    "addr:full":"2104 W Epler Ave Indianapolis IN 46217",
    "addr:housenumber":"2104",
    "addr:postcode":"46217",
    "addr:street":"W Epler Ave",
    "iso:country":"US",
    "sg:address":"2104 W Epler Ave",
    "sg:city":"Indianapolis",
    "sg:classifiers":[
        {
            "category":"Retail",
            "subcategory":"Auto Rental",
            "type":"Services"
        },
        {
            "category":"Professional",
            "subcategory":"Business Services",
            "type":"Services"
        },
        {
            "category":"Retail",
            "subcategory":"Storage",
            "type":"Services"
        },
        {
            "category":"Freight",
            "type":"Transportation"
        },
        {
            "category":"Manufacturing",
            "subcategory":"Buildings",
            "type":"Manufacturing & Wholesale Goods"
        },
        {
            "category":"Building & Trades",
            "subcategory":"Equipment Rental",
            "type":"Services"
        }
    ],
    "sg:phone":"+1 866 344 4391",
    "sg:postcode":"46217",
    "sg:province":"IN",
    "sg:tags":[
        "renting",
        "cargo",
        "leasing",
        "container",
        "portable",
        "mobile",
        "household",
        "commercial",
        "trailers-offices",
        "trailer",
        "modulars",
        "self",
        "unit",
        "contractors'"
    ],
    "sg:website":"http://ad.doubleclick.net/clk;224317918;45423610;b?http://www.mobilemini.com/branch-locations.php?source=yellowpages",
    "wof:name":"Mobile Mini",
    "wof:placetype":"venue"
},
  "geometry": {"coordinates":[-86.20106,39.685604],"type":"Point"}
}