{
  "type": "Feature",
  "properties": {
    "addr:full":"4040 Millersville Rd Indianapolis IN 46205",
    "addr:housenumber":"4040",
    "addr:postcode":"46205",
    "addr:street":"Millersville Rd",
    "iso:country":"US",
    "sg:address":"4040 Millersville Rd",
    "sg:city":"Indianapolis",
    "sg:classifiers":[
        {
            "category":"Food & Beverages",
            "subcategory":"Groceries & Convenience Stores",
            "type":"Retail Goods"
        }
    ],
    "sg:phone":"+1 317 377 1075",
    "sg:postcode":"46205",
    "sg:province":"IN",
    "wof:name":"Cathy's Cafe & Mini Mart",
    "wof:placetype":"venue"
},
  "geometry": {"coordinates":[-86.125733,39.828825],"type":"Point"}
}