{
  "type": "Feature",
  "properties": {
    "addr:full":"40 N Main St Martinsville IN 46151",
    "addr:housenumber":"40",
    "addr:postcode":"46151",
    "addr:street":"N Main St",
    "iso:country":"US",
    "sg:address":"40 N Main St",
    "sg:city":"Martinsville",
    "sg:classifiers":[
        {
            "category":"Restaurant",
            "type":"Food & Drink"
        }
    ],
    "sg:phone":"+1 765 352 1732",
    "sg:postcode":"46151",
    "sg:province":"IN",
    "wof:name":"Ruby's Diner",
    "wof:placetype":"venue"
},
  "geometry": {"coordinates":[-86.428668,39.427464],"type":"Point"}
}