{
  "type": "Feature",
  "properties": {
    "addr:full":"1962 Co Rd 20 Corunna IN 46730",
    "addr:housenumber":"1962;20",
    "addr:postcode":"46730",
    "addr:street":"Co Rd",
    "iso:country":"US",
    "sg:address":"1962 Co Rd 20",
    "sg:city":"Corunna",
    "sg:classifiers":[
        {
            "category":"Insurance",
            "subcategory":"Hazard Insurance",
            "type":"Services"
        }
    ],
    "sg:phone":"+1 260 281 2966",
    "sg:postcode":"46730",
    "sg:province":"IN",
    "sg:tags":[
        "bond"
    ],
    "wof:name":"S & L Enterprises Group Inc",
    "wof:placetype":"venue"
},
  "geometry": {"coordinates":[-85.11143800000001,41.453315],"type":"Point"}
}