{
  "type": "Feature",
  "properties": {
    "iso:country":"US",
    "sg:address":"231 N Wayne St",
    "sg:city":"Warren",
    "sg:classifiers":[
        {
            "category":"Home & Garden",
            "subcategory":"Household Appliances",
            "type":"Retail Goods"
        }
    ],
    "sg:phone":"+1 260 375 3828",
    "sg:postcode":"46792",
    "sg:province":"IN",
    "wof:name":"George De Weese Appliance Sls",
    "wof:placetype":"venue"
},
  "geometry": {"coordinates":[-85.42661,40.683354],"type":"Point"}
}