{
  "type": "Feature",
  "properties": {
    "addr:full":"4770 Covert Ave Evansville IN 47714",
    "addr:postcode":"4770;47714",
    "addr:street":"Covert Ave",
    "iso:country":"US",
    "sg:address":"4770 Covert Ave",
    "sg:city":"Evansville",
    "sg:classifiers":[
        {
            "category":"Organizations",
            "subcategory":"Professional Association",
            "type":"Services"
        }
    ],
    "sg:phone":"+1 812 479 6550",
    "sg:postcode":"47714",
    "sg:province":"IN",
    "wof:name":"Muscular Dystrophy Assn",
    "wof:placetype":"venue"
},
  "geometry": {"coordinates":[-87.495149,37.954979],"type":"Point"}
}