{
  "type": "Feature",
  "properties": {
    "iso:country":"US",
    "sg:address":"2030 N Birdie Galyan Rd",
    "sg:city":"Bloomington",
    "sg:classifiers":[
        {
            "category":"Building & Trades",
            "subcategory":"Construction",
            "type":"Services"
        }
    ],
    "sg:phone":"+1 812 331 2746",
    "sg:postcode":"47408",
    "sg:province":"IN",
    "sg:tags":[
        "general",
        "contractor"
    ],
    "wof:name":"Bluegill Construction Co",
    "wof:placetype":"venue"
},
  "geometry": {"coordinates":[-86.418147,39.19852],"type":"Point"}
}