{
  "type": "Feature",
  "properties": {
    "iso:country":"US",
    "sg:address":"5350 US Hwy 6",
    "sg:city":"Portage",
    "sg:classifiers":[
        {
            "category":"Restaurant",
            "type":"Food & Drink"
        }
    ],
    "sg:phone":"+1 219 764 0730",
    "sg:postcode":"46368",
    "sg:province":"IN",
    "wof:name":"Maple Tree House Of Pancakes",
    "wof:placetype":"venue"
},
  "geometry": {"coordinates":[-87.207621,41.550674],"type":"Point"}
}