{
  "type": "Feature",
  "properties": {
    "iso:country":"US",
    "sg:address":"108 W Washington St",
    "sg:city":"Winchester",
    "sg:classifiers":[
        {
            "category":"Organizations",
            "subcategory":"Religious Organization",
            "type":"Services"
        }
    ],
    "sg:phone":"+1 765 584 3398",
    "sg:postcode":"47394",
    "sg:province":"IN",
    "sg:tags":[
        "church"
    ],
    "wof:name":"Church Of God",
    "wof:placetype":"venue"
},
  "geometry": {"coordinates":[-84.982424,40.172611],"type":"Point"}
}