{
  "type": "Feature",
  "properties": {
    "iso:country":"US",
    "sg:address":"101 N 7th St",
    "sg:city":"Garrett",
    "sg:classifiers":[
        {
            "category":"Shopping",
            "subcategory":"Used Merchandise",
            "type":"Retail Goods"
        }
    ],
    "sg:phone":"+1 260 357 4558",
    "sg:postcode":"46738",
    "sg:province":"IN",
    "wof:name":"Parker Antiques",
    "wof:placetype":"venue"
},
  "geometry": {"coordinates":[-85.11889499999999,41.350553],"type":"Point"}
}