{
  "type": "Feature",
  "properties": {
    "iso:country":"US",
    "sg:address":"902 N Pennsylvania St",
    "sg:city":"Indianapolis",
    "sg:classifiers":[
        {
            "category":"Real Estate",
            "subcategory":"Real Estate Operator",
            "type":"Services"
        }
    ],
    "sg:phone":"+1 317 634 5555",
    "sg:postcode":"46204",
    "sg:province":"IN",
    "sg:tags":[
        "apartment"
    ],
    "wof:name":"Pennsylvania Place Apartments",
    "wof:placetype":"venue"
},
  "geometry": {"coordinates":[-86.155794,39.779629],"type":"Point"}
}