{
  "type": "Feature",
  "properties": {
    "iso:country":"US",
    "sg:address":"57057 Ash Rd",
    "sg:city":"Osceola",
    "sg:classifiers":[
        {
            "category":"Recreation",
            "type":"Entertainment"
        }
    ],
    "sg:phone":"+1 574 674 9765",
    "sg:postcode":"46561",
    "sg:province":"IN",
    "sg:tags":[
        "parks"
    ],
    "sg:website":"www.sjcparks.org",
    "wof:name":"Ferrettie/Baugo Creek County",
    "wof:placetype":"venue"
},
  "geometry": {"coordinates":[-86.061176,41.666567],"type":"Point"}
}