{
  "type": "Feature",
  "properties": {
    "iso:country":"US",
    "sg:address":"401 W 5th Ave",
    "sg:city":"Gary",
    "sg:classifiers":[
        {
            "category":"Retail",
            "subcategory":"Auto Repair",
            "type":"Services"
        }
    ],
    "sg:phone":"+1 219 886 3775",
    "sg:postcode":"46402",
    "sg:province":"IN",
    "sg:tags":[
        "repairing",
        "automobile"
    ],
    "wof:name":"Auto World Performance Plus",
    "wof:placetype":"venue"
},
  "geometry": {"coordinates":[-87.34267699999999,41.602039],"type":"Point"}
}