{
  "type": "Feature",
  "properties": {
    "iso:country":"US",
    "sg:address":"1026 Virginia Ave",
    "sg:city":"Indianapolis",
    "sg:classifiers":[
        {
            "category":"Restaurant",
            "type":"Food & Drink"
        }
    ],
    "sg:phone":"+1 317 635 6252",
    "sg:postcode":"46203",
    "sg:province":"IN",
    "sg:tags":[
        "eating"
    ],
    "wof:name":"Itza Pizza",
    "wof:placetype":"venue"
},
  "geometry": {"coordinates":[-86.141013,39.753356],"type":"Point"}
}