{
  "type": "Feature",
  "properties": {
    "iso:country":"US",
    "sg:address":"1301 Lincolnway E",
    "sg:city":"Goshen",
    "sg:classifiers":[
        {
            "category":"Manufacturing",
            "subcategory":"Tools & Machinery",
            "type":"Manufacturing & Wholesale Goods"
        }
    ],
    "sg:phone":"+1 574 533 7085",
    "sg:postcode":"46526",
    "sg:province":"IN",
    "sg:tags":[
        "machine",
        "shop"
    ],
    "wof:name":"Goshen Machine & Tool Inc",
    "wof:placetype":"venue"
},
  "geometry": {"coordinates":[-85.812326,41.573311],"type":"Point"}
}