{
  "type": "Feature",
  "properties": {
    "iso:country":"US",
    "sg:address":"2600 S Madison St",
    "sg:city":"Muncie",
    "sg:classifiers":[
        {
            "category":"Wholesale",
            "subcategory":"Machinery & Supplies",
            "type":"Manufacturing & Wholesale Goods"
        }
    ],
    "sg:phone":"+1 765 284 9166",
    "sg:postcode":"47302",
    "sg:province":"IN",
    "sg:tags":[
        "compressor",
        "gas"
    ],
    "wof:name":"Flow Solutions",
    "wof:placetype":"venue"
},
  "geometry": {"coordinates":[-85.381653,40.170307],"type":"Point"}
}