{
  "type": "Feature",
  "properties": {
    "iso:country":"US",
    "sg:address":"1734 W Plymouth St",
    "sg:city":"Bremen",
    "sg:classifiers":[
        {
            "category":"Manufacturing",
            "subcategory":"Tools & Machinery",
            "type":"Manufacturing & Wholesale Goods"
        }
    ],
    "sg:phone":"+1 574 546 2438",
    "sg:postcode":"46506",
    "sg:province":"IN",
    "sg:tags":[
        "equipment",
        "lighting"
    ],
    "wof:name":"Mint City Specialties",
    "wof:placetype":"venue"
},
  "geometry": {"coordinates":[-86.168738,41.446107],"type":"Point"}
}