{
  "type": "Feature",
  "properties": {
    "addr:full":"605 Monroe St Rochester IN 46975",
    "addr:housenumber":"605",
    "addr:postcode":"46975",
    "addr:street":"Monroe St",
    "iso:country":"US",
    "sg:address":"605 Monroe St",
    "sg:city":"Rochester",
    "sg:classifiers":[
        {
            "category":"Professional",
            "subcategory":"Business Services",
            "type":"Services"
        }
    ],
    "sg:phone":"+1 574 224 3742",
    "sg:postcode":"46975",
    "sg:province":"IN",
    "sg:tags":[
        "drafting"
    ],
    "wof:name":"CRS Machining Co",
    "wof:placetype":"venue"
},
  "geometry": {"coordinates":[-86.212805,41.068013],"type":"Point"}
}