{
  "type": "Feature",
  "properties": {
    "iso:country":"US",
    "sg:address":"3400 E Morgan Ave",
    "sg:city":"Evansville",
    "sg:classifiers":[
        {
            "category":"Autos & Motor Vehicles",
            "subcategory":"Auto Supplies",
            "type":"Retail Goods"
        }
    ],
    "sg:phone":"+1 812 476 4514",
    "sg:postcode":"47715",
    "sg:province":"IN",
    "sg:tags":[
        "tire"
    ],
    "wof:name":"Tornatta Tire",
    "wof:placetype":"venue"
},
  "geometry": {"coordinates":[-87.511472,37.991434],"type":"Point"}
}