{
  "type": "Feature",
  "properties": {
    "iso:country":"US",
    "sg:address":"2060 S 925 W",
    "sg:city":"Manilla",
    "sg:classifiers":[
        {
            "category":"Retail",
            "subcategory":"Repair Shop",
            "type":"Services"
        }
    ],
    "sg:phone":"+1 765 544 2502",
    "sg:postcode":"46150",
    "sg:province":"IN",
    "sg:tags":[
        "refrigeration"
    ],
    "wof:name":"Cadwallader Heating & Cooling",
    "wof:placetype":"venue"
},
  "geometry": {"coordinates":[-85.617349,39.58315],"type":"Point"}
}