{
  "type": "Feature",
  "properties": {
    "iso:country":"US",
    "sg:address":"200 W 103rd St",
    "sg:city":"Indianapolis",
    "sg:classifiers":[
        {
            "category":"Health Services",
            "subcategory":"Doctor",
            "type":"Services"
        }
    ],
    "sg:phone":"+1 317 278 5050",
    "sg:postcode":"46290",
    "sg:province":"IN",
    "sg:tags":[
        "physician",
        "surgeon"
    ],
    "wof:name":"Iu Medical Group Special Care",
    "wof:placetype":"venue"
},
  "geometry": {"coordinates":[-86.161889,39.935729],"type":"Point"}
}