{
  "type": "Feature",
  "properties": {
    "iso:country":"US",
    "sg:address":"8801 Melton Rd",
    "sg:city":"Gary",
    "sg:classifiers":[
        {
            "category":"Shopping",
            "subcategory":"Books",
            "type":"Retail Goods"
        }
    ],
    "sg:phone":"+1 219 938 2194",
    "sg:postcode":"46403",
    "sg:province":"IN",
    "sg:tags":[
        "dealer"
    ],
    "sg:website":"www.fun69.com",
    "wof:name":"Michigan Street Theatre & Book",
    "wof:placetype":"venue"
},
  "geometry": {"coordinates":[-87.226817,41.594397],"type":"Point"}
}