{
  "type": "Feature",
  "properties": {
    "iso:country":"US",
    "sg:address":"904 E 10th St",
    "sg:city":"Jeffersonville",
    "sg:classifiers":[
        {
            "category":"Banks & Credit Unions",
            "subcategory":"Investment Brokerage",
            "type":"Services"
        }
    ],
    "sg:phone":"+1 812 284 5910",
    "sg:postcode":"47130",
    "sg:province":"IN",
    "sg:tags":[
        "advisory",
        "financial"
    ],
    "wof:name":"K T's Financial Help Svc",
    "wof:placetype":"venue"
},
  "geometry": {"coordinates":[-85.734599,38.284924],"type":"Point"}
}