{
  "type": "Feature",
  "properties": {
    "addr:full":"1301 W Kathy's Way Greensburg IN 47240",
    "addr:housenumber":"1301",
    "addr:postcode":"47240",
    "addr:street":"W Kathy'S Way",
    "iso:country":"US",
    "sg:address":"1301 W Kathy's Way",
    "sg:city":"Greensburg",
    "sg:classifiers":[
        {
            "category":"Social Services",
            "type":"Services"
        }
    ],
    "sg:phone":"+1 812 663 9622",
    "sg:postcode":"47240",
    "sg:province":"IN",
    "sg:tags":[
        "organization",
        "welfare"
    ],
    "sg:website":"www.ymca.org",
    "wof:name":"YMCA",
    "wof:placetype":"venue"
},
  "geometry": {"coordinates":[-85.499976,39.345327],"type":"Point"}
}