{
  "type": "Feature",
  "properties": {
    "iso:country":"US",
    "sg:address":"54 Pearl St",
    "sg:city":"New Albany",
    "sg:classifiers":[
        {
            "category":"Manufacturing",
            "subcategory":"Jewelry",
            "type":"Manufacturing & Wholesale Goods"
        },
        {
            "category":"Shopping",
            "subcategory":"Jewelry",
            "type":"Retail Goods"
        }
    ],
    "sg:phone":"+1 812 945 7212",
    "sg:postcode":"47150",
    "sg:province":"IN",
    "wof:name":"Wood Brothers Jewelers",
    "wof:placetype":"venue"
},
  "geometry": {"coordinates":[-85.821538,38.28322],"type":"Point"}
}