{
  "type": "Feature",
  "properties": {
    "iso:country":"US",
    "sg:address":"6720 Allisonville Rd",
    "sg:city":"Indianapolis",
    "sg:classifiers":[
        {
            "category":"Building & Trades",
            "subcategory":"Landscaping Services",
            "type":"Services"
        }
    ],
    "sg:phone":"+1 317 257 0581",
    "sg:postcode":"46220",
    "sg:province":"IN",
    "wof:name":"Ken S Northside Tree Inc",
    "wof:placetype":"venue"
},
  "geometry": {"coordinates":[-86.091733,39.878836],"type":"Point"}
}