{
  "type": "Feature",
  "properties": {
    "iso:country":"US",
    "sg:address":"5960 E 500 S",
    "sg:city":"Whitestown",
    "sg:classifiers":[
        {
            "category":"Real Estate",
            "subcategory":"Real Estate Agent",
            "type":"Services"
        }
    ],
    "sg:phone":"+1 317 769 6691",
    "sg:postcode":"46075",
    "sg:province":"IN",
    "wof:name":"Max Properties",
    "wof:placetype":"venue"
},
  "geometry": {"coordinates":[-86.34819,39.96826],"type":"Point"}
}