{
  "type": "Feature",
  "properties": {
    "iso:country":"US",
    "sg:address":"955 S Hebron Ave",
    "sg:city":"Evansville",
    "sg:classifiers":[
        {
            "category":"Professional",
            "type":"Services"
        }
    ],
    "sg:phone":"+1 812 473 0900",
    "sg:postcode":"47714",
    "sg:province":"IN",
    "sg:tags":[
        "establishment"
    ],
    "wof:name":"Data Systems Intl",
    "wof:placetype":"venue"
},
  "geometry": {"coordinates":[-87.495777,37.964097],"type":"Point"}
}