{
  "type": "Feature",
  "properties": {
    "iso:country":"US",
    "sg:address":"8880 E 96TH ST",
    "sg:city":"FISHERS",
    "sg:classifiers":[
        {
            "category":"Restaurant",
            "type":"Food & Drink"
        }
    ],
    "sg:phone":"+1 317 595 8844",
    "sg:postcode":"46037",
    "sg:province":"IN",
    "sg:tags":[
        "pizza"
    ],
    "sg:website":"http://www.donatos.com/",
    "wof:name":"Donatos Pizzeria",
    "wof:placetype":"venue"
},
  "geometry": {"coordinates":[-86.011942,39.927233],"type":"Point"}
}