{
  "type": "Feature",
  "properties": {
    "iso:country":"US",
    "sg:address":"1401 Weber Dr",
    "sg:city":"Indianapolis",
    "sg:classifiers":[
        {
            "category":"Manufacturing",
            "subcategory":"Printing",
            "type":"Manufacturing & Wholesale Goods"
        }
    ],
    "sg:phone":"+1 317 780 0105",
    "sg:postcode":"46227",
    "sg:province":"IN",
    "sg:tags":[
        "multimedia"
    ],
    "wof:name":"Cutting Edge Multimedia",
    "wof:placetype":"venue"
},
  "geometry": {"coordinates":[-86.133748,39.662704],"type":"Point"}
}