{
  "type": "Feature",
  "properties": {
    "iso:country":"US",
    "sg:address":"1 N Broadway",
    "sg:city":"Peru",
    "sg:classifiers":[
        {
            "category":"Professional",
            "subcategory":"Lawyer & Legal Services",
            "type":"Services"
        }
    ],
    "sg:phone":"+1 765 473 7455",
    "sg:postcode":"46970",
    "sg:province":"IN",
    "sg:tags":[
        "attorney"
    ],
    "wof:name":"Thomas A Keith",
    "wof:placetype":"venue"
},
  "geometry": {"coordinates":[-86.069736,40.754591],"type":"Point"}
}