{
  "type": "Feature",
  "properties": {
    "iso:country":"US",
    "sg:address":"4510 Grape Rd",
    "sg:city":"Mishawaka",
    "sg:classifiers":[
        {
            "category":"Shopping",
            "subcategory":"Clothing, Apparel, & Fashions",
            "type":"Retail Goods"
        }
    ],
    "sg:phone":"+1 574 243 4750",
    "sg:postcode":"46545",
    "sg:province":"IN",
    "wof:name":"Old Navy",
    "wof:placetype":"venue"
},
  "geometry": {"coordinates":[-86.18734600000001,41.699042],"type":"Point"}
}