{
  "type": "Feature",
  "properties": {
    "iso:country":"US",
    "sg:address":"221 Golfway Dr",
    "sg:city":"Fort Wayne",
    "sg:classifiers":[
        {
            "category":"Building & Trades",
            "subcategory":"Construction",
            "type":"Services"
        }
    ],
    "sg:phone":"+1 260 625 6030",
    "sg:postcode":"46814",
    "sg:province":"IN",
    "sg:tags":[
        "home",
        "builder"
    ],
    "wof:name":"Hoeppner Fine Homes & Estates",
    "wof:placetype":"venue"
},
  "geometry": {"coordinates":[-85.300005,41.077422],"type":"Point"}
}