{
  "type": "Feature",
  "properties": {
    "iso:country":"US",
    "sg:address":"1035 Main St",
    "sg:city":"Anderson",
    "sg:classifiers":[
        {
            "category":"Government",
            "subcategory":"Office",
            "type":"Public Place"
        }
    ],
    "sg:phone":"+1 765 648 6310",
    "sg:postcode":"46016",
    "sg:province":"IN",
    "sg:tags":[
        "village"
    ],
    "wof:name":"Anderson Plaza Parking Garage",
    "wof:placetype":"venue"
},
  "geometry": {"coordinates":[-85.678252,40.105448],"type":"Point"}
}