{
  "type": "Feature",
  "properties": {
    "iso:country":"US",
    "sg:address":"5417 E 38th St",
    "sg:city":"Indianapolis",
    "sg:classifiers":[
        {
            "category":"Personal",
            "subcategory":"Beauty Salon",
            "type":"Services"
        }
    ],
    "sg:phone":"+1 317 547 6388",
    "sg:postcode":"46218",
    "sg:province":"IN",
    "wof:name":"Hairtight Alibi Hair Salon",
    "wof:placetype":"venue"
},
  "geometry": {"coordinates":[-86.075305,39.825368],"type":"Point"}
}