{
  "type": "Feature",
  "properties": {
    "iso:country":"US",
    "sg:address":"5311 Schneider Rd",
    "sg:city":"Newburgh",
    "sg:classifiers":[
        {
            "category":"Freight",
            "type":"Transportation"
        }
    ],
    "sg:phone":"+1 812 858 1000",
    "sg:postcode":"47630",
    "sg:province":"IN",
    "wof:name":"All Freight Svc",
    "wof:placetype":"venue"
},
  "geometry": {"coordinates":[-87.347564,37.961747],"type":"Point"}
}