{
  "type": "Feature",
  "properties": {
    "iso:country":"US",
    "sg:address":"7747 89th St",
    "sg:city":"Indianapolis",
    "sg:classifiers":[
        {
            "category":"Restaurant",
            "type":"Food & Drink"
        }
    ],
    "sg:phone":"+1 317 570 2750",
    "sg:postcode":"46256",
    "sg:province":"IN",
    "sg:tags":[
        "management"
    ],
    "wof:name":"CJM Contractors Inc",
    "wof:placetype":"venue"
},
  "geometry": {"coordinates":[-86.030346,39.917454],"type":"Point"}
}