{
  "type": "Feature",
  "properties": {
    "addr:full":"3012 N Webster Ave Indianapolis IN 46226",
    "addr:housenumber":"3012",
    "addr:postcode":"46226",
    "addr:street":"N Webster Ave",
    "iso:country":"US",
    "sg:address":"3012 N Webster Ave",
    "sg:city":"Indianapolis",
    "sg:classifiers":[
        {
            "category":"Food & Beverages",
            "subcategory":"Groceries & Convenience Stores",
            "type":"Retail Goods"
        }
    ],
    "sg:phone":"+1 317 377 0768",
    "sg:postcode":"46226",
    "sg:province":"IN",
    "wof:name":"Quick Stop",
    "wof:placetype":"venue"
},
  "geometry": {"coordinates":[-86.06313900000001,39.812607],"type":"Point"}
}