{
  "type": "Feature",
  "properties": {
    "iso:country":"US",
    "sg:address":"504 E State Rd 28",
    "sg:city":"Williamsport",
    "sg:classifiers":[
        {
            "category":"Health Services",
            "subcategory":"Chiropractor",
            "type":"Services"
        }
    ],
    "sg:phone":"+1 765 762 2384",
    "sg:postcode":"47993",
    "sg:province":"IN",
    "wof:name":"Chiropractic Care Ctr",
    "wof:placetype":"venue"
},
  "geometry": {"coordinates":[-87.305408,40.279866],"type":"Point"}
}