{
  "type": "Feature",
  "properties": {
    "iso:country":"US",
    "sg:address":"49 W Maryland St",
    "sg:city":"Indianapolis",
    "sg:classifiers":[
        {
            "category":"Shopping",
            "subcategory":"Clothing, Apparel, & Fashions",
            "type":"Retail Goods"
        }
    ],
    "sg:phone":"+1 317 951 0048",
    "sg:postcode":"46204",
    "sg:province":"IN",
    "sg:tags":[
        "sportswear"
    ],
    "wof:name":"Pacific Sunwear",
    "wof:placetype":"venue"
},
  "geometry": {"coordinates":[-86.159267,39.765585],"type":"Point"}
}