{
  "type": "Feature",
  "properties": {
    "addr:full":"23 S 8th St Noblesville IN 46060",
    "addr:housenumber":"23",
    "addr:postcode":"46060",
    "addr:street":"S 8Th St",
    "iso:country":"US",
    "sg:address":"23 S 8th St",
    "sg:city":"Noblesville",
    "sg:classifiers":[
        {
            "category":"Utilities",
            "subcategory":"Mobile Phone",
            "type":"Services"
        }
    ],
    "sg:phone":"+1 317 776 2003",
    "sg:postcode":"46060",
    "sg:province":"IN",
    "sg:tags":[
        "telephone",
        "cellular"
    ],
    "wof:name":"Daystar Global Wireless",
    "wof:placetype":"venue"
},
  "geometry": {"coordinates":[-86.01479,40.045397],"type":"Point"}
}