{
  "type": "Feature",
  "properties": {
    "iso:country":"US",
    "sg:address":"1017 Byland Dr",
    "sg:city":"Beech Grove",
    "sg:classifiers":[
        {
            "category":"Professional",
            "subcategory":"Lawyer & Legal Services",
            "type":"Services"
        }
    ],
    "sg:phone":"+1 317 784 1717",
    "sg:postcode":"46107",
    "sg:province":"IN",
    "sg:tags":[
        "attorney"
    ],
    "wof:name":"Charles W Hunter Law Office",
    "wof:placetype":"venue"
},
  "geometry": {"coordinates":[-86.094228,39.716222],"type":"Point"}
}