{
  "type": "Feature",
  "properties": {
    "iso:country":"US",
    "sg:address":"8628 Orchard Grove Ln",
    "sg:city":"Camby",
    "sg:classifiers":[
        {
            "category":"Health Services",
            "subcategory":"Health Practitioner",
            "type":"Services"
        }
    ],
    "sg:phone":"+1 317 856 4856",
    "sg:postcode":"46113",
    "sg:province":"IN",
    "sg:tags":[
        "nurse",
        "registry"
    ],
    "wof:name":"Heartland Nursing",
    "wof:placetype":"venue"
},
  "geometry": {"coordinates":[-86.312614,39.63608],"type":"Point"}
}