{
  "type": "Feature",
  "properties": {
    "iso:country":"US",
    "sg:address":"8066 Roberts Ridge Rd",
    "sg:city":"Newburgh",
    "sg:classifiers":[
        {
            "category":"Building & Trades",
            "subcategory":"Construction",
            "type":"Services"
        }
    ],
    "sg:phone":"+1 812 853 5444",
    "sg:postcode":"47630",
    "sg:province":"IN",
    "sg:tags":[
        "tile",
        "dealer",
        "contractor"
    ],
    "wof:name":"W E B Tile Specialty",
    "wof:placetype":"venue"
},
  "geometry": {"coordinates":[-87.398268,37.954306],"type":"Point"}
}