{
  "type": "Feature",
  "properties": {
    "iso:country":"US",
    "sg:address":"62839 Co Rd 37",
    "sg:city":"Goshen",
    "sg:classifiers":[
        {
            "category":"Wholesale",
            "subcategory":"Farm Supplies",
            "type":"Manufacturing & Wholesale Goods"
        }
    ],
    "sg:phone":"+1 574 642 3523",
    "sg:postcode":"46528",
    "sg:province":"IN",
    "sg:tags":[
        "feed"
    ],
    "wof:name":"Clinton Center Feed",
    "wof:placetype":"venue"
},
  "geometry": {"coordinates":[-85.713768,41.583618],"type":"Point"}
}