{
  "type": "Feature",
  "properties": {
    "iso:country":"US",
    "sg:address":"10085 W 100 S",
    "sg:city":"Angola",
    "sg:classifiers":[
        {
            "category":"Farming",
            "subcategory":"Livestock Farm",
            "type":"Manufacturing & Wholesale Goods"
        }
    ],
    "sg:phone":"+1 260 665 6926",
    "sg:postcode":"46703",
    "sg:province":"IN",
    "sg:tags":[
        "beef",
        "feedlot",
        "cattle"
    ],
    "wof:name":"Groosbeck Farms",
    "wof:placetype":"venue"
},
  "geometry": {"coordinates":[-85.179173,41.627474],"type":"Point"}
}