{
  "type": "Feature",
  "properties": {
    "iso:country":"US",
    "sg:address":"7438 S 1000 W",
    "sg:city":"Redkey",
    "sg:classifiers":[
        {
            "category":"Real Estate",
            "subcategory":"Real Estate Agent",
            "type":"Services"
        }
    ],
    "sg:phone":"+1 765 369 2402",
    "sg:postcode":"47373",
    "sg:province":"IN",
    "sg:tags":[
        "inspection"
    ],
    "wof:name":"Ligget & Assoc Inc",
    "wof:placetype":"venue"
},
  "geometry": {"coordinates":[-85.168434,40.329756],"type":"Point"}
}