{
  "type": "Feature",
  "properties": {
    "iso:country":"US",
    "sg:address":"920 S Rangeline Rd",
    "sg:city":"Anderson",
    "sg:classifiers":[
        {
            "category":"Home & Garden",
            "subcategory":"Garden Supply",
            "type":"Retail Goods"
        }
    ],
    "sg:phone":"+1 765 644 0966",
    "sg:postcode":"46012",
    "sg:province":"IN",
    "sg:tags":[
        "lawn"
    ],
    "wof:name":"R W Geeting Sales & Supply Co",
    "wof:placetype":"venue"
},
  "geometry": {"coordinates":[-85.633503,40.101493],"type":"Point"}
}