{
  "type": "Feature",
  "properties": {
    "iso:country":"US",
    "sg:address":"2524 Miracle Ln",
    "sg:city":"Mishawaka",
    "sg:classifiers":[
        {
            "category":"Shopping",
            "subcategory":"Crafts & Fabrics",
            "type":"Retail Goods"
        }
    ],
    "sg:phone":"+1 574 258 1029",
    "sg:postcode":"46545",
    "sg:province":"IN",
    "sg:tags":[
        "shop"
    ],
    "wof:name":"Hancock Fabrics",
    "wof:placetype":"venue"
},
  "geometry": {"coordinates":[-86.192814,41.681556],"type":"Point"}
}