{
  "type": "Feature",
  "properties": {
    "iso:country":"US",
    "sg:address":"1102 South St",
    "sg:city":"Shirley",
    "sg:classifiers":[
        {
            "category":"Manufacturing",
            "subcategory":"Metals",
            "type":"Manufacturing & Wholesale Goods"
        }
    ],
    "sg:phone":"+1 765 737 6551",
    "sg:postcode":"47384",
    "sg:province":"IN",
    "sg:tags":[
        "casting",
        "investment"
    ],
    "wof:name":"Metals Technology Corp",
    "wof:placetype":"venue"
},
  "geometry": {"coordinates":[-85.586471,39.889501],"type":"Point"}
}