{
  "type": "Feature",
  "properties": {
    "iso:country":"US",
    "sg:address":"508 Jackson St",
    "sg:city":"Jasper",
    "sg:classifiers":[
        {
            "category":"Banks & Credit Unions",
            "subcategory":"Investment Brokerage",
            "type":"Services"
        }
    ],
    "sg:phone":"+1 812 634 0070",
    "sg:postcode":"47546",
    "sg:province":"IN",
    "sg:tags":[
        "advisory",
        "financial"
    ],
    "wof:name":"Carnegie Wealth Strategies",
    "wof:placetype":"venue"
},
  "geometry": {"coordinates":[-86.92975800000001,38.391329],"type":"Point"}
}