{
  "type": "Feature",
  "properties": {
    "iso:country":"US",
    "sg:address":"3811 Washington St",
    "sg:city":"Gary",
    "sg:classifiers":[
        {
            "category":"Organizations",
            "subcategory":"Religious Organization",
            "type":"Services"
        }
    ],
    "sg:phone":"+1 219 887 1070",
    "sg:postcode":"46408",
    "sg:province":"IN",
    "sg:tags":[
        "church"
    ],
    "wof:name":"House Of Praise",
    "wof:placetype":"venue"
},
  "geometry": {"coordinates":[-87.337574,41.547856],"type":"Point"}
}