{
  "type": "Feature",
  "properties": {
    "iso:country":"US",
    "sg:address":"501 N Range St",
    "sg:city":"Wolcott",
    "sg:classifiers":[
        {
            "category":"Professional",
            "subcategory":"Management & Consulting",
            "type":"Services"
        }
    ],
    "sg:phone":"+1 219 279 2246",
    "sg:postcode":"47995",
    "sg:province":"IN",
    "sg:tags":[
        "communications",
        "public",
        "relations",
        "telephone"
    ],
    "wof:name":"Promotional Advantage Inc",
    "wof:placetype":"venue"
},
  "geometry": {"coordinates":[-87.04159,40.763249],"type":"Point"}
}