{
  "type": "Feature",
  "properties": {
    "addr:full":"7275 N Co Rd 550 E Pittsboro IN 46167",
    "addr:housenumber":"7275",
    "addr:postcode":"46167",
    "addr:street":"N Co Rd 550 E",
    "iso:country":"US",
    "sg:address":"7275 N Co Rd 550 E",
    "sg:city":"Pittsboro",
    "sg:classifiers":[
        {
            "category":"Professional",
            "subcategory":"Management & Consulting",
            "type":"Services"
        }
    ],
    "sg:phone":"+1 317 892 2721",
    "sg:postcode":"46167",
    "sg:province":"IN",
    "sg:tags":[
        "consultant",
        "business"
    ],
    "wof:name":"Aspire",
    "wof:placetype":"venue"
},
  "geometry": {"coordinates":[-86.43005100000001,39.871948],"type":"Point"}
}