{
  "type": "Feature",
  "properties": {
    "iso:country":"US",
    "sg:address":"21040 US Hwy 52",
    "sg:city":"Laurel",
    "sg:classifiers":[
        {
            "category":"Recreation",
            "type":"Entertainment"
        }
    ],
    "sg:phone":"+1 765 698 2044",
    "sg:postcode":"47024",
    "sg:province":"IN",
    "wof:name":"Salt Creek Ranch",
    "wof:placetype":"venue"
},
  "geometry": {"coordinates":[-85.167679,39.448271],"type":"Point"}
}