{
  "type": "Feature",
  "properties": {
    "iso:country":"US",
    "sg:address":"5353 E State Rd 46",
    "sg:city":"Bloomington",
    "sg:classifiers":[
        {
            "category":"Retail",
            "subcategory":"Portrait Studio",
            "type":"Services"
        }
    ],
    "sg:phone":"+1 812 334 1746",
    "sg:postcode":"47401",
    "sg:province":"IN",
    "sg:tags":[
        "photographer"
    ],
    "wof:name":"Shadow & Light Studio",
    "wof:placetype":"venue"
},
  "geometry": {"coordinates":[-86.458404,39.166902],"type":"Point"}
}