{
  "type": "Feature",
  "properties": {
    "iso:country":"US",
    "sg:address":"1202 Washington St",
    "sg:city":"Lafayette",
    "sg:classifiers":[
        {
            "category":"Building & Trades",
            "subcategory":"Landscaping Services",
            "type":"Services"
        }
    ],
    "sg:phone":"+1 765 491 3622",
    "sg:postcode":"47905",
    "sg:province":"IN",
    "sg:tags":[
        "landscape",
        "contractor"
    ],
    "wof:name":"Arizona Sun Landscape",
    "wof:placetype":"venue"
},
  "geometry": {"coordinates":[-86.899731,40.405725],"type":"Point"}
}