{
  "type": "Feature",
  "properties": {
    "addr:full":"235 Morton Ave Martinsville IN 46151",
    "addr:housenumber":"235",
    "addr:postcode":"46151",
    "addr:street":"Morton Ave",
    "iso:country":"US",
    "sg:address":"235 Morton Ave",
    "sg:city":"Martinsville",
    "sg:classifiers":[
        {
            "category":"Shopping",
            "subcategory":"Books",
            "type":"Retail Goods"
        }
    ],
    "sg:phone":"+1 765 349 6130",
    "sg:postcode":"46151",
    "sg:province":"IN",
    "sg:tags":[
        "dealer"
    ],
    "wof:name":"Hadley Christian Book Store",
    "wof:placetype":"venue"
},
  "geometry": {"coordinates":[-86.42902599999999,39.419066],"type":"Point"}
}