{
  "type": "Feature",
  "properties": {
    "addr:full":"3917 E 10th St Indianapolis IN 46201",
    "addr:housenumber":"3917",
    "addr:postcode":"46201",
    "addr:street":"E 10Th St",
    "iso:country":"US",
    "sg:address":"3917 E 10th St",
    "sg:city":"Indianapolis",
    "sg:classifiers":[
        {
            "category":"Wholesale",
            "subcategory":"Apparel",
            "type":"Manufacturing & Wholesale Goods"
        }
    ],
    "sg:phone":"+1 317 354 0973",
    "sg:postcode":"46201",
    "sg:province":"IN",
    "wof:name":"Woo Young Park Kim",
    "wof:placetype":"venue"
},
  "geometry": {"coordinates":[-86.09897100000001,39.781355],"type":"Point"}
}