{
  "type": "Feature",
  "properties": {
    "iso:country":"US",
    "sg:address":"112 W Jefferson St",
    "sg:city":"Plymouth",
    "sg:classifiers":[
        {
            "category":"Government",
            "subcategory":"Court House",
            "type":"Public Place"
        }
    ],
    "sg:phone":"+1 574 935 8666",
    "sg:postcode":"46563",
    "sg:province":"IN",
    "sg:tags":[
        "county",
        "counsel"
    ],
    "wof:name":"Marshall Cnty Prosecuting Atty",
    "wof:placetype":"venue"
},
  "geometry": {"coordinates":[-86.30964400000001,41.343611],"type":"Point"}
}