{
  "type": "Feature",
  "properties": {
    "iso:country":"US",
    "sg:address":"142 W Washington Ave",
    "sg:city":"Chandler",
    "sg:classifiers":[
        {
            "category":"Building & Trades",
            "subcategory":"Electrical",
            "type":"Services"
        }
    ],
    "sg:phone":"+1 812 925 8001",
    "sg:postcode":"47610",
    "sg:province":"IN",
    "sg:tags":[
        "electric",
        "contractor"
    ],
    "wof:name":"Adkins & Sons Electric",
    "wof:placetype":"venue"
},
  "geometry": {"coordinates":[-87.36888999999999,38.040212],"type":"Point"}
}