{
  "type": "Feature",
  "properties": {
    "iso:country":"US",
    "sg:address":"772 W 3rd St",
    "sg:city":"Huntingburg",
    "sg:classifiers":[
        {
            "category":"Building & Trades",
            "subcategory":"Construction",
            "type":"Services"
        }
    ],
    "sg:phone":"+1 812 683 4424",
    "sg:postcode":"47542",
    "sg:province":"IN",
    "wof:name":"Blitz Builders Inc",
    "wof:placetype":"venue"
},
  "geometry": {"coordinates":[-86.96716000000001,38.294152],"type":"Point"}
}