{
  "type": "Feature",
  "properties": {
    "iso:country":"US",
    "sg:address":"1925 N Greensburg Xing",
    "sg:city":"Greensburg",
    "sg:classifiers":[
        {
            "category":"Wholesale",
            "subcategory":"Farm Supplies",
            "type":"Manufacturing & Wholesale Goods"
        }
    ],
    "sg:phone":"+1 812 662 7447",
    "sg:postcode":"47240",
    "sg:province":"IN",
    "wof:name":"Tractor Supply Co",
    "wof:placetype":"venue"
},
  "geometry": {"coordinates":[-85.61994,39.351993],"type":"Point"}
}