{
  "type": "Feature",
  "properties": {
    "iso:country":"US",
    "sg:address":"915 S College Mall Rd",
    "sg:city":"Bloomington",
    "sg:classifiers":[
        {
            "category":"Retail",
            "subcategory":"Laundry & Dry Cleaning",
            "type":"Services"
        }
    ],
    "sg:phone":"+1 812 332 4300",
    "sg:postcode":"47401",
    "sg:province":"IN",
    "sg:tags":[
        "cleaner"
    ],
    "wof:name":"Crosstown Cleaners",
    "wof:placetype":"venue"
},
  "geometry": {"coordinates":[-86.497575,39.156426],"type":"Point"}
}