{
  "type": "Feature",
  "properties": {
    "iso:country":"US",
    "sg:address":"555 S Indiana St",
    "sg:city":"Mooresville",
    "sg:classifiers":[
        {
            "category":"Restaurant",
            "type":"Food & Drink"
        }
    ],
    "sg:phone":"+1 317 831 3345",
    "sg:postcode":"46158",
    "sg:province":"IN",
    "wof:name":"Gray Brothers Cafeteria",
    "wof:placetype":"venue"
},
  "geometry": {"coordinates":[-86.374876,39.603993],"type":"Point"}
}