{
  "type": "Feature",
  "properties": {
    "iso:country":"US",
    "sg:address":"2809 E 56th St",
    "sg:city":"Indianapolis",
    "sg:classifiers":[
        {
            "category":"Wholesale",
            "subcategory":"Non-durable Goods",
            "type":"Manufacturing & Wholesale Goods"
        }
    ],
    "sg:phone":"+1 317 257 1536",
    "sg:postcode":"46220",
    "sg:province":"IN",
    "sg:tags":[
        "advertising"
    ],
    "wof:name":"Don Payne Inc",
    "wof:placetype":"venue"
},
  "geometry": {"coordinates":[-86.11590200000001,39.854956],"type":"Point"}
}