{
  "type": "Feature",
  "properties": {
    "addr:full":"11452 State Rd 62 Charlestown IN 47111",
    "addr:housenumber":"11452;62",
    "addr:postcode":"47111",
    "addr:street":"State Rd",
    "iso:country":"US",
    "sg:address":"11452 State Rd 62",
    "sg:city":"Charlestown",
    "sg:classifiers":[
        {
            "category":"Professional",
            "subcategory":"Research",
            "type":"Services"
        }
    ],
    "sg:phone":"+1 812 256 6753",
    "sg:postcode":"47111",
    "sg:province":"IN",
    "sg:tags":[
        "environmental",
        "ecological"
    ],
    "wof:name":"Cape Environmental",
    "wof:placetype":"venue"
},
  "geometry": {"coordinates":[-85.658732,38.438916],"type":"Point"}
}