{
  "type": "Feature",
  "properties": {
    "iso:country":"US",
    "sg:address":"722 W 151st St",
    "sg:city":"East Chicago",
    "sg:classifiers":[
        {
            "category":"Retail",
            "subcategory":"Auto Repair",
            "type":"Services"
        }
    ],
    "sg:phone":"+1 219 398 1044",
    "sg:postcode":"46312",
    "sg:province":"IN",
    "wof:name":"Hoekstra Alignment & Service",
    "wof:placetype":"venue"
},
  "geometry": {"coordinates":[-87.4804,41.621399],"type":"Point"}
}