{
  "type": "Feature",
  "properties": {
    "addr:full":"1418 Blackiston Mill Rd Ste 10 Clarksville IN 47129",
    "addr:housenumber":"1418",
    "addr:postcode":"47129",
    "addr:street":"Blackiston Mill Rd Ste 10",
    "iso:country":"US",
    "sg:address":"1418 Blackiston Mill Rd Ste 10",
    "sg:city":"Clarksville",
    "sg:classifiers":[
        {
            "category":"Banks & Credit Unions",
            "subcategory":"Investment Brokerage",
            "type":"Services"
        },
        {
            "category":"Banks & Credit Unions",
            "subcategory":"Bank",
            "type":"Services"
        },
        {
            "category":"Banks & Credit Unions",
            "subcategory":"Financial Services",
            "type":"Services"
        },
        {
            "category":"Insurance",
            "subcategory":"Insurance Agent",
            "type":"Services"
        },
        {
            "category":"Insurance",
            "subcategory":"Life Insurance",
            "type":"Services"
        },
        {
            "category":"Professional",
            "subcategory":"Management & Consulting",
            "type":"Services"
        },
        {
            "category":"Insurance",
            "subcategory":"Hazard Insurance",
            "type":"Services"
        }
    ],
    "sg:phone":"+1 812 284 4963",
    "sg:postcode":"47129",
    "sg:province":"IN",
    "sg:tags":[
        "advisory",
        "mutual",
        "retirement",
        "planner",
        "profit",
        "transfer",
        "sharing",
        "broker",
        "pension",
        "fund",
        "consultant",
        "planning",
        "plan",
        "annuity",
        "bond",
        "counseling",
        "security",
        "debt",
        "analyst",
        "financing",
        "stock"
    ],
    "sg:website":"http://www.edwardjones.com",
    "wof:name":"Edward Jones Investments",
    "wof:placetype":"venue"
},
  "geometry": {"coordinates":[-85.768702,38.310584],"type":"Point"}
}