{
  "type": "Feature",
  "properties": {
    "iso:country":"US",
    "sg:address":"730 E 106th St",
    "sg:city":"Indianapolis",
    "sg:classifiers":[
        {
            "category":"Retail",
            "subcategory":"Auto Repair",
            "type":"Services"
        }
    ],
    "sg:phone":"+1 317 569 1040",
    "sg:postcode":"46280",
    "sg:province":"IN",
    "sg:tags":[
        "body",
        "shop"
    ],
    "wof:name":"Mkb Car Company",
    "wof:placetype":"venue"
},
  "geometry": {"coordinates":[-86.145798,39.9417],"type":"Point"}
}