{
  "type": "Feature",
  "properties": {
    "iso:country":"US",
    "sg:address":"1254 S Main St",
    "sg:city":"Bluffton",
    "sg:classifiers":[
        {
            "category":"Social Services",
            "type":"Services"
        }
    ],
    "sg:phone":"+1 260 827 0053",
    "sg:postcode":"46714",
    "sg:province":"IN",
    "sg:tags":[
        "food",
        "banks"
    ],
    "wof:name":"Wells County Food Bank",
    "wof:placetype":"venue"
},
  "geometry": {"coordinates":[-85.170046,40.725714],"type":"Point"}
}