{
  "type": "Feature",
  "properties": {
    "iso:country":"US",
    "sg:address":"327 N Illinois St",
    "sg:city":"Indianapolis",
    "sg:classifiers":[
        {
            "category":"Professional",
            "type":"Services"
        }
    ],
    "sg:phone":"+1 317 638 5840",
    "sg:postcode":"46204",
    "sg:province":"IN",
    "wof:name":"Maintenance Services",
    "wof:placetype":"venue"
},
  "geometry": {"coordinates":[-86.159688,39.77276],"type":"Point"}
}