{
  "type": "Feature",
  "properties": {
    "iso:country":"US",
    "sg:address":"1027 E Main St",
    "sg:city":"Plainfield",
    "sg:classifiers":[
        {
            "category":"Real Estate",
            "subcategory":"Real Estate Agent",
            "type":"Services"
        }
    ],
    "sg:phone":"+1 317 839 5121",
    "sg:postcode":"46168",
    "sg:province":"IN",
    "wof:name":"Main Street Realty",
    "wof:placetype":"venue"
},
  "geometry": {"coordinates":[-86.388077,39.707261],"type":"Point"}
}