{
  "type": "Feature",
  "properties": {
    "iso:country":"US",
    "sg:address":"3026 Mayfield Way",
    "sg:city":"Long Beach",
    "sg:classifiers":[
        {
            "category":"Building & Trades",
            "subcategory":"Construction",
            "type":"Services"
        }
    ],
    "sg:phone":"+1 219 872 8091",
    "sg:postcode":"46360",
    "sg:province":"IN",
    "sg:tags":[
        "general",
        "contractor"
    ],
    "wof:name":"Shinn Inc",
    "wof:placetype":"venue"
},
  "geometry": {"coordinates":[-86.837085,41.749921],"type":"Point"}
}