{
  "type": "Feature",
  "properties": {
    "iso:country":"US",
    "sg:address":"8451 State Rd 46",
    "sg:city":"Ellettsville",
    "sg:classifiers":[
        {
            "category":"Building & Trades",
            "subcategory":"Construction",
            "type":"Services"
        }
    ],
    "sg:phone":"+1 812 876 0789",
    "sg:postcode":"47429",
    "sg:province":"IN",
    "sg:tags":[
        "contractor"
    ],
    "wof:name":"Hines Guttering & Seal Coating",
    "wof:placetype":"venue"
},
  "geometry": {"coordinates":[-86.65561,39.254177],"type":"Point"}
}