{
  "type": "Feature",
  "properties": {
    "iso:country":"US",
    "sg:address":"210 Elm St",
    "sg:city":"Westfield",
    "sg:classifiers":[
        {
            "category":"Autos & Motor Vehicles",
            "subcategory":"Automobile Sales",
            "type":"Retail Goods"
        }
    ],
    "sg:phone":"+1 317 867 0500",
    "sg:postcode":"46074",
    "sg:province":"IN",
    "sg:tags":[
        "car",
        "dealer"
    ],
    "wof:name":"Red Line Motors",
    "wof:placetype":"venue"
},
  "geometry": {"coordinates":[-86.136436,40.042011],"type":"Point"}
}