{
  "type": "Feature",
  "properties": {
    "iso:country":"US",
    "sg:address":"209 E Main St",
    "sg:city":"Saratoga",
    "sg:classifiers":[
        {
            "category":"Government",
            "subcategory":"Post Office",
            "type":"Public Place"
        }
    ],
    "sg:phone":"+1 765 584 0090",
    "sg:postcode":"47394",
    "sg:province":"IN",
    "wof:name":"US Post Office",
    "wof:placetype":"venue"
},
  "geometry": {"coordinates":[-84.917576,40.23691],"type":"Point"}
}