{
  "type": "Feature",
  "properties": {
    "iso:country":"US",
    "sg:address":"830 State St",
    "sg:city":"Newburgh",
    "sg:classifiers":[
        {
            "category":"Food & Beverages",
            "subcategory":"Liquor & Beverages",
            "type":"Retail Goods"
        }
    ],
    "sg:phone":"+1 812 853 5735",
    "sg:postcode":"47630",
    "sg:province":"IN",
    "wof:name":"Frontier Wines & Spirits",
    "wof:placetype":"venue"
},
  "geometry": {"coordinates":[-87.405116,37.95282],"type":"Point"}
}