{
  "type": "Feature",
  "properties": {
    "iso:country":"US",
    "sg:address":"5950 Hohman Ave",
    "sg:city":"Hammond",
    "sg:classifiers":[
        {
            "category":"Professional",
            "subcategory":"Management & Consulting",
            "type":"Services"
        }
    ],
    "sg:phone":"+1 219 931 0605",
    "sg:postcode":"46320",
    "sg:province":"IN",
    "sg:tags":[
        "consultant",
        "training"
    ],
    "wof:name":"Ishmon & Assoc",
    "wof:placetype":"venue"
},
  "geometry": {"coordinates":[-87.522046,41.605382],"type":"Point"}
}