{
  "type": "Feature",
  "properties": {
    "iso:country":"US",
    "sg:address":"107 S Main St",
    "sg:city":"Nappanee",
    "sg:classifiers":[
        {
            "category":"Shopping",
            "subcategory":"Jewelry",
            "type":"Retail Goods"
        }
    ],
    "sg:phone":"+1 574 773 3241",
    "sg:postcode":"46550",
    "sg:province":"IN",
    "sg:tags":[
        "jeweler"
    ],
    "wof:name":"E Newcomer & Son",
    "wof:placetype":"venue"
},
  "geometry": {"coordinates":[-86.001208,41.44259],"type":"Point"}
}