{
  "type": "Feature",
  "properties": {
    "iso:country":"US",
    "sg:address":"1155 N Main St",
    "sg:city":"Nappanee",
    "sg:classifiers":[
        {
            "category":"Social Services",
            "subcategory":"Child Care",
            "type":"Services"
        }
    ],
    "sg:phone":"+1 574 773 3917",
    "sg:postcode":"46550",
    "sg:province":"IN",
    "sg:tags":[
        "kindergarten",
        "academic",
        "school"
    ],
    "wof:name":"Presbyterian Nursery School",
    "wof:placetype":"venue"
},
  "geometry": {"coordinates":[-86.00141000000001,41.452066],"type":"Point"}
}