{
  "type": "Feature",
  "properties": {
    "iso:country":"US",
    "sg:address":"9355 S State Rd 9",
    "sg:city":"Columbia City",
    "sg:classifiers":[
        {
            "category":"Building & Trades",
            "subcategory":"Construction",
            "type":"Services"
        }
    ],
    "sg:phone":"+1 260 396 2088",
    "sg:postcode":"46725",
    "sg:province":"IN",
    "sg:tags":[
        "carpentry",
        "contractor"
    ],
    "wof:name":"Rick Michel Carpentry",
    "wof:placetype":"venue"
},
  "geometry": {"coordinates":[-85.470589,41.028559],"type":"Point"}
}