{
  "type": "Feature",
  "properties": {
    "addr:full":"2617 E State Rd 64 Winslow IN 47598",
    "addr:housenumber":"2617;64",
    "addr:postcode":"47598",
    "addr:street":"E State Rd",
    "iso:country":"US",
    "sg:address":"2617 E State Rd 64",
    "sg:city":"Winslow",
    "sg:classifiers":[
        {
            "category":"Home & Garden",
            "subcategory":"Hardware",
            "type":"Retail Goods"
        }
    ],
    "sg:phone":"+1 812 789 2232",
    "sg:postcode":"47598",
    "sg:province":"IN",
    "wof:name":"Grubb Hardware & Farm Supply",
    "wof:placetype":"venue"
},
  "geometry": {"coordinates":[-87.22810800000001,38.331738],"type":"Point"}
}