{
  "type": "Feature",
  "properties": {
    "addr:full":"5008 N Camp Arthur Rd Bruceville IN 47516",
    "addr:housenumber":"5008",
    "addr:postcode":"47516",
    "addr:street":"N Camp Arthur Rd",
    "iso:country":"US",
    "sg:address":"5008 N Camp Arthur Rd",
    "sg:city":"Bruceville",
    "sg:phone":"+1 812 886 4023",
    "sg:postcode":"47516",
    "sg:province":"IN",
    "sg:tags":[
        "farm",
        "soybean"
    ],
    "wof:name":"Steve Keller",
    "wof:placetype":"venue"
},
  "geometry": {"coordinates":[-87.470615,38.749851],"type":"Point"}
}