{
  "type": "Feature",
  "properties": {
    "addr:full":"3702 W Sample St South Bend IN 46619",
    "addr:housenumber":"3702",
    "addr:postcode":"46619",
    "addr:street":"W Sample St",
    "iso:country":"US",
    "sg:address":"3702 W Sample St",
    "sg:city":"South Bend",
    "sg:classifiers":[
        {
            "category":"Professional",
            "subcategory":"Testing Lab",
            "type":"Services"
        }
    ],
    "sg:phone":"+1 574 287 9363",
    "sg:postcode":"46619",
    "sg:province":"IN",
    "sg:tags":[
        "laboratory"
    ],
    "wof:name":"American Plant Diagnostics Inc",
    "wof:placetype":"venue"
},
  "geometry": {"coordinates":[-86.299677,41.664593],"type":"Point"}
}