{
  "type": "Feature",
  "properties": {
    "iso:country":"US",
    "sg:address":"1015 Spring St",
    "sg:city":"Fort Wayne",
    "sg:classifiers":[
        {
            "category":"Retail",
            "subcategory":"Auto Repair",
            "type":"Services"
        }
    ],
    "sg:phone":"+1 260 426 1660",
    "sg:postcode":"46808",
    "sg:province":"IN",
    "sg:tags":[
        "repairing",
        "automobile"
    ],
    "wof:name":"Bill's Auto Repair",
    "wof:placetype":"venue"
},
  "geometry": {"coordinates":[-85.155784,41.088764],"type":"Point"}
}