{
  "type": "Feature",
  "properties": {
    "iso:country":"US",
    "sg:address":"216 State Rd 930 E",
    "sg:city":"New Haven",
    "sg:classifiers":[
        {
            "category":"Building & Trades",
            "subcategory":"Electrical",
            "type":"Services"
        }
    ],
    "sg:phone":"+1 260 749 9201",
    "sg:postcode":"46774",
    "sg:province":"IN",
    "sg:tags":[
        "booth",
        "equipment",
        "telephone",
        "pay"
    ],
    "wof:name":"Bair Payphones Inc",
    "wof:placetype":"venue"
},
  "geometry": {"coordinates":[-85.029273,41.068639],"type":"Point"}
}