{
  "type": "Feature",
  "properties": {
    "iso:country":"US",
    "sg:address":"3955 W 47th Ave",
    "sg:city":"Gary",
    "sg:classifiers":[
        {
            "category":"Government",
            "subcategory":"Fire Station",
            "type":"Public Place"
        }
    ],
    "sg:phone":"+1 219 980 8620",
    "sg:postcode":"46408",
    "sg:province":"IN",
    "sg:tags":[
        "department"
    ],
    "wof:name":"Lakeridge Fire Dept",
    "wof:placetype":"venue"
},
  "geometry": {"coordinates":[-87.384759,41.533456],"type":"Point"}
}