{
  "type": "Feature",
  "properties": {
    "iso:country":"US",
    "sg:address":"815 E State Rd 47",
    "sg:city":"Lebanon",
    "sg:classifiers":[
        {
            "category":"Professional",
            "subcategory":"Accounting & Tax Preparation",
            "type":"Services"
        }
    ],
    "sg:phone":"+1 765 325 4863",
    "sg:postcode":"46052",
    "sg:province":"IN",
    "sg:tags":[
        "bookkeeping",
        "general"
    ],
    "wof:name":"Hull Bookkeeping",
    "wof:placetype":"venue"
},
  "geometry": {"coordinates":[-86.453054,40.126222],"type":"Point"}
}