{
  "type": "Feature",
  "properties": {
    "iso:country":"US",
    "sg:address":"3645 E Market St",
    "sg:city":"Star City",
    "sg:classifiers":[
        {
            "category":"Organizations",
            "subcategory":"Religious Organization",
            "type":"Services"
        }
    ],
    "sg:phone":"+1 574 595 7744",
    "sg:postcode":"46985",
    "sg:province":"IN",
    "sg:tags":[
        "clergy"
    ],
    "wof:name":"Thornhope Community Holiness",
    "wof:placetype":"venue"
},
  "geometry": {"coordinates":[-86.529967,40.925871],"type":"Point"}
}