{
  "type": "Feature",
  "properties": {
    "iso:country":"US",
    "sg:address":"2222 Woodlawn Dr",
    "sg:city":"Laporte",
    "sg:classifiers":[
        {
            "category":"Sports & Exercise",
            "subcategory":"Golf",
            "type":"Entertainment"
        }
    ],
    "sg:phone":"+1 219 362 2651",
    "sg:postcode":"46350",
    "sg:province":"IN",
    "sg:tags":[
        "course"
    ],
    "wof:name":"Beechwood Golf Course",
    "wof:placetype":"venue"
},
  "geometry": {"coordinates":[-86.706039,41.595773],"type":"Point"}
}