{
  "type": "Feature",
  "properties": {
    "iso:country":"US",
    "sg:address":"414 E McGalliard Rd",
    "sg:city":"Muncie",
    "sg:classifiers":[
        {
            "category":"Health Services",
            "subcategory":"Hospital",
            "type":"Services"
        }
    ],
    "sg:phone":"+1 765 649 9161",
    "sg:postcode":"47303",
    "sg:province":"IN",
    "sg:tags":[
        "mental"
    ],
    "wof:name":"Center For Mental Health",
    "wof:placetype":"venue"
},
  "geometry": {"coordinates":[-85.381799,40.219084],"type":"Point"}
}