{
  "type": "Feature",
  "properties": {
    "iso:country":"US",
    "sg:address":"109 S 5th St",
    "sg:city":"Logansport",
    "sg:classifiers":[
        {
            "category":"Shopping",
            "subcategory":"Tobacco",
            "type":"Retail Goods"
        }
    ],
    "sg:phone":"+1 574 753 7231",
    "sg:postcode":"46947",
    "sg:province":"IN",
    "sg:tags":[
        "product"
    ],
    "wof:name":"Smoke House",
    "wof:placetype":"venue"
},
  "geometry": {"coordinates":[-86.364513,40.754197],"type":"Point"}
}