{
  "type": "Feature",
  "properties": {
    "iso:country":"US",
    "sg:address":"6437 Columbia Ave",
    "sg:city":"Hammond",
    "sg:classifiers":[
        {
            "category":"Restaurant",
            "type":"Food & Drink"
        }
    ],
    "sg:phone":"+1 219 933 7077",
    "sg:postcode":"46320",
    "sg:province":"IN",
    "sg:website":"www.mcdonalds.com",
    "wof:name":"McDonald's Restaurants",
    "wof:placetype":"venue"
},
  "geometry": {"coordinates":[-87.500124,41.596423],"type":"Point"}
}