{
  "type": "Feature",
  "properties": {
    "iso:country":"US",
    "sg:address":"1920 N Oak Rd",
    "sg:city":"Plymouth",
    "sg:classifiers":[
        {
            "category":"Professional",
            "subcategory":"Business Services",
            "type":"Services"
        }
    ],
    "sg:phone":"+1 574 936 1611",
    "sg:postcode":"46563",
    "sg:province":"IN",
    "sg:tags":[
        "interior",
        "consultant",
        "design",
        "decorator"
    ],
    "wof:name":"Interiors Direct Ashley Gllry",
    "wof:placetype":"venue"
},
  "geometry": {"coordinates":[-86.328756,41.357223],"type":"Point"}
}