{
  "type": "Feature",
  "properties": {
    "iso:country":"US",
    "sg:address":"3834 S Emerson Ave",
    "sg:city":"Indianapolis",
    "sg:classifiers":[
        {
            "category":"Health Services",
            "subcategory":"Doctor",
            "type":"Services"
        }
    ],
    "sg:phone":"+1 317 787 3171",
    "sg:postcode":"46203",
    "sg:province":"IN",
    "sg:tags":[
        "clinic"
    ],
    "sg:website":"www.fmc.com",
    "wof:name":"Dialysis Institute-Beech Grove",
    "wof:placetype":"venue"
},
  "geometry": {"coordinates":[-86.082663,39.710038],"type":"Point"}
}