{
  "type": "Feature",
  "properties": {
    "addr:full":"3325 E Market St Logansport IN 46947",
    "addr:housenumber":"3325",
    "addr:postcode":"46947",
    "addr:street":"E Market St",
    "iso:country":"US",
    "sg:address":"3325 E Market St",
    "sg:city":"Logansport",
    "sg:classifiers":[
        {
            "category":"Building & Trades",
            "subcategory":"Equipment Rental",
            "type":"Services"
        }
    ],
    "sg:phone":"+1 574 722 1411",
    "sg:postcode":"46947",
    "sg:province":"IN",
    "sg:tags":[
        "yard"
    ],
    "wof:name":"Logansport Equipment Rental",
    "wof:placetype":"venue"
},
  "geometry": {"coordinates":[-86.332769,40.758352],"type":"Point"}
}