{
  "type": "Feature",
  "properties": {
    "iso:country":"US",
    "sg:address":"2546 E 200 N",
    "sg:city":"Shelbyville",
    "sg:classifiers":[
        {
            "category":"Manufacturing",
            "subcategory":"Printing",
            "type":"Manufacturing & Wholesale Goods"
        }
    ],
    "sg:phone":"+1 317 392 3676",
    "sg:postcode":"46176",
    "sg:province":"IN",
    "sg:tags":[
        "printer"
    ],
    "wof:name":"Blue River Printing",
    "wof:placetype":"venue"
},
  "geometry": {"coordinates":[-85.731136,39.55461],"type":"Point"}
}