{
  "type": "Feature",
  "properties": {
    "iso:country":"US",
    "sg:address":"1101 W Jefferson St",
    "sg:city":"Plymouth",
    "sg:classifiers":[
        {
            "category":"Retail",
            "subcategory":"Auto Repair",
            "type":"Services"
        }
    ],
    "sg:phone":"+1 574 936 3005",
    "sg:postcode":"46563",
    "sg:province":"IN",
    "sg:tags":[
        "wrecker"
    ],
    "wof:name":"Bob's 24 Hour Towing",
    "wof:placetype":"venue"
},
  "geometry": {"coordinates":[-86.322312,41.343109],"type":"Point"}
}