{
  "type": "Feature",
  "properties": {
    "iso:country":"US",
    "sg:address":"201 N Morton St",
    "sg:city":"Franklin",
    "sg:classifiers":[
        {
            "category":"Building & Trades",
            "subcategory":"Equipment Rental",
            "type":"Services"
        }
    ],
    "sg:phone":"+1 317 736 4455",
    "sg:postcode":"46131",
    "sg:province":"IN",
    "sg:tags":[
        "leasing",
        "furniture"
    ],
    "wof:name":"American Rental",
    "wof:placetype":"venue"
},
  "geometry": {"coordinates":[-86.06419,39.483309],"type":"Point"}
}