{
  "type": "Feature",
  "properties": {
    "iso:country":"US",
    "sg:address":"6020 S Range Rd",
    "sg:city":"North Judson",
    "sg:classifiers":[
        {
            "category":"Autos & Motor Vehicles",
            "subcategory":"Automobile Sales",
            "type":"Retail Goods"
        }
    ],
    "sg:phone":"+1 574 896 3039",
    "sg:postcode":"46366",
    "sg:province":"IN",
    "sg:tags":[
        "car",
        "dealer"
    ],
    "wof:name":"Roy Shepherd Auto Sales",
    "wof:placetype":"venue"
},
  "geometry": {"coordinates":[-86.698277,41.215233],"type":"Point"}
}