{
  "type": "Feature",
  "properties": {
    "iso:country":"US",
    "sg:address":"180 State Rd 267",
    "sg:city":"Avon",
    "sg:classifiers":[
        {
            "category":"Professional",
            "subcategory":"Engineering",
            "type":"Services"
        }
    ],
    "sg:phone":"+1 317 272 5508",
    "sg:postcode":"46123",
    "sg:province":"IN",
    "sg:tags":[
        "engineer"
    ],
    "wof:name":"Butterworth & Kruse Consulting",
    "wof:placetype":"venue"
},
  "geometry": {"coordinates":[-86.39964500000001,39.76354],"type":"Point"}
}