{
  "type": "Feature",
  "properties": {
    "iso:country":"US",
    "sg:address":"8474 W Sycamore Rd",
    "sg:city":"Fairland",
    "sg:classifiers":[
        {
            "category":"Building & Trades",
            "subcategory":"Construction",
            "type":"Services"
        }
    ],
    "sg:phone":"+1 317 862 3372",
    "sg:postcode":"46126",
    "sg:province":"IN",
    "sg:tags":[
        "hanging",
        "contractor"
    ],
    "wof:name":"Personal Touch Painting Ind",
    "wof:placetype":"venue"
},
  "geometry": {"coordinates":[-85.94065399999999,39.665121],"type":"Point"}
}