{
  "type": "Feature",
  "properties": {
    "iso:country":"US",
    "sg:address":"2070 N Arlington Ave",
    "sg:city":"Indianapolis",
    "sg:classifiers":[
        {
            "category":"Shopping",
            "subcategory":"Florist",
            "type":"Retail Goods"
        }
    ],
    "sg:phone":"+1 317 357 1772",
    "sg:postcode":"46218",
    "sg:province":"IN",
    "sg:tags":[
        "plant"
    ],
    "wof:name":"Jill's Garden Harmony",
    "wof:placetype":"venue"
},
  "geometry": {"coordinates":[-86.06444999999999,39.795253],"type":"Point"}
}