{
  "type": "Feature",
  "properties": {
    "addr:full":"6831 E 32nd St Indianapolis IN 46226",
    "addr:housenumber":"6831",
    "addr:postcode":"46226",
    "addr:street":"E 32Nd St",
    "iso:country":"US",
    "sg:address":"6831 E 32nd St",
    "sg:city":"Indianapolis",
    "sg:classifiers":[
        {
            "category":"Building & Trades",
            "subcategory":"Construction",
            "type":"Services"
        }
    ],
    "sg:phone":"+1 317 396 0480",
    "sg:postcode":"46226",
    "sg:province":"IN",
    "sg:tags":[
        "contractor"
    ],
    "wof:name":"Greenfield Builders Inc",
    "wof:placetype":"venue"
},
  "geometry": {"coordinates":[-86.04794800000001,39.815774],"type":"Point"}
}