{
  "type": "Feature",
  "properties": {
    "addr:full":"8 W Main St Washington IN 47501",
    "addr:housenumber":"8",
    "addr:postcode":"47501",
    "addr:street":"W Main St",
    "iso:country":"US",
    "sg:address":"8 W Main St",
    "sg:city":"Washington",
    "sg:classifiers":[
        {
            "category":"Professional",
            "subcategory":"Accounting & Tax Preparation",
            "type":"Services"
        }
    ],
    "sg:phone":"+1 812 254 3442",
    "sg:postcode":"47501",
    "sg:province":"IN",
    "sg:tags":[
        "accountant"
    ],
    "wof:name":"David R Frette CPA",
    "wof:placetype":"venue"
},
  "geometry": {"coordinates":[-87.176496,38.656991],"type":"Point"}
}