{
  "type": "Feature",
  "properties": {
    "addr:full":"1449 S Lake Park Ave Hobart IN 46342",
    "addr:housenumber":"1449",
    "addr:postcode":"46342",
    "addr:street":"S Lake Park Ave",
    "iso:country":"US",
    "sg:address":"1449 S Lake Park Ave",
    "sg:city":"Hobart",
    "sg:classifiers":[
        {
            "category":"Banks & Credit Unions",
            "subcategory":"Bank",
            "type":"Services"
        }
    ],
    "sg:phone":"+1 219 942 5456",
    "sg:postcode":"46342",
    "sg:province":"IN",
    "sg:tags":[
        "loan",
        "real estate"
    ],
    "wof:name":"Mortgage Executive",
    "wof:placetype":"venue"
},
  "geometry": {"coordinates":[-87.25884600000001,41.513403],"type":"Point"}
}