{
  "type": "Feature",
  "properties": {
    "iso:country":"US",
    "sg:address":"2202 W Huron St",
    "sg:city":"South Bend",
    "sg:classifiers":[
        {
            "category":"Government",
            "subcategory":"Office",
            "type":"Public Place"
        }
    ],
    "sg:phone":"+1 574 235 5800",
    "sg:postcode":"46619",
    "sg:province":"IN",
    "sg:tags":[
        "village"
    ],
    "wof:name":"West Side Partnership Program",
    "wof:placetype":"venue"
},
  "geometry": {"coordinates":[-86.281634,41.670176],"type":"Point"}
}