{
  "type": "Feature",
  "properties": {
    "iso:country":"US",
    "sg:address":"6121 E Co Rd 100 S",
    "sg:city":"Avon",
    "sg:classifiers":[
        {
            "category":"Social Services",
            "subcategory":"Child Care",
            "type":"Services"
        }
    ],
    "sg:phone":"+1 317 797 5925",
    "sg:postcode":"46123",
    "sg:province":"IN",
    "wof:name":"Pre-School Apple House",
    "wof:placetype":"venue"
},
  "geometry": {"coordinates":[-86.417163,39.747807],"type":"Point"}
}