{
  "type": "Feature",
  "properties": {
    "iso:country":"US",
    "sg:address":"9017 W Co Rd 350 S",
    "sg:city":"Shirley",
    "sg:classifiers":[
        {
            "category":"Home & Garden",
            "subcategory":"Home Furnishings",
            "type":"Retail Goods"
        }
    ],
    "sg:phone":"+1 765 737 6868",
    "sg:postcode":"47384",
    "sg:province":"IN",
    "wof:name":"Interiors By Suzanne",
    "wof:placetype":"venue"
},
  "geometry": {"coordinates":[-85.557436,39.880064],"type":"Point"}
}