{
  "type": "Feature",
  "properties": {
    "iso:country":"US",
    "sg:address":"207 Fair St",
    "sg:city":"Valparaiso",
    "sg:classifiers":[
        {
            "category":"Professional",
            "subcategory":"Management & Consulting",
            "type":"Services"
        }
    ],
    "sg:phone":"+1 219 464 0235",
    "sg:postcode":"46383",
    "sg:province":"IN",
    "sg:tags":[
        "business"
    ],
    "wof:name":"Enviro Compliant Service LLC",
    "wof:placetype":"venue"
},
  "geometry": {"coordinates":[-87.057407,41.481352],"type":"Point"}
}