{
  "type": "Feature",
  "properties": {
    "iso:country":"US",
    "sg:address":"508 E Charles St",
    "sg:city":"Marion",
    "sg:classifiers":[
        {
            "category":"Banks & Credit Unions",
            "subcategory":"Bank",
            "type":"Services"
        }
    ],
    "sg:phone":"+1 765 662 3969",
    "sg:postcode":"46952",
    "sg:province":"IN",
    "sg:website":"www.cscfcu.org",
    "wof:name":"Charles St Comm FEDERAL Cu",
    "wof:placetype":"venue"
},
  "geometry": {"coordinates":[-85.653921,40.574407],"type":"Point"}
}