{
  "type": "Feature",
  "properties": {
    "addr:full":"4688 Cleveland St Gary IN 46408",
    "addr:housenumber":"4688",
    "addr:postcode":"46408",
    "addr:street":"Cleveland St Gary",
    "iso:country":"US",
    "sg:address":"4688 Cleveland St",
    "sg:city":"Gary",
    "sg:classifiers":[
        {
            "category":"Retail",
            "subcategory":"Auto Repair",
            "type":"Services"
        }
    ],
    "sg:phone":"+1 219 985 0455",
    "sg:postcode":"46408",
    "sg:province":"IN",
    "sg:tags":[
        "repairing",
        "tire"
    ],
    "wof:name":"Joes Tire Shop",
    "wof:placetype":"venue"
},
  "geometry": {"coordinates":[-87.36055,41.534936],"type":"Point"}
}