{
  "type": "Feature",
  "properties": {
    "addr:full":"54023 Adams St Elkhart IN 46514",
    "addr:housenumber":"54023",
    "addr:postcode":"46514",
    "addr:street":"Adams St",
    "iso:country":"US",
    "sg:address":"54023 Adams St",
    "sg:city":"Elkhart",
    "sg:classifiers":[
        {
            "category":"Real Estate",
            "subcategory":"Real Estate Agent",
            "type":"Services"
        }
    ],
    "sg:phone":"+1 574 262 2088",
    "sg:postcode":"46514",
    "sg:province":"IN",
    "wof:name":"Carol Harman",
    "wof:placetype":"venue"
},
  "geometry": {"coordinates":[-85.962019,41.708492],"type":"Point"}
}