{
  "type": "Feature",
  "properties": {
    "iso:country":"US",
    "sg:address":"9485 W Polk Rd",
    "sg:city":"Lexington",
    "sg:classifiers":[
        {
            "category":"Building & Trades",
            "subcategory":"Plumbing",
            "type":"Services"
        }
    ],
    "sg:phone":"+1 812 599 1819",
    "sg:postcode":"47138",
    "sg:province":"IN",
    "sg:tags":[
        "heating",
        "contractor"
    ],
    "wof:name":"Gordon Heating Cooling Elctrc",
    "wof:placetype":"venue"
},
  "geometry": {"coordinates":[-85.560792,38.7225],"type":"Point"}
}