{
  "type": "Feature",
  "properties": {
    "iso:country":"US",
    "sg:address":"602 Fletcher Ave",
    "sg:city":"Spencer",
    "sg:phone":"+1 812 829 3903",
    "sg:postcode":"47460",
    "sg:province":"IN",
    "sg:tags":[
        "farm",
        "soybean",
        "beef",
        "feedlot",
        "cattle"
    ],
    "wof:name":"Lewis Scholl",
    "wof:placetype":"venue"
},
  "geometry": {"coordinates":[-86.756409,39.291183],"type":"Point"}
}