{
  "type": "Feature",
  "properties": {
    "iso:country":"US",
    "sg:address":"1940 E Tipton St",
    "sg:city":"Seymour",
    "sg:classifiers":[
        {
            "category":"Autos & Motor Vehicles",
            "subcategory":"Automobile Sales",
            "type":"Retail Goods"
        }
    ],
    "sg:phone":"+1 812 523 5000",
    "sg:postcode":"47274",
    "sg:province":"IN",
    "sg:tags":[
        "car",
        "dealer"
    ],
    "wof:name":"Acra Automotive Group",
    "wof:placetype":"venue"
},
  "geometry": {"coordinates":[-85.858131,38.957907],"type":"Point"}
}