{
  "type": "Feature",
  "properties": {
    "iso:country":"US",
    "sg:address":"5301 Winthrop Ave",
    "sg:city":"Indianapolis",
    "sg:classifiers":[
        {
            "category":"Retail",
            "subcategory":"Auto Repair",
            "type":"Services"
        }
    ],
    "sg:phone":"+1 317 923 6641",
    "sg:postcode":"46220",
    "sg:province":"IN",
    "sg:tags":[
        "body",
        "automobile",
        "painting"
    ],
    "wof:name":"T & H Bodyshop",
    "wof:placetype":"venue"
},
  "geometry": {"coordinates":[-86.14180399999999,39.85111],"type":"Point"}
}