{
  "type": "Feature",
  "properties": {
    "iso:country":"US",
    "sg:address":"17022 Stonegate Ct",
    "sg:city":"Granger",
    "sg:classifiers":[
        {
            "category":"Shopping",
            "subcategory":"Hobbies, Toys, & Games",
            "type":"Retail Goods"
        }
    ],
    "sg:phone":"+1 574 277 4793",
    "sg:postcode":"46530",
    "sg:province":"IN",
    "wof:name":"Checkered Cottage",
    "wof:placetype":"venue"
},
  "geometry": {"coordinates":[-86.198599,41.758763],"type":"Point"}
}