{
  "type": "Feature",
  "properties": {
    "iso:country":"US",
    "sg:address":"99 Shorewood Dr",
    "sg:city":"Valparaiso",
    "sg:classifiers":[
        {
            "category":"Building & Trades",
            "subcategory":"Construction",
            "type":"Services"
        }
    ],
    "sg:phone":"+1 219 531 0009",
    "sg:postcode":"46385",
    "sg:province":"IN",
    "sg:tags":[
        "general",
        "contractor"
    ],
    "wof:name":"Northwind Construction",
    "wof:placetype":"venue"
},
  "geometry": {"coordinates":[-87.140437,41.453607],"type":"Point"}
}