{
  "type": "Feature",
  "properties": {
    "iso:country":"US",
    "sg:address":"8424 Naab Rd",
    "sg:city":"Indianapolis",
    "sg:classifiers":[
        {
            "category":"Health Services",
            "subcategory":"Medical Lab",
            "type":"Services"
        }
    ],
    "sg:phone":"+1 317 802 0671",
    "sg:postcode":"46260",
    "sg:province":"IN",
    "sg:tags":[
        "laboratory"
    ],
    "wof:name":"Quest Diagnostics Inc",
    "wof:placetype":"venue"
},
  "geometry": {"coordinates":[-86.19844000000001,39.908382],"type":"Point"}
}