{
  "type": "Feature",
  "properties": {
    "iso:country":"US",
    "sg:address":"107 W Main St",
    "sg:city":"Greentown",
    "sg:classifiers":[
        {
            "category":"Professional",
            "subcategory":"Computer Services",
            "type":"Services"
        }
    ],
    "sg:phone":"+1 765 628 7001",
    "sg:postcode":"46936",
    "sg:province":"IN",
    "wof:name":"Buckley's Computer Svc",
    "wof:placetype":"venue"
},
  "geometry": {"coordinates":[-85.967242,40.477877],"type":"Point"}
}