{
  "type": "Feature",
  "properties": {
    "addr:full":"5536 Brookville Rd Indianapolis IN 46219",
    "addr:housenumber":"5536",
    "addr:postcode":"46219",
    "addr:street":"Brookville Rd",
    "iso:country":"US",
    "sg:address":"5536 Brookville Rd",
    "sg:city":"Indianapolis",
    "sg:classifiers":[
        {
            "category":"Building & Trades",
            "subcategory":"Construction",
            "type":"Services"
        }
    ],
    "sg:phone":"+1 317 356 7286",
    "sg:postcode":"46219",
    "sg:province":"IN",
    "sg:tags":[
        "concrete",
        "contractor"
    ],
    "wof:name":"Light-Crete Products & Svc Inc",
    "wof:placetype":"venue"
},
  "geometry": {"coordinates":[-86.071293,39.759602],"type":"Point"}
}