{
  "type": "Feature",
  "properties": {
    "iso:country":"US",
    "sg:address":"6780 W 30th Dr",
    "sg:city":"West Terre Haute",
    "sg:classifiers":[
        {
            "category":"Retail",
            "subcategory":"Repair Shop",
            "type":"Services"
        }
    ],
    "sg:phone":"+1 812 533 0685",
    "sg:postcode":"47885",
    "sg:province":"IN",
    "sg:tags":[
        "bathtub",
        "sink",
        "refinishing"
    ],
    "wof:name":"Bath Options",
    "wof:placetype":"venue"
},
  "geometry": {"coordinates":[-87.520692,39.429949],"type":"Point"}
}