{
  "type": "Feature",
  "properties": {
    "iso:country":"US",
    "sg:address":"5415 State Rd 3",
    "sg:city":"Howe",
    "sg:classifiers":[
        {
            "category":"Organizations",
            "subcategory":"Religious Organization",
            "type":"Services"
        }
    ],
    "sg:phone":"+1 260 562 2505",
    "sg:postcode":"46746",
    "sg:province":"IN",
    "sg:tags":[
        "church"
    ],
    "wof:name":"Brighton Chapel Church",
    "wof:placetype":"venue"
},
  "geometry": {"coordinates":[-85.311015,41.718253],"type":"Point"}
}