{
  "type": "Feature",
  "properties": {
    "iso:country":"US",
    "sg:address":"1414 Fairground Rd",
    "sg:city":"Rising Sun",
    "sg:classifiers":[
        {
            "category":"Real Estate",
            "subcategory":"Real Estate Agent",
            "type":"Services"
        }
    ],
    "sg:phone":"+1 812 438 1246",
    "sg:postcode":"47040",
    "sg:province":"IN",
    "sg:tags":[
        "cooperative"
    ],
    "wof:name":"Ohio Co Op Extension",
    "wof:placetype":"venue"
},
  "geometry": {"coordinates":[-84.864017,38.957488],"type":"Point"}
}