{
  "type": "Feature",
  "properties": {
    "iso:country":"US",
    "sg:address":"814 Sunnyside Ave",
    "sg:city":"Aurora",
    "sg:classifiers":[
        {
            "category":"Organizations",
            "subcategory":"Religious Organization",
            "type":"Services"
        }
    ],
    "sg:phone":"+1 812 926 2259",
    "sg:postcode":"47001",
    "sg:province":"IN",
    "sg:tags":[
        "church"
    ],
    "wof:name":"Aurora Church Of Christ",
    "wof:placetype":"venue"
},
  "geometry": {"coordinates":[-84.904713,39.07431],"type":"Point"}
}