{
  "type": "Feature",
  "properties": {
    "iso:country":"US",
    "sg:address":"37 W 5th St",
    "sg:city":"New Albany",
    "sg:classifiers":[
        {
            "category":"Government",
            "subcategory":"Office",
            "type":"Public Place"
        }
    ],
    "sg:phone":"+1 812 948 5356",
    "sg:postcode":"47150",
    "sg:province":"IN",
    "sg:tags":[
        "city",
        "program"
    ],
    "wof:name":"Sanitation Dept",
    "wof:placetype":"venue"
},
  "geometry": {"coordinates":[-85.82828499999999,38.281237],"type":"Point"}
}