{
  "type": "Feature",
  "properties": {
    "iso:country":"US",
    "sg:address":"570 S Main St",
    "sg:city":"Churubusco",
    "sg:classifiers":[
        {
            "category":"Manufacturing",
            "subcategory":"Motor Vehicles & Parts",
            "type":"Manufacturing & Wholesale Goods"
        }
    ],
    "sg:phone":"+1 260 693 2111",
    "sg:postcode":"46723",
    "sg:province":"IN",
    "sg:tags":[
        "automobile",
        "supply"
    ],
    "wof:name":"Dana Corp",
    "wof:placetype":"venue"
},
  "geometry": {"coordinates":[-85.317973,41.227588],"type":"Point"}
}