{
  "type": "Feature",
  "properties": {
    "iso:country":"US",
    "sg:address":"2350 Turpin Ln",
    "sg:city":"Evansville",
    "sg:classifiers":[
        {
            "category":"Professional",
            "subcategory":"Business Services",
            "type":"Services"
        }
    ],
    "sg:phone":"+1 812 985 9011",
    "sg:postcode":"47712",
    "sg:province":"IN",
    "wof:name":"Professional Estimating Svc",
    "wof:placetype":"venue"
},
  "geometry": {"coordinates":[-87.691168,37.95246],"type":"Point"}
}