{
  "type": "Feature",
  "properties": {
    "iso:country":"US",
    "sg:address":"23 W Jackson St",
    "sg:city":"Sullivan",
    "sg:classifiers":[
        {
            "category":"Personal",
            "subcategory":"Beauty Salon",
            "type":"Services"
        }
    ],
    "sg:phone":"+1 812 268 3476",
    "sg:postcode":"47882",
    "sg:province":"IN",
    "sg:tags":[
        "shop"
    ],
    "wof:name":"Cheri's Country Hair Salon",
    "wof:placetype":"venue"
},
  "geometry": {"coordinates":[-87.408127,39.094303],"type":"Point"}
}