{
  "type": "Feature",
  "properties": {
    "iso:country":"US",
    "sg:address":"8720 Stellhorn Rd",
    "sg:city":"Fort Wayne",
    "sg:classifiers":[
        {
            "category":"Travel",
            "subcategory":"Travel Agent",
            "type":"Entertainment"
        }
    ],
    "sg:phone":"+1 260 486 1711",
    "sg:postcode":"46815",
    "sg:province":"IN",
    "sg:tags":[
        "ticket",
        "cruise"
    ],
    "wof:name":"Cruises Inc",
    "wof:placetype":"venue"
},
  "geometry": {"coordinates":[-85.026877,41.121272],"type":"Point"}
}