{
  "type": "Feature",
  "properties": {
    "iso:country":"US",
    "sg:address":"844 Oak Rd",
    "sg:city":"Lakeville",
    "sg:classifiers":[
        {
            "category":"Education",
            "subcategory":"Special Training",
            "type":"Public Place"
        }
    ],
    "sg:phone":"+1 574 340 3193",
    "sg:postcode":"46536",
    "sg:province":"IN",
    "sg:tags":[
        "program"
    ],
    "wof:name":"Faith Training Ctr",
    "wof:placetype":"venue"
},
  "geometry": {"coordinates":[-86.329425,41.465843],"type":"Point"}
}