{
  "type": "Feature",
  "properties": {
    "iso:country":"US",
    "sg:address":"5755 San Paul Cir",
    "sg:city":"Indianapolis",
    "sg:classifiers":[
        {
            "category":"Sports & Exercise",
            "subcategory":"Gym",
            "type":"Entertainment"
        }
    ],
    "sg:phone":"+1 317 541 0477",
    "sg:postcode":"46226",
    "sg:province":"IN",
    "sg:tags":[
        "spa",
        "health"
    ],
    "wof:name":"Dee's Day Spa",
    "wof:placetype":"venue"
},
  "geometry": {"coordinates":[-86.049387,39.858943],"type":"Point"}
}