{
  "type": "Feature",
  "properties": {
    "iso:country":"US",
    "sg:address":"8850 W 400 S",
    "sg:city":"Topeka",
    "sg:classifiers":[
        {
            "category":"Professional",
            "type":"Services"
        }
    ],
    "sg:phone":"+1 260 593 9090",
    "sg:postcode":"46571",
    "sg:province":"IN",
    "sg:tags":[
        "establishment"
    ],
    "wof:name":"Mission Interests Committee",
    "wof:placetype":"venue"
},
  "geometry": {"coordinates":[-85.594461,41.582155],"type":"Point"}
}