{
  "type": "Feature",
  "properties": {
    "iso:country":"US",
    "sg:address":"1500 Garfield St",
    "sg:city":"Lebanon",
    "sg:classifiers":[
        {
            "category":"Education",
            "subcategory":"School",
            "type":"Public Place"
        }
    ],
    "sg:phone":"+1 765 482 5940",
    "sg:postcode":"46052",
    "sg:province":"IN",
    "wof:name":"Harney Elementary",
    "wof:placetype":"venue"
},
  "geometry": {"coordinates":[-86.47757,40.05956],"type":"Point"}
}