{
  "type": "Feature",
  "properties": {
    "iso:country":"US",
    "sg:address":"5845 Lawton Loop W Dr",
    "sg:city":"Indianapolis",
    "sg:classifiers":[
        {
            "category":"Professional",
            "subcategory":"Lawyer & Legal Services",
            "type":"Services"
        },
        {
            "category":"Government",
            "subcategory":"Court House",
            "type":"Public Place"
        }
    ],
    "sg:phone":"+1 317 545 4838",
    "sg:postcode":"46216",
    "sg:province":"IN",
    "sg:tags":[
        "attorney"
    ],
    "wof:name":"Stephen A Harlow",
    "wof:placetype":"venue"
},
  "geometry": {"coordinates":[-86.01623499999999,39.857234],"type":"Point"}
}