{
  "type": "Feature",
  "properties": {
    "iso:country":"US",
    "sg:address":"230 W Catalpa Dr",
    "sg:city":"Mishawaka",
    "sg:classifiers":[
        {
            "category":"Freight",
            "type":"Transportation"
        }
    ],
    "sg:phone":"+1 574 255 2068",
    "sg:postcode":"46545",
    "sg:province":"IN",
    "sg:tags":[
        "trucking"
    ],
    "wof:name":"Gainey Transportation Svc",
    "wof:placetype":"venue"
},
  "geometry": {"coordinates":[-86.18194099999999,41.691344],"type":"Point"}
}