{
  "type": "Feature",
  "properties": {
    "iso:country":"US",
    "sg:address":"554 W 9th St",
    "sg:city":"Mishawaka",
    "sg:classifiers":[
        {
            "category":"Personal",
            "subcategory":"Beauty Salon",
            "type":"Services"
        }
    ],
    "sg:phone":"+1 574 256 6539",
    "sg:postcode":"46544",
    "sg:province":"IN",
    "sg:tags":[
        "shop"
    ],
    "wof:name":"P J's Shear Designs",
    "wof:placetype":"venue"
},
  "geometry": {"coordinates":[-86.187113,41.654032],"type":"Point"}
}