{
  "type": "Feature",
  "properties": {
    "iso:country":"US",
    "sg:address":"2210 Burton Ln",
    "sg:city":"Martinsville",
    "sg:classifiers":[
        {
            "category":"Restaurant",
            "type":"Food & Drink"
        }
    ],
    "sg:phone":"+1 765 342 5003",
    "sg:postcode":"46151",
    "sg:province":"IN",
    "wof:name":"Busick Family Restaurant",
    "wof:placetype":"venue"
},
  "geometry": {"coordinates":[-86.437218,39.404971],"type":"Point"}
}