{
  "type": "Feature",
  "properties": {
    "iso:country":"US",
    "sg:address":"826 W Main St",
    "sg:city":"New Albany",
    "sg:classifiers":[
        {
            "category":"Shopping",
            "subcategory":"Used Merchandise",
            "type":"Retail Goods"
        }
    ],
    "sg:phone":"+1 812 945 6650",
    "sg:postcode":"47150",
    "sg:province":"IN",
    "sg:tags":[
        "shop",
        "consignment"
    ],
    "wof:name":"Albanys",
    "wof:placetype":"venue"
},
  "geometry": {"coordinates":[-85.831238,38.279817],"type":"Point"}
}