{
  "type": "Feature",
  "properties": {
    "addr:full":"6245 N Washington Blvd Indianapolis IN 46220",
    "addr:housenumber":"6245",
    "addr:postcode":"46220",
    "addr:street":"N Washington Blvd",
    "iso:country":"US",
    "sg:address":"6245 N Washington Blvd",
    "sg:city":"Indianapolis",
    "sg:classifiers":[
        {
            "category":"Professional",
            "type":"Services"
        }
    ],
    "sg:phone":"+1 317 205 1016",
    "sg:postcode":"46220",
    "sg:province":"IN",
    "wof:name":"Lincoln Speech Therapy Service",
    "wof:placetype":"venue"
},
  "geometry": {"coordinates":[-86.152001,39.869243],"type":"Point"}
}