{
  "type": "Feature",
  "properties": {
    "addr:full":"1331 W 37th Ave Hobart IN 46342",
    "addr:housenumber":"1331",
    "addr:postcode":"46342",
    "addr:street":"W 37Th Ave",
    "iso:country":"US",
    "sg:address":"1331 W 37th Ave",
    "sg:city":"Hobart",
    "sg:classifiers":[
        {
            "category":"Shopping",
            "subcategory":"Florist",
            "type":"Retail Goods"
        }
    ],
    "sg:phone":"+1 219 947 1516",
    "sg:postcode":"46342",
    "sg:province":"IN",
    "wof:name":"Bryan's Florist",
    "wof:placetype":"venue"
},
  "geometry": {"coordinates":[-87.275205,41.550876],"type":"Point"}
}