{
  "type": "Feature",
  "properties": {
    "iso:country":"US",
    "sg:address":"409 N Co Rd 75 W",
    "sg:city":"Greencastle",
    "sg:classifiers":[
        {
            "category":"Government",
            "subcategory":"Office",
            "type":"Public Place"
        }
    ],
    "sg:phone":"+1 765 653 5812",
    "sg:postcode":"46135",
    "sg:province":"IN",
    "sg:tags":[
        "village"
    ],
    "wof:name":"Greencastle Pumping Station",
    "wof:placetype":"venue"
},
  "geometry": {"coordinates":[-86.866513,39.669992],"type":"Point"}
}