{
  "type": "Feature",
  "properties": {
    "iso:country":"US",
    "sg:address":"112 W Main St",
    "sg:city":"Winamac",
    "sg:classifiers":[
        {
            "category":"Sports & Exercise",
            "subcategory":"Gym",
            "type":"Entertainment"
        }
    ],
    "sg:phone":"+1 574 946 7626",
    "sg:postcode":"46996",
    "sg:province":"IN",
    "sg:tags":[
        "club",
        "health",
        "studio",
        "gymnasium"
    ],
    "wof:name":"Curves For Women",
    "wof:placetype":"venue"
},
  "geometry": {"coordinates":[-86.604149,41.050968],"type":"Point"}
}