{
  "type": "Feature",
  "properties": {
    "iso:country":"US",
    "sg:address":"13438 E State Rd 114",
    "sg:city":"Akron",
    "sg:classifiers":[
        {
            "category":"Retail",
            "subcategory":"Veterinary Services",
            "type":"Services"
        }
    ],
    "sg:phone":"+1 574 893 4028",
    "sg:postcode":"46910",
    "sg:province":"IN",
    "sg:tags":[
        "veterinarian"
    ],
    "wof:name":"Akron Animal Clinic",
    "wof:placetype":"venue"
},
  "geometry": {"coordinates":[-85.99513399999999,41.032024],"type":"Point"}
}