{
  "type": "Feature",
  "properties": {
    "iso:country":"US",
    "sg:address":"193 S Harristown Rd",
    "sg:city":"Salem",
    "sg:classifiers":[
        {
            "category":"Building & Trades",
            "subcategory":"Landscaping Services",
            "type":"Services"
        }
    ],
    "sg:phone":"+1 812 883 6024",
    "sg:postcode":"47167",
    "sg:province":"IN",
    "sg:tags":[
        "tree"
    ],
    "wof:name":"H & H Stump Removal",
    "wof:placetype":"venue"
},
  "geometry": {"coordinates":[-86.024562,38.6001],"type":"Point"}
}