{
  "type": "Feature",
  "properties": {
    "iso:country":"US",
    "sg:address":"690 Cielo Vista Dr",
    "sg:city":"Greenwood",
    "sg:classifiers":[
        {
            "category":"Professional",
            "subcategory":"Business Services",
            "type":"Services"
        }
    ],
    "sg:phone":"+1 317 888 7432",
    "sg:postcode":"46143",
    "sg:province":"IN",
    "sg:tags":[
        "interior",
        "consultant",
        "design",
        "decorator"
    ],
    "wof:name":"Laird Studio",
    "wof:placetype":"venue"
},
  "geometry": {"coordinates":[-86.096577,39.607151],"type":"Point"}
}