{
  "type": "Feature",
  "properties": {
    "iso:country":"US",
    "sg:address":"6925 W 38th St",
    "sg:city":"Indianapolis",
    "sg:classifiers":[
        {
            "category":"Retail",
            "subcategory":"Photofinishing",
            "type":"Services"
        }
    ],
    "sg:phone":"+1 317 297 0326",
    "sg:postcode":"46254",
    "sg:province":"IN",
    "sg:tags":[
        "photo",
        "finishing"
    ],
    "wof:name":"Qualex Inc",
    "wof:placetype":"venue"
},
  "geometry": {"coordinates":[-86.282721,39.823252],"type":"Point"}
}