{
  "type": "Feature",
  "properties": {
    "addr:full":"12953 Publishers Dr Ste 200 Fishers IN 46038",
    "addr:postcode":"12953;46038",
    "addr:street":"Publishers Dr Ste 200",
    "iso:country":"US",
    "sg:address":"12953 Publishers Dr Ste 200",
    "sg:city":"Fishers",
    "sg:classifiers":[
        {
            "category":"Sports & Exercise",
            "subcategory":"Sports Center",
            "type":"Entertainment"
        }
    ],
    "sg:phone":"+1 317 577 4150",
    "sg:postcode":"46038",
    "sg:province":"IN",
    "sg:tags":[
        "athletic"
    ],
    "wof:name":"Patrick Nagle Golf",
    "wof:placetype":"venue"
},
  "geometry": {"coordinates":[-86.00226000000001,39.976002],"type":"Point"}
}