{
  "type": "Feature",
  "properties": {
    "addr:full":"7744 Four Leaf Dr Greenville IN 47124",
    "addr:housenumber":"7744",
    "addr:postcode":"47124",
    "addr:street":"Four Leaf Dr",
    "iso:country":"US",
    "sg:address":"7744 Four Leaf Dr",
    "sg:city":"Greenville",
    "sg:classifiers":[
        {
            "category":"Shopping",
            "subcategory":"Gifts & Souvenirs",
            "type":"Retail Goods"
        }
    ],
    "sg:phone":"+1 812 923 9668",
    "sg:postcode":"47124",
    "sg:province":"IN",
    "wof:name":"Todays Gifts LLC",
    "wof:placetype":"venue"
},
  "geometry": {"coordinates":[-85.944412,38.350286],"type":"Point"}
}