{
  "type": "Feature",
  "properties": {
    "iso:country":"US",
    "sg:address":"1100 Stadium Dr",
    "sg:city":"Indianapolis",
    "sg:classifiers":[
        {
            "category":"Professional",
            "subcategory":"Management & Consulting",
            "type":"Services"
        }
    ],
    "sg:phone":"+1 317 972 1214",
    "sg:postcode":"46202",
    "sg:province":"IN",
    "sg:tags":[
        "consultant",
        "energy",
        "conservation"
    ],
    "wof:name":"Genome Resources",
    "wof:placetype":"venue"
},
  "geometry": {"coordinates":[-86.177722,39.782477],"type":"Point"}
}