{
  "type": "Feature",
  "properties": {
    "addr:full":"7401 N Shadeland Ave Indianapolis IN 46250",
    "addr:housenumber":"7401",
    "addr:postcode":"46250",
    "addr:street":"N Shadeland Ave",
    "iso:country":"US",
    "sg:address":"7401 N Shadeland Ave",
    "sg:city":"Indianapolis",
    "sg:classifiers":[
        {
            "category":"Restaurant",
            "type":"Food & Drink"
        }
    ],
    "sg:phone":"+1 317 845 1500",
    "sg:postcode":"46250",
    "sg:province":"IN",
    "wof:name":"Subway Sandwiches & Salads",
    "wof:placetype":"venue"
},
  "geometry": {"coordinates":[-86.04603,39.88947],"type":"Point"}
}