{
  "type": "Feature",
  "properties": {
    "addr:full":"724 N Pershing Ave Indianapolis IN 46222",
    "addr:housenumber":"724",
    "addr:postcode":"46222",
    "addr:street":"N Pershing Ave",
    "iso:country":"US",
    "sg:address":"724 N Pershing Ave",
    "sg:city":"Indianapolis",
    "sg:classifiers":[
        {
            "category":"Shopping",
            "subcategory":"Discount & Variety Stores",
            "type":"Retail Goods"
        }
    ],
    "sg:phone":"+1 317 634 5311",
    "sg:postcode":"46222",
    "sg:province":"IN",
    "wof:name":"Pershing Variety",
    "wof:placetype":"venue"
},
  "geometry": {"coordinates":[-86.19977299999999,39.778456],"type":"Point"}
}