{
  "type": "Feature",
  "properties": {
    "iso:country":"US",
    "sg:address":"2150 S Co Rd 125 W",
    "sg:city":"Logansport",
    "sg:classifiers":[
        {
            "category":"Freight",
            "type":"Transportation"
        }
    ],
    "sg:phone":"+1 574 753 0424",
    "sg:postcode":"46947",
    "sg:province":"IN",
    "sg:tags":[
        "warehouse",
        "storage"
    ],
    "sg:website":"www.hansoncoldstorage.com",
    "wof:name":"Hanson Cold Storage",
    "wof:placetype":"venue"
},
  "geometry": {"coordinates":[-86.393872,40.734334],"type":"Point"}
}