{
  "type": "Feature",
  "properties": {
    "iso:country":"US",
    "sg:address":"155 Indiana Ave",
    "sg:city":"Valparaiso",
    "sg:classifiers":[
        {
            "category":"Government",
            "subcategory":"Office",
            "type":"Public Place"
        }
    ],
    "sg:phone":"+1 219 465 3593",
    "sg:postcode":"46383",
    "sg:province":"IN",
    "wof:name":"Porter County Emerg Planning",
    "wof:placetype":"venue"
},
  "geometry": {"coordinates":[-87.06231200000001,41.466735],"type":"Point"}
}