{
  "type": "Feature",
  "properties": {
    "iso:country":"US",
    "sg:address":"1419 W Walnut St",
    "sg:city":"Washington",
    "sg:classifiers":[
        {
            "category":"Organizations",
            "subcategory":"Religious Organization",
            "type":"Services"
        }
    ],
    "sg:phone":"+1 812 254 1311",
    "sg:postcode":"47501",
    "sg:province":"IN",
    "sg:tags":[
        "church"
    ],
    "wof:name":"First United Pentecostal Chr",
    "wof:placetype":"venue"
},
  "geometry": {"coordinates":[-87.193362,38.658517],"type":"Point"}
}