{
  "type": "Feature",
  "properties": {
    "iso:country":"US",
    "sg:address":"2777 E 83rd Pl",
    "sg:city":"Merrillville",
    "sg:classifiers":[
        {
            "category":"Manufacturing",
            "subcategory":"Motor Vehicles & Parts",
            "type":"Manufacturing & Wholesale Goods"
        }
    ],
    "sg:phone":"+1 219 942 0069",
    "sg:postcode":"46410",
    "sg:province":"IN",
    "sg:tags":[
        "muffler",
        "exhaust",
        "system"
    ],
    "sg:website":"www.epiflex.com",
    "wof:name":"Exhaust Productions Inc",
    "wof:placetype":"venue"
},
  "geometry": {"coordinates":[-87.299339,41.466403],"type":"Point"}
}