{
  "type": "Feature",
  "properties": {
    "iso:country":"US",
    "sg:address":"6812 E Co Rd 1500 N",
    "sg:city":"Batesville",
    "sg:classifiers":[
        {
            "category":"Building & Trades",
            "subcategory":"Construction",
            "type":"Services"
        }
    ],
    "sg:phone":"+1 812 934 3728",
    "sg:postcode":"47006",
    "sg:province":"IN",
    "sg:tags":[
        "general",
        "contractor"
    ],
    "wof:name":"Hartman Construction Co",
    "wof:placetype":"venue"
},
  "geometry": {"coordinates":[-85.14093099999999,39.294978],"type":"Point"}
}