{
  "type": "Feature",
  "properties": {
    "addr:full":"3500 N 1st Ave Evansville IN 47710",
    "addr:housenumber":"3500",
    "addr:postcode":"47710",
    "addr:street":"N 1St Ave",
    "iso:country":"US",
    "sg:address":"3500 N 1st Ave",
    "sg:city":"Evansville",
    "sg:classifiers":[
        {
            "category":"Home & Garden",
            "subcategory":"Building Materials",
            "type":"Retail Goods"
        }
    ],
    "sg:phone":"+1 812 423 5312",
    "sg:postcode":"47710",
    "sg:province":"IN",
    "sg:tags":[
        "glass",
        "window",
        "plate"
    ],
    "sg:website":"www.harmonautoglass.com",
    "wof:name":"Harmon Auto Glass",
    "wof:placetype":"venue"
},
  "geometry": {"coordinates":[-87.57423799999999,38.013193],"type":"Point"}
}