{
  "type": "Feature",
  "properties": {
    "iso:country":"US",
    "sg:address":"505 E Main St",
    "sg:city":"Silver Lake",
    "sg:classifiers":[
        {
            "category":"Manufacturing",
            "subcategory":"Furniture",
            "type":"Manufacturing & Wholesale Goods"
        }
    ],
    "sg:phone":"+1 260 352 2102",
    "sg:postcode":"46982",
    "sg:province":"IN",
    "sg:website":"www.wabashvalley.com",
    "wof:name":"Wabash Valley Mfg Inc",
    "wof:placetype":"venue"
},
  "geometry": {"coordinates":[-85.887243,41.072069],"type":"Point"}
}