{
  "type": "Feature",
  "properties": {
    "iso:country":"US",
    "sg:address":"206 E Main St",
    "sg:city":"Thorntown",
    "sg:classifiers":[
        {
            "category":"Real Estate",
            "subcategory":"Real Estate Agent",
            "type":"Services"
        }
    ],
    "sg:phone":"+1 765 436 7733",
    "sg:postcode":"46071",
    "sg:province":"IN",
    "wof:name":"Star Real Estate Svc",
    "wof:placetype":"venue"
},
  "geometry": {"coordinates":[-86.60458300000001,40.129335],"type":"Point"}
}