{
  "type": "Feature",
  "properties": {
    "iso:country":"US",
    "sg:address":"8185 E 21st St",
    "sg:city":"Indianapolis",
    "sg:classifiers":[
        {
            "category":"Professional",
            "subcategory":"Detective & Security Services",
            "type":"Services"
        }
    ],
    "sg:phone":"+1 317 898 2870",
    "sg:postcode":"46219",
    "sg:province":"IN",
    "wof:name":"American Security Systems Inc",
    "wof:placetype":"venue"
},
  "geometry": {"coordinates":[-86.023106,39.796498],"type":"Point"}
}