{
  "type": "Feature",
  "properties": {
    "iso:country":"US",
    "sg:address":"1415 Harding Ct",
    "sg:city":"Indianapolis",
    "sg:classifiers":[
        {
            "category":"Wholesale",
            "subcategory":"Farm Supplies",
            "type":"Manufacturing & Wholesale Goods"
        }
    ],
    "sg:phone":"+1 317 787 0310",
    "sg:postcode":"46217",
    "sg:province":"IN",
    "sg:tags":[
        "fertilizer"
    ],
    "wof:name":"Lesco Service Ctr",
    "wof:placetype":"venue"
},
  "geometry": {"coordinates":[-86.18608399999999,39.693867],"type":"Point"}
}