{
  "type": "Feature",
  "properties": {
    "addr:full":"114 W 2nd St Marion IN 46952",
    "addr:housenumber":"114",
    "addr:postcode":"46952",
    "addr:street":"W 2Nd St",
    "iso:country":"US",
    "sg:address":"114 W 2nd St",
    "sg:city":"Marion",
    "sg:classifiers":[
        {
            "category":"Banks & Credit Unions",
            "subcategory":"Bank",
            "type":"Services"
        }
    ],
    "sg:phone":"+1 765 662 0471",
    "sg:postcode":"46952",
    "sg:province":"IN",
    "sg:tags":[
        "loan",
        "real estate"
    ],
    "wof:name":"Mortgage Loan Inc",
    "wof:placetype":"venue"
},
  "geometry": {"coordinates":[-85.660873,40.559823],"type":"Point"}
}