{
  "type": "Feature",
  "properties": {
    "iso:country":"US",
    "sg:address":"1095 Conner St",
    "sg:city":"Noblesville",
    "sg:classifiers":[
        {
            "category":"Food & Beverages",
            "subcategory":"Candy",
            "type":"Retail Goods"
        }
    ],
    "sg:phone":"+1 317 770 1360",
    "sg:postcode":"46060",
    "sg:province":"IN",
    "sg:website":"www.lotsacandy.com",
    "wof:name":"Candy Bouquet",
    "wof:placetype":"venue"
},
  "geometry": {"coordinates":[-86.011167,40.045525],"type":"Point"}
}