{
  "type": "Feature",
  "properties": {
    "addr:full":"3049 N Post Rd Indianapolis IN 46226",
    "addr:housenumber":"3049",
    "addr:postcode":"46226",
    "addr:street":"N Post Rd",
    "iso:country":"US",
    "sg:address":"3049 N Post Rd",
    "sg:city":"Indianapolis",
    "sg:classifiers":[
        {
            "category":"Freight",
            "type":"Transportation"
        }
    ],
    "sg:phone":"+1 317 899 7475",
    "sg:postcode":"46226",
    "sg:province":"IN",
    "sg:tags":[
        "cartage",
        "trucking"
    ],
    "sg:website":"www.kidglove.com",
    "wof:name":"Kid Glove Warehouse",
    "wof:placetype":"venue"
},
  "geometry": {"coordinates":[-86.00972299999999,39.811364],"type":"Point"}
}