{
  "type": "Feature",
  "properties": {
    "addr:full":"2249 S 800 W Wabash IN 46992",
    "addr:housenumber":"2249;800",
    "addr:postcode":"46992",
    "addr:street":"S;W Wabash",
    "iso:country":"US",
    "sg:address":"2249 S 800 W",
    "sg:city":"Wabash",
    "sg:classifiers":[
        {
            "category":"Building & Trades",
            "subcategory":"Landscaping Services",
            "type":"Services"
        }
    ],
    "sg:phone":"+1 260 563 2699",
    "sg:postcode":"46992",
    "sg:province":"IN",
    "sg:tags":[
        "landscape",
        "contractor"
    ],
    "wof:name":"Pries Turf Management & Lawn",
    "wof:placetype":"venue"
},
  "geometry": {"coordinates":[-85.94166,40.795927],"type":"Point"}
}