{
  "type": "Feature",
  "properties": {
    "iso:country":"US",
    "sg:address":"5602 Elmwood Avenue",
    "sg:city":"Indianapolis",
    "sg:classifiers":[
        {
            "category":"Building & Trades",
            "subcategory":"Cleaning & Sanitation",
            "type":"Services"
        },
        {
            "category":"Building & Trades",
            "subcategory":"Construction",
            "type":"Services"
        }
    ],
    "sg:phone":"+1 317 771 4660",
    "sg:postcode":"46203",
    "sg:province":"IN",
    "sg:tags":[
        "roofing",
        "industrial",
        "washing",
        "power",
        "cleaning-exterior",
        "contractor",
        "contractors-commercial"
    ],
    "sg:website":"http://www.stopthestreaking.com",
    "wof:name":"Indiana Roof Cleaning LLC",
    "wof:placetype":"venue"
},
  "geometry": {"coordinates":[-86.069576,39.706064],"type":"Point"}
}