{
  "type": "Feature",
  "properties": {
    "iso:country":"US",
    "sg:address":"5701 US Hwy 41",
    "sg:city":"Evansville",
    "sg:classifiers":[
        {
            "category":"Travel",
            "subcategory":"Hotels & Motels",
            "type":"Entertainment"
        }
    ],
    "sg:phone":"+1 812 464 1010",
    "sg:postcode":"47711",
    "sg:province":"IN",
    "wof:name":"Days Inn",
    "wof:placetype":"venue"
},
  "geometry": {"coordinates":[-87.538935,38.028105],"type":"Point"}
}