{
  "type": "Feature",
  "properties": {
    "iso:country":"US",
    "sg:address":"7270 S State Rd 9",
    "sg:city":"Wolcottville",
    "sg:classifiers":[
        {
            "category":"Organizations",
            "subcategory":"Religious Organization",
            "type":"Services"
        }
    ],
    "sg:phone":"+1 260 854 9106",
    "sg:postcode":"46795",
    "sg:province":"IN",
    "sg:tags":[
        "church"
    ],
    "wof:name":"Church of Stone Incorporated",
    "wof:placetype":"venue"
},
  "geometry": {"coordinates":[-85.36658,41.536556],"type":"Point"}
}