{
  "type": "Feature",
  "properties": {
    "iso:country":"US",
    "sg:address":"5935 Hohman Ave",
    "sg:city":"Hammond",
    "sg:classifiers":[
        {
            "category":"Health Services",
            "subcategory":"Health Practitioner",
            "type":"Services"
        }
    ],
    "sg:phone":"+1 219 933 0361",
    "sg:postcode":"46320",
    "sg:province":"IN",
    "sg:tags":[
        "pathologist",
        "speech"
    ],
    "wof:name":"Speech Plus",
    "wof:placetype":"venue"
},
  "geometry": {"coordinates":[-87.521896,41.605128],"type":"Point"}
}