{
  "type": "Feature",
  "properties": {
    "addr:full":"2730 Columbus Ave Anderson IN 46016",
    "addr:housenumber":"2730",
    "addr:postcode":"46016",
    "addr:street":"Columbus Ave",
    "iso:country":"US",
    "sg:address":"2730 Columbus Ave",
    "sg:city":"Anderson",
    "sg:classifiers":[
        {
            "category":"Bars & Pubs",
            "type":"Food & Drink"
        }
    ],
    "sg:phone":"+1 765 644 2077",
    "sg:postcode":"46016",
    "sg:province":"IN",
    "wof:name":"Thunderbird Bar & Restaurant",
    "wof:placetype":"venue"
},
  "geometry": {"coordinates":[-85.666917,40.088582],"type":"Point"}
}