{
  "type": "Feature",
  "properties": {
    "addr:full":"495 State Rte 246 Clay City IN 47841",
    "addr:housenumber":"495",
    "addr:postcode":"47841",
    "addr:street":"State Rte 246",
    "iso:country":"US",
    "sg:address":"495 State Rte 246",
    "sg:city":"Clay City",
    "sg:classifiers":[
        {
            "category":"Building & Trades",
            "subcategory":"Construction",
            "type":"Services"
        }
    ],
    "sg:phone":"+1 812 939 0019",
    "sg:postcode":"47841",
    "sg:province":"IN",
    "sg:tags":[
        "house"
    ],
    "wof:name":"John Moore Construction Inc",
    "wof:placetype":"venue"
},
  "geometry": {"coordinates":[-87.11268699999999,39.279718],"type":"Point"}
}