{
  "type": "Feature",
  "properties": {
    "addr:full":"27 S 1st St Scottsburg IN 47170",
    "addr:housenumber":"27",
    "addr:postcode":"47170",
    "addr:street":"S 1St St",
    "iso:country":"US",
    "sg:address":"27 S 1st St",
    "sg:city":"Scottsburg",
    "sg:classifiers":[
        {
            "category":"Food & Beverages",
            "subcategory":"Bakery",
            "type":"Retail Goods"
        }
    ],
    "sg:phone":"+1 812 752 9320",
    "sg:postcode":"47170",
    "sg:province":"IN",
    "sg:tags":[
        "baker"
    ],
    "wof:name":"Cakery",
    "wof:placetype":"venue"
},
  "geometry": {"coordinates":[-85.76889300000001,38.68552],"type":"Point"}
}