{
  "type": "Feature",
  "properties": {
    "addr:full":"2448 E Stop 11 Rd Indianapolis IN 46227",
    "addr:housenumber":"2448;11",
    "addr:postcode":"46227",
    "addr:street":"E Stop;Rd",
    "iso:country":"US",
    "sg:address":"2448 E Stop 11 Rd",
    "sg:city":"Indianapolis",
    "sg:classifiers":[
        {
            "category":"Government",
            "subcategory":"Police Station",
            "type":"Public Place"
        },
        {
            "category":"Professional",
            "subcategory":"Lawyer & Legal Services",
            "type":"Services"
        }
    ],
    "sg:phone":"+1 317 883 8800",
    "sg:postcode":"46227",
    "sg:province":"IN",
    "sg:tags":[
        "attorney",
        "law",
        "family",
        "divorce",
        "practice",
        "traffic",
        "criminal"
    ],
    "sg:website":"http://www.winkleryorklaw.com",
    "wof:name":"Law Office of Melissa Winkler-York LLC",
    "wof:placetype":"venue"
},
  "geometry": {"coordinates":[-86.119737,39.650245],"type":"Point"}
}