{
  "type": "Feature",
  "properties": {
    "addr:full":"2104 E Chicago Ave East Chicago IN 46312",
    "addr:housenumber":"2104",
    "addr:postcode":"46312",
    "addr:street":"E Chicago Ave",
    "iso:country":"US",
    "sg:address":"2104 E Chicago Ave",
    "sg:city":"East Chicago",
    "sg:classifiers":[
        {
            "category":"Restaurant",
            "type":"Food & Drink"
        }
    ],
    "sg:phone":"+1 219 397 5301",
    "sg:postcode":"46312",
    "sg:province":"IN",
    "wof:name":"J & J Fish",
    "wof:placetype":"venue"
},
  "geometry": {"coordinates":[-87.452016,41.629189],"type":"Point"}
}