{
  "type": "Feature",
  "properties": {
    "iso:country":"US",
    "sg:address":"1309 W Broadway St",
    "sg:city":"Princeton",
    "sg:classifiers":[
        {
            "category":"Health Services",
            "subcategory":"Doctor",
            "type":"Services"
        }
    ],
    "sg:phone":"+1 812 385 1838",
    "sg:postcode":"47670",
    "sg:province":"IN",
    "sg:tags":[
        "physician",
        "surgeon"
    ],
    "wof:name":"Southern Illinois Anesthesia",
    "wof:placetype":"venue"
},
  "geometry": {"coordinates":[-87.58206199999999,38.355313],"type":"Point"}
}