{
  "type": "Feature",
  "properties": {
    "addr:full":"3749 Ridge Rd Highland IN 46322",
    "addr:housenumber":"3749",
    "addr:postcode":"46322",
    "addr:street":"Ridge Rd",
    "iso:country":"US",
    "sg:address":"3749 Ridge Rd",
    "sg:city":"Highland",
    "sg:classifiers":[
        {
            "category":"Wholesale",
            "subcategory":"Plants",
            "type":"Manufacturing & Wholesale Goods"
        }
    ],
    "sg:phone":"+1 219 838 0145",
    "sg:postcode":"46322",
    "sg:province":"IN",
    "sg:tags":[
        "florist"
    ],
    "wof:name":"G & H Wholesale Florists Inc",
    "wof:placetype":"venue"
},
  "geometry": {"coordinates":[-87.437798,41.5522],"type":"Point"}
}