{
  "type": "Feature",
  "properties": {
    "iso:country":"US",
    "sg:address":"2222 N 500 E",
    "sg:city":"Huntington",
    "sg:classifiers":[
        {
            "category":"Wholesale",
            "subcategory":"Farm Supplies",
            "type":"Manufacturing & Wholesale Goods"
        }
    ],
    "sg:phone":"+1 260 356 5325",
    "sg:postcode":"46750",
    "sg:province":"IN",
    "wof:name":"Kreider Fencing & Construction",
    "wof:placetype":"venue"
},
  "geometry": {"coordinates":[-85.354901,40.860189],"type":"Point"}
}