{
  "type": "Feature",
  "properties": {
    "addr:full":"2006 Shelby St Indianapolis IN 46203",
    "addr:housenumber":"2006",
    "addr:postcode":"46203",
    "addr:street":"Shelby St",
    "iso:country":"US",
    "sg:address":"2006 Shelby St",
    "sg:city":"Indianapolis",
    "sg:classifiers":[
        {
            "category":"Autos & Motor Vehicles",
            "subcategory":"Auto Supplies",
            "type":"Retail Goods"
        }
    ],
    "sg:phone":"+1 317 783 5367",
    "sg:postcode":"46203",
    "sg:province":"IN",
    "sg:tags":[
        "used",
        "tire"
    ],
    "wof:name":"Better Used Tires",
    "wof:placetype":"venue"
},
  "geometry": {"coordinates":[-86.139836,39.739604],"type":"Point"}
}