{
  "type": "Feature",
  "properties": {
    "iso:country":"US",
    "sg:address":"108 W Plymouth St",
    "sg:city":"Bremen",
    "sg:classifiers":[
        {
            "category":"Restaurant",
            "type":"Food & Drink"
        }
    ],
    "sg:phone":"+1 574 546 3233",
    "sg:postcode":"46506",
    "sg:province":"IN",
    "wof:name":"Wooden Peel",
    "wof:placetype":"venue"
},
  "geometry": {"coordinates":[-86.147565,41.446456],"type":"Point"}
}