{
  "type": "Feature",
  "properties": {
    "iso:country":"US",
    "sg:address":"2703 Poinsette Dr",
    "sg:city":"Fort Wayne",
    "sg:classifiers":[
        {
            "category":"Retail",
            "subcategory":"Repair Shop",
            "type":"Services"
        }
    ],
    "sg:phone":"+1 260 637 0020",
    "sg:postcode":"46808",
    "sg:province":"IN",
    "sg:tags":[
        "water",
        "equipment",
        "softening"
    ],
    "wof:name":"API Advance Products Inc",
    "wof:placetype":"venue"
},
  "geometry": {"coordinates":[-85.16047500000001,41.100299],"type":"Point"}
}