{
  "type": "Feature",
  "properties": {
    "iso:country":"US",
    "sg:address":"7038 E 65th St",
    "sg:city":"Indianapolis",
    "sg:classifiers":[
        {
            "category":"Professional",
            "subcategory":"Accounting & Tax Preparation",
            "type":"Services"
        }
    ],
    "sg:phone":"+1 317 842 1270",
    "sg:postcode":"46256",
    "sg:province":"IN",
    "sg:tags":[
        "return",
        "filing"
    ],
    "wof:name":"Nixon Financial Svc",
    "wof:placetype":"venue"
},
  "geometry": {"coordinates":[-86.044579,39.876261],"type":"Point"}
}