{
  "type": "Feature",
  "properties": {
    "iso:country":"US",
    "sg:address":"129 E Chestnut St",
    "sg:city":"Corydon",
    "sg:classifiers":[
        {
            "category":"Organizations",
            "subcategory":"Community Association",
            "type":"Services"
        }
    ],
    "sg:phone":"+1 812 738 7203",
    "sg:postcode":"47112",
    "sg:province":"IN",
    "sg:tags":[
        "fraternal"
    ],
    "wof:name":"Corydon Moose Lodge",
    "wof:placetype":"venue"
},
  "geometry": {"coordinates":[-86.126025,38.210486],"type":"Point"}
}