{
  "type": "Feature",
  "properties": {
    "addr:full":"3300 Prague Rd Indianapolis IN 46227",
    "addr:housenumber":"3300",
    "addr:postcode":"46227",
    "addr:street":"Prague Rd",
    "iso:country":"US",
    "sg:address":"3300 Prague Rd",
    "sg:city":"Indianapolis",
    "sg:classifiers":[
        {
            "category":"Professional",
            "type":"Services"
        }
    ],
    "sg:phone":"+1 317 783 7726",
    "sg:postcode":"46227",
    "sg:province":"IN",
    "sg:tags":[
        "establishment"
    ],
    "wof:name":"WBIW",
    "wof:placetype":"venue"
},
  "geometry": {"coordinates":[-86.11013800000001,39.690206],"type":"Point"}
}