{
  "type": "Feature",
  "properties": {
    "iso:country":"US",
    "sg:address":"208 W Main St",
    "sg:city":"Portland",
    "sg:classifiers":[
        {
            "category":"Personal",
            "subcategory":"Beauty Salon",
            "type":"Services"
        }
    ],
    "sg:phone":"+1 260 726 2444",
    "sg:postcode":"47371",
    "sg:province":"IN",
    "sg:tags":[
        "shop"
    ],
    "wof:name":"Beck's Hair-Em",
    "wof:placetype":"venue"
},
  "geometry": {"coordinates":[-84.97924,40.433404],"type":"Point"}
}