{
  "type": "Feature",
  "properties": {
    "addr:full":"101 S Morrison Rd Muncie IN 47304",
    "addr:housenumber":"101",
    "addr:postcode":"47304",
    "addr:street":"S Morrison Rd",
    "iso:country":"US",
    "sg:address":"101 S Morrison Rd",
    "sg:city":"Muncie",
    "sg:classifiers":[
        {
            "category":"Organizations",
            "subcategory":"Religious Organization",
            "type":"Services"
        }
    ],
    "sg:phone":"+1 765 288 3238",
    "sg:postcode":"47304",
    "sg:province":"IN",
    "sg:tags":[
        "church"
    ],
    "wof:name":"First Brethren Church",
    "wof:placetype":"venue"
},
  "geometry": {"coordinates":[-85.44268599999999,40.192344],"type":"Point"}
}