{
  "type": "Feature",
  "properties": {
    "addr:full":"215 Jackson St Anderson IN 46016",
    "addr:housenumber":"215",
    "addr:postcode":"46016",
    "addr:street":"Jackson St",
    "iso:country":"US",
    "sg:address":"215 Jackson St",
    "sg:city":"Anderson",
    "sg:classifiers":[
        {
            "category":"Health Services",
            "subcategory":"Hospital",
            "type":"Services"
        }
    ],
    "sg:phone":"+1 765 646 8124",
    "sg:postcode":"46016",
    "sg:province":"IN",
    "sg:tags":[
        "general"
    ],
    "wof:name":"Saint Johns Hospital",
    "wof:placetype":"venue"
},
  "geometry": {"coordinates":[-85.68059100000001,40.112812],"type":"Point"}
}