{
  "type": "Feature",
  "properties": {
    "iso:country":"US",
    "sg:address":"1201 Wright Ave",
    "sg:city":"La Porte",
    "sg:classifiers":[
        {
            "category":"Shopping",
            "subcategory":"Gifts & Souvenirs",
            "type":"Retail Goods"
        }
    ],
    "sg:phone":"+1 219 324 7777",
    "sg:postcode":"46350",
    "sg:province":"IN",
    "wof:name":"Timeless-Gifts",
    "wof:placetype":"venue"
},
  "geometry": {"coordinates":[-86.713991,41.596447],"type":"Point"}
}