{
  "type": "Feature",
  "properties": {
    "iso:country":"US",
    "sg:address":"4025 Option Pass",
    "sg:city":"Fort Wayne",
    "sg:classifiers":[
        {
            "category":"Wholesale",
            "subcategory":"Vending Machines",
            "type":"Manufacturing & Wholesale Goods"
        }
    ],
    "sg:phone":"+1 260 489 4813",
    "sg:postcode":"46818",
    "sg:province":"IN",
    "wof:name":"Snyder Distributing Inc",
    "wof:placetype":"venue"
},
  "geometry": {"coordinates":[-85.196231,41.13809],"type":"Point"}
}