{
  "type": "Feature",
  "properties": {
    "iso:country":"US",
    "sg:address":"105 Boyd Blvd",
    "sg:city":"Laporte",
    "sg:classifiers":[
        {
            "category":"Government",
            "subcategory":"Fire Station",
            "type":"Public Place"
        }
    ],
    "sg:phone":"+1 219 362 1222",
    "sg:postcode":"46350",
    "sg:province":"IN",
    "sg:tags":[
        "department"
    ],
    "wof:name":"LA Porte Fire Dept",
    "wof:placetype":"venue"
},
  "geometry": {"coordinates":[-86.695535,41.622659],"type":"Point"}
}