{
  "type": "Feature",
  "properties": {
    "iso:country":"US",
    "sg:address":"1264 S State Rd 3",
    "sg:city":"Rushville",
    "sg:classifiers":[
        {
            "category":"Insurance",
            "subcategory":"Insurance Agent",
            "type":"Services"
        }
    ],
    "sg:phone":"+1 765 938 2217",
    "sg:postcode":"46173",
    "sg:province":"IN",
    "wof:name":"Dyer Insurance",
    "wof:placetype":"venue"
},
  "geometry": {"coordinates":[-85.444163,39.593922],"type":"Point"}
}