{
  "type": "Feature",
  "properties": {
    "iso:country":"US",
    "sg:address":"912 W Main St",
    "sg:city":"Crawfordsville",
    "sg:classifiers":[
        {
            "category":"Building & Trades",
            "subcategory":"Pest Control",
            "type":"Services"
        }
    ],
    "sg:phone":"+1 765 362 7707",
    "sg:postcode":"47933",
    "sg:province":"IN",
    "wof:name":"Arab Termite & Pest Control",
    "wof:placetype":"venue"
},
  "geometry": {"coordinates":[-86.913095,40.041691],"type":"Point"}
}