{
  "type": "Feature",
  "properties": {
    "addr:full":"14 N Indiana St Mooresville IN 46158",
    "addr:housenumber":"14",
    "addr:postcode":"46158",
    "addr:street":"N Indiana St",
    "iso:country":"US",
    "sg:address":"14 N Indiana St",
    "sg:city":"Mooresville",
    "sg:classifiers":[
        {
            "category":"Insurance",
            "subcategory":"Insurance Agent",
            "type":"Services"
        }
    ],
    "sg:phone":"+1 317 831 1081",
    "sg:postcode":"46158",
    "sg:province":"IN",
    "wof:name":"Alexander Insurance",
    "wof:placetype":"venue"
},
  "geometry": {"coordinates":[-86.375012,39.613245],"type":"Point"}
}