{
  "type": "Feature",
  "properties": {
    "iso:country":"US",
    "sg:address":"105 W Roe St",
    "sg:city":"Ossian",
    "sg:classifiers":[
        {
            "category":"Government",
            "subcategory":"Office",
            "type":"Public Place"
        }
    ],
    "sg:phone":"+1 260 622 4109",
    "sg:postcode":"46777",
    "sg:province":"IN",
    "sg:tags":[
        "county",
        "govt",
        "program"
    ],
    "wof:name":"Wells County Auto License",
    "wof:placetype":"venue"
},
  "geometry": {"coordinates":[-85.167963,40.881824],"type":"Point"}
}