{
  "type": "Feature",
  "properties": {
    "iso:country":"US",
    "sg:address":"2222 S Michigan St",
    "sg:city":"South Bend",
    "sg:classifiers":[
        {
            "category":"Retail",
            "subcategory":"Auto Repair",
            "type":"Services"
        }
    ],
    "sg:phone":"+1 574 234 7105",
    "sg:postcode":"46613",
    "sg:province":"IN",
    "sg:tags":[
        "muffler",
        "exhaust",
        "system"
    ],
    "wof:name":"Discount Muffler & Tire Inc",
    "wof:placetype":"venue"
},
  "geometry": {"coordinates":[-86.249638,41.650796],"type":"Point"}
}