{
  "type": "Feature",
  "properties": {
    "iso:country":"US",
    "sg:address":"3502 W Joliet Rd",
    "sg:city":"Laporte",
    "sg:classifiers":[
        {
            "category":"Organizations",
            "subcategory":"Religious Organization",
            "type":"Services"
        }
    ],
    "sg:phone":"+1 219 362 3812",
    "sg:postcode":"46350",
    "sg:province":"IN",
    "sg:tags":[
        "church"
    ],
    "wof:name":"Door Village United Methodist",
    "wof:placetype":"venue"
},
  "geometry": {"coordinates":[-86.768863,41.574541],"type":"Point"}
}