{
  "type": "Feature",
  "properties": {
    "iso:country":"US",
    "sg:address":"588 W 375 N",
    "sg:city":"Rochester",
    "sg:classifiers":[
        {
            "category":"Freight",
            "type":"Transportation"
        }
    ],
    "sg:phone":"+1 574 224 2846",
    "sg:postcode":"46975",
    "sg:province":"IN",
    "sg:tags":[
        "trucking"
    ],
    "wof:name":"Eriks Trucking",
    "wof:placetype":"venue"
},
  "geometry": {"coordinates":[-86.241492,41.109654],"type":"Point"}
}