{
  "type": "Feature",
  "properties": {
    "iso:country":"US",
    "sg:address":"107 N Main St",
    "sg:city":"Batesville",
    "sg:classifiers":[
        {
            "category":"Arts & Performance",
            "subcategory":"Theater",
            "type":"Entertainment"
        }
    ],
    "sg:phone":"+1 812 934 3212",
    "sg:postcode":"47006",
    "sg:province":"IN",
    "sg:website":"www.wolftheatres.com",
    "wof:name":"Gibson Theatre",
    "wof:placetype":"venue"
},
  "geometry": {"coordinates":[-85.221509,39.300047],"type":"Point"}
}