{
  "type": "Feature",
  "properties": {
    "iso:country":"US",
    "sg:address":"850 W Business 30",
    "sg:city":"Columbia City",
    "sg:classifiers":[
        {
            "category":"Organizations",
            "subcategory":"Religious Organization",
            "type":"Services"
        }
    ],
    "sg:phone":"+1 260 244 6055",
    "sg:postcode":"46725",
    "sg:province":"IN",
    "sg:tags":[
        "church"
    ],
    "wof:name":"Faith Baptist Church",
    "wof:placetype":"venue"
},
  "geometry": {"coordinates":[-85.50857000000001,41.159587],"type":"Point"}
}