{
  "type": "Feature",
  "properties": {
    "addr:full":"3902 N Pasadena St Indianapolis IN 46226",
    "addr:housenumber":"3902",
    "addr:postcode":"46226",
    "addr:street":"N Pasadena St",
    "iso:country":"US",
    "sg:address":"3902 N Pasadena St",
    "sg:city":"Indianapolis",
    "sg:classifiers":[
        {
            "category":"Shopping",
            "subcategory":"Gifts & Souvenirs",
            "type":"Retail Goods"
        }
    ],
    "sg:phone":"+1 317 547 8227",
    "sg:postcode":"46226",
    "sg:province":"IN",
    "wof:name":"Family Gifts",
    "wof:placetype":"venue"
},
  "geometry": {"coordinates":[-86.054171,39.827933],"type":"Point"}
}