{
  "type": "Feature",
  "properties": {
    "iso:country":"US",
    "sg:address":"3896 Wolf Creek Cir",
    "sg:city":"Carmel",
    "sg:classifiers":[
        {
            "category":"Insurance",
            "subcategory":"Insurance Agent",
            "type":"Services"
        }
    ],
    "sg:phone":"+1 317 848 7996",
    "sg:postcode":"46033",
    "sg:province":"IN",
    "wof:name":"Trak Agency Inc",
    "wof:placetype":"venue"
},
  "geometry": {"coordinates":[-86.100392,39.933415],"type":"Point"}
}