{
  "type": "Feature",
  "properties": {
    "iso:country":"US",
    "sg:address":"4849 Ford St",
    "sg:city":"South Bend",
    "sg:classifiers":[
        {
            "category":"Social Services",
            "subcategory":"Child Care",
            "type":"Services"
        }
    ],
    "sg:phone":"+1 574 234 1127",
    "sg:postcode":"46619",
    "sg:province":"IN",
    "sg:tags":[
        "kindergarten",
        "academic",
        "school"
    ],
    "wof:name":"Fellowship Baptist School",
    "wof:placetype":"venue"
},
  "geometry": {"coordinates":[-86.315674,41.668423],"type":"Point"}
}