{
  "type": "Feature",
  "properties": {
    "iso:country":"US",
    "sg:address":"91 Industrial Blvd",
    "sg:city":"Logansport",
    "sg:classifiers":[
        {
            "category":"Manufacturing",
            "subcategory":"Motor Vehicles & Parts",
            "type":"Manufacturing & Wholesale Goods"
        }
    ],
    "sg:phone":"+1 574 735 0235",
    "sg:postcode":"46947",
    "sg:province":"IN",
    "sg:tags":[
        "automobile",
        "supply"
    ],
    "wof:name":"Federal Mogul Lighting Elctrcl",
    "wof:placetype":"venue"
},
  "geometry": {"coordinates":[-86.379458,40.7223],"type":"Point"}
}