{
  "type": "Feature",
  "properties": {
    "addr:full":"121 N Hart St Princeton IN 47670",
    "addr:housenumber":"121",
    "addr:postcode":"47670",
    "addr:street":"N Hart St",
    "iso:country":"US",
    "sg:address":"121 N Hart St",
    "sg:city":"Princeton",
    "sg:classifiers":[
        {
            "category":"Banks & Credit Unions",
            "subcategory":"Investment Brokerage",
            "type":"Services"
        }
    ],
    "sg:phone":"+1 812 385 3323",
    "sg:postcode":"47670",
    "sg:province":"IN",
    "sg:tags":[
        "security"
    ],
    "wof:name":"Hilliard Lyons Inc",
    "wof:placetype":"venue"
},
  "geometry": {"coordinates":[-87.568826,38.356031],"type":"Point"}
}