{
  "type": "Feature",
  "properties": {
    "iso:country":"US",
    "sg:address":"7202 N Shadeland Ave",
    "sg:city":"Indianapolis",
    "sg:classifiers":[
        {
            "category":"Health Services",
            "subcategory":"Doctor",
            "type":"Services"
        }
    ],
    "sg:phone":"+1 317 585 4441",
    "sg:postcode":"46250",
    "sg:province":"IN",
    "sg:tags":[
        "physician",
        "surgeon"
    ],
    "wof:name":"Signature Medical Resources",
    "wof:placetype":"venue"
},
  "geometry": {"coordinates":[-86.046176,39.885852],"type":"Point"}
}