{
  "type": "Feature",
  "properties": {
    "iso:country":"US",
    "sg:address":"905 S Commerce Dr",
    "sg:city":"Seymour",
    "sg:classifiers":[
        {
            "category":"Manufacturing",
            "subcategory":"Buildings",
            "type":"Manufacturing & Wholesale Goods"
        }
    ],
    "sg:phone":"+1 812 524 9895",
    "sg:postcode":"47274",
    "sg:province":"IN",
    "sg:tags":[
        "prefab"
    ],
    "wof:name":"Gateway Homes Of Seymour",
    "wof:placetype":"venue"
},
  "geometry": {"coordinates":[-85.842931,38.951228],"type":"Point"}
}