{
  "type": "Feature",
  "properties": {
    "addr:full":"4810 Coldwater Rd Fort Wayne IN 46825",
    "addr:housenumber":"4810",
    "addr:postcode":"46825",
    "addr:street":"Coldwater Rd",
    "iso:country":"US",
    "sg:address":"4810 Coldwater Rd",
    "sg:city":"Fort Wayne",
    "sg:classifiers":[
        {
            "category":"Restaurant",
            "type":"Food & Drink"
        }
    ],
    "sg:menulink":"http://www.allmenus.com/in/washington/163382-rallys/menu/",
    "sg:phone":"+1 260 483 4335",
    "sg:postcode":"46825",
    "sg:province":"IN",
    "sg:tags":[
        "sandwich",
        "dog",
        "burger",
        "hot",
        "wrap",
        "american"
    ],
    "wof:name":"Rally's",
    "wof:placetype":"venue"
},
  "geometry": {"coordinates":[-85.135465,41.122725],"type":"Point"}
}