{
  "type": "Feature",
  "properties": {
    "iso:country":"US",
    "sg:address":"955 Treelane Dr",
    "sg:city":"Newburgh",
    "sg:classifiers":[
        {
            "category":"Building & Trades",
            "subcategory":"Plumbing",
            "type":"Services"
        }
    ],
    "sg:phone":"+1 812 858 3503",
    "sg:postcode":"47630",
    "sg:province":"IN",
    "sg:tags":[
        "mechanical",
        "contractor"
    ],
    "wof:name":"Power Plant Ind",
    "wof:placetype":"venue"
},
  "geometry": {"coordinates":[-87.390771,37.949789],"type":"Point"}
}