{
  "type": "Feature",
  "properties": {
    "addr:full":"712 Green Blvd Aurora IN 47001",
    "addr:housenumber":"712",
    "addr:postcode":"47001",
    "addr:street":"Green Blvd",
    "iso:country":"US",
    "sg:address":"712 Green Blvd",
    "sg:city":"Aurora",
    "sg:classifiers":[
        {
            "category":"Home & Garden",
            "subcategory":"Building Materials",
            "type":"Retail Goods"
        }
    ],
    "sg:phone":"+1 812 926 0107",
    "sg:postcode":"47001",
    "sg:province":"IN",
    "sg:tags":[
        "glass",
        "window",
        "plate"
    ],
    "wof:name":"John Seeger Glass Co",
    "wof:placetype":"venue"
},
  "geometry": {"coordinates":[-84.89651000000001,39.063254],"type":"Point"}
}