{
  "type": "Feature",
  "properties": {
    "addr:full":"636 N Luett Ave Indianapolis IN 46222",
    "addr:housenumber":"636",
    "addr:postcode":"46222",
    "addr:street":"N Luett Ave",
    "iso:country":"US",
    "sg:address":"636 N Luett Ave",
    "sg:city":"Indianapolis",
    "sg:classifiers":[
        {
            "category":"Organizations",
            "subcategory":"Religious Organization",
            "type":"Services"
        }
    ],
    "sg:phone":"+1 317 631 4822",
    "sg:postcode":"46222",
    "sg:province":"IN",
    "sg:tags":[
        "church"
    ],
    "wof:name":"Folds Of Christ Church Inc",
    "wof:placetype":"venue"
},
  "geometry": {"coordinates":[-86.22420200000001,39.776124],"type":"Point"}
}