{
  "type": "Feature",
  "properties": {
    "iso:country":"US",
    "sg:address":"12166 Madrone Dr",
    "sg:city":"Indianapolis",
    "sg:classifiers":[
        {
            "category":"Professional",
            "subcategory":"Management & Consulting",
            "type":"Services"
        }
    ],
    "sg:phone":"+1 317 816 2176",
    "sg:postcode":"46236",
    "sg:province":"IN",
    "wof:name":"ADT Securities",
    "wof:placetype":"venue"
},
  "geometry": {"coordinates":[-85.950043,39.904012],"type":"Point"}
}