{
  "type": "Feature",
  "properties": {
    "iso:country":"US",
    "sg:address":"2031 S Weimer Rd",
    "sg:city":"Bloomington",
    "sg:classifiers":[
        {
            "category":"Farming",
            "subcategory":"Livestock Farm",
            "type":"Manufacturing & Wholesale Goods"
        }
    ],
    "sg:phone":"+1 812 334 8843",
    "sg:postcode":"47403",
    "sg:province":"IN",
    "sg:tags":[
        "beef",
        "feedlot",
        "cattle"
    ],
    "wof:name":"Harvey Sudbury",
    "wof:placetype":"venue"
},
  "geometry": {"coordinates":[-86.56211999999999,39.14298],"type":"Point"}
}