{
  "type": "Feature",
  "properties": {
    "iso:country":"US",
    "sg:address":"249 America Pl",
    "sg:city":"Jeffersonville",
    "sg:classifiers":[
        {
            "category":"Manufacturing",
            "subcategory":"Furniture",
            "type":"Manufacturing & Wholesale Goods"
        }
    ],
    "sg:phone":"+1 812 284 8400",
    "sg:postcode":"47130",
    "sg:province":"IN",
    "sg:tags":[
        "wood",
        "fixture",
        "store"
    ],
    "sg:website":"www.jcmoag.com",
    "wof:name":"J C Moag",
    "wof:placetype":"venue"
},
  "geometry": {"coordinates":[-85.7366,38.288378],"type":"Point"}
}