{
  "type": "Feature",
  "properties": {
    "iso:country":"US",
    "sg:address":"6517 E State Rd 164",
    "sg:city":"Celestine",
    "sg:classifiers":[
        {
            "category":"Wholesale",
            "subcategory":"Non-durable Goods",
            "type":"Manufacturing & Wholesale Goods"
        }
    ],
    "sg:phone":"+1 812 482 6051",
    "sg:postcode":"47521",
    "sg:province":"IN",
    "sg:tags":[
        "advertising"
    ],
    "wof:name":"Bohnert Advertising Inc",
    "wof:placetype":"venue"
},
  "geometry": {"coordinates":[-86.78834500000001,38.386985],"type":"Point"}
}