{
  "type": "Feature",
  "properties": {
    "iso:country":"US",
    "sg:address":"100 I St",
    "sg:city":"Laporte",
    "sg:classifiers":[
        {
            "category":"Personal",
            "subcategory":"Beauty Salon",
            "type":"Services"
        }
    ],
    "sg:phone":"+1 219 362 2464",
    "sg:postcode":"46350",
    "sg:province":"IN",
    "wof:name":"New Wave Hair Salon",
    "wof:placetype":"venue"
},
  "geometry": {"coordinates":[-86.728997,41.606571],"type":"Point"}
}