{
  "type": "Feature",
  "properties": {
    "iso:country":"US",
    "sg:address":"901 Loper Dr",
    "sg:city":"Shelbyville",
    "sg:classifiers":[
        {
            "category":"Education",
            "subcategory":"School",
            "type":"Public Place"
        }
    ],
    "sg:phone":"+1 317 398 9725",
    "sg:postcode":"46176",
    "sg:province":"IN",
    "wof:name":"William F Loper School",
    "wof:placetype":"venue"
},
  "geometry": {"coordinates":[-85.764879,39.511966],"type":"Point"}
}