{
  "type": "Feature",
  "properties": {
    "addr:full":"4160 Grape Rd Mishawaka IN 46545",
    "addr:housenumber":"4160",
    "addr:postcode":"46545",
    "addr:street":"Grape Rd",
    "iso:country":"US",
    "sg:address":"4160 Grape Rd",
    "sg:city":"Mishawaka",
    "sg:classifiers":[
        {
            "category":"Restaurant",
            "type":"Food & Drink"
        }
    ],
    "sg:menulink":"http://www.allmenus.com/in/georgetown/9860-don-pablos/menu/",
    "sg:phone":"+1 574 254 9395",
    "sg:postcode":"46545",
    "sg:province":"IN",
    "sg:tags":[
        "sandwich",
        "mexican",
        "salad",
        "soup",
        "american",
        "wrap",
        "tex-mex"
    ],
    "wof:name":"Don Pablo's",
    "wof:placetype":"venue"
},
  "geometry": {"coordinates":[-86.187399,41.699009],"type":"Point"}
}