{
  "type": "Feature",
  "properties": {
    "iso:country":"US",
    "sg:address":"7546 Chestnut Ave",
    "sg:city":"Hammond",
    "sg:classifiers":[
        {
            "category":"Farming",
            "subcategory":"Farm & Veterinary Services",
            "type":"Manufacturing & Wholesale Goods"
        }
    ],
    "sg:phone":"+1 219 845 6222",
    "sg:postcode":"46324",
    "sg:province":"IN",
    "sg:tags":[
        "plow",
        "snow"
    ],
    "wof:name":"Wanna Get Plowed Inc",
    "wof:placetype":"venue"
},
  "geometry": {"coordinates":[-87.495432,41.575299],"type":"Point"}
}