{
  "type": "Feature",
  "properties": {
    "addr:full":"500 Broadway Chesterton IN 46304",
    "addr:housenumber":"500",
    "addr:postcode":"46304",
    "addr:street":"Broadway",
    "iso:country":"US",
    "sg:address":"500 Broadway",
    "sg:city":"Chesterton",
    "sg:classifiers":[
        {
            "category":"Wholesale",
            "subcategory":"Medical Equipment & Supplies",
            "type":"Manufacturing & Wholesale Goods"
        }
    ],
    "sg:phone":"+1 219 395 1026",
    "sg:postcode":"46304",
    "sg:province":"IN",
    "sg:tags":[
        "physician",
        "surgeon"
    ],
    "wof:name":"E & S Medical Supply",
    "wof:placetype":"venue"
},
  "geometry": {"coordinates":[-87.05909800000001,41.611368],"type":"Point"}
}