{
  "type": "Feature",
  "properties": {
    "iso:country":"US",
    "sg:address":"432 Wall St",
    "sg:city":"Jeffersonville",
    "sg:classifiers":[
        {
            "category":"Health Services",
            "subcategory":"Optometrist",
            "type":"Services"
        }
    ],
    "sg:phone":"+1 812 283 7492",
    "sg:postcode":"47130",
    "sg:province":"IN",
    "wof:name":"Troy Coker OD",
    "wof:placetype":"venue"
},
  "geometry": {"coordinates":[-85.740269,38.273966],"type":"Point"}
}