{
  "type": "Feature",
  "properties": {
    "iso:country":"US",
    "sg:address":"2701 Beech St",
    "sg:city":"Valparaiso",
    "sg:classifiers":[
        {
            "category":"Wholesale",
            "subcategory":"Painting Supplies",
            "type":"Manufacturing & Wholesale Goods"
        }
    ],
    "sg:phone":"+1 219 531 0929",
    "sg:postcode":"46383",
    "sg:province":"IN",
    "sg:tags":[
        "equipment",
        "painter"
    ],
    "wof:name":"Permanent Restoration Products",
    "wof:placetype":"venue"
},
  "geometry": {"coordinates":[-87.03187,41.474003],"type":"Point"}
}