{
  "type": "Feature",
  "properties": {
    "iso:country":"US",
    "sg:address":"1929 E Morgan Ave",
    "sg:city":"Evansville",
    "sg:classifiers":[
        {
            "category":"Autos & Motor Vehicles",
            "subcategory":"Automobile Sales",
            "type":"Retail Goods"
        }
    ],
    "sg:phone":"+1 812 471 0103",
    "sg:postcode":"47711",
    "sg:province":"IN",
    "sg:tags":[
        "car",
        "dealer"
    ],
    "wof:name":"Calcars Inc",
    "wof:placetype":"venue"
},
  "geometry": {"coordinates":[-87.52942299999999,37.991624],"type":"Point"}
}