{
  "type": "Feature",
  "properties": {
    "addr:full":"945 E Main St Danville IN 46122",
    "addr:housenumber":"945",
    "addr:postcode":"46122",
    "addr:street":"E Main St",
    "iso:country":"US",
    "sg:address":"945 E Main St",
    "sg:city":"Danville",
    "sg:classifiers":[
        {
            "category":"Government",
            "subcategory":"Office",
            "type":"Public Place"
        }
    ],
    "sg:phone":"+1 317 745 9250",
    "sg:postcode":"46122",
    "sg:province":"IN",
    "wof:name":"Hendricks Cnty Animal Control",
    "wof:placetype":"venue"
},
  "geometry": {"coordinates":[-86.511155,39.759485],"type":"Point"}
}