{
  "type": "Feature",
  "properties": {
    "iso:country":"US",
    "sg:address":"3325 Middlebury St",
    "sg:city":"Elkhart",
    "sg:classifiers":[
        {
            "category":"Manufacturing",
            "subcategory":"Retail Goods",
            "type":"Manufacturing & Wholesale Goods"
        }
    ],
    "sg:phone":"+1 574 295 3761",
    "sg:postcode":"46516",
    "sg:province":"IN",
    "sg:tags":[
        "manufacturer"
    ],
    "sg:website":"www.wagnerconst.com",
    "wof:name":"Butler Manufacturing Co",
    "wof:placetype":"venue"
},
  "geometry": {"coordinates":[-85.908778,41.68166],"type":"Point"}
}