{
  "type": "Feature",
  "properties": {
    "iso:country":"US",
    "sg:address":"3301 W Mount Pleasant Blvd",
    "sg:city":"Muncie",
    "sg:classifiers":[
        {
            "category":"Manufacturing",
            "subcategory":"Tools & Machinery",
            "type":"Manufacturing & Wholesale Goods"
        }
    ],
    "sg:phone":"+1 765 288 8098",
    "sg:postcode":"47302",
    "sg:province":"IN",
    "sg:tags":[
        "machine",
        "shop"
    ],
    "wof:name":"Henman Engineering & Machine",
    "wof:placetype":"venue"
},
  "geometry": {"coordinates":[-85.422624,40.158144],"type":"Point"}
}