{
  "type": "Feature",
  "properties": {
    "addr:full":"806 W Ohio St Rockville IN 47872",
    "addr:housenumber":"806",
    "addr:postcode":"47872",
    "addr:street":"W Ohio St",
    "iso:country":"US",
    "sg:address":"806 W Ohio St",
    "sg:city":"Rockville",
    "sg:classifiers":[
        {
            "category":"Shopping",
            "subcategory":"Pharmacy",
            "type":"Retail Goods"
        }
    ],
    "sg:phone":"+1 765 569 5314",
    "sg:postcode":"47872",
    "sg:province":"IN",
    "wof:name":"CVS Pharmacy",
    "wof:placetype":"venue"
},
  "geometry": {"coordinates":[-87.239262,39.76332],"type":"Point"}
}