{
  "type": "Feature",
  "properties": {
    "iso:country":"US",
    "sg:address":"1299 W Southport Rd",
    "sg:city":"Indianapolis",
    "sg:classifiers":[
        {
            "category":"Shopping",
            "subcategory":"Pharmacy",
            "type":"Retail Goods"
        }
    ],
    "sg:phone":"+1 317 859 5881",
    "sg:postcode":"46217",
    "sg:province":"IN",
    "wof:name":"CVS Pharmacy",
    "wof:placetype":"venue"
},
  "geometry": {"coordinates":[-86.18159300000001,39.663811],"type":"Point"}
}