{
  "type": "Feature",
  "properties": {
    "iso:country":"US",
    "sg:address":"505 W Main St",
    "sg:city":"Gas City",
    "sg:classifiers":[
        {
            "category":"Restaurant",
            "type":"Food & Drink"
        }
    ],
    "sg:phone":"+1 765 677 0699",
    "sg:postcode":"46933",
    "sg:province":"IN",
    "wof:name":"Trejos Gyros Inc",
    "wof:placetype":"venue"
},
  "geometry": {"coordinates":[-85.62261700000001,40.487755],"type":"Point"}
}