{
  "type": "Feature",
  "properties": {
    "iso:country":"US",
    "sg:address":"8259 Zionsville Rd",
    "sg:city":"Indianapolis",
    "sg:classifiers":[
        {
            "category":"Wholesale",
            "subcategory":"Office Equipment",
            "type":"Manufacturing & Wholesale Goods"
        }
    ],
    "sg:phone":"+1 317 876 3918",
    "sg:postcode":"46268",
    "sg:province":"IN",
    "sg:tags":[
        "vault",
        "safe"
    ],
    "wof:name":"Indianapolis Vault",
    "wof:placetype":"venue"
},
  "geometry": {"coordinates":[-86.259794,39.903575],"type":"Point"}
}