{
  "type": "Feature",
  "properties": {
    "iso:country":"US",
    "sg:address":"210 Marciel Dr",
    "sg:city":"Fort Wayne",
    "sg:classifiers":[
        {
            "category":"Shopping",
            "type":"Retail Goods"
        }
    ],
    "sg:phone":"+1 260 483 1161",
    "sg:postcode":"46825",
    "sg:province":"IN",
    "sg:tags":[
        "trophy",
        "medal",
        "award"
    ],
    "wof:name":"Classic Trophy Co",
    "wof:placetype":"venue"
},
  "geometry": {"coordinates":[-85.141847,41.123138],"type":"Point"}
}