{
  "type": "Feature",
  "properties": {
    "iso:country":"US",
    "sg:address":"11771 State Rd 160",
    "sg:city":"Salem",
    "sg:classifiers":[
        {
            "category":"Freight",
            "type":"Transportation"
        }
    ],
    "sg:phone":"+1 812 967 1451",
    "sg:postcode":"47167",
    "sg:province":"IN",
    "sg:tags":[
        "operator",
        "local",
        "trucking"
    ],
    "wof:name":"J/T Trucking Inc",
    "wof:placetype":"venue"
},
  "geometry": {"coordinates":[-85.890389,38.57297],"type":"Point"}
}