{
  "type": "Feature",
  "properties": {
    "iso:country":"US",
    "sg:address":"25 The Meadows",
    "sg:city":"Terre Haute",
    "sg:classifiers":[
        {
            "category":"Shopping",
            "type":"Retail Goods"
        }
    ],
    "sg:phone":"+1 812 234 9332",
    "sg:postcode":"47803",
    "sg:province":"IN",
    "sg:tags":[
        "hearing",
        "equipment",
        "supply",
        "impaired"
    ],
    "wof:name":"Sonotone Hearing Aid Ctr",
    "wof:placetype":"venue"
},
  "geometry": {"coordinates":[-87.377291,39.464198],"type":"Point"}
}