{
  "type": "Feature",
  "properties": {
    "addr:full":"14042 Oakridge Rd Carmel IN 46032",
    "addr:housenumber":"14042",
    "addr:postcode":"46032",
    "addr:street":"Oakridge Rd",
    "iso:country":"US",
    "sg:address":"14042 Oakridge Rd",
    "sg:city":"Carmel",
    "sg:classifiers":[
        {
            "category":"Professional",
            "subcategory":"Lawyer & Legal Services",
            "type":"Services"
        }
    ],
    "sg:phone":"+1 317 815 0200",
    "sg:postcode":"46032",
    "sg:province":"IN",
    "wof:name":"Ryan David J",
    "wof:placetype":"venue"
},
  "geometry": {"coordinates":[-86.146028,39.991858],"type":"Point"}
}