{
  "type": "Feature",
  "properties": {
    "addr:full":"1520 Steam Engine Rd SW Corydon IN 47112",
    "addr:housenumber":"1520",
    "addr:postcode":"47112",
    "addr:street":"Steam Engine Rd Sw",
    "iso:country":"US",
    "sg:address":"1520 Steam Engine Rd SW",
    "sg:city":"Corydon",
    "sg:phone":"+1 812 738 3741",
    "sg:postcode":"47112",
    "sg:province":"IN",
    "sg:tags":[
        "farm",
        "corn",
        "soybean"
    ],
    "wof:name":"Mathes John",
    "wof:placetype":"venue"
},
  "geometry": {"coordinates":[-86.165024,38.1771],"type":"Point"}
}