{
  "type": "Feature",
  "properties": {
    "addr:full":"8300 N State Rd 37 Bloomington IN 47404",
    "addr:housenumber":"8300;37",
    "addr:postcode":"47404",
    "addr:street":"N State Rd",
    "iso:country":"US",
    "sg:address":"8300 N State Rd 37",
    "sg:city":"Bloomington",
    "sg:classifiers":[
        {
            "category":"Building & Trades",
            "subcategory":"Construction",
            "type":"Services"
        }
    ],
    "sg:phone":"+1 812 876 3162",
    "sg:postcode":"47404",
    "sg:province":"IN",
    "sg:tags":[
        "designer",
        "dealer",
        "pool",
        "swimming"
    ],
    "sg:website":"www.parkerpoolsandspas.com",
    "wof:name":"Parker Pools",
    "wof:placetype":"venue"
},
  "geometry": {"coordinates":[-86.51390499999999,39.330629],"type":"Point"}
}