{
  "type": "Feature",
  "properties": {
    "addr:full":"8696 E 116th St Fishers IN 46038",
    "addr:housenumber":"8696",
    "addr:postcode":"46038",
    "addr:street":"E 116Th St",
    "iso:country":"US",
    "sg:address":"8696 E 116th St",
    "sg:city":"Fishers",
    "sg:classifiers":[
        {
            "category":"Real Estate",
            "subcategory":"Real Estate Agent",
            "type":"Services"
        },
        {
            "category":"Farming",
            "subcategory":"Fish & Marine Products",
            "type":"Manufacturing & Wholesale Goods"
        }
    ],
    "sg:phone":"+1 317 576 9520",
    "sg:postcode":"46038",
    "sg:province":"IN",
    "sg:tags":[
        "preserves",
        "leasing",
        "fishing",
        "hunting"
    ],
    "wof:name":"Base Camp Leasing LLC",
    "wof:placetype":"venue"
},
  "geometry": {"coordinates":[-86.016436,39.956768],"type":"Point"}
}