{
  "type": "Feature",
  "properties": {
    "iso:country":"US",
    "sg:address":"4416 S Madison St",
    "sg:city":"Muncie",
    "sg:classifiers":[
        {
            "category":"Autos & Motor Vehicles",
            "subcategory":"Auto Supplies",
            "type":"Retail Goods"
        }
    ],
    "sg:phone":"+1 765 284 9776",
    "sg:postcode":"47302",
    "sg:province":"IN",
    "sg:tags":[
        "automobile",
        "parts"
    ],
    "wof:name":"G W Pierce Auto Parts Inc",
    "wof:placetype":"venue"
},
  "geometry": {"coordinates":[-85.385615,40.152899],"type":"Point"}
}