{
  "type": "Feature",
  "properties": {
    "iso:country":"US",
    "sg:address":"8669 Bash St",
    "sg:city":"Indianapolis",
    "sg:classifiers":[
        {
            "category":"Real Estate",
            "subcategory":"Real Estate Agent",
            "type":"Services"
        }
    ],
    "sg:phone":"+1 317 577 5936",
    "sg:postcode":"46256",
    "sg:province":"IN",
    "wof:name":"B & B Properties",
    "wof:placetype":"venue"
},
  "geometry": {"coordinates":[-86.043167,39.913768],"type":"Point"}
}