{
  "type": "Feature",
  "properties": {
    "addr:full":"8125 W 10th St Indianapolis IN 46214",
    "addr:housenumber":"8125",
    "addr:postcode":"46214",
    "addr:street":"W 10Th St",
    "iso:country":"US",
    "sg:address":"8125 W 10th St",
    "sg:city":"Indianapolis",
    "sg:classifiers":[
        {
            "category":"Retail",
            "subcategory":"Auto Rental",
            "type":"Services"
        },
        {
            "category":"Building & Trades",
            "subcategory":"Construction",
            "type":"Services"
        },
        {
            "category":"Professional",
            "subcategory":"Business Services",
            "type":"Services"
        },
        {
            "category":"Retail",
            "subcategory":"Storage",
            "type":"Services"
        },
        {
            "category":"Manufacturing",
            "subcategory":"Buildings",
            "type":"Manufacturing & Wholesale Goods"
        },
        {
            "category":"Building & Trades",
            "subcategory":"Equipment Rental",
            "type":"Services"
        }
    ],
    "sg:phone":"+1 317 209 0531",
    "sg:postcode":"46214",
    "sg:province":"IN",
    "sg:tags":[
        "renting",
        "leasing",
        "modular",
        "mobile",
        "household",
        "commercial",
        "prefabricated",
        "buildings-pre-cut",
        "buildings-portable",
        "trailer",
        "unit",
        "contractors'"
    ],
    "sg:website":"http://www.willscot.com",
    "wof:name":"Williams Scotsman Indianapolis",
    "wof:placetype":"venue"
},
  "geometry": {"coordinates":[-86.30302,39.779012],"type":"Point"}
}