{
  "type": "Feature",
  "properties": {
    "iso:country":"US",
    "sg:address":"1226 N Illinois St",
    "sg:city":"Indianapolis",
    "sg:classifiers":[
        {
            "category":"Professional",
            "type":"Services"
        }
    ],
    "sg:phone":"+1 317 636 2804",
    "sg:postcode":"46202",
    "sg:province":"IN",
    "sg:tags":[
        "establishment"
    ],
    "wof:name":"Sharon's Place",
    "wof:placetype":"venue"
},
  "geometry": {"coordinates":[-86.159497,39.783485],"type":"Point"}
}