{
  "type": "Feature",
  "properties": {
    "iso:country":"US",
    "sg:address":"10830 Ireland Rd",
    "sg:city":"Osceola",
    "sg:classifiers":[
        {
            "category":"Insurance",
            "subcategory":"Insurance Agent",
            "type":"Services"
        }
    ],
    "sg:phone":"+1 574 674 6474",
    "sg:postcode":"46561",
    "sg:province":"IN",
    "wof:name":"Charles Clarke & Assoc",
    "wof:placetype":"venue"
},
  "geometry": {"coordinates":[-86.07905599999999,41.630135],"type":"Point"}
}