{
  "type": "Feature",
  "properties": {
    "iso:country":"US",
    "sg:address":"9495 W State Rd 120",
    "sg:city":"Orland",
    "sg:classifiers":[
        {
            "category":"Cinema",
            "subcategory":"Movie Rental",
            "type":"Entertainment"
        }
    ],
    "sg:phone":"+1 260 829 6744",
    "sg:postcode":"46776",
    "sg:province":"IN",
    "sg:tags":[
        "leasing",
        "video",
        "disc",
        "tape"
    ],
    "wof:name":"Orland Video & Gifts",
    "wof:placetype":"venue"
},
  "geometry": {"coordinates":[-85.171189,41.730573],"type":"Point"}
}