{
  "type": "Feature",
  "properties": {
    "addr:full":"252 W US Hwy 6 Valparaiso IN 46385",
    "addr:housenumber":"252",
    "addr:postcode":"46385",
    "addr:street":"W Us Hwy 6",
    "iso:country":"US",
    "sg:address":"252 W US Hwy 6",
    "sg:city":"Valparaiso",
    "sg:classifiers":[
        {
            "category":"Manufacturing",
            "subcategory":"Tools & Machinery",
            "type":"Manufacturing & Wholesale Goods"
        }
    ],
    "sg:phone":"+1 219 929 5360",
    "sg:postcode":"46385",
    "sg:province":"IN",
    "sg:tags":[
        "equipment",
        "sewer",
        "cleaning",
        "supply"
    ],
    "wof:name":"Ground Improvement Svc",
    "wof:placetype":"venue"
},
  "geometry": {"coordinates":[-87.115257,41.550184],"type":"Point"}
}