{
  "type": "Feature",
  "properties": {
    "iso:country":"US",
    "sg:address":"3292 E 350 S",
    "sg:city":"Monroe",
    "sg:classifiers":[
        {
            "category":"Real Estate",
            "subcategory":"Real Estate Operator",
            "type":"Services"
        }
    ],
    "sg:phone":"+1 260 589 3367",
    "sg:postcode":"46772",
    "sg:province":"IN",
    "sg:tags":[
        "property",
        "lessor"
    ],
    "wof:name":"John Sipe Trucking",
    "wof:placetype":"venue"
},
  "geometry": {"coordinates":[-84.878832,40.695054],"type":"Point"}
}