{
  "type": "Feature",
  "properties": {
    "iso:country":"US",
    "sg:address":"9 W Main St",
    "sg:city":"Poseyville",
    "sg:classifiers":[
        {
            "category":"Personal",
            "subcategory":"Beauty Salon",
            "type":"Services"
        }
    ],
    "sg:phone":"+1 812 874 2222",
    "sg:postcode":"47633",
    "sg:province":"IN",
    "wof:name":"Uptown Salon",
    "wof:placetype":"venue"
},
  "geometry": {"coordinates":[-87.783574,38.169793],"type":"Point"}
}