{
  "type": "Feature",
  "properties": {
    "iso:country":"US",
    "sg:address":"7463 Avalon Trail Rd",
    "sg:city":"Indianapolis",
    "sg:classifiers":[
        {
            "category":"Retail",
            "subcategory":"Portrait Studio",
            "type":"Services"
        }
    ],
    "sg:phone":"+1 317 842 0685",
    "sg:postcode":"46250",
    "sg:province":"IN",
    "sg:tags":[
        "photographer"
    ],
    "sg:website":"www.jerrygoldbergphotography.com",
    "wof:name":"Jerry Goldberg Photography",
    "wof:placetype":"venue"
},
  "geometry": {"coordinates":[-86.049854,39.886868],"type":"Point"}
}