{
  "type": "Feature",
  "properties": {
    "addr:full":"6745 Gray Rd Indianapolis IN 46237",
    "addr:housenumber":"6745",
    "addr:postcode":"46237",
    "addr:street":"Gray Rd",
    "iso:country":"US",
    "sg:address":"6745 Gray Rd",
    "sg:city":"Indianapolis",
    "sg:classifiers":[
        {
            "category":"Health Services",
            "subcategory":"Doctor",
            "type":"Services"
        }
    ],
    "sg:phone":"+1 317 786 1277",
    "sg:postcode":"46237",
    "sg:province":"IN",
    "sg:tags":[
        "dentist"
    ],
    "wof:name":"Steve Douglas DDS",
    "wof:placetype":"venue"
},
  "geometry": {"coordinates":[-86.096687,39.669345],"type":"Point"}
}