{
  "type": "Feature",
  "properties": {
    "iso:country":"US",
    "sg:address":"3801 W Morris St",
    "sg:city":"Indianapolis",
    "sg:classifiers":[
        {
            "category":"Taxi",
            "type":"Transportation"
        }
    ],
    "sg:phone":"+1 317 247 6233",
    "sg:postcode":"46241",
    "sg:province":"IN",
    "sg:tags":[
        "taxicab"
    ],
    "wof:name":"Greater Indianapolis Trnsprtn",
    "wof:placetype":"venue"
},
  "geometry": {"coordinates":[-86.22666,39.74988],"type":"Point"}
}