{
  "type": "Feature",
  "properties": {
    "iso:country":"US",
    "sg:address":"3033 W 37th Ave",
    "sg:city":"Hobart",
    "sg:classifiers":[
        {
            "category":"Retail",
            "subcategory":"Repair Shop",
            "type":"Services"
        }
    ],
    "sg:phone":"+1 219 947 4594",
    "sg:postcode":"46342",
    "sg:province":"IN",
    "sg:tags":[
        "lock",
        "locksmith"
    ],
    "wof:name":"Keyed Rite Inc",
    "wof:placetype":"venue"
},
  "geometry": {"coordinates":[-87.292324,41.55098],"type":"Point"}
}