{
  "type": "Feature",
  "properties": {
    "iso:country":"US",
    "sg:address":"8330 Naab Rd",
    "sg:city":"Indianapolis",
    "sg:classifiers":[
        {
            "category":"Professional",
            "type":"Services"
        }
    ],
    "sg:phone":"+1 317 824 0017",
    "sg:postcode":"46260",
    "sg:province":"IN",
    "sg:tags":[
        "establishment"
    ],
    "wof:name":"Myers & Cleary",
    "wof:placetype":"venue"
},
  "geometry": {"coordinates":[-86.198369,39.910119],"type":"Point"}
}