{
  "type": "Feature",
  "properties": {
    "addr:full":"5714 Hollopeter Rd Leo IN 46765",
    "addr:housenumber":"5714",
    "addr:postcode":"46765",
    "addr:street":"Hollopeter Rd Leo",
    "iso:country":"US",
    "sg:address":"5714 Hollopeter Rd",
    "sg:city":"Leo",
    "sg:classifiers":[
        {
            "category":"Shopping",
            "subcategory":"Gifts & Souvenirs",
            "type":"Retail Goods"
        }
    ],
    "sg:phone":"+1 260 627 5240",
    "sg:postcode":"46765",
    "sg:province":"IN",
    "wof:name":"Promotional Gifts & More",
    "wof:placetype":"venue"
},
  "geometry": {"coordinates":[-85.060351,41.243973],"type":"Point"}
}