{
  "type": "Feature",
  "properties": {
    "iso:country":"US",
    "sg:address":"3806 Southland Ave",
    "sg:city":"Kokomo",
    "sg:classifiers":[
        {
            "category":"Education",
            "subcategory":"Special Training",
            "type":"Public Place"
        }
    ],
    "sg:phone":"+1 765 453 8880",
    "sg:postcode":"46902",
    "sg:province":"IN",
    "sg:tags":[
        "tutoring"
    ],
    "wof:name":"Learning Studio",
    "wof:placetype":"venue"
},
  "geometry": {"coordinates":[-86.1313,40.443455],"type":"Point"}
}