{
  "type": "Feature",
  "properties": {
    "iso:country":"US",
    "sg:address":"2510 N Cullen Ave",
    "sg:city":"Evansville",
    "sg:classifiers":[
        {
            "category":"Autos & Motor Vehicles",
            "subcategory":"Auto Supplies",
            "type":"Retail Goods"
        }
    ],
    "sg:phone":"+1 812 473 1104",
    "sg:postcode":"47715",
    "sg:province":"IN",
    "sg:tags":[
        "filter",
        "gas"
    ],
    "wof:name":"Mid-America Filter & Equipment",
    "wof:placetype":"venue"
},
  "geometry": {"coordinates":[-87.486409,38.000319],"type":"Point"}
}