{
  "type": "Feature",
  "properties": {
    "iso:country":"US",
    "sg:address":"2861 S Yonkers Ct",
    "sg:city":"Bloomington",
    "sg:classifiers":[
        {
            "category":"Professional",
            "subcategory":"Art Services",
            "type":"Services"
        }
    ],
    "sg:phone":"+1 812 334 3408",
    "sg:postcode":"47403",
    "sg:province":"IN",
    "sg:tags":[
        "commercial",
        "design"
    ],
    "wof:name":"Tm Tm Marketing",
    "wof:placetype":"venue"
},
  "geometry": {"coordinates":[-86.574512,39.135729],"type":"Point"}
}