{
  "type": "Feature",
  "properties": {
    "iso:country":"US",
    "sg:address":"107 E Washington St",
    "sg:city":"St Paul",
    "sg:classifiers":[
        {
            "category":"Food & Beverages",
            "subcategory":"Liquor & Beverages",
            "type":"Retail Goods"
        }
    ],
    "sg:phone":"+1 765 525 6347",
    "sg:postcode":"47272",
    "sg:province":"IN",
    "wof:name":"St Paul Liquor Shoppe Inc",
    "wof:placetype":"venue"
},
  "geometry": {"coordinates":[-85.629349,39.427783],"type":"Point"}
}