{
  "type": "Feature",
  "properties": {
    "iso:country":"US",
    "sg:address":"3610 Eagle Emblem Ct",
    "sg:city":"Greenwood",
    "sg:classifiers":[
        {
            "category":"Restaurant",
            "type":"Food & Drink"
        }
    ],
    "sg:phone":"+1 317 887 0713",
    "sg:postcode":"46143",
    "sg:province":"IN",
    "wof:name":"Mc Donald's",
    "wof:placetype":"venue"
},
  "geometry": {"coordinates":[-86.169201,39.598037],"type":"Point"}
}