{
  "type": "Feature",
  "properties": {
    "addr:full":"46 Putnam St Greencastle IN 46128",
    "addr:housenumber":"46",
    "addr:postcode":"46128",
    "addr:street":"Putnam St",
    "iso:country":"US",
    "sg:address":"46 Putnam St",
    "sg:city":"Greencastle",
    "sg:classifiers":[
        {
            "category":"Banks & Credit Unions",
            "subcategory":"Bank",
            "type":"Services"
        }
    ],
    "sg:phone":"+1 765 653 8778",
    "sg:postcode":"46128",
    "sg:province":"IN",
    "wof:name":"National City Bank",
    "wof:placetype":"venue"
},
  "geometry": {"coordinates":[-86.755217,39.670522],"type":"Point"}
}