{
  "type": "Feature",
  "properties": {
    "iso:country":"US",
    "sg:address":"203 W Washington St",
    "sg:city":"Bluffton",
    "sg:classifiers":[
        {
            "category":"Personal",
            "subcategory":"Beauty Salon",
            "type":"Services"
        }
    ],
    "sg:phone":"+1 260 824 0766",
    "sg:postcode":"46714",
    "sg:province":"IN",
    "wof:name":"Shear Style",
    "wof:placetype":"venue"
},
  "geometry": {"coordinates":[-85.17401099999999,40.738792],"type":"Point"}
}