{
  "type": "Feature",
  "properties": {
    "addr:full":"312 E Commercial Ave Lowell IN 46356",
    "addr:housenumber":"312",
    "addr:postcode":"46356",
    "addr:street":"E Commercial Ave",
    "iso:country":"US",
    "sg:address":"312 E Commercial Ave",
    "sg:city":"Lowell",
    "sg:classifiers":[
        {
            "category":"Restaurant",
            "type":"Food & Drink"
        }
    ],
    "sg:phone":"+1 219 696 7784",
    "sg:postcode":"46356",
    "sg:province":"IN",
    "wof:name":"Stork's Nest Restaurant & Lounge",
    "wof:placetype":"venue"
},
  "geometry": {"coordinates":[-87.423897,41.290401],"type":"Point"}
}