{
  "type": "Feature",
  "properties": {
    "iso:country":"US",
    "sg:address":"2895 Circle Dr",
    "sg:city":"Gary",
    "sg:classifiers":[
        {
            "category":"Organizations",
            "subcategory":"Religious Organization",
            "type":"Services"
        }
    ],
    "sg:phone":"+1 219 949 3549",
    "sg:postcode":"46404",
    "sg:province":"IN",
    "sg:tags":[
        "churches-baptist-missionary"
    ],
    "wof:name":"Pleasant Valley M B Church",
    "wof:placetype":"venue"
},
  "geometry": {"coordinates":[-87.38558999999999,41.566123],"type":"Point"}
}