{
  "type": "Feature",
  "properties": {
    "addr:full":"1404 Prospect St Indianapolis IN 46203",
    "addr:housenumber":"1404",
    "addr:postcode":"46203",
    "addr:street":"Prospect St",
    "iso:country":"US",
    "sg:address":"1404 Prospect St",
    "sg:city":"Indianapolis",
    "sg:classifiers":[
        {
            "category":"Restaurant",
            "type":"Food & Drink"
        }
    ],
    "sg:phone":"+1 317 637 4671",
    "sg:postcode":"46203",
    "sg:province":"IN",
    "wof:name":"Church's Chicken",
    "wof:placetype":"venue"
},
  "geometry": {"coordinates":[-86.135808,39.752365],"type":"Point"}
}