{
  "type": "Feature",
  "properties": {
    "addr:full":"106 N 12th St Clinton IN 47842",
    "addr:housenumber":"106",
    "addr:postcode":"47842",
    "addr:street":"N 12Th St",
    "iso:country":"US",
    "sg:address":"106 N 12th St",
    "sg:city":"Clinton",
    "sg:classifiers":[
        {
            "category":"Freight",
            "type":"Transportation"
        }
    ],
    "sg:phone":"+1 765 832 7268",
    "sg:postcode":"47842",
    "sg:province":"IN",
    "sg:tags":[
        "hauling",
        "trucking"
    ],
    "wof:name":"D L Bogetto & Sons Cartage Inc",
    "wof:placetype":"venue"
},
  "geometry": {"coordinates":[-87.41252799999999,39.661441],"type":"Point"}
}