{
  "type": "Feature",
  "properties": {
    "addr:full":"2426 E Pierceton Rd Winona Lake IN 46590",
    "addr:housenumber":"2426",
    "addr:postcode":"46590",
    "addr:street":"E Pierceton Rd",
    "iso:country":"US",
    "sg:address":"2426 E Pierceton Rd",
    "sg:city":"Winona Lake",
    "sg:classifiers":[
        {
            "category":"Organizations",
            "subcategory":"Non-profit Organization",
            "type":"Services"
        }
    ],
    "sg:phone":"+1 574 267 7988",
    "sg:postcode":"46590",
    "sg:province":"IN",
    "sg:website":"www.upi.org",
    "wof:name":"Unlimited Potential Inc",
    "wof:placetype":"venue"
},
  "geometry": {"coordinates":[-85.79400800000001,41.211916],"type":"Point"}
}