{
  "type": "Feature",
  "properties": {
    "iso:country":"US",
    "sg:address":"640 Patrick Pl",
    "sg:city":"Brownsburg",
    "sg:classifiers":[
        {
            "category":"Real Estate",
            "subcategory":"Real Estate Agent",
            "type":"Services"
        }
    ],
    "sg:phone":"+1 317 852 5700",
    "sg:postcode":"46112",
    "sg:province":"IN",
    "wof:name":"Sell It Yourself Realty Svc",
    "wof:placetype":"venue"
},
  "geometry": {"coordinates":[-86.383526,39.853756],"type":"Point"}
}