{
  "type": "Feature",
  "properties": {
    "addr:full":"28391 Glenview Dr Elkhart IN 46514",
    "addr:housenumber":"28391",
    "addr:postcode":"46514",
    "addr:street":"Glenview Dr",
    "iso:country":"US",
    "sg:address":"28391 Glenview Dr",
    "sg:city":"Elkhart",
    "sg:classifiers":[
        {
            "category":"Professional",
            "type":"Services"
        }
    ],
    "sg:phone":"+1 574 266 5770",
    "sg:postcode":"46514",
    "sg:province":"IN",
    "sg:tags":[
        "establishment"
    ],
    "wof:name":"Kibbechem Inc Plant 2",
    "wof:placetype":"venue"
},
  "geometry": {"coordinates":[-86.01254900000001,41.725729],"type":"Point"}
}