{
  "type": "Feature",
  "properties": {
    "iso:country":"US",
    "sg:address":"1610 Winchester St",
    "sg:city":"Decatur",
    "sg:classifiers":[
        {
            "category":"Restaurant",
            "type":"Food & Drink"
        }
    ],
    "sg:phone":"+1 260 724 8868",
    "sg:postcode":"46733",
    "sg:province":"IN",
    "sg:tags":[
        "pizza"
    ],
    "wof:name":"Tony's Pizza Svc",
    "wof:placetype":"venue"
},
  "geometry": {"coordinates":[-84.931351,40.814225],"type":"Point"}
}