{
  "type": "Feature",
  "properties": {
    "iso:country":"US",
    "sg:address":"616 W Lincoln Ave",
    "sg:city":"Goshen",
    "sg:classifiers":[
        {
            "category":"Government",
            "subcategory":"Office",
            "type":"Public Place"
        }
    ],
    "sg:phone":"+1 574 533 4763",
    "sg:postcode":"46526",
    "sg:province":"IN",
    "sg:tags":[
        "state",
        "program"
    ],
    "wof:name":"Auto License Branch",
    "wof:placetype":"venue"
},
  "geometry": {"coordinates":[-85.844956,41.586314],"type":"Point"}
}