{
  "type": "Feature",
  "properties": {
    "iso:country":"US",
    "sg:address":"400 E Walnut St",
    "sg:city":"Kokomo",
    "sg:classifiers":[
        {
            "category":"Real Estate",
            "subcategory":"Real Estate Agent",
            "type":"Services"
        }
    ],
    "sg:phone":"+1 765 454 6925",
    "sg:postcode":"46901",
    "sg:province":"IN",
    "sg:tags":[
        "authorities",
        "housing"
    ],
    "wof:name":"Kokomo Housing Authority",
    "wof:placetype":"venue"
},
  "geometry": {"coordinates":[-86.125993,40.487457],"type":"Point"}
}