{
  "type": "Feature",
  "properties": {
    "iso:country":"US",
    "sg:address":"828 Spring St",
    "sg:city":"Jeffersonville",
    "sg:classifiers":[
        {
            "category":"Retail",
            "subcategory":"Auto Repair",
            "type":"Services"
        }
    ],
    "sg:phone":"+1 812 280 1966",
    "sg:postcode":"47130",
    "sg:province":"IN",
    "sg:tags":[
        "body",
        "automobile",
        "painting"
    ],
    "wof:name":"Great Lakes Auto Svc & Body",
    "wof:placetype":"venue"
},
  "geometry": {"coordinates":[-85.744821,38.277669],"type":"Point"}
}