{
  "type": "Feature",
  "properties": {
    "iso:country":"US",
    "sg:address":"51700 Bluffside Ct",
    "sg:city":"Granger",
    "sg:classifiers":[
        {
            "category":"Professional",
            "type":"Services"
        }
    ],
    "sg:phone":"+1 574 243 8600",
    "sg:postcode":"46530",
    "sg:province":"IN",
    "sg:tags":[
        "establishment"
    ],
    "wof:name":"Keynote Developement Corp",
    "wof:placetype":"venue"
},
  "geometry": {"coordinates":[-86.173406,41.744399],"type":"Point"}
}