{
  "type": "Feature",
  "properties": {
    "iso:country":"US",
    "sg:address":"6310 E State Blvd",
    "sg:city":"Fort Wayne",
    "sg:classifiers":[
        {
            "category":"Food & Beverages",
            "subcategory":"Groceries & Convenience Stores",
            "type":"Retail Goods"
        }
    ],
    "sg:phone":"+1 260 749 5102",
    "sg:postcode":"46815",
    "sg:province":"IN",
    "sg:tags":[
        "grocer"
    ],
    "wof:name":"Scott's Food Stores",
    "wof:placetype":"venue"
},
  "geometry": {"coordinates":[-85.059398,41.100964],"type":"Point"}
}