{
  "type": "Feature",
  "properties": {
    "iso:country":"US",
    "sg:address":"303 W Carmel Dr",
    "sg:city":"Carmel",
    "sg:classifiers":[
        {
            "category":"Manufacturing",
            "subcategory":"Printing",
            "type":"Manufacturing & Wholesale Goods"
        }
    ],
    "sg:phone":"+1 317 844 9171",
    "sg:postcode":"46032",
    "sg:province":"IN",
    "sg:tags":[
        "commercial"
    ],
    "wof:name":"Carmel Pro Printer Inc",
    "wof:placetype":"venue"
},
  "geometry": {"coordinates":[-86.130265,39.961373],"type":"Point"}
}