{
  "type": "Feature",
  "properties": {
    "iso:country":"US",
    "sg:address":"1625 N Garvin St",
    "sg:city":"Evansville",
    "sg:classifiers":[
        {
            "category":"Building & Trades",
            "subcategory":"Construction",
            "type":"Services"
        }
    ],
    "sg:phone":"+1 812 401 9655",
    "sg:postcode":"47711",
    "sg:province":"IN",
    "sg:tags":[
        "concrete",
        "contractor"
    ],
    "wof:name":"Apex Concrete Construction",
    "wof:placetype":"venue"
},
  "geometry": {"coordinates":[-87.556533,37.993127],"type":"Point"}
}