{
  "type": "Feature",
  "properties": {
    "iso:country":"US",
    "sg:address":"15114 Hidden Oaks Run",
    "sg:city":"Huntertown",
    "sg:classifiers":[
        {
            "category":"Insurance",
            "subcategory":"Insurance Agent",
            "type":"Services"
        }
    ],
    "sg:phone":"+1 260 338 1494",
    "sg:postcode":"46748",
    "sg:province":"IN",
    "wof:name":"Lutheran Brotherhood Insurance",
    "wof:placetype":"venue"
},
  "geometry": {"coordinates":[-85.159735,41.224482],"type":"Point"}
}