{
  "type": "Feature",
  "properties": {
    "iso:country":"US",
    "sg:address":"1803 Fieldhouse Ave",
    "sg:city":"Elkhart",
    "sg:classifiers":[
        {
            "category":"Wholesale",
            "subcategory":"Furniture",
            "type":"Manufacturing & Wholesale Goods"
        }
    ],
    "sg:phone":"+1 574 522 2636",
    "sg:postcode":"46517",
    "sg:province":"IN",
    "sg:tags":[
        "seating",
        "company"
    ],
    "sg:website":"www.dabrevi.com",
    "wof:name":"Dabrevi Designs Inc",
    "wof:placetype":"venue"
},
  "geometry": {"coordinates":[-85.999123,41.665997],"type":"Point"}
}