{
  "type": "Feature",
  "properties": {
    "iso:country":"US",
    "sg:address":"208 Yukon Pass",
    "sg:city":"Auburn",
    "sg:classifiers":[
        {
            "category":"Manufacturing",
            "subcategory":"Motor Vehicles & Parts",
            "type":"Manufacturing & Wholesale Goods"
        }
    ],
    "sg:phone":"+1 260 925 2237",
    "sg:postcode":"46706",
    "sg:province":"IN",
    "sg:tags":[
        "mfg"
    ],
    "wof:name":"Kdz Kustoms LLC",
    "wof:placetype":"venue"
},
  "geometry": {"coordinates":[-85.053686,41.393125],"type":"Point"}
}