{
  "type": "Feature",
  "properties": {
    "iso:country":"US",
    "sg:address":"133 E Main St",
    "sg:city":"North Manchester",
    "sg:classifiers":[
        {
            "category":"Insurance",
            "subcategory":"Insurance Agent",
            "type":"Services"
        }
    ],
    "sg:phone":"+1 260 982 6633",
    "sg:postcode":"46962",
    "sg:province":"IN",
    "wof:name":"Sites Insurance",
    "wof:placetype":"venue"
},
  "geometry": {"coordinates":[-85.818536,40.797953],"type":"Point"}
}