{
  "type": "Feature",
  "properties": {
    "iso:country":"US",
    "sg:address":"107 W Lafayette St",
    "sg:city":"Lagrange",
    "sg:classifiers":[
        {
            "category":"Organizations",
            "subcategory":"Religious Organization",
            "type":"Services"
        }
    ],
    "sg:phone":"+1 260 463 2243",
    "sg:postcode":"46761",
    "sg:province":"IN",
    "wof:name":"Brighton Chapel",
    "wof:placetype":"venue"
},
  "geometry": {"coordinates":[-85.418003,41.642906],"type":"Point"}
}