{
  "type": "Feature",
  "properties": {
    "addr:full":"2021 Woodcrest Rd Indianapolis IN 46227",
    "addr:housenumber":"2021",
    "addr:postcode":"46227",
    "addr:street":"Woodcrest Rd",
    "iso:country":"US",
    "sg:address":"2021 Woodcrest Rd",
    "sg:city":"Indianapolis",
    "sg:classifiers":[
        {
            "category":"Personal",
            "subcategory":"Beauty Salon",
            "type":"Services"
        }
    ],
    "sg:phone":"+1 317 784 1589",
    "sg:postcode":"46227",
    "sg:province":"IN",
    "wof:name":"Ann's Salon Inc",
    "wof:placetype":"venue"
},
  "geometry": {"coordinates":[-86.124301,39.697515],"type":"Point"}
}