{
  "type": "Feature",
  "properties": {
    "iso:country":"US",
    "sg:address":"3419 Roosevelt Ave",
    "sg:city":"Indianapolis",
    "sg:classifiers":[
        {
            "category":"Manufacturing",
            "subcategory":"Building Materials",
            "type":"Manufacturing & Wholesale Goods"
        }
    ],
    "sg:phone":"+1 317 547 3535",
    "sg:postcode":"46218",
    "sg:province":"IN",
    "wof:name":"Chisholm Lumber Supply Co Inc",
    "wof:placetype":"venue"
},
  "geometry": {"coordinates":[-86.108126,39.799282],"type":"Point"}
}