{
  "type": "Feature",
  "properties": {
    "addr:full":"6202 W Jefferson Blvd Fort Wayne IN 46804",
    "addr:housenumber":"6202",
    "addr:postcode":"46804",
    "addr:street":"W Jefferson Blvd",
    "iso:country":"US",
    "sg:address":"6202 W Jefferson Blvd",
    "sg:city":"Fort Wayne",
    "sg:classifiers":[
        {
            "category":"Shopping",
            "subcategory":"Pharmacy",
            "type":"Retail Goods"
        }
    ],
    "sg:phone":"+1 260 432 5100",
    "sg:postcode":"46804",
    "sg:province":"IN",
    "sg:website":"www.walgreens.com",
    "wof:name":"Walgreens",
    "wof:placetype":"venue"
},
  "geometry": {"coordinates":[-85.22065600000001,41.058372],"type":"Point"}
}