{
  "type": "Feature",
  "properties": {
    "addr:full":"8345 S US Hwy 421 San Pierre IN 46374",
    "addr:housenumber":"8345",
    "addr:postcode":"pierre;46374",
    "addr:street":"S Us Hwy 421",
    "iso:country":"US",
    "sg:address":"8345 S US Hwy 421",
    "sg:city":"San Pierre",
    "sg:classifiers":[
        {
            "category":"Professional",
            "type":"Services"
        }
    ],
    "sg:phone":"+1 219 828 3061",
    "sg:postcode":"46374",
    "sg:province":"IN",
    "sg:tags":[
        "establishment"
    ],
    "wof:name":"Crown Castle USA",
    "wof:placetype":"venue"
},
  "geometry": {"coordinates":[-86.89110100000001,41.181571],"type":"Point"}
}