{
  "type": "Feature",
  "properties": {
    "addr:full":"741 S State St Greenfield IN 46140",
    "addr:housenumber":"741",
    "addr:postcode":"46140",
    "addr:street":"S State St",
    "iso:country":"US",
    "sg:address":"741 S State St",
    "sg:city":"Greenfield",
    "sg:classifiers":[
        {
            "category":"Shopping",
            "subcategory":"Bicycles & Sporting Goods",
            "type":"Retail Goods"
        },
        {
            "category":"Sports & Exercise",
            "subcategory":"Swimming Pool",
            "type":"Entertainment"
        }
    ],
    "sg:phone":"+1 317 462 6881",
    "sg:postcode":"46140",
    "sg:province":"IN",
    "sg:tags":[
        "equipment",
        "repair",
        "supply"
    ],
    "wof:name":"Poolcare Pool & Liner Service Inc",
    "wof:placetype":"venue"
},
  "geometry": {"coordinates":[-85.767662,39.776642],"type":"Point"}
}