{
  "type": "Feature",
  "properties": {
    "iso:country":"US",
    "sg:address":"5407 Fielding Manor Dr",
    "sg:city":"Evansville",
    "sg:classifiers":[
        {
            "category":"Real Estate",
            "subcategory":"Architect",
            "type":"Services"
        }
    ],
    "sg:phone":"+1 812 477 8606",
    "sg:postcode":"47715",
    "sg:province":"IN",
    "wof:name":"Actaeon Limited",
    "wof:placetype":"venue"
},
  "geometry": {"coordinates":[-87.483616,37.975173],"type":"Point"}
}