{
  "type": "Feature",
  "properties": {
    "iso:country":"US",
    "sg:address":"5420 E 650 N",
    "sg:city":"Rochester",
    "sg:classifiers":[
        {
            "category":"Organizations",
            "subcategory":"Religious Organization",
            "type":"Services"
        }
    ],
    "sg:phone":"+1 574 223 7323",
    "sg:postcode":"46975",
    "sg:province":"IN",
    "sg:tags":[
        "church"
    ],
    "wof:name":"Talma Grace Bible Church",
    "wof:placetype":"venue"
},
  "geometry": {"coordinates":[-86.140654,41.153511],"type":"Point"}
}