{
  "type": "Feature",
  "properties": {
    "addr:full":"5335 Winthrop Ave Indianapolis IN 46220",
    "addr:housenumber":"5335",
    "addr:postcode":"46220",
    "addr:street":"Winthrop Ave",
    "iso:country":"US",
    "sg:address":"5335 Winthrop Ave",
    "sg:city":"Indianapolis",
    "sg:classifiers":[
        {
            "category":"Retail",
            "subcategory":"Repair Shop",
            "type":"Services"
        }
    ],
    "sg:phone":"+1 317 283 2555",
    "sg:postcode":"46220",
    "sg:province":"IN",
    "sg:tags":[
        "upholsterer"
    ],
    "wof:name":"Hughey Hartman",
    "wof:placetype":"venue"
},
  "geometry": {"coordinates":[-86.141718,39.850395],"type":"Point"}
}