{
  "type": "Feature",
  "properties": {
    "iso:country":"US",
    "sg:address":"1749 Commerce Ct",
    "sg:city":"Logansport",
    "sg:classifiers":[
        {
            "category":"Real Estate",
            "subcategory":"Real Estate Operator",
            "type":"Services"
        }
    ],
    "sg:phone":"+1 574 722 5439",
    "sg:postcode":"46947",
    "sg:province":"IN",
    "sg:tags":[
        "apartment"
    ],
    "wof:name":"Logansport Apartments",
    "wof:placetype":"venue"
},
  "geometry": {"coordinates":[-86.353053,40.770778],"type":"Point"}
}