{
  "type": "Feature",
  "properties": {
    "iso:country":"US",
    "sg:address":"718 Broadway",
    "sg:city":"Fort Wayne",
    "sg:classifiers":[
        {
            "category":"Professional",
            "subcategory":"Lawyer & Legal Services",
            "type":"Services"
        }
    ],
    "sg:phone":"+1 260 490 1097",
    "sg:postcode":"46802",
    "sg:province":"IN",
    "sg:tags":[
        "attorney"
    ],
    "wof:name":"Whitmore Rochyby Grunden",
    "wof:placetype":"venue"
},
  "geometry": {"coordinates":[-85.148715,41.078063],"type":"Point"}
}