{
  "type": "Feature",
  "properties": {
    "iso:country":"US",
    "sg:address":"736 Cross St",
    "sg:city":"Evansville",
    "sg:classifiers":[
        {
            "category":"Real Estate",
            "subcategory":"Real Estate Agent",
            "type":"Services"
        }
    ],
    "sg:phone":"+1 812 428 8527",
    "sg:postcode":"47713",
    "sg:province":"IN",
    "wof:name":"Caldwell Homes",
    "wof:placetype":"venue"
},
  "geometry": {"coordinates":[-87.55493800000001,37.950807],"type":"Point"}
}