{
  "type": "Feature",
  "properties": {
    "iso:country":"US",
    "sg:address":"4615 S 200 E",
    "sg:city":"Pleasant Lake",
    "sg:classifiers":[
        {
            "category":"Farming",
            "subcategory":"Farm",
            "type":"Manufacturing & Wholesale Goods"
        }
    ],
    "sg:phone":"+1 260 475 5028",
    "sg:postcode":"46779",
    "sg:province":"IN",
    "sg:tags":[
        "crop",
        "general"
    ],
    "wof:name":"Ingledue John",
    "wof:placetype":"venue"
},
  "geometry": {"coordinates":[-84.95259299999999,41.578133],"type":"Point"}
}