{
  "type": "Feature",
  "properties": {
    "iso:country":"US",
    "sg:address":"1828 Co Rd 750 S",
    "sg:city":"Trafalgar",
    "sg:classifiers":[
        {
            "category":"Farming",
            "subcategory":"Crops",
            "type":"Manufacturing & Wholesale Goods"
        }
    ],
    "sg:phone":"+1 317 933 3393",
    "sg:postcode":"46181",
    "sg:province":"IN",
    "sg:tags":[
        "farm",
        "field",
        "operation",
        "timber",
        "tract"
    ],
    "wof:name":"Kenneth Nettles",
    "wof:placetype":"venue"
},
  "geometry": {"coordinates":[-86.13668,39.365148],"type":"Point"}
}