{
  "type": "Feature",
  "properties": {
    "iso:country":"US",
    "sg:address":"2802 W 16th St",
    "sg:city":"Indianapolis",
    "sg:classifiers":[
        {
            "category":"Shopping",
            "subcategory":"Used Merchandise",
            "type":"Retail Goods"
        }
    ],
    "sg:phone":"+1 317 972 0325",
    "sg:postcode":"46222",
    "sg:province":"IN",
    "sg:tags":[
        "pawnbroker"
    ],
    "wof:name":"Pawn Mart Install",
    "wof:placetype":"venue"
},
  "geometry": {"coordinates":[-86.207345,39.787992],"type":"Point"}
}