{
  "type": "Feature",
  "properties": {
    "iso:country":"US",
    "sg:address":"222 State Rd 129",
    "sg:city":"Batesville",
    "sg:classifiers":[
        {
            "category":"Health Services",
            "subcategory":"Doctor",
            "type":"Services"
        }
    ],
    "sg:phone":"+1 812 934 4262",
    "sg:postcode":"47006",
    "sg:province":"IN",
    "sg:tags":[
        "physician",
        "surgeon"
    ],
    "wof:name":"Surgical Associates Of Se In",
    "wof:placetype":"venue"
},
  "geometry": {"coordinates":[-85.202499,39.288585],"type":"Point"}
}