{
  "type": "Feature",
  "properties": {
    "iso:country":"US",
    "sg:address":"1867 N Allen Chapel Rd",
    "sg:city":"Kendallville",
    "sg:classifiers":[
        {
            "category":"Building & Trades",
            "subcategory":"Construction",
            "type":"Services"
        }
    ],
    "sg:phone":"+1 260 347 5023",
    "sg:postcode":"46755",
    "sg:province":"IN",
    "sg:tags":[
        "general",
        "contractor"
    ],
    "wof:name":"Kline Builders Inc",
    "wof:placetype":"venue"
},
  "geometry": {"coordinates":[-85.23177800000001,41.479196],"type":"Point"}
}