{
  "type": "Feature",
  "properties": {
    "iso:country":"US",
    "sg:address":"9250 Columbia Ave Ste A2",
    "sg:city":"Munster",
    "sg:classifiers":[
        {
            "category":"Health Services",
            "subcategory":"Doctor",
            "type":"Services"
        }
    ],
    "sg:phone":"+1 219 836 7100",
    "sg:postcode":"46321",
    "sg:province":"IN",
    "sg:tags":[
        "surgeon",
        "cosmetic"
    ],
    "sg:website":"www.ashpoleplasticsurgery.com",
    "wof:name":"Ashpole Plastic Surgery",
    "wof:placetype":"venue"
},
  "geometry": {"coordinates":[-87.506477,41.545189],"type":"Point"}
}