{
  "type": "Feature",
  "properties": {
    "iso:country":"US",
    "sg:address":"217 W Court Ave",
    "sg:city":"Jeffersonville",
    "sg:classifiers":[
        {
            "category":"Government",
            "subcategory":"Office",
            "type":"Public Place"
        }
    ],
    "sg:phone":"+1 812 285 6345",
    "sg:postcode":"47130",
    "sg:province":"IN",
    "wof:name":"Clark County Veterans Svc Ofcr",
    "wof:placetype":"venue"
},
  "geometry": {"coordinates":[-85.744255,38.273238],"type":"Point"}
}