{
  "type": "Feature",
  "properties": {
    "iso:country":"US",
    "sg:address":"542 S Co Rd 150 W",
    "sg:city":"Greensburg",
    "sg:classifiers":[
        {
            "category":"Professional",
            "subcategory":"Lawyer & Legal Services",
            "type":"Services"
        }
    ],
    "sg:phone":"+1 812 663 9282",
    "sg:postcode":"47240",
    "sg:province":"IN",
    "sg:tags":[
        "attorney"
    ],
    "wof:name":"Hamilton & Tebbe Law Office",
    "wof:placetype":"venue"
},
  "geometry": {"coordinates":[-85.508247,39.325742],"type":"Point"}
}