{
  "type": "Feature",
  "properties": {
    "iso:country":"US",
    "sg:address":"1912 N Glendale Dr",
    "sg:city":"Fort Wayne",
    "sg:classifiers":[
        {
            "category":"Real Estate",
            "subcategory":"Real Estate Agent",
            "type":"Services"
        }
    ],
    "sg:phone":"+1 260 745 3745",
    "sg:postcode":"46804",
    "sg:province":"IN",
    "wof:name":"Statewide Real Estate Solution",
    "wof:placetype":"venue"
},
  "geometry": {"coordinates":[-85.209889,41.063975],"type":"Point"}
}