{
  "type": "Feature",
  "properties": {
    "iso:country":"US",
    "sg:address":"314 Jefferson St",
    "sg:city":"Madison",
    "sg:classifiers":[
        {
            "category":"Manufacturing",
            "subcategory":"Paper Products",
            "type":"Manufacturing & Wholesale Goods"
        }
    ],
    "sg:phone":"+1 812 265 6072",
    "sg:postcode":"47250",
    "sg:province":"IN",
    "sg:tags":[
        "bag"
    ],
    "wof:name":"Stormer Packaging",
    "wof:placetype":"venue"
},
  "geometry": {"coordinates":[-85.37714800000001,38.735523],"type":"Point"}
}