{
  "type": "Feature",
  "properties": {
    "addr:full":"6685 Federal Ave Portage IN 46368",
    "addr:housenumber":"6685",
    "addr:postcode":"46368",
    "addr:street":"Federal Ave",
    "iso:country":"US",
    "sg:address":"6685 Federal Ave",
    "sg:city":"Portage",
    "sg:classifiers":[
        {
            "category":"Real Estate",
            "subcategory":"Real Estate Agent",
            "type":"Services"
        }
    ],
    "sg:phone":"+1 219 763 3486",
    "sg:postcode":"46368",
    "sg:province":"IN",
    "wof:name":"R E & L",
    "wof:placetype":"venue"
},
  "geometry": {"coordinates":[-87.156206,41.587563],"type":"Point"}
}