{
  "type": "Feature",
  "properties": {
    "iso:country":"US",
    "sg:address":"4219 Cleveland St",
    "sg:city":"Gary",
    "sg:classifiers":[
        {
            "category":"Health Services",
            "subcategory":"Clinic",
            "type":"Services"
        }
    ],
    "sg:phone":"+1 219 884 2485",
    "sg:postcode":"46408",
    "sg:province":"IN",
    "wof:name":"Parent Information Dist Ctr I",
    "wof:placetype":"venue"
},
  "geometry": {"coordinates":[-87.360473,41.541518],"type":"Point"}
}