{
  "type": "Feature",
  "properties": {
    "iso:country":"US",
    "sg:address":"5049 N State Rd 1",
    "sg:city":"Ossian",
    "sg:classifiers":[
        {
            "category":"Building & Trades",
            "subcategory":"Pest Control",
            "type":"Services"
        }
    ],
    "sg:phone":"+1 260 824 2399",
    "sg:postcode":"46777",
    "sg:province":"IN",
    "wof:name":"American Pest Professional",
    "wof:placetype":"venue"
},
  "geometry": {"coordinates":[-85.166096,40.815217],"type":"Point"}
}