{
  "type": "Feature",
  "properties": {
    "addr:full":"106 S Main St Goshen IN 46526",
    "addr:housenumber":"106",
    "addr:postcode":"46526",
    "addr:street":"S Main St",
    "iso:country":"US",
    "sg:address":"106 S Main St",
    "sg:city":"Goshen",
    "sg:classifiers":[
        {
            "category":"Professional",
            "subcategory":"Printing & Photocopies",
            "type":"Services"
        }
    ],
    "sg:phone":"+1 574 534 1411",
    "sg:postcode":"46526",
    "sg:province":"IN",
    "sg:tags":[
        "duplicating",
        "copying"
    ],
    "wof:name":"Instant Copy Of Indiana Inc",
    "wof:placetype":"venue"
},
  "geometry": {"coordinates":[-85.834418,41.585916],"type":"Point"}
}