{
  "type": "Feature",
  "properties": {
    "addr:full":"102 N Park Ln Royal Center IN 46978",
    "addr:housenumber":"102",
    "addr:postcode":"46978",
    "addr:street":"N Park Ln",
    "iso:country":"US",
    "sg:address":"102 N Park Ln",
    "sg:city":"Royal Center",
    "sg:classifiers":[
        {
            "category":"Wholesale",
            "subcategory":"Sporting Goods",
            "type":"Manufacturing & Wholesale Goods"
        }
    ],
    "sg:phone":"+1 574 643 6215",
    "sg:postcode":"46978",
    "sg:province":"IN",
    "sg:tags":[
        "tackle",
        "fishing"
    ],
    "wof:name":"Floyd's Baits & Svc",
    "wof:placetype":"venue"
},
  "geometry": {"coordinates":[-86.497118,40.869344],"type":"Point"}
}