{
  "type": "Feature",
  "properties": {
    "iso:country":"US",
    "sg:address":"3431 E State Blvd",
    "sg:city":"Fort Wayne",
    "sg:classifiers":[
        {
            "category":"Personal",
            "subcategory":"Beauty Salon",
            "type":"Services"
        }
    ],
    "sg:phone":"+1 260 483 2457",
    "sg:postcode":"46805",
    "sg:province":"IN",
    "wof:name":"New Revelation Hair Care Ctr",
    "wof:placetype":"venue"
},
  "geometry": {"coordinates":[-85.095832,41.097487],"type":"Point"}
}