{
  "type": "Feature",
  "properties": {
    "iso:country":"US",
    "sg:address":"1504 Royal Lake Dr",
    "sg:city":"Indianapolis",
    "sg:classifiers":[
        {
            "category":"Banks & Credit Unions",
            "subcategory":"Investment Brokerage",
            "type":"Services"
        }
    ],
    "sg:phone":"+1 317 253 0139",
    "sg:postcode":"46228",
    "sg:province":"IN",
    "sg:tags":[
        "advisory",
        "financial"
    ],
    "wof:name":"Financial BCB",
    "wof:placetype":"venue"
},
  "geometry": {"coordinates":[-86.18459799999999,39.864282],"type":"Point"}
}