{
  "type": "Feature",
  "properties": {
    "iso:country":"US",
    "sg:address":"1031 S Main St",
    "sg:city":"Edinburgh",
    "sg:classifiers":[
        {
            "category":"Manufacturing",
            "subcategory":"Tools & Machinery",
            "type":"Manufacturing & Wholesale Goods"
        }
    ],
    "sg:phone":"+1 812 526 2030",
    "sg:postcode":"46124",
    "sg:province":"IN",
    "sg:tags":[
        "mold"
    ],
    "wof:name":"L & B Mold Inc",
    "wof:placetype":"venue"
},
  "geometry": {"coordinates":[-85.96747000000001,39.347125],"type":"Point"}
}