{
  "type": "Feature",
  "properties": {
    "addr:full":"5061 Sherwood Ct Pittsboro IN 46167",
    "addr:housenumber":"5061",
    "addr:postcode":"46167",
    "addr:street":"Sherwood Ct",
    "iso:country":"US",
    "sg:address":"5061 Sherwood Ct",
    "sg:city":"Pittsboro",
    "sg:classifiers":[
        {
            "category":"Farming",
            "subcategory":"Farm",
            "type":"Manufacturing & Wholesale Goods"
        }
    ],
    "sg:phone":"+1 317 892 3337",
    "sg:postcode":"46167",
    "sg:province":"IN",
    "sg:tags":[
        "crop",
        "general"
    ],
    "wof:name":"Hitchings Farms Inc",
    "wof:placetype":"venue"
},
  "geometry": {"coordinates":[-86.438935,39.853915],"type":"Point"}
}