{
  "type": "Feature",
  "properties": {
    "iso:country":"US",
    "sg:address":"7393 Bus Center Dr",
    "sg:city":"Avon",
    "sg:classifiers":[
        {
            "category":"Real Estate",
            "subcategory":"Real Estate Agent",
            "type":"Services"
        }
    ],
    "sg:phone":"+1 317 272 8737",
    "sg:postcode":"46123",
    "sg:province":"IN",
    "wof:name":"Tom Gilbert & Assoc",
    "wof:placetype":"venue"
},
  "geometry": {"coordinates":[-86.392036,39.762089],"type":"Point"}
}