{
  "type": "Feature",
  "properties": {
    "iso:country":"US",
    "sg:address":"1320 S Grandstaff Dr",
    "sg:city":"Auburn",
    "sg:classifiers":[
        {
            "category":"Professional",
            "subcategory":"Lawyer & Legal Services",
            "type":"Services"
        }
    ],
    "sg:phone":"+1 260 925 3787",
    "sg:postcode":"46706",
    "sg:province":"IN",
    "sg:tags":[
        "attorney"
    ],
    "wof:name":"James P Mc Canna Law Offices",
    "wof:placetype":"venue"
},
  "geometry": {"coordinates":[-85.071343,41.356342],"type":"Point"}
}