{
  "type": "Feature",
  "properties": {
    "iso:country":"US",
    "sg:address":"4433 N Franklin Rd",
    "sg:city":"Indianapolis",
    "sg:classifiers":[
        {
            "category":"Organizations",
            "subcategory":"Religious Organization",
            "type":"Services"
        }
    ],
    "sg:phone":"+1 317 547 3728",
    "sg:postcode":"46226",
    "sg:province":"IN",
    "wof:name":"Little Babes Outreach Ministry",
    "wof:placetype":"venue"
},
  "geometry": {"coordinates":[-86.027037,39.837387],"type":"Point"}
}