{
  "type": "Feature",
  "properties": {
    "iso:country":"US",
    "sg:address":"2403 N Clinton St",
    "sg:city":"Fort Wayne",
    "sg:classifiers":[
        {
            "category":"Professional",
            "subcategory":"Business Services",
            "type":"Services"
        }
    ],
    "sg:phone":"+1 260 482 1345",
    "sg:postcode":"46805",
    "sg:province":"IN",
    "wof:name":"Tailored Sales Training",
    "wof:placetype":"venue"
},
  "geometry": {"coordinates":[-85.138208,41.099073],"type":"Point"}
}