{
  "type": "Feature",
  "properties": {
    "iso:country":"US",
    "sg:address":"1010 W 6th St",
    "sg:city":"Jasper",
    "sg:classifiers":[
        {
            "category":"Autos & Motor Vehicles",
            "subcategory":"Automobile Sales",
            "type":"Retail Goods"
        }
    ],
    "sg:phone":"+1 812 683 4808",
    "sg:postcode":"47546",
    "sg:province":"IN",
    "sg:tags":[
        "used"
    ],
    "wof:name":"S&S Sales",
    "wof:placetype":"venue"
},
  "geometry": {"coordinates":[-86.946116,38.393377],"type":"Point"}
}