{
  "type": "Feature",
  "properties": {
    "addr:full":"1435 N Michigan St Plymouth IN 46563",
    "addr:housenumber":"1435",
    "addr:postcode":"46563",
    "addr:street":"N Michigan St",
    "iso:country":"US",
    "sg:address":"1435 N Michigan St",
    "sg:city":"Plymouth",
    "sg:classifiers":[
        {
            "category":"Real Estate",
            "subcategory":"Real Estate Agent",
            "type":"Services"
        }
    ],
    "sg:phone":"+1 574 936 4487",
    "sg:postcode":"46563",
    "sg:province":"IN",
    "wof:name":"CCR Property Managers",
    "wof:placetype":"venue"
},
  "geometry": {"coordinates":[-86.31057,41.351167],"type":"Point"}
}