{
  "type": "Feature",
  "properties": {
    "addr:full":"1303 N Reed Rd Kokomo IN 46901",
    "addr:housenumber":"1303",
    "addr:postcode":"46901",
    "addr:street":"N Reed Rd",
    "iso:country":"US",
    "sg:address":"1303 N Reed Rd",
    "sg:city":"Kokomo",
    "sg:classifiers":[
        {
            "category":"Food & Beverages",
            "subcategory":"Groceries & Convenience Stores",
            "type":"Retail Goods"
        }
    ],
    "sg:phone":"+1 765 459 8820",
    "sg:postcode":"46901",
    "sg:province":"IN",
    "wof:name":"Gas America",
    "wof:placetype":"venue"
},
  "geometry": {"coordinates":[-86.109173,40.498407],"type":"Point"}
}