{
  "type": "Feature",
  "properties": {
    "iso:country":"US",
    "sg:address":"6386 N Co Rd 930 E",
    "sg:city":"Forest",
    "sg:classifiers":[
        {
            "category":"Farming",
            "subcategory":"Farm",
            "type":"Manufacturing & Wholesale Goods"
        }
    ],
    "sg:phone":"+1 765 249 2146",
    "sg:postcode":"46039",
    "sg:province":"IN",
    "sg:tags":[
        "crop",
        "general"
    ],
    "wof:name":"Conrad Coleman",
    "wof:placetype":"venue"
},
  "geometry": {"coordinates":[-86.33279,40.383413],"type":"Point"}
}