{
  "type": "Feature",
  "properties": {
    "iso:country":"US",
    "sg:address":"305 E Clifty Dr",
    "sg:city":"Madison",
    "sg:classifiers":[
        {
            "category":"Autos & Motor Vehicles",
            "subcategory":"Automobile Sales",
            "type":"Retail Goods"
        }
    ],
    "sg:phone":"+1 812 273 9525",
    "sg:postcode":"47250",
    "sg:province":"IN",
    "sg:tags":[
        "car",
        "dealer"
    ],
    "wof:name":"J D Byrider Svc",
    "wof:placetype":"venue"
},
  "geometry": {"coordinates":[-85.381633,38.776659],"type":"Point"}
}