{
  "type": "Feature",
  "properties": {
    "iso:country":"US",
    "sg:address":"2602 E 55th St",
    "sg:city":"Indianapolis",
    "sg:classifiers":[
        {
            "category":"Wholesale",
            "subcategory":"Electrical",
            "type":"Manufacturing & Wholesale Goods"
        }
    ],
    "sg:phone":"+1 317 255 2125",
    "sg:postcode":"46220",
    "sg:province":"IN",
    "sg:tags":[
        "alarm",
        "burglar",
        "system"
    ],
    "sg:website":"www.nelsonalarm.com",
    "wof:name":"Nelson Alarm Co",
    "wof:placetype":"venue"
},
  "geometry": {"coordinates":[-86.1177,39.852722],"type":"Point"}
}