{
  "type": "Feature",
  "properties": {
    "addr:full":"560 S Douglas Ave Columbia City IN 46725",
    "addr:housenumber":"560",
    "addr:postcode":"46725",
    "addr:street":"S Douglas Ave",
    "iso:country":"US",
    "sg:address":"560 S Douglas Ave",
    "sg:city":"Columbia City",
    "sg:classifiers":[
        {
            "category":"Manufacturing",
            "subcategory":"Signs",
            "type":"Manufacturing & Wholesale Goods"
        }
    ],
    "sg:phone":"+1 260 244 7131",
    "sg:postcode":"46725",
    "sg:province":"IN",
    "wof:name":"Martin & Co",
    "wof:placetype":"venue"
},
  "geometry": {"coordinates":[-85.478602,41.14931],"type":"Point"}
}