{
  "type": "Feature",
  "properties": {
    "iso:country":"US",
    "sg:address":"6625 Network Way",
    "sg:city":"Indianapolis",
    "sg:classifiers":[
        {
            "category":"Wholesale",
            "subcategory":"Machinery & Supplies",
            "type":"Manufacturing & Wholesale Goods"
        }
    ],
    "sg:phone":"+1 317 390 5000",
    "sg:postcode":"46278",
    "sg:province":"IN",
    "sg:tags":[
        "packaging"
    ],
    "sg:website":"www.alcoacsi.com",
    "wof:name":"Alcoa Closure Systems Intl",
    "wof:placetype":"venue"
},
  "geometry": {"coordinates":[-86.278131,39.876375],"type":"Point"}
}