{
  "type": "Feature",
  "properties": {
    "iso:country":"US",
    "sg:address":"2220 19th St",
    "sg:city":"Elkhart",
    "sg:classifiers":[
        {
            "category":"Manufacturing",
            "subcategory":"Tools & Machinery",
            "type":"Manufacturing & Wholesale Goods"
        }
    ],
    "sg:phone":"+1 574 293 0231",
    "sg:postcode":"46517",
    "sg:province":"IN",
    "sg:tags":[
        "machine",
        "shop"
    ],
    "wof:name":"Grove Machine Inc",
    "wof:placetype":"venue"
},
  "geometry": {"coordinates":[-85.999084,41.665786],"type":"Point"}
}