{
  "type": "Feature",
  "properties": {
    "iso:country":"US",
    "sg:address":"100 S Cob St",
    "sg:city":"Elwood",
    "sg:classifiers":[
        {
            "category":"Freight",
            "type":"Transportation"
        }
    ],
    "sg:phone":"+1 765 552 7311",
    "sg:postcode":"46036",
    "sg:province":"IN",
    "sg:tags":[
        "grain",
        "elevator"
    ],
    "wof:name":"Hartley Grain Co",
    "wof:placetype":"venue"
},
  "geometry": {"coordinates":[-85.898292,40.31829],"type":"Point"}
}