{
  "type": "Feature",
  "properties": {
    "iso:country":"US",
    "sg:address":"8104 Dean Rd",
    "sg:city":"Indianapolis",
    "sg:classifiers":[
        {
            "category":"Professional",
            "subcategory":"Management & Consulting",
            "type":"Services"
        }
    ],
    "sg:phone":"+1 317 579 0808",
    "sg:postcode":"46240",
    "sg:province":"IN",
    "sg:tags":[
        "business"
    ],
    "wof:name":"John O Bodman Co Inc",
    "wof:placetype":"venue"
},
  "geometry": {"coordinates":[-86.098556,39.900622],"type":"Point"}
}