{
  "type": "Feature",
  "properties": {
    "iso:country":"US",
    "sg:address":"8200 Haverstick Rd",
    "sg:city":"Indianapolis",
    "sg:classifiers":[
        {
            "category":"Insurance",
            "subcategory":"Insurance Agent",
            "type":"Services"
        }
    ],
    "sg:phone":"+1 317 259 0528",
    "sg:postcode":"46240",
    "sg:province":"IN",
    "sg:tags":[
        "adjuster"
    ],
    "wof:name":"Gallagher Bassett Svc Inc",
    "wof:placetype":"venue"
},
  "geometry": {"coordinates":[-86.11741000000001,39.904871],"type":"Point"}
}