{
  "type": "Feature",
  "properties": {
    "iso:country":"US",
    "sg:address":"2011 Emerald Pines Ln",
    "sg:city":"Westfield",
    "sg:classifiers":[
        {
            "category":"Organizations",
            "subcategory":"Religious Organization",
            "type":"Services"
        }
    ],
    "sg:phone":"+1 317 896 9604",
    "sg:postcode":"46074",
    "sg:province":"IN",
    "wof:name":"Student Impact",
    "wof:placetype":"venue"
},
  "geometry": {"coordinates":[-86.12381600000001,40.034727],"type":"Point"}
}