{
  "type": "Feature",
  "properties": {
    "iso:country":"US",
    "sg:address":"527 E 31st St",
    "sg:city":"Marion",
    "sg:classifiers":[
        {
            "category":"Shopping",
            "subcategory":"Florist",
            "type":"Retail Goods"
        }
    ],
    "sg:phone":"+1 765 664 0021",
    "sg:postcode":"46953",
    "sg:province":"IN",
    "wof:name":"Marion Floral Vice's",
    "wof:placetype":"venue"
},
  "geometry": {"coordinates":[-85.654349,40.533101],"type":"Point"}
}