{
  "type": "Feature",
  "properties": {
    "iso:country":"US",
    "sg:address":"3426 N Wells St",
    "sg:city":"Fort Wayne",
    "sg:classifiers":[
        {
            "category":"Manufacturing",
            "subcategory":"Food",
            "type":"Manufacturing & Wholesale Goods"
        }
    ],
    "sg:phone":"+1 260 483 3102",
    "sg:postcode":"46808",
    "sg:province":"IN",
    "sg:tags":[
        "frozen",
        "dessert",
        "ice",
        "cream"
    ],
    "wof:name":"Edy's Grand Ice Cream",
    "wof:placetype":"venue"
},
  "geometry": {"coordinates":[-85.147724,41.109676],"type":"Point"}
}