{
  "type": "Feature",
  "properties": {
    "iso:country":"US",
    "sg:address":"55911 Hoosier Ave",
    "sg:city":"Mishawaka",
    "sg:classifiers":[
        {
            "category":"Building & Trades",
            "subcategory":"Electrical",
            "type":"Services"
        }
    ],
    "sg:phone":"+1 574 259 5568",
    "sg:postcode":"46545",
    "sg:province":"IN",
    "sg:tags":[
        "electric",
        "contractor"
    ],
    "wof:name":"Revell-Banes Electric",
    "wof:placetype":"venue"
},
  "geometry": {"coordinates":[-86.126655,41.680798],"type":"Point"}
}