{
  "type": "Feature",
  "properties": {
    "iso:country":"US",
    "sg:address":"6080 Buttontown Rd",
    "sg:city":"Greenville",
    "sg:classifiers":[
        {
            "category":"Building & Trades",
            "subcategory":"Construction",
            "type":"Services"
        }
    ],
    "sg:phone":"+1 812 923 9496",
    "sg:postcode":"47124",
    "sg:province":"IN",
    "sg:tags":[
        "house"
    ],
    "wof:name":"Wagoner Remodeling Inc",
    "wof:placetype":"venue"
},
  "geometry": {"coordinates":[-85.985212,38.363674],"type":"Point"}
}