{
  "type": "Feature",
  "properties": {
    "iso:country":"US",
    "sg:address":"802 13th St",
    "sg:city":"Tell City",
    "sg:classifiers":[
        {
            "category":"Organizations",
            "subcategory":"Religious Organization",
            "type":"Services"
        }
    ],
    "sg:phone":"+1 812 547 2270",
    "sg:postcode":"47586",
    "sg:province":"IN",
    "sg:tags":[
        "church"
    ],
    "wof:name":"First Baptist Church",
    "wof:placetype":"venue"
},
  "geometry": {"coordinates":[-86.76311800000001,37.953744],"type":"Point"}
}