{
  "type": "Feature",
  "properties": {
    "iso:country":"US",
    "sg:address":"121 7th Ave NW",
    "sg:city":"Demotte",
    "sg:classifiers":[
        {
            "category":"Freight",
            "type":"Transportation"
        }
    ],
    "sg:phone":"+1 219 987 4954",
    "sg:postcode":"46310",
    "sg:province":"IN",
    "sg:tags":[
        "operator",
        "local",
        "trucking"
    ],
    "wof:name":"Grace & Co Trucking",
    "wof:placetype":"venue"
},
  "geometry": {"coordinates":[-87.199554,41.209203],"type":"Point"}
}