{
  "type": "Feature",
  "properties": {
    "iso:country":"US",
    "sg:address":"15886 Michigan Rd",
    "sg:city":"Argos",
    "sg:classifiers":[
        {
            "category":"Manufacturing",
            "subcategory":"Motor Vehicles & Parts",
            "type":"Manufacturing & Wholesale Goods"
        }
    ],
    "sg:phone":"+1 574 892 5151",
    "sg:postcode":"46501",
    "sg:province":"IN",
    "sg:tags":[
        "designer",
        "trailer"
    ],
    "wof:name":"Ameri-Can Engineering Inc",
    "wof:placetype":"venue"
},
  "geometry": {"coordinates":[-86.249252,41.245586],"type":"Point"}
}