{
  "type": "Feature",
  "properties": {
    "iso:country":"US",
    "sg:address":"510 W Jackson St",
    "sg:city":"Mulberry",
    "sg:classifiers":[
        {
            "category":"Health Services",
            "subcategory":"Doctor",
            "type":"Services"
        }
    ],
    "sg:phone":"+1 765 296 2070",
    "sg:postcode":"46058",
    "sg:province":"IN",
    "sg:tags":[
        "physician",
        "surgeon"
    ],
    "wof:name":"Family Practice Ctr",
    "wof:placetype":"venue"
},
  "geometry": {"coordinates":[-86.674786,40.347598],"type":"Point"}
}