{
  "type": "Feature",
  "properties": {
    "iso:country":"US",
    "sg:address":"650 N Girls School Rd",
    "sg:city":"Indianapolis",
    "sg:classifiers":[
        {
            "category":"Health Services",
            "subcategory":"Doctor",
            "type":"Services"
        }
    ],
    "sg:phone":"+1 317 209 9702",
    "sg:postcode":"46214",
    "sg:province":"IN",
    "sg:tags":[
        "dentist"
    ],
    "wof:name":"Westside Family Dental",
    "wof:placetype":"venue"
},
  "geometry": {"coordinates":[-86.289258,39.77586],"type":"Point"}
}