{
  "type": "Feature",
  "properties": {
    "iso:country":"US",
    "sg:address":"510 E Columbia Ave",
    "sg:city":"Eaton",
    "sg:classifiers":[
        {
            "category":"Organizations",
            "subcategory":"Religious Organization",
            "type":"Services"
        }
    ],
    "sg:phone":"+1 765 396 9066",
    "sg:postcode":"47338",
    "sg:province":"IN",
    "sg:tags":[
        "church"
    ],
    "wof:name":"First Baptist Church Eaton",
    "wof:placetype":"venue"
},
  "geometry": {"coordinates":[-85.35062600000001,40.338549],"type":"Point"}
}