{
  "type": "Feature",
  "properties": {
    "addr:full":"417 W Creighton Ave Fort Wayne IN 46807",
    "addr:housenumber":"417",
    "addr:postcode":"46807",
    "addr:street":"W Creighton Ave",
    "iso:country":"US",
    "sg:address":"417 W Creighton Ave",
    "sg:city":"Fort Wayne",
    "sg:classifiers":[
        {
            "category":"Food & Beverages",
            "subcategory":"Groceries & Convenience Stores",
            "type":"Retail Goods"
        }
    ],
    "sg:phone":"+1 260 744 2039",
    "sg:postcode":"46807",
    "sg:province":"IN",
    "sg:tags":[
        "grocer"
    ],
    "wof:name":"Supermarket Los Lagos Inc",
    "wof:placetype":"venue"
},
  "geometry": {"coordinates":[-85.144789,41.064057],"type":"Point"}
}