{
  "type": "Feature",
  "properties": {
    "iso:country":"US",
    "sg:address":"5450 S Co Rd 100 W",
    "sg:city":"Oakland City",
    "sg:classifiers":[
        {
            "category":"Building & Trades",
            "subcategory":"Construction",
            "type":"Services"
        }
    ],
    "sg:phone":"+1 812 749 3843",
    "sg:postcode":"47660",
    "sg:province":"IN",
    "sg:tags":[
        "house"
    ],
    "wof:name":"Potts Brothers Construction",
    "wof:placetype":"venue"
},
  "geometry": {"coordinates":[-87.296969,38.342352],"type":"Point"}
}