{
  "type": "Feature",
  "properties": {
    "addr:full":"10423 Indianapolis Blvd Highland IN 46322",
    "addr:housenumber":"10423",
    "addr:postcode":"46322",
    "addr:street":"Indianapolis Blvd",
    "iso:country":"US",
    "sg:address":"10423 Indianapolis Blvd",
    "sg:city":"Highland",
    "sg:classifiers":[
        {
            "category":"Shopping",
            "subcategory":"Shoes",
            "type":"Retail Goods"
        }
    ],
    "sg:phone":"+1 219 922 6861",
    "sg:postcode":"46322",
    "sg:province":"IN",
    "wof:name":"Famous Footwear",
    "wof:placetype":"venue"
},
  "geometry": {"coordinates":[-87.471165,41.525353],"type":"Point"}
}