{
  "type": "Feature",
  "properties": {
    "addr:full":"113 N 5th St Lafayette IN 47901",
    "addr:housenumber":"113",
    "addr:postcode":"47901",
    "addr:street":"N 5Th St",
    "iso:country":"US",
    "sg:address":"113 N 5th St",
    "sg:city":"Lafayette",
    "sg:classifiers":[
        {
            "category":"Bars & Pubs",
            "type":"Food & Drink"
        },
        {
            "category":"Restaurant",
            "type":"Food & Drink"
        }
    ],
    "sg:menulink":"http://www.allmenus.com/in/fairfield/279984-knickerbocker-saloon/menu/",
    "sg:phone":"+1 765 423 2234",
    "sg:postcode":"47901",
    "sg:province":"IN",
    "sg:tags":[
        "food",
        "american",
        "pub"
    ],
    "wof:name":"Knickerbocker Saloon",
    "wof:placetype":"venue"
},
  "geometry": {"coordinates":[-86.891666,40.41842],"type":"Point"}
}