{
  "type": "Feature",
  "properties": {
    "iso:country":"US",
    "sg:address":"1107 Governors Ln",
    "sg:city":"Seymour",
    "sg:classifiers":[
        {
            "category":"Professional",
            "subcategory":"Business Services",
            "type":"Services"
        }
    ],
    "sg:phone":"+1 812 522 0656",
    "sg:postcode":"47274",
    "sg:province":"IN",
    "wof:name":"Vinson & Vinson Enterprises",
    "wof:placetype":"venue"
},
  "geometry": {"coordinates":[-85.906682,38.967023],"type":"Point"}
}