{
  "type": "Feature",
  "properties": {
    "iso:country":"US",
    "sg:address":"230 N Hart St",
    "sg:city":"Princeton",
    "sg:classifiers":[
        {
            "category":"Personal",
            "subcategory":"Barber",
            "type":"Services"
        }
    ],
    "sg:phone":"+1 812 386 6585",
    "sg:postcode":"47670",
    "sg:province":"IN",
    "wof:name":"Dean's Barber Shop",
    "wof:placetype":"venue"
},
  "geometry": {"coordinates":[-87.56867200000001,38.356431],"type":"Point"}
}