{
  "type": "Feature",
  "properties": {
    "iso:country":"US",
    "sg:address":"506 N Maine St",
    "sg:city":"Remington",
    "sg:classifiers":[
        {
            "category":"Retail",
            "subcategory":"Repair Shop",
            "type":"Services"
        }
    ],
    "sg:phone":"+1 219 261 3534",
    "sg:postcode":"47977",
    "sg:province":"IN",
    "sg:tags":[
        "water",
        "equipment",
        "softening"
    ],
    "wof:name":"Clear Water Systems Inc",
    "wof:placetype":"venue"
},
  "geometry": {"coordinates":[-87.153709,40.766853],"type":"Point"}
}