{
  "type": "Feature",
  "properties": {
    "iso:country":"US",
    "sg:address":"2222 E Markland Ave",
    "sg:city":"Kokomo",
    "sg:classifiers":[
        {
            "category":"Shopping",
            "subcategory":"Clothing, Apparel, & Fashions",
            "type":"Retail Goods"
        }
    ],
    "sg:phone":"+1 765 236 1358",
    "sg:postcode":"46901",
    "sg:province":"IN",
    "wof:name":"Clothes Closet",
    "wof:placetype":"venue"
},
  "geometry": {"coordinates":[-86.099732,40.47679],"type":"Point"}
}