{
  "type": "Feature",
  "properties": {
    "addr:full":"12449 US Hwy 41 Evansville IN 47725",
    "addr:housenumber":"12449",
    "addr:postcode":"47725",
    "addr:street":"Us Hwy 41",
    "iso:country":"US",
    "sg:address":"12449 US Hwy 41",
    "sg:city":"Evansville",
    "sg:classifiers":[
        {
            "category":"Government",
            "subcategory":"Office",
            "type":"Public Place"
        }
    ],
    "sg:phone":"+1 812 867 0582",
    "sg:postcode":"47725",
    "sg:province":"IN",
    "sg:tags":[
        "federal"
    ],
    "wof:name":"US Consolidated Farm Svc Agcy",
    "wof:placetype":"venue"
},
  "geometry": {"coordinates":[-87.55670000000001,38.088872],"type":"Point"}
}