{
  "type": "Feature",
  "properties": {
    "iso:country":"US",
    "sg:address":"217 SE Greenville Ave",
    "sg:city":"Winchester",
    "sg:classifiers":[
        {
            "category":"Food & Beverages",
            "subcategory":"Bakery",
            "type":"Retail Goods"
        }
    ],
    "sg:phone":"+1 765 584 8401",
    "sg:postcode":"47394",
    "sg:province":"IN",
    "sg:tags":[
        "pie"
    ],
    "sg:website":"www.wickspies.com",
    "wof:name":"Wick's Pies Inc",
    "wof:placetype":"venue"
},
  "geometry": {"coordinates":[-84.974788,40.171554],"type":"Point"}
}