{
  "type": "Feature",
  "properties": {
    "iso:country":"US",
    "sg:address":"8405 Harrison Dr",
    "sg:city":"Indianapolis",
    "sg:classifiers":[
        {
            "category":"Home & Garden",
            "subcategory":"Building Materials",
            "type":"Retail Goods"
        },
        {
            "category":"Building & Trades",
            "subcategory":"Construction",
            "type":"Services"
        }
    ],
    "sg:phone":"+1 317 547 3029",
    "sg:postcode":"46226",
    "sg:province":"IN",
    "sg:tags":[
        "concrete",
        "staining",
        "contractor"
    ],
    "wof:name":"Rodger Carman Concrete Sr",
    "wof:placetype":"venue"
},
  "geometry": {"coordinates":[-86.020241,39.845717],"type":"Point"}
}