{
  "type": "Feature",
  "properties": {
    "iso:country":"US",
    "sg:address":"117 N Main St",
    "sg:city":"Hebron",
    "sg:classifiers":[
        {
            "category":"Professional",
            "subcategory":"Management & Consulting",
            "type":"Services"
        }
    ],
    "sg:phone":"+1 219 996 5558",
    "sg:postcode":"46341",
    "sg:province":"IN",
    "sg:tags":[
        "marketing",
        "program"
    ],
    "wof:name":"Builders Resource",
    "wof:placetype":"venue"
},
  "geometry": {"coordinates":[-87.199907,41.319133],"type":"Point"}
}