{
  "type": "Feature",
  "properties": {
    "addr:full":"3301 Shiloh Rd SW Corydon IN 47112",
    "addr:housenumber":"3301",
    "addr:postcode":"47112",
    "addr:street":"Shiloh Rd Sw",
    "iso:country":"US",
    "sg:address":"3301 Shiloh Rd SW",
    "sg:city":"Corydon",
    "sg:classifiers":[
        {
            "category":"Retail",
            "subcategory":"Laundry & Dry Cleaning",
            "type":"Services"
        }
    ],
    "sg:phone":"+1 812 738 8913",
    "sg:postcode":"47112",
    "sg:province":"IN",
    "wof:name":"Duraclean By Russ",
    "wof:placetype":"venue"
},
  "geometry": {"coordinates":[-86.161385,38.151379],"type":"Point"}
}