{
  "type": "Feature",
  "properties": {
    "iso:country":"US",
    "sg:address":"2151 N New Jersey St",
    "sg:city":"Indianapolis",
    "sg:classifiers":[
        {
            "category":"Personal",
            "subcategory":"Barber",
            "type":"Services"
        }
    ],
    "sg:phone":"+1 317 923 0438",
    "sg:postcode":"46202",
    "sg:province":"IN",
    "wof:name":"Carol & Everybody's Barber Shp",
    "wof:placetype":"venue"
},
  "geometry": {"coordinates":[-86.150897,39.796595],"type":"Point"}
}