{
  "type": "Feature",
  "properties": {
    "addr:full":"8558 E 900 N Wilkinson IN 46186",
    "addr:housenumber":"8558",
    "addr:postcode":"46186",
    "addr:street":"E 900 N Wilkinson",
    "iso:country":"US",
    "sg:address":"8558 E 900 N",
    "sg:city":"Wilkinson",
    "sg:classifiers":[
        {
            "category":"Farming",
            "subcategory":"Farm",
            "type":"Manufacturing & Wholesale Goods"
        }
    ],
    "sg:phone":"+1 765 781 0003",
    "sg:postcode":"46186",
    "sg:province":"IN",
    "wof:name":"Simpson Farm",
    "wof:placetype":"venue"
},
  "geometry": {"coordinates":[-85.639351,39.916608],"type":"Point"}
}