{
  "type": "Feature",
  "properties": {
    "iso:country":"US",
    "sg:address":"1617 Montcalm St",
    "sg:city":"Indianapolis",
    "sg:classifiers":[
        {
            "category":"Organizations",
            "subcategory":"Religious Organization",
            "type":"Services"
        }
    ],
    "sg:phone":"+1 317 974 0388",
    "sg:postcode":"46202",
    "sg:province":"IN",
    "sg:tags":[
        "church"
    ],
    "wof:name":"God In Christ Apostolic Faith",
    "wof:placetype":"venue"
},
  "geometry": {"coordinates":[-86.180037,39.789785],"type":"Point"}
}