{
  "type": "Feature",
  "properties": {
    "iso:country":"US",
    "sg:address":"7660 US Hwy 31 S",
    "sg:city":"Indianapolis",
    "sg:classifiers":[
        {
            "category":"Professional",
            "subcategory":"Lawyer & Legal Services",
            "type":"Services"
        }
    ],
    "sg:phone":"+1 317 887 9600",
    "sg:postcode":"46227",
    "sg:province":"IN",
    "sg:tags":[
        "attorney"
    ],
    "wof:name":"Harshey Law Office",
    "wof:placetype":"venue"
},
  "geometry": {"coordinates":[-86.140542,39.655225],"type":"Point"}
}