{
  "type": "Feature",
  "properties": {
    "iso:country":"US",
    "sg:address":"220 E Washington Ave",
    "sg:city":"Hobart",
    "sg:classifiers":[
        {
            "category":"Retail",
            "subcategory":"Repair Shop",
            "type":"Services"
        }
    ],
    "sg:phone":"+1 219 962 2720",
    "sg:postcode":"46342",
    "sg:province":"IN",
    "sg:tags":[
        "plumbing",
        "drain",
        "cleaning",
        "sewer"
    ],
    "wof:name":"Quick Rod Electric Sewer",
    "wof:placetype":"venue"
},
  "geometry": {"coordinates":[-87.273274,41.556424],"type":"Point"}
}