{
  "type": "Feature",
  "properties": {
    "iso:country":"US",
    "sg:address":"49 W Maryland St",
    "sg:city":"Indianapolis",
    "sg:classifiers":[
        {
            "category":"Manufacturing",
            "subcategory":"Metals",
            "type":"Manufacturing & Wholesale Goods"
        }
    ],
    "sg:phone":"+1 317 638 0986",
    "sg:postcode":"46204",
    "sg:province":"IN",
    "sg:tags":[
        "engraver"
    ],
    "wof:name":"Laser Art",
    "wof:placetype":"venue"
},
  "geometry": {"coordinates":[-86.159267,39.765585],"type":"Point"}
}