{
  "type": "Feature",
  "properties": {
    "iso:country":"US",
    "sg:address":"95 S Main St",
    "sg:city":"Spencer",
    "sg:classifiers":[
        {
            "category":"Wholesale",
            "subcategory":"Chemicals & Plastics",
            "type":"Manufacturing & Wholesale Goods"
        }
    ],
    "sg:phone":"+1 812 829 4851",
    "sg:postcode":"47460",
    "sg:province":"IN",
    "sg:website":"www.medpoly.com",
    "wof:name":"Medical Polymers Inc",
    "wof:placetype":"venue"
},
  "geometry": {"coordinates":[-86.76243,39.285178],"type":"Point"}
}