{
  "type": "Feature",
  "properties": {
    "iso:country":"US",
    "sg:address":"9159 Nora Ln",
    "sg:city":"Indianapolis",
    "sg:classifiers":[
        {
            "category":"Manufacturing",
            "subcategory":"Printing",
            "type":"Manufacturing & Wholesale Goods"
        }
    ],
    "sg:phone":"+1 317 446 9960",
    "sg:postcode":"46240",
    "sg:province":"IN",
    "sg:tags":[
        "publisher",
        "software"
    ],
    "wof:name":"Inskeep & Assoc Inc",
    "wof:placetype":"venue"
},
  "geometry": {"coordinates":[-86.132265,39.921511],"type":"Point"}
}