{
  "type": "Feature",
  "properties": {
    "iso:country":"US",
    "sg:address":"509 S Canal St",
    "sg:city":"Covington",
    "sg:classifiers":[
        {
            "category":"Government",
            "subcategory":"Office",
            "type":"Public Place"
        }
    ],
    "sg:phone":"+1 765 793 2421",
    "sg:postcode":"47918",
    "sg:province":"IN",
    "sg:tags":[
        "village"
    ],
    "wof:name":"Covington Electric Dept",
    "wof:placetype":"venue"
},
  "geometry": {"coordinates":[-87.25403900000001,40.293828],"type":"Point"}
}