{
  "type": "Feature",
  "properties": {
    "addr:full":"52336 Ash Rd Granger IN 46530",
    "addr:housenumber":"52336",
    "addr:postcode":"46530",
    "addr:street":"Ash Rd",
    "iso:country":"US",
    "sg:address":"52336 Ash Rd",
    "sg:city":"Granger",
    "sg:classifiers":[
        {
            "category":"Professional",
            "type":"Services"
        }
    ],
    "sg:phone":"+1 574 232 7289",
    "sg:postcode":"46530",
    "sg:province":"IN",
    "sg:tags":[
        "establishment"
    ],
    "wof:name":"A T M's By Roller",
    "wof:placetype":"venue"
},
  "geometry": {"coordinates":[-86.062347,41.736143],"type":"Point"}
}