{
  "type": "Feature",
  "properties": {
    "iso:country":"US",
    "sg:address":"625 N Walnut St",
    "sg:city":"Bloomington",
    "sg:classifiers":[
        {
            "category":"Professional",
            "subcategory":"Accounting & Tax Preparation",
            "type":"Services"
        }
    ],
    "sg:phone":"+1 812 336 2415",
    "sg:postcode":"47404",
    "sg:province":"IN",
    "sg:tags":[
        "accountant"
    ],
    "wof:name":"L A Merry & Associates PC",
    "wof:placetype":"venue"
},
  "geometry": {"coordinates":[-86.533699,39.172001],"type":"Point"}
}