{
  "type": "Feature",
  "properties": {
    "iso:country":"US",
    "sg:address":"119 W Court Ave",
    "sg:city":"Jeffersonville",
    "sg:classifiers":[
        {
            "category":"Retail",
            "subcategory":"Laundry & Dry Cleaning",
            "type":"Services"
        }
    ],
    "sg:phone":"+1 812 282 3293",
    "sg:postcode":"47130",
    "sg:province":"IN",
    "sg:tags":[
        "cleaners"
    ],
    "wof:name":"Jeffersonville One Hr Cleaners",
    "wof:placetype":"venue"
},
  "geometry": {"coordinates":[-85.74326,38.273629],"type":"Point"}
}