{
  "type": "Feature",
  "properties": {
    "addr:full":"5650 Caito Dr Indianapolis IN 46226",
    "addr:housenumber":"5650",
    "addr:postcode":"46226",
    "addr:street":"Caito Dr",
    "iso:country":"US",
    "sg:address":"5650 Caito Dr",
    "sg:city":"Indianapolis",
    "sg:classifiers":[
        {
            "category":"Social Services",
            "type":"Services"
        }
    ],
    "sg:phone":"+1 317 568 1000",
    "sg:postcode":"46226",
    "sg:province":"IN",
    "sg:tags":[
        "agency",
        "adoption"
    ],
    "wof:name":"Bethany Christian Svc",
    "wof:placetype":"venue"
},
  "geometry": {"coordinates":[-86.041768,39.855894],"type":"Point"}
}