{
  "type": "Feature",
  "properties": {
    "iso:country":"US",
    "sg:address":"3986 Main St",
    "sg:city":"Richland",
    "sg:classifiers":[
        {
            "category":"Wholesale",
            "subcategory":"Non-durable Goods",
            "type":"Manufacturing & Wholesale Goods"
        }
    ],
    "sg:phone":"+1 812 359 5415",
    "sg:postcode":"47634",
    "sg:province":"IN",
    "sg:tags":[
        "novelty"
    ],
    "wof:name":"DES Enterprises",
    "wof:placetype":"venue"
},
  "geometry": {"coordinates":[-87.168415,37.944196],"type":"Point"}
}