{
  "type": "Feature",
  "properties": {
    "addr:full":"5977 E 82nd St Indianapolis IN 46250",
    "addr:housenumber":"5977",
    "addr:postcode":"46250",
    "addr:street":"E 82Nd St",
    "iso:country":"US",
    "sg:address":"5977 E 82nd St",
    "sg:city":"Indianapolis",
    "sg:classifiers":[
        {
            "category":"Manufacturing",
            "subcategory":"Metals",
            "type":"Manufacturing & Wholesale Goods"
        }
    ],
    "sg:phone":"+1 317 849 2340",
    "sg:postcode":"46250",
    "sg:province":"IN",
    "sg:tags":[
        "coating"
    ],
    "wof:name":"PPG Porter Paints",
    "wof:placetype":"venue"
},
  "geometry": {"coordinates":[-86.066371,39.905178],"type":"Point"}
}