{
  "type": "Feature",
  "properties": {
    "iso:country":"US",
    "sg:address":"2519 E 65th St",
    "sg:city":"Indianapolis",
    "sg:classifiers":[
        {
            "category":"Insurance",
            "subcategory":"Insurance Agent",
            "type":"Services"
        }
    ],
    "sg:phone":"+1 317 251 1400",
    "sg:postcode":"46220",
    "sg:province":"IN",
    "wof:name":"State Farm Insurance",
    "wof:placetype":"venue"
},
  "geometry": {"coordinates":[-86.11994900000001,39.875903],"type":"Point"}
}