{
  "type": "Feature",
  "properties": {
    "iso:country":"US",
    "sg:address":"230 W Ottawa St",
    "sg:city":"Logansport",
    "sg:classifiers":[
        {
            "category":"Social Services",
            "subcategory":"Child Care",
            "type":"Services"
        }
    ],
    "sg:phone":"+1 574 722 5114",
    "sg:postcode":"46947",
    "sg:province":"IN",
    "sg:tags":[
        "day",
        "provider"
    ],
    "wof:name":"Cindys Child Care",
    "wof:placetype":"venue"
},
  "geometry": {"coordinates":[-86.37374800000001,40.757162],"type":"Point"}
}