{
  "type": "Feature",
  "properties": {
    "iso:country":"US",
    "sg:address":"800 S McDonald St",
    "sg:city":"Attica",
    "sg:classifiers":[
        {
            "category":"Building & Trades",
            "subcategory":"Construction",
            "type":"Services"
        }
    ],
    "sg:phone":"+1 765 762 3598",
    "sg:postcode":"47918",
    "sg:province":"IN",
    "sg:tags":[
        "contractor"
    ],
    "wof:name":"Pierce Drywall Plaster & Pain",
    "wof:placetype":"venue"
},
  "geometry": {"coordinates":[-87.249808,40.285478],"type":"Point"}
}