{
  "type": "Feature",
  "properties": {
    "iso:country":"US",
    "sg:address":"120 Main St",
    "sg:city":"Rising Sun",
    "sg:classifiers":[
        {
            "category":"Shopping",
            "subcategory":"Musical Instruments",
            "type":"Retail Goods"
        }
    ],
    "sg:phone":"+1 812 438 3715",
    "sg:postcode":"47040",
    "sg:province":"IN",
    "sg:tags":[
        "music",
        "dealer"
    ],
    "wof:name":"Zeiler Music Ctr",
    "wof:placetype":"venue"
},
  "geometry": {"coordinates":[-84.851544,38.947867],"type":"Point"}
}