{
  "type": "Feature",
  "properties": {
    "iso:country":"US",
    "sg:address":"2310 W Southport Rd",
    "sg:city":"Indianapolis",
    "sg:classifiers":[
        {
            "category":"Personal",
            "type":"Services"
        }
    ],
    "sg:phone":"+1 317 888 9485",
    "sg:postcode":"46217",
    "sg:province":"IN",
    "sg:tags":[
        "consultant",
        "program",
        "health",
        "fitness"
    ],
    "wof:name":"Ladies Workout Express",
    "wof:placetype":"venue"
},
  "geometry": {"coordinates":[-86.197947,39.663678],"type":"Point"}
}