{
  "type": "Feature",
  "properties": {
    "iso:country":"US",
    "sg:address":"5661 Hodgin Rd",
    "sg:city":"Richmond",
    "sg:classifiers":[
        {
            "category":"Building & Trades",
            "subcategory":"Landscaping Services",
            "type":"Services"
        }
    ],
    "sg:phone":"+1 765 966 8722",
    "sg:postcode":"47374",
    "sg:province":"IN",
    "wof:name":"Timothy Newman",
    "wof:placetype":"venue"
},
  "geometry": {"coordinates":[-84.827596,39.81414],"type":"Point"}
}