{
  "type": "Feature",
  "properties": {
    "iso:country":"US",
    "sg:address":"8129 Retreat Ln",
    "sg:city":"Indianapolis",
    "sg:classifiers":[
        {
            "category":"Building & Trades",
            "subcategory":"Landscaping Services",
            "type":"Services"
        },
        {
            "category":"Professional",
            "subcategory":"Employment Agencies",
            "type":"Services"
        },
        {
            "category":"Home & Garden",
            "subcategory":"Building Materials",
            "type":"Retail Goods"
        },
        {
            "category":"Building & Trades",
            "subcategory":"Construction",
            "type":"Services"
        },
        {
            "category":"Sports & Exercise",
            "subcategory":"Swimming Pool",
            "type":"Entertainment"
        }
    ],
    "sg:phone":"+1 317 650 5131",
    "sg:postcode":"46259",
    "sg:province":"IN",
    "sg:tags":[
        "repair",
        "consulting",
        "trenching",
        "excavation",
        "builder",
        "cover",
        "contractor",
        "concrete",
        "landscape",
        "designing",
        "underground",
        "enclosure",
        "patio"
    ],
    "sg:website":"http://www.mudslingersinc.com",
    "wof:name":"Mud Slingers Pool & Patio",
    "wof:placetype":"venue"
},
  "geometry": {"coordinates":[-85.97884999999999,39.652015],"type":"Point"}
}