{
  "type": "Feature",
  "properties": {
    "iso:country":"US",
    "sg:address":"215 W Main St",
    "sg:city":"Monrovia",
    "sg:classifiers":[
        {
            "category":"Shopping",
            "subcategory":"Music",
            "type":"Retail Goods"
        }
    ],
    "sg:phone":"+1 317 996 2255",
    "sg:postcode":"46157",
    "sg:province":"IN",
    "sg:tags":[
        "video",
        "disc",
        "tape",
        "cassette"
    ],
    "wof:name":"Rewinds Video Inc",
    "wof:placetype":"venue"
},
  "geometry": {"coordinates":[-86.483011,39.578779],"type":"Point"}
}