{
  "type": "Feature",
  "properties": {
    "iso:country":"US",
    "sg:address":"7950 N Shadeland Ave Ste 400",
    "sg:city":"Indianapolis",
    "sg:classifiers":[
        {
            "category":"Health Services",
            "subcategory":"Dentist",
            "type":"Services"
        }
    ],
    "sg:phone":"+1 317 849 9961",
    "sg:postcode":"46250",
    "sg:province":"IN",
    "sg:tags":[
        "product",
        "dentistry",
        "whitening",
        "dentists-cosmetic",
        "teeth"
    ],
    "sg:website":"www.perfectsmilesin.com",
    "wof:name":"Davidson Danielle DDS",
    "wof:placetype":"venue"
},
  "geometry": {"coordinates":[-86.046269,39.899339],"type":"Point"}
}