{
  "type": "Feature",
  "properties": {
    "iso:country":"US",
    "sg:address":"9630 Shelborne Rd",
    "sg:city":"Carmel",
    "sg:classifiers":[
        {
            "category":"Professional",
            "subcategory":"Management & Consulting",
            "type":"Services"
        }
    ],
    "sg:phone":"+1 317 415 0274",
    "sg:postcode":"46032",
    "sg:province":"IN",
    "sg:tags":[
        "consultant",
        "business"
    ],
    "wof:name":"Mickler & Assoc Inc",
    "wof:placetype":"venue"
},
  "geometry": {"coordinates":[-86.222363,39.926727],"type":"Point"}
}