{
  "type": "Feature",
  "properties": {
    "iso:country":"US",
    "sg:address":"205 E Palmer St",
    "sg:city":"Indianapolis",
    "sg:classifiers":[
        {
            "category":"Building & Trades",
            "subcategory":"Equipment Rental",
            "type":"Services"
        }
    ],
    "sg:phone":"+1 317 632 7226",
    "sg:postcode":"46225",
    "sg:province":"IN",
    "sg:tags":[
        "tents-rental",
        "camping",
        "tent"
    ],
    "sg:website":"http://www.americantentandawning.com",
    "wof:name":"American Tent & Awning Co Inc",
    "wof:placetype":"venue"
},
  "geometry": {"coordinates":[-86.155173,39.746071],"type":"Point"}
}