{
  "type": "Feature",
  "properties": {
    "addr:full":"20 S Indiana St Mooresville IN 46158",
    "addr:housenumber":"20",
    "addr:postcode":"46158",
    "addr:street":"S Indiana St",
    "iso:country":"US",
    "sg:address":"20 S Indiana St",
    "sg:city":"Mooresville",
    "sg:classifiers":[
        {
            "category":"Social Services",
            "type":"Services"
        }
    ],
    "sg:phone":"+1 317 831 9764",
    "sg:postcode":"46158",
    "sg:province":"IN",
    "sg:tags":[
        "counselor",
        "marriage",
        "family"
    ],
    "wof:name":"Counseling Services",
    "wof:placetype":"venue"
},
  "geometry": {"coordinates":[-86.37500199999999,39.611982],"type":"Point"}
}