{
  "type": "Feature",
  "properties": {
    "iso:country":"US",
    "sg:address":"18751 Turkey Point Rd",
    "sg:city":"Guilford",
    "sg:classifiers":[
        {
            "category":"Building & Trades",
            "subcategory":"Electrical",
            "type":"Services"
        }
    ],
    "sg:phone":"+1 812 926 9315",
    "sg:postcode":"47022",
    "sg:province":"IN",
    "sg:tags":[
        "electrical",
        "contractor"
    ],
    "wof:name":"Electrical Services & Supplies",
    "wof:placetype":"venue"
},
  "geometry": {"coordinates":[-84.986034,39.141364],"type":"Point"}
}