{
  "type": "Feature",
  "properties": {
    "iso:country":"US",
    "sg:address":"249 S Main St",
    "sg:city":"Clinton",
    "sg:classifiers":[
        {
            "category":"Home & Garden",
            "subcategory":"Hardware",
            "type":"Retail Goods"
        }
    ],
    "sg:phone":"+1 765 832 8550",
    "sg:postcode":"47842",
    "sg:province":"IN",
    "wof:name":"Horney's True Value Hardware",
    "wof:placetype":"venue"
},
  "geometry": {"coordinates":[-87.398368,39.658819],"type":"Point"}
}