{
  "type": "Feature",
  "properties": {
    "iso:country":"US",
    "sg:address":"1511 Milburn Blvd",
    "sg:city":"Mishawaka",
    "sg:classifiers":[
        {
            "category":"Organizations",
            "subcategory":"Professional Association",
            "type":"Services"
        }
    ],
    "sg:phone":"+1 574 255 1966",
    "sg:postcode":"46544",
    "sg:province":"IN",
    "wof:name":"Mishawaka Education Assoc",
    "wof:placetype":"venue"
},
  "geometry": {"coordinates":[-86.198739,41.655244],"type":"Point"}
}