{
  "type": "Feature",
  "properties": {
    "iso:country":"US",
    "sg:address":"608 Gerald Dr",
    "sg:city":"Clarksville",
    "sg:classifiers":[
        {
            "category":"Professional",
            "subcategory":"Lawyer & Legal Services",
            "type":"Services"
        }
    ],
    "sg:phone":"+1 812 288 0783",
    "sg:postcode":"47129",
    "sg:province":"IN",
    "sg:tags":[
        "attorney"
    ],
    "wof:name":"Samuel K Gwin",
    "wof:placetype":"venue"
},
  "geometry": {"coordinates":[-85.761927,38.309385],"type":"Point"}
}