{
  "type": "Feature",
  "properties": {
    "iso:country":"US",
    "sg:address":"309 Medic Way",
    "sg:city":"Greencastle",
    "sg:classifiers":[
        {
            "category":"Health Services",
            "subcategory":"Doctor",
            "type":"Services"
        }
    ],
    "sg:phone":"+1 765 653 2626",
    "sg:postcode":"46135",
    "sg:province":"IN",
    "sg:tags":[
        "physician",
        "surgeon"
    ],
    "wof:name":"Putnam Family Health Care Inc",
    "wof:placetype":"venue"
},
  "geometry": {"coordinates":[-86.849355,39.618948],"type":"Point"}
}