{
  "type": "Feature",
  "properties": {
    "addr:full":"6650 Page Blvd Indianapolis IN 46220",
    "addr:housenumber":"6650",
    "addr:postcode":"46220",
    "addr:street":"Page Blvd",
    "iso:country":"US",
    "sg:address":"6650 Page Blvd",
    "sg:city":"Indianapolis",
    "sg:classifiers":[
        {
            "category":"Manufacturing",
            "subcategory":"Tools & Machinery",
            "type":"Manufacturing & Wholesale Goods"
        }
    ],
    "sg:phone":"+1 317 253 9916",
    "sg:postcode":"46220",
    "sg:province":"IN",
    "sg:tags":[
        "machine"
    ],
    "wof:name":"Fabrication Equip. Sales Inc.",
    "wof:placetype":"venue"
},
  "geometry": {"coordinates":[-86.13405899999999,39.877345],"type":"Point"}
}