{
  "type": "Feature",
  "properties": {
    "iso:country":"US",
    "sg:address":"52025 Gumwood Rd",
    "sg:city":"Granger",
    "sg:classifiers":[
        {
            "category":"Education",
            "subcategory":"Special Training",
            "type":"Public Place"
        }
    ],
    "sg:phone":"+1 574 273 3032",
    "sg:postcode":"46530",
    "sg:province":"IN",
    "sg:tags":[
        "tutoring"
    ],
    "wof:name":"Kumon Math & Reading Ctr",
    "wof:placetype":"venue"
},
  "geometry": {"coordinates":[-86.178371,41.733922],"type":"Point"}
}