{
  "type": "Feature",
  "properties": {
    "iso:country":"US",
    "sg:address":"3966 Tyler St",
    "sg:city":"Gary",
    "sg:classifiers":[
        {
            "category":"Wholesale",
            "subcategory":"Groceries",
            "type":"Manufacturing & Wholesale Goods"
        }
    ],
    "sg:phone":"+1 219 985 0828",
    "sg:postcode":"46408",
    "sg:province":"IN",
    "sg:tags":[
        "food",
        "distributor",
        "snack"
    ],
    "wof:name":"Y E S Distributors",
    "wof:placetype":"venue"
},
  "geometry": {"coordinates":[-87.34741099999999,41.546238],"type":"Point"}
}