{
  "type": "Feature",
  "properties": {
    "iso:country":"US",
    "sg:address":"1257 Lafayette Ave",
    "sg:city":"Terre Haute",
    "sg:classifiers":[
        {
            "category":"Arts & Performance",
            "subcategory":"Theater",
            "type":"Entertainment"
        }
    ],
    "sg:phone":"+1 812 232 4926",
    "sg:postcode":"47804",
    "sg:province":"IN",
    "sg:tags":[
        "group"
    ],
    "wof:name":"Harmony Hall",
    "wof:placetype":"venue"
},
  "geometry": {"coordinates":[-87.398999,39.491216],"type":"Point"}
}