{
  "type": "Feature",
  "properties": {
    "iso:country":"US",
    "sg:address":"113 W Main St",
    "sg:city":"Greenfield",
    "sg:classifiers":[
        {
            "category":"Home & Garden",
            "subcategory":"Home Furnishings",
            "type":"Retail Goods"
        }
    ],
    "sg:phone":"+1 317 462 6386",
    "sg:postcode":"46140",
    "sg:province":"IN",
    "sg:tags":[
        "curtain",
        "made",
        "drapery"
    ],
    "wof:name":"Curtain Creations & Gift Shop",
    "wof:placetype":"venue"
},
  "geometry": {"coordinates":[-85.770262,39.785084],"type":"Point"}
}