{
  "type": "Feature",
  "properties": {
    "iso:country":"US",
    "sg:address":"8836 W State Rd 64",
    "sg:city":"Huntingburg",
    "sg:classifiers":[
        {
            "category":"Manufacturing",
            "subcategory":"Lumber",
            "type":"Manufacturing & Wholesale Goods"
        }
    ],
    "sg:phone":"+1 812 536 2171",
    "sg:postcode":"47542",
    "sg:province":"IN",
    "sg:tags":[
        "sawmill"
    ],
    "wof:name":"C & L Lumber",
    "wof:placetype":"venue"
},
  "geometry": {"coordinates":[-87.072447,38.303811],"type":"Point"}
}