{
  "type": "Feature",
  "properties": {
    "iso:country":"US",
    "sg:address":"8902 E 35th St",
    "sg:city":"Indianapolis",
    "sg:classifiers":[
        {
            "category":"Organizations",
            "subcategory":"Community Association",
            "type":"Services"
        }
    ],
    "sg:phone":"+1 317 899 2755",
    "sg:postcode":"46226",
    "sg:province":"IN",
    "wof:name":"Order of Eastrn Star Bch Grove",
    "wof:placetype":"venue"
},
  "geometry": {"coordinates":[-86.012087,39.820563],"type":"Point"}
}