{
  "type": "Feature",
  "properties": {
    "iso:country":"US",
    "sg:address":"4358 W 300 S",
    "sg:city":"Marion",
    "sg:classifiers":[
        {
            "category":"Farming",
            "subcategory":"Livestock Farm",
            "type":"Manufacturing & Wholesale Goods"
        }
    ],
    "sg:phone":"+1 765 384 7586",
    "sg:postcode":"46953",
    "sg:province":"IN",
    "sg:tags":[
        "beef",
        "feedlot",
        "cattle"
    ],
    "wof:name":"Barry Key",
    "wof:placetype":"venue"
},
  "geometry": {"coordinates":[-85.754995,40.509048],"type":"Point"}
}