{
  "type": "Feature",
  "properties": {
    "iso:country":"US",
    "sg:address":"4506 E Co Rd 500 S",
    "sg:city":"Greensburg",
    "sg:phone":"+1 812 663 7296",
    "sg:postcode":"47240",
    "sg:province":"IN",
    "sg:tags":[
        "farm",
        "field",
        "corn",
        "soybean",
        "crop"
    ],
    "wof:name":"Mike Spreckelson Farm",
    "wof:placetype":"venue"
},
  "geometry": {"coordinates":[-85.39532800000001,39.263838],"type":"Point"}
}