{
  "type": "Feature",
  "properties": {
    "iso:country":"US",
    "sg:address":"3140 E Pontiac St",
    "sg:city":"Fort Wayne",
    "sg:classifiers":[
        {
            "category":"Wholesale",
            "subcategory":"Metals & Minerals",
            "type":"Manufacturing & Wholesale Goods"
        }
    ],
    "sg:phone":"+1 260 420 3333",
    "sg:postcode":"46803",
    "sg:province":"IN",
    "sg:tags":[
        "pipe"
    ],
    "wof:name":"Mid-States Pipe & Supply Co",
    "wof:placetype":"venue"
},
  "geometry": {"coordinates":[-85.097089,41.061412],"type":"Point"}
}