{
  "type": "Feature",
  "properties": {
    "iso:country":"US",
    "sg:address":"4049 Millersville Rd",
    "sg:city":"Indianapolis",
    "sg:classifiers":[
        {
            "category":"Building & Trades",
            "subcategory":"Cleaning & Sanitation",
            "type":"Services"
        }
    ],
    "sg:phone":"+1 317 542 8444",
    "sg:postcode":"46205",
    "sg:province":"IN",
    "sg:tags":[
        "filter"
    ],
    "wof:name":"Clean Air Svc Inc",
    "wof:placetype":"venue"
},
  "geometry": {"coordinates":[-86.126398,39.82866],"type":"Point"}
}