{
  "type": "Feature",
  "properties": {
    "iso:country":"US",
    "sg:address":"607 W Franklin St",
    "sg:city":"Berne",
    "sg:classifiers":[
        {
            "category":"Autos & Motor Vehicles",
            "subcategory":"Auto Supplies",
            "type":"Retail Goods"
        }
    ],
    "sg:phone":"+1 260 589 3104",
    "sg:postcode":"46711",
    "sg:province":"IN",
    "sg:tags":[
        "automobile",
        "parts"
    ],
    "wof:name":"Grimm's Auto Svc",
    "wof:placetype":"venue"
},
  "geometry": {"coordinates":[-84.957263,40.656817],"type":"Point"}
}