{
  "type": "Feature",
  "properties": {
    "iso:country":"US",
    "sg:address":"2000 E State St",
    "sg:city":"Huntington",
    "sg:classifiers":[
        {
            "category":"Bars & Pubs",
            "type":"Food & Drink"
        }
    ],
    "sg:phone":"+1 260 356 3052",
    "sg:postcode":"46750",
    "sg:province":"IN",
    "wof:name":"Boondocks",
    "wof:placetype":"venue"
},
  "geometry": {"coordinates":[-85.469984,40.882093],"type":"Point"}
}