{
  "type": "Feature",
  "properties": {
    "iso:country":"US",
    "sg:address":"406 S Maple St",
    "sg:city":"Fortville",
    "sg:classifiers":[
        {
            "category":"Personal",
            "subcategory":"Beauty Salon",
            "type":"Services"
        }
    ],
    "sg:phone":"+1 317 485 7444",
    "sg:postcode":"46040",
    "sg:province":"IN",
    "wof:name":"Lords & Ladies Hair Studio",
    "wof:placetype":"venue"
},
  "geometry": {"coordinates":[-85.848004,39.93127],"type":"Point"}
}