{
  "type": "Feature",
  "properties": {
    "iso:country":"US",
    "sg:address":"17 E Co Rd 350 N",
    "sg:city":"Greencastle",
    "sg:classifiers":[
        {
            "category":"Building & Trades",
            "subcategory":"Construction",
            "type":"Services"
        }
    ],
    "sg:phone":"+1 765 653 6735",
    "sg:postcode":"46135",
    "sg:province":"IN",
    "sg:tags":[
        "water",
        "well",
        "drilling"
    ],
    "wof:name":"Scobee Well Drilling",
    "wof:placetype":"venue"
},
  "geometry": {"coordinates":[-86.848299,39.711324],"type":"Point"}
}