{
  "type": "Feature",
  "properties": {
    "iso:country":"US",
    "sg:address":"901 S Gardener St",
    "sg:city":"Scottsburg",
    "sg:classifiers":[
        {
            "category":"Retail",
            "subcategory":"Repair Shop",
            "type":"Services"
        }
    ],
    "sg:phone":"+1 812 752 3172",
    "sg:postcode":"47170",
    "sg:province":"IN",
    "sg:tags":[
        "farm",
        "equipment",
        "parts"
    ],
    "wof:name":"Wells-Deal Ag & Outdoor Power",
    "wof:placetype":"venue"
},
  "geometry": {"coordinates":[-85.777231,38.673203],"type":"Point"}
}