{
  "type": "Feature",
  "properties": {
    "iso:country":"US",
    "sg:address":"4934 Brock St",
    "sg:city":"Indianapolis",
    "sg:classifiers":[
        {
            "category":"Shopping",
            "subcategory":"Gifts & Souvenirs",
            "type":"Retail Goods"
        }
    ],
    "sg:phone":"+1 317 291 2142",
    "sg:postcode":"46254",
    "sg:province":"IN",
    "wof:name":"Gods Perfect Gifts Inc",
    "wof:placetype":"venue"
},
  "geometry": {"coordinates":[-86.243649,39.844647],"type":"Point"}
}