{
  "type": "Feature",
  "properties": {
    "iso:country":"US",
    "sg:address":"122 E Rudisill Blvd",
    "sg:city":"Fort Wayne",
    "sg:classifiers":[
        {
            "category":"Shopping",
            "type":"Retail Goods"
        }
    ],
    "sg:phone":"+1 260 458 8100",
    "sg:postcode":"46806",
    "sg:province":"IN",
    "sg:tags":[
        "telephone",
        "cellular"
    ],
    "wof:name":"Wireless Toyz",
    "wof:placetype":"venue"
},
  "geometry": {"coordinates":[-85.13634,41.050011],"type":"Point"}
}