{
  "type": "Feature",
  "properties": {
    "iso:country":"US",
    "sg:address":"396 W Jefferson St",
    "sg:city":"Franklin",
    "sg:classifiers":[
        {
            "category":"Retail",
            "subcategory":"Repair Shop",
            "type":"Services"
        }
    ],
    "sg:phone":"+1 317 738 3003",
    "sg:postcode":"46131",
    "sg:province":"IN",
    "sg:tags":[
        "lock",
        "locksmith"
    ],
    "wof:name":"Bob's Entry Svc",
    "wof:placetype":"venue"
},
  "geometry": {"coordinates":[-86.060378,39.480386],"type":"Point"}
}