{
  "type": "Feature",
  "properties": {
    "addr:full":"10 W 8th St Anderson IN 46016",
    "addr:housenumber":"10",
    "addr:postcode":"46016",
    "addr:street":"W 8Th St",
    "iso:country":"US",
    "sg:address":"10 W 8th St",
    "sg:city":"Anderson",
    "sg:classifiers":[
        {
            "category":"Organizations",
            "subcategory":"Political Organization",
            "type":"Services"
        }
    ],
    "sg:phone":"+1 765 608 1840",
    "sg:postcode":"46016",
    "sg:province":"IN",
    "wof:name":"Penpac",
    "wof:placetype":"venue"
},
  "geometry": {"coordinates":[-85.68046099999999,40.107963],"type":"Point"}
}