{
  "type": "Feature",
  "properties": {
    "iso:country":"US",
    "sg:address":"923 N Lynhurst Dr",
    "sg:city":"Indianapolis",
    "sg:classifiers":[
        {
            "category":"Home & Garden",
            "subcategory":"Garden Supply",
            "type":"Retail Goods"
        }
    ],
    "sg:phone":"+1 317 244 9747",
    "sg:postcode":"46224",
    "sg:province":"IN",
    "sg:tags":[
        "lawn",
        "mower"
    ],
    "wof:name":"Mower Zone",
    "wof:placetype":"venue"
},
  "geometry": {"coordinates":[-86.250517,39.779611],"type":"Point"}
}