{
  "type": "Feature",
  "properties": {
    "iso:country":"US",
    "sg:address":"1006 W York Rd",
    "sg:city":"Austin",
    "sg:classifiers":[
        {
            "category":"Retail",
            "subcategory":"Auto Repair",
            "type":"Services"
        }
    ],
    "sg:phone":"+1 812 794 2515",
    "sg:postcode":"47102",
    "sg:province":"IN",
    "sg:tags":[
        "body",
        "automobile",
        "painting"
    ],
    "wof:name":"Marty's Auto Body",
    "wof:placetype":"venue"
},
  "geometry": {"coordinates":[-85.81849800000001,38.73586],"type":"Point"}
}