{
  "type": "Feature",
  "properties": {
    "iso:country":"US",
    "sg:address":"5341 N Keystone Ave",
    "sg:city":"Indianapolis",
    "sg:classifiers":[
        {
            "category":"Restaurant",
            "type":"Food & Drink"
        }
    ],
    "sg:phone":"+1 317 251 3381",
    "sg:postcode":"46220",
    "sg:province":"IN",
    "wof:name":"Sharks Fish & Chicken",
    "wof:placetype":"venue"
},
  "geometry": {"coordinates":[-86.121992,39.849756],"type":"Point"}
}