{
  "type": "Feature",
  "properties": {
    "iso:country":"US",
    "sg:address":"4401 S Michigan St",
    "sg:city":"South Bend",
    "sg:classifiers":[
        {
            "category":"Food & Beverages",
            "subcategory":"Liquor & Beverages",
            "type":"Retail Goods"
        }
    ],
    "sg:phone":"+1 574 291 2600",
    "sg:postcode":"46614",
    "sg:province":"IN",
    "wof:name":"Landmark Liquor",
    "wof:placetype":"venue"
},
  "geometry": {"coordinates":[-86.251035,41.628982],"type":"Point"}
}