{
  "type": "Feature",
  "properties": {
    "iso:country":"US",
    "sg:address":"1904 S Market St",
    "sg:city":"Kokomo",
    "sg:classifiers":[
        {
            "category":"Wholesale",
            "subcategory":"Construction Materials",
            "type":"Manufacturing & Wholesale Goods"
        }
    ],
    "sg:phone":"+1 765 453 2279",
    "sg:postcode":"46902",
    "sg:province":"IN",
    "sg:tags":[
        "fence"
    ],
    "wof:name":"Ideal Decks & Fencing",
    "wof:placetype":"venue"
},
  "geometry": {"coordinates":[-86.128367,40.463443],"type":"Point"}
}