{
  "type": "Feature",
  "properties": {
    "iso:country":"US",
    "sg:address":"3044 E Middle Fork Ct",
    "sg:city":"Salem",
    "sg:classifiers":[
        {
            "category":"Social Services",
            "subcategory":"Child Care",
            "type":"Services"
        }
    ],
    "sg:phone":"+1 812 883 7177",
    "sg:postcode":"47167",
    "sg:province":"IN",
    "wof:name":"Little Angels Daycare",
    "wof:placetype":"venue"
},
  "geometry": {"coordinates":[-86.031473,38.558192],"type":"Point"}
}