{
  "type": "Feature",
  "properties": {
    "iso:country":"US",
    "sg:address":"1610 N Delaware St",
    "sg:city":"Indianapolis",
    "sg:classifiers":[
        {
            "category":"Building & Trades",
            "subcategory":"Construction",
            "type":"Services"
        }
    ],
    "sg:phone":"+1 317 339 5399",
    "sg:postcode":"46202",
    "sg:province":"IN",
    "sg:tags":[
        "house"
    ],
    "wof:name":"Mullin Remodeling Inc",
    "wof:placetype":"venue"
},
  "geometry": {"coordinates":[-86.153779,39.789956],"type":"Point"}
}