{
  "type": "Feature",
  "properties": {
    "iso:country":"US",
    "sg:address":"6810 River Haze Rd",
    "sg:city":"Fort Wayne",
    "sg:classifiers":[
        {
            "category":"Banks & Credit Unions",
            "subcategory":"Financial Services",
            "type":"Services"
        }
    ],
    "sg:phone":"+1 260 747 9424",
    "sg:postcode":"46819",
    "sg:province":"IN",
    "sg:tags":[
        "trust",
        "nonprofit",
        "management"
    ],
    "wof:name":"Walb Heller Family Foundation",
    "wof:placetype":"venue"
},
  "geometry": {"coordinates":[-85.144441,41.02105],"type":"Point"}
}