{
  "type": "Feature",
  "properties": {
    "iso:country":"US",
    "sg:address":"4515 N State Rd 101",
    "sg:city":"Decatur",
    "sg:classifiers":[
        {
            "category":"Organizations",
            "subcategory":"Religious Organization",
            "type":"Services"
        }
    ],
    "sg:phone":"+1 260 592 7722",
    "sg:postcode":"46733",
    "sg:province":"IN",
    "sg:tags":[
        "church"
    ],
    "wof:name":"Mt Zion United Brethren Church",
    "wof:placetype":"venue"
},
  "geometry": {"coordinates":[-84.841569,40.817622],"type":"Point"}
}