{
  "type": "Feature",
  "properties": {
    "iso:country":"US",
    "sg:address":"7445 E 400 S",
    "sg:city":"Wolcottville",
    "sg:classifiers":[
        {
            "category":"Wholesale",
            "subcategory":"Construction Materials",
            "type":"Manufacturing & Wholesale Goods"
        }
    ],
    "sg:phone":"+1 260 351 4393",
    "sg:postcode":"46795",
    "sg:province":"IN",
    "sg:tags":[
        "sand",
        "gravel"
    ],
    "wof:name":"Irving Gravel Co",
    "wof:placetype":"venue"
},
  "geometry": {"coordinates":[-85.284878,41.58517],"type":"Point"}
}