{
  "type": "Feature",
  "properties": {
    "iso:country":"US",
    "sg:address":"234 S Meridian St",
    "sg:city":"Indianapolis",
    "sg:classifiers":[
        {
            "category":"Restaurant",
            "type":"Food & Drink"
        }
    ],
    "sg:phone":"+1 317 822 6274",
    "sg:postcode":"46225",
    "sg:province":"IN",
    "sg:website":"www.claddaghirishpubs.com",
    "wof:name":"Claddagh Irish Pub",
    "wof:placetype":"venue"
},
  "geometry": {"coordinates":[-86.158317,39.763011],"type":"Point"}
}