{
  "type": "Feature",
  "properties": {
    "iso:country":"US",
    "sg:address":"7020 Cline Ave",
    "sg:city":"Hammond",
    "sg:classifiers":[
        {
            "category":"Wholesale",
            "subcategory":"Construction Materials",
            "type":"Manufacturing & Wholesale Goods"
        }
    ],
    "sg:phone":"+1 219 844 5828",
    "sg:postcode":"46323",
    "sg:province":"IN",
    "sg:tags":[
        "sand",
        "gravel"
    ],
    "wof:name":"Indiana Material Transfer Inc",
    "wof:placetype":"venue"
},
  "geometry": {"coordinates":[-87.43291499999999,41.584676],"type":"Point"}
}