{
  "type": "Feature",
  "properties": {
    "iso:country":"US",
    "sg:address":"210 N Middleboro Ave",
    "sg:city":"Mishawaka",
    "sg:classifiers":[
        {
            "category":"Building & Trades",
            "subcategory":"Construction",
            "type":"Services"
        }
    ],
    "sg:phone":"+1 574 256 2763",
    "sg:postcode":"46544",
    "sg:province":"IN",
    "sg:tags":[
        "house"
    ],
    "wof:name":"Deal Construction Inc",
    "wof:placetype":"venue"
},
  "geometry": {"coordinates":[-86.21319,41.659147],"type":"Point"}
}