{
  "type": "Feature",
  "properties": {
    "iso:country":"US",
    "sg:address":"3534 Commerce Dr",
    "sg:city":"Warsaw",
    "sg:classifiers":[
        {
            "category":"Professional",
            "subcategory":"Employment Agencies",
            "type":"Services"
        }
    ],
    "sg:phone":"+1 574 269 5627",
    "sg:postcode":"46580",
    "sg:province":"IN",
    "sg:tags":[
        "help",
        "contractor"
    ],
    "wof:name":"Staffmark",
    "wof:placetype":"venue"
},
  "geometry": {"coordinates":[-85.80638,41.233204],"type":"Point"}
}