{
  "type": "Feature",
  "properties": {
    "addr:full":"3450 S Spiceland Rd New Castle IN 47362",
    "addr:housenumber":"3450",
    "addr:postcode":"47362",
    "addr:street":"S Spiceland Rd New",
    "iso:country":"US",
    "sg:address":"3450 S Spiceland Rd",
    "sg:city":"New Castle",
    "sg:classifiers":[
        {
            "category":"Utilities",
            "subcategory":"Refuse",
            "type":"Services"
        }
    ],
    "sg:phone":"+1 765 529 2337",
    "sg:postcode":"47362",
    "sg:province":"IN",
    "sg:tags":[
        "garbage",
        "collection"
    ],
    "sg:website":"www.hayescompany.com",
    "wof:name":"Big B Rubbish Removal",
    "wof:placetype":"venue"
},
  "geometry": {"coordinates":[-85.40926399999999,39.881803],"type":"Point"}
}