{
  "type": "Feature",
  "properties": {
    "addr:full":"10920 E Co Rd 500 S Crothersville IN 47229",
    "addr:housenumber":"10920;500",
    "addr:postcode":"47229",
    "addr:street":"E Co Rd;S",
    "iso:country":"US",
    "sg:address":"10920 E Co Rd 500 S",
    "sg:city":"Crothersville",
    "sg:classifiers":[
        {
            "category":"Wholesale",
            "subcategory":"Auto Parts",
            "type":"Manufacturing & Wholesale Goods"
        }
    ],
    "sg:phone":"+1 812 793 2243",
    "sg:postcode":"47229",
    "sg:province":"IN",
    "sg:tags":[
        "automobile",
        "rebuilt"
    ],
    "wof:name":"Automotive Logistics Ctr",
    "wof:placetype":"venue"
},
  "geometry": {"coordinates":[-85.837524,38.808414],"type":"Point"}
}