{
  "type": "Feature",
  "properties": {
    "addr:full":"120 N Red Bank Rd Evansville IN 47712",
    "addr:housenumber":"120",
    "addr:postcode":"47712",
    "addr:street":"N Red Bank Rd",
    "iso:country":"US",
    "sg:address":"120 N Red Bank Rd",
    "sg:city":"Evansville",
    "sg:classifiers":[
        {
            "category":"Retail",
            "subcategory":"Portrait Studio",
            "type":"Services"
        }
    ],
    "sg:phone":"+1 812 425 9628",
    "sg:postcode":"47712",
    "sg:province":"IN",
    "sg:tags":[
        "photo"
    ],
    "wof:name":"Tj Cole Video & Photography",
    "wof:placetype":"venue"
},
  "geometry": {"coordinates":[-87.636746,37.981601],"type":"Point"}
}