{
  "type": "Feature",
  "properties": {
    "iso:country":"US",
    "sg:address":"1914 N Denby Ave",
    "sg:city":"Evansville",
    "sg:classifiers":[
        {
            "category":"Manufacturing",
            "subcategory":"Tools & Machinery",
            "type":"Manufacturing & Wholesale Goods"
        }
    ],
    "sg:phone":"+1 812 424 2602",
    "sg:postcode":"47711",
    "sg:province":"IN",
    "wof:name":"Champ Converters",
    "wof:placetype":"venue"
},
  "geometry": {"coordinates":[-87.550869,37.99465],"type":"Point"}
}