{
  "type": "Feature",
  "properties": {
    "addr:full":"7371 Travis Rd Greenwood IN 46143",
    "addr:housenumber":"7371",
    "addr:postcode":"46143",
    "addr:street":"Travis Rd",
    "iso:country":"US",
    "sg:address":"7371 Travis Rd",
    "sg:city":"Greenwood",
    "sg:classifiers":[
        {
            "category":"Insurance",
            "subcategory":"Insurance Agent",
            "type":"Services"
        }
    ],
    "sg:phone":"+1 317 422 5249",
    "sg:postcode":"46143",
    "sg:province":"IN",
    "sg:tags":[
        "consultant"
    ],
    "wof:name":"K T Enterprises",
    "wof:placetype":"venue"
},
  "geometry": {"coordinates":[-86.24237100000001,39.568785],"type":"Point"}
}