{
  "type": "Feature",
  "properties": {
    "iso:country":"US",
    "sg:address":"3258 170th Pl",
    "sg:city":"Hammond",
    "sg:classifiers":[
        {
            "category":"Organizations",
            "subcategory":"Community Association",
            "type":"Services"
        }
    ],
    "sg:phone":"+1 219 554 1565",
    "sg:postcode":"46323",
    "sg:province":"IN",
    "wof:name":"Cierra Program The",
    "wof:placetype":"venue"
},
  "geometry": {"coordinates":[-87.449916,41.585059],"type":"Point"}
}