{
  "type": "Feature",
  "properties": {
    "iso:country":"US",
    "sg:address":"10119 Donald Ave",
    "sg:city":"Leo",
    "sg:classifiers":[
        {
            "category":"Building & Trades",
            "subcategory":"Construction",
            "type":"Services"
        }
    ],
    "sg:phone":"+1 260 627 0343",
    "sg:postcode":"46765",
    "sg:province":"IN",
    "sg:tags":[
        "general",
        "contractor"
    ],
    "wof:name":"Dwight Silvers Construction",
    "wof:placetype":"venue"
},
  "geometry": {"coordinates":[-85.017662,41.226392],"type":"Point"}
}