{
  "type": "Feature",
  "properties": {
    "iso:country":"US",
    "sg:address":"1059 Wernsing Rd",
    "sg:city":"Jasper",
    "sg:classifiers":[
        {
            "category":"Building & Trades",
            "subcategory":"Construction",
            "type":"Services"
        }
    ],
    "sg:phone":"+1 812 482 2267",
    "sg:postcode":"47546",
    "sg:province":"IN",
    "sg:tags":[
        "contractor"
    ],
    "wof:name":"Southern Indiana Supply",
    "wof:placetype":"venue"
},
  "geometry": {"coordinates":[-86.942436,38.374204],"type":"Point"}
}