{
  "type": "Feature",
  "properties": {
    "iso:country":"US",
    "sg:address":"321 W 3rd St",
    "sg:city":"Marion",
    "sg:classifiers":[
        {
            "category":"Shopping",
            "subcategory":"Pharmacy",
            "type":"Retail Goods"
        }
    ],
    "sg:phone":"+1 765 662 1316",
    "sg:postcode":"46952",
    "sg:province":"IN",
    "wof:name":"CVS Pharmacy",
    "wof:placetype":"venue"
},
  "geometry": {"coordinates":[-85.663116,40.558745],"type":"Point"}
}