{
  "type": "Feature",
  "properties": {
    "addr:full":"20938 State Rd 119 Goshen IN 46526",
    "addr:housenumber":"20938;119",
    "addr:postcode":"46526",
    "addr:street":"State Rd",
    "iso:country":"US",
    "sg:address":"20938 State Rd 119",
    "sg:city":"Goshen",
    "sg:classifiers":[
        {
            "category":"Professional",
            "subcategory":"Business Services",
            "type":"Services"
        }
    ],
    "sg:phone":"+1 574 534 0504",
    "sg:postcode":"46526",
    "sg:province":"IN",
    "sg:tags":[
        "appraiser"
    ],
    "wof:name":"Bill Briscoe Appraisals",
    "wof:placetype":"venue"
},
  "geometry": {"coordinates":[-85.866501,41.573278],"type":"Point"}
}