{
  "type": "Feature",
  "properties": {
    "addr:full":"14741 Hazel Dell Crossing Ste 1000 Noblesville IN 46062",
    "addr:housenumber":"14741",
    "addr:postcode":"46062",
    "addr:street":"Hazel Dell Crossing Ste 1000",
    "iso:country":"US",
    "sg:address":"14741 Hazel Dell Crossing Ste 1000",
    "sg:city":"Noblesville",
    "sg:classifiers":[
        {
            "category":"Restaurant",
            "type":"Food & Drink"
        }
    ],
    "sg:phone":"+1 317 580 0630",
    "sg:postcode":"46062",
    "sg:province":"IN",
    "sg:tags":[
        "new",
        "american"
    ],
    "sg:website":"www.mudsocksgrill.com",
    "wof:name":"Mudsocks Grill",
    "wof:placetype":"venue"
},
  "geometry": {"coordinates":[-86.068015,40.002185],"type":"Point"}
}