{
  "type": "Feature",
  "properties": {
    "iso:country":"US",
    "sg:address":"648 E 1100 N",
    "sg:city":"North Manchester",
    "sg:classifiers":[
        {
            "category":"Wholesale",
            "subcategory":"Farm Supplies",
            "type":"Manufacturing & Wholesale Goods"
        }
    ],
    "sg:phone":"+1 260 982 2181",
    "sg:postcode":"46962",
    "sg:province":"IN",
    "sg:tags":[
        "grain"
    ],
    "wof:name":"Strauss Inc",
    "wof:placetype":"venue"
},
  "geometry": {"coordinates":[-85.777118,40.98607],"type":"Point"}
}