{
  "type": "Feature",
  "properties": {
    "addr:full":"7 Johnson Ave Indianapolis IN 46219",
    "addr:housenumber":"7",
    "addr:postcode":"46219",
    "addr:street":"Johnson Ave",
    "iso:country":"US",
    "sg:address":"7 Johnson Ave",
    "sg:city":"Indianapolis",
    "sg:classifiers":[
        {
            "category":"Professional",
            "subcategory":"Advertising",
            "type":"Services"
        }
    ],
    "sg:phone":"+1 317 375 4399",
    "sg:postcode":"46219",
    "sg:province":"IN",
    "sg:tags":[
        "counselor"
    ],
    "sg:website":"www.lodgedesign.com",
    "wof:name":"Lodge Design Co",
    "wof:placetype":"venue"
},
  "geometry": {"coordinates":[-86.072001,39.769164],"type":"Point"}
}