{
  "type": "Feature",
  "properties": {
    "iso:country":"US",
    "sg:address":"201 E Elm St",
    "sg:city":"New Albany",
    "sg:classifiers":[
        {
            "category":"Health Services",
            "subcategory":"Nursing And Care Facility",
            "type":"Services"
        }
    ],
    "sg:phone":"+1 812 945 9517",
    "sg:postcode":"47150",
    "sg:province":"IN",
    "sg:tags":[
        "home",
        "retirement",
        "community"
    ],
    "wof:name":"Robert E Lee Healthplex",
    "wof:placetype":"venue"
},
  "geometry": {"coordinates":[-85.821502,38.287785],"type":"Point"}
}