{
  "type": "Feature",
  "properties": {
    "iso:country":"US",
    "sg:address":"8520 N 850 W",
    "sg:city":"Fairland",
    "sg:classifiers":[
        {
            "category":"Building & Trades",
            "subcategory":"Construction",
            "type":"Services"
        }
    ],
    "sg:phone":"+1 317 835 4595",
    "sg:postcode":"46126",
    "sg:province":"IN",
    "sg:tags":[
        "general",
        "contractor"
    ],
    "wof:name":"EEMC Inc",
    "wof:placetype":"venue"
},
  "geometry": {"coordinates":[-85.942598,39.646486],"type":"Point"}
}