{
  "type": "Feature",
  "properties": {
    "iso:country":"US",
    "sg:address":"1706 Huffman Blvd",
    "sg:city":"Fort Wayne",
    "sg:classifiers":[
        {
            "category":"Building & Trades",
            "subcategory":"Cleaning & Sanitation",
            "type":"Services"
        }
    ],
    "sg:phone":"+1 260 422 9232",
    "sg:postcode":"46808",
    "sg:province":"IN",
    "sg:tags":[
        "maintenance"
    ],
    "wof:name":"T and C Services",
    "wof:placetype":"venue"
},
  "geometry": {"coordinates":[-85.166415,41.093727],"type":"Point"}
}