{
  "type": "Feature",
  "properties": {
    "iso:country":"US",
    "sg:address":"115 Harvest Rd",
    "sg:city":"Bluffton",
    "sg:classifiers":[
        {
            "category":"Government",
            "subcategory":"Office",
            "type":"Public Place"
        }
    ],
    "sg:phone":"+1 260 824 1930",
    "sg:postcode":"46714",
    "sg:province":"IN",
    "sg:tags":[
        "federal"
    ],
    "wof:name":"US Consolidated Farm Svc Agcy",
    "wof:placetype":"venue"
},
  "geometry": {"coordinates":[-85.16988499999999,40.722313],"type":"Point"}
}