{
  "type": "Feature",
  "properties": {
    "iso:country":"US",
    "sg:address":"300 Pendleton Ave",
    "sg:city":"Anderson",
    "sg:classifiers":[
        {
            "category":"Autos & Motor Vehicles",
            "subcategory":"Automobile Sales",
            "type":"Retail Goods"
        }
    ],
    "sg:phone":"+1 765 649 7027",
    "sg:postcode":"46016",
    "sg:province":"IN",
    "sg:tags":[
        "car",
        "dealer"
    ],
    "wof:name":"Midland Auto Sales",
    "wof:placetype":"venue"
},
  "geometry": {"coordinates":[-85.683613,40.098948],"type":"Point"}
}