{
  "type": "Feature",
  "properties": {
    "addr:full":"702 N Prince St Princeton IN 47670",
    "addr:housenumber":"702",
    "addr:postcode":"47670",
    "addr:street":"N Prince St",
    "iso:country":"US",
    "sg:address":"702 N Prince St",
    "sg:city":"Princeton",
    "sg:classifiers":[
        {
            "category":"Restaurant",
            "type":"Food & Drink"
        }
    ],
    "sg:phone":"+1 812 385 3131",
    "sg:postcode":"47670",
    "sg:province":"IN",
    "wof:name":"Dick Clarks Family Restaurant",
    "wof:placetype":"venue"
},
  "geometry": {"coordinates":[-87.56607,38.361652],"type":"Point"}
}