{
  "type": "Feature",
  "properties": {
    "iso:country":"US",
    "sg:address":"410 Valley Dr",
    "sg:city":"Martinsville",
    "sg:classifiers":[
        {
            "category":"Shopping",
            "subcategory":"Department Store",
            "type":"Retail Goods"
        }
    ],
    "sg:phone":"+1 765 342 3786",
    "sg:postcode":"46151",
    "sg:province":"IN",
    "wof:name":"Wal-Mart",
    "wof:placetype":"venue"
},
  "geometry": {"coordinates":[-86.412824,39.431687],"type":"Point"}
}