{
  "type": "Feature",
  "properties": {
    "iso:country":"US",
    "sg:address":"9901 Pendleton Pike",
    "sg:city":"Indianapolis",
    "sg:classifiers":[
        {
            "category":"Shopping",
            "subcategory":"Computers & Home Electronics",
            "type":"Retail Goods"
        }
    ],
    "sg:phone":"+1 317 897 1138",
    "sg:postcode":"46236",
    "sg:province":"IN",
    "wof:name":"Neways",
    "wof:placetype":"venue"
},
  "geometry": {"coordinates":[-85.99226,39.852966],"type":"Point"}
}