{
  "type": "Feature",
  "properties": {
    "iso:country":"US",
    "sg:address":"9270 US Hwy 20",
    "sg:city":"Shipshewana",
    "sg:classifiers":[
        {
            "category":"Manufacturing",
            "subcategory":"Wood Products",
            "type":"Manufacturing & Wholesale Goods"
        }
    ],
    "sg:phone":"+1 260 768 9197",
    "sg:postcode":"46565",
    "sg:province":"IN",
    "sg:tags":[
        "cargo",
        "container",
        "freight"
    ],
    "sg:website":"www.tntrailers.com",
    "wof:name":"T N Trailers",
    "wof:placetype":"venue"
},
  "geometry": {"coordinates":[-85.604481,41.654402],"type":"Point"}
}