{
  "type": "Feature",
  "properties": {
    "iso:country":"US",
    "sg:address":"5436 W 400 N",
    "sg:city":"Madison",
    "sg:classifiers":[
        {
            "category":"Retail",
            "subcategory":"Repair Shop",
            "type":"Services"
        }
    ],
    "sg:phone":"+1 812 273 5964",
    "sg:postcode":"47250",
    "sg:province":"IN",
    "sg:tags":[
        "farm",
        "machinery"
    ],
    "wof:name":"Lambs Tractor Repair",
    "wof:placetype":"venue"
},
  "geometry": {"coordinates":[-85.486737,38.79634],"type":"Point"}
}