{
  "type": "Feature",
  "properties": {
    "iso:country":"US",
    "sg:address":"145 W 14th St",
    "sg:city":"Anderson",
    "sg:classifiers":[
        {
            "category":"Wholesale",
            "subcategory":"Machinery & Supplies",
            "type":"Manufacturing & Wholesale Goods"
        }
    ],
    "sg:phone":"+1 765 649 5508",
    "sg:postcode":"46016",
    "sg:province":"IN",
    "sg:tags":[
        "equipment",
        "industrial"
    ],
    "wof:name":"Jack Raper Ind Supply Inc",
    "wof:placetype":"venue"
},
  "geometry": {"coordinates":[-85.68168300000001,40.10205],"type":"Point"}
}