{
  "type": "Feature",
  "properties": {
    "addr:full":"208 W Wall St Sullivan IN 47882",
    "addr:housenumber":"208",
    "addr:postcode":"47882",
    "addr:street":"W Wall St",
    "iso:country":"US",
    "sg:address":"208 W Wall St",
    "sg:city":"Sullivan",
    "sg:classifiers":[
        {
            "category":"Retail",
            "subcategory":"Laundry & Dry Cleaning",
            "type":"Services"
        }
    ],
    "sg:phone":"+1 812 268 5383",
    "sg:postcode":"47882",
    "sg:province":"IN",
    "sg:tags":[
        "cleaners"
    ],
    "wof:name":"Globe Cleaners",
    "wof:placetype":"venue"
},
  "geometry": {"coordinates":[-87.41179,39.096582],"type":"Point"}
}