{
  "type": "Feature",
  "properties": {
    "iso:country":"US",
    "sg:address":"303 N Indiana St",
    "sg:city":"Danville",
    "sg:classifiers":[
        {
            "category":"Professional",
            "subcategory":"Research",
            "type":"Services"
        }
    ],
    "sg:phone":"+1 317 718 3688",
    "sg:postcode":"46122",
    "sg:province":"IN",
    "sg:tags":[
        "environmental",
        "ecological"
    ],
    "wof:name":"O & M Inc",
    "wof:placetype":"venue"
},
  "geometry": {"coordinates":[-86.52272,39.765037],"type":"Point"}
}