{
  "type": "Feature",
  "properties": {
    "iso:country":"US",
    "sg:address":"1647 Hedden Park",
    "sg:city":"New Albany",
    "sg:classifiers":[
        {
            "category":"Professional",
            "subcategory":"Business Services",
            "type":"Services"
        }
    ],
    "sg:phone":"+1 812 945 4367",
    "sg:postcode":"47150",
    "sg:province":"IN",
    "wof:name":"Tim Reeves",
    "wof:placetype":"venue"
},
  "geometry": {"coordinates":[-85.807284,38.308538],"type":"Point"}
}