{
  "type": "Feature",
  "properties": {
    "iso:country":"US",
    "sg:address":"5601 US Hwy 31 E",
    "sg:city":"Clarksville",
    "sg:classifiers":[
        {
            "category":"Sports & Exercise",
            "subcategory":"Gym",
            "type":"Entertainment"
        }
    ],
    "sg:phone":"+1 812 288 9921",
    "sg:postcode":"47129",
    "sg:province":"IN",
    "sg:tags":[
        "club",
        "health",
        "studio",
        "gymnasium"
    ],
    "wof:name":"Curves For Women",
    "wof:placetype":"venue"
},
  "geometry": {"coordinates":[-85.74807699999999,38.339973],"type":"Point"}
}