{
  "type": "Feature",
  "properties": {
    "addr:full":"2912 N Regal Dr Laporte IN 46350",
    "addr:housenumber":"2912",
    "addr:postcode":"46350",
    "addr:street":"N Regal Dr",
    "iso:country":"US",
    "sg:address":"2912 N Regal Dr",
    "sg:city":"Laporte",
    "sg:classifiers":[
        {
            "category":"Professional",
            "subcategory":"Lawyer & Legal Services",
            "type":"Services"
        }
    ],
    "sg:phone":"+1 219 326 7259",
    "sg:postcode":"46350",
    "sg:province":"IN",
    "sg:tags":[
        "attorney"
    ],
    "wof:name":"Cynthia A Hedge",
    "wof:placetype":"venue"
},
  "geometry": {"coordinates":[-86.80569800000001,41.648967],"type":"Point"}
}