{
  "type": "Feature",
  "properties": {
    "iso:country":"US",
    "sg:address":"633 S Buffalo St",
    "sg:city":"Warsaw",
    "sg:classifiers":[
        {
            "category":"Shopping",
            "type":"Retail Goods"
        }
    ],
    "sg:phone":"+1 574 267 8933",
    "sg:postcode":"46580",
    "sg:province":"IN",
    "sg:tags":[
        "monument"
    ],
    "wof:name":"Patten Monument Co",
    "wof:placetype":"venue"
},
  "geometry": {"coordinates":[-85.856581,41.232273],"type":"Point"}
}