{
  "type": "Feature",
  "properties": {
    "addr:full":"204 Elm Grove Rd Bluffton IN 46714",
    "addr:housenumber":"204",
    "addr:postcode":"46714",
    "addr:street":"Elm Grove Rd",
    "iso:country":"US",
    "sg:address":"204 Elm Grove Rd",
    "sg:city":"Bluffton",
    "sg:classifiers":[
        {
            "category":"Manufacturing",
            "subcategory":"Rubber & Plastics",
            "type":"Manufacturing & Wholesale Goods"
        }
    ],
    "sg:phone":"+1 260 824 0160",
    "sg:postcode":"46714",
    "sg:province":"IN",
    "sg:tags":[
        "product",
        "mfg"
    ],
    "wof:name":"Tnm Plastics",
    "wof:placetype":"venue"
},
  "geometry": {"coordinates":[-85.154782,40.739996],"type":"Point"}
}