{
  "type": "Feature",
  "properties": {
    "iso:country":"US",
    "sg:address":"8834 Birkdale Cir",
    "sg:city":"Indianapolis",
    "sg:classifiers":[
        {
            "category":"Building & Trades",
            "subcategory":"Cleaning & Sanitation",
            "type":"Services"
        }
    ],
    "sg:phone":"+1 317 329 0685",
    "sg:postcode":"46234",
    "sg:province":"IN",
    "sg:tags":[
        "personal",
        "maintenance"
    ],
    "wof:name":"Guy Some Maintenance",
    "wof:placetype":"venue"
},
  "geometry": {"coordinates":[-86.31996599999999,39.806916],"type":"Point"}
}