{
  "type": "Feature",
  "properties": {
    "iso:country":"US",
    "sg:address":"222 N 3rd St",
    "sg:city":"Kentland",
    "sg:classifiers":[
        {
            "category":"Personal",
            "subcategory":"Beauty Salon",
            "type":"Services"
        }
    ],
    "sg:phone":"+1 219 474 6060",
    "sg:postcode":"47951",
    "sg:province":"IN",
    "wof:name":"Hair On The Square",
    "wof:placetype":"venue"
},
  "geometry": {"coordinates":[-87.445183,40.769912],"type":"Point"}
}