{
  "type": "Feature",
  "properties": {
    "addr:full":"144 Oak Park Dr Roanoke IN 46783",
    "addr:housenumber":"144",
    "addr:postcode":"46783",
    "addr:street":"Oak Park Dr",
    "iso:country":"US",
    "sg:address":"144 Oak Park Dr",
    "sg:city":"Roanoke",
    "sg:classifiers":[
        {
            "category":"Government",
            "subcategory":"Office",
            "type":"Public Place"
        }
    ],
    "sg:phone":"+1 260 672 9207",
    "sg:postcode":"46783",
    "sg:province":"IN",
    "sg:tags":[
        "city",
        "taxation"
    ],
    "wof:name":"Jackson Twp Trustee Assessor",
    "wof:placetype":"venue"
},
  "geometry": {"coordinates":[-85.373902,40.97029],"type":"Point"}
}