{
  "type": "Feature",
  "properties": {
    "iso:country":"US",
    "sg:address":"6041 McCasland Ave",
    "sg:city":"Portage",
    "sg:classifiers":[
        {
            "category":"Real Estate",
            "subcategory":"Real Estate Operator",
            "type":"Services"
        }
    ],
    "sg:phone":"+1 219 764 0972",
    "sg:postcode":"46368",
    "sg:province":"IN",
    "sg:tags":[
        "apartment"
    ],
    "wof:name":"Canden Apartments",
    "wof:placetype":"venue"
},
  "geometry": {"coordinates":[-87.181707,41.582112],"type":"Point"}
}