{
  "type": "Feature",
  "properties": {
    "iso:country":"US",
    "sg:address":"1526 S Green River Rd",
    "sg:city":"Evansville",
    "sg:classifiers":[
        {
            "category":"Real Estate",
            "subcategory":"Developer",
            "type":"Services"
        }
    ],
    "sg:phone":"+1 812 476 1456",
    "sg:postcode":"47715",
    "sg:province":"IN",
    "sg:tags":[
        "cemetery"
    ],
    "wof:name":"Park Lawn Cemetery & Mausoleum",
    "wof:placetype":"venue"
},
  "geometry": {"coordinates":[-87.49276399999999,37.955451],"type":"Point"}
}