{
  "type": "Feature",
  "properties": {
    "iso:country":"US",
    "sg:address":"31 3rd St SW",
    "sg:city":"Carmel",
    "sg:classifiers":[
        {
            "category":"Health Services",
            "subcategory":"Dentist",
            "type":"Services"
        }
    ],
    "sg:phone":"+1 317 569 9259",
    "sg:postcode":"46032",
    "sg:province":"IN",
    "wof:name":"Dental Art Solutions",
    "wof:placetype":"venue"
},
  "geometry": {"coordinates":[-86.127247,39.975693],"type":"Point"}
}