{
  "type": "Feature",
  "properties": {
    "iso:country":"US",
    "sg:address":"101 N Pawnee Ct",
    "sg:city":"La Porte",
    "sg:classifiers":[
        {
            "category":"Professional",
            "subcategory":"Business Services",
            "type":"Services"
        }
    ],
    "sg:phone":"+1 219 362 8628",
    "sg:postcode":"46350",
    "sg:province":"IN",
    "wof:name":"Hnm Enterprises LLC",
    "wof:placetype":"venue"
},
  "geometry": {"coordinates":[-86.770521,41.6065],"type":"Point"}
}