{
  "type": "Feature",
  "properties": {
    "addr:full":"712 E 19th St Anderson IN 46016",
    "addr:housenumber":"712",
    "addr:postcode":"46016",
    "addr:street":"E 19Th St",
    "iso:country":"US",
    "sg:address":"712 E 19th St",
    "sg:city":"Anderson",
    "sg:classifiers":[
        {
            "category":"Manufacturing",
            "subcategory":"Metals",
            "type":"Manufacturing & Wholesale Goods"
        }
    ],
    "sg:phone":"+1 765 642 6778",
    "sg:postcode":"46016",
    "sg:province":"IN",
    "sg:tags":[
        "fabricator",
        "sheet"
    ],
    "wof:name":"Anderson Welding & Fabrication",
    "wof:placetype":"venue"
},
  "geometry": {"coordinates":[-85.668421,40.097583],"type":"Point"}
}