{
  "type": "Feature",
  "properties": {
    "iso:country":"US",
    "sg:address":"1140 W 81st Ave",
    "sg:city":"Merrillville",
    "sg:classifiers":[
        {
            "category":"Professional",
            "type":"Services"
        }
    ],
    "sg:phone":"+1 219 736 7795",
    "sg:postcode":"46410",
    "sg:province":"IN",
    "sg:tags":[
        "establishment"
    ],
    "wof:name":"Kaplan Enterprises",
    "wof:placetype":"venue"
},
  "geometry": {"coordinates":[-87.348541,41.471173],"type":"Point"}
}