{
  "type": "Feature",
  "properties": {
    "addr:full":"3195 Grant St Gary IN 46408",
    "addr:housenumber":"3195",
    "addr:postcode":"46408",
    "addr:street":"Grant St Gary",
    "iso:country":"US",
    "sg:address":"3195 Grant St",
    "sg:city":"Gary",
    "sg:classifiers":[
        {
            "category":"Food & Beverages",
            "subcategory":"Liquor & Beverages",
            "type":"Retail Goods"
        }
    ],
    "sg:phone":"+1 219 884 4512",
    "sg:postcode":"46408",
    "sg:province":"IN",
    "sg:tags":[
        "store"
    ],
    "wof:name":"Champs Liquors",
    "wof:placetype":"venue"
},
  "geometry": {"coordinates":[-87.355974,41.560552],"type":"Point"}
}