{
  "type": "Feature",
  "properties": {
    "iso:country":"US",
    "sg:address":"1030 E Jefferson St",
    "sg:city":"Tipton",
    "sg:classifiers":[
        {
            "category":"Retail",
            "subcategory":"Auto Repair",
            "type":"Services"
        }
    ],
    "sg:phone":"+1 765 675 8833",
    "sg:postcode":"46072",
    "sg:province":"IN",
    "sg:tags":[
        "exhaust",
        "general",
        "supply"
    ],
    "wof:name":"Tuff Muff",
    "wof:placetype":"venue"
},
  "geometry": {"coordinates":[-86.029104,40.282799],"type":"Point"}
}