{
  "type": "Feature",
  "properties": {
    "iso:country":"US",
    "sg:address":"13431 Old Meridian St",
    "sg:city":"Carmel",
    "sg:classifiers":[
        {
            "category":"Health Services",
            "subcategory":"Hospital",
            "type":"Services"
        }
    ],
    "sg:phone":"+1 317 338 2345",
    "sg:postcode":"46032",
    "sg:province":"IN",
    "wof:name":"St Vincent Hospital & Health",
    "wof:placetype":"venue"
},
  "geometry": {"coordinates":[-86.145341,39.97837],"type":"Point"}
}