{
  "type": "Feature",
  "properties": {
    "iso:country":"US",
    "sg:address":"4244 State Rd 227",
    "sg:city":"Richmond",
    "sg:classifiers":[
        {
            "category":"Travel",
            "subcategory":"Campground",
            "type":"Entertainment"
        }
    ],
    "sg:phone":"+1 765 962 7907",
    "sg:postcode":"47374",
    "sg:province":"IN",
    "wof:name":"Grandpa's Farm Camp Ground",
    "wof:placetype":"venue"
},
  "geometry": {"coordinates":[-84.853302,39.770243],"type":"Point"}
}