{
  "type": "Feature",
  "properties": {
    "addr:full":"333 W 89th Ave Merrillville IN 46410",
    "addr:housenumber":"333",
    "addr:postcode":"46410",
    "addr:street":"W 89Th Ave",
    "iso:country":"US",
    "sg:address":"333 W 89th Ave",
    "sg:city":"Merrillville",
    "sg:classifiers":[
        {
            "category":"Health Services",
            "subcategory":"Doctor",
            "type":"Services"
        }
    ],
    "sg:phone":"+1 219 736 5818",
    "sg:postcode":"46410",
    "sg:province":"IN",
    "sg:tags":[
        "physician",
        "reconstructive",
        "surgeons",
        "surgeon",
        "plastic"
    ],
    "wof:name":"Yessenow Centre PC",
    "wof:placetype":"venue"
},
  "geometry": {"coordinates":[-87.339073,41.457649],"type":"Point"}
}