{
  "type": "Feature",
  "properties": {
    "iso:country":"US",
    "sg:address":"211 W Main St",
    "sg:city":"Loogootee",
    "sg:classifiers":[
        {
            "category":"Home & Garden",
            "subcategory":"Garden Supply",
            "type":"Retail Goods"
        }
    ],
    "sg:phone":"+1 812 295 4505",
    "sg:postcode":"47553",
    "sg:province":"IN",
    "sg:tags":[
        "tie",
        "railroad"
    ],
    "wof:name":"Koppers Co Tie Yard",
    "wof:placetype":"venue"
},
  "geometry": {"coordinates":[-86.915346,38.676502],"type":"Point"}
}