{
  "type": "Feature",
  "properties": {
    "iso:country":"US",
    "sg:address":"1320 Lincolnway S",
    "sg:city":"Ligonier",
    "sg:classifiers":[
        {
            "category":"Restaurant",
            "type":"Food & Drink"
        }
    ],
    "sg:menulink":"http://www.allmenus.com/in/ligonier/186464-mcdonalds/menu/",
    "sg:postcode":"46767",
    "sg:province":"IN",
    "sg:tags":[
        "burger",
        "american"
    ],
    "wof:name":"McDonald's",
    "wof:placetype":"venue"
},
  "geometry": {"coordinates":[-85.586332,41.453087],"type":"Point"}
}