{
  "type": "Feature",
  "properties": {
    "iso:country":"US",
    "sg:address":"4969 Madison St",
    "sg:city":"Gary",
    "sg:classifiers":[
        {
            "category":"Professional",
            "type":"Services"
        }
    ],
    "sg:phone":"+1 219 887 0639",
    "sg:postcode":"46408",
    "sg:province":"IN",
    "wof:name":"Lbs Glove and Company",
    "wof:placetype":"venue"
},
  "geometry": {"coordinates":[-87.340942,41.528953],"type":"Point"}
}