{
  "type": "Feature",
  "properties": {
    "iso:country":"US",
    "sg:address":"16516 Indianapolis Rd",
    "sg:city":"Yoder",
    "sg:classifiers":[
        {
            "category":"Building & Trades",
            "subcategory":"Landscaping Services",
            "type":"Services"
        }
    ],
    "sg:phone":"+1 260 638 4897",
    "sg:postcode":"46798",
    "sg:province":"IN",
    "sg:tags":[
        "landscape",
        "contractor"
    ],
    "wof:name":"Dreamlawn Fertilizing Inc",
    "wof:placetype":"venue"
},
  "geometry": {"coordinates":[-85.277443,40.926297],"type":"Point"}
}