{
  "type": "Feature",
  "properties": {
    "iso:country":"US",
    "sg:address":"3300 N Co Rd 500 E",
    "sg:city":"Danville",
    "sg:classifiers":[
        {
            "category":"Building & Trades",
            "subcategory":"Construction",
            "type":"Services"
        }
    ],
    "sg:phone":"+1 317 892 3066",
    "sg:postcode":"46122",
    "sg:province":"IN",
    "sg:tags":[
        "excavating",
        "contractor"
    ],
    "wof:name":"Jimmie Carlton Excavating",
    "wof:placetype":"venue"
},
  "geometry": {"coordinates":[-86.438716,39.813195],"type":"Point"}
}