{
  "type": "Feature",
  "properties": {
    "iso:country":"US",
    "sg:address":"1915 West St",
    "sg:city":"New Albany",
    "sg:classifiers":[
        {
            "category":"Banks & Credit Unions",
            "subcategory":"Bank",
            "type":"Services"
        }
    ],
    "sg:phone":"+1 812 949 3664",
    "sg:postcode":"47150",
    "sg:province":"IN",
    "sg:tags":[
        "loan",
        "real estate"
    ],
    "wof:name":"Kentuckiana Sunrise Mortgage",
    "wof:placetype":"venue"
},
  "geometry": {"coordinates":[-85.836562,38.299753],"type":"Point"}
}