{
  "type": "Feature",
  "properties": {
    "iso:country":"US",
    "sg:address":"2512 E 8th St",
    "sg:city":"Anderson",
    "sg:classifiers":[
        {
            "category":"Building & Trades",
            "subcategory":"Construction",
            "type":"Services"
        }
    ],
    "sg:phone":"+1 765 642 3347",
    "sg:postcode":"46012",
    "sg:province":"IN",
    "sg:tags":[
        "contractor"
    ],
    "wof:name":"Nancy Lee",
    "wof:placetype":"venue"
},
  "geometry": {"coordinates":[-85.645933,40.108037],"type":"Point"}
}