{
  "type": "Feature",
  "properties": {
    "iso:country":"US",
    "sg:address":"5690 State Rd 9",
    "sg:city":"Howe",
    "sg:classifiers":[
        {
            "category":"Retail",
            "subcategory":"Repair Shop",
            "type":"Services"
        }
    ],
    "sg:phone":"+1 260 562 2030",
    "sg:postcode":"46746",
    "sg:province":"IN",
    "wof:name":"Michiana Taxidermy",
    "wof:placetype":"venue"
},
  "geometry": {"coordinates":[-85.426037,41.723795],"type":"Point"}
}