{
  "type": "Feature",
  "properties": {
    "iso:country":"US",
    "sg:address":"111 N 4th St",
    "sg:city":"Kentland",
    "sg:classifiers":[
        {
            "category":"Banks & Credit Unions",
            "subcategory":"Financial Services",
            "type":"Services"
        }
    ],
    "sg:phone":"+1 219 474 5155",
    "sg:postcode":"47951",
    "sg:province":"IN",
    "sg:tags":[
        "company",
        "holding"
    ],
    "sg:website":"www.kentlandbank.com",
    "wof:name":"Ken Bancorp",
    "wof:placetype":"venue"
},
  "geometry": {"coordinates":[-87.443285,40.76897],"type":"Point"}
}