{
  "type": "Feature",
  "properties": {
    "iso:country":"US",
    "sg:address":"185 E Carlisle St",
    "sg:city":"Mooresville",
    "sg:classifiers":[
        {
            "category":"Personal",
            "subcategory":"Beauty Salon",
            "type":"Services"
        }
    ],
    "sg:phone":"+1 317 831 6766",
    "sg:postcode":"46158",
    "sg:province":"IN",
    "sg:tags":[
        "shop"
    ],
    "wof:name":"Guys & Gals Shoppe",
    "wof:placetype":"venue"
},
  "geometry": {"coordinates":[-86.374593,39.617482],"type":"Point"}
}