{
  "type": "Feature",
  "properties": {
    "iso:country":"US",
    "sg:address":"10801 Eagle Crossing Dr",
    "sg:city":"Evansville",
    "sg:classifiers":[
        {
            "category":"Professional",
            "type":"Services"
        }
    ],
    "sg:phone":"+1 812 476 9768",
    "sg:postcode":"47725",
    "sg:province":"IN",
    "wof:name":"Really Good Stuff Inc",
    "wof:placetype":"venue"
},
  "geometry": {"coordinates":[-87.51391099999999,38.076277],"type":"Point"}
}