{
  "type": "Feature",
  "properties": {
    "iso:country":"US",
    "sg:address":"10605 W 750 N",
    "sg:city":"Shipshewana",
    "sg:classifiers":[
        {
            "category":"Farming",
            "subcategory":"Farm",
            "type":"Manufacturing & Wholesale Goods"
        }
    ],
    "sg:phone":"+1 260 768 7825",
    "sg:postcode":"46565",
    "sg:province":"IN",
    "wof:name":"Spring Valley Farms",
    "wof:placetype":"venue"
},
  "geometry": {"coordinates":[-85.632219,41.748168],"type":"Point"}
}