{
  "type": "Feature",
  "properties": {
    "iso:country":"US",
    "sg:address":"5353 Mc Farland Rd",
    "sg:city":"Indianapolis",
    "sg:classifiers":[
        {
            "category":"Organizations",
            "subcategory":"Religious Organization",
            "type":"Services"
        }
    ],
    "sg:phone":"+1 317 786 4371",
    "sg:postcode":"46227",
    "sg:province":"IN",
    "sg:tags":[
        "church"
    ],
    "sg:website":"www.stjudeindy.org",
    "wof:name":"St Jude",
    "wof:placetype":"venue"
},
  "geometry": {"coordinates":[-86.111307,39.689171],"type":"Point"}
}