{
  "type": "Feature",
  "properties": {
    "iso:country":"US",
    "sg:address":"5734 Calumet Ave",
    "sg:city":"Hammond",
    "sg:classifiers":[
        {
            "category":"Building & Trades",
            "subcategory":"Construction",
            "type":"Services"
        }
    ],
    "sg:phone":"+1 219 932 0412",
    "sg:postcode":"46320",
    "sg:province":"IN",
    "sg:tags":[
        "roofing",
        "contractor"
    ],
    "wof:name":"Newell Roofing Corp",
    "wof:placetype":"venue"
},
  "geometry": {"coordinates":[-87.509002,41.610021],"type":"Point"}
}