{
  "type": "Feature",
  "properties": {
    "iso:country":"US",
    "sg:address":"5415 W Mooresville Rd",
    "sg:city":"Indianapolis",
    "sg:classifiers":[
        {
            "category":"Building & Trades",
            "subcategory":"Construction",
            "type":"Services"
        }
    ],
    "sg:phone":"+1 317 856 4744",
    "sg:postcode":"46221",
    "sg:province":"IN",
    "sg:tags":[
        "siding",
        "contractor"
    ],
    "wof:name":"JJJ Enterprises",
    "wof:placetype":"venue"
},
  "geometry": {"coordinates":[-86.254935,39.701725],"type":"Point"}
}