{
  "type": "Feature",
  "properties": {
    "iso:country":"US",
    "sg:address":"4088 Kerr Rd",
    "sg:city":"Cedar Grove",
    "sg:classifiers":[
        {
            "category":"Building & Trades",
            "subcategory":"Construction",
            "type":"Services"
        }
    ],
    "sg:phone":"+1 765 647 2612",
    "sg:postcode":"47016",
    "sg:province":"IN",
    "sg:tags":[
        "house"
    ],
    "wof:name":"Wendel Const",
    "wof:placetype":"venue"
},
  "geometry": {"coordinates":[-84.876502,39.378488],"type":"Point"}
}