{
  "type": "Feature",
  "properties": {
    "iso:country":"US",
    "sg:address":"2836 N B St",
    "sg:city":"Elwood",
    "sg:classifiers":[
        {
            "category":"Retail",
            "subcategory":"Auto Repair",
            "type":"Services"
        }
    ],
    "sg:phone":"+1 765 552 6235",
    "sg:postcode":"46036",
    "sg:province":"IN",
    "sg:tags":[
        "body",
        "automobile",
        "painting"
    ],
    "wof:name":"Fettig's Body Shop",
    "wof:placetype":"venue"
},
  "geometry": {"coordinates":[-85.824279,40.279002],"type":"Point"}
}