{
  "type": "Feature",
  "properties": {
    "iso:country":"US",
    "sg:address":"18160 US Hwy 31",
    "sg:city":"Westfield",
    "sg:classifiers":[
        {
            "category":"Wholesale",
            "subcategory":"Farm Supplies",
            "type":"Manufacturing & Wholesale Goods"
        }
    ],
    "sg:phone":"+1 317 867 3505",
    "sg:postcode":"46074",
    "sg:province":"IN",
    "wof:name":"Tractor Supply Co",
    "wof:placetype":"venue"
},
  "geometry": {"coordinates":[-86.133853,40.050936],"type":"Point"}
}