{
  "type": "Feature",
  "properties": {
    "iso:country":"US",
    "sg:address":"825 N Harrison St",
    "sg:city":"Warsaw",
    "sg:classifiers":[
        {
            "category":"Organizations",
            "subcategory":"Religious Organization",
            "type":"Services"
        }
    ],
    "sg:phone":"+1 574 269 1478",
    "sg:postcode":"46580",
    "sg:province":"IN",
    "sg:tags":[
        "church"
    ],
    "wof:name":"United Pentecostal",
    "wof:placetype":"venue"
},
  "geometry": {"coordinates":[-85.82852699999999,41.243034],"type":"Point"}
}