{
  "type": "Feature",
  "properties": {
    "addr:full":"22440 Main St Woodburn IN 46797",
    "addr:housenumber":"22440",
    "addr:postcode":"46797",
    "addr:street":"Main St",
    "iso:country":"US",
    "sg:address":"22440 Main St",
    "sg:city":"Woodburn",
    "sg:classifiers":[
        {
            "category":"Professional",
            "subcategory":"Credit Reporting & Collection",
            "type":"Services"
        }
    ],
    "sg:phone":"+1 260 632 4245",
    "sg:postcode":"46797",
    "sg:province":"IN",
    "sg:tags":[
        "child",
        "day",
        "care"
    ],
    "wof:name":"Financial Prtners Federal Care",
    "wof:placetype":"venue"
},
  "geometry": {"coordinates":[-84.85272000000001,41.124982],"type":"Point"}
}