{
  "type": "Feature",
  "properties": {
    "iso:country":"US",
    "sg:address":"110 N Detroit St",
    "sg:city":"Lagrange",
    "sg:classifiers":[
        {
            "category":"Home & Garden",
            "subcategory":"Furniture",
            "type":"Retail Goods"
        }
    ],
    "sg:phone":"+1 260 463 4040",
    "sg:postcode":"46761",
    "sg:province":"IN",
    "wof:name":"Big John's Furniture-Elctrncs",
    "wof:placetype":"venue"
},
  "geometry": {"coordinates":[-85.417928,41.644328],"type":"Point"}
}