{
  "type": "Feature",
  "properties": {
    "iso:country":"US",
    "sg:address":"106 S Walnut St",
    "sg:city":"Ridgeville",
    "sg:classifiers":[
        {
            "category":"Government",
            "subcategory":"Police Station",
            "type":"Public Place"
        }
    ],
    "sg:phone":"+1 765 857 2661",
    "sg:postcode":"47380",
    "sg:province":"IN",
    "sg:tags":[
        "department"
    ],
    "wof:name":"Ridgeville Police Dept",
    "wof:placetype":"venue"
},
  "geometry": {"coordinates":[-85.029227,40.289087],"type":"Point"}
}