{
  "type": "Feature",
  "properties": {
    "iso:country":"US",
    "sg:address":"1988 E State St",
    "sg:city":"Terre Haute",
    "sg:classifiers":[
        {
            "category":"Building & Trades",
            "subcategory":"Construction",
            "type":"Services"
        }
    ],
    "sg:phone":"+1 812 232 3782",
    "sg:postcode":"47834",
    "sg:province":"IN",
    "sg:tags":[
        "waterproofing",
        "contractor"
    ],
    "wof:name":"Americrawl Inc",
    "wof:placetype":"venue"
},
  "geometry": {"coordinates":[-87.07197,39.535252],"type":"Point"}
}