{
  "type": "Feature",
  "properties": {
    "iso:country":"US",
    "sg:address":"4317 Clubview Dr",
    "sg:city":"Fort Wayne",
    "sg:classifiers":[
        {
            "category":"Manufacturing",
            "subcategory":"Metals",
            "type":"Manufacturing & Wholesale Goods"
        }
    ],
    "sg:phone":"+1 260 432 2480",
    "sg:postcode":"46804",
    "sg:province":"IN",
    "sg:tags":[
        "finisher"
    ],
    "wof:name":"Heavy Duty Mfg Co",
    "wof:placetype":"venue"
},
  "geometry": {"coordinates":[-85.197959,41.042559],"type":"Point"}
}