{
  "type": "Feature",
  "properties": {
    "iso:country":"US",
    "sg:address":"106 S Randolph St",
    "sg:city":"Garrett",
    "sg:classifiers":[
        {
            "category":"Real Estate",
            "subcategory":"Real Estate Agent",
            "type":"Services"
        }
    ],
    "sg:phone":"+1 260 357 6622",
    "sg:postcode":"46738",
    "sg:province":"IN",
    "sg:tags":[
        "management"
    ],
    "wof:name":"SNG Safeguarding",
    "wof:placetype":"venue"
},
  "geometry": {"coordinates":[-85.13556800000001,41.350339],"type":"Point"}
}