{
  "type": "Feature",
  "properties": {
    "iso:country":"US",
    "sg:address":"88 E Morgan St",
    "sg:city":"Spencer",
    "sg:classifiers":[
        {
            "category":"Autos & Motor Vehicles",
            "subcategory":"Automobile Sales",
            "type":"Retail Goods"
        }
    ],
    "sg:phone":"+1 812 829 2500",
    "sg:postcode":"47460",
    "sg:province":"IN",
    "sg:tags":[
        "car",
        "dealer"
    ],
    "wof:name":"Spencer Ford",
    "wof:placetype":"venue"
},
  "geometry": {"coordinates":[-86.762125,39.286969],"type":"Point"}
}