{
  "type": "Feature",
  "properties": {
    "iso:country":"US",
    "sg:address":"811 Main St",
    "sg:city":"Jasper",
    "sg:classifiers":[
        {
            "category":"Organizations",
            "subcategory":"Professional Association",
            "type":"Services"
        }
    ],
    "sg:phone":"+1 812 482 4292",
    "sg:postcode":"47546",
    "sg:province":"IN",
    "wof:name":"Columbian Home",
    "wof:placetype":"venue"
},
  "geometry": {"coordinates":[-86.930875,38.393602],"type":"Point"}
}