{
  "type": "Feature",
  "properties": {
    "iso:country":"US",
    "sg:address":"2917 W Mishawaka Ave",
    "sg:city":"South Bend",
    "sg:classifiers":[
        {
            "category":"Insurance",
            "subcategory":"Insurance Agent",
            "type":"Services"
        }
    ],
    "sg:phone":"+1 574 288 4465",
    "sg:postcode":"46615",
    "sg:province":"IN",
    "wof:name":"American Family Insurance",
    "wof:placetype":"venue"
},
  "geometry": {"coordinates":[-86.206379,41.665793],"type":"Point"}
}