{
  "type": "Feature",
  "properties": {
    "addr:full":"2815 Indianapolis Boulevard Whiting IN 46394",
    "addr:housenumber":"2815",
    "addr:postcode":"46394",
    "addr:street":"Indianapolis Boulevard",
    "iso:country":"US",
    "sg:address":"2815 Indianapolis Boulevard",
    "sg:city":"Whiting",
    "sg:classifiers":[
        {
            "category":"Personal",
            "type":"Services"
        }
    ],
    "sg:phone":"+1 219 473 7700",
    "sg:postcode":"46394",
    "sg:province":"IN",
    "sg:tags":[
        "local"
    ],
    "sg:website":"www.bp.com",
    "wof:name":"BP Products North America",
    "wof:placetype":"venue"
},
  "geometry": {"coordinates":[-87.484036,41.662973],"type":"Point"}
}