{
  "type": "Feature",
  "properties": {
    "iso:country":"US",
    "sg:address":"1615 Estella Ave",
    "sg:city":"Fort Wayne",
    "sg:classifiers":[
        {
            "category":"Wholesale",
            "subcategory":"Chemicals & Plastics",
            "type":"Manufacturing & Wholesale Goods"
        }
    ],
    "sg:phone":"+1 260 749 9950",
    "sg:postcode":"46803",
    "sg:province":"IN",
    "sg:website":"www.ulrichchem.com",
    "wof:name":"Ulrich Chemical Inc",
    "wof:placetype":"venue"
},
  "geometry": {"coordinates":[-85.061189,41.071825],"type":"Point"}
}