{
  "type": "Feature",
  "properties": {
    "iso:country":"US",
    "sg:address":"6341 Mann Rd",
    "sg:city":"Indianapolis",
    "sg:classifiers":[
        {
            "category":"Organizations",
            "subcategory":"Religious Organization",
            "type":"Services"
        }
    ],
    "sg:phone":"+1 317 856 0589",
    "sg:postcode":"46221",
    "sg:province":"IN",
    "sg:tags":[
        "church"
    ],
    "sg:website":"www.mtpleasantbaptist-indy.com",
    "wof:name":"Mt Pleasant Baptist Church",
    "wof:placetype":"venue"
},
  "geometry": {"coordinates":[-86.246813,39.676356],"type":"Point"}
}