{
  "type": "Feature",
  "properties": {
    "iso:country":"US",
    "sg:address":"2950 N High School Rd",
    "sg:city":"Indianapolis",
    "sg:classifiers":[
        {
            "category":"Retail",
            "subcategory":"Funeral Services",
            "type":"Services"
        }
    ],
    "sg:phone":"+1 317 387 7000",
    "sg:postcode":"46224",
    "sg:province":"IN",
    "sg:tags":[
        "director"
    ],
    "sg:website":"www.flannerbuchanan.com",
    "wof:name":"Flanner & Buchanan Mortuaries",
    "wof:placetype":"venue"
},
  "geometry": {"coordinates":[-86.27006,39.808333],"type":"Point"}
}