{
  "type": "Feature",
  "properties": {
    "addr:full":"26084 Co Rd 6 Elkhart IN 46514",
    "addr:housenumber":"26084",
    "addr:postcode":"46514",
    "addr:street":"Co Rd 6",
    "iso:country":"US",
    "sg:address":"26084 Co Rd 6",
    "sg:city":"Elkhart",
    "sg:classifiers":[
        {
            "category":"Recreation",
            "type":"Entertainment"
        }
    ],
    "sg:phone":"+1 574 299 0901",
    "sg:postcode":"46514",
    "sg:province":"IN",
    "sg:tags":[
        "paint",
        "ball",
        "sport"
    ],
    "wof:name":"Paintball Outfitters II",
    "wof:placetype":"venue"
},
  "geometry": {"coordinates":[-85.96476199999999,41.724224],"type":"Point"}
}