{
  "type": "Feature",
  "properties": {
    "iso:country":"US",
    "sg:address":"17606 State Rd 60",
    "sg:city":"Borden",
    "sg:classifiers":[
        {
            "category":"Wholesale",
            "subcategory":"Machinery & Supplies",
            "type":"Manufacturing & Wholesale Goods"
        }
    ],
    "sg:phone":"+1 812 967 3029",
    "sg:postcode":"47106",
    "sg:province":"IN",
    "sg:tags":[
        "farm",
        "equipment",
        "repair"
    ],
    "wof:name":"Wright Brothers Sales",
    "wof:placetype":"venue"
},
  "geometry": {"coordinates":[-85.903173,38.445672],"type":"Point"}
}