{
  "type": "Feature",
  "properties": {
    "iso:country":"US",
    "sg:address":"600 S Main St",
    "sg:city":"South Whitley",
    "sg:classifiers":[
        {
            "category":"Government",
            "subcategory":"Office",
            "type":"Public Place"
        }
    ],
    "sg:phone":"+1 260 723 4020",
    "sg:postcode":"46787",
    "sg:province":"IN",
    "sg:tags":[
        "village"
    ],
    "wof:name":"South Whitley Wastewater Plant",
    "wof:placetype":"venue"
},
  "geometry": {"coordinates":[-85.62912799999999,41.080651],"type":"Point"}
}