{
  "type": "Feature",
  "properties": {
    "addr:full":"1969 Conner St Noblesville IN 46060",
    "addr:housenumber":"1969",
    "addr:postcode":"46060",
    "addr:street":"Conner St",
    "iso:country":"US",
    "sg:address":"1969 Conner St",
    "sg:city":"Noblesville",
    "sg:classifiers":[
        {
            "category":"Health Services",
            "subcategory":"Hospital",
            "type":"Services"
        }
    ],
    "sg:phone":"+1 317 776 3730",
    "sg:postcode":"46060",
    "sg:province":"IN",
    "sg:tags":[
        "mental"
    ],
    "sg:website":"www.cfmh.org",
    "wof:name":"CMH Assoc",
    "wof:placetype":"venue"
},
  "geometry": {"coordinates":[-85.99997500000001,40.045533],"type":"Point"}
}