{
  "type": "Feature",
  "properties": {
    "iso:country":"US",
    "sg:address":"1919 S Post Rd",
    "sg:city":"Indianapolis",
    "sg:classifiers":[
        {
            "category":"Social Services",
            "type":"Services"
        }
    ],
    "sg:phone":"+1 317 862 7040",
    "sg:postcode":"46239",
    "sg:province":"IN",
    "sg:tags":[
        "youth",
        "organization",
        "center"
    ],
    "wof:name":"Sports World",
    "wof:placetype":"venue"
},
  "geometry": {"coordinates":[-86.008574,39.741977],"type":"Point"}
}