{
  "type": "Feature",
  "properties": {
    "iso:country":"US",
    "sg:address":"1510 N Co Rd 600 E",
    "sg:city":"Avon",
    "sg:classifiers":[
        {
            "category":"Building & Trades",
            "subcategory":"Construction",
            "type":"Services"
        }
    ],
    "sg:phone":"+1 317 919 4241",
    "sg:postcode":"46123",
    "sg:province":"IN",
    "sg:tags":[
        "hanging",
        "contractor"
    ],
    "wof:name":"Genesis Preferred Painting",
    "wof:placetype":"venue"
},
  "geometry": {"coordinates":[-86.419377,39.791644],"type":"Point"}
}