{
  "type": "Feature",
  "properties": {
    "iso:country":"US",
    "sg:address":"8604 Allisonville Rd",
    "sg:city":"Indianapolis",
    "sg:classifiers":[
        {
            "category":"Banks & Credit Unions",
            "subcategory":"Financial Services",
            "type":"Services"
        }
    ],
    "sg:phone":"+1 317 845 8900",
    "sg:postcode":"46250",
    "sg:province":"IN",
    "sg:tags":[
        "broker",
        "mortgage"
    ],
    "wof:name":"Ofg Financial",
    "wof:placetype":"venue"
},
  "geometry": {"coordinates":[-86.075104,39.912498],"type":"Point"}
}