{
  "type": "Feature",
  "properties": {
    "addr:full":"6430 W 11th St Indianapolis IN 46214",
    "addr:housenumber":"6430",
    "addr:postcode":"46214",
    "addr:street":"W 11Th St",
    "iso:country":"US",
    "sg:address":"6430 W 11th St",
    "sg:city":"Indianapolis",
    "sg:classifiers":[
        {
            "category":"Manufacturing",
            "subcategory":"Tools & Machinery",
            "type":"Manufacturing & Wholesale Goods"
        }
    ],
    "sg:phone":"+1 317 241 0461",
    "sg:postcode":"46214",
    "sg:province":"IN",
    "sg:tags":[
        "equipment",
        "mfg"
    ],
    "wof:name":"Frank Glass Inc",
    "wof:placetype":"venue"
},
  "geometry": {"coordinates":[-86.272999,39.780792],"type":"Point"}
}