{
  "type": "Feature",
  "properties": {
    "iso:country":"US",
    "sg:address":"6931 Lincoln Pkwy",
    "sg:city":"Fort Wayne",
    "sg:classifiers":[
        {
            "category":"Manufacturing",
            "subcategory":"Tools & Machinery",
            "type":"Manufacturing & Wholesale Goods"
        }
    ],
    "sg:phone":"+1 260 434 1734",
    "sg:postcode":"46804",
    "sg:province":"IN",
    "sg:tags":[
        "machine",
        "shop"
    ],
    "sg:website":"www.top-notchtool.com",
    "wof:name":"Top Notch Tool",
    "wof:placetype":"venue"
},
  "geometry": {"coordinates":[-85.23307,41.086128],"type":"Point"}
}