{
  "type": "Feature",
  "properties": {
    "iso:country":"US",
    "sg:address":"1822 Schuyler Ave",
    "sg:city":"Lafayette",
    "sg:classifiers":[
        {
            "category":"Retail",
            "subcategory":"Auto Repair",
            "type":"Services"
        }
    ],
    "sg:phone":"+1 765 742 6626",
    "sg:postcode":"47904",
    "sg:province":"IN",
    "sg:tags":[
        "transmission"
    ],
    "wof:name":"Brettnacher's Transmissions",
    "wof:placetype":"venue"
},
  "geometry": {"coordinates":[-86.876587,40.441003],"type":"Point"}
}