{
  "type": "Feature",
  "properties": {
    "addr:full":"129 N Green St Crawfordsville IN 47933",
    "addr:housenumber":"129",
    "addr:postcode":"47933",
    "addr:street":"N Green St",
    "iso:country":"US",
    "sg:address":"129 N Green St",
    "sg:city":"Crawfordsville",
    "sg:classifiers":[
        {
            "category":"Building & Trades",
            "subcategory":"Plumbing",
            "type":"Services"
        }
    ],
    "sg:phone":"+1 765 362 6655",
    "sg:postcode":"47933",
    "sg:province":"IN",
    "sg:tags":[
        "repairing",
        "heating",
        "system"
    ],
    "wof:name":"Todd Mechanical Htg Clng",
    "wof:placetype":"venue"
},
  "geometry": {"coordinates":[-86.899941,40.042561],"type":"Point"}
}