{
  "type": "Feature",
  "properties": {
    "iso:country":"US",
    "sg:address":"511 N Commerce St",
    "sg:city":"Portland",
    "sg:classifiers":[
        {
            "category":"Building & Trades",
            "subcategory":"Plumbing",
            "type":"Services"
        }
    ],
    "sg:phone":"+1 260 726 8234",
    "sg:postcode":"47371",
    "sg:province":"IN",
    "sg:tags":[
        "plumbing",
        "contractor"
    ],
    "wof:name":"Aker Plumbing",
    "wof:placetype":"venue"
},
  "geometry": {"coordinates":[-84.979298,40.438145],"type":"Point"}
}