{
  "type": "Feature",
  "properties": {
    "addr:full":"429 E Margaret Dr Terre Haute IN 47802",
    "addr:housenumber":"429",
    "addr:postcode":"47802",
    "addr:street":"E Margaret Dr",
    "iso:country":"US",
    "sg:address":"429 E Margaret Dr",
    "sg:city":"Terre Haute",
    "sg:classifiers":[
        {
            "category":"Bars & Pubs",
            "type":"Food & Drink"
        },
        {
            "category":"Restaurant",
            "type":"Food & Drink"
        }
    ],
    "sg:menulink":"http://www.allmenus.com/in/honey-creek/34407-cracker-barrel-old-country-store/menu/",
    "sg:phone":"+1 812 235 6593",
    "sg:postcode":"47802",
    "sg:province":"IN",
    "sg:tags":[
        "american",
        "southern"
    ],
    "wof:name":"Cracker Barrel Old Country Store",
    "wof:placetype":"venue"
},
  "geometry": {"coordinates":[-87.41194299999999,39.433773],"type":"Point"}
}