{
  "type": "Feature",
  "properties": {
    "iso:country":"US",
    "sg:address":"1005 Whitmore St",
    "sg:city":"Anderson",
    "sg:classifiers":[
        {
            "category":"Professional",
            "type":"Services"
        }
    ],
    "sg:phone":"+1 765 378 3531",
    "sg:postcode":"46012",
    "sg:province":"IN",
    "wof:name":"Midwest Corporate Controllers",
    "wof:placetype":"venue"
},
  "geometry": {"coordinates":[-85.598902,40.126127],"type":"Point"}
}