{
  "type": "Feature",
  "properties": {
    "iso:country":"US",
    "sg:address":"573 W Simpson Chapel Rd",
    "sg:city":"Bloomington",
    "sg:classifiers":[
        {
            "category":"Wholesale",
            "subcategory":"Non-durable Goods",
            "type":"Manufacturing & Wholesale Goods"
        }
    ],
    "sg:phone":"+1 812 876 4500",
    "sg:postcode":"47404",
    "sg:province":"IN",
    "sg:tags":[
        "candle"
    ],
    "sg:website":"www.fdlfragrances.com",
    "wof:name":"Fdl Fragrances Inc",
    "wof:placetype":"venue"
},
  "geometry": {"coordinates":[-86.53159599999999,39.273165],"type":"Point"}
}