{
  "type": "Feature",
  "properties": {
    "iso:country":"US",
    "sg:address":"5435 W 75th Ave",
    "sg:city":"Schererville",
    "sg:classifiers":[
        {
            "category":"Shopping",
            "subcategory":"Bicycles & Sporting Goods",
            "type":"Retail Goods"
        }
    ],
    "sg:phone":"+1 219 322 0790",
    "sg:postcode":"46375",
    "sg:province":"IN",
    "sg:tags":[
        "equipment",
        "archery",
        "supply"
    ],
    "sg:website":"www.kustom-king.com",
    "wof:name":"Kustom King Arrows",
    "wof:placetype":"venue"
},
  "geometry": {"coordinates":[-87.40065800000001,41.482564],"type":"Point"}
}