{
  "type": "Feature",
  "properties": {
    "iso:country":"US",
    "sg:address":"220 E Main St",
    "sg:city":"Centerville",
    "sg:classifiers":[
        {
            "category":"Banks & Credit Unions",
            "subcategory":"Bank",
            "type":"Services"
        }
    ],
    "sg:phone":"+1 765 855 3453",
    "sg:postcode":"47339",
    "sg:province":"IN",
    "wof:name":"US Bank",
    "wof:placetype":"venue"
},
  "geometry": {"coordinates":[-85.08551300000001,39.97783],"type":"Point"}
}