{
  "type": "Feature",
  "properties": {
    "iso:country":"US",
    "sg:address":"10 Highland Ave",
    "sg:city":"Franklin",
    "sg:classifiers":[
        {
            "category":"Restaurant",
            "type":"Food & Drink"
        }
    ],
    "sg:phone":"+1 317 736 4927",
    "sg:postcode":"46131",
    "sg:province":"IN",
    "sg:tags":[
        "eating",
        "caterer"
    ],
    "wof:name":"Contemporary Catering",
    "wof:placetype":"venue"
},
  "geometry": {"coordinates":[-86.060168,39.491025],"type":"Point"}
}