{
  "type": "Feature",
  "properties": {
    "addr:full":"606 E 19th St Huntingburg IN 47542",
    "addr:housenumber":"606",
    "addr:postcode":"47542",
    "addr:street":"E 19Th St",
    "iso:country":"US",
    "sg:address":"606 E 19th St",
    "sg:city":"Huntingburg",
    "sg:classifiers":[
        {
            "category":"Retail",
            "subcategory":"Auto Repair",
            "type":"Services"
        }
    ],
    "sg:phone":"+1 812 683 2122",
    "sg:postcode":"47542",
    "sg:province":"IN",
    "sg:tags":[
        "transmission"
    ],
    "wof:name":"Doctor Transmission Auto Clnc",
    "wof:placetype":"venue"
},
  "geometry": {"coordinates":[-86.95330800000001,38.313569],"type":"Point"}
}