{
  "type": "Feature",
  "properties": {
    "iso:country":"US",
    "sg:address":"9101 S Co Rd 200 W",
    "sg:city":"Muncie",
    "sg:classifiers":[
        {
            "category":"Farming",
            "subcategory":"Livestock Farm",
            "type":"Manufacturing & Wholesale Goods"
        }
    ],
    "sg:phone":"+1 765 284 7967",
    "sg:postcode":"47302",
    "sg:province":"IN",
    "sg:tags":[
        "feedlot",
        "hog",
        "or",
        "beef",
        "cattle"
    ],
    "wof:name":"Harvest Daze Farms",
    "wof:placetype":"venue"
},
  "geometry": {"coordinates":[-85.422824,40.11461],"type":"Point"}
}