{
  "type": "Feature",
  "properties": {
    "iso:country":"US",
    "sg:address":"413 Concord Ln",
    "sg:city":"Carmel",
    "sg:classifiers":[
        {
            "category":"Building & Trades",
            "subcategory":"Landscaping Services",
            "type":"Services"
        }
    ],
    "sg:phone":"+1 317 582 0235",
    "sg:postcode":"46032",
    "sg:province":"IN",
    "sg:tags":[
        "landscape",
        "contractor"
    ],
    "wof:name":"LRS Horticultural Svc",
    "wof:placetype":"venue"
},
  "geometry": {"coordinates":[-86.11831599999999,39.974146],"type":"Point"}
}