{
  "type": "Feature",
  "properties": {
    "iso:country":"US",
    "sg:address":"5888 W 71st St",
    "sg:city":"Indianapolis",
    "sg:classifiers":[
        {
            "category":"Building & Trades",
            "subcategory":"Construction",
            "type":"Services"
        }
    ],
    "sg:phone":"+1 317 388 1866",
    "sg:postcode":"46278",
    "sg:province":"IN",
    "sg:tags":[
        "foundation"
    ],
    "wof:name":"Fasteel Of Indiana Inc",
    "wof:placetype":"venue"
},
  "geometry": {"coordinates":[-86.26495300000001,39.8817],"type":"Point"}
}