{
  "type": "Feature",
  "properties": {
    "iso:country":"US",
    "sg:address":"52933 Glenmoor St",
    "sg:city":"Elkhart",
    "sg:classifiers":[
        {
            "category":"Building & Trades",
            "subcategory":"Construction",
            "type":"Services"
        }
    ],
    "sg:phone":"+1 574 264 7392",
    "sg:postcode":"46514",
    "sg:province":"IN",
    "sg:tags":[
        "house"
    ],
    "wof:name":"Jack Rodman",
    "wof:placetype":"venue"
},
  "geometry": {"coordinates":[-86.03819799999999,41.721264],"type":"Point"}
}