{
  "type": "Feature",
  "properties": {
    "iso:country":"US",
    "sg:address":"12 N 17th St",
    "sg:city":"Richmond",
    "sg:classifiers":[
        {
            "category":"Professional",
            "subcategory":"Advertising",
            "type":"Services"
        }
    ],
    "sg:phone":"+1 765 962 3220",
    "sg:postcode":"47374",
    "sg:province":"IN",
    "sg:website":"www.porteradvertising.com",
    "wof:name":"Porter Advertising",
    "wof:placetype":"venue"
},
  "geometry": {"coordinates":[-84.878927,39.83142],"type":"Point"}
}