{
  "type": "Feature",
  "properties": {
    "iso:country":"US",
    "sg:address":"1221 Oxford St",
    "sg:city":"Fort Wayne",
    "sg:classifiers":[
        {
            "category":"Personal",
            "subcategory":"Barber",
            "type":"Services"
        }
    ],
    "sg:phone":"+1 260 456 8536",
    "sg:postcode":"46806",
    "sg:province":"IN",
    "sg:tags":[
        "shop"
    ],
    "wof:name":"Yvonne's Barber Shop",
    "wof:placetype":"venue"
},
  "geometry": {"coordinates":[-85.120366,41.053503],"type":"Point"}
}