{
  "type": "Feature",
  "properties": {
    "iso:country":"US",
    "sg:address":"7355 Brighton Cir",
    "sg:city":"Fishers",
    "sg:classifiers":[
        {
            "category":"Professional",
            "subcategory":"Business Services",
            "type":"Services"
        }
    ],
    "sg:phone":"+1 317 578 3102",
    "sg:postcode":"46038",
    "sg:province":"IN",
    "wof:name":"Ivy Design",
    "wof:placetype":"venue"
},
  "geometry": {"coordinates":[-86.03859799999999,39.942845],"type":"Point"}
}