{
  "type": "Feature",
  "properties": {
    "addr:full":"3919 E McGalliard Rd Muncie IN 47303",
    "addr:housenumber":"3919",
    "addr:postcode":"47303",
    "addr:street":"E Mcgalliard Rd",
    "iso:country":"US",
    "sg:address":"3919 E McGalliard Rd",
    "sg:city":"Muncie",
    "sg:phone":"+1 765 284 7374",
    "sg:postcode":"47303",
    "sg:province":"IN",
    "sg:tags":[
        "oil"
    ],
    "wof:name":"Norrick Petroleum",
    "wof:placetype":"venue"
},
  "geometry": {"coordinates":[-85.33019899999999,40.219145],"type":"Point"}
}