{
  "type": "Feature",
  "properties": {
    "iso:country":"US",
    "sg:address":"4700 W Lloyd Expy",
    "sg:city":"Evansville",
    "sg:classifiers":[
        {
            "category":"Restaurant",
            "type":"Food & Drink"
        }
    ],
    "sg:menulink":"http://www.allmenus.com/in/poplar-grove/79540-pizza-hut/menu/",
    "sg:phone":"+1 812 425 6666",
    "sg:postcode":"47712",
    "sg:province":"IN",
    "sg:tags":[
        "american",
        "pizza"
    ],
    "wof:name":"Pizza Hut",
    "wof:placetype":"venue"
},
  "geometry": {"coordinates":[-87.632695,37.977191],"type":"Point"}
}