{
  "type": "Feature",
  "properties": {
    "iso:country":"US",
    "sg:address":"215 S 10th St",
    "sg:city":"Noblesville",
    "sg:classifiers":[
        {
            "category":"Professional",
            "type":"Services"
        }
    ],
    "sg:phone":"+1 317 773 0878",
    "sg:postcode":"46060",
    "sg:province":"IN",
    "sg:tags":[
        "establishment"
    ],
    "wof:name":"Magnetek Inc",
    "wof:placetype":"venue"
},
  "geometry": {"coordinates":[-86.012313,40.043642],"type":"Point"}
}