{
  "type": "Feature",
  "properties": {
    "iso:country":"US",
    "sg:address":"116 S 6th St",
    "sg:city":"Logansport",
    "sg:classifiers":[
        {
            "category":"Autos & Motor Vehicles",
            "subcategory":"Auto Supplies",
            "type":"Retail Goods"
        }
    ],
    "sg:phone":"+1 574 722 6655",
    "sg:postcode":"46947",
    "sg:province":"IN",
    "sg:tags":[
        "automobile",
        "parts"
    ],
    "wof:name":"Schraders Auto Tech",
    "wof:placetype":"venue"
},
  "geometry": {"coordinates":[-86.362769,40.753865],"type":"Point"}
}