{
  "type": "Feature",
  "properties": {
    "iso:country":"US",
    "sg:address":"9245 Calumet Ave",
    "sg:city":"Munster",
    "sg:classifiers":[
        {
            "category":"Health Services",
            "subcategory":"Medical Lab",
            "type":"Services"
        }
    ],
    "sg:phone":"+1 219 836 4702",
    "sg:postcode":"46321",
    "sg:province":"IN",
    "sg:tags":[
        "x",
        "laboratory"
    ],
    "wof:name":"Sonographic Images",
    "wof:placetype":"venue"
},
  "geometry": {"coordinates":[-87.508967,41.541977],"type":"Point"}
}