{
  "type": "Feature",
  "properties": {
    "iso:country":"US",
    "sg:address":"3073 E Amy Ln",
    "sg:city":"Bloomington",
    "sg:classifiers":[
        {
            "category":"Real Estate",
            "subcategory":"Real Estate Operator",
            "type":"Services"
        }
    ],
    "sg:phone":"+1 812 339 7884",
    "sg:postcode":"47408",
    "sg:province":"IN",
    "sg:tags":[
        "apartment"
    ],
    "wof:name":"Cedargate Apartments",
    "wof:placetype":"venue"
},
  "geometry": {"coordinates":[-86.496201,39.1693],"type":"Point"}
}