{
  "type": "Feature",
  "properties": {
    "iso:country":"US",
    "sg:address":"1436 Leopold St",
    "sg:city":"Jasper",
    "sg:classifiers":[
        {
            "category":"Organizations",
            "subcategory":"Religious Organization",
            "type":"Services"
        }
    ],
    "sg:phone":"+1 812 547 6360",
    "sg:postcode":"47546",
    "sg:province":"IN",
    "sg:tags":[
        "church"
    ],
    "wof:name":"Troy Christian Church",
    "wof:placetype":"venue"
},
  "geometry": {"coordinates":[-86.924926,38.399593],"type":"Point"}
}