{
  "type": "Feature",
  "properties": {
    "iso:country":"US",
    "sg:address":"1067 Wabash Ave",
    "sg:city":"Clinton",
    "sg:classifiers":[
        {
            "category":"Personal",
            "subcategory":"Beauty Salon",
            "type":"Services"
        }
    ],
    "sg:phone":"+1 765 832 7589",
    "sg:postcode":"47842",
    "sg:province":"IN",
    "sg:tags":[
        "shop"
    ],
    "wof:name":"Patsys Unisex Styling",
    "wof:placetype":"venue"
},
  "geometry": {"coordinates":[-87.411704,39.652104],"type":"Point"}
}