{
  "type": "Feature",
  "properties": {
    "addr:full":"2203 45th St Highland IN 46322",
    "addr:housenumber":"2203",
    "addr:postcode":"46322",
    "addr:street":"45Th St",
    "iso:country":"US",
    "sg:address":"2203 45th St",
    "sg:city":"Highland",
    "sg:classifiers":[
        {
            "category":"Real Estate",
            "subcategory":"Real Estate Services",
            "type":"Services"
        },
        {
            "category":"Banks & Credit Unions",
            "subcategory":"Bank",
            "type":"Services"
        },
        {
            "category":"Banks & Credit Unions",
            "subcategory":"Financial Services",
            "type":"Services"
        }
    ],
    "sg:phone":"+1 219 922 3155",
    "sg:postcode":"46322",
    "sg:province":"IN",
    "sg:tags":[
        "commercial",
        "loan",
        "saving"
    ],
    "sg:website":"https://www.53.com/",
    "wof:name":"Fifth Third Bank",
    "wof:placetype":"venue"
},
  "geometry": {"coordinates":[-87.475916,41.53759],"type":"Point"}
}