{
  "type": "Feature",
  "properties": {
    "addr:full":"3 E Michigan St Remington IN 47977",
    "addr:housenumber":"3",
    "addr:postcode":"47977",
    "addr:street":"E Michigan St",
    "iso:country":"US",
    "sg:address":"3 E Michigan St",
    "sg:city":"Remington",
    "sg:classifiers":[
        {
            "category":"Government",
            "subcategory":"Office",
            "type":"Public Place"
        }
    ],
    "sg:phone":"+1 219 261 2523",
    "sg:postcode":"47977",
    "sg:province":"IN",
    "sg:tags":[
        "city"
    ],
    "wof:name":"Remington Town Hall",
    "wof:placetype":"venue"
},
  "geometry": {"coordinates":[-87.149597,40.762162],"type":"Point"}
}