{
  "type": "Feature",
  "properties": {
    "iso:country":"US",
    "sg:address":"53631 Fir Rd",
    "sg:city":"Granger",
    "sg:classifiers":[
        {
            "category":"Building & Trades",
            "subcategory":"Landscaping Services",
            "type":"Services"
        }
    ],
    "sg:phone":"+1 574 277 7210",
    "sg:postcode":"46530",
    "sg:province":"IN",
    "sg:tags":[
        "landscape",
        "contractor"
    ],
    "wof:name":"Inspirational Water Gardens",
    "wof:placetype":"venue"
},
  "geometry": {"coordinates":[-86.163427,41.719159],"type":"Point"}
}