{
  "type": "Feature",
  "properties": {
    "iso:country":"US",
    "sg:address":"8 S Court St",
    "sg:city":"Sullivan",
    "sg:classifiers":[
        {
            "category":"Shopping",
            "subcategory":"Jewelry",
            "type":"Retail Goods"
        }
    ],
    "sg:phone":"+1 812 268 5277",
    "sg:postcode":"47882",
    "sg:province":"IN",
    "sg:tags":[
        "jeweler"
    ],
    "wof:name":"Brown Jewelry Store",
    "wof:placetype":"venue"
},
  "geometry": {"coordinates":[-87.408458,39.095361],"type":"Point"}
}