{
  "type": "Feature",
  "properties": {
    "addr:full":"240 S 6th St Richmond IN 47374",
    "addr:housenumber":"240",
    "addr:postcode":"47374",
    "addr:street":"S 6Th St",
    "iso:country":"US",
    "sg:address":"240 S 6th St",
    "sg:city":"Richmond",
    "sg:classifiers":[
        {
            "category":"Organizations",
            "subcategory":"Religious Organization",
            "type":"Services"
        }
    ],
    "sg:phone":"+1 765 966 0916",
    "sg:postcode":"47374",
    "sg:province":"IN",
    "sg:tags":[
        "church"
    ],
    "sg:website":"www.richmondcatholiccommunity.com",
    "wof:name":"Richmond Catholic Education",
    "wof:placetype":"venue"
},
  "geometry": {"coordinates":[-84.894548,39.825354],"type":"Point"}
}