{
  "type": "Feature",
  "properties": {
    "iso:country":"US",
    "sg:address":"1821 E Schug Rd",
    "sg:city":"Columbia City",
    "sg:classifiers":[
        {
            "category":"Professional",
            "type":"Services"
        }
    ],
    "sg:phone":"+1 260 691 3787",
    "sg:postcode":"46725",
    "sg:province":"IN",
    "sg:tags":[
        "establishment"
    ],
    "wof:name":"Facts Inc",
    "wof:placetype":"venue"
},
  "geometry": {"coordinates":[-85.456853,41.254509],"type":"Point"}
}