{
  "type": "Feature",
  "properties": {
    "iso:country":"US",
    "sg:address":"208 E Southway Blvd",
    "sg:city":"Kokomo",
    "sg:classifiers":[
        {
            "category":"Food & Beverages",
            "subcategory":"Groceries & Convenience Stores",
            "type":"Retail Goods"
        }
    ],
    "sg:phone":"+1 765 865 7520",
    "sg:postcode":"46902",
    "sg:province":"IN",
    "sg:tags":[
        "grocer"
    ],
    "sg:website":"www.marshsupermarkets.com",
    "wof:name":"Marsh Supermarket",
    "wof:placetype":"venue"
},
  "geometry": {"coordinates":[-86.12619100000001,40.444355],"type":"Point"}
}