{
  "type": "Feature",
  "properties": {
    "addr:full":"200 Russell St Hammond IN 46320",
    "addr:housenumber":"200",
    "addr:postcode":"46320",
    "addr:street":"Russell St",
    "iso:country":"US",
    "sg:address":"200 Russell St",
    "sg:city":"Hammond",
    "sg:classifiers":[
        {
            "category":"Insurance",
            "subcategory":"Insurance Agent",
            "type":"Services"
        }
    ],
    "sg:phone":"+1 219 852 0961",
    "sg:postcode":"46320",
    "sg:province":"IN",
    "wof:name":"Northwestern Mutual Financial",
    "wof:placetype":"venue"
},
  "geometry": {"coordinates":[-87.519615,41.616831],"type":"Point"}
}