{
  "type": "Feature",
  "properties": {
    "iso:country":"US",
    "sg:address":"5209 N State Rd 109",
    "sg:city":"Columbia City",
    "sg:classifiers":[
        {
            "category":"Education",
            "subcategory":"School",
            "type":"Public Place"
        }
    ],
    "sg:phone":"+1 260 691 2371",
    "sg:postcode":"46725",
    "sg:province":"IN",
    "wof:name":"Northern Heights School",
    "wof:placetype":"venue"
},
  "geometry": {"coordinates":[-85.49182,41.247543],"type":"Point"}
}