{
  "type": "Feature",
  "properties": {
    "iso:country":"US",
    "sg:address":"731 Osage St",
    "sg:city":"Fort Wayne",
    "sg:classifiers":[
        {
            "category":"Building & Trades",
            "subcategory":"Construction",
            "type":"Services"
        }
    ],
    "sg:phone":"+1 260 424 0990",
    "sg:postcode":"46808",
    "sg:province":"IN",
    "sg:tags":[
        "paving",
        "contractor"
    ],
    "wof:name":"Midwest United Co",
    "wof:placetype":"venue"
},
  "geometry": {"coordinates":[-85.160945,41.080381],"type":"Point"}
}