{
  "type": "Feature",
  "properties": {
    "addr:full":"936 W Walnut St Albany IN 47320",
    "addr:housenumber":"936",
    "addr:postcode":"47320",
    "addr:street":"W Walnut St",
    "iso:country":"US",
    "sg:address":"936 W Walnut St",
    "sg:city":"Albany",
    "sg:classifiers":[
        {
            "category":"Health Services",
            "subcategory":"Doctor",
            "type":"Services"
        }
    ],
    "sg:phone":"+1 765 789 4454",
    "sg:postcode":"47320",
    "sg:province":"IN",
    "sg:tags":[
        "dentist"
    ],
    "wof:name":"Albany Family Dentistry",
    "wof:placetype":"venue"
},
  "geometry": {"coordinates":[-85.247939,40.300655],"type":"Point"}
}