{
  "type": "Feature",
  "properties": {
    "iso:country":"US",
    "sg:address":"302 S Wilder St",
    "sg:city":"Greensburg",
    "sg:classifiers":[
        {
            "category":"Wholesale",
            "subcategory":"Meat",
            "type":"Manufacturing & Wholesale Goods"
        }
    ],
    "sg:phone":"+1 812 663 2602",
    "sg:postcode":"47240",
    "sg:province":"IN",
    "sg:website":"www.conagrafoods.com",
    "wof:name":"Con Agra Foods",
    "wof:placetype":"venue"
},
  "geometry": {"coordinates":[-85.474784,39.334506],"type":"Point"}
}