{
  "type": "Feature",
  "properties": {
    "iso:country":"US",
    "sg:address":"430 E. Kirkwood Unit 7",
    "sg:city":"Bloomington",
    "sg:classifiers":[
        {
            "category":"Bars & Pubs",
            "type":"Food & Drink"
        }
    ],
    "sg:postcode":"47401",
    "sg:province":"IN",
    "sg:website":"www.festered.net/jr/",
    "wof:name":"Jungle Room",
    "wof:placetype":"venue"
},
  "geometry": {"coordinates":[-86.529315,39.166532],"type":"Point"}
}