{
  "type": "Feature",
  "properties": {
    "iso:country":"US",
    "sg:address":"4017 S Meridian St",
    "sg:city":"Indianapolis",
    "sg:classifiers":[
        {
            "category":"Organizations",
            "subcategory":"Religious Organization",
            "type":"Services"
        }
    ],
    "sg:phone":"+1 317 782 3558",
    "sg:postcode":"46217",
    "sg:province":"IN",
    "wof:name":"Blessings of Love Ministries",
    "wof:placetype":"venue"
},
  "geometry": {"coordinates":[-86.158368,39.707354],"type":"Point"}
}