{
  "type": "Feature",
  "properties": {
    "iso:country":"US",
    "sg:address":"915 N Main St",
    "sg:city":"Fairmount",
    "sg:classifiers":[
        {
            "category":"Autos & Motor Vehicles",
            "subcategory":"Automobile Sales",
            "type":"Retail Goods"
        }
    ],
    "sg:phone":"+1 765 948 3377",
    "sg:postcode":"46928",
    "sg:province":"IN",
    "sg:tags":[
        "car",
        "dealer"
    ],
    "wof:name":"Quaker Classic Inc",
    "wof:placetype":"venue"
},
  "geometry": {"coordinates":[-85.647735,40.423407],"type":"Point"}
}