{
  "type": "Feature",
  "properties": {
    "iso:country":"US",
    "sg:address":"4331 Vogel Rd",
    "sg:city":"Evansville",
    "sg:classifiers":[
        {
            "category":"Professional",
            "subcategory":"Accounting & Tax Preparation",
            "type":"Services"
        }
    ],
    "sg:phone":"+1 812 473 5455",
    "sg:postcode":"47715",
    "sg:province":"IN",
    "sg:tags":[
        "return",
        "filing"
    ],
    "wof:name":"H & R Block Tax Svc",
    "wof:placetype":"venue"
},
  "geometry": {"coordinates":[-87.498721,37.987615],"type":"Point"}
}