{
  "type": "Feature",
  "properties": {
    "iso:country":"US",
    "sg:address":"3066 W 300 S",
    "sg:city":"Tipton",
    "sg:classifiers":[
        {
            "category":"Building & Trades",
            "subcategory":"Construction",
            "type":"Services"
        }
    ],
    "sg:phone":"+1 765 675 4195",
    "sg:postcode":"46072",
    "sg:province":"IN",
    "sg:tags":[
        "drainage",
        "contractor"
    ],
    "wof:name":"Ripberger Drainage",
    "wof:placetype":"venue"
},
  "geometry": {"coordinates":[-86.070341,40.261108],"type":"Point"}
}