{
  "type": "Feature",
  "properties": {
    "iso:country":"US",
    "sg:address":"6520 Cornell Ave",
    "sg:city":"Indianapolis",
    "sg:classifiers":[
        {
            "category":"Shopping",
            "subcategory":"Bicycles & Sporting Goods",
            "type":"Retail Goods"
        }
    ],
    "sg:phone":"+1 317 253 2611",
    "sg:postcode":"46220",
    "sg:province":"IN",
    "sg:website":"www.thebikeline.com",
    "wof:name":"Bike Line",
    "wof:placetype":"venue"
},
  "geometry": {"coordinates":[-86.142505,39.873618],"type":"Point"}
}