{
  "type": "Feature",
  "properties": {
    "iso:country":"US",
    "sg:address":"6834 Lake Forest Village Cir",
    "sg:city":"Fort Wayne",
    "sg:classifiers":[
        {
            "category":"Real Estate",
            "subcategory":"Real Estate Operator",
            "type":"Services"
        }
    ],
    "sg:phone":"+1 260 749 8671",
    "sg:postcode":"46815",
    "sg:province":"IN",
    "sg:tags":[
        "apartment"
    ],
    "wof:name":"Lake Forest Village Apartments",
    "wof:placetype":"venue"
},
  "geometry": {"coordinates":[-85.048207,41.089585],"type":"Point"}
}