{
  "type": "Feature",
  "properties": {
    "iso:country":"US",
    "sg:address":"3905 W 96th St",
    "sg:city":"Indianapolis",
    "sg:classifiers":[
        {
            "category":"Shopping",
            "subcategory":"Bicycles & Sporting Goods",
            "type":"Retail Goods"
        }
    ],
    "sg:phone":"+1 317 872 4248",
    "sg:postcode":"46268",
    "sg:province":"IN",
    "sg:tags":[
        "saddlery",
        "harness"
    ],
    "sg:website":"www.grandchampiontack.com",
    "wof:name":"Grand Champion Tack & Saddlery",
    "wof:placetype":"venue"
},
  "geometry": {"coordinates":[-86.22869,39.926266],"type":"Point"}
}