{
  "type": "Feature",
  "properties": {
    "addr:full":"520 S Armstrong St Kokomo IN 46901",
    "addr:housenumber":"520",
    "addr:postcode":"46901",
    "addr:street":"S Armstrong St",
    "iso:country":"US",
    "sg:address":"520 S Armstrong St",
    "sg:city":"Kokomo",
    "sg:classifiers":[
        {
            "category":"Professional",
            "type":"Services"
        }
    ],
    "sg:phone":"+1 765 452 2338",
    "sg:postcode":"46901",
    "sg:province":"IN",
    "wof:name":"Junk B Gone",
    "wof:placetype":"venue"
},
  "geometry": {"coordinates":[-86.13528599999999,40.481549],"type":"Point"}
}