{
  "type": "Feature",
  "properties": {
    "iso:country":"US",
    "sg:address":"7260 Josiah Ct",
    "sg:city":"Indianapolis",
    "sg:classifiers":[
        {
            "category":"Building & Trades",
            "subcategory":"Construction",
            "type":"Services"
        }
    ],
    "sg:phone":"+1 317 862 4591",
    "sg:postcode":"46259",
    "sg:province":"IN",
    "sg:tags":[
        "home",
        "builder"
    ],
    "wof:name":"J & R Eaton Homes",
    "wof:placetype":"venue"
},
  "geometry": {"coordinates":[-86.039115,39.663597],"type":"Point"}
}