{
  "type": "Feature",
  "properties": {
    "iso:country":"US",
    "sg:address":"1415 Coliseum Blvd W",
    "sg:city":"Fort Wayne",
    "sg:classifiers":[
        {
            "category":"Shopping",
            "subcategory":"Computers & Home Electronics",
            "type":"Retail Goods"
        }
    ],
    "sg:phone":"+1 260 471 7320",
    "sg:postcode":"46808",
    "sg:province":"IN",
    "sg:tags":[
        "audio"
    ],
    "wof:name":"Concept Audio & More LLC",
    "wof:placetype":"venue"
},
  "geometry": {"coordinates":[-85.164009,41.117675],"type":"Point"}
}