{
  "type": "Feature",
  "properties": {
    "addr:full":"688 S Co Rd 925 W Logansport IN 46947",
    "addr:housenumber":"688;925",
    "addr:postcode":"46947",
    "addr:street":"S Co Rd;W Logansport",
    "iso:country":"US",
    "sg:address":"688 S Co Rd 925 W",
    "sg:city":"Logansport",
    "sg:phone":"+1 574 826 4417",
    "sg:postcode":"46947",
    "sg:province":"IN",
    "sg:tags":[
        "farm",
        "corn",
        "soybean"
    ],
    "wof:name":"Gary Berkshire",
    "wof:placetype":"venue"
},
  "geometry": {"coordinates":[-86.548148,40.754636],"type":"Point"}
}