{
  "type": "Feature",
  "properties": {
    "iso:country":"US",
    "sg:address":"1033 E 1150 S",
    "sg:city":"Ladoga",
    "sg:phone":"+1 765 866 1991",
    "sg:postcode":"47954",
    "sg:province":"IN",
    "sg:tags":[
        "wheat",
        "beef",
        "farm",
        "corn",
        "cattle",
        "feedlot"
    ],
    "wof:name":"Denis Bannon",
    "wof:placetype":"venue"
},
  "geometry": {"coordinates":[-86.88731300000001,39.873012],"type":"Point"}
}