{
  "type": "Feature",
  "properties": {
    "iso:country":"US",
    "sg:address":"125 Hunter Station Way",
    "sg:city":"Sellersburg",
    "sg:classifiers":[
        {
            "category":"Banks & Credit Unions",
            "subcategory":"Bank",
            "type":"Services"
        }
    ],
    "sg:phone":"+1 812 248 2200",
    "sg:postcode":"47172",
    "sg:province":"IN",
    "wof:name":"First Savings Bank Fsb",
    "wof:placetype":"venue"
},
  "geometry": {"coordinates":[-85.77220199999999,38.382702],"type":"Point"}
}