{
  "type": "Feature",
  "properties": {
    "iso:country":"US",
    "sg:address":"50707 Princess Way",
    "sg:city":"Granger",
    "sg:classifiers":[
        {
            "category":"Travel",
            "subcategory":"Campground",
            "type":"Entertainment"
        }
    ],
    "sg:phone":"+1 574 277 1335",
    "sg:postcode":"46530",
    "sg:province":"IN",
    "wof:name":"KOA Kampgrounds",
    "wof:placetype":"venue"
},
  "geometry": {"coordinates":[-86.116376,41.759667],"type":"Point"}
}