{
  "type": "Feature",
  "properties": {
    "addr:full":"3205 S 3rd St Terre Haute IN 47802",
    "addr:housenumber":"3205",
    "addr:postcode":"47802",
    "addr:street":"S 3Rd St",
    "iso:country":"US",
    "sg:address":"3205 S 3rd St",
    "sg:city":"Terre Haute",
    "sg:classifiers":[
        {
            "category":"Health Services",
            "subcategory":"Doctor",
            "type":"Services"
        }
    ],
    "sg:phone":"+1 812 234 9821",
    "sg:postcode":"47802",
    "sg:province":"IN",
    "sg:tags":[
        "dentist"
    ],
    "wof:name":"Cynthia L All DDS",
    "wof:placetype":"venue"
},
  "geometry": {"coordinates":[-87.415907,39.425784],"type":"Point"}
}