{
  "type": "Feature",
  "properties": {
    "iso:country":"US",
    "sg:address":"1761 E Lincoln Rd",
    "sg:city":"Kokomo",
    "sg:classifiers":[
        {
            "category":"Wholesale",
            "subcategory":"Electrical",
            "type":"Manufacturing & Wholesale Goods"
        }
    ],
    "sg:phone":"+1 765 453 5500",
    "sg:postcode":"46902",
    "sg:province":"IN",
    "sg:tags":[
        "equipment",
        "electric",
        "supply"
    ],
    "wof:name":"International Rectifier Corp",
    "wof:placetype":"venue"
},
  "geometry": {"coordinates":[-86.111856,40.455196],"type":"Point"}
}