{
  "type": "Feature",
  "properties": {
    "iso:country":"US",
    "sg:address":"816 E Auto Mall Rd",
    "sg:city":"Bloomington",
    "sg:classifiers":[
        {
            "category":"Professional",
            "subcategory":"Business Services",
            "type":"Services"
        }
    ],
    "sg:phone":"+1 812 333 6245",
    "sg:postcode":"47401",
    "sg:province":"IN",
    "sg:tags":[
        "packaging"
    ],
    "wof:name":"Pak Mail Ctr",
    "wof:placetype":"venue"
},
  "geometry": {"coordinates":[-86.49616,39.155571],"type":"Point"}
}