{
  "type": "Feature",
  "properties": {
    "iso:country":"US",
    "sg:address":"53541 Hyde Park Dr",
    "sg:city":"Bristol",
    "sg:classifiers":[
        {
            "category":"Real Estate",
            "subcategory":"Real Estate Agent",
            "type":"Services"
        }
    ],
    "sg:phone":"+1 574 264 1934",
    "sg:postcode":"46507",
    "sg:province":"IN",
    "wof:name":"C E Artley Broker",
    "wof:placetype":"venue"
},
  "geometry": {"coordinates":[-85.897777,41.717076],"type":"Point"}
}