{
  "type": "Feature",
  "properties": {
    "iso:country":"US",
    "sg:address":"1342 S Range Line Rd",
    "sg:city":"Carmel",
    "sg:classifiers":[
        {
            "category":"Restaurant",
            "type":"Food & Drink"
        }
    ],
    "sg:phone":"+1 317 848 2711",
    "sg:postcode":"46032",
    "sg:province":"IN",
    "sg:tags":[
        "caterer"
    ],
    "wof:name":"Milender Catering Svc Inc",
    "wof:placetype":"venue"
},
  "geometry": {"coordinates":[-86.126917,39.961317],"type":"Point"}
}