{
  "type": "Feature",
  "properties": {
    "iso:country":"US",
    "sg:address":"4188 Wyntree Dr",
    "sg:city":"Newburgh",
    "sg:classifiers":[
        {
            "category":"Organizations",
            "subcategory":"Religious Organization",
            "type":"Services"
        }
    ],
    "sg:phone":"+1 812 858 5800",
    "sg:postcode":"47630",
    "sg:province":"IN",
    "sg:tags":[
        "church"
    ],
    "wof:name":"Eagle's Way Church",
    "wof:placetype":"venue"
},
  "geometry": {"coordinates":[-87.39978499999999,37.976426],"type":"Point"}
}