{
  "type": "Feature",
  "properties": {
    "iso:country":"US",
    "sg:address":"55743 Willowbend Blvd",
    "sg:city":"Bristol",
    "sg:classifiers":[
        {
            "category":"Building & Trades",
            "subcategory":"Construction",
            "type":"Services"
        }
    ],
    "sg:phone":"+1 574 848 1584",
    "sg:postcode":"46507",
    "sg:province":"IN",
    "sg:tags":[
        "contractor"
    ],
    "wof:name":"Hoards Drywall",
    "wof:placetype":"venue"
},
  "geometry": {"coordinates":[-85.850202,41.685166],"type":"Point"}
}