{
  "type": "Feature",
  "properties": {
    "iso:country":"US",
    "sg:address":"3808 N 1st Ave",
    "sg:city":"Evansville",
    "sg:classifiers":[
        {
            "category":"Wholesale",
            "subcategory":"Machinery & Supplies",
            "type":"Manufacturing & Wholesale Goods"
        }
    ],
    "sg:phone":"+1 812 422 8040",
    "sg:postcode":"47710",
    "sg:province":"IN",
    "sg:tags":[
        "salon",
        "beauty"
    ],
    "wof:name":"Blondie's Supply Inc",
    "wof:placetype":"venue"
},
  "geometry": {"coordinates":[-87.574218,38.01412],"type":"Point"}
}