{
  "type": "Feature",
  "properties": {
    "iso:country":"US",
    "sg:address":"8836 W State Rd 18",
    "sg:city":"Bryant",
    "sg:classifiers":[
        {
            "category":"Building & Trades",
            "subcategory":"Construction",
            "type":"Services"
        }
    ],
    "sg:phone":"+1 260 731 4541",
    "sg:postcode":"47326",
    "sg:province":"IN",
    "sg:tags":[
        "general",
        "contractor"
    ],
    "wof:name":"Lica Construction",
    "wof:placetype":"venue"
},
  "geometry": {"coordinates":[-85.146885,40.552772],"type":"Point"}
}