{
  "type": "Feature",
  "properties": {
    "addr:full":"1207 Lincoln Way W Mishawaka IN 46544",
    "addr:housenumber":"1207",
    "addr:postcode":"46544",
    "addr:street":"Lincoln Way W",
    "iso:country":"US",
    "sg:address":"1207 Lincoln Way W",
    "sg:city":"Mishawaka",
    "sg:classifiers":[
        {
            "category":"Health Services",
            "subcategory":"Doctor",
            "type":"Services"
        }
    ],
    "sg:phone":"+1 574 255 4733",
    "sg:postcode":"46544",
    "sg:province":"IN",
    "sg:tags":[
        "physician",
        "surgeon"
    ],
    "wof:name":"Mishawaka Osteopathic Clinic",
    "wof:placetype":"venue"
},
  "geometry": {"coordinates":[-86.194982,41.65998],"type":"Point"}
}