{
  "type": "Feature",
  "properties": {
    "iso:country":"US",
    "sg:address":"1495 N Main St",
    "sg:city":"Crown Point",
    "sg:classifiers":[
        {
            "category":"Restaurant",
            "type":"Food & Drink"
        }
    ],
    "sg:menulink":"http://www.allmenus.com/in/ross/208003-taco-bell/menu/",
    "sg:phone":"+1 219 226 0484",
    "sg:postcode":"46307",
    "sg:province":"IN",
    "sg:tags":[
        "mexican"
    ],
    "wof:name":"Taco Bell",
    "wof:placetype":"venue"
},
  "geometry": {"coordinates":[-87.364717,41.437547],"type":"Point"}
}