{
  "type": "Feature",
  "properties": {
    "iso:country":"US",
    "sg:address":"13730 N 100 W",
    "sg:city":"Edinburgh",
    "sg:classifiers":[
        {
            "category":"Museum",
            "type":"Entertainment"
        }
    ],
    "sg:phone":"+1 812 526 0000",
    "sg:postcode":"46124",
    "sg:province":"IN",
    "wof:name":"Henry Breeding Farm",
    "wof:placetype":"venue"
},
  "geometry": {"coordinates":[-85.933595,39.3202],"type":"Point"}
}