{
  "type": "Feature",
  "properties": {
    "iso:country":"US",
    "sg:address":"214 E 17th St",
    "sg:city":"Huntingburg",
    "sg:classifiers":[
        {
            "category":"Health Services",
            "subcategory":"Doctor",
            "type":"Services"
        }
    ],
    "sg:phone":"+1 812 683 6345",
    "sg:postcode":"47542",
    "sg:province":"IN",
    "sg:tags":[
        "physician",
        "surgeon"
    ],
    "wof:name":"Edythe C Haygood MD",
    "wof:placetype":"venue"
},
  "geometry": {"coordinates":[-86.959369,38.311323],"type":"Point"}
}