{
  "type": "Feature",
  "properties": {
    "addr:full":"1324 N Fares Ave Evansville IN 47711",
    "addr:housenumber":"1324",
    "addr:postcode":"47711",
    "addr:street":"N Fares Ave",
    "iso:country":"US",
    "sg:address":"1324 N Fares Ave",
    "sg:city":"Evansville",
    "sg:classifiers":[
        {
            "category":"Professional",
            "subcategory":"Business Services",
            "type":"Services"
        }
    ],
    "sg:phone":"+1 812 422 3271",
    "sg:postcode":"47711",
    "sg:province":"IN",
    "sg:tags":[
        "interior",
        "consultant",
        "design",
        "decorator"
    ],
    "wof:name":"Gallagher Niemeier Interiors",
    "wof:placetype":"venue"
},
  "geometry": {"coordinates":[-87.54301100000001,37.988992],"type":"Point"}
}