{
  "type": "Feature",
  "properties": {
    "addr:full":"3040 N Huntersville Rd Batesville IN 47006",
    "addr:housenumber":"3040",
    "addr:postcode":"47006",
    "addr:street":"N Huntersville Rd",
    "iso:country":"US",
    "sg:address":"3040 N Huntersville Rd",
    "sg:city":"Batesville",
    "sg:phone":"+1 812 934 2065",
    "sg:postcode":"47006",
    "sg:province":"IN",
    "sg:tags":[
        "wheat",
        "farm",
        "corn",
        "crop",
        "field",
        "soybean"
    ],
    "wof:name":"Richard Hirt",
    "wof:placetype":"venue"
},
  "geometry": {"coordinates":[-85.24008000000001,39.346267],"type":"Point"}
}