{
  "type": "Feature",
  "properties": {
    "iso:country":"US",
    "sg:address":"5229 Coldwater Rd",
    "sg:city":"Fort Wayne",
    "sg:classifiers":[
        {
            "category":"Health Services",
            "subcategory":"Optometrist",
            "type":"Services"
        }
    ],
    "sg:phone":"+1 260 484 1453",
    "sg:postcode":"46825",
    "sg:province":"IN",
    "wof:name":"Rutan Optometry Assoc",
    "wof:placetype":"venue"
},
  "geometry": {"coordinates":[-85.135685,41.125703],"type":"Point"}
}