{
  "type": "Feature",
  "properties": {
    "iso:country":"US",
    "sg:address":"6828 NW Suburban Dr",
    "sg:city":"Michigan City",
    "sg:classifiers":[
        {
            "category":"Building & Trades",
            "subcategory":"Construction",
            "type":"Services"
        }
    ],
    "sg:phone":"+1 219 617 0605",
    "sg:postcode":"46360",
    "sg:province":"IN",
    "sg:tags":[
        "concrete",
        "contractor"
    ],
    "wof:name":"M & M Concrete",
    "wof:placetype":"venue"
},
  "geometry": {"coordinates":[-86.765805,41.707726],"type":"Point"}
}