{
  "type": "Feature",
  "properties": {
    "iso:country":"US",
    "sg:address":"6938 Burmaster Ct",
    "sg:city":"Indianapolis",
    "sg:classifiers":[
        {
            "category":"Freight",
            "type":"Transportation"
        }
    ],
    "sg:phone":"+1 317 298 1864",
    "sg:postcode":"46214",
    "sg:province":"IN",
    "sg:tags":[
        "operator",
        "local",
        "trucking"
    ],
    "wof:name":"Scorpion Trucking Co Inc",
    "wof:placetype":"venue"
},
  "geometry": {"coordinates":[-86.283124,39.815505],"type":"Point"}
}