{
  "type": "Feature",
  "properties": {
    "iso:country":"US",
    "sg:address":"6101 N Keystone Ave",
    "sg:city":"Indianapolis",
    "sg:classifiers":[
        {
            "category":"Home & Garden",
            "subcategory":"Home Furnishings",
            "type":"Retail Goods"
        }
    ],
    "sg:phone":"+1 317 254 8407",
    "sg:postcode":"46220",
    "sg:province":"IN",
    "sg:tags":[
        "housewares"
    ],
    "wof:name":"Lechter's Housewares",
    "wof:placetype":"venue"
},
  "geometry": {"coordinates":[-86.12215399999999,39.866857],"type":"Point"}
}