{
  "type": "Feature",
  "properties": {
    "iso:country":"US",
    "sg:address":"350 Tracy Rd",
    "sg:city":"New Whiteland",
    "sg:classifiers":[
        {
            "category":"Food & Beverages",
            "subcategory":"Liquor & Beverages",
            "type":"Retail Goods"
        }
    ],
    "sg:phone":"+1 317 535 8096",
    "sg:postcode":"46184",
    "sg:province":"IN",
    "wof:name":"Brew House Too",
    "wof:placetype":"venue"
},
  "geometry": {"coordinates":[-86.107394,39.564134],"type":"Point"}
}