{
  "type": "Feature",
  "properties": {
    "iso:country":"US",
    "sg:address":"2543 W Garden Dr",
    "sg:city":"Greenfield",
    "sg:classifiers":[
        {
            "category":"Building & Trades",
            "subcategory":"Electrical",
            "type":"Services"
        }
    ],
    "sg:phone":"+1 317 462 3602",
    "sg:postcode":"46140",
    "sg:province":"IN",
    "sg:tags":[
        "electrical",
        "contractor"
    ],
    "wof:name":"Grabbe Electric",
    "wof:placetype":"venue"
},
  "geometry": {"coordinates":[-85.849672,39.778384],"type":"Point"}
}