{
  "type": "Feature",
  "properties": {
    "iso:country":"US",
    "sg:address":"605 E McKinley Ave",
    "sg:city":"Mishawaka",
    "sg:classifiers":[
        {
            "category":"Professional",
            "subcategory":"Accounting & Tax Preparation",
            "type":"Services"
        }
    ],
    "sg:phone":"+1 574 259 9931",
    "sg:postcode":"46545",
    "sg:province":"IN",
    "sg:tags":[
        "accountant"
    ],
    "wof:name":"John P Husband CPA",
    "wof:placetype":"venue"
},
  "geometry": {"coordinates":[-86.17163600000001,41.680344],"type":"Point"}
}