{
  "type": "Feature",
  "properties": {
    "iso:country":"US",
    "sg:address":"2808 Brentwood Dr",
    "sg:city":"Anderson",
    "sg:classifiers":[
        {
            "category":"Professional",
            "type":"Services"
        }
    ],
    "sg:phone":"+1 765 644 5851",
    "sg:postcode":"46011",
    "sg:province":"IN",
    "wof:name":"Daughters of Isis of Nort",
    "wof:placetype":"venue"
},
  "geometry": {"coordinates":[-85.716764,40.096657],"type":"Point"}
}