{
  "type": "Feature",
  "properties": {
    "iso:country":"US",
    "sg:address":"11108 W 181st Ave",
    "sg:city":"Lowell",
    "sg:classifiers":[
        {
            "category":"Shopping",
            "subcategory":"Used Merchandise",
            "type":"Retail Goods"
        }
    ],
    "sg:phone":"+1 219 696 4669",
    "sg:postcode":"46356",
    "sg:province":"IN",
    "wof:name":"Treasure Trove Inc",
    "wof:placetype":"venue"
},
  "geometry": {"coordinates":[-87.46960900000001,41.290053],"type":"Point"}
}