{
  "type": "Feature",
  "properties": {
    "iso:country":"US",
    "sg:address":"1621 S 25th St",
    "sg:city":"Terre Haute",
    "sg:classifiers":[
        {
            "category":"Home & Garden",
            "subcategory":"Home Furnishings",
            "type":"Retail Goods"
        }
    ],
    "sg:phone":"+1 812 232 3987",
    "sg:postcode":"47803",
    "sg:province":"IN",
    "sg:tags":[
        "curtain",
        "made",
        "drapery"
    ],
    "wof:name":"Ace Blind & Drapery Svc",
    "wof:placetype":"venue"
},
  "geometry": {"coordinates":[-87.3789,39.450134],"type":"Point"}
}