{
  "type": "Feature",
  "properties": {
    "iso:country":"US",
    "sg:address":"421 Amos Rd",
    "sg:city":"Shelbyville",
    "sg:classifiers":[
        {
            "category":"Building & Trades",
            "subcategory":"Construction",
            "type":"Services"
        }
    ],
    "sg:phone":"+1 317 392 2181",
    "sg:postcode":"46176",
    "sg:province":"IN",
    "wof:name":"M & J Properties Inc",
    "wof:placetype":"venue"
},
  "geometry": {"coordinates":[-85.761786,39.520936],"type":"Point"}
}