{
  "type": "Feature",
  "properties": {
    "iso:country":"US",
    "sg:address":"4394 E US Hwy 52",
    "sg:city":"Rushville",
    "sg:classifiers":[
        {
            "category":"Autos & Motor Vehicles",
            "subcategory":"Automobile Sales",
            "type":"Retail Goods"
        }
    ],
    "sg:phone":"+1 765 932 5358",
    "sg:postcode":"46173",
    "sg:province":"IN",
    "sg:tags":[
        "car",
        "dealer"
    ],
    "wof:name":"Comer Auto Sales & Svc",
    "wof:placetype":"venue"
},
  "geometry": {"coordinates":[-85.359951,39.543468],"type":"Point"}
}