{
  "type": "Feature",
  "properties": {
    "iso:country":"US",
    "sg:address":"8200 N Ravenwood Dr",
    "sg:city":"Muncie",
    "sg:classifiers":[
        {
            "category":"Professional",
            "subcategory":"Employment Agencies",
            "type":"Services"
        }
    ],
    "sg:phone":"+1 765 282 1681",
    "sg:postcode":"47303",
    "sg:province":"IN",
    "wof:name":"Metro Tech",
    "wof:placetype":"venue"
},
  "geometry": {"coordinates":[-85.41569,40.266895],"type":"Point"}
}