{
  "type": "Feature",
  "properties": {
    "iso:country":"US",
    "sg:address":"7440 Main St NE",
    "sg:city":"Lanesville",
    "sg:classifiers":[
        {
            "category":"Restaurant",
            "type":"Food & Drink"
        }
    ],
    "sg:phone":"+1 812 952 3114",
    "sg:postcode":"47136",
    "sg:province":"IN",
    "wof:name":"K & H Cafe",
    "wof:placetype":"venue"
},
  "geometry": {"coordinates":[-85.98483400000001,38.237972],"type":"Point"}
}