{
  "type": "Feature",
  "properties": {
    "iso:country":"US",
    "sg:address":"6215 W Jefferson Blvd",
    "sg:city":"Fort Wayne",
    "sg:classifiers":[
        {
            "category":"Retail",
            "subcategory":"Car Wash",
            "type":"Services"
        }
    ],
    "sg:phone":"+1 260 436 0420",
    "sg:postcode":"46804",
    "sg:province":"IN",
    "sg:tags":[
        "polishing",
        "washing"
    ],
    "wof:name":"Mike's Car Wash Inc",
    "wof:placetype":"venue"
},
  "geometry": {"coordinates":[-85.22046400000001,41.058329],"type":"Point"}
}