{
  "type": "Feature",
  "properties": {
    "iso:country":"US",
    "sg:address":"315 SE Martin Luther King Jr Blvd",
    "sg:city":"Evansville",
    "sg:classifiers":[
        {
            "category":"Education",
            "subcategory":"School",
            "type":"Public Place"
        }
    ],
    "sg:phone":"+1 812 428 8520",
    "sg:postcode":"47713",
    "sg:province":"IN",
    "wof:name":"John F Kennedy Tower",
    "wof:placetype":"venue"
},
  "geometry": {"coordinates":[-87.565631,37.970349],"type":"Point"}
}