{
  "type": "Feature",
  "properties": {
    "iso:country":"US",
    "sg:address":"725 E Main St",
    "sg:city":"Richmond",
    "sg:classifiers":[
        {
            "category":"Shopping",
            "subcategory":"Hobbies, Toys, & Games",
            "type":"Retail Goods"
        }
    ],
    "sg:phone":"+1 765 962 4500",
    "sg:postcode":"47374",
    "sg:province":"IN",
    "sg:tags":[
        "model",
        "supply"
    ],
    "wof:name":"R T's Hobby Haus",
    "wof:placetype":"venue"
},
  "geometry": {"coordinates":[-84.89255199999999,39.828985],"type":"Point"}
}