{
  "type": "Feature",
  "properties": {
    "addr:full":"125 E Davis Dr Terre Haute IN 47802",
    "addr:housenumber":"125",
    "addr:postcode":"47802",
    "addr:street":"E Davis Dr",
    "iso:country":"US",
    "sg:address":"125 E Davis Dr",
    "sg:city":"Terre Haute",
    "sg:classifiers":[
        {
            "category":"Shopping",
            "subcategory":"Stationery & Office Supplies",
            "type":"Retail Goods"
        }
    ],
    "sg:phone":"+1 812 478 9545",
    "sg:postcode":"47802",
    "sg:province":"IN",
    "sg:website":"www.staples.com",
    "wof:name":"Staples The Office Superstore",
    "wof:placetype":"venue"
},
  "geometry": {"coordinates":[-87.41471900000001,39.42681],"type":"Point"}
}