{
  "type": "Feature",
  "properties": {
    "iso:country":"US",
    "sg:address":"8450 S US Hwy 41",
    "sg:city":"Terre Haute",
    "sg:classifiers":[
        {
            "category":"Building & Trades",
            "subcategory":"Landscaping Services",
            "type":"Services"
        }
    ],
    "sg:phone":"+1 812 299 8873",
    "sg:postcode":"47802",
    "sg:province":"IN",
    "sg:tags":[
        "landscape",
        "contractor"
    ],
    "wof:name":"Schroeder Lawn & Landscape",
    "wof:placetype":"venue"
},
  "geometry": {"coordinates":[-87.38805600000001,39.364611],"type":"Point"}
}