{
  "type": "Feature",
  "properties": {
    "iso:country":"US",
    "sg:address":"320 North Dr",
    "sg:city":"Elkhart",
    "sg:classifiers":[
        {
            "category":"Building & Trades",
            "subcategory":"Cleaning & Sanitation",
            "type":"Services"
        }
    ],
    "sg:phone":"+1 574 262 4159",
    "sg:postcode":"46514",
    "sg:province":"IN",
    "sg:tags":[
        "maintenance"
    ],
    "wof:name":"Midwest Commercial Cleaning",
    "wof:placetype":"venue"
},
  "geometry": {"coordinates":[-85.974239,41.716363],"type":"Point"}
}