{
  "type": "Feature",
  "properties": {
    "iso:country":"US",
    "sg:address":"9525 Wicker Ave",
    "sg:city":"St John",
    "sg:classifiers":[
        {
            "category":"Real Estate",
            "subcategory":"Real Estate Agent",
            "type":"Services"
        }
    ],
    "sg:phone":"+1 219 365 3146",
    "sg:postcode":"46373",
    "sg:province":"IN",
    "sg:website":"www.century21mccarthy.com",
    "wof:name":"Mc Carthy Realty Inc",
    "wof:placetype":"venue"
},
  "geometry": {"coordinates":[-87.470012,41.447304],"type":"Point"}
}