{
  "type": "Feature",
  "properties": {
    "addr:full":"9820 Crystal Cove Ct New Haven IN 46774",
    "addr:housenumber":"9820",
    "addr:postcode":"in 46774",
    "addr:street":"Crystal Cove Ct",
    "iso:country":"US",
    "sg:address":"9820 Crystal Cove Ct",
    "sg:city":"New Haven",
    "sg:classifiers":[
        {
            "category":"Real Estate",
            "subcategory":"Real Estate Agent",
            "type":"Services"
        }
    ],
    "sg:phone":"+1 260 749 4924",
    "sg:postcode":"46774",
    "sg:province":"IN",
    "wof:name":"Thomas Isenbarger",
    "wof:placetype":"venue"
},
  "geometry": {"coordinates":[-85.01422599999999,41.050873],"type":"Point"}
}