{
  "type": "Feature",
  "properties": {
    "iso:country":"US",
    "sg:address":"2798 S Morgantown Rd",
    "sg:city":"Greenwood",
    "sg:classifiers":[
        {
            "category":"Manufacturing",
            "subcategory":"Metals",
            "type":"Manufacturing & Wholesale Goods"
        },
        {
            "category":"Manufacturing",
            "subcategory":"Buildings",
            "type":"Manufacturing & Wholesale Goods"
        },
        {
            "category":"Building & Trades",
            "subcategory":"Construction",
            "type":"Services"
        }
    ],
    "sg:phone":"+1 317 422 8000",
    "sg:postcode":"46143",
    "sg:province":"IN",
    "sg:tags":[
        "steel",
        "home",
        "builder",
        "erectors",
        "contractor"
    ],
    "sg:website":"http://www.jdccontractors.com",
    "wof:name":"J DC Associates Inc",
    "wof:placetype":"venue"
},
  "geometry": {"coordinates":[-86.196917,39.574298],"type":"Point"}
}