{
  "type": "Feature",
  "properties": {
    "addr:full":"1102 15th St Bedford IN 47421",
    "addr:housenumber":"1102",
    "addr:postcode":"47421",
    "addr:street":"15Th St",
    "iso:country":"US",
    "sg:address":"1102 15th St",
    "sg:city":"Bedford",
    "sg:classifiers":[
        {
            "category":"Organizations",
            "subcategory":"Community Association",
            "type":"Services"
        }
    ],
    "sg:phone":"+1 812 275 3557",
    "sg:postcode":"47421",
    "sg:province":"IN",
    "sg:tags":[
        "fraternal"
    ],
    "wof:name":"Elks Lodge",
    "wof:placetype":"venue"
},
  "geometry": {"coordinates":[-86.48571699999999,38.862065],"type":"Point"}
}