{
  "type": "Feature",
  "properties": {
    "iso:country":"US",
    "sg:address":"3377 N State Rd 57",
    "sg:city":"Petersburg",
    "sg:classifiers":[
        {
            "category":"Retail",
            "subcategory":"Repair Shop",
            "type":"Services"
        }
    ],
    "sg:phone":"+1 812 354 8899",
    "sg:postcode":"47567",
    "sg:province":"IN",
    "sg:tags":[
        "welding"
    ],
    "wof:name":"Onyett Fabricators Inc",
    "wof:placetype":"venue"
},
  "geometry": {"coordinates":[-87.295826,38.465597],"type":"Point"}
}