{
  "type": "Feature",
  "properties": {
    "iso:country":"US",
    "sg:address":"252 Spring St",
    "sg:city":"Jeffersonville",
    "sg:classifiers":[
        {
            "category":"Shopping",
            "subcategory":"Used Merchandise",
            "type":"Retail Goods"
        }
    ],
    "sg:phone":"+1 812 284 5339",
    "sg:postcode":"47130",
    "sg:province":"IN",
    "sg:tags":[
        "antique"
    ],
    "wof:name":"Sam Cox Antiques",
    "wof:placetype":"venue"
},
  "geometry": {"coordinates":[-85.739966,38.271282],"type":"Point"}
}