{
  "type": "Feature",
  "properties": {
    "iso:country":"US",
    "sg:address":"1100 W 350 S",
    "sg:city":"Shelbyville",
    "sg:classifiers":[
        {
            "category":"Real Estate",
            "subcategory":"Real Estate Operator",
            "type":"Services"
        }
    ],
    "sg:phone":"+1 317 392 2979",
    "sg:postcode":"46176",
    "sg:province":"IN",
    "sg:tags":[
        "farm",
        "corn",
        "property",
        "soybean",
        "lessor"
    ],
    "wof:name":"Harold Fix",
    "wof:placetype":"venue"
},
  "geometry": {"coordinates":[-85.80095300000001,39.475522],"type":"Point"}
}