{
  "type": "Feature",
  "properties": {
    "iso:country":"US",
    "sg:address":"510 W Main St",
    "sg:city":"Newburgh",
    "sg:classifiers":[
        {
            "category":"Shopping",
            "subcategory":"Used Merchandise",
            "type":"Retail Goods"
        }
    ],
    "sg:phone":"+1 812 853 8707",
    "sg:postcode":"47630",
    "sg:province":"IN",
    "sg:tags":[
        "antique"
    ],
    "wof:name":"Stems N Gems Antq Collectibles",
    "wof:placetype":"venue"
},
  "geometry": {"coordinates":[-87.412436,37.947492],"type":"Point"}
}