{
  "type": "Feature",
  "properties": {
    "iso:country":"US",
    "sg:address":"5751 W 73rd St",
    "sg:city":"Indianapolis",
    "sg:classifiers":[
        {
            "category":"Professional",
            "type":"Services"
        }
    ],
    "sg:phone":"+1 317 216 7988",
    "sg:postcode":"46278",
    "sg:province":"IN",
    "sg:tags":[
        "establishment"
    ],
    "wof:name":"Action Micro Technologies Inc",
    "wof:placetype":"venue"
},
  "geometry": {"coordinates":[-86.264959,39.884795],"type":"Point"}
}