{
  "type": "Feature",
  "properties": {
    "iso:country":"US",
    "sg:address":"5901 Scatterfield Rd",
    "sg:city":"Anderson",
    "sg:classifiers":[
        {
            "category":"Travel",
            "subcategory":"Hotels & Motels",
            "type":"Entertainment"
        }
    ],
    "sg:phone":"+1 765 649 5484",
    "sg:postcode":"46013",
    "sg:province":"IN",
    "wof:name":"Anderson Inns Inc",
    "wof:placetype":"venue"
},
  "geometry": {"coordinates":[-85.653051,40.060948],"type":"Point"}
}