{
  "type": "Feature",
  "properties": {
    "iso:country":"US",
    "sg:address":"10815 Pendleton Pike",
    "sg:city":"Indianapolis",
    "sg:classifiers":[
        {
            "category":"Restaurant",
            "type":"Food & Drink"
        }
    ],
    "sg:menulink":"http://www.allmenus.com/in/lawrence/151615-aw-restaurant/menu/",
    "sg:phone":"+1 317 826 0298",
    "sg:postcode":"46236",
    "sg:province":"IN",
    "sg:tags":[
        "burger",
        "american",
        "dog",
        "pub",
        "hot"
    ],
    "wof:name":"A&W Restaurant",
    "wof:placetype":"venue"
},
  "geometry": {"coordinates":[-85.975651,39.860648],"type":"Point"}
}