{
  "type": "Feature",
  "properties": {
    "iso:country":"US",
    "sg:address":"501 E Monroe St",
    "sg:city":"South Bend",
    "sg:classifiers":[
        {
            "category":"Government",
            "subcategory":"Office",
            "type":"Public Place"
        }
    ],
    "sg:phone":"+1 574 236 8100",
    "sg:postcode":"46601",
    "sg:province":"IN",
    "sg:tags":[
        "federal",
        "security"
    ],
    "wof:name":"US Defense Contract Adm Svc",
    "wof:placetype":"venue"
},
  "geometry": {"coordinates":[-86.243304,41.67095],"type":"Point"}
}