{
  "type": "Feature",
  "properties": {
    "iso:country":"US",
    "sg:address":"1935 Old State Rd",
    "sg:city":"Corydon",
    "sg:classifiers":[
        {
            "category":"Shopping",
            "type":"Retail Goods"
        }
    ],
    "sg:phone":"+1 812 734 0296",
    "sg:postcode":"47126",
    "sg:province":"IN",
    "sg:tags":[
        "merchandise"
    ],
    "wof:name":"Tractor Supply 617",
    "wof:placetype":"venue"
},
  "geometry": {"coordinates":[-85.757029,38.570198],"type":"Point"}
}