{
  "type": "Feature",
  "properties": {
    "iso:country":"US",
    "sg:address":"353 W 3rd St",
    "sg:city":"Connersville",
    "sg:classifiers":[
        {
            "category":"Real Estate",
            "subcategory":"Real Estate Agent",
            "type":"Services"
        }
    ],
    "sg:phone":"+1 765 825 4668",
    "sg:postcode":"47331",
    "sg:province":"IN",
    "sg:tags":[
        "authorities",
        "housing"
    ],
    "wof:name":"Fayette County Housing Auth",
    "wof:placetype":"venue"
},
  "geometry": {"coordinates":[-85.144623,39.640353],"type":"Point"}
}