{
  "type": "Feature",
  "properties": {
    "addr:full":"10 Spring Lake Dr Westfield IN 46074",
    "addr:housenumber":"10",
    "addr:postcode":"46074",
    "addr:street":"Spring Lake Dr",
    "iso:country":"US",
    "sg:address":"10 Spring Lake Dr",
    "sg:city":"Westfield",
    "sg:classifiers":[
        {
            "category":"Retail",
            "subcategory":"Pet Boarding",
            "type":"Services"
        }
    ],
    "sg:phone":"+1 317 867 6363",
    "sg:postcode":"46074",
    "sg:province":"IN",
    "sg:tags":[
        "boarding/pet",
        "sitting"
    ],
    "sg:website":"www.thecarmelpetsitter.com",
    "wof:name":"The Carmel Pet Sitter, Llc",
    "wof:placetype":"venue"
},
  "geometry": {"coordinates":[-86.155967,40.033983],"type":"Point"}
}