{
  "type": "Feature",
  "properties": {
    "iso:country":"US",
    "sg:address":"2626 N State Rd 39",
    "sg:city":"Laporte",
    "sg:classifiers":[
        {
            "category":"Building & Trades",
            "subcategory":"Construction",
            "type":"Services"
        }
    ],
    "sg:phone":"+1 219 362 3390",
    "sg:postcode":"46350",
    "sg:province":"IN",
    "sg:tags":[
        "general",
        "contractor"
    ],
    "wof:name":"Harold Knoll & Son General",
    "wof:placetype":"venue"
},
  "geometry": {"coordinates":[-86.738363,41.63717],"type":"Point"}
}