{
  "type": "Feature",
  "properties": {
    "iso:country":"US",
    "sg:address":"3758 S Meridian Rd",
    "sg:city":"Morocco",
    "sg:classifiers":[
        {
            "category":"Building & Trades",
            "subcategory":"Construction",
            "type":"Services"
        }
    ],
    "sg:phone":"+1 219 285 6314",
    "sg:postcode":"47963",
    "sg:province":"IN",
    "sg:tags":[
        "masonry",
        "contractor"
    ],
    "wof:name":"All American Masonry Inc",
    "wof:placetype":"venue"
},
  "geometry": {"coordinates":[-87.39264799999999,40.944079],"type":"Point"}
}