{
  "type": "Feature",
  "properties": {
    "iso:country":"US",
    "sg:address":"439 E Lincoln Rd",
    "sg:city":"Kokomo",
    "sg:classifiers":[
        {
            "category":"Food & Beverages",
            "subcategory":"Groceries & Convenience Stores",
            "type":"Retail Goods"
        }
    ],
    "sg:phone":"+1 765 865 9788",
    "sg:postcode":"46902",
    "sg:province":"IN",
    "sg:tags":[
        "grocer"
    ],
    "wof:name":"Enternal Prosperity",
    "wof:placetype":"venue"
},
  "geometry": {"coordinates":[-86.12387,40.455097],"type":"Point"}
}