{
  "type": "Feature",
  "properties": {
    "iso:country":"US",
    "sg:address":"826 S Adams St",
    "sg:city":"Versailles",
    "sg:classifiers":[
        {
            "category":"Restaurant",
            "type":"Food & Drink"
        }
    ],
    "sg:phone":"+1 812 689 5776",
    "sg:postcode":"47042",
    "sg:province":"IN",
    "sg:tags":[
        "caterer"
    ],
    "wof:name":"Rolling Pin Catering",
    "wof:placetype":"venue"
},
  "geometry": {"coordinates":[-85.25577,39.063086],"type":"Point"}
}