{
  "type": "Feature",
  "properties": {
    "addr:full":"57766 Co Rd 3 Elkhart IN 46517",
    "addr:housenumber":"57766",
    "addr:postcode":"46517",
    "addr:street":"Co Rd 3",
    "iso:country":"US",
    "sg:address":"57766 Co Rd 3",
    "sg:city":"Elkhart",
    "sg:classifiers":[
        {
            "category":"Home & Garden",
            "subcategory":"Home Furnishings",
            "type":"Retail Goods"
        }
    ],
    "sg:phone":"+1 574 522 0871",
    "sg:postcode":"46517",
    "sg:province":"IN",
    "sg:tags":[
        "lighting"
    ],
    "sg:website":"www.gustafsonlighting.com",
    "wof:name":"R B Gustafson Co",
    "wof:placetype":"venue"
},
  "geometry": {"coordinates":[-86.022351,41.655496],"type":"Point"}
}