{
  "type": "Feature",
  "properties": {
    "iso:country":"US",
    "sg:address":"2549 Portage Mall",
    "sg:city":"Portage",
    "sg:classifiers":[
        {
            "category":"Retail",
            "subcategory":"Repair Shop",
            "type":"Services"
        }
    ],
    "sg:phone":"+1 219 762 9181",
    "sg:postcode":"46368",
    "sg:province":"IN",
    "sg:tags":[
        "television",
        "radio"
    ],
    "wof:name":"John's Radio & TV",
    "wof:placetype":"venue"
},
  "geometry": {"coordinates":[-87.17635900000001,41.577812],"type":"Point"}
}