{
  "type": "Feature",
  "properties": {
    "addr:full":"121 N Main St Tipton IN 46072",
    "addr:housenumber":"121",
    "addr:postcode":"46072",
    "addr:street":"N Main St",
    "iso:country":"US",
    "sg:address":"121 N Main St",
    "sg:city":"Tipton",
    "sg:classifiers":[
        {
            "category":"Organizations",
            "subcategory":"Non-profit Organization",
            "type":"Services"
        }
    ],
    "sg:phone":"+1 765 675 6715",
    "sg:postcode":"46072",
    "sg:province":"IN",
    "sg:tags":[
        "human"
    ],
    "wof:name":"Habitat For Humanity",
    "wof:placetype":"venue"
},
  "geometry": {"coordinates":[-86.041178,40.283288],"type":"Point"}
}