{
  "type": "Feature",
  "properties": {
    "iso:country":"US",
    "sg:address":"5296 E 65th St",
    "sg:city":"Indianapolis",
    "sg:classifiers":[
        {
            "category":"Manufacturing",
            "subcategory":"Printing",
            "type":"Manufacturing & Wholesale Goods"
        }
    ],
    "sg:phone":"+1 317 849 5528",
    "sg:postcode":"46220",
    "sg:province":"IN",
    "sg:tags":[
        "commercial"
    ],
    "sg:website":"www.uniqueprinting.com",
    "wof:name":"Unique Printing & Labels Inc",
    "wof:placetype":"venue"
},
  "geometry": {"coordinates":[-86.08337400000001,39.876017],"type":"Point"}
}