{
  "type": "Feature",
  "properties": {
    "iso:country":"US",
    "sg:address":"3040 Claremont Ave",
    "sg:city":"Evansville",
    "sg:classifiers":[
        {
            "category":"Freight",
            "type":"Transportation"
        }
    ],
    "sg:phone":"+1 812 423 9940",
    "sg:postcode":"47712",
    "sg:province":"IN",
    "sg:tags":[
        "trucking"
    ],
    "sg:website":"www.ozark.com",
    "wof:name":"Ozark Motor Lines",
    "wof:placetype":"venue"
},
  "geometry": {"coordinates":[-87.611705,37.971243],"type":"Point"}
}