{
  "type": "Feature",
  "properties": {
    "iso:country":"US",
    "sg:address":"7780 Michigan Rd",
    "sg:city":"Indianapolis",
    "sg:classifiers":[
        {
            "category":"Shopping",
            "subcategory":"Shoes",
            "type":"Retail Goods"
        }
    ],
    "sg:phone":"+1 317 872 3075",
    "sg:postcode":"46268",
    "sg:province":"IN",
    "wof:name":"Institute Of Biomechanics Inc",
    "wof:placetype":"venue"
},
  "geometry": {"coordinates":[-86.214156,39.893364],"type":"Point"}
}