{
  "type": "Feature",
  "properties": {
    "iso:country":"US",
    "sg:address":"5125 W 10th St",
    "sg:city":"Indianapolis",
    "sg:classifiers":[
        {
            "category":"Professional",
            "subcategory":"Business Services",
            "type":"Services"
        }
    ],
    "sg:phone":"+1 317 240 3126",
    "sg:postcode":"46224",
    "sg:province":"IN",
    "wof:name":"Jal Driveaway LLC",
    "wof:placetype":"venue"
},
  "geometry": {"coordinates":[-86.244962,39.77998],"type":"Point"}
}