{
  "type": "Feature",
  "properties": {
    "iso:country":"US",
    "sg:address":"594 S Miami St",
    "sg:city":"Wabash",
    "sg:classifiers":[
        {
            "category":"Insurance",
            "subcategory":"Insurance Agent",
            "type":"Services"
        }
    ],
    "sg:phone":"+1 260 774 3523",
    "sg:postcode":"46992",
    "sg:province":"IN",
    "sg:website":"www.infarmbureau.com",
    "wof:name":"Farm Bureau Insurance",
    "wof:placetype":"venue"
},
  "geometry": {"coordinates":[-85.821798,40.792522],"type":"Point"}
}