{
  "type": "Feature",
  "properties": {
    "addr:full":"2825 E 56th St Indianapolis IN 46220",
    "addr:housenumber":"2825",
    "addr:postcode":"46220",
    "addr:street":"E 56Th St",
    "iso:country":"US",
    "sg:address":"2825 E 56th St",
    "sg:city":"Indianapolis",
    "sg:classifiers":[
        {
            "category":"Professional",
            "subcategory":"Employment Agencies",
            "type":"Services"
        }
    ],
    "sg:phone":"+1 317 251 1135",
    "sg:postcode":"46220",
    "sg:province":"IN",
    "sg:tags":[
        "medical"
    ],
    "wof:name":"ATC Healthcare Svc",
    "wof:placetype":"venue"
},
  "geometry": {"coordinates":[-86.116101,39.854955],"type":"Point"}
}