{
  "type": "Feature",
  "properties": {
    "addr:full":"7575 Peachwood Dr Newburgh IN 47630",
    "addr:housenumber":"7575",
    "addr:postcode":"47630",
    "addr:street":"Peachwood Dr",
    "iso:country":"US",
    "sg:address":"7575 Peachwood Dr",
    "sg:city":"Newburgh",
    "sg:classifiers":[
        {
            "category":"Shopping",
            "subcategory":"Computers & Home Electronics",
            "type":"Retail Goods"
        },
        {
            "category":"Professional",
            "subcategory":"Computer Services",
            "type":"Services"
        }
    ],
    "sg:phone":"+1 812 490 7232",
    "sg:postcode":"47630",
    "sg:province":"IN",
    "sg:tags":[
        "stereo",
        "installation"
    ],
    "wof:name":"Newburgh Audio",
    "wof:placetype":"venue"
},
  "geometry": {"coordinates":[-87.388608,37.978944],"type":"Point"}
}