{
  "type": "Feature",
  "properties": {
    "iso:country":"US",
    "sg:address":"1001 N Hickory Rd",
    "sg:city":"South Bend",
    "sg:classifiers":[
        {
            "category":"Banks & Credit Unions",
            "subcategory":"Investment Brokerage",
            "type":"Services"
        }
    ],
    "sg:phone":"+1 574 288 4963",
    "sg:postcode":"46615",
    "sg:province":"IN",
    "sg:tags":[
        "advisory",
        "financial"
    ],
    "wof:name":"Achieve Financial",
    "wof:placetype":"venue"
},
  "geometry": {"coordinates":[-86.196581,41.68752],"type":"Point"}
}