{
  "type": "Feature",
  "properties": {
    "iso:country":"US",
    "sg:address":"700 Willow St Ste 200",
    "sg:city":"Vincennes",
    "sg:classifiers":[
        {
            "category":"Health Services",
            "subcategory":"Doctor",
            "type":"Services"
        }
    ],
    "sg:phone":"+1 812 885 8040",
    "sg:postcode":"47591",
    "sg:province":"IN",
    "sg:tags":[
        "physician",
        "endocrinology",
        "surgeons",
        "metabolism",
        "medicine",
        "surgeon",
        "diabetes",
        "rehabilitation",
        "physical"
    ],
    "wof:name":"Jane Bridges Md",
    "wof:placetype":"venue"
},
  "geometry": {"coordinates":[-87.53757899999999,38.677795],"type":"Point"}
}