{
  "type": "Feature",
  "properties": {
    "iso:country":"US",
    "sg:address":"4625 Round Lake Rd",
    "sg:city":"Indianapolis",
    "sg:classifiers":[
        {
            "category":"Food & Beverages",
            "subcategory":"Candy",
            "type":"Retail Goods"
        }
    ],
    "sg:phone":"+1 317 466 1263",
    "sg:postcode":"46205",
    "sg:province":"IN",
    "sg:tags":[
        "confectionery"
    ],
    "wof:name":"Shelly's Candy Store",
    "wof:placetype":"venue"
},
  "geometry": {"coordinates":[-86.118253,39.840991],"type":"Point"}
}