{
  "type": "Feature",
  "properties": {
    "iso:country":"US",
    "sg:address":"10333 N Meridian St",
    "sg:city":"Indianapolis",
    "sg:classifiers":[
        {
            "category":"Professional",
            "subcategory":"Lawyer & Legal Services",
            "type":"Services"
        }
    ],
    "sg:phone":"+1 317 844 9999",
    "sg:postcode":"46290",
    "sg:province":"IN",
    "wof:name":"Doehrman Chamberlain Atty",
    "wof:placetype":"venue"
},
  "geometry": {"coordinates":[-86.15770000000001,39.936798],"type":"Point"}
}