{
  "type": "Feature",
  "properties": {
    "iso:country":"US",
    "sg:address":"134 N 3rd St",
    "sg:city":"Boonville",
    "sg:classifiers":[
        {
            "category":"Organizations",
            "subcategory":"Community Association",
            "type":"Services"
        }
    ],
    "sg:phone":"+1 812 897 1180",
    "sg:postcode":"47601",
    "sg:province":"IN",
    "sg:tags":[
        "fraternal"
    ],
    "wof:name":"Elks Lodge",
    "wof:placetype":"venue"
},
  "geometry": {"coordinates":[-87.27433499999999,38.050011],"type":"Point"}
}