{
  "type": "Feature",
  "properties": {
    "iso:country":"US",
    "sg:address":"1057 E Co Rd 325 N",
    "sg:city":"Greencastle",
    "sg:classifiers":[
        {
            "category":"Real Estate",
            "subcategory":"Real Estate Operator",
            "type":"Services"
        }
    ],
    "sg:phone":"+1 765 653 3852",
    "sg:postcode":"46135",
    "sg:province":"IN",
    "sg:tags":[
        "property",
        "lessor"
    ],
    "wof:name":"Sam Goad",
    "wof:placetype":"venue"
},
  "geometry": {"coordinates":[-86.830967,39.708543],"type":"Point"}
}