{
  "type": "Feature",
  "properties": {
    "iso:country":"US",
    "sg:address":"410 S Spring St",
    "sg:city":"Mishawaka",
    "sg:classifiers":[
        {
            "category":"Shopping",
            "subcategory":"Hobbies, Toys, & Games",
            "type":"Retail Goods"
        }
    ],
    "sg:phone":"+1 574 252 7245",
    "sg:postcode":"46544",
    "sg:province":"IN",
    "sg:tags":[
        "model",
        "supply"
    ],
    "wof:name":"Mishawaka Rail Yard",
    "wof:placetype":"venue"
},
  "geometry": {"coordinates":[-86.18321,41.656999],"type":"Point"}
}