{
  "type": "Feature",
  "properties": {
    "iso:country":"US",
    "sg:address":"1221 Drover St",
    "sg:city":"Indianapolis",
    "sg:classifiers":[
        {
            "category":"Professional",
            "subcategory":"Business Services",
            "type":"Services"
        }
    ],
    "sg:phone":"+1 317 972 1436",
    "sg:postcode":"46221",
    "sg:province":"IN",
    "sg:tags":[
        "auctioneer"
    ],
    "wof:name":"Aucton On Drover Street",
    "wof:placetype":"venue"
},
  "geometry": {"coordinates":[-86.176247,39.748126],"type":"Point"}
}