{
  "type": "Feature",
  "properties": {
    "iso:country":"US",
    "sg:address":"8201 Madison Ave",
    "sg:city":"Indianapolis",
    "sg:classifiers":[
        {
            "category":"Real Estate",
            "subcategory":"Real Estate Operator",
            "type":"Services"
        }
    ],
    "sg:phone":"+1 317 889 3100",
    "sg:postcode":"46227",
    "sg:province":"IN",
    "sg:tags":[
        "apartment"
    ],
    "wof:name":"Berkley Commons Apartments",
    "wof:placetype":"venue"
},
  "geometry": {"coordinates":[-86.12022399999999,39.645479],"type":"Point"}
}