{
  "type": "Feature",
  "properties": {
    "iso:country":"US",
    "sg:address":"20 W Walnut St",
    "sg:city":"Hagerstown",
    "sg:classifiers":[
        {
            "category":"Professional",
            "subcategory":"Lawyer & Legal Services",
            "type":"Services"
        }
    ],
    "sg:phone":"+1 765 489 4535",
    "sg:postcode":"47346",
    "sg:province":"IN",
    "sg:tags":[
        "attorney"
    ],
    "wof:name":"Federico Law Office",
    "wof:placetype":"venue"
},
  "geometry": {"coordinates":[-85.162178,39.91006],"type":"Point"}
}