{
  "type": "Feature",
  "properties": {
    "addr:full":"2004 Dayton Ave Indianapolis IN 46203",
    "addr:housenumber":"2004",
    "addr:postcode":"46203",
    "addr:street":"Dayton Ave",
    "iso:country":"US",
    "sg:address":"2004 Dayton Ave",
    "sg:city":"Indianapolis",
    "sg:classifiers":[
        {
            "category":"Social Services",
            "subcategory":"Child Care",
            "type":"Services"
        }
    ],
    "sg:phone":"+1 317 375 3700",
    "sg:postcode":"46203",
    "sg:province":"IN",
    "wof:name":"Masada Child Care",
    "wof:placetype":"venue"
},
  "geometry": {"coordinates":[-86.09056,39.741648],"type":"Point"}
}