{
  "type": "Feature",
  "properties": {
    "iso:country":"US",
    "sg:address":"110 W National Ave",
    "sg:city":"Brazil",
    "sg:classifiers":[
        {
            "category":"Home & Garden",
            "subcategory":"Carpets & Floor Coverings",
            "type":"Retail Goods"
        }
    ],
    "sg:phone":"+1 812 443 4071",
    "sg:postcode":"47834",
    "sg:province":"IN",
    "sg:tags":[
        "dealer",
        "rug"
    ],
    "wof:name":"Mc Curdy's Decorating Ctr",
    "wof:placetype":"venue"
},
  "geometry": {"coordinates":[-87.128048,39.523066],"type":"Point"}
}