{
  "type": "Feature",
  "properties": {
    "addr:full":"3919 Lafayette Rd Indianapolis IN 46254",
    "addr:housenumber":"3919",
    "addr:postcode":"46254",
    "iso:country":"US",
    "sg:address":"3919 Lafayette Rd",
    "sg:city":"Indianapolis",
    "sg:classifiers":[
        {
            "category":"Real Estate",
            "subcategory":"Real Estate Operator",
            "type":"Services"
        }
    ],
    "sg:phone":"+1 317 291 6390",
    "sg:postcode":"46254",
    "sg:province":"IN",
    "sg:tags":[
        "mall",
        "shopping",
        "center"
    ],
    "wof:name":"Lafayette Square",
    "wof:placetype":"venue"
},
  "geometry": {"coordinates":[-86.238894,39.827877],"type":"Point"}
}