{
  "type": "Feature",
  "properties": {
    "iso:country":"US",
    "sg:address":"555 E Olmstead Ave",
    "sg:city":"Evansville",
    "sg:classifiers":[
        {
            "category":"Professional",
            "type":"Services"
        }
    ],
    "sg:phone":"+1 812 437 6972",
    "sg:postcode":"47711",
    "sg:province":"IN",
    "wof:name":"Internet Services Internationa",
    "wof:placetype":"venue"
},
  "geometry": {"coordinates":[-87.55549499999999,38.004724],"type":"Point"}
}