{
  "type": "Feature",
  "properties": {
    "iso:country":"US",
    "sg:address":"646 W 38th St",
    "sg:city":"Indianapolis",
    "sg:classifiers":[
        {
            "category":"Restaurant",
            "type":"Food & Drink"
        }
    ],
    "sg:phone":"+1 317 927 7044",
    "sg:postcode":"46208",
    "sg:province":"IN",
    "sg:tags":[
        "eating"
    ],
    "wof:name":"Baileys Restaurant",
    "wof:placetype":"venue"
},
  "geometry": {"coordinates":[-86.17052700000001,39.824878],"type":"Point"}
}