{
  "type": "Feature",
  "properties": {
    "iso:country":"US",
    "sg:address":"2024 E 12th St",
    "sg:city":"Indianapolis",
    "sg:classifiers":[
        {
            "category":"Social Services",
            "subcategory":"Child Care",
            "type":"Services"
        }
    ],
    "sg:phone":"+1 317 638 6838",
    "sg:postcode":"46201",
    "sg:province":"IN",
    "sg:tags":[
        "kindergarten",
        "academic",
        "school"
    ],
    "wof:name":"Near Eastside Christian School",
    "wof:placetype":"venue"
},
  "geometry": {"coordinates":[-86.125418,39.783989],"type":"Point"}
}