{
  "type": "Feature",
  "properties": {
    "iso:country":"US",
    "sg:address":"900 N Baker Rd",
    "sg:city":"Boonville",
    "sg:classifiers":[
        {
            "category":"Wholesale",
            "subcategory":"Machinery & Supplies",
            "type":"Manufacturing & Wholesale Goods"
        }
    ],
    "sg:phone":"+1 812 897 8888",
    "sg:postcode":"47601",
    "sg:province":"IN",
    "sg:tags":[
        "water",
        "material",
        "works"
    ],
    "wof:name":"J & J Municipal Supply Inc",
    "wof:placetype":"venue"
},
  "geometry": {"coordinates":[-87.32011300000001,38.047838],"type":"Point"}
}