{
  "type": "Feature",
  "properties": {
    "iso:country":"US",
    "sg:address":"575 E Business 30",
    "sg:city":"Columbia City",
    "sg:classifiers":[
        {
            "category":"Personal",
            "subcategory":"Beauty Salon",
            "type":"Services"
        }
    ],
    "sg:phone":"+1 260 244 5500",
    "sg:postcode":"46725",
    "sg:province":"IN",
    "wof:name":"Headquarters East",
    "wof:placetype":"venue"
},
  "geometry": {"coordinates":[-85.479483,41.148052],"type":"Point"}
}