{
  "type": "Feature",
  "properties": {
    "iso:country":"US",
    "sg:address":"3612 Seilo Ridge N",
    "sg:city":"Jeffersonville",
    "sg:classifiers":[
        {
            "category":"Freight",
            "type":"Transportation"
        }
    ],
    "sg:phone":"+1 812 284 2390",
    "sg:postcode":"47130",
    "sg:province":"IN",
    "sg:tags":[
        "operator",
        "local",
        "trucking"
    ],
    "wof:name":"Leuthart Trucking Inc",
    "wof:placetype":"venue"
},
  "geometry": {"coordinates":[-85.70147,38.325145],"type":"Point"}
}