{
  "type": "Feature",
  "properties": {
    "iso:country":"US",
    "sg:address":"1826 W Main St",
    "sg:city":"Fort Wayne",
    "sg:classifiers":[
        {
            "category":"Personal",
            "subcategory":"Beauty Salon",
            "type":"Services"
        }
    ],
    "sg:phone":"+1 260 424 1516",
    "sg:postcode":"46808",
    "sg:province":"IN",
    "wof:name":"Earl's Beauty Station",
    "wof:placetype":"venue"
},
  "geometry": {"coordinates":[-85.16739800000001,41.078595],"type":"Point"}
}