{
  "type": "Feature",
  "properties": {
    "iso:country":"US",
    "sg:address":"1296 W 300 N",
    "sg:city":"Bluffton",
    "sg:classifiers":[
        {
            "category":"Building & Trades",
            "subcategory":"Electrical",
            "type":"Services"
        }
    ],
    "sg:phone":"+1 260 543 2243",
    "sg:postcode":"46714",
    "sg:province":"IN",
    "sg:tags":[
        "electrical",
        "electric",
        "contractor"
    ],
    "wof:name":"Dettmer Electric Inc",
    "wof:placetype":"venue"
},
  "geometry": {"coordinates":[-85.247406,40.78575],"type":"Point"}
}