{
  "type": "Feature",
  "properties": {
    "iso:country":"US",
    "sg:address":"8826 S 750 W",
    "sg:city":"Holland",
    "sg:classifiers":[
        {
            "category":"Utilities",
            "subcategory":"Water",
            "type":"Services"
        }
    ],
    "sg:phone":"+1 812 536 3641",
    "sg:postcode":"47541",
    "sg:province":"IN",
    "sg:tags":[
        "company",
        "sewage"
    ],
    "wof:name":"Holland Water Plant",
    "wof:placetype":"venue"
},
  "geometry": {"coordinates":[-87.045147,38.248972],"type":"Point"}
}