{
  "type": "Feature",
  "properties": {
    "iso:country":"US",
    "sg:address":"871 E Davis Rd",
    "sg:city":"Greenfield",
    "sg:classifiers":[
        {
            "category":"Sports & Exercise",
            "subcategory":"Golf",
            "type":"Entertainment"
        }
    ],
    "sg:phone":"+1 317 462 7813",
    "sg:postcode":"46140",
    "sg:province":"IN",
    "sg:tags":[
        "course"
    ],
    "wof:name":"Shekinah On The Brandywine",
    "wof:placetype":"venue"
},
  "geometry": {"coordinates":[-85.755576,39.771865],"type":"Point"}
}