{
  "type": "Feature",
  "properties": {
    "iso:country":"US",
    "sg:address":"556 S Maple St",
    "sg:city":"French Lick",
    "sg:classifiers":[
        {
            "category":"Real Estate",
            "subcategory":"Real Estate Operator",
            "type":"Services"
        }
    ],
    "sg:phone":"+1 812 936 2800",
    "sg:postcode":"47432",
    "sg:province":"IN",
    "sg:tags":[
        "apartment"
    ],
    "wof:name":"Camelot Court Of French Lick",
    "wof:placetype":"venue"
},
  "geometry": {"coordinates":[-86.62024,38.54602],"type":"Point"}
}