{
  "type": "Feature",
  "properties": {
    "iso:country":"US",
    "sg:address":"7375 Ralston Ave",
    "sg:city":"Indianapolis",
    "sg:classifiers":[
        {
            "category":"Personal",
            "subcategory":"Beauty Salon",
            "type":"Services"
        },
        {
            "category":"Personal",
            "subcategory":"Skin Care",
            "type":"Services"
        }
    ],
    "sg:phone":"+1 317 257 4954",
    "sg:postcode":"46240",
    "sg:province":"IN",
    "sg:tags":[
        "cosmetologist",
        "cosmetic"
    ],
    "wof:name":"Kimberly Wright",
    "wof:placetype":"venue"
},
  "geometry": {"coordinates":[-86.13127900000001,39.889515],"type":"Point"}
}