{
  "type": "Feature",
  "properties": {
    "iso:country":"US",
    "sg:address":"511 Eastern Blvd",
    "sg:city":"Clarksville",
    "sg:classifiers":[
        {
            "category":"Home & Garden",
            "subcategory":"Carpets & Floor Coverings",
            "type":"Retail Goods"
        }
    ],
    "sg:phone":"+1 812 282 3020",
    "sg:postcode":"47130",
    "sg:province":"IN",
    "wof:name":"Clarksville Carpet Outlet",
    "wof:placetype":"venue"
},
  "geometry": {"coordinates":[-85.760574,38.297475],"type":"Point"}
}