{
  "type": "Feature",
  "properties": {
    "iso:country":"US",
    "sg:address":"1633 Kehoe Ln",
    "sg:city":"Jeffersonville",
    "sg:classifiers":[
        {
            "category":"Restaurant",
            "type":"Food & Drink"
        }
    ],
    "sg:phone":"+1 812 283 1195",
    "sg:postcode":"47130",
    "sg:province":"IN",
    "sg:tags":[
        "eating"
    ],
    "wof:name":"Moreland Catering",
    "wof:placetype":"venue"
},
  "geometry": {"coordinates":[-85.721977,38.299724],"type":"Point"}
}