{
  "type": "Feature",
  "properties": {
    "iso:country":"US",
    "sg:address":"450 N 14th St",
    "sg:city":"New Castle",
    "sg:classifiers":[
        {
            "category":"Organizations",
            "subcategory":"Labor Organization",
            "type":"Services"
        }
    ],
    "sg:phone":"+1 765 529 4690",
    "sg:postcode":"47362",
    "sg:province":"IN",
    "wof:name":"Uswa Local",
    "wof:placetype":"venue"
},
  "geometry": {"coordinates":[-85.36876700000001,39.935882],"type":"Point"}
}