{
  "type": "Feature",
  "properties": {
    "iso:country":"US",
    "sg:address":"225 E State St",
    "sg:city":"Albany",
    "sg:classifiers":[
        {
            "category":"Utilities",
            "subcategory":"Water",
            "type":"Services"
        }
    ],
    "sg:phone":"+1 765 789 4343",
    "sg:postcode":"47320",
    "sg:province":"IN",
    "sg:tags":[
        "company",
        "sewage"
    ],
    "wof:name":"Albany City Water Works",
    "wof:placetype":"venue"
},
  "geometry": {"coordinates":[-85.23532899999999,40.299716],"type":"Point"}
}