{
  "type": "Feature",
  "properties": {
    "iso:country":"US",
    "sg:address":"348 Vine St",
    "sg:city":"Clinton",
    "sg:classifiers":[
        {
            "category":"Personal",
            "subcategory":"Beauty Salon",
            "type":"Services"
        }
    ],
    "sg:phone":"+1 765 832 2170",
    "sg:postcode":"47842",
    "sg:province":"IN",
    "wof:name":"Laurel Lee's Beauty Shop",
    "wof:placetype":"venue"
},
  "geometry": {"coordinates":[-87.400582,39.660395],"type":"Point"}
}