{
  "type": "Feature",
  "properties": {
    "addr:full":"8815 N Co Rd 600 W Muncie IN 47304",
    "addr:housenumber":"8815",
    "addr:postcode":"47304",
    "addr:street":"N Co Rd 600 W",
    "iso:country":"US",
    "sg:address":"8815 N Co Rd 600 W",
    "sg:city":"Muncie",
    "sg:classifiers":[
        {
            "category":"Real Estate",
            "subcategory":"Real Estate Operator",
            "type":"Services"
        }
    ],
    "sg:phone":"+1 765 358 4551",
    "sg:postcode":"47304",
    "sg:province":"IN",
    "sg:tags":[
        "mobile",
        "home",
        "site",
        "community"
    ],
    "wof:name":"Edgeman Lake Mobile Home Park",
    "wof:placetype":"venue"
},
  "geometry": {"coordinates":[-85.500693,40.26804],"type":"Point"}
}