{
  "type": "Feature",
  "properties": {
    "iso:country":"US",
    "sg:address":"650 S Eisenhower Dr",
    "sg:city":"Edinburgh",
    "sg:classifiers":[
        {
            "category":"Government",
            "subcategory":"Office",
            "type":"Public Place"
        }
    ],
    "sg:phone":"+1 812 526 3529",
    "sg:postcode":"46124",
    "sg:province":"IN",
    "sg:tags":[
        "village"
    ],
    "wof:name":"Resthaven Municipal Cemetery",
    "wof:placetype":"venue"
},
  "geometry": {"coordinates":[-85.970302,39.349153],"type":"Point"}
}