{
  "type": "Feature",
  "properties": {
    "iso:country":"US",
    "sg:address":"6391 W 750 N",
    "sg:city":"Mc Cordsville",
    "sg:phone":"+1 317 335 3725",
    "sg:postcode":"46055",
    "sg:province":"IN",
    "sg:tags":[
        "farm",
        "corn",
        "soybean"
    ],
    "wof:name":"David Boucher",
    "wof:placetype":"venue"
},
  "geometry": {"coordinates":[-85.926627,39.891509],"type":"Point"}
}