{
  "type": "Feature",
  "properties": {
    "addr:full":"7856 Interstate Plaza Dr Hammond IN 46324",
    "addr:housenumber":"7856",
    "addr:postcode":"46324",
    "addr:street":"Interstate Plaza Dr",
    "iso:country":"US",
    "sg:address":"7856 Interstate Plaza Dr",
    "sg:city":"Hammond",
    "sg:classifiers":[
        {
            "category":"Government",
            "subcategory":"Post Office",
            "type":"Public Place"
        }
    ],
    "sg:phone":"+1 219 844 6700",
    "sg:postcode":"46324",
    "sg:province":"IN",
    "wof:name":"US Post Office",
    "wof:placetype":"venue"
},
  "geometry": {"coordinates":[-87.473418,41.57188],"type":"Point"}
}