{
  "type": "Feature",
  "properties": {
    "addr:full":"1300 E 700 S North Judson IN 46366",
    "addr:housenumber":"1300",
    "addr:postcode":"46366",
    "addr:street":"E 700 S North Judson",
    "iso:country":"US",
    "sg:address":"1300 E 700 S",
    "sg:city":"North Judson",
    "sg:phone":"+1 574 896 5773",
    "sg:postcode":"46366",
    "sg:province":"IN",
    "sg:tags":[
        "farm",
        "corn",
        "soybean"
    ],
    "wof:name":"J Troike",
    "wof:placetype":"venue"
},
  "geometry": {"coordinates":[-86.673334,41.200866],"type":"Point"}
}