{
  "type": "Feature",
  "properties": {
    "iso:country":"US",
    "sg:address":"1551 N Post Rd",
    "sg:city":"Indianapolis",
    "sg:classifiers":[
        {
            "category":"Cinema",
            "subcategory":"Movie Rental",
            "type":"Entertainment"
        }
    ],
    "sg:phone":"+1 317 897 1303",
    "sg:postcode":"46219",
    "sg:province":"IN",
    "sg:tags":[
        "leasing",
        "video",
        "disc",
        "tape"
    ],
    "sg:website":"www.familyvideo.com",
    "wof:name":"Family Video",
    "wof:placetype":"venue"
},
  "geometry": {"coordinates":[-86.009235,39.78834],"type":"Point"}
}