{
  "type": "Feature",
  "properties": {
    "addr:full":"300 Herzelle St Cannelton IN 47520",
    "addr:housenumber":"300",
    "addr:postcode":"47520",
    "addr:street":"Herzelle St",
    "iso:country":"US",
    "sg:address":"300 Herzelle St",
    "sg:city":"Cannelton",
    "sg:classifiers":[
        {
            "category":"Government",
            "subcategory":"Office",
            "type":"Public Place"
        }
    ],
    "sg:phone":"+1 812 547 5861",
    "sg:postcode":"47520",
    "sg:province":"IN",
    "sg:tags":[
        "village"
    ],
    "wof:name":"Sewage Treatment Plant",
    "wof:placetype":"venue"
},
  "geometry": {"coordinates":[-86.747968,37.915381],"type":"Point"}
}