{
  "type": "Feature",
  "properties": {
    "iso:country":"US",
    "sg:address":"3902 Murvihill Rd",
    "sg:city":"Valparaiso",
    "sg:classifiers":[
        {
            "category":"Education",
            "subcategory":"Special Training",
            "type":"Public Place"
        }
    ],
    "sg:phone":"+1 219 462 6630",
    "sg:postcode":"46383",
    "sg:province":"IN",
    "sg:tags":[
        "aircraft",
        "school"
    ],
    "wof:name":"Murvihill Aero Svc",
    "wof:placetype":"venue"
},
  "geometry": {"coordinates":[-87.005897,41.448894],"type":"Point"}
}