{
  "type": "Feature",
  "properties": {
    "iso:country":"US",
    "sg:address":"408 S Huntington St",
    "sg:city":"Syracuse",
    "sg:classifiers":[
        {
            "category":"Real Estate",
            "subcategory":"Real Estate Agent",
            "type":"Services"
        }
    ],
    "sg:phone":"+1 574 457 4678",
    "sg:postcode":"46567",
    "sg:province":"IN",
    "sg:website":"www.loganrogersrealty.com",
    "wof:name":"Logan-Rogers Realty",
    "wof:placetype":"venue"
},
  "geometry": {"coordinates":[-85.747521,41.418765],"type":"Point"}
}