{
  "type": "Feature",
  "properties": {
    "iso:country":"US",
    "sg:address":"104 E Heap St",
    "sg:city":"Farmersburg",
    "sg:classifiers":[
        {
            "category":"Government",
            "subcategory":"Fire Station",
            "type":"Public Place"
        }
    ],
    "sg:phone":"+1 812 696 2151",
    "sg:postcode":"47850",
    "sg:province":"IN",
    "sg:tags":[
        "department"
    ],
    "wof:name":"Farmersburg Fire House",
    "wof:placetype":"venue"
},
  "geometry": {"coordinates":[-87.37940500000001,39.252988],"type":"Point"}
}