{
  "type": "Feature",
  "properties": {
    "iso:country":"US",
    "sg:address":"607 Western Ave",
    "sg:city":"Winchester",
    "sg:classifiers":[
        {
            "category":"Organizations",
            "subcategory":"Religious Organization",
            "type":"Services"
        }
    ],
    "sg:phone":"+1 765 584 1954",
    "sg:postcode":"47394",
    "sg:province":"IN",
    "sg:tags":[
        "church"
    ],
    "wof:name":"Open Bible Standard Churches",
    "wof:placetype":"venue"
},
  "geometry": {"coordinates":[-84.985828,40.165588],"type":"Point"}
}