{
  "type": "Feature",
  "properties": {
    "iso:country":"US",
    "sg:address":"1121 S Seminary St",
    "sg:city":"Bloomfield",
    "sg:classifiers":[
        {
            "category":"Freight",
            "type":"Transportation"
        }
    ],
    "sg:phone":"+1 812 384 8367",
    "sg:postcode":"47424",
    "sg:province":"IN",
    "sg:tags":[
        "delivery",
        "mail"
    ],
    "wof:name":"B & S Enterprises",
    "wof:placetype":"venue"
},
  "geometry": {"coordinates":[-86.94335100000001,39.016453],"type":"Point"}
}