{
  "type": "Feature",
  "properties": {
    "iso:country":"US",
    "sg:address":"2983 E Paw Paw Pike",
    "sg:city":"Peru",
    "sg:classifiers":[
        {
            "category":"Farming",
            "subcategory":"Aquatic Farm",
            "type":"Manufacturing & Wholesale Goods"
        }
    ],
    "sg:phone":"+1 765 564 5542",
    "sg:postcode":"46970",
    "sg:province":"IN",
    "sg:tags":[
        "fish"
    ],
    "wof:name":"Sweetwater Springs Fish Farm",
    "wof:placetype":"venue"
},
  "geometry": {"coordinates":[-86.021132,40.769346],"type":"Point"}
}