{
  "type": "Feature",
  "properties": {
    "iso:country":"US",
    "sg:address":"302 Waldron St",
    "sg:city":"West Lafayette",
    "sg:classifiers":[
        {
            "category":"Organizations",
            "subcategory":"Community Association",
            "type":"Services"
        }
    ],
    "sg:phone":"+1 765 743 9676",
    "sg:postcode":"47906",
    "sg:province":"IN",
    "sg:tags":[
        "sorority",
        "fraternity"
    ],
    "wof:name":"Phi Sigma Kappa",
    "wof:placetype":"venue"
},
  "geometry": {"coordinates":[-86.917862,40.428266],"type":"Point"}
}