{
  "type": "Feature",
  "properties": {
    "addr:full":"2841 Crosscreek Cir Westfield IN 46074",
    "addr:housenumber":"2841",
    "addr:postcode":"46074",
    "addr:street":"Crosscreek Cir",
    "iso:country":"US",
    "sg:address":"2841 Crosscreek Cir",
    "sg:city":"Westfield",
    "sg:classifiers":[
        {
            "category":"Professional",
            "subcategory":"Art Services",
            "type":"Services"
        }
    ],
    "sg:phone":"+1 317 896 5471",
    "sg:postcode":"46074",
    "sg:province":"IN",
    "sg:tags":[
        "graphic",
        "commercial",
        "designer",
        "artist"
    ],
    "wof:name":"Beyer Graphics",
    "wof:placetype":"venue"
},
  "geometry": {"coordinates":[-86.114825,40.046105],"type":"Point"}
}