{
  "type": "Feature",
  "properties": {
    "iso:country":"US",
    "sg:address":"2656 Manker St",
    "sg:city":"Indianapolis",
    "sg:classifiers":[
        {
            "category":"Wholesale",
            "subcategory":"Non-durable Goods",
            "type":"Manufacturing & Wholesale Goods"
        },
        {
            "category":"Professional",
            "subcategory":"Business Services",
            "type":"Services"
        }
    ],
    "sg:phone":"+1 317 786 4972",
    "sg:postcode":"46203",
    "sg:province":"IN",
    "sg:tags":[
        "broker",
        "merchandise",
        "merchandise-wholesale"
    ],
    "wof:name":"World Marketing Associates",
    "wof:placetype":"venue"
},
  "geometry": {"coordinates":[-86.142021,39.728721],"type":"Point"}
}