{
  "type": "Feature",
  "properties": {
    "iso:country":"US",
    "sg:address":"1533 E Commerce Dr",
    "sg:city":"Greensburg",
    "sg:classifiers":[
        {
            "category":"Personal",
            "subcategory":"Beauty Salon",
            "type":"Services"
        }
    ],
    "sg:phone":"+1 812 663 2345",
    "sg:postcode":"47240",
    "sg:province":"IN",
    "wof:name":"Totally You",
    "wof:placetype":"venue"
},
  "geometry": {"coordinates":[-85.47192200000001,39.352316],"type":"Point"}
}