{
  "type": "Feature",
  "properties": {
    "iso:country":"US",
    "sg:address":"4789 Kentucky Ave",
    "sg:city":"Indianapolis",
    "sg:classifiers":[
        {
            "category":"Restaurant",
            "type":"Food & Drink"
        }
    ],
    "sg:phone":"+1 317 856 3300",
    "sg:postcode":"46221",
    "sg:province":"IN",
    "wof:name":"KFC",
    "wof:placetype":"venue"
},
  "geometry": {"coordinates":[-86.26506999999999,39.698656],"type":"Point"}
}