{
  "type": "Feature",
  "properties": {
    "iso:country":"US",
    "sg:address":"7712 Bluffton Rd",
    "sg:city":"Fort Wayne",
    "sg:classifiers":[
        {
            "category":"Organizations",
            "subcategory":"Non-profit Organization",
            "type":"Services"
        }
    ],
    "sg:phone":"+1 260 747 7767",
    "sg:postcode":"46809",
    "sg:province":"IN",
    "wof:name":"Veterans Of Foreign Wars",
    "wof:placetype":"venue"
},
  "geometry": {"coordinates":[-85.16925000000001,41.009436],"type":"Point"}
}