{
  "type": "Feature",
  "properties": {
    "iso:country":"US",
    "sg:address":"6910 N Main St",
    "sg:city":"Granger",
    "sg:classifiers":[
        {
            "category":"Professional",
            "subcategory":"Business Services",
            "type":"Services"
        }
    ],
    "sg:phone":"+1 574 243 4292",
    "sg:postcode":"46530",
    "sg:province":"IN",
    "sg:tags":[
        "packaging"
    ],
    "wof:name":"One Source Packaging LLC",
    "wof:placetype":"venue"
},
  "geometry": {"coordinates":[-86.17803000000001,41.722915],"type":"Point"}
}