{
  "type": "Feature",
  "properties": {
    "addr:full":"317 N Brady St Muncie IN 47305",
    "addr:housenumber":"317",
    "addr:postcode":"47305",
    "addr:street":"N Brady St",
    "iso:country":"US",
    "sg:address":"317 N Brady St",
    "sg:city":"Muncie",
    "sg:classifiers":[
        {
            "category":"Bus Charters",
            "type":"Transportation"
        }
    ],
    "sg:phone":"+1 765 289 0492",
    "sg:postcode":"47305",
    "sg:province":"IN",
    "sg:tags":[
        "rental"
    ],
    "sg:website":"www.fourstarcharter.usrc.net",
    "wof:name":"Ashley Travel",
    "wof:placetype":"venue"
},
  "geometry": {"coordinates":[-85.36979599999999,40.195439],"type":"Point"}
}