{
  "type": "Feature",
  "properties": {
    "addr:full":"2225 N Park Rd Connersville IN 47331",
    "addr:housenumber":"2225",
    "addr:postcode":"47331",
    "addr:street":"N Park Rd",
    "iso:country":"US",
    "sg:address":"2225 N Park Rd",
    "sg:city":"Connersville",
    "sg:classifiers":[
        {
            "category":"Restaurant",
            "type":"Food & Drink"
        }
    ],
    "sg:menulink":"http://www.allmenus.com/in/harrison/83616-papa-johns-pizza/menu/",
    "sg:phone":"+1 765 825 2214",
    "sg:postcode":"47331",
    "sg:province":"IN",
    "sg:tags":[
        "american",
        "pizza"
    ],
    "wof:name":"Papa John's Pizza",
    "wof:placetype":"venue"
},
  "geometry": {"coordinates":[-85.129052,39.661269],"type":"Point"}
}