{
  "type": "Feature",
  "properties": {
    "iso:country":"US",
    "sg:address":"4633 S Burnette Dr",
    "sg:city":"South Bend",
    "sg:classifiers":[
        {
            "category":"Professional",
            "subcategory":"Research",
            "type":"Services"
        }
    ],
    "sg:phone":"+1 574 231 1523",
    "sg:postcode":"46614",
    "sg:province":"IN",
    "sg:tags":[
        "medical"
    ],
    "wof:name":"Hoveround",
    "wof:placetype":"venue"
},
  "geometry": {"coordinates":[-86.261396,41.626445],"type":"Point"}
}