{
  "type": "Feature",
  "properties": {
    "iso:country":"US",
    "sg:address":"2516 Industrial Park Dr S",
    "sg:city":"Goshen",
    "sg:classifiers":[
        {
            "category":"Professional",
            "subcategory":"Business Services",
            "type":"Services"
        }
    ],
    "sg:phone":"+1 574 534 5155",
    "sg:postcode":"46526",
    "sg:province":"IN",
    "sg:tags":[
        "packaging"
    ],
    "wof:name":"Packship USA",
    "wof:placetype":"venue"
},
  "geometry": {"coordinates":[-85.820274,41.553271],"type":"Point"}
}