{
  "type": "Feature",
  "properties": {
    "addr:full":"16067 Colorado St Hebron IN 46341",
    "addr:housenumber":"16067",
    "addr:postcode":"46341",
    "addr:street":"Colorado St",
    "iso:country":"US",
    "sg:address":"16067 Colorado St",
    "sg:city":"Hebron",
    "sg:classifiers":[
        {
            "category":"Retail",
            "subcategory":"Car Wash",
            "type":"Services"
        }
    ],
    "sg:phone":"+1 219 996 6081",
    "sg:postcode":"46341",
    "sg:province":"IN",
    "sg:tags":[
        "truck",
        "cleaning"
    ],
    "wof:name":"Omega Chemical Products",
    "wof:placetype":"venue"
},
  "geometry": {"coordinates":[-87.296357,41.320662],"type":"Point"}
}