{
  "type": "Feature",
  "properties": {
    "iso:country":"US",
    "sg:address":"715 N Ewing St",
    "sg:city":"Seymour",
    "sg:classifiers":[
        {
            "category":"Personal",
            "subcategory":"Barber",
            "type":"Services"
        }
    ],
    "sg:phone":"+1 812 524 9240",
    "sg:postcode":"47274",
    "sg:province":"IN",
    "wof:name":"Burnside Barbers",
    "wof:placetype":"venue"
},
  "geometry": {"coordinates":[-85.88963,38.9661],"type":"Point"}
}