{
  "type": "Feature",
  "properties": {
    "iso:country":"US",
    "sg:address":"1111 Lake St",
    "sg:city":"La Porte",
    "sg:classifiers":[
        {
            "category":"Professional",
            "subcategory":"Secretarial Services",
            "type":"Services"
        }
    ],
    "sg:phone":"+1 219 362 2906",
    "sg:postcode":"46350",
    "sg:province":"IN",
    "sg:tags":[
        "reporting"
    ],
    "wof:name":"Sues Typing Service",
    "wof:placetype":"venue"
},
  "geometry": {"coordinates":[-86.728089,41.611886],"type":"Point"}
}