{
  "type": "Feature",
  "properties": {
    "addr:full":"690 E Morgan St Martinsville IN 46151",
    "addr:housenumber":"690",
    "addr:postcode":"46151",
    "addr:street":"E Morgan St",
    "iso:country":"US",
    "sg:address":"690 E Morgan St",
    "sg:city":"Martinsville",
    "sg:classifiers":[
        {
            "category":"Health Services",
            "subcategory":"Chiropractor",
            "type":"Services"
        }
    ],
    "sg:phone":"+1 765 342 2208",
    "sg:postcode":"46151",
    "sg:province":"IN",
    "wof:name":"Martinsville Chiropractic Care",
    "wof:placetype":"venue"
},
  "geometry": {"coordinates":[-86.420275,39.427901],"type":"Point"}
}