{
  "type": "Feature",
  "properties": {
    "addr:full":"515 S East St Lebanon IN 46052",
    "addr:housenumber":"515",
    "addr:postcode":"46052",
    "addr:street":"S East St",
    "iso:country":"US",
    "sg:address":"515 S East St",
    "sg:city":"Lebanon",
    "sg:classifiers":[
        {
            "category":"Retail",
            "subcategory":"Auto Repair",
            "type":"Services"
        }
    ],
    "sg:phone":"+1 765 482 2090",
    "sg:postcode":"46052",
    "sg:province":"IN",
    "sg:tags":[
        "repairing",
        "automobile"
    ],
    "wof:name":"Chambers Body Shop",
    "wof:placetype":"venue"
},
  "geometry": {"coordinates":[-86.46681599999999,40.04386],"type":"Point"}
}