{
  "type": "Feature",
  "properties": {
    "iso:country":"US",
    "sg:address":"1432 Maynard Dr",
    "sg:city":"Indianapolis",
    "sg:classifiers":[
        {
            "category":"Building & Trades",
            "subcategory":"Construction",
            "type":"Services"
        }
    ],
    "sg:phone":"+1 317 787 0970",
    "sg:postcode":"46227",
    "sg:province":"IN",
    "sg:tags":[
        "excavation",
        "excavating",
        "contractor"
    ],
    "wof:name":"J T Ferguson Excavating",
    "wof:placetype":"venue"
},
  "geometry": {"coordinates":[-86.132019,39.669779],"type":"Point"}
}