{
  "type": "Feature",
  "properties": {
    "iso:country":"US",
    "sg:address":"1000 S Meridian St",
    "sg:city":"Washington",
    "sg:classifiers":[
        {
            "category":"Real Estate",
            "subcategory":"Real Estate Operator",
            "type":"Services"
        }
    ],
    "sg:phone":"+1 812 254 3577",
    "sg:postcode":"47501",
    "sg:province":"IN",
    "sg:tags":[
        "building",
        "apartment"
    ],
    "wof:name":"R J Wells & Associates",
    "wof:placetype":"venue"
},
  "geometry": {"coordinates":[-87.175342,38.646793],"type":"Point"}
}