{
  "type": "Feature",
  "properties": {
    "iso:country":"US",
    "sg:address":"1950 Justin St",
    "sg:city":"Jasper",
    "sg:classifiers":[
        {
            "category":"Organizations",
            "subcategory":"Religious Organization",
            "type":"Services"
        }
    ],
    "sg:phone":"+1 812 634 2959",
    "sg:postcode":"47546",
    "sg:province":"IN",
    "sg:tags":[
        "church"
    ],
    "wof:name":"Jehovah's Witnesses",
    "wof:placetype":"venue"
},
  "geometry": {"coordinates":[-86.915712,38.365206],"type":"Point"}
}