{
  "type": "Feature",
  "properties": {
    "iso:country":"US",
    "sg:address":"6906 State Rd 1",
    "sg:city":"Spencerville",
    "sg:classifiers":[
        {
            "category":"Restaurant",
            "type":"Food & Drink"
        }
    ],
    "sg:phone":"+1 260 238 4915",
    "sg:postcode":"46788",
    "sg:province":"IN",
    "wof:name":"Covered Bridge Restaurant",
    "wof:placetype":"venue"
},
  "geometry": {"coordinates":[-84.921986,41.282339],"type":"Point"}
}