{
  "type": "Feature",
  "properties": {
    "iso:country":"US",
    "sg:address":"5131 College Corner Pike",
    "sg:city":"Oxford",
    "sg:classifiers":[
        {
            "category":"Building & Trades",
            "subcategory":"Plumbing",
            "type":"Services"
        }
    ],
    "sg:phone":"+1 513 523 4010",
    "sg:postcode":"45056",
    "sg:province":"IN",
    "sg:tags":[
        "heating",
        "contractor",
        "p",
        "conditioning",
        "plumbing",
        "air"
    ],
    "sg:website":"www.bbplumbing.com",
    "wof:name":"B & B Plumbing & Heating Co",
    "wof:placetype":"venue"
},
  "geometry": {"coordinates":[-84.752403,39.514034],"type":"Point"}
}