{
  "type": "Feature",
  "properties": {
    "iso:country":"US",
    "sg:address":"183 Matteson St",
    "sg:city":"Dyer",
    "sg:classifiers":[
        {
            "category":"Restaurant",
            "type":"Food & Drink"
        }
    ],
    "sg:phone":"+1 219 865 2922",
    "sg:postcode":"46311",
    "sg:province":"IN",
    "sg:tags":[
        "pizza"
    ],
    "wof:name":"State Line Pizza II",
    "wof:placetype":"venue"
},
  "geometry": {"coordinates":[-87.523403,41.498451],"type":"Point"}
}