{
  "type": "Feature",
  "properties": {
    "iso:country":"US",
    "sg:address":"1110 E Diamond Ave",
    "sg:city":"Evansville",
    "sg:classifiers":[
        {
            "category":"Building & Trades",
            "subcategory":"Cleaning & Sanitation",
            "type":"Services"
        }
    ],
    "sg:phone":"+1 812 423 5070",
    "sg:postcode":"47711",
    "sg:province":"IN",
    "sg:tags":[
        "janitor"
    ],
    "wof:name":"A-1 Cleaning Svc",
    "wof:placetype":"venue"
},
  "geometry": {"coordinates":[-87.546197,37.999085],"type":"Point"}
}