{
  "type": "Feature",
  "properties": {
    "iso:country":"US",
    "sg:address":"1740 S Wabash St",
    "sg:city":"Wabash",
    "sg:classifiers":[
        {
            "category":"Shopping",
            "subcategory":"Used Merchandise",
            "type":"Retail Goods"
        }
    ],
    "sg:phone":"+1 260 563 3467",
    "sg:postcode":"46992",
    "sg:province":"IN",
    "wof:name":"Antiques & More",
    "wof:placetype":"venue"
},
  "geometry": {"coordinates":[-85.819797,40.779975],"type":"Point"}
}