{
  "type": "Feature",
  "properties": {
    "iso:country":"US",
    "sg:address":"701 E 7th St",
    "sg:city":"Hobart",
    "sg:classifiers":[
        {
            "category":"Retail",
            "subcategory":"Funeral Services",
            "type":"Services"
        }
    ],
    "sg:phone":"+1 219 942 1117",
    "sg:postcode":"46342",
    "sg:province":"IN",
    "sg:tags":[
        "director"
    ],
    "wof:name":"Burns Funeral Home",
    "wof:placetype":"venue"
},
  "geometry": {"coordinates":[-87.252025,41.527131],"type":"Point"}
}