{
  "type": "Feature",
  "properties": {
    "iso:country":"US",
    "sg:address":"420 Lincolnway W",
    "sg:city":"South Bend",
    "sg:classifiers":[
        {
            "category":"Food & Beverages",
            "subcategory":"Groceries & Convenience Stores",
            "type":"Retail Goods"
        }
    ],
    "sg:phone":"+1 574 232 9411",
    "sg:postcode":"46601",
    "sg:province":"IN",
    "wof:name":"Mekong Oriental Market",
    "wof:placetype":"venue"
},
  "geometry": {"coordinates":[-86.256343,41.679612],"type":"Point"}
}