{
  "type": "Feature",
  "properties": {
    "iso:country":"US",
    "sg:address":"502 S Warren St",
    "sg:city":"South Bend",
    "sg:classifiers":[
        {
            "category":"Organizations",
            "subcategory":"Religious Organization",
            "type":"Services"
        }
    ],
    "sg:phone":"+1 574 288 9228",
    "sg:postcode":"46619",
    "sg:province":"IN",
    "sg:tags":[
        "church"
    ],
    "wof:name":"Grace Memorial Church Of God",
    "wof:placetype":"venue"
},
  "geometry": {"coordinates":[-86.2799,41.669633],"type":"Point"}
}