{
  "type": "Feature",
  "properties": {
    "iso:country":"US",
    "sg:address":"4524 Candletree Cir",
    "sg:city":"Indianapolis",
    "sg:classifiers":[
        {
            "category":"Building & Trades",
            "subcategory":"Landscaping Services",
            "type":"Services"
        }
    ],
    "sg:phone":"+1 317 471 5413",
    "sg:postcode":"46254",
    "sg:province":"IN",
    "sg:tags":[
        "lawn",
        "maintenance",
        "grounds"
    ],
    "wof:name":"Universal Services",
    "wof:placetype":"venue"
},
  "geometry": {"coordinates":[-86.236788,39.83662],"type":"Point"}
}