{
  "type": "Feature",
  "properties": {
    "iso:country":"US",
    "sg:address":"6155 Bristlecone Dr",
    "sg:city":"Fishers",
    "sg:classifiers":[
        {
            "category":"Professional",
            "subcategory":"Computer Services",
            "type":"Services"
        }
    ],
    "sg:phone":"+1 317 913 9761",
    "sg:postcode":"46038",
    "sg:province":"IN",
    "sg:tags":[
        "related"
    ],
    "wof:name":"Cheung & Chai LLC",
    "wof:placetype":"venue"
},
  "geometry": {"coordinates":[-86.06704,39.93797],"type":"Point"}
}