{
  "type": "Feature",
  "properties": {
    "iso:country":"US",
    "sg:address":"4040 Country Pl",
    "sg:city":"Zionsville",
    "sg:classifiers":[
        {
            "category":"Professional",
            "subcategory":"Management & Consulting",
            "type":"Services"
        }
    ],
    "sg:phone":"+1 317 873 6071",
    "sg:postcode":"46077",
    "sg:province":"IN",
    "sg:tags":[
        "business"
    ],
    "wof:name":"Nurse Consultants of Indiana",
    "wof:placetype":"venue"
},
  "geometry": {"coordinates":[-86.229935,40.006797],"type":"Point"}
}