{
  "type": "Feature",
  "properties": {
    "iso:country":"US",
    "sg:address":"1950 W 86th St Ste 202",
    "sg:city":"Indianapolis",
    "sg:classifiers":[
        {
            "category":"Health Services",
            "subcategory":"Doctor",
            "type":"Services"
        }
    ],
    "sg:phone":"+1 317 824 1725",
    "sg:postcode":"46260",
    "sg:province":"IN",
    "sg:tags":[
        "psychiatrist"
    ],
    "sg:website":"www.rajclinics.com",
    "wof:name":"Raj Clinics the",
    "wof:placetype":"venue"
},
  "geometry": {"coordinates":[-86.195037,39.912248],"type":"Point"}
}