{
  "type": "Feature",
  "properties": {
    "iso:country":"US",
    "sg:address":"1524 S Madison St",
    "sg:city":"Muncie",
    "sg:classifiers":[
        {
            "category":"Retail",
            "subcategory":"Auto Repair",
            "type":"Services"
        }
    ],
    "sg:phone":"+1 765 288 4489",
    "sg:postcode":"47302",
    "sg:province":"IN",
    "sg:tags":[
        "repairing",
        "automobile"
    ],
    "wof:name":"Madison Street Automotive",
    "wof:placetype":"venue"
},
  "geometry": {"coordinates":[-85.381615,40.181471],"type":"Point"}
}