{
  "type": "Feature",
  "properties": {
    "addr:full":"1618 Fabricon Blvd Jeffersonville IN 47130",
    "addr:housenumber":"1618",
    "addr:postcode":"47130",
    "addr:street":"Fabricon Blvd",
    "iso:country":"US",
    "sg:address":"1618 Fabricon Blvd",
    "sg:city":"Jeffersonville",
    "sg:classifiers":[
        {
            "category":"Freight",
            "type":"Transportation"
        }
    ],
    "sg:phone":"+1 812 218 8990",
    "sg:postcode":"47130",
    "sg:province":"IN",
    "sg:tags":[
        "broker",
        "trucking"
    ],
    "wof:name":"N Flyte Trucking",
    "wof:placetype":"venue"
},
  "geometry": {"coordinates":[-85.74596099999999,38.315508],"type":"Point"}
}