{
  "type": "Feature",
  "properties": {
    "iso:country":"US",
    "sg:address":"8012 Bald Knob Rd",
    "sg:city":"Mount Vernon",
    "sg:classifiers":[
        {
            "category":"Organizations",
            "subcategory":"Religious Organization",
            "type":"Services"
        }
    ],
    "sg:phone":"+1 812 838 0318",
    "sg:postcode":"47620",
    "sg:province":"IN",
    "wof:name":"Blacks Chpel Untd Mthdst Chrch",
    "wof:placetype":"venue"
},
  "geometry": {"coordinates":[-87.963278,37.921496],"type":"Point"}
}