{
  "type": "Feature",
  "properties": {
    "iso:country":"US",
    "sg:address":"615 W 12th St",
    "sg:city":"Huntingburg",
    "sg:classifiers":[
        {
            "category":"Building & Trades",
            "subcategory":"Construction",
            "type":"Services"
        }
    ],
    "sg:phone":"+1 812 683 3551",
    "sg:postcode":"47542",
    "sg:province":"IN",
    "sg:tags":[
        "concrete",
        "contractor"
    ],
    "wof:name":"Ready Mix Dispatch",
    "wof:placetype":"venue"
},
  "geometry": {"coordinates":[-86.96853299999999,38.305986],"type":"Point"}
}