{
  "type": "Feature",
  "properties": {
    "addr:full":"7215 Grand Ritz Ln Indianapolis IN 46237",
    "addr:housenumber":"7215",
    "addr:postcode":"46237",
    "addr:street":"Grand Ritz Ln",
    "iso:country":"US",
    "sg:address":"7215 Grand Ritz Ln",
    "sg:city":"Indianapolis",
    "sg:classifiers":[
        {
            "category":"Real Estate",
            "subcategory":"Real Estate Operator",
            "type":"Services"
        }
    ],
    "sg:phone":"+1 317 888 6000",
    "sg:postcode":"46237",
    "sg:province":"IN",
    "sg:tags":[
        "apartment"
    ],
    "wof:name":"Grand Oaks Apartment",
    "wof:placetype":"venue"
},
  "geometry": {"coordinates":[-86.100853,39.662471],"type":"Point"}
}