{
  "type": "Feature",
  "properties": {
    "iso:country":"US",
    "sg:address":"2627 45th St",
    "sg:city":"Highland",
    "sg:classifiers":[
        {
            "category":"Health Services",
            "subcategory":"Doctor",
            "type":"Services"
        }
    ],
    "sg:phone":"+1 219 924 0554",
    "sg:postcode":"46322",
    "sg:province":"IN",
    "sg:tags":[
        "dentist"
    ],
    "wof:name":"Smile Solutions Inc",
    "wof:placetype":"venue"
},
  "geometry": {"coordinates":[-87.46515100000001,41.537581],"type":"Point"}
}