{
  "type": "Feature",
  "properties": {
    "iso:country":"US",
    "sg:address":"1614 S 8th St",
    "sg:city":"Goshen",
    "sg:classifiers":[
        {
            "category":"Education",
            "subcategory":"Special Training",
            "type":"Public Place"
        }
    ],
    "sg:phone":"+1 574 202 0211",
    "sg:postcode":"46526",
    "sg:province":"IN",
    "wof:name":"Studio Demusique",
    "wof:placetype":"venue"
},
  "geometry": {"coordinates":[-85.82783499999999,41.568099],"type":"Point"}
}