{
  "type": "Feature",
  "properties": {
    "iso:country":"US",
    "sg:address":"2718 W Mishawaka Ave",
    "sg:city":"South Bend",
    "sg:classifiers":[
        {
            "category":"Retail",
            "subcategory":"Repair Shop",
            "type":"Services"
        }
    ],
    "sg:phone":"+1 574 232 5170",
    "sg:postcode":"46615",
    "sg:province":"IN",
    "sg:tags":[
        "sharpening"
    ],
    "wof:name":"Sharprite Precision Grinding",
    "wof:placetype":"venue"
},
  "geometry": {"coordinates":[-86.20812,41.66564],"type":"Point"}
}