{
  "type": "Feature",
  "properties": {
    "addr:full":"63900 Pine Rd North Liberty IN 46554",
    "addr:housenumber":"63900",
    "addr:postcode":"46554",
    "addr:street":"Pine Rd",
    "iso:country":"US",
    "sg:address":"63900 Pine Rd",
    "sg:city":"North Liberty",
    "sg:classifiers":[
        {
            "category":"Building & Trades",
            "subcategory":"Construction",
            "type":"Services"
        }
    ],
    "sg:phone":"+1 574 656 3890",
    "sg:postcode":"46554",
    "sg:province":"IN",
    "sg:tags":[
        "builder",
        "deck"
    ],
    "wof:name":"Chuck's Custom Carpentry",
    "wof:placetype":"venue"
},
  "geometry": {"coordinates":[-86.35005700000001,41.573381],"type":"Point"}
}