{
  "type": "Feature",
  "properties": {
    "iso:country":"US",
    "sg:address":"9766 E State Rd 164",
    "sg:city":"Celestine",
    "sg:classifiers":[
        {
            "category":"Building & Trades",
            "subcategory":"Construction",
            "type":"Services"
        }
    ],
    "sg:phone":"+1 812 389 2428",
    "sg:postcode":"47521",
    "sg:province":"IN",
    "sg:tags":[
        "agricultural",
        "excavating",
        "supply"
    ],
    "wof:name":"Knies Farms and Supplies",
    "wof:placetype":"venue"
},
  "geometry": {"coordinates":[-86.723523,38.370822],"type":"Point"}
}