{
  "type": "Feature",
  "properties": {
    "iso:country":"US",
    "sg:address":"7143 State Rd 39",
    "sg:city":"Clayton",
    "sg:classifiers":[
        {
            "category":"Sports & Exercise",
            "subcategory":"Golf",
            "type":"Entertainment"
        }
    ],
    "sg:phone":"+1 317 539 2013",
    "sg:postcode":"46118",
    "sg:province":"IN",
    "sg:tags":[
        "course"
    ],
    "wof:name":"Deer Creek Golf Course",
    "wof:placetype":"venue"
},
  "geometry": {"coordinates":[-86.485289,39.657492],"type":"Point"}
}