{
  "type": "Feature",
  "properties": {
    "iso:country":"US",
    "sg:address":"760 W 81st Ave",
    "sg:city":"Merrillville",
    "sg:classifiers":[
        {
            "category":"Autos & Motor Vehicles",
            "subcategory":"Auto Supplies",
            "type":"Retail Goods"
        },
        {
            "category":"Retail",
            "subcategory":"Auto Repair",
            "type":"Services"
        }
    ],
    "sg:phone":"+1 219 738 1960",
    "sg:postcode":"46410",
    "sg:province":"IN",
    "sg:tags":[
        "wheel",
        "exhaust",
        "oil",
        "tire",
        "transmission",
        "automobile",
        "wheels-aligning",
        "servicing-automotive",
        "system",
        "alignment-frame",
        "lube",
        "brake",
        "axle",
        "equipment-service",
        "muffler",
        "balancing",
        "air conditioning"
    ],
    "sg:website":"http://www.midas.com",
    "wof:name":"Midas Auto Svc Experts",
    "wof:placetype":"venue"
},
  "geometry": {"coordinates":[-87.34587500000001,41.471276],"type":"Point"}
}