{
  "type": "Feature",
  "properties": {
    "iso:country":"US",
    "sg:address":"3551 Lafayette Rd",
    "sg:city":"Indianapolis",
    "sg:classifiers":[
        {
            "category":"Arts & Performance",
            "subcategory":"Theater",
            "type":"Entertainment"
        }
    ],
    "sg:phone":"+1 317 297 0429",
    "sg:postcode":"46222",
    "sg:province":"IN",
    "sg:tags":[
        "entertainer"
    ],
    "wof:name":"Brad's Gold Showclub",
    "wof:placetype":"venue"
},
  "geometry": {"coordinates":[-86.232796,39.82168],"type":"Point"}
}