{
  "type": "Feature",
  "properties": {
    "iso:country":"US",
    "sg:address":"3327 45th St",
    "sg:city":"Highland",
    "sg:classifiers":[
        {
            "category":"Professional",
            "subcategory":"Management & Consulting",
            "type":"Services"
        }
    ],
    "sg:phone":"+1 219 924 0353",
    "sg:postcode":"46322",
    "sg:province":"IN",
    "sg:tags":[
        "consultant",
        "business"
    ],
    "wof:name":"MDF Management",
    "wof:placetype":"venue"
},
  "geometry": {"coordinates":[-87.448659,41.537489],"type":"Point"}
}