{
  "type": "Feature",
  "properties": {
    "iso:country":"US",
    "sg:address":"9664 Woodstone Ct",
    "sg:city":"Fishers",
    "sg:classifiers":[
        {
            "category":"Education",
            "subcategory":"Special Training",
            "type":"Public Place"
        }
    ],
    "sg:phone":"+1 317 576 0790",
    "sg:postcode":"46037",
    "sg:province":"IN",
    "sg:tags":[
        "school",
        "educational"
    ],
    "wof:name":"After Bankruptcy Foundation",
    "wof:placetype":"venue"
},
  "geometry": {"coordinates":[-85.990332,39.928003],"type":"Point"}
}