{
  "type": "Feature",
  "properties": {
    "iso:country":"US",
    "sg:address":"703 N Calumet Ave",
    "sg:city":"Valparaiso",
    "sg:classifiers":[
        {
            "category":"Food & Beverages",
            "subcategory":"Specialty",
            "type":"Retail Goods"
        }
    ],
    "sg:phone":"+1 219 531 1415",
    "sg:postcode":"46383",
    "sg:province":"IN",
    "sg:tags":[
        "vitamin"
    ],
    "wof:name":"Shaklee Authorized Distr",
    "wof:placetype":"venue"
},
  "geometry": {"coordinates":[-87.036856,41.537587],"type":"Point"}
}