{
  "type": "Feature",
  "properties": {
    "iso:country":"US",
    "sg:address":"835 169th St",
    "sg:city":"Hammond",
    "sg:classifiers":[
        {
            "category":"Health Services",
            "subcategory":"Doctor",
            "type":"Services"
        }
    ],
    "sg:phone":"+1 219 932 1220",
    "sg:postcode":"46324",
    "sg:province":"IN",
    "sg:tags":[
        "physician",
        "surgeon"
    ],
    "wof:name":"Mahendra A Patel MD",
    "wof:placetype":"venue"
},
  "geometry": {"coordinates":[-87.50761,41.588329],"type":"Point"}
}