{
  "type": "Feature",
  "properties": {
    "iso:country":"US",
    "sg:address":"2211 Newton St",
    "sg:city":"Columbus",
    "sg:classifiers":[
        {
            "category":"Professional",
            "subcategory":"Art Services",
            "type":"Services"
        }
    ],
    "sg:phone":"+1 812 376 6796",
    "sg:postcode":"47201",
    "sg:province":"IN",
    "sg:tags":[
        "photography",
        "commercial"
    ],
    "wof:name":"Terry M Bickers Photography",
    "wof:placetype":"venue"
},
  "geometry": {"coordinates":[-85.910816,39.220757],"type":"Point"}
}