{
  "type": "Feature",
  "properties": {
    "iso:country":"US",
    "sg:address":"4625 Rosslyn Ave",
    "sg:city":"Indianapolis",
    "sg:classifiers":[
        {
            "category":"Social Services",
            "subcategory":"Child Care",
            "type":"Services"
        }
    ],
    "sg:phone":"+1 317 259 0569",
    "sg:postcode":"46205",
    "sg:province":"IN",
    "wof:name":"Natasha's Day Care",
    "wof:placetype":"venue"
},
  "geometry": {"coordinates":[-86.133545,39.841213],"type":"Point"}
}