{
  "type": "Feature",
  "properties": {
    "iso:country":"US",
    "sg:address":"2200 Ferry St",
    "sg:city":"Lafayette",
    "sg:classifiers":[
        {
            "category":"Shopping",
            "subcategory":"Pharmacy",
            "type":"Retail Goods"
        }
    ],
    "sg:phone":"+1 765 447 1000",
    "sg:postcode":"47904",
    "sg:province":"IN",
    "wof:name":"Parkside Pharmacy",
    "wof:placetype":"venue"
},
  "geometry": {"coordinates":[-86.871245,40.418973],"type":"Point"}
}