{
  "type": "Feature",
  "properties": {
    "iso:country":"US",
    "sg:address":"60 N Main St",
    "sg:city":"Zionsville",
    "sg:classifiers":[
        {
            "category":"Health Services",
            "subcategory":"Doctor",
            "type":"Services"
        }
    ],
    "sg:phone":"+1 317 873 3793",
    "sg:postcode":"46077",
    "sg:province":"IN",
    "sg:tags":[
        "dentist"
    ],
    "wof:name":"Cascione Family Dentistry",
    "wof:placetype":"venue"
},
  "geometry": {"coordinates":[-86.262186,39.951898],"type":"Point"}
}