{
  "type": "Feature",
  "properties": {
    "iso:country":"US",
    "sg:address":"5629 E Co Rd 525 N",
    "sg:city":"Twelve Mile",
    "sg:classifiers":[
        {
            "category":"Retail",
            "subcategory":"Repair Shop",
            "type":"Services"
        }
    ],
    "sg:phone":"+1 574 664 4521",
    "sg:postcode":"46988",
    "sg:province":"IN",
    "sg:tags":[
        "water",
        "equipment",
        "softening"
    ],
    "wof:name":"Water Soft Of Indiana",
    "wof:placetype":"venue"
},
  "geometry": {"coordinates":[-86.273111,40.840911],"type":"Point"}
}