{
  "type": "Feature",
  "properties": {
    "iso:country":"US",
    "sg:address":"201 S Heaton St",
    "sg:city":"Knox",
    "sg:classifiers":[
        {
            "category":"Building & Trades",
            "subcategory":"Cleaning & Sanitation",
            "type":"Services"
        }
    ],
    "sg:phone":"+1 574 772 5153",
    "sg:postcode":"46534",
    "sg:province":"IN",
    "sg:tags":[
        "house"
    ],
    "wof:name":"Shirley Ann Cleans",
    "wof:placetype":"venue"
},
  "geometry": {"coordinates":[-86.620696,41.295664],"type":"Point"}
}