{
  "type": "Feature",
  "properties": {
    "addr:full":"5776 Handy Rd Bloomington IN 47401",
    "addr:housenumber":"5776",
    "addr:postcode":"47401",
    "addr:street":"Handy Rd",
    "iso:country":"US",
    "sg:address":"5776 Handy Rd",
    "sg:city":"Bloomington",
    "sg:classifiers":[
        {
            "category":"Building & Trades",
            "subcategory":"Construction",
            "type":"Services"
        }
    ],
    "sg:phone":"+1 812 824 2027",
    "sg:postcode":"47401",
    "sg:province":"IN",
    "sg:tags":[
        "fire",
        "restoration",
        "damage"
    ],
    "wof:name":"Servpro Of Monroe County",
    "wof:placetype":"venue"
},
  "geometry": {"coordinates":[-86.49046800000001,39.093958],"type":"Point"}
}