{
  "type": "Feature",
  "properties": {
    "iso:country":"US",
    "sg:address":"2734 Washington Ave",
    "sg:city":"Vincennes",
    "sg:classifiers":[
        {
            "category":"Professional",
            "type":"Services"
        }
    ],
    "sg:phone":"+1 812 885 0078",
    "sg:postcode":"47591",
    "sg:province":"IN",
    "sg:tags":[
        "establishment"
    ],
    "wof:name":"Bulk Convenience Inc",
    "wof:placetype":"venue"
},
  "geometry": {"coordinates":[-87.50002499999999,38.684735],"type":"Point"}
}