{
  "type": "Feature",
  "properties": {
    "iso:country":"US",
    "sg:address":"2560 W Morris St",
    "sg:city":"Indianapolis",
    "sg:classifiers":[
        {
            "category":"Retail",
            "subcategory":"Auto Rental",
            "type":"Services"
        }
    ],
    "sg:phone":"+1 317 636 1529",
    "sg:postcode":"46221",
    "sg:province":"IN",
    "sg:tags":[
        "renting",
        "leasing",
        "trailer"
    ],
    "wof:name":"Tip Trailer Leasing",
    "wof:placetype":"venue"
},
  "geometry": {"coordinates":[-86.20334,39.750816],"type":"Point"}
}