{
  "type": "Feature",
  "properties": {
    "iso:country":"US",
    "sg:address":"4760 Pennwood Dr",
    "sg:city":"Indianapolis",
    "sg:classifiers":[
        {
            "category":"Professional",
            "type":"Services"
        }
    ],
    "sg:phone":"+1 317 860 0484",
    "sg:postcode":"46205",
    "sg:province":"IN",
    "sg:tags":[
        "establishment"
    ],
    "wof:name":"Abbie Hunt Bryce Home",
    "wof:placetype":"venue"
},
  "geometry": {"coordinates":[-86.11843399999999,39.843217],"type":"Point"}
}