{
  "type": "Feature",
  "properties": {
    "iso:country":"US",
    "sg:address":"2691 Nichol Ave",
    "sg:city":"Anderson",
    "sg:classifiers":[
        {
            "category":"Building & Trades",
            "subcategory":"Pest Control",
            "type":"Services"
        }
    ],
    "sg:phone":"+1 765 644 2533",
    "sg:postcode":"46011",
    "sg:province":"IN",
    "wof:name":"Baxter Pest Doctors",
    "wof:placetype":"venue"
},
  "geometry": {"coordinates":[-85.71880899999999,40.10152],"type":"Point"}
}