{
  "type": "Feature",
  "properties": {
    "addr:full":"2001 Miami Rd South Bend IN 46613",
    "addr:housenumber":"2001",
    "addr:postcode":"46613",
    "addr:street":"Miami Rd",
    "iso:country":"US",
    "sg:address":"2001 Miami Rd",
    "sg:city":"South Bend",
    "sg:classifiers":[
        {
            "category":"Personal",
            "subcategory":"Beauty Salon",
            "type":"Services"
        }
    ],
    "sg:phone":"+1 574 289 2328",
    "sg:postcode":"46613",
    "sg:province":"IN",
    "sg:tags":[
        "shop"
    ],
    "wof:name":"Serendipity",
    "wof:placetype":"venue"
},
  "geometry": {"coordinates":[-86.23491199999999,41.653286],"type":"Point"}
}