{
  "type": "Feature",
  "properties": {
    "iso:country":"US",
    "sg:address":"3304 W Co Rd 240 NW",
    "sg:city":"Greensburg",
    "sg:classifiers":[
        {
            "category":"Professional",
            "subcategory":"Business Services",
            "type":"Services"
        }
    ],
    "sg:phone":"+1 812 663 9385",
    "sg:postcode":"47240",
    "sg:province":"IN",
    "sg:tags":[
        "appraiser"
    ],
    "wof:name":"Colson Real Estate Appraisals",
    "wof:placetype":"venue"
},
  "geometry": {"coordinates":[-85.545379,39.360982],"type":"Point"}
}