{
  "type": "Feature",
  "properties": {
    "iso:country":"US",
    "sg:address":"10 Adams Ave",
    "sg:city":"Peru",
    "sg:classifiers":[
        {
            "category":"Personal",
            "subcategory":"Beauty Salon",
            "type":"Services"
        }
    ],
    "sg:phone":"+1 765 472 7745",
    "sg:postcode":"46970",
    "sg:province":"IN",
    "wof:name":"Permanent Solutions",
    "wof:placetype":"venue"
},
  "geometry": {"coordinates":[-86.07435099999999,40.76498],"type":"Point"}
}