{
  "type": "Feature",
  "properties": {
    "iso:country":"US",
    "sg:address":"255 W McClain St",
    "sg:city":"Scottsburg",
    "sg:classifiers":[
        {
            "category":"Organizations",
            "subcategory":"Religious Organization",
            "type":"Services"
        }
    ],
    "sg:phone":"+1 812 752 2115",
    "sg:postcode":"47170",
    "sg:province":"IN",
    "sg:tags":[
        "church"
    ],
    "sg:website":"www.fcc-scottsburg.org",
    "wof:name":"First Christian Church",
    "wof:placetype":"venue"
},
  "geometry": {"coordinates":[-85.77322700000001,38.685661],"type":"Point"}
}