{
  "type": "Feature",
  "properties": {
    "iso:country":"US",
    "sg:address":"2212 N Ivanhoe St",
    "sg:city":"Muncie",
    "sg:classifiers":[
        {
            "category":"Professional",
            "subcategory":"Lawyer & Legal Services",
            "type":"Services"
        }
    ],
    "sg:phone":"+1 765 282 2274",
    "sg:postcode":"47304",
    "sg:province":"IN",
    "sg:tags":[
        "attorney"
    ],
    "wof:name":"Joseph M Speece",
    "wof:placetype":"venue"
},
  "geometry": {"coordinates":[-85.432452,40.212044],"type":"Point"}
}