{
  "type": "Feature",
  "properties": {
    "iso:country":"US",
    "sg:address":"145 Shorewood Dr",
    "sg:city":"Valparaiso",
    "sg:classifiers":[
        {
            "category":"Real Estate",
            "subcategory":"Real Estate Operator",
            "type":"Services"
        }
    ],
    "sg:phone":"+1 219 465 0332",
    "sg:postcode":"46385",
    "sg:province":"IN",
    "sg:tags":[
        "property",
        "lessor"
    ],
    "wof:name":"Kent Hill",
    "wof:placetype":"venue"
},
  "geometry": {"coordinates":[-87.14800200000001,41.456458],"type":"Point"}
}