{
  "type": "Feature",
  "properties": {
    "iso:country":"US",
    "sg:address":"8364 Brookville Rd",
    "sg:city":"Indianapolis",
    "sg:classifiers":[
        {
            "category":"Building & Trades",
            "subcategory":"Construction",
            "type":"Services"
        }
    ],
    "sg:phone":"+1 317 375 1813",
    "sg:postcode":"46239",
    "sg:province":"IN",
    "sg:tags":[
        "concrete",
        "contractor"
    ],
    "wof:name":"Cherokee Decorative Concrete",
    "wof:placetype":"venue"
},
  "geometry": {"coordinates":[-86.014147,39.747606],"type":"Point"}
}