{
  "type": "Feature",
  "properties": {
    "iso:country":"US",
    "sg:address":"1230 N Jackson St",
    "sg:city":"Greencastle",
    "sg:classifiers":[
        {
            "category":"Wholesale",
            "subcategory":"Machinery & Supplies",
            "type":"Manufacturing & Wholesale Goods"
        }
    ],
    "sg:phone":"+1 765 653 2431",
    "sg:postcode":"46135",
    "sg:province":"IN",
    "sg:tags":[
        "farm",
        "equipment"
    ],
    "wof:name":"Countryside Lawn & Garden",
    "wof:placetype":"venue"
},
  "geometry": {"coordinates":[-86.866125,39.654649],"type":"Point"}
}