{
  "type": "Feature",
  "properties": {
    "iso:country":"US",
    "sg:address":"50 N Post Rd",
    "sg:city":"Indianapolis",
    "sg:classifiers":[
        {
            "category":"Retail",
            "subcategory":"Auto Repair",
            "type":"Services"
        }
    ],
    "sg:phone":"+1 317 897 2220",
    "sg:postcode":"46219",
    "sg:province":"IN",
    "sg:tags":[
        "body",
        "automobile",
        "painting"
    ],
    "wof:name":"Eastside Collision",
    "wof:placetype":"venue"
},
  "geometry": {"coordinates":[-86.009324,39.776114],"type":"Point"}
}