{
  "type": "Feature",
  "properties": {
    "addr:full":"11249 Lantern Rd Fishers IN 46038",
    "addr:housenumber":"11249",
    "addr:postcode":"46038",
    "addr:street":"Lantern Rd",
    "iso:country":"US",
    "sg:address":"11249 Lantern Rd",
    "sg:city":"Fishers",
    "sg:phone":"+1 317 849 2409",
    "sg:postcode":"46038",
    "sg:province":"IN",
    "sg:tags":[
        "farm",
        "corn",
        "soybean"
    ],
    "wof:name":"Bob Stewart",
    "wof:placetype":"venue"
},
  "geometry": {"coordinates":[-86.01394500000001,39.949632],"type":"Point"}
}