{
  "type": "Feature",
  "properties": {
    "iso:country":"US",
    "sg:address":"235 N Burkhardt Rd",
    "sg:city":"Evansville",
    "sg:classifiers":[
        {
            "category":"Shopping",
            "subcategory":"Stationery & Office Supplies",
            "type":"Retail Goods"
        }
    ],
    "sg:phone":"+1 812 475 9357",
    "sg:postcode":"47715",
    "sg:province":"IN",
    "sg:website":"www.staples.com",
    "wof:name":"Staples The Office Superstore",
    "wof:placetype":"venue"
},
  "geometry": {"coordinates":[-87.473964,37.980903],"type":"Point"}
}