{
  "type": "Feature",
  "properties": {
    "iso:country":"US",
    "sg:address":"8685 E Co Rd 1300 N",
    "sg:city":"Osgood",
    "sg:classifiers":[
        {
            "category":"Professional",
            "subcategory":"Computer Services",
            "type":"Services"
        }
    ],
    "sg:phone":"+1 812 663 8708",
    "sg:postcode":"47041",
    "sg:province":"IN",
    "sg:tags":[
        "development",
        "web",
        "site",
        "maintenance"
    ],
    "wof:name":"Ruth Griffith",
    "wof:placetype":"venue"
},
  "geometry": {"coordinates":[-85.130469,39.26612],"type":"Point"}
}