{
  "type": "Feature",
  "properties": {
    "addr:full":"123 S Main St Versailles IN 47042",
    "addr:housenumber":"123",
    "addr:postcode":"47042",
    "addr:street":"S Main St",
    "iso:country":"US",
    "sg:address":"123 S Main St",
    "sg:city":"Versailles",
    "sg:classifiers":[
        {
            "category":"Professional",
            "subcategory":"Lawyer & Legal Services",
            "type":"Services"
        }
    ],
    "sg:phone":"+1 812 689 5111",
    "sg:postcode":"47042",
    "sg:province":"IN",
    "sg:tags":[
        "attorney"
    ],
    "wof:name":"Eaton & Day",
    "wof:placetype":"venue"
},
  "geometry": {"coordinates":[-85.251379,39.07135],"type":"Point"}
}