{
  "type": "Feature",
  "properties": {
    "addr:full":"5457 Central Ave Portage IN 46368",
    "addr:housenumber":"5457",
    "addr:postcode":"46368",
    "addr:street":"Central Ave",
    "iso:country":"US",
    "sg:address":"5457 Central Ave",
    "sg:city":"Portage",
    "sg:classifiers":[
        {
            "category":"Banks & Credit Unions",
            "subcategory":"Bank",
            "type":"Services"
        }
    ],
    "sg:phone":"+1 219 763 9003",
    "sg:postcode":"46368",
    "sg:province":"IN",
    "sg:tags":[
        "loan"
    ],
    "wof:name":"MJM Mortgage Svc",
    "wof:placetype":"venue"
},
  "geometry": {"coordinates":[-87.205958,41.574988],"type":"Point"}
}