{
  "type": "Feature",
  "properties": {
    "iso:country":"US",
    "sg:address":"20 N Meridian St",
    "sg:city":"Indianapolis",
    "sg:classifiers":[
        {
            "category":"Real Estate",
            "subcategory":"Real Estate Agent",
            "type":"Services"
        }
    ],
    "sg:phone":"+1 317 423 2862",
    "sg:postcode":"46204",
    "sg:province":"IN",
    "wof:name":"Rei Real Estate Svc",
    "wof:placetype":"venue"
},
  "geometry": {"coordinates":[-86.158062,39.767955],"type":"Point"}
}