{
  "type": "Feature",
  "properties": {
    "addr:full":"2009 19th St Bedford IN 47421",
    "addr:housenumber":"2009",
    "addr:postcode":"47421",
    "addr:street":"19Th St",
    "iso:country":"US",
    "sg:address":"2009 19th St",
    "sg:city":"Bedford",
    "sg:classifiers":[
        {
            "category":"Organizations",
            "subcategory":"Community Association",
            "type":"Services"
        }
    ],
    "sg:phone":"+1 812 279 6123",
    "sg:postcode":"47421",
    "sg:province":"IN",
    "sg:tags":[
        "club"
    ],
    "sg:website":"www.limestonegirlsclub.org",
    "wof:name":"Limestone Girls Club",
    "wof:placetype":"venue"
},
  "geometry": {"coordinates":[-86.49996,38.856833],"type":"Point"}
}