{
  "type": "Feature",
  "properties": {
    "iso:country":"US",
    "sg:address":"2810 Condit St",
    "sg:city":"Highland",
    "sg:classifiers":[
        {
            "category":"Manufacturing",
            "subcategory":"Printing",
            "type":"Manufacturing & Wholesale Goods"
        }
    ],
    "sg:phone":"+1 219 934 9133",
    "sg:postcode":"46322",
    "sg:province":"IN",
    "sg:tags":[
        "newspaper"
    ],
    "wof:name":"Beat Entertainment Magazine",
    "wof:placetype":"venue"
},
  "geometry": {"coordinates":[-87.459414,41.556452],"type":"Point"}
}