{
  "type": "Feature",
  "properties": {
    "iso:country":"US",
    "sg:address":"1013 W 52nd St",
    "sg:city":"Indianapolis",
    "sg:classifiers":[
        {
            "category":"Professional",
            "type":"Services"
        }
    ],
    "sg:phone":"+1 317 202 9476",
    "sg:postcode":"46228",
    "sg:province":"IN",
    "sg:tags":[
        "establishment"
    ],
    "wof:name":"Stephen Hopkins & Assoc Inc",
    "wof:placetype":"venue"
},
  "geometry": {"coordinates":[-86.181735,39.84646],"type":"Point"}
}