{
  "type": "Feature",
  "properties": {
    "iso:country":"US",
    "sg:address":"2636 Dearborn St",
    "sg:city":"Lake Station",
    "sg:classifiers":[
        {
            "category":"Autos & Motor Vehicles",
            "subcategory":"Automobile Sales",
            "type":"Retail Goods"
        }
    ],
    "sg:phone":"+1 219 962 3755",
    "sg:postcode":"46405",
    "sg:province":"IN",
    "sg:tags":[
        "car",
        "dealer"
    ],
    "wof:name":"Hall's Auto Sales",
    "wof:placetype":"venue"
},
  "geometry": {"coordinates":[-87.277545,41.568603],"type":"Point"}
}