{
  "type": "Feature",
  "properties": {
    "iso:country":"US",
    "sg:address":"528 W Grove St",
    "sg:city":"Mishawaka",
    "sg:classifiers":[
        {
            "category":"Professional",
            "subcategory":"Business Services",
            "type":"Services"
        }
    ],
    "sg:phone":"+1 574 255 1749",
    "sg:postcode":"46545",
    "sg:province":"IN",
    "wof:name":"Lloyd L Long Enterprises",
    "wof:placetype":"venue"
},
  "geometry": {"coordinates":[-86.189496,41.667093],"type":"Point"}
}