{
  "type": "Feature",
  "properties": {
    "iso:country":"US",
    "sg:address":"60 S 900 E",
    "sg:city":"Zionsville",
    "sg:classifiers":[
        {
            "category":"Sports & Exercise",
            "subcategory":"Golf",
            "type":"Entertainment"
        }
    ],
    "sg:phone":"+1 317 769 2363",
    "sg:postcode":"46077",
    "sg:province":"IN",
    "sg:tags":[
        "course"
    ],
    "wof:name":"Hickory Bend Golf Course",
    "wof:placetype":"venue"
},
  "geometry": {"coordinates":[-86.298931,40.039951],"type":"Point"}
}