{
  "type": "Feature",
  "properties": {
    "iso:country":"US",
    "sg:address":"1250 N Post Rd",
    "sg:city":"Indianapolis",
    "sg:classifiers":[
        {
            "category":"Health Services",
            "subcategory":"Doctor",
            "type":"Services"
        }
    ],
    "sg:phone":"+1 317 889 7980",
    "sg:postcode":"46219",
    "sg:province":"IN",
    "sg:tags":[
        "physician",
        "surgeon"
    ],
    "wof:name":"Center For Diagnostic Imaging",
    "wof:placetype":"venue"
},
  "geometry": {"coordinates":[-86.009338,39.786464],"type":"Point"}
}