{
  "type": "Feature",
  "properties": {
    "iso:country":"US",
    "sg:address":"411 3rd St",
    "sg:city":"Covington",
    "sg:classifiers":[
        {
            "category":"Building & Trades",
            "subcategory":"Construction",
            "type":"Services"
        }
    ],
    "sg:phone":"+1 765 793 3681",
    "sg:postcode":"47932",
    "sg:province":"IN",
    "sg:tags":[
        "contractor"
    ],
    "wof:name":"Legacy Building",
    "wof:placetype":"venue"
},
  "geometry": {"coordinates":[-87.398101,40.138251],"type":"Point"}
}