{
  "type": "Feature",
  "properties": {
    "addr:full":"1649 N Shadeland Ave Indianapolis IN 46219",
    "addr:housenumber":"1649",
    "addr:postcode":"46219",
    "addr:street":"N Shadeland Ave",
    "iso:country":"US",
    "sg:address":"1649 N Shadeland Ave",
    "sg:city":"Indianapolis",
    "sg:classifiers":[
        {
            "category":"Personal",
            "subcategory":"Barber",
            "type":"Services"
        }
    ],
    "sg:phone":"+1 317 322 8573",
    "sg:postcode":"46219",
    "sg:province":"IN",
    "wof:name":"Shadeland Barber Shop",
    "wof:placetype":"venue"
},
  "geometry": {"coordinates":[-86.045388,39.789877],"type":"Point"}
}