{
  "type": "Feature",
  "properties": {
    "iso:country":"US",
    "sg:address":"79 S Main St",
    "sg:city":"Linton",
    "sg:classifiers":[
        {
            "category":"Manufacturing",
            "subcategory":"Printing",
            "type":"Manufacturing & Wholesale Goods"
        }
    ],
    "sg:phone":"+1 812 847 4487",
    "sg:postcode":"47441",
    "sg:province":"IN",
    "sg:tags":[
        "newspaper"
    ],
    "sg:website":"www.dailycitizen.com",
    "wof:name":"Linton Daily Citizen",
    "wof:placetype":"venue"
},
  "geometry": {"coordinates":[-87.166048,39.032945],"type":"Point"}
}