{
  "type": "Feature",
  "properties": {
    "iso:country":"US",
    "sg:address":"205 S Adams St",
    "sg:city":"Hebron",
    "sg:classifiers":[
        {
            "category":"Social Services",
            "type":"Services"
        }
    ],
    "sg:phone":"+1 219 996 2499",
    "sg:postcode":"46341",
    "sg:province":"IN",
    "sg:tags":[
        "youth",
        "organization",
        "center"
    ],
    "wof:name":"Hebron Scout Cabin",
    "wof:placetype":"venue"
},
  "geometry": {"coordinates":[-87.202569,41.317608],"type":"Point"}
}