{
  "type": "Feature",
  "properties": {
    "iso:country":"US",
    "sg:address":"649 Cherry St",
    "sg:city":"Hammond",
    "sg:classifiers":[
        {
            "category":"Insurance",
            "subcategory":"Insurance Agent",
            "type":"Services"
        }
    ],
    "sg:phone":"+1 219 933 1411",
    "sg:postcode":"46324",
    "sg:province":"IN",
    "sg:tags":[
        "adjuster"
    ],
    "wof:name":"Municipal Adjusting Co Inc",
    "wof:placetype":"venue"
},
  "geometry": {"coordinates":[-87.51241,41.589238],"type":"Point"}
}