{
  "type": "Feature",
  "properties": {
    "addr:full":"2127 S Calhoun St Fort Wayne IN 46802",
    "addr:housenumber":"2127",
    "addr:postcode":"46802",
    "addr:street":"S Calhoun St",
    "iso:country":"US",
    "sg:address":"2127 S Calhoun St",
    "sg:city":"Fort Wayne",
    "sg:classifiers":[
        {
            "category":"Autos & Motor Vehicles",
            "subcategory":"Automobile Sales",
            "type":"Retail Goods"
        }
    ],
    "sg:phone":"+1 260 745 5249",
    "sg:postcode":"46802",
    "sg:province":"IN",
    "sg:tags":[
        "car",
        "dealer"
    ],
    "wof:name":"South Central Motors Inc",
    "wof:placetype":"venue"
},
  "geometry": {"coordinates":[-85.13795399999999,41.065492],"type":"Point"}
}