{
  "type": "Feature",
  "properties": {
    "iso:country":"US",
    "sg:address":"7110 Lima Rd",
    "sg:city":"Fort Wayne",
    "sg:classifiers":[
        {
            "category":"Banks & Credit Unions",
            "subcategory":"Bank",
            "type":"Services"
        }
    ],
    "sg:phone":"+1 260 467 5538",
    "sg:postcode":"46818",
    "sg:province":"IN",
    "wof:name":"Star Financial Bank",
    "wof:placetype":"venue"
},
  "geometry": {"coordinates":[-85.162333,41.139724],"type":"Point"}
}