{
  "type": "Feature",
  "properties": {
    "addr:full":"5150 W 76th St Indianapolis IN 46268",
    "addr:housenumber":"5150",
    "addr:postcode":"46268",
    "addr:street":"W 76Th St",
    "iso:country":"US",
    "sg:address":"5150 W 76th St",
    "sg:city":"Indianapolis",
    "sg:classifiers":[
        {
            "category":"Professional",
            "subcategory":"Advertising",
            "type":"Services"
        }
    ],
    "sg:phone":"+1 317 876 3661",
    "sg:postcode":"46268",
    "sg:province":"IN",
    "sg:tags":[
        "distributing",
        "sample"
    ],
    "sg:website":"www.jitindy.com",
    "wof:name":"JIT Svc",
    "wof:placetype":"venue"
},
  "geometry": {"coordinates":[-86.249583,39.891142],"type":"Point"}
}