{
  "type": "Feature",
  "properties": {
    "iso:country":"US",
    "sg:address":"3361 Schollenbarger Rd",
    "sg:city":"Oxford",
    "sg:phone":"+1 513 523 2106",
    "sg:postcode":"45056",
    "sg:province":"IN",
    "sg:tags":[
        "wheat",
        "farm",
        "corn",
        "crop",
        "field",
        "soybean"
    ],
    "wof:name":"Eddie Stang",
    "wof:placetype":"venue"
},
  "geometry": {"coordinates":[-84.67626799999999,39.494326],"type":"Point"}
}