{
  "type": "Feature",
  "properties": {
    "iso:country":"US",
    "sg:address":"1509 S Macedonia Ave",
    "sg:city":"Muncie",
    "sg:classifiers":[
        {
            "category":"Manufacturing",
            "subcategory":"Glass & Minerals",
            "type":"Manufacturing & Wholesale Goods"
        }
    ],
    "sg:phone":"+1 765 741 7000",
    "sg:postcode":"47302",
    "sg:province":"IN",
    "sg:tags":[
        "container"
    ],
    "sg:website":"www.sgcontainers.com",
    "wof:name":"Saint-Gobain Containers",
    "wof:placetype":"venue"
},
  "geometry": {"coordinates":[-85.367718,40.181778],"type":"Point"}
}