{
  "type": "Feature",
  "properties": {
    "iso:country":"US",
    "sg:address":"24720 Lamong Rd",
    "sg:city":"Sheridan",
    "sg:phone":"+1 317 758 5420",
    "sg:postcode":"46069",
    "sg:province":"IN",
    "sg:tags":[
        "farm",
        "corn",
        "soybean"
    ],
    "wof:name":"Kim Hollingswort",
    "wof:placetype":"venue"
},
  "geometry": {"coordinates":[-86.20407899999999,40.1447],"type":"Point"}
}