{
  "type": "Feature",
  "properties": {
    "addr:full":"330 Entrance Dr New Haven IN 46774",
    "addr:housenumber":"330",
    "addr:postcode":"46774",
    "addr:street":"Entrance Dr",
    "iso:country":"US",
    "sg:address":"330 Entrance Dr",
    "sg:city":"New Haven",
    "sg:classifiers":[
        {
            "category":"Organizations",
            "subcategory":"Community Association",
            "type":"Services"
        }
    ],
    "sg:phone":"+1 260 749 1188",
    "sg:postcode":"46774",
    "sg:province":"IN",
    "sg:tags":[
        "military"
    ],
    "wof:name":"American Legion",
    "wof:placetype":"venue"
},
  "geometry": {"coordinates":[-85.036492,41.068456],"type":"Point"}
}