{
  "type": "Feature",
  "properties": {
    "addr:full":"5718 Industrial Rd Fort Wayne IN 46825",
    "addr:housenumber":"5718",
    "addr:postcode":"46825",
    "addr:street":"Industrial Rd",
    "iso:country":"US",
    "sg:address":"5718 Industrial Rd",
    "sg:city":"Fort Wayne",
    "sg:classifiers":[
        {
            "category":"Retail",
            "subcategory":"Auto Repair",
            "type":"Services"
        }
    ],
    "sg:phone":"+1 260 484 8206",
    "sg:postcode":"46825",
    "sg:province":"IN",
    "sg:tags":[
        "automobile",
        "customizing"
    ],
    "wof:name":"Fine Lines",
    "wof:placetype":"venue"
},
  "geometry": {"coordinates":[-85.14709999999999,41.131464],"type":"Point"}
}