{
  "type": "Feature",
  "properties": {
    "iso:country":"US",
    "sg:address":"4956 E 56th St",
    "sg:city":"Indianapolis",
    "sg:classifiers":[
        {
            "category":"Insurance",
            "subcategory":"Insurance Agent",
            "type":"Services"
        }
    ],
    "sg:phone":"+1 317 205 3966",
    "sg:postcode":"46220",
    "sg:province":"IN",
    "wof:name":"American Family Insurance",
    "wof:placetype":"venue"
},
  "geometry": {"coordinates":[-86.083962,39.855073],"type":"Point"}
}