{
  "type": "Feature",
  "properties": {
    "iso:country":"US",
    "sg:address":"106 N Metts St",
    "sg:city":"Ossian",
    "sg:classifiers":[
        {
            "category":"Insurance",
            "subcategory":"Insurance Agent",
            "type":"Services"
        }
    ],
    "sg:phone":"+1 260 622 4169",
    "sg:postcode":"46777",
    "sg:province":"IN",
    "wof:name":"Insurance & Business Spec",
    "wof:placetype":"venue"
},
  "geometry": {"coordinates":[-85.165277,40.88024],"type":"Point"}
}