{
  "type": "Feature",
  "properties": {
    "addr:full":"101 S Main St Monticello IN 47960",
    "addr:housenumber":"101",
    "addr:postcode":"47960",
    "addr:street":"S Main St",
    "iso:country":"US",
    "sg:address":"101 S Main St",
    "sg:city":"Monticello",
    "sg:classifiers":[
        {
            "category":"Professional",
            "subcategory":"Accounting & Tax Preparation",
            "type":"Services"
        }
    ],
    "sg:phone":"+1 574 583 4829",
    "sg:postcode":"47960",
    "sg:province":"IN",
    "sg:tags":[
        "return",
        "filing"
    ],
    "wof:name":"Twin Lakes Tax Assoc",
    "wof:placetype":"venue"
},
  "geometry": {"coordinates":[-86.76191900000001,40.744939],"type":"Point"}
}