{
  "type": "Feature",
  "properties": {
    "iso:country":"US",
    "sg:address":"4758 E Noos",
    "sg:city":"Kokomo",
    "sg:classifiers":[
        {
            "category":"Manufacturing",
            "subcategory":"Printing",
            "type":"Manufacturing & Wholesale Goods"
        }
    ],
    "sg:phone":"+1 765 457 8580",
    "sg:postcode":"46953",
    "sg:province":"IN",
    "sg:tags":[
        "screen"
    ],
    "wof:name":"ADI Screen Printing",
    "wof:placetype":"venue"
},
  "geometry": {"coordinates":[-85.598279,40.552812],"type":"Point"}
}