{
  "type": "Feature",
  "properties": {
    "iso:country":"US",
    "sg:address":"7301 Woodland Dr",
    "sg:city":"Indianapolis",
    "sg:classifiers":[
        {
            "category":"Manufacturing",
            "subcategory":"Printing",
            "type":"Manufacturing & Wholesale Goods"
        }
    ],
    "sg:phone":"+1 317 293 1500",
    "sg:postcode":"46278",
    "sg:province":"IN",
    "sg:tags":[
        "printer"
    ],
    "sg:website":"www.gacindy.com",
    "wof:name":"Graphic Arts Ctr Indianapolis",
    "wof:placetype":"venue"
},
  "geometry": {"coordinates":[-86.266954,39.886409],"type":"Point"}
}