{
  "type": "Feature",
  "properties": {
    "iso:country":"US",
    "sg:address":"136 E 3rd St",
    "sg:city":"Rushville",
    "sg:classifiers":[
        {
            "category":"Home & Garden",
            "subcategory":"Building Materials",
            "type":"Retail Goods"
        }
    ],
    "sg:phone":"+1 765 938 5110",
    "sg:postcode":"46173",
    "sg:province":"IN",
    "sg:tags":[
        "glass",
        "leaded"
    ],
    "wof:name":"Glasermeister Inc",
    "wof:placetype":"venue"
},
  "geometry": {"coordinates":[-85.443817,39.609415],"type":"Point"}
}