{
  "type": "Feature",
  "properties": {
    "addr:full":"4158 N 400 W Sharpsville IN 46068",
    "addr:housenumber":"4158",
    "addr:postcode":"46068",
    "addr:street":"N 400 W",
    "iso:country":"US",
    "sg:address":"4158 N 400 W",
    "sg:city":"Sharpsville",
    "sg:classifiers":[
        {
            "category":"Shopping",
            "subcategory":"Florist",
            "type":"Retail Goods"
        }
    ],
    "sg:phone":"+1 765 963 2739",
    "sg:postcode":"46068",
    "sg:province":"IN",
    "wof:name":"Brumbaugh Greenhouse & Flower",
    "wof:placetype":"venue"
},
  "geometry": {"coordinates":[-86.088579,40.369994],"type":"Point"}
}