{
  "type": "Feature",
  "properties": {
    "iso:country":"US",
    "sg:address":"118 N Van Rensselaer St",
    "sg:city":"Rensselaer",
    "sg:classifiers":[
        {
            "category":"Insurance",
            "subcategory":"Insurance Agent",
            "type":"Services"
        }
    ],
    "sg:phone":"+1 219 866 8644",
    "sg:postcode":"47978",
    "sg:province":"IN",
    "wof:name":"Shelter Insurance",
    "wof:placetype":"venue"
},
  "geometry": {"coordinates":[-87.152545,40.936645],"type":"Point"}
}