{
  "type": "Feature",
  "properties": {
    "iso:country":"US",
    "sg:address":"322 N Front St",
    "sg:city":"Rensselaer",
    "sg:classifiers":[
        {
            "category":"Farming",
            "subcategory":"Farm",
            "type":"Manufacturing & Wholesale Goods"
        }
    ],
    "sg:phone":"+1 219 866 5902",
    "sg:postcode":"47978",
    "sg:province":"IN",
    "sg:tags":[
        "crop",
        "general"
    ],
    "wof:name":"Branson Merle",
    "wof:placetype":"venue"
},
  "geometry": {"coordinates":[-87.155348,40.937596],"type":"Point"}
}