{
  "type": "Feature",
  "properties": {
    "iso:country":"US",
    "sg:address":"3333 N Everbrook Ln",
    "sg:city":"Muncie",
    "sg:classifiers":[
        {
            "category":"Home & Garden",
            "subcategory":"Furniture",
            "type":"Retail Goods"
        }
    ],
    "sg:phone":"+1 765 284 4221",
    "sg:postcode":"47304",
    "sg:province":"IN",
    "sg:tags":[
        "mattress"
    ],
    "wof:name":"Today's Bedroom One",
    "wof:placetype":"venue"
},
  "geometry": {"coordinates":[-85.426677,40.21677],"type":"Point"}
}