{
  "type": "Feature",
  "properties": {
    "addr:full":"3000 State Rd 62 Jeffersonville IN 47130",
    "addr:housenumber":"3000;62",
    "addr:postcode":"47130",
    "addr:street":"State Rd",
    "iso:country":"US",
    "sg:address":"3000 State Rd 62",
    "sg:city":"Jeffersonville",
    "sg:classifiers":[
        {
            "category":"Restaurant",
            "type":"Food & Drink"
        }
    ],
    "sg:phone":"+1 812 283 0663",
    "sg:postcode":"47130",
    "sg:province":"IN",
    "wof:name":"Mc Donald's",
    "wof:placetype":"venue"
},
  "geometry": {"coordinates":[-85.712463,38.324432],"type":"Point"}
}