{
  "type": "Feature",
  "properties": {
    "iso:country":"US",
    "sg:address":"425 W Maple St",
    "sg:city":"Waterloo",
    "sg:classifiers":[
        {
            "category":"Travel",
            "subcategory":"Hotels & Motels",
            "type":"Entertainment"
        }
    ],
    "sg:phone":"+1 260 837 5323",
    "sg:postcode":"46793",
    "sg:province":"IN",
    "sg:tags":[
        "breakfast",
        "accommodation",
        "bed"
    ],
    "wof:name":"Maple Leaf Inn",
    "wof:placetype":"venue"
},
  "geometry": {"coordinates":[-85.02446399999999,41.429857],"type":"Point"}
}