{
  "type": "Feature",
  "properties": {
    "addr:full":"10405 Glen Arbor Pass Fort Wayne IN 46814",
    "addr:housenumber":"10405",
    "addr:postcode":"46814",
    "addr:street":"Glen Arbor Pass",
    "iso:country":"US",
    "sg:address":"10405 Glen Arbor Pass",
    "sg:city":"Fort Wayne",
    "sg:classifiers":[
        {
            "category":"Professional",
            "type":"Services"
        }
    ],
    "sg:phone":"+1 260 625 5798",
    "sg:postcode":"46814",
    "sg:province":"IN",
    "wof:name":"Mr Eric R Evans",
    "wof:placetype":"venue"
},
  "geometry": {"coordinates":[-85.27788700000001,41.066275],"type":"Point"}
}