{
  "type": "Feature",
  "properties": {
    "addr:full":"633 Library Park Dr Greenwood IN 46142",
    "addr:housenumber":"633",
    "addr:postcode":"46142",
    "addr:street":"Library Park Dr",
    "iso:country":"US",
    "sg:address":"633 Library Park Dr",
    "sg:city":"Greenwood",
    "sg:classifiers":[
        {
            "category":"Professional",
            "subcategory":"Computer Services",
            "type":"Services"
        }
    ],
    "sg:phone":"+1 317 865 4835",
    "sg:postcode":"46142",
    "sg:province":"IN",
    "sg:tags":[
        "website",
        "design"
    ],
    "sg:website":"www.imaxindy.com",
    "wof:name":"Web Pros",
    "wof:placetype":"venue"
},
  "geometry": {"coordinates":[-86.157269,39.60657],"type":"Point"}
}