{
  "type": "Feature",
  "properties": {
    "addr:full":"5017 Jaysue St Anderson IN 46013",
    "addr:housenumber":"5017",
    "addr:postcode":"46013",
    "addr:street":"Jaysue St",
    "iso:country":"US",
    "sg:address":"5017 Jaysue St",
    "sg:city":"Anderson",
    "sg:classifiers":[
        {
            "category":"Professional",
            "subcategory":"Management & Consulting",
            "type":"Services"
        }
    ],
    "sg:phone":"+1 765 649 3538",
    "sg:postcode":"46013",
    "sg:province":"IN",
    "sg:tags":[
        "automotive",
        "quality"
    ],
    "wof:name":"Ralph Gordon",
    "wof:placetype":"venue"
},
  "geometry": {"coordinates":[-85.65840300000001,40.061962],"type":"Point"}
}