{
  "type": "Feature",
  "properties": {
    "iso:country":"US",
    "sg:address":"2036 Traders Xing",
    "sg:city":"Fort Wayne",
    "sg:classifiers":[
        {
            "category":"Wholesale",
            "subcategory":"Durable Goods & Equipment",
            "type":"Manufacturing & Wholesale Goods"
        }
    ],
    "sg:phone":"+1 260 637 8806",
    "sg:postcode":"46845",
    "sg:province":"IN",
    "sg:tags":[
        "representative",
        "manufacturer"
    ],
    "wof:name":"Sheean & Assoc Inc",
    "wof:placetype":"venue"
},
  "geometry": {"coordinates":[-85.116331,41.179202],"type":"Point"}
}