{
  "type": "Feature",
  "properties": {
    "iso:country":"US",
    "sg:address":"3600 N German Church Rd",
    "sg:city":"Indianapolis",
    "sg:classifiers":[
        {
            "category":"Education",
            "subcategory":"School",
            "type":"Public Place"
        }
    ],
    "sg:phone":"+1 317 891 0730",
    "sg:postcode":"46235",
    "sg:province":"IN",
    "wof:name":"Andrew J Brown Charter School",
    "wof:placetype":"venue"
},
  "geometry": {"coordinates":[-85.972027,39.82322],"type":"Point"}
}