{
  "type": "Feature",
  "properties": {
    "iso:country":"US",
    "sg:address":"2510 Hulman St",
    "sg:city":"Terre Haute",
    "sg:classifiers":[
        {
            "category":"Health Services",
            "subcategory":"Doctor",
            "type":"Services"
        }
    ],
    "sg:phone":"+1 812 232 2445",
    "sg:postcode":"47803",
    "sg:province":"IN",
    "sg:tags":[
        "dentist"
    ],
    "wof:name":"David E Cox Inc",
    "wof:placetype":"venue"
},
  "geometry": {"coordinates":[-87.377699,39.448482],"type":"Point"}
}