{
  "type": "Feature",
  "properties": {
    "iso:country":"US",
    "sg:address":"407 Ferry St",
    "sg:city":"Lafayette",
    "sg:classifiers":[
        {
            "category":"Real Estate",
            "subcategory":"Real Estate Agent",
            "type":"Services"
        }
    ],
    "sg:phone":"+1 765 429 5991",
    "sg:postcode":"47901",
    "sg:province":"IN",
    "wof:name":"Cypress Realty Inc",
    "wof:placetype":"venue"
},
  "geometry": {"coordinates":[-86.891922,40.419968],"type":"Point"}
}