{
  "type": "Feature",
  "properties": {
    "iso:country":"US",
    "sg:address":"8404 S 825 E",
    "sg:city":"Ladoga",
    "sg:classifiers":[
        {
            "category":"Farming",
            "subcategory":"Farm",
            "type":"Manufacturing & Wholesale Goods"
        }
    ],
    "sg:phone":"+1 765 942 2046",
    "sg:postcode":"47954",
    "sg:province":"IN",
    "sg:tags":[
        "crop",
        "general"
    ],
    "wof:name":"Gary D Bradley Farm",
    "wof:placetype":"venue"
},
  "geometry": {"coordinates":[-86.747411,39.915738],"type":"Point"}
}