{
  "type": "Feature",
  "properties": {
    "addr:full":"1750 25th St Columbus IN 47201",
    "addr:housenumber":"1750",
    "addr:postcode":"47201",
    "addr:street":"25Th St",
    "iso:country":"US",
    "sg:address":"1750 25th St",
    "sg:city":"Columbus",
    "sg:classifiers":[
        {
            "category":"Food & Beverages",
            "subcategory":"Groceries & Convenience Stores",
            "type":"Retail Goods"
        }
    ],
    "sg:phone":"+1 812 000 1111",
    "sg:postcode":"47201",
    "sg:province":"IN",
    "sg:tags":[
        "grocer"
    ],
    "wof:name":"Aldi",
    "wof:placetype":"venue"
},
  "geometry": {"coordinates":[-85.906567,39.222993],"type":"Point"}
}