{
  "type": "Feature",
  "properties": {
    "iso:country":"US",
    "sg:address":"51537 Bittersweet Rd",
    "sg:city":"Granger",
    "sg:classifiers":[
        {
            "category":"Insurance",
            "subcategory":"Insurance Agent",
            "type":"Services"
        }
    ],
    "sg:phone":"+1 574 272 7711",
    "sg:postcode":"46530",
    "sg:province":"IN",
    "wof:name":"Graham Snyder",
    "wof:placetype":"venue"
},
  "geometry": {"coordinates":[-86.110936,41.744156],"type":"Point"}
}