{
  "type": "Feature",
  "properties": {
    "addr:full":"1218 5th St Bedford IN 47421",
    "addr:housenumber":"1218",
    "addr:postcode":"47421",
    "addr:street":"5Th St",
    "iso:country":"US",
    "sg:address":"1218 5th St",
    "sg:city":"Bedford",
    "sg:classifiers":[
        {
            "category":"Manufacturing",
            "subcategory":"Metals",
            "type":"Manufacturing & Wholesale Goods"
        }
    ],
    "sg:phone":"+1 812 275 4489",
    "sg:postcode":"47421",
    "sg:province":"IN",
    "sg:tags":[
        "steel"
    ],
    "wof:name":"Sigma Steel Inc",
    "wof:placetype":"venue"
},
  "geometry": {"coordinates":[-86.487579,38.874306],"type":"Point"}
}