{
  "type": "Feature",
  "properties": {
    "addr:full":"6135 N Meridian St Indianapolis IN 46208",
    "addr:housenumber":"6135",
    "addr:postcode":"46208",
    "addr:street":"N Meridian St",
    "iso:country":"US",
    "sg:address":"6135 N Meridian St",
    "sg:city":"Indianapolis",
    "sg:classifiers":[
        {
            "category":"Professional",
            "subcategory":"Accounting & Tax Preparation",
            "type":"Services"
        }
    ],
    "sg:phone":"+1 317 257 8900",
    "sg:postcode":"46208",
    "sg:province":"IN",
    "sg:tags":[
        "accountant"
    ],
    "sg:website":"www.deesaul.com",
    "wof:name":"Dee Saul & Co Inc",
    "wof:placetype":"venue"
},
  "geometry": {"coordinates":[-86.15589199999999,39.86508],"type":"Point"}
}