{
  "type": "Feature",
  "properties": {
    "iso:country":"US",
    "sg:address":"467 N Emmons St",
    "sg:city":"Madison",
    "sg:classifiers":[
        {
            "category":"Building & Trades",
            "subcategory":"Construction",
            "type":"Services"
        }
    ],
    "sg:phone":"+1 812 599 2497",
    "sg:postcode":"47250",
    "sg:province":"IN",
    "sg:tags":[
        "dry wall",
        "contractor"
    ],
    "wof:name":"Absolutely Drywall",
    "wof:placetype":"venue"
},
  "geometry": {"coordinates":[-85.45401699999999,38.749829],"type":"Point"}
}