{
  "type": "Feature",
  "properties": {
    "iso:country":"US",
    "sg:address":"3508 Stellhorn Rd",
    "sg:city":"Fort Wayne",
    "sg:classifiers":[
        {
            "category":"Professional",
            "subcategory":"Business Services",
            "type":"Services"
        }
    ],
    "sg:phone":"+1 260 485 1990",
    "sg:postcode":"46815",
    "sg:province":"IN",
    "sg:tags":[
        "broker"
    ],
    "sg:website":"www.anthonywayne.com",
    "wof:name":"Anthony Wayne Business Exch",
    "wof:placetype":"venue"
},
  "geometry": {"coordinates":[-85.096613,41.119227],"type":"Point"}
}