{
  "type": "Feature",
  "properties": {
    "iso:country":"US",
    "sg:address":"6247 E Neitzel Rd",
    "sg:city":"Mooresville",
    "sg:classifiers":[
        {
            "category":"Banks & Credit Unions",
            "subcategory":"Investment Brokerage",
            "type":"Services"
        }
    ],
    "sg:phone":"+1 317 831 8298",
    "sg:postcode":"46158",
    "sg:province":"IN",
    "sg:tags":[
        "advisory"
    ],
    "wof:name":"Wayne Kefauver",
    "wof:placetype":"venue"
},
  "geometry": {"coordinates":[-86.312591,39.59631],"type":"Point"}
}