{
  "type": "Feature",
  "properties": {
    "iso:country":"US",
    "sg:address":"106 W Pearl St",
    "sg:city":"Winamac",
    "sg:classifiers":[
        {
            "category":"Professional",
            "subcategory":"Lawyer & Legal Services",
            "type":"Services"
        }
    ],
    "sg:phone":"+1 574 946 6575",
    "sg:postcode":"46996",
    "sg:province":"IN",
    "sg:tags":[
        "attorney"
    ],
    "wof:name":"Patrick Blankenship",
    "wof:placetype":"venue"
},
  "geometry": {"coordinates":[-86.605681,41.051525],"type":"Point"}
}