{
  "type": "Feature",
  "properties": {
    "iso:country":"US",
    "sg:address":"9239 N 450 E",
    "sg:city":"Pine Village",
    "sg:classifiers":[
        {
            "category":"Shopping",
            "type":"Retail Goods"
        }
    ],
    "sg:phone":"+1 765 385 2633",
    "sg:postcode":"47975",
    "sg:province":"IN",
    "sg:tags":[
        "merchandise"
    ],
    "wof:name":"Petal Vine Collection",
    "wof:placetype":"venue"
},
  "geometry": {"coordinates":[-87.235252,40.464677],"type":"Point"}
}