{
  "type": "Feature",
  "properties": {
    "iso:country":"US",
    "sg:address":"575 W State Rd 8",
    "sg:city":"Hebron",
    "sg:classifiers":[
        {
            "category":"Freight",
            "type":"Transportation"
        }
    ],
    "sg:phone":"+1 219 987 6009",
    "sg:postcode":"46341",
    "sg:province":"IN",
    "sg:tags":[
        "commercial",
        "storage"
    ],
    "wof:name":"American U Lock",
    "wof:placetype":"venue"
},
  "geometry": {"coordinates":[-87.181109,41.317947],"type":"Point"}
}