{
  "type": "Feature",
  "properties": {
    "iso:country":"US",
    "sg:address":"513 N College Ave",
    "sg:city":"Indianapolis",
    "sg:classifiers":[
        {
            "category":"Real Estate",
            "subcategory":"Developer",
            "type":"Services"
        }
    ],
    "sg:phone":"+1 317 636 5782",
    "sg:postcode":"46202",
    "sg:province":"IN",
    "wof:name":"LRTB",
    "wof:placetype":"venue"
},
  "geometry": {"coordinates":[-86.145272,39.775009],"type":"Point"}
}