{
  "type": "Feature",
  "properties": {
    "iso:country":"US",
    "sg:address":"322 Waldron St",
    "sg:city":"West Lafayette",
    "sg:classifiers":[
        {
            "category":"Organizations",
            "subcategory":"Community Association",
            "type":"Services"
        }
    ],
    "sg:phone":"+1 765 743 1234",
    "sg:postcode":"47906",
    "sg:province":"IN",
    "sg:tags":[
        "sorority",
        "fraternity"
    ],
    "wof:name":"Twin Pines Co-Op House",
    "wof:placetype":"venue"
},
  "geometry": {"coordinates":[-86.91786,40.428056],"type":"Point"}
}