{
  "type": "Feature",
  "properties": {
    "iso:country":"US",
    "sg:address":"9347 Eastwind Ln",
    "sg:city":"Indianapolis",
    "sg:classifiers":[
        {
            "category":"Professional",
            "subcategory":"Computer Services",
            "type":"Services"
        }
    ],
    "sg:phone":"+1 317 842 1428",
    "sg:postcode":"46256",
    "sg:province":"IN",
    "sg:tags":[
        "programing",
        "custom"
    ],
    "wof:name":"C T Solution Inc",
    "wof:placetype":"venue"
},
  "geometry": {"coordinates":[-85.988806,39.923563],"type":"Point"}
}