{
  "type": "Feature",
  "properties": {
    "addr:full":"2733 E Main St Plainfield IN 46168",
    "addr:housenumber":"2733",
    "addr:postcode":"46168",
    "addr:street":"E Main St",
    "iso:country":"US",
    "sg:address":"2733 E Main St",
    "sg:city":"Plainfield",
    "sg:classifiers":[
        {
            "category":"Shopping",
            "subcategory":"Bicycles & Sporting Goods",
            "type":"Retail Goods"
        },
        {
            "category":"Education",
            "subcategory":"School",
            "type":"Public Place"
        },
        {
            "category":"Sports & Exercise",
            "subcategory":"Golf",
            "type":"Entertainment"
        }
    ],
    "sg:phone":"+1 317 838 0380",
    "sg:postcode":"46168",
    "sg:province":"IN",
    "sg:tags":[
        "instruction",
        "course",
        "practice",
        "equipment",
        "range",
        "supply"
    ],
    "sg:website":"http://www.golfheadquartersonline.com",
    "wof:name":"Golf Headquarters",
    "wof:placetype":"venue"
},
  "geometry": {"coordinates":[-86.352935,39.719484],"type":"Point"}
}