{
  "type": "Feature",
  "properties": {
    "iso:country":"US",
    "sg:address":"851 Indian Boundary Rd",
    "sg:city":"Chesterton",
    "sg:classifiers":[
        {
            "category":"Banks & Credit Unions",
            "subcategory":"Investment Brokerage",
            "type":"Services"
        }
    ],
    "sg:phone":"+1 219 929 1234",
    "sg:postcode":"46304",
    "sg:province":"IN",
    "sg:tags":[
        "consultant",
        "planning",
        "financial"
    ],
    "sg:website":"www.bradwerner.com",
    "wof:name":"Brad Werner & Co",
    "wof:placetype":"venue"
},
  "geometry": {"coordinates":[-87.03879,41.616942],"type":"Point"}
}