{
  "type": "Feature",
  "properties": {
    "iso:country":"US",
    "sg:address":"202 N Mill St",
    "sg:city":"Plainfield",
    "sg:classifiers":[
        {
            "category":"Home & Garden",
            "subcategory":"Home Furnishings",
            "type":"Retail Goods"
        }
    ],
    "sg:phone":"+1 317 837 6300",
    "sg:postcode":"46168",
    "sg:province":"IN",
    "sg:tags":[
        "pillow"
    ],
    "wof:name":"B & J Pillows",
    "wof:placetype":"venue"
},
  "geometry": {"coordinates":[-86.404905,39.705244],"type":"Point"}
}