{
  "type": "Feature",
  "properties": {
    "iso:country":"US",
    "sg:address":"304 S Washington St",
    "sg:city":"Greenwood",
    "sg:classifiers":[
        {
            "category":"Manufacturing",
            "subcategory":"Printing",
            "type":"Manufacturing & Wholesale Goods"
        }
    ],
    "sg:phone":"+1 765 763 0411",
    "sg:postcode":"46143",
    "sg:province":"IN",
    "sg:tags":[
        "printer"
    ],
    "wof:name":"High Hopes Printing & Signs",
    "wof:placetype":"venue"
},
  "geometry": {"coordinates":[-86.103411,39.612814],"type":"Point"}
}