{
  "type": "Feature",
  "properties": {
    "addr:full":"443 N Capitol Ave Corydon IN 47112",
    "addr:housenumber":"443",
    "addr:postcode":"47112",
    "addr:street":"N Capitol Ave",
    "iso:country":"US",
    "sg:address":"443 N Capitol Ave",
    "sg:city":"Corydon",
    "sg:classifiers":[
        {
            "category":"Autos & Motor Vehicles",
            "subcategory":"Auto Supplies",
            "type":"Retail Goods"
        }
    ],
    "sg:phone":"+1 812 738 3545",
    "sg:postcode":"47112",
    "sg:province":"IN",
    "sg:tags":[
        "automobile",
        "parts"
    ],
    "sg:website":"www.autozone.com",
    "wof:name":"Autozone",
    "wof:placetype":"venue"
},
  "geometry": {"coordinates":[-86.12634799999999,38.213152],"type":"Point"}
}