{
  "type": "Feature",
  "properties": {
    "iso:country":"US",
    "sg:address":"211 W Broadway St",
    "sg:city":"Fortville",
    "sg:classifiers":[
        {
            "category":"Shopping",
            "subcategory":"Florist",
            "type":"Retail Goods"
        }
    ],
    "sg:phone":"+1 317 485 5441",
    "sg:postcode":"46040",
    "sg:province":"IN",
    "wof:name":"Flowers & More",
    "wof:placetype":"venue"
},
  "geometry": {"coordinates":[-85.848842,39.930977],"type":"Point"}
}