{
  "type": "Feature",
  "properties": {
    "iso:country":"US",
    "sg:address":"7966 Wicker Ave",
    "sg:city":"St John",
    "sg:classifiers":[
        {
            "category":"Personal",
            "type":"Services"
        }
    ],
    "sg:phone":"+1 219 365 8159",
    "sg:postcode":"46373",
    "sg:province":"IN",
    "sg:tags":[
        "wear",
        "formal"
    ],
    "wof:name":"Dunhill Tuxedos",
    "wof:placetype":"venue"
},
  "geometry": {"coordinates":[-87.470504,41.47438],"type":"Point"}
}