{
  "type": "Feature",
  "properties": {
    "iso:country":"US",
    "sg:address":"12211 US Hwy 27 S",
    "sg:city":"Fort Wayne",
    "sg:classifiers":[
        {
            "category":"Travel",
            "subcategory":"Hotels & Motels",
            "type":"Entertainment"
        }
    ],
    "sg:phone":"+1 260 639 3677",
    "sg:postcode":"46816",
    "sg:province":"IN",
    "wof:name":"Country Inn",
    "wof:placetype":"venue"
},
  "geometry": {"coordinates":[-85.079223,40.971111],"type":"Point"}
}