{
  "type": "Feature",
  "properties": {
    "addr:full":"513 W 8th St Connersville IN 47331",
    "addr:housenumber":"513",
    "addr:postcode":"47331",
    "addr:street":"W 8Th St",
    "iso:country":"US",
    "sg:address":"513 W 8th St",
    "sg:city":"Connersville",
    "sg:classifiers":[
        {
            "category":"Retail",
            "subcategory":"Funeral Services",
            "type":"Services"
        }
    ],
    "sg:phone":"+1 765 825 1761",
    "sg:postcode":"47331",
    "sg:province":"IN",
    "sg:tags":[
        "director"
    ],
    "wof:name":"Urban-Winkler Funeral Home",
    "wof:placetype":"venue"
},
  "geometry": {"coordinates":[-85.141187,39.645683],"type":"Point"}
}