{
  "type": "Feature",
  "properties": {
    "iso:country":"US",
    "sg:address":"121 N Main St",
    "sg:city":"Crown Point",
    "sg:classifiers":[
        {
            "category":"Personal",
            "type":"Services"
        },
        {
            "category":"Retail",
            "subcategory":"Auto Repair",
            "type":"Services"
        }
    ],
    "sg:phone":"+1 219 696 6677",
    "sg:postcode":"46307",
    "sg:province":"IN",
    "sg:tags":[
        "towing"
    ],
    "wof:name":"Master Transmissions",
    "wof:placetype":"venue"
},
  "geometry": {"coordinates":[-87.364502,41.418098],"type":"Point"}
}