{
  "type": "Feature",
  "properties": {
    "addr:full":"900 Ridge Rd Ste S Munster IN 46321",
    "addr:housenumber":"900",
    "addr:postcode":"46321",
    "addr:street":"Ridge Rd Ste S",
    "iso:country":"US",
    "sg:address":"900 Ridge Rd Ste S",
    "sg:city":"Munster",
    "sg:classifiers":[
        {
            "category":"Professional",
            "subcategory":"Accounting & Tax Preparation",
            "type":"Services"
        }
    ],
    "sg:phone":"+1 219 836 4930",
    "sg:postcode":"46321",
    "sg:province":"IN",
    "sg:tags":[
        "accountant"
    ],
    "sg:website":"www.homerwilsonco.com",
    "wof:name":"Homer Wilson & Co Ltd",
    "wof:placetype":"venue"
},
  "geometry": {"coordinates":[-87.506798,41.560902],"type":"Point"}
}