{
  "type": "Feature",
  "properties": {
    "addr:full":"1109 S Miller St Shelbyville IN 46176",
    "addr:housenumber":"1109",
    "addr:postcode":"46176",
    "addr:street":"S Miller St",
    "iso:country":"US",
    "sg:address":"1109 S Miller St",
    "sg:city":"Shelbyville",
    "sg:classifiers":[
        {
            "category":"Building & Trades",
            "subcategory":"Plumbing",
            "type":"Services"
        }
    ],
    "sg:phone":"+1 317 398 2954",
    "sg:postcode":"46176",
    "sg:province":"IN",
    "sg:tags":[
        "plumbing",
        "contractor"
    ],
    "wof:name":"Christman & Heady Plumbing Svc",
    "wof:placetype":"venue"
},
  "geometry": {"coordinates":[-85.784823,39.514337],"type":"Point"}
}