{
  "type": "Feature",
  "properties": {
    "iso:country":"US",
    "sg:address":"1355 Lakeview Dr",
    "sg:city":"Huntingburg",
    "sg:classifiers":[
        {
            "category":"Professional",
            "subcategory":"Business Services",
            "type":"Services"
        }
    ],
    "sg:phone":"+1 812 683 2326",
    "sg:postcode":"47542",
    "sg:province":"IN",
    "wof:name":"Daniel Bean",
    "wof:placetype":"venue"
},
  "geometry": {"coordinates":[-86.955809,38.276421],"type":"Point"}
}