{
  "type": "Feature",
  "properties": {
    "iso:country":"US",
    "sg:address":"14386 Co Rd 14",
    "sg:city":"Middlebury",
    "sg:classifiers":[
        {
            "category":"Manufacturing",
            "subcategory":"Tools & Machinery",
            "type":"Manufacturing & Wholesale Goods"
        }
    ],
    "sg:phone":"+1 574 825 2877",
    "sg:postcode":"46540",
    "sg:province":"IN",
    "sg:tags":[
        "windmill"
    ],
    "wof:name":"Miller's Windmill Svc",
    "wof:placetype":"venue"
},
  "geometry": {"coordinates":[-85.74262899999999,41.68268],"type":"Point"}
}