{
  "type": "Feature",
  "properties": {
    "addr:full":"5716 S Bridgeton Ln South Bend IN 46614",
    "addr:housenumber":"5716",
    "addr:postcode":"46614",
    "addr:street":"S Bridgeton Ln",
    "iso:country":"US",
    "sg:address":"5716 S Bridgeton Ln",
    "sg:city":"South Bend",
    "sg:classifiers":[
        {
            "category":"Wholesale",
            "subcategory":"Machinery & Supplies",
            "type":"Manufacturing & Wholesale Goods"
        }
    ],
    "sg:phone":"+1 574 231 0094",
    "sg:postcode":"46614",
    "sg:province":"IN",
    "sg:tags":[
        "equipment",
        "material",
        "handling"
    ],
    "wof:name":"Courtney Material Handling Inc",
    "wof:placetype":"venue"
},
  "geometry": {"coordinates":[-86.222596,41.61177],"type":"Point"}
}