{
  "type": "Feature",
  "properties": {
    "addr:full":"4410 E 62nd St Indianapolis IN 46220",
    "addr:housenumber":"4410",
    "addr:postcode":"46220",
    "addr:street":"E 62Nd St",
    "iso:country":"US",
    "sg:address":"4410 E 62nd St",
    "sg:city":"Indianapolis",
    "sg:classifiers":[
        {
            "category":"Wholesale",
            "subcategory":"Plants",
            "type":"Manufacturing & Wholesale Goods"
        }
    ],
    "sg:phone":"+1 317 253 9014",
    "sg:postcode":"46220",
    "sg:province":"IN",
    "sg:tags":[
        "supply"
    ],
    "wof:name":"Oracion Mouton Enterprise",
    "wof:placetype":"venue"
},
  "geometry": {"coordinates":[-86.093186,39.868702],"type":"Point"}
}