{
  "type": "Feature",
  "properties": {
    "iso:country":"US",
    "sg:address":"221 US Hwy 41",
    "sg:city":"Schererville",
    "sg:classifiers":[
        {
            "category":"Restaurant",
            "type":"Food & Drink"
        }
    ],
    "sg:phone":"+1 219 865 0900",
    "sg:postcode":"46375",
    "sg:province":"IN",
    "wof:name":"Woodhollow Loft Bar & Grill",
    "wof:placetype":"venue"
},
  "geometry": {"coordinates":[-87.47122299999999,41.520261],"type":"Point"}
}