{
  "type": "Feature",
  "properties": {
    "iso:country":"US",
    "sg:address":"1531 W 200 N",
    "sg:city":"Greenfield",
    "sg:classifiers":[
        {
            "category":"Shopping",
            "subcategory":"Computers & Home Electronics",
            "type":"Retail Goods"
        }
    ],
    "sg:phone":"+1 317 326 4747",
    "sg:postcode":"46140",
    "sg:province":"IN",
    "sg:tags":[
        "software"
    ],
    "wof:name":"Lawson Software Inc",
    "wof:placetype":"venue"
},
  "geometry": {"coordinates":[-85.83099199999999,39.813149],"type":"Point"}
}