{
  "type": "Feature",
  "properties": {
    "iso:country":"US",
    "sg:address":"3800 W Michigan St Apt 904",
    "sg:city":"Indianapolis",
    "sg:classifiers":[
        {
            "category":"Shopping",
            "subcategory":"Gifts & Souvenirs",
            "type":"Retail Goods"
        }
    ],
    "sg:phone":"+1 317 247 0846",
    "sg:postcode":"46222",
    "sg:province":"IN",
    "sg:tags":[
        "shop"
    ],
    "wof:name":"Affordable Gifts Hq",
    "wof:placetype":"venue"
},
  "geometry": {"coordinates":[-86.225182,39.77375],"type":"Point"}
}