{
  "type": "Feature",
  "properties": {
    "iso:country":"US",
    "sg:address":"2030 Runaway Bay Dr",
    "sg:city":"Indianapolis",
    "sg:classifiers":[
        {
            "category":"Real Estate",
            "subcategory":"Real Estate Operator",
            "type":"Services"
        }
    ],
    "sg:phone":"+1 317 243 2600",
    "sg:postcode":"46224",
    "sg:province":"IN",
    "sg:tags":[
        "apartment"
    ],
    "wof:name":"Runaway Bay",
    "wof:placetype":"venue"
},
  "geometry": {"coordinates":[-86.26602800000001,39.794233],"type":"Point"}
}