{
  "type": "Feature",
  "properties": {
    "iso:country":"US",
    "sg:address":"5438 State Rd 16",
    "sg:city":"Rensselaer",
    "sg:classifiers":[
        {
            "category":"Freight",
            "type":"Transportation"
        }
    ],
    "sg:phone":"+1 219 866 4146",
    "sg:postcode":"47978",
    "sg:province":"IN",
    "sg:tags":[
        "livestock",
        "hauling"
    ],
    "wof:name":"Poultry Pride Inc",
    "wof:placetype":"venue"
},
  "geometry": {"coordinates":[-87.149014,40.866533],"type":"Point"}
}