{
  "type": "Feature",
  "properties": {
    "iso:country":"US",
    "sg:address":"9812 E Ellsworth Rd",
    "sg:city":"Celestine",
    "sg:classifiers":[
        {
            "category":"Recreation",
            "subcategory":"Marina",
            "type":"Entertainment"
        }
    ],
    "sg:phone":"+1 812 678 4991",
    "sg:postcode":"47521",
    "sg:province":"IN",
    "wof:name":"Lick Fork Marina Inc",
    "wof:placetype":"venue"
},
  "geometry": {"coordinates":[-86.728844,38.407408],"type":"Point"}
}