{
  "type": "Feature",
  "properties": {
    "iso:country":"US",
    "sg:address":"901 Sycamore St",
    "sg:city":"Evansville",
    "sg:classifiers":[
        {
            "category":"Personal",
            "subcategory":"Beauty Salon",
            "type":"Services"
        }
    ],
    "sg:phone":"+1 812 422 1100",
    "sg:postcode":"47708",
    "sg:province":"IN",
    "wof:name":"Splash Studio",
    "wof:placetype":"venue"
},
  "geometry": {"coordinates":[-87.565725,37.975498],"type":"Point"}
}