{
  "type": "Feature",
  "properties": {
    "addr:full":"225 W 30th St Connersville IN 47331",
    "addr:housenumber":"225",
    "addr:postcode":"47331",
    "addr:street":"W 30Th St",
    "iso:country":"US",
    "sg:address":"225 W 30th St",
    "sg:city":"Connersville",
    "sg:classifiers":[
        {
            "category":"Restaurant",
            "type":"Food & Drink"
        }
    ],
    "sg:phone":"+1 765 825 9222",
    "sg:postcode":"47331",
    "sg:province":"IN",
    "wof:name":"Long John Silver's",
    "wof:placetype":"venue"
},
  "geometry": {"coordinates":[-85.130984,39.671542],"type":"Point"}
}