{
  "type": "Feature",
  "properties": {
    "iso:country":"US",
    "sg:address":"1080 E Hanna Ave",
    "sg:city":"Indianapolis",
    "sg:classifiers":[
        {
            "category":"Government",
            "subcategory":"Fire Station",
            "type":"Public Place"
        }
    ],
    "sg:phone":"+1 317 327 6095",
    "sg:postcode":"46227",
    "sg:province":"IN",
    "sg:tags":[
        "protection"
    ],
    "wof:name":"Fire Dept-Station 26",
    "wof:placetype":"venue"
},
  "geometry": {"coordinates":[-86.141574,39.708363],"type":"Point"}
}