{
  "type": "Feature",
  "properties": {
    "iso:country":"US",
    "sg:address":"240 California St",
    "sg:city":"Columbus",
    "sg:classifiers":[
        {
            "category":"Professional",
            "subcategory":"Accounting & Tax Preparation",
            "type":"Services"
        }
    ],
    "sg:phone":"+1 812 372 9888",
    "sg:postcode":"47201",
    "sg:province":"IN",
    "sg:tags":[
        "bookkeeping",
        "general"
    ],
    "wof:name":"ETC Svc Inc",
    "wof:placetype":"venue"
},
  "geometry": {"coordinates":[-85.9133,39.201227],"type":"Point"}
}