{
  "type": "Feature",
  "properties": {
    "iso:country":"US",
    "sg:address":"4806 S Co Rd 950 E",
    "sg:city":"Walton",
    "sg:classifiers":[
        {
            "category":"Building & Trades",
            "subcategory":"Plumbing",
            "type":"Services"
        }
    ],
    "sg:phone":"+1 574 626 2100",
    "sg:postcode":"46994",
    "sg:province":"IN",
    "sg:tags":[
        "contractor"
    ],
    "wof:name":"Tri County Heating",
    "wof:placetype":"venue"
},
  "geometry": {"coordinates":[-86.194788,40.697047],"type":"Point"}
}