{
  "type": "Feature",
  "properties": {
    "addr:full":"5403 Broadway St Indianapolis IN 46220",
    "addr:housenumber":"5403",
    "addr:postcode":"46220",
    "addr:street":"Broadway St",
    "iso:country":"US",
    "sg:address":"5403 Broadway St",
    "sg:city":"Indianapolis",
    "sg:classifiers":[
        {
            "category":"Banks & Credit Unions",
            "subcategory":"Bank",
            "type":"Services"
        }
    ],
    "sg:phone":"+1 317 257 5898",
    "sg:postcode":"46220",
    "sg:province":"IN",
    "sg:tags":[
        "broker",
        "mortgage"
    ],
    "wof:name":"Lee Mortgage",
    "wof:placetype":"venue"
},
  "geometry": {"coordinates":[-86.14786700000001,39.854169],"type":"Point"}
}