{
  "type": "Feature",
  "properties": {
    "iso:country":"US",
    "sg:address":"3521 Cardinal Ln",
    "sg:city":"Fort Wayne",
    "sg:classifiers":[
        {
            "category":"Wholesale",
            "subcategory":"Machinery & Supplies",
            "type":"Manufacturing & Wholesale Goods"
        }
    ],
    "sg:phone":"+1 260 493 1711",
    "sg:postcode":"46815",
    "sg:province":"IN",
    "sg:tags":[
        "cleaning"
    ],
    "wof:name":"Superior Cleaning",
    "wof:placetype":"venue"
},
  "geometry": {"coordinates":[-85.028152,41.110814],"type":"Point"}
}