{
  "type": "Feature",
  "properties": {
    "addr:full":"112 N Detroit St Lagrange IN 46761",
    "addr:housenumber":"112",
    "addr:postcode":"46761",
    "addr:street":"N Detroit St",
    "iso:country":"US",
    "sg:address":"112 N Detroit St",
    "sg:city":"Lagrange",
    "sg:classifiers":[
        {
            "category":"Real Estate",
            "subcategory":"Real Estate Agent",
            "type":"Services"
        }
    ],
    "sg:phone":"+1 260 463 2013",
    "sg:postcode":"46761",
    "sg:province":"IN",
    "wof:name":"Lewis & Lambright Inc",
    "wof:placetype":"venue"
},
  "geometry": {"coordinates":[-85.417928,41.644308],"type":"Point"}
}