{
  "type": "Feature",
  "properties": {
    "iso:country":"US",
    "sg:address":"3125 Dandy Trl",
    "sg:city":"Indianapolis",
    "sg:classifiers":[
        {
            "category":"Banks & Credit Unions",
            "subcategory":"Investment Brokerage",
            "type":"Services"
        }
    ],
    "sg:phone":"+1 317 216 9633",
    "sg:postcode":"46214",
    "sg:province":"IN",
    "sg:tags":[
        "security"
    ],
    "sg:website":"www.edwardjones.com",
    "wof:name":"Edward Jones Co",
    "wof:placetype":"venue"
},
  "geometry": {"coordinates":[-86.306933,39.811963],"type":"Point"}
}