{
  "type": "Feature",
  "properties": {
    "addr:full":"3903 N New Jersey St Indianapolis IN 46205",
    "addr:housenumber":"3903",
    "addr:postcode":"46205",
    "addr:street":"N New Jersey St",
    "iso:country":"US",
    "sg:address":"3903 N New Jersey St",
    "sg:city":"Indianapolis",
    "sg:classifiers":[
        {
            "category":"Professional",
            "subcategory":"Engineering",
            "type":"Services"
        }
    ],
    "sg:phone":"+1 317 283 3879",
    "sg:postcode":"46205",
    "sg:province":"IN",
    "sg:tags":[
        "consulting",
        "electronic",
        "system",
        "for",
        "engineer"
    ],
    "wof:name":"Norman Birnbaum",
    "wof:placetype":"venue"
},
  "geometry": {"coordinates":[-86.150891,39.826731],"type":"Point"}
}