{
  "type": "Feature",
  "properties": {
    "iso:country":"US",
    "sg:address":"117 E Church St",
    "sg:city":"Alexandria",
    "sg:classifiers":[
        {
            "category":"Education",
            "subcategory":"Library",
            "type":"Public Place"
        }
    ],
    "sg:phone":"+1 765 724 2196",
    "sg:postcode":"46001",
    "sg:province":"IN",
    "sg:website":"www.alex.lib.in.us",
    "wof:name":"Alexandria-Monroe Public Lbrry",
    "wof:placetype":"venue"
},
  "geometry": {"coordinates":[-85.674142,40.263503],"type":"Point"}
}