{
  "type": "Feature",
  "properties": {
    "iso:country":"US",
    "sg:address":"1830 Lexington Ave",
    "sg:city":"Indianapolis",
    "sg:classifiers":[
        {
            "category":"Education",
            "subcategory":"Dance Studio",
            "type":"Public Place"
        }
    ],
    "sg:phone":"+1 317 685 8675",
    "sg:postcode":"46203",
    "sg:province":"IN",
    "wof:name":"Motus Dance Theatre",
    "wof:placetype":"venue"
},
  "geometry": {"coordinates":[-86.128599,39.756181],"type":"Point"}
}