{
  "type": "Feature",
  "properties": {
    "iso:country":"US",
    "sg:address":"725 N Capitol Ave",
    "sg:city":"Indianapolis",
    "sg:classifiers":[
        {
            "category":"Retail",
            "subcategory":"Auto Repair",
            "type":"Services"
        }
    ],
    "sg:phone":"+1 317 634 3379",
    "sg:postcode":"46204",
    "sg:province":"IN",
    "sg:tags":[
        "repairing",
        "automobile"
    ],
    "wof:name":"Matt's Alignment Svc Inc",
    "wof:placetype":"venue"
},
  "geometry": {"coordinates":[-86.161259,39.776992],"type":"Point"}
}