{
  "type": "Feature",
  "properties": {
    "iso:country":"US",
    "sg:address":"1129 Dennison Ave",
    "sg:city":"New Albany",
    "sg:classifiers":[
        {
            "category":"Recreation",
            "type":"Entertainment"
        }
    ],
    "sg:phone":"+1 812 945 2828",
    "sg:postcode":"47150",
    "sg:province":"IN",
    "sg:tags":[
        "parks"
    ],
    "wof:name":"Vance Recreation Ctr Housing",
    "wof:placetype":"venue"
},
  "geometry": {"coordinates":[-85.834171,38.294919],"type":"Point"}
}