{
  "type": "Feature",
  "properties": {
    "iso:country":"US",
    "sg:address":"22 Artist Dr",
    "sg:city":"Nashville",
    "sg:classifiers":[
        {
            "category":"Professional",
            "subcategory":"Accounting & Tax Preparation",
            "type":"Services"
        }
    ],
    "sg:phone":"+1 812 988 9060",
    "sg:postcode":"47448",
    "sg:province":"IN",
    "sg:tags":[
        "accountant"
    ],
    "wof:name":"Sandra Sage",
    "wof:placetype":"venue"
},
  "geometry": {"coordinates":[-86.243173,39.206789],"type":"Point"}
}