{
  "type": "Feature",
  "properties": {
    "iso:country":"US",
    "sg:address":"312 W Main St",
    "sg:city":"Richmond",
    "sg:classifiers":[
        {
            "category":"Banks & Credit Unions",
            "subcategory":"Bank",
            "type":"Services"
        }
    ],
    "sg:phone":"+1 765 966 2228",
    "sg:postcode":"47374",
    "sg:province":"IN",
    "sg:tags":[
        "state"
    ],
    "wof:name":"Southeast Telco Federal Cr Un",
    "wof:placetype":"venue"
},
  "geometry": {"coordinates":[-84.90551499999999,39.829211],"type":"Point"}
}