{
  "type": "Feature",
  "properties": {
    "iso:country":"US",
    "sg:address":"16987 Stonegate Ct",
    "sg:city":"Granger",
    "sg:classifiers":[
        {
            "category":"Building & Trades",
            "subcategory":"Construction",
            "type":"Services"
        }
    ],
    "sg:phone":"+1 574 277 5063",
    "sg:postcode":"46530",
    "sg:province":"IN",
    "sg:tags":[
        "carpentry",
        "contractor"
    ],
    "wof:name":"Jt Customs",
    "wof:placetype":"venue"
},
  "geometry": {"coordinates":[-86.199145,41.758904],"type":"Point"}
}