{
  "type": "Feature",
  "properties": {
    "iso:country":"US",
    "sg:address":"7091 N US Hwy 231",
    "sg:city":"Jasper",
    "sg:classifiers":[
        {
            "category":"Autos & Motor Vehicles",
            "subcategory":"Recreational Vehicle Sales",
            "type":"Retail Goods"
        }
    ],
    "sg:phone":"+1 812 695 2044",
    "sg:postcode":"47546",
    "sg:province":"IN",
    "sg:tags":[
        "canopy",
        "shell",
        "truck",
        "cap"
    ],
    "wof:name":"Meyer Truck Equipment Sales",
    "wof:placetype":"venue"
},
  "geometry": {"coordinates":[-86.91466200000001,38.484634],"type":"Point"}
}