{
  "type": "Feature",
  "properties": {
    "iso:country":"US",
    "sg:address":"101 E Harris St",
    "sg:city":"Eaton",
    "sg:classifiers":[
        {
            "category":"Wholesale",
            "subcategory":"Hardware",
            "type":"Manufacturing & Wholesale Goods"
        }
    ],
    "sg:phone":"+1 765 396 9212",
    "sg:postcode":"47338",
    "sg:province":"IN",
    "sg:tags":[
        "heating"
    ],
    "wof:name":"C & C Distributors",
    "wof:placetype":"venue"
},
  "geometry": {"coordinates":[-85.354334,40.341892],"type":"Point"}
}