{
  "type": "Feature",
  "properties": {
    "iso:country":"US",
    "sg:address":"630 E Lake Shore Dr",
    "sg:city":"Culver",
    "sg:classifiers":[
        {
            "category":"Restaurant",
            "type":"Food & Drink"
        }
    ],
    "sg:phone":"+1 574 842 2526",
    "sg:postcode":"46511",
    "sg:province":"IN",
    "sg:tags":[
        "eating"
    ],
    "wof:name":"Renfrow S Rock Roll Cafe",
    "wof:placetype":"venue"
},
  "geometry": {"coordinates":[-86.418739,41.218874],"type":"Point"}
}