{
  "type": "Feature",
  "properties": {
    "iso:country":"US",
    "sg:address":"1981 E Co Rd 550 S",
    "sg:city":"Carlisle",
    "sg:phone":"+1 812 268 5366",
    "sg:postcode":"47838",
    "sg:province":"IN",
    "sg:tags":[
        "farm",
        "corn",
        "soybean"
    ],
    "wof:name":"Dale Haberle",
    "wof:placetype":"venue"
},
  "geometry": {"coordinates":[-87.37445,39.003146],"type":"Point"}
}