{
  "type": "Feature",
  "properties": {
    "iso:country":"US",
    "sg:address":"800 E 96th St",
    "sg:city":"Indianapolis",
    "sg:classifiers":[
        {
            "category":"Professional",
            "subcategory":"Accounting & Tax Preparation",
            "type":"Services"
        }
    ],
    "sg:phone":"+1 317 580 2083",
    "sg:postcode":"46240",
    "sg:province":"IN",
    "sg:tags":[
        "accountant"
    ],
    "wof:name":"Vidya Harish",
    "wof:placetype":"venue"
},
  "geometry": {"coordinates":[-86.142386,39.92713],"type":"Point"}
}