{
  "type": "Feature",
  "properties": {
    "iso:country":"US",
    "sg:address":"935 N Detroit St",
    "sg:city":"Warsaw",
    "sg:classifiers":[
        {
            "category":"Health Services",
            "subcategory":"Doctor",
            "type":"Services"
        }
    ],
    "sg:phone":"+1 574 267 3359",
    "sg:postcode":"46580",
    "sg:province":"IN",
    "sg:tags":[
        "dentist"
    ],
    "wof:name":"Michael J Conley DDS",
    "wof:placetype":"venue"
},
  "geometry": {"coordinates":[-85.852513,41.251737],"type":"Point"}
}