{
  "type": "Feature",
  "properties": {
    "iso:country":"US",
    "sg:address":"774 State Rd 38",
    "sg:city":"New Castle",
    "sg:classifiers":[
        {
            "category":"Home & Garden",
            "subcategory":"Garden Supply",
            "type":"Retail Goods"
        }
    ],
    "sg:phone":"+1 765 529 6807",
    "sg:postcode":"47362",
    "sg:province":"IN",
    "sg:tags":[
        "lawn",
        "mower"
    ],
    "wof:name":"Dennis Farm & Lawn Equipment",
    "wof:placetype":"venue"
},
  "geometry": {"coordinates":[-85.376464,39.931501],"type":"Point"}
}