{
  "type": "Feature",
  "properties": {
    "iso:country":"US",
    "sg:address":"4145 W Co Rd 400 S",
    "sg:city":"Logansport",
    "sg:classifiers":[
        {
            "category":"Home & Garden",
            "subcategory":"Garden Supply",
            "type":"Retail Goods"
        }
    ],
    "sg:phone":"+1 574 753 2929",
    "sg:postcode":"46947",
    "sg:province":"IN",
    "sg:tags":[
        "fertilizer"
    ],
    "wof:name":"North Central Co-Op",
    "wof:placetype":"venue"
},
  "geometry": {"coordinates":[-86.451931,40.706528],"type":"Point"}
}