{
  "type": "Feature",
  "properties": {
    "addr:full":"600 Leiter Dr Warsaw IN 46580",
    "addr:housenumber":"600",
    "addr:postcode":"46580",
    "addr:street":"Leiter Dr",
    "iso:country":"US",
    "sg:address":"600 Leiter Dr",
    "sg:city":"Warsaw",
    "sg:classifiers":[
        {
            "category":"Retail",
            "subcategory":"Auto Repair",
            "type":"Services"
        }
    ],
    "sg:phone":"+1 574 268 6360",
    "sg:postcode":"46580",
    "sg:province":"IN",
    "sg:tags":[
        "repairing",
        "automobile"
    ],
    "wof:name":"Boggs Automotive",
    "wof:placetype":"venue"
},
  "geometry": {"coordinates":[-85.87616800000001,41.242958],"type":"Point"}
}