{
  "type": "Feature",
  "properties": {
    "iso:country":"US",
    "sg:address":"1 Technology Way",
    "sg:city":"Indianapolis",
    "sg:classifiers":[
        {
            "category":"Wholesale",
            "subcategory":"Non-durable Goods",
            "type":"Manufacturing & Wholesale Goods"
        }
    ],
    "sg:phone":"+1 317 614 1515",
    "sg:postcode":"46268",
    "sg:province":"IN",
    "sg:tags":[
        "rubber",
        "sponge"
    ],
    "sg:website":"www.hitechfoam.com",
    "wof:name":"Hi Tech Foam Products Inc",
    "wof:placetype":"venue"
},
  "geometry": {"coordinates":[-86.250468,39.884177],"type":"Point"}
}