{
  "type": "Feature",
  "properties": {
    "addr:full":"806 Martinsburg Rd Salem IN 47167",
    "addr:housenumber":"806",
    "addr:postcode":"47167",
    "addr:street":"Martinsburg Rd",
    "iso:country":"US",
    "sg:address":"806 Martinsburg Rd",
    "sg:city":"Salem",
    "sg:classifiers":[
        {
            "category":"Health Services",
            "subcategory":"Clinic",
            "type":"Services"
        }
    ],
    "sg:phone":"+1 812 883 5368",
    "sg:postcode":"47167",
    "sg:province":"IN",
    "sg:website":"www.hoosieruplands.org",
    "wof:name":"Hoosier Uplands",
    "wof:placetype":"venue"
},
  "geometry": {"coordinates":[-86.09378100000001,38.597472],"type":"Point"}
}