{
  "type": "Feature",
  "properties": {
    "iso:country":"US",
    "sg:address":"9615 E Jackson St",
    "sg:city":"Selma",
    "sg:classifiers":[
        {
            "category":"Building & Trades",
            "subcategory":"Construction",
            "type":"Services"
        }
    ],
    "sg:phone":"+1 765 747 6900",
    "sg:postcode":"47383",
    "sg:province":"IN",
    "sg:tags":[
        "concrete",
        "contractor"
    ],
    "wof:name":"Morrow's Pools & Spas",
    "wof:placetype":"venue"
},
  "geometry": {"coordinates":[-85.27352500000001,40.193022],"type":"Point"}
}