{
  "type": "Feature",
  "properties": {
    "addr:full":"2220 Main St Lafayette IN 47904",
    "addr:housenumber":"2220",
    "addr:postcode":"47904",
    "addr:street":"Main St",
    "iso:country":"US",
    "sg:address":"2220 Main St",
    "sg:city":"Lafayette",
    "sg:classifiers":[
        {
            "category":"Health Services",
            "subcategory":"Chiropractor",
            "type":"Services"
        }
    ],
    "sg:phone":"+1 765 447 2220",
    "sg:postcode":"47904",
    "sg:province":"IN",
    "wof:name":"R J Rodibaugh DC",
    "wof:placetype":"venue"
},
  "geometry": {"coordinates":[-86.870726,40.410376],"type":"Point"}
}