{
  "type": "Feature",
  "properties": {
    "iso:country":"US",
    "sg:address":"9517 State Rd 250",
    "sg:city":"Canaan",
    "sg:classifiers":[
        {
            "category":"Education",
            "subcategory":"Special Training",
            "type":"Public Place"
        }
    ],
    "sg:phone":"+1 812 839 3429",
    "sg:postcode":"47224",
    "sg:province":"IN",
    "sg:tags":[
        "instruction",
        "music"
    ],
    "wof:name":"MUSICAL Resource",
    "wof:placetype":"venue"
},
  "geometry": {"coordinates":[-85.21072,38.871019],"type":"Point"}
}