{
  "type": "Feature",
  "properties": {
    "iso:country":"US",
    "sg:address":"3832 N Illinois St",
    "sg:city":"Indianapolis",
    "sg:classifiers":[
        {
            "category":"Shopping",
            "type":"Retail Goods"
        }
    ],
    "sg:phone":"+1 317 926 2525",
    "sg:postcode":"46208",
    "sg:province":"IN",
    "sg:tags":[
        "cosmetic",
        "perfume"
    ],
    "wof:name":"Sun Beauty Supply",
    "wof:placetype":"venue"
},
  "geometry": {"coordinates":[-86.159283,39.825401],"type":"Point"}
}