{
  "type": "Feature",
  "properties": {
    "iso:country":"US",
    "sg:address":"3720 Broadway",
    "sg:city":"Gary",
    "sg:classifiers":[
        {
            "category":"Shopping",
            "subcategory":"Clothing, Apparel, & Fashions",
            "type":"Retail Goods"
        }
    ],
    "sg:phone":"+1 219 884 2196",
    "sg:postcode":"46408",
    "sg:province":"IN",
    "wof:name":"Goldstar Fashion Inc",
    "wof:placetype":"venue"
},
  "geometry": {"coordinates":[-87.336591,41.550076],"type":"Point"}
}