{
  "type": "Feature",
  "properties": {
    "addr:full":"1090 Yandes St Franklin IN 46131",
    "addr:housenumber":"1090",
    "addr:postcode":"46131",
    "addr:street":"Yandes St",
    "iso:country":"US",
    "sg:address":"1090 Yandes St",
    "sg:city":"Franklin",
    "sg:classifiers":[
        {
            "category":"Building & Trades",
            "subcategory":"Landscaping Services",
            "type":"Services"
        }
    ],
    "sg:phone":"+1 317 738 0618",
    "sg:postcode":"46131",
    "sg:province":"IN",
    "wof:name":"Prices Custom Lawn",
    "wof:placetype":"venue"
},
  "geometry": {"coordinates":[-86.049877,39.491707],"type":"Point"}
}