{
  "type": "Feature",
  "properties": {
    "iso:country":"US",
    "sg:address":"7040 Guion Rd",
    "sg:city":"Indianapolis",
    "sg:classifiers":[
        {
            "category":"Wholesale",
            "subcategory":"Medical Equipment & Supplies",
            "type":"Manufacturing & Wholesale Goods"
        },
        {
            "category":"Health Services",
            "subcategory":"Hospital",
            "type":"Services"
        },
        {
            "category":"Professional",
            "subcategory":"Detective & Security Services",
            "type":"Services"
        },
        {
            "category":"Building & Trades",
            "subcategory":"Construction",
            "type":"Services"
        },
        {
            "category":"Retail",
            "subcategory":"Auto Repair",
            "type":"Services"
        }
    ],
    "sg:phone":"+1 317 347 6400",
    "sg:postcode":"46268",
    "sg:province":"IN",
    "sg:tags":[
        "wheelchairs-repair",
        "mobility",
        "consultant",
        "wheelchair",
        "ramp",
        "system",
        "scooter",
        "lift",
        "aid",
        "equipment-repairing"
    ],
    "sg:website":"http://www.adaptngo.com",
    "wof:name":"Home Health Depot",
    "wof:placetype":"venue"
},
  "geometry": {"coordinates":[-86.23156299999999,39.87292],"type":"Point"}
}