{
  "type": "Feature",
  "properties": {
    "addr:full":"5950 N Keystone Ave Indianapolis IN 46220",
    "addr:housenumber":"5950",
    "addr:postcode":"46220",
    "addr:street":"N Keystone Ave",
    "iso:country":"US",
    "sg:address":"5950 N Keystone Ave",
    "sg:city":"Indianapolis",
    "sg:classifiers":[
        {
            "category":"Professional",
            "type":"Services"
        }
    ],
    "sg:phone":"+1 317 257 5833",
    "sg:postcode":"46220",
    "sg:province":"IN",
    "wof:name":"Jmu Inc",
    "wof:placetype":"venue"
},
  "geometry": {"coordinates":[-86.122294,39.864458],"type":"Point"}
}