{
  "type": "Feature",
  "properties": {
    "iso:country":"US",
    "sg:address":"810 Indiana Ave",
    "sg:city":"Richmond",
    "sg:classifiers":[
        {
            "category":"Real Estate",
            "subcategory":"Real Estate Operator",
            "type":"Services"
        }
    ],
    "sg:phone":"+1 765 965 0533",
    "sg:postcode":"47374",
    "sg:province":"IN",
    "sg:tags":[
        "mobile",
        "home",
        "community"
    ],
    "wof:name":"Westridge Estates",
    "wof:placetype":"venue"
},
  "geometry": {"coordinates":[-84.915955,39.838336],"type":"Point"}
}