{
  "type": "Feature",
  "properties": {
    "iso:country":"US",
    "sg:address":"2410 Lake Ave",
    "sg:city":"Fort Wayne",
    "sg:classifiers":[
        {
            "category":"Professional",
            "subcategory":"Accounting & Tax Preparation",
            "type":"Services"
        }
    ],
    "sg:phone":"+1 260 423 9405",
    "sg:postcode":"46805",
    "sg:province":"IN",
    "sg:tags":[
        "accountant"
    ],
    "wof:name":"Leonard J Andorfer & Co",
    "wof:placetype":"venue"
},
  "geometry": {"coordinates":[-85.10596700000001,41.089767],"type":"Point"}
}