{
  "type": "Feature",
  "properties": {
    "addr:full":"2074 N 50 W Laporte IN 46350",
    "addr:housenumber":"2074",
    "addr:postcode":"46350",
    "addr:street":"N 50 W Laporte",
    "iso:country":"US",
    "sg:address":"2074 N 50 W",
    "sg:city":"Laporte",
    "sg:classifiers":[
        {
            "category":"Building & Trades",
            "subcategory":"Construction",
            "type":"Services"
        }
    ],
    "sg:phone":"+1 219 326 1688",
    "sg:postcode":"46350",
    "sg:province":"IN",
    "sg:tags":[
        "excavating",
        "contractor"
    ],
    "wof:name":"Keller's Limestone Svc Inc",
    "wof:placetype":"venue"
},
  "geometry": {"coordinates":[-86.709276,41.641689],"type":"Point"}
}