{
  "type": "Feature",
  "properties": {
    "iso:country":"US",
    "sg:address":"4429 S US Hwy 41",
    "sg:city":"Terre Haute",
    "sg:classifiers":[
        {
            "category":"Food & Beverages",
            "subcategory":"Bakery",
            "type":"Retail Goods"
        }
    ],
    "sg:phone":"+1 812 235 8354",
    "sg:postcode":"47802",
    "sg:province":"IN",
    "sg:tags":[
        "baker"
    ],
    "wof:name":"Wonder Bread",
    "wof:placetype":"venue"
},
  "geometry": {"coordinates":[-87.414416,39.412607],"type":"Point"}
}