{
  "type": "Feature",
  "properties": {
    "addr:full":"12741 State Rd 62 St Meinrad IN 47577",
    "addr:housenumber":"12741;62",
    "addr:postcode":"meinrad in 47577",
    "addr:street":"State Rd",
    "iso:country":"US",
    "sg:address":"12741 State Rd 62",
    "sg:city":"St Meinrad",
    "sg:classifiers":[
        {
            "category":"Food & Beverages",
            "subcategory":"Groceries & Convenience Stores",
            "type":"Retail Goods"
        }
    ],
    "sg:phone":"+1 812 357 5711",
    "sg:postcode":"47577",
    "sg:province":"IN",
    "sg:tags":[
        "grocer"
    ],
    "wof:name":"Country Side Foods Inc",
    "wof:placetype":"venue"
},
  "geometry": {"coordinates":[-86.814808,38.169463],"type":"Point"}
}