{
  "type": "Feature",
  "properties": {
    "iso:country":"US",
    "sg:address":"627 S Walnut St",
    "sg:city":"Muncie",
    "sg:classifiers":[
        {
            "category":"Manufacturing",
            "subcategory":"Printing",
            "type":"Manufacturing & Wholesale Goods"
        }
    ],
    "sg:phone":"+1 765 286 3984",
    "sg:postcode":"47305",
    "sg:province":"IN",
    "sg:tags":[
        "periodical"
    ],
    "wof:name":"Muncie Star Press",
    "wof:placetype":"venue"
},
  "geometry": {"coordinates":[-85.386515,40.188545],"type":"Point"}
}