{
  "type": "Feature",
  "properties": {
    "addr:full":"8841 Morse St Crown Point IN 46307",
    "addr:housenumber":"8841",
    "addr:postcode":"46307",
    "addr:street":"Morse St",
    "iso:country":"US",
    "sg:address":"8841 Morse St",
    "sg:city":"Crown Point",
    "sg:classifiers":[
        {
            "category":"Real Estate",
            "subcategory":"Real Estate Agent",
            "type":"Services"
        }
    ],
    "sg:phone":"+1 219 365 3276",
    "sg:postcode":"46307",
    "sg:province":"IN",
    "wof:name":"Ursula Buchnat Realtor",
    "wof:placetype":"venue"
},
  "geometry": {"coordinates":[-87.42107300000001,41.456257],"type":"Point"}
}