{
  "type": "Feature",
  "properties": {
    "iso:country":"US",
    "sg:address":"8752 E 116th St",
    "sg:city":"Fishers",
    "sg:classifiers":[
        {
            "category":"Restaurant",
            "type":"Food & Drink"
        }
    ],
    "sg:phone":"+1 317 576 1123",
    "sg:postcode":"46038",
    "sg:province":"IN",
    "wof:name":"Roly Poly Fishers Llc",
    "wof:placetype":"venue"
},
  "geometry": {"coordinates":[-86.0149,39.956699],"type":"Point"}
}