{
  "type": "Feature",
  "properties": {
    "addr:full":"21 N Range Line Rd Carmel IN 46032",
    "addr:housenumber":"21",
    "addr:postcode":"46032",
    "addr:street":"N Range Line Rd",
    "iso:country":"US",
    "sg:address":"21 N Range Line Rd",
    "sg:city":"Carmel",
    "sg:classifiers":[
        {
            "category":"Banks & Credit Unions",
            "subcategory":"Bank",
            "type":"Services"
        }
    ],
    "sg:phone":"+1 317 580 4110",
    "sg:postcode":"46032",
    "sg:province":"IN",
    "wof:name":"Natcity Investments",
    "wof:placetype":"venue"
},
  "geometry": {"coordinates":[-86.126881,39.97881],"type":"Point"}
}