{
  "type": "Feature",
  "properties": {
    "iso:country":"US",
    "sg:address":"120 N 36th St",
    "sg:city":"Lafayette",
    "sg:classifiers":[
        {
            "category":"Manufacturing",
            "subcategory":"Metals",
            "type":"Manufacturing & Wholesale Goods"
        }
    ],
    "sg:phone":"+1 765 447 5036",
    "sg:postcode":"47905",
    "sg:province":"IN",
    "sg:tags":[
        "plating"
    ],
    "wof:name":"Industrial Plating Inc",
    "wof:placetype":"venue"
},
  "geometry": {"coordinates":[-86.850034,40.418753],"type":"Point"}
}