{
  "type": "Feature",
  "properties": {
    "addr:full":"620 Verdant St Elkhart IN 46516",
    "addr:housenumber":"620",
    "addr:postcode":"46516",
    "addr:street":"Verdant St",
    "iso:country":"US",
    "sg:address":"620 Verdant St",
    "sg:city":"Elkhart",
    "sg:classifiers":[
        {
            "category":"Professional",
            "subcategory":"Advertising",
            "type":"Services"
        }
    ],
    "sg:phone":"+1 574 522 7604",
    "sg:postcode":"46516",
    "sg:province":"IN",
    "sg:tags":[
        "designer",
        "display",
        "producer"
    ],
    "wof:name":"Presentation Products",
    "wof:placetype":"venue"
},
  "geometry": {"coordinates":[-85.89446,41.684611],"type":"Point"}
}