{
  "type": "Feature",
  "properties": {
    "iso:country":"US",
    "sg:address":"705 S Earl Ave",
    "sg:city":"Lafayette",
    "sg:classifiers":[
        {
            "category":"Manufacturing",
            "subcategory":"Signs",
            "type":"Manufacturing & Wholesale Goods"
        }
    ],
    "sg:phone":"+1 765 447 5978",
    "sg:postcode":"47904",
    "sg:province":"IN",
    "wof:name":"Signs Of Success",
    "wof:placetype":"venue"
},
  "geometry": {"coordinates":[-86.860622,40.408767],"type":"Point"}
}