{
  "type": "Feature",
  "properties": {
    "iso:country":"US",
    "sg:address":"1890 S Meridian Rd",
    "sg:city":"Jasper",
    "sg:classifiers":[
        {
            "category":"Wholesale",
            "subcategory":"Meat",
            "type":"Manufacturing & Wholesale Goods"
        }
    ],
    "sg:phone":"+1 812 482 5501",
    "sg:postcode":"47546",
    "sg:province":"IN",
    "sg:tags":[
        "poultry",
        "plant",
        "processing"
    ],
    "wof:name":"Tyson Foods Inc",
    "wof:placetype":"venue"
},
  "geometry": {"coordinates":[-86.910661,38.364757],"type":"Point"}
}