{
  "type": "Feature",
  "properties": {
    "iso:country":"US",
    "sg:address":"531 5th St",
    "sg:city":"Columbus",
    "sg:classifiers":[
        {
            "category":"Organizations",
            "subcategory":"Religious Organization",
            "type":"Services"
        }
    ],
    "sg:phone":"+1 812 379 4491",
    "sg:postcode":"47201",
    "sg:province":"IN",
    "sg:tags":[
        "church"
    ],
    "sg:website":"www.fccoc.org",
    "wof:name":"First Christian Church",
    "wof:placetype":"venue"
},
  "geometry": {"coordinates":[-85.918848,39.203481],"type":"Point"}
}