{
  "type": "Feature",
  "properties": {
    "iso:country":"US",
    "sg:address":"17840 N 450 E",
    "sg:city":"Summitville",
    "sg:classifiers":[
        {
            "category":"Freight",
            "type":"Transportation"
        }
    ],
    "sg:phone":"+1 765 536 2914",
    "sg:postcode":"46070",
    "sg:province":"IN",
    "sg:tags":[
        "farm",
        "product",
        "warehousing"
    ],
    "wof:name":"Ellis Guy",
    "wof:placetype":"venue"
},
  "geometry": {"coordinates":[-85.588009,40.358861],"type":"Point"}
}