{
  "type": "Feature",
  "properties": {
    "iso:country":"US",
    "sg:address":"3047 Grandma Barnes Rd",
    "sg:city":"Nashville",
    "sg:classifiers":[
        {
            "category":"Manufacturing",
            "subcategory":"Tools & Machinery",
            "type":"Manufacturing & Wholesale Goods"
        },
        {
            "category":"Retail",
            "subcategory":"Repair Shop",
            "type":"Services"
        }
    ],
    "sg:phone":"+1 812 988 7649",
    "sg:postcode":"47448",
    "sg:province":"IN",
    "sg:tags":[
        "machine",
        "machinery-rebuild"
    ],
    "wof:name":"Orbit Machine & Tool",
    "wof:placetype":"venue"
},
  "geometry": {"coordinates":[-86.26982099999999,39.230028],"type":"Point"}
}