{
  "type": "Feature",
  "properties": {
    "iso:country":"US",
    "sg:address":"402 Washington St",
    "sg:city":"Columbus",
    "sg:classifiers":[
        {
            "category":"Professional",
            "subcategory":"Employment Agencies",
            "type":"Services"
        }
    ],
    "sg:phone":"+1 812 375 9391",
    "sg:postcode":"47201",
    "sg:province":"IN",
    "sg:tags":[
        "employ",
        "datum",
        "help",
        "supply"
    ],
    "wof:name":"S&R Resources",
    "wof:placetype":"venue"
},
  "geometry": {"coordinates":[-85.92119599999999,39.203461],"type":"Point"}
}