{
  "type": "Feature",
  "properties": {
    "addr:full":"2324 Edison Rd South Bend IN 46615",
    "addr:housenumber":"2324",
    "addr:postcode":"46615",
    "addr:street":"Edison Rd",
    "iso:country":"US",
    "sg:address":"2324 Edison Rd",
    "sg:city":"South Bend",
    "sg:classifiers":[
        {
            "category":"Retail",
            "subcategory":"Car Wash",
            "type":"Services"
        }
    ],
    "sg:phone":"+1 574 233 4006",
    "sg:postcode":"46615",
    "sg:province":"IN",
    "sg:tags":[
        "polishing",
        "washing"
    ],
    "wof:name":"Hi Speed Auto Wash-Edison",
    "wof:placetype":"venue"
},
  "geometry": {"coordinates":[-86.213742,41.694452],"type":"Point"}
}