{
  "type": "Feature",
  "properties": {
    "iso:country":"US",
    "sg:address":"8733 Founders Rd",
    "sg:city":"Indianapolis",
    "sg:classifiers":[
        {
            "category":"Organizations",
            "subcategory":"Membership Organization",
            "type":"Services"
        }
    ],
    "sg:phone":"+1 317 872 3275",
    "sg:postcode":"46268",
    "sg:province":"IN",
    "sg:tags":[
        "sorority",
        "fraternity"
    ],
    "wof:name":"Beta Tau Of Sigma",
    "wof:placetype":"venue"
},
  "geometry": {"coordinates":[-86.216454,39.91386],"type":"Point"}
}