{
  "type": "Feature",
  "properties": {
    "iso:country":"US",
    "sg:address":"11134 W Sycamore Hills Dr",
    "sg:city":"Fort Wayne",
    "sg:classifiers":[
        {
            "category":"Professional",
            "subcategory":"Business Services",
            "type":"Services"
        }
    ],
    "sg:phone":"+1 260 625 6221",
    "sg:postcode":"46814",
    "sg:province":"IN",
    "wof:name":"C & M Business Services Inc",
    "wof:placetype":"venue"
},
  "geometry": {"coordinates":[-85.28274500000001,41.071968],"type":"Point"}
}