{
  "type": "Feature",
  "properties": {
    "iso:country":"US",
    "sg:address":"1832 E State Rd 44",
    "sg:city":"Shelbyville",
    "sg:classifiers":[
        {
            "category":"Banks & Credit Unions",
            "subcategory":"Bank",
            "type":"Services"
        }
    ],
    "sg:phone":"+1 317 398 4121",
    "sg:postcode":"46176",
    "sg:province":"IN",
    "wof:name":"National City Bank",
    "wof:placetype":"venue"
},
  "geometry": {"coordinates":[-85.745389,39.522496],"type":"Point"}
}