{
  "type": "Feature",
  "properties": {
    "iso:country":"US",
    "sg:address":"7844 Marshall St",
    "sg:city":"Merrillville",
    "sg:classifiers":[
        {
            "category":"Restaurant",
            "type":"Food & Drink"
        }
    ],
    "sg:phone":"+1 219 769 6114",
    "sg:postcode":"46410",
    "sg:province":"IN",
    "wof:name":"Roma Pizza",
    "wof:placetype":"venue"
},
  "geometry": {"coordinates":[-87.369864,41.474043],"type":"Point"}
}