{
  "type": "Feature",
  "properties": {
    "iso:country":"US",
    "sg:address":"5518 Calumet Ave",
    "sg:city":"Hammond",
    "sg:classifiers":[
        {
            "category":"Organizations",
            "subcategory":"Non-profit Organization",
            "type":"Services"
        }
    ],
    "sg:phone":"+1 219 882 6159",
    "sg:postcode":"46320",
    "sg:province":"IN",
    "wof:name":"LCEOC Inc",
    "wof:placetype":"venue"
},
  "geometry": {"coordinates":[-87.508982,41.612484],"type":"Point"}
}