{
  "type": "Feature",
  "properties": {
    "iso:country":"US",
    "sg:address":"10333 Aurora Ct",
    "sg:city":"Noblesville",
    "sg:classifiers":[
        {
            "category":"Professional",
            "subcategory":"Management & Consulting",
            "type":"Services"
        }
    ],
    "sg:phone":"+1 317 776 0655",
    "sg:postcode":"46038",
    "sg:province":"IN",
    "sg:tags":[
        "business"
    ],
    "wof:name":"Ea Educational Consultants",
    "wof:placetype":"venue"
},
  "geometry": {"coordinates":[-85.984031,39.987788],"type":"Point"}
}