{
  "type": "Feature",
  "properties": {
    "iso:country":"US",
    "sg:address":"5252 E Main St",
    "sg:city":"Avon",
    "sg:classifiers":[
        {
            "category":"Manufacturing",
            "subcategory":"Printing",
            "type":"Manufacturing & Wholesale Goods"
        }
    ],
    "sg:phone":"+1 317 745 4083",
    "sg:postcode":"46123",
    "sg:province":"IN",
    "sg:tags":[
        "printer"
    ],
    "wof:name":"Printer",
    "wof:placetype":"venue"
},
  "geometry": {"coordinates":[-86.430886,39.762301],"type":"Point"}
}