{
  "type": "Feature",
  "properties": {
    "addr:full":"35 Beck Ln Lafayette IN 47909",
    "addr:housenumber":"35",
    "addr:postcode":"47909",
    "addr:street":"Beck Ln",
    "iso:country":"US",
    "sg:address":"35 Beck Ln",
    "sg:city":"Lafayette",
    "sg:classifiers":[
        {
            "category":"Restaurant",
            "type":"Food & Drink"
        }
    ],
    "sg:menulink":"http://www.allmenus.com/in/fairfield/76465-dominos-pizza/menu/",
    "sg:phone":"+1 765 474 2444",
    "sg:postcode":"47909",
    "sg:province":"IN",
    "sg:tags":[
        "american",
        "wing",
        "pizza"
    ],
    "wof:name":"Domino's Pizza",
    "wof:placetype":"venue"
},
  "geometry": {"coordinates":[-86.90413700000001,40.387909],"type":"Point"}
}