{
  "type": "Feature",
  "properties": {
    "iso:country":"US",
    "sg:address":"6405 Castleway Ct",
    "sg:city":"Indianapolis",
    "sg:classifiers":[
        {
            "category":"Insurance",
            "subcategory":"Insurance Agent",
            "type":"Services"
        }
    ],
    "sg:phone":"+1 317 243 3257",
    "sg:postcode":"46250",
    "sg:province":"IN",
    "sg:tags":[
        "consultant"
    ],
    "sg:website":"www.efiglobal.com",
    "wof:name":"Engineering & Fire Invstgtns",
    "wof:placetype":"venue"
},
  "geometry": {"coordinates":[-86.057216,39.902327],"type":"Point"}
}