{
  "type": "Feature",
  "properties": {
    "iso:country":"US",
    "sg:address":"1 N Capitol Ave",
    "sg:city":"Indianapolis",
    "sg:classifiers":[
        {
            "category":"Government",
            "subcategory":"Office",
            "type":"Public Place"
        }
    ],
    "sg:phone":"+1 317 231 7121",
    "sg:postcode":"46204",
    "sg:province":"IN",
    "sg:tags":[
        "city"
    ],
    "sg:website":"www.indygov.org",
    "wof:name":"Bart Peterson For Mayor Campgn",
    "wof:placetype":"venue"
},
  "geometry": {"coordinates":[-86.16168999999999,39.767905],"type":"Point"}
}