{
  "type": "Feature",
  "properties": {
    "iso:country":"US",
    "sg:address":"723 E 8th St",
    "sg:city":"Anderson",
    "sg:classifiers":[
        {
            "category":"Restaurant",
            "type":"Food & Drink"
        }
    ],
    "sg:phone":"+1 765 640 9028",
    "sg:postcode":"46012",
    "sg:province":"IN",
    "wof:name":"Nile Restaurant",
    "wof:placetype":"venue"
},
  "geometry": {"coordinates":[-85.669508,40.107828],"type":"Point"}
}