{
  "type": "Feature",
  "properties": {
    "iso:country":"US",
    "sg:address":"2014 W 2nd St",
    "sg:city":"Marion",
    "sg:classifiers":[
        {
            "category":"Sports & Exercise",
            "subcategory":"Bowling",
            "type":"Entertainment"
        }
    ],
    "sg:phone":"+1 765 662 7673",
    "sg:postcode":"46952",
    "sg:province":"IN",
    "sg:tags":[
        "center"
    ],
    "wof:name":"Crest Lanes Inc",
    "wof:placetype":"venue"
},
  "geometry": {"coordinates":[-85.68929,40.559864],"type":"Point"}
}