{
  "type": "Feature",
  "properties": {
    "addr:full":"11946 Fishers Crossing Dr Fishers IN 46038",
    "addr:housenumber":"11946",
    "addr:postcode":"46038",
    "addr:street":"Fishers Crossing Dr",
    "iso:country":"US",
    "sg:address":"11946 Fishers Crossing Dr",
    "sg:city":"Fishers",
    "sg:classifiers":[
        {
            "category":"Health Services",
            "subcategory":"Health Practitioner",
            "type":"Services"
        }
    ],
    "sg:phone":"+1 317 570 1268",
    "sg:postcode":"46038",
    "sg:province":"IN",
    "sg:tags":[
        "therapist",
        "physical"
    ],
    "wof:name":"Capstone Physical Therapy",
    "wof:placetype":"venue"
},
  "geometry": {"coordinates":[-86.039343,39.961953],"type":"Point"}
}