{
  "type": "Feature",
  "properties": {
    "iso:country":"US",
    "sg:address":"8234 Carloway Rd",
    "sg:city":"Indianapolis",
    "sg:classifiers":[
        {
            "category":"Professional",
            "subcategory":"Credit Reporting & Collection",
            "type":"Services"
        }
    ],
    "sg:phone":"+1 317 826 5771",
    "sg:postcode":"46236",
    "sg:province":"IN",
    "sg:tags":[
        "system"
    ],
    "wof:name":"Judicial Recovery Specialist",
    "wof:placetype":"venue"
},
  "geometry": {"coordinates":[-85.954121,39.906721],"type":"Point"}
}