{
  "type": "Feature",
  "properties": {
    "iso:country":"US",
    "sg:address":"4321 E 82nd St",
    "sg:city":"Indianapolis",
    "sg:classifiers":[
        {
            "category":"Education",
            "subcategory":"Special Training",
            "type":"Public Place"
        }
    ],
    "sg:phone":"+1 317 598 4465",
    "sg:postcode":"46250",
    "sg:province":"IN",
    "sg:tags":[
        "tutoring"
    ],
    "wof:name":"Educational Advantage",
    "wof:placetype":"venue"
},
  "geometry": {"coordinates":[-86.09178,39.906288],"type":"Point"}
}