{
  "type": "Feature",
  "properties": {
    "iso:country":"US",
    "sg:address":"2201 Greentree N",
    "sg:city":"Clarksville",
    "sg:classifiers":[
        {
            "category":"Health Services",
            "subcategory":"Health Practitioner",
            "type":"Services"
        }
    ],
    "sg:phone":"+1 812 283 2013",
    "sg:postcode":"47129",
    "sg:province":"IN",
    "sg:tags":[
        "occupational",
        "safety"
    ],
    "wof:name":"Employcare Occupational Health",
    "wof:placetype":"venue"
},
  "geometry": {"coordinates":[-85.76673599999999,38.331306],"type":"Point"}
}