{
  "type": "Feature",
  "properties": {
    "iso:country":"US",
    "sg:address":"1010 W 7th St",
    "sg:city":"Auburn",
    "sg:classifiers":[
        {
            "category":"Food & Beverages",
            "subcategory":"Groceries & Convenience Stores",
            "type":"Retail Goods"
        }
    ],
    "sg:phone":"+1 260 925 0272",
    "sg:postcode":"46706",
    "sg:province":"IN",
    "sg:tags":[
        "grocer"
    ],
    "wof:name":"Mor-For-Less",
    "wof:placetype":"venue"
},
  "geometry": {"coordinates":[-85.071841,41.366766],"type":"Point"}
}