{
  "type": "Feature",
  "properties": {
    "iso:country":"US",
    "sg:address":"110 S Main St",
    "sg:city":"Dunkirk",
    "sg:classifiers":[
        {
            "category":"Food & Beverages",
            "subcategory":"Groceries & Convenience Stores",
            "type":"Retail Goods"
        }
    ],
    "sg:phone":"+1 765 768 6346",
    "sg:postcode":"47336",
    "sg:province":"IN",
    "wof:name":"J A Miller & Sons Oil",
    "wof:placetype":"venue"
},
  "geometry": {"coordinates":[-85.209919,40.374926],"type":"Point"}
}