{
  "type": "Feature",
  "properties": {
    "iso:country":"US",
    "sg:address":"314 E Kirkwood Ave",
    "sg:city":"Bloomington",
    "sg:classifiers":[
        {
            "category":"Shopping",
            "subcategory":"Clothing, Apparel, & Fashions",
            "type":"Retail Goods"
        }
    ],
    "sg:phone":"+1 812 332 0526",
    "sg:postcode":"47408",
    "sg:province":"IN",
    "sg:tags":[
        "shop",
        "bridal",
        "accessory"
    ],
    "sg:website":"www.bridalessentials.biz",
    "wof:name":"Bridal Essentials",
    "wof:placetype":"venue"
},
  "geometry": {"coordinates":[-86.53040300000001,39.166401],"type":"Point"}
}