{
  "type": "Feature",
  "properties": {
    "iso:country":"US",
    "sg:address":"1525 Audubon Dr",
    "sg:city":"Evansville",
    "sg:classifiers":[
        {
            "category":"Professional",
            "subcategory":"Accounting & Tax Preparation",
            "type":"Services"
        }
    ],
    "sg:phone":"+1 812 437 4777",
    "sg:postcode":"47715",
    "sg:province":"IN",
    "sg:tags":[
        "return"
    ],
    "wof:name":"Beacon Tax Service",
    "wof:placetype":"venue"
},
  "geometry": {"coordinates":[-87.464705,37.955751],"type":"Point"}
}