{
  "type": "Feature",
  "properties": {
    "addr:full":"624 E Chicago Ave East Chicago IN 46312",
    "addr:housenumber":"624",
    "addr:postcode":"46312",
    "addr:street":"E Chicago Ave",
    "iso:country":"US",
    "sg:address":"624 E Chicago Ave",
    "sg:city":"East Chicago",
    "sg:classifiers":[
        {
            "category":"Food & Beverages",
            "subcategory":"Groceries & Convenience Stores",
            "type":"Retail Goods"
        }
    ],
    "sg:phone":"+1 219 391 8969",
    "sg:postcode":"46312",
    "sg:province":"IN",
    "sg:tags":[
        "grocer"
    ],
    "wof:name":"LA Mexicana",
    "wof:placetype":"venue"
},
  "geometry": {"coordinates":[-87.464749,41.629343],"type":"Point"}
}