{
  "type": "Feature",
  "properties": {
    "addr:full":"4303 Washington St Columbus IN 47203",
    "addr:housenumber":"4303",
    "addr:postcode":"47203",
    "addr:street":"Washington St",
    "iso:country":"US",
    "sg:address":"4303 Washington St",
    "sg:city":"Columbus",
    "sg:classifiers":[
        {
            "category":"Retail",
            "subcategory":"Laundry & Dry Cleaning",
            "type":"Services"
        }
    ],
    "sg:phone":"+1 812 376 3650",
    "sg:postcode":"47203",
    "sg:province":"IN",
    "sg:tags":[
        "cleaners",
        "rug",
        "carpet"
    ],
    "wof:name":"Blancett's Custom Carpet Clean",
    "wof:placetype":"venue"
},
  "geometry": {"coordinates":[-85.918418,39.246871],"type":"Point"}
}