{
  "type": "Feature",
  "properties": {
    "addr:full":"2020 Shelby St Indianapolis IN 46203",
    "addr:housenumber":"2020",
    "addr:postcode":"46203",
    "addr:street":"Shelby St",
    "iso:country":"US",
    "sg:address":"2020 Shelby St",
    "sg:city":"Indianapolis",
    "sg:classifiers":[
        {
            "category":"Autos & Motor Vehicles",
            "subcategory":"Automobile Sales",
            "type":"Retail Goods"
        }
    ],
    "sg:phone":"+1 317 631 5015",
    "sg:postcode":"46203",
    "sg:province":"IN",
    "sg:tags":[
        "car",
        "used",
        "dealer"
    ],
    "wof:name":"Fountain Square Motors Inc",
    "wof:placetype":"venue"
},
  "geometry": {"coordinates":[-86.139838,39.739718],"type":"Point"}
}