{
  "type": "Feature",
  "properties": {
    "iso:country":"US",
    "sg:address":"3201 E Jackson St",
    "sg:city":"Muncie",
    "sg:classifiers":[
        {
            "category":"Insurance",
            "subcategory":"Insurance Agent",
            "type":"Services"
        }
    ],
    "sg:phone":"+1 765 281 1955",
    "sg:postcode":"47303",
    "sg:province":"IN",
    "wof:name":"American Family Insurance",
    "wof:placetype":"venue"
},
  "geometry": {"coordinates":[-85.34956699999999,40.192975],"type":"Point"}
}