{
  "type": "Feature",
  "properties": {
    "iso:country":"US",
    "sg:address":"10 W Van Trees St",
    "sg:city":"Washington",
    "sg:classifiers":[
        {
            "category":"Wholesale",
            "subcategory":"Farm Supplies",
            "type":"Manufacturing & Wholesale Goods"
        }
    ],
    "sg:phone":"+1 812 254 5429",
    "sg:postcode":"47501",
    "sg:province":"IN",
    "sg:tags":[
        "feed"
    ],
    "wof:name":"Feed My Sheep Of Daviess Cty",
    "wof:placetype":"venue"
},
  "geometry": {"coordinates":[-87.175566,38.657809],"type":"Point"}
}