{
  "type": "Feature",
  "properties": {
    "iso:country":"US",
    "sg:address":"9501 Airport Dr",
    "sg:city":"Fort Wayne",
    "sg:classifiers":[
        {
            "category":"Wholesale",
            "subcategory":"Chemicals & Plastics",
            "type":"Manufacturing & Wholesale Goods"
        }
    ],
    "sg:phone":"+1 260 478 1639",
    "sg:postcode":"46809",
    "sg:province":"IN",
    "wof:name":"Genova-Indiana",
    "wof:placetype":"venue"
},
  "geometry": {"coordinates":[-85.183025,40.9914],"type":"Point"}
}