{
  "type": "Feature",
  "properties": {
    "iso:country":"US",
    "sg:address":"308 E Stop 11 Rd",
    "sg:city":"Indianapolis",
    "sg:classifiers":[
        {
            "category":"Shopping",
            "subcategory":"Hobbies, Toys, & Games",
            "type":"Retail Goods"
        }
    ],
    "sg:phone":"+1 317 859 6575",
    "sg:postcode":"46227",
    "sg:province":"IN",
    "sg:tags":[
        "craft",
        "supply"
    ],
    "wof:name":"Michelle's Arts & Crafts",
    "wof:placetype":"venue"
},
  "geometry": {"coordinates":[-86.151239,39.651787],"type":"Point"}
}