{
  "type": "Feature",
  "properties": {
    "iso:country":"US",
    "sg:address":"3712 Lake City Hwy",
    "sg:city":"Warsaw",
    "sg:classifiers":[
        {
            "category":"Banks & Credit Unions",
            "subcategory":"Bank",
            "type":"Services"
        }
    ],
    "sg:phone":"+1 574 267 3181",
    "sg:postcode":"46580",
    "sg:province":"IN",
    "sg:tags":[
        "loan",
        "real estate"
    ],
    "wof:name":"Wholesale Mortgage Funding",
    "wof:placetype":"venue"
},
  "geometry": {"coordinates":[-85.799162,41.229504],"type":"Point"}
}