{
  "type": "Feature",
  "properties": {
    "addr:full":"822 W 1st St Ste 7 Bloomington IN 47403",
    "addr:housenumber":"822",
    "addr:postcode":"47403",
    "addr:street":"W 1St St Ste 7",
    "iso:country":"US",
    "sg:address":"822 W 1st St Ste 7",
    "sg:city":"Bloomington",
    "sg:classifiers":[
        {
            "category":"Health Services",
            "subcategory":"Doctor",
            "type":"Services"
        }
    ],
    "sg:phone":"+1 812 330 9962",
    "sg:postcode":"47403",
    "sg:province":"IN",
    "wof:name":"Ray James Bradley MD",
    "wof:placetype":"venue"
},
  "geometry": {"coordinates":[-86.544601,39.1595],"type":"Point"}
}