{
  "type": "Feature",
  "properties": {
    "iso:country":"US",
    "sg:address":"1309 S Miller St",
    "sg:city":"Shelbyville",
    "sg:classifiers":[
        {
            "category":"Home & Garden",
            "subcategory":"Building Materials",
            "type":"Retail Goods"
        }
    ],
    "sg:phone":"+1 317 398 9773",
    "sg:postcode":"46176",
    "sg:province":"IN",
    "sg:tags":[
        "lumber"
    ],
    "wof:name":"Builders Lumber & Hardware Inc",
    "wof:placetype":"venue"
},
  "geometry": {"coordinates":[-85.784854,39.512773],"type":"Point"}
}