{
  "type": "Feature",
  "properties": {
    "iso:country":"US",
    "sg:address":"604 W Main St",
    "sg:city":"Plainfield",
    "sg:classifiers":[
        {
            "category":"Personal",
            "subcategory":"Beauty Salon",
            "type":"Services"
        }
    ],
    "sg:phone":"+1 317 837 9205",
    "sg:postcode":"46168",
    "sg:province":"IN",
    "wof:name":"Lovely Lady Riders",
    "wof:placetype":"venue"
},
  "geometry": {"coordinates":[-86.408559,39.701009],"type":"Point"}
}