{
  "type": "Feature",
  "properties": {
    "iso:country":"US",
    "sg:address":"5990 N 750 E",
    "sg:city":"Hamlet",
    "sg:classifiers":[
        {
            "category":"Education",
            "subcategory":"School",
            "type":"Public Place"
        }
    ],
    "sg:phone":"+1 574 867 2711",
    "sg:postcode":"46532",
    "sg:province":"IN",
    "wof:name":"Oregon Davis School",
    "wof:placetype":"venue"
},
  "geometry": {"coordinates":[-86.553245,41.387952],"type":"Point"}
}