{
  "type": "Feature",
  "properties": {
    "iso:country":"US",
    "sg:address":"1211 Kristopher Ave",
    "sg:city":"Scottsburg",
    "sg:classifiers":[
        {
            "category":"Shopping",
            "subcategory":"Bicycles & Sporting Goods",
            "type":"Retail Goods"
        }
    ],
    "sg:phone":"+1 812 752 0765",
    "sg:postcode":"47170",
    "sg:province":"IN",
    "wof:name":"Pistol City Shooters LLC",
    "wof:placetype":"venue"
},
  "geometry": {"coordinates":[-85.786732,38.691484],"type":"Point"}
}