{
  "type": "Feature",
  "properties": {
    "iso:country":"US",
    "sg:address":"4373 E State Rd 256",
    "sg:city":"Scottsburg",
    "sg:classifiers":[
        {
            "category":"Shopping",
            "subcategory":"Bicycles & Sporting Goods",
            "type":"Retail Goods"
        }
    ],
    "sg:phone":"+1 812 794 2540",
    "sg:postcode":"47170",
    "sg:province":"IN",
    "wof:name":"Bass Den",
    "wof:placetype":"venue"
},
  "geometry": {"coordinates":[-85.693597,38.736757],"type":"Point"}
}