{
  "type": "Feature",
  "properties": {
    "iso:country":"US",
    "sg:address":"1738 W 14th St",
    "sg:city":"Marion",
    "sg:classifiers":[
        {
            "category":"Building & Trades",
            "subcategory":"Construction",
            "type":"Services"
        }
    ],
    "sg:phone":"+1 765 662 6781",
    "sg:postcode":"46953",
    "sg:province":"IN",
    "sg:tags":[
        "house"
    ],
    "wof:name":"Ice Son Construction",
    "wof:placetype":"venue"
},
  "geometry": {"coordinates":[-85.682672,40.547466],"type":"Point"}
}