{
  "type": "Feature",
  "properties": {
    "iso:country":"US",
    "sg:address":"1850 E 62nd St",
    "sg:city":"Indianapolis",
    "sg:classifiers":[
        {
            "category":"Restaurant",
            "type":"Food & Drink"
        }
    ],
    "sg:phone":"+1 317 251 8610",
    "sg:postcode":"46220",
    "sg:province":"IN",
    "wof:name":"Khoury's Restaurant",
    "wof:placetype":"venue"
},
  "geometry": {"coordinates":[-86.128714,39.86872],"type":"Point"}
}