{
  "type": "Feature",
  "properties": {
    "addr:full":"2145 Bergdolt Rd Evansville IN 47711",
    "addr:housenumber":"2145",
    "addr:postcode":"47711",
    "addr:street":"Bergdolt Rd",
    "iso:country":"US",
    "sg:address":"2145 Bergdolt Rd",
    "sg:city":"Evansville",
    "sg:classifiers":[
        {
            "category":"Professional",
            "subcategory":"Computer Services",
            "type":"Services"
        }
    ],
    "sg:phone":"+1 812 428 7669",
    "sg:postcode":"47711",
    "sg:province":"IN",
    "sg:tags":[
        "consultant",
        "designer"
    ],
    "wof:name":"Strouse Software Systems",
    "wof:placetype":"venue"
},
  "geometry": {"coordinates":[-87.526166,38.020581],"type":"Point"}
}