{
  "type": "Feature",
  "properties": {
    "iso:country":"US",
    "sg:address":"6076 Tybalt Ln",
    "sg:city":"Indianapolis",
    "sg:classifiers":[
        {
            "category":"Personal",
            "type":"Services"
        }
    ],
    "sg:phone":"+1 317 299 5362",
    "sg:postcode":"46254",
    "sg:province":"IN",
    "sg:tags":[
        "car",
        "loading",
        "unloading"
    ],
    "wof:name":"Morton Movers",
    "wof:placetype":"venue"
},
  "geometry": {"coordinates":[-86.26793499999999,39.864736],"type":"Point"}
}