{
  "type": "Feature",
  "properties": {
    "addr:full":"201 W Main St Odon IN 47562",
    "addr:housenumber":"201",
    "addr:postcode":"47562",
    "addr:street":"W Main St",
    "iso:country":"US",
    "sg:address":"201 W Main St",
    "sg:city":"Odon",
    "sg:classifiers":[
        {
            "category":"Retail",
            "subcategory":"Auto Rental",
            "type":"Services"
        }
    ],
    "sg:phone":"+1 812 636 7161",
    "sg:postcode":"47562",
    "sg:province":"IN",
    "sg:tags":[
        "truck"
    ],
    "wof:name":"U-Haul",
    "wof:placetype":"venue"
},
  "geometry": {"coordinates":[-86.99302299999999,38.842607],"type":"Point"}
}