{
  "type": "Feature",
  "properties": {
    "iso:country":"US",
    "sg:address":"13267 N White Lick Rd",
    "sg:city":"Mooresville",
    "sg:classifiers":[
        {
            "category":"Farming",
            "subcategory":"Livestock Farm",
            "type":"Manufacturing & Wholesale Goods"
        }
    ],
    "sg:phone":"+1 317 831 3666",
    "sg:postcode":"46158",
    "sg:province":"IN",
    "sg:tags":[
        "feedlot",
        "corn",
        "soybean",
        "beef",
        "cattle"
    ],
    "wof:name":"Copeland Farms",
    "wof:placetype":"venue"
},
  "geometry": {"coordinates":[-86.394572,39.6172],"type":"Point"}
}