{
  "type": "Feature",
  "properties": {
    "iso:country":"US",
    "sg:address":"6435 E 30th St",
    "sg:city":"Indianapolis",
    "sg:classifiers":[
        {
            "category":"Wholesale",
            "subcategory":"Construction Materials",
            "type":"Manufacturing & Wholesale Goods"
        }
    ],
    "sg:phone":"+1 317 546 9378",
    "sg:postcode":"46219",
    "sg:province":"IN",
    "sg:tags":[
        "roofing"
    ],
    "wof:name":"Shelter Distribution",
    "wof:placetype":"venue"
},
  "geometry": {"coordinates":[-86.046328,39.810993],"type":"Point"}
}