{
  "type": "Feature",
  "properties": {
    "iso:country":"US",
    "sg:address":"310 S Kentucky Ave",
    "sg:city":"Evansville",
    "sg:classifiers":[
        {
            "category":"Wholesale",
            "subcategory":"Machinery & Supplies",
            "type":"Manufacturing & Wholesale Goods"
        }
    ],
    "sg:phone":"+1 812 422 2171",
    "sg:postcode":"47714",
    "sg:province":"IN",
    "sg:tags":[
        "equipment",
        "layer",
        "carpet"
    ],
    "wof:name":"Huff's Carpet Supply Inc",
    "wof:placetype":"venue"
},
  "geometry": {"coordinates":[-87.547634,37.974628],"type":"Point"}
}