{
  "type": "Feature",
  "properties": {
    "addr:full":"4041 Franklin St Michigan City IN 46360",
    "addr:housenumber":"4041",
    "addr:postcode":"46360",
    "addr:street":"Franklin St",
    "iso:country":"US",
    "sg:address":"4041 Franklin St",
    "sg:city":"Michigan City",
    "sg:classifiers":[
        {
            "category":"Shopping",
            "subcategory":"Clothing, Apparel, & Fashions",
            "type":"Retail Goods"
        }
    ],
    "sg:phone":"+1 219 879 8734",
    "sg:postcode":"46360",
    "sg:province":"IN",
    "sg:tags":[
        "item",
        "boutique"
    ],
    "wof:name":"Claire's Boutique",
    "wof:placetype":"venue"
},
  "geometry": {"coordinates":[-86.894051,41.680936],"type":"Point"}
}