{
  "type": "Feature",
  "properties": {
    "iso:country":"US",
    "sg:address":"5811 N Post Rd",
    "sg:city":"Indianapolis",
    "sg:classifiers":[
        {
            "category":"Professional",
            "subcategory":"Employment Agencies",
            "type":"Services"
        }
    ],
    "sg:phone":"+1 317 257 8534",
    "sg:postcode":"46216",
    "sg:province":"IN",
    "sg:tags":[
        "help",
        "contractor"
    ],
    "wof:name":"Assured Healthcare",
    "wof:placetype":"venue"
},
  "geometry": {"coordinates":[-86.010205,39.848574],"type":"Point"}
}