{
  "type": "Feature",
  "properties": {
    "addr:full":"511 Zimmerman Dr Princeton IN 47670",
    "addr:housenumber":"511",
    "addr:postcode":"47670",
    "addr:street":"Zimmerman Dr",
    "iso:country":"US",
    "sg:address":"511 Zimmerman Dr",
    "sg:city":"Princeton",
    "sg:classifiers":[
        {
            "category":"Real Estate",
            "subcategory":"Real Estate Services",
            "type":"Services"
        },
        {
            "category":"Real Estate",
            "subcategory":"Real Estate Agent",
            "type":"Services"
        }
    ],
    "sg:phone":"+1 812 386 6745",
    "sg:postcode":"47670",
    "sg:province":"IN",
    "sg:tags":[
        "buyer",
        "broker"
    ],
    "wof:name":"The Reality Center",
    "wof:placetype":"venue"
},
  "geometry": {"coordinates":[-87.56166,38.372686],"type":"Point"}
}