{
  "type": "Feature",
  "properties": {
    "iso:country":"US",
    "sg:address":"501 State Rd 46 E",
    "sg:city":"Nashville",
    "sg:classifiers":[
        {
            "category":"Restaurant",
            "type":"Food & Drink"
        }
    ],
    "sg:phone":"+1 812 988 4452",
    "sg:postcode":"47448",
    "sg:province":"IN",
    "wof:name":"Mc Donald's",
    "wof:placetype":"venue"
},
  "geometry": {"coordinates":[-86.246957,39.202923],"type":"Point"}
}