{
  "type": "Feature",
  "properties": {
    "addr:full":"921 Broadway Chesterton IN 46304",
    "addr:housenumber":"921",
    "addr:postcode":"46304",
    "addr:street":"Broadway",
    "iso:country":"US",
    "sg:address":"921 Broadway",
    "sg:city":"Chesterton",
    "sg:classifiers":[
        {
            "category":"Retail",
            "subcategory":"Auto Rental",
            "type":"Services"
        }
    ],
    "sg:phone":"+1 219 926 7622",
    "sg:postcode":"46304",
    "sg:province":"IN",
    "sg:tags":[
        "renting",
        "truck",
        "leasing"
    ],
    "wof:name":"U-Haul Co",
    "wof:placetype":"venue"
},
  "geometry": {"coordinates":[-87.065128,41.611541],"type":"Point"}
}