{
  "type": "Feature",
  "properties": {
    "iso:country":"US",
    "sg:address":"9085 Ernestine St",
    "sg:city":"Wheatfield",
    "sg:classifiers":[
        {
            "category":"Building & Trades",
            "subcategory":"Construction",
            "type":"Services"
        }
    ],
    "sg:phone":"+1 219 956 3535",
    "sg:postcode":"46392",
    "sg:province":"IN",
    "sg:tags":[
        "painter"
    ],
    "wof:name":"Daniel T Fritts Painting",
    "wof:placetype":"venue"
},
  "geometry": {"coordinates":[-87.139588,41.142517],"type":"Point"}
}