{
  "type": "Feature",
  "properties": {
    "addr:full":"9137 Gloeckner Creek Rd Brookville IN 47012",
    "addr:housenumber":"9137",
    "addr:postcode":"47012",
    "addr:street":"Gloeckner Creek Rd",
    "iso:country":"US",
    "sg:address":"9137 Gloeckner Creek Rd",
    "sg:city":"Brookville",
    "sg:classifiers":[
        {
            "category":"Wholesale",
            "subcategory":"Machinery & Supplies",
            "type":"Manufacturing & Wholesale Goods"
        },
        {
            "category":"Professional",
            "type":"Services"
        }
    ],
    "sg:phone":"+1 765 647 2326",
    "sg:postcode":"47012",
    "sg:province":"IN",
    "sg:tags":[
        "equipment",
        "industrial",
        "establishment"
    ],
    "wof:name":"Integrated Handling Syst Inc",
    "wof:placetype":"venue"
},
  "geometry": {"coordinates":[-84.967045,39.424778],"type":"Point"}
}