{
  "type": "Feature",
  "properties": {
    "iso:country":"US",
    "sg:address":"1437 N State Rd 29",
    "sg:city":"Michigantown",
    "sg:classifiers":[
        {
            "category":"Farming",
            "subcategory":"Farm & Veterinary Services",
            "type":"Manufacturing & Wholesale Goods"
        }
    ],
    "sg:phone":"+1 765 249 2385",
    "sg:postcode":"46057",
    "sg:province":"IN",
    "sg:tags":[
        "breeder",
        "livestock"
    ],
    "wof:name":"Premier Swine Breeding Systems",
    "wof:placetype":"venue"
},
  "geometry": {"coordinates":[-86.392832,40.302786],"type":"Point"}
}