{
  "type": "Feature",
  "properties": {
    "iso:country":"US",
    "sg:address":"9659 Farragut Cir",
    "sg:city":"Indianapolis",
    "sg:classifiers":[
        {
            "category":"Banks & Credit Unions",
            "subcategory":"Investment Brokerage",
            "type":"Services"
        }
    ],
    "sg:phone":"+1 317 841 9641",
    "sg:postcode":"46256",
    "sg:province":"IN",
    "wof:name":"Decision Resources",
    "wof:placetype":"venue"
},
  "geometry": {"coordinates":[-85.968413,39.930024],"type":"Point"}
}