{
  "type": "Feature",
  "properties": {
    "iso:country":"US",
    "sg:address":"3006 Campbell St",
    "sg:city":"Valparaiso",
    "sg:classifiers":[
        {
            "category":"Professional",
            "type":"Services"
        }
    ],
    "sg:phone":"+1 219 462 4175",
    "sg:postcode":"46385",
    "sg:province":"IN",
    "wof:name":"Elite Services of Indiana LLC",
    "wof:placetype":"venue"
},
  "geometry": {"coordinates":[-87.0659,41.495796],"type":"Point"}
}