{
  "type": "Feature",
  "properties": {
    "addr:full":"995 John-Bart Rd Lebanon IN 46052",
    "addr:housenumber":"995",
    "addr:postcode":"46052",
    "addr:street":"John-Bart Rd",
    "iso:country":"US",
    "sg:address":"995 John-Bart Rd",
    "sg:city":"Lebanon",
    "sg:classifiers":[
        {
            "category":"Professional",
            "type":"Services"
        }
    ],
    "sg:phone":"+1 765 482 0934",
    "sg:postcode":"46052",
    "sg:province":"IN",
    "wof:name":"Kincaid Family Ltd Partne",
    "wof:placetype":"venue"
},
  "geometry": {"coordinates":[-86.450625,40.055607],"type":"Point"}
}