{
  "type": "Feature",
  "properties": {
    "iso:country":"US",
    "sg:address":"111 S Vine St",
    "sg:city":"Batesville",
    "sg:classifiers":[
        {
            "category":"Organizations",
            "subcategory":"Membership Organization",
            "type":"Services"
        }
    ],
    "sg:phone":"+1 812 934 2641",
    "sg:postcode":"47006",
    "sg:province":"IN",
    "wof:name":"Knights Of St John",
    "wof:placetype":"venue"
},
  "geometry": {"coordinates":[-85.22561399999999,39.298886],"type":"Point"}
}