{
  "type": "Feature",
  "properties": {
    "iso:country":"US",
    "sg:address":"2250 N Mitthoeffer Rd",
    "sg:city":"Indianapolis",
    "sg:classifiers":[
        {
            "category":"Building & Trades",
            "subcategory":"Landscaping Services",
            "type":"Services"
        }
    ],
    "sg:phone":"+1 317 897 8431",
    "sg:postcode":"46229",
    "sg:province":"IN",
    "sg:tags":[
        "builder",
        "contractor",
        "landscape",
        "deck"
    ],
    "wof:name":"Ajays Nursery Inc",
    "wof:placetype":"venue"
},
  "geometry": {"coordinates":[-85.990593,39.799758],"type":"Point"}
}