{
  "type": "Feature",
  "properties": {
    "iso:country":"US",
    "sg:address":"7404 Aruba Ln",
    "sg:city":"Indianapolis",
    "sg:classifiers":[
        {
            "category":"Personal",
            "type":"Services"
        }
    ],
    "sg:phone":"+1 317 298 5231",
    "sg:postcode":"46214",
    "sg:province":"IN",
    "wof:name":"Formalties Event Cnsltn Design",
    "wof:placetype":"venue"
},
  "geometry": {"coordinates":[-86.291875,39.821124],"type":"Point"}
}