{
  "type": "Feature",
  "properties": {
    "iso:country":"US",
    "sg:address":"7038 Forest Park Dr",
    "sg:city":"Indianapolis",
    "sg:classifiers":[
        {
            "category":"Recreation",
            "subcategory":"Marina",
            "type":"Entertainment"
        }
    ],
    "sg:phone":"+1 317 887 6555",
    "sg:postcode":"46217",
    "sg:province":"IN",
    "sg:tags":[
        "storage",
        "boat"
    ],
    "wof:name":"Affordable Boat & Rv Storage",
    "wof:placetype":"venue"
},
  "geometry": {"coordinates":[-86.17220500000001,39.661118],"type":"Point"}
}