{
  "type": "Feature",
  "properties": {
    "addr:full":"2027 E Brookside Ave Indianapolis IN 46201",
    "addr:housenumber":"2027",
    "addr:postcode":"46201",
    "addr:street":"E Brookside Ave",
    "iso:country":"US",
    "sg:address":"2027 E Brookside Ave",
    "sg:city":"Indianapolis",
    "sg:classifiers":[
        {
            "category":"Organizations",
            "subcategory":"Religious Organization",
            "type":"Services"
        }
    ],
    "sg:phone":"+1 317 639 5978",
    "sg:postcode":"46201",
    "sg:province":"IN",
    "wof:name":"We As One Ministries Inc",
    "wof:placetype":"venue"
},
  "geometry": {"coordinates":[-86.12516100000001,39.788144],"type":"Point"}
}