{
  "type": "Feature",
  "properties": {
    "iso:country":"US",
    "sg:address":"1225 S Scott St",
    "sg:city":"Bluffton",
    "sg:classifiers":[
        {
            "category":"Home & Garden",
            "subcategory":"Garden Supply",
            "type":"Retail Goods"
        }
    ],
    "sg:phone":"+1 260 824 2695",
    "sg:postcode":"46714",
    "sg:province":"IN",
    "sg:tags":[
        "center"
    ],
    "wof:name":"Janet's Garden Ctr",
    "wof:placetype":"venue"
},
  "geometry": {"coordinates":[-85.17017800000001,40.727705],"type":"Point"}
}