{
  "type": "Feature",
  "properties": {
    "iso:country":"US",
    "sg:address":"6095 W 400 N",
    "sg:city":"Warsaw",
    "sg:classifiers":[
        {
            "category":"Farming",
            "subcategory":"Farm",
            "type":"Manufacturing & Wholesale Goods"
        }
    ],
    "sg:phone":"+1 574 858 9814",
    "sg:postcode":"46582",
    "sg:province":"IN",
    "sg:tags":[
        "crop",
        "general"
    ],
    "wof:name":"Irwin Farms",
    "wof:placetype":"venue"
},
  "geometry": {"coordinates":[-85.961663,41.290051],"type":"Point"}
}