{
  "type": "Feature",
  "properties": {
    "iso:country":"US",
    "sg:address":"815 E Bradford St",
    "sg:city":"Marion",
    "sg:classifiers":[
        {
            "category":"Organizations",
            "subcategory":"Religious Organization",
            "type":"Services"
        }
    ],
    "sg:phone":"+1 765 662 7728",
    "sg:postcode":"46952",
    "sg:province":"IN",
    "wof:name":"Calvary Assembly of God",
    "wof:placetype":"venue"
},
  "geometry": {"coordinates":[-85.64684699999999,40.567156],"type":"Point"}
}