{
  "type": "Feature",
  "properties": {
    "iso:country":"US",
    "sg:address":"9633 Kennedy Ave",
    "sg:city":"Highland",
    "sg:classifiers":[
        {
            "category":"Building & Trades",
            "subcategory":"Construction",
            "type":"Services"
        }
    ],
    "sg:phone":"+1 219 922 6300",
    "sg:postcode":"46322",
    "sg:province":"IN",
    "sg:tags":[
        "carpentry",
        "general",
        "contractor"
    ],
    "wof:name":"Makin It Construction",
    "wof:placetype":"venue"
},
  "geometry": {"coordinates":[-87.461513,41.538075],"type":"Point"}
}