{
  "type": "Feature",
  "properties": {
    "iso:country":"US",
    "sg:address":"111 S 2nd St",
    "sg:city":"Centerville",
    "sg:classifiers":[
        {
            "category":"Social Services",
            "subcategory":"Adult Care",
            "type":"Services"
        }
    ],
    "sg:phone":"+1 765 855 5651",
    "sg:postcode":"47330",
    "sg:province":"IN",
    "sg:tags":[
        "organization",
        "senior",
        "citizen"
    ],
    "wof:name":"Centerville Abington Sr Ctr",
    "wof:placetype":"venue"
},
  "geometry": {"coordinates":[-84.993106,39.817635],"type":"Point"}
}