{
  "type": "Feature",
  "properties": {
    "iso:country":"US",
    "sg:address":"1535 N Cline Ave",
    "sg:city":"Griffith",
    "sg:classifiers":[
        {
            "category":"Education",
            "subcategory":"Dance Studio",
            "type":"Public Place"
        }
    ],
    "sg:phone":"+1 219 838 2813",
    "sg:postcode":"46319",
    "sg:province":"IN",
    "sg:tags":[
        "art",
        "performing",
        "instruction",
        "dancing"
    ],
    "sg:website":"www.jeannesdanceacademy.com",
    "wof:name":"Jeanne's Dance Academy Inc",
    "wof:placetype":"venue"
},
  "geometry": {"coordinates":[-87.432602,41.549099],"type":"Point"}
}