{
  "type": "Feature",
  "properties": {
    "iso:country":"US",
    "sg:address":"2440 Glick St",
    "sg:city":"Lafayette",
    "sg:classifiers":[
        {
            "category":"Education",
            "subcategory":"Special Training",
            "type":"Public Place"
        }
    ],
    "sg:phone":"+1 765 474 7767",
    "sg:postcode":"47905",
    "sg:province":"IN",
    "sg:tags":[
        "instruction",
        "driving"
    ],
    "wof:name":"Milestone Driving School Inc",
    "wof:placetype":"venue"
},
  "geometry": {"coordinates":[-86.867977,40.399034],"type":"Point"}
}