{
  "type": "Feature",
  "properties": {
    "iso:country":"US",
    "sg:address":"68 E Rampart St",
    "sg:city":"Shelbyville",
    "sg:classifiers":[
        {
            "category":"Travel",
            "subcategory":"Hotels & Motels",
            "type":"Entertainment"
        }
    ],
    "sg:phone":"+1 317 398 0472",
    "sg:postcode":"46176",
    "sg:province":"IN",
    "wof:name":"Holiday Inn Express Shelbyvll",
    "wof:placetype":"venue"
},
  "geometry": {"coordinates":[-85.773581,39.547464],"type":"Point"}
}