{
  "type": "Feature",
  "properties": {
    "iso:country":"US",
    "sg:address":"1 S Shield St",
    "sg:city":"Knox",
    "sg:classifiers":[
        {
            "category":"Education",
            "subcategory":"Special Training",
            "type":"Public Place"
        }
    ],
    "sg:phone":"+1 574 772 4433",
    "sg:postcode":"46534",
    "sg:province":"IN",
    "wof:name":"Computer Tutor",
    "wof:placetype":"venue"
},
  "geometry": {"coordinates":[-86.624335,41.297467],"type":"Point"}
}