{
  "type": "Feature",
  "properties": {
    "iso:country":"US",
    "sg:address":"1307 Smith St",
    "sg:city":"Logansport",
    "sg:classifiers":[
        {
            "category":"Professional",
            "subcategory":"Accounting & Tax Preparation",
            "type":"Services"
        }
    ],
    "sg:phone":"+1 574 722 3911",
    "sg:postcode":"46947",
    "sg:province":"IN",
    "sg:tags":[
        "accountant"
    ],
    "wof:name":"Brink & Brink",
    "wof:placetype":"venue"
},
  "geometry": {"coordinates":[-86.354857,40.767388],"type":"Point"}
}