{
  "type": "Feature",
  "properties": {
    "iso:country":"US",
    "sg:address":"5887 N 800 E",
    "sg:city":"New Carlisle",
    "sg:classifiers":[
        {
            "category":"Building & Trades",
            "subcategory":"Construction",
            "type":"Services"
        }
    ],
    "sg:phone":"+1 574 654 3754",
    "sg:postcode":"46552",
    "sg:province":"IN",
    "sg:tags":[
        "excavating",
        "contractor"
    ],
    "wof:name":"K-Fex Excavating & Trucking",
    "wof:placetype":"venue"
},
  "geometry": {"coordinates":[-86.545058,41.68605],"type":"Point"}
}