{
  "type": "Feature",
  "properties": {
    "iso:country":"US",
    "sg:address":"300 S Michigan St",
    "sg:city":"South Bend",
    "sg:classifiers":[
        {
            "category":"Professional",
            "subcategory":"Management & Consulting",
            "type":"Services"
        }
    ],
    "sg:phone":"+1 574 282 4350",
    "sg:postcode":"46601",
    "sg:province":"IN",
    "sg:tags":[
        "consultant",
        "business"
    ],
    "wof:name":"Small Business Development Ctr",
    "wof:placetype":"venue"
},
  "geometry": {"coordinates":[-86.250282,41.672317],"type":"Point"}
}