{
  "type": "Feature",
  "properties": {
    "addr:full":"2587 Stringtown Rd Evansville IN 47711",
    "addr:housenumber":"2587",
    "addr:postcode":"47711",
    "addr:street":"Stringtown Rd",
    "iso:country":"US",
    "sg:address":"2587 Stringtown Rd",
    "sg:city":"Evansville",
    "sg:classifiers":[
        {
            "category":"Retail",
            "subcategory":"Laundry & Dry Cleaning",
            "type":"Services"
        }
    ],
    "sg:phone":"+1 812 425 9471",
    "sg:postcode":"47711",
    "sg:province":"IN",
    "sg:tags":[
        "cleaners"
    ],
    "wof:name":"Crescent Cleaners",
    "wof:placetype":"venue"
},
  "geometry": {"coordinates":[-87.55395799999999,38.003223],"type":"Point"}
}