{
  "type": "Feature",
  "properties": {
    "iso:country":"US",
    "sg:address":"2201 8th Ave",
    "sg:city":"Terre Haute",
    "sg:classifiers":[
        {
            "category":"Personal",
            "subcategory":"Beauty Salon",
            "type":"Services"
        }
    ],
    "sg:phone":"+1 812 234 4760",
    "sg:postcode":"47804",
    "sg:province":"IN",
    "wof:name":"Hair With Flair",
    "wof:placetype":"venue"
},
  "geometry": {"coordinates":[-87.383736,39.484826],"type":"Point"}
}