{
  "type": "Feature",
  "properties": {
    "iso:country":"US",
    "sg:address":"3320 N Wells St",
    "sg:city":"Fort Wayne",
    "sg:classifiers":[
        {
            "category":"Freight",
            "type":"Transportation"
        }
    ],
    "sg:phone":"+1 260 483 3141",
    "sg:postcode":"46808",
    "sg:province":"IN",
    "sg:tags":[
        "trucking"
    ],
    "sg:website":"www.abf.com",
    "wof:name":"ABF Freight System Inc",
    "wof:placetype":"venue"
},
  "geometry": {"coordinates":[-85.147828,41.110925],"type":"Point"}
}