{
  "type": "Feature",
  "properties": {
    "iso:country":"US",
    "sg:address":"313 N Warpath Dr",
    "sg:city":"Milan",
    "sg:classifiers":[
        {
            "category":"Home & Garden",
            "subcategory":"Garden Supply",
            "type":"Retail Goods"
        }
    ],
    "sg:phone":"+1 812 654 2523",
    "sg:postcode":"47031",
    "sg:province":"IN",
    "sg:tags":[
        "engine"
    ],
    "wof:name":"Schebler Lawn & Garden",
    "wof:placetype":"venue"
},
  "geometry": {"coordinates":[-85.129921,39.12542],"type":"Point"}
}