{
  "type": "Feature",
  "properties": {
    "iso:country":"US",
    "sg:address":"8014 Acorn Hill Cove",
    "sg:city":"Fort Wayne",
    "sg:classifiers":[
        {
            "category":"Retail",
            "subcategory":"Repair Shop",
            "type":"Services"
        }
    ],
    "sg:phone":"+1 260 417 1298",
    "sg:postcode":"46804",
    "sg:province":"IN",
    "wof:name":"AAA Piano Works",
    "wof:placetype":"venue"
},
  "geometry": {"coordinates":[-85.248366,41.080362],"type":"Point"}
}