{
  "type": "Feature",
  "properties": {
    "iso:country":"US",
    "sg:address":"11691 N Executive Dr",
    "sg:city":"Edinburgh",
    "sg:classifiers":[
        {
            "category":"Shopping",
            "subcategory":"Clothing, Apparel, & Fashions",
            "type":"Retail Goods"
        }
    ],
    "sg:phone":"+1 812 526 6130",
    "sg:postcode":"46124",
    "sg:province":"IN",
    "wof:name":"Kasper LTD",
    "wof:placetype":"venue"
},
  "geometry": {"coordinates":[-85.964145,39.310054],"type":"Point"}
}