{
  "type": "Feature",
  "properties": {
    "iso:country":"US",
    "sg:address":"1904 Elmwood Ave",
    "sg:city":"Lafayette",
    "sg:classifiers":[
        {
            "category":"Banks & Credit Unions",
            "subcategory":"Bank",
            "type":"Services"
        }
    ],
    "sg:phone":"+1 765 423 7100",
    "sg:postcode":"47904",
    "sg:province":"IN",
    "wof:name":"Lafayette Bank & Trust Co",
    "wof:placetype":"venue"
},
  "geometry": {"coordinates":[-86.87433299999999,40.428056],"type":"Point"}
}