{
  "type": "Feature",
  "properties": {
    "addr:full":"9554 S Lake Ridge Dr Bloomington IN 47401",
    "addr:housenumber":"9554",
    "addr:postcode":"47401",
    "addr:street":"S Lake Ridge Dr",
    "iso:country":"US",
    "sg:address":"9554 S Lake Ridge Dr",
    "sg:city":"Bloomington",
    "sg:classifiers":[
        {
            "category":"Real Estate",
            "subcategory":"Real Estate Agent",
            "type":"Services"
        }
    ],
    "sg:phone":"+1 812 824 7797",
    "sg:postcode":"47401",
    "sg:province":"IN",
    "sg:tags":[
        "agency",
        "rental"
    ],
    "wof:name":"Rental Unit 177",
    "wof:placetype":"venue"
},
  "geometry": {"coordinates":[-86.506777,39.030378],"type":"Point"}
}