{
  "type": "Feature",
  "properties": {
    "iso:country":"US",
    "sg:address":"200 SW 1st St",
    "sg:city":"Loogootee",
    "sg:classifiers":[
        {
            "category":"Building & Trades",
            "subcategory":"Construction",
            "type":"Services"
        }
    ],
    "sg:phone":"+1 812 295 4348",
    "sg:postcode":"47553",
    "sg:province":"IN",
    "sg:tags":[
        "excavating",
        "contractor"
    ],
    "wof:name":"Gary V Burris",
    "wof:placetype":"venue"
},
  "geometry": {"coordinates":[-86.91621,38.673106],"type":"Point"}
}