{
  "type": "Feature",
  "properties": {
    "addr:full":"6343 Constitution Dr Fort Wayne IN 46804",
    "addr:housenumber":"6343",
    "addr:postcode":"46804",
    "addr:street":"Constitution Dr",
    "iso:country":"US",
    "sg:address":"6343 Constitution Dr",
    "sg:city":"Fort Wayne",
    "sg:classifiers":[
        {
            "category":"Personal",
            "type":"Services"
        }
    ],
    "sg:phone":"+1 260 434 0066",
    "sg:postcode":"46804",
    "sg:province":"IN",
    "sg:tags":[
        "miscellaneous"
    ],
    "wof:name":"Personal Success Coaching",
    "wof:placetype":"venue"
},
  "geometry": {"coordinates":[-85.22600199999999,41.067863],"type":"Point"}
}