{
  "type": "Feature",
  "properties": {
    "iso:country":"US",
    "sg:address":"726 Wedeking Ave",
    "sg:city":"Evansville",
    "sg:classifiers":[
        {
            "category":"Education",
            "subcategory":"Junior College",
            "type":"Public Place"
        }
    ],
    "sg:phone":"+1 812 435 8280",
    "sg:postcode":"47711",
    "sg:province":"IN",
    "sg:tags":[
        "technical",
        "institute"
    ],
    "wof:name":"North Evening School",
    "wof:placetype":"venue"
},
  "geometry": {"coordinates":[-87.552566,37.997625],"type":"Point"}
}