{
  "type": "Feature",
  "properties": {
    "iso:country":"US",
    "sg:address":"2441 Production Dr",
    "sg:city":"Indianapolis",
    "sg:classifiers":[
        {
            "category":"Freight",
            "type":"Transportation"
        }
    ],
    "sg:phone":"+1 317 241 1012",
    "sg:postcode":"46241",
    "sg:province":"IN",
    "sg:tags":[
        "broker",
        "customs"
    ],
    "wof:name":"Dynasty International",
    "wof:placetype":"venue"
},
  "geometry": {"coordinates":[-86.258557,39.731862],"type":"Point"}
}