{
  "type": "Feature",
  "properties": {
    "iso:country":"US",
    "sg:address":"9555 E 206th St",
    "sg:city":"Noblesville",
    "sg:classifiers":[
        {
            "category":"Farming",
            "subcategory":"Nursery",
            "type":"Manufacturing & Wholesale Goods"
        }
    ],
    "sg:phone":"+1 317 773 1214",
    "sg:postcode":"46060",
    "sg:province":"IN",
    "sg:tags":[
        "greenhouse"
    ],
    "wof:name":"Gatewood Vegetable Farms",
    "wof:placetype":"venue"
},
  "geometry": {"coordinates":[-86.00022,40.087323],"type":"Point"}
}