{
  "type": "Feature",
  "properties": {
    "iso:country":"US",
    "sg:address":"2855 S 100 W",
    "sg:city":"Fowler",
    "sg:classifiers":[
        {
            "category":"Real Estate",
            "subcategory":"Real Estate Operator",
            "type":"Services"
        }
    ],
    "sg:phone":"+1 765 884 1432",
    "sg:postcode":"47944",
    "sg:province":"IN",
    "sg:tags":[
        "property",
        "lessor"
    ],
    "wof:name":"Donald Garing",
    "wof:placetype":"venue"
},
  "geometry": {"coordinates":[-87.342343,40.565695],"type":"Point"}
}