{
  "type": "Feature",
  "properties": {
    "addr:full":"1700 Riverfork Dr Huntington IN 46750",
    "addr:housenumber":"1700",
    "addr:postcode":"46750",
    "addr:street":"Riverfork Dr",
    "iso:country":"US",
    "sg:address":"1700 Riverfork Dr",
    "sg:city":"Huntington",
    "sg:classifiers":[
        {
            "category":"Autos & Motor Vehicles",
            "subcategory":"Automobile Sales",
            "type":"Retail Goods"
        }
    ],
    "sg:phone":"+1 260 454 0088",
    "sg:postcode":"46750",
    "sg:province":"IN",
    "sg:tags":[
        "truck"
    ],
    "wof:name":"L & E Truck Repair",
    "wof:placetype":"venue"
},
  "geometry": {"coordinates":[-85.524219,40.866484],"type":"Point"}
}