{
  "type": "Feature",
  "properties": {
    "iso:country":"US",
    "sg:address":"702 N River Dr",
    "sg:city":"Marion",
    "sg:classifiers":[
        {
            "category":"Health Services",
            "subcategory":"Doctor",
            "type":"Services"
        }
    ],
    "sg:phone":"+1 765 664 1076",
    "sg:postcode":"46952",
    "sg:province":"IN",
    "sg:tags":[
        "dentist"
    ],
    "wof:name":"Marion Oral & Maxillofacial",
    "wof:placetype":"venue"
},
  "geometry": {"coordinates":[-85.660318,40.576234],"type":"Point"}
}