{
  "type": "Feature",
  "properties": {
    "addr:full":"9129 Crestwood Ct Munster IN 46321",
    "addr:housenumber":"9129",
    "addr:postcode":"46321",
    "addr:street":"Crestwood Ct",
    "iso:country":"US",
    "sg:address":"9129 Crestwood Ct",
    "sg:city":"Munster",
    "sg:classifiers":[
        {
            "category":"Wholesale",
            "subcategory":"Farm Supplies",
            "type":"Manufacturing & Wholesale Goods"
        }
    ],
    "sg:phone":"+1 219 923 5744",
    "sg:postcode":"46321",
    "sg:province":"IN",
    "sg:tags":[
        "livestock"
    ],
    "wof:name":"South Chicago Livestock",
    "wof:placetype":"venue"
},
  "geometry": {"coordinates":[-87.482972,41.547524],"type":"Point"}
}