{
  "type": "Feature",
  "properties": {
    "iso:country":"US",
    "sg:address":"5631 S State Rd 9",
    "sg:city":"Columbia City",
    "sg:classifiers":[
        {
            "category":"Building & Trades",
            "subcategory":"Construction",
            "type":"Services"
        }
    ],
    "sg:phone":"+1 260 396 2232",
    "sg:postcode":"46725",
    "sg:province":"IN",
    "sg:tags":[
        "road",
        "contractor"
    ],
    "wof:name":"Highway Dept",
    "wof:placetype":"venue"
},
  "geometry": {"coordinates":[-85.470045,41.080547],"type":"Point"}
}