{
  "type": "Feature",
  "properties": {
    "iso:country":"US",
    "sg:address":"366 W Deerfield Rd",
    "sg:city":"Union City",
    "sg:classifiers":[
        {
            "category":"Shopping",
            "subcategory":"Pharmacy",
            "type":"Retail Goods"
        }
    ],
    "sg:phone":"+1 765 964 7666",
    "sg:postcode":"47390",
    "sg:province":"IN",
    "wof:name":"Rite Aid Pharmacy",
    "wof:placetype":"venue"
},
  "geometry": {"coordinates":[-84.808233,40.210043],"type":"Point"}
}