{
  "type": "Feature",
  "properties": {
    "iso:country":"US",
    "sg:address":"1310 NW 5th St",
    "sg:city":"Richmond",
    "sg:classifiers":[
        {
            "category":"Manufacturing",
            "subcategory":"Printing",
            "type":"Manufacturing & Wholesale Goods"
        }
    ],
    "sg:phone":"+1 765 962 7674",
    "sg:postcode":"47374",
    "sg:province":"IN",
    "sg:tags":[
        "printer"
    ],
    "wof:name":"Bill's Printing",
    "wof:placetype":"venue"
},
  "geometry": {"coordinates":[-84.907979,39.845463],"type":"Point"}
}