{
  "type": "Feature",
  "properties": {
    "iso:country":"US",
    "sg:address":"6237 N Holly Dr",
    "sg:city":"Ellettsville",
    "sg:classifiers":[
        {
            "category":"Building & Trades",
            "subcategory":"Construction",
            "type":"Services"
        }
    ],
    "sg:phone":"+1 812 325 2402",
    "sg:postcode":"47429",
    "sg:province":"IN",
    "sg:tags":[
        "repairing",
        "remodeling",
        "contractor"
    ],
    "wof:name":"Allen Gosney Construction",
    "wof:placetype":"venue"
},
  "geometry": {"coordinates":[-86.605086,39.238255],"type":"Point"}
}