{
  "type": "Feature",
  "properties": {
    "addr:full":"202 Lincoln Way E Mishawaka IN 46544",
    "addr:housenumber":"202",
    "addr:postcode":"46544",
    "addr:street":"Lincoln Way E",
    "iso:country":"US",
    "sg:address":"202 Lincoln Way E",
    "sg:city":"Mishawaka",
    "sg:classifiers":[
        {
            "category":"Banks & Credit Unions",
            "subcategory":"Bank",
            "type":"Services"
        }
    ],
    "sg:phone":"+1 574 256 6113",
    "sg:postcode":"46544",
    "sg:province":"IN",
    "sg:website":"www.nationalcity.com",
    "wof:name":"National City Bank",
    "wof:placetype":"venue"
},
  "geometry": {"coordinates":[-86.177976,41.661196],"type":"Point"}
}