{
  "type": "Feature",
  "properties": {
    "iso:country":"US",
    "sg:address":"7715 Sunny Ln",
    "sg:city":"Fort Wayne",
    "sg:classifiers":[
        {
            "category":"Organizations",
            "subcategory":"Religious Organization",
            "type":"Services"
        }
    ],
    "sg:phone":"+1 260 485 5311",
    "sg:postcode":"46835",
    "sg:province":"IN",
    "sg:tags":[
        "church"
    ],
    "wof:name":"Bethany United Methodist Chr",
    "wof:placetype":"venue"
},
  "geometry": {"coordinates":[-85.07193599999999,41.152691],"type":"Point"}
}