{
  "type": "Feature",
  "properties": {
    "iso:country":"US",
    "sg:address":"2331 Main St",
    "sg:city":"Huntertown",
    "sg:classifiers":[
        {
            "category":"Building & Trades",
            "subcategory":"Construction",
            "type":"Services"
        }
    ],
    "sg:phone":"+1 260 637 8523",
    "sg:postcode":"46748",
    "sg:province":"IN",
    "sg:tags":[
        "insulation",
        "heat",
        "contractor"
    ],
    "wof:name":"N U Insulation Inc",
    "wof:placetype":"venue"
},
  "geometry": {"coordinates":[-85.17554,41.227046],"type":"Point"}
}