{
  "type": "Feature",
  "properties": {
    "iso:country":"US",
    "sg:address":"2120 E Co Rd 150 S",
    "sg:city":"Frankfort",
    "sg:classifiers":[
        {
            "category":"Arts & Performance",
            "subcategory":"Theater",
            "type":"Entertainment"
        }
    ],
    "sg:phone":"+1 765 659 1657",
    "sg:postcode":"46041",
    "sg:province":"IN",
    "wof:name":"Red Barn Summer Theatre",
    "wof:placetype":"venue"
},
  "geometry": {"coordinates":[-86.483124,40.264383],"type":"Point"}
}