{
  "type": "Feature",
  "properties": {
    "iso:country":"US",
    "sg:address":"2101 E Market St",
    "sg:city":"Logansport",
    "sg:classifiers":[
        {
            "category":"Building & Trades",
            "subcategory":"Construction",
            "type":"Services"
        }
    ],
    "sg:phone":"+1 574 721 4858",
    "sg:postcode":"46947",
    "sg:province":"IN",
    "sg:tags":[
        "general",
        "contractor"
    ],
    "wof:name":"Dirty Deeds",
    "wof:placetype":"venue"
},
  "geometry": {"coordinates":[-86.340277,40.75723],"type":"Point"}
}