{
  "type": "Feature",
  "properties": {
    "iso:country":"US",
    "sg:address":"3424 Plantation Trl",
    "sg:city":"Fort Wayne",
    "sg:classifiers":[
        {
            "category":"Personal",
            "type":"Services"
        }
    ],
    "sg:phone":"+1 260 489 4536",
    "sg:postcode":"46818",
    "sg:province":"IN",
    "sg:tags":[
        "consultant",
        "program",
        "health",
        "fitness"
    ],
    "wof:name":"Health Beats Education Inc",
    "wof:placetype":"venue"
},
  "geometry": {"coordinates":[-85.187383,41.157853],"type":"Point"}
}