{
  "type": "Feature",
  "properties": {
    "iso:country":"US",
    "sg:address":"6740 Broadway",
    "sg:city":"Merrillville",
    "sg:classifiers":[
        {
            "category":"Restaurant",
            "type":"Food & Drink"
        }
    ],
    "sg:phone":"+1 219 736 0620",
    "sg:postcode":"46410",
    "sg:province":"IN",
    "wof:name":"Central Gyros",
    "wof:placetype":"venue"
},
  "geometry": {"coordinates":[-87.336111,41.493565],"type":"Point"}
}