{
  "type": "Feature",
  "properties": {
    "addr:full":"2240 W 175 N Lagrange IN 46761",
    "addr:housenumber":"2240",
    "addr:postcode":"46761",
    "addr:street":"W 175 N",
    "iso:country":"US",
    "sg:address":"2240 W 175 N",
    "sg:city":"Lagrange",
    "sg:classifiers":[
        {
            "category":"Retail",
            "subcategory":"Repair Shop",
            "type":"Services"
        }
    ],
    "sg:phone":"+1 260 499 3280",
    "sg:postcode":"46761",
    "sg:province":"IN",
    "sg:tags":[
        "farm",
        "equipment",
        "parts"
    ],
    "wof:name":"E & S Wood Creations",
    "wof:placetype":"venue"
},
  "geometry": {"coordinates":[-85.469559,41.666192],"type":"Point"}
}