{
  "type": "Feature",
  "properties": {
    "iso:country":"US",
    "sg:address":"426 N Lake St",
    "sg:city":"Warsaw",
    "sg:classifiers":[
        {
            "category":"Shopping",
            "subcategory":"Clothing, Apparel, & Fashions",
            "type":"Retail Goods"
        }
    ],
    "sg:phone":"+1 574 269 1764",
    "sg:postcode":"46580",
    "sg:province":"IN",
    "sg:tags":[
        "alteration"
    ],
    "wof:name":"Luan's Sew Special",
    "wof:placetype":"venue"
},
  "geometry": {"coordinates":[-85.859095,41.241999],"type":"Point"}
}