{
  "type": "Feature",
  "properties": {
    "addr:full":"19226 Co Rd 146 New Paris IN 46553",
    "addr:housenumber":"19226;146",
    "addr:postcode":"in 46553",
    "addr:street":"Co Rd",
    "iso:country":"US",
    "sg:address":"19226 Co Rd 146",
    "sg:city":"New Paris",
    "sg:classifiers":[
        {
            "category":"Freight",
            "type":"Transportation"
        }
    ],
    "sg:phone":"+1 574 831 4120",
    "sg:postcode":"46553",
    "sg:province":"IN",
    "sg:tags":[
        "warehouse",
        "self",
        "storage"
    ],
    "wof:name":"Ripco Limited Inc",
    "wof:placetype":"venue"
},
  "geometry": {"coordinates":[-85.834087,41.493099],"type":"Point"}
}