{
  "type": "Feature",
  "properties": {
    "addr:full":"1241 Cumberland Ave West Lafayette IN 47906",
    "addr:housenumber":"1241",
    "addr:postcode":"47906",
    "addr:street":"Cumberland Ave",
    "iso:country":"US",
    "sg:address":"1241 Cumberland Ave",
    "sg:city":"West Lafayette",
    "sg:classifiers":[
        {
            "category":"Insurance",
            "subcategory":"Life Insurance",
            "type":"Services"
        }
    ],
    "sg:phone":"+1 765 463 4587",
    "sg:postcode":"47906",
    "sg:province":"IN",
    "wof:name":"R E Moulton Inc",
    "wof:placetype":"venue"
},
  "geometry": {"coordinates":[-86.92587,40.460636],"type":"Point"}
}