{
  "type": "Feature",
  "properties": {
    "iso:country":"US",
    "sg:address":"4301 E Market St",
    "sg:city":"Logansport",
    "sg:classifiers":[
        {
            "category":"Autos & Motor Vehicles",
            "subcategory":"Automobile Sales",
            "type":"Retail Goods"
        }
    ],
    "sg:phone":"+1 574 753 6285",
    "sg:postcode":"46947",
    "sg:province":"IN",
    "sg:tags":[
        "car",
        "dealer"
    ],
    "wof:name":"Mike Anderson Pontiac-Olds-GMC",
    "wof:placetype":"venue"
},
  "geometry": {"coordinates":[-86.327473,40.757956],"type":"Point"}
}