{
  "type": "Feature",
  "properties": {
    "iso:country":"US",
    "sg:address":"1502 Bluffton Rd",
    "sg:city":"Fort Wayne",
    "sg:classifiers":[
        {
            "category":"Restaurant",
            "type":"Food & Drink"
        }
    ],
    "sg:phone":"+1 260 747 7509",
    "sg:postcode":"46809",
    "sg:province":"IN",
    "sg:website":"www.donhalls.com",
    "wof:name":"Original Drive In",
    "wof:placetype":"venue"
},
  "geometry": {"coordinates":[-85.164241,41.049936],"type":"Point"}
}