{
  "type": "Feature",
  "properties": {
    "addr:full":"829 E Calvert St South Bend IN 46613",
    "addr:housenumber":"829",
    "addr:postcode":"46613",
    "addr:street":"E Calvert St",
    "iso:country":"US",
    "sg:address":"829 E Calvert St",
    "sg:city":"South Bend",
    "sg:classifiers":[
        {
            "category":"Organizations",
            "subcategory":"Religious Organization",
            "type":"Services"
        }
    ],
    "sg:phone":"+1 574 287 1700",
    "sg:postcode":"46613",
    "sg:province":"IN",
    "sg:tags":[
        "church"
    ],
    "sg:website":"www.ourladyofhungary.com",
    "wof:name":"Our Lady Of Hungary",
    "wof:placetype":"venue"
},
  "geometry": {"coordinates":[-86.238175,41.654643],"type":"Point"}
}