{
  "type": "Feature",
  "properties": {
    "iso:country":"US",
    "sg:address":"2001 Rembrandt St",
    "sg:city":"Indianapolis",
    "sg:classifiers":[
        {
            "category":"Building & Trades",
            "subcategory":"Construction",
            "type":"Services"
        }
    ],
    "sg:phone":"+1 317 632 3471",
    "sg:postcode":"46202",
    "sg:province":"IN",
    "sg:tags":[
        "tennis",
        "court"
    ],
    "wof:name":"Harris Barrier Corp",
    "wof:placetype":"venue"
},
  "geometry": {"coordinates":[-86.181857,39.794862],"type":"Point"}
}