{
  "type": "Feature",
  "properties": {
    "iso:country":"US",
    "sg:address":"730 W 1150 S",
    "sg:city":"Romney",
    "sg:classifiers":[
        {
            "category":"Wholesale",
            "subcategory":"Farm Supplies",
            "type":"Manufacturing & Wholesale Goods"
        }
    ],
    "sg:phone":"+1 765 538 2814",
    "sg:postcode":"47981",
    "sg:province":"IN",
    "sg:tags":[
        "grain"
    ],
    "wof:name":"Kokomo Grain Co Inc",
    "wof:placetype":"venue"
},
  "geometry": {"coordinates":[-86.927376,40.251341],"type":"Point"}
}