{
  "type": "Feature",
  "properties": {
    "iso:country":"US",
    "sg:address":"116 S Main St",
    "sg:city":"Tipton",
    "sg:classifiers":[
        {
            "category":"Manufacturing",
            "subcategory":"Printing",
            "type":"Manufacturing & Wholesale Goods"
        }
    ],
    "sg:phone":"+1 765 675 2115",
    "sg:postcode":"46072",
    "sg:province":"IN",
    "sg:tags":[
        "newspaper"
    ],
    "wof:name":"Tipton Tribune",
    "wof:placetype":"venue"
},
  "geometry": {"coordinates":[-86.041279,40.282028],"type":"Point"}
}