{
  "type": "Feature",
  "properties": {
    "addr:full":"8001 State Rd 60 Sellersburg IN 47172",
    "addr:housenumber":"8001;60",
    "addr:postcode":"47172",
    "addr:street":"State Rd",
    "iso:country":"US",
    "sg:address":"8001 State Rd 60",
    "sg:city":"Sellersburg",
    "sg:classifiers":[
        {
            "category":"Food & Beverages",
            "subcategory":"Groceries & Convenience Stores",
            "type":"Retail Goods"
        }
    ],
    "sg:phone":"+1 812 246 8077",
    "sg:postcode":"47172",
    "sg:province":"IN",
    "wof:name":"Sav-A-Step Food Mart Inc",
    "wof:placetype":"venue"
},
  "geometry": {"coordinates":[-85.76329800000001,38.385201],"type":"Point"}
}