{
  "type": "Feature",
  "properties": {
    "iso:country":"US",
    "sg:address":"230 Crestwood Ln",
    "sg:city":"Richmond",
    "sg:classifiers":[
        {
            "category":"Building & Trades",
            "subcategory":"Construction",
            "type":"Services"
        }
    ],
    "sg:phone":"+1 765 939 7833",
    "sg:postcode":"47374",
    "sg:province":"IN",
    "wof:name":"Scotts Sealing Service",
    "wof:placetype":"venue"
},
  "geometry": {"coordinates":[-84.953855,39.817399],"type":"Point"}
}