{
  "type": "Feature",
  "properties": {
    "addr:full":"5020 Southport Crossing Pl Indianapolis IN 46237",
    "addr:housenumber":"5020",
    "addr:postcode":"46237",
    "addr:street":"Southport Crossing Pl",
    "iso:country":"US",
    "sg:address":"5020 Southport Crossing Pl",
    "sg:city":"Indianapolis",
    "sg:phone":"+1 317 884 0968",
    "sg:postcode":"46237",
    "sg:province":"IN",
    "sg:website":"http://www.pandaexpress.com",
    "wof:name":"Panda Express",
    "wof:placetype":"venue"
},
  "geometry": {"coordinates":[-86.08342,39.66473],"type":"Point"}
}