{
  "type": "Feature",
  "properties": {
    "addr:full":"570 Sibley St Hammond IN 46320",
    "addr:housenumber":"570",
    "addr:postcode":"46320",
    "addr:street":"Sibley St",
    "iso:country":"US",
    "sg:address":"570 Sibley St",
    "sg:city":"Hammond",
    "sg:classifiers":[
        {
            "category":"Place Of Worship",
            "subcategory":"Church",
            "type":"Public Place"
        },
        {
            "category":"Place Of Worship",
            "type":"Public Place"
        }
    ],
    "sg:phone":"+1 219 932 0204",
    "sg:postcode":"46320",
    "sg:province":"IN",
    "sg:tags":[
        "churches-catholic-traditional",
        "churches-catholic"
    ],
    "wof:name":"All Saints Church",
    "wof:placetype":"venue"
},
  "geometry": {"coordinates":[-87.514375,41.616697],"type":"Point"}
}