{
  "type": "Feature",
  "properties": {
    "iso:country":"US",
    "sg:address":"11904 S US Hwy 41",
    "sg:city":"Terre Haute",
    "sg:classifiers":[
        {
            "category":"Home & Garden",
            "subcategory":"Building Materials",
            "type":"Retail Goods"
        }
    ],
    "sg:phone":"+1 812 299 3113",
    "sg:postcode":"47802",
    "sg:province":"IN",
    "sg:tags":[
        "modular"
    ],
    "sg:website":"www.boot.net",
    "wof:name":"USA Custom Homes LLC",
    "wof:placetype":"venue"
},
  "geometry": {"coordinates":[-87.388014,39.315231],"type":"Point"}
}