{
  "type": "Feature",
  "properties": {
    "iso:country":"US",
    "sg:address":"212 Brown St",
    "sg:city":"West Lafayette",
    "sg:classifiers":[
        {
            "category":"Restaurant",
            "type":"Food & Drink"
        }
    ],
    "sg:phone":"+1 765 743 1668",
    "sg:postcode":"47906",
    "sg:province":"IN",
    "wof:name":"Bruno's",
    "wof:placetype":"venue"
},
  "geometry": {"coordinates":[-86.90406,40.422178],"type":"Point"}
}