{
  "type": "Feature",
  "properties": {
    "addr:full":"505 N 4th St Richmond IN 47374",
    "addr:housenumber":"505",
    "addr:postcode":"47374",
    "addr:street":"N 4Th St",
    "iso:country":"US",
    "sg:address":"505 N 4th St",
    "sg:city":"Richmond",
    "sg:classifiers":[
        {
            "category":"Wholesale",
            "subcategory":"Farm Supplies",
            "type":"Manufacturing & Wholesale Goods"
        }
    ],
    "sg:phone":"+1 765 962 9561",
    "sg:postcode":"47374",
    "sg:province":"IN",
    "sg:tags":[
        "feed"
    ],
    "wof:name":"Land O'Lakes Purina Feed",
    "wof:placetype":"venue"
},
  "geometry": {"coordinates":[-84.896193,39.833612],"type":"Point"}
}