{
  "type": "Feature",
  "properties": {
    "addr:full":"3191 W 200 S Warsaw IN 46580",
    "addr:housenumber":"3191",
    "addr:postcode":"46580",
    "addr:street":"W 200 S Warsaw",
    "iso:country":"US",
    "sg:address":"3191 W 200 S",
    "sg:city":"Warsaw",
    "sg:classifiers":[
        {
            "category":"Organizations",
            "subcategory":"Religious Organization",
            "type":"Services"
        }
    ],
    "sg:phone":"+1 574 267 4594",
    "sg:postcode":"46580",
    "sg:province":"IN",
    "sg:tags":[
        "church"
    ],
    "wof:name":"Jehovah's Witnesses",
    "wof:placetype":"venue"
},
  "geometry": {"coordinates":[-85.903711,41.203976],"type":"Point"}
}