{
  "type": "Feature",
  "properties": {
    "iso:country":"US",
    "sg:address":"5555 S US Hwy 41",
    "sg:city":"Terre Haute",
    "sg:classifiers":[
        {
            "category":"Travel",
            "subcategory":"Travel Agent",
            "type":"Entertainment"
        }
    ],
    "sg:phone":"+1 812 299 4646",
    "sg:postcode":"47802",
    "sg:province":"IN",
    "sg:tags":[
        "agency",
        "bureau"
    ],
    "wof:name":"Travel Network",
    "wof:placetype":"venue"
},
  "geometry": {"coordinates":[-87.403234,39.401713],"type":"Point"}
}