{
  "type": "Feature",
  "properties": {
    "addr:full":"29 W Main St Jamestown IN 46147",
    "addr:housenumber":"29",
    "addr:postcode":"46147",
    "addr:street":"W Main St",
    "iso:country":"US",
    "sg:address":"29 W Main St",
    "sg:city":"Jamestown",
    "sg:classifiers":[
        {
            "category":"Restaurant",
            "type":"Food & Drink"
        }
    ],
    "sg:phone":"+1 765 676 6369",
    "sg:postcode":"46147",
    "sg:province":"IN",
    "sg:tags":[
        "caterer"
    ],
    "wof:name":"Cochran's Catering & Cakes",
    "wof:placetype":"venue"
},
  "geometry": {"coordinates":[-86.62903900000001,39.92652],"type":"Point"}
}