{
  "type": "Feature",
  "properties": {
    "iso:country":"US",
    "sg:address":"8217 E Co Rd 200 S",
    "sg:city":"New Point",
    "sg:classifiers":[
        {
            "category":"Government",
            "subcategory":"Office",
            "type":"Public Place"
        }
    ],
    "sg:phone":"+1 812 663 7905",
    "sg:postcode":"47263",
    "sg:province":"IN",
    "sg:tags":[
        "village"
    ],
    "wof:name":"Town Of New Point",
    "wof:placetype":"venue"
},
  "geometry": {"coordinates":[-85.333201,39.309349],"type":"Point"}
}