{
  "type": "Feature",
  "properties": {
    "iso:country":"US",
    "sg:address":"403 W 8th St",
    "sg:city":"Anderson",
    "sg:classifiers":[
        {
            "category":"Professional",
            "subcategory":"Management & Consulting",
            "type":"Services"
        }
    ],
    "sg:phone":"+1 765 649 4684",
    "sg:postcode":"46016",
    "sg:province":"IN",
    "sg:tags":[
        "consultant"
    ],
    "wof:name":"Criminal Justice",
    "wof:placetype":"venue"
},
  "geometry": {"coordinates":[-85.685857,40.107809],"type":"Point"}
}