{
  "type": "Feature",
  "properties": {
    "addr:full":"929 E Main St Richmond IN 47374",
    "addr:housenumber":"929",
    "addr:postcode":"47374",
    "addr:street":"E Main St",
    "iso:country":"US",
    "sg:address":"929 E Main St",
    "sg:city":"Richmond",
    "sg:classifiers":[
        {
            "category":"Professional",
            "subcategory":"Employment Agencies",
            "type":"Services"
        }
    ],
    "sg:phone":"+1 765 939 6300",
    "sg:postcode":"47374",
    "sg:province":"IN",
    "sg:tags":[
        "opportunity"
    ],
    "wof:name":"Adecco",
    "wof:placetype":"venue"
},
  "geometry": {"coordinates":[-84.88936,39.828982],"type":"Point"}
}