{
  "type": "Feature",
  "properties": {
    "addr:full":"40 Bryants Creek Dr Patriot IN 47038",
    "addr:housenumber":"40",
    "addr:postcode":"patriot;47038",
    "addr:street":"Bryants Creek Dr",
    "iso:country":"US",
    "sg:address":"40 Bryants Creek Dr",
    "sg:city":"Patriot",
    "sg:classifiers":[
        {
            "category":"Government",
            "subcategory":"Office",
            "type":"Public Place"
        }
    ],
    "sg:phone":"+1 812 594 9913",
    "sg:postcode":"47038",
    "sg:province":"IN",
    "sg:tags":[
        "executive"
    ],
    "wof:name":"Posey Township Trustee",
    "wof:placetype":"venue"
},
  "geometry": {"coordinates":[-84.863428,38.822688],"type":"Point"}
}