{
  "type": "Feature",
  "properties": {
    "iso:country":"US",
    "sg:address":"715 W 21st St",
    "sg:city":"Connersville",
    "sg:classifiers":[
        {
            "category":"Social Services",
            "subcategory":"Adult Care",
            "type":"Services"
        }
    ],
    "sg:phone":"+1 765 827 1502",
    "sg:postcode":"47331",
    "sg:province":"IN",
    "sg:tags":[
        "organization",
        "senior",
        "citizen"
    ],
    "wof:name":"Area 9 Agency On Aging",
    "wof:placetype":"venue"
},
  "geometry": {"coordinates":[-85.138966,39.658943],"type":"Point"}
}