{
  "type": "Feature",
  "properties": {
    "iso:country":"US",
    "sg:address":"9803 Redbud Rd",
    "sg:city":"Munster",
    "sg:classifiers":[
        {
            "category":"Professional",
            "subcategory":"Accounting & Tax Preparation",
            "type":"Services"
        }
    ],
    "sg:phone":"+1 219 922 6212",
    "sg:postcode":"46321",
    "sg:province":"IN",
    "sg:tags":[
        "billing"
    ],
    "wof:name":"Cornerstone Creative Solutions",
    "wof:placetype":"venue"
},
  "geometry": {"coordinates":[-87.499393,41.534733],"type":"Point"}
}