{
  "type": "Feature",
  "properties": {
    "addr:full":"422 S Detroit St Warsaw IN 46580",
    "addr:housenumber":"422",
    "addr:postcode":"46580",
    "addr:street":"S Detroit St",
    "iso:country":"US",
    "sg:address":"422 S Detroit St",
    "sg:city":"Warsaw",
    "sg:classifiers":[
        {
            "category":"Building & Trades",
            "subcategory":"Construction",
            "type":"Services"
        }
    ],
    "sg:phone":"+1 574 267 8928",
    "sg:postcode":"46580",
    "sg:province":"IN",
    "sg:tags":[
        "dry wall",
        "contractor"
    ],
    "wof:name":"Divine Drywall & Paint",
    "wof:placetype":"venue"
},
  "geometry": {"coordinates":[-85.852897,41.234931],"type":"Point"}
}