{
  "type": "Feature",
  "properties": {
    "iso:country":"US",
    "sg:address":"5346 W 79th St",
    "sg:city":"Indianapolis",
    "sg:classifiers":[
        {
            "category":"Personal",
            "type":"Services"
        }
    ],
    "sg:phone":"+1 317 872 6750",
    "sg:postcode":"46268",
    "sg:province":"IN",
    "sg:tags":[
        "consultant",
        "program",
        "health",
        "fitness"
    ],
    "wof:name":"Corpfit Inc",
    "wof:placetype":"venue"
},
  "geometry": {"coordinates":[-86.255405,39.896382],"type":"Point"}
}