{
  "type": "Feature",
  "properties": {
    "iso:country":"US",
    "sg:address":"9497 W State Rd 120",
    "sg:city":"Orland",
    "sg:classifiers":[
        {
            "category":"Retail",
            "subcategory":"Auto Repair",
            "type":"Services"
        }
    ],
    "sg:phone":"+1 260 829 6287",
    "sg:postcode":"46776",
    "sg:province":"IN",
    "sg:tags":[
        "wrecker"
    ],
    "wof:name":"Bill's Professional Towing",
    "wof:placetype":"venue"
},
  "geometry": {"coordinates":[-85.171213,41.730566],"type":"Point"}
}