{
  "type": "Feature",
  "properties": {
    "addr:full":"700 E Walnut St Evansville IN 47713",
    "addr:housenumber":"700",
    "addr:postcode":"47713",
    "addr:street":"E Walnut St",
    "iso:country":"US",
    "sg:address":"700 E Walnut St",
    "sg:city":"Evansville",
    "sg:classifiers":[
        {
            "category":"Professional",
            "subcategory":"Employment Agencies",
            "type":"Services"
        }
    ],
    "sg:phone":"+1 812 424 4473",
    "sg:postcode":"47713",
    "sg:province":"IN",
    "sg:tags":[
        "opportunity"
    ],
    "sg:website":"www.workoneevansville.com",
    "wof:name":"Workone Evansville",
    "wof:placetype":"venue"
},
  "geometry": {"coordinates":[-87.554514,37.973616],"type":"Point"}
}