{
  "type": "Feature",
  "properties": {
    "addr:full":"21 Gostlin St Hammond IN 46327",
    "addr:housenumber":"21",
    "addr:postcode":"46327",
    "addr:street":"Gostlin St",
    "iso:country":"US",
    "sg:address":"21 Gostlin St",
    "sg:city":"Hammond",
    "sg:classifiers":[
        {
            "category":"Autos & Motor Vehicles",
            "subcategory":"Fuel & Gas Station",
            "type":"Retail Goods"
        }
    ],
    "sg:phone":"+1 219 937 6547",
    "sg:postcode":"46327",
    "sg:province":"IN",
    "sg:tags":[
        "oil"
    ],
    "wof:name":"Ridgeway IV",
    "wof:placetype":"venue"
},
  "geometry": {"coordinates":[-87.524863,41.632873],"type":"Point"}
}