{
  "type": "Feature",
  "properties": {
    "iso:country":"US",
    "sg:address":"800 W McGalliard Rd",
    "sg:city":"Muncie",
    "sg:classifiers":[
        {
            "category":"Shopping",
            "subcategory":"Florist",
            "type":"Retail Goods"
        }
    ],
    "sg:phone":"+1 765 747 4013",
    "sg:postcode":"47303",
    "sg:province":"IN",
    "wof:name":"Annie's Arbor Flowers & Gifts",
    "wof:placetype":"venue"
},
  "geometry": {"coordinates":[-85.395962,40.218956],"type":"Point"}
}