{
  "type": "Feature",
  "properties": {
    "addr:full":"200 Maine St Walkerton IN 46574",
    "addr:housenumber":"200",
    "addr:postcode":"46574",
    "addr:street":"Maine St",
    "iso:country":"US",
    "sg:address":"200 Maine St",
    "sg:city":"Walkerton",
    "sg:classifiers":[
        {
            "category":"Organizations",
            "subcategory":"Religious Organization",
            "type":"Services"
        }
    ],
    "sg:phone":"+1 574 586 3753",
    "sg:postcode":"46574",
    "sg:province":"IN",
    "sg:tags":[
        "church"
    ],
    "wof:name":"First Baptist Church",
    "wof:placetype":"venue"
},
  "geometry": {"coordinates":[-86.48475500000001,41.461559],"type":"Point"}
}