{
  "type": "Feature",
  "properties": {
    "iso:country":"US",
    "sg:address":"601 N 2nd St",
    "sg:city":"Vincennes",
    "sg:classifiers":[
        {
            "category":"Shopping",
            "type":"Retail Goods"
        }
    ],
    "sg:phone":"+1 812 882 4715",
    "sg:postcode":"47591",
    "sg:province":"IN",
    "sg:tags":[
        "hearing",
        "equipment",
        "supply",
        "impaired"
    ],
    "wof:name":"Beltone Hearing Aid Ctr",
    "wof:placetype":"venue"
},
  "geometry": {"coordinates":[-87.52571399999999,38.683434],"type":"Point"}
}