{
  "type": "Feature",
  "properties": {
    "iso:country":"US",
    "sg:address":"125 N Monroe St",
    "sg:city":"Williamsport",
    "sg:classifiers":[
        {
            "category":"Government",
            "subcategory":"Court House",
            "type":"Public Place"
        }
    ],
    "sg:phone":"+1 765 762 2720",
    "sg:postcode":"47993",
    "sg:province":"IN",
    "sg:tags":[
        "county"
    ],
    "wof:name":"Court House Maintenance",
    "wof:placetype":"venue"
},
  "geometry": {"coordinates":[-87.294178,40.287871],"type":"Point"}
}