{
  "type": "Feature",
  "properties": {
    "addr:full":"147 S Franklin St Knightstown IN 46148",
    "addr:housenumber":"147",
    "addr:postcode":"46148",
    "addr:street":"S Franklin St",
    "iso:country":"US",
    "sg:address":"147 S Franklin St",
    "sg:city":"Knightstown",
    "sg:classifiers":[
        {
            "category":"Building & Trades",
            "subcategory":"Plumbing",
            "type":"Services"
        }
    ],
    "sg:phone":"+1 765 345 5903",
    "sg:postcode":"46148",
    "sg:province":"IN",
    "sg:tags":[
        "contractor"
    ],
    "wof:name":"Kiser Plumbing & Heating",
    "wof:placetype":"venue"
},
  "geometry": {"coordinates":[-85.52718900000001,39.79366],"type":"Point"}
}