{
  "type": "Feature",
  "properties": {
    "iso:country":"US",
    "sg:address":"119 N Main St",
    "sg:city":"Wolcottville",
    "sg:classifiers":[
        {
            "category":"Shopping",
            "subcategory":"Jewelry",
            "type":"Retail Goods"
        }
    ],
    "sg:phone":"+1 260 854 4000",
    "sg:postcode":"46795",
    "sg:province":"IN",
    "sg:tags":[
        "jeweler"
    ],
    "wof:name":"J Klingler Jewelers",
    "wof:placetype":"venue"
},
  "geometry": {"coordinates":[-85.36657,41.527247],"type":"Point"}
}