{
  "type": "Feature",
  "properties": {
    "iso:country":"US",
    "sg:address":"907 N Nappanee St",
    "sg:city":"Elkhart",
    "sg:classifiers":[
        {
            "category":"Autos & Motor Vehicles",
            "subcategory":"Automobile Sales",
            "type":"Retail Goods"
        }
    ],
    "sg:phone":"+1 574 266 6777",
    "sg:postcode":"46514",
    "sg:province":"IN",
    "sg:tags":[
        "car",
        "dealer"
    ],
    "wof:name":"Michael's Motors",
    "wof:placetype":"venue"
},
  "geometry": {"coordinates":[-86.003553,41.695385],"type":"Point"}
}