{
  "type": "Feature",
  "properties": {
    "iso:country":"US",
    "sg:address":"212 S Indiana Ave",
    "sg:city":"Bloomington",
    "sg:classifiers":[
        {
            "category":"Restaurant",
            "type":"Food & Drink"
        }
    ],
    "sg:phone":"+1 812 333 7366",
    "sg:postcode":"47408",
    "sg:province":"IN",
    "wof:name":"Penn Station East Coast Subs",
    "wof:placetype":"venue"
},
  "geometry": {"coordinates":[-86.527,39.1651],"type":"Point"}
}