{
  "type": "Feature",
  "properties": {
    "iso:country":"US",
    "sg:address":"5077 S 500 E",
    "sg:city":"Oxford",
    "sg:classifiers":[
        {
            "category":"Wholesale",
            "subcategory":"Farm Supplies",
            "type":"Manufacturing & Wholesale Goods"
        }
    ],
    "sg:phone":"+1 765 385 5181",
    "sg:postcode":"47971",
    "sg:province":"IN",
    "sg:tags":[
        "fertilizer"
    ],
    "wof:name":"A G Gobel Svc",
    "wof:placetype":"venue"
},
  "geometry": {"coordinates":[-87.227042,40.532353],"type":"Point"}
}