{
  "type": "Feature",
  "properties": {
    "iso:country":"US",
    "sg:address":"6354 Central Ave",
    "sg:city":"Portage",
    "sg:classifiers":[
        {
            "category":"Personal",
            "subcategory":"Beauty Salon",
            "type":"Services"
        }
    ],
    "sg:phone":"+1 219 764 2600",
    "sg:postcode":"46368",
    "sg:province":"IN",
    "wof:name":"Salon Lydia",
    "wof:placetype":"venue"
},
  "geometry": {"coordinates":[-87.171757,41.575973],"type":"Point"}
}