{
  "type": "Feature",
  "properties": {
    "iso:country":"US",
    "sg:address":"806 Vera Ave",
    "sg:city":"Beverly Shores",
    "sg:classifiers":[
        {
            "category":"Wholesale",
            "subcategory":"Electrical",
            "type":"Manufacturing & Wholesale Goods"
        }
    ],
    "sg:phone":"+1 219 872 5003",
    "sg:postcode":"46301",
    "sg:province":"IN",
    "sg:tags":[
        "alarm",
        "burglar",
        "system"
    ],
    "wof:name":"Liberty Alarm Co",
    "wof:placetype":"venue"
},
  "geometry": {"coordinates":[-86.962328,41.695483],"type":"Point"}
}