{
  "type": "Feature",
  "properties": {
    "iso:country":"US",
    "sg:address":"27 Pasco Ave",
    "sg:city":"Evansville",
    "sg:classifiers":[
        {
            "category":"Professional",
            "subcategory":"Business Services",
            "type":"Services"
        }
    ],
    "sg:phone":"+1 812 425 2504",
    "sg:postcode":"47713",
    "sg:province":"IN",
    "sg:tags":[
        "paging",
        "answering"
    ],
    "wof:name":"Cape Ida Message Ctr",
    "wof:placetype":"venue"
},
  "geometry": {"coordinates":[-87.56349299999999,37.975323],"type":"Point"}
}