{
  "type": "Feature",
  "properties": {
    "iso:country":"US",
    "sg:address":"8122 Shore Dr",
    "sg:city":"Newburgh",
    "sg:classifiers":[
        {
            "category":"Shopping",
            "subcategory":"Hobbies, Toys, & Games",
            "type":"Retail Goods"
        }
    ],
    "sg:phone":"+1 812 858 1184",
    "sg:postcode":"47630",
    "sg:province":"IN",
    "wof:name":"Discovery Toys",
    "wof:placetype":"venue"
},
  "geometry": {"coordinates":[-87.398591,37.955428],"type":"Point"}
}