{
  "type": "Feature",
  "properties": {
    "iso:country":"US",
    "sg:address":"10137 N State Rd 13",
    "sg:city":"Syracuse",
    "sg:classifiers":[
        {
            "category":"Shopping",
            "subcategory":"Computers & Home Electronics",
            "type":"Retail Goods"
        }
    ],
    "sg:phone":"+1 574 457 2244",
    "sg:postcode":"46567",
    "sg:province":"IN",
    "sg:tags":[
        "antenna"
    ],
    "wof:name":"Frost TV & Antenna Svc",
    "wof:placetype":"venue"
},
  "geometry": {"coordinates":[-85.701669,41.382645],"type":"Point"}
}