{
  "type": "Feature",
  "properties": {
    "iso:country":"US",
    "sg:address":"1729 Orkney Ln",
    "sg:city":"New Haven",
    "sg:classifiers":[
        {
            "category":"Restaurant",
            "type":"Food & Drink"
        }
    ],
    "sg:phone":"+1 260 493 8088",
    "sg:postcode":"46774",
    "sg:province":"IN",
    "sg:tags":[
        "eating"
    ],
    "wof:name":"Golden Gate Chinese Restaurant",
    "wof:placetype":"venue"
},
  "geometry": {"coordinates":[-85.00682,41.056838],"type":"Point"}
}