{
  "type": "Feature",
  "properties": {
    "iso:country":"US",
    "sg:address":"5105 Plaza Ave",
    "sg:city":"Portage",
    "sg:classifiers":[
        {
            "category":"Autos & Motor Vehicles",
            "subcategory":"Fuel & Gas Station",
            "type":"Retail Goods"
        }
    ],
    "sg:phone":"+1 219 762 8380",
    "sg:postcode":"46368",
    "sg:province":"IN",
    "sg:tags":[
        "oil"
    ],
    "wof:name":"BP",
    "wof:placetype":"venue"
},
  "geometry": {"coordinates":[-87.215448,41.585195],"type":"Point"}
}