{
  "type": "Feature",
  "properties": {
    "iso:country":"US",
    "sg:address":"503 N Washington St",
    "sg:city":"Huntingburg",
    "sg:classifiers":[
        {
            "category":"Professional",
            "subcategory":"Accounting & Tax Preparation",
            "type":"Services"
        }
    ],
    "sg:phone":"+1 812 683 3040",
    "sg:postcode":"47542",
    "sg:province":"IN",
    "sg:tags":[
        "return",
        "filing"
    ],
    "wof:name":"Urban O Blessinger Income Tax",
    "wof:placetype":"venue"
},
  "geometry": {"coordinates":[-86.949849,38.297635],"type":"Point"}
}