{
  "type": "Feature",
  "properties": {
    "iso:country":"US",
    "sg:address":"7229 W 25th Ave",
    "sg:city":"Gary",
    "sg:classifiers":[
        {
            "category":"Organizations",
            "subcategory":"Community Association",
            "type":"Services"
        }
    ],
    "sg:phone":"+1 219 845 5267",
    "sg:postcode":"46406",
    "sg:province":"IN",
    "wof:name":"Foe 2593",
    "wof:placetype":"venue"
},
  "geometry": {"coordinates":[-87.43086700000001,41.573516],"type":"Point"}
}