{
  "type": "Feature",
  "properties": {
    "addr:full":"5515 Salem Dr S Carmel IN 46033",
    "addr:housenumber":"5515",
    "addr:postcode":"46033",
    "addr:street":"Salem Dr S",
    "iso:country":"US",
    "sg:address":"5515 Salem Dr S",
    "sg:city":"Carmel",
    "sg:classifiers":[
        {
            "category":"Banks & Credit Unions",
            "subcategory":"Investment Brokerage",
            "type":"Services"
        }
    ],
    "sg:phone":"+1 317 566 8180",
    "sg:postcode":"46033",
    "sg:province":"IN",
    "sg:tags":[
        "advisory",
        "financial"
    ],
    "wof:name":"Dehnke Financial Group",
    "wof:placetype":"venue"
},
  "geometry": {"coordinates":[-86.073981,39.993401],"type":"Point"}
}