{
  "type": "Feature",
  "properties": {
    "iso:country":"US",
    "sg:address":"14611 W Commerce Rd",
    "sg:city":"Daleville",
    "sg:classifiers":[
        {
            "category":"Retail",
            "subcategory":"Auto Repair",
            "type":"Services"
        }
    ],
    "sg:phone":"+1 765 378 7691",
    "sg:postcode":"47334",
    "sg:province":"IN",
    "sg:tags":[
        "truck"
    ],
    "wof:name":"Clerk Detroit Diesel Allison",
    "wof:placetype":"venue"
},
  "geometry": {"coordinates":[-85.558179,40.113415],"type":"Point"}
}