{
  "type": "Feature",
  "properties": {
    "addr:full":"1645 S 25th St Terre Haute IN 47803",
    "addr:housenumber":"1645",
    "addr:postcode":"47803",
    "addr:street":"S 25Th St",
    "iso:country":"US",
    "sg:address":"1645 S 25th St",
    "sg:city":"Terre Haute",
    "sg:classifiers":[
        {
            "category":"Personal",
            "subcategory":"Beauty Salon",
            "type":"Services"
        }
    ],
    "sg:phone":"+1 812 238 1711",
    "sg:postcode":"47803",
    "sg:province":"IN",
    "sg:tags":[
        "shop"
    ],
    "wof:name":"Unto You E Bryant",
    "wof:placetype":"venue"
},
  "geometry": {"coordinates":[-87.37889300000001,39.448653],"type":"Point"}
}