{
  "type": "Feature",
  "properties": {
    "iso:country":"US",
    "sg:address":"107 US Hwy 66 E",
    "sg:city":"Tell City",
    "sg:classifiers":[
        {
            "category":"Wholesale",
            "subcategory":"Medical Equipment & Supplies",
            "type":"Manufacturing & Wholesale Goods"
        }
    ],
    "sg:phone":"+1 812 547 5846",
    "sg:postcode":"47586",
    "sg:province":"IN",
    "sg:tags":[
        "hospital"
    ],
    "wof:name":"Medi Home Care",
    "wof:placetype":"venue"
},
  "geometry": {"coordinates":[-86.764665,37.942496],"type":"Point"}
}