{
  "type": "Feature",
  "properties": {
    "iso:country":"US",
    "sg:address":"1058 S 475 W",
    "sg:city":"Rushville",
    "sg:classifiers":[
        {
            "category":"Farming",
            "subcategory":"Farm",
            "type":"Manufacturing & Wholesale Goods"
        }
    ],
    "sg:phone":"+1 765 663 2514",
    "sg:postcode":"46173",
    "sg:province":"IN",
    "sg:tags":[
        "crop",
        "general"
    ],
    "wof:name":"G Miller Farms Inc",
    "wof:placetype":"venue"
},
  "geometry": {"coordinates":[-85.532425,39.59667],"type":"Point"}
}