{
  "type": "Feature",
  "properties": {
    "iso:country":"US",
    "sg:address":"190 S Main St",
    "sg:city":"Spencer",
    "sg:classifiers":[
        {
            "category":"Autos & Motor Vehicles",
            "subcategory":"Auto Supplies",
            "type":"Retail Goods"
        }
    ],
    "sg:phone":"+1 812 829 6272",
    "sg:postcode":"47460",
    "sg:province":"IN",
    "sg:tags":[
        "automobile",
        "parts"
    ],
    "wof:name":"Owen Valley Auto Parts",
    "wof:placetype":"venue"
},
  "geometry": {"coordinates":[-86.76242499999999,39.284224],"type":"Point"}
}