{
  "type": "Feature",
  "properties": {
    "addr:full":"8249 Zionsville Rd Indianapolis IN 46268",
    "addr:housenumber":"8249",
    "addr:postcode":"46268",
    "addr:street":"Zionsville Rd",
    "iso:country":"US",
    "sg:address":"8249 Zionsville Rd",
    "sg:city":"Indianapolis",
    "sg:classifiers":[
        {
            "category":"Wholesale",
            "subcategory":"Stationery",
            "type":"Manufacturing & Wholesale Goods"
        }
    ],
    "sg:phone":"+1 317 870 1000",
    "sg:postcode":"46268",
    "sg:province":"IN",
    "sg:tags":[
        "packaging",
        "material"
    ],
    "wof:name":"Welch Packaging Indianapolis",
    "wof:placetype":"venue"
},
  "geometry": {"coordinates":[-86.259866,39.902271],"type":"Point"}
}