{
  "type": "Feature",
  "properties": {
    "iso:country":"US",
    "sg:address":"866 S Co Rd 625 E",
    "sg:city":"Avon",
    "sg:classifiers":[
        {
            "category":"Organizations",
            "subcategory":"Professional Association",
            "type":"Services"
        }
    ],
    "sg:phone":"+1 317 839 5480",
    "sg:postcode":"46123",
    "sg:province":"IN",
    "wof:name":"Avon Jr Athletic Assn",
    "wof:placetype":"venue"
},
  "geometry": {"coordinates":[-86.414044,39.750106],"type":"Point"}
}