{
  "type": "Feature",
  "properties": {
    "iso:country":"US",
    "sg:address":"4643 Gaywood Dr",
    "sg:city":"Fort Wayne",
    "sg:classifiers":[
        {
            "category":"Organizations",
            "subcategory":"Religious Organization",
            "type":"Services"
        }
    ],
    "sg:phone":"+1 260 745 5340",
    "sg:postcode":"46806",
    "sg:province":"IN",
    "wof:name":"Catholic Diocese",
    "wof:placetype":"venue"
},
  "geometry": {"coordinates":[-85.122524,41.042122],"type":"Point"}
}