{
  "type": "Feature",
  "properties": {
    "iso:country":"US",
    "sg:address":"210 N Van Buren St",
    "sg:city":"Shipshewana",
    "sg:classifiers":[
        {
            "category":"Shopping",
            "subcategory":"Hobbies, Toys, & Games",
            "type":"Retail Goods"
        }
    ],
    "sg:phone":"+1 260 768 4725",
    "sg:postcode":"46565",
    "sg:province":"IN",
    "sg:website":"www.riegsecker.com",
    "wof:name":"Dad's Toys",
    "wof:placetype":"venue"
},
  "geometry": {"coordinates":[-85.580732,41.677133],"type":"Point"}
}