{
  "type": "Feature",
  "properties": {
    "iso:country":"US",
    "sg:address":"1608 S Bend Ave",
    "sg:city":"South Bend",
    "sg:classifiers":[
        {
            "category":"Professional",
            "type":"Services"
        }
    ],
    "sg:phone":"+1 574 232 5360",
    "sg:postcode":"46617",
    "sg:province":"IN",
    "wof:name":"Bosom Buddies Inc",
    "wof:placetype":"venue"
},
  "geometry": {"coordinates":[-86.224942,41.693487],"type":"Point"}
}