{
  "type": "Feature",
  "properties": {
    "iso:country":"US",
    "sg:address":"63 W Wardell St",
    "sg:city":"Scottsburg",
    "sg:classifiers":[
        {
            "category":"Professional",
            "subcategory":"Lawyer & Legal Services",
            "type":"Services"
        }
    ],
    "sg:phone":"+1 812 752 2344",
    "sg:postcode":"47170",
    "sg:province":"IN",
    "wof:name":"Dietrich Law Office",
    "wof:placetype":"venue"
},
  "geometry": {"coordinates":[-85.77084499999999,38.684708],"type":"Point"}
}