{
  "type": "Feature",
  "properties": {
    "iso:country":"US",
    "sg:address":"910 E Ireland Rd",
    "sg:city":"South Bend",
    "sg:classifiers":[
        {
            "category":"Personal",
            "subcategory":"Tanning Parlor",
            "type":"Services"
        }
    ],
    "sg:phone":"+1 574 291 9100",
    "sg:postcode":"46614",
    "sg:province":"IN",
    "sg:tags":[
        "salon"
    ],
    "wof:name":"Pro Tan Tanning Salon",
    "wof:placetype":"venue"
},
  "geometry": {"coordinates":[-86.234953,41.629323],"type":"Point"}
}