{
  "type": "Feature",
  "properties": {
    "iso:country":"US",
    "sg:address":"7850 S Victor Pike",
    "sg:city":"Bloomington",
    "sg:classifiers":[
        {
            "category":"Mining & Drilling",
            "type":"Manufacturing & Wholesale Goods"
        }
    ],
    "sg:phone":"+1 812 824 6670",
    "sg:postcode":"47403",
    "sg:province":"IN",
    "sg:tags":[
        "stone"
    ],
    "wof:name":"BTI Crushed Stone Sales",
    "wof:placetype":"venue"
},
  "geometry": {"coordinates":[-86.585967,39.055854],"type":"Point"}
}