{
  "type": "Feature",
  "properties": {
    "addr:full":"7920 W Jefferson Blvd Fort Wayne IN 46804",
    "addr:housenumber":"7920",
    "addr:postcode":"46804",
    "addr:street":"W Jefferson Blvd",
    "iso:country":"US",
    "sg:address":"7920 W Jefferson Blvd",
    "sg:city":"Fort Wayne",
    "sg:classifiers":[
        {
            "category":"Health Services",
            "subcategory":"Doctor",
            "type":"Services"
        }
    ],
    "sg:phone":"+1 260 436 5670",
    "sg:postcode":"46804",
    "sg:province":"IN",
    "sg:tags":[
        "physician",
        "surgeon"
    ],
    "sg:website":"www.fortwayneallergy.com",
    "wof:name":"Ft Wayne Allergy Consultants",
    "wof:placetype":"venue"
},
  "geometry": {"coordinates":[-85.242986,41.039742],"type":"Point"}
}