{
  "type": "Feature",
  "properties": {
    "iso:country":"US",
    "sg:address":"10 W Rampart St",
    "sg:city":"Shelbyville",
    "sg:classifiers":[
        {
            "category":"Restaurant",
            "type":"Food & Drink"
        }
    ],
    "sg:menulink":"http://www.allmenus.com/in/addison/186546-mcdonalds/menu/",
    "sg:postcode":"46176",
    "sg:province":"IN",
    "sg:tags":[
        "burger",
        "american"
    ],
    "wof:name":"McDonald's",
    "wof:placetype":"venue"
},
  "geometry": {"coordinates":[-85.775193,39.547461],"type":"Point"}
}