{
  "type": "Feature",
  "properties": {
    "iso:country":"US",
    "sg:address":"21 Vernon St",
    "sg:city":"North Vernon",
    "sg:classifiers":[
        {
            "category":"Banks & Credit Unions",
            "subcategory":"Bank",
            "type":"Services"
        }
    ],
    "sg:phone":"+1 812 346 1995",
    "sg:postcode":"47265",
    "sg:province":"IN",
    "wof:name":"Main Source Bank",
    "wof:placetype":"venue"
},
  "geometry": {"coordinates":[-85.624056,39.002021],"type":"Point"}
}