{
  "type": "Feature",
  "properties": {
    "addr:full":"10 E Mill St Brooklyn IN 46111",
    "addr:housenumber":"10",
    "addr:postcode":"46111",
    "addr:street":"E Mill St",
    "iso:country":"US",
    "sg:address":"10 E Mill St",
    "sg:city":"Brooklyn",
    "sg:classifiers":[
        {
            "category":"Banks & Credit Unions",
            "subcategory":"Bank",
            "type":"Services"
        }
    ],
    "sg:phone":"+1 317 831 2110",
    "sg:postcode":"46111",
    "sg:province":"IN",
    "wof:name":"Citizens Bank",
    "wof:placetype":"venue"
},
  "geometry": {"coordinates":[-86.369997,39.538532],"type":"Point"}
}