{
  "type": "Feature",
  "properties": {
    "iso:country":"US",
    "sg:address":"8655 NW Winchester Rd",
    "sg:city":"Decatur",
    "sg:classifiers":[
        {
            "category":"Freight",
            "type":"Transportation"
        }
    ],
    "sg:phone":"+1 260 728 9952",
    "sg:postcode":"46733",
    "sg:province":"IN",
    "wof:name":"Camelot Carriage Rides",
    "wof:placetype":"venue"
},
  "geometry": {"coordinates":[-84.973814,40.871718],"type":"Point"}
}