{
  "type": "Feature",
  "properties": {
    "iso:country":"US",
    "sg:address":"5410 Hartford Dr",
    "sg:city":"Fort Wayne",
    "sg:classifiers":[
        {
            "category":"Real Estate",
            "subcategory":"Surveying",
            "type":"Services"
        }
    ],
    "sg:phone":"+1 260 486 7563",
    "sg:postcode":"46835",
    "sg:province":"IN",
    "sg:tags":[
        "surveyor"
    ],
    "wof:name":"Gale L Fansier",
    "wof:placetype":"venue"
},
  "geometry": {"coordinates":[-85.04214899999999,41.131087],"type":"Point"}
}