{
  "type": "Feature",
  "properties": {
    "iso:country":"US",
    "sg:address":"5436 N Keystone Ave",
    "sg:city":"Indianapolis",
    "sg:classifiers":[
        {
            "category":"Shopping",
            "subcategory":"Music",
            "type":"Retail Goods"
        }
    ],
    "sg:phone":"+1 317 253 0124",
    "sg:postcode":"46220",
    "sg:province":"IN",
    "sg:tags":[
        "durable"
    ],
    "wof:name":"Howards Hard To Find",
    "wof:placetype":"venue"
},
  "geometry": {"coordinates":[-86.122157,39.852182],"type":"Point"}
}