{
  "type": "Feature",
  "properties": {
    "iso:country":"US",
    "sg:address":"5540 W 84th St",
    "sg:city":"Indianapolis",
    "sg:classifiers":[
        {
            "category":"Building & Trades",
            "subcategory":"Construction",
            "type":"Services"
        }
    ],
    "sg:phone":"+1 317 875 0608",
    "sg:postcode":"46268",
    "sg:province":"IN",
    "sg:tags":[
        "waterproofing",
        "contractor"
    ],
    "wof:name":"Alldry Waterproofing-Indiana",
    "wof:placetype":"venue"
},
  "geometry": {"coordinates":[-86.25808,39.907057],"type":"Point"}
}