{
  "type": "Feature",
  "properties": {
    "iso:country":"US",
    "sg:address":"7025 Central Dr SW",
    "sg:city":"Central",
    "sg:classifiers":[
        {
            "category":"Home & Garden",
            "subcategory":"Building Materials",
            "type":"Retail Goods"
        }
    ],
    "sg:phone":"+1 812 732 4358",
    "sg:postcode":"47110",
    "sg:province":"IN",
    "wof:name":"Longbottom & Hardsaw Inc",
    "wof:placetype":"venue"
},
  "geometry": {"coordinates":[-86.15879200000001,38.099381],"type":"Point"}
}