{
  "type": "Feature",
  "properties": {
    "iso:country":"US",
    "sg:address":"828 Watt St",
    "sg:city":"Jeffersonville",
    "sg:classifiers":[
        {
            "category":"Retail",
            "subcategory":"Funeral Services",
            "type":"Services"
        }
    ],
    "sg:phone":"+1 812 283 6731",
    "sg:postcode":"47130",
    "sg:province":"IN",
    "sg:tags":[
        "director"
    ],
    "wof:name":"Mason Funeral Home",
    "wof:placetype":"venue"
},
  "geometry": {"coordinates":[-85.73989,38.280075],"type":"Point"}
}