{
  "type": "Feature",
  "properties": {
    "iso:country":"US",
    "sg:address":"207 S Taylor St",
    "sg:city":"St Paul",
    "sg:classifiers":[
        {
            "category":"Manufacturing",
            "subcategory":"Signs",
            "type":"Manufacturing & Wholesale Goods"
        }
    ],
    "sg:phone":"+1 765 525 7446",
    "sg:postcode":"47272",
    "sg:province":"IN",
    "wof:name":"Sign Masters",
    "wof:placetype":"venue"
},
  "geometry": {"coordinates":[-85.628405,39.426068],"type":"Point"}
}