{
  "type": "Feature",
  "properties": {
    "iso:country":"US",
    "sg:address":"3541 Cardinal Ct",
    "sg:city":"Columbus",
    "sg:classifiers":[
        {
            "category":"Real Estate",
            "subcategory":"Real Estate Operator",
            "type":"Services"
        }
    ],
    "sg:phone":"+1 812 376 9160",
    "sg:postcode":"47203",
    "sg:province":"IN",
    "sg:tags":[
        "apartment"
    ],
    "wof:name":"Willowood Apartments",
    "wof:placetype":"venue"
},
  "geometry": {"coordinates":[-85.88023099999999,39.239123],"type":"Point"}
}