{
  "type": "Feature",
  "properties": {
    "iso:country":"US",
    "sg:address":"316 N Tennessee St",
    "sg:city":"Danville",
    "sg:classifiers":[
        {
            "category":"Building & Trades",
            "subcategory":"Plumbing",
            "type":"Services"
        }
    ],
    "sg:phone":"+1 317 745 5024",
    "sg:postcode":"46122",
    "sg:province":"IN",
    "sg:tags":[
        "contractor"
    ],
    "wof:name":"North Mechanical",
    "wof:placetype":"venue"
},
  "geometry": {"coordinates":[-86.521632,39.764414],"type":"Point"}
}