{
  "type": "Feature",
  "properties": {
    "addr:full":"190 Green Meadows Dr Greenfield IN 46140",
    "addr:housenumber":"190",
    "addr:postcode":"46140",
    "addr:street":"Green Meadows Dr",
    "iso:country":"US",
    "sg:address":"190 Green Meadows Dr",
    "sg:city":"Greenfield",
    "sg:classifiers":[
        {
            "category":"Social Services",
            "subcategory":"Child Care",
            "type":"Services"
        }
    ],
    "sg:phone":"+1 317 462 8478",
    "sg:postcode":"46140",
    "sg:province":"IN",
    "wof:name":"House Of Kids Daycare Inc",
    "wof:placetype":"venue"
},
  "geometry": {"coordinates":[-85.77345,39.804469],"type":"Point"}
}