{
  "type": "Feature",
  "properties": {
    "iso:country":"US",
    "sg:address":"7520 E County Line Rd",
    "sg:city":"Edinburgh",
    "sg:classifiers":[
        {
            "category":"Retail",
            "subcategory":"Auto Repair",
            "type":"Services"
        }
    ],
    "sg:phone":"+1 812 526 6594",
    "sg:postcode":"46124",
    "sg:province":"IN",
    "sg:tags":[
        "automobile",
        "customizing"
    ],
    "wof:name":"Supreme Customs",
    "wof:placetype":"venue"
},
  "geometry": {"coordinates":[-85.95668499999999,39.347308],"type":"Point"}
}