{
  "type": "Feature",
  "properties": {
    "iso:country":"US",
    "sg:address":"5301 Commerce Cir",
    "sg:city":"Indianapolis",
    "sg:classifiers":[
        {
            "category":"Manufacturing",
            "subcategory":"Signs",
            "type":"Manufacturing & Wholesale Goods"
        }
    ],
    "sg:phone":"+1 317 887 4895",
    "sg:postcode":"46237",
    "sg:province":"IN",
    "wof:name":"Sign Guys",
    "wof:placetype":"venue"
},
  "geometry": {"coordinates":[-86.07881,39.655581],"type":"Point"}
}