{
  "type": "Feature",
  "properties": {
    "iso:country":"US",
    "sg:address":"4491 W 29th Ave",
    "sg:city":"Gary",
    "sg:classifiers":[
        {
            "category":"Organizations",
            "subcategory":"Religious Organization",
            "type":"Services"
        }
    ],
    "sg:phone":"+1 219 977 8729",
    "sg:postcode":"46404",
    "sg:province":"IN",
    "sg:tags":[
        "church"
    ],
    "wof:name":"Prayer Tower Fellowship Church",
    "wof:placetype":"venue"
},
  "geometry": {"coordinates":[-87.39174300000001,41.566083],"type":"Point"}
}