{
  "type": "Feature",
  "properties": {
    "iso:country":"US",
    "sg:address":"10433 N 500 E",
    "sg:city":"Lewisville",
    "sg:classifiers":[
        {
            "category":"Wholesale",
            "subcategory":"Farm Supplies",
            "type":"Manufacturing & Wholesale Goods"
        }
    ],
    "sg:phone":"+1 765 645 5012",
    "sg:postcode":"47352",
    "sg:province":"IN",
    "sg:tags":[
        "feed"
    ],
    "wof:name":"Gordon's Trucking",
    "wof:placetype":"venue"
},
  "geometry": {"coordinates":[-85.352832,39.771659],"type":"Point"}
}