{
  "type": "Feature",
  "properties": {
    "addr:full":"19 S 6th St Terre Haute IN 47807",
    "addr:housenumber":"19",
    "addr:postcode":"47807",
    "addr:street":"S 6Th St",
    "iso:country":"US",
    "sg:address":"19 S 6th St",
    "sg:city":"Terre Haute",
    "sg:classifiers":[
        {
            "category":"Insurance",
            "subcategory":"Insurance Agent",
            "type":"Services"
        }
    ],
    "sg:phone":"+1 812 232 5815",
    "sg:postcode":"47807",
    "sg:province":"IN",
    "wof:name":"Merrill & Merrill",
    "wof:placetype":"venue"
},
  "geometry": {"coordinates":[-87.41007,39.465634],"type":"Point"}
}