{
  "type": "Feature",
  "properties": {
    "iso:country":"US",
    "sg:address":"2013 S Burlington Dr",
    "sg:city":"Muncie",
    "sg:classifiers":[
        {
            "category":"Manufacturing",
            "subcategory":"Signs",
            "type":"Manufacturing & Wholesale Goods"
        }
    ],
    "sg:phone":"+1 765 288 8353",
    "sg:postcode":"47302",
    "sg:province":"IN",
    "sg:tags":[
        "specialty",
        "mfg"
    ],
    "wof:name":"Finyl Vinyl",
    "wof:placetype":"venue"
},
  "geometry": {"coordinates":[-85.346418,40.176545],"type":"Point"}
}