{
  "type": "Feature",
  "properties": {
    "iso:country":"US",
    "sg:address":"2451 E State Rd 164",
    "sg:city":"Jasper",
    "sg:classifiers":[
        {
            "category":"Real Estate",
            "subcategory":"Real Estate Operator",
            "type":"Services"
        }
    ],
    "sg:phone":"+1 812 634 9228",
    "sg:postcode":"47546",
    "sg:province":"IN",
    "sg:tags":[
        "property",
        "lessor"
    ],
    "wof:name":"Steve Vogler",
    "wof:placetype":"venue"
},
  "geometry": {"coordinates":[-86.862058,38.386974],"type":"Point"}
}