{
  "type": "Feature",
  "properties": {
    "iso:country":"US",
    "sg:address":"1107 Paul Dr",
    "sg:city":"Indianapolis",
    "sg:classifiers":[
        {
            "category":"Shopping",
            "type":"Retail Goods"
        }
    ],
    "sg:phone":"+1 317 891 9434",
    "sg:postcode":"46229",
    "sg:province":"IN",
    "sg:tags":[
        "cosmetic",
        "perfume"
    ],
    "wof:name":"Kim Dorsey Cosmetics",
    "wof:placetype":"venue"
},
  "geometry": {"coordinates":[-85.952949,39.784476],"type":"Point"}
}