{
  "type": "Feature",
  "properties": {
    "iso:country":"US",
    "sg:address":"7563 State Rd 110",
    "sg:city":"Culver",
    "sg:classifiers":[
        {
            "category":"Health Services",
            "subcategory":"Doctor",
            "type":"Services"
        }
    ],
    "sg:phone":"+1 574 542 2110",
    "sg:postcode":"46511",
    "sg:province":"IN",
    "wof:name":"Thomas M Pugh DDS",
    "wof:placetype":"venue"
},
  "geometry": {"coordinates":[-86.386557,41.1718],"type":"Point"}
}