{
  "type": "Feature",
  "properties": {
    "iso:country":"US",
    "sg:address":"106 S Main St",
    "sg:city":"Salem",
    "sg:classifiers":[
        {
            "category":"Restaurant",
            "type":"Food & Drink"
        }
    ],
    "sg:phone":"+1 812 883 5388",
    "sg:postcode":"47167",
    "sg:province":"IN",
    "wof:name":"Peking Chinese Restaurant",
    "wof:placetype":"venue"
},
  "geometry": {"coordinates":[-86.10068,38.605239],"type":"Point"}
}