{
  "type": "Feature",
  "properties": {
    "iso:country":"US",
    "sg:address":"10423 Starview Ct",
    "sg:city":"Indianapolis",
    "sg:classifiers":[
        {
            "category":"Social Services",
            "subcategory":"Child Care",
            "type":"Services"
        }
    ],
    "sg:phone":"+1 317 894 2304",
    "sg:postcode":"46229",
    "sg:province":"IN",
    "sg:tags":[
        "preschool"
    ],
    "wof:name":"Nancys Preschool",
    "wof:placetype":"venue"
},
  "geometry": {"coordinates":[-85.981988,39.805186],"type":"Point"}
}