{
  "type": "Feature",
  "properties": {
    "iso:country":"US",
    "sg:address":"1402 N Eastern Ave",
    "sg:city":"Connersville",
    "sg:classifiers":[
        {
            "category":"Shopping",
            "subcategory":"Florist",
            "type":"Retail Goods"
        }
    ],
    "sg:phone":"+1 765 825 7679",
    "sg:postcode":"47331",
    "sg:province":"IN",
    "wof:name":"Keen Blossoms & Blooms",
    "wof:placetype":"venue"
},
  "geometry": {"coordinates":[-85.130838,39.650028],"type":"Point"}
}