{
  "type": "Feature",
  "properties": {
    "addr:full":"111 E Monroe St Williamsport IN 47993",
    "addr:housenumber":"111",
    "addr:postcode":"47993",
    "addr:street":"E Monroe St",
    "iso:country":"US",
    "sg:address":"111 E Monroe St",
    "sg:city":"Williamsport",
    "sg:classifiers":[
        {
            "category":"Retail",
            "subcategory":"Funeral Services",
            "type":"Services"
        }
    ],
    "sg:phone":"+1 765 762 3464",
    "sg:postcode":"47993",
    "sg:province":"IN",
    "sg:tags":[
        "director"
    ],
    "wof:name":"Grady Funeral Homes Inc",
    "wof:placetype":"venue"
},
  "geometry": {"coordinates":[-87.291483,40.284893],"type":"Point"}
}