{
  "type": "Feature",
  "properties": {
    "iso:country":"US",
    "sg:address":"6240 W 34th St",
    "sg:city":"Indianapolis",
    "sg:classifiers":[
        {
            "category":"Food & Beverages",
            "subcategory":"Groceries & Convenience Stores",
            "type":"Retail Goods"
        }
    ],
    "sg:phone":"+1 317 299 8310",
    "sg:postcode":"46224",
    "sg:province":"IN",
    "sg:tags":[
        "grocer"
    ],
    "wof:name":"Tienda Suarez",
    "wof:placetype":"venue"
},
  "geometry": {"coordinates":[-86.269713,39.816315],"type":"Point"}
}