{
  "type": "Feature",
  "properties": {
    "iso:country":"US",
    "sg:address":"118 W Washington St",
    "sg:city":"Shelbyville",
    "sg:classifiers":[
        {
            "category":"Social Services",
            "type":"Services"
        }
    ],
    "sg:phone":"+1 317 392 4673",
    "sg:postcode":"46176",
    "sg:province":"IN",
    "sg:tags":[
        "counseling"
    ],
    "wof:name":"Oasis Of Hope Counseling",
    "wof:placetype":"venue"
},
  "geometry": {"coordinates":[-85.781364,39.524518],"type":"Point"}
}