{
  "type": "Feature",
  "properties": {
    "iso:country":"US",
    "sg:address":"9330 Sheffield Ave",
    "sg:city":"Dyer",
    "sg:classifiers":[
        {
            "category":"Recreation",
            "type":"Entertainment"
        }
    ],
    "sg:phone":"+1 219 365 3414",
    "sg:postcode":"46311",
    "sg:province":"IN",
    "sg:tags":[
        "stable"
    ],
    "wof:name":"Clark's Greenview Stable",
    "wof:placetype":"venue"
},
  "geometry": {"coordinates":[-87.51822199999999,41.449698],"type":"Point"}
}