{
  "type": "Feature",
  "properties": {
    "iso:country":"US",
    "sg:address":"102 1st St",
    "sg:city":"Laporte",
    "sg:classifiers":[
        {
            "category":"Real Estate",
            "subcategory":"Real Estate Agent",
            "type":"Services"
        }
    ],
    "sg:phone":"+1 219 324 7058",
    "sg:postcode":"46350",
    "sg:province":"IN",
    "wof:name":"Bortz Realty",
    "wof:placetype":"venue"
},
  "geometry": {"coordinates":[-86.720021,41.606411],"type":"Point"}
}