{
  "type": "Feature",
  "properties": {
    "addr:full":"3900 E 31st Ave Hobart IN 46342",
    "addr:housenumber":"3900",
    "addr:postcode":"46342",
    "addr:street":"E 31St Ave",
    "iso:country":"US",
    "sg:address":"3900 E 31st Ave",
    "sg:city":"Hobart",
    "sg:classifiers":[
        {
            "category":"Building & Trades",
            "subcategory":"Electrical",
            "type":"Services"
        }
    ],
    "sg:phone":"+1 219 962 5100",
    "sg:postcode":"46342",
    "sg:province":"IN",
    "sg:tags":[
        "electric",
        "contractor"
    ],
    "wof:name":"Delta Sun Electric Corp",
    "wof:placetype":"venue"
},
  "geometry": {"coordinates":[-87.231337,41.561605],"type":"Point"}
}