{
  "type": "Feature",
  "properties": {
    "iso:country":"US",
    "sg:address":"3716 S Reed Rd",
    "sg:city":"Kokomo",
    "sg:classifiers":[
        {
            "category":"Home & Garden",
            "subcategory":"Carpets & Floor Coverings",
            "type":"Retail Goods"
        }
    ],
    "sg:phone":"+1 765 453 4950",
    "sg:postcode":"46902",
    "sg:province":"IN",
    "sg:tags":[
        "dealer",
        "rug"
    ],
    "wof:name":"Buddy's Carpet",
    "wof:placetype":"venue"
},
  "geometry": {"coordinates":[-86.125691,40.441391],"type":"Point"}
}