{
  "type": "Feature",
  "properties": {
    "iso:country":"US",
    "sg:address":"2498 W Roeder Rd",
    "sg:city":"Boonville",
    "sg:classifiers":[
        {
            "category":"Health Services",
            "subcategory":"Optometrist",
            "type":"Services"
        }
    ],
    "sg:phone":"+1 812 897 1562",
    "sg:postcode":"47601",
    "sg:province":"IN",
    "wof:name":"John A Gilles Od",
    "wof:placetype":"venue"
},
  "geometry": {"coordinates":[-87.292719,37.989953],"type":"Point"}
}