{
  "type": "Feature",
  "properties": {
    "iso:country":"US",
    "sg:address":"790 Joliet St",
    "sg:city":"Dyer",
    "sg:classifiers":[
        {
            "category":"Restaurant",
            "type":"Food & Drink"
        }
    ],
    "sg:menulink":"http://www.allmenus.com/in/st-john/174139-wendys/menu/",
    "sg:phone":"+1 219 864 4631",
    "sg:postcode":"46311",
    "sg:province":"IN",
    "sg:tags":[
        "burger",
        "american",
        "soup"
    ],
    "wof:name":"Wendy's",
    "wof:placetype":"venue"
},
  "geometry": {"coordinates":[-87.50765,41.492807],"type":"Point"}
}