{
  "type": "Feature",
  "properties": {
    "iso:country":"US",
    "sg:address":"4236 Co Rd W 400 S",
    "sg:city":"Russiaville",
    "sg:classifiers":[
        {
            "category":"Retail",
            "subcategory":"Animal Services",
            "type":"Services"
        }
    ],
    "sg:phone":"+1 765 883 5415",
    "sg:postcode":"46979",
    "sg:province":"IN",
    "sg:tags":[
        "breeder",
        "horse"
    ],
    "wof:name":"Red Top Stables Feed & Supls",
    "wof:placetype":"venue"
},
  "geometry": {"coordinates":[-86.207628,40.417641],"type":"Point"}
}