{
  "type": "Feature",
  "properties": {
    "iso:country":"US",
    "sg:address":"5820 Franklin St",
    "sg:city":"Michigan City",
    "sg:classifiers":[
        {
            "category":"Restaurant",
            "type":"Food & Drink"
        }
    ],
    "sg:menulink":"http://www.allmenus.com/in/coolspring/17046-damons-grill/menu/",
    "sg:phone":"+1 219 879 8900",
    "sg:postcode":"46360",
    "sg:province":"IN",
    "sg:tags":[
        "barbecue",
        "american",
        "steakhouse",
        "burger"
    ],
    "wof:name":"Damon's Grill",
    "wof:placetype":"venue"
},
  "geometry": {"coordinates":[-86.894008,41.667603],"type":"Point"}
}