{
  "type": "Feature",
  "properties": {
    "iso:country":"US",
    "sg:address":"1201 W Pike St",
    "sg:city":"Goshen",
    "sg:classifiers":[
        {
            "category":"Organizations",
            "subcategory":"Non-profit Organization",
            "type":"Services"
        }
    ],
    "sg:phone":"+1 574 533 6460",
    "sg:postcode":"46526",
    "sg:province":"IN",
    "wof:name":"Veterans Of Foreign Wars",
    "wof:placetype":"venue"
},
  "geometry": {"coordinates":[-85.85231400000001,41.588986],"type":"Point"}
}