{
  "type": "Feature",
  "properties": {
    "iso:country":"US",
    "sg:address":"402 Broadway",
    "sg:city":"Chesterton",
    "sg:classifiers":[
        {
            "category":"Shopping",
            "subcategory":"Used Merchandise",
            "type":"Retail Goods"
        }
    ],
    "sg:phone":"+1 219 395 8899",
    "sg:postcode":"46304",
    "sg:province":"IN",
    "sg:tags":[
        "antique"
    ],
    "wof:name":"Antiques 101",
    "wof:placetype":"venue"
},
  "geometry": {"coordinates":[-87.056896,41.611201],"type":"Point"}
}