{
  "type": "Feature",
  "properties": {
    "iso:country":"US",
    "sg:address":"2214 High St",
    "sg:city":"Seymour",
    "sg:classifiers":[
        {
            "category":"Building & Trades",
            "subcategory":"Landscaping Services",
            "type":"Services"
        }
    ],
    "sg:phone":"+1 812 523 8501",
    "sg:postcode":"47274",
    "sg:province":"IN",
    "sg:tags":[
        "landscape"
    ],
    "wof:name":"Taskey Lawn & Landscape Svcs",
    "wof:placetype":"venue"
},
  "geometry": {"coordinates":[-85.893457,38.988564],"type":"Point"}
}