{
  "type": "Feature",
  "properties": {
    "iso:country":"US",
    "sg:address":"213 N 9th St",
    "sg:city":"Elwood",
    "sg:classifiers":[
        {
            "category":"Organizations",
            "subcategory":"Religious Organization",
            "type":"Services"
        }
    ],
    "sg:phone":"+1 765 552 5233",
    "sg:postcode":"46036",
    "sg:province":"IN",
    "sg:tags":[
        "church"
    ],
    "wof:name":"First General Baptist Church",
    "wof:placetype":"venue"
},
  "geometry": {"coordinates":[-85.850122,40.279401],"type":"Point"}
}