{
  "type": "Feature",
  "properties": {
    "iso:country":"US",
    "sg:address":"7417 Salem Ridge Rd",
    "sg:city":"Aurora",
    "sg:classifiers":[
        {
            "category":"Building & Trades",
            "subcategory":"Cleaning & Sanitation",
            "type":"Services"
        }
    ],
    "sg:phone":"+1 812 438 2565",
    "sg:postcode":"47001",
    "sg:province":"IN",
    "sg:tags":[
        "maintenance"
    ],
    "wof:name":"Janets Cleaning",
    "wof:placetype":"venue"
},
  "geometry": {"coordinates":[-84.955152,38.957744],"type":"Point"}
}