{
  "type": "Feature",
  "properties": {
    "addr:full":"13880 W Commerce Rd Daleville IN 47334",
    "addr:housenumber":"13880",
    "addr:postcode":"47334",
    "addr:street":"W Commerce Rd",
    "iso:country":"US",
    "sg:address":"13880 W Commerce Rd",
    "sg:city":"Daleville",
    "sg:classifiers":[
        {
            "category":"Wholesale",
            "subcategory":"Electrical",
            "type":"Manufacturing & Wholesale Goods"
        }
    ],
    "sg:phone":"+1 765 378 8030",
    "sg:postcode":"47334",
    "sg:province":"IN",
    "sg:tags":[
        "equipment",
        "electric",
        "supply"
    ],
    "wof:name":"Wesco Distributing Inc",
    "wof:placetype":"venue"
},
  "geometry": {"coordinates":[-85.54982099999999,40.113508],"type":"Point"}
}