{
  "type": "Feature",
  "properties": {
    "addr:full":"4625 E 96th St Indianapolis IN 46240",
    "addr:housenumber":"4625",
    "addr:postcode":"46240",
    "addr:street":"E 96Th St",
    "iso:country":"US",
    "sg:address":"4625 E 96th St",
    "sg:city":"Indianapolis",
    "sg:classifiers":[
        {
            "category":"Building & Trades",
            "subcategory":"Locksmith",
            "type":"Services"
        }
    ],
    "sg:phone":"+1 317 708 4935",
    "sg:postcode":"46240",
    "sg:province":"IN",
    "sg:tags":[
        "key"
    ],
    "wof:name":"24 Hour A Locksmith",
    "wof:placetype":"venue"
},
  "geometry": {"coordinates":[-86.090643,39.926693],"type":"Point"}
}