{
  "type": "Feature",
  "properties": {
    "addr:full":"6974 S Co Rd 300 E Greensburg IN 47240",
    "addr:housenumber":"6974",
    "addr:postcode":"47240",
    "addr:street":"S Co Rd 300 E",
    "iso:country":"US",
    "sg:address":"6974 S Co Rd 300 E",
    "sg:city":"Greensburg",
    "sg:classifiers":[
        {
            "category":"Farming",
            "subcategory":"Livestock Farm",
            "type":"Manufacturing & Wholesale Goods"
        }
    ],
    "sg:phone":"+1 812 663 4989",
    "sg:postcode":"47240",
    "sg:province":"IN",
    "sg:tags":[
        "hog",
        "or",
        "feedlot"
    ],
    "wof:name":"Steve Fry",
    "wof:placetype":"venue"
},
  "geometry": {"coordinates":[-85.41985200000001,39.234712],"type":"Point"}
}