{
  "type": "Feature",
  "properties": {
    "iso:country":"US",
    "sg:address":"105 N Washington St",
    "sg:city":"Danville",
    "sg:classifiers":[
        {
            "category":"Professional",
            "subcategory":"Lawyer & Legal Services",
            "type":"Services"
        }
    ],
    "sg:phone":"+1 317 745 1300",
    "sg:postcode":"46122",
    "sg:province":"IN",
    "sg:tags":[
        "attorney"
    ],
    "wof:name":"Willliam O Harrington PC",
    "wof:placetype":"venue"
},
  "geometry": {"coordinates":[-86.523741,39.763619],"type":"Point"}
}