{
  "type": "Feature",
  "properties": {
    "iso:country":"US",
    "sg:address":"739 N Warman Ave",
    "sg:city":"Indianapolis",
    "sg:classifiers":[
        {
            "category":"Social Services",
            "subcategory":"Child Care",
            "type":"Services"
        }
    ],
    "sg:phone":"+1 317 423 2440",
    "sg:postcode":"46222",
    "sg:province":"IN",
    "wof:name":"Edens Child Development Mnstry",
    "wof:placetype":"venue"
},
  "geometry": {"coordinates":[-86.20632999999999,39.778243],"type":"Point"}
}