{
  "type": "Feature",
  "properties": {
    "iso:country":"US",
    "sg:address":"8104 E Main St",
    "sg:city":"Dugger",
    "sg:classifiers":[
        {
            "category":"Restaurant",
            "type":"Food & Drink"
        }
    ],
    "sg:phone":"+1 812 648 3544",
    "sg:postcode":"47848",
    "sg:province":"IN",
    "wof:name":"Ole Coalminer Restaurant",
    "wof:placetype":"venue"
},
  "geometry": {"coordinates":[-87.257294,39.067616],"type":"Point"}
}