{
  "type": "Feature",
  "properties": {
    "iso:country":"US",
    "sg:address":"206 E 6th St",
    "sg:city":"Fowler",
    "sg:classifiers":[
        {
            "category":"Personal",
            "subcategory":"Beauty Salon",
            "type":"Services"
        }
    ],
    "sg:phone":"+1 765 884 8812",
    "sg:postcode":"47944",
    "sg:province":"IN",
    "wof:name":"Bobbie Shop",
    "wof:placetype":"venue"
},
  "geometry": {"coordinates":[-87.322159,40.616657],"type":"Point"}
}