{
  "type": "Feature",
  "properties": {
    "iso:country":"US",
    "sg:address":"2946 E 3rd St",
    "sg:city":"Bloomington",
    "sg:classifiers":[
        {
            "category":"Personal",
            "subcategory":"Beauty Salon",
            "type":"Services"
        }
    ],
    "sg:phone":"+1 812 332 9333",
    "sg:postcode":"47401",
    "sg:province":"IN",
    "wof:name":"Regis Salons",
    "wof:placetype":"venue"
},
  "geometry": {"coordinates":[-86.493476,39.164135],"type":"Point"}
}