{
  "type": "Feature",
  "properties": {
    "iso:country":"US",
    "sg:address":"3302 N Washington Blvd",
    "sg:city":"Indianapolis",
    "sg:classifiers":[
        {
            "category":"Manufacturing",
            "subcategory":"Printing",
            "type":"Manufacturing & Wholesale Goods"
        }
    ],
    "sg:phone":"+1 317 283 5433",
    "sg:postcode":"46205",
    "sg:province":"IN",
    "sg:tags":[
        "publisher",
        "guide"
    ],
    "wof:name":"Lifeworks Publishing",
    "wof:placetype":"venue"
},
  "geometry": {"coordinates":[-86.152157,39.817555],"type":"Point"}
}