{
  "type": "Feature",
  "properties": {
    "iso:country":"US",
    "sg:address":"130 W 29th St",
    "sg:city":"Indianapolis",
    "sg:classifiers":[
        {
            "category":"Organizations",
            "subcategory":"Religious Organization",
            "type":"Services"
        }
    ],
    "sg:phone":"+1 317 926 8292",
    "sg:postcode":"46208",
    "sg:province":"IN",
    "wof:name":"New Lbrty Mssnary Bptst Church",
    "wof:placetype":"venue"
},
  "geometry": {"coordinates":[-86.15904500000001,39.808367],"type":"Point"}
}