{
  "type": "Feature",
  "properties": {
    "addr:full":"1000 Waterway Blvd Indianapolis IN 46202",
    "addr:housenumber":"1000",
    "addr:postcode":"46202",
    "addr:street":"Waterway Blvd",
    "iso:country":"US",
    "sg:address":"1000 Waterway Blvd",
    "sg:city":"Indianapolis",
    "sg:classifiers":[
        {
            "category":"Professional",
            "subcategory":"Business Services",
            "type":"Services"
        }
    ],
    "sg:phone":"+1 317 633 2070",
    "sg:postcode":"46202",
    "sg:province":"IN",
    "sg:tags":[
        "license"
    ],
    "wof:name":"Curtis Archives",
    "wof:placetype":"venue"
},
  "geometry": {"coordinates":[-86.182132,39.783359],"type":"Point"}
}