{
  "type": "Feature",
  "properties": {
    "iso:country":"US",
    "sg:address":"7750 Broadway",
    "sg:city":"Merrillville",
    "sg:classifiers":[
        {
            "category":"Banks & Credit Unions",
            "subcategory":"Bank",
            "type":"Services"
        }
    ],
    "sg:phone":"+1 219 736 2490",
    "sg:postcode":"46410",
    "sg:province":"IN",
    "sg:tags":[
        "loan"
    ],
    "wof:name":"Check 'n Go",
    "wof:placetype":"venue"
},
  "geometry": {"coordinates":[-87.33606399999999,41.47775],"type":"Point"}
}