{
  "type": "Feature",
  "properties": {
    "addr:full":"7200 W 21st Ave Gary IN 46406",
    "addr:housenumber":"7200",
    "addr:postcode":"46406",
    "addr:street":"W 21St Ave",
    "iso:country":"US",
    "sg:address":"7200 W 21st Ave",
    "sg:city":"Gary",
    "sg:classifiers":[
        {
            "category":"Building & Trades",
            "subcategory":"Construction",
            "type":"Services"
        }
    ],
    "sg:phone":"+1 219 944 6100",
    "sg:postcode":"46406",
    "sg:province":"IN",
    "sg:tags":[
        "general",
        "contractor"
    ],
    "wof:name":"CCL Construction Inc",
    "wof:placetype":"venue"
},
  "geometry": {"coordinates":[-87.42942600000001,41.580907],"type":"Point"}
}