{
  "type": "Feature",
  "properties": {
    "iso:country":"US",
    "sg:address":"2701 N Cullen Ave",
    "sg:city":"Evansville",
    "sg:classifiers":[
        {
            "category":"Building & Trades",
            "subcategory":"Landscaping Services",
            "type":"Services"
        }
    ],
    "sg:phone":"+1 812 471 0590",
    "sg:postcode":"47715",
    "sg:province":"IN",
    "sg:tags":[
        "lawn",
        "maintenance",
        "grounds"
    ],
    "wof:name":"Tru Green Chem Lawn",
    "wof:placetype":"venue"
},
  "geometry": {"coordinates":[-87.486266,37.998751],"type":"Point"}
}