{
  "type": "Feature",
  "properties": {
    "iso:country":"US",
    "sg:address":"525 Broadway St",
    "sg:city":"New Haven",
    "sg:classifiers":[
        {
            "category":"Bars & Pubs",
            "type":"Food & Drink"
        }
    ],
    "sg:phone":"+1 260 749 5396",
    "sg:postcode":"46774",
    "sg:province":"IN",
    "wof:name":"Rack & Helen's Bar",
    "wof:placetype":"venue"
},
  "geometry": {"coordinates":[-85.016979,41.072503],"type":"Point"}
}