{
  "type": "Feature",
  "properties": {
    "iso:country":"US",
    "sg:address":"9538 E 126th St",
    "sg:city":"Fishers",
    "sg:classifiers":[
        {
            "category":"Retail",
            "subcategory":"Laundry & Dry Cleaning",
            "type":"Services"
        }
    ],
    "sg:phone":"+1 317 845 1244",
    "sg:postcode":"46038",
    "sg:province":"IN",
    "sg:tags":[
        "cleaners"
    ],
    "sg:website":"www.classiccleaners.com",
    "wof:name":"Classic Cleaners",
    "wof:placetype":"venue"
},
  "geometry": {"coordinates":[-85.999347,39.971703],"type":"Point"}
}