{
  "type": "Feature",
  "properties": {
    "iso:country":"US",
    "sg:address":"517 N Walnut St",
    "sg:city":"Bloomington",
    "sg:classifiers":[
        {
            "category":"Government",
            "subcategory":"Office",
            "type":"Public Place"
        }
    ],
    "sg:phone":"+1 812 333 5762",
    "sg:postcode":"47404",
    "sg:province":"IN",
    "sg:tags":[
        "armed",
        "force",
        "recruiting"
    ],
    "wof:name":"US Army Recruiting",
    "wof:placetype":"venue"
},
  "geometry": {"coordinates":[-86.533644,39.171464],"type":"Point"}
}