{
  "type": "Feature",
  "properties": {
    "addr:full":"1004 Oak Grove Ct Valparaiso IN 46383",
    "addr:housenumber":"1004",
    "addr:postcode":"46383",
    "addr:street":"Oak Grove Ct",
    "iso:country":"US",
    "sg:address":"1004 Oak Grove Ct",
    "sg:city":"Valparaiso",
    "sg:classifiers":[
        {
            "category":"Professional",
            "subcategory":"Business Services",
            "type":"Services"
        }
    ],
    "sg:phone":"+1 219 464 9487",
    "sg:postcode":"46383",
    "sg:province":"IN",
    "wof:name":"Andrews Group LLC",
    "wof:placetype":"venue"
},
  "geometry": {"coordinates":[-87.048412,41.505221],"type":"Point"}
}