{
  "type": "Feature",
  "properties": {
    "iso:country":"US",
    "sg:address":"1020 Canal Rd",
    "sg:city":"Lafayette",
    "sg:classifiers":[
        {
            "category":"Government",
            "subcategory":"Office",
            "type":"Public Place"
        }
    ],
    "sg:phone":"+1 765 476 4561",
    "sg:postcode":"47904",
    "sg:province":"IN",
    "sg:tags":[
        "village"
    ],
    "wof:name":"Lafayette Canal Pumping Sta",
    "wof:placetype":"venue"
},
  "geometry": {"coordinates":[-86.893489,40.425743],"type":"Point"}
}