{
  "type": "Feature",
  "properties": {
    "iso:country":"US",
    "sg:address":"1613 Grove Dr",
    "sg:city":"Fort Wayne",
    "sg:classifiers":[
        {
            "category":"Organizations",
            "subcategory":"Religious Organization",
            "type":"Services"
        }
    ],
    "sg:phone":"+1 260 489 1140",
    "sg:postcode":"46825",
    "sg:province":"IN",
    "wof:name":"Faith Missionary Church",
    "wof:placetype":"venue"
},
  "geometry": {"coordinates":[-85.164855,41.150055],"type":"Point"}
}