{
  "type": "Feature",
  "properties": {
    "iso:country":"US",
    "sg:address":"514 Hawpatch Rd",
    "sg:city":"Lagrange",
    "sg:classifiers":[
        {
            "category":"Manufacturing",
            "subcategory":"Retail Goods",
            "type":"Manufacturing & Wholesale Goods"
        }
    ],
    "sg:phone":"+1 260 463 8443",
    "sg:postcode":"46761",
    "sg:province":"IN",
    "sg:tags":[
        "product",
        "mfg"
    ],
    "wof:name":"Tiny Town",
    "wof:placetype":"venue"
},
  "geometry": {"coordinates":[-85.41967699999999,41.639828],"type":"Point"}
}