{
  "type": "Feature",
  "properties": {
    "iso:country":"US",
    "sg:address":"2419 W Jefferson Blvd",
    "sg:city":"Fort Wayne",
    "sg:classifiers":[
        {
            "category":"Restaurant",
            "type":"Food & Drink"
        }
    ],
    "sg:phone":"+1 260 432 6038",
    "sg:postcode":"46802",
    "sg:province":"IN",
    "wof:name":"El Charro Restrnt",
    "wof:placetype":"venue"
},
  "geometry": {"coordinates":[-85.172759,41.07402],"type":"Point"}
}