{
  "type": "Feature",
  "properties": {
    "iso:country":"US",
    "sg:address":"5 Northview Dr",
    "sg:city":"Valparaiso",
    "sg:classifiers":[
        {
            "category":"Professional",
            "subcategory":"Management & Consulting",
            "type":"Services"
        }
    ],
    "sg:phone":"+1 219 462 6903",
    "sg:postcode":"46383",
    "sg:province":"IN",
    "wof:name":"Robert Skadberg",
    "wof:placetype":"venue"
},
  "geometry": {"coordinates":[-87.05992,41.483453],"type":"Point"}
}