{
  "type": "Feature",
  "properties": {
    "iso:country":"US",
    "sg:address":"2011 Bundy Ave",
    "sg:city":"New Castle",
    "sg:classifiers":[
        {
            "category":"Home & Garden",
            "subcategory":"Building Materials",
            "type":"Retail Goods"
        }
    ],
    "sg:phone":"+1 765 529 1156",
    "sg:postcode":"47362",
    "sg:province":"IN",
    "sg:tags":[
        "windows"
    ],
    "wof:name":"Radford's LLC",
    "wof:placetype":"venue"
},
  "geometry": {"coordinates":[-85.382394,39.912859],"type":"Point"}
}