{
  "type": "Feature",
  "properties": {
    "addr:full":"914 W 5th St Mount Vernon IN 47620",
    "addr:housenumber":"914",
    "addr:postcode":"47620",
    "addr:street":"W 5Th St",
    "iso:country":"US",
    "sg:address":"914 W 5th St",
    "sg:city":"Mount Vernon",
    "sg:classifiers":[
        {
            "category":"Building & Trades",
            "subcategory":"Plumbing",
            "type":"Services"
        }
    ],
    "sg:phone":"+1 812 838 3675",
    "sg:postcode":"47620",
    "sg:province":"IN",
    "sg:tags":[
        "contractor"
    ],
    "wof:name":"Eaton David Heating & AC",
    "wof:placetype":"venue"
},
  "geometry": {"coordinates":[-87.90625,37.930411],"type":"Point"}
}