{
  "type": "Feature",
  "properties": {
    "iso:country":"US",
    "sg:address":"7765 S 175 W",
    "sg:city":"Milroy",
    "sg:classifiers":[
        {
            "category":"Manufacturing",
            "subcategory":"Tools & Machinery",
            "type":"Manufacturing & Wholesale Goods"
        }
    ],
    "sg:phone":"+1 765 629 2675",
    "sg:postcode":"46156",
    "sg:province":"IN",
    "sg:tags":[
        "machine",
        "vending"
    ],
    "sg:website":"www.harcourtoutlines.com",
    "wof:name":"Harcourt Outlines Inc",
    "wof:placetype":"venue"
},
  "geometry": {"coordinates":[-85.474034,39.50138],"type":"Point"}
}