{
  "type": "Feature",
  "properties": {
    "iso:country":"US",
    "sg:address":"390 Cmns Mall",
    "sg:city":"Columbus",
    "sg:classifiers":[
        {
            "category":"Museum",
            "type":"Entertainment"
        }
    ],
    "sg:phone":"+1 812 376 2597",
    "sg:postcode":"47201",
    "sg:province":"IN",
    "wof:name":"Indianapolis Museum Of Art",
    "wof:placetype":"venue"
},
  "geometry": {"coordinates":[-85.92205,39.202404],"type":"Point"}
}