{
  "type": "Feature",
  "properties": {
    "addr:full":"3001 N Anthony Blvd Fort Wayne IN 46805",
    "addr:housenumber":"3001",
    "addr:postcode":"46805",
    "addr:street":"N Anthony Blvd",
    "iso:country":"US",
    "sg:address":"3001 N Anthony Blvd",
    "sg:city":"Fort Wayne",
    "sg:classifiers":[
        {
            "category":"Professional",
            "subcategory":"Business Services",
            "type":"Services"
        }
    ],
    "sg:phone":"+1 260 471 0997",
    "sg:postcode":"46805",
    "sg:province":"IN",
    "wof:name":"Notary Service",
    "wof:placetype":"venue"
},
  "geometry": {"coordinates":[-85.115785,41.103757],"type":"Point"}
}