{
  "type": "Feature",
  "properties": {
    "iso:country":"US",
    "sg:address":"7140 Tapper Ave",
    "sg:city":"Hammond",
    "sg:classifiers":[
        {
            "category":"Professional",
            "subcategory":"Management & Consulting",
            "type":"Services"
        }
    ],
    "sg:phone":"+1 219 937 1816",
    "sg:postcode":"46324",
    "sg:province":"IN",
    "sg:tags":[
        "business"
    ],
    "wof:name":"Cme Consulting",
    "wof:placetype":"venue"
},
  "geometry": {"coordinates":[-87.505111,41.583603],"type":"Point"}
}