{
  "type": "Feature",
  "properties": {
    "iso:country":"US",
    "sg:address":"2535 N Capitol Ave",
    "sg:city":"Indianapolis",
    "sg:classifiers":[
        {
            "category":"Building & Trades",
            "subcategory":"Construction",
            "type":"Services"
        }
    ],
    "sg:phone":"+1 317 920 0450",
    "sg:postcode":"46208",
    "sg:province":"IN",
    "sg:tags":[
        "management"
    ],
    "wof:name":"J C Ripberger",
    "wof:placetype":"venue"
},
  "geometry": {"coordinates":[-86.161266,39.80336],"type":"Point"}
}