{
  "type": "Feature",
  "properties": {
    "iso:country":"US",
    "sg:address":"102 S Spring St",
    "sg:city":"Odon",
    "sg:classifiers":[
        {
            "category":"Health Services",
            "subcategory":"Chiropractor",
            "type":"Services"
        }
    ],
    "sg:phone":"+1 812 636 8101",
    "sg:postcode":"47562",
    "sg:province":"IN",
    "wof:name":"Odon Family Chiropractic",
    "wof:placetype":"venue"
},
  "geometry": {"coordinates":[-86.991348,38.842645],"type":"Point"}
}