{
  "type": "Feature",
  "properties": {
    "iso:country":"US",
    "sg:address":"641 Green Rd",
    "sg:city":"Madison",
    "sg:classifiers":[
        {
            "category":"Government",
            "subcategory":"Post Office",
            "type":"Public Place"
        }
    ],
    "sg:phone":"+1 812 273 1188",
    "sg:postcode":"47250",
    "sg:province":"IN",
    "sg:tags":[
        "postal",
        "us"
    ],
    "wof:name":"North Madison Station",
    "wof:placetype":"venue"
},
  "geometry": {"coordinates":[-85.39877,38.761784],"type":"Point"}
}