{
  "type": "Feature",
  "properties": {
    "addr:full":"3001 Charlestown Xing New Albany IN 47150",
    "addr:housenumber":"3001",
    "addr:postcode":"47150",
    "addr:street":"Charlestown Xing",
    "iso:country":"US",
    "sg:address":"3001 Charlestown Xing",
    "sg:city":"New Albany",
    "sg:classifiers":[
        {
            "category":"Utilities",
            "subcategory":"Mobile Phone",
            "type":"Services"
        }
    ],
    "sg:phone":"+1 812 542 0176",
    "sg:postcode":"47150",
    "sg:province":"IN",
    "sg:tags":[
        "telephone",
        "cellular"
    ],
    "wof:name":"Cingular Wireless",
    "wof:placetype":"venue"
},
  "geometry": {"coordinates":[-85.79844199999999,38.352424],"type":"Point"}
}