{
  "type": "Feature",
  "properties": {
    "addr:full":"7901 E State Rd 28-67 Albany IN 47320",
    "addr:housenumber":"7901;28-67",
    "addr:postcode":"47320",
    "addr:street":"E State Rd",
    "iso:country":"US",
    "sg:address":"7901 E State Rd 28-67",
    "sg:city":"Albany",
    "sg:classifiers":[
        {
            "category":"Sports & Exercise",
            "subcategory":"Race Track",
            "type":"Entertainment"
        }
    ],
    "sg:phone":"+1 765 789 8470",
    "sg:postcode":"47320",
    "sg:province":"IN",
    "sg:website":"www.munciedragway.com",
    "wof:name":"Muncie Dragway",
    "wof:placetype":"venue"
},
  "geometry": {"coordinates":[-85.30084600000001,40.291889],"type":"Point"}
}