{
  "type": "Feature",
  "properties": {
    "iso:country":"US",
    "sg:address":"4359 State Rd 1",
    "sg:city":"Hagerstown",
    "sg:classifiers":[
        {
            "category":"Wholesale",
            "subcategory":"Farm Supplies",
            "type":"Manufacturing & Wholesale Goods"
        }
    ],
    "sg:phone":"+1 765 489 6291",
    "sg:postcode":"47346",
    "sg:province":"IN",
    "sg:tags":[
        "feed"
    ],
    "sg:website":"www.admworld.com",
    "wof:name":"Adm Alliance Nutrition",
    "wof:placetype":"venue"
},
  "geometry": {"coordinates":[-85.143566,39.891966],"type":"Point"}
}