{
  "type": "Feature",
  "properties": {
    "iso:country":"US",
    "sg:address":"8708 Chapel Glen Dr",
    "sg:city":"Indianapolis",
    "sg:classifiers":[
        {
            "category":"Freight",
            "type":"Transportation"
        }
    ],
    "sg:phone":"+1 317 441 6263",
    "sg:postcode":"46234",
    "sg:province":"IN",
    "sg:tags":[
        "operator",
        "trucking"
    ],
    "wof:name":"Blachkey Trucking",
    "wof:placetype":"venue"
},
  "geometry": {"coordinates":[-86.31671,39.773187],"type":"Point"}
}