{
  "type": "Feature",
  "properties": {
    "iso:country":"US",
    "sg:address":"247 Pearl St",
    "sg:city":"Fort Wayne",
    "sg:classifiers":[
        {
            "category":"Organizations",
            "subcategory":"Religious Organization",
            "type":"Services"
        }
    ],
    "sg:phone":"+1 260 422 1472",
    "sg:postcode":"46802",
    "sg:province":"IN",
    "sg:tags":[
        "church"
    ],
    "sg:website":"www.churchofthelamb.com",
    "wof:name":"Church Of The Lamb",
    "wof:placetype":"venue"
},
  "geometry": {"coordinates":[-85.143492,41.080263],"type":"Point"}
}