{
  "type": "Feature",
  "properties": {
    "iso:country":"US",
    "sg:address":"5330 Vogel Rd",
    "sg:city":"Evansville",
    "sg:classifiers":[
        {
            "category":"Banks & Credit Unions",
            "subcategory":"Bank",
            "type":"Services"
        }
    ],
    "sg:phone":"+1 812 476 9740",
    "sg:postcode":"47715",
    "sg:province":"IN",
    "sg:tags":[
        "loan",
        "real estate"
    ],
    "wof:name":"Oxford Mortgage Corp",
    "wof:placetype":"venue"
},
  "geometry": {"coordinates":[-87.487006,37.987766],"type":"Point"}
}