{
  "type": "Feature",
  "properties": {
    "iso:country":"US",
    "sg:address":"2525 E 10th St",
    "sg:city":"Anderson",
    "sg:classifiers":[
        {
            "category":"Professional",
            "subcategory":"Management & Consulting",
            "type":"Services"
        }
    ],
    "sg:phone":"+1 765 644 5673",
    "sg:postcode":"46012",
    "sg:province":"IN",
    "wof:name":"American Weight Loss Center In",
    "wof:placetype":"venue"
},
  "geometry": {"coordinates":[-85.646518,40.105788],"type":"Point"}
}