{
  "type": "Feature",
  "properties": {
    "iso:country":"US",
    "sg:address":"3800 Shelby St",
    "sg:city":"Indianapolis",
    "sg:classifiers":[
        {
            "category":"Wholesale",
            "subcategory":"Vending Machines",
            "type":"Manufacturing & Wholesale Goods"
        }
    ],
    "sg:phone":"+1 317 786 1454",
    "sg:postcode":"46227",
    "sg:province":"IN",
    "wof:name":"Canteen Service Co",
    "wof:placetype":"venue"
},
  "geometry": {"coordinates":[-86.13949100000001,39.708961],"type":"Point"}
}