{
  "type": "Feature",
  "properties": {
    "addr:full":"1100 Pidco Dr Plymouth IN 46563",
    "addr:housenumber":"1100",
    "addr:postcode":"46563",
    "addr:street":"Pidco Dr",
    "iso:country":"US",
    "sg:address":"1100 Pidco Dr",
    "sg:city":"Plymouth",
    "sg:classifiers":[
        {
            "category":"Manufacturing",
            "subcategory":"Paper Products",
            "type":"Manufacturing & Wholesale Goods"
        }
    ],
    "sg:phone":"+1 574 936 5788",
    "sg:postcode":"46563",
    "sg:province":"IN",
    "sg:tags":[
        "converter"
    ],
    "wof:name":"GMI Group",
    "wof:placetype":"venue"
},
  "geometry": {"coordinates":[-86.325045,41.351524],"type":"Point"}
}