{
  "type": "Feature",
  "properties": {
    "iso:country":"US",
    "sg:address":"4104 Lincoln Way E",
    "sg:city":"Mishawaka",
    "sg:classifiers":[
        {
            "category":"Retail",
            "subcategory":"Self-service Laundry",
            "type":"Services"
        }
    ],
    "sg:phone":"+1 574 255 3522",
    "sg:postcode":"46544",
    "sg:province":"IN",
    "wof:name":"Violet Ray Laundromat",
    "wof:placetype":"venue"
},
  "geometry": {"coordinates":[-86.113281,41.663367],"type":"Point"}
}