{
  "type": "Feature",
  "properties": {
    "iso:country":"US",
    "sg:address":"1200 W Columbia St",
    "sg:city":"Evansville",
    "sg:classifiers":[
        {
            "category":"Shopping",
            "type":"Retail Goods"
        }
    ],
    "sg:phone":"+1 812 425 0628",
    "sg:postcode":"47710",
    "sg:province":"IN",
    "sg:tags":[
        "trophy",
        "medal",
        "award"
    ],
    "wof:name":"Tri-State Trophies",
    "wof:placetype":"venue"
},
  "geometry": {"coordinates":[-87.58219099999999,37.984936],"type":"Point"}
}