{
  "type": "Feature",
  "properties": {
    "iso:country":"US",
    "sg:address":"2630 US Hwy 31 S",
    "sg:city":"Greenwood",
    "sg:classifiers":[
        {
            "category":"Building & Trades",
            "subcategory":"Landscaping Services",
            "type":"Services"
        }
    ],
    "sg:phone":"+1 317 422 1236",
    "sg:postcode":"46143",
    "sg:province":"IN",
    "sg:tags":[
        "tree"
    ],
    "wof:name":"South Central Tree Svc",
    "wof:placetype":"venue"
},
  "geometry": {"coordinates":[-86.09856499999999,39.579821],"type":"Point"}
}