{
  "type": "Feature",
  "properties": {
    "iso:country":"US",
    "sg:address":"325 N 9th St",
    "sg:city":"Lafayette",
    "sg:classifiers":[
        {
            "category":"Insurance",
            "subcategory":"Insurance Agent",
            "type":"Services"
        }
    ],
    "sg:phone":"+1 765 742 5411",
    "sg:postcode":"47904",
    "sg:province":"IN",
    "wof:name":"RME Insurance",
    "wof:placetype":"venue"
},
  "geometry": {"coordinates":[-86.88675499999999,40.420711],"type":"Point"}
}