{
  "type": "Feature",
  "properties": {
    "iso:country":"US",
    "sg:address":"930 N Main St",
    "sg:city":"Milan",
    "sg:classifiers":[
        {
            "category":"Wholesale",
            "subcategory":"Motor Vehicles",
            "type":"Manufacturing & Wholesale Goods"
        }
    ],
    "sg:phone":"+1 812 654 2849",
    "sg:postcode":"47031",
    "sg:province":"IN",
    "sg:tags":[
        "automobile",
        "truck",
        "broker"
    ],
    "wof:name":"Milan Auto Sales",
    "wof:placetype":"venue"
},
  "geometry": {"coordinates":[-85.131511,39.132168],"type":"Point"}
}