{
  "type": "Feature",
  "properties": {
    "iso:country":"US",
    "sg:address":"14024 Buena Vista Rd",
    "sg:city":"Rushville",
    "sg:classifiers":[
        {
            "category":"Government",
            "subcategory":"Office",
            "type":"Public Place"
        }
    ],
    "sg:phone":"+1 765 679 1700",
    "sg:postcode":"46173",
    "sg:province":"IN",
    "sg:tags":[
        "village"
    ],
    "wof:name":"Posey Township Trustee",
    "wof:placetype":"venue"
},
  "geometry": {"coordinates":[-85.289,39.498355],"type":"Point"}
}