{
  "type": "Feature",
  "properties": {
    "iso:country":"US",
    "sg:address":"1300 N Pennsylvania St",
    "sg:city":"Indianapolis",
    "sg:classifiers":[
        {
            "category":"Travel",
            "subcategory":"Hotels & Motels",
            "type":"Entertainment"
        }
    ],
    "sg:phone":"+1 317 822 9500",
    "sg:postcode":"46202",
    "sg:province":"IN",
    "wof:name":"Choice Hotels Intl",
    "wof:placetype":"venue"
},
  "geometry": {"coordinates":[-86.15577999999999,39.785742],"type":"Point"}
}