{
  "type": "Feature",
  "properties": {
    "iso:country":"US",
    "sg:address":"2340 E 10th St",
    "sg:city":"Indianapolis",
    "sg:classifiers":[
        {
            "category":"Health Services",
            "subcategory":"Medical Lab",
            "type":"Services"
        }
    ],
    "sg:phone":"+1 317 634 8739",
    "sg:postcode":"46201",
    "sg:province":"IN",
    "sg:tags":[
        "laboratory"
    ],
    "wof:name":"Laboratory Corp Of America",
    "wof:placetype":"venue"
},
  "geometry": {"coordinates":[-86.121809,39.781406],"type":"Point"}
}