{
  "type": "Feature",
  "properties": {
    "addr:full":"2211 Raymond Park Dr Indianapolis IN 46239",
    "addr:housenumber":"2211",
    "addr:postcode":"46239",
    "addr:street":"Raymond Park Dr",
    "iso:country":"US",
    "sg:address":"2211 Raymond Park Dr",
    "sg:city":"Indianapolis",
    "sg:classifiers":[
        {
            "category":"Building & Trades",
            "subcategory":"Construction",
            "type":"Services"
        }
    ],
    "sg:phone":"+1 317 357 5282",
    "sg:postcode":"46239",
    "sg:province":"IN",
    "sg:tags":[
        "home",
        "builder"
    ],
    "wof:name":"KB Home",
    "wof:placetype":"venue"
},
  "geometry": {"coordinates":[-86.022497,39.739545],"type":"Point"}
}