{
  "type": "Feature",
  "properties": {
    "iso:country":"US",
    "sg:address":"10477 State Rd 48",
    "sg:city":"Aurora",
    "sg:classifiers":[
        {
            "category":"Food & Beverages",
            "subcategory":"Groceries & Convenience Stores",
            "type":"Retail Goods"
        }
    ],
    "sg:phone":"+1 812 926 3606",
    "sg:postcode":"47001",
    "sg:province":"IN",
    "sg:tags":[
        "grocer"
    ],
    "wof:name":"Manchester Market",
    "wof:placetype":"venue"
},
  "geometry": {"coordinates":[-85.012576,39.152191],"type":"Point"}
}