{
  "type": "Feature",
  "properties": {
    "addr:full":"6234 Co Rd W 100 N Kokomo IN 46901",
    "addr:housenumber":"6234;100",
    "addr:postcode":"46901",
    "addr:street":"Co Rd W;N",
    "iso:country":"US",
    "sg:address":"6234 Co Rd W 100 N",
    "sg:city":"Kokomo",
    "sg:classifiers":[
        {
            "category":"Professional",
            "subcategory":"Management & Consulting",
            "type":"Services"
        }
    ],
    "sg:phone":"+1 765 457 0395",
    "sg:postcode":"46901",
    "sg:province":"IN",
    "sg:tags":[
        "business"
    ],
    "wof:name":"Gillette Spectroscopy Ser",
    "wof:placetype":"venue"
},
  "geometry": {"coordinates":[-86.249297,40.48967],"type":"Point"}
}