{
  "type": "Feature",
  "properties": {
    "iso:country":"US",
    "sg:address":"111 E Washington St",
    "sg:city":"Goshen",
    "sg:classifiers":[
        {
            "category":"Shopping",
            "subcategory":"Hobbies, Toys, & Games",
            "type":"Retail Goods"
        }
    ],
    "sg:phone":"+1 574 534 7662",
    "sg:postcode":"46528",
    "sg:province":"IN",
    "wof:name":"Mike's Toy Store",
    "wof:placetype":"venue"
},
  "geometry": {"coordinates":[-85.699051,41.524344],"type":"Point"}
}