{
  "type": "Feature",
  "properties": {
    "iso:country":"US",
    "sg:address":"8507 Castleton Blvd",
    "sg:city":"Indianapolis",
    "sg:phone":"+1 317 849 2434",
    "sg:postcode":"46256",
    "sg:province":"IN",
    "sg:tags":[
        "product",
        "petroleum"
    ],
    "wof:name":"Quaker State Corporation",
    "wof:placetype":"venue"
},
  "geometry": {"coordinates":[-86.01536,39.91163],"type":"Point"}
}