{
  "type": "Feature",
  "properties": {
    "iso:country":"US",
    "sg:address":"908 N Walnut St",
    "sg:city":"Bloomington",
    "sg:classifiers":[
        {
            "category":"Autos & Motor Vehicles",
            "subcategory":"Automobile Sales",
            "type":"Retail Goods"
        },
        {
            "category":"Airline",
            "type":"Transportation"
        }
    ],
    "sg:phone":"+1 812 339 7269",
    "sg:postcode":"47404",
    "sg:province":"IN",
    "sg:tags":[
        "shuttle",
        "airport",
        "limo"
    ],
    "sg:website":"www.classictouchlimo.com",
    "wof:name":"Classic Touch Limousine Service Inc",
    "wof:placetype":"venue"
},
  "geometry": {"coordinates":[-86.533537,39.174983],"type":"Point"}
}