{
  "type": "Feature",
  "properties": {
    "iso:country":"US",
    "sg:address":"7295 W Johnson Rd",
    "sg:city":"Michigan City",
    "sg:classifiers":[
        {
            "category":"Home & Garden",
            "subcategory":"Carpets & Floor Coverings",
            "type":"Retail Goods"
        }
    ],
    "sg:phone":"+1 219 874 3252",
    "sg:postcode":"46360",
    "sg:province":"IN",
    "sg:tags":[
        "dealer",
        "rug"
    ],
    "wof:name":"Carpet Town",
    "wof:placetype":"venue"
},
  "geometry": {"coordinates":[-86.84075900000001,41.668851],"type":"Point"}
}