{
  "type": "Feature",
  "properties": {
    "addr:full":"735 W Greenview Ave South Bend IN 46619",
    "addr:housenumber":"735",
    "addr:postcode":"46619",
    "addr:street":"W Greenview Ave",
    "iso:country":"US",
    "sg:address":"735 W Greenview Ave",
    "sg:city":"South Bend",
    "sg:classifiers":[
        {
            "category":"Wholesale",
            "subcategory":"Home Furnishings",
            "type":"Manufacturing & Wholesale Goods"
        }
    ],
    "sg:phone":"+1 574 287 8830",
    "sg:postcode":"46619",
    "sg:province":"IN",
    "wof:name":"Wayne Keppler Decorations",
    "wof:placetype":"venue"
},
  "geometry": {"coordinates":[-86.309151,41.665276],"type":"Point"}
}