{
  "type": "Feature",
  "properties": {
    "addr:full":"1061 E 236th St Sheridan IN 46069",
    "addr:housenumber":"1061",
    "addr:postcode":"46069",
    "addr:street":"E 236Th St",
    "iso:country":"US",
    "sg:address":"1061 E 236th St",
    "sg:city":"Sheridan",
    "sg:classifiers":[
        {
            "category":"Wholesale",
            "subcategory":"Groceries",
            "type":"Manufacturing & Wholesale Goods"
        }
    ],
    "sg:phone":"+1 317 758 4331",
    "sg:postcode":"46069",
    "sg:province":"IN",
    "sg:tags":[
        "syrup"
    ],
    "wof:name":"R W Pickett & Son Sorghum Mfg",
    "wof:placetype":"venue"
},
  "geometry": {"coordinates":[-86.14356100000001,40.130828],"type":"Point"}
}