{
  "type": "Feature",
  "properties": {
    "iso:country":"US",
    "sg:address":"68206 Co Rd 23",
    "sg:city":"New Paris",
    "sg:classifiers":[
        {
            "category":"Professional",
            "type":"Services"
        }
    ],
    "sg:phone":"+1 574 831 3784",
    "sg:postcode":"46553",
    "sg:province":"IN",
    "sg:tags":[
        "establishment"
    ],
    "wof:name":"B & C Equipment",
    "wof:placetype":"venue"
},
  "geometry": {"coordinates":[-85.828069,41.502662],"type":"Point"}
}