{
  "type": "Feature",
  "properties": {
    "iso:country":"US",
    "sg:address":"10101 Broadway",
    "sg:city":"Crown Point",
    "sg:classifiers":[
        {
            "category":"Retail",
            "subcategory":"Funeral Services",
            "type":"Services"
        }
    ],
    "sg:phone":"+1 219 769 0044",
    "sg:postcode":"46307",
    "sg:province":"IN",
    "wof:name":"Burns Funeral Home Inc",
    "wof:placetype":"venue"
},
  "geometry": {"coordinates":[-87.33553499999999,41.434823],"type":"Point"}
}