{
  "type": "Feature",
  "properties": {
    "iso:country":"US",
    "sg:address":"4770 Duffy Rd",
    "sg:city":"Floyds Knobs",
    "sg:classifiers":[
        {
            "category":"Food & Beverages",
            "subcategory":"Groceries & Convenience Stores",
            "type":"Retail Goods"
        }
    ],
    "sg:phone":"+1 812 923 7757",
    "sg:postcode":"47119",
    "sg:province":"IN",
    "wof:name":"Sav-A-Step Food Mart",
    "wof:placetype":"venue"
},
  "geometry": {"coordinates":[-85.897537,38.309459],"type":"Point"}
}