{
  "type": "Feature",
  "properties": {
    "iso:country":"US",
    "sg:address":"1314 E Memorial Dr",
    "sg:city":"Muncie",
    "sg:classifiers":[
        {
            "category":"Retail",
            "subcategory":"Repair Shop",
            "type":"Services"
        }
    ],
    "sg:phone":"+1 765 289 9442",
    "sg:postcode":"47302",
    "sg:province":"IN",
    "sg:tags":[
        "scooter",
        "motorcycle",
        "motor"
    ],
    "wof:name":"Muncie Custom Cycle & Pawn",
    "wof:placetype":"venue"
},
  "geometry": {"coordinates":[-85.37131100000001,40.178385],"type":"Point"}
}