{
  "type": "Feature",
  "properties": {
    "iso:country":"US",
    "sg:address":"7998 Georgetown Rd",
    "sg:city":"Indianapolis",
    "sg:classifiers":[
        {
            "category":"Real Estate",
            "subcategory":"Real Estate Agent",
            "type":"Services"
        }
    ],
    "sg:phone":"+1 317 637 4000",
    "sg:postcode":"46268",
    "sg:province":"IN",
    "sg:tags":[
        "consultant"
    ],
    "wof:name":"ABM Janitorial",
    "wof:placetype":"venue"
},
  "geometry": {"coordinates":[-86.240977,39.899285],"type":"Point"}
}