{
  "type": "Feature",
  "properties": {
    "iso:country":"US",
    "sg:address":"4635 W 84th St",
    "sg:city":"Indianapolis",
    "sg:classifiers":[
        {
            "category":"Shopping",
            "subcategory":"Stationery & Office Supplies",
            "type":"Retail Goods"
        }
    ],
    "sg:phone":"+1 317 824 5757",
    "sg:postcode":"46268",
    "sg:province":"IN",
    "sg:tags":[
        "packing",
        "materials-shipping"
    ],
    "sg:website":"http://www.insertec.com",
    "wof:name":"Insertec Inc.",
    "wof:placetype":"venue"
},
  "geometry": {"coordinates":[-86.236735,39.907028],"type":"Point"}
}