{
  "type": "Feature",
  "properties": {
    "iso:country":"US",
    "sg:address":"1604 S Wabash St",
    "sg:city":"Wabash",
    "sg:classifiers":[
        {
            "category":"Shopping",
            "subcategory":"Bicycles & Sporting Goods",
            "type":"Retail Goods"
        }
    ],
    "sg:phone":"+1 260 563 4686",
    "sg:postcode":"46992",
    "sg:province":"IN",
    "wof:name":"Sports Unlimited",
    "wof:placetype":"venue"
},
  "geometry": {"coordinates":[-85.819953,40.782689],"type":"Point"}
}