{
  "type": "Feature",
  "properties": {
    "iso:country":"US",
    "sg:address":"645 N Buckeye St",
    "sg:city":"Osgood",
    "sg:classifiers":[
        {
            "category":"Food & Beverages",
            "subcategory":"Groceries & Convenience Stores",
            "type":"Retail Goods"
        }
    ],
    "sg:phone":"+1 812 689 5128",
    "sg:postcode":"47037",
    "sg:province":"IN",
    "wof:name":"Day-Nite Food Mart",
    "wof:placetype":"venue"
},
  "geometry": {"coordinates":[-85.292949,39.133074],"type":"Point"}
}