{
  "type": "Feature",
  "properties": {
    "iso:country":"US",
    "sg:address":"610 Pine Ln",
    "sg:city":"Ellettsville",
    "sg:classifiers":[
        {
            "category":"Autos & Motor Vehicles",
            "subcategory":"Automobile Sales",
            "type":"Retail Goods"
        }
    ],
    "sg:phone":"+1 812 824 8828",
    "sg:postcode":"47429",
    "sg:province":"IN",
    "sg:tags":[
        "truck"
    ],
    "wof:name":"Mossbrucker H & C Xpress Truck",
    "wof:placetype":"venue"
},
  "geometry": {"coordinates":[-86.628028,39.232542],"type":"Point"}
}