{
  "type": "Feature",
  "properties": {
    "iso:country":"US",
    "sg:address":"2274 E 116th St",
    "sg:city":"Carmel",
    "sg:classifiers":[
        {
            "category":"Professional",
            "type":"Services"
        }
    ],
    "sg:phone":"+1 317 575 8661",
    "sg:postcode":"46032",
    "sg:province":"IN",
    "wof:name":"Central Guarantees Inc",
    "wof:placetype":"venue"
},
  "geometry": {"coordinates":[-86.116966,39.956731],"type":"Point"}
}