{
  "type": "Feature",
  "properties": {
    "addr:full":"5152 E 50 N Laporte IN 46350",
    "addr:housenumber":"5152;50",
    "addr:postcode":"46350",
    "addr:street":"E;N Laporte",
    "iso:country":"US",
    "sg:address":"5152 E 50 N",
    "sg:city":"Laporte",
    "sg:classifiers":[
        {
            "category":"Building & Trades",
            "subcategory":"Landscaping Services",
            "type":"Services"
        }
    ],
    "sg:phone":"+1 219 369 9227",
    "sg:postcode":"46350",
    "sg:province":"IN",
    "sg:tags":[
        "landscape",
        "contractor"
    ],
    "wof:name":"Bornell Landscaping & Design",
    "wof:placetype":"venue"
},
  "geometry": {"coordinates":[-86.59867199999999,41.616286],"type":"Point"}
}