{
  "type": "Feature",
  "properties": {
    "iso:country":"US",
    "sg:address":"3913 Merchant Rd",
    "sg:city":"Fort Wayne",
    "sg:classifiers":[
        {
            "category":"Professional",
            "subcategory":"Engineering",
            "type":"Services"
        }
    ],
    "sg:phone":"+1 260 497 8127",
    "sg:postcode":"46818",
    "sg:province":"IN",
    "sg:tags":[
        "engineer"
    ],
    "wof:name":"Geotechnical & Materials Eng",
    "wof:placetype":"venue"
},
  "geometry": {"coordinates":[-85.196242,41.136831],"type":"Point"}
}