{
  "type": "Feature",
  "properties": {
    "iso:country":"US",
    "sg:address":"1020 Professional Blvd",
    "sg:city":"Evansville",
    "sg:classifiers":[
        {
            "category":"Professional",
            "subcategory":"Research",
            "type":"Services"
        }
    ],
    "sg:phone":"+1 812 473 0141",
    "sg:postcode":"47714",
    "sg:province":"IN",
    "sg:tags":[
        "medical"
    ],
    "wof:name":"Research Solutions",
    "wof:placetype":"venue"
},
  "geometry": {"coordinates":[-87.499573,37.961984],"type":"Point"}
}