{
  "type": "Feature",
  "properties": {
    "iso:country":"US",
    "sg:address":"6520 Cornell Ave",
    "sg:city":"Indianapolis",
    "sg:classifiers":[
        {
            "category":"Autos & Motor Vehicles",
            "subcategory":"Motorcycle Sales",
            "type":"Retail Goods"
        }
    ],
    "sg:phone":"+1 317 595 0269",
    "sg:postcode":"46220",
    "sg:province":"IN",
    "sg:tags":[
        "scooter"
    ],
    "wof:name":"Revard BMW",
    "wof:placetype":"venue"
},
  "geometry": {"coordinates":[-86.142505,39.873618],"type":"Point"}
}