{
  "type": "Feature",
  "properties": {
    "iso:country":"US",
    "sg:address":"516 N Main St",
    "sg:city":"Columbia City",
    "sg:classifiers":[
        {
            "category":"Food & Beverages",
            "subcategory":"Groceries & Convenience Stores",
            "type":"Retail Goods"
        }
    ],
    "sg:phone":"+1 260 244 4964",
    "sg:postcode":"46725",
    "sg:province":"IN",
    "wof:name":"Lassus Brothers Oil",
    "wof:placetype":"venue"
},
  "geometry": {"coordinates":[-85.48665,41.165702],"type":"Point"}
}