{
  "type": "Feature",
  "properties": {
    "addr:full":"8241 Wicker Ave Saint John IN 46373",
    "addr:housenumber":"8241",
    "addr:postcode":"46373",
    "addr:street":"Wicker Ave",
    "iso:country":"US",
    "sg:address":"8241 Wicker Ave",
    "sg:city":"Saint John",
    "sg:classifiers":[
        {
            "category":"Restaurant",
            "type":"Food & Drink"
        }
    ],
    "sg:phone":"+1 219 365 5200",
    "sg:postcode":"46373",
    "sg:province":"IN",
    "sg:tags":[
        "eating"
    ],
    "wof:name":"Rosatis Pizza",
    "wof:placetype":"venue"
},
  "geometry": {"coordinates":[-87.470315,41.467898],"type":"Point"}
}