{
  "type": "Feature",
  "properties": {
    "iso:country":"US",
    "sg:address":"307 S Washington St",
    "sg:city":"Reynolds",
    "sg:classifiers":[
        {
            "category":"Government",
            "subcategory":"Office",
            "type":"Public Place"
        }
    ],
    "sg:phone":"+1 219 984 6425",
    "sg:postcode":"47980",
    "sg:province":"IN",
    "sg:tags":[
        "village"
    ],
    "wof:name":"Reynolds Clerk",
    "wof:placetype":"venue"
},
  "geometry": {"coordinates":[-86.873823,40.748093],"type":"Point"}
}