{
  "type": "Feature",
  "properties": {
    "addr:full":"30 Taney Pl Merrillville IN 46410",
    "addr:housenumber":"30",
    "addr:postcode":"46410",
    "addr:street":"Taney Pl",
    "iso:country":"US",
    "sg:address":"30 Taney Pl",
    "sg:city":"Merrillville",
    "sg:classifiers":[
        {
            "category":"Fast Food",
            "type":"Food & Drink"
        },
        {
            "category":"Restaurant",
            "type":"Food & Drink"
        }
    ],
    "sg:phone":"+1 219 769 4330",
    "sg:postcode":"46410",
    "sg:province":"IN",
    "sg:tags":[
        "hamburger",
        "hot",
        "dog",
        "american",
        "take",
        "chicken"
    ],
    "sg:website":"http://www.mcdonalds.com",
    "wof:name":"McDonald's",
    "wof:placetype":"venue"
},
  "geometry": {"coordinates":[-87.372513,41.473598],"type":"Point"}
}