{
  "type": "Feature",
  "properties": {
    "iso:country":"US",
    "sg:address":"2415 W Thompson Rd",
    "sg:city":"Indianapolis",
    "sg:classifiers":[
        {
            "category":"Wholesale",
            "subcategory":"Machinery & Supplies",
            "type":"Manufacturing & Wholesale Goods"
        }
    ],
    "sg:phone":"+1 317 787 3400",
    "sg:postcode":"46217",
    "sg:province":"IN",
    "sg:tags":[
        "equipment",
        "material",
        "handling"
    ],
    "sg:website":"www.kensar.com",
    "wof:name":"Kensar Used & Rental Equipment",
    "wof:placetype":"venue"
},
  "geometry": {"coordinates":[-86.202169,39.692107],"type":"Point"}
}