{
  "type": "Feature",
  "properties": {
    "iso:country":"US",
    "sg:address":"1343 Sagamore Pkwy N",
    "sg:city":"Lafayette",
    "sg:classifiers":[
        {
            "category":"Retail",
            "subcategory":"Veterinary Services",
            "type":"Services"
        }
    ],
    "sg:phone":"+1 765 449 2001",
    "sg:postcode":"47904",
    "sg:province":"IN",
    "sg:tags":[
        "veterinarian"
    ],
    "wof:name":"Animal Emergency Clinic",
    "wof:placetype":"venue"
},
  "geometry": {"coordinates":[-86.85842,40.42812],"type":"Point"}
}