{
  "type": "Feature",
  "properties": {
    "addr:full":"2466 E. 146th St Carmel IN 46033",
    "addr:housenumber":"2466",
    "addr:postcode":"46033",
    "addr:street":"E. 146Th St",
    "iso:country":"US",
    "sg:address":"2466 E. 146th St",
    "sg:city":"Carmel",
    "sg:classifiers":[
        {
            "category":"Ice Cream",
            "type":"Food & Drink"
        }
    ],
    "sg:phone":"+1 317 705 1855",
    "sg:postcode":"46033",
    "sg:province":"IN",
    "sg:tags":[
        "frozen",
        "yogurt"
    ],
    "sg:website":"www.handelsicecream.com",
    "wof:name":"Handel's Homemade Ice Cream",
    "wof:placetype":"venue"
},
  "geometry": {"coordinates":[-86.11940800000001,40.001874],"type":"Point"}
}