{
  "type": "Feature",
  "properties": {
    "addr:full":"8298 W Chicken Run Rd Madison IN 47250",
    "addr:housenumber":"8298",
    "addr:postcode":"47250",
    "addr:street":"W Chicken Run Rd",
    "iso:country":"US",
    "sg:address":"8298 W Chicken Run Rd",
    "sg:city":"Madison",
    "sg:classifiers":[
        {
            "category":"Professional",
            "subcategory":"Accounting & Tax Preparation",
            "type":"Services"
        }
    ],
    "sg:phone":"+1 812 866 8272",
    "sg:postcode":"47250",
    "sg:province":"IN",
    "sg:tags":[
        "accountant"
    ],
    "wof:name":"Reardon & Co",
    "wof:placetype":"venue"
},
  "geometry": {"coordinates":[-85.54125500000001,38.766894],"type":"Point"}
}