{
  "type": "Feature",
  "properties": {
    "iso:country":"US",
    "sg:address":"2150 N Purdum St",
    "sg:city":"Kokomo",
    "sg:classifiers":[
        {
            "category":"Retail",
            "subcategory":"Repair Shop",
            "type":"Services"
        }
    ],
    "sg:phone":"+1 765 457 8883",
    "sg:postcode":"46901",
    "sg:province":"IN",
    "sg:tags":[
        "upholsterer"
    ],
    "wof:name":"Bagwell's Upholstery Shop",
    "wof:placetype":"venue"
},
  "geometry": {"coordinates":[-86.124129,40.506364],"type":"Point"}
}