{
  "type": "Feature",
  "properties": {
    "iso:country":"US",
    "sg:address":"302 W 11th St",
    "sg:city":"Mishawaka",
    "sg:classifiers":[
        {
            "category":"Organizations",
            "subcategory":"Community Association",
            "type":"Services"
        }
    ],
    "sg:phone":"+1 574 255 8729",
    "sg:postcode":"46544",
    "sg:province":"IN",
    "sg:tags":[
        "club"
    ],
    "wof:name":"De Amicis Club",
    "wof:placetype":"venue"
},
  "geometry": {"coordinates":[-86.18458099999999,41.652695],"type":"Point"}
}