{
  "type": "Feature",
  "properties": {
    "iso:country":"US",
    "sg:address":"6501 Grape Rd",
    "sg:city":"Mishawaka",
    "sg:classifiers":[
        {
            "category":"Shopping",
            "subcategory":"Clothing, Apparel, & Fashions",
            "type":"Retail Goods"
        }
    ],
    "sg:phone":"+1 574 273 0850",
    "sg:postcode":"46545",
    "sg:province":"IN",
    "sg:tags":[
        "lingerie"
    ],
    "sg:website":"www.victoriassecret.com",
    "wof:name":"Victoria's Secret",
    "wof:placetype":"venue"
},
  "geometry": {"coordinates":[-86.187781,41.716898],"type":"Point"}
}