{
  "type": "Feature",
  "properties": {
    "iso:country":"US",
    "sg:address":"116 S Indiana Ave",
    "sg:city":"Sellersburg",
    "sg:classifiers":[
        {
            "category":"Shopping",
            "subcategory":"Pharmacy",
            "type":"Retail Goods"
        }
    ],
    "sg:phone":"+1 812 246 3421",
    "sg:postcode":"47172",
    "sg:province":"IN",
    "wof:name":"Disbro's Drugs & Gifts",
    "wof:placetype":"venue"
},
  "geometry": {"coordinates":[-85.756713,38.398194],"type":"Point"}
}