{
  "type": "Feature",
  "properties": {
    "iso:country":"US",
    "sg:address":"850 Crown Ct",
    "sg:city":"Crown Point",
    "sg:classifiers":[
        {
            "category":"Building & Trades",
            "subcategory":"Construction",
            "type":"Services"
        }
    ],
    "sg:phone":"+1 219 531 5774",
    "sg:postcode":"46307",
    "sg:province":"IN",
    "sg:tags":[
        "general",
        "contractor"
    ],
    "wof:name":"Rockville Developments",
    "wof:placetype":"venue"
},
  "geometry": {"coordinates":[-87.35300100000001,41.431275],"type":"Point"}
}