{
  "type": "Feature",
  "properties": {
    "iso:country":"US",
    "sg:address":"3014 Pitt St",
    "sg:city":"Anderson",
    "sg:classifiers":[
        {
            "category":"Personal",
            "subcategory":"Beauty Salon",
            "type":"Services"
        }
    ],
    "sg:phone":"+1 765 644 4566",
    "sg:postcode":"46016",
    "sg:province":"IN",
    "sg:tags":[
        "cosmetologist"
    ],
    "wof:name":"Nicole M Kennedy",
    "wof:placetype":"venue"
},
  "geometry": {"coordinates":[-85.662211,40.085284],"type":"Point"}
}