{
  "type": "Feature",
  "properties": {
    "addr:full":"120 E State St Pendleton IN 46064",
    "addr:housenumber":"120",
    "addr:postcode":"46064",
    "addr:street":"E State St",
    "iso:country":"US",
    "sg:address":"120 E State St",
    "sg:city":"Pendleton",
    "sg:classifiers":[
        {
            "category":"Government",
            "subcategory":"Police Station",
            "type":"Public Place"
        }
    ],
    "sg:phone":"+1 765 778 3933",
    "sg:postcode":"46064",
    "sg:province":"IN",
    "sg:tags":[
        "department"
    ],
    "wof:name":"Pendleton Police Dept",
    "wof:placetype":"venue"
},
  "geometry": {"coordinates":[-85.74531500000001,40.002407],"type":"Point"}
}