{
  "type": "Feature",
  "properties": {
    "addr:full":"3605 N State Rd 19 Etna Green IN 46524",
    "addr:housenumber":"3605;19",
    "addr:postcode":"46524",
    "addr:street":"N State Rd;Etna Green",
    "iso:country":"US",
    "sg:address":"3605 N State Rd 19",
    "sg:city":"Etna Green",
    "sg:classifiers":[
        {
            "category":"Food & Beverages",
            "subcategory":"Groceries & Convenience Stores",
            "type":"Retail Goods"
        }
    ],
    "sg:phone":"+1 574 858 2577",
    "sg:postcode":"46524",
    "sg:province":"IN",
    "wof:name":"Mike's Mini Mart",
    "wof:placetype":"venue"
},
  "geometry": {"coordinates":[-86.04714199999999,41.285914],"type":"Point"}
}