{
  "type": "Feature",
  "properties": {
    "iso:country":"US",
    "sg:address":"2025 E 21st Ave",
    "sg:city":"Gary",
    "sg:classifiers":[
        {
            "category":"Recreation",
            "type":"Entertainment"
        }
    ],
    "sg:phone":"+1 219 883 9305",
    "sg:postcode":"46407",
    "sg:province":"IN",
    "sg:tags":[
        "parks"
    ],
    "wof:name":"Hatcher Park",
    "wof:placetype":"venue"
},
  "geometry": {"coordinates":[-87.31307700000001,41.580095],"type":"Point"}
}