{
  "type": "Feature",
  "properties": {
    "iso:country":"US",
    "sg:address":"601 Noble Dr",
    "sg:city":"Fort Wayne",
    "sg:classifiers":[
        {
            "category":"Organizations",
            "subcategory":"Non-profit Organization",
            "type":"Services"
        }
    ],
    "sg:phone":"+1 260 484 2543",
    "sg:postcode":"46825",
    "sg:province":"IN",
    "wof:name":"Junior Achievement",
    "wof:placetype":"venue"
},
  "geometry": {"coordinates":[-85.134024,41.119703],"type":"Point"}
}