{
  "type": "Feature",
  "properties": {
    "iso:country":"US",
    "sg:address":"613 W Main St",
    "sg:city":"Farmersburg",
    "sg:classifiers":[
        {
            "category":"Insurance",
            "subcategory":"Insurance Agent",
            "type":"Services"
        }
    ],
    "sg:phone":"+1 812 696 2464",
    "sg:postcode":"47850",
    "sg:province":"IN",
    "wof:name":"Marvin K Harris Insurance",
    "wof:placetype":"venue"
},
  "geometry": {"coordinates":[-87.386184,39.253962],"type":"Point"}
}