{
  "type": "Feature",
  "properties": {
    "iso:country":"US",
    "sg:address":"6440 N State Rd 37",
    "sg:city":"Elwood",
    "sg:classifiers":[
        {
            "category":"Real Estate",
            "subcategory":"Real Estate Operator",
            "type":"Services"
        }
    ],
    "sg:phone":"+1 765 552 7574",
    "sg:postcode":"46036",
    "sg:province":"IN",
    "sg:tags":[
        "property",
        "lessor"
    ],
    "wof:name":"Craig Illa Jeanne",
    "wof:placetype":"venue"
},
  "geometry": {"coordinates":[-85.86263099999999,40.199545],"type":"Point"}
}