{
  "type": "Feature",
  "properties": {
    "iso:country":"US",
    "sg:address":"1630 W Park Rd",
    "sg:city":"Greensburg",
    "sg:classifiers":[
        {
            "category":"Organizations",
            "subcategory":"Community Association",
            "type":"Services"
        }
    ],
    "sg:phone":"+1 812 663 8492",
    "sg:postcode":"47240",
    "sg:province":"IN",
    "sg:tags":[
        "club"
    ],
    "sg:website":"www.greensburgcountryclub.com",
    "wof:name":"Mulligan Grille",
    "wof:placetype":"venue"
},
  "geometry": {"coordinates":[-85.508296,39.328945],"type":"Point"}
}