{
  "type": "Feature",
  "properties": {
    "addr:full":"521 E 86th Ave Merrillville IN 46410",
    "addr:housenumber":"521",
    "addr:postcode":"46410",
    "addr:street":"E 86Th Ave",
    "iso:country":"US",
    "sg:address":"521 E 86th Ave",
    "sg:city":"Merrillville",
    "sg:classifiers":[
        {
            "category":"Health Services",
            "subcategory":"Health Practitioner",
            "type":"Services"
        }
    ],
    "sg:phone":"+1 219 736 2801",
    "sg:postcode":"46410",
    "sg:province":"IN",
    "sg:tags":[
        "therapist",
        "physical"
    ],
    "wof:name":"Integrated Therapy Practice",
    "wof:placetype":"venue"
},
  "geometry": {"coordinates":[-87.32663599999999,41.462729],"type":"Point"}
}