{
  "type": "Feature",
  "properties": {
    "iso:country":"US",
    "sg:address":"8400 Louisiana St",
    "sg:city":"Merrillville",
    "sg:classifiers":[
        {
            "category":"Social Services",
            "subcategory":"Child Care",
            "type":"Services"
        }
    ],
    "sg:phone":"+1 219 757 1957",
    "sg:postcode":"46410",
    "sg:province":"IN",
    "wof:name":"Lake County Child Care Develop",
    "wof:placetype":"venue"
},
  "geometry": {"coordinates":[-87.319782,41.466303],"type":"Point"}
}