{
  "type": "Feature",
  "properties": {
    "addr:full":"901 Alderbrook Ct Crown Point IN 46307",
    "addr:housenumber":"901",
    "addr:postcode":"46307",
    "addr:street":"Alderbrook Ct",
    "iso:country":"US",
    "sg:address":"901 Alderbrook Ct",
    "sg:city":"Crown Point",
    "sg:classifiers":[
        {
            "category":"Building & Trades",
            "subcategory":"Construction",
            "type":"Services"
        }
    ],
    "sg:phone":"+1 219 226 1751",
    "sg:postcode":"46307",
    "sg:province":"IN",
    "sg:tags":[
        "contractor"
    ],
    "wof:name":"Heritage Homes",
    "wof:placetype":"venue"
},
  "geometry": {"coordinates":[-87.37869999999999,41.434601],"type":"Point"}
}