{
  "type": "Feature",
  "properties": {
    "iso:country":"US",
    "sg:address":"130 5th St",
    "sg:city":"North Vernon",
    "sg:classifiers":[
        {
            "category":"Autos & Motor Vehicles",
            "subcategory":"Auto Supplies",
            "type":"Retail Goods"
        }
    ],
    "sg:phone":"+1 812 346 5070",
    "sg:postcode":"47265",
    "sg:province":"IN",
    "sg:tags":[
        "automobile",
        "parts"
    ],
    "wof:name":"Right Auto Parts",
    "wof:placetype":"venue"
},
  "geometry": {"coordinates":[-85.623536,39.00718],"type":"Point"}
}