{
  "type": "Feature",
  "properties": {
    "iso:country":"US",
    "sg:address":"9930 Geist Crossing Dr",
    "sg:city":"Indianapolis",
    "sg:classifiers":[
        {
            "category":"Real Estate",
            "subcategory":"Real Estate Agent",
            "type":"Services"
        }
    ],
    "sg:phone":"+1 317 841 8880",
    "sg:postcode":"46256",
    "sg:province":"IN",
    "sg:website":"http://www.talktotucker.com",
    "wof:name":"Fc Tucker Co Inc Realtors",
    "wof:placetype":"venue"
},
  "geometry": {"coordinates":[-85.992439,39.899172],"type":"Point"}
}