{
  "type": "Feature",
  "properties": {
    "iso:country":"US",
    "sg:address":"2211 Massachusetts Ave",
    "sg:city":"Indianapolis",
    "sg:classifiers":[
        {
            "category":"Wholesale",
            "subcategory":"Machinery & Supplies",
            "type":"Manufacturing & Wholesale Goods"
        }
    ],
    "sg:phone":"+1 317 638 4100",
    "sg:postcode":"46218",
    "sg:province":"IN",
    "sg:tags":[
        "machine",
        "tool"
    ],
    "wof:name":"Machinery Mart Inc",
    "wof:placetype":"venue"
},
  "geometry": {"coordinates":[-86.121146,39.791308],"type":"Point"}
}