{
  "type": "Feature",
  "properties": {
    "iso:country":"US",
    "sg:address":"8424 State Rd 67",
    "sg:city":"Pendleton",
    "sg:classifiers":[
        {
            "category":"Restaurant",
            "type":"Food & Drink"
        }
    ],
    "sg:phone":"+1 765 778 9650",
    "sg:postcode":"46064",
    "sg:province":"IN",
    "wof:name":"Top Notch Cafe Inc",
    "wof:placetype":"venue"
},
  "geometry": {"coordinates":[-85.77033,39.973938],"type":"Point"}
}