{
  "type": "Feature",
  "properties": {
    "iso:country":"US",
    "sg:address":"1808 S Main St",
    "sg:city":"Kokomo",
    "sg:classifiers":[
        {
            "category":"Professional",
            "subcategory":"Management & Consulting",
            "type":"Services"
        }
    ],
    "sg:phone":"+1 765 455 0850",
    "sg:postcode":"46902",
    "sg:province":"IN",
    "sg:tags":[
        "consultant",
        "library"
    ],
    "wof:name":"INCOLSA",
    "wof:placetype":"venue"
},
  "geometry": {"coordinates":[-86.13094,40.464718],"type":"Point"}
}