{
  "type": "Feature",
  "properties": {
    "iso:country":"US",
    "sg:address":"6909 State Rd 1",
    "sg:city":"Spencerville",
    "sg:classifiers":[
        {
            "category":"Government",
            "subcategory":"Post Office",
            "type":"Public Place"
        }
    ],
    "sg:phone":"+1 260 238 4316",
    "sg:postcode":"46788",
    "sg:province":"IN",
    "wof:name":"US Post Office",
    "wof:placetype":"venue"
},
  "geometry": {"coordinates":[-84.921904,41.282101],"type":"Point"}
}