{
  "type": "Feature",
  "properties": {
    "iso:country":"US",
    "sg:address":"6602 Hoover Rd",
    "sg:city":"Indianapolis",
    "sg:classifiers":[
        {
            "category":"Education",
            "subcategory":"School",
            "type":"Public Place"
        }
    ],
    "sg:phone":"+1 317 251 1261",
    "sg:postcode":"46260",
    "sg:province":"IN",
    "sg:website":"www.hhai.org",
    "wof:name":"Hasten Hebrew Academy",
    "wof:placetype":"venue"
},
  "geometry": {"coordinates":[-86.17456199999999,39.87689],"type":"Point"}
}