{
  "type": "Feature",
  "properties": {
    "iso:country":"US",
    "sg:address":"148 E Howard St",
    "sg:city":"Parker City",
    "sg:classifiers":[
        {
            "category":"Organizations",
            "subcategory":"Religious Organization",
            "type":"Services"
        }
    ],
    "sg:phone":"+1 765 468 6517",
    "sg:postcode":"47368",
    "sg:province":"IN",
    "wof:name":"Parker Friends Church",
    "wof:placetype":"venue"
},
  "geometry": {"coordinates":[-85.203478,40.190503],"type":"Point"}
}