{
  "type": "Feature",
  "properties": {
    "iso:country":"US",
    "sg:address":"1092 Crabtree Ln",
    "sg:city":"Chesterton",
    "sg:classifiers":[
        {
            "category":"Wholesale",
            "subcategory":"Auto Parts",
            "type":"Manufacturing & Wholesale Goods"
        }
    ],
    "sg:phone":"+1 219 926 5786",
    "sg:postcode":"46304",
    "sg:province":"IN",
    "sg:tags":[
        "fastener",
        "industrial",
        "supply"
    ],
    "wof:name":"Barnes Distribution",
    "wof:placetype":"venue"
},
  "geometry": {"coordinates":[-87.064717,41.594741],"type":"Point"}
}