{
  "type": "Feature",
  "properties": {
    "iso:country":"US",
    "sg:address":"1076 State Rd 101",
    "sg:city":"Liberty",
    "sg:classifiers":[
        {
            "category":"Recreation",
            "type":"Entertainment"
        }
    ],
    "sg:phone":"+1 765 458 1400",
    "sg:postcode":"47353",
    "sg:province":"IN",
    "sg:tags":[
        "amusement"
    ],
    "wof:name":"Jeff Russell Motor Sports",
    "wof:placetype":"venue"
},
  "geometry": {"coordinates":[-84.93844,39.61569],"type":"Point"}
}