{
  "type": "Feature",
  "properties": {
    "iso:country":"US",
    "sg:address":"225 E 10th St",
    "sg:city":"Indianapolis",
    "sg:classifiers":[
        {
            "category":"Wholesale",
            "subcategory":"Photographic Equipment",
            "type":"Manufacturing & Wholesale Goods"
        }
    ],
    "sg:phone":"+1 317 488 1030",
    "sg:postcode":"46202",
    "sg:province":"IN",
    "sg:tags":[
        "identification"
    ],
    "sg:website":"www.asapident.com",
    "wof:name":"ASAP Identification Ents",
    "wof:placetype":"venue"
},
  "geometry": {"coordinates":[-86.152486,39.781004],"type":"Point"}
}