{
  "type": "Feature",
  "properties": {
    "iso:country":"US",
    "sg:address":"1516 N Main St",
    "sg:city":"Evansville",
    "sg:classifiers":[
        {
            "category":"Wholesale",
            "subcategory":"Construction Materials",
            "type":"Manufacturing & Wholesale Goods"
        }
    ],
    "sg:phone":"+1 812 426 0667",
    "sg:postcode":"47711",
    "sg:province":"IN",
    "sg:tags":[
        "fence"
    ],
    "wof:name":"Tri-State Fence Co",
    "wof:placetype":"venue"
},
  "geometry": {"coordinates":[-87.563729,37.991906],"type":"Point"}
}