{
  "type": "Feature",
  "properties": {
    "iso:country":"US",
    "sg:address":"5342 W 79th St",
    "sg:city":"Indianapolis",
    "sg:classifiers":[
        {
            "category":"Wholesale",
            "subcategory":"Electrical",
            "type":"Manufacturing & Wholesale Goods"
        }
    ],
    "sg:phone":"+1 317 337 2020",
    "sg:postcode":"46268",
    "sg:province":"IN",
    "sg:tags":[
        "control",
        "security",
        "system"
    ],
    "wof:name":"NTC Electronics Inc",
    "wof:placetype":"venue"
},
  "geometry": {"coordinates":[-86.255486,39.896379],"type":"Point"}
}