{
  "type": "Feature",
  "properties": {
    "addr:full":"114 S Ohio St Culver IN 46511",
    "addr:housenumber":"114",
    "addr:postcode":"46511",
    "addr:street":"S Ohio St",
    "iso:country":"US",
    "sg:address":"114 S Ohio St",
    "sg:city":"Culver",
    "sg:classifiers":[
        {
            "category":"Farming",
            "subcategory":"Farm",
            "type":"Manufacturing & Wholesale Goods"
        }
    ],
    "sg:phone":"+1 574 842 3049",
    "sg:postcode":"46511",
    "sg:province":"IN",
    "sg:tags":[
        "crop",
        "general"
    ],
    "wof:name":"Rooster Hill Farm LLC",
    "wof:placetype":"venue"
},
  "geometry": {"coordinates":[-86.424657,41.216587],"type":"Point"}
}