{
  "type": "Feature",
  "properties": {
    "addr:full":"700 N Walnut St Bloomington IN 47404",
    "addr:housenumber":"700",
    "addr:postcode":"47404",
    "addr:street":"N Walnut St",
    "iso:country":"US",
    "sg:address":"700 N Walnut St",
    "sg:city":"Bloomington",
    "sg:classifiers":[
        {
            "category":"Shopping",
            "type":"Retail Goods"
        }
    ],
    "sg:phone":"+1 812 330 1525",
    "sg:postcode":"47404",
    "sg:province":"IN",
    "sg:tags":[
        "chemical"
    ],
    "wof:name":"Jlm Marketing Inc",
    "wof:placetype":"venue"
},
  "geometry": {"coordinates":[-86.533569,39.174393],"type":"Point"}
}