{
  "type": "Feature",
  "properties": {
    "iso:country":"US",
    "sg:address":"2070 N 500 E",
    "sg:city":"Hartford City",
    "sg:phone":"+1 765 348 4874",
    "sg:postcode":"47348",
    "sg:province":"IN",
    "sg:tags":[
        "farm",
        "corn",
        "soybean"
    ],
    "wof:name":"Everett Carney",
    "wof:placetype":"venue"
},
  "geometry": {"coordinates":[-85.278008,40.485373],"type":"Point"}
}