{
  "type": "Feature",
  "properties": {
    "iso:country":"US",
    "sg:address":"412 E Main St",
    "sg:city":"Delphi",
    "sg:classifiers":[
        {
            "category":"Farming",
            "subcategory":"Farm",
            "type":"Manufacturing & Wholesale Goods"
        }
    ],
    "sg:phone":"+1 765 564 5191",
    "sg:postcode":"46923",
    "sg:province":"IN",
    "wof:name":"Underhill Farms",
    "wof:placetype":"venue"
},
  "geometry": {"coordinates":[-86.669779,40.587626],"type":"Point"}
}