{
  "type": "Feature",
  "properties": {
    "iso:country":"US",
    "sg:address":"215 W Main St",
    "sg:city":"Portland",
    "sg:classifiers":[
        {
            "category":"Building & Trades",
            "subcategory":"Plumbing",
            "type":"Services"
        }
    ],
    "sg:phone":"+1 260 726 3517",
    "sg:postcode":"47371",
    "sg:province":"IN",
    "sg:tags":[
        "conditioning",
        "air",
        "system",
        "contractor"
    ],
    "wof:name":"Hanni Plumbing Heating & AC",
    "wof:placetype":"venue"
},
  "geometry": {"coordinates":[-84.97929000000001,40.433252],"type":"Point"}
}