{
  "type": "Feature",
  "properties": {
    "addr:full":"11595 N Meridian St Carmel IN 46032",
    "addr:housenumber":"11595",
    "addr:postcode":"46032",
    "addr:street":"N Meridian St",
    "iso:country":"US",
    "sg:address":"11595 N Meridian St",
    "sg:city":"Carmel",
    "sg:classifiers":[
        {
            "category":"Wholesale",
            "subcategory":"Electrical",
            "type":"Manufacturing & Wholesale Goods"
        }
    ],
    "sg:phone":"+1 317 844 3577",
    "sg:postcode":"46032",
    "sg:province":"IN",
    "sg:tags":[
        "equipment",
        "telephone",
        "system"
    ],
    "wof:name":"Lucent Technologies",
    "wof:placetype":"venue"
},
  "geometry": {"coordinates":[-86.15755299999999,39.956188],"type":"Point"}
}