{
  "type": "Feature",
  "properties": {
    "iso:country":"US",
    "sg:address":"601 N Meridian St",
    "sg:city":"Portland",
    "sg:classifiers":[
        {
            "category":"Shopping",
            "subcategory":"Tobacco",
            "type":"Retail Goods"
        }
    ],
    "sg:phone":"+1 260 726 3370",
    "sg:postcode":"47371",
    "sg:province":"IN",
    "sg:tags":[
        "cigarette",
        "cigar",
        "dealer"
    ],
    "wof:name":"Low Bob's Discount Tobacco",
    "wof:placetype":"venue"
},
  "geometry": {"coordinates":[-84.978028,40.438485],"type":"Point"}
}