{
  "type": "Feature",
  "properties": {
    "iso:country":"US",
    "sg:address":"1833 E 750 N",
    "sg:city":"Leesburg",
    "sg:classifiers":[
        {
            "category":"Retail",
            "subcategory":"Auto Repair",
            "type":"Services"
        }
    ],
    "sg:phone":"+1 574 453 4540",
    "sg:postcode":"46538",
    "sg:province":"IN",
    "sg:tags":[
        "body",
        "automobile",
        "painting"
    ],
    "wof:name":"Leesburg Paint Shop",
    "wof:placetype":"venue"
},
  "geometry": {"coordinates":[-85.809541,41.342035],"type":"Point"}
}