{
  "type": "Feature",
  "properties": {
    "addr:full":"1208 E Glen Park Ave Griffith IN 46319",
    "addr:housenumber":"1208",
    "addr:postcode":"46319",
    "addr:street":"E Glen Park Ave",
    "iso:country":"US",
    "sg:address":"1208 E Glen Park Ave",
    "sg:city":"Griffith",
    "sg:classifiers":[
        {
            "category":"Cinema",
            "subcategory":"Movie Rental",
            "type":"Entertainment"
        }
    ],
    "sg:phone":"+1 219 838 1676",
    "sg:postcode":"46319",
    "sg:province":"IN",
    "sg:tags":[
        "leasing",
        "video",
        "disc",
        "tape"
    ],
    "wof:name":"Family Video",
    "wof:placetype":"venue"
},
  "geometry": {"coordinates":[-87.413167,41.53729],"type":"Point"}
}