{
  "type": "Feature",
  "properties": {
    "iso:country":"US",
    "sg:address":"8188 W Howard Rd",
    "sg:city":"Bloomington",
    "sg:classifiers":[
        {
            "category":"Building & Trades",
            "subcategory":"Landscaping Services",
            "type":"Services"
        }
    ],
    "sg:phone":"+1 812 876 8384",
    "sg:postcode":"47404",
    "sg:province":"IN",
    "wof:name":"C & C Tree Service",
    "wof:placetype":"venue"
},
  "geometry": {"coordinates":[-86.650552,39.188201],"type":"Point"}
}