{
  "type": "Feature",
  "properties": {
    "iso:country":"US",
    "sg:address":"1505 S East St",
    "sg:city":"Indianapolis",
    "sg:classifiers":[
        {
            "category":"Retail",
            "subcategory":"Funeral Services",
            "type":"Services"
        }
    ],
    "sg:phone":"+1 317 262 8488",
    "sg:postcode":"46225",
    "sg:province":"IN",
    "sg:tags":[
        "director"
    ],
    "wof:name":"G H Herrmann Funeral Home Inc",
    "wof:placetype":"venue"
},
  "geometry": {"coordinates":[-86.149462,39.745588],"type":"Point"}
}