{
  "type": "Feature",
  "properties": {
    "iso:country":"US",
    "sg:address":"3022 E 10th St",
    "sg:city":"Indianapolis",
    "sg:classifiers":[
        {
            "category":"Building & Trades",
            "subcategory":"Pest Control",
            "type":"Services"
        }
    ],
    "sg:phone":"+1 317 639 1658",
    "sg:postcode":"46201",
    "sg:province":"IN",
    "wof:name":"Economy Termite Control Co",
    "wof:placetype":"venue"
},
  "geometry": {"coordinates":[-86.11249599999999,39.781432],"type":"Point"}
}