{
  "type": "Feature",
  "properties": {
    "iso:country":"US",
    "sg:address":"9104 Crawfordsville Rd",
    "sg:city":"Indianapolis",
    "sg:classifiers":[
        {
            "category":"Professional",
            "subcategory":"Detective & Security Services",
            "type":"Services"
        }
    ],
    "sg:phone":"+1 317 299 3244",
    "sg:postcode":"46234",
    "sg:province":"IN",
    "sg:tags":[
        "investigator"
    ],
    "wof:name":"American Justice Special",
    "wof:placetype":"venue"
},
  "geometry": {"coordinates":[-86.324461,39.816716],"type":"Point"}
}