{
  "type": "Feature",
  "properties": {
    "iso:country":"US",
    "sg:address":"53510 Laplace Dr",
    "sg:city":"Middlebury",
    "sg:classifiers":[
        {
            "category":"Building & Trades",
            "subcategory":"Plumbing",
            "type":"Services"
        }
    ],
    "sg:phone":"+1 574 825 5464",
    "sg:postcode":"46540",
    "sg:province":"IN",
    "sg:tags":[
        "plumbing",
        "contractor"
    ],
    "wof:name":"Michael's Plumbing Svc",
    "wof:placetype":"venue"
},
  "geometry": {"coordinates":[-85.672128,41.721729],"type":"Point"}
}