{
  "type": "Feature",
  "properties": {
    "iso:country":"US",
    "sg:address":"7807 N Clinton St",
    "sg:city":"Fort Wayne",
    "sg:classifiers":[
        {
            "category":"Building & Trades",
            "subcategory":"Construction",
            "type":"Services"
        }
    ],
    "sg:phone":"+1 260 484 4848",
    "sg:postcode":"46825",
    "sg:province":"IN",
    "sg:tags":[
        "general",
        "contractor"
    ],
    "wof:name":"Tecton Corp",
    "wof:placetype":"venue"
},
  "geometry": {"coordinates":[-85.110364,41.152339],"type":"Point"}
}