{
  "type": "Feature",
  "properties": {
    "iso:country":"US",
    "sg:address":"321 N Center St",
    "sg:city":"Plymouth",
    "sg:classifiers":[
        {
            "category":"Organizations",
            "subcategory":"Religious Organization",
            "type":"Services"
        }
    ],
    "sg:phone":"+1 574 936 3927",
    "sg:postcode":"46563",
    "sg:province":"IN",
    "wof:name":"Indiana KY Cnfrence Untd Churc",
    "wof:placetype":"venue"
},
  "geometry": {"coordinates":[-86.310718,41.342355],"type":"Point"}
}