{
  "type": "Feature",
  "properties": {
    "iso:country":"US",
    "sg:address":"1307 W Main St",
    "sg:city":"Mitchell",
    "sg:classifiers":[
        {
            "category":"Food & Beverages",
            "subcategory":"Groceries & Convenience Stores",
            "type":"Retail Goods"
        }
    ],
    "sg:phone":"+1 812 849 4513",
    "sg:postcode":"47446",
    "sg:province":"IN",
    "sg:tags":[
        "grocer"
    ],
    "wof:name":"Mills Market",
    "wof:placetype":"venue"
},
  "geometry": {"coordinates":[-86.483769,38.731731],"type":"Point"}
}