{
  "type": "Feature",
  "properties": {
    "iso:country":"US",
    "sg:address":"8655 River Crossing Blvd",
    "sg:city":"Indianapolis",
    "sg:classifiers":[
        {
            "category":"Home & Garden",
            "subcategory":"Furniture",
            "type":"Retail Goods"
        }
    ],
    "sg:phone":"+1 317 580 9978",
    "sg:postcode":"46240",
    "sg:province":"IN",
    "sg:tags":[
        "mattress"
    ],
    "wof:name":"Select Comfort Corp",
    "wof:placetype":"venue"
},
  "geometry": {"coordinates":[-86.106595,39.912498],"type":"Point"}
}