{
  "type": "Feature",
  "properties": {
    "iso:country":"US",
    "sg:address":"6050 US Hwy 6",
    "sg:city":"Portage",
    "sg:classifiers":[
        {
            "category":"Retail",
            "subcategory":"Portrait Studio",
            "type":"Services"
        }
    ],
    "sg:phone":"+1 219 764 8115",
    "sg:postcode":"46368",
    "sg:province":"IN",
    "sg:tags":[
        "photographer"
    ],
    "wof:name":"Olan Mills Portrait Studio",
    "wof:placetype":"venue"
},
  "geometry": {"coordinates":[-87.18120399999999,41.550563],"type":"Point"}
}