{
  "type": "Feature",
  "properties": {
    "iso:country":"US",
    "sg:address":"7619 S 1150 E",
    "sg:city":"Otterbein",
    "sg:classifiers":[
        {
            "category":"Manufacturing",
            "subcategory":"Printing",
            "type":"Manufacturing & Wholesale Goods"
        }
    ],
    "sg:phone":"+1 765 583 8100",
    "sg:postcode":"47970",
    "sg:province":"IN",
    "sg:tags":[
        "screen"
    ],
    "wof:name":"Scooters Custom Screen Print",
    "wof:placetype":"venue"
},
  "geometry": {"coordinates":[-87.103412,40.500221],"type":"Point"}
}