{
  "type": "Feature",
  "properties": {
    "iso:country":"US",
    "sg:address":"5813 N Co Rd 275 E",
    "sg:city":"Petersburg",
    "sg:classifiers":[
        {
            "category":"Manufacturing",
            "subcategory":"Tools & Machinery",
            "type":"Manufacturing & Wholesale Goods"
        }
    ],
    "sg:phone":"+1 812 354 6981",
    "sg:postcode":"47567",
    "sg:province":"IN",
    "sg:tags":[
        "machine",
        "repair",
        "mfg"
    ],
    "wof:name":"Jones Saw Tools",
    "wof:placetype":"venue"
},
  "geometry": {"coordinates":[-87.226483,38.508041],"type":"Point"}
}