{
  "type": "Feature",
  "properties": {
    "iso:country":"US",
    "sg:address":"2727 E 86th St",
    "sg:city":"Indianapolis",
    "sg:classifiers":[
        {
            "category":"Shopping",
            "subcategory":"Jewelry",
            "type":"Retail Goods"
        }
    ],
    "sg:phone":"+1 317 251 5944",
    "sg:postcode":"46240",
    "sg:province":"IN",
    "sg:tags":[
        "jeweler"
    ],
    "wof:name":"Harry Gaunt Jewelers",
    "wof:placetype":"venue"
},
  "geometry": {"coordinates":[-86.118627,39.912374],"type":"Point"}
}