{
  "type": "Feature",
  "properties": {
    "addr:full":"61410 Co Rd 3 Elkhart IN 46517",
    "addr:housenumber":"61410",
    "addr:postcode":"46517",
    "addr:street":"Co Rd 3",
    "iso:country":"US",
    "sg:address":"61410 Co Rd 3",
    "sg:city":"Elkhart",
    "sg:classifiers":[
        {
            "category":"Farming",
            "subcategory":"Livestock Farm",
            "type":"Manufacturing & Wholesale Goods"
        }
    ],
    "sg:phone":"+1 574 295 1593",
    "sg:postcode":"46517",
    "sg:province":"IN",
    "sg:tags":[
        "beef",
        "feedlot",
        "cattle"
    ],
    "wof:name":"David Gongwer Farm",
    "wof:placetype":"venue"
},
  "geometry": {"coordinates":[-86.02201599999999,41.602651],"type":"Point"}
}