{
  "type": "Feature",
  "properties": {
    "iso:country":"US",
    "sg:address":"665 Alabama Ave",
    "sg:city":"Sellersburg",
    "sg:classifiers":[
        {
            "category":"Shopping",
            "subcategory":"Florist",
            "type":"Retail Goods"
        }
    ],
    "sg:phone":"+1 812 246 9998",
    "sg:postcode":"47172",
    "sg:province":"IN",
    "wof:name":"Sellersburg Florist",
    "wof:placetype":"venue"
},
  "geometry": {"coordinates":[-85.769477,38.401842],"type":"Point"}
}