{
  "type": "Feature",
  "properties": {
    "addr:full":"8910 Purdue Rd Indianapolis IN 46268",
    "addr:housenumber":"8910",
    "addr:postcode":"46268",
    "addr:street":"Purdue Rd",
    "iso:country":"US",
    "sg:address":"8910 Purdue Rd",
    "sg:city":"Indianapolis",
    "sg:classifiers":[
        {
            "category":"Insurance",
            "subcategory":"Insurance Agent",
            "type":"Services"
        }
    ],
    "sg:phone":"+1 317 870 2266",
    "sg:postcode":"46268",
    "sg:province":"IN",
    "wof:name":"State Farm Insurance",
    "wof:placetype":"venue"
},
  "geometry": {"coordinates":[-86.219444,39.913687],"type":"Point"}
}