{
  "type": "Feature",
  "properties": {
    "addr:full":"2425 W Michigan St Indianapolis IN 46222",
    "addr:housenumber":"2425",
    "addr:postcode":"46222",
    "addr:street":"W Michigan St",
    "iso:country":"US",
    "sg:address":"2425 W Michigan St",
    "sg:city":"Indianapolis",
    "sg:classifiers":[
        {
            "category":"Restaurant",
            "type":"Food & Drink"
        }
    ],
    "sg:phone":"+1 317 632 6377",
    "sg:postcode":"46222",
    "sg:province":"IN",
    "sg:tags":[
        "caterer"
    ],
    "wof:name":"Adam's Ala Carte Catering Svc",
    "wof:placetype":"venue"
},
  "geometry": {"coordinates":[-86.202153,39.774571],"type":"Point"}
}