{
  "type": "Feature",
  "properties": {
    "iso:country":"US",
    "sg:address":"129 S Catherwood Ave",
    "sg:city":"Indianapolis",
    "sg:classifiers":[
        {
            "category":"Shopping",
            "type":"Retail Goods"
        }
    ],
    "sg:phone":"+1 317 358 1091",
    "sg:postcode":"46219",
    "sg:province":"IN",
    "sg:tags":[
        "candle"
    ],
    "wof:name":"Suzan Candles",
    "wof:placetype":"venue"
},
  "geometry": {"coordinates":[-86.06132700000001,39.768891],"type":"Point"}
}