{
  "type": "Feature",
  "properties": {
    "iso:country":"US",
    "sg:address":"107 N Buckeye St",
    "sg:city":"Kokomo",
    "sg:classifiers":[
        {
            "category":"Banks & Credit Unions",
            "subcategory":"Bank",
            "type":"Services"
        }
    ],
    "sg:phone":"+1 765 454 7500",
    "sg:postcode":"46901",
    "sg:province":"IN",
    "wof:name":"Regions",
    "wof:placetype":"venue"
},
  "geometry": {"coordinates":[-86.13252300000001,40.487343],"type":"Point"}
}