{
  "type": "Feature",
  "properties": {
    "iso:country":"US",
    "sg:address":"288 Glencarry Ct",
    "sg:city":"Valparaiso",
    "sg:classifiers":[
        {
            "category":"Real Estate",
            "subcategory":"Real Estate Operator",
            "type":"Services"
        }
    ],
    "sg:phone":"+1 219 548 2596",
    "sg:postcode":"46385",
    "sg:province":"IN",
    "sg:tags":[
        "property",
        "lessor"
    ],
    "wof:name":"Steven H Muntzing",
    "wof:placetype":"venue"
},
  "geometry": {"coordinates":[-87.123138,41.439731],"type":"Point"}
}