{
  "type": "Feature",
  "properties": {
    "iso:country":"US",
    "sg:address":"6736 S 500 W",
    "sg:city":"Jamestown",
    "sg:classifiers":[
        {
            "category":"Wholesale",
            "subcategory":"Farm Supplies",
            "type":"Manufacturing & Wholesale Goods"
        }
    ],
    "sg:phone":"+1 765 676 5718",
    "sg:postcode":"46147",
    "sg:province":"IN",
    "sg:tags":[
        "raw",
        "product",
        "material",
        "se"
    ],
    "wof:name":"K D Stables Hrse & Carriage Co",
    "wof:placetype":"venue"
},
  "geometry": {"coordinates":[-86.562904,39.941175],"type":"Point"}
}