{
  "type": "Feature",
  "properties": {
    "iso:country":"US",
    "sg:address":"829 Washington Blvd",
    "sg:city":"Anderson",
    "sg:classifiers":[
        {
            "category":"Building & Trades",
            "subcategory":"Construction",
            "type":"Services"
        }
    ],
    "sg:phone":"+1 765 642 3639",
    "sg:postcode":"46016",
    "sg:province":"IN",
    "sg:tags":[
        "contractor"
    ],
    "wof:name":"T & M Construction",
    "wof:placetype":"venue"
},
  "geometry": {"coordinates":[-85.667242,40.088866],"type":"Point"}
}