{
  "type": "Feature",
  "properties": {
    "iso:country":"US",
    "sg:address":"537 E National Ave",
    "sg:city":"Brazil",
    "sg:classifiers":[
        {
            "category":"Shopping",
            "subcategory":"Computers & Home Electronics",
            "type":"Retail Goods"
        }
    ],
    "sg:phone":"+1 812 443 7825",
    "sg:postcode":"47834",
    "sg:province":"IN",
    "sg:tags":[
        "equipment",
        "dealer"
    ],
    "wof:name":"Computer Central",
    "wof:placetype":"venue"
},
  "geometry": {"coordinates":[-87.11979599999999,39.524834],"type":"Point"}
}