{
  "type": "Feature",
  "properties": {
    "iso:country":"US",
    "sg:address":"827 W 13th St",
    "sg:city":"Rochester",
    "sg:classifiers":[
        {
            "category":"Health Services",
            "subcategory":"Nursing And Care Facility",
            "type":"Services"
        }
    ],
    "sg:phone":"+1 574 223 4331",
    "sg:postcode":"46975",
    "sg:province":"IN",
    "sg:tags":[
        "home",
        "convalescent"
    ],
    "wof:name":"Life Care Ctr Of Rochester",
    "wof:placetype":"venue"
},
  "geometry": {"coordinates":[-86.226172,41.061284],"type":"Point"}
}