{
  "type": "Feature",
  "properties": {
    "addr:full":"6960 Hillsdale Ct Indianapolis IN 46250",
    "addr:housenumber":"6960",
    "addr:postcode":"46250",
    "addr:street":"Hillsdale Ct",
    "iso:country":"US",
    "sg:address":"6960 Hillsdale Ct",
    "sg:city":"Indianapolis",
    "sg:classifiers":[
        {
            "category":"Professional",
            "subcategory":"Employment Agencies",
            "type":"Services"
        }
    ],
    "sg:phone":"+1 317 596 4904",
    "sg:postcode":"46250",
    "sg:province":"IN",
    "sg:tags":[
        "help",
        "contractor"
    ],
    "wof:name":"First Call Temporary & Pro Svc",
    "wof:placetype":"venue"
},
  "geometry": {"coordinates":[-86.046993,39.896238],"type":"Point"}
}