{
  "type": "Feature",
  "properties": {
    "iso:country":"US",
    "sg:address":"219 W High St",
    "sg:city":"Lawrenceburg",
    "sg:classifiers":[
        {
            "category":"Government",
            "subcategory":"Office",
            "type":"Public Place"
        }
    ],
    "sg:phone":"+1 812 537 8740",
    "sg:postcode":"47025",
    "sg:province":"IN",
    "wof:name":"Dearborn Juvenile Detention",
    "wof:placetype":"venue"
},
  "geometry": {"coordinates":[-84.849975,39.090893],"type":"Point"}
}