{
  "type": "Feature",
  "properties": {
    "iso:country":"US",
    "sg:address":"707 Louisedale Dr",
    "sg:city":"Fort Wayne",
    "sg:classifiers":[
        {
            "category":"Building & Trades",
            "subcategory":"Plumbing",
            "type":"Services"
        }
    ],
    "sg:phone":"+1 260 373 2406",
    "sg:postcode":"46808",
    "sg:province":"IN",
    "sg:tags":[
        "septic"
    ],
    "wof:name":"Hoosier Sanitary",
    "wof:placetype":"venue"
},
  "geometry": {"coordinates":[-85.154219,41.113678],"type":"Point"}
}