{
  "type": "Feature",
  "properties": {
    "iso:country":"US",
    "sg:address":"1809 Meridian St",
    "sg:city":"Anderson",
    "sg:classifiers":[
        {
            "category":"Real Estate",
            "subcategory":"Real Estate Agent",
            "type":"Services"
        }
    ],
    "sg:phone":"+1 765 644 2516",
    "sg:postcode":"46016",
    "sg:province":"IN",
    "wof:name":"Helen Rogers Real Estate Agcy",
    "wof:placetype":"venue"
},
  "geometry": {"coordinates":[-85.679209,40.097493],"type":"Point"}
}