{
  "type": "Feature",
  "properties": {
    "iso:country":"US",
    "sg:address":"10238 US Hwy 36",
    "sg:city":"Avon",
    "sg:classifiers":[
        {
            "category":"Banks & Credit Unions",
            "subcategory":"Bank",
            "type":"Services"
        }
    ],
    "sg:phone":"+1 317 271 5900",
    "sg:postcode":"46123",
    "sg:province":"IN",
    "sg:tags":[
        "loan",
        "real estate"
    ],
    "wof:name":"Indy Mortgage Inc",
    "wof:placetype":"venue"
},
  "geometry": {"coordinates":[-86.343834,39.763777],"type":"Point"}
}