{
  "type": "Feature",
  "properties": {
    "iso:country":"US",
    "sg:address":"905 E Main St",
    "sg:city":"Richmond",
    "sg:classifiers":[
        {
            "category":"Personal",
            "subcategory":"Beauty Salon",
            "type":"Services"
        }
    ],
    "sg:phone":"+1 765 962 4341",
    "sg:postcode":"47374",
    "sg:province":"IN",
    "wof:name":"Personal Touch",
    "wof:placetype":"venue"
},
  "geometry": {"coordinates":[-84.889124,39.828987],"type":"Point"}
}