{
  "type": "Feature",
  "properties": {
    "iso:country":"US",
    "sg:address":"402 S Washington St",
    "sg:city":"Marion",
    "sg:classifiers":[
        {
            "category":"Banks & Credit Unions",
            "subcategory":"Bank",
            "type":"Services"
        }
    ],
    "sg:phone":"+1 765 649 5392",
    "sg:postcode":"46953",
    "sg:province":"IN",
    "sg:tags":[
        "mortgage",
        "loan",
        "broker",
        "real estate"
    ],
    "wof:name":"Equity Plus Mortgage Corp",
    "wof:placetype":"venue"
},
  "geometry": {"coordinates":[-85.659857,40.556946],"type":"Point"}
}