{
  "type": "Feature",
  "properties": {
    "iso:country":"US",
    "sg:address":"30 W Eads Pkwy",
    "sg:city":"Lawrenceburg",
    "sg:classifiers":[
        {
            "category":"Restaurant",
            "type":"Food & Drink"
        }
    ],
    "sg:phone":"+1 812 537 2355",
    "sg:postcode":"47025",
    "sg:province":"IN",
    "wof:name":"KFC",
    "wof:placetype":"venue"
},
  "geometry": {"coordinates":[-84.855176,39.096708],"type":"Point"}
}