{
  "type": "Feature",
  "properties": {
    "addr:full":"418 4th St Logansport IN 46947",
    "addr:housenumber":"418",
    "addr:postcode":"46947",
    "addr:street":"4Th St",
    "iso:country":"US",
    "sg:address":"418 4th St",
    "sg:city":"Logansport",
    "sg:classifiers":[
        {
            "category":"Social Services",
            "type":"Services"
        }
    ],
    "sg:phone":"+1 574 722 1979",
    "sg:postcode":"46947",
    "sg:province":"IN",
    "sg:tags":[
        "organization",
        "welfare"
    ],
    "wof:name":"Salvation Army",
    "wof:placetype":"venue"
},
  "geometry": {"coordinates":[-86.36546300000001,40.752651],"type":"Point"}
}