{
  "type": "Feature",
  "properties": {
    "iso:country":"US",
    "sg:address":"5832 US Hwy 6",
    "sg:city":"Butler",
    "sg:classifiers":[
        {
            "category":"Freight",
            "type":"Transportation"
        }
    ],
    "sg:phone":"+1 260 868 5291",
    "sg:postcode":"46721",
    "sg:province":"IN",
    "sg:tags":[
        "trucking"
    ],
    "wof:name":"Stemen Transit Inc",
    "wof:placetype":"venue"
},
  "geometry": {"coordinates":[-84.915999,41.428627],"type":"Point"}
}