{
  "type": "Feature",
  "properties": {
    "iso:country":"US",
    "sg:address":"3012 Saint Joseph Rd",
    "sg:city":"New Albany",
    "sg:classifiers":[
        {
            "category":"Banks & Credit Unions",
            "subcategory":"Bank",
            "type":"Services"
        }
    ],
    "sg:phone":"+1 812 945 1100",
    "sg:postcode":"47150",
    "sg:province":"IN",
    "sg:tags":[
        "loan",
        "real estate"
    ],
    "sg:website":"www.momentumone.net",
    "wof:name":"Momentum One Mortgage",
    "wof:placetype":"venue"
},
  "geometry": {"coordinates":[-85.80393,38.342974],"type":"Point"}
}