{
  "type": "Feature",
  "properties": {
    "iso:country":"US",
    "sg:address":"431 W 9th St",
    "sg:city":"Anderson",
    "sg:classifiers":[
        {
            "category":"Health Services",
            "subcategory":"Hospital",
            "type":"Services"
        }
    ],
    "sg:phone":"+1 765 649 2234",
    "sg:postcode":"46016",
    "sg:province":"IN",
    "sg:tags":[
        "mental"
    ],
    "wof:name":"Anderson Psychiatric Clinic",
    "wof:placetype":"venue"
},
  "geometry": {"coordinates":[-85.68564000000001,40.107013],"type":"Point"}
}