{
  "type": "Feature",
  "properties": {
    "iso:country":"US",
    "sg:address":"4491 Hoover Rd",
    "sg:city":"Nashville",
    "sg:classifiers":[
        {
            "category":"Wholesale",
            "subcategory":"Construction Materials",
            "type":"Manufacturing & Wholesale Goods"
        }
    ],
    "sg:phone":"+1 812 988 2669",
    "sg:postcode":"47448",
    "sg:province":"IN",
    "wof:name":"T & M Transport",
    "wof:placetype":"venue"
},
  "geometry": {"coordinates":[-86.116001,39.256781],"type":"Point"}
}