{
  "type": "Feature",
  "properties": {
    "iso:country":"US",
    "sg:address":"1420 Keller St",
    "sg:city":"Evansville",
    "sg:classifiers":[
        {
            "category":"Organizations",
            "subcategory":"Religious Organization",
            "type":"Services"
        }
    ],
    "sg:phone":"+1 812 424 5223",
    "sg:postcode":"47710",
    "sg:province":"IN",
    "sg:tags":[
        "church"
    ],
    "wof:name":"Friendship Southern Baptist",
    "wof:placetype":"venue"
},
  "geometry": {"coordinates":[-87.584558,37.996452],"type":"Point"}
}