{
  "type": "Feature",
  "properties": {
    "addr:full":"111 Monument Cir Indianapolis IN 46204",
    "addr:housenumber":"111",
    "addr:postcode":"46204",
    "addr:street":"Monument Cir",
    "iso:country":"US",
    "sg:address":"111 Monument Cir",
    "sg:city":"Indianapolis",
    "sg:classifiers":[
        {
            "category":"Travel",
            "subcategory":"Travel Agent",
            "type":"Entertainment"
        }
    ],
    "sg:phone":"+1 317 631 1492",
    "sg:postcode":"46204",
    "sg:province":"IN",
    "sg:tags":[
        "agency",
        "bureau"
    ],
    "sg:website":"www.travelfares.com",
    "wof:name":"Columbus Travel",
    "wof:placetype":"venue"
},
  "geometry": {"coordinates":[-86.15789599999999,39.769152],"type":"Point"}
}