{
  "type": "Feature",
  "properties": {
    "iso:country":"US",
    "sg:address":"2211 E Jefferson Blvd",
    "sg:city":"South Bend",
    "sg:classifiers":[
        {
            "category":"Real Estate",
            "subcategory":"Architect",
            "type":"Services"
        }
    ],
    "sg:phone":"+1 574 236 4400",
    "sg:postcode":"46615",
    "sg:province":"IN",
    "wof:name":"DLZ Corp",
    "wof:placetype":"venue"
},
  "geometry": {"coordinates":[-86.21364800000001,41.672992],"type":"Point"}
}