{
  "type": "Feature",
  "properties": {
    "iso:country":"US",
    "sg:address":"3200 W 96th St",
    "sg:city":"Indianapolis",
    "sg:classifiers":[
        {
            "category":"Sports & Exercise",
            "subcategory":"Golf",
            "type":"Entertainment"
        }
    ],
    "sg:phone":"+1 317 872 3387",
    "sg:postcode":"46268",
    "sg:province":"IN",
    "wof:name":"Twin Lakes Golf Club",
    "wof:placetype":"venue"
},
  "geometry": {"coordinates":[-86.216003,39.926498],"type":"Point"}
}