{
  "type": "Feature",
  "properties": {
    "addr:full":"569 Dawson St Columbus IN 47201",
    "addr:housenumber":"569",
    "addr:postcode":"47201",
    "addr:street":"Dawson St",
    "iso:country":"US",
    "sg:address":"569 Dawson St",
    "sg:city":"Columbus",
    "sg:classifiers":[
        {
            "category":"Building & Trades",
            "subcategory":"Landscaping Services",
            "type":"Services"
        }
    ],
    "sg:phone":"+1 812 376 7980",
    "sg:postcode":"47201",
    "sg:province":"IN",
    "sg:tags":[
        "lawn",
        "maintenance",
        "grounds"
    ],
    "wof:name":"W & R Mowing",
    "wof:placetype":"venue"
},
  "geometry": {"coordinates":[-85.92900299999999,39.157873],"type":"Point"}
}