{
  "type": "Feature",
  "properties": {
    "iso:country":"US",
    "sg:address":"9465 Counselors Row Ste 200",
    "sg:city":"Indianapolis",
    "sg:classifiers":[
        {
            "category":"Professional",
            "subcategory":"Lawyer & Legal Services",
            "type":"Services"
        }
    ],
    "sg:phone":"+1 317 805 4838",
    "sg:postcode":"46240",
    "sg:province":"IN",
    "wof:name":"McDonald Harvey E Atty",
    "wof:placetype":"venue"
},
  "geometry": {"coordinates":[-86.102898,39.925098],"type":"Point"}
}