{
  "type": "Feature",
  "properties": {
    "addr:full":"401 N Morton St Bloomington IN 47403",
    "addr:housenumber":"401",
    "addr:postcode":"47403",
    "addr:street":"N Morton St",
    "iso:country":"US",
    "sg:address":"401 N Morton St",
    "sg:city":"Bloomington",
    "sg:classifiers":[
        {
            "category":"Food & Beverages",
            "subcategory":"Farmers Market",
            "type":"Retail Goods"
        }
    ],
    "sg:postcode":"47403",
    "sg:province":"IN",
    "wof:name":"Bloomington Community Farmer's Market",
    "wof:placetype":"venue"
},
  "geometry": {"coordinates":[-86.536298,39.162837],"type":"Point"}
}