{
  "type": "Feature",
  "properties": {
    "iso:country":"US",
    "sg:address":"604 Co Rd 3 N",
    "sg:city":"Elkhart",
    "sg:classifiers":[
        {
            "category":"Wholesale",
            "subcategory":"Construction Materials",
            "type":"Manufacturing & Wholesale Goods"
        }
    ],
    "sg:phone":"+1 574 293 2913",
    "sg:postcode":"46514",
    "sg:province":"IN",
    "sg:tags":[
        "trade",
        "contractor"
    ],
    "wof:name":"Allied Fence",
    "wof:placetype":"venue"
},
  "geometry": {"coordinates":[-86.016426,41.695598],"type":"Point"}
}