{
  "type": "Feature",
  "properties": {
    "iso:country":"US",
    "sg:address":"1490 W Main St",
    "sg:city":"Mitchell",
    "sg:classifiers":[
        {
            "category":"Health Services",
            "subcategory":"Doctor",
            "type":"Services"
        }
    ],
    "sg:phone":"+1 812 849 6434",
    "sg:postcode":"47446",
    "sg:province":"IN",
    "sg:tags":[
        "physician",
        "surgeon"
    ],
    "wof:name":"Mitchell Family Practice",
    "wof:placetype":"venue"
},
  "geometry": {"coordinates":[-86.484327,38.731576],"type":"Point"}
}