{
  "type": "Feature",
  "properties": {
    "addr:full":"248 Hunter Station Rd Sellersburg IN 47172",
    "addr:housenumber":"248",
    "addr:postcode":"47172",
    "addr:street":"Hunter Station Rd",
    "iso:country":"US",
    "sg:address":"248 Hunter Station Rd",
    "sg:city":"Sellersburg",
    "sg:classifiers":[
        {
            "category":"Shopping",
            "subcategory":"Florist",
            "type":"Retail Goods"
        }
    ],
    "sg:phone":"+1 812 246 2910",
    "sg:postcode":"47172",
    "sg:province":"IN",
    "wof:name":"Nance's Florist",
    "wof:placetype":"venue"
},
  "geometry": {"coordinates":[-85.77649599999999,38.378059],"type":"Point"}
}