{
  "type": "Feature",
  "properties": {
    "iso:country":"US",
    "sg:address":"6045 Stoney Creek Dr",
    "sg:city":"Fort Wayne",
    "sg:classifiers":[
        {
            "category":"Insurance",
            "subcategory":"Insurance Agent",
            "type":"Services"
        }
    ],
    "sg:phone":"+1 260 482 8771",
    "sg:postcode":"46825",
    "sg:province":"IN",
    "wof:name":"Nicholas Financial Svc",
    "wof:placetype":"venue"
},
  "geometry": {"coordinates":[-85.139347,41.133431],"type":"Point"}
}