{
  "type": "Feature",
  "properties": {
    "iso:country":"US",
    "sg:address":"6222 Central Ave",
    "sg:city":"Portage",
    "sg:phone":"+1 219 762 2388",
    "sg:postcode":"46368",
    "sg:province":"IN",
    "wof:name":"Jade Garden Inc",
    "wof:placetype":"venue"
},
  "geometry": {"coordinates":[-87.17397699999999,41.575909],"type":"Point"}
}