{
  "type": "Feature",
  "properties": {
    "iso:country":"US",
    "sg:address":"7608 W Fielding Rd",
    "sg:city":"Glenwood",
    "sg:phone":"+1 765 679 5330",
    "sg:postcode":"46133",
    "sg:province":"IN",
    "sg:tags":[
        "farm",
        "corn"
    ],
    "wof:name":"Darrell Cox Farm",
    "wof:placetype":"venue"
},
  "geometry": {"coordinates":[-85.286051,39.618191],"type":"Point"}
}