{
  "type": "Feature",
  "properties": {
    "iso:country":"US",
    "sg:address":"1214 E 15th St",
    "sg:city":"Indianapolis",
    "sg:classifiers":[
        {
            "category":"Social Services",
            "subcategory":"Child Care",
            "type":"Services"
        }
    ],
    "sg:phone":"+1 317 636 7254",
    "sg:postcode":"46202",
    "sg:province":"IN",
    "wof:name":"M2M Child Care",
    "wof:placetype":"venue"
},
  "geometry": {"coordinates":[-86.13799899999999,39.786748],"type":"Point"}
}