{
  "type": "Feature",
  "properties": {
    "iso:country":"US",
    "sg:address":"4833 E Co Rd 600 S",
    "sg:city":"Walton",
    "sg:classifiers":[
        {
            "category":"Personal",
            "subcategory":"Beauty Salon",
            "type":"Services"
        }
    ],
    "sg:phone":"+1 574 626 2139",
    "sg:postcode":"46994",
    "sg:province":"IN",
    "wof:name":"Kerrie's Kountry KLIP & KURL",
    "wof:placetype":"venue"
},
  "geometry": {"coordinates":[-86.281464,40.678414],"type":"Point"}
}