{
  "type": "Feature",
  "properties": {
    "iso:country":"US",
    "sg:address":"6237 W Lincoln St",
    "sg:city":"Richland",
    "sg:classifiers":[
        {
            "category":"Building & Trades",
            "subcategory":"Construction",
            "type":"Services"
        }
    ],
    "sg:phone":"+1 812 359 4653",
    "sg:postcode":"47634",
    "sg:province":"IN",
    "sg:tags":[
        "house"
    ],
    "wof:name":"Richland Builders Construction",
    "wof:placetype":"venue"
},
  "geometry": {"coordinates":[-87.17164,37.946251],"type":"Point"}
}