{
  "type": "Feature",
  "properties": {
    "addr:full":"7660 N 100 W Wawaka IN 46794",
    "addr:housenumber":"7660",
    "addr:postcode":"46794",
    "addr:street":"N 100 W",
    "iso:country":"US",
    "sg:address":"7660 N 100 W",
    "sg:city":"Wawaka",
    "sg:classifiers":[
        {
            "category":"Shopping",
            "type":"Retail Goods"
        }
    ],
    "sg:phone":"+1 260 761 2002",
    "sg:postcode":"46794",
    "sg:province":"IN",
    "sg:tags":[
        "telephone",
        "cellular"
    ],
    "wof:name":"Verizon Wireless",
    "wof:placetype":"venue"
},
  "geometry": {"coordinates":[-85.45563799999999,41.463957],"type":"Point"}
}