{
  "type": "Feature",
  "properties": {
    "iso:country":"US",
    "sg:address":"2250 Teal Rd",
    "sg:city":"Lafayette",
    "sg:classifiers":[
        {
            "category":"Banks & Credit Unions",
            "subcategory":"Bank",
            "type":"Services"
        }
    ],
    "sg:phone":"+1 765 477 7222",
    "sg:postcode":"47909",
    "sg:province":"IN",
    "wof:name":"Charter One Bank",
    "wof:placetype":"venue"
},
  "geometry": {"coordinates":[-86.866811,40.395514],"type":"Point"}
}