{
  "type": "Feature",
  "properties": {
    "iso:country":"US",
    "sg:address":"620 E Main St",
    "sg:city":"Centerville",
    "sg:classifiers":[
        {
            "category":"Retail",
            "subcategory":"Auto Repair",
            "type":"Services"
        }
    ],
    "sg:phone":"+1 765 855 2700",
    "sg:postcode":"47330",
    "sg:province":"IN",
    "sg:tags":[
        "automobile",
        "lubrication"
    ],
    "wof:name":"Andy's Express Lube",
    "wof:placetype":"venue"
},
  "geometry": {"coordinates":[-84.987396,39.818104],"type":"Point"}
}