{
  "type": "Feature",
  "properties": {
    "iso:country":"US",
    "sg:address":"2720 California Rd",
    "sg:city":"Elkhart",
    "sg:classifiers":[
        {
            "category":"Professional",
            "type":"Services"
        }
    ],
    "sg:phone":"+1 574 262 5885",
    "sg:postcode":"46514",
    "sg:province":"IN",
    "sg:tags":[
        "establishment"
    ],
    "wof:name":"Michiana Freenet Society Inc",
    "wof:placetype":"venue"
},
  "geometry": {"coordinates":[-86.013937,41.695303],"type":"Point"}
}