{
  "type": "Feature",
  "properties": {
    "iso:country":"US",
    "sg:address":"506 NW 5th St",
    "sg:city":"Richmond",
    "sg:classifiers":[
        {
            "category":"Freight",
            "type":"Transportation"
        }
    ],
    "sg:phone":"+1 765 939 6116",
    "sg:postcode":"47374",
    "sg:province":"IN",
    "sg:tags":[
        "trucking"
    ],
    "wof:name":"Chaler Corp",
    "wof:placetype":"venue"
},
  "geometry": {"coordinates":[-84.908047,39.834277],"type":"Point"}
}