{
  "type": "Feature",
  "properties": {
    "iso:country":"US",
    "sg:address":"3505 N Home St",
    "sg:city":"Mishawaka",
    "sg:classifiers":[
        {
            "category":"Building & Trades",
            "subcategory":"Landscaping Services",
            "type":"Services"
        }
    ],
    "sg:phone":"+1 574 252 5530",
    "sg:postcode":"46545",
    "sg:province":"IN",
    "sg:tags":[
        "lawn",
        "maintenance",
        "grounds"
    ],
    "wof:name":"Scotts Lawn Svc",
    "wof:placetype":"venue"
},
  "geometry": {"coordinates":[-86.148735,41.689338],"type":"Point"}
}