{
  "type": "Feature",
  "properties": {
    "addr:full":"1549 E Wabash St Frankfort IN 46041",
    "addr:housenumber":"1549",
    "addr:postcode":"46041",
    "addr:street":"E Wabash St",
    "iso:country":"US",
    "sg:address":"1549 E Wabash St",
    "sg:city":"Frankfort",
    "sg:classifiers":[
        {
            "category":"Retail",
            "subcategory":"Car Wash",
            "type":"Services"
        }
    ],
    "sg:phone":"+1 765 659 5229",
    "sg:postcode":"46041",
    "sg:province":"IN",
    "sg:tags":[
        "polishing",
        "washing"
    ],
    "wof:name":"Diamond Car Wash",
    "wof:placetype":"venue"
},
  "geometry": {"coordinates":[-86.49514499999999,40.278883],"type":"Point"}
}