{
  "type": "Feature",
  "properties": {
    "iso:country":"US",
    "sg:address":"10412 N Dearborn Rd",
    "sg:city":"Sunman",
    "sg:classifiers":[
        {
            "category":"Travel",
            "subcategory":"Campground",
            "type":"Entertainment"
        }
    ],
    "sg:phone":"+1 812 623 2136",
    "sg:postcode":"47041",
    "sg:province":"IN",
    "sg:tags":[
        "camp"
    ],
    "wof:name":"Lake In The Pines",
    "wof:placetype":"venue"
},
  "geometry": {"coordinates":[-85.012045,39.234186],"type":"Point"}
}