{
  "type": "Feature",
  "properties": {
    "iso:country":"US",
    "sg:address":"4219 Short Ter",
    "sg:city":"Carmel",
    "sg:classifiers":[
        {
            "category":"Personal",
            "type":"Services"
        }
    ],
    "sg:phone":"+1 317 706 0209",
    "sg:postcode":"46033",
    "sg:province":"IN",
    "wof:name":"Personal Chef Marketing",
    "wof:placetype":"venue"
},
  "geometry": {"coordinates":[-86.09700599999999,40.001935],"type":"Point"}
}