{
  "type": "Feature",
  "properties": {
    "iso:country":"US",
    "sg:address":"2760 Wooded Glen Ct",
    "sg:city":"Indianapolis",
    "sg:classifiers":[
        {
            "category":"Utilities",
            "subcategory":"Mobile Phone",
            "type":"Services"
        }
    ],
    "sg:phone":"+1 317 471 8731",
    "sg:postcode":"46268",
    "sg:province":"IN",
    "sg:tags":[
        "communication",
        "radiotelephone"
    ],
    "wof:name":"One Player Away Inc",
    "wof:placetype":"venue"
},
  "geometry": {"coordinates":[-86.209536,39.915181],"type":"Point"}
}