{
  "type": "Feature",
  "properties": {
    "iso:country":"US",
    "sg:address":"1127 Brook Ln",
    "sg:city":"Indianapolis",
    "sg:classifiers":[
        {
            "category":"Personal",
            "subcategory":"Beauty Salon",
            "type":"Services"
        },
        {
            "category":"Personal",
            "subcategory":"Skin Care",
            "type":"Services"
        }
    ],
    "sg:phone":"+1 317 632 4047",
    "sg:postcode":"46202",
    "sg:province":"IN",
    "sg:tags":[
        "cosmetologist",
        "cosmetic"
    ],
    "wof:name":"Diane Burhannon",
    "wof:placetype":"venue"
},
  "geometry": {"coordinates":[-86.17385899999999,39.781849],"type":"Point"}
}