{
  "type": "Feature",
  "properties": {
    "iso:country":"US",
    "sg:address":"490 N Thorn Rd",
    "sg:city":"Walkerton",
    "sg:classifiers":[
        {
            "category":"Building & Trades",
            "subcategory":"Construction",
            "type":"Services"
        }
    ],
    "sg:phone":"+1 574 586 2239",
    "sg:postcode":"46574",
    "sg:province":"IN",
    "sg:tags":[
        "designer",
        "dealer",
        "pool",
        "swimming"
    ],
    "wof:name":"D J's Pools & Supplies",
    "wof:placetype":"venue"
},
  "geometry": {"coordinates":[-86.435332,41.470082],"type":"Point"}
}