{
  "type": "Feature",
  "properties": {
    "iso:country":"US",
    "sg:address":"790 A St NE",
    "sg:city":"Linton",
    "sg:classifiers":[
        {
            "category":"Restaurant",
            "type":"Food & Drink"
        }
    ],
    "sg:phone":"+1 812 847 2207",
    "sg:postcode":"47441",
    "sg:province":"IN",
    "sg:tags":[
        "pizza"
    ],
    "wof:name":"Pizza City",
    "wof:placetype":"venue"
},
  "geometry": {"coordinates":[-87.158363,39.035766],"type":"Point"}
}