{
  "type": "Feature",
  "properties": {
    "addr:full":"4252 S 500 W Kingman IN 47952",
    "addr:housenumber":"4252;500",
    "addr:postcode":"47952",
    "addr:street":"S;W",
    "iso:country":"US",
    "sg:address":"4252 S 500 W",
    "sg:city":"Kingman",
    "sg:classifiers":[
        {
            "category":"Farming",
            "subcategory":"Livestock Farm",
            "type":"Manufacturing & Wholesale Goods"
        }
    ],
    "sg:phone":"+1 765 397 3409",
    "sg:postcode":"47952",
    "sg:province":"IN",
    "sg:tags":[
        "hog",
        "or",
        "feedlot"
    ],
    "wof:name":"Charles Nixon",
    "wof:placetype":"venue"
},
  "geometry": {"coordinates":[-87.356239,39.972684],"type":"Point"}
}