{
  "type": "Feature",
  "properties": {
    "addr:full":"59029 Co Rd 35 Middlebury IN 46540",
    "addr:housenumber":"59029;35",
    "addr:postcode":"46540",
    "addr:street":"Co Rd",
    "iso:country":"US",
    "sg:address":"59029 Co Rd 35",
    "sg:city":"Middlebury",
    "sg:classifiers":[
        {
            "category":"Farming",
            "subcategory":"Livestock Farm",
            "type":"Manufacturing & Wholesale Goods"
        }
    ],
    "sg:phone":"+1 574 825 5368",
    "sg:postcode":"46540",
    "sg:province":"IN",
    "sg:tags":[
        "beef",
        "feedlot",
        "cattle"
    ],
    "wof:name":"Hochstetler Laban",
    "wof:placetype":"venue"
},
  "geometry": {"coordinates":[-85.73456899999999,41.637798],"type":"Point"}
}