{
  "type": "Feature",
  "properties": {
    "iso:country":"US",
    "sg:address":"424 W McKinley Ave",
    "sg:city":"Mishawaka",
    "sg:classifiers":[
        {
            "category":"Food & Beverages",
            "subcategory":"Groceries & Convenience Stores",
            "type":"Retail Goods"
        }
    ],
    "sg:phone":"+1 574 256 1841",
    "sg:postcode":"46545",
    "sg:province":"IN",
    "sg:tags":[
        "grocer"
    ],
    "sg:website":"www.martins-supermarket.com",
    "wof:name":"Martin's Super Market",
    "wof:placetype":"venue"
},
  "geometry": {"coordinates":[-86.187943,41.680422],"type":"Point"}
}