{
  "type": "Feature",
  "properties": {
    "iso:country":"US",
    "sg:address":"1924 Elkhart Rd",
    "sg:city":"Goshen",
    "sg:classifiers":[
        {
            "category":"Wholesale",
            "subcategory":"Machinery & Supplies",
            "type":"Manufacturing & Wholesale Goods"
        }
    ],
    "sg:phone":"+1 574 533 3118",
    "sg:postcode":"46526",
    "sg:province":"IN",
    "sg:tags":[
        "rubber",
        "product"
    ],
    "sg:website":"www.trianglerubberco.com",
    "wof:name":"Triangle Rubber Co",
    "wof:placetype":"venue"
},
  "geometry": {"coordinates":[-85.865638,41.600661],"type":"Point"}
}