{
  "type": "Feature",
  "properties": {
    "iso:country":"US",
    "sg:address":"5033 Cider Mill Ct",
    "sg:city":"Evansville",
    "sg:classifiers":[
        {
            "category":"Shopping",
            "subcategory":"Luggage & Leather Goods",
            "type":"Retail Goods"
        }
    ],
    "sg:phone":"+1 812 867 9520",
    "sg:postcode":"47711",
    "sg:province":"IN",
    "wof:name":"Michael Trent Inc",
    "wof:placetype":"venue"
},
  "geometry": {"coordinates":[-87.548918,38.023308],"type":"Point"}
}