{
  "type": "Feature",
  "properties": {
    "addr:full":"7401 N Kitley Ave Indianapolis IN 46250",
    "addr:housenumber":"7401",
    "addr:postcode":"46250",
    "addr:street":"N Kitley Ave",
    "iso:country":"US",
    "sg:address":"7401 N Kitley Ave",
    "sg:city":"Indianapolis",
    "sg:classifiers":[
        {
            "category":"Building & Trades",
            "subcategory":"Construction",
            "type":"Services"
        }
    ],
    "sg:phone":"+1 317 842 6026",
    "sg:postcode":"46250",
    "sg:province":"IN",
    "sg:tags":[
        "house"
    ],
    "wof:name":"Robert V Prout Contractor",
    "wof:placetype":"venue"
},
  "geometry": {"coordinates":[-86.05551199999999,39.890685],"type":"Point"}
}