{
  "type": "Feature",
  "properties": {
    "iso:country":"US",
    "sg:address":"742 W 6th St",
    "sg:city":"Jasper",
    "sg:classifiers":[
        {
            "category":"Health Services",
            "subcategory":"Medical Lab",
            "type":"Services"
        }
    ],
    "sg:phone":"+1 812 482 6322",
    "sg:postcode":"47546",
    "sg:province":"IN",
    "sg:tags":[
        "laboratory"
    ],
    "wof:name":"Schwenk Dental Laboratory",
    "wof:placetype":"venue"
},
  "geometry": {"coordinates":[-86.940551,38.392084],"type":"Point"}
}