{
  "type": "Feature",
  "properties": {
    "iso:country":"US",
    "sg:address":"1104 N Huntington Ave",
    "sg:city":"Warren",
    "sg:classifiers":[
        {
            "category":"Retail",
            "subcategory":"Auto Repair",
            "type":"Services"
        }
    ],
    "sg:phone":"+1 260 375 3975",
    "sg:postcode":"46792",
    "sg:province":"IN",
    "sg:tags":[
        "body",
        "automobile",
        "painting"
    ],
    "wof:name":"Martins Auto Body Shop",
    "wof:placetype":"venue"
},
  "geometry": {"coordinates":[-85.428455,40.689914],"type":"Point"}
}