{
  "type": "Feature",
  "properties": {
    "addr:full":"103 N Court St Sullivan IN 47882",
    "addr:housenumber":"103",
    "addr:postcode":"47882",
    "addr:street":"N Court St",
    "iso:country":"US",
    "sg:address":"103 N Court St",
    "sg:city":"Sullivan",
    "sg:classifiers":[
        {
            "category":"Insurance",
            "subcategory":"Insurance Agent",
            "type":"Services"
        }
    ],
    "sg:phone":"+1 812 268 0837",
    "sg:postcode":"47882",
    "sg:province":"IN",
    "wof:name":"Risinger Insurance",
    "wof:placetype":"venue"
},
  "geometry": {"coordinates":[-87.408266,39.09682],"type":"Point"}
}