{
  "type": "Feature",
  "properties": {
    "iso:country":"US",
    "sg:address":"474 S Troll St",
    "sg:city":"Sullivan",
    "sg:classifiers":[
        {
            "category":"Professional",
            "subcategory":"Computer Services",
            "type":"Services"
        }
    ],
    "sg:phone":"+1 812 268 6808",
    "sg:postcode":"47882",
    "sg:province":"IN",
    "sg:tags":[
        "internet"
    ],
    "wof:name":"Sullivan Smartband",
    "wof:placetype":"venue"
},
  "geometry": {"coordinates":[-87.412111,39.088822],"type":"Point"}
}