{
  "type": "Feature",
  "properties": {
    "addr:full":"221 US Hwy 20 Middlebury IN 46540",
    "addr:housenumber":"221",
    "addr:postcode":"46540",
    "addr:street":"Us Hwy 20",
    "iso:country":"US",
    "sg:address":"221 US Hwy 20",
    "sg:city":"Middlebury",
    "sg:classifiers":[
        {
            "category":"Home & Garden",
            "subcategory":"Mobile Homes",
            "type":"Retail Goods"
        }
    ],
    "sg:phone":"+1 574 825 5668",
    "sg:postcode":"46540",
    "sg:province":"IN",
    "sg:website":"www.schulthomes.com",
    "wof:name":"Schult Homes Corp",
    "wof:placetype":"venue"
},
  "geometry": {"coordinates":[-85.670445,41.654119],"type":"Point"}
}