{
  "type": "Feature",
  "properties": {
    "addr:full":"66 Kings Hwy Winona Lake IN 46590",
    "addr:housenumber":"66",
    "addr:postcode":"46590",
    "addr:street":"Kings Hwy",
    "iso:country":"US",
    "sg:address":"66 Kings Hwy",
    "sg:city":"Winona Lake",
    "sg:classifiers":[
        {
            "category":"Organizations",
            "subcategory":"Religious Organization",
            "type":"Services"
        }
    ],
    "sg:phone":"+1 574 267 6736",
    "sg:postcode":"46590",
    "sg:province":"IN",
    "wof:name":"Wallace E Jones Rev",
    "wof:placetype":"venue"
},
  "geometry": {"coordinates":[-85.822784,41.23151],"type":"Point"}
}