{
  "type": "Feature",
  "properties": {
    "addr:full":"6701 S Harding St Indianapolis IN 46217",
    "addr:housenumber":"6701",
    "addr:postcode":"46217",
    "addr:street":"S Harding St",
    "iso:country":"US",
    "sg:address":"6701 S Harding St",
    "sg:city":"Indianapolis",
    "sg:classifiers":[
        {
            "category":"Recreation",
            "type":"Entertainment"
        }
    ],
    "sg:phone":"+1 317 784 7447",
    "sg:postcode":"46217",
    "sg:province":"IN",
    "sg:tags":[
        "amusement"
    ],
    "wof:name":"Indianapolis Sports Park Inc",
    "wof:placetype":"venue"
},
  "geometry": {"coordinates":[-86.186948,39.669613],"type":"Point"}
}