{
  "type": "Feature",
  "properties": {
    "iso:country":"US",
    "sg:address":"426 S Lake St",
    "sg:city":"Gary",
    "sg:classifiers":[
        {
            "category":"Wholesale",
            "subcategory":"Stationery",
            "type":"Manufacturing & Wholesale Goods"
        }
    ],
    "sg:phone":"+1 219 938 3333",
    "sg:postcode":"46403",
    "sg:province":"IN",
    "sg:tags":[
        "envelope"
    ],
    "wof:name":"PAPER-Papers.Com",
    "wof:placetype":"venue"
},
  "geometry": {"coordinates":[-87.268052,41.601764],"type":"Point"}
}