{
  "type": "Feature",
  "properties": {
    "iso:country":"US",
    "sg:address":"6494 State Rd 64",
    "sg:city":"Georgetown",
    "sg:classifiers":[
        {
            "category":"Food & Beverages",
            "subcategory":"Groceries & Convenience Stores",
            "type":"Retail Goods"
        }
    ],
    "sg:phone":"+1 812 923 3061",
    "sg:postcode":"47122",
    "sg:province":"IN",
    "wof:name":"Jacobi's Foodmart & Gas",
    "wof:placetype":"venue"
},
  "geometry": {"coordinates":[-85.928483,38.287322],"type":"Point"}
}