{
  "type": "Feature",
  "properties": {
    "iso:country":"US",
    "sg:address":"3311 S Base Rd",
    "sg:city":"Rushville",
    "sg:classifiers":[
        {
            "category":"Farming",
            "subcategory":"Dairy Farm",
            "type":"Manufacturing & Wholesale Goods"
        }
    ],
    "sg:phone":"+1 765 932 3825",
    "sg:postcode":"46173",
    "sg:province":"IN",
    "wof:name":"Willow Creek Dairy Inc",
    "wof:placetype":"venue"
},
  "geometry": {"coordinates":[-85.444173,39.564272],"type":"Point"}
}