{
  "type": "Feature",
  "properties": {
    "iso:country":"US",
    "sg:address":"1815 E Bristol St",
    "sg:city":"Elkhart",
    "sg:classifiers":[
        {
            "category":"Real Estate",
            "subcategory":"Real Estate Agent",
            "type":"Services"
        }
    ],
    "sg:phone":"+1 574 262 0770",
    "sg:postcode":"46514",
    "sg:province":"IN",
    "wof:name":"Mary Mucha",
    "wof:placetype":"venue"
},
  "geometry": {"coordinates":[-85.948761,41.702538],"type":"Point"}
}