{
  "type": "Feature",
  "properties": {
    "addr:full":"1702 Lafayette St Valparaiso IN 46383",
    "addr:housenumber":"1702",
    "addr:postcode":"46383",
    "addr:street":"Lafayette St",
    "iso:country":"US",
    "sg:address":"1702 Lafayette St",
    "sg:city":"Valparaiso",
    "sg:phone":"+1 219 462 7054",
    "sg:postcode":"46383",
    "sg:province":"IN",
    "sg:tags":[
        "product",
        "petroleum"
    ],
    "wof:name":"Western Petroleum Company",
    "wof:placetype":"venue"
},
  "geometry": {"coordinates":[-87.06220999999999,41.483354],"type":"Point"}
}