{
  "type": "Feature",
  "properties": {
    "iso:country":"US",
    "sg:address":"900 E Tipton St",
    "sg:city":"Seymour",
    "sg:classifiers":[
        {
            "category":"Shopping",
            "type":"Retail Goods"
        }
    ],
    "sg:phone":"+1 812 523 1400",
    "sg:postcode":"47274",
    "sg:province":"IN",
    "sg:tags":[
        "merchandise"
    ],
    "wof:name":"Cellulink Communications",
    "wof:placetype":"venue"
},
  "geometry": {"coordinates":[-85.876544,38.958114],"type":"Point"}
}