{
  "type": "Feature",
  "properties": {
    "addr:full":"535 N Clark St Markle IN 46770",
    "addr:housenumber":"535",
    "addr:postcode":"46770",
    "addr:street":"N Clark St",
    "iso:country":"US",
    "sg:address":"535 N Clark St",
    "sg:city":"Markle",
    "sg:classifiers":[
        {
            "category":"Building & Trades",
            "subcategory":"Construction",
            "type":"Services"
        }
    ],
    "sg:phone":"+1 260 758 2793",
    "sg:postcode":"46770",
    "sg:province":"IN",
    "sg:tags":[
        "tile",
        "dealer"
    ],
    "wof:name":"Mason Floor Covering & Carpet",
    "wof:placetype":"venue"
},
  "geometry": {"coordinates":[-85.335549,40.829302],"type":"Point"}
}