{
  "type": "Feature",
  "properties": {
    "iso:country":"US",
    "sg:address":"101 W Marion St",
    "sg:city":"Danville",
    "sg:classifiers":[
        {
            "category":"Government",
            "subcategory":"Office",
            "type":"Public Place"
        }
    ],
    "sg:phone":"+1 317 745 9264",
    "sg:postcode":"46122",
    "sg:province":"IN",
    "wof:name":"Hendricks County Adult Prbtn",
    "wof:placetype":"venue"
},
  "geometry": {"coordinates":[-86.526237,39.759865],"type":"Point"}
}