{
  "type": "Feature",
  "properties": {
    "iso:country":"US",
    "sg:address":"8962 Crawfordsville Rd",
    "sg:city":"Indianapolis",
    "sg:classifiers":[
        {
            "category":"Building & Trades",
            "subcategory":"Construction",
            "type":"Services"
        }
    ],
    "sg:phone":"+1 317 388 9388",
    "sg:postcode":"46234",
    "sg:province":"IN",
    "sg:tags":[
        "siding",
        "contractor"
    ],
    "wof:name":"Sycamore Structures Inc",
    "wof:placetype":"venue"
},
  "geometry": {"coordinates":[-86.322091,39.81578],"type":"Point"}
}