{
  "type": "Feature",
  "properties": {
    "iso:country":"US",
    "sg:address":"6910 N Main St",
    "sg:city":"Granger",
    "sg:classifiers":[
        {
            "category":"Health Services",
            "subcategory":"Clinic",
            "type":"Services"
        }
    ],
    "sg:phone":"+1 574 277 4121",
    "sg:postcode":"46530",
    "sg:province":"IN",
    "sg:tags":[
        "home"
    ],
    "wof:name":"Comfort Keepers",
    "wof:placetype":"venue"
},
  "geometry": {"coordinates":[-86.17803000000001,41.722915],"type":"Point"}
}