{
  "type": "Feature",
  "properties": {
    "iso:country":"US",
    "sg:address":"905 E Tipton St",
    "sg:city":"Seymour",
    "sg:classifiers":[
        {
            "category":"Real Estate",
            "subcategory":"Real Estate Agent",
            "type":"Services"
        }
    ],
    "sg:phone":"+1 812 522 5060",
    "sg:postcode":"47274",
    "sg:province":"IN",
    "sg:tags":[
        "consultant"
    ],
    "wof:name":"South Central Realty",
    "wof:placetype":"venue"
},
  "geometry": {"coordinates":[-85.876508,38.958189],"type":"Point"}
}