{
  "type": "Feature",
  "properties": {
    "iso:country":"US",
    "sg:address":"5435 Emerson Way",
    "sg:city":"Indianapolis",
    "sg:classifiers":[
        {
            "category":"Insurance",
            "subcategory":"Insurance Agent",
            "type":"Services"
        }
    ],
    "sg:phone":"+1 317 541 1899",
    "sg:postcode":"46226",
    "sg:province":"IN",
    "wof:name":"Physicians Mutual Insurance Co",
    "wof:placetype":"venue"
},
  "geometry": {"coordinates":[-86.087289,39.850972],"type":"Point"}
}