{
  "type": "Feature",
  "properties": {
    "iso:country":"US",
    "sg:address":"21 NE 5th St",
    "sg:city":"Washington",
    "sg:classifiers":[
        {
            "category":"Shopping",
            "subcategory":"Gifts & Souvenirs",
            "type":"Retail Goods"
        }
    ],
    "sg:phone":"+1 812 254 1120",
    "sg:postcode":"47501",
    "sg:province":"IN",
    "sg:tags":[
        "shop"
    ],
    "wof:name":"Back Porch Treasure's",
    "wof:placetype":"venue"
},
  "geometry": {"coordinates":[-87.170272,38.657605],"type":"Point"}
}