{
  "type": "Feature",
  "properties": {
    "iso:country":"US",
    "sg:address":"113 Court St",
    "sg:city":"Tipton",
    "sg:classifiers":[
        {
            "category":"Utilities",
            "subcategory":"Water",
            "type":"Services"
        }
    ],
    "sg:phone":"+1 765 675 7629",
    "sg:postcode":"46072",
    "sg:province":"IN",
    "sg:tags":[
        "company",
        "sewage"
    ],
    "wof:name":"Tipton Municipal Utilities",
    "wof:placetype":"venue"
},
  "geometry": {"coordinates":[-86.040322,40.282108],"type":"Point"}
}