{
  "type": "Feature",
  "properties": {
    "iso:country":"US",
    "sg:address":"1334 S Reisner St",
    "sg:city":"Indianapolis",
    "sg:classifiers":[
        {
            "category":"Shopping",
            "type":"Retail Goods"
        }
    ],
    "sg:phone":"+1 317 632 8389",
    "sg:postcode":"46221",
    "sg:province":"IN",
    "sg:tags":[
        "merchandise"
    ],
    "wof:name":"Kenneth Bishop Jensen",
    "wof:placetype":"venue"
},
  "geometry": {"coordinates":[-86.189575,39.748744],"type":"Point"}
}