{
  "type": "Feature",
  "properties": {
    "iso:country":"US",
    "sg:address":"375 S Park St",
    "sg:city":"Pekin",
    "sg:classifiers":[
        {
            "category":"Social Services",
            "subcategory":"Child Care",
            "type":"Services"
        }
    ],
    "sg:phone":"+1 812 967 5224",
    "sg:postcode":"47165",
    "sg:province":"IN",
    "wof:name":"Karen's Kidz Daycare",
    "wof:placetype":"venue"
},
  "geometry": {"coordinates":[-86.01867,38.501233],"type":"Point"}
}