{
  "type": "Feature",
  "properties": {
    "addr:full":"1100 S Tiger Dr Yorktown IN 47396",
    "addr:housenumber":"1100",
    "addr:postcode":"47396",
    "addr:street":"S Tiger Dr",
    "iso:country":"US",
    "sg:address":"1100 S Tiger Dr",
    "sg:city":"Yorktown",
    "sg:classifiers":[
        {
            "category":"Education",
            "subcategory":"School",
            "type":"Public Place"
        }
    ],
    "sg:phone":"+1 765 759 2550",
    "sg:postcode":"47396",
    "sg:province":"IN",
    "wof:name":"Yorktown High School",
    "wof:placetype":"venue"
},
  "geometry": {"coordinates":[-85.49499400000001,40.183523],"type":"Point"}
}