{
  "type": "Feature",
  "properties": {
    "iso:country":"US",
    "sg:address":"1121 Sheffield Ave",
    "sg:city":"Dyer",
    "sg:classifiers":[
        {
            "category":"Banks & Credit Unions",
            "subcategory":"Bank",
            "type":"Services"
        }
    ],
    "sg:phone":"+1 219 865 3100",
    "sg:postcode":"46311",
    "sg:province":"IN",
    "wof:name":"Centier Bank",
    "wof:placetype":"venue"
},
  "geometry": {"coordinates":[-87.518703,41.512885],"type":"Point"}
}