{
  "type": "Feature",
  "properties": {
    "iso:country":"US",
    "sg:address":"410 S Armstrong St",
    "sg:city":"Kokomo",
    "sg:classifiers":[
        {
            "category":"Building & Trades",
            "subcategory":"Construction",
            "type":"Services"
        }
    ],
    "sg:phone":"+1 765 854 0428",
    "sg:postcode":"46901",
    "sg:province":"IN",
    "sg:tags":[
        "roofing",
        "contractor"
    ],
    "wof:name":"Nelson Roofs",
    "wof:placetype":"venue"
},
  "geometry": {"coordinates":[-86.135215,40.482335],"type":"Point"}
}