{
  "type": "Feature",
  "properties": {
    "iso:country":"US",
    "sg:address":"830 Green Blvd",
    "sg:city":"Aurora",
    "sg:classifiers":[
        {
            "category":"Restaurant",
            "type":"Food & Drink"
        }
    ],
    "sg:phone":"+1 812 926 4131",
    "sg:postcode":"47001",
    "sg:province":"IN",
    "wof:name":"Burger King",
    "wof:placetype":"venue"
},
  "geometry": {"coordinates":[-84.89446599999999,39.067752],"type":"Point"}
}