{
  "type": "Feature",
  "properties": {
    "iso:country":"US",
    "sg:address":"204 E Utica St",
    "sg:city":"Sellersburg",
    "sg:classifiers":[
        {
            "category":"Professional",
            "subcategory":"Computer Services",
            "type":"Services"
        }
    ],
    "sg:phone":"+1 812 248 9722",
    "sg:postcode":"47172",
    "sg:province":"IN",
    "sg:tags":[
        "repair"
    ],
    "wof:name":"Bits & Bytes Computer Repair",
    "wof:placetype":"venue"
},
  "geometry": {"coordinates":[-85.75547299999999,38.398244],"type":"Point"}
}