{
  "type": "Feature",
  "properties": {
    "iso:country":"US",
    "sg:address":"1022 16th St",
    "sg:city":"Bedford",
    "sg:classifiers":[
        {
            "category":"Banks & Credit Unions",
            "subcategory":"Investment Brokerage",
            "type":"Services"
        }
    ],
    "sg:phone":"+1 812 279 3511",
    "sg:postcode":"47421",
    "sg:province":"IN",
    "sg:tags":[
        "stock",
        "bond"
    ],
    "wof:name":"Edward Jones Co",
    "wof:placetype":"venue"
},
  "geometry": {"coordinates":[-86.485339,38.860929],"type":"Point"}
}